{
  "type": "Feature",
  "properties": {
    "iso:country":"NZ",
    "sg:address":"766 Gt South Rd Penrose ",
    "sg:city":"Auckland",
    "sg:classifiers":[
        {
            "category":"Shopping",
            "subcategory":"Beauty & Cosmetics",
            "type":"Retail Goods"
        }
    ],
    "sg:phone":"+64 9-525 4213",
    "sg:province":"Auckland",
    "sg:tags":[
        "medical",
        "health"
    ],
    "wof:name":"Leow Dr Thye K",
    "wof:placetype":"venue"
},
  "geometry": {"coordinates":[174.817139,-36.910694],"type":"Point"}
}