{
  "type": "Feature",
  "properties": {
    "iso:country":"NZ",
    "sg:address":"115 Brougham St Mt Victoria ",
    "sg:city":"Wellington",
    "sg:orig_category":"Travel And Tourism: Accommodation: Backpackers",
    "sg:phone":"+64 4-385 7872",
    "sg:province":"Wellington",
    "sg:website":"http://www.wellingtonbackpackers.co.nz",
    "wof:name":"Rowena's City Lodge",
    "wof:placetype":"venue"
},
  "geometry": {"coordinates":[174.783905,-41.299656],"type":"Point"}
}