{
  "type": "Feature",
  "properties": {
    "iso:country":"NZ",
    "sg:address":"247 Remuera Rd Remuera ",
    "sg:city":"Auckland",
    "sg:orig_category":"Health And Beauty: Specialists: Physiotherapists",
    "sg:phone":"+64 9-524 4858",
    "sg:province":"Auckland",
    "wof:name":"Susan Lugton Physiotherapy",
    "wof:placetype":"venue"
},
  "geometry": {"coordinates":[174.79156499999999,-36.879539],"type":"Point"}
}