{
  "type": "Feature",
  "properties": {
    "addr:full":"State Highway 6  Greymouth West Coast",
    "addr:street":"State Highway 6",
    "iso:country":"NZ",
    "sg:address":"State Highway 6 ",
    "sg:city":"Greymouth",
    "sg:classifiers":[
        {
            "category":"Travel",
            "subcategory":"Bed & Breakfast",
            "type":"Entertainment"
        }
    ],
    "sg:phone":"+64 3-768 6832",
    "sg:province":"West Coast",
    "sg:tags":[
        "tourism",
        "accommodation"
    ],
    "sg:website":"http://oaklodge.co.nz",
    "wof:name":"Oak Lodge",
    "wof:placetype":"venue"
},
  "geometry": {"coordinates":[171.21106,-42.450195],"type":"Point"}
}