{
  "type": "Feature",
  "properties": {
    "addr:full":"27 Grey Rd  Timaru Canterbury",
    "addr:housenumber":"27",
    "addr:street":"Grey Rd",
    "iso:country":"NZ",
    "sg:address":"27 Grey Rd ",
    "sg:city":"Timaru",
    "sg:classifiers":[
        {
            "category":"Food Court",
            "type":"Food & Drink"
        }
    ],
    "sg:phone":"+64 3-684 5062",
    "sg:province":"Canterbury",
    "sg:tags":[
        "packer",
        "processing",
        "processor"
    ],
    "wof:name":"Timaru Concentrators Limited",
    "wof:placetype":"venue"
},
  "geometry": {"coordinates":[171.24610899999999,-44.397938],"type":"Point"}
}