{
  "type": "Feature",
  "properties": {
    "addr:full":"196 High St Lower  Hutt Wellington",
    "addr:housenumber":"196",
    "addr:street":"High St",
    "iso:country":"NZ",
    "sg:address":"196 High St Lower ",
    "sg:city":"Hutt",
    "sg:classifiers":[
        {
            "category":"Shopping",
            "subcategory":"Crafts & Fabrics",
            "type":"Retail Goods"
        }
    ],
    "sg:phone":"+64 4-566 4141",
    "sg:province":"Wellington",
    "sg:tags":[
        "foot",
        "clothing",
        "retailer",
        "footwear",
        "wear"
    ],
    "wof:name":"Bay Shoes For All",
    "wof:placetype":"venue"
},
  "geometry": {"coordinates":[174.90329,-41.209309],"type":"Point"}
}