{
  "type": "Feature",
  "properties": {
    "addr:full":"59 Beazley Ave Newlands  Wellington Wellington",
    "addr:housenumber":"59",
    "addr:street":"Beazley Ave",
    "iso:country":"NZ",
    "sg:address":"59 Beazley Ave Newlands ",
    "sg:city":"Wellington",
    "sg:classifiers":[
        {
            "category":"Health Services",
            "subcategory":"Dentist",
            "type":"Services"
        }
    ],
    "sg:phone":"+64 4-478 6890",
    "sg:province":"Wellington",
    "sg:tags":[
        "dental",
        "clinic",
        "beauty"
    ],
    "wof:name":"Paparangi School Dental Clinic",
    "wof:placetype":"venue"
},
  "geometry": {"coordinates":[174.819489,-41.225929],"type":"Point"}
}