{
  "type": "Feature",
  "properties": {
    "iso:country":"NZ",
    "sg:address":"4 Athol - Five Rivers Hwy Athol ",
    "sg:city":"Garston",
    "sg:classifiers":[
        {
            "category":"Bars & Pubs",
            "subcategory":"Wine Bar",
            "type":"Food & Drink"
        }
    ],
    "sg:phone":"+64 3-248 8859",
    "sg:tags":[
        "wining",
        "dining",
        "cafe"
    ],
    "wof:name":"Highway Cafe",
    "wof:placetype":"venue"
},
  "geometry": {"coordinates":[168.684158,-45.465092],"type":"Point"}
}