{
  "type": "Feature",
  "properties": {
    "iso:country":"NZ",
    "sg:address":"49 Glover St ",
    "sg:city":"Hawera",
    "sg:orig_category":"Automotive: Parts And Supplies: Tyres",
    "sg:phone":"+64 6-278 0060",
    "sg:province":"Taranaki",
    "wof:name":"Beaurepaires For Tyres",
    "wof:placetype":"venue"
},
  "geometry": {"coordinates":[174.283554,-39.58297],"type":"Point"}
}