{
  "type": "Feature",
  "properties": {
    "addr:full":"28 Burleigh St Grafton  Auckland Auckland",
    "addr:housenumber":"28",
    "addr:street":"Burleigh St",
    "iso:country":"NZ",
    "sg:address":"28 Burleigh St Grafton ",
    "sg:city":"Auckland",
    "sg:classifiers":[
        {
            "category":"Personal",
            "subcategory":"Adult",
            "type":"Services"
        }
    ],
    "sg:phone":"+64 9-337 0049",
    "sg:province":"Auckland",
    "sg:tags":[
        "sport",
        "parlour",
        "massage",
        "leisure"
    ],
    "wof:name":"No. 28",
    "wof:placetype":"venue"
},
  "geometry": {"coordinates":[174.76236,-36.865929],"type":"Point"}
}