{
  "type": "Feature",
  "properties": {
    "addr:full":"67 State Highway 6 Frankton  Queenstown Waikato",
    "addr:housenumber":"67",
    "addr:street":"State Highway 6",
    "iso:country":"NZ",
    "sg:address":"67 State Highway 6 Frankton ",
    "sg:city":"Queenstown",
    "sg:orig_category":"Industrial: Engineering: Engineers: Engineers - General",
    "sg:phone":"+64 3-442 3244",
    "sg:province":"Waikato",
    "wof:name":"Dart Marine & Engineering Ltd",
    "wof:placetype":"venue"
},
  "geometry": {"coordinates":[168.73840300000001,-45.012768],"type":"Point"}
}