{
  "type": "Feature",
  "properties": {
    "addr:full":"62 Sunnyvale St Bell Block New  Plymouth Taranaki",
    "addr:housenumber":"62",
    "addr:street":"Sunnyvale St",
    "iso:country":"NZ",
    "sg:address":"62 Sunnyvale St Bell Block New ",
    "sg:city":"Plymouth",
    "sg:classifiers":[
        {
            "category":"Personal",
            "subcategory":"Tanning Parlor",
            "type":"Services"
        }
    ],
    "sg:phone":"+64 6-755 3389",
    "sg:province":"Taranaki",
    "sg:tags":[
        "sun",
        "health",
        "beauty"
    ],
    "wof:name":"High Voltage Sun Shack",
    "wof:placetype":"venue"
},
  "geometry": {"coordinates":[174.154099,-39.028427],"type":"Point"}
}