{
  "type": "Feature",
  "properties": {
    "addr:full":"185 Shaw Ave New Brighton  Christchurch Canterbury",
    "addr:housenumber":"185",
    "addr:street":"Shaw Ave",
    "iso:country":"NZ",
    "sg:address":"185 Shaw Ave New Brighton ",
    "sg:city":"Christchurch",
    "sg:classifiers":[
        {
            "category":"Communications",
            "subcategory":"Film & Video Production",
            "type":"Services"
        }
    ],
    "sg:phone":"+64 3-388 9339",
    "sg:province":"Canterbury",
    "sg:tags":[
        "sport",
        "leisure",
        "library",
        "entertainment"
    ],
    "wof:name":"Video Ezy",
    "wof:placetype":"venue"
},
  "geometry": {"coordinates":[172.726868,-43.507675],"type":"Point"}
}