{
  "type": "Feature",
  "properties": {
    "addr:full":"Gloucester St Mt Maunganui  Tauranga Bay of Plenty",
    "addr:street":"Gloucester St",
    "iso:country":"NZ",
    "sg:address":"Gloucester St Mt Maunganui ",
    "sg:city":"Tauranga",
    "sg:classifiers":[
        {
            "category":"Education",
            "subcategory":"Dance Studio",
            "type":"Public Place"
        }
    ],
    "sg:phone":"+64 7-571 1940",
    "sg:province":"Bay of Plenty",
    "sg:tags":[
        "school",
        "dancing",
        "-",
        "leisure",
        "sports",
        "sport"
    ],
    "wof:name":"The Dance Centre",
    "wof:placetype":"venue"
},
  "geometry": {"coordinates":[176.208359,-37.65926],"type":"Point"}
}