{
  "type": "Feature",
  "properties": {
    "iso:country":"NZ",
    "sg:address":"77 Cleghorn St Redwoodtown ",
    "sg:city":"Blenheim",
    "sg:classifiers":[
        {
            "category":"Bars & Pubs",
            "subcategory":"Lounge",
            "type":"Food & Drink"
        }
    ],
    "sg:phone":"+64 3-578 3319",
    "sg:province":"Marlborough",
    "sg:tags":[
        "baker",
        "-"
    ],
    "wof:name":"Redwood Bakery (2001) Ltd",
    "wof:placetype":"venue"
},
  "geometry": {"coordinates":[173.955368,-41.53038],"type":"Point"}
}