{
  "type": "Feature",
  "properties": {
    "addr:full":"Bowen St  Dargaville Northland",
    "addr:street":"Bowen St",
    "iso:country":"NZ",
    "sg:address":"Bowen St ",
    "sg:city":"Dargaville",
    "sg:classifiers":[
        {
            "category":"Travel",
            "subcategory":"Hotels & Motels",
            "type":"Entertainment"
        }
    ],
    "sg:phone":"+64 9-439 8082",
    "sg:province":"Northland",
    "sg:tags":[
        "tavern",
        "tourism",
        "accommodation"
    ],
    "wof:name":"Kauri House Lodge",
    "wof:placetype":"venue"
},
  "geometry": {"coordinates":[173.88194300000001,-35.9314],"type":"Point"}
}