{
  "type": "Feature",
  "properties": {
    "addr:full":"39 Norwich St Linwood  Christchurch Canterbury",
    "addr:housenumber":"39",
    "addr:street":"Norwich St",
    "iso:country":"NZ",
    "sg:address":"39 Norwich St Linwood ",
    "sg:city":"Christchurch",
    "sg:classifiers":[
        {
            "category":"Professional",
            "subcategory":"Art Services",
            "type":"Services"
        }
    ],
    "sg:phone":"+64 3-981 3119",
    "sg:province":"Canterbury",
    "sg:tags":[
        "personal",
        "photographer",
        "services",
        "garden",
        "home"
    ],
    "sg:website":"http://www.yellowpages.co.nz/for/gordonheywardphotography/dp50783.html",
    "wof:name":"Gordon Heyward",
    "wof:placetype":"venue"
},
  "geometry": {"coordinates":[172.67245500000001,-43.53112],"type":"Point"}
}