{
  "type": "Feature",
  "properties": {
    "addr:full":"1c Grant St Kamo  Whangarei Northland",
    "addr:housenumber":"1c",
    "addr:street":"Grant St",
    "iso:country":"NZ",
    "sg:address":"1c Grant St Kamo ",
    "sg:city":"Whangarei",
    "sg:classifiers":[
        {
            "category":"Shopping",
            "subcategory":"Clothing, Apparel, & Fashions",
            "type":"Retail Goods"
        }
    ],
    "sg:phone":"+64 9-435 5930",
    "sg:province":"Northland",
    "sg:tags":[
        "-",
        "hire",
        "clothing",
        "fabric"
    ],
    "wof:name":"Incognito",
    "wof:placetype":"venue"
},
  "geometry": {"coordinates":[174.30128500000001,-35.68338],"type":"Point"}
}