{
  "type": "Feature",
  "properties": {
    "iso:country":"NZ",
    "sg:address":"16 Beach Rd Otahuhu ",
    "sg:city":"Auckland",
    "sg:classifiers":[
        {
            "category":"Manufacturing",
            "subcategory":"Glass & Minerals",
            "type":"Manufacturing & Wholesale Goods"
        }
    ],
    "sg:phone":"+64 9-276 7154",
    "sg:province":"Auckland",
    "sg:tags":[
        "chemical",
        "paint",
        "industrial",
        "manufacturer",
        "compounds"
    ],
    "wof:name":"Rohm And Haas New Zealand Ltd",
    "wof:placetype":"venue"
},
  "geometry": {"coordinates":[174.85611,-36.940605],"type":"Point"}
}