{
  "type": "Feature",
  "properties": {
    "iso:country":"NZ",
    "sg:address":"217 North Rd ",
    "sg:city":"Invercargill",
    "sg:classifiers":[
        {
            "category":"Travel",
            "subcategory":"Hotels & Motels",
            "type":"Entertainment"
        }
    ],
    "sg:phone":"+64 800 667 000",
    "sg:province":"Southland",
    "sg:tags":[
        "holiday",
        "tourism",
        "accommodation"
    ],
    "wof:name":"Swan Lake Motor Inn Ltd",
    "wof:placetype":"venue"
},
  "geometry": {"coordinates":[168.34712200000001,-46.379871],"type":"Point"}
}