{
  "type": "Feature",
  "properties": {
    "iso:country":"NZ",
    "sg:address":"PO Box 216 Te ",
    "sg:city":"Awamutu",
    "sg:classifiers":[
        {
            "category":"Personal",
            "subcategory":"Massage",
            "type":"Services"
        }
    ],
    "sg:phone":"+64 7-871 5917",
    "sg:province":"Waikato",
    "sg:tags":[
        "services",
        "health",
        "-",
        "beauty",
        "fitness"
    ],
    "wof:name":"Te Awamutu Sport & Theraputic Massage",
    "wof:placetype":"venue"
},
  "geometry": {"coordinates":[175.319244,-38.009647],"type":"Point"}
}