{
  "type": "Feature",
  "properties": {
    "addr:full":"Kairanga Bunnythorpe Rd RD 8 Palmerston  Palmerston North Manawatu-Wanganui",
    "addr:street":"Kairanga Bunnythorpe Rd Rd 8",
    "iso:country":"NZ",
    "sg:address":"Kairanga Bunnythorpe Rd RD 8 Palmerston ",
    "sg:city":"Palmerston North",
    "sg:classifiers":[
        {
            "category":"Farming",
            "subcategory":"Farm",
            "type":"Manufacturing & Wholesale Goods"
        }
    ],
    "sg:phone":"+64 6-354 7362",
    "sg:province":"Manawatu-Wanganui",
    "sg:tags":[
        "-",
        "ostrich"
    ],
    "wof:name":"Sharella Park - Ostrich Farm",
    "wof:placetype":"venue"
},
  "geometry": {"coordinates":[175.611481,-40.357418],"type":"Point"}
}