{
  "type": "Feature",
  "properties": {
    "iso:country":"NZ",
    "sg:address":"952 Tukairangi Rd ",
    "sg:city":"Taupo",
    "sg:classifiers":[
        {
            "category":"Shopping",
            "subcategory":"Pets & Pet Supplies",
            "type":"Retail Goods"
        }
    ],
    "sg:phone":"+64 7-378 2865",
    "sg:province":"Waikato",
    "sg:tags":[
        "home",
        "grooming",
        "garden",
        "pets"
    ],
    "wof:name":"SNIPSHAPE Dog Grooming",
    "wof:placetype":"venue"
},
  "geometry": {"coordinates":[176.084351,-38.689285],"type":"Point"}
}