{
  "type": "Feature",
  "properties": {
    "addr:full":"101 A Kapera Rd Brooklyn  Wellington Wellington",
    "addr:housenumber":"101",
    "addr:street":"A Kapera Rd",
    "iso:country":"NZ",
    "sg:address":"101 A Kapera Rd Brooklyn ",
    "sg:city":"Wellington",
    "sg:classifiers":[
        {
            "category":"Coffee & Tea",
            "type":"Food & Drink"
        }
    ],
    "sg:phone":"+64 4-476 0624",
    "sg:province":"Wellington",
    "sg:tags":[
        "merchant"
    ],
    "wof:name":"Burton Hollis Ltd",
    "wof:placetype":"venue"
},
  "geometry": {"coordinates":[174.76118500000001,-41.304153],"type":"Point"}
}