{
  "type": "Feature",
  "properties": {
    "addr:full":"264 Mt Eden Rd Mt Eden  Auckland Auckland",
    "addr:housenumber":"264",
    "addr:street":"Mt Eden Rd",
    "iso:country":"NZ",
    "sg:address":"264 Mt Eden Rd Mt Eden ",
    "sg:city":"Auckland",
    "sg:orig_category":"Industrial: Packaging: Paper Products",
    "sg:phone":"+64 9-570 1090",
    "sg:province":"Auckland",
    "wof:name":"Tork Products",
    "wof:placetype":"venue"
},
  "geometry": {"coordinates":[174.76205400000001,-36.882732],"type":"Point"}
}