{
  "type": "Feature",
  "properties": {
    "addr:full":"219 Broadway Ave Palmerston  Palmerston North Manawatu-Wanganui",
    "addr:housenumber":"219",
    "addr:street":"Broadway Ave",
    "iso:country":"NZ",
    "sg:address":"219 Broadway Ave Palmerston ",
    "sg:city":"Palmerston North",
    "sg:orig_category":"Home And Garden",
    "sg:phone":"+64 6-358 9009",
    "sg:province":"Manawatu-Wanganui",
    "sg:website":"http://www.yellowpages.co.nz/for/ljhookerpalmerstonnorth/dp20700.html",
    "wof:name":"L.J. Hooker",
    "wof:placetype":"venue"
},
  "geometry": {"coordinates":[175.61850000000001,-40.35136],"type":"Point"}
}