{
  "type": "Feature",
  "properties": {
    "addr:full":"153 Ocean View Rd Oneroa  Auckland Auckland",
    "addr:housenumber":"153",
    "addr:street":"Ocean View Rd",
    "iso:country":"NZ",
    "sg:address":"153 Ocean View Rd Oneroa ",
    "sg:city":"Auckland",
    "sg:classifiers":[
        {
            "category":"Ice Cream",
            "type":"Food & Drink"
        }
    ],
    "sg:phone":"+64 9-372 9458",
    "sg:province":"Auckland",
    "sg:tags":[
        "-"
    ],
    "wof:name":"The Conservatory",
    "wof:placetype":"venue"
},
  "geometry": {"coordinates":[174.732178,-36.843193],"type":"Point"}
}