{
  "type": "Feature",
  "properties": {
    "addr:full":"State Highway 7 Totara Flat  Ahaura Auckland",
    "addr:housenumber":"ahaura",
    "addr:street":"State Highway 7 Totara Flat",
    "iso:country":"NZ",
    "sg:address":"State Highway 7 Totara Flat ",
    "sg:city":"Ahaura",
    "sg:classifiers":[
        {
            "category":"Home & Garden",
            "subcategory":"Garden Supply",
            "type":"Retail Goods"
        }
    ],
    "sg:phone":"+64 3-732 3610",
    "sg:province":"Auckland",
    "sg:tags":[
        "products",
        "nursery",
        "gardening"
    ],
    "wof:name":"Supersphag Ltd",
    "wof:placetype":"venue"
},
  "geometry": {"coordinates":[171.61463900000001,-42.30069],"type":"Point"}
}