{
  "type": "Feature",
  "properties": {
    "addr:full":"73 Argyle Ave Palmerston  Palmerston North Manawatu-Wanganui",
    "addr:housenumber":"73",
    "addr:street":"Argyle Ave",
    "iso:country":"NZ",
    "sg:address":"73 Argyle Ave Palmerston ",
    "sg:city":"Palmerston North",
    "sg:orig_category":"Home And Garden: Gardening: Services: Tree Services",
    "sg:phone":"+64 6-356 2175",
    "sg:province":"Manawatu-Wanganui",
    "wof:name":"Tree Care Services",
    "wof:placetype":"venue"
},
  "geometry": {"coordinates":[175.603455,-40.348263],"type":"Point"}
}