{
  "type": "Feature",
  "properties": {
    "addr:full":"50 Maria Pl Extension  Wanganui Manawatu-Wanganui",
    "addr:housenumber":"50",
    "addr:street":"Maria Pl Extension",
    "iso:country":"NZ",
    "sg:address":"50 Maria Pl Extension ",
    "sg:city":"Wanganui",
    "sg:classifiers":[
        {
            "category":"Building & Trades",
            "subcategory":"Cleaning & Sanitation",
            "type":"Services"
        }
    ],
    "sg:phone":"+64 6-347 6688",
    "sg:province":"Manawatu-Wanganui",
    "sg:tags":[
        "equipment",
        "industrial",
        "maintenance"
    ],
    "wof:name":"Superclean Distributors",
    "wof:placetype":"venue"
},
  "geometry": {"coordinates":[175.04864499999999,-39.935692],"type":"Point"}
}