{
  "type": "Feature",
  "properties": {
    "addr:full":"P O Box 165  Kerikeri Northland",
    "addr:housenumber":"165",
    "addr:street":"P O Box",
    "iso:country":"NZ",
    "sg:address":"P O Box 165 ",
    "sg:city":"Kerikeri",
    "sg:orig_category":"Home And Garden: Gardening: Services: Tree Services",
    "sg:phone":"+64 9-407 9915",
    "sg:province":"Northland",
    "wof:name":"Harrison Tom & Sons Ltd",
    "wof:placetype":"venue"
},
  "geometry": {"coordinates":[173.949905,-35.226269],"type":"Point"}
}