{
  "type": "Feature",
  "properties": {
    "addr:full":"906 Mountain Rd R D 9  Inglewood",
    "addr:housenumber":"906;9",
    "addr:street":"Mountain Rd R D",
    "iso:country":"NZ",
    "sg:address":"906 Mountain Rd R D 9 ",
    "sg:city":"Inglewood",
    "sg:classifiers":[
        {
            "category":"Shopping",
            "subcategory":"Pets & Pet Supplies",
            "type":"Retail Goods"
        }
    ],
    "sg:phone":"+64 6-756 7073",
    "sg:tags":[
        "boarding",
        "garden",
        "pets",
        "catteries",
        "home",
        "kennel"
    ],
    "wof:name":"K-9 Boarding Kennels",
    "wof:placetype":"venue"
},
  "geometry": {"coordinates":[174.20588699999999,-39.156784],"type":"Point"}
}