{
  "type": "Feature",
  "properties": {
    "addr:full":"cnr Bond & Ohaupo Rds Te  Awamutu Waikato",
    "addr:housenumber":"cnr",
    "addr:street":"Bond;Rds",
    "iso:country":"NZ",
    "sg:address":"cnr Bond & Ohaupo Rds Te ",
    "sg:city":"Awamutu",
    "sg:classifiers":[
        {
            "category":"Retail",
            "subcategory":"Auto Repair",
            "type":"Services"
        }
    ],
    "sg:phone":"+64 7-871 8496",
    "sg:province":"Waikato",
    "sg:tags":[
        "clutch",
        "brake",
        "servicing",
        "automotive"
    ],
    "wof:name":"Pit Stop",
    "wof:placetype":"venue"
},
  "geometry": {"coordinates":[175.30587800000001,-37.9193],"type":"Point"}
}