{
  "type": "Feature",
  "properties": {
    "addr:full":"213 Commerce St  Hamilton Waikato",
    "addr:housenumber":"213",
    "addr:street":"Commerce St",
    "iso:country":"NZ",
    "sg:address":"213 Commerce St ",
    "sg:city":"Hamilton",
    "sg:classifiers":[
        {
            "category":"Social Services",
            "subcategory":"Job Training",
            "type":"Services"
        }
    ],
    "sg:phone":"+64 7-957 2850",
    "sg:province":"Waikato",
    "sg:tags":[
        "education"
    ],
    "wof:name":"Kershaw Training Enterprises",
    "wof:placetype":"venue"
},
  "geometry": {"coordinates":[-84.580231,39.407902],"type":"Point"}
}