{
  "type": "Feature",
  "properties": {
    "addr:full":"77 King St  Hamilton Waikato",
    "addr:housenumber":"77",
    "addr:street":"King St",
    "iso:country":"NZ",
    "sg:address":"77 King St ",
    "sg:city":"Hamilton",
    "sg:classifiers":[
        {
            "category":"Retail",
            "subcategory":"Laundry & Dry Cleaning",
            "type":"Services"
        }
    ],
    "sg:phone":"+64 7-846 0710",
    "sg:province":"Waikato",
    "sg:tags":[
        "repair",
        "clothing",
        "fabric",
        "cleaner"
    ],
    "wof:name":"SmartCare Property Services",
    "wof:placetype":"venue"
},
  "geometry": {"coordinates":[175.26617400000001,-37.789642],"type":"Point"}
}