{
  "type": "Feature",
  "properties": {
    "iso:country":"NZ",
    "sg:address":"30 Midland St ",
    "sg:city":"Dunedin",
    "sg:classifiers":[
        {
            "category":"Autos & Motor Vehicles",
            "subcategory":"Automobile Sales",
            "type":"Retail Goods"
        }
    ],
    "sg:phone":"+64 3-456 4008",
    "sg:province":"Otago",
    "sg:tags":[
        "bus",
        "leasing",
        "truck",
        "automotive"
    ],
    "wof:name":"Southern International Ltd",
    "wof:placetype":"venue"
},
  "geometry": {"coordinates":[-82.784721,28.013355],"type":"Point"}
}