{
  "type": "Feature",
  "properties": {
    "addr:full":"19 Carrick Pl Mt Eden  Auckland Auckland",
    "addr:housenumber":"19",
    "addr:street":"Carrick Pl",
    "iso:country":"NZ",
    "sg:address":"19 Carrick Pl Mt Eden ",
    "sg:city":"Auckland",
    "sg:classifiers":[
        {
            "category":"Education",
            "subcategory":"Music School",
            "type":"Public Place"
        }
    ],
    "sg:phone":"+64 9-638 9477",
    "sg:province":"Auckland",
    "sg:tags":[
        "training",
        "art"
    ],
    "wof:name":"Auckland City Art School",
    "wof:placetype":"venue"
},
  "geometry": {"coordinates":[174.752197,-36.875286],"type":"Point"}
}