{
  "type": "Feature",
  "properties": {
    "iso:country":"NZ",
    "sg:address":"9 Westmoreland St West Grey Lynn ",
    "sg:city":"Auckland",
    "sg:classifiers":[
        {
            "category":"Professional",
            "subcategory":"Art Services",
            "type":"Services"
        }
    ],
    "sg:phone":"+64 9-378 0296",
    "sg:province":"Auckland",
    "sg:tags":[
        "equipment",
        "arts",
        "sport",
        "film",
        "leisure"
    ],
    "wof:name":"R W Developments Ltd",
    "wof:placetype":"venue"
},
  "geometry": {"coordinates":[-119.104576,36.597755],"type":"Point"}
}