{
  "type": "Feature",
  "properties": {
    "iso:country":"NZ",
    "sg:address":"174 Dee St ",
    "sg:city":"Invercargill",
    "sg:classifiers":[
        {
            "category":"Autos & Motor Vehicles",
            "subcategory":"Automobile Sales",
            "type":"Retail Goods"
        }
    ],
    "sg:phone":"+64 3-218 7197",
    "sg:province":"Southland",
    "sg:tags":[
        "leasing",
        "car",
        "-",
        "truck",
        "automotive",
        "new"
    ],
    "wof:name":"Invercargill Honda",
    "wof:placetype":"venue"
},
  "geometry": {"coordinates":[168.34732099999999,-46.392628],"type":"Point"}
}