{
  "type": "Feature",
  "properties": {
    "iso:country":"NZ",
    "sg:address":"PO Box 52124 Kingsland ",
    "sg:city":"Auckland",
    "sg:classifiers":[
        {
            "category":"Shopping",
            "subcategory":"Computers & Home Electronics",
            "type":"Retail Goods"
        }
    ],
    "sg:phone":"+64 9-913 7840",
    "sg:province":"Auckland",
    "sg:tags":[
        "recording",
        "equipment",
        "sport",
        "music",
        "leisure"
    ],
    "wof:name":"Ad Infinitum",
    "wof:placetype":"venue"
},
  "geometry": {"coordinates":[174.74469,-36.870129],"type":"Point"}
}