{
  "type": "Feature",
  "properties": {
    "addr:full":"2 Egremont St Belmont  Auckland Auckland",
    "addr:housenumber":"2",
    "addr:street":"Egremont St",
    "iso:country":"NZ",
    "sg:address":"2 Egremont St Belmont ",
    "sg:city":"Auckland",
    "sg:orig_category":"Farming: Services: Veterinarians",
    "sg:phone":"+64 9-446 1155",
    "sg:province":"Auckland",
    "wof:name":"Belmont Veterinary Clinic",
    "wof:placetype":"venue"
},
  "geometry": {"coordinates":[174.789185,-36.807011],"type":"Point"}
}