{
  "type": "Feature",
  "properties": {
    "iso:country":"NZ",
    "sg:address":"122 Church St ",
    "sg:city":"Opotiki",
    "sg:classifiers":[
        {
            "category":"Shopping",
            "subcategory":"Bicycles & Sporting Goods",
            "type":"Retail Goods"
        }
    ],
    "sg:phone":"+64 7-315 6238",
    "sg:tags":[
        "sport",
        "fishing",
        "hunting",
        "retailers"
    ],
    "wof:name":"Sportsworld Hickeys",
    "wof:placetype":"venue"
},
  "geometry": {"coordinates":[177.28454600000001,-38.003643],"type":"Point"}
}