{
  "type": "Feature",
  "properties": {
    "addr:full":"8 Fraser St  Whakatane Bay of Plenty",
    "addr:housenumber":"8",
    "addr:street":"Fraser St",
    "iso:country":"NZ",
    "sg:address":"8 Fraser St ",
    "sg:city":"Whakatane",
    "sg:orig_category":"Health And Beauty: Specialists: Midwives",
    "sg:phone":"+64 7-308 9094",
    "sg:province":"Bay of Plenty",
    "wof:name":"Armitstead Jean",
    "wof:placetype":"venue"
},
  "geometry": {"coordinates":[176.972916,-37.961739],"type":"Point"}
}