{
  "type": "Feature",
  "properties": {
    "addr:full":"Melville Park  Hamilton Waikato",
    "addr:street":"Park",
    "iso:country":"NZ",
    "sg:address":"Melville Park ",
    "sg:city":"Hamilton",
    "sg:classifiers":[
        {
            "category":"Home & Garden",
            "subcategory":"Garden Supply",
            "type":"Retail Goods"
        }
    ],
    "sg:phone":"+64 7-834 2025",
    "sg:province":"Waikato",
    "sg:tags":[
        "trainer",
        "breeder",
        "/",
        "pets",
        "animal"
    ],
    "wof:name":"Hamilton Dog Obedience Club",
    "wof:placetype":"venue"
},
  "geometry": {"coordinates":[-84.62075,39.40604],"type":"Point"}
}