{
  "type": "Feature",
  "properties": {
    "addr:full":"180 Gill St New  Plymouth Taranaki",
    "addr:housenumber":"180",
    "addr:street":"Gill St",
    "iso:country":"NZ",
    "sg:address":"180 Gill St New ",
    "sg:city":"Plymouth",
    "sg:orig_category":"Shopping: Sports Retailers: Sports Goods",
    "sg:phone":"+64 6-758 5259",
    "sg:province":"Taranaki",
    "sg:website":"http://www.yellowpages.co.nz/for/tridentelectronics/dp41983.html",
    "wof:name":"Trident Electronics Ltd",
    "wof:placetype":"venue"
},
  "geometry": {"coordinates":[-116.81972500000001,43.97221],"type":"Point"}
}