{
  "type": "Feature",
  "properties": {
    "iso:country":"NZ",
    "sg:address":"2/219 Alexandra St Te ",
    "sg:city":"Awamutu",
    "sg:classifiers":[
        {
            "category":"Arts & Performance",
            "subcategory":"Art Gallery",
            "type":"Entertainment"
        }
    ],
    "sg:phone":"+64 7-870 1647",
    "sg:province":"Waikato",
    "sg:tags":[
        "arts",
        "sport",
        "leisure"
    ],
    "wof:name":"Arcade Gallery",
    "wof:placetype":"venue"
},
  "geometry": {"coordinates":[175.32337999999999,-38.009506],"type":"Point"}
}