{
  "type": "Feature",
  "properties": {
    "iso:country":"NZ",
    "sg:address":"6 Wilson Rd Glen Eden ",
    "sg:city":"Auckland",
    "sg:classifiers":[
        {
            "category":"Health Services",
            "subcategory":"Clinic",
            "type":"Services"
        }
    ],
    "sg:phone":"+64 9-818 7111",
    "sg:province":"Auckland",
    "sg:tags":[
        "medical",
        "beauty"
    ],
    "wof:name":"West Coast Rd Surgery",
    "wof:placetype":"venue"
},
  "geometry": {"coordinates":[174.653473,-36.911999],"type":"Point"}
}