{
  "type": "Feature",
  "properties": {
    "addr:full":"22 Tararua St  Masterton Wellington",
    "addr:housenumber":"22",
    "addr:street":"Tararua St",
    "iso:country":"NZ",
    "sg:address":"22 Tararua St ",
    "sg:city":"Masterton",
    "sg:classifiers":[
        {
            "category":"Health Services",
            "subcategory":"Doctor",
            "type":"Services"
        }
    ],
    "sg:phone":"+64 6-377 1788",
    "sg:province":"Wellington",
    "sg:tags":[
        "beauty"
    ],
    "wof:name":"Phillipa Mills",
    "wof:placetype":"venue"
},
  "geometry": {"coordinates":[175.641052,-40.950119],"type":"Point"}
}