{
  "type": "Feature",
  "properties": {
    "addr:full":"40 Harwood Street Hamilton 3204",
    "addr:housenumber":"40",
    "addr:postcode":"3204",
    "addr:street":"Harwood Street",
    "iso:country":"NZ",
    "sg:address":"40 Harwood Street",
    "sg:city":"Hamilton",
    "sg:classifiers":[
        {
            "category":"Professional",
            "subcategory":"Computer Services",
            "type":"Services"
        }
    ],
    "sg:postcode":"3204",
    "sg:tags":[
        "cms",
        "content-management-system",
        "saas",
        "content-managed",
        "website-editor"
    ],
    "sg:website":"http://webfreedom.co.nz",
    "wof:name":"WebFreedom",
    "wof:placetype":"venue"
},
  "geometry": {"coordinates":[175.27465799999999,-37.78062],"type":"Point"}
}