{
  "type": "Feature",
  "properties": {
    "iso:country":"NZ",
    "sg:address":"92 Railside Ave Henderson ",
    "sg:city":"Auckland",
    "sg:classifiers":[
        {
            "category":"Banks & Credit Unions",
            "subcategory":"Investment Brokerage",
            "type":"Services"
        }
    ],
    "sg:phone":"+64 9-836 3159",
    "sg:province":"Auckland",
    "sg:tags":[
        "automotive",
        "leasing",
        "sale"
    ],
    "sg:website":"http://www.forward-specialties.co.nz",
    "wof:name":"Forward Specialties (1988) Ltd LMVD & (2000) Ltd",
    "wof:placetype":"venue"
},
  "geometry": {"coordinates":[174.631607,-36.884918],"type":"Point"}
}