{
  "type": "Feature",
  "properties": {
    "addr:full":"50 Leven St  Invercargill Southland",
    "addr:housenumber":"50",
    "addr:street":"Leven St",
    "iso:country":"NZ",
    "sg:address":"50 Leven St ",
    "sg:city":"Invercargill",
    "sg:orig_category":"Automotive: Accessories: Car Audio Systems",
    "sg:phone":"+64 3-214 3131",
    "sg:province":"Southland",
    "wof:name":"Precision Car Sound",
    "wof:placetype":"venue"
},
  "geometry": {"coordinates":[168.345505,-46.409042],"type":"Point"}
}