{
  "type": "Feature",
  "properties": {
    "addr:full":"40 Anderson Rd Reece Block  Wanaka Otago",
    "addr:housenumber":"40",
    "addr:street":"Anderson Rd;Otago",
    "iso:country":"NZ",
    "sg:address":"40 Anderson Rd Reece Block ",
    "sg:city":"Wanaka",
    "sg:classifiers":[
        {
            "category":"Home & Garden",
            "subcategory":"Home Furnishings",
            "type":"Retail Goods"
        }
    ],
    "sg:phone":"+64 3-443 1667",
    "sg:province":"Otago",
    "sg:tags":[
        "furniture/furnishings",
        "upholstery",
        "supply"
    ],
    "wof:name":"Pembroke Upholstery",
    "wof:placetype":"venue"
},
  "geometry": {"coordinates":[169.138443,-44.693981],"type":"Point"}
}