{
  "type": "Feature",
  "properties": {
    "addr:full":"65 Dudley St Lower  Hutt Wellington",
    "addr:housenumber":"65",
    "addr:street":"Dudley St",
    "iso:country":"NZ",
    "sg:address":"65 Dudley St Lower ",
    "sg:city":"Hutt",
    "sg:orig_category":"Industrial: Electrical/Electronic",
    "sg:phone":"+64 4-569 3042",
    "sg:province":"Wellington",
    "wof:name":"ACTS Electronics",
    "wof:placetype":"venue"
},
  "geometry": {"coordinates":[174.902557,-41.208477],"type":"Point"}
}