{
  "type": "Feature",
  "properties": {
    "addr:full":"4 Mihini Rd Henderson  Auckland Auckland",
    "addr:housenumber":"4",
    "addr:street":"Mihini Rd",
    "iso:country":"NZ",
    "sg:address":"4 Mihini Rd Henderson ",
    "sg:city":"Auckland",
    "sg:classifiers":[
        {
            "category":"Manufacturing",
            "subcategory":"Tools & Machinery",
            "type":"Manufacturing & Wholesale Goods"
        }
    ],
    "sg:phone":"+64 9-838 5771",
    "sg:province":"Auckland",
    "sg:tags":[
        "equipment",
        "industrial",
        "label"
    ],
    "wof:name":"Westech Industries",
    "wof:placetype":"venue"
},
  "geometry": {"coordinates":[174.63294999999999,-36.877289],"type":"Point"}
}