{
  "type": "Feature",
  "properties": {
    "addr:full":"Bader Dve  Auckland Auckland",
    "iso:country":"NZ",
    "sg:address":"Bader Dve ",
    "sg:city":"Auckland",
    "sg:orig_category":"Clothing And Fabric: Clothing: Children'S Wear",
    "sg:phone":"+64 9-275 7119",
    "sg:province":"Auckland",
    "wof:name":"Farmers Trading Co Ltd",
    "wof:placetype":"venue"
},
  "geometry": {"coordinates":[174.77563499999999,-36.814896],"type":"Point"}
}