{
  "type": "Feature",
  "properties": {
    "addr:full":"41 Grand Dve Remuera  Auckland Auckland",
    "addr:housenumber":"41",
    "addr:street":"Grand Dve",
    "iso:country":"NZ",
    "sg:address":"41 Grand Dve Remuera ",
    "sg:city":"Auckland",
    "sg:orig_category":"Automotive: Accessories: Car Security Systems",
    "sg:phone":"+64 9-524 5893",
    "sg:province":"Auckland",
    "wof:name":"Mr Car Alarm",
    "wof:placetype":"venue"
},
  "geometry": {"coordinates":[174.80886799999999,-36.869381],"type":"Point"}
}