{
  "type": "Feature",
  "properties": {
    "iso:country":"NZ",
    "sg:address":"Unit/27b Cain Rd Penrose ",
    "sg:city":"Auckland",
    "sg:classifiers":[
        {
            "category":"Building & Trades",
            "subcategory":"Pest Control",
            "type":"Services"
        }
    ],
    "sg:phone":"+64 9-526 5232",
    "sg:province":"Auckland",
    "sg:tags":[
        "home",
        "garden"
    ],
    "wof:name":"Gerrard's Pesticides NZ Ltd",
    "wof:placetype":"venue"
},
  "geometry": {"coordinates":[174.81016500000001,-36.911617],"type":"Point"}
}