{
  "type": "Feature",
  "properties": {
    "iso:country":"NZ",
    "sg:address":"Main St Pleasant Point ",
    "sg:city":"Timaru",
    "sg:orig_category":"Home And Garden: Accessories: Hardware",
    "sg:phone":"+64 3-614 7853",
    "sg:province":"Canterbury",
    "wof:name":"Shortus's General Store",
    "wof:placetype":"venue"
},
  "geometry": {"coordinates":[-80.307152,40.299591],"type":"Point"}
}