{
  "type": "Feature",
  "properties": {
    "addr:full":"10 Ross Reid Pl East Tamaki  Auckland Auckland",
    "addr:housenumber":"10",
    "addr:street":"Ross Reid Pl",
    "iso:country":"NZ",
    "sg:address":"10 Ross Reid Pl East Tamaki ",
    "sg:city":"Auckland",
    "sg:orig_category":"Industrial: Products: Filters And Filtration",
    "sg:phone":"+64 9-274 7366",
    "sg:province":"Auckland",
    "wof:name":"Amiad NZ",
    "wof:placetype":"venue"
},
  "geometry": {"coordinates":[174.886841,-36.941986],"type":"Point"}
}