{
  "type": "Feature",
  "properties": {
    "iso:country":"NZ",
    "sg:address":"PO Box 400 ",
    "sg:city":"Timaru",
    "sg:classifiers":[
        {
            "category":"Professional",
            "subcategory":"Art Services",
            "type":"Services"
        }
    ],
    "sg:phone":"+64 274 342 372",
    "sg:province":"Canterbury",
    "sg:tags":[
        "personal",
        "photographer",
        "services",
        "garden",
        "home"
    ],
    "sg:website":"http://www.yellowpages.co.nz/for/photoone/dp33904.html",
    "wof:name":"Photo-One",
    "wof:placetype":"venue"
},
  "geometry": {"coordinates":[171.237411,-44.395428],"type":"Point"}
}