{
  "type": "Feature",
  "properties": {
    "addr:full":"Albert St Palmerston  Palmerston North Manawatu-Wanganui",
    "addr:street":"Albert St Palmerston",
    "iso:country":"NZ",
    "sg:address":"Albert St Palmerston ",
    "sg:city":"Palmerston North",
    "sg:orig_category":"Sports And Leisure: Sports: Golf",
    "sg:phone":"+64 6-355 3888",
    "sg:province":"Manawatu-Wanganui",
    "wof:name":"Brendan Martens Golf Professional",
    "wof:placetype":"venue"
},
  "geometry": {"coordinates":[175.62844799999999,-40.355831],"type":"Point"}
}