{
  "type": "Feature",
  "properties": {
    "addr:full":"1092 Tutanekai St  Rotorua Bay of Plenty",
    "addr:housenumber":"1092",
    "addr:street":"Tutanekai St",
    "iso:country":"NZ",
    "sg:address":"1092 Tutanekai St ",
    "sg:city":"Rotorua",
    "sg:classifiers":[
        {
            "category":"Ice Cream",
            "type":"Food & Drink"
        }
    ],
    "sg:phone":"+64 7-347 9340",
    "sg:province":"Bay of Plenty",
    "sg:tags":[
        "-"
    ],
    "wof:name":"Lady Jane's Ice Cream Parlour",
    "wof:placetype":"venue"
},
  "geometry": {"coordinates":[176.251678,-38.133087],"type":"Point"}
}