{
  "type": "Feature",
  "properties": {
    "addr:full":"158 Broadway  Kaikohe Manawatu-Wanganui",
    "addr:housenumber":"158",
    "addr:street":"Broadway",
    "iso:country":"NZ",
    "sg:address":"158 Broadway ",
    "sg:city":"Kaikohe",
    "sg:classifiers":[
        {
            "category":"Restaurant",
            "type":"Food & Drink"
        }
    ],
    "sg:phone":"+64 9-401 0149",
    "sg:province":"Manawatu-Wanganui",
    "sg:tags":[
        "wining",
        "dining"
    ],
    "wof:name":"Mid North Motor Inn",
    "wof:placetype":"venue"
},
  "geometry": {"coordinates":[173.80107100000001,-35.407009],"type":"Point"}
}