{
  "type": "Feature",
  "properties": {
    "addr:full":"949 South Rd  Manaia Wellington",
    "addr:housenumber":"949",
    "addr:street":"South Rd",
    "iso:country":"NZ",
    "sg:address":"949 South Rd ",
    "sg:city":"Manaia",
    "sg:classifiers":[
        {
            "category":"Retail",
            "subcategory":"Auto Repair",
            "type":"Services"
        }
    ],
    "sg:phone":"+64 6-274 8778",
    "sg:province":"Wellington",
    "sg:tags":[
        "automotive",
        "restoration",
        "servicing",
        "car"
    ],
    "wof:name":"Craigs Panel & Paint",
    "wof:placetype":"venue"
},
  "geometry": {"coordinates":[174.006561,-39.548565],"type":"Point"}
}