{
  "type": "Feature",
  "properties": {
    "iso:country":"NZ",
    "sg:address":"Shop 7 15 Cook St Howick ",
    "sg:city":"Auckland",
    "sg:classifiers":[
        {
            "category":"Bars & Pubs",
            "subcategory":"Lounge",
            "type":"Food & Drink"
        }
    ],
    "sg:phone":"+64 9-279 3774",
    "sg:province":"Auckland",
    "sg:tags":[
        "-"
    ],
    "sg:website":"http://www.thechocolatecakecompany.co.nz",
    "wof:name":"The Chocolate Cake Company",
    "wof:placetype":"venue"
},
  "geometry": {"coordinates":[174.933304,-36.89584],"type":"Point"}
}