{
  "type": "Feature",
  "properties": {
    "iso:country":"NZ",
    "sg:address":"5 Chinook Pl Hornby ",
    "sg:city":"Christchurch",
    "sg:classifiers":[
        {
            "category":"Government",
            "subcategory":"Office",
            "type":"Public Place"
        }
    ],
    "sg:phone":"+64 3-349 0290",
    "sg:province":"Canterbury",
    "sg:tags":[
        "industrial",
        "galvanizer",
        "-",
        "equipment",
        "hot",
        "machinery",
        "dip"
    ],
    "wof:name":"Southgalv Ltd",
    "wof:placetype":"venue"
},
  "geometry": {"coordinates":[172.536331,-43.534431],"type":"Point"}
}