{
  "type": "Feature",
  "properties": {
    "iso:country":"NZ",
    "sg:address":"PO Box 112138 ",
    "sg:city":"Penrose",
    "sg:classifiers":[
        {
            "category":"Education",
            "subcategory":"Special Training",
            "type":"Public Place"
        }
    ],
    "sg:phone":"+64 21 724 970",
    "sg:province":"Auckland",
    "sg:tags":[
        "sale",
        "vocational"
    ],
    "wof:name":"salescoaching.net",
    "wof:placetype":"venue"
},
  "geometry": {"coordinates":[123.25756800000001,42.39241],"type":"Point"}
}