{
  "type": "Feature",
  "properties": {
    "addr:full":"39 C Stanhope Rd Mt Wellington  Auckland Auckland",
    "addr:housenumber":"39 c",
    "addr:street":"Stanhope Rd",
    "iso:country":"NZ",
    "sg:address":"39 C Stanhope Rd Mt Wellington ",
    "sg:city":"Auckland",
    "sg:orig_category":"Industrial: Services: Toolmakers And Designers",
    "sg:phone":"+64 9-579 1808",
    "sg:province":"Auckland",
    "wof:name":"Budget Tools",
    "wof:placetype":"venue"
},
  "geometry": {"coordinates":[174.830276,-36.893166],"type":"Point"}
}