{
  "type": "Feature",
  "properties": {
    "addr:full":"7 Sims Rd Penrose  Auckland Auckland",
    "addr:housenumber":"7",
    "addr:street":"Sims Rd",
    "iso:country":"NZ",
    "sg:address":"7 Sims Rd Penrose ",
    "sg:city":"Auckland",
    "sg:classifiers":[
        {
            "category":"Autos & Motor Vehicles",
            "subcategory":"Automobile Sales",
            "type":"Retail Goods"
        }
    ],
    "sg:phone":"+64 9-579 5855",
    "sg:province":"Auckland",
    "sg:tags":[
        "automotive"
    ],
    "sg:website":"http://www.yellowpages.co.nz/for/arobrosltd/dp25711.html",
    "wof:name":"Aro Bros Ltd",
    "wof:placetype":"venue"
},
  "geometry": {"coordinates":[174.824265,-36.916016],"type":"Point"}
}