{
  "type": "Feature",
  "properties": {
    "addr:full":"R D 2 State Highway 16  Helensville Auckland",
    "addr:housenumber":"2",
    "addr:street":"R D;State Highway 16",
    "iso:country":"NZ",
    "sg:address":"R D 2 State Highway 16 ",
    "sg:city":"Helensville",
    "sg:classifiers":[
        {
            "category":"Utilities",
            "type":"Services"
        }
    ],
    "sg:phone":"+64 256824472",
    "sg:province":"Auckland",
    "sg:tags":[
        "industrial",
        "energy",
        "utilities",
        "coal",
        "wood",
        "coke"
    ],
    "wof:name":"Bridge R L & C M",
    "wof:placetype":"venue"
},
  "geometry": {"coordinates":[174.45178200000001,-36.683239],"type":"Point"}
}