{
  "type": "Feature",
  "properties": {
    "addr:full":"13 Walters Rd Mt Wellington  Auckland Auckland",
    "addr:housenumber":"13",
    "addr:street":"Walters Rd",
    "iso:country":"NZ",
    "sg:address":"13 Walters Rd Mt Wellington ",
    "sg:city":"Auckland",
    "sg:orig_category":"Shopping: Gifts",
    "sg:phone":"+64 9-276 1202",
    "sg:province":"Auckland",
    "sg:website":"http://www.yellowpages.co.nz/pages/202980763/dp21141.html",
    "wof:name":"Baskets By Patricia",
    "wof:placetype":"venue"
},
  "geometry": {"coordinates":[174.84573399999999,-36.934696],"type":"Point"}
}