{
  "type": "Feature",
  "properties": {
    "addr:full":"Suite 1, Ascot Hospital 90 Greenlane Rd East Remuera Auckland Auckland",
    "addr:housenumber":"suite 1;90",
    "addr:street":"Ascot Hospital;Greenlane Rd East",
    "iso:country":"NZ",
    "sg:address":"Suite 1, Ascot Hospital 90 Greenlane Rd East Remuera",
    "sg:city":"Auckland",
    "sg:classifiers":[
        {
            "category":"Shopping",
            "subcategory":"Beauty & Cosmetics",
            "type":"Retail Goods"
        }
    ],
    "sg:phone":"+64 9-520 9670",
    "sg:province":"Auckland",
    "sg:tags":[
        "medical",
        "health"
    ],
    "sg:website":"http://www.thebreastcentre.co.nz",
    "wof:name":"The Breast Centre",
    "wof:placetype":"venue"
},
  "geometry": {"coordinates":[174.80886799999999,-36.869381],"type":"Point"}
}