{
  "type": "Feature",
  "properties": {
    "addr:full":"State Highway 1 R D 8 Whangarei  Waiotira",
    "addr:housenumber":"8",
    "addr:street":"State Highway 1 R D",
    "iso:country":"NZ",
    "sg:address":"State Highway 1 R D 8 Whangarei ",
    "sg:city":"Waiotira",
    "sg:classifiers":[
        {
            "category":"Landmark",
            "subcategory":"Tourist Information",
            "type":"Public Place"
        }
    ],
    "sg:phone":"+64 9-432 9889",
    "sg:tags":[
        "travel",
        "tourism",
        "tour",
        "sightseeing"
    ],
    "wof:name":"North New Zealand Inbound Tour Corporation",
    "wof:placetype":"venue"
},
  "geometry": {"coordinates":[174.19816599999999,-35.931419],"type":"Point"}
}