{
  "type": "Feature",
  "properties": {
    "addr:full":"Hull Rd Mt  Maunganui Bay of Plenty",
    "addr:street":"Hull Rd;Maunganui",
    "iso:country":"NZ",
    "sg:address":"Hull Rd Mt ",
    "sg:city":"Maunganui",
    "sg:classifiers":[
        {
            "category":"Parking",
            "subcategory":"Garage",
            "type":"Transportation"
        }
    ],
    "sg:phone":"+64 7-575 4129",
    "sg:province":"Bay of Plenty",
    "sg:tags":[
        "hire",
        "container",
        "transport",
        "lease"
    ],
    "sg:website":"http://www.nzlgroup.co.nz",
    "wof:name":"NZL Group Ltd",
    "wof:placetype":"venue"
},
  "geometry": {"coordinates":[176.18627900000001,-37.641048],"type":"Point"}
}