{
  "type": "Feature",
  "properties": {
    "addr:full":"37 Puckey Ave  Kaitaia Northland",
    "addr:housenumber":"37",
    "addr:street":"Puckey Ave",
    "iso:country":"NZ",
    "sg:address":"37 Puckey Ave ",
    "sg:city":"Kaitaia",
    "sg:classifiers":[
        {
            "category":"Health Services",
            "subcategory":"Clinic",
            "type":"Services"
        }
    ],
    "sg:phone":"+64 9-408 1170",
    "sg:province":"Northland",
    "sg:tags":[
        "medical",
        "beauty"
    ],
    "wof:name":"Williams Dr Cecil",
    "wof:placetype":"venue"
},
  "geometry": {"coordinates":[173.25984199999999,-35.111786],"type":"Point"}
}