{
  "type": "Feature",
  "properties": {
    "addr:full":"7 Parkway Dve Mairangi Bay  Auckland Wellington",
    "addr:housenumber":"7",
    "addr:street":"Parkway Dve",
    "iso:country":"NZ",
    "sg:address":"7 Parkway Dve Mairangi Bay ",
    "sg:city":"Auckland",
    "sg:orig_category":"Home And Garden: Furniture/Furnishings",
    "sg:phone":"+64 800 466 375",
    "sg:province":"Wellington",
    "sg:website":"http://www.homeplus.co.nz",
    "wof:name":"HomePlus",
    "wof:placetype":"venue"
},
  "geometry": {"coordinates":[174.77041600000001,-36.884109],"type":"Point"}
}