{
  "type": "Feature",
  "properties": {
    "iso:country":"NZ",
    "sg:address":"Best Is R D 1 ",
    "sg:city":"Richmond",
    "sg:orig_category":"Home And Garden: Gardening: Services: Kerbing",
    "sg:phone":"+64 800 527 981",
    "sg:province":"Nelson",
    "wof:name":"Kwik Kerb Nelson",
    "wof:placetype":"venue"
},
  "geometry": {"coordinates":[-72.367256,42.800056],"type":"Point"}
}