{
  "type": "Feature",
  "properties": {
    "iso:country":"NZ",
    "sg:address":"18 Gloucester St Greenmeadows ",
    "sg:city":"Napier",
    "sg:orig_category":"Industrial: Chemicals And Compounds: Solvents",
    "sg:phone":"+64 6-844 2589",
    "sg:province":"Hawke's Bay",
    "wof:name":"Ken-Coll Equipment",
    "wof:placetype":"venue"
},
  "geometry": {"coordinates":[176.862671,-39.525475],"type":"Point"}
}