{
  "type": "Feature",
  "properties": {
    "iso:country":"NZ",
    "sg:address":"407 Moray Pl ",
    "sg:city":"Dunedin",
    "sg:classifiers":[
        {
            "category":"Shopping",
            "subcategory":"Crafts & Fabrics",
            "type":"Retail Goods"
        }
    ],
    "sg:phone":"+64 3-477 7115",
    "sg:province":"Otago",
    "sg:tags":[
        "clothing"
    ],
    "sg:website":"http://www.ps.org.nz/otago",
    "wof:name":"Presbyterian Support (Otago)",
    "wof:placetype":"venue"
},
  "geometry": {"coordinates":[170.505157,-45.875378],"type":"Point"}
}