{
  "type": "Feature",
  "properties": {
    "addr:full":"120 Railside Ave Henderson  Auckland Auckland",
    "addr:housenumber":"120",
    "addr:street":"Railside Ave",
    "iso:country":"NZ",
    "sg:address":"120 Railside Ave Henderson ",
    "sg:city":"Auckland",
    "sg:orig_category":"Industrial: Services: Drum Reconditioners",
    "sg:phone":"+64 9-835 1403",
    "sg:province":"Auckland",
    "wof:name":"Henderson Pallet Ltd",
    "wof:placetype":"venue"
},
  "geometry": {"coordinates":[174.631775,-36.888012],"type":"Point"}
}