{
  "type": "Feature",
  "properties": {
    "addr:full":"1195 Wharf Rd  Coromandel",
    "addr:housenumber":"1195",
    "addr:street":"Wharf Rd",
    "iso:country":"NZ",
    "sg:address":"1195 Wharf Rd ",
    "sg:city":"Coromandel",
    "sg:classifiers":[
        {
            "category":"Restaurant",
            "type":"Food & Drink"
        }
    ],
    "sg:phone":"+64 7-866 8853",
    "sg:tags":[
        "fishing",
        "sea"
    ],
    "wof:name":"Sanford Limited Coromandel Branch",
    "wof:placetype":"venue"
},
  "geometry": {"coordinates":[175.493042,-36.761242],"type":"Point"}
}