{
  "type": "Feature",
  "properties": {
    "addr:full":"Whakatane RD  3",
    "addr:street":"Whakatane Rd 3",
    "iso:country":"NZ",
    "sg:address":"Whakatane RD ",
    "sg:city":"3",
    "sg:orig_category":"Farming: Horticulture",
    "sg:phone":"+64 7-304 8329",
    "wof:name":"Awakeri Enterprises",
    "wof:placetype":"venue"
},
  "geometry": {"coordinates":[176.984207,-37.965302],"type":"Point"}
}