{
  "type": "Feature",
  "properties": {
    "iso:country":"NZ",
    "sg:address":"Cuba Mall ",
    "sg:city":"Wellington",
    "sg:classifiers":[
        {
            "category":"Health Services",
            "subcategory":"Doctor",
            "type":"Services"
        }
    ],
    "sg:phone":"+64 4-383 9780",
    "sg:province":"Wellington",
    "sg:tags":[
        "beauty"
    ],
    "wof:name":"Blue Phoenix",
    "wof:placetype":"venue"
},
  "geometry": {"coordinates":[-77.806793,21.511021],"type":"Point"}
}