{
  "type": "Feature",
  "properties": {
    "iso:country":"NZ",
    "sg:address":"139 Newton Rd Newton ",
    "sg:city":"Auckland",
    "sg:orig_category":"Clothing And Fabric: Fabric: Drapers",
    "sg:phone":"+64 9-366 1991",
    "sg:province":"Auckland",
    "wof:name":"Global Fabrics",
    "wof:placetype":"venue"
},
  "geometry": {"coordinates":[174.759384,-36.863503],"type":"Point"}
}