{
  "type": "Feature",
  "properties": {
    "iso:country":"NZ",
    "sg:address":"74 Wilson St ",
    "sg:city":"Wanganui",
    "sg:orig_category":"Shopping: Retail Stores: Secondhand Dealers",
    "sg:phone":"+64 6-345 2667",
    "sg:province":"Manawatu-Wanganui",
    "wof:name":"Jon's Used Furniture Ltd",
    "wof:placetype":"venue"
},
  "geometry": {"coordinates":[175.045853,-39.933235],"type":"Point"}
}