{
  "type": "Feature",
  "properties": {
    "addr:full":"26 Kaka Rd Raumati  Kapiti",
    "addr:housenumber":"26",
    "addr:street":"Kaka Rd",
    "iso:country":"NZ",
    "sg:address":"26 Kaka Rd Raumati ",
    "sg:city":"Kapiti",
    "sg:classifiers":[
        {
            "category":"Social Services",
            "subcategory":"Child Care",
            "type":"Services"
        }
    ],
    "sg:phone":"+64 4-905 2216",
    "sg:tags":[
        "baby",
        "home",
        "product",
        "garden",
        "children"
    ],
    "wof:name":"Baby-On-The-Move",
    "wof:placetype":"venue"
},
  "geometry": {"coordinates":[174.98718299999999,-40.914898],"type":"Point"}
}