{
  "type": "Feature",
  "properties": {
    "iso:country":"NZ",
    "sg:address":"154 Hillside Rd ",
    "sg:city":"Dunedin",
    "sg:classifiers":[
        {
            "category":"Social Services",
            "subcategory":"Child Care",
            "type":"Services"
        }
    ],
    "sg:phone":"+64 3-455 8687",
    "sg:province":"Otago",
    "sg:tags":[
        "baby",
        "home",
        "product",
        "garden",
        "children"
    ],
    "wof:name":"Second Childhood",
    "wof:placetype":"venue"
},
  "geometry": {"coordinates":[-82.784721,28.013355],"type":"Point"}
}