{
  "type": "Feature",
  "properties": {
    "iso:country":"NZ",
    "sg:address":"14/2 Tavern Rd Silverdale Hibiscus ",
    "sg:city":"Hibiscus Coast",
    "sg:classifiers":[
        {
            "category":"Sports & Exercise",
            "subcategory":"Swimming Pool",
            "type":"Entertainment"
        }
    ],
    "sg:phone":"+64 9-427 4478",
    "sg:province":"Auckland",
    "sg:tags":[
        "kayak",
        "shopping",
        "canoe",
        "sports",
        "water",
        "retailers"
    ],
    "wof:name":"Barracuda Kayaks",
    "wof:placetype":"venue"
},
  "geometry": {"coordinates":[174.67746,-36.620598],"type":"Point"}
}