{
  "type": "Feature",
  "properties": {
    "addr:full":"120 Tahunanui Dve Tahunanui  Nelson Nelson",
    "addr:housenumber":"120",
    "addr:street":"Tahunanui Dve",
    "iso:country":"NZ",
    "sg:address":"120 Tahunanui Dve Tahunanui ",
    "sg:city":"Nelson",
    "sg:orig_category":"Industrial: Engineering: Engineers: Engineers - General",
    "sg:phone":"+64 3-546 5065",
    "sg:province":"Nelson",
    "wof:name":"G P Engineering Ltd",
    "wof:placetype":"venue"
},
  "geometry": {"coordinates":[173.24464399999999,-41.283855],"type":"Point"}
}