{
  "type": "Feature",
  "properties": {
    "iso:country":"NZ",
    "sg:address":"Hawkes Bay ",
    "sg:city":"Napier",
    "sg:orig_category":"Automotive: Parts And Supplies: Tyres",
    "sg:phone":"+64 800 386 567",
    "sg:province":"Hawke's Bay",
    "sg:website":"http://www.dunlop.co.nz",
    "wof:name":"Dunlop Flag Dealers",
    "wof:placetype":"venue"
},
  "geometry": {"coordinates":[176.916443,-39.49107],"type":"Point"}
}