{
  "type": "Feature",
  "properties": {
    "addr:full":"10/59 View Rd Glenfield  Auckland Auckland",
    "addr:housenumber":"10 / 59",
    "addr:street":"View Rd",
    "iso:country":"NZ",
    "sg:address":"10/59 View Rd Glenfield ",
    "sg:city":"Auckland",
    "sg:classifiers":[
        {
            "category":"Home & Garden",
            "subcategory":"Home Furnishings",
            "type":"Retail Goods"
        }
    ],
    "sg:phone":"+64 9-441 6159",
    "sg:province":"Auckland",
    "sg:tags":[
        "furniture/furnishings",
        "upholstery",
        "supply"
    ],
    "wof:name":"Total Trim Canvas & Upholstery Specialists",
    "wof:placetype":"venue"
},
  "geometry": {"coordinates":[174.736053,-36.771542],"type":"Point"}
}