{
  "type": "Feature",
  "properties": {
    "addr:full":"11 a Douglas Alexander Pde Albany  Auckland Auckland",
    "addr:housenumber":"11 a",
    "addr:street":"Douglas Alexander",
    "iso:country":"NZ",
    "sg:address":"11 a Douglas Alexander Pde Albany ",
    "sg:city":"Auckland",
    "sg:orig_category":"Health And Beauty: Products: Home Healthcare Equipment",
    "sg:phone":"+64 9-414 4805",
    "sg:province":"Auckland",
    "wof:name":"Plega Healthcare NZ Ltd",
    "wof:placetype":"venue"
},
  "geometry": {"coordinates":[174.69966099999999,-36.745281],"type":"Point"}
}