{
  "type": "Feature",
  "properties": {
    "addr:full":"38-40 Ben Lomond Cre Pakuranga  Auckland Auckland",
    "addr:housenumber":"38-40",
    "iso:country":"NZ",
    "sg:address":"38-40 Ben Lomond Cre Pakuranga ",
    "sg:city":"Auckland",
    "sg:classifiers":[
        {
            "category":"Marine",
            "type":"Transportation"
        }
    ],
    "sg:phone":"+64 9-576 3573",
    "sg:province":"Auckland",
    "sg:tags":[
        "boats",
        "builder",
        "yacht",
        "transport",
        "boat"
    ],
    "wof:name":"Marten Spars Limited",
    "wof:placetype":"venue"
},
  "geometry": {"coordinates":[174.90065000000001,-36.915932],"type":"Point"}
}