{
  "type": "Feature",
  "properties": {
    "iso:country":"NZ",
    "sg:address":"124 Sixteenth Ave ",
    "sg:city":"Tauranga",
    "sg:classifiers":[
        {
            "category":"Health Services",
            "subcategory":"Health Practitioner",
            "type":"Services"
        }
    ],
    "sg:phone":"+64 7-577 0637",
    "sg:province":"Bay of Plenty",
    "sg:tags":[
        "services",
        "beauty",
        "acupuncturists"
    ],
    "wof:name":"Healing World",
    "wof:placetype":"venue"
},
  "geometry": {"coordinates":[176.153976,-37.706142],"type":"Point"}
}