{
  "type": "Feature",
  "properties": {
    "iso:country":"NZ",
    "sg:address":"648 Dominion Rd Balmoral ",
    "sg:city":"Auckland",
    "sg:orig_category":"Shopping: Hobbies And Games: Handcrafts",
    "sg:phone":"+64 9-630 8479",
    "sg:province":"Auckland",
    "wof:name":"Bear Essentials",
    "wof:placetype":"venue"
},
  "geometry": {"coordinates":[174.747467,-36.886997],"type":"Point"}
}