{
  "type": "Feature",
  "properties": {
    "addr:full":"47 Commercial St  Takaka",
    "addr:housenumber":"47",
    "addr:street":"Commercial St",
    "iso:country":"NZ",
    "sg:address":"47 Commercial St ",
    "sg:city":"Takaka",
    "sg:classifiers":[
        {
            "category":"Food & Beverages",
            "subcategory":"Fruits & Vegetables",
            "type":"Retail Goods"
        }
    ],
    "sg:phone":"+64 3-525 8677",
    "sg:tags":[
        "product",
        "drink",
        "organic",
        "veges"
    ],
    "wof:name":"Golden Bay Organics",
    "wof:placetype":"venue"
},
  "geometry": {"coordinates":[172.80714399999999,-40.85276],"type":"Point"}
}