{
  "type": "Feature",
  "properties": {
    "addr:full":"Lynmall Shopping Centre New Lynn  Auckland Auckland",
    "iso:country":"NZ",
    "sg:address":"Lynmall Shopping Centre New Lynn ",
    "sg:city":"Auckland",
    "sg:classifiers":[
        {
            "category":"Internet Cafe",
            "subcategory":"None",
            "type":"Food & Drink"
        }
    ],
    "sg:phone":"+64 9-825 0915",
    "sg:province":"Auckland",
    "sg:tags":[
        "wining",
        "dining"
    ],
    "wof:name":"Warp 9",
    "wof:placetype":"venue"
},
  "geometry": {"coordinates":[174.68308999999999,-36.920143],"type":"Point"}
}