{
  "type": "Feature",
  "properties": {
    "iso:country":"NZ",
    "sg:address":"70 Allens Rd East Tamaki ",
    "sg:city":"Auckland",
    "sg:classifiers":[
        {
            "category":"Home & Garden",
            "subcategory":"Building Materials",
            "type":"Retail Goods"
        }
    ],
    "sg:phone":"+64 9-273 8600",
    "sg:province":"Auckland",
    "sg:tags":[
        "door",
        "fitting",
        "fittings"
    ],
    "wof:name":"B & D Doors New Zealand",
    "wof:placetype":"venue"
},
  "geometry": {"coordinates":[174.88490300000001,-36.938564],"type":"Point"}
}