{
  "type": "Feature",
  "properties": {
    "iso:country":"NZ",
    "sg:address":"78-80 King St Palmerston ",
    "sg:city":"Palmerston North",
    "sg:classifiers":[
        {
            "category":"Retail",
            "subcategory":"Repair Shop",
            "type":"Services"
        }
    ],
    "sg:phone":"+64 6-355 2826",
    "sg:province":"Manawatu-Wanganui",
    "sg:tags":[
        "clothing",
        "fabric",
        "cleaning"
    ],
    "wof:name":"Marilyns Sewing Studio",
    "wof:placetype":"venue"
},
  "geometry": {"coordinates":[175.61187699999999,-40.353645],"type":"Point"}
}