{
  "type": "Feature",
  "properties": {
    "addr:full":"1/21 Bancroft Cre Glendene  Auckland Auckland",
    "addr:housenumber":"1 / 21",
    "iso:country":"NZ",
    "sg:address":"1/21 Bancroft Cre Glendene ",
    "sg:city":"Auckland",
    "sg:orig_category":"Home And Garden: Furniture/Furnishings: Cabinetmakers",
    "sg:phone":"+64 9-818 5428",
    "sg:province":"Auckland",
    "wof:name":"Bennett Furniture Polishing",
    "wof:placetype":"venue"
},
  "geometry": {"coordinates":[174.63952599999999,-36.914719],"type":"Point"}
}