{
  "type": "Feature",
  "properties": {
    "iso:country":"NZ",
    "sg:address":"589 A Tremaine Ave Palmerston ",
    "sg:city":"Palmerston North",
    "sg:orig_category":"Automotive: Parts And Supplies: Tyres",
    "sg:phone":"+64 6-353 3590",
    "sg:province":"Manawatu-Wanganui",
    "wof:name":"Tremaine Tyres & Wheels Ltd",
    "wof:placetype":"venue"
},
  "geometry": {"coordinates":[175.603836,-40.34219],"type":"Point"}
}