{
  "type": "Feature",
  "properties": {
    "iso:country":"NZ",
    "sg:address":"46 Seddon St ",
    "sg:city":"Raetihi",
    "sg:classifiers":[
        {
            "category":"Landmark",
            "subcategory":"Tourist Information",
            "type":"Public Place"
        }
    ],
    "sg:phone":"+64 6-385 4805",
    "sg:tags":[
        "services",
        "travel",
        "tourism"
    ],
    "wof:name":"Raetihi Information Centre",
    "wof:placetype":"venue"
},
  "geometry": {"coordinates":[175.28218100000001,-39.427719],"type":"Point"}
}