{
  "type": "Feature",
  "properties": {
    "addr:full":"Campbell St  Tokoroa",
    "addr:street":"Campbell St",
    "iso:country":"NZ",
    "sg:address":"Campbell St ",
    "sg:city":"Tokoroa",
    "sg:classifiers":[
        {
            "category":"Retail",
            "subcategory":"Auto Repair",
            "type":"Services"
        }
    ],
    "sg:phone":"+64 7-886 7061",
    "sg:tags":[
        "wheel",
        "automotive",
        "servicing",
        "alignment"
    ],
    "wof:name":"Pitstop Mufflers",
    "wof:placetype":"venue"
},
  "geometry": {"coordinates":[175.868683,-38.218544],"type":"Point"}
}