{
  "type": "Feature",
  "properties": {
    "addr:full":"29 Kinghorne St Strathmore  Wellington Wellington",
    "addr:housenumber":"29",
    "addr:street":"Kinghorne St",
    "iso:country":"NZ",
    "sg:address":"29 Kinghorne St Strathmore ",
    "sg:city":"Wellington",
    "sg:orig_category":"Industrial: Equipment And Machinery: Generators",
    "sg:phone":"+64 4-939 0124",
    "sg:province":"Wellington",
    "wof:name":"Picture Power",
    "wof:placetype":"venue"
},
  "geometry": {"coordinates":[174.823792,-41.327236],"type":"Point"}
}