{
  "type": "Feature",
  "properties": {
    "addr:full":"Main Rd Sth  Otaki",
    "addr:street":"Main Rd",
    "iso:country":"NZ",
    "sg:address":"Main Rd Sth ",
    "sg:city":"Otaki",
    "sg:classifiers":[
        {
            "category":"Manufacturing",
            "subcategory":"Glass & Minerals",
            "type":"Manufacturing & Wholesale Goods"
        }
    ],
    "sg:phone":"+64 6-364 8932",
    "sg:tags":[
        "raw",
        "industrial",
        "quarry",
        "materials"
    ],
    "wof:name":"Winstone Aggregates A Division of Fletcher Concrete & Infrastructure Ltd",
    "wof:placetype":"venue"
},
  "geometry": {"coordinates":[173.227676,-41.317719],"type":"Point"}
}