{
  "type": "Feature",
  "properties": {
    "addr:full":"15 Rakino Way Mt Wellington  Auckland Auckland",
    "addr:housenumber":"15",
    "addr:street":"Rakino Way",
    "iso:country":"NZ",
    "sg:address":"15 Rakino Way Mt Wellington ",
    "sg:city":"Auckland",
    "sg:orig_category":"Industrial: Products: Laboratory Supplies",
    "sg:phone":"+64 9-276 4157",
    "sg:province":"Auckland",
    "wof:name":"Roche Diagnostics NZ Ltd",
    "wof:placetype":"venue"
},
  "geometry": {"coordinates":[174.85777300000001,-36.922935],"type":"Point"}
}