{
  "type": "Feature",
  "properties": {
    "iso:country":"NZ",
    "sg:address":"9 Marina View Mana ",
    "sg:city":"Wellington",
    "sg:classifiers":[
        {
            "category":"Shopping",
            "subcategory":"Bicycles & Sporting Goods",
            "type":"Retail Goods"
        }
    ],
    "sg:phone":"+64 4-233 8238",
    "sg:province":"Wellington",
    "sg:tags":[
        "sport",
        "fishing",
        "hunting",
        "retailers"
    ],
    "sg:website":"http://www.divespot.co.nz",
    "wof:name":"Dive Spot",
    "wof:placetype":"venue"
},
  "geometry": {"coordinates":[174.870544,-41.095112],"type":"Point"}
}