{
  "type": "Feature",
  "properties": {
    "iso:country":"NZ",
    "sg:address":"233 Victoria St ",
    "sg:city":"Wellington",
    "sg:classifiers":[
        {
            "category":"Food & Beverages",
            "subcategory":"Liquor & Beverages",
            "type":"Retail Goods"
        }
    ],
    "sg:phone":"+64 4-801 8805",
    "sg:province":"Wellington",
    "sg:tags":[
        "drink",
        "outlet"
    ],
    "wof:name":"The Mill Liquorsave",
    "wof:placetype":"venue"
},
  "geometry": {"coordinates":[-3.230097,50.981392],"type":"Point"}
}