{
  "type": "Feature",
  "properties": {
    "iso:country":"NZ",
    "sg:address":"71 Kemp Rd Massey ",
    "sg:city":"Auckland",
    "sg:classifiers":[
        {
            "category":"Real Estate",
            "subcategory":"Real Estate Services",
            "type":"Services"
        }
    ],
    "sg:phone":"+64 800 224 766",
    "sg:province":"Auckland",
    "sg:tags":[
        "home",
        "garden",
        "ironing"
    ],
    "wof:name":"Impress Ironing Services",
    "wof:placetype":"venue"
},
  "geometry": {"coordinates":[174.612289,-36.834621],"type":"Point"}
}