{
  "type": "Feature",
  "properties": {
    "iso:country":"NZ",
    "sg:address":"343 Gt South Rd Takanini ",
    "sg:city":"Auckland",
    "sg:orig_category":"Industrial: Engineering: Engineers - Mechanical",
    "sg:phone":"+64 9-298 8092",
    "sg:province":"Auckland",
    "wof:name":"Seel Engineering & Hydraulics Ltd",
    "wof:placetype":"venue"
},
  "geometry": {"coordinates":[174.931046,-37.052597],"type":"Point"}
}