{
  "type": "Feature",
  "properties": {
    "iso:country":"NZ",
    "sg:address":"2 Triangle Rd ",
    "sg:city":"Massey",
    "sg:classifiers":[
        {
            "category":"Food & Beverages",
            "subcategory":"Meat & Fish",
            "type":"Retail Goods"
        }
    ],
    "sg:phone":"+64 9-833 6272",
    "sg:tags":[
        "drink"
    ],
    "wof:name":"Mad Butcher",
    "wof:placetype":"venue"
},
  "geometry": {"coordinates":[-75.834679,39.310669],"type":"Point"}
}