{
  "type": "Feature",
  "properties": {
    "iso:country":"NZ",
    "sg:address":"Roberts St ",
    "sg:city":"Hastings",
    "sg:classifiers":[
        {
            "category":"Arena",
            "subcategory":"Sports Club",
            "type":"Entertainment"
        }
    ],
    "sg:phone":"+64 6-870 9266",
    "sg:province":"Hawke's Bay",
    "sg:tags":[
        "-",
        "leisure",
        "sports"
    ],
    "wof:name":"Cornwall Cricket Club (Hastings)",
    "wof:placetype":"venue"
},
  "geometry": {"coordinates":[-81.45462,29.646435],"type":"Point"}
}