{
  "type": "Feature",
  "properties": {
    "addr:full":"13 Hope St  Masterton Wellington",
    "addr:housenumber":"13",
    "addr:street":"Hope St",
    "iso:country":"NZ",
    "sg:address":"13 Hope St ",
    "sg:city":"Masterton",
    "sg:classifiers":[
        {
            "category":"Utilities",
            "subcategory":"Refuse",
            "type":"Services"
        }
    ],
    "sg:phone":"+64 6-377 4020",
    "sg:province":"Wellington",
    "sg:tags":[
        "bin",
        "hire",
        "garden",
        "cleaning",
        "rubbish",
        "home"
    ],
    "wof:name":"Tidy Bins",
    "wof:placetype":"venue"
},
  "geometry": {"coordinates":[175.66439800000001,-40.945438],"type":"Point"}
}