{
  "type": "Feature",
  "properties": {
    "addr:full":"Rock Shop Plaza Manners  Mall",
    "iso:country":"NZ",
    "sg:address":"Rock Shop Plaza Manners ",
    "sg:city":"Mall",
    "sg:classifiers":[
        {
            "category":"Health Services",
            "subcategory":"Podiatrist",
            "type":"Services"
        }
    ],
    "sg:phone":"+64 4-473 6131",
    "sg:tags":[
        "lens",
        "optical",
        "contact",
        "beauty"
    ],
    "wof:name":"Mills Moss & O'Connor Optometrists: Capitaleyes",
    "wof:placetype":"venue"
},
  "geometry": {"coordinates":[-82.883911,37.327473],"type":"Point"}
}