{
  "type": "Feature",
  "properties": {
    "addr:full":"R D 2 Ngaruawahia Te  Akau",
    "addr:housenumber":"2",
    "addr:street":"R D",
    "iso:country":"NZ",
    "sg:address":"R D 2 Ngaruawahia Te ",
    "sg:city":"Akau",
    "sg:classifiers":[
        {
            "category":"Manufacturing",
            "subcategory":"Glass & Minerals",
            "type":"Manufacturing & Wholesale Goods"
        }
    ],
    "sg:phone":"+64 7-825 4792",
    "sg:tags":[
        "raw",
        "industrial",
        "quarry",
        "materials"
    ],
    "wof:name":"Waingaro Quarry Limited",
    "wof:placetype":"venue"
},
  "geometry": {"coordinates":[175.14703399999999,-37.669849],"type":"Point"}
}