{
  "type": "Feature",
  "properties": {
    "addr:full":"State Highway 34 RD 2 Whakatane  Kawerau",
    "addr:street":"State Highway 34 Rd 2 Whakatane",
    "iso:country":"NZ",
    "sg:address":"State Highway 34 RD 2 Whakatane ",
    "sg:city":"Kawerau",
    "sg:orig_category":"Farming: Farms - General: Poultry",
    "sg:phone":"+64 7-323 8300",
    "wof:name":"Tarawera Egg Farm",
    "wof:placetype":"venue"
},
  "geometry": {"coordinates":[176.70512400000001,-38.087139],"type":"Point"}
}