{
  "type": "Feature",
  "properties": {
    "addr:full":"332 Broadway Ave Palmerston  Palmerston North Manawatu-Wanganui",
    "addr:housenumber":"332",
    "addr:street":"Broadway Ave",
    "iso:country":"NZ",
    "sg:address":"332 Broadway Ave Palmerston ",
    "sg:city":"Palmerston North",
    "sg:orig_category":"Health And Beauty: Dental: Dentists",
    "sg:phone":"+64 6-358 1509",
    "sg:province":"Manawatu-Wanganui",
    "wof:name":"Murray Ross",
    "wof:placetype":"venue"
},
  "geometry": {"coordinates":[175.62657200000001,-40.348049],"type":"Point"}
}