{
  "type": "Feature",
  "properties": {
    "iso:country":"NZ",
    "sg:address":"332 Broadway Ave Palmerston ",
    "sg:city":"Palmerston North",
    "sg:orig_category":"Health And Beauty: Dental: Dentists",
    "sg:phone":"+64 6-358 1509",
    "sg:province":"Manawatu-Wanganui",
    "wof:name":"Murray Ross",
    "wof:placetype":"venue"
},
  "geometry": {"coordinates":[175.626572,-40.348049],"type":"Point"}
}