{
  "type": "Feature",
  "properties": {
    "iso:country":"NZ",
    "sg:address":"No 2 Shed Kaiti Beach Rd ",
    "sg:city":"Gisborne",
    "sg:orig_category":"Transport: Boats And Marine: Shipping: Shipping Companies",
    "sg:phone":"+64 6-868 1612",
    "sg:province":"Gisborne",
    "wof:name":"Adsteam Port Services Ltd",
    "wof:placetype":"venue"
},
  "geometry": {"coordinates":[178.024475,-38.66597],"type":"Point"}
}