{
  "type": "Feature",
  "properties": {
    "addr:full":"Kopipi Cre Ngunguru  Whangarei Northland",
    "iso:country":"NZ",
    "sg:address":"Kopipi Cre Ngunguru ",
    "sg:city":"Whangarei",
    "sg:orig_category":"Health And Beauty: Beauty: Hairdressers",
    "sg:phone":"+64 9-434 3538",
    "sg:province":"Northland",
    "wof:name":"Ngunguru Hair Salon",
    "wof:placetype":"venue"
},
  "geometry": {"coordinates":[174.50528,-35.625801],"type":"Point"}
}