{
  "type": "Feature",
  "properties": {
    "addr:full":"496 Heads Rd  Wanganui Manawatu-Wanganui",
    "addr:housenumber":"496",
    "addr:street":"Heads Rd",
    "iso:country":"NZ",
    "sg:address":"496 Heads Rd ",
    "sg:city":"Wanganui",
    "sg:classifiers":[
        {
            "category":"Restaurant",
            "type":"Food & Drink"
        }
    ],
    "sg:phone":"+64 6-344 7000",
    "sg:province":"Manawatu-Wanganui",
    "sg:tags":[
        "merchant",
        "fish",
        "sea"
    ],
    "wof:name":"Wanganui Fish Wholesalers",
    "wof:placetype":"venue"
},
  "geometry": {"coordinates":[174.99603300000001,-39.943142],"type":"Point"}
}