{
  "type": "Feature",
  "properties": {
    "addr:full":"Auckland  Auckland Auckland",
    "iso:country":"NZ",
    "sg:address":"Auckland ",
    "sg:city":"Auckland",
    "sg:orig_category":"Automotive: Parts And Supplies: Tyres",
    "sg:phone":"+64 800 466 393",
    "sg:province":"Auckland",
    "sg:website":"http://www.goodyear.co.nz",
    "wof:name":"Goodyear Authorised Dealers",
    "wof:placetype":"venue"
},
  "geometry": {"coordinates":[174.78450000000001,-37.006058],"type":"Point"}
}