{
  "type": "Feature",
  "properties": {
    "iso:country":"NZ",
    "sg:address":"457 German Rd ",
    "sg:city":"Oxford",
    "sg:orig_category":"Industrial: Services: Gear Cutters",
    "sg:phone":"+64 3-312 3344",
    "wof:name":"Barry Lindon Gear Cutting",
    "wof:placetype":"venue"
},
  "geometry": {"coordinates":[-85.835701,33.613075],"type":"Point"}
}