{
  "type": "Feature",
  "properties": {
    "addr:full":"200 Ferry Rd  Christchurch Canterbury",
    "addr:housenumber":"200",
    "addr:street":"Ferry Rd",
    "iso:country":"NZ",
    "sg:address":"200 Ferry Rd ",
    "sg:city":"Christchurch",
    "sg:classifiers":[
        {
            "category":"Social Services",
            "subcategory":"Retirement Home",
            "type":"Services"
        }
    ],
    "sg:phone":"+64 3-366 6072",
    "sg:province":"Canterbury",
    "sg:tags":[
        "automotive"
    ],
    "sg:website":"http://www.yellowpages.co.nz/for/abouttownrentals/dp27364.html",
    "wof:name":"About Town Rentals",
    "wof:placetype":"venue"
},
  "geometry": {"coordinates":[-76.537834,37.605659],"type":"Point"}
}