{
  "type": "Feature",
  "properties": {
    "iso:country":"NZ",
    "sg:address":"Dock Wharf Rail Ferry Terminal Thorndon ",
    "sg:city":"Wellington",
    "sg:classifiers":[
        {
            "category":"Farming",
            "subcategory":"Fish & Marine Products",
            "type":"Manufacturing & Wholesale Goods"
        }
    ],
    "sg:phone":"+64 4-499 1560",
    "sg:province":"Wellington",
    "sg:tags":[
        "-",
        "boat",
        "transport"
    ],
    "wof:name":"Quay Marine Services Ltd",
    "wof:placetype":"venue"
},
  "geometry": {"coordinates":[174.776016,-41.274925],"type":"Point"}
}