{
  "type": "Feature",
  "properties": {
    "iso:country":"NZ",
    "sg:address":"59 Shirley Rd Papatoetoe ",
    "sg:city":"Auckland",
    "sg:classifiers":[
        {
            "category":"Shopping",
            "subcategory":"Thrift Store",
            "type":"Retail Goods"
        }
    ],
    "sg:phone":"+64 9-277 2190",
    "sg:province":"Canterbury",
    "sg:tags":[
        "-",
        "clothing",
        "secondhand",
        "fabric"
    ],
    "wof:name":"Southside Recycling Centre",
    "wof:placetype":"venue"
},
  "geometry": {"coordinates":[174.850311,-36.978245],"type":"Point"}
}