{
  "type": "Feature",
  "properties": {
    "addr:full":"8 Warren Pl  Mapua",
    "addr:housenumber":"8",
    "addr:street":"Warren Pl",
    "iso:country":"NZ",
    "sg:address":"8 Warren Pl ",
    "sg:city":"Mapua",
    "sg:classifiers":[
        {
            "category":"Home & Garden",
            "subcategory":"Building Materials",
            "type":"Retail Goods"
        }
    ],
    "sg:phone":"+64 3-540 2123",
    "sg:tags":[
        "design",
        "fitting",
        "fittings",
        "kitchen"
    ],
    "wof:name":"Ruby Bay Joinery Ltd",
    "wof:placetype":"venue"
},
  "geometry": {"coordinates":[-90.233299,32.227798],"type":"Point"}
}