{
  "type": "Feature",
  "properties": {
    "iso:country":"NZ",
    "sg:address":"439 Lake Rd Takapuna ",
    "sg:city":"Auckland",
    "sg:orig_category":"Health And Beauty: Specialists: Physiotherapists",
    "sg:phone":"+64 9-486 3194",
    "sg:province":"Auckland",
    "wof:name":"Foster Marcelle Physiotherapist",
    "wof:placetype":"venue"
},
  "geometry": {"coordinates":[174.773743,-36.791271],"type":"Point"}
}