{
  "type": "Feature",
  "properties": {
    "addr:full":"11 Boronia St  Tokoroa",
    "addr:housenumber":"11",
    "addr:street":"Boronia St",
    "iso:country":"NZ",
    "sg:address":"11 Boronia St ",
    "sg:city":"Tokoroa",
    "sg:orig_category":"Industrial: Parts",
    "sg:phone":"+64 7-886 4020",
    "sg:website":"http://www.valverepair.co.nz",
    "wof:name":"I V E Group",
    "wof:placetype":"venue"
},
  "geometry": {"coordinates":[175.876846,-38.232845],"type":"Point"}
}