{
  "type": "Feature",
  "properties": {
    "addr:full":"418 Kamo Rd  Whangarei Northland",
    "addr:housenumber":"418",
    "addr:street":"Kamo Rd",
    "iso:country":"NZ",
    "sg:address":"418 Kamo Rd ",
    "sg:city":"Whangarei",
    "sg:orig_category":"Shopping: Retail Stores: Department Stores",
    "sg:phone":"+64 9-435 3349",
    "sg:province":"Northland",
    "wof:name":"Variety Discounters Kamo",
    "wof:placetype":"venue"
},
  "geometry": {"coordinates":[174.300735,-35.682625],"type":"Point"}
}