{
  "type": "Feature",
  "properties": {
    "iso:country":"NZ",
    "sg:address":"101-105 Fergusson St Feilding ",
    "sg:city":"Feilding",
    "sg:orig_category":"Shopping: Accessories: Bags - Fashion",
    "sg:phone":"+64 6-323 4248",
    "sg:province":"Manawatu-Wanganui",
    "wof:name":"Turners Gifts & Luggage",
    "wof:placetype":"venue"
},
  "geometry": {"coordinates":[175.566757,-40.226425],"type":"Point"}
}