{
  "type": "Feature",
  "properties": {
    "iso:country":"NZ",
    "sg:address":"PO Box 329 ",
    "sg:city":"Cambridge",
    "sg:orig_category":"Sports And Leisure: General: Clubs",
    "sg:phone":"+64 7-827 6004",
    "sg:province":"Waikato",
    "wof:name":"Cambridge Jockey Club",
    "wof:placetype":"venue"
},
  "geometry": {"coordinates":[-116.67604799999999,44.572186],"type":"Point"}
}