{
  "type": "Feature",
  "properties": {
    "addr:full":"26 Ventura St Mangere  Auckland Auckland",
    "addr:housenumber":"26",
    "addr:street":"Ventura St",
    "iso:country":"NZ",
    "sg:address":"26 Ventura St Mangere ",
    "sg:city":"Auckland",
    "sg:orig_category":"Home And Garden: Outdoor: Stonemasons",
    "sg:phone":"+64 9-257 2040",
    "sg:province":"Auckland",
    "wof:name":"Real Stone Masons Ltd",
    "wof:placetype":"venue"
},
  "geometry": {"coordinates":[174.79283100000001,-36.958729],"type":"Point"}
}