{
  "type": "Feature",
  "properties": {
    "addr:full":"R D 4  Hamilton Waikato",
    "addr:housenumber":"4",
    "addr:street":"R D",
    "iso:country":"NZ",
    "sg:address":"R D 4 ",
    "sg:city":"Hamilton",
    "sg:classifiers":[
        {
            "category":"Home & Garden",
            "subcategory":"Garden Supply",
            "type":"Retail Goods"
        }
    ],
    "sg:phone":"+64 25518810",
    "sg:province":"Waikato",
    "sg:tags":[
        "products",
        "lawn",
        "gardening",
        "turf"
    ],
    "wof:name":"Small Block Maintenance",
    "wof:placetype":"venue"
},
  "geometry": {"coordinates":[175.276993,-37.783215],"type":"Point"}
}