{
  "type": "Feature",
  "properties": {
    "addr:full":"159 Manukau Rd  Pukekohe Auckland",
    "addr:housenumber":"159",
    "addr:street":"Manukau Rd",
    "iso:country":"NZ",
    "sg:address":"159 Manukau Rd ",
    "sg:city":"Pukekohe",
    "sg:classifiers":[
        {
            "category":"Utilities",
            "subcategory":"Fuel Oil & Lpg",
            "type":"Services"
        }
    ],
    "sg:phone":"+64 9-238 7049",
    "sg:province":"Auckland",
    "sg:tags":[
        "petrol",
        "energy",
        "industrial",
        "utilities"
    ],
    "wof:name":"Mobil Oil New Zealand Limited",
    "wof:placetype":"venue"
},
  "geometry": {"coordinates":[174.930252,-37.195728],"type":"Point"}
}