{
  "type": "Feature",
  "properties": {
    "iso:country":"NZ",
    "sg:address":"90 Bryant St Palmerston ",
    "sg:city":"Palmerston North",
    "sg:orig_category":"Non-Classified Establishments",
    "sg:phone":"+64 6-358 0886",
    "sg:province":"Manawatu-Wanganui",
    "wof:name":"Vinart Motorsport Ltd",
    "wof:placetype":"venue"
},
  "geometry": {"coordinates":[175.600204,-40.361053],"type":"Point"}
}