{
  "type": "Feature",
  "properties": {
    "addr:full":"4107 Gt North Rd Glen Eden  Auckland Auckland",
    "addr:housenumber":"4107",
    "addr:street":"Gt North Rd",
    "iso:country":"NZ",
    "sg:address":"4107 Gt North Rd Glen Eden ",
    "sg:city":"Auckland",
    "sg:orig_category":"Transport: Boats And Marine: Boats: Boat Dealers",
    "sg:phone":"+64 9-818 5604",
    "sg:province":"Auckland",
    "sg:website":"http://www.bensemann.co.nz",
    "wof:name":"Bensemann Boating Centre Ltd",
    "wof:placetype":"venue"
},
  "geometry": {"coordinates":[174.65733299999999,-36.903194],"type":"Point"}
}