{
  "type": "Feature",
  "properties": {
    "iso:country":"NZ",
    "sg:address":"Westgate Shopping Centre Fernhill Dve Westgate ",
    "sg:city":"Auckland",
    "sg:classifiers":[
        {
            "category":"Shopping",
            "subcategory":"Crafts & Fabrics",
            "type":"Retail Goods"
        }
    ],
    "sg:phone":"+64 9-831 0277",
    "sg:province":"Otago",
    "sg:tags":[
        "sport",
        "art",
        "leisure",
        "hobbies"
    ],
    "wof:name":"Craftworld",
    "wof:placetype":"venue"
},
  "geometry": {"coordinates":[-119.104584,36.59774],"type":"Point"}
}