{
  "type": "Feature",
  "properties": {
    "iso:country":"NZ",
    "sg:address":"PO Box 5138 ",
    "sg:city":"Wellington",
    "sg:classifiers":[
        {
            "category":"Communications",
            "subcategory":"Television Station",
            "type":"Services"
        }
    ],
    "sg:phone":"+64 508 726 362",
    "sg:province":"Wellington",
    "sg:tags":[
        "broadcasting"
    ],
    "sg:website":"http://www.sandman.co.nz",
    "wof:name":"Sandman Ltd",
    "wof:placetype":"venue"
},
  "geometry": {"coordinates":[-85.910454,33.827946],"type":"Point"}
}