{
  "type": "Feature",
  "properties": {
    "iso:country":"NZ",
    "sg:address":"346 Victoria Ave ",
    "sg:city":"Wanganui",
    "sg:orig_category":"Shopping: Sports Retailers: Sports Goods: Canvas Goods",
    "sg:phone":"+64 6-345 4997",
    "sg:province":"Manawatu-Wanganui",
    "wof:name":"Blind Boutique",
    "wof:placetype":"venue"
},
  "geometry": {"coordinates":[175.041931,-39.926746],"type":"Point"}
}