{
  "type": "Feature",
  "properties": {
    "addr:full":"22 Ben Lomond Cre Pakuranga  Auckland Auckland",
    "addr:housenumber":"22",
    "iso:country":"NZ",
    "sg:address":"22 Ben Lomond Cre Pakuranga ",
    "sg:city":"Auckland",
    "sg:classifiers":[
        {
            "category":"Manufacturing",
            "subcategory":"Chemicals & Compounds",
            "type":"Manufacturing & Wholesale Goods"
        }
    ],
    "sg:phone":"+64 9-576 9046",
    "sg:province":"Auckland",
    "sg:tags":[
        "soap",
        "industrial",
        "washing",
        "powder",
        "compounds"
    ],
    "wof:name":"The Soap Factory Ltd",
    "wof:placetype":"venue"
},
  "geometry": {"coordinates":[174.89977999999999,-36.914951],"type":"Point"}
}