{
  "type": "Feature",
  "properties": {
    "iso:country":"NZ",
    "sg:address":"91 Revell St ",
    "sg:city":"Hokitika",
    "sg:orig_category":"Clothing And Fabric: Fabric: Textiles",
    "sg:phone":"+64 3-755 7758",
    "sg:province":"West Coast",
    "wof:name":"Addisons Clothing",
    "wof:placetype":"venue"
},
  "geometry": {"coordinates":[170.967926,-42.711647],"type":"Point"}
}