{
  "type": "Feature",
  "properties": {
    "iso:country":"NZ",
    "sg:address":"66 McLean St ",
    "sg:city":"Waitara",
    "sg:orig_category":"Automotive: General Services: Service Stations",
    "sg:phone":"+64 6-754 7718",
    "wof:name":"Rosewarne Motors Ltd",
    "wof:placetype":"venue"
},
  "geometry": {"coordinates":[174.239532,-39.000023],"type":"Point"}
}