{
  "type": "Feature",
  "properties": {
    "iso:country":"NZ",
    "sg:address":"26 Kenneth Small Pl Remuera ",
    "sg:city":"Auckland",
    "sg:orig_category":"Shopping: Retail Stores: Dolls",
    "sg:phone":"+64 9-520 4254",
    "sg:province":"Auckland",
    "wof:name":"Te Kahurangi Dolls",
    "wof:placetype":"venue"
},
  "geometry": {"coordinates":[174.808868,-36.869381],"type":"Point"}
}