{
  "type": "Feature",
  "properties": {
    "addr:full":"cnr Panama & Featherston Sts  Wellington Wellington",
    "addr:street":"Cnr Panama & Featherston Sts",
    "iso:country":"NZ",
    "sg:address":"cnr Panama & Featherston Sts ",
    "sg:city":"Wellington",
    "sg:classifiers":[
        {
            "category":"Travel",
            "subcategory":"Travel Agent",
            "type":"Entertainment"
        }
    ],
    "sg:phone":"+64 4-472 4294",
    "sg:province":"Wellington",
    "sg:tags":[
        "tourism",
        "broker"
    ],
    "sg:website":"http://www.unitedtravel.co.nz/Page.php?page=238",
    "wof:name":"Harbour City United Travel",
    "wof:placetype":"venue"
},
  "geometry": {"coordinates":[175.32214400000001,-41.112888],"type":"Point"}
}