{
  "type": "Feature",
  "properties": {
    "iso:country":"NZ",
    "sg:address":"324 High St ",
    "sg:city":"Carterton",
    "sg:classifiers":[
        {
            "category":"Home & Garden",
            "subcategory":"Garden Supply",
            "type":"Retail Goods"
        }
    ],
    "sg:phone":"+64 6-379 8946",
    "sg:tags":[
        "products",
        "nursery",
        "gardening"
    ],
    "wof:name":"Potagers Plant Farm",
    "wof:placetype":"venue"
},
  "geometry": {"coordinates":[-82.190933,36.941956],"type":"Point"}
}