{
  "type": "Feature",
  "properties": {
    "addr:full":"73 The Concourse Massey  Auckland Auckland",
    "addr:housenumber":"73;concourse",
    "addr:street":"The",
    "iso:country":"NZ",
    "sg:address":"73 The Concourse Massey ",
    "sg:city":"Auckland",
    "sg:classifiers":[
        {
            "category":"Sports & Exercise",
            "subcategory":"Sports Center",
            "type":"Entertainment"
        }
    ],
    "sg:phone":"+64 9-836 4604",
    "sg:province":"Auckland",
    "sg:tags":[
        "sporting",
        "sports",
        "-",
        "leisure",
        "facility"
    ],
    "wof:name":"Waitemata Indoor Cricket Centre",
    "wof:placetype":"venue"
},
  "geometry": {"coordinates":[174.63568100000001,-36.828793],"type":"Point"}
}