{
  "type": "Feature",
  "properties": {
    "addr:full":"2 Fred Thomas Dve Takapuna  Auckland Auckland",
    "addr:housenumber":"2",
    "addr:street":"Fred;Dve",
    "iso:country":"NZ",
    "sg:address":"2 Fred Thomas Dve Takapuna ",
    "sg:city":"Auckland",
    "sg:classifiers":[
        {
            "category":"Marine",
            "type":"Transportation"
        }
    ],
    "sg:phone":"+64 9-489 1850",
    "sg:province":"Auckland",
    "sg:tags":[
        "transport",
        "boat"
    ],
    "sg:website":"http://www.cbes.org.nz",
    "wof:name":"Coastguard Boating Education",
    "wof:placetype":"venue"
},
  "geometry": {"coordinates":[174.762924,-36.790657],"type":"Point"}
}