{
  "type": "Feature",
  "properties": {
    "iso:country":"NZ",
    "sg:address":"45 Horormatangi St ",
    "sg:city":"Taupo",
    "sg:classifiers":[
        {
            "category":"Restaurant",
            "type":"Food & Drink"
        }
    ],
    "sg:phone":"+64 7-377 4478",
    "sg:province":"Waikato",
    "sg:tags":[
        "wining",
        "dining"
    ],
    "sg:website":"http://www.villino.co.nz",
    "wof:name":"Villino Restaurant",
    "wof:placetype":"venue"
},
  "geometry": {"coordinates":[176.071808,-38.687187],"type":"Point"}
}