{
  "type": "Feature",
  "properties": {
    "addr:full":"P O Box 260035 Howick East  Auckland Auckland",
    "addr:postcode":"260035;east",
    "addr:street":"Box",
    "iso:country":"NZ",
    "sg:address":"P O Box 260035 Howick East ",
    "sg:city":"Auckland",
    "sg:classifiers":[
        {
            "category":"Real Estate",
            "subcategory":"Real Estate Services",
            "type":"Services"
        }
    ],
    "sg:phone":"+64 9-537 0140",
    "sg:province":"Auckland",
    "sg:tags":[
        "home",
        "garden"
    ],
    "wof:name":"Realty Information Limited",
    "wof:placetype":"venue"
},
  "geometry": {"coordinates":[174.916946,-36.894379],"type":"Point"}
}