{
  "type": "Feature",
  "properties": {
    "iso:country":"NZ",
    "sg:address":"335 Fenton St ",
    "sg:city":"Rotorua",
    "sg:classifiers":[
        {
            "category":"Travel",
            "subcategory":"Hotels & Motels",
            "type":"Entertainment"
        }
    ],
    "sg:phone":"+64 7-349 0960",
    "sg:province":"Bay of Plenty",
    "sg:tags":[
        "lodge",
        "tourism",
        "accommodation"
    ],
    "sg:website":"http://www.yellowpages.co.nz/for/coachmanmotorinn/dp46045.html",
    "wof:name":"Coachman Motor Inn",
    "wof:placetype":"venue"
},
  "geometry": {"coordinates":[176.25367700000001,-38.15406],"type":"Point"}
}