{
  "type": "Feature",
  "properties": {
    "addr:full":"3/1 Tainui Rd Mt Wellington  Auckland Auckland",
    "addr:housenumber":"3 / 1",
    "addr:street":"Tainui Rd",
    "iso:country":"NZ",
    "sg:address":"3/1 Tainui Rd Mt Wellington ",
    "sg:city":"Auckland",
    "sg:orig_category":"Industrial: Packaging: Boxes And Cases",
    "sg:phone":"+64 9-570 1861",
    "sg:province":"Auckland",
    "wof:name":"Box-A-Long Ltd",
    "wof:placetype":"venue"
},
  "geometry": {"coordinates":[174.85202000000001,-36.889355],"type":"Point"}
}