{
  "type": "Feature",
  "properties": {
    "iso:country":"NZ",
    "sg:address":"179 Burnett St ",
    "sg:city":"Ashburton",
    "sg:classifiers":[
        {
            "category":"Shopping",
            "subcategory":"Crafts & Fabrics",
            "type":"Retail Goods"
        }
    ],
    "sg:phone":"+64 3-308 6243",
    "sg:province":"Canterbury",
    "sg:tags":[
        "knitting",
        "wool",
        "clothing"
    ],
    "wof:name":"Yarn Barn",
    "wof:placetype":"venue"
},
  "geometry": {"coordinates":[-77.127831,39.012852],"type":"Point"}
}