{
  "type": "Feature",
  "properties": {
    "addr:full":"PO Box 549 Paraparaumu  Wellington Wellington",
    "addr:housenumber":"po",
    "addr:street":"Box 549",
    "iso:country":"NZ",
    "sg:address":"PO Box 549 Paraparaumu ",
    "sg:city":"Wellington",
    "sg:classifiers":[
        {
            "category":"Shopping",
            "subcategory":"Computers & Home Electronics",
            "type":"Retail Goods"
        }
    ],
    "sg:phone":"+64 4-902 5454",
    "sg:province":"Wellington",
    "sg:tags":[
        "equipment",
        "sport",
        "leisure",
        "entertainment"
    ],
    "wof:name":"Music Systems (NZ) Limited",
    "wof:placetype":"venue"
},
  "geometry": {"coordinates":[175.00799599999999,-40.910465],"type":"Point"}
}