{
  "type": "Feature",
  "properties": {
    "addr:full":"Anderson Rd  Kaukapakapa",
    "addr:street":"Anderson Rd",
    "iso:country":"NZ",
    "sg:address":"Anderson Rd ",
    "sg:city":"Kaukapakapa",
    "sg:orig_category":"Sports And Leisure: Sports: Equestrian: Equestrian Supplies",
    "sg:phone":"+64 9-420 5888",
    "wof:name":"Trent Equestrian",
    "wof:placetype":"venue"
},
  "geometry": {"coordinates":[174.502365,-36.618408],"type":"Point"}
}