{
  "type": "Feature",
  "properties": {
    "iso:country":"NZ",
    "sg:address":"Kitchener St ",
    "sg:city":"Wairoa",
    "sg:classifiers":[
        {
            "category":"Restaurant",
            "type":"Food & Drink"
        }
    ],
    "sg:phone":"+64 6-838 8685",
    "sg:tags":[
        "wining",
        "dining",
        "pizza"
    ],
    "wof:name":"Robbie's Pizza Place",
    "wof:placetype":"venue"
},
  "geometry": {"coordinates":[177.42314099999999,-39.047649],"type":"Point"}
}