{
  "type": "Feature",
  "properties": {
    "addr:full":"122 Wainoni Rd  Christchurch Canterbury",
    "addr:housenumber":"122",
    "addr:street":"Wainoni Rd",
    "iso:country":"NZ",
    "sg:address":"122 Wainoni Rd ",
    "sg:city":"Christchurch",
    "sg:classifiers":[
        {
            "category":"Food Court",
            "type":"Food & Drink"
        }
    ],
    "sg:phone":"+64 3-388 5602",
    "sg:province":"Canterbury",
    "sg:tags":[
        "manufacturer"
    ],
    "wof:name":"Double R Softdrinks Ltd",
    "wof:placetype":"venue"
},
  "geometry": {"coordinates":[172.68888899999999,-43.514896],"type":"Point"}
}