{
  "type": "Feature",
  "properties": {
    "addr:full":"Room 14 Albert Building 81 Peel St  Gisborne Gisborne",
    "addr:housenumber":"14;81",
    "addr:street":"Peel St",
    "iso:country":"NZ",
    "sg:address":"Room 14 Albert Building 81 Peel St ",
    "sg:city":"Gisborne",
    "sg:orig_category":"Farming: Forestry: Logging Services",
    "sg:phone":"+64 6-863 3523",
    "sg:province":"Gisborne",
    "wof:name":"Kaimahi Logging Co. Ltd",
    "wof:placetype":"venue"
},
  "geometry": {"coordinates":[178.024475,-38.66597],"type":"Point"}
}