{
  "type": "Feature",
  "properties": {
    "iso:country":"NZ",
    "sg:address":"61 Walker St ",
    "sg:city":"Bluff",
    "sg:classifiers":[
        {
            "category":"Organizations",
            "subcategory":"Labor Organization",
            "type":"Services"
        }
    ],
    "sg:phone":"+64 3-212 7254",
    "sg:tags":[
        "services",
        "charter",
        "tourism",
        "travel",
        "boat"
    ],
    "wof:name":"Mana Charters",
    "wof:placetype":"venue"
},
  "geometry": {"coordinates":[-80.84745,32.260349],"type":"Point"}
}