{
  "type": "Feature",
  "properties": {
    "addr:full":"8 Ascension Pl Mairangi Bay  Auckland Auckland",
    "addr:housenumber":"8",
    "addr:street":"Ascension Pl",
    "iso:country":"NZ",
    "sg:address":"8 Ascension Pl Mairangi Bay ",
    "sg:city":"Auckland",
    "sg:orig_category":"Shopping: Sports Retailers: Water Sports: Diving Equipment",
    "sg:phone":"+64 9-479 4826",
    "sg:province":"Auckland",
    "wof:name":"Sport Divers Supplies Ltd",
    "wof:placetype":"venue"
},
  "geometry": {"coordinates":[174.74816899999999,-36.738461],"type":"Point"}
}