{
  "type": "Feature",
  "properties": {
    "iso:country":"NZ",
    "sg:address":"22 St Heliers Bay Rd",
    "sg:city":"Auckland",
    "sg:classifiers":[
        {
            "category":"Banks & Credit Unions",
            "subcategory":"Bank",
            "type":"Services"
        }
    ],
    "sg:phone":"+64 9556482",
    "sg:province":"Auckland",
    "wof:name":"ANZ Banking Group (New Zealand) Ltd",
    "wof:placetype":"venue"
},
  "geometry": {"coordinates":[174.85775799999999,-36.850716],"type":"Point"}
}