{
  "type": "Feature",
  "properties": {
    "addr:full":"163 D Wordsworth St Sydenham  Christchurch Canterbury",
    "addr:housenumber":"163 d",
    "addr:street":"Wordsworth St",
    "iso:country":"NZ",
    "sg:address":"163 D Wordsworth St Sydenham ",
    "sg:city":"Christchurch",
    "sg:orig_category":"Industrial: Parts: Bearings",
    "sg:phone":"+64 3-379 4610",
    "sg:province":"Canterbury",
    "wof:name":"SKF New Zealand Ltd",
    "wof:placetype":"venue"
},
  "geometry": {"coordinates":[172.643204,-43.544533],"type":"Point"}
}