{
  "type": "Feature",
  "properties": {
    "iso:country":"NZ",
    "sg:address":"181 Mahurangi East Rd Snells Beach ",
    "sg:city":"Warkworth",
    "sg:orig_category":"Sports And Leisure: Entertainment: Balloons",
    "sg:phone":"+64 9-425 4073",
    "sg:province":"Auckland",
    "wof:name":"The Balloon Works",
    "wof:placetype":"venue"
},
  "geometry": {"coordinates":[174.71961999999999,-36.409065],"type":"Point"}
}