{
  "type": "Feature",
  "properties": {
    "iso:country":"NZ",
    "sg:address":"Omahuta Rd ",
    "sg:city":"Okaihau",
    "sg:orig_category":"Home And Garden: Furniture/Furnishings: Cabinetmakers",
    "sg:phone":"+64 9-401 9222",
    "wof:name":"MacCarthy Noel",
    "wof:placetype":"venue"
},
  "geometry": {"coordinates":[173.765503,-35.323444],"type":"Point"}
}