{
  "type": "Feature",
  "properties": {
    "addr:full":"8 St Andrew Pl North Balclutha  Balclutha",
    "addr:housenumber":"8",
    "addr:street":"St Andrew Pl North",
    "iso:country":"NZ",
    "sg:address":"8 St Andrew Pl North Balclutha ",
    "sg:city":"Balclutha",
    "sg:orig_category":"Health And Beauty: Specialists: Midwives",
    "sg:phone":"+64 3-418 1007",
    "wof:name":"McIntosh Carolyn",
    "wof:placetype":"venue"
},
  "geometry": {"coordinates":[169.74679599999999,-46.234798],"type":"Point"}
}