{
  "type": "Feature",
  "properties": {
    "iso:country":"NZ",
    "sg:address":"2 Don St ",
    "sg:city":"Invercargill",
    "sg:classifiers":[
        {
            "category":"Shopping",
            "subcategory":"Gifts & Souvenirs",
            "type":"Retail Goods"
        }
    ],
    "sg:phone":"+64 3-218 3054",
    "sg:province":"Southland",
    "sg:tags":[
        "travel",
        "tourism"
    ],
    "wof:name":"Invercargill Souvenirs & Gifts",
    "wof:placetype":"venue"
},
  "geometry": {"coordinates":[168.347641,-46.410637],"type":"Point"}
}