{
  "type": "Feature",
  "properties": {
    "iso:country":"NZ",
    "sg:address":"PO Box 12028 ",
    "sg:city":"Penrose",
    "sg:orig_category":"Home And Garden: Gardening: Services: Garden Maintenance",
    "sg:phone":"+64 9-525 4014",
    "sg:province":"Auckland",
    "wof:name":"V.I.P. Home Services",
    "wof:placetype":"venue"
},
  "geometry": {"coordinates":[-105.02407100000001,38.431049],"type":"Point"}
}