{
  "type": "Feature",
  "properties": {
    "addr:full":"4/60 Glenmall Pl Glen Eden  Auckland Auckland",
    "addr:housenumber":"4 / 60",
    "addr:street":"Glenmall Pl",
    "iso:country":"NZ",
    "sg:address":"4/60 Glenmall Pl Glen Eden ",
    "sg:city":"Auckland",
    "sg:classifiers":[
        {
            "category":"Restaurant",
            "type":"Food & Drink"
        }
    ],
    "sg:phone":"+64 9-818 1763",
    "sg:province":"Auckland",
    "sg:tags":[
        "brewing",
        "supply"
    ],
    "wof:name":"Open-It Home Brew Suppliers",
    "wof:placetype":"venue"
},
  "geometry": {"coordinates":[174.65237400000001,-36.910801],"type":"Point"}
}