{
  "type": "Feature",
  "properties": {
    "addr:full":"Cnr McLean & West Quay  Waitara Taranaki",
    "addr:street":"Cnr Mclean & West Quay",
    "iso:country":"NZ",
    "sg:address":"Cnr McLean & West Quay ",
    "sg:city":"Waitara",
    "sg:classifiers":[
        {
            "category":"Sports & Exercise",
            "subcategory":"Swimming Pool",
            "type":"Entertainment"
        }
    ],
    "sg:phone":"+64 6-754 8368",
    "sg:province":"Taranaki",
    "sg:tags":[
        "kayak",
        "shopping",
        "canoe",
        "sports",
        "water",
        "retailers"
    ],
    "wof:name":"Canoe & Kayak - Taranaki",
    "wof:placetype":"venue"
},
  "geometry": {"coordinates":[174.23730499999999,-39.00127],"type":"Point"}
}