{
  "type": "Feature",
  "properties": {
    "iso:country":"NZ",
    "sg:address":"40 Raroa Tce Greenacres ",
    "sg:city":"Wellington",
    "sg:orig_category":"Home And Garden: Gardening: Services: Lawnmowing Services",
    "sg:phone":"+64 4-232 3530",
    "sg:province":"Wellington",
    "wof:name":"Down 2 Earth",
    "wof:placetype":"venue"
},
  "geometry": {"coordinates":[174.838821,-41.16589],"type":"Point"}
}