{
  "type": "Feature",
  "properties": {
    "addr:full":"20 Radnor Rd Mt Roskill  Auckland Auckland",
    "addr:housenumber":"20",
    "addr:street":"Radnor Rd",
    "iso:country":"NZ",
    "sg:address":"20 Radnor Rd Mt Roskill ",
    "sg:city":"Auckland",
    "sg:classifiers":[
        {
            "category":"Social Services",
            "subcategory":"Retirement Home",
            "type":"Services"
        }
    ],
    "sg:phone":"+64 9-620 8021",
    "sg:province":"Auckland",
    "sg:tags":[
        "care",
        "garden",
        "elderly",
        "village"
    ],
    "wof:name":"Gracedale Homes",
    "wof:placetype":"venue"
},
  "geometry": {"coordinates":[174.738754,-36.909721],"type":"Point"}
}