{
  "type": "Feature",
  "properties": {
    "iso:country":"NZ",
    "sg:address":"35 Colwyn St Bryndwr ",
    "sg:city":"Christchurch",
    "sg:classifiers":[
        {
            "category":"Health Services",
            "subcategory":"Health Practitioner",
            "type":"Services"
        }
    ],
    "sg:phone":"+64 3-351 5886",
    "sg:province":"Canterbury",
    "sg:tags":[
        "consultant",
        "medical",
        "beauty"
    ],
    "wof:name":"SlumberDry",
    "wof:placetype":"venue"
},
  "geometry": {"coordinates":[172.59506200000001,-43.505569],"type":"Point"}
}