{
  "type": "Feature",
  "properties": {
    "iso:country":"NZ",
    "sg:address":"41 Merchiston St Andersons Bay ",
    "sg:city":"Dunedin",
    "sg:classifiers":[
        {
            "category":"Travel",
            "subcategory":"Travel Agent",
            "type":"Entertainment"
        }
    ],
    "sg:phone":"+64 3-454 5288",
    "sg:province":"Otago",
    "sg:tags":[
        "tourism",
        "broker"
    ],
    "wof:name":"Ability 2 Travel",
    "wof:placetype":"venue"
},
  "geometry": {"coordinates":[170.533554,-45.896965],"type":"Point"}
}