{
  "type": "Feature",
  "properties": {
    "addr:full":"Hukanui Health Centre 141 Hukanui Rd  Hamilton Waikato",
    "addr:housenumber":"141",
    "addr:street":"Hukanui Rd",
    "iso:country":"NZ",
    "sg:address":"Hukanui Health Centre 141 Hukanui Rd ",
    "sg:city":"Hamilton",
    "sg:classifiers":[
        {
            "category":"Health Services",
            "subcategory":"Clinic",
            "type":"Services"
        }
    ],
    "sg:phone":"+64 7-855 6199",
    "sg:province":"Waikato",
    "sg:tags":[
        "medical",
        "beauty"
    ],
    "wof:name":"Raju Dr Suhana (Sue)",
    "wof:placetype":"venue"
},
  "geometry": {"coordinates":[175.276993,-37.783215],"type":"Point"}
}