{
  "type": "Feature",
  "properties": {
    "iso:country":"NZ",
    "sg:address":"PO Box 11209 ",
    "sg:city":"Ellerslie",
    "sg:classifiers":[
        {
            "category":"Shopping",
            "subcategory":"Pharmacy",
            "type":"Retail Goods"
        }
    ],
    "sg:phone":"+64 508 272 236",
    "sg:province":"Auckland",
    "sg:tags":[
        "products",
        "medical",
        "health",
        "beauty",
        "supply"
    ],
    "wof:name":"Bodyworks Healthcare",
    "wof:placetype":"venue"
},
  "geometry": {"coordinates":[-84.79688299999999,32.634495],"type":"Point"}
}