{
  "type": "Feature",
  "properties": {
    "iso:country":"NZ",
    "sg:address":"Maritime Building Marsden Rd ",
    "sg:city":"Paihia",
    "sg:orig_category":"Shopping: Retail Stores: Books: Libraries",
    "sg:phone":"+64 9-402 7345",
    "sg:province":"Northland",
    "wof:name":"Bay of Islands Visitor Information & Bookings",
    "wof:placetype":"venue"
},
  "geometry": {"coordinates":[174.091064,-35.283699],"type":"Point"}
}