{
  "type": "Feature",
  "properties": {
    "addr:full":"26 Kohinoor Ave Mangere Central  Auckland Auckland",
    "addr:housenumber":"26",
    "addr:street":"Kohinoor Ave",
    "iso:country":"NZ",
    "sg:address":"26 Kohinoor Ave Mangere Central ",
    "sg:city":"Auckland",
    "sg:classifiers":[
        {
            "category":"Professional",
            "subcategory":"Art Services",
            "type":"Services"
        }
    ],
    "sg:phone":"+64 9-275 3325",
    "sg:province":"Auckland",
    "sg:tags":[
        "picture",
        "arts",
        "sport",
        "framing",
        "leisure"
    ],
    "wof:name":"Premier Picture Moulding Co NZ Ltd",
    "wof:placetype":"venue"
},
  "geometry": {"coordinates":[174.788681,-36.977364],"type":"Point"}
}