{
  "type": "Feature",
  "properties": {
    "iso:country":"NZ",
    "sg:address":"81 Alberton Ave Mt Albert ",
    "sg:city":"Auckland",
    "sg:classifiers":[
        {
            "category":"Restaurant",
            "type":"Food & Drink"
        }
    ],
    "sg:phone":"+64 9-815 7136",
    "sg:province":"Auckland",
    "sg:tags":[
        "sea"
    ],
    "wof:name":"Prospect House International",
    "wof:placetype":"venue"
},
  "geometry": {"coordinates":[174.723602,-36.885197],"type":"Point"}
}