{
  "type": "Feature",
  "properties": {
    "addr:full":"101 Cryers Rd East Tamaki  Auckland Auckland",
    "addr:housenumber":"101",
    "addr:street":"Cryers Rd",
    "iso:country":"NZ",
    "sg:address":"101 Cryers Rd East Tamaki ",
    "sg:city":"Auckland",
    "sg:orig_category":"Automotive: Sales And Leasing: Trailers",
    "sg:phone":"+64 9-273 1740",
    "sg:province":"Auckland",
    "wof:name":"Steelbro Trailers",
    "wof:placetype":"venue"
},
  "geometry": {"coordinates":[174.892166,-36.931362],"type":"Point"}
}