{
  "type": "Feature",
  "properties": {
    "addr:full":"BNZ Building Suite 1 Victoria St  Cambridge Waikato",
    "addr:housenumber":"suite 1",
    "addr:street":"Victoria St",
    "iso:country":"NZ",
    "sg:address":"BNZ Building Suite 1 Victoria St ",
    "sg:city":"Cambridge",
    "sg:classifiers":[
        {
            "category":"Banks & Credit Unions",
            "subcategory":"Investment Brokerage",
            "type":"Services"
        }
    ],
    "sg:phone":"+64 7-827 7244",
    "sg:province":"Waikato",
    "sg:tags":[
        "personal",
        "accountant",
        "chartered",
        "-",
        "finance"
    ],
    "sg:website":"http://www.yellowpages.co.nz/pages/220297887/dp47803.html",
    "wof:name":"Beban Associates",
    "wof:placetype":"venue"
},
  "geometry": {"coordinates":[-90.285141,41.302124],"type":"Point"}
}