{
  "type": "Feature",
  "properties": {
    "iso:country":"NZ",
    "sg:address":"Butchers Bridge Rd Waiuku ",
    "sg:city":"Pukekohe",
    "sg:classifiers":[
        {
            "category":"Professional",
            "subcategory":"Art Services",
            "type":"Services"
        }
    ],
    "sg:phone":"+64 9-235 8046",
    "sg:province":"Auckland",
    "sg:tags":[
        "picture",
        "arts",
        "sport",
        "framing",
        "leisure"
    ],
    "wof:name":"Waiuku Picture Framers",
    "wof:placetype":"venue"
},
  "geometry": {"coordinates":[174.712997,-37.259445],"type":"Point"}
}