{
  "type": "Feature",
  "properties": {
    "iso:country":"NZ",
    "sg:address":"4 a Park Ave Miramar ",
    "sg:city":"Wellington",
    "sg:orig_category":"Shopping: Retail Stores: Books: Bookshops",
    "sg:phone":"+64 4-939 1414",
    "sg:province":"Wellington",
    "wof:name":"Miramar Books & Lotto",
    "wof:placetype":"venue"
},
  "geometry": {"coordinates":[174.81665,-41.316162],"type":"Point"}
}