{
  "type": "Feature",
  "properties": {
    "iso:country":"NZ",
    "sg:address":"R D 7 ",
    "sg:city":"Waimate",
    "sg:orig_category":"Farming: Agriculture: Agricultural Contractors",
    "sg:phone":"+64 25344819",
    "wof:name":"Kinsman Contracting Ltd",
    "wof:placetype":"venue"
},
  "geometry": {"coordinates":[171.042496,-44.733086],"type":"Point"}
}