{
  "type": "Feature",
  "properties": {
    "iso:country":"NZ",
    "sg:address":"278 A, Remuera Road - Auckland ",
    "sg:city":"5",
    "sg:classifiers":[
        {
            "category":"Professional",
            "subcategory":"Art Services",
            "type":"Services"
        }
    ],
    "sg:phone":"+64 6495203169",
    "sg:province":"Auckland",
    "sg:tags":[
        "export-import"
    ],
    "wof:name":"Royal Nepalese Honorary Consulate",
    "wof:placetype":"venue"
},
  "geometry": {"coordinates":[174.804947,-36.869678],"type":"Point"}
}