{
  "type": "Feature",
  "properties": {
    "iso:country":"NZ",
    "sg:address":"19 Seddon St ",
    "sg:city":"Waihi",
    "sg:orig_category":"Shopping: Retail Stores: Antiques",
    "sg:phone":"+64 7-863 9282",
    "wof:name":"Pure Nostalgia",
    "wof:placetype":"venue"
},
  "geometry": {"coordinates":[175.842484,-37.390285],"type":"Point"}
}