{
  "type": "Feature",
  "properties": {
    "iso:country":"NZ",
    "sg:address":"91 Kingsley St Sydenham ",
    "sg:city":"Christchurch",
    "sg:classifiers":[
        {
            "category":"Manufacturing",
            "subcategory":"Tools & Machinery",
            "type":"Manufacturing & Wholesale Goods"
        }
    ],
    "sg:phone":"+64 3-366 6387",
    "sg:province":"Canterbury",
    "sg:tags":[
        "equipment",
        "industrial",
        "hydraulic"
    ],
    "wof:name":"Seals & O'Rings",
    "wof:placetype":"venue"
},
  "geometry": {"coordinates":[172.64485168460001,-43.5434951782],"type":"Point"}
}