{
  "type": "Feature",
  "properties": {
    "addr:full":"213 Main Rd Tawa  Wellington Wellington",
    "addr:housenumber":"213",
    "addr:street":"Main Rd",
    "iso:country":"NZ",
    "sg:address":"213 Main Rd Tawa ",
    "sg:city":"Wellington",
    "sg:classifiers":[
        {
            "category":"Manufacturing",
            "subcategory":"Furniture",
            "type":"Manufacturing & Wholesale Goods"
        }
    ],
    "sg:phone":"+64 4-232 9271",
    "sg:province":"Wellington",
    "sg:tags":[
        "furniture/furnishings",
        "home",
        "garden",
        "manufacturer"
    ],
    "wof:name":"Customised Carpentry & Cabinet Making Ltd",
    "wof:placetype":"venue"
},
  "geometry": {"coordinates":[174.82484400000001,-41.168655],"type":"Point"}
}