{
  "type": "Feature",
  "properties": {
    "iso:country":"NZ",
    "sg:address":"20 Morningside Dve Kingsland ",
    "sg:city":"Auckland",
    "sg:classifiers":[
        {
            "category":"Retail",
            "subcategory":"Auto Repair",
            "type":"Services"
        }
    ],
    "sg:phone":"+64 9-849 3737",
    "sg:province":"Auckland",
    "sg:tags":[
        "clutch",
        "brake",
        "servicing",
        "automotive"
    ],
    "wof:name":"Auto Clutch Ltd",
    "wof:placetype":"venue"
},
  "geometry": {"coordinates":[174.74468999999999,-36.870129],"type":"Point"}
}