{
  "type": "Feature",
  "properties": {
    "addr:full":"Westcity Shopping Centre  Auckland Auckland",
    "iso:country":"NZ",
    "sg:address":"Westcity Shopping Centre ",
    "sg:city":"Auckland",
    "sg:orig_category":"Clothing And Fabric: Clothing: Children'S Wear",
    "sg:phone":"+64 9-839 0820",
    "sg:province":"Auckland",
    "wof:name":"Farmers Trading Co Ltd",
    "wof:placetype":"venue"
},
  "geometry": {"coordinates":[174.875122,-36.956177],"type":"Point"}
}