{
  "type": "Feature",
  "properties": {
    "addr:full":"Whatawhata Rd Dinsdale  Hamilton Waikato",
    "addr:street":"Whatawhata Rd",
    "iso:country":"NZ",
    "sg:address":"Whatawhata Rd Dinsdale ",
    "sg:city":"Hamilton",
    "sg:orig_category":"Farming: Farms - General: Poultry",
    "sg:phone":"+64 7-846 2939",
    "sg:province":"Waikato",
    "wof:name":"Dinsdale Poultry",
    "wof:placetype":"venue"
},
  "geometry": {"coordinates":[175.23814400000001,-37.797169],"type":"Point"}
}