{
  "type": "Feature",
  "properties": {
    "iso:country":"NZ",
    "sg:address":"714 Karamu Rd Nth ",
    "sg:city":"Hastings",
    "sg:classifiers":[
        {
            "category":"Building & Trades",
            "subcategory":"Construction",
            "type":"Services"
        }
    ],
    "sg:phone":"+64 6-870 8970",
    "sg:province":"Hawke's Bay",
    "sg:tags":[
        "home",
        "garden",
        "related",
        "plasterer"
    ],
    "wof:name":"Hitex Plaster Hawkes Bay Ltd",
    "wof:placetype":"venue"
},
  "geometry": {"coordinates":[176.87951699999999,-39.669403],"type":"Point"}
}