{
  "type": "Feature",
  "properties": {
    "addr:full":"1527 Drummond-Otautau Rd R D 3  Drummond",
    "addr:housenumber":"1527;3",
    "addr:street":"Drummond-Otautau Rd R D",
    "iso:country":"NZ",
    "sg:address":"1527 Drummond-Otautau Rd R D 3 ",
    "sg:city":"Drummond",
    "sg:orig_category":"Industrial: Engineering: Engineers: Engineers - General",
    "sg:phone":"+64 3-236 2749",
    "wof:name":"Davis Engineering Drummond",
    "wof:placetype":"venue"
},
  "geometry": {"coordinates":[168.14570599999999,-46.144859],"type":"Point"}
}