{
  "type": "Feature",
  "properties": {
    "addr:full":"Eveleyn Couzins Ave Richmond  Christchurch Nelson",
    "addr:street":"Couzins Ave",
    "iso:country":"NZ",
    "sg:address":"Eveleyn Couzins Ave Richmond ",
    "sg:city":"Christchurch",
    "sg:classifiers":[
        {
            "category":"Recreation",
            "type":"Entertainment"
        }
    ],
    "sg:phone":"+64 3-381 2825",
    "sg:province":"Nelson",
    "sg:tags":[
        "sport",
        "leisure"
    ],
    "wof:name":"Richmond Working Mens Pigeon Club",
    "wof:placetype":"venue"
},
  "geometry": {"coordinates":[172.66009500000001,-43.518803],"type":"Point"}
}