{
  "type": "Feature",
  "properties": {
    "addr:full":"85 Port Rd Seaview Lower  Hutt Wellington",
    "addr:housenumber":"85",
    "addr:street":"Port Rd",
    "iso:country":"NZ",
    "sg:address":"85 Port Rd Seaview Lower ",
    "sg:city":"Hutt",
    "sg:orig_category":"Industrial: Services",
    "sg:phone":"+64 4-576 5016",
    "sg:province":"Wellington",
    "sg:website":"http://www.els.co.nz",
    "wof:name":"Environmental Laboratory Services Ltd",
    "wof:placetype":"venue"
},
  "geometry": {"coordinates":[174.89944499999999,-41.245834],"type":"Point"}
}