{
  "type": "Feature",
  "properties": {
    "addr:full":"99 Birch Ave Roundabout  Tauranga Bay of Plenty",
    "addr:housenumber":"99",
    "addr:street":"Birch Ave",
    "iso:country":"NZ",
    "sg:address":"99 Birch Ave Roundabout ",
    "sg:city":"Tauranga",
    "sg:orig_category":"Transport: Boats And Marine: Products: Marine Engines",
    "sg:phone":"+64 800 254 000",
    "sg:province":"Bay of Plenty",
    "sg:website":"http://www.yellowpages.co.nz/for/taurangamotormachining/dp48429.html",
    "wof:name":"Doctor Repower-Tauranga Motor Machining Ltd",
    "wof:placetype":"venue"
},
  "geometry": {"coordinates":[176.14176900000001,-37.699589],"type":"Point"}
}