{
  "type": "Feature",
  "properties": {
    "iso:country":"NZ",
    "sg:address":"Gresson St ",
    "sg:city":"Greymouth",
    "sg:classifiers":[
        {
            "category":"Retail",
            "subcategory":"Auto Repair",
            "type":"Services"
        }
    ],
    "sg:phone":"+64 3-768 5469",
    "sg:province":"West Coast",
    "sg:tags":[
        "automotive",
        "servicing"
    ],
    "wof:name":"Clements Mechanical Ltd",
    "wof:placetype":"venue"
},
  "geometry": {"coordinates":[171.20387299999999,-42.447323],"type":"Point"}
}