{
  "type": "Feature",
  "properties": {
    "addr:full":"215 Gordon Rd Mosgiel  Dunedin Otago",
    "addr:housenumber":"215",
    "addr:street":"Gordon Rd",
    "iso:country":"NZ",
    "sg:address":"215 Gordon Rd Mosgiel ",
    "sg:city":"Dunedin",
    "sg:classifiers":[
        {
            "category":"Sports & Exercise",
            "subcategory":"Sports Center",
            "type":"Entertainment"
        }
    ],
    "sg:phone":"+64 3-489 6008",
    "sg:province":"Otago",
    "sg:tags":[
        "sporting",
        "sports",
        "-",
        "leisure",
        "facility"
    ],
    "wof:name":"Mosgiel Pool",
    "wof:placetype":"venue"
},
  "geometry": {"coordinates":[170.34494000000001,-45.868977],"type":"Point"}
}