{
  "type": "Feature",
  "properties": {
    "addr:full":"405 Remuera Rd Remuera  Auckland Auckland",
    "addr:housenumber":"405",
    "addr:street":"Remuera Rd",
    "iso:country":"NZ",
    "sg:address":"405 Remuera Rd Remuera ",
    "sg:city":"Auckland",
    "sg:classifiers":[
        {
            "category":"Travel",
            "subcategory":"Travel Agent",
            "type":"Entertainment"
        }
    ],
    "sg:phone":"+64 9-520 3176",
    "sg:province":"Auckland",
    "sg:tags":[
        "tourism",
        "broker"
    ],
    "wof:name":"Travel Smart",
    "wof:placetype":"venue"
},
  "geometry": {"coordinates":[174.798935,-36.880943],"type":"Point"}
}