{
  "type": "Feature",
  "properties": {
    "addr:full":"P O Box 60586 Titirangi  Auckland Auckland",
    "addr:housenumber":"box",
    "addr:postcode":"60586",
    "iso:country":"NZ",
    "sg:address":"P O Box 60586 Titirangi ",
    "sg:city":"Auckland",
    "sg:orig_category":"Health And Beauty: Mental: Psychology",
    "sg:phone":"+64 800 225 465",
    "sg:province":"Auckland",
    "sg:website":"http://www.healtheconnections.co.nz",
    "wof:name":"Health E Connections",
    "wof:placetype":"venue"
},
  "geometry": {"coordinates":[174.66279599999999,-36.926861],"type":"Point"}
}