{
  "type": "Feature",
  "properties": {
    "iso:country":"NZ",
    "sg:address":"Cambridge Rd ",
    "sg:city":"Hamilton",
    "sg:classifiers":[
        {
            "category":"Sports & Exercise",
            "subcategory":"Tennis Court",
            "type":"Entertainment"
        }
    ],
    "sg:phone":"+64 7-856 9372",
    "sg:province":"Waikato",
    "sg:tags":[
        "hobby",
        "leisure"
    ],
    "wof:name":"Roberton Pharmacy Ltd",
    "wof:placetype":"venue"
},
  "geometry": {"coordinates":[175.30941799999999,-37.797588],"type":"Point"}
}