{
  "type": "Feature",
  "properties": {
    "addr:full":"8-10 Gordon St  Dannevirke",
    "addr:housenumber":"8-10",
    "addr:street":"Gordon St",
    "iso:country":"NZ",
    "sg:address":"8-10 Gordon St ",
    "sg:city":"Dannevirke",
    "sg:classifiers":[
        {
            "category":"Utilities",
            "subcategory":"Cable",
            "type":"Services"
        }
    ],
    "sg:phone":"+64 6-374 8039",
    "sg:tags":[
        "electricity",
        "energy",
        "industrial",
        "utilities",
        "supply"
    ],
    "wof:name":"Scanpower",
    "wof:placetype":"venue"
},
  "geometry": {"coordinates":[-98.60567500000001,41.329346],"type":"Point"}
}