{
  "type": "Feature",
  "properties": {
    "addr:full":"149 Hurndal St  Maungaturoto",
    "addr:housenumber":"149",
    "addr:street":"Hurndal St",
    "iso:country":"NZ",
    "sg:address":"149 Hurndal St ",
    "sg:city":"Maungaturoto",
    "sg:classifiers":[
        {
            "category":"Home & Garden",
            "subcategory":"Building Materials",
            "type":"Retail Goods"
        }
    ],
    "sg:phone":"+64 9-431 8185",
    "sg:tags":[
        "electrician",
        "related"
    ],
    "wof:name":"Craig Garnett Electrical",
    "wof:placetype":"venue"
},
  "geometry": {"coordinates":[174.358597,-36.109028],"type":"Point"}
}