{
  "type": "Feature",
  "properties": {
    "addr:full":"518 Sloane St Te  Awamutu Waikato",
    "addr:housenumber":"518",
    "addr:street":"Sloane St",
    "iso:country":"NZ",
    "sg:address":"518 Sloane St Te ",
    "sg:city":"Awamutu",
    "sg:orig_category":"Shopping: Sports Retailers: Cycles",
    "sg:phone":"+64 7-871 4816",
    "sg:province":"Waikato",
    "wof:name":"Te Awamutu Cycles & Mowers",
    "wof:placetype":"venue"
},
  "geometry": {"coordinates":[175.324387,-38.014763],"type":"Point"}
}