{
  "type": "Feature",
  "properties": {
    "iso:country":"NZ",
    "sg:address":"240 Forbury Rd Saint Clair ",
    "sg:city":"Dunedin",
    "sg:classifiers":[
        {
            "category":"Personal",
            "subcategory":"Tanning Parlor",
            "type":"Services"
        }
    ],
    "sg:phone":"+64 3-455 7882",
    "sg:province":"Otago",
    "sg:tags":[
        "sun",
        "health",
        "beauty"
    ],
    "wof:name":"Zaibatsu Hair Art",
    "wof:placetype":"venue"
},
  "geometry": {"coordinates":[170.490036,-45.911179],"type":"Point"}
}