{
  "type": "Feature",
  "properties": {
    "addr:full":"19 B Roxburgh Cre Palmerston  Palmerston North Manawatu-Wanganui",
    "addr:housenumber":"19 b",
    "addr:street":"Cre",
    "iso:country":"NZ",
    "sg:address":"19 B Roxburgh Cre Palmerston ",
    "sg:city":"Palmerston North",
    "sg:orig_category":"Industrial: Services: Specialist Services: Electroplating/Polishing",
    "sg:phone":"+64 6-357 9668",
    "sg:province":"Manawatu-Wanganui",
    "wof:name":"Plating Developments",
    "wof:placetype":"venue"
},
  "geometry": {"coordinates":[175.64404300000001,-40.359612],"type":"Point"}
}