{
  "type": "Feature",
  "properties": {
    "iso:country":"NZ",
    "sg:address":"50 Waitapu Rd ",
    "sg:city":"Takaka",
    "sg:classifiers":[
        {
            "category":"Home & Garden",
            "subcategory":"Building Materials",
            "type":"Retail Goods"
        }
    ],
    "sg:phone":"+64 3-525 7114",
    "sg:tags":[
        "builder",
        "related"
    ],
    "sg:website":"http://www.thehousecompanynz.com",
    "wof:name":"The House Company (Tasman Bays) Ltd",
    "wof:placetype":"venue"
},
  "geometry": {"coordinates":[172.805374,-40.846447],"type":"Point"}
}