{
  "type": "Feature",
  "properties": {
    "iso:country":"NZ",
    "sg:address":"509 New Brighton Rd North New Brighton ",
    "sg:city":"Christchurch",
    "sg:classifiers":[
        {
            "category":"Food Court",
            "type":"Food & Drink"
        }
    ],
    "sg:phone":"+64 3-388 3843",
    "sg:province":"Canterbury",
    "sg:tags":[
        "packer",
        "processing",
        "processor"
    ],
    "wof:name":"Competitive Packers 1995 Ltd",
    "wof:placetype":"venue"
},
  "geometry": {"coordinates":[172.711105,-43.50428],"type":"Point"}
}