{
  "type": "Feature",
  "properties": {
    "addr:full":"134 A Colombo St Sydenham  Christchurch Canterbury",
    "addr:housenumber":"134 a",
    "addr:street":"Colombo St",
    "iso:country":"NZ",
    "sg:address":"134 A Colombo St Sydenham ",
    "sg:city":"Christchurch",
    "sg:classifiers":[
        {
            "category":"Food & Beverages",
            "subcategory":"Meat & Fish",
            "type":"Retail Goods"
        }
    ],
    "sg:phone":"+64 3-332 6148",
    "sg:province":"Canterbury",
    "sg:tags":[
        "drink"
    ],
    "wof:name":"Banfields of Beckenham",
    "wof:placetype":"venue"
},
  "geometry": {"coordinates":[172.63685599999999,-43.557159],"type":"Point"}
}