{
  "type": "Feature",
  "properties": {
    "addr:full":"Shop 5 24 Onetangi Rd Onetangi  Auckland Auckland",
    "addr:housenumber":"shop 5 24",
    "addr:street":"Onetangi Rd",
    "iso:country":"NZ",
    "sg:address":"Shop 5 24 Onetangi Rd Onetangi ",
    "sg:city":"Auckland",
    "sg:classifiers":[
        {
            "category":"Communications",
            "subcategory":"Film & Video Production",
            "type":"Services"
        }
    ],
    "sg:phone":"+64 9-372 9148",
    "sg:province":"Auckland",
    "sg:tags":[
        "sport",
        "leisure",
        "library",
        "entertainment"
    ],
    "wof:name":"Onetangi Videos",
    "wof:placetype":"venue"
},
  "geometry": {"coordinates":[174.64369199999999,-36.869297],"type":"Point"}
}