{
  "type": "Feature",
  "properties": {
    "iso:country":"NZ",
    "sg:address":"170 Richmond Rd Grey Lynn ",
    "sg:city":"Auckland",
    "sg:classifiers":[
        {
            "category":"Bars & Pubs",
            "subcategory":"Lounge",
            "type":"Food & Drink"
        }
    ],
    "sg:phone":"+64 9-378 0606",
    "sg:province":"Nelson",
    "sg:tags":[
        "baker",
        "-"
    ],
    "wof:name":"Busy Oven Bakery",
    "wof:placetype":"venue"
},
  "geometry": {"coordinates":[174.73994400000001,-36.856621],"type":"Point"}
}