{
  "type": "Feature",
  "properties": {
    "addr:full":"8/243 Salisbury  St",
    "addr:housenumber":"8 / 243",
    "addr:street":"Salisbury St",
    "iso:country":"NZ",
    "sg:address":"8/243 Salisbury ",
    "sg:city":"St",
    "sg:orig_category":"Health And Beauty: Specialists: Podiatrists",
    "sg:phone":"+64 252884352",
    "wof:name":"Linda Price",
    "wof:placetype":"venue"
},
  "geometry": {"coordinates":[-73.15593699999999,43.921032],"type":"Point"}
}