{
  "type": "Feature",
  "properties": {
    "addr:full":"1 Glen Mall Shopg Cen Glen Eden  Auckland Auckland",
    "addr:housenumber":"1",
    "addr:street":"Glen Mall;Cen",
    "iso:country":"NZ",
    "sg:address":"1 Glen Mall Shopg Cen Glen Eden ",
    "sg:city":"Auckland",
    "sg:classifiers":[
        {
            "category":"Bars & Pubs",
            "subcategory":"Lounge",
            "type":"Food & Drink"
        }
    ],
    "sg:phone":"+64 9-818 5037",
    "sg:province":"Auckland",
    "sg:tags":[
        "-"
    ],
    "wof:name":"Cottage Bakeries",
    "wof:placetype":"venue"
},
  "geometry": {"coordinates":[174.63601700000001,-36.909389],"type":"Point"}
}