{
  "type": "Feature",
  "properties": {
    "iso:country":"NZ",
    "sg:address":"PO Box 10182 Bayfair Mt ",
    "sg:city":"Maunganui",
    "sg:orig_category":"Home And Garden: Gardening: Services: Landscaping",
    "sg:phone":"+64 21 462 605",
    "sg:province":"Bay of Plenty",
    "wof:name":"Outdoor Impressions Landscaping Ltd",
    "wof:placetype":"venue"
},
  "geometry": {"coordinates":[176.186279,-37.641048],"type":"Point"}
}