{
  "type": "Feature",
  "properties": {
    "addr:full":"PO Box 10182 Bayfair Mt  Maunganui Bay of Plenty",
    "addr:housenumber":"po box",
    "addr:postcode":"10182",
    "addr:street":"Maunganui Bay",
    "iso:country":"NZ",
    "sg:address":"PO Box 10182 Bayfair Mt ",
    "sg:city":"Maunganui",
    "sg:orig_category":"Home And Garden: Gardening: Services: Landscaping",
    "sg:phone":"+64 21 462 605",
    "sg:province":"Bay of Plenty",
    "wof:name":"Outdoor Impressions Landscaping Ltd",
    "wof:placetype":"venue"
},
  "geometry": {"coordinates":[176.18627900000001,-37.641048],"type":"Point"}
}