{
  "type": "Feature",
  "properties": {
    "addr:full":"36 Hammond St  Bulls",
    "addr:housenumber":"36",
    "addr:street":"Hammond St",
    "iso:country":"NZ",
    "sg:address":"36 Hammond St ",
    "sg:city":"Bulls",
    "sg:classifiers":[
        {
            "category":"Shopping",
            "subcategory":"Crafts & Fabrics",
            "type":"Retail Goods"
        }
    ],
    "sg:phone":"+64 6-322 0840",
    "sg:tags":[
        "pottery",
        "home",
        "accessories",
        "garden",
        "supply"
    ],
    "wof:name":"Chrisso Pottery",
    "wof:placetype":"venue"
},
  "geometry": {"coordinates":[175.38324,-40.17292],"type":"Point"}
}