{
  "type": "Feature",
  "properties": {
    "addr:full":"2 Killarney St Takapuna  Auckland Auckland",
    "addr:housenumber":"2",
    "addr:street":"Killarney St",
    "iso:country":"NZ",
    "sg:address":"2 Killarney St Takapuna ",
    "sg:city":"Auckland",
    "sg:orig_category":"Non-Classified Establishments",
    "sg:phone":"+64 9-489 9409",
    "sg:province":"Auckland",
    "sg:website":"http://www.yellowpages.co.nz/for/killarney/dp57023.html",
    "wof:name":"Killarney St Catering",
    "wof:placetype":"venue"
},
  "geometry": {"coordinates":[174.77330000000001,-36.783138],"type":"Point"}
}