{
  "type": "Feature",
  "properties": {
    "addr:full":"PO Box 2077 Raumati South  Paraparaumu Wellington",
    "addr:housenumber":"po",
    "addr:street":"Box 2077 Raumati South",
    "iso:country":"NZ",
    "sg:address":"PO Box 2077 Raumati South ",
    "sg:city":"Paraparaumu",
    "sg:classifiers":[
        {
            "category":"Shopping",
            "subcategory":"Pharmacy",
            "type":"Retail Goods"
        }
    ],
    "sg:phone":"+64 4-299 9363",
    "sg:province":"Wellington",
    "sg:tags":[
        "products",
        "medical",
        "health",
        "beauty",
        "supply"
    ],
    "wof:name":"Juven8",
    "wof:placetype":"venue"
},
  "geometry": {"coordinates":[174.980042,-40.930641],"type":"Point"}
}