{
  "type": "Feature",
  "properties": {
    "addr:full":"Mould St  Waitara",
    "addr:street":"Mould St",
    "iso:country":"NZ",
    "sg:address":"Mould St ",
    "sg:city":"Waitara",
    "sg:orig_category":"Automotive: General Services: Rental Vehicles",
    "sg:phone":"+64 6-754 4425",
    "wof:name":"24 hour Hire Ltd",
    "wof:placetype":"venue"
},
  "geometry": {"coordinates":[174.22395299999999,-38.998825],"type":"Point"}
}