{
  "type": "Feature",
  "properties": {
    "addr:full":"PO Box 25653 St Heliers  Auckland Auckland",
    "addr:housenumber":"po box 25653",
    "iso:country":"NZ",
    "sg:address":"PO Box 25653 St Heliers ",
    "sg:city":"Auckland",
    "sg:classifiers":[
        {
            "category":"Food & Beverages",
            "subcategory":"Groceries & Convenience Stores",
            "type":"Retail Goods"
        }
    ],
    "sg:phone":"+64 9-575 7569",
    "sg:province":"Auckland",
    "sg:tags":[
        "foodstuff",
        "drink",
        "-"
    ],
    "wof:name":"Peerless Edible Oils",
    "wof:placetype":"venue"
},
  "geometry": {"coordinates":[174.862976,-36.856163],"type":"Point"}
}