{
  "type": "Feature",
  "properties": {
    "iso:country":"NZ",
    "sg:address":"90 Devonport Rd ",
    "sg:city":"Tauranga",
    "sg:orig_category":"Shopping: Sports Retailers: Sports Goods: Sportswear",
    "sg:phone":"+64 7-578 2288",
    "sg:province":"Auckland",
    "wof:name":"Wright Sports Ltd",
    "wof:placetype":"venue"
},
  "geometry": {"coordinates":[176.169556,-37.686199],"type":"Point"}
}