{
  "type": "Feature",
  "properties": {
    "addr:full":"St Georges Medical Centre 249 Papanui Rd  Christchurch Canterbury",
    "addr:housenumber":"249",
    "addr:street":"Papanui Rd",
    "iso:country":"NZ",
    "sg:address":"St Georges Medical Centre 249 Papanui Rd ",
    "sg:city":"Christchurch",
    "sg:classifiers":[
        {
            "category":"Health Services",
            "subcategory":"Health Practitioner",
            "type":"Services"
        }
    ],
    "sg:phone":"+64 3-375 4060",
    "sg:province":"Canterbury",
    "sg:tags":[
        "specialist",
        "medical",
        "beauty",
        "specialists"
    ],
    "wof:name":"Conaghan Mr C J",
    "wof:placetype":"venue"
},
  "geometry": {"coordinates":[172.637314,-43.531315],"type":"Point"}
}