{
  "type": "Feature",
  "properties": {
    "addr:full":"10 Babich Rd Henderson  Auckland Auckland",
    "addr:housenumber":"10",
    "addr:street":"Babich Rd",
    "iso:country":"NZ",
    "sg:address":"10 Babich Rd Henderson ",
    "sg:city":"Auckland",
    "sg:classifiers":[
        {
            "category":"Food & Beverages",
            "subcategory":"Liquor & Beverages",
            "type":"Retail Goods"
        }
    ],
    "sg:phone":"+64 9-833 7859",
    "sg:province":"Auckland",
    "sg:tags":[
        "drink",
        "maker",
        "wine"
    ],
    "sg:website":"http://www.babich.co.nz",
    "wof:name":"Babich Wines Ltd",
    "wof:placetype":"venue"
},
  "geometry": {"coordinates":[174.59965500000001,-36.879326],"type":"Point"}
}