{
  "type": "Feature",
  "properties": {
    "addr:full":"59 Hassall St  Timaru Canterbury",
    "addr:housenumber":"59",
    "addr:street":"Hassall St",
    "iso:country":"NZ",
    "sg:address":"59 Hassall St ",
    "sg:city":"Timaru",
    "sg:classifiers":[
        {
            "category":"Personal",
            "subcategory":"Beauty Salon",
            "type":"Services"
        }
    ],
    "sg:phone":"+64 3-688 1810",
    "sg:province":"Canterbury",
    "sg:tags":[
        "therapy",
        "health"
    ],
    "wof:name":"Anna Frances Aesthetics",
    "wof:placetype":"venue"
},
  "geometry": {"coordinates":[171.23867799999999,-44.404388],"type":"Point"}
}