{
  "type": "Feature",
  "properties": {
    "addr:full":"PO Box 31482 Lower Hutt  Wellington Wellington",
    "addr:housenumber":"po box",
    "addr:postcode":"31482",
    "iso:country":"NZ",
    "sg:address":"PO Box 31482 Lower Hutt ",
    "sg:city":"Wellington",
    "sg:classifiers":[
        {
            "category":"Food & Beverages",
            "subcategory":"Groceries & Convenience Stores",
            "type":"Retail Goods"
        }
    ],
    "sg:phone":"+64 4-939 7783",
    "sg:province":"Wellington",
    "sg:tags":[
        "foodstuff",
        "drink",
        "-"
    ],
    "wof:name":"Spudnik Distributors",
    "wof:placetype":"venue"
},
  "geometry": {"coordinates":[174.90838600000001,-41.206631],"type":"Point"}
}