{
  "type": "Feature",
  "properties": {
    "iso:country":"NZ",
    "sg:address":"Quarry Hills R D 1 ",
    "sg:city":"Tokanui",
    "sg:orig_category":"Transport: Transportation: Transport Operators",
    "sg:phone":"+64 3-246 8494",
    "wof:name":"Callahan Transport",
    "wof:placetype":"venue"
},
  "geometry": {"coordinates":[168.943924,-46.565258],"type":"Point"}
}