{
  "type": "Feature",
  "properties": {
    "addr:full":"Pearn Cre Northcote  Auckland Auckland",
    "iso:country":"NZ",
    "sg:address":"Pearn Cre Northcote ",
    "sg:city":"Auckland",
    "sg:orig_category":"Home And Garden: Children",
    "sg:phone":"+64 9-419 8226",
    "sg:province":"Auckland",
    "wof:name":"Onepoto Awhina Educare Northcote Community House",
    "wof:placetype":"venue"
},
  "geometry": {"coordinates":[174.747849,-36.801125],"type":"Point"}
}