{
  "type": "Feature",
  "properties": {
    "iso:country":"NZ",
    "sg:address":"29 Dawsons Rd R D 1 Upper Moutere ",
    "sg:city":"Nelson",
    "sg:classifiers":[
        {
            "category":"Building & Trades",
            "subcategory":"Plumbing",
            "type":"Services"
        }
    ],
    "sg:phone":"+64 3-540 3455",
    "sg:province":"Nelson",
    "sg:tags":[
        "home",
        "plumber",
        "garden",
        "related"
    ],
    "wof:name":"McDowell Plumbing",
    "wof:placetype":"venue"
},
  "geometry": {"coordinates":[173.006546,-41.272099],"type":"Point"}
}