{
  "type": "Feature",
  "properties": {
    "addr:full":"15 Eric Paton Way Panmure  Auckland Auckland",
    "addr:housenumber":"15",
    "addr:street":"Eric Paton Way",
    "iso:country":"NZ",
    "sg:address":"15 Eric Paton Way Panmure ",
    "sg:city":"Auckland",
    "sg:classifiers":[
        {
            "category":"Retail",
            "subcategory":"Auto Repair",
            "type":"Services"
        }
    ],
    "sg:phone":"+64 9-527 3932",
    "sg:province":"Auckland",
    "sg:tags":[
        "transmission",
        "automotive",
        "servicing"
    ],
    "wof:name":"C & D Automatics Ltd",
    "wof:placetype":"venue"
},
  "geometry": {"coordinates":[174.85749799999999,-36.90181],"type":"Point"}
}