{
  "type": "Feature",
  "properties": {
    "iso:country":"NZ",
    "sg:address":"Rotowaro Rd ",
    "sg:city":"Huntly",
    "sg:classifiers":[
        {
            "category":"Utilities",
            "subcategory":"Fuel Oil & Lpg",
            "type":"Services"
        }
    ],
    "sg:phone":"+64 7-828 9772",
    "sg:tags":[
        "coal",
        "energy",
        "industrial",
        "mine",
        "utilities"
    ],
    "wof:name":"Mines Rescue Station Huntly",
    "wof:placetype":"venue"
},
  "geometry": {"coordinates":[175.022705,-37.628353],"type":"Point"}
}