{
  "type": "Feature",
  "properties": {
    "iso:country":"NZ",
    "sg:address":"702 Port Rd ",
    "sg:city":"Whangamata",
    "sg:orig_category":"Farming: Services: Veterinarians",
    "sg:phone":"+64 7-865 8109",
    "wof:name":"Whangamata Veterinary Hospital",
    "wof:placetype":"venue"
},
  "geometry": {"coordinates":[175.877808,-37.200172],"type":"Point"}
}