{
  "type": "Feature",
  "properties": {
    "addr:full":"4 Cherrywood Dve Otumoetai  Tauranga Bay of Plenty",
    "addr:housenumber":"4",
    "addr:street":"Cherrywood Dve Otumoetai",
    "iso:country":"NZ",
    "sg:address":"4 Cherrywood Dve Otumoetai ",
    "sg:city":"Tauranga",
    "sg:orig_category":"Shopping: Retail Stores: Florists",
    "sg:phone":"+64 7-576 5004",
    "sg:province":"Bay of Plenty",
    "sg:website":"http://www.yellowpages.co.nz/for/cherrywoodflorist/dp48223.html",
    "wof:name":"Cherrywood Florist",
    "wof:placetype":"venue"
},
  "geometry": {"coordinates":[176.14269999999999,-37.667744],"type":"Point"}
}