{
  "type": "Feature",
  "properties": {
    "addr:full":"159 A Onehunga Mall Onehunga  Auckland Auckland",
    "addr:housenumber":"159 a",
    "addr:street":"Mall",
    "iso:country":"NZ",
    "sg:address":"159 A Onehunga Mall Onehunga ",
    "sg:city":"Auckland",
    "sg:orig_category":"Shopping: Retail Stores: Lotto Outlets",
    "sg:phone":"+64 9-634 2202",
    "sg:province":"Auckland",
    "wof:name":"LuckyLand Lotto",
    "wof:placetype":"venue"
},
  "geometry": {"coordinates":[174.78564499999999,-36.923729],"type":"Point"}
}