{
  "type": "Feature",
  "properties": {
    "iso:country":"NZ",
    "sg:address":"22 Edward St ",
    "sg:city":"Wakefield",
    "sg:orig_category":"Shopping: Retail Stores: Supermarkets",
    "sg:phone":"+64 3-541 8470",
    "wof:name":"Wakefield Supermarket",
    "wof:placetype":"venue"
},
  "geometry": {"coordinates":[-71.08847,42.50938],"type":"Point"}
}