{
  "type": "Feature",
  "properties": {
    "iso:country":"NZ",
    "sg:address":"524 A Wairakei Rd Burnside ",
    "sg:city":"Christchurch",
    "sg:classifiers":[
        {
            "category":"Shopping",
            "subcategory":"Beauty & Cosmetics",
            "type":"Retail Goods"
        }
    ],
    "sg:phone":"+64 3-359 7297",
    "sg:province":"Canterbury",
    "sg:tags":[
        "health",
        "perfumery"
    ],
    "wof:name":"Peerage Products 2000 Ltd",
    "wof:placetype":"venue"
},
  "geometry": {"coordinates":[172.566925,-43.488934],"type":"Point"}
}