{
  "type": "Feature",
  "properties": {
    "iso:country":"NZ",
    "sg:address":"164 Mill Rd Manurewa R D ",
    "sg:city":"Auckland",
    "sg:classifiers":[
        {
            "category":"Shopping",
            "subcategory":"Pets & Pet Supplies",
            "type":"Retail Goods"
        }
    ],
    "sg:phone":"+64 9-266 6512",
    "sg:province":"Auckland",
    "sg:tags":[
        "boarding",
        "garden",
        "pets",
        "catteries",
        "home",
        "kennel"
    ],
    "wof:name":"Alfriston Hts Boarding Cattery",
    "wof:placetype":"venue"
},
  "geometry": {"coordinates":[174.916962,-37.021488],"type":"Point"}
}