{
  "type": "Feature",
  "properties": {
    "addr:full":"43 Seaview Rd Seaview Lower  Hutt Wellington",
    "addr:housenumber":"43",
    "addr:street":"Seaview Rd",
    "iso:country":"NZ",
    "sg:address":"43 Seaview Rd Seaview Lower ",
    "sg:city":"Hutt",
    "sg:classifiers":[
        {
            "category":"Home & Garden",
            "subcategory":"Building Materials",
            "type":"Retail Goods"
        }
    ],
    "sg:phone":"+64 4-568 5042",
    "sg:province":"Wellington",
    "sg:tags":[
        "door",
        "fitting",
        "fittings"
    ],
    "wof:name":"PlaceMakers",
    "wof:placetype":"venue"
},
  "geometry": {"coordinates":[174.89956699999999,-41.246059],"type":"Point"}
}