{
  "type": "Feature",
  "properties": {
    "addr:full":"926 State Highway 17 Dairy Flat R D 2 Albany  Auckland Auckland",
    "addr:housenumber":"926;2",
    "addr:street":"State Highway 17 Dairy Flat R D",
    "iso:country":"NZ",
    "sg:address":"926 State Highway 17 Dairy Flat R D 2 Albany ",
    "sg:city":"Auckland",
    "sg:classifiers":[
        {
            "category":"Shopping",
            "subcategory":"Pets & Pet Supplies",
            "type":"Retail Goods"
        }
    ],
    "sg:phone":"+64 9-415 9232",
    "sg:province":"Auckland",
    "sg:tags":[
        "boarding",
        "garden",
        "pets",
        "catteries",
        "home",
        "kennel"
    ],
    "wof:name":"Purrs and Paws Boarding Cattery",
    "wof:placetype":"venue"
},
  "geometry": {"coordinates":[174.709686,-36.720142],"type":"Point"}
}