{
  "type": "Feature",
  "properties": {
    "addr:full":"146 Marua Rd Ellerslie  Auckland Auckland",
    "addr:housenumber":"146",
    "addr:street":"Marua Rd",
    "iso:country":"NZ",
    "sg:address":"146 Marua Rd Ellerslie ",
    "sg:city":"Auckland",
    "sg:classifiers":[
        {
            "category":"Education",
            "subcategory":"University",
            "type":"Public Place"
        }
    ],
    "sg:phone":"+64 9-525 3596",
    "sg:province":"Auckland",
    "sg:tags":[
        "training",
        "adult"
    ],
    "wof:name":"Auckland Academy East",
    "wof:placetype":"venue"
},
  "geometry": {"coordinates":[174.825424,-36.892048],"type":"Point"}
}