{
  "type": "Feature",
  "properties": {
    "iso:country":"NZ",
    "sg:address":"36-40 Atkinson Ave Otahuhu ",
    "sg:city":"Auckland",
    "sg:classifiers":[
        {
            "category":"Shopping",
            "subcategory":"Stationery & Office Supplies",
            "type":"Retail Goods"
        }
    ],
    "sg:phone":"+64 9-276 2003",
    "sg:province":"Auckland",
    "sg:tags":[
        "supplies",
        "educational",
        "material",
        "education",
        "training"
    ],
    "wof:name":"PIERC Education",
    "wof:placetype":"venue"
},
  "geometry": {"coordinates":[174.844177,-36.941734],"type":"Point"}
}