{
  "type": "Feature",
  "properties": {
    "iso:country":"NZ",
    "sg:address":"160 Kelvin Grove Rd Palmerston ",
    "sg:city":"Palmerston North",
    "sg:classifiers":[
        {
            "category":"Personal",
            "subcategory":"Beauty Salon",
            "type":"Services"
        }
    ],
    "sg:phone":"+64 6-353 0463",
    "sg:province":"Wellington",
    "sg:tags":[
        "therapy",
        "health"
    ],
    "wof:name":"Creative Beauty Therapy",
    "wof:placetype":"venue"
},
  "geometry": {"coordinates":[175.65271,-40.320553],"type":"Point"}
}