{
  "type": "Feature",
  "properties": {
    "addr:full":"84 Chapel St  Masterton Wellington",
    "addr:housenumber":"84",
    "addr:street":"Chapel St",
    "iso:country":"NZ",
    "sg:address":"84 Chapel St ",
    "sg:city":"Masterton",
    "sg:classifiers":[
        {
            "category":"Retail",
            "subcategory":"Auto Repair",
            "type":"Services"
        }
    ],
    "sg:phone":"+64 6-377 4899",
    "sg:province":"Wellington",
    "sg:tags":[
        "automotive",
        "servicing"
    ],
    "wof:name":"Paul Croft Automotive",
    "wof:placetype":"venue"
},
  "geometry": {"coordinates":[175.65010100000001,-40.95562],"type":"Point"}
}