{
  "type": "Feature",
  "properties": {
    "iso:country":"NZ",
    "sg:address":"26 Durham St ",
    "sg:city":"Picton",
    "sg:classifiers":[
        {
            "category":"Building & Trades",
            "subcategory":"Plumbing",
            "type":"Services"
        }
    ],
    "sg:phone":"+64 25332040",
    "sg:province":"Marlborough",
    "sg:tags":[
        "home",
        "plumber",
        "garden",
        "related"
    ],
    "wof:name":"Bowers Plumbing & Gasfitting",
    "wof:placetype":"venue"
},
  "geometry": {"coordinates":[-2.846859,53.236282],"type":"Point"}
}