{
  "type": "Feature",
  "properties": {
    "addr:full":"Trentham  Wellington Wellington",
    "iso:country":"NZ",
    "sg:address":"Trentham ",
    "sg:city":"Wellington",
    "sg:classifiers":[
        {
            "category":"Retail",
            "subcategory":"Funeral Services",
            "type":"Services"
        }
    ],
    "sg:phone":"+64 4-939 0545",
    "sg:province":"Wellington",
    "sg:tags":[
        "arrangements",
        "arrangement"
    ],
    "wof:name":"Twilight Express",
    "wof:placetype":"venue"
},
  "geometry": {"coordinates":[175.03883400000001,-41.13356],"type":"Point"}
}