{
  "type": "Feature",
  "properties": {
    "iso:country":"NZ",
    "sg:address":"Martin Pl Havelock North ",
    "sg:city":"Hastings",
    "sg:orig_category":"Transport: Transportation: Refrigerated Transport",
    "sg:phone":"+64 6-877 7152",
    "sg:province":"Hawke's Bay",
    "wof:name":"Trans Otway Ltd",
    "wof:placetype":"venue"
},
  "geometry": {"coordinates":[176.87867700000001,-39.665905],"type":"Point"}
}