{
  "type": "Feature",
  "properties": {
    "iso:country":"NZ",
    "sg:address":"201 State Highway 2 ",
    "sg:city":"Carterton",
    "sg:classifiers":[
        {
            "category":"Shopping",
            "subcategory":"Pets & Pet Supplies",
            "type":"Retail Goods"
        }
    ],
    "sg:phone":"+64 6-379 6909",
    "sg:tags":[
        "boarding",
        "garden",
        "pets",
        "catteries",
        "home",
        "kennel"
    ],
    "wof:name":"The Flower Barn Boarding Cattery",
    "wof:placetype":"venue"
},
  "geometry": {"coordinates":[175.53002900000001,-41.022228],"type":"Point"}
}