{
  "type": "Feature",
  "properties": {
    "iso:country":"NZ",
    "sg:address":"220 Main Hwy ",
    "sg:city":"Otaki",
    "sg:orig_category":"Shopping: Accessories: Bags - Fashion",
    "sg:phone":"+64 6-364 7680",
    "wof:name":"Bags 4 Less",
    "wof:placetype":"venue"
},
  "geometry": {"coordinates":[175.148788,-40.759144],"type":"Point"}
}