{
  "type": "Feature",
  "properties": {
    "addr:full":"York St  Russell",
    "addr:street":"York St",
    "iso:country":"NZ",
    "sg:address":"York St ",
    "sg:city":"Russell",
    "sg:orig_category":"Shopping: Retail Stores: Supermarkets",
    "sg:phone":"+64 9-403 7602",
    "wof:name":"Bay 4 Square Discount",
    "wof:placetype":"venue"
},
  "geometry": {"coordinates":[-82.726128,38.538174],"type":"Point"}
}