{
  "type": "Feature",
  "properties": {
    "addr:full":"353 Great South Rd Otahuhu  Auckland Auckland",
    "addr:housenumber":"353",
    "addr:street":"Great South Rd",
    "iso:country":"NZ",
    "sg:address":"353 Great South Rd Otahuhu ",
    "sg:city":"Auckland",
    "sg:orig_category":"Shopping: Gifts: China And Glassware",
    "sg:phone":"+64 9-276 2230",
    "sg:province":"Auckland",
    "wof:name":"Big Bear (NZ) Ltd",
    "wof:placetype":"venue"
},
  "geometry": {"coordinates":[174.84281899999999,-36.94352],"type":"Point"}
}