{
  "type": "Feature",
  "properties": {
    "addr:full":"193 College St Palmerston  Palmerston North Manawatu-Wanganui",
    "addr:housenumber":"193",
    "addr:street":"College St Palmerston",
    "iso:country":"NZ",
    "sg:address":"193 College St Palmerston ",
    "sg:city":"Palmerston North",
    "sg:classifiers":[
        {
            "category":"Bars & Pubs",
            "subcategory":"Lounge",
            "type":"Food & Drink"
        }
    ],
    "sg:phone":"+64 6-357 3405",
    "sg:province":"Manawatu-Wanganui",
    "sg:tags":[
        "-"
    ],
    "wof:name":"Winter Family Bakery",
    "wof:placetype":"venue"
},
  "geometry": {"coordinates":[175.59953300000001,-40.36935],"type":"Point"}
}