{
  "type": "Feature",
  "properties": {
    "addr:full":"11-21 Hutt Rd Petone Lower  Hutt Wellington",
    "addr:housenumber":"11-21",
    "addr:street":"Hutt Rd",
    "iso:country":"NZ",
    "sg:address":"11-21 Hutt Rd Petone Lower ",
    "sg:city":"Hutt",
    "sg:orig_category":"Industrial: Engineering: Engineers - Mechanical",
    "sg:phone":"+64 4-568 6007",
    "sg:province":"Wellington",
    "sg:website":"http://www.acme-eng.co.nz",
    "wof:name":"Acme Engineering Ltd",
    "wof:placetype":"venue"
},
  "geometry": {"coordinates":[174.87283300000001,-41.221539],"type":"Point"}
}