{
  "type": "Feature",
  "properties": {
    "addr:full":"17 Glasgow St  Tauranga Bay of Plenty",
    "addr:housenumber":"17",
    "addr:street":"Glasgow St",
    "iso:country":"NZ",
    "sg:address":"17 Glasgow St ",
    "sg:city":"Tauranga",
    "sg:classifiers":[
        {
            "category":"Retail",
            "subcategory":"Auto Repair",
            "type":"Services"
        }
    ],
    "sg:phone":"+64 7-578 7337",
    "sg:province":"Bay of Plenty",
    "sg:tags":[
        "automotive",
        "electric",
        "servicing"
    ],
    "wof:name":"In City Auto Electrical",
    "wof:placetype":"venue"
},
  "geometry": {"coordinates":[176.162567,-37.687637],"type":"Point"}
}