{
  "type": "Feature",
  "properties": {
    "iso:country":"NZ",
    "sg:address":"4/312 Blockhouse Bay Rd Avondale ",
    "sg:city":"Auckland",
    "sg:orig_category":"Transport: Transportation: Refrigerated Transport",
    "sg:phone":"+64 9-828 2164",
    "sg:province":"Auckland",
    "wof:name":"Kohu Distributors",
    "wof:placetype":"venue"
},
  "geometry": {"coordinates":[174.701935,-36.908279],"type":"Point"}
}