{
  "type": "Feature",
  "properties": {
    "addr:full":"32 Collingwood St Palmerston  Palmerston North Manawatu-Wanganui",
    "addr:housenumber":"32",
    "addr:street":"Collingwood St Palmerston",
    "iso:country":"NZ",
    "sg:address":"32 Collingwood St Palmerston ",
    "sg:city":"Palmerston North",
    "sg:classifiers":[
        {
            "category":"Education",
            "subcategory":"Dance Studio",
            "type":"Public Place"
        }
    ],
    "sg:phone":"+64 6-358 3062",
    "sg:province":"Manawatu-Wanganui",
    "sg:tags":[
        "school",
        "dancing",
        "-",
        "leisure",
        "sports",
        "sport"
    ],
    "wof:name":"Britten Barry A & Gwenda",
    "wof:placetype":"venue"
},
  "geometry": {"coordinates":[175.62468000000001,-40.370049],"type":"Point"}
}