{
  "type": "Feature",
  "properties": {
    "addr:full":"29 Selwyn St Onehunga  Auckland Auckland",
    "addr:housenumber":"29",
    "addr:street":"Selwyn St",
    "iso:country":"NZ",
    "sg:address":"29 Selwyn St Onehunga ",
    "sg:city":"Auckland",
    "sg:orig_category":"Automotive: Parts And Supplies: Tyres",
    "sg:phone":"+64 9-636 7001",
    "sg:province":"Auckland",
    "wof:name":"Onehunga Tyre & Mechanical Ltd",
    "wof:placetype":"venue"
},
  "geometry": {"coordinates":[174.78346300000001,-36.924572],"type":"Point"}
}