{
  "type": "Feature",
  "properties": {
    "iso:country":"NZ",
    "sg:address":"19 Derby St ",
    "sg:city":"Gisborne",
    "sg:classifiers":[
        {
            "category":"Personal",
            "type":"Services"
        }
    ],
    "sg:phone":"+64 6-867 8522",
    "sg:province":"Gisborne",
    "sg:tags":[
        "services",
        "home",
        "garden",
        "counselling"
    ],
    "wof:name":"Gisborne Counselling & Psychological Services",
    "wof:placetype":"venue"
},
  "geometry": {"coordinates":[178.024902,-38.662109],"type":"Point"}
}