{
  "type": "Feature",
  "properties": {
    "addr:full":"606 Rosebank Rd Avondale  Auckland Auckland",
    "addr:housenumber":"606",
    "addr:street":"Rosebank Rd",
    "iso:country":"NZ",
    "sg:address":"606 Rosebank Rd Avondale ",
    "sg:city":"Auckland",
    "sg:orig_category":"Industrial: Parts: Pipes, Tubes And Cabling: Pipes",
    "sg:phone":"+64 9-828 1353",
    "sg:province":"Auckland",
    "wof:name":"John Guest Pacific Ltd",
    "wof:placetype":"venue"
},
  "geometry": {"coordinates":[174.68568400000001,-36.888668],"type":"Point"}
}