{
  "type": "Feature",
  "properties": {
    "addr:full":"After Hours  Wellington Wellington",
    "iso:country":"NZ",
    "sg:address":"After Hours ",
    "sg:city":"Wellington",
    "sg:orig_category":"Transport: Transportation: Heavy Haulage",
    "sg:phone":"+64 4-235 8282",
    "sg:province":"Wellington",
    "wof:name":"Bradley Heavy Haulage",
    "wof:placetype":"venue"
},
  "geometry": {"coordinates":[-85.910454,33.827946],"type":"Point"}
}