{
  "type": "Feature",
  "properties": {
    "addr:full":"St Heliers Bay Rd St Heliers  Auckland Auckland",
    "addr:street":"St Heliers Bay Rd St",
    "iso:country":"NZ",
    "sg:address":"St Heliers Bay Rd St Heliers ",
    "sg:city":"Auckland",
    "sg:orig_category":"Education And Training: General: Schools",
    "sg:phone":"+64 9-575 8311",
    "sg:province":"Auckland",
    "wof:name":"St Heliers School",
    "wof:placetype":"venue"
},
  "geometry": {"coordinates":[174.858429,-36.852245],"type":"Point"}
}