{
  "type": "Feature",
  "properties": {
    "iso:country":"NZ",
    "sg:address":"Opua Estate ",
    "sg:city":"Paihia",
    "sg:orig_category":"Industrial: Products: Window Control Gear",
    "sg:phone":"+64 9-402 8394",
    "sg:province":"Northland",
    "wof:name":"Morgan Aluminium",
    "wof:placetype":"venue"
},
  "geometry": {"coordinates":[174.091064,-35.283699],"type":"Point"}
}