{
  "type": "Feature",
  "properties": {
    "addr:full":"39 Rutherford Tce Meadowbank  Auckland Auckland",
    "addr:housenumber":"39",
    "addr:street":"Rutherford Tce",
    "iso:country":"NZ",
    "sg:address":"39 Rutherford Tce Meadowbank ",
    "sg:city":"Auckland",
    "sg:classifiers":[
        {
            "category":"Manufacturing",
            "subcategory":"Tools & Machinery",
            "type":"Manufacturing & Wholesale Goods"
        }
    ],
    "sg:phone":"+64 9-528 5529",
    "sg:province":"Auckland",
    "sg:tags":[
        "specialist",
        "industrial",
        "bar",
        "coding",
        "equipment"
    ],
    "wof:name":"Scanalog Systems Ltd",
    "wof:placetype":"venue"
},
  "geometry": {"coordinates":[174.83712800000001,-36.872089],"type":"Point"}
}