{
  "type": "Feature",
  "properties": {
    "addr:full":"z8862/12 Main South Rd Concord  Dunedin Otago",
    "addr:housenumber":"12",
    "addr:street":"Main South Rd",
    "iso:country":"NZ",
    "sg:address":"z8862/12 Main South Rd Concord ",
    "sg:city":"Dunedin",
    "sg:classifiers":[
        {
            "category":"Personal",
            "subcategory":"Tanning Parlor",
            "type":"Services"
        }
    ],
    "sg:phone":"+64 3-488 1794",
    "sg:province":"Otago",
    "sg:tags":[
        "sun",
        "health",
        "beauty"
    ],
    "wof:name":"Scandals Hair Design & Sunbed",
    "wof:placetype":"venue"
},
  "geometry": {"coordinates":[170.45739699999999,-45.902618],"type":"Point"}
}