{
  "type": "Feature",
  "properties": {
    "addr:full":"PO Box 30-285 Lower  Hutt Wellington",
    "addr:housenumber":"po box 30-285",
    "iso:country":"NZ",
    "sg:address":"PO Box 30-285 Lower ",
    "sg:city":"Hutt",
    "sg:classifiers":[
        {
            "category":"Shopping",
            "subcategory":"Computers & Home Electronics",
            "type":"Retail Goods"
        }
    ],
    "sg:phone":"+64 4-567 7157",
    "sg:province":"Wellington",
    "sg:tags":[
        "equipment",
        "sport",
        "leisure",
        "entertainment"
    ],
    "wof:name":"Entertainment Masters",
    "wof:placetype":"venue"
},
  "geometry": {"coordinates":[174.90838600000001,-41.206631],"type":"Point"}
}