{
  "type": "Feature",
  "properties": {
    "addr:full":"Geange St Upper  Hutt Wellington",
    "addr:street":"St",
    "iso:country":"NZ",
    "sg:address":"Geange St Upper ",
    "sg:city":"Hutt",
    "sg:classifiers":[
        {
            "category":"Retail",
            "subcategory":"Auto Repair",
            "type":"Services"
        }
    ],
    "sg:phone":"+64 4-528 8836",
    "sg:province":"Wellington",
    "sg:tags":[
        "wheel",
        "automotive",
        "servicing",
        "alignment"
    ],
    "wof:name":"Upper Hutt Tyres & Alignments",
    "wof:placetype":"venue"
},
  "geometry": {"coordinates":[175.07060200000001,-41.125053],"type":"Point"}
}