{
  "type": "Feature",
  "properties": {
    "addr:full":"Pah St  Motueka Tasman",
    "addr:street":"Pah St",
    "iso:country":"NZ",
    "sg:address":"Pah St ",
    "sg:city":"Motueka",
    "sg:orig_category":"Sports And Leisure: General: Halls",
    "sg:phone":"+64 3-528 7885",
    "sg:province":"Tasman",
    "wof:name":"Motueka Memorial Hall",
    "wof:placetype":"venue"
},
  "geometry": {"coordinates":[173.00595100000001,-41.110043],"type":"Point"}
}