{
  "type": "Feature",
  "properties": {
    "iso:country":"NZ",
    "sg:address":"22 Weka St Otahuhu ",
    "sg:city":"Auckland",
    "sg:classifiers":[
        {
            "category":"Manufacturing",
            "subcategory":"Textiles",
            "type":"Manufacturing & Wholesale Goods"
        }
    ],
    "sg:phone":"+64 9-259 4446",
    "sg:province":"Auckland",
    "sg:tags":[
        "clothing",
        "fabric",
        "manufacturer"
    ],
    "wof:name":"E-Max Ltd",
    "wof:placetype":"venue"
},
  "geometry": {"coordinates":[174.83570900000001,-36.951813],"type":"Point"}
}