{
  "type": "Feature",
  "properties": {
    "iso:country":"NZ",
    "sg:address":"62 Hull Rd Mt ",
    "sg:city":"Maunganui",
    "sg:classifiers":[
        {
            "category":"Education",
            "subcategory":"Special Training",
            "type":"Public Place"
        }
    ],
    "sg:phone":"+64 7-575 3771",
    "sg:province":"Bay of Plenty",
    "sg:tags":[
        "driver"
    ],
    "wof:name":"R B Machinery",
    "wof:placetype":"venue"
},
  "geometry": {"coordinates":[176.186279,-37.641048],"type":"Point"}
}