{
  "type": "Feature",
  "properties": {
    "addr:full":"Kauri Dve Wairakei  Taupo Waikato",
    "iso:country":"NZ",
    "sg:address":"Kauri Dve Wairakei ",
    "sg:city":"Taupo",
    "sg:classifiers":[
        {
            "category":"Health Services",
            "subcategory":"Dentist",
            "type":"Services"
        }
    ],
    "sg:phone":"+64 7-374 8252",
    "sg:province":"Waikato",
    "sg:tags":[
        "dental",
        "clinic",
        "beauty"
    ],
    "wof:name":"Wairakei School Dental Clinic",
    "wof:placetype":"venue"
},
  "geometry": {"coordinates":[176.06947299999999,-38.731045],"type":"Point"}
}