{
  "type": "Feature",
  "properties": {
    "addr:full":"71 High St  Blenheim Marlborough",
    "addr:housenumber":"71",
    "addr:street":"High St",
    "iso:country":"NZ",
    "sg:address":"71 High St ",
    "sg:city":"Blenheim",
    "sg:classifiers":[
        {
            "category":"Bars & Pubs",
            "subcategory":"Wine Bar",
            "type":"Food & Drink"
        }
    ],
    "sg:phone":"+64 3-579 2925",
    "sg:province":"Marlborough",
    "sg:tags":[
        "wining",
        "dining"
    ],
    "wof:name":"Bragato's Wine Bar",
    "wof:placetype":"venue"
},
  "geometry": {"coordinates":[-79.65303,34.510719],"type":"Point"}
}