{
  "type": "Feature",
  "properties": {
    "addr:full":"51 Park Rse Campbells Bay  Auckland Auckland",
    "addr:housenumber":"51",
    "addr:street":"Park Rse",
    "iso:country":"NZ",
    "sg:address":"51 Park Rse Campbells Bay ",
    "sg:city":"Auckland",
    "sg:orig_category":"Automotive: Servicing And Repair: Car Trimming/Upholstery",
    "sg:phone":"+64 9-478 5482",
    "sg:province":"Auckland",
    "wof:name":"Jim Woonton Auto Upholstery",
    "wof:placetype":"venue"
},
  "geometry": {"coordinates":[174.75715600000001,-36.748329],"type":"Point"}
}