{
  "type": "Feature",
  "properties": {
    "iso:country":"NZ",
    "sg:address":"475 A Manukau Rd Epsom ",
    "sg:city":"Auckland",
    "sg:classifiers":[
        {
            "category":"Health Services",
            "subcategory":"Dentist",
            "type":"Services"
        }
    ],
    "sg:phone":"+64 9-631 5416",
    "sg:province":"Auckland",
    "sg:tags":[
        "dental",
        "beauty"
    ],
    "wof:name":"Epsom Dental Care",
    "wof:placetype":"venue"
},
  "geometry": {"coordinates":[174.77404799999999,-36.894482],"type":"Point"}
}