{
  "type": "Feature",
  "properties": {
    "addr:full":"Professional Suites Chartwell Square  Hamilton Waikato",
    "addr:street":"Chartwell Square",
    "iso:country":"NZ",
    "sg:address":"Professional Suites Chartwell Square ",
    "sg:city":"Hamilton",
    "sg:classifiers":[
        {
            "category":"Health Services",
            "subcategory":"Dentist",
            "type":"Services"
        }
    ],
    "sg:phone":"+64 7-855 4904",
    "sg:province":"Waikato",
    "sg:tags":[
        "dental",
        "beauty"
    ],
    "wof:name":"Chartwell Dental Centre",
    "wof:placetype":"venue"
},
  "geometry": {"coordinates":[175.27124000000001,-37.763653],"type":"Point"}
}