{
  "type": "Feature",
  "properties": {
    "addr:full":"Harold St Mt Eden  Auckland Auckland",
    "addr:street":"Harold St",
    "iso:country":"NZ",
    "sg:address":"Harold St Mt Eden ",
    "sg:city":"Auckland",
    "sg:classifiers":[
        {
            "category":"Home & Garden",
            "subcategory":"Furniture",
            "type":"Retail Goods"
        }
    ],
    "sg:phone":"+64 9-623 2014",
    "sg:province":"Auckland",
    "sg:tags":[
        "furniture/furnishings",
        "furnishing"
    ],
    "sg:website":"http://www.yellowpages.co.nz/for/cintesi/dp21301.html",
    "wof:name":"Cintesi",
    "wof:placetype":"venue"
},
  "geometry": {"coordinates":[174.761368,-36.86916],"type":"Point"}
}