{
  "type": "Feature",
  "properties": {
    "addr:full":"159 Stafford St  Timaru Canterbury",
    "addr:housenumber":"159",
    "addr:street":"Stafford St",
    "iso:country":"NZ",
    "sg:address":"159 Stafford St ",
    "sg:city":"Timaru",
    "sg:classifiers":[
        {
            "category":"Personal",
            "subcategory":"Tattoo Parlor",
            "type":"Services"
        }
    ],
    "sg:phone":"+64 3-688 0973",
    "sg:province":"Canterbury",
    "sg:tags":[
        "services",
        "home",
        "tattooists",
        "garden"
    ],
    "wof:name":"4Skin Tattoo & Piercing",
    "wof:placetype":"venue"
},
  "geometry": {"coordinates":[171.25479100000001,-44.396698],"type":"Point"}
}