{
  "type": "Feature",
  "properties": {
    "iso:country":"NZ",
    "sg:address":"45 Woodmancote Rd Khandallah ",
    "sg:city":"Wellington",
    "sg:classifiers":[
        {
            "category":"Sports & Exercise",
            "subcategory":"Sports Center",
            "type":"Entertainment"
        }
    ],
    "sg:phone":"+64 4-479 6644",
    "sg:province":"Wellington",
    "sg:tags":[
        "sporting",
        "sports",
        "-",
        "leisure",
        "facility"
    ],
    "wof:name":"Wellington City Council",
    "wof:placetype":"venue"
},
  "geometry": {"coordinates":[174.788544,-41.242058],"type":"Point"}
}