{
  "type": "Feature",
  "properties": {
    "iso:country":"NZ",
    "sg:address":"759 Lake Monowai Rd Monowai 2 ",
    "sg:city":"Otautau",
    "sg:classifiers":[
        {
            "category":"Recreation",
            "type":"Entertainment"
        }
    ],
    "sg:phone":"+64 3-225 5191",
    "sg:tags":[
        "shopping",
        "hunting",
        "fishing",
        "retailers",
        "sport",
        "trip"
    ],
    "wof:name":"Fishing Hunting South Limited",
    "wof:placetype":"venue"
},
  "geometry": {"coordinates":[167.998795,-46.142715],"type":"Point"}
}