{
  "type": "Feature",
  "properties": {
    "iso:country":"NZ",
    "sg:address":"3 Donnor Pl Mt Wellington ",
    "sg:city":"Auckland",
    "sg:classifiers":[
        {
            "category":"Shopping",
            "subcategory":"Beauty & Cosmetics",
            "type":"Retail Goods"
        }
    ],
    "sg:phone":"+64 9-574 3350",
    "sg:province":"Auckland",
    "sg:tags":[
        "health",
        "perfumery"
    ],
    "wof:name":"Dr Hauschka Skincare",
    "wof:placetype":"venue"
},
  "geometry": {"coordinates":[174.849564,-36.912094],"type":"Point"}
}