{
  "type": "Feature",
  "properties": {
    "addr:full":"Suite 16 Marinoto Clinic 72 Newington Ave Maori Hill Dunedin Otago",
    "addr:housenumber":"72",
    "addr:street":"Suite 16;Newington Ave",
    "iso:country":"NZ",
    "sg:address":"Suite 16 Marinoto Clinic 72 Newington Ave Maori Hill",
    "sg:city":"Dunedin",
    "sg:classifiers":[
        {
            "category":"Health Services",
            "subcategory":"Health Practitioner",
            "type":"Services"
        }
    ],
    "sg:phone":"+64 3-479 2202",
    "sg:province":"Otago",
    "sg:tags":[
        "specialist",
        "medical",
        "beauty",
        "specialists"
    ],
    "wof:name":"Swan Andrew",
    "wof:placetype":"venue"
},
  "geometry": {"coordinates":[170.502701,-45.859348],"type":"Point"}
}