{
  "type": "Feature",
  "properties": {
    "iso:country":"NZ",
    "sg:address":"2 Nova Scotia Drive Waipu ",
    "sg:city":"Whangarei",
    "sg:classifiers":[
        {
            "category":"Health Services",
            "subcategory":"Clinic",
            "type":"Services"
        }
    ],
    "sg:phone":"+64 9-432 1190",
    "sg:province":"Canterbury",
    "sg:tags":[
        "medical",
        "beauty"
    ],
    "wof:name":"Waipu Medical Centre",
    "wof:placetype":"venue"
},
  "geometry": {"coordinates":[174.44288635250001,-35.9868011475],"type":"Point"}
}