{
  "type": "Feature",
  "properties": {
    "addr:full":"Shop 30 Village Ct Havelock  Palmerston North Manawatu-Wanganui",
    "addr:housenumber":"30",
    "addr:street":"Village Ct",
    "iso:country":"NZ",
    "sg:address":"Shop 30 Village Ct Havelock ",
    "sg:city":"Palmerston North",
    "sg:orig_category":"Clothing And Fabric: Clothing: Children'S Wear",
    "sg:phone":"+64 6-877 9797",
    "sg:province":"Manawatu-Wanganui",
    "wof:name":"Jitterbugs Clothing",
    "wof:placetype":"venue"
},
  "geometry": {"coordinates":[176.87951699999999,-39.669403],"type":"Point"}
}