{
  "type": "Feature",
  "properties": {
    "addr:full":"53 Union St  Hawera Taranaki",
    "addr:housenumber":"53",
    "addr:street":"Union St",
    "iso:country":"NZ",
    "sg:address":"53 Union St ",
    "sg:city":"Hawera",
    "sg:classifiers":[
        {
            "category":"Retail",
            "subcategory":"Auto Repair",
            "type":"Services"
        }
    ],
    "sg:phone":"+64 6-278 5744",
    "sg:province":"Taranaki",
    "sg:tags":[
        "automotive",
        "electric",
        "servicing"
    ],
    "wof:name":"Weir David Auto Electrician",
    "wof:placetype":"venue"
},
  "geometry": {"coordinates":[174.28331,-39.585484],"type":"Point"}
}