{
  "type": "Feature",
  "properties": {
    "addr:full":"6 D Cartwright Rd Kelston  Auckland Auckland",
    "addr:housenumber":"6 d",
    "addr:street":"Cartwright Rd",
    "iso:country":"NZ",
    "sg:address":"6 D Cartwright Rd Kelston ",
    "sg:city":"Auckland",
    "sg:classifiers":[
        {
            "category":"Manufacturing",
            "subcategory":"Rubber & Plastics",
            "type":"Manufacturing & Wholesale Goods"
        }
    ],
    "sg:phone":"+64 9-818 0038",
    "sg:province":"Auckland",
    "sg:tags":[
        "repair",
        "industrial",
        "-",
        "goods"
    ],
    "wof:name":"Mid West Industries",
    "wof:placetype":"venue"
},
  "geometry": {"coordinates":[174.66717499999999,-36.899097],"type":"Point"}
}