{
  "type": "Feature",
  "properties": {
    "addr:full":"50 Orwell Cre Newfield  Invercargill Southland",
    "addr:housenumber":"50",
    "addr:street":"Orwell Cre",
    "iso:country":"NZ",
    "sg:address":"50 Orwell Cre Newfield ",
    "sg:city":"Invercargill",
    "sg:classifiers":[
        {
            "category":"Home & Garden",
            "subcategory":"Garden Supply",
            "type":"Retail Goods"
        }
    ],
    "sg:phone":"+64 25331223",
    "sg:province":"Southland",
    "sg:tags":[
        "fencing",
        "outdoor",
        "contractor"
    ],
    "wof:name":"Rex Beech Fencing",
    "wof:placetype":"venue"
},
  "geometry": {"coordinates":[168.38241600000001,-46.415192],"type":"Point"}
}