{
  "type": "Feature",
  "properties": {
    "addr:full":"136 Grafton Rd Grafton  Auckland Auckland",
    "addr:housenumber":"136",
    "addr:street":"Grafton Rd",
    "iso:country":"NZ",
    "sg:address":"136 Grafton Rd Grafton ",
    "sg:city":"Auckland",
    "sg:classifiers":[
        {
            "category":"Education",
            "subcategory":"Special Training",
            "type":"Public Place"
        }
    ],
    "sg:phone":"+64 9-309 5970",
    "sg:province":"Auckland",
    "sg:website":"http://www.wcad.ac.nz",
    "wof:name":"WHITECLIFFE COLLEGE OF ARTS & DESIGN",
    "wof:placetype":"venue"
},
  "geometry": {"coordinates":[174.765366,-36.862389],"type":"Point"}
}