{
  "type": "Feature",
  "properties": {
    "iso:country":"NZ",
    "sg:address":"Opp Tga City Council Willow St ",
    "sg:city":"Tauranga",
    "sg:orig_category":"Sports And Leisure: Sports: Skiing",
    "sg:phone":"+64 7-578 6904",
    "sg:province":"Bay of Plenty",
    "wof:name":"Broncos Sports World Ltd",
    "wof:placetype":"venue"
},
  "geometry": {"coordinates":[176.144745,-37.703156],"type":"Point"}
}