{
  "type": "Feature",
  "properties": {
    "iso:country":"NZ",
    "sg:address":"Arcade Burnett St ",
    "sg:city":"Ashburton",
    "sg:orig_category":"Clothing And Fabric: Clothing: Children'S Wear",
    "sg:phone":"+64 3-308 7597",
    "sg:province":"Canterbury",
    "wof:name":"Tots To Teens",
    "wof:placetype":"venue"
},
  "geometry": {"coordinates":[-77.127831,39.012852],"type":"Point"}
}