{
  "type": "Feature",
  "properties": {
    "iso:country":"NZ",
    "sg:address":"23 Meadows Rd Washdyke ",
    "sg:city":"Timaru",
    "sg:classifiers":[
        {
            "category":"Wholesale",
            "subcategory":"Auto Parts",
            "type":"Manufacturing & Wholesale Goods"
        }
    ],
    "sg:phone":"+64 3-686 6663",
    "sg:province":"Canterbury",
    "sg:tags":[
        "automotive",
        "supplies"
    ],
    "wof:name":"Total Fleet Management",
    "wof:placetype":"venue"
},
  "geometry": {"coordinates":[171.241486,-44.357136],"type":"Point"}
}