{
  "type": "Feature",
  "properties": {
    "iso:country":"NZ",
    "sg:address":"34 State Highway 27 ",
    "sg:city":"Tirau",
    "sg:orig_category":"Travel And Tourism: Accommodation: Farmstays And Homestays",
    "sg:phone":"+64 7-883 1349",
    "sg:website":"http://www.matamata-info.co.nz/RosebudCottage",
    "wof:name":"Rosebud Country Cottage",
    "wof:placetype":"venue"
},
  "geometry": {"coordinates":[175.756134,-37.944466],"type":"Point"}
}