{
  "type": "Feature",
  "properties": {
    "addr:full":"28 Sanday St  Palmerston",
    "addr:housenumber":"28",
    "addr:street":"Sanday St",
    "iso:country":"NZ",
    "sg:address":"28 Sanday St ",
    "sg:city":"Palmerston",
    "sg:orig_category":"Health And Beauty: Products: Pharmacies",
    "sg:phone":"+64 3-465 1120",
    "wof:name":"Waihemo Pharmacy",
    "wof:placetype":"venue"
},
  "geometry": {"coordinates":[170.71542400000001,-45.4851],"type":"Point"}
}