{
  "type": "Feature",
  "properties": {
    "addr:full":"Birch Hill Cottage State Highway 1  Blenheim Marlborough",
    "addr:street":"State Highway 1",
    "iso:country":"NZ",
    "sg:address":"Birch Hill Cottage State Highway 1 ",
    "sg:city":"Blenheim",
    "sg:orig_category":"Home And Garden: Gardening: Services: Tree Services",
    "sg:phone":"+64 25992594",
    "sg:province":"Marlborough",
    "wof:name":"Marlborough Stump Grinding",
    "wof:placetype":"venue"
},
  "geometry": {"coordinates":[-79.65212200000001,34.513569],"type":"Point"}
}