{
  "type": "Feature",
  "properties": {
    "addr:full":"51 Rimu St Glenwood  Timaru Canterbury",
    "addr:housenumber":"51",
    "addr:street":"Rimu St",
    "iso:country":"NZ",
    "sg:address":"51 Rimu St Glenwood ",
    "sg:city":"Timaru",
    "sg:classifiers":[
        {
            "category":"Home & Garden",
            "subcategory":"Carpets & Floor Coverings",
            "type":"Retail Goods"
        }
    ],
    "sg:phone":"+64 800 928 928",
    "sg:province":"Canterbury",
    "sg:tags":[
        "cleaning",
        "furniture"
    ],
    "wof:name":"Kiwi Cleaning Services Ltd",
    "wof:placetype":"venue"
},
  "geometry": {"coordinates":[171.211975,-44.390118],"type":"Point"}
}