{
  "type": "Feature",
  "properties": {
    "addr:full":"3/1207 Great North Rd Point Chevalier  Auckland Auckland",
    "addr:housenumber":"3 / 1207",
    "addr:street":"Great North Rd",
    "iso:country":"NZ",
    "sg:address":"3/1207 Great North Rd Point Chevalier ",
    "sg:city":"Auckland",
    "sg:classifiers":[
        {
            "category":"Communications",
            "subcategory":"Film & Video Production",
            "type":"Services"
        }
    ],
    "sg:phone":"+64 9-815 3606",
    "sg:province":"Auckland",
    "sg:tags":[
        "sport",
        "leisure",
        "library",
        "entertainment"
    ],
    "wof:name":"Point Video",
    "wof:placetype":"venue"
},
  "geometry": {"coordinates":[174.710556,-36.870323],"type":"Point"}
}