{
  "type": "Feature",
  "properties": {
    "addr:full":"47 Firth St Drury  Auckland Auckland",
    "addr:housenumber":"47",
    "addr:street":"Firth St",
    "iso:country":"NZ",
    "sg:address":"47 Firth St Drury ",
    "sg:city":"Auckland",
    "sg:orig_category":"Industrial: Services: Toolmakers And Designers",
    "sg:phone":"+64 9-294 8844",
    "sg:province":"Auckland",
    "wof:name":"EDM Engineering Ltd",
    "wof:placetype":"venue"
},
  "geometry": {"coordinates":[174.94786099999999,-37.102081],"type":"Point"}
}