{
  "type": "Feature",
  "properties": {
    "iso:country":"NZ",
    "sg:address":"47 Firth St Drury ",
    "sg:city":"Auckland",
    "sg:orig_category":"Industrial: Services: Toolmakers And Designers",
    "sg:phone":"+64 9-294 8844",
    "sg:province":"Auckland",
    "wof:name":"EDM Engineering Ltd",
    "wof:placetype":"venue"
},
  "geometry": {"coordinates":[174.947861,-37.102081],"type":"Point"}
}