{
  "type": "Feature",
  "properties": {
    "iso:country":"NZ",
    "sg:address":"7 Grove St ",
    "sg:city":"Nelson",
    "sg:classifiers":[
        {
            "category":"Travel",
            "subcategory":"Bed & Breakfast",
            "type":"Entertainment"
        }
    ],
    "sg:phone":"+64 800 464 566",
    "sg:province":"Nelson",
    "sg:tags":[
        "tourism"
    ],
    "sg:website":"http://www.yellowpages.co.nz/for/mikonuibedandbreakfast/dp57543.html",
    "wof:name":"Mikonui Bed and Breakfast",
    "wof:placetype":"venue"
},
  "geometry": {"coordinates":[173.28491199999999,-41.268913],"type":"Point"}
}