{
  "type": "Feature",
  "properties": {
    "addr:full":"The Link Arcade Broadway Ave Palmerston  Palmerston North Waikato",
    "addr:street":"The Link Arcade Broadway Ave",
    "iso:country":"NZ",
    "sg:address":"The Link Arcade Broadway Ave Palmerston ",
    "sg:city":"Palmerston North",
    "sg:orig_category":"Health And Beauty: Beauty: Hairdressers",
    "sg:phone":"+64 6-358 1309",
    "sg:province":"Waikato",
    "wof:name":"Hair Transformer",
    "wof:placetype":"venue"
},
  "geometry": {"coordinates":[175.611481,-40.357422],"type":"Point"}
}