{
  "type": "Feature",
  "properties": {
    "addr:full":"101 O'Donnell Ave Mt Roskill  Auckland Auckland",
    "addr:housenumber":"101",
    "addr:street":"O'Donnell Ave",
    "iso:country":"NZ",
    "sg:address":"101 O'Donnell Ave Mt Roskill ",
    "sg:city":"Auckland",
    "sg:classifiers":[
        {
            "category":"Home & Garden",
            "subcategory":"Furniture",
            "type":"Retail Goods"
        }
    ],
    "sg:phone":"+64 9-620 1020",
    "sg:province":"Auckland",
    "sg:tags":[
        "furniture/furnishings",
        "designer"
    ],
    "wof:name":"Deligion Design Handcast Pewter Handles",
    "wof:placetype":"venue"
},
  "geometry": {"coordinates":[174.74276699999999,-36.905891],"type":"Point"}
}