{
  "type": "Feature",
  "properties": {
    "addr:full":"53 Chalmers St Hornby  Christchurch Canterbury",
    "addr:housenumber":"53",
    "addr:street":"Chalmers St",
    "iso:country":"NZ",
    "sg:address":"53 Chalmers St Hornby ",
    "sg:city":"Christchurch",
    "sg:classifiers":[
        {
            "category":"Social Services",
            "subcategory":"Child Care",
            "type":"Services"
        }
    ],
    "sg:phone":"+64 3-349 9394",
    "sg:province":"Canterbury",
    "sg:tags":[
        "baby",
        "home",
        "product",
        "garden",
        "children"
    ],
    "wof:name":"Baby City",
    "wof:placetype":"venue"
},
  "geometry": {"coordinates":[172.525192,-43.542301],"type":"Point"}
}