{
  "type": "Feature",
  "properties": {
    "iso:country":"NZ",
    "sg:address":"35 Campbell St ",
    "sg:city":"Cambridge",
    "sg:classifiers":[
        {
            "category":"Professional",
            "subcategory":"Art Services",
            "type":"Services"
        }
    ],
    "sg:phone":"+64 7-827 4899",
    "sg:province":"Waikato",
    "sg:tags":[
        "picture",
        "arts",
        "sport",
        "framing",
        "leisure"
    ],
    "wof:name":"Paperartzi Studio",
    "wof:placetype":"venue"
},
  "geometry": {"coordinates":[-81.565002,40.011871],"type":"Point"}
}