{
  "type": "Feature",
  "properties": {
    "iso:country":"NZ",
    "sg:address":"18 Colombo St Cashmere ",
    "sg:city":"Christchurch",
    "sg:orig_category":"Food And Drink: Meats: Butchers",
    "sg:phone":"+64 3-332 6071",
    "sg:province":"Canterbury",
    "wof:name":"Cashmere Cuisine",
    "wof:placetype":"venue"
},
  "geometry": {"coordinates":[172.635681,-43.566891],"type":"Point"}
}