{
  "type": "Feature",
  "properties": {
    "addr:full":"18 Colombo St Cashmere  Christchurch Canterbury",
    "addr:housenumber":"18",
    "addr:street":"Colombo St",
    "iso:country":"NZ",
    "sg:address":"18 Colombo St Cashmere ",
    "sg:city":"Christchurch",
    "sg:orig_category":"Food And Drink: Meats: Butchers",
    "sg:phone":"+64 3-332 6071",
    "sg:province":"Canterbury",
    "wof:name":"Cashmere Cuisine",
    "wof:placetype":"venue"
},
  "geometry": {"coordinates":[172.63568100000001,-43.566891],"type":"Point"}
}