{
  "type": "Feature",
  "properties": {
    "addr:full":"cnr Queen St & Main Rd Kopu  Thames Waikato",
    "addr:housenumber":"cnr",
    "addr:street":"Queen St & Main Rd",
    "iso:country":"NZ",
    "sg:address":"cnr Queen St & Main Rd Kopu ",
    "sg:city":"Thames",
    "sg:orig_category":"Industrial: Products: Window Control Gear",
    "sg:phone":"+64 7-868 9149",
    "sg:province":"Waikato",
    "wof:name":"Fisher Coromandel",
    "wof:placetype":"venue"
},
  "geometry": {"coordinates":[175.57692,-37.18845],"type":"Point"}
}