{
  "type": "Feature",
  "properties": {
    "addr:full":"PO Box 99807 Newmarket  Auckland Auckland",
    "addr:housenumber":"po box 99807",
    "iso:country":"NZ",
    "sg:address":"PO Box 99807 Newmarket ",
    "sg:city":"Auckland",
    "sg:classifiers":[
        {
            "category":"Farming",
            "subcategory":"Fish & Marine Products",
            "type":"Manufacturing & Wholesale Goods"
        }
    ],
    "sg:phone":"+64 9-376 2244",
    "sg:province":"Auckland",
    "sg:tags":[
        "boats",
        "yacht",
        "transport",
        "boat",
        "supply"
    ],
    "wof:name":"Jet Dock System (Australasia)Ltd",
    "wof:placetype":"venue"
},
  "geometry": {"coordinates":[174.77375799999999,-36.867878],"type":"Point"}
}