{
  "type": "Feature",
  "properties": {
    "addr:full":"Frankton Marina  Queenstown Waikato",
    "iso:country":"NZ",
    "sg:address":"Frankton Marina ",
    "sg:city":"Queenstown",
    "sg:classifiers":[
        {
            "category":"Sports & Exercise",
            "subcategory":"Sports Center",
            "type":"Entertainment"
        }
    ],
    "sg:phone":"+64 3-442 3454",
    "sg:province":"Waikato",
    "sg:tags":[
        "sporting",
        "sports",
        "-",
        "leisure",
        "facility"
    ],
    "wof:name":"Water Sport World",
    "wof:placetype":"venue"
},
  "geometry": {"coordinates":[168.73263499999999,-45.020927],"type":"Point"}
}