{
  "type": "Feature",
  "properties": {
    "iso:country":"NZ",
    "sg:address":"Pet Medical Plan 24 Croydon St ",
    "sg:city":"Sydenham",
    "sg:orig_category":"Farming: Services",
    "sg:phone":"+64 800 738 752",
    "sg:province":"Canterbury",
    "sg:website":"http://www.petplan.co.nz",
    "wof:name":"Ellenco Enterprizes Ltd",
    "wof:placetype":"venue"
},
  "geometry": {"coordinates":[-5.877069,54.60693],"type":"Point"}
}