{
  "type": "Feature",
  "properties": {
    "addr:full":"Bristol St Riverlands  Blenheim Marlborough",
    "addr:street":"Bristol St",
    "iso:country":"NZ",
    "sg:address":"Bristol St Riverlands ",
    "sg:city":"Blenheim",
    "sg:orig_category":"Storage: Storage",
    "sg:phone":"+64 3-577 8838",
    "sg:province":"Marlborough",
    "wof:name":"Allied Movers (NZ) Ltd",
    "wof:placetype":"venue"
},
  "geometry": {"coordinates":[174.01097100000001,-41.530647],"type":"Point"}
}