{
  "type": "Feature",
  "properties": {
    "addr:full":"48 John St  Whangarei Northland",
    "addr:housenumber":"48",
    "addr:street":"John St",
    "iso:country":"NZ",
    "sg:address":"48 John St ",
    "sg:city":"Whangarei",
    "sg:classifiers":[
        {
            "category":"Home & Garden",
            "subcategory":"Carpets & Floor Coverings",
            "type":"Retail Goods"
        }
    ],
    "sg:phone":"+64 9-438 7848",
    "sg:province":"Northland",
    "sg:tags":[
        "cleaning",
        "furniture"
    ],
    "wof:name":"ChemDry Northland",
    "wof:placetype":"venue"
},
  "geometry": {"coordinates":[174.32313500000001,-35.72472],"type":"Point"}
}