{
  "type": "Feature",
  "properties": {
    "addr:full":"13 Waikaukau Rd Glen Eden  Auckland Auckland",
    "addr:housenumber":"13",
    "addr:street":"Waikaukau Rd",
    "iso:country":"NZ",
    "sg:address":"13 Waikaukau Rd Glen Eden ",
    "sg:city":"Auckland",
    "sg:orig_category":"Industrial: Engineering: Engineers - Precision",
    "sg:phone":"+64 9-818 1148",
    "sg:province":"Auckland",
    "wof:name":"Production & Development",
    "wof:placetype":"venue"
},
  "geometry": {"coordinates":[174.637619,-36.907177],"type":"Point"}
}