{
  "type": "Feature",
  "properties": {
    "iso:country":"NZ",
    "sg:address":"6 Gladstone Rd Richmond ",
    "sg:city":"Nelson",
    "sg:orig_category":"Industrial: Products: Filters And Filtration",
    "sg:phone":"+64 3-544 6029",
    "sg:province":"Nelson",
    "wof:name":"Heslop Lloyd Motors Ltd",
    "wof:placetype":"venue"
},
  "geometry": {"coordinates":[173.180511,-41.337242],"type":"Point"}
}