{
  "type": "Feature",
  "properties": {
    "iso:country":"NZ",
    "sg:address":"Parker Lane R D 2 ",
    "sg:city":"Pukekohe",
    "sg:orig_category":"Farming: Horticulture: Soil Testing",
    "sg:phone":"+64 9-238 3103",
    "sg:province":"Gisborne",
    "wof:name":"Agricultural Consulting Services",
    "wof:placetype":"venue"
},
  "geometry": {"coordinates":[-97.731216,30.222851],"type":"Point"}
}