{
  "type": "Feature",
  "properties": {
    "addr:full":"49 Matai St  Taupo Waikato",
    "addr:housenumber":"49",
    "addr:street":"Matai St",
    "iso:country":"NZ",
    "sg:address":"49 Matai St ",
    "sg:city":"Taupo",
    "sg:classifiers":[
        {
            "category":"Home & Garden",
            "subcategory":"Building Materials",
            "type":"Retail Goods"
        }
    ],
    "sg:phone":"+64 7-378 0664",
    "sg:province":"Waikato",
    "sg:tags":[
        "door",
        "fitting",
        "fittings"
    ],
    "wof:name":"Bennett Doors Ltd",
    "wof:placetype":"venue"
},
  "geometry": {"coordinates":[176.102768,-38.688934],"type":"Point"}
}