{
  "type": "Feature",
  "properties": {
    "addr:full":"16 Jutland Rd Takapuna  Auckland Auckland",
    "addr:housenumber":"16",
    "addr:street":"Jutland Rd",
    "iso:country":"NZ",
    "sg:address":"16 Jutland Rd Takapuna ",
    "sg:city":"Auckland",
    "sg:orig_category":"Sports And Leisure: Entertainment: Musicians",
    "sg:phone":"+64 9-489 9416",
    "sg:province":"Auckland",
    "wof:name":"Barbershop Chorus City of Sails",
    "wof:placetype":"venue"
},
  "geometry": {"coordinates":[174.76788300000001,-36.787838],"type":"Point"}
}