{
  "type": "Feature",
  "properties": {
    "iso:country":"NZ",
    "sg:address":"4 Shortland St Auckland City ",
    "sg:city":"Auckland",
    "sg:classifiers":[
        {
            "category":"Communications",
            "subcategory":"Film & Video Production",
            "type":"Services"
        }
    ],
    "sg:phone":"+64 9-366 6001",
    "sg:province":"Auckland",
    "sg:tags":[
        "sport",
        "leisure",
        "library",
        "entertainment"
    ],
    "wof:name":"Source The Sound & Video",
    "wof:placetype":"venue"
},
  "geometry": {"coordinates":[174.766357,-36.846287],"type":"Point"}
}