{
  "type": "Feature",
  "properties": {
    "iso:country":"NZ",
    "sg:address":"Gulf Harbour Marina Whangaparaoa Hibiscus ",
    "sg:city":"Hibiscus Coast",
    "sg:classifiers":[
        {
            "category":"Marine",
            "type":"Transportation"
        }
    ],
    "sg:phone":"+64 9-424 1719",
    "sg:province":"Auckland",
    "sg:tags":[
        "boats",
        "builder",
        "yacht",
        "transport",
        "boat"
    ],
    "wof:name":"Brin Wilson Boats",
    "wof:placetype":"venue"
},
  "geometry": {"coordinates":[174.749161,-36.634239],"type":"Point"}
}