{
  "type": "Feature",
  "properties": {
    "iso:country":"NZ",
    "sg:address":"151 Seaview Rd New ",
    "sg:city":"Plymouth",
    "sg:orig_category":"Home And Garden: Gardening: Services: Lawnmowing Services",
    "sg:phone":"+64 6-753 6577",
    "sg:province":"Taranaki",
    "wof:name":"Seaview Section Services",
    "wof:placetype":"venue"
},
  "geometry": {"coordinates":[-70.536819,41.893902],"type":"Point"}
}