{
  "type": "Feature",
  "properties": {
    "iso:country":"NZ",
    "sg:address":"42 Vestey Dve Mt Wellington ",
    "sg:city":"Auckland",
    "sg:orig_category":"Industrial: Services: Specialist Services: Heat Exchange/Treatment",
    "sg:phone":"+64 9-573 3073",
    "sg:province":"Auckland",
    "wof:name":"Invensys",
    "wof:placetype":"venue"
},
  "geometry": {"coordinates":[174.830292,-36.909569],"type":"Point"}
}