{
  "type": "Feature",
  "properties": {
    "addr:full":"745 Gordonton Rd  Hamilton Waikato",
    "addr:housenumber":"745",
    "addr:street":"Gordonton Rd",
    "iso:country":"NZ",
    "sg:address":"745 Gordonton Rd ",
    "sg:city":"Hamilton",
    "sg:orig_category":"Sports And Leisure: Hobbies: Calligraphy",
    "sg:phone":"+64 7-824 3560",
    "sg:province":"Waikato",
    "wof:name":"Marian Riddell Calligraphy",
    "wof:placetype":"venue"
},
  "geometry": {"coordinates":[175.293442,-37.748657],"type":"Point"}
}