{
  "type": "Feature",
  "properties": {
    "addr:full":"Cnr Maraekakaho Rd & Heretaunga St  Hastings Hawke's Bay",
    "addr:street":"Cnr Maraekakaho Rd & Heretaunga St",
    "iso:country":"NZ",
    "sg:address":"Cnr Maraekakaho Rd & Heretaunga St ",
    "sg:city":"Hastings",
    "sg:orig_category":"Automotive: General Services: Service Stations",
    "sg:phone":"+64 6-873 4630",
    "sg:province":"Hawke's Bay",
    "wof:name":"BP Oil",
    "wof:placetype":"venue"
},
  "geometry": {"coordinates":[176.844818,-39.64167],"type":"Point"}
}