{
  "type": "Feature",
  "properties": {
    "addr:full":"25 James Gro Stokes Valley Lower  Hutt Wellington",
    "addr:housenumber":"25",
    "addr:street":"James Gro Stokes Valley",
    "iso:country":"NZ",
    "sg:address":"25 James Gro Stokes Valley Lower ",
    "sg:city":"Hutt",
    "sg:classifiers":[
        {
            "category":"Landmark",
            "subcategory":"Tourist Information",
            "type":"Public Place"
        }
    ],
    "sg:phone":"+64 4-563 5211",
    "sg:province":"Wellington",
    "sg:tags":[
        "services",
        "travel",
        "tourism"
    ],
    "wof:name":"NZ Institute Of Public Administration",
    "wof:placetype":"venue"
},
  "geometry": {"coordinates":[174.98187300000001,-41.17495],"type":"Point"}
}