{
  "type": "Feature",
  "properties": {
    "addr:full":"Gladstone Building 95 Stafford St  Timaru Canterbury",
    "addr:housenumber":"95",
    "addr:street":"Stafford St",
    "iso:country":"NZ",
    "sg:address":"Gladstone Building 95 Stafford St ",
    "sg:city":"Timaru",
    "sg:classifiers":[
        {
            "category":"Banks & Credit Unions",
            "subcategory":"Investment Brokerage",
            "type":"Services"
        }
    ],
    "sg:phone":"+64 3-684 8886",
    "sg:province":"Canterbury",
    "sg:tags":[
        "personal",
        "accountant",
        "chartered",
        "-",
        "finance"
    ],
    "wof:name":"Gawler Stephen",
    "wof:placetype":"venue"
},
  "geometry": {"coordinates":[171.23741100000001,-44.395428],"type":"Point"}
}