{
  "type": "Feature",
  "properties": {
    "addr:full":"475 Main Rd Riwaka  Motueka Tasman",
    "addr:housenumber":"475",
    "addr:street":"Main Rd",
    "iso:country":"NZ",
    "sg:address":"475 Main Rd Riwaka ",
    "sg:city":"Motueka",
    "sg:classifiers":[
        {
            "category":"Home & Garden",
            "subcategory":"Carpets & Floor Coverings",
            "type":"Retail Goods"
        }
    ],
    "sg:phone":"+64 252491307",
    "sg:province":"Tasman",
    "sg:tags":[
        "cleaning",
        "furniture"
    ],
    "wof:name":"Halls Mat Binding",
    "wof:placetype":"venue"
},
  "geometry": {"coordinates":[173.013443,-41.108101],"type":"Point"}
}