{
  "type": "Feature",
  "properties": {
    "addr:full":"7 Main Rd  Fairfield",
    "addr:housenumber":"7",
    "addr:street":"Main Rd",
    "iso:country":"NZ",
    "sg:address":"7 Main Rd ",
    "sg:city":"Fairfield",
    "sg:classifiers":[
        {
            "category":"Shopping",
            "subcategory":"Crafts & Fabrics",
            "type":"Retail Goods"
        }
    ],
    "sg:phone":"+64 508 827 826",
    "sg:tags":[
        "clothing"
    ],
    "sg:website":"http://www.tartansofnz.com",
    "wof:name":"Tartans Of New Zealand",
    "wof:placetype":"venue"
},
  "geometry": {"coordinates":[170.403412,-45.897236],"type":"Point"}
}