{
  "type": "Feature",
  "properties": {
    "addr:full":"19 Mandeville St Riccarton  Christchurch Canterbury",
    "addr:housenumber":"19",
    "addr:street":"Mandeville St;Christchurch",
    "iso:country":"NZ",
    "sg:address":"19 Mandeville St Riccarton ",
    "sg:city":"Christchurch",
    "sg:orig_category":"Farming: Services: Irrigation",
    "sg:phone":"+64 3-963 1780",
    "sg:province":"Canterbury",
    "wof:name":"Water Dynamics",
    "wof:placetype":"venue"
},
  "geometry": {"coordinates":[172.60676599999999,-43.535473],"type":"Point"}
}