{
  "type": "Feature",
  "properties": {
    "iso:country":"NZ",
    "sg:address":"130 Coonor Rd ",
    "sg:city":"Timaru",
    "sg:classifiers":[
        {
            "category":"Retail",
            "subcategory":"Laundry & Dry Cleaning",
            "type":"Services"
        }
    ],
    "sg:phone":"+64 3-688 0187",
    "sg:province":"Canterbury",
    "sg:tags":[
        "product",
        "wool",
        "clothing",
        "fabric"
    ],
    "wof:name":"Hanson G S",
    "wof:placetype":"venue"
},
  "geometry": {"coordinates":[171.22380100000001,-44.407902],"type":"Point"}
}