{
  "type": "Feature",
  "properties": {
    "addr:full":"Compass Community Village Seventeenth Ave  Tauranga Bay of Plenty",
    "addr:street":"Seventeenth Ave",
    "iso:country":"NZ",
    "sg:address":"Compass Community Village Seventeenth Ave ",
    "sg:city":"Tauranga",
    "sg:classifiers":[
        {
            "category":"Wholesale",
            "subcategory":"Medical Equipment & Supplies",
            "type":"Manufacturing & Wholesale Goods"
        }
    ],
    "sg:phone":"+64 7-578 2929",
    "sg:province":"Bay of Plenty",
    "sg:tags":[
        "health",
        "disability",
        "products",
        "beauty",
        "aid"
    ],
    "wof:name":"Disability Information Service Centre Inc",
    "wof:placetype":"venue"
},
  "geometry": {"coordinates":[176.15922499999999,-37.711418],"type":"Point"}
}