{
  "type": "Feature",
  "properties": {
    "addr:full":"PO Box 11091 Sockburn  Halswell Canterbury",
    "addr:housenumber":"po box",
    "addr:street":"11091 Sockburn",
    "iso:country":"NZ",
    "sg:address":"PO Box 11091 Sockburn ",
    "sg:city":"Halswell",
    "sg:classifiers":[
        {
            "category":"Manufacturing",
            "subcategory":"Glass & Minerals",
            "type":"Manufacturing & Wholesale Goods"
        }
    ],
    "sg:phone":"+64 3-322 6325",
    "sg:province":"Canterbury",
    "sg:tags":[
        "chemical",
        "paint",
        "industrial",
        "manufacturer",
        "compounds"
    ],
    "wof:name":"Agrippa Paints",
    "wof:placetype":"venue"
},
  "geometry": {"coordinates":[172.55044599999999,-43.534962],"type":"Point"}
}