{
  "type": "Feature",
  "properties": {
    "iso:country":"NZ",
    "sg:address":"David Forman Hse 134 Queens Dve Lower ",
    "sg:city":"Hutt",
    "sg:classifiers":[
        {
            "category":"Food Court",
            "type":"Food & Drink"
        }
    ],
    "sg:phone":"+64 4-560 3300",
    "sg:province":"Wellington",
    "sg:tags":[
        "packer",
        "processing",
        "processor"
    ],
    "wof:name":"Heinz-Wattie Ltd",
    "wof:placetype":"venue"
},
  "geometry": {"coordinates":[174.904526,-41.208431],"type":"Point"}
}