{
  "type": "Feature",
  "properties": {
    "iso:country":"NZ",
    "sg:address":"66 Peel St ",
    "sg:city":"Gisborne",
    "sg:orig_category":"Home And Garden: Accessories: Linen",
    "sg:phone":"+64 6-868 8986",
    "sg:province":"Gisborne",
    "wof:name":"Bay Beds Gisborne",
    "wof:placetype":"venue"
},
  "geometry": {"coordinates":[178.02565000000001,-38.666859],"type":"Point"}
}