{
  "type": "Feature",
  "properties": {
    "iso:country":"NZ",
    "sg:address":"23-25 Buchan St Sydenham ",
    "sg:city":"Christchurch",
    "sg:classifiers":[
        {
            "category":"Shopping",
            "type":"Retail Goods"
        }
    ],
    "sg:phone":"+64 3-377 0235",
    "sg:province":"Canterbury",
    "sg:tags":[
        "chemical",
        "industrial",
        "cleaning",
        "maintenance"
    ],
    "wof:name":"Kleenwash Supplies",
    "wof:placetype":"venue"
},
  "geometry": {"coordinates":[172.638153,-43.546127],"type":"Point"}
}