{
  "type": "Feature",
  "properties": {
    "iso:country":"NZ",
    "sg:address":"53 Childers Tce Kilbirnie ",
    "sg:city":"Wellington",
    "sg:classifiers":[
        {
            "category":"Education",
            "subcategory":"Dance Studio",
            "type":"Public Place"
        }
    ],
    "sg:phone":"+64 4-934 9769",
    "sg:province":"Wellington",
    "sg:tags":[
        "school",
        "dancing",
        "-",
        "leisure",
        "sports",
        "sport"
    ],
    "wof:name":"Jean Goodman Dance Studios",
    "wof:placetype":"venue"
},
  "geometry": {"coordinates":[174.79341099999999,-41.319092],"type":"Point"}
}