{
  "type": "Feature",
  "properties": {
    "addr:full":"Avondale  Auckland Auckland",
    "iso:country":"NZ",
    "sg:address":"Avondale ",
    "sg:city":"Auckland",
    "sg:classifiers":[
        {
            "category":"Arts & Performance",
            "subcategory":"Music",
            "type":"Entertainment"
        }
    ],
    "sg:phone":"+64 9-828 9384",
    "sg:province":"Auckland",
    "sg:tags":[
        "mobile",
        "sport",
        "-",
        "leisure",
        "disco"
    ],
    "wof:name":"Black Or White Auckland Mobile DJ Services",
    "wof:placetype":"venue"
},
  "geometry": {"coordinates":[174.696991,-36.89856],"type":"Point"}
}