{
  "type": "Feature",
  "properties": {
    "iso:country":"NZ",
    "sg:address":"Remuera Mall 319 Remuera Rd Remuera ",
    "sg:city":"Auckland",
    "sg:classifiers":[
        {
            "category":"Shopping",
            "subcategory":"Hobbies, Toys, & Games",
            "type":"Retail Goods"
        }
    ],
    "sg:phone":"+64 9-524 4973",
    "sg:province":"Auckland",
    "sg:tags":[
        "hobby"
    ],
    "sg:website":"http://www.thegiftroom.co.nz",
    "wof:name":"Lladro Gallery The",
    "wof:placetype":"venue"
},
  "geometry": {"coordinates":[174.808868,-36.869381],"type":"Point"}
}