{
  "type": "Feature",
  "properties": {
    "addr:full":"20 Wear St  Oamaru Otago",
    "addr:housenumber":"20",
    "addr:street":"Wear St",
    "iso:country":"NZ",
    "sg:address":"20 Wear St ",
    "sg:city":"Oamaru",
    "sg:classifiers":[
        {
            "category":"Health Services",
            "subcategory":"Dentist",
            "type":"Services"
        }
    ],
    "sg:phone":"+64 3-434 9111",
    "sg:province":"Otago",
    "sg:tags":[
        "dental",
        "beauty"
    ],
    "wof:name":"Dodd Graeme J B.D.S",
    "wof:placetype":"venue"
},
  "geometry": {"coordinates":[170.97126800000001,-45.098721],"type":"Point"}
}