{
  "type": "Feature",
  "properties": {
    "iso:country":"NZ",
    "sg:address":"PO Box 43088 Wainuiomata Lower ",
    "sg:city":"Hutt",
    "sg:classifiers":[
        {
            "category":"Banks & Credit Unions",
            "subcategory":"Investment Brokerage",
            "type":"Services"
        }
    ],
    "sg:phone":"+64 4-564 5216",
    "sg:province":"Wellington",
    "sg:tags":[
        "chemical",
        "industrial",
        "-",
        "compounds"
    ],
    "wof:name":"CHEM 2000",
    "wof:placetype":"venue"
},
  "geometry": {"coordinates":[174.95083600000001,-41.261421],"type":"Point"}
}