{
  "type": "Feature",
  "properties": {
    "addr:full":"Mobile Service  Napier Hawke's Bay",
    "iso:country":"NZ",
    "sg:address":"Mobile Service ",
    "sg:city":"Napier",
    "sg:orig_category":"Home And Garden: Accessories: Kitchenware",
    "sg:phone":"+64 6-844 8814",
    "sg:province":"Hawke's Bay",
    "wof:name":"Mister Sharp",
    "wof:placetype":"venue"
},
  "geometry": {"coordinates":[-80.588562,38.790821],"type":"Point"}
}