{
  "type": "Feature",
  "properties": {
    "addr:full":"Waitikiri Dve Burwood  Christchurch Canterbury",
    "addr:street":"Dve",
    "iso:country":"NZ",
    "sg:address":"Waitikiri Dve Burwood ",
    "sg:city":"Christchurch",
    "sg:orig_category":"Sports And Leisure: Sports: Golf",
    "sg:phone":"+64 3-383 0729",
    "sg:province":"Canterbury",
    "wof:name":"Waitikiri Golf Club",
    "wof:placetype":"venue"
},
  "geometry": {"coordinates":[172.68199200000001,-43.494564],"type":"Point"}
}