{
  "type": "Feature",
  "properties": {
    "iso:country":"NZ",
    "sg:address":"1st Floor 10 Kingdon St Newmarket ",
    "sg:city":"Auckland",
    "sg:orig_category":"Sports And Leisure: Sports: Golf",
    "sg:phone":"+64 9-529 1930",
    "sg:province":"Auckland",
    "sg:website":"http://www.thegolfhouse.co.nz",
    "wof:name":"The Golf House Ltd",
    "wof:placetype":"venue"
},
  "geometry": {"coordinates":[174.776733,-36.866398],"type":"Point"}
}