{
  "type": "Feature",
  "properties": {
    "addr:full":"933 New North Rd Mt Albert  Auckland Auckland",
    "addr:housenumber":"933",
    "addr:street":"New North Rd",
    "iso:country":"NZ",
    "sg:address":"933 New North Rd Mt Albert ",
    "sg:city":"Auckland",
    "sg:classifiers":[
        {
            "category":"Internet Cafe",
            "subcategory":"None",
            "type":"Food & Drink"
        }
    ],
    "sg:phone":"+64 9-815 8288",
    "sg:province":"Auckland",
    "sg:tags":[
        "wining",
        "dining"
    ],
    "wof:name":"Cyber City",
    "wof:placetype":"venue"
},
  "geometry": {"coordinates":[174.713257,-36.886093],"type":"Point"}
}