{
  "type": "Feature",
  "properties": {
    "iso:country":"NZ",
    "sg:address":"PO Box 300-003 Albany ",
    "sg:city":"Auckland",
    "sg:orig_category":"Industrial: Parts: Valves",
    "sg:phone":"+64 9-414 1028",
    "sg:province":"Auckland",
    "wof:name":"Process Solutions Ltd",
    "wof:placetype":"venue"
},
  "geometry": {"coordinates":[174.770416,-36.884109],"type":"Point"}
}