{
  "type": "Feature",
  "properties": {
    "addr:full":"458 Manchester St St Albans  Christchurch Canterbury",
    "addr:housenumber":"458",
    "addr:street":"Manchester St",
    "iso:country":"NZ",
    "sg:address":"458 Manchester St St Albans ",
    "sg:city":"Christchurch",
    "sg:classifiers":[
        {
            "category":"Education",
            "subcategory":"Music School",
            "type":"Public Place"
        }
    ],
    "sg:phone":"+64 3-366 8541",
    "sg:province":"Canterbury",
    "sg:tags":[
        "sport",
        "teacher",
        "leisure"
    ],
    "wof:name":"Sing It",
    "wof:placetype":"venue"
},
  "geometry": {"coordinates":[172.63980100000001,-43.516521],"type":"Point"}
}