{
  "type": "Feature",
  "properties": {
    "addr:full":"Goldfields Shopping Centre Queen St  Thames Auckland",
    "addr:street":"Queen St",
    "iso:country":"NZ",
    "sg:address":"Goldfields Shopping Centre Queen St ",
    "sg:city":"Thames",
    "sg:orig_category":"Shopping: Retail Stores: Department Stores",
    "sg:phone":"+64 7-868 9666",
    "sg:province":"Auckland",
    "wof:name":"The Warehouse Ltd",
    "wof:placetype":"venue"
},
  "geometry": {"coordinates":[151.699219,-28.449089],"type":"Point"}
}