{
  "type": "Feature",
  "properties": {
    "iso:country":"NZ",
    "sg:address":"251 Stafford St ",
    "sg:city":"Timaru",
    "sg:classifiers":[
        {
            "category":"Bars & Pubs",
            "subcategory":"Wine Bar",
            "type":"Food & Drink"
        }
    ],
    "sg:phone":"+64 3-684 7711",
    "sg:province":"Canterbury",
    "sg:tags":[
        "wining",
        "dining",
        "cafe"
    ],
    "wof:name":"Touch of Kiwi",
    "wof:placetype":"venue"
},
  "geometry": {"coordinates":[171.252045,-44.394726],"type":"Point"}
}