{
  "type": "Feature",
  "properties": {
    "addr:full":"Central Pacific House 396 Great North Rd Henderson Auckland Auckland",
    "addr:housenumber":"396",
    "addr:street":"Great North Rd",
    "iso:country":"NZ",
    "sg:address":"Central Pacific House 396 Great North Rd Henderson",
    "sg:city":"Auckland",
    "sg:classifiers":[
        {
            "category":"Banks & Credit Unions",
            "subcategory":"Financial Services",
            "type":"Services"
        }
    ],
    "sg:phone":"+64 9-835 0331",
    "sg:province":"Auckland",
    "sg:tags":[
        "lender",
        "money",
        "-",
        "finance",
        "personal"
    ],
    "wof:name":"Central Pacific Finance Ltd",
    "wof:placetype":"venue"
},
  "geometry": {"coordinates":[174.63294999999999,-36.877289],"type":"Point"}
}