{
  "type": "Feature",
  "properties": {
    "iso:country":"NZ",
    "sg:address":"158 Tay St ",
    "sg:city":"Invercargill",
    "sg:orig_category":"Food And Drink: Catering: Caterers",
    "sg:phone":"+64 3-218 4648",
    "sg:province":"Southland",
    "wof:name":"Sandwich Supplies",
    "wof:placetype":"venue"
},
  "geometry": {"coordinates":[168.380325,-46.40926],"type":"Point"}
}