{
  "type": "Feature",
  "properties": {
    "addr:full":"Peterson Rd R D 2 Papakura  Auckland Auckland",
    "addr:housenumber":"2",
    "addr:street":"Peterson Rd R D",
    "iso:country":"NZ",
    "sg:address":"Peterson Rd R D 2 Papakura ",
    "sg:city":"Auckland",
    "sg:classifiers":[
        {
            "category":"Home & Garden",
            "subcategory":"Building Materials",
            "type":"Retail Goods"
        }
    ],
    "sg:phone":"+64 9-299 8132",
    "sg:province":"Auckland",
    "sg:tags":[
        "builder",
        "related"
    ],
    "wof:name":"Ardmore Ostrich Farms Ltd",
    "wof:placetype":"venue"
},
  "geometry": {"coordinates":[174.95945699999999,-37.059521],"type":"Point"}
}