{
  "type": "Feature",
  "properties": {
    "iso:country":"NZ",
    "sg:address":"30 Kokiri St Te Atatu ",
    "sg:city":"South",
    "sg:classifiers":[
        {
            "category":"Sports & Exercise",
            "subcategory":"Swimming Pool",
            "type":"Entertainment"
        }
    ],
    "sg:phone":"+64 252863970",
    "sg:province":"Auckland",
    "sg:tags":[
        "home",
        "outdoor",
        "garden",
        "spa"
    ],
    "wof:name":"Pool Maintenence Company",
    "wof:placetype":"venue"
},
  "geometry": {"coordinates":[174.648865,-36.862682],"type":"Point"}
}