{
  "type": "Feature",
  "properties": {
    "addr:full":"178 Lincoln Rd Henderson  Auckland Auckland",
    "addr:housenumber":"178",
    "addr:street":"Lincoln Rd",
    "iso:country":"NZ",
    "sg:address":"178 Lincoln Rd Henderson ",
    "sg:city":"Auckland",
    "sg:classifiers":[
        {
            "category":"Personal",
            "subcategory":"Tattoo Parlor",
            "type":"Services"
        }
    ],
    "sg:phone":"+64 9-835 1277",
    "sg:province":"Auckland",
    "sg:tags":[
        "services",
        "home",
        "tattooists",
        "garden"
    ],
    "sg:website":"http://eurotattoo.co.nz",
    "wof:name":"Monique's Euro Tattoo Studio",
    "wof:placetype":"venue"
},
  "geometry": {"coordinates":[174.62823499999999,-36.870419],"type":"Point"}
}