{
  "type": "Feature",
  "properties": {
    "addr:full":"Kaitaia Plaza  Kaitaia Northland",
    "iso:country":"NZ",
    "sg:address":"Kaitaia Plaza ",
    "sg:city":"Kaitaia",
    "sg:classifiers":[
        {
            "category":"Shopping",
            "subcategory":"Pharmacy",
            "type":"Retail Goods"
        }
    ],
    "sg:phone":"+64 9-408 2606",
    "sg:province":"Northland",
    "sg:tags":[
        "product",
        "health"
    ],
    "wof:name":"It's Healthy Wholefoods",
    "wof:placetype":"venue"
},
  "geometry": {"coordinates":[173.259445,-35.114212],"type":"Point"}
}