{
  "type": "Feature",
  "properties": {
    "addr:full":"97 Liverpool St  Wanganui Manawatu-Wanganui",
    "addr:housenumber":"97",
    "addr:street":"Liverpool St",
    "iso:country":"NZ",
    "sg:address":"97 Liverpool St ",
    "sg:city":"Wanganui",
    "sg:classifiers":[
        {
            "category":"Professional",
            "subcategory":"Art Services",
            "type":"Services"
        }
    ],
    "sg:phone":"+64 6-347 1071",
    "sg:province":"Manawatu-Wanganui",
    "sg:tags":[
        "personal",
        "photographer",
        "services",
        "garden",
        "home"
    ],
    "wof:name":"Capture Photography",
    "wof:placetype":"venue"
},
  "geometry": {"coordinates":[175.03929099999999,-39.929123],"type":"Point"}
}