{
  "type": "Feature",
  "properties": {
    "iso:country":"NZ",
    "sg:address":"39 Lake Rd ",
    "sg:city":"Hamilton",
    "sg:classifiers":[
        {
            "category":"Home & Garden",
            "subcategory":"Home Furnishings",
            "type":"Retail Goods"
        }
    ],
    "sg:phone":"+64 7-847 2246",
    "sg:province":"Waikato",
    "sg:tags":[
        "furniture/furnishings",
        "product",
        "cane"
    ],
    "wof:name":"Cane Factory & Upholstery Shop",
    "wof:placetype":"venue"
},
  "geometry": {"coordinates":[-75.535759,42.831093],"type":"Point"}
}