{
  "type": "Feature",
  "properties": {
    "iso:country":"NZ",
    "sg:address":"Level 4 120 The Terrace ",
    "sg:city":"Wellington",
    "sg:classifiers":[
        {
            "category":"Sports & Exercise",
            "subcategory":"Athletic Track",
            "type":"Entertainment"
        }
    ],
    "sg:phone":"+64 4-499 5950",
    "sg:province":"Waikato",
    "sg:tags":[
        "machine",
        "gaming",
        "leisure"
    ],
    "wof:name":"Cascade Consulting Ltd",
    "wof:placetype":"venue"
},
  "geometry": {"coordinates":[-82.181892,41.14233],"type":"Point"}
}