{
  "type": "Feature",
  "properties": {
    "addr:full":"Cnr Lambton Quay & Hunter  Sts Wellington",
    "addr:street":"Cnr Lambton",
    "iso:country":"NZ",
    "sg:address":"Cnr Lambton Quay & Hunter ",
    "sg:city":"Sts",
    "sg:classifiers":[
        {
            "category":"Travel",
            "subcategory":"Hotels & Motels",
            "type":"Entertainment"
        }
    ],
    "sg:phone":"+64 800 802 123",
    "sg:province":"Wellington",
    "sg:tags":[
        "tavern",
        "tourism",
        "accommodation"
    ],
    "wof:name":"Quest Apartments New Zealand",
    "wof:placetype":"venue"
},
  "geometry": {"coordinates":[-82.28636899999999,42.845188],"type":"Point"}
}