{
  "type": "Feature",
  "properties": {
    "iso:country":"NZ",
    "sg:address":"R D 2 ",
    "sg:city":"Otautau",
    "sg:orig_category":"Farming: Services: Livestock Related: Sheep Dipping",
    "sg:phone":"+64 3-225 8301",
    "wof:name":"Booth Agricultural Spraying & Dipping",
    "wof:placetype":"venue"
},
  "geometry": {"coordinates":[167.998795,-46.142715],"type":"Point"}
}