{
  "type": "Feature",
  "properties": {
    "addr:full":"473 Papanui Rd Papanui  Christchurch Canterbury",
    "addr:housenumber":"473",
    "addr:street":"Papanui Rd",
    "iso:country":"NZ",
    "sg:address":"473 Papanui Rd Papanui ",
    "sg:city":"Christchurch",
    "sg:classifiers":[
        {
            "category":"Sports & Exercise",
            "subcategory":"Bowling",
            "type":"Entertainment"
        }
    ],
    "sg:phone":"+64 3-354 3530",
    "sg:province":"Canterbury",
    "sg:tags":[
        "party",
        "leisure",
        "supply"
    ],
    "wof:name":"Pinata Party",
    "wof:placetype":"venue"
},
  "geometry": {"coordinates":[172.60934399999999,-43.498814],"type":"Point"}
}