{
  "type": "Feature",
  "properties": {
    "addr:full":"24 Hannigan Dve Mt Wellington  Auckland Auckland",
    "addr:housenumber":"24",
    "addr:street":"Hannigan Dve",
    "iso:country":"NZ",
    "sg:address":"24 Hannigan Dve Mt Wellington ",
    "sg:city":"Auckland",
    "sg:classifiers":[
        {
            "category":"Banks & Credit Unions",
            "subcategory":"Investment Brokerage",
            "type":"Services"
        }
    ],
    "sg:phone":"+64 9-570 2125",
    "sg:province":"Auckland",
    "sg:tags":[
        "industrial",
        "cleaning",
        "maintenance"
    ],
    "wof:name":"James Products Ltd",
    "wof:placetype":"venue"
},
  "geometry": {"coordinates":[174.83029199999999,-36.909569],"type":"Point"}
}