{
  "type": "Feature",
  "properties": {
    "addr:full":"99-107 Khyber Pass Road, Grafton  Auckland Auckland",
    "addr:postcode":"99-107",
    "addr:street":"Pass Road",
    "iso:country":"NZ",
    "sg:address":"99-107 Khyber Pass Road, Grafton ",
    "sg:city":"Auckland",
    "sg:classifiers":[
        {
            "category":"Shopping",
            "subcategory":"Beauty & Cosmetics",
            "type":"Retail Goods"
        }
    ],
    "sg:phone":"+64 9-373 1280",
    "sg:province":"Auckland",
    "sg:tags":[
        "health",
        "perfumery"
    ],
    "wof:name":"Nu Skin New Zealand Inc",
    "wof:placetype":"venue"
},
  "geometry": {"coordinates":[174.764557,-36.864925],"type":"Point"}
}