{
  "type": "Feature",
  "properties": {
    "iso:country":"NZ",
    "sg:address":"47 Victor St Avondale ",
    "sg:city":"Auckland",
    "sg:orig_category":"Education And Training: General: Schools",
    "sg:phone":"+64 9-828 7024",
    "sg:province":"Auckland",
    "wof:name":"Avondale College",
    "wof:placetype":"venue"
},
  "geometry": {"coordinates":[174.690979,-36.891769],"type":"Point"}
}