{
  "type": "Feature",
  "properties": {
    "addr:full":"11 Vedders Rd Rd2 Ohiwa Harbour  Opotiki",
    "addr:housenumber":"11",
    "addr:street":"Vedders Rd Rd2 Ohiwa Harbour",
    "iso:country":"NZ",
    "sg:address":"11 Vedders Rd Rd2 Ohiwa Harbour ",
    "sg:city":"Opotiki",
    "sg:classifiers":[
        {
            "category":"Autos & Motor Vehicles",
            "subcategory":"Automobile Sales",
            "type":"Retail Goods"
        }
    ],
    "sg:phone":"+64 7-315 4606",
    "sg:tags":[
        "home",
        "caravan",
        "leasing",
        "automotive"
    ],
    "wof:name":"Camper & Motor Home Hire",
    "wof:placetype":"venue"
},
  "geometry": {"coordinates":[177.15867600000001,-37.989239],"type":"Point"}
}