{
  "type": "Feature",
  "properties": {
    "iso:country":"NZ",
    "sg:address":"1st Floor 99-101 Willis St ",
    "sg:city":"Wellington",
    "sg:classifiers":[
        {
            "category":"Personal",
            "subcategory":"Beauty Salon",
            "type":"Services"
        }
    ],
    "sg:phone":"+64 4-499 1771",
    "sg:province":"Wellington",
    "sg:tags":[
        "artist",
        "health",
        "make-up"
    ],
    "wof:name":"Essence Beauty Therapy For Men & Women",
    "wof:placetype":"venue"
},
  "geometry": {"coordinates":[-85.910454,33.827946],"type":"Point"}
}