{
  "type": "Feature",
  "properties": {
    "iso:country":"NZ",
    "sg:address":"26 Broughton St South Dunedin ",
    "sg:city":"Dunedin",
    "sg:classifiers":[
        {
            "category":"Professional",
            "type":"Services"
        }
    ],
    "sg:phone":"+64 3-455 3988",
    "sg:province":"Otago",
    "sg:tags":[
        "services",
        "car",
        "valet",
        "automotive"
    ],
    "wof:name":"A1 Auto Groomers",
    "wof:placetype":"venue"
},
  "geometry": {"coordinates":[170.500595,-45.893661],"type":"Point"}
}