{
  "type": "Feature",
  "properties": {
    "iso:country":"NZ",
    "sg:address":"PO Box 12977 Penrose ",
    "sg:city":"Auckland",
    "sg:classifiers":[
        {
            "category":"Home & Garden",
            "subcategory":"Carpets & Floor Coverings",
            "type":"Retail Goods"
        }
    ],
    "sg:phone":"+64 9-636 1320",
    "sg:province":"Auckland",
    "sg:tags":[
        "cleaning",
        "furniture"
    ],
    "wof:name":"Enviro Clean & Restoration Ltd",
    "wof:placetype":"venue"
},
  "geometry": {"coordinates":[174.81016500000001,-36.911617],"type":"Point"}
}