{
  "type": "Feature",
  "properties": {
    "addr:full":"PO Box 15-706 New Lynn  Auckland Auckland",
    "addr:housenumber":"po box",
    "addr:street":"15-706",
    "iso:country":"NZ",
    "sg:address":"PO Box 15-706 New Lynn ",
    "sg:city":"Auckland",
    "sg:classifiers":[
        {
            "category":"Shopping",
            "subcategory":"Computers & Home Electronics",
            "type":"Retail Goods"
        }
    ],
    "sg:phone":"+64 9-627 2395",
    "sg:province":"Auckland",
    "sg:tags":[
        "equipment",
        "sport",
        "leisure",
        "entertainment"
    ],
    "wof:name":"Funco Promotions",
    "wof:placetype":"venue"
},
  "geometry": {"coordinates":[174.68308999999999,-36.920143],"type":"Point"}
}