{
  "type": "Feature",
  "properties": {
    "iso:country":"NZ",
    "sg:address":"21 Manchester St Melrose ",
    "sg:city":"Wellington",
    "sg:classifiers":[
        {
            "category":"Travel",
            "subcategory":"Hotels & Motels",
            "type":"Entertainment"
        }
    ],
    "sg:phone":"+64 4-389 9011",
    "sg:province":"Wellington",
    "sg:tags":[
        "lodge",
        "tourism",
        "accommodation"
    ],
    "sg:website":"http://capitalhouse.virtualave.net",
    "wof:name":"Capital House Conference & Accommodation Centre",
    "wof:placetype":"venue"
},
  "geometry": {"coordinates":[174.78772,-41.322273],"type":"Point"}
}