{
  "type": "Feature",
  "properties": {
    "iso:country":"NZ",
    "sg:address":"131 Middle Renwick Rd ",
    "sg:city":"Blenheim",
    "sg:classifiers":[
        {
            "category":"Home & Garden",
            "subcategory":"Garden Supply",
            "type":"Retail Goods"
        }
    ],
    "sg:phone":"+64 3-578 4353",
    "sg:province":"Marlborough",
    "sg:tags":[
        "products",
        "nursery",
        "gardening"
    ],
    "wof:name":"Springlands Garden Centre & Cafe",
    "wof:placetype":"venue"
},
  "geometry": {"coordinates":[173.924408,-41.50964],"type":"Point"}
}