{
  "type": "Feature",
  "properties": {
    "iso:country":"NZ",
    "sg:address":"6 Princes St PO Box 12125 ",
    "sg:city":"Hamilton",
    "sg:classifiers":[
        {
            "category":"Banks & Credit Unions",
            "subcategory":"Financial Services",
            "type":"Services"
        }
    ],
    "sg:phone":"+64 800 438 666",
    "sg:province":"Waikato",
    "sg:tags":[
        "finance"
    ],
    "sg:website":"http://www.yellowpages.co.nz/pages/215298376/dp22863.html",
    "wof:name":"Mortgage Link Paris Mortgage Services",
    "wof:placetype":"venue"
},
  "geometry": {"coordinates":[-87.988968,34.142426],"type":"Point"}
}