{
  "type": "Feature",
  "properties": {
    "iso:country":"NZ",
    "sg:address":"31 Horomatangi St ",
    "sg:city":"Taupo",
    "sg:orig_category":"Shopping: Retail Stores: Books: Bookshops",
    "sg:phone":"+64 7-378 9966",
    "sg:province":"Waikato",
    "wof:name":"Whitcoulls",
    "wof:placetype":"venue"
},
  "geometry": {"coordinates":[176.07107500000001,-38.686977],"type":"Point"}
}