{
  "type": "Feature",
  "properties": {
    "iso:country":"NZ",
    "sg:address":"6 Russell St Upper ",
    "sg:city":"Hutt",
    "sg:orig_category":"Shopping: Retail Stores: Antiques",
    "sg:phone":"+64 4-527 8398",
    "sg:province":"Wellington",
    "wof:name":"Lion Bazaar",
    "wof:placetype":"venue"
},
  "geometry": {"coordinates":[175.07221999999999,-41.124947],"type":"Point"}
}