{
  "type": "Feature",
  "properties": {
    "iso:country":"NZ",
    "sg:address":"Wellington Airport Rongotai ",
    "sg:city":"Wellington",
    "sg:classifiers":[
        {
            "category":"Airport",
            "type":"Transportation"
        }
    ],
    "sg:phone":"+64 4-387 3712",
    "sg:province":"Wellington",
    "sg:tags":[
        "aircraft",
        "transport",
        "sale",
        "maintenance",
        "air"
    ],
    "wof:name":"Aviation Radio Ltd",
    "wof:placetype":"venue"
},
  "geometry": {"coordinates":[174.803177,-41.324219],"type":"Point"}
}