{
  "type": "Feature",
  "properties": {
    "addr:full":"PO Box 19723 Woolston  Christchurch Canterbury",
    "addr:housenumber":"po box 19723;christchurch",
    "iso:country":"NZ",
    "sg:address":"PO Box 19723 Woolston ",
    "sg:city":"Christchurch",
    "sg:classifiers":[
        {
            "category":"Shopping",
            "subcategory":"Gifts & Souvenirs",
            "type":"Retail Goods"
        }
    ],
    "sg:phone":"+64 3-381 0519",
    "sg:province":"Canterbury",
    "sg:tags":[
        "travel",
        "tourism"
    ],
    "wof:name":"Tarata",
    "wof:placetype":"venue"
},
  "geometry": {"coordinates":[172.677719,-43.54937],"type":"Point"}
}