{
  "type": "Feature",
  "properties": {
    "addr:full":"70 Hunua Rd Papakura  Auckland Auckland",
    "addr:housenumber":"70",
    "addr:street":"Hunua Rd",
    "iso:country":"NZ",
    "sg:address":"70 Hunua Rd Papakura ",
    "sg:city":"Auckland",
    "sg:classifiers":[
        {
            "category":"Home & Garden",
            "subcategory":"Building Materials",
            "type":"Retail Goods"
        }
    ],
    "sg:phone":"+64 9-296 0200",
    "sg:province":"Auckland",
    "sg:tags":[
        "door",
        "fitting",
        "fittings"
    ],
    "wof:name":"Nationwide Prehung Doors Ltd",
    "wof:placetype":"venue"
},
  "geometry": {"coordinates":[174.96386699999999,-37.074951],"type":"Point"}
}