{
  "type": "Feature",
  "properties": {
    "addr:full":"741 Beach Rd Browns Bay  Auckland Auckland",
    "addr:housenumber":"741",
    "addr:street":"Beach Rd",
    "iso:country":"NZ",
    "sg:address":"741 Beach Rd Browns Bay ",
    "sg:city":"Auckland",
    "sg:classifiers":[
        {
            "category":"Retail",
            "subcategory":"Auto Repair",
            "type":"Services"
        }
    ],
    "sg:phone":"+64 9-476 0032",
    "sg:province":"Auckland",
    "sg:tags":[
        "wheel",
        "automotive",
        "servicing",
        "alignment"
    ],
    "wof:name":"Discount Tyres",
    "wof:placetype":"venue"
},
  "geometry": {"coordinates":[174.74311800000001,-36.718365],"type":"Point"}
}