{
  "type": "Feature",
  "properties": {
    "iso:country":"NZ",
    "sg:address":"182 Hillside Rd South Dunedin ",
    "sg:city":"Dunedin",
    "sg:classifiers":[
        {
            "category":"Sports & Exercise",
            "subcategory":"Playing Field",
            "type":"Entertainment"
        }
    ],
    "sg:phone":"+64 3-455 3246",
    "sg:province":"Otago",
    "sg:tags":[
        "hobby",
        "hobbies",
        "leisure",
        "supply"
    ],
    "wof:name":"Clint's Auto Repairs & Sales LMVD",
    "wof:placetype":"venue"
},
  "geometry": {"coordinates":[170.497253,-45.893593],"type":"Point"}
}