{
  "type": "Feature",
  "properties": {
    "addr:full":"Unit B 1 Lowther St Sockburn  Christchurch Canterbury",
    "addr:housenumber":"1",
    "addr:street":"Lowther St",
    "iso:country":"NZ",
    "sg:address":"Unit B 1 Lowther St Sockburn ",
    "sg:city":"Christchurch",
    "sg:orig_category":"Automotive: Servicing And Repair: Car Trimming/Upholstery",
    "sg:phone":"+64 3-348 4233",
    "sg:province":"Canterbury",
    "wof:name":"Hornby Car Upholstery",
    "wof:placetype":"venue"
},
  "geometry": {"coordinates":[172.55043000000001,-43.534966],"type":"Point"}
}