{
  "type": "Feature",
  "properties": {
    "addr:full":"46 Taharoto Rd Takapuna  Auckland Auckland",
    "addr:housenumber":"46",
    "addr:street":"Taharoto Rd",
    "iso:country":"NZ",
    "sg:address":"46 Taharoto Rd Takapuna ",
    "sg:city":"Auckland",
    "sg:orig_category":"Clothing And Fabric: Fabric: Textiles",
    "sg:phone":"+64 800 777 345",
    "sg:province":"Auckland",
    "wof:name":"Marcrest Hotel Supply",
    "wof:placetype":"venue"
},
  "geometry": {"coordinates":[174.76101700000001,-36.789391],"type":"Point"}
}