{
  "type": "Feature",
  "properties": {
    "iso:country":"NZ",
    "sg:address":"31 Leslie Hills Dve Riccarton ",
    "sg:city":"Christchurch",
    "sg:orig_category":"Industrial: Electrical/Electronic: Electronic Equipment",
    "sg:phone":"+64 3-341 5166",
    "sg:province":"Canterbury",
    "wof:name":"EDAC Electronics Ltd",
    "wof:placetype":"venue"
},
  "geometry": {"coordinates":[172.60823099999999,-43.53368],"type":"Point"}
}