{
  "type": "Feature",
  "properties": {
    "iso:country":"NZ",
    "sg:address":"26 Esk St ",
    "sg:city":"Invercargill",
    "sg:classifiers":[
        {
            "category":"Shopping",
            "subcategory":"Shoes",
            "type":"Retail Goods"
        }
    ],
    "sg:phone":"+64 3-218 6816",
    "sg:province":"Southland",
    "sg:tags":[
        "foot",
        "clothing",
        "fabric",
        "wear"
    ],
    "wof:name":"Goodalls Footwear",
    "wof:placetype":"venue"
},
  "geometry": {"coordinates":[168.34783899999999,-46.411812],"type":"Point"}
}