{
  "type": "Feature",
  "properties": {
    "iso:country":"NZ",
    "sg:address":"189 The Strand ",
    "sg:city":"Whakatane",
    "sg:orig_category":"Health And Beauty: Products: Pharmacies",
    "sg:phone":"+64 7-308 6988",
    "sg:province":"Auckland",
    "wof:name":"Atmores Unichem Pharmacy",
    "wof:placetype":"venue"
},
  "geometry": {"coordinates":[176.99498,-37.951969],"type":"Point"}
}