{
  "type": "Feature",
  "properties": {
    "addr:full":"62 Otepuni Ave  Invercargill Wellington",
    "addr:housenumber":"62",
    "addr:street":"Otepuni Ave",
    "iso:country":"NZ",
    "sg:address":"62 Otepuni Ave ",
    "sg:city":"Invercargill",
    "sg:orig_category":"Automotive: Parts And Supplies: Automotive Dismantlers",
    "sg:phone":"+64 3-216 7905",
    "sg:province":"Wellington",
    "wof:name":"Ray's Auto Dismantlers",
    "wof:placetype":"venue"
},
  "geometry": {"coordinates":[168.38107299999999,-46.414204],"type":"Point"}
}