{
  "type": "Feature",
  "properties": {
    "iso:country":"NZ",
    "sg:address":"P O Box 29250, Christchurch ",
    "sg:city":"Wellington",
    "sg:classifiers":[
        {
            "category":"Building & Trades",
            "subcategory":"Landscaping Services",
            "type":"Services"
        }
    ],
    "sg:phone":"+64 4-472 5181",
    "sg:province":"Wellington",
    "sg:tags":[
        "personal",
        "home",
        "garden"
    ],
    "sg:website":"http://www.spielrein.co.nz",
    "wof:name":"Spielrein & Associate",
    "wof:placetype":"venue"
},
  "geometry": {"coordinates":[-85.910454,33.827946],"type":"Point"}
}