{
  "type": "Feature",
  "properties": {
    "addr:full":"63 Whakatiki St Upper  Hutt Wellington",
    "addr:housenumber":"63",
    "addr:street":"Whakatiki St",
    "iso:country":"NZ",
    "sg:address":"63 Whakatiki St Upper ",
    "sg:city":"Hutt",
    "sg:orig_category":"Storage: Storage",
    "sg:phone":"+64 800 447 878",
    "sg:province":"Wellington",
    "wof:name":"Whakatiki Safe Storage",
    "wof:placetype":"venue"
},
  "geometry": {"coordinates":[175.069031,-41.12458],"type":"Point"}
}