{
  "type": "Feature",
  "properties": {
    "addr:full":"Hunter Rd Eureka  Hamilton Waikato",
    "addr:street":"Hunter Rd",
    "iso:country":"NZ",
    "sg:address":"Hunter Rd Eureka ",
    "sg:city":"Hamilton",
    "sg:classifiers":[
        {
            "category":"Shopping",
            "subcategory":"Crafts & Fabrics",
            "type":"Retail Goods"
        }
    ],
    "sg:phone":"+64 7-824 1684",
    "sg:province":"Waikato",
    "sg:tags":[
        "merchant",
        "clothing",
        "hide",
        "skin"
    ],
    "wof:name":"Nichols (NZ) Ltd",
    "wof:placetype":"venue"
},
  "geometry": {"coordinates":[175.436813,-37.744522],"type":"Point"}
}