{
  "type": "Feature",
  "properties": {
    "iso:country":"NZ",
    "sg:address":"89 Thorndon Qy ",
    "sg:city":"Wellington",
    "sg:classifiers":[
        {
            "category":"Food & Beverages",
            "subcategory":"Groceries & Convenience Stores",
            "type":"Retail Goods"
        }
    ],
    "sg:phone":"+64 4-499 9595",
    "sg:province":"Wellington",
    "sg:tags":[
        "foodstuff",
        "drink",
        "-"
    ],
    "wof:name":"Abba Foods Marketing Ltd",
    "wof:placetype":"venue"
},
  "geometry": {"coordinates":[174.782822,-41.275467],"type":"Point"}
}