{
  "type": "Feature",
  "properties": {
    "addr:full":"89 Thorndon Qy  Wellington Wellington",
    "addr:housenumber":"89",
    "addr:street":"Thorndon Qy",
    "iso:country":"NZ",
    "sg:address":"89 Thorndon Qy ",
    "sg:city":"Wellington",
    "sg:classifiers":[
        {
            "category":"Food & Beverages",
            "subcategory":"Groceries & Convenience Stores",
            "type":"Retail Goods"
        }
    ],
    "sg:phone":"+64 4-499 9595",
    "sg:province":"Wellington",
    "sg:tags":[
        "foodstuff",
        "drink",
        "-"
    ],
    "wof:name":"Abba Foods Marketing Ltd",
    "wof:placetype":"venue"
},
  "geometry": {"coordinates":[174.78282200000001,-41.275467],"type":"Point"}
}