{
  "type": "Feature",
  "properties": {
    "addr:full":"2 Victoria St Alicetown  Wellington Wellington",
    "addr:housenumber":"2",
    "addr:street":"Victoria St",
    "iso:country":"NZ",
    "sg:address":"2 Victoria St Alicetown ",
    "sg:city":"Wellington",
    "sg:orig_category":"Industrial: Packaging: Paper And Cardboard",
    "sg:phone":"+64 4-939 7273",
    "sg:province":"Wellington",
    "wof:name":"Paper Source",
    "wof:placetype":"venue"
},
  "geometry": {"coordinates":[174.88769500000001,-41.218372],"type":"Point"}
}