{
  "type": "Feature",
  "properties": {
    "iso:country":"NZ",
    "sg:address":"Level 7 1 Fitzherbert Ave Palmerston ",
    "sg:city":"Palmerston North",
    "sg:orig_category":"Health And Beauty: Mental: Psychology",
    "sg:phone":"+64 6-353 2121",
    "sg:province":"Manawatu-Wanganui",
    "wof:name":"Laura Crymble Registered Psychologist",
    "wof:placetype":"venue"
},
  "geometry": {"coordinates":[175.612122,-40.357304],"type":"Point"}
}