{
  "type": "Feature",
  "properties": {
    "addr:full":"79 Walters Rd  Marshland",
    "addr:housenumber":"79",
    "addr:street":"Walters Rd",
    "iso:country":"NZ",
    "sg:address":"79 Walters Rd ",
    "sg:city":"Marshland",
    "sg:orig_category":"Home And Garden: Gardening: Products: Greenhouses And Shadehouses",
    "sg:phone":"+64 800 427 367",
    "wof:name":"Harford Greenhouses",
    "wof:placetype":"venue"
},
  "geometry": {"coordinates":[-123.32075500000001,46.114265],"type":"Point"}
}