{
  "type": "Feature",
  "properties": {
    "iso:country":"NZ",
    "sg:address":"Westfields Shoppingtown St'Lukes Mt Albert ",
    "sg:city":"Auckland",
    "sg:orig_category":"Shopping: Accessories: Sunglasses",
    "sg:phone":"+64 9-815 8045",
    "sg:province":"Auckland",
    "wof:name":"Sunglass Hut International",
    "wof:placetype":"venue"
},
  "geometry": {"coordinates":[174.714798,-36.88784],"type":"Point"}
}