{
  "type": "Feature",
  "properties": {
    "iso:country":"NZ",
    "sg:address":"370 Neilson St Te Papapa ",
    "sg:city":"Auckland",
    "sg:orig_category":"Industrial: Metal: Scrap Metal Dealers",
    "sg:phone":"+64 9-636 8628",
    "sg:province":"Auckland",
    "wof:name":"McCamish Metals",
    "wof:placetype":"venue"
},
  "geometry": {"coordinates":[174.809555,-36.925148],"type":"Point"}
}