{
  "type": "Feature",
  "properties": {
    "addr:full":"Nelson Creek Hotel Nelson Creek  Ngahere",
    "addr:street":"Nelson",
    "iso:country":"NZ",
    "sg:address":"Nelson Creek Hotel Nelson Creek ",
    "sg:city":"Ngahere",
    "sg:classifiers":[
        {
            "category":"Travel",
            "subcategory":"Hotels & Motels",
            "type":"Entertainment"
        }
    ],
    "sg:phone":"+64 3-732 4845",
    "sg:tags":[
        "tavern",
        "tourism",
        "accommodation"
    ],
    "wof:name":"Nelson Creek Hotel",
    "wof:placetype":"venue"
},
  "geometry": {"coordinates":[171.51828,-42.405891],"type":"Point"}
}