{
  "type": "Feature",
  "properties": {
    "iso:country":"NZ",
    "sg:address":"2 Charles St Kamo ",
    "sg:city":"Whangarei",
    "sg:classifiers":[
        {
            "category":"Arena",
            "subcategory":"Sports Club",
            "type":"Entertainment"
        }
    ],
    "sg:phone":"+64 9-435 5304",
    "sg:province":"Northland",
    "sg:tags":[
        "martial art",
        "-",
        "leisure",
        "sports"
    ],
    "wof:name":"Nam Wah Pai Kung Fu & Tai Chi",
    "wof:placetype":"venue"
},
  "geometry": {"coordinates":[174.306946,-35.679508],"type":"Point"}
}