{
  "type": "Feature",
  "properties": {
    "iso:country":"NZ",
    "sg:address":"79 Mackay St ",
    "sg:city":"Greymouth",
    "sg:orig_category":"Shopping: Retail Stores: Toys",
    "sg:phone":"+64 3-768 5758",
    "sg:province":"West Coast",
    "wof:name":"Toyworld",
    "wof:placetype":"venue"
},
  "geometry": {"coordinates":[171.210632,-42.448502],"type":"Point"}
}