{
  "type": "Feature",
  "properties": {
    "addr:full":"879 Downs Rd West Eyreton  Cust",
    "addr:housenumber":"879",
    "addr:street":"Downs Rd West;Cust",
    "iso:country":"NZ",
    "sg:address":"879 Downs Rd West Eyreton ",
    "sg:city":"Cust",
    "sg:classifiers":[
        {
            "category":"Food & Beverages",
            "subcategory":"Fruits & Vegetables",
            "type":"Retail Goods"
        }
    ],
    "sg:phone":"+64 3-312 5177",
    "sg:tags":[
        "product",
        "drink",
        "organic",
        "veges"
    ],
    "wof:name":"Whymor Organic Orchard",
    "wof:placetype":"venue"
},
  "geometry": {"coordinates":[172.381561,-43.31918],"type":"Point"}
}