{
  "type": "Feature",
  "properties": {
    "iso:country":"NZ",
    "sg:address":"6 Smarts Rd Hornby ",
    "sg:city":"Christchurch",
    "sg:classifiers":[
        {
            "category":"Retail",
            "subcategory":"Auto Repair",
            "type":"Services"
        }
    ],
    "sg:phone":"+64 3-344 2909",
    "sg:province":"Canterbury",
    "sg:tags":[
        "automotive",
        "absorber",
        "shock",
        "servicing"
    ],
    "wof:name":"Pit Stop",
    "wof:placetype":"venue"
},
  "geometry": {"coordinates":[172.53633099999999,-43.534431],"type":"Point"}
}