{
  "type": "Feature",
  "properties": {
    "iso:country":"NZ",
    "sg:address":"191 Bain St ",
    "sg:city":"Invercargill",
    "sg:orig_category":"Industrial: Abrasives: Abrasive Blasting",
    "sg:phone":"+64 25355169",
    "sg:province":"Southland",
    "wof:name":"Barnes Abrasive Blasting",
    "wof:placetype":"venue"
},
  "geometry": {"coordinates":[168.374588,-46.448273],"type":"Point"}
}