{
  "type": "Feature",
  "properties": {
    "addr:full":"120 Church St Onehunga  Auckland Auckland",
    "addr:housenumber":"120",
    "addr:street":"Church St",
    "iso:country":"NZ",
    "sg:address":"120 Church St Onehunga ",
    "sg:city":"Auckland",
    "sg:classifiers":[
        {
            "category":"Personal",
            "subcategory":"Tanning Parlor",
            "type":"Services"
        }
    ],
    "sg:phone":"+64 9-634 1879",
    "sg:province":"Auckland",
    "sg:tags":[
        "sun",
        "health",
        "beauty"
    ],
    "wof:name":"Hotheads",
    "wof:placetype":"venue"
},
  "geometry": {"coordinates":[174.787384,-36.922615],"type":"Point"}
}