{
  "type": "Feature",
  "properties": {
    "iso:country":"NZ",
    "sg:address":"119 Hukanui Rd ",
    "sg:city":"Hamilton",
    "sg:classifiers":[
        {
            "category":"Education",
            "subcategory":"Special Training",
            "type":"Public Place"
        }
    ],
    "sg:phone":"+64 7-853 5013",
    "sg:province":"Waikato",
    "sg:tags":[
        "tutor",
        "coach",
        "teacher"
    ],
    "wof:name":"Kip McGrath Education Centres",
    "wof:placetype":"venue"
},
  "geometry": {"coordinates":[175.283096,-37.755547],"type":"Point"}
}