{
  "type": "Feature",
  "properties": {
    "iso:country":"NZ",
    "sg:address":"96 College St Palmerston ",
    "sg:city":"Palmerston North",
    "sg:classifiers":[
        {
            "category":"Health Services",
            "subcategory":"Health Practitioner",
            "type":"Services"
        }
    ],
    "sg:phone":"+64 6-355 0502",
    "sg:province":"Manawatu-Wanganui",
    "sg:tags":[
        "specialist",
        "medical",
        "beauty",
        "specialists"
    ],
    "wof:name":"Lombard Dr Stephan",
    "wof:placetype":"venue"
},
  "geometry": {"coordinates":[175.591873,-40.373089],"type":"Point"}
}