{
  "type": "Feature",
  "properties": {
    "addr:full":"State Highway 3  Wanganui Manawatu-Wanganui",
    "addr:street":"State Highway 3",
    "iso:country":"NZ",
    "sg:address":"State Highway 3 ",
    "sg:city":"Wanganui",
    "sg:classifiers":[
        {
            "category":"Manufacturing",
            "subcategory":"Food",
            "type":"Manufacturing & Wholesale Goods"
        }
    ],
    "sg:phone":"+64 6-348 8000",
    "sg:province":"Manawatu-Wanganui",
    "sg:tags":[
        "processing",
        "drink"
    ],
    "wof:name":"Rivercity Cold Storage & Processing",
    "wof:placetype":"venue"
},
  "geometry": {"coordinates":[175.031509,-39.93544],"type":"Point"}
}