{
  "type": "Feature",
  "properties": {
    "iso:country":"NZ",
    "sg:address":"Grafton Business Centre 6-8 Nugent St Grafton ",
    "sg:city":"Auckland",
    "sg:classifiers":[
        {
            "category":"Building & Trades",
            "subcategory":"Pest Control",
            "type":"Services"
        }
    ],
    "sg:phone":"+64 9-379 9711",
    "sg:province":"Auckland",
    "sg:tags":[
        "home",
        "garden"
    ],
    "wof:name":"Bugsaway Environmental Services Limited",
    "wof:placetype":"venue"
},
  "geometry": {"coordinates":[174.76547199999999,-36.862892],"type":"Point"}
}