{
  "type": "Feature",
  "properties": {
    "addr:full":"263 Hill Rd Eskdale  Napier Hawke's Bay",
    "addr:housenumber":"263",
    "addr:street":"Hill Rd",
    "iso:country":"NZ",
    "sg:address":"263 Hill Rd Eskdale ",
    "sg:city":"Napier",
    "sg:classifiers":[
        {
            "category":"Travel",
            "subcategory":"Bed & Breakfast",
            "type":"Entertainment"
        }
    ],
    "sg:phone":"+64 6-836 6666",
    "sg:province":"Hawke's Bay",
    "sg:tags":[
        "tourism",
        "accommodation"
    ],
    "wof:name":"The Grange",
    "wof:placetype":"venue"
},
  "geometry": {"coordinates":[176.85485800000001,-39.411442],"type":"Point"}
}