{
  "type": "Feature",
  "properties": {
    "addr:full":"Sunday Creek Rd  Thorpe",
    "addr:street":"Sunday Creek Rd",
    "iso:country":"NZ",
    "sg:address":"Sunday Creek Rd ",
    "sg:city":"Thorpe",
    "sg:classifiers":[
        {
            "category":"Shopping",
            "subcategory":"Pets & Pet Supplies",
            "type":"Retail Goods"
        }
    ],
    "sg:phone":"+64 3-543 3780",
    "sg:tags":[
        "boarding",
        "garden",
        "pets",
        "catteries",
        "home",
        "kennel"
    ],
    "wof:name":"Sunday Creek Rd Boarding Kennels",
    "wof:placetype":"venue"
},
  "geometry": {"coordinates":[-81.519226,37.369015],"type":"Point"}
}