{
  "type": "Feature",
  "properties": {
    "addr:full":"710 Karamu Rd Nth  Hastings Hawke's Bay",
    "addr:housenumber":"710",
    "addr:street":"Karamu Rd",
    "iso:country":"NZ",
    "sg:address":"710 Karamu Rd Nth ",
    "sg:city":"Hastings",
    "sg:classifiers":[
        {
            "category":"Sports & Exercise",
            "subcategory":"Swimming Pool",
            "type":"Entertainment"
        }
    ],
    "sg:phone":"+64 6-878 9671",
    "sg:province":"Hawke's Bay",
    "sg:tags":[
        "home",
        "outdoor",
        "garden",
        "spa"
    ],
    "wof:name":"Bermuda Lifestyle",
    "wof:placetype":"venue"
},
  "geometry": {"coordinates":[176.87951699999999,-39.669403],"type":"Point"}
}