{
  "type": "Feature",
  "properties": {
    "iso:country":"NZ",
    "sg:address":"58 Tukehu St ",
    "sg:city":"Turangi",
    "sg:classifiers":[
        {
            "category":"Utilities",
            "type":"Services"
        }
    ],
    "sg:phone":"+64 7-386 5578",
    "sg:tags":[
        "industrial",
        "energy",
        "utilities",
        "coal",
        "wood",
        "coke"
    ],
    "wof:name":"Firewood Factory",
    "wof:placetype":"venue"
},
  "geometry": {"coordinates":[175.802582,-38.998955],"type":"Point"}
}