{
  "type": "Feature",
  "properties": {
    "addr:full":"12 Dellwood Green, Waimea Village Richmond  Nelson Nelson",
    "addr:housenumber":"12",
    "addr:street":"Dellwood Green Waimea Village",
    "iso:country":"NZ",
    "sg:address":"12 Dellwood Green, Waimea Village Richmond ",
    "sg:city":"Nelson",
    "sg:classifiers":[
        {
            "category":"Personal",
            "type":"Services"
        }
    ],
    "sg:phone":"+64 3-544 4263",
    "sg:province":"Nelson",
    "sg:tags":[
        "celebrant",
        "arrangements",
        "marriage",
        "wedding"
    ],
    "wof:name":"Ward J A (Jack) JP",
    "wof:placetype":"venue"
},
  "geometry": {"coordinates":[-121.765488,39.553471],"type":"Point"}
}