{
  "type": "Feature",
  "properties": {
    "addr:full":"153 A Bank St  Whangarei Northland",
    "addr:housenumber":"153 a",
    "addr:street":"Bank St",
    "iso:country":"NZ",
    "sg:address":"153 A Bank St ",
    "sg:city":"Whangarei",
    "sg:classifiers":[
        {
            "category":"Health Services",
            "subcategory":"Dentist",
            "type":"Services"
        }
    ],
    "sg:phone":"+64 9-438 3671",
    "sg:province":"Northland",
    "sg:tags":[
        "dental",
        "beauty"
    ],
    "wof:name":"Askew Dental Repairs",
    "wof:placetype":"venue"
},
  "geometry": {"coordinates":[174.321854,-35.717636],"type":"Point"}
}