{
  "type": "Feature",
  "properties": {
    "iso:country":"NZ",
    "sg:address":"23 Jesmond St ",
    "sg:city":"Ngaruawahia",
    "sg:orig_category":"Health And Beauty: Products: Pharmacies",
    "sg:phone":"+64 7-824 8604",
    "wof:name":"Shersons Pharmacy Ltd",
    "wof:placetype":"venue"
},
  "geometry": {"coordinates":[175.14892599999999,-37.665878],"type":"Point"}
}