{
  "type": "Feature",
  "properties": {
    "addr:full":"359 Queen St  Masterton Wellington",
    "addr:housenumber":"359",
    "addr:street":"Queen St",
    "iso:country":"NZ",
    "sg:address":"359 Queen St ",
    "sg:city":"Masterton",
    "sg:classifiers":[
        {
            "category":"Home & Garden",
            "subcategory":"Building Materials",
            "type":"Retail Goods"
        }
    ],
    "sg:phone":"+64 6-370 0040",
    "sg:province":"Wellington",
    "sg:tags":[
        "design",
        "fitting",
        "fittings",
        "kitchen"
    ],
    "wof:name":"Plumbing World",
    "wof:placetype":"venue"
},
  "geometry": {"coordinates":[175.65408300000001,-40.954754],"type":"Point"}
}