{
  "type": "Feature",
  "properties": {
    "addr:full":"cnr Lincoln Rd & Bernard St Addington  Christchurch Canterbury",
    "addr:street":"Cnr Lincoln Rd & Bernard St",
    "iso:country":"NZ",
    "sg:address":"cnr Lincoln Rd & Bernard St Addington ",
    "sg:city":"Christchurch",
    "sg:orig_category":"Automotive: General Services: Vehicle Certification",
    "sg:phone":"+64 3-338 0111",
    "sg:province":"Canterbury",
    "wof:name":"Auto Inspection Services Ltd",
    "wof:placetype":"venue"
},
  "geometry": {"coordinates":[172.61793499999999,-43.54319],"type":"Point"}
}