{
  "type": "Feature",
  "properties": {
    "iso:country":"NZ",
    "sg:address":"69 Keswick Cre ",
    "sg:city":"Hamilton",
    "sg:classifiers":[
        {
            "category":"Home & Garden",
            "subcategory":"Building Materials",
            "type":"Retail Goods"
        }
    ],
    "sg:phone":"+64 7-853 6629",
    "sg:province":"Waikato",
    "sg:tags":[
        "brick",
        "outdoor",
        "paving"
    ],
    "wof:name":"A J Humphries",
    "wof:placetype":"venue"
},
  "geometry": {"coordinates":[-87.9889678955,34.1424255371],"type":"Point"}
}