{
  "type": "Feature",
  "properties": {
    "iso:country":"NZ",
    "sg:address":"520 Mt Eden Rd Mt Eden ",
    "sg:city":"Auckland",
    "sg:orig_category":"Health And Beauty: Dental: Dentists",
    "sg:phone":"+64 9-630 5467",
    "sg:province":"Auckland",
    "sg:website":"http://www.gooddentists.co.nz",
    "wof:name":"Good Dentists",
    "wof:placetype":"venue"
},
  "geometry": {"coordinates":[174.76113899999999,-36.884609],"type":"Point"}
}