{
  "type": "Feature",
  "properties": {
    "addr:full":"318 West Bank Rd R D 2  Whakatane Bay of Plenty",
    "addr:housenumber":"318;2",
    "addr:street":"West Bank Rd R D;Bay",
    "iso:country":"NZ",
    "sg:address":"318 West Bank Rd R D 2 ",
    "sg:city":"Whakatane",
    "sg:classifiers":[
        {
            "category":"Farming",
            "subcategory":"Farm & Veterinary Services",
            "type":"Manufacturing & Wholesale Goods"
        }
    ],
    "sg:phone":"+64 7-304 9950",
    "sg:province":"Bay of Plenty",
    "sg:tags":[
        "supplies",
        "supply"
    ],
    "wof:name":"Farm Monitoring Service",
    "wof:placetype":"venue"
},
  "geometry": {"coordinates":[176.98419200000001,-37.965305],"type":"Point"}
}