{
  "type": "Feature",
  "properties": {
    "addr:full":"Gardner Valley Rd Upper  Moutere",
    "addr:street":"Valley Rd",
    "iso:country":"NZ",
    "sg:address":"Gardner Valley Rd Upper ",
    "sg:city":"Moutere",
    "sg:orig_category":"Shopping: Retail Stores: Antiques",
    "sg:phone":"+64 3-543 2186",
    "wof:name":"The Haybarn, Antiques & Country Collectables",
    "wof:placetype":"venue"
},
  "geometry": {"coordinates":[173.011627,-41.236519],"type":"Point"}
}