{
  "type": "Feature",
  "properties": {
    "addr:full":"428 Old North Rd Washdyke  Timaru Canterbury",
    "addr:housenumber":"428",
    "addr:street":"Old North Rd",
    "iso:country":"NZ",
    "sg:address":"428 Old North Rd Washdyke ",
    "sg:city":"Timaru",
    "sg:classifiers":[
        {
            "category":"Retail",
            "subcategory":"Auto Repair",
            "type":"Services"
        }
    ],
    "sg:phone":"+64 3-688 2159",
    "sg:province":"Canterbury",
    "sg:tags":[
        "muffler",
        "exhaust",
        "servicing",
        "automotive"
    ],
    "wof:name":"Timaru Exhaust Specialists Ltd",
    "wof:placetype":"venue"
},
  "geometry": {"coordinates":[171.23985300000001,-44.351528],"type":"Point"}
}