{
  "type": "Feature",
  "properties": {
    "iso:country":"NZ",
    "sg:address":"428 Old North Rd Washdyke ",
    "sg:city":"Timaru",
    "sg:classifiers":[
        {
            "category":"Retail",
            "subcategory":"Auto Repair",
            "type":"Services"
        }
    ],
    "sg:phone":"+64 3-688 2159",
    "sg:province":"Canterbury",
    "sg:tags":[
        "muffler",
        "exhaust",
        "servicing",
        "automotive"
    ],
    "wof:name":"Timaru Exhaust Specialists Ltd",
    "wof:placetype":"venue"
},
  "geometry": {"coordinates":[171.239853,-44.351528],"type":"Point"}
}