{
  "type": "Feature",
  "properties": {
    "addr:full":"PO Box 100722  Auckland Auckland",
    "addr:housenumber":"po;100722",
    "addr:street":"Box",
    "iso:country":"NZ",
    "sg:address":"PO Box 100722 ",
    "sg:city":"Auckland",
    "sg:classifiers":[
        {
            "category":"Shopping",
            "subcategory":"Beauty & Cosmetics",
            "type":"Retail Goods"
        }
    ],
    "sg:phone":"+64 9-478 4800",
    "sg:province":"Auckland",
    "sg:tags":[
        "supply",
        "health",
        "hairdressing"
    ],
    "wof:name":"Ascot Agencies Ltd",
    "wof:placetype":"venue"
},
  "geometry": {"coordinates":[174.77041600000001,-36.884109],"type":"Point"}
}