{
  "type": "Feature",
  "properties": {
    "addr:full":"Maraetai Beach  Auckland Auckland",
    "addr:street":"Maraetai",
    "iso:country":"NZ",
    "sg:address":"Maraetai Beach ",
    "sg:city":"Auckland",
    "sg:classifiers":[
        {
            "category":"Professional",
            "subcategory":"Art Services",
            "type":"Services"
        }
    ],
    "sg:phone":"+64 9-536 5977",
    "sg:province":"Auckland",
    "sg:tags":[
        "personal",
        "photographer",
        "services",
        "garden",
        "home"
    ],
    "sg:website":"http://www.creativeshotz.co.nz",
    "wof:name":"Creative Shotz Photography Ltd",
    "wof:placetype":"venue"
},
  "geometry": {"coordinates":[175.03952000000001,-36.88023],"type":"Point"}
}