{
  "type": "Feature",
  "properties": {
    "iso:country":"NZ",
    "sg:address":"Level 8 CMC Building 89 Courtenay Pl ",
    "sg:city":"Wellington",
    "sg:orig_category":"Shopping: Retail Stores: Books: Libraries",
    "sg:phone":"+64 4-801 8465",
    "sg:province":"Wellington",
    "wof:name":"Energy Library & Information Services Ltd",
    "wof:placetype":"venue"
},
  "geometry": {"coordinates":[-100.21676600000001,34.856194],"type":"Point"}
}