{
  "type": "Feature",
  "properties": {
    "addr:full":"443 Queen St  Masterton Wellington",
    "addr:housenumber":"443",
    "addr:street":"Queen St",
    "iso:country":"NZ",
    "sg:address":"443 Queen St ",
    "sg:city":"Masterton",
    "sg:classifiers":[
        {
            "category":"Bars & Pubs",
            "subcategory":"Lounge",
            "type":"Food & Drink"
        }
    ],
    "sg:phone":"+64 6-378 7177",
    "sg:province":"Wellington",
    "sg:tags":[
        "baker",
        "-"
    ],
    "wof:name":"Kuripuni Hot Bread Shop",
    "wof:placetype":"venue"
},
  "geometry": {"coordinates":[175.64828499999999,-40.958401],"type":"Point"}
}