{
  "type": "Feature",
  "properties": {
    "addr:full":"385 Bushmere Rd  Gisborne Gisborne",
    "addr:housenumber":"385",
    "addr:street":"Bushmere Rd",
    "iso:country":"NZ",
    "sg:address":"385 Bushmere Rd ",
    "sg:city":"Gisborne",
    "sg:classifiers":[
        {
            "category":"Food & Beverages",
            "subcategory":"Liquor & Beverages",
            "type":"Retail Goods"
        }
    ],
    "sg:phone":"+64 6-867 7931",
    "sg:province":"Gisborne",
    "sg:tags":[
        "drink",
        "maker",
        "wine"
    ],
    "wof:name":"Pouparae Park",
    "wof:placetype":"venue"
},
  "geometry": {"coordinates":[177.942307,-38.645187],"type":"Point"}
}