{
  "type": "Feature",
  "properties": {
    "iso:country":"NZ",
    "sg:address":"103 Victoria St ",
    "sg:city":"Wellington",
    "sg:orig_category":"Shopping: Gifts: Gift Baskets",
    "sg:phone":"+64 4-499 5580",
    "sg:province":"Wellington",
    "wof:name":"Baskets Bunches & Bows",
    "wof:placetype":"venue"
},
  "geometry": {"coordinates":[-3.230097,50.981392],"type":"Point"}
}