{
  "type": "Feature",
  "properties": {
    "addr:full":"99 Tukapa St New  Plymouth Taranaki",
    "addr:housenumber":"99",
    "addr:street":"Tukapa St",
    "iso:country":"NZ",
    "sg:address":"99 Tukapa St New ",
    "sg:city":"Plymouth",
    "sg:orig_category":"Health And Beauty: Products: Pharmacies",
    "sg:phone":"+64 6-753 9505",
    "sg:province":"Taranaki",
    "sg:website":"http://www.carefirst.co.nz",
    "wof:name":"Carefirst.co",
    "wof:placetype":"venue"
},
  "geometry": {"coordinates":[174.05935700000001,-39.073696],"type":"Point"}
}