{
  "type": "Feature",
  "properties": {
    "addr:full":"Health Services 18 A Goodshed Rd Upper Hutt  Wellington Wellington",
    "addr:housenumber":"18",
    "addr:street":"A Goodshed Rd",
    "iso:country":"NZ",
    "sg:address":"Health Services 18 A Goodshed Rd Upper Hutt ",
    "sg:city":"Wellington",
    "sg:classifiers":[
        {
            "category":"Health Services",
            "subcategory":"Health Practitioner",
            "type":"Services"
        }
    ],
    "sg:phone":"+64 4-939 1616",
    "sg:province":"Wellington",
    "sg:tags":[
        "consultant",
        "medical",
        "beauty"
    ],
    "wof:name":"Te Rongopai Morehu Trust",
    "wof:placetype":"venue"
},
  "geometry": {"coordinates":[174.90838600000001,-41.206631],"type":"Point"}
}