{
  "type": "Feature",
  "properties": {
    "addr:full":"P O Box 138  Hawera Taranaki",
    "addr:housenumber":"138",
    "addr:street":"P O Box",
    "iso:country":"NZ",
    "sg:address":"P O Box 138 ",
    "sg:city":"Hawera",
    "sg:orig_category":"Industrial: Engineering: Engineers - Automation",
    "sg:phone":"+64 6-278 8079",
    "sg:province":"Taranaki",
    "wof:name":"Icon Automation Ltd",
    "wof:placetype":"venue"
},
  "geometry": {"coordinates":[174.27131700000001,-39.57584],"type":"Point"}
}