{
  "type": "Feature",
  "properties": {
    "addr:full":"64/2B Henderson Valley Rd Henderson  Auckland Auckland",
    "addr:housenumber":"64 / 2b",
    "addr:street":"Henderson Valley Rd",
    "iso:country":"NZ",
    "sg:address":"64/2B Henderson Valley Rd Henderson ",
    "sg:city":"Auckland",
    "sg:orig_category":"Automotive: Accessories: Towbars",
    "sg:phone":"+64 9-838 8724",
    "sg:province":"Auckland",
    "wof:name":"A 1 Bars (1994) Ltd",
    "wof:placetype":"venue"
},
  "geometry": {"coordinates":[174.62922699999999,-36.880695],"type":"Point"}
}