{
  "type": "Feature",
  "properties": {
    "iso:country":"NZ",
    "sg:address":"64/2B Henderson Valley Rd Henderson ",
    "sg:city":"Auckland",
    "sg:orig_category":"Automotive: Accessories: Towbars",
    "sg:phone":"+64 9-838 8724",
    "sg:province":"Auckland",
    "wof:name":"A 1 Bars (1994) Ltd",
    "wof:placetype":"venue"
},
  "geometry": {"coordinates":[174.629227,-36.880695],"type":"Point"}
}