{
  "type": "Feature",
  "properties": {
    "addr:full":"PO Box 19004 Courtenay Place  Wellington Bay of Plenty",
    "addr:housenumber":"po box",
    "addr:postcode":"19004",
    "addr:street":"Place Wellington",
    "iso:country":"NZ",
    "sg:address":"PO Box 19004 Courtenay Place ",
    "sg:city":"Wellington",
    "sg:classifiers":[
        {
            "category":"Travel",
            "subcategory":"Hotels & Motels",
            "type":"Entertainment"
        }
    ],
    "sg:phone":"+64 4-973 2660",
    "sg:province":"Bay of Plenty",
    "sg:tags":[
        "tavern",
        "tourism",
        "accommodation"
    ],
    "sg:website":"http://www.yellowpages.co.nz/pages/400042228/dp58183.html",
    "wof:name":"Stay-Here.co.nz",
    "wof:placetype":"venue"
},
  "geometry": {"coordinates":[-85.910454,33.827946],"type":"Point"}
}