{
  "type": "Feature",
  "properties": {
    "addr:full":"151 Waikawa Rd  Picton Marlborough",
    "addr:housenumber":"151",
    "addr:street":"Waikawa Rd",
    "iso:country":"NZ",
    "sg:address":"151 Waikawa Rd ",
    "sg:city":"Picton",
    "sg:orig_category":"Transport: Boats And Marine: Boats: Boat Dealers",
    "sg:phone":"+64 3-573 7008",
    "sg:province":"Marlborough",
    "wof:name":"Picton Marine Brokers",
    "wof:placetype":"venue"
},
  "geometry": {"coordinates":[174.01000999999999,-41.290752],"type":"Point"}
}