{
  "type": "Feature",
  "properties": {
    "addr:full":"Auckland  Auckland Auckland",
    "iso:country":"NZ",
    "sg:address":"Auckland ",
    "sg:city":"Auckland",
    "sg:classifiers":[
        {
            "category":"Airline",
            "type":"Transportation"
        }
    ],
    "sg:phone":"+64 800 737 767",
    "sg:province":"Auckland",
    "sg:tags":[
        "services",
        "travel",
        "tourism"
    ],
    "sg:website":"http://www.airnewzealand.co.nz",
    "wof:name":"Air New Zealand Travelcentre",
    "wof:placetype":"venue"
},
  "geometry": {"coordinates":[174.78450000000001,-37.006058],"type":"Point"}
}