{
  "type": "Feature",
  "properties": {
    "iso:country":"NZ",
    "sg:address":"6 Senior Pl Bromley ",
    "sg:city":"Christchurch",
    "sg:orig_category":"Home And Garden: Furniture/Furnishings: Chairmakers",
    "sg:phone":"+64 3-389 5716",
    "sg:province":"Canterbury",
    "wof:name":"Upholstery Services Ltd",
    "wof:placetype":"venue"
},
  "geometry": {"coordinates":[172.696442,-43.530273],"type":"Point"}
}