{
  "type": "Feature",
  "properties": {
    "iso:country":"NZ",
    "sg:address":"10 Butel Ave ",
    "sg:city":"Arrowtown",
    "sg:classifiers":[
        {
            "category":"Shopping",
            "subcategory":"Crafts & Fabrics",
            "type":"Retail Goods"
        }
    ],
    "sg:phone":"+64 3-442 1772",
    "sg:province":"Otago",
    "sg:tags":[
        "sport",
        "art",
        "leisure",
        "hobbies"
    ],
    "wof:name":"Destination Art",
    "wof:placetype":"venue"
},
  "geometry": {"coordinates":[168.83934,-44.947559],"type":"Point"}
}