{
  "type": "Feature",
  "properties": {
    "iso:country":"NZ",
    "sg:address":"91 Thames St ",
    "sg:city":"Napier",
    "sg:classifiers":[
        {
            "category":"Winery",
            "type":"Food & Drink"
        }
    ],
    "sg:phone":"+64 6-833 6830",
    "sg:province":"Hawke's Bay",
    "sg:tags":[
        "wining",
        "vineyard",
        "dining"
    ],
    "wof:name":"Corbans Hawke's Bay Winery",
    "wof:placetype":"venue"
},
  "geometry": {"coordinates":[-80.588562,38.790821],"type":"Point"}
}