{
  "type": "Feature",
  "properties": {
    "iso:country":"NZ",
    "sg:address":"Suite 2/3 Mortimer Pass Newmarket ",
    "sg:city":"Auckland",
    "sg:classifiers":[
        {
            "category":"Arena",
            "subcategory":"Sports Club",
            "type":"Entertainment"
        }
    ],
    "sg:phone":"+64 9-520 8321",
    "sg:province":"Auckland",
    "sg:tags":[
        "arts",
        "writer",
        "leisure",
        "author"
    ],
    "wof:name":"The Human Garden Agency",
    "wof:placetype":"venue"
},
  "geometry": {"coordinates":[174.77626,-36.871613],"type":"Point"}
}