{
  "type": "Feature",
  "properties": {
    "addr:full":"41 Ferguson Pl  Rotorua Bay of Plenty",
    "addr:housenumber":"41",
    "addr:street":"Ferguson Pl",
    "iso:country":"NZ",
    "sg:address":"41 Ferguson Pl ",
    "sg:city":"Rotorua",
    "sg:classifiers":[
        {
            "category":"Utilities",
            "subcategory":"Refuse",
            "type":"Services"
        }
    ],
    "sg:phone":"+64 7-349 0222",
    "sg:province":"Bay of Plenty",
    "sg:tags":[
        "bin",
        "hire",
        "garden",
        "cleaning",
        "rubbish",
        "home"
    ],
    "wof:name":"Waste Management NZ Ltd",
    "wof:placetype":"venue"
},
  "geometry": {"coordinates":[176.225235,-38.118881],"type":"Point"}
}