{
  "type": "Feature",
  "properties": {
    "iso:country":"NZ",
    "sg:address":"81 Formby St ",
    "sg:city":"Outram",
    "sg:orig_category":"Farming: Agriculture",
    "sg:phone":"+64 3-486 1807",
    "wof:name":"John Eaton Agricultural Spraying",
    "wof:placetype":"venue"
},
  "geometry": {"coordinates":[170.228638,-45.863293],"type":"Point"}
}