{
  "type": "Feature",
  "properties": {
    "addr:full":"81 Formby St  Outram",
    "addr:housenumber":"81",
    "addr:street":"Formby St",
    "iso:country":"NZ",
    "sg:address":"81 Formby St ",
    "sg:city":"Outram",
    "sg:orig_category":"Farming: Agriculture",
    "sg:phone":"+64 3-486 1807",
    "wof:name":"John Eaton Agricultural Spraying",
    "wof:placetype":"venue"
},
  "geometry": {"coordinates":[170.22863799999999,-45.863293],"type":"Point"}
}