{
  "type": "Feature",
  "properties": {
    "addr:full":"31 Jarden Mle Ngauranga  Wellington Wellington",
    "addr:housenumber":"31;mle",
    "addr:street":"Jarden;Wellington",
    "iso:country":"NZ",
    "sg:address":"31 Jarden Mle Ngauranga ",
    "sg:city":"Wellington",
    "sg:classifiers":[
        {
            "category":"Shopping",
            "subcategory":"Beauty & Cosmetics",
            "type":"Retail Goods"
        }
    ],
    "sg:phone":"+64 4-473 3799",
    "sg:province":"Wellington",
    "sg:tags":[
        "supply",
        "health",
        "hairdressing"
    ],
    "wof:name":"Nioxin & Scruples",
    "wof:placetype":"venue"
},
  "geometry": {"coordinates":[174.81047100000001,-41.24865],"type":"Point"}
}