{
  "type": "Feature",
  "properties": {
    "iso:country":"NZ",
    "sg:address":"PO Box 253 Ostend ",
    "sg:city":"Auckland",
    "sg:classifiers":[
        {
            "category":"Social Services",
            "subcategory":"Retirement Home",
            "type":"Services"
        }
    ],
    "sg:phone":"+64 9-372 2820",
    "sg:province":"Auckland",
    "sg:tags":[
        "care",
        "garden",
        "elderly",
        "village"
    ],
    "wof:name":"Waiheke Retirement Village",
    "wof:placetype":"venue"
},
  "geometry": {"coordinates":[175.046066,-36.799],"type":"Point"}
}