{
  "type": "Feature",
  "properties": {
    "addr:full":"155-157 High St  Hawera Taranaki",
    "addr:housenumber":"155-157",
    "addr:street":"High St",
    "iso:country":"NZ",
    "sg:address":"155-157 High St ",
    "sg:city":"Hawera",
    "sg:orig_category":"Home And Garden: Accessories: Hardware",
    "sg:phone":"+64 6-278 5019",
    "sg:province":"Taranaki",
    "wof:name":"Mitre 10",
    "wof:placetype":"venue"
},
  "geometry": {"coordinates":[174.28166200000001,-39.588943],"type":"Point"}
}