{
  "type": "Feature",
  "properties": {
    "addr:full":"Level 28 Grand Plimmer Tower cnr Boulcott St &, Gilmer Tce  Wellington Wellington",
    "addr:housenumber":"28",
    "addr:street":"Grand Plimmer;Cnr Boulcott St & Gilmer",
    "iso:country":"NZ",
    "sg:address":"Level 28 Grand Plimmer Tower cnr Boulcott St &, Gilmer Tce ",
    "sg:city":"Wellington",
    "sg:orig_category":"Automotive: General Services: Car Parking",
    "sg:phone":"+64 4-473 2293",
    "sg:province":"Wellington",
    "wof:name":"Wilson Parking New Zealand (1992) Limited",
    "wof:placetype":"venue"
},
  "geometry": {"coordinates":[174.92103599999999,-41.202091],"type":"Point"}
}