{
  "type": "Feature",
  "properties": {
    "iso:country":"NZ",
    "sg:address":"Maitai Retreat Maitai Valley Road Maitai Valley ",
    "sg:city":"Nelson",
    "sg:classifiers":[
        {
            "category":"Personal",
            "subcategory":"Massage",
            "type":"Services"
        }
    ],
    "sg:phone":"+64 3-546 9551",
    "sg:province":"Wellington",
    "sg:tags":[
        "services",
        "health",
        "-",
        "beauty",
        "fitness"
    ],
    "wof:name":"Jane Pujji",
    "wof:placetype":"venue"
},
  "geometry": {"coordinates":[173.30371099999999,-41.273663],"type":"Point"}
}