{
  "type": "Feature",
  "properties": {
    "addr:full":"24 Atkinson St Normanby  Hawera Taranaki",
    "addr:housenumber":"24",
    "addr:street":"Atkinson St",
    "iso:country":"NZ",
    "sg:address":"24 Atkinson St Normanby ",
    "sg:city":"Hawera",
    "sg:classifiers":[
        {
            "category":"Sports & Exercise",
            "subcategory":"Race Track",
            "type":"Entertainment"
        }
    ],
    "sg:phone":"+64 6-272 8021",
    "sg:province":"Taranaki",
    "sg:tags":[
        "blacksmith",
        "farrier",
        "equestrian",
        "leisure",
        "sports"
    ],
    "wof:name":"Jensen Gary",
    "wof:placetype":"venue"
},
  "geometry": {"coordinates":[174.270523,-39.542404],"type":"Point"}
}