{
  "type": "Feature",
  "properties": {
    "iso:country":"NZ",
    "sg:address":"Back St Opua ",
    "sg:city":"Paihia",
    "sg:orig_category":"Health And Beauty: Specialists: Physiotherapists",
    "sg:phone":"+64 9-402 7024",
    "sg:province":"Northland",
    "wof:name":"Bogardus Doug",
    "wof:placetype":"venue"
},
  "geometry": {"coordinates":[174.114532,-35.31221],"type":"Point"}
}