{
  "type": "Feature",
  "properties": {
    "iso:country":"NZ",
    "sg:address":"23 Leeds St Linwood ",
    "sg:city":"Christchurch",
    "sg:classifiers":[
        {
            "category":"Recreation",
            "type":"Entertainment"
        }
    ],
    "sg:phone":"+64 3-377 3730",
    "sg:province":"Canterbury",
    "sg:tags":[
        "sport",
        "leisure"
    ],
    "sg:website":"http://www.yellowpages.co.nz/pages/224998598/dp45726.html",
    "wof:name":"Action Dirt Karts Ltd",
    "wof:placetype":"venue"
},
  "geometry": {"coordinates":[172.66214,-43.53146],"type":"Point"}
}