{
  "type": "Feature",
  "properties": {
    "addr:full":"PO Box 47862 Ponsonby  Auckland Auckland",
    "addr:housenumber":"po box",
    "addr:postcode":"47862",
    "iso:country":"NZ",
    "sg:address":"PO Box 47862 Ponsonby ",
    "sg:city":"Auckland",
    "sg:classifiers":[
        {
            "category":"Arena",
            "subcategory":"Sports Club",
            "type":"Entertainment"
        }
    ],
    "sg:phone":"+64 9-376 6881",
    "sg:province":"Auckland",
    "sg:tags":[
        "arts",
        "writer",
        "leisure",
        "author"
    ],
    "wof:name":"Piranha Talent Agency Ltd",
    "wof:placetype":"venue"
},
  "geometry": {"coordinates":[174.74241599999999,-36.85326],"type":"Point"}
}