{
  "type": "Feature",
  "properties": {
    "addr:full":"PO Box 290  Whitianga",
    "addr:housenumber":"po",
    "addr:street":"Box 290",
    "iso:country":"NZ",
    "sg:address":"PO Box 290 ",
    "sg:city":"Whitianga",
    "sg:classifiers":[
        {
            "category":"Wholesale",
            "subcategory":"Machinery & Supplies",
            "type":"Manufacturing & Wholesale Goods"
        }
    ],
    "sg:phone":"+64 25976311",
    "sg:tags":[
        "equipment",
        "crane",
        "industrial",
        "hoist",
        "lifting"
    ],
    "wof:name":"Coro Crane Hire",
    "wof:placetype":"venue"
},
  "geometry": {"coordinates":[175.699524,-36.821472],"type":"Point"}
}