{
  "type": "Feature",
  "properties": {
    "iso:country":"NZ",
    "sg:address":"184 Armagh St ",
    "sg:city":"Christchurch",
    "sg:classifiers":[
        {
            "category":"Banks & Credit Unions",
            "subcategory":"Financial Services",
            "type":"Services"
        }
    ],
    "sg:phone":"+64 3-379 8843",
    "sg:province":"Canterbury",
    "sg:tags":[
        "personal",
        "superannuation",
        "-",
        "finance"
    ],
    "wof:name":"SIL Marketing",
    "wof:placetype":"venue"
},
  "geometry": {"coordinates":[-76.537834,37.605659],"type":"Point"}
}