{
  "type": "Feature",
  "properties": {
    "addr:full":"652 Great South Road Manukau City  Auckland Wellington",
    "addr:housenumber":"652",
    "addr:street":"Great South Road",
    "iso:country":"NZ",
    "sg:address":"652 Great South Road Manukau City ",
    "sg:city":"Auckland",
    "sg:orig_category":"Farming: Farms - General: Poultry",
    "sg:phone":"+64 9-263 7400",
    "sg:province":"Wellington",
    "wof:name":"Brinks Chicken",
    "wof:placetype":"venue"
},
  "geometry": {"coordinates":[174.88176000000001,-36.987083],"type":"Point"}
}