{
  "type": "Feature",
  "properties": {
    "iso:country":"NZ",
    "sg:address":"691 Manukau Rd Royal Oak ",
    "sg:city":"Auckland",
    "sg:classifiers":[
        {
            "category":"Health Services",
            "subcategory":"Health Practitioner",
            "type":"Services"
        }
    ],
    "sg:phone":"+64 9-526 0623",
    "sg:province":"Auckland",
    "sg:tags":[
        "services",
        "beauty",
        "acupuncturists"
    ],
    "wof:name":"Dr Desmond E Chung",
    "wof:placetype":"venue"
},
  "geometry": {"coordinates":[174.775665,-36.910736],"type":"Point"}
}