{
  "type": "Feature",
  "properties": {
    "addr:full":"Westfield Shoppingtown Pakuranga  Auckland Auckland",
    "iso:country":"NZ",
    "sg:address":"Westfield Shoppingtown Pakuranga ",
    "sg:city":"Auckland",
    "sg:orig_category":"Health And Beauty: Products: Pharmacies",
    "sg:phone":"+64 9-576 8074",
    "sg:province":"Auckland",
    "wof:name":"Life Pharmacy Pakuranga",
    "wof:placetype":"venue"
},
  "geometry": {"coordinates":[174.892807,-36.901218],"type":"Point"}
}