{
  "type": "Feature",
  "properties": {
    "iso:country":"NZ",
    "sg:address":"896 Papamoa Beach Rd ",
    "sg:city":"Papamoa",
    "sg:orig_category":"Farming: Services: Veterinarians",
    "sg:phone":"+64 7-542 2642",
    "wof:name":"Papamoa Beach Road Vet Clinic",
    "wof:placetype":"venue"
},
  "geometry": {"coordinates":[176.317047,-37.708721],"type":"Point"}
}