{
  "type": "Feature",
  "properties": {
    "iso:country":"NZ",
    "sg:address":"2 Hyland Bra Governors ",
    "sg:city":"Bay",
    "sg:orig_category":"Industrial: Engineering: Engineers - Patternmakers",
    "sg:phone":"+64 3-329 9970",
    "wof:name":"Bill Revis Patterns",
    "wof:placetype":"venue"
},
  "geometry": {"coordinates":[172.64686599999999,-43.62109],"type":"Point"}
}