{
  "type": "Feature",
  "properties": {
    "addr:full":"16 Haining St  Wellington Wellington",
    "addr:housenumber":"16",
    "addr:street":"Haining St",
    "iso:country":"NZ",
    "sg:address":"16 Haining St ",
    "sg:city":"Wellington",
    "sg:classifiers":[
        {
            "category":"Professional",
            "type":"Services"
        }
    ],
    "sg:phone":"+64 4-384 2689",
    "sg:province":"Wellington",
    "sg:tags":[
        "services",
        "car",
        "valet",
        "automotive"
    ],
    "wof:name":"Tidy Car Wellington",
    "wof:placetype":"venue"
},
  "geometry": {"coordinates":[-85.910454,33.827946],"type":"Point"}
}