{
  "type": "Feature",
  "properties": {
    "addr:full":"17 Hautonga St Petone  Wellington Wellington",
    "addr:housenumber":"17",
    "addr:street":"Hautonga St",
    "iso:country":"NZ",
    "sg:address":"17 Hautonga St Petone ",
    "sg:city":"Wellington",
    "sg:orig_category":"Industrial: Parts: Pipes, Tubes And Cabling: Pipes",
    "sg:phone":"+64 4-576 8990",
    "sg:province":"Wellington",
    "wof:name":"Steel & Tube Piping Systems",
    "wof:placetype":"venue"
},
  "geometry": {"coordinates":[174.89399700000001,-41.233036],"type":"Point"}
}