{
  "type": "Feature",
  "properties": {
    "iso:country":"NZ",
    "sg:address":"404 Wellington Rd ",
    "sg:city":"Marton",
    "sg:classifiers":[
        {
            "category":"Autos & Motor Vehicles",
            "subcategory":"Motorcycle Sales",
            "type":"Retail Goods"
        }
    ],
    "sg:phone":"+64 6-327 7115",
    "sg:tags":[
        "automotive",
        "scooter",
        "leasing"
    ],
    "wof:name":"Robbie's Mechanical Services",
    "wof:placetype":"venue"
},
  "geometry": {"coordinates":[-3.01544,53.799294],"type":"Point"}
}