{
  "type": "Feature",
  "properties": {
    "iso:country":"NZ",
    "sg:address":"575 Arapuni Rd Te ",
    "sg:city":"Awamutu",
    "sg:classifiers":[
        {
            "category":"Travel",
            "subcategory":"Travel Agent",
            "type":"Entertainment"
        }
    ],
    "sg:phone":"+64 7-872 7880",
    "sg:province":"Waikato",
    "sg:tags":[
        "tour",
        "tourism",
        "adventure",
        "sightseeing"
    ],
    "wof:name":"Real Rock Ltd",
    "wof:placetype":"venue"
},
  "geometry": {"coordinates":[175.358475,-38.042297],"type":"Point"}
}