{
  "type": "Feature",
  "properties": {
    "iso:country":"NZ",
    "sg:address":"PO Box 2650 Christchurch ",
    "sg:city":"Springfield",
    "sg:classifiers":[
        {
            "category":"Home & Garden",
            "subcategory":"Garden Supply",
            "type":"Retail Goods"
        }
    ],
    "sg:phone":"+64 3-318 4123",
    "sg:tags":[
        "trainer",
        "breeder",
        "/",
        "pets",
        "animal"
    ],
    "wof:name":"Canterbury Bull Terrier Club",
    "wof:placetype":"venue"
},
  "geometry": {"coordinates":[171.92628500000001,-43.334629],"type":"Point"}
}