{
  "type": "Feature",
  "properties": {
    "addr:full":"www.yellowpages.co.nz/for/ezflownailsystemsnz  Whakatane Bay of Plenty",
    "addr:street":"Whakatane",
    "iso:country":"NZ",
    "sg:address":"www.yellowpages.co.nz/for/ezflownailsystemsnz ",
    "sg:city":"Whakatane",
    "sg:classifiers":[
        {
            "category":"Insurance",
            "subcategory":"Health Insurance",
            "type":"Services"
        }
    ],
    "sg:phone":"+64 7-304 6245",
    "sg:province":"Bay of Plenty",
    "sg:tags":[
        "beauty",
        "supply"
    ],
    "sg:website":"http://www.yellowpages.co.nz/for/ezflownailsystemsnz/dp55743.html",
    "wof:name":"EzFlow Nail Systems NZ",
    "wof:placetype":"venue"
},
  "geometry": {"coordinates":[176.984207,-37.965302],"type":"Point"}
}