{
  "type": "Feature",
  "properties": {
    "iso:country":"NZ",
    "sg:address":"Level 1 Mbank Shp Centre Meadowbank ",
    "sg:city":"Auckland",
    "sg:classifiers":[
        {
            "category":"Education",
            "subcategory":"Special Training",
            "type":"Public Place"
        }
    ],
    "sg:phone":"+64 9-528 9207",
    "sg:province":"Auckland",
    "sg:tags":[
        "tutor",
        "coach",
        "teacher"
    ],
    "wof:name":"Straight A's Ltd",
    "wof:placetype":"venue"
},
  "geometry": {"coordinates":[174.827087,-36.870098],"type":"Point"}
}