{
  "type": "Feature",
  "properties": {
    "addr:full":"45 Horseshoe Lake Rd Burwood  Christchurch Canterbury",
    "addr:housenumber":"45",
    "addr:street":"Horseshoe Lake Rd",
    "iso:country":"NZ",
    "sg:address":"45 Horseshoe Lake Rd Burwood ",
    "sg:city":"Christchurch",
    "sg:orig_category":"Sports And Leisure: Sports: Golf: Golf Professionals",
    "sg:phone":"+64 3-385 2738",
    "sg:province":"Canterbury",
    "wof:name":"Christchurch Golf Club Inc",
    "wof:placetype":"venue"
},
  "geometry": {"coordinates":[172.668228,-43.503456],"type":"Point"}
}