{
  "type": "Feature",
  "properties": {
    "iso:country":"NZ",
    "sg:address":"7 A Taupo St ",
    "sg:city":"Putaruru",
    "sg:orig_category":"Industrial: Metal: Products: Aluminium Products",
    "sg:phone":"+64 7-883 3233",
    "wof:name":"Omega Waikato",
    "wof:placetype":"venue"
},
  "geometry": {"coordinates":[175.78526299999999,-38.056492],"type":"Point"}
}