{
  "type": "Feature",
  "properties": {
    "iso:country":"NZ",
    "sg:address":"161 Ruapehu St ",
    "sg:city":"Taupo",
    "sg:classifiers":[
        {
            "category":"Personal",
            "subcategory":"Adult",
            "type":"Services"
        }
    ],
    "sg:phone":"+64 7-377 3311",
    "sg:province":"Waikato",
    "sg:tags":[
        "sport",
        "parlour",
        "massage",
        "leisure"
    ],
    "wof:name":"Bobby's Massage & Sauna",
    "wof:placetype":"venue"
},
  "geometry": {"coordinates":[176.073532,-38.684113],"type":"Point"}
}