{
  "type": "Feature",
  "properties": {
    "addr:full":"88 Spey St  Invercargill Southland",
    "addr:housenumber":"88",
    "addr:street":"Spey St",
    "iso:country":"NZ",
    "sg:address":"88 Spey St ",
    "sg:city":"Invercargill",
    "sg:classifiers":[
        {
            "category":"Personal",
            "subcategory":"Piercing",
            "type":"Services"
        }
    ],
    "sg:phone":"+64 3-218 8718",
    "sg:province":"Southland",
    "sg:tags":[
        "body",
        "ear",
        "health",
        "nose",
        "beauty"
    ],
    "wof:name":"Buzzworks Tattooing and Body Piercing Clinic",
    "wof:placetype":"venue"
},
  "geometry": {"coordinates":[168.34779399999999,-46.409485],"type":"Point"}
}