{
  "type": "Feature",
  "properties": {
    "addr:full":"102 Great South Rd Epsom  Auckland Auckland",
    "addr:housenumber":"102",
    "addr:street":"Great South Rd",
    "iso:country":"NZ",
    "sg:address":"102 Great South Rd Epsom ",
    "sg:city":"Auckland",
    "sg:classifiers":[
        {
            "category":"Insurance",
            "subcategory":"Health Insurance",
            "type":"Services"
        }
    ],
    "sg:phone":"+64 9-524 9872",
    "sg:province":"Auckland",
    "sg:tags":[
        "mental",
        "beauty"
    ],
    "wof:name":"Stenhouse Glen",
    "wof:placetype":"venue"
},
  "geometry": {"coordinates":[174.78277600000001,-36.879719],"type":"Point"}
}