{
  "type": "Feature",
  "properties": {
    "iso:country":"NZ",
    "sg:address":"26 A Oruanui St ",
    "sg:city":"Taupo",
    "sg:orig_category":"Sports And Leisure: Sports: Equestrian: Saddlers",
    "sg:phone":"+64 7-378 4916",
    "sg:province":"Waikato",
    "wof:name":"Taupo Saddlery",
    "wof:placetype":"venue"
},
  "geometry": {"coordinates":[176.072357,-38.682781],"type":"Point"}
}