{
  "type": "Feature",
  "properties": {
    "addr:full":"50 Lunn Ave Mt Wellington  Auckland Auckland",
    "addr:housenumber":"50",
    "addr:street":"Lunn Ave",
    "iso:country":"NZ",
    "sg:address":"50 Lunn Ave Mt Wellington ",
    "sg:city":"Auckland",
    "sg:orig_category":"Industrial: Engineering: Engineers: Engineers Supplies",
    "sg:phone":"+64 9-570 8855",
    "sg:province":"Auckland",
    "wof:name":"Sulco Tools & Equipment",
    "wof:placetype":"venue"
},
  "geometry": {"coordinates":[174.83644100000001,-36.892139],"type":"Point"}
}