{
  "type": "Feature",
  "properties": {
    "iso:country":"NZ",
    "sg:address":"671 Frankley Rd R D 1 New ",
    "sg:city":"Plymouth",
    "sg:classifiers":[
        {
            "category":"Shopping",
            "subcategory":"Pets & Pet Supplies",
            "type":"Retail Goods"
        }
    ],
    "sg:phone":"+64 6-753 9325",
    "sg:province":"Taranaki",
    "sg:tags":[
        "boarding",
        "garden",
        "pets",
        "catteries",
        "home",
        "kennel"
    ],
    "wof:name":"Redwood Boarding Kennels",
    "wof:placetype":"venue"
},
  "geometry": {"coordinates":[-82.319611,39.301723],"type":"Point"}
}