{
  "type": "Feature",
  "properties": {
    "addr:full":"Hospital Rd  Whangarei Northland",
    "addr:street":"Hospital Rd",
    "iso:country":"NZ",
    "sg:address":"Hospital Rd ",
    "sg:city":"Whangarei",
    "sg:orig_category":"Health And Beauty: Medical: Hospitals",
    "sg:phone":"+64 9-430 4100",
    "sg:province":"Northland",
    "wof:name":"Whangarei Hospital",
    "wof:placetype":"venue"
},
  "geometry": {"coordinates":[174.32015999999999,-35.708782],"type":"Point"}
}