{
  "type": "Feature",
  "properties": {
    "iso:country":"NZ",
    "sg:address":"95 A Main South Rd ",
    "sg:city":"Sockburn",
    "sg:orig_category":"Home And Garden: Furniture/Furnishings",
    "sg:phone":"+64 800 861 300",
    "sg:province":"Canterbury",
    "sg:website":"http://www.yellowpages.co.nz/for/aquaplus/dp34643.html",
    "wof:name":"Waterbed Components NZ",
    "wof:placetype":"venue"
},
  "geometry": {"coordinates":[172.560272,-43.536076],"type":"Point"}
}