{
  "type": "Feature",
  "properties": {
    "addr:full":"26 Hatrick St  Wanganui Manawatu-Wanganui",
    "addr:housenumber":"26",
    "addr:street":"Hatrick St",
    "iso:country":"NZ",
    "sg:address":"26 Hatrick St ",
    "sg:city":"Wanganui",
    "sg:classifiers":[
        {
            "category":"Retail",
            "subcategory":"Auto Repair",
            "type":"Services"
        }
    ],
    "sg:phone":"+64 6-345 4402",
    "sg:province":"Manawatu-Wanganui",
    "sg:tags":[
        "automotive",
        "servicing"
    ],
    "wof:name":"Rivers Speed & Spares",
    "wof:placetype":"venue"
},
  "geometry": {"coordinates":[175.04490699999999,-39.936325],"type":"Point"}
}