{
  "type": "Feature",
  "properties": {
    "iso:country":"NZ",
    "sg:address":"Waterfront Rd ",
    "sg:city":"Mangonui",
    "sg:orig_category":"Travel And Tourism: Accommodation: Backpackers",
    "sg:phone":"+64 9-406 0003",
    "wof:name":"Mangonui Hotel",
    "wof:placetype":"venue"
},
  "geometry": {"coordinates":[173.536865,-34.989635],"type":"Point"}
}