{
  "type": "Feature",
  "properties": {
    "addr:full":"Lever St Ahuriri  Napier Hawke's Bay",
    "addr:street":"Lever St",
    "iso:country":"NZ",
    "sg:address":"Lever St Ahuriri ",
    "sg:city":"Napier",
    "sg:classifiers":[
        {
            "category":"Retail",
            "subcategory":"Laundry & Dry Cleaning",
            "type":"Services"
        }
    ],
    "sg:phone":"+64 6-835 8646",
    "sg:province":"Hawke's Bay",
    "sg:tags":[
        "product",
        "wool",
        "clothing",
        "fabric"
    ],
    "wof:name":"Williams & Kettle Ltd",
    "wof:placetype":"venue"
},
  "geometry": {"coordinates":[176.89804100000001,-39.48526],"type":"Point"}
}