{
  "type": "Feature",
  "properties": {
    "iso:country":"NZ",
    "sg:address":"515 Wairakei Rd Burnside ",
    "sg:city":"Christchurch",
    "sg:orig_category":"Industrial: Instruments: Industrial Instruments",
    "sg:phone":"+64 3-359 7061",
    "sg:province":"Canterbury",
    "sg:website":"http://www.qel.co.nz",
    "wof:name":"Quasar Electronics Limited",
    "wof:placetype":"venue"
},
  "geometry": {"coordinates":[172.567459,-43.489197],"type":"Point"}
}