{
  "type": "Feature",
  "properties": {
    "iso:country":"NZ",
    "sg:address":"19 Jellicoe St Te Puke ",
    "sg:city":"Tauranga",
    "sg:orig_category":"Health And Beauty: Dental: Dentists",
    "sg:phone":"+64 7-573 7856",
    "sg:province":"Bay of Plenty",
    "wof:name":"The Tooth Fairy Dental Centre",
    "wof:placetype":"venue"
},
  "geometry": {"coordinates":[176.32008400000001,-37.786819],"type":"Point"}
}