{
  "type": "Feature",
  "properties": {
    "addr:full":"39 c Victoria St  Cambridge Waikato",
    "addr:housenumber":"39 c",
    "addr:street":"Victoria St",
    "iso:country":"NZ",
    "sg:address":"39 c Victoria St ",
    "sg:city":"Cambridge",
    "sg:orig_category":"Shopping: Engravers",
    "sg:phone":"+64 7-827 8082",
    "sg:province":"Waikato",
    "wof:name":"Etching & Design",
    "wof:placetype":"venue"
},
  "geometry": {"coordinates":[-116.67604799999999,44.572186],"type":"Point"}
}