{
  "type": "Feature",
  "properties": {
    "iso:country":"NZ",
    "sg:address":"45 Mawhitiwhiti Rd Normanby ",
    "sg:city":"Hawera",
    "sg:orig_category":"Industrial: Metal: Stainless Steel",
    "sg:phone":"+64 6-272 8473",
    "sg:province":"Taranaki",
    "wof:name":"Mobile Engineering Services",
    "wof:placetype":"venue"
},
  "geometry": {"coordinates":[174.271317,-39.57584],"type":"Point"}
}