{
  "type": "Feature",
  "properties": {
    "iso:country":"NZ",
    "sg:address":"58 Gaunt St Auckland Central ",
    "sg:city":"Auckland",
    "sg:classifiers":[
        {
            "category":"Internet Cafe",
            "subcategory":"None",
            "type":"Food & Drink"
        }
    ],
    "sg:phone":"+64 9-309 9539",
    "sg:province":"Auckland",
    "sg:tags":[
        "fish",
        "processing",
        "processor"
    ],
    "wof:name":"New Zealand Wholesale Seafoods",
    "wof:placetype":"venue"
},
  "geometry": {"coordinates":[174.75559999999999,-36.844707],"type":"Point"}
}