{
  "type": "Feature",
  "properties": {
    "iso:country":"NZ",
    "sg:address":"75 Broadway ",
    "sg:city":"Kaikohe",
    "sg:orig_category":"Shopping: Sports Retailers: Sports Goods: Sporting Goods",
    "sg:phone":"+64 9-401 1004",
    "sg:province":"Manawatu-Wanganui",
    "wof:name":"Kaikohe Cycle & Sports",
    "wof:placetype":"venue"
},
  "geometry": {"coordinates":[173.80107100000001,-35.407009],"type":"Point"}
}