{
  "type": "Feature",
  "properties": {
    "addr:full":"56 Ghuznee St  Wellington Wellington",
    "addr:housenumber":"56",
    "addr:street":"Ghuznee St",
    "iso:country":"NZ",
    "sg:address":"56 Ghuznee St ",
    "sg:city":"Wellington",
    "sg:classifiers":[
        {
            "category":"Retail",
            "subcategory":"Laundry & Dry Cleaning",
            "type":"Services"
        }
    ],
    "sg:phone":"+64 4-384 5874",
    "sg:province":"Wellington",
    "sg:tags":[
        "repair",
        "clothing",
        "fabric",
        "cleaner"
    ],
    "wof:name":"Rupal Shoes & Bag Repairs & Drycleaning",
    "wof:placetype":"venue"
},
  "geometry": {"coordinates":[174.77562,-41.293106],"type":"Point"}
}