{
  "type": "Feature",
  "properties": {
    "iso:country":"NZ",
    "sg:address":"96 Miro St ",
    "sg:city":"Ohakune",
    "sg:classifiers":[
        {
            "category":"Sports & Exercise",
            "subcategory":"Playing Field",
            "type":"Entertainment"
        }
    ],
    "sg:phone":"+64 6-385 8573",
    "sg:tags":[
        "skiing",
        "ski",
        "leisure",
        "sports"
    ],
    "wof:name":"Snowliner Shuttle",
    "wof:placetype":"venue"
},
  "geometry": {"coordinates":[175.413834,-39.406551],"type":"Point"}
}