{
  "type": "Feature",
  "properties": {
    "addr:full":"101 Duke St Frankton  Hamilton Waikato",
    "addr:housenumber":"101",
    "addr:street":"Duke St",
    "iso:country":"NZ",
    "sg:address":"101 Duke St Frankton ",
    "sg:city":"Hamilton",
    "sg:orig_category":"Industrial: Metal: Services: Steel Processing",
    "sg:phone":"+64 7-847 7526",
    "sg:province":"Waikato",
    "wof:name":"Waikato Steel Fabricators",
    "wof:placetype":"venue"
},
  "geometry": {"coordinates":[175.25709499999999,-37.80164],"type":"Point"}
}