{
  "type": "Feature",
  "properties": {
    "iso:country":"NZ",
    "sg:address":"139 Cascades Rd Pakuranga ",
    "sg:city":"Auckland",
    "sg:classifiers":[
        {
            "category":"Retail",
            "subcategory":"Auto Repair",
            "type":"Services"
        }
    ],
    "sg:phone":"+64 9-576 5971",
    "sg:province":"Auckland",
    "sg:tags":[
        "automotive",
        "servicing"
    ],
    "wof:name":"Cascade Motors Ltd",
    "wof:placetype":"venue"
},
  "geometry": {"coordinates":[174.90231299999999,-36.913418],"type":"Point"}
}