{
  "type": "Feature",
  "properties": {
    "iso:country":"NZ",
    "sg:address":"82 Austin St Onekawa ",
    "sg:city":"Napier",
    "sg:classifiers":[
        {
            "category":"Home & Garden",
            "subcategory":"Building Materials",
            "type":"Retail Goods"
        }
    ],
    "sg:phone":"+64 6-843 7391",
    "sg:province":"Hawke's Bay",
    "sg:tags":[
        "design",
        "fitting",
        "fittings",
        "kitchen"
    ],
    "wof:name":"Custom Built Joinery",
    "wof:placetype":"venue"
},
  "geometry": {"coordinates":[176.87841800000001,-39.499508],"type":"Point"}
}