{
  "type": "Feature",
  "properties": {
    "addr:full":"Caswell St Te  Anau Southland",
    "addr:street":"Caswell St",
    "iso:country":"NZ",
    "sg:address":"Caswell St Te ",
    "sg:city":"Anau",
    "sg:orig_category":"Industrial: Metal: Products: Aluminium Products",
    "sg:phone":"+64 3-249 8180",
    "sg:province":"Southland",
    "wof:name":"Fiordland Aluminium & Joinery",
    "wof:placetype":"venue"
},
  "geometry": {"coordinates":[167.73002600000001,-45.410892],"type":"Point"}
}