{
  "type": "Feature",
  "properties": {
    "iso:country":"NZ",
    "sg:address":"Greenmeadows Shopping Ctr Greenmeadows ",
    "sg:city":"Napier",
    "sg:orig_category":"Shopping: Gifts: Gift Baskets",
    "sg:phone":"+64 6-844 6185",
    "sg:province":"Hawke's Bay",
    "wof:name":"On Impulse",
    "wof:placetype":"venue"
},
  "geometry": {"coordinates":[176.856247,-39.520939],"type":"Point"}
}