{
  "type": "Feature",
  "properties": {
    "addr:full":"134 Riri St  Rotorua Bay of Plenty",
    "addr:housenumber":"134",
    "addr:street":"Riri St",
    "iso:country":"NZ",
    "sg:address":"134 Riri St ",
    "sg:city":"Rotorua",
    "sg:orig_category":"Farming: Forestry: Logging Services",
    "sg:phone":"+64 7-348 6938",
    "sg:province":"Bay of Plenty",
    "wof:name":"Gracie W L & Associates Ltd",
    "wof:placetype":"venue"
},
  "geometry": {"coordinates":[176.22669999999999,-38.134129],"type":"Point"}
}