{
  "type": "Feature",
  "properties": {
    "addr:full":"117 A Ponsonby Rd Ponsonby  Auckland Auckland",
    "addr:housenumber":"117 a",
    "addr:street":"Ponsonby Rd",
    "iso:country":"NZ",
    "sg:address":"117 A Ponsonby Rd Ponsonby ",
    "sg:city":"Auckland",
    "sg:classifiers":[
        {
            "category":"Personal",
            "subcategory":"Beauty Salon",
            "type":"Services"
        }
    ],
    "sg:phone":"+64 9-376 6461",
    "sg:province":"Auckland",
    "sg:tags":[
        "therapy",
        "health"
    ],
    "wof:name":"Persona Image & Beauty Therapy Studio",
    "wof:placetype":"venue"
},
  "geometry": {"coordinates":[174.746567,-36.855755],"type":"Point"}
}