{
  "type": "Feature",
  "properties": {
    "iso:country":"NZ",
    "sg:address":"36 Cameron St ",
    "sg:city":"Whangarei",
    "sg:orig_category":"Clothing And Fabric: Clothing: Jeans",
    "sg:phone":"+64 9-438 8670",
    "sg:province":"Northland",
    "wof:name":"Jeans West Corporation",
    "wof:placetype":"venue"
},
  "geometry": {"coordinates":[174.32110599999999,-35.725647],"type":"Point"}
}