{
  "type": "Feature",
  "properties": {
    "addr:full":"125 Ingestre St  Wanganui Manawatu-Wanganui",
    "addr:housenumber":"125",
    "addr:street":"Ingestre St",
    "iso:country":"NZ",
    "sg:address":"125 Ingestre St ",
    "sg:city":"Wanganui",
    "sg:orig_category":"Industrial: Packaging: Packaging - General",
    "sg:phone":"+64 6-347 1444",
    "sg:province":"Manawatu-Wanganui",
    "wof:name":"Workforce Supplies",
    "wof:placetype":"venue"
},
  "geometry": {"coordinates":[175.045502,-39.932709],"type":"Point"}
}