{
  "type": "Feature",
  "properties": {
    "iso:country":"NZ",
    "sg:address":"15 Newbery St Opawa ",
    "sg:city":"Christchurch",
    "sg:classifiers":[
        {
            "category":"Professional",
            "type":"Services"
        }
    ],
    "sg:phone":"+64 3-332 2503",
    "sg:province":"Canterbury",
    "sg:tags":[
        "function",
        "entertainment",
        "leisure",
        "planning",
        "party",
        "sport"
    ],
    "sg:website":"http://www.newberylodge.co.nz",
    "wof:name":"Newbery Lodge",
    "wof:placetype":"venue"
},
  "geometry": {"coordinates":[172.663422,-43.556431],"type":"Point"}
}