{
  "type": "Feature",
  "properties": {
    "addr:full":"18 a Marybank Rd Atawhai  Nelson Nelson",
    "addr:housenumber":"18",
    "addr:street":"A Marybank Rd",
    "iso:country":"NZ",
    "sg:address":"18 a Marybank Rd Atawhai ",
    "sg:city":"Nelson",
    "sg:classifiers":[
        {
            "category":"Sports & Exercise",
            "subcategory":"Athletic Track",
            "type":"Entertainment"
        }
    ],
    "sg:phone":"+64 3-545 2006",
    "sg:province":"Nelson",
    "sg:tags":[
        "aerial",
        "para",
        "gliding",
        "hang",
        "leisure",
        "sports"
    ],
    "wof:name":"Adventure Paragliding",
    "wof:placetype":"venue"
},
  "geometry": {"coordinates":[173.316666,-41.237453],"type":"Point"}
}