{
  "type": "Feature",
  "properties": {
    "addr:full":"90 Wairau Rd Glenfield  Auckland Auckland",
    "addr:housenumber":"90",
    "addr:street":"Wairau Rd",
    "iso:country":"NZ",
    "sg:address":"90 Wairau Rd Glenfield ",
    "sg:city":"Auckland",
    "sg:classifiers":[
        {
            "category":"Manufacturing",
            "subcategory":"Glass & Minerals",
            "type":"Manufacturing & Wholesale Goods"
        }
    ],
    "sg:phone":"+64 9-443 3430",
    "sg:province":"Auckland",
    "sg:tags":[
        "chemical",
        "fibre",
        "industrial",
        "compounds"
    ],
    "wof:name":"A.C.E. Systems",
    "wof:placetype":"venue"
},
  "geometry": {"coordinates":[174.74314899999999,-36.775761],"type":"Point"}
}