{
  "type": "Feature",
  "properties": {
    "iso:country":"NZ",
    "sg:address":"Shop 22 Trafalgar Square 33 Taupo Qy ",
    "sg:city":"Wanganui",
    "sg:classifiers":[
        {
            "category":"Shopping",
            "subcategory":"Gifts & Souvenirs",
            "type":"Retail Goods"
        }
    ],
    "sg:phone":"+64 6-348 9095",
    "sg:province":"Nelson",
    "sg:tags":[
        "shop",
        "gifts",
        "supplier"
    ],
    "wof:name":"Special Spot",
    "wof:placetype":"venue"
},
  "geometry": {"coordinates":[-0.12799,51.507961],"type":"Point"}
}