{
  "type": "Feature",
  "properties": {
    "iso:country":"NZ",
    "sg:address":"101 Heu Heu St ",
    "sg:city":"Taupo",
    "sg:orig_category":"Health And Beauty: Specialists: Osteopaths",
    "sg:phone":"+64 7-378 1690",
    "sg:province":"Waikato",
    "wof:name":"Berkahn Fiona",
    "wof:placetype":"venue"
},
  "geometry": {"coordinates":[176.07515,-38.688961],"type":"Point"}
}