{
  "type": "Feature",
  "properties": {
    "iso:country":"NZ",
    "sg:address":"Jellicoe Ct ",
    "sg:city":"Kawerau",
    "sg:classifiers":[
        {
            "category":"Communications",
            "subcategory":"Film & Video Production",
            "type":"Services"
        }
    ],
    "sg:phone":"+64 7-323 7855",
    "sg:tags":[
        "sport",
        "leisure",
        "library",
        "entertainment"
    ],
    "wof:name":"Video Ezy",
    "wof:placetype":"venue"
},
  "geometry": {"coordinates":[176.70210299999999,-38.087158],"type":"Point"}
}