{
  "type": "Feature",
  "properties": {
    "iso:country":"NZ",
    "sg:address":"135 Constable St Newtown ",
    "sg:city":"Wellington",
    "sg:classifiers":[
        {
            "category":"Social Services",
            "subcategory":"Retirement Home",
            "type":"Services"
        }
    ],
    "sg:phone":"+64 4-389 7007",
    "sg:province":"Wellington",
    "sg:tags":[
        "elderly",
        "convalescent",
        "garden",
        "rest",
        "care"
    ],
    "wof:name":"Hadleigh Retirement Home & Hospital",
    "wof:placetype":"venue"
},
  "geometry": {"coordinates":[174.787689,-41.312538],"type":"Point"}
}