{
  "type": "Feature",
  "properties": {
    "iso:country":"NZ",
    "sg:address":"18 Jasper Pl Palmerston ",
    "sg:city":"Palmerston North",
    "sg:classifiers":[
        {
            "category":"Shopping",
            "subcategory":"Crafts & Fabrics",
            "type":"Retail Goods"
        }
    ],
    "sg:phone":"+64 6-354 5172",
    "sg:province":"Manawatu-Wanganui",
    "sg:tags":[
        "clothing"
    ],
    "wof:name":"Golden Fleece Wools Ltd",
    "wof:placetype":"venue"
},
  "geometry": {"coordinates":[175.599442,-40.339542],"type":"Point"}
}