{
  "type": "Feature",
  "properties": {
    "addr:full":"142 Somme Pde  Wanganui Manawatu-Wanganui",
    "addr:housenumber":"142;pde",
    "addr:street":"Somme",
    "iso:country":"NZ",
    "sg:address":"142 Somme Pde ",
    "sg:city":"Wanganui",
    "sg:orig_category":"Health And Beauty: Products: Pharmacies",
    "sg:phone":"+64 6-343 8155",
    "sg:province":"Manawatu-Wanganui",
    "wof:name":"Stimpsons Pharmacy",
    "wof:placetype":"venue"
},
  "geometry": {"coordinates":[175.05406199999999,-39.909943],"type":"Point"}
}