{
  "type": "Feature",
  "properties": {
    "addr:full":"245 Cambridge Rd Hillcrest  Hamilton Waikato",
    "addr:housenumber":"245",
    "addr:street":"Cambridge Rd",
    "iso:country":"NZ",
    "sg:address":"245 Cambridge Rd Hillcrest ",
    "sg:city":"Hamilton",
    "sg:classifiers":[
        {
            "category":"Food & Beverages",
            "subcategory":"Cheese",
            "type":"Retail Goods"
        }
    ],
    "sg:phone":"+64 7-856 6633",
    "sg:province":"Waikato",
    "sg:tags":[
        "merchant",
        "drink",
        "-"
    ],
    "wof:name":"Gouda Cheese Shop",
    "wof:placetype":"venue"
},
  "geometry": {"coordinates":[175.32164,-37.800709],"type":"Point"}
}