{
  "type": "Feature",
  "properties": {
    "iso:country":"NZ",
    "sg:address":"81 Manchester St ",
    "sg:city":"Christchurch",
    "sg:orig_category":"Shopping: Sports Retailers: Cycles",
    "sg:phone":"+64 3-366 3773",
    "sg:province":"Canterbury",
    "sg:website":"http://www.scottybrowns.com",
    "wof:name":"Scotty Brown's Cyclesave",
    "wof:placetype":"venue"
},
  "geometry": {"coordinates":[-76.537834,37.605659],"type":"Point"}
}