{
  "type": "Feature",
  "properties": {
    "iso:country":"NZ",
    "sg:address":"Auckland PO Box 91307 Auckland Mail Centre ",
    "sg:city":"Auckland",
    "sg:orig_category":"Transport: Distribution - General: Distributors",
    "sg:phone":"+64 21 647 466",
    "sg:province":"Auckland",
    "wof:name":"Saben Ltd",
    "wof:placetype":"venue"
},
  "geometry": {"coordinates":[-119.104576,36.597755],"type":"Point"}
}