{
  "type": "Feature",
  "properties": {
    "addr:full":"30 Bisley St Palmerston  Palmerston North Manawatu-Wanganui",
    "addr:housenumber":"30",
    "addr:street":"Bisley St Palmerston",
    "iso:country":"NZ",
    "sg:address":"30 Bisley St Palmerston ",
    "sg:city":"Palmerston North",
    "sg:classifiers":[
        {
            "category":"Building & Trades",
            "subcategory":"Pest Control",
            "type":"Services"
        }
    ],
    "sg:phone":"+64 6-357 7695",
    "sg:province":"Manawatu-Wanganui",
    "sg:tags":[
        "home",
        "garden"
    ],
    "wof:name":"Ace Fly & Insect Busters",
    "wof:placetype":"venue"
},
  "geometry": {"coordinates":[175.59350599999999,-40.339184],"type":"Point"}
}