{
  "type": "Feature",
  "properties": {
    "addr:full":"390 Heads Rd  Wanganui Manawatu-Wanganui",
    "addr:housenumber":"390",
    "addr:street":"Heads Rd",
    "iso:country":"NZ",
    "sg:address":"390 Heads Rd ",
    "sg:city":"Wanganui",
    "sg:orig_category":"Transport: Transportation: Transport Operators",
    "sg:phone":"+64 6-343 6862",
    "sg:province":"Manawatu-Wanganui",
    "wof:name":"Dave Hoskin Carriers Ltd",
    "wof:placetype":"venue"
},
  "geometry": {"coordinates":[175.01014699999999,-39.947643],"type":"Point"}
}