{
  "type": "Feature",
  "properties": {
    "addr:full":"45 Ardmore St  Wanaka Otago",
    "addr:housenumber":"45",
    "addr:street":"Ardmore St",
    "iso:country":"NZ",
    "sg:address":"45 Ardmore St ",
    "sg:city":"Wanaka",
    "sg:classifiers":[
        {
            "category":"Travel",
            "subcategory":"Travel Agent",
            "type":"Entertainment"
        }
    ],
    "sg:phone":"+64 3-443 1599",
    "sg:province":"Otago",
    "sg:tags":[
        "tourism",
        "-",
        "accommodation",
        "booking"
    ],
    "wof:name":"Wanaka Reservations",
    "wof:placetype":"venue"
},
  "geometry": {"coordinates":[169.136765,-44.693958],"type":"Point"}
}