{
  "type": "Feature",
  "properties": {
    "iso:country":"NZ",
    "sg:address":"330 Dominion Rd Mt Eden Private Bag 56909 Dominion, Road ",
    "sg:city":"Auckland",
    "sg:classifiers":[
        {
            "category":"Communications",
            "subcategory":"Film & Video Production",
            "type":"Services"
        }
    ],
    "sg:phone":"+64 9-630 7333",
    "sg:province":"Auckland",
    "sg:tags":[
        "broadcasting",
        "studio",
        "producer"
    ],
    "wof:name":"Greenstone Pictures Limited",
    "wof:placetype":"venue"
},
  "geometry": {"coordinates":[174.770416,-36.884109],"type":"Point"}
}