{
  "type": "Feature",
  "properties": {
    "addr:full":"12 Dodsons Valley Rd  Nelson Nelson",
    "addr:housenumber":"12",
    "addr:street":"Dodsons Valley Rd",
    "iso:country":"NZ",
    "sg:address":"12 Dodsons Valley Rd ",
    "sg:city":"Nelson",
    "sg:classifiers":[
        {
            "category":"Social Services",
            "subcategory":"Child Care",
            "type":"Services"
        }
    ],
    "sg:phone":"+64 3-545 2233",
    "sg:province":"Nelson",
    "sg:tags":[
        "home",
        "garden",
        "children"
    ],
    "wof:name":"Atawhai Montessori",
    "wof:placetype":"venue"
},
  "geometry": {"coordinates":[-121.765488,39.553471],"type":"Point"}
}