{
  "type": "Feature",
  "properties": {
    "iso:country":"NZ",
    "sg:address":"10 London Qy ",
    "sg:city":"Picton",
    "sg:classifiers":[
        {
            "category":"Landmark",
            "subcategory":"Tourist Information",
            "type":"Public Place"
        }
    ],
    "sg:phone":"+64 3-573 8843",
    "sg:province":"Marlborough",
    "sg:tags":[
        "travel",
        "tourism",
        "tour",
        "sightseeing"
    ],
    "sg:website":"http://www.soundsconnection.co.nz",
    "wof:name":"Sounds Connection",
    "wof:placetype":"venue"
},
  "geometry": {"coordinates":[-2.846859,53.236282],"type":"Point"}
}