{
  "type": "Feature",
  "properties": {
    "iso:country":"NZ",
    "sg:address":"First Floor 154 Queen St Auckland Central ",
    "sg:city":"Auckland",
    "sg:classifiers":[
        {
            "category":"Internet Cafe",
            "subcategory":"None",
            "type":"Food & Drink"
        }
    ],
    "sg:phone":"+64 9-309 8897",
    "sg:province":"Auckland",
    "sg:tags":[
        "wining",
        "dining"
    ],
    "wof:name":"iPlay Internet Centre",
    "wof:placetype":"venue"
},
  "geometry": {"coordinates":[174.7659,-36.847675],"type":"Point"}
}