{
  "type": "Feature",
  "properties": {
    "addr:full":"12 Clarkson Ave  Wanganui Manawatu-Wanganui",
    "addr:housenumber":"12",
    "addr:street":"Clarkson Ave",
    "iso:country":"NZ",
    "sg:address":"12 Clarkson Ave ",
    "sg:city":"Wanganui",
    "sg:classifiers":[
        {
            "category":"Social Services",
            "subcategory":"Child Care",
            "type":"Services"
        }
    ],
    "sg:phone":"+64 6-344 7220",
    "sg:province":"Manawatu-Wanganui",
    "sg:tags":[
        "home",
        "garden",
        "children"
    ],
    "wof:name":"Barnardos New Zealand",
    "wof:placetype":"venue"
},
  "geometry": {"coordinates":[175.00668300000001,-39.924507],"type":"Point"}
}