{
  "type": "Feature",
  "properties": {
    "iso:country":"NZ",
    "sg:address":"9 The Square Manor Park Lower ",
    "sg:city":"Hutt",
    "sg:classifiers":[
        {
            "category":"Home & Garden",
            "subcategory":"Furniture",
            "type":"Retail Goods"
        }
    ],
    "sg:phone":"+64 4-563 7502",
    "sg:province":"Wellington",
    "sg:tags":[
        "furniture/furnishings",
        "repair",
        "finishing"
    ],
    "wof:name":"D & D Furniture Repairs",
    "wof:placetype":"venue"
},
  "geometry": {"coordinates":[174.980179,-41.156868],"type":"Point"}
}