{
  "type": "Feature",
  "properties": {
    "iso:country":"NZ",
    "sg:address":"PO Box 925 ",
    "sg:city":"Hamilton",
    "sg:classifiers":[
        {
            "category":"Utilities",
            "subcategory":"Cable",
            "type":"Services"
        }
    ],
    "sg:phone":"+64 7-838 1399",
    "sg:province":"Waikato",
    "sg:tags":[
        "electricity",
        "energy",
        "industrial",
        "utilities",
        "supply"
    ],
    "sg:website":"http://www.wel.co.nz",
    "wof:name":"WEL Networks Ltd",
    "wof:placetype":"venue"
},
  "geometry": {"coordinates":[-114.170662,46.252956],"type":"Point"}
}