{
  "type": "Feature",
  "properties": {
    "iso:country":"NZ",
    "sg:address":"6 /11 View Rd Henderson ",
    "sg:city":"Auckland",
    "sg:orig_category":"Industrial: Packaging: Packaging Machinery",
    "sg:phone":"+64 9-837 2100",
    "sg:province":"Auckland",
    "wof:name":"Electro Engineering Ltd, For Manual Stretch Film Wrappers",
    "wof:placetype":"venue"
},
  "geometry": {"coordinates":[174.632812,-36.886375],"type":"Point"}
}