{
  "type": "Feature",
  "properties": {
    "iso:country":"NZ",
    "sg:address":"31 Hurndal St ",
    "sg:city":"Maungaturoto",
    "sg:classifiers":[
        {
            "category":"Retail",
            "subcategory":"Auto Repair",
            "type":"Services"
        }
    ],
    "sg:phone":"+64 9-431 8281",
    "sg:tags":[
        "automotive",
        "panel",
        "servicing",
        "beater"
    ],
    "wof:name":"Maungaturoto Panelbeaters Ltd",
    "wof:placetype":"venue"
},
  "geometry": {"coordinates":[174.358597,-36.109028],"type":"Point"}
}