{
  "type": "Feature",
  "properties": {
    "addr:full":"37 Korau Grove Stokes Valley Lower  Hutt Wellington",
    "addr:housenumber":"37",
    "addr:street":"Korau Grove",
    "iso:country":"NZ",
    "sg:address":"37 Korau Grove Stokes Valley Lower ",
    "sg:city":"Hutt",
    "sg:orig_category":"Home And Garden: Gardening: Services: Lawnmowing Services",
    "sg:phone":"+64 4-570 0110",
    "sg:province":"Wellington",
    "wof:name":"Green Acres Lawnmowing",
    "wof:placetype":"venue"
},
  "geometry": {"coordinates":[174.98187300000001,-41.17495],"type":"Point"}
}