{
  "type": "Feature",
  "properties": {
    "addr:full":"Dunedin PO Box  296",
    "addr:housenumber":"box 296",
    "iso:country":"NZ",
    "sg:address":"Dunedin PO Box ",
    "sg:city":"296",
    "sg:orig_category":"Automotive: Parts And Supplies: Windscreens",
    "sg:phone":"+64 3-455 1950",
    "wof:name":"Ultra Bond Windscreen Repairs",
    "wof:placetype":"venue"
},
  "geometry": {"coordinates":[-82.784729,28.013371],"type":"Point"}
}