{
  "type": "Feature",
  "properties": {
    "addr:full":"Merriland Shopping Centre Mangorei Rd New  Plymouth Taranaki",
    "addr:street":"Mangorei Rd",
    "iso:country":"NZ",
    "sg:address":"Merriland Shopping Centre Mangorei Rd New ",
    "sg:city":"Plymouth",
    "sg:orig_category":"Shopping: Retail Stores: Lotto Outlets",
    "sg:phone":"+64 6-758 0753",
    "sg:province":"Taranaki",
    "wof:name":"Merriland Lotto & Post",
    "wof:placetype":"venue"
},
  "geometry": {"coordinates":[174.074005,-39.058292],"type":"Point"}
}