{
  "type": "Feature",
  "properties": {
    "addr:full":"Heatherlea Rd  Levin Manawatu-Wanganui",
    "addr:street":"Heatherlea Rd",
    "iso:country":"NZ",
    "sg:address":"Heatherlea Rd ",
    "sg:city":"Levin",
    "sg:orig_category":"Transport: Transportation: Furniture Removal/Packers",
    "sg:phone":"+64 6-368 2357",
    "sg:province":"Manawatu-Wanganui",
    "wof:name":"Budget Removal",
    "wof:placetype":"venue"
},
  "geometry": {"coordinates":[175.299072,-40.592625],"type":"Point"}
}