{
  "type": "Feature",
  "properties": {
    "addr:full":"Classique Lodge Gorrie Rd R D Upper  Hutt Wellington",
    "addr:street":"Gorrie Rd R D",
    "iso:country":"NZ",
    "sg:address":"Classique Lodge Gorrie Rd R D Upper ",
    "sg:city":"Hutt",
    "sg:orig_category":"Health And Beauty: Mental: Psychology",
    "sg:phone":"+64 4-528 5429",
    "sg:province":"Wellington",
    "wof:name":"John Moynihan",
    "wof:placetype":"venue"
},
  "geometry": {"coordinates":[175.069031,-41.12458],"type":"Point"}
}