{
  "type": "Feature",
  "properties": {
    "iso:country":"NZ",
    "sg:address":"Cnr Chatham Rd & Caernarvon Dve Flaxmere ",
    "sg:city":"Hastings",
    "sg:orig_category":"Health And Beauty: Specialists: Physiotherapists",
    "sg:phone":"+64 6-873 9026",
    "sg:province":"Hawke's Bay",
    "wof:name":"Flaxmere Health",
    "wof:placetype":"venue"
},
  "geometry": {"coordinates":[176.78323399999999,-39.623001],"type":"Point"}
}