{
  "type": "Feature",
  "properties": {
    "addr:full":"cnr Mill Rd & Main Hwy  Otaki",
    "addr:street":"Cnr Mill Rd & Main Hwy",
    "iso:country":"NZ",
    "sg:address":"cnr Mill Rd & Main Hwy ",
    "sg:city":"Otaki",
    "sg:classifiers":[
        {
            "category":"Retail",
            "subcategory":"Auto Repair",
            "type":"Services"
        }
    ],
    "sg:phone":"+64 6-364 7171",
    "sg:tags":[
        "breakdown",
        "automotive",
        "towing",
        "servicing"
    ],
    "wof:name":"Otaki Motors & Auto Electrical",
    "wof:placetype":"venue"
},
  "geometry": {"coordinates":[175.14880400000001,-40.75914],"type":"Point"}
}