{
  "type": "Feature",
  "properties": {
    "iso:country":"NZ",
    "sg:address":"8/78 Henderson Valley Rd Henderson ",
    "sg:city":"Auckland",
    "sg:classifiers":[
        {
            "category":"Retail",
            "subcategory":"Auto Repair",
            "type":"Services"
        }
    ],
    "sg:phone":"+64 9-836 3204",
    "sg:province":"Auckland",
    "sg:tags":[
        "automotive",
        "panel",
        "servicing",
        "beater"
    ],
    "wof:name":"Europro Limited",
    "wof:placetype":"venue"
},
  "geometry": {"coordinates":[174.626907,-36.888958],"type":"Point"}
}