{
  "type": "Feature",
  "properties": {
    "iso:country":"NZ",
    "sg:address":"36 Tacy St Evans Bay ",
    "sg:city":"Wellington",
    "sg:classifiers":[
        {
            "category":"Restaurant",
            "type":"Food & Drink"
        }
    ],
    "sg:phone":"+64 4-387 7545",
    "sg:province":"Wellington",
    "sg:tags":[
        "catering",
        "supply"
    ],
    "wof:name":"Hawley Andrew Ltd",
    "wof:placetype":"venue"
},
  "geometry": {"coordinates":[174.908569,-41.278835],"type":"Point"}
}