{
  "type": "Feature",
  "properties": {
    "iso:country":"NZ",
    "sg:address":"4 Kokako St ",
    "sg:city":"Rotorua",
    "sg:classifiers":[
        {
            "category":"Shopping",
            "subcategory":"Bicycles & Sporting Goods",
            "type":"Retail Goods"
        }
    ],
    "sg:phone":"+64 7-346 2123",
    "sg:province":"Bay of Plenty",
    "sg:tags":[
        "cycle",
        "sport",
        "sale",
        "retailers",
        "cycles"
    ],
    "wof:name":"Selwyn Cycles",
    "wof:placetype":"venue"
},
  "geometry": {"coordinates":[176.223129,-38.117577],"type":"Point"}
}