{
  "type": "Feature",
  "properties": {
    "addr:full":"10 Oak Rd Manukau City  Auckland Auckland",
    "addr:housenumber":"10",
    "addr:street":"Oak Rd",
    "iso:country":"NZ",
    "sg:address":"10 Oak Rd Manukau City ",
    "sg:city":"Auckland",
    "sg:orig_category":"Industrial: Instruments: Alignment And Balancing",
    "sg:phone":"+64 9-263 7761",
    "sg:province":"Auckland",
    "wof:name":"Driveshaft Centre (Beatty's)",
    "wof:placetype":"venue"
},
  "geometry": {"coordinates":[174.88145399999999,-36.98967],"type":"Point"}
}