{
  "type": "Feature",
  "properties": {
    "iso:country":"NZ",
    "sg:address":"Mt Horrible Rd Claremont ",
    "sg:city":"Timaru",
    "sg:classifiers":[
        {
            "category":"Personal",
            "type":"Services"
        }
    ],
    "sg:phone":"+64 3-686 2950",
    "sg:province":"Canterbury",
    "sg:tags":[
        "arrangements",
        "wedding"
    ],
    "wof:name":"Castle Claremont",
    "wof:placetype":"venue"
},
  "geometry": {"coordinates":[171.23739599999999,-44.395432],"type":"Point"}
}