{
  "type": "Feature",
  "properties": {
    "iso:country":"NZ",
    "sg:address":"1/1 Amyes Rd Hornby ",
    "sg:city":"Christchurch",
    "sg:classifiers":[
        {
            "category":"Shopping",
            "subcategory":"Pets & Pet Supplies",
            "type":"Retail Goods"
        }
    ],
    "sg:phone":"+64 3-349 7559",
    "sg:province":"Canterbury",
    "sg:tags":[
        "home",
        "grooming",
        "garden",
        "pets"
    ],
    "wof:name":"Brushworkz - Pet Grooming Salon",
    "wof:placetype":"venue"
},
  "geometry": {"coordinates":[172.525558,-43.545399],"type":"Point"}
}