{
  "type": "Feature",
  "properties": {
    "iso:country":"NZ",
    "sg:address":"226 Dominion Rd ",
    "sg:city":"Auckland",
    "sg:orig_category":"Shopping: Hobbies And Games: Collectables",
    "sg:phone":"+64 9-378 8547",
    "sg:province":"Auckland",
    "wof:name":"Veneer Collectables",
    "wof:placetype":"venue"
},
  "geometry": {"coordinates":[-119.104576,36.597755],"type":"Point"}
}