{
  "type": "Feature",
  "properties": {
    "addr:full":"PO Box 34531 Birkenhead  Auckland Auckland",
    "addr:housenumber":"po box 34531",
    "iso:country":"NZ",
    "sg:address":"PO Box 34531 Birkenhead ",
    "sg:city":"Auckland",
    "sg:classifiers":[
        {
            "category":"Education",
            "subcategory":"University",
            "type":"Public Place"
        }
    ],
    "sg:phone":"+64 9-480 4405",
    "sg:province":"Auckland",
    "sg:tags":[
        "training",
        "instruction",
        "language"
    ],
    "wof:name":"Immanuel Education Ltd",
    "wof:placetype":"venue"
},
  "geometry": {"coordinates":[174.734467,-36.818214],"type":"Point"}
}