{
  "type": "Feature",
  "properties": {
    "addr:full":"17 Homestead Rd  Kerikeri Northland",
    "addr:housenumber":"17",
    "addr:street":"Homestead Rd",
    "iso:country":"NZ",
    "sg:address":"17 Homestead Rd ",
    "sg:city":"Kerikeri",
    "sg:classifiers":[
        {
            "category":"Travel",
            "subcategory":"Hotels & Motels",
            "type":"Entertainment"
        }
    ],
    "sg:phone":"+64 800 222 407",
    "sg:province":"Northland",
    "sg:tags":[
        "lodge",
        "tourism",
        "accommodation"
    ],
    "sg:website":"http://www.kerikerihomesteadmotel.co.nz",
    "wof:name":"Kerikeri Homestead Motel",
    "wof:placetype":"venue"
},
  "geometry": {"coordinates":[173.94717399999999,-35.227131],"type":"Point"}
}