{
  "type": "Feature",
  "properties": {
    "addr:full":"Cnr Woods Rd & Commerce St  Whangarei Northland",
    "addr:street":"Cnr Woods Rd & Commerce St",
    "iso:country":"NZ",
    "sg:address":"Cnr Woods Rd & Commerce St ",
    "sg:city":"Whangarei",
    "sg:classifiers":[
        {
            "category":"Autos & Motor Vehicles",
            "subcategory":"Automobile Sales",
            "type":"Retail Goods"
        }
    ],
    "sg:phone":"+64 9-430 3000",
    "sg:province":"Northland",
    "sg:tags":[
        "car",
        "-used",
        "leasing",
        "truck",
        "automotive"
    ],
    "wof:name":"Euro Cars Northland LMVD",
    "wof:placetype":"venue"
},
  "geometry": {"coordinates":[174.320526,-35.725399],"type":"Point"}
}