{
  "type": "Feature",
  "properties": {
    "iso:country":"NZ",
    "sg:address":"57 View Rd Glenfield ",
    "sg:city":"Auckland",
    "sg:orig_category":"Industrial: Services",
    "sg:phone":"+64 9-444 5199",
    "sg:province":"Auckland",
    "sg:website":"http://www.yellowpages.co.nz/for/mascot/dp12580.html",
    "wof:name":"Mascot Diecasters Ltd",
    "wof:placetype":"venue"
},
  "geometry": {"coordinates":[174.735916,-36.771641],"type":"Point"}
}