{
  "type": "Feature",
  "properties": {
    "iso:country":"NZ",
    "sg:address":"151 The Parade Island Bay ",
    "sg:city":"Wellington",
    "sg:orig_category":"Shopping: Retail Stores: Books: Bookshops",
    "sg:phone":"+64 4-383 7102",
    "sg:province":"Auckland",
    "wof:name":"Island Bay Stationers",
    "wof:placetype":"venue"
},
  "geometry": {"coordinates":[174.77349899999999,-41.335121],"type":"Point"}
}