{
  "type": "Feature",
  "properties": {
    "addr:full":"33 Victoria Ave  Wanganui Manawatu-Wanganui",
    "addr:housenumber":"33",
    "addr:street":"Victoria Ave",
    "iso:country":"NZ",
    "sg:address":"33 Victoria Ave ",
    "sg:city":"Wanganui",
    "sg:classifiers":[
        {
            "category":"Home & Garden",
            "subcategory":"Home Furnishings",
            "type":"Retail Goods"
        }
    ],
    "sg:phone":"+64 6-345 4554",
    "sg:province":"Manawatu-Wanganui",
    "sg:tags":[
        "furniture/furnishings",
        "bedding",
        "bed"
    ],
    "wof:name":"Wanganui Furnishers",
    "wof:placetype":"venue"
},
  "geometry": {"coordinates":[175.05432099999999,-39.934414],"type":"Point"}
}