{
  "type": "Feature",
  "properties": {
    "iso:country":"NZ",
    "sg:address":"48 Broadway Newmarket ",
    "sg:city":"Auckland",
    "sg:classifiers":[
        {
            "category":"Health Services",
            "subcategory":"Hospital",
            "type":"Services"
        }
    ],
    "sg:phone":"+64 9-520 6731",
    "sg:province":"Manawatu-Wanganui",
    "sg:tags":[
        "medical",
        "beauty"
    ],
    "wof:name":"L'unova",
    "wof:placetype":"venue"
},
  "geometry": {"coordinates":[174.779175,-36.865265],"type":"Point"}
}