{
  "type": "Feature",
  "properties": {
    "iso:country":"NZ",
    "sg:address":"Leinster House 158 Leinster Rd Merivale ",
    "sg:city":"Christchurch",
    "sg:classifiers":[
        {
            "category":"Fast Food",
            "type":"Food & Drink"
        }
    ],
    "sg:phone":"+64 3-355 8330",
    "sg:province":"Canterbury",
    "sg:tags":[
        "wining",
        "dining",
        "takeaway"
    ],
    "wof:name":"Little India Bistro & Tandoor",
    "wof:placetype":"venue"
},
  "geometry": {"coordinates":[172.620758,-43.514442],"type":"Point"}
}