{
  "type": "Feature",
  "properties": {
    "iso:country":"NZ",
    "sg:address":"PO Box 283 ",
    "sg:city":"Rangiora",
    "sg:orig_category":"Home And Garden: Gardening: Services: Tree Services",
    "sg:phone":"+64 3-313 4393",
    "sg:province":"Canterbury",
    "wof:name":"Ford Graeme Tree Services",
    "wof:placetype":"venue"
},
  "geometry": {"coordinates":[172.59030200000001,-43.302963],"type":"Point"}
}