{
  "type": "Feature",
  "properties": {
    "iso:country":"NZ",
    "sg:address":"Homedale Rd Wainuiomata Lower ",
    "sg:city":"Hutt",
    "sg:classifiers":[
        {
            "category":"Health Services",
            "subcategory":"Dentist",
            "type":"Services"
        }
    ],
    "sg:phone":"+64 4-564 8321",
    "sg:province":"Wellington",
    "sg:tags":[
        "dental",
        "clinic",
        "beauty"
    ],
    "wof:name":"Wainuiomata School Dental Clinic",
    "wof:placetype":"venue"
},
  "geometry": {"coordinates":[174.950836,-41.261421],"type":"Point"}
}