{
  "type": "Feature",
  "properties": {
    "addr:full":"210 Alexandra St Te  Awamutu Waikato",
    "addr:housenumber":"210",
    "addr:street":"Alexandra St",
    "iso:country":"NZ",
    "sg:address":"210 Alexandra St Te ",
    "sg:city":"Awamutu",
    "sg:classifiers":[
        {
            "category":"Travel",
            "subcategory":"Travel Agent",
            "type":"Entertainment"
        }
    ],
    "sg:phone":"+64 7-871 5098",
    "sg:province":"Waikato",
    "sg:tags":[
        "tourism",
        "broker"
    ],
    "wof:name":"Holiday Shoppe",
    "wof:placetype":"venue"
},
  "geometry": {"coordinates":[175.32360800000001,-38.009293],"type":"Point"}
}