{
  "type": "Feature",
  "properties": {
    "iso:country":"NZ",
    "sg:address":"314 Cameron Rd ",
    "sg:city":"Tauranga",
    "sg:orig_category":"Home And Garden: Furniture/Furnishings: Blinds",
    "sg:phone":"+64 7-577 9444",
    "sg:province":"Bay of Plenty",
    "wof:name":"Drapemakers",
    "wof:placetype":"venue"
},
  "geometry": {"coordinates":[176.1651,-37.689747],"type":"Point"}
}