{
  "type": "Feature",
  "properties": {
    "addr:full":"12 George Tce Onehunga  Auckland Auckland",
    "addr:housenumber":"12",
    "addr:street":"George Tce",
    "iso:country":"NZ",
    "sg:address":"12 George Tce Onehunga ",
    "sg:city":"Auckland",
    "sg:classifiers":[
        {
            "category":"Home & Garden",
            "subcategory":"Building Materials",
            "type":"Retail Goods"
        }
    ],
    "sg:phone":"+64 9-634 1914",
    "sg:province":"Auckland",
    "sg:tags":[
        "electrician",
        "related"
    ],
    "wof:name":"Noble Electrical Ltd",
    "wof:placetype":"venue"
},
  "geometry": {"coordinates":[174.77877799999999,-36.924446],"type":"Point"}
}