{
  "type": "Feature",
  "properties": {
    "addr:full":"Grey Lynn PO Box 99557 Newmarket  Auckland Auckland",
    "addr:housenumber":"po box",
    "addr:postcode":"99557",
    "iso:country":"NZ",
    "sg:address":"Grey Lynn PO Box 99557 Newmarket ",
    "sg:city":"Auckland",
    "sg:classifiers":[
        {
            "category":"Travel",
            "subcategory":"Travel Agent",
            "type":"Entertainment"
        }
    ],
    "sg:phone":"+64 9-360 7669",
    "sg:province":"Auckland",
    "sg:tags":[
        "tourism",
        "broker"
    ],
    "sg:website":"http://www.activeasia.co.nz",
    "wof:name":"Active Asia",
    "wof:placetype":"venue"
},
  "geometry": {"coordinates":[174.77041600000001,-36.884109],"type":"Point"}
}