{
  "type": "Feature",
  "properties": {
    "addr:full":"269 Gloucester St Taradale  Napier Hawke's Bay",
    "addr:housenumber":"269",
    "addr:street":"Gloucester St",
    "iso:country":"NZ",
    "sg:address":"269 Gloucester St Taradale ",
    "sg:city":"Napier",
    "sg:classifiers":[
        {
            "category":"Shopping",
            "subcategory":"Gifts & Souvenirs",
            "type":"Retail Goods"
        }
    ],
    "sg:phone":"+64 6-844 7514",
    "sg:province":"Hawke's Bay",
    "sg:tags":[
        "shop",
        "gifts",
        "supplier"
    ],
    "wof:name":"Craftsman Gifts & Souvenirs",
    "wof:placetype":"venue"
},
  "geometry": {"coordinates":[176.84831199999999,-39.535725],"type":"Point"}
}