{
  "type": "Feature",
  "properties": {
    "addr:full":"1 Jarden Mile Ngauranga  Wellington Waikato",
    "addr:housenumber":"1",
    "addr:street":"Jarden Mile",
    "iso:country":"NZ",
    "sg:address":"1 Jarden Mile Ngauranga ",
    "sg:city":"Wellington",
    "sg:classifiers":[
        {
            "category":"Food & Beverages",
            "subcategory":"Candy",
            "type":"Retail Goods"
        }
    ],
    "sg:phone":"+64 4-472 6757",
    "sg:province":"Waikato",
    "sg:tags":[
        "confectioner",
        "drink",
        "-"
    ],
    "wof:name":"Cadbury Confectionery Ltd",
    "wof:placetype":"venue"
},
  "geometry": {"coordinates":[174.812286,-41.247353],"type":"Point"}
}