{
  "type": "Feature",
  "properties": {
    "iso:country":"NZ",
    "sg:address":"NZWTA House cnr Bridge & Lever Sts ",
    "sg:city":"Napier",
    "sg:orig_category":"Transport: Boats And Marine: Shipping: Shipping Companies",
    "sg:phone":"+64 6-835 9359",
    "sg:province":"Hawke's Bay",
    "wof:name":"Cosco (NZ) Ltd",
    "wof:placetype":"venue"
},
  "geometry": {"coordinates":[-80.588562,38.790821],"type":"Point"}
}