{
  "type": "Feature",
  "properties": {
    "addr:full":"96 St Georges Bay Rd  Auckland Auckland",
    "addr:housenumber":"96",
    "addr:street":"St Georges Bay Rd",
    "iso:country":"NZ",
    "sg:address":"96 St Georges Bay Rd ",
    "sg:city":"Auckland",
    "sg:classifiers":[
        {
            "category":"Manufacturing",
            "subcategory":"Textiles",
            "type":"Manufacturing & Wholesale Goods"
        }
    ],
    "sg:phone":"+64 9-366 1506",
    "sg:province":"Auckland",
    "sg:tags":[
        "clothing",
        "fabric",
        "manufacturer"
    ],
    "wof:name":"Network Apparel (NZ) Ltd",
    "wof:placetype":"venue"
},
  "geometry": {"coordinates":[-119.10457599999999,36.597755],"type":"Point"}
}