{
  "type": "Feature",
  "properties": {
    "iso:country":"NZ",
    "sg:address":"22 Downer St Lower ",
    "sg:city":"Hutt",
    "sg:classifiers":[
        {
            "category":"Home & Garden",
            "subcategory":"Kitchen Supply",
            "type":"Retail Goods"
        }
    ],
    "sg:phone":"+64 4-570 0117",
    "sg:province":"Wellington",
    "sg:tags":[
        "food",
        "equipment",
        "drink",
        "catering"
    ],
    "wof:name":"Spunglo (NZ) Limited",
    "wof:placetype":"venue"
},
  "geometry": {"coordinates":[174.91246,-41.206036],"type":"Point"}
}