{
  "type": "Feature",
  "properties": {
    "iso:country":"NZ",
    "sg:address":"2 Insoll Ave ",
    "sg:city":"Hamilton",
    "sg:classifiers":[
        {
            "category":"Social Services",
            "subcategory":"Retirement Home",
            "type":"Services"
        }
    ],
    "sg:phone":"+64 7-854 7695",
    "sg:province":"Waikato",
    "sg:tags":[
        "personal",
        "services",
        "garden",
        "elderly",
        "care"
    ],
    "wof:name":"Rossendale Community Support",
    "wof:placetype":"venue"
},
  "geometry": {"coordinates":[-87.988968,34.142426],"type":"Point"}
}