{
  "type": "Feature",
  "properties": {
    "addr:full":"1342 Cameron Rd Greerton  Tauranga Bay of Plenty",
    "addr:housenumber":"1342",
    "addr:street":"Cameron Rd",
    "iso:country":"NZ",
    "sg:address":"1342 Cameron Rd Greerton ",
    "sg:city":"Tauranga",
    "sg:classifiers":[
        {
            "category":"Restaurant",
            "type":"Food & Drink"
        }
    ],
    "sg:phone":"+64 7-578 5901",
    "sg:province":"Bay of Plenty",
    "sg:tags":[
        "merchant",
        "fish",
        "sea"
    ],
    "wof:name":"Greerton Fish N Chips Bar",
    "wof:placetype":"venue"
},
  "geometry": {"coordinates":[176.13249200000001,-37.726753],"type":"Point"}
}