{
  "type": "Feature",
  "properties": {
    "iso:country":"NZ",
    "sg:address":"24-30 Hopper St Mt Cook ",
    "sg:city":"Wellington",
    "sg:orig_category":"Transport: Boats And Marine: Shipping: Ship Provedores",
    "sg:phone":"+64 4-385 0924",
    "sg:province":"Wellington",
    "wof:name":"Japan Marine Providores Ltd",
    "wof:placetype":"venue"
},
  "geometry": {"coordinates":[174.773697,-41.299164],"type":"Point"}
}