{
  "type": "Feature",
  "properties": {
    "addr:full":"173 King Edward St South Dunedin  Dunedin Otago",
    "addr:housenumber":"173",
    "addr:street":"King Edward St",
    "iso:country":"NZ",
    "sg:address":"173 King Edward St South Dunedin ",
    "sg:city":"Dunedin",
    "sg:orig_category":"Industrial: Equipment And Machinery: Specialist Equipment: Machinery: Sewing Machines",
    "sg:phone":"+64 3-455 3979",
    "sg:province":"Otago",
    "wof:name":"Dunedin Sewing Machine Repairs",
    "wof:placetype":"venue"
},
  "geometry": {"coordinates":[170.49902299999999,-45.894348],"type":"Point"}
}