{
  "type": "Feature",
  "properties": {
    "addr:full":"254 Broadway Newmarket  Auckland Manawatu-Wanganui",
    "addr:housenumber":"254",
    "addr:street":"Broadway",
    "iso:country":"NZ",
    "sg:address":"254 Broadway Newmarket ",
    "sg:city":"Auckland",
    "sg:orig_category":"Clothing And Fabric: Clothing: Women'S Fashions",
    "sg:phone":"+64 9-520 7630",
    "sg:province":"Manawatu-Wanganui",
    "wof:name":"Saks",
    "wof:placetype":"venue"
},
  "geometry": {"coordinates":[174.777817,-36.869602],"type":"Point"}
}