{
  "type": "Feature",
  "properties": {
    "addr:full":"Porritt Park 845 Avonside Dve Wainoni  Christchurch Canterbury",
    "addr:housenumber":"845",
    "addr:street":"Porritt;Avonside Dve",
    "iso:country":"NZ",
    "sg:address":"Porritt Park 845 Avonside Dve Wainoni ",
    "sg:city":"Christchurch",
    "sg:classifiers":[
        {
            "category":"Sports & Exercise",
            "subcategory":"Sports Center",
            "type":"Entertainment"
        }
    ],
    "sg:phone":"+64 3-389 9126",
    "sg:province":"Canterbury",
    "sg:tags":[
        "sporting",
        "sports",
        "-",
        "leisure",
        "facility"
    ],
    "wof:name":"Canterbury Hockey Association (Inc)",
    "wof:placetype":"venue"
},
  "geometry": {"coordinates":[172.68995699999999,-43.520218],"type":"Point"}
}