{
  "type": "Feature",
  "properties": {
    "iso:country":"NZ",
    "sg:address":"Kaharoa Rd ",
    "sg:city":"Patea",
    "sg:orig_category":"Sports And Leisure: Sports: Equestrian: Horse Agistment/Training",
    "sg:phone":"+64 6-273 8664",
    "wof:name":"Gray Kevin",
    "wof:placetype":"venue"
},
  "geometry": {"coordinates":[174.541046,-39.708488],"type":"Point"}
}