{
  "type": "Feature",
  "properties": {
    "iso:country":"NZ",
    "sg:address":"20 Malden St Palmerston ",
    "sg:city":"Palmerston North",
    "sg:orig_category":"Industrial: Services: Drillers",
    "sg:phone":"+64 6-353 3700",
    "sg:province":"Manawatu-Wanganui",
    "sg:website":"http://www.abequipment.co.nz",
    "wof:name":"AB Equipment Ltd",
    "wof:placetype":"venue"
},
  "geometry": {"coordinates":[175.62106299999999,-40.333313],"type":"Point"}
}