{
  "type": "Feature",
  "properties": {
    "addr:full":"9 B Earl Dve Katikati  Tauranga Bay of Plenty",
    "addr:housenumber":"9 b",
    "addr:street":"Earl Dve",
    "iso:country":"NZ",
    "sg:address":"9 B Earl Dve Katikati ",
    "sg:city":"Tauranga",
    "sg:orig_category":"Farming: Horticulture: Horticultural Supplies",
    "sg:phone":"+64 7-549 2564",
    "sg:province":"Bay of Plenty",
    "wof:name":"Bay Horticultural Supplies",
    "wof:placetype":"venue"
},
  "geometry": {"coordinates":[175.92103599999999,-37.555531],"type":"Point"}
}