{
  "type": "Feature",
  "properties": {
    "iso:country":"NZ",
    "sg:address":"131 Onehunga Mall Onehunga ",
    "sg:city":"Auckland",
    "sg:classifiers":[
        {
            "category":"Shopping",
            "subcategory":"Thrift Store",
            "type":"Retail Goods"
        }
    ],
    "sg:phone":"+64 9-634 1411",
    "sg:province":"Auckland",
    "sg:tags":[
        "-",
        "clothing",
        "secondhand",
        "fabric"
    ],
    "wof:name":"Auckland City Mission",
    "wof:placetype":"venue"
},
  "geometry": {"coordinates":[174.78576699999999,-36.924603],"type":"Point"}
}