{
  "type": "Feature",
  "properties": {
    "addr:full":"109 Gladstone Rd  Gisborne Gisborne",
    "addr:housenumber":"109",
    "addr:street":"Gladstone Rd",
    "iso:country":"NZ",
    "sg:address":"109 Gladstone Rd ",
    "sg:city":"Gisborne",
    "sg:orig_category":"Clothing And Fabric: Clothing: Women'S Fashions",
    "sg:phone":"+64 6-867 2037",
    "sg:province":"Gisborne",
    "wof:name":"Fay Marie",
    "wof:placetype":"venue"
},
  "geometry": {"coordinates":[178.02574200000001,-38.666073],"type":"Point"}
}