{
  "type": "Feature",
  "properties": {
    "iso:country":"NZ",
    "sg:address":"24 Andromeda Cre East Tamaki ",
    "sg:city":"Auckland",
    "sg:classifiers":[
        {
            "category":"Bars & Pubs",
            "type":"Food & Drink"
        }
    ],
    "sg:phone":"+64 9-274 7236",
    "sg:province":"Auckland",
    "wof:name":"Ceracell Beekeeping Supplies Ltd",
    "wof:placetype":"venue"
},
  "geometry": {"coordinates":[174.886673,-36.949055],"type":"Point"}
}