{
  "type": "Feature",
  "properties": {
    "iso:country":"NZ",
    "sg:address":"106 Hokonui Dve ",
    "sg:city":"Gore",
    "sg:classifiers":[
        {
            "category":"Retail",
            "subcategory":"Funeral Services",
            "type":"Services"
        }
    ],
    "sg:phone":"+64 3-208 8004",
    "sg:province":"Southland",
    "sg:tags":[
        "arrangements",
        "arrangement"
    ],
    "wof:name":"Stephen Funeral Home",
    "wof:placetype":"venue"
},
  "geometry": {"coordinates":[168.937439,-46.100636],"type":"Point"}
}