{
  "type": "Feature",
  "properties": {
    "addr:full":"14 Belgium St Ostend  Auckland Auckland",
    "addr:housenumber":"14",
    "addr:street":"Belgium St",
    "iso:country":"NZ",
    "sg:address":"14 Belgium St Ostend ",
    "sg:city":"Auckland",
    "sg:classifiers":[
        {
            "category":"Restaurant",
            "type":"Food & Drink"
        }
    ],
    "sg:phone":"+64 9-372 8789",
    "sg:province":"Auckland",
    "sg:tags":[
        "wining",
        "dining",
        "pizza"
    ],
    "wof:name":"Mangrove Pizza",
    "wof:placetype":"venue"
},
  "geometry": {"coordinates":[175.04553200000001,-36.795601],"type":"Point"}
}