{
  "type": "Feature",
  "properties": {
    "addr:full":"C/- Pukekohe Hospital Tuakau Rd  Pukekohe Auckland",
    "addr:street":"C /;Tuakau Rd",
    "iso:country":"NZ",
    "sg:address":"C/- Pukekohe Hospital Tuakau Rd ",
    "sg:city":"Pukekohe",
    "sg:classifiers":[
        {
            "category":"Professional",
            "type":"Services"
        }
    ],
    "sg:phone":"+64 9-238 8567",
    "sg:province":"Auckland",
    "sg:tags":[
        "home",
        "cleaning",
        "help",
        "garden"
    ],
    "wof:name":"Counties Manukau Homecare",
    "wof:placetype":"venue"
},
  "geometry": {"coordinates":[174.930252,-37.195728],"type":"Point"}
}