{
  "type": "Feature",
  "properties": {
    "addr:full":"62 Gladstone Rd  Gisborne Gisborne",
    "addr:housenumber":"62",
    "addr:street":"Gladstone Rd",
    "iso:country":"NZ",
    "sg:address":"62 Gladstone Rd ",
    "sg:city":"Gisborne",
    "sg:orig_category":"Shopping: Retail Stores: Books: Bookshops",
    "sg:phone":"+64 6-868 4494",
    "sg:province":"Gisborne",
    "wof:name":"Muirs Book Shop",
    "wof:placetype":"venue"
},
  "geometry": {"coordinates":[178.026489,-38.666992],"type":"Point"}
}