{
  "type": "Feature",
  "properties": {
    "iso:country":"NZ",
    "sg:address":"Idiom Studio 26 Elizabeth St Mt Victoria ",
    "sg:city":"Wellington",
    "sg:classifiers":[
        {
            "category":"Sports & Exercise",
            "subcategory":"Sports Center",
            "type":"Entertainment"
        }
    ],
    "sg:phone":"+64 4-939 1214",
    "sg:province":"Wellington",
    "sg:tags":[
        "art",
        "leisure"
    ],
    "wof:name":"Dave Kent Design",
    "wof:placetype":"venue"
},
  "geometry": {"coordinates":[174.78509500000001,-41.296368],"type":"Point"}
}