{
  "type": "Feature",
  "properties": {
    "iso:country":"NZ",
    "sg:address":"474 Pukehina Pde Pukehina Te ",
    "sg:city":"Puke",
    "sg:classifiers":[
        {
            "category":"Education",
            "subcategory":"Music School",
            "type":"Public Place"
        }
    ],
    "sg:phone":"+64 7-533 3206",
    "sg:province":"Bay of Plenty",
    "sg:tags":[
        "sport",
        "teacher",
        "leisure"
    ],
    "wof:name":"Studio 474",
    "wof:placetype":"venue"
},
  "geometry": {"coordinates":[176.320084,-37.786819],"type":"Point"}
}