{
  "type": "Feature",
  "properties": {
    "addr:full":"Malden St Palmerston  Palmerston North Manawatu-Wanganui",
    "addr:street":"Malden St Palmerston",
    "iso:country":"NZ",
    "sg:address":"Malden St Palmerston ",
    "sg:city":"Palmerston North",
    "sg:orig_category":"Industrial: Parts: Bolts And Nuts",
    "sg:phone":"+64 6-356 5252",
    "sg:province":"Manawatu-Wanganui",
    "wof:name":"Steel & Tube Distribution",
    "wof:placetype":"venue"
},
  "geometry": {"coordinates":[175.62318400000001,-40.331715],"type":"Point"}
}