{
  "type": "Feature",
  "properties": {
    "addr:full":"Estuary View Rd Waiau Pa  Pukekohe Waikato",
    "addr:street":"View Rd",
    "iso:country":"NZ",
    "sg:address":"Estuary View Rd Waiau Pa ",
    "sg:city":"Pukekohe",
    "sg:orig_category":"Transport: Land: Horse Transport",
    "sg:phone":"+64 800 766 939",
    "sg:province":"Waikato",
    "wof:name":"Pony Express",
    "wof:placetype":"venue"
},
  "geometry": {"coordinates":[174.90362500000001,-37.20063],"type":"Point"}
}