{
  "type": "Feature",
  "properties": {
    "iso:country":"NZ",
    "sg:address":"7 Hewlett St ",
    "sg:city":"Whangarei",
    "sg:orig_category":"Non-Classified Establishments",
    "sg:phone":"+64 9-438 4107",
    "sg:province":"Northland",
    "sg:website":"http://www.yellowpages.co.nz/for/mcraeengineering/dp25186.html",
    "wof:name":"McRae Engineering Ltd",
    "wof:placetype":"venue"
},
  "geometry": {"coordinates":[174.341034,-35.740559],"type":"Point"}
}