{
  "type": "Feature",
  "properties": {
    "iso:country":"NZ",
    "sg:address":"3 Gordon Rd Otahuhu ",
    "sg:city":"Auckland",
    "sg:orig_category":"Automotive: General Services: Engine Importers/Dealers",
    "sg:phone":"+64 9-276 3388",
    "sg:province":"Auckland",
    "wof:name":"Parts Imports Co Ltd",
    "wof:placetype":"venue"
},
  "geometry": {"coordinates":[174.842407,-36.941792],"type":"Point"}
}