{
  "type": "Feature",
  "properties": {
    "addr:full":"104 Lower Dent St  Whangarei Northland",
    "addr:housenumber":"104",
    "addr:street":"Lower Dent St",
    "iso:country":"NZ",
    "sg:address":"104 Lower Dent St ",
    "sg:city":"Whangarei",
    "sg:classifiers":[
        {
            "category":"Brewery",
            "type":"Food & Drink"
        }
    ],
    "sg:phone":"+64 9-438 4664",
    "sg:province":"Northland",
    "sg:tags":[
        "brewer"
    ],
    "wof:name":"Brauhaus Frings/Northland Breweries",
    "wof:placetype":"venue"
},
  "geometry": {"coordinates":[174.32678200000001,-35.726192],"type":"Point"}
}