{
  "type": "Feature",
  "properties": {
    "addr:full":"27 Milburn St Kew  Dunedin Otago",
    "addr:housenumber":"27",
    "addr:street":"Milburn St",
    "iso:country":"NZ",
    "sg:address":"27 Milburn St Kew ",
    "sg:city":"Dunedin",
    "sg:classifiers":[
        {
            "category":"Personal",
            "type":"Services"
        }
    ],
    "sg:phone":"+64 3-487 6367",
    "sg:province":"Otago",
    "sg:tags":[
        "celebrant",
        "arrangements",
        "marriage",
        "wedding"
    ],
    "wof:name":"Coster Rev D",
    "wof:placetype":"venue"
},
  "geometry": {"coordinates":[170.47444200000001,-45.903728],"type":"Point"}
}