{
  "type": "Feature",
  "properties": {
    "addr:full":"650 Swanson Rd Swanson  Auckland Auckland",
    "addr:housenumber":"650",
    "addr:street":"Swanson Rd",
    "iso:country":"NZ",
    "sg:address":"650 Swanson Rd Swanson ",
    "sg:city":"Auckland",
    "sg:classifiers":[
        {
            "category":"Retail",
            "subcategory":"Auto Repair",
            "type":"Services"
        }
    ],
    "sg:phone":"+64 9-833 8956",
    "sg:province":"Auckland",
    "sg:tags":[
        "automotive",
        "electric",
        "servicing"
    ],
    "wof:name":"Swanson Road Automotive Electrical",
    "wof:placetype":"venue"
},
  "geometry": {"coordinates":[174.58670000000001,-36.865501],"type":"Point"}
}