{
  "type": "Feature",
  "properties": {
    "addr:full":"138 King St  Whakatane Bay of Plenty",
    "addr:housenumber":"138",
    "addr:street":"King St",
    "iso:country":"NZ",
    "sg:address":"138 King St ",
    "sg:city":"Whakatane",
    "sg:classifiers":[
        {
            "category":"Recreation",
            "type":"Entertainment"
        }
    ],
    "sg:phone":"+64 7-308 6227",
    "sg:province":"Bay of Plenty",
    "sg:tags":[
        "shopping",
        "hunting",
        "fishing",
        "retailers",
        "sport",
        "trip"
    ],
    "wof:name":"Greg Smeal Fishing",
    "wof:placetype":"venue"
},
  "geometry": {"coordinates":[176.981964,-37.964809],"type":"Point"}
}