{
  "type": "Feature",
  "properties": {
    "iso:country":"NZ",
    "sg:address":"11 Rogers St ",
    "sg:city":"Cromwell",
    "sg:classifiers":[
        {
            "category":"Building & Trades",
            "subcategory":"Plumbing",
            "type":"Services"
        }
    ],
    "sg:phone":"+64 25337544",
    "sg:tags":[
        "home",
        "plumber",
        "garden",
        "related"
    ],
    "sg:website":"http://www.yellowpages.co.nz/for/toughplumbing/dp24663.html",
    "wof:name":"AAA Tough Plumbing & Drainage",
    "wof:placetype":"venue"
},
  "geometry": {"coordinates":[-72.651642,41.598629],"type":"Point"}
}