{
  "type": "Feature",
  "properties": {
    "addr:full":"158 Cambridge Rd  Tauranga Bay of Plenty",
    "addr:housenumber":"158",
    "addr:street":"Cambridge Rd",
    "iso:country":"NZ",
    "sg:address":"158 Cambridge Rd ",
    "sg:city":"Tauranga",
    "sg:classifiers":[
        {
            "category":"Bars & Pubs",
            "type":"Food & Drink"
        }
    ],
    "sg:phone":"+64 7-577 1106",
    "sg:province":"Bay of Plenty",
    "sg:tags":[
        "wining",
        "dining",
        "brasserie"
    ],
    "wof:name":"McSwiggans Irish Pub",
    "wof:placetype":"venue"
},
  "geometry": {"coordinates":[176.12934899999999,-37.702759],"type":"Point"}
}