{
  "type": "Feature",
  "properties": {
    "iso:country":"NZ",
    "sg:address":"59 Lake Rd ",
    "sg:city":"Hamilton",
    "sg:classifiers":[
        {
            "category":"Retail",
            "subcategory":"Auto Repair",
            "type":"Services"
        }
    ],
    "sg:phone":"+64 7-847 6097",
    "sg:province":"Waikato",
    "sg:tags":[
        "transmission",
        "automotive",
        "servicing"
    ],
    "wof:name":"Torquewinder",
    "wof:placetype":"venue"
},
  "geometry": {"coordinates":[-75.536034,42.832039],"type":"Point"}
}