{
  "type": "Feature",
  "properties": {
    "iso:country":"NZ",
    "sg:address":"96 Onerahi Rd ",
    "sg:city":"Whangarei",
    "sg:orig_category":"Farming: Horticulture: Horticultural Supplies",
    "sg:phone":"+64 9-436 1968",
    "sg:province":"Northland",
    "wof:name":"Northern Natives",
    "wof:placetype":"venue"
},
  "geometry": {"coordinates":[174.367569,-35.750248],"type":"Point"}
}