{
  "type": "Feature",
  "properties": {
    "addr:full":"3 Princes Ave Mt Roskill  Auckland Auckland",
    "addr:housenumber":"3",
    "addr:street":"Princes Ave",
    "iso:country":"NZ",
    "sg:address":"3 Princes Ave Mt Roskill ",
    "sg:city":"Auckland",
    "sg:classifiers":[
        {
            "category":"Bars & Pubs",
            "subcategory":"Wine Bar",
            "type":"Food & Drink"
        }
    ],
    "sg:phone":"+64 9-979 2900",
    "sg:province":"Auckland",
    "sg:tags":[
        "distributor"
    ],
    "wof:name":"Vintners New Zealand",
    "wof:placetype":"venue"
},
  "geometry": {"coordinates":[174.74276699999999,-36.905895],"type":"Point"}
}