{
  "type": "Feature",
  "properties": {
    "iso:country":"NZ",
    "sg:address":"Albert St ",
    "sg:city":"Greymouth",
    "sg:classifiers":[
        {
            "category":"Restaurant",
            "type":"Food & Drink"
        }
    ],
    "sg:phone":"+64 3-768 6814",
    "sg:province":"West Coast",
    "sg:tags":[
        "fruit",
        "veges"
    ],
    "wof:name":"MG Marketing (Market Gardeners Ltd)",
    "wof:placetype":"venue"
},
  "geometry": {"coordinates":[171.209656,-42.450211],"type":"Point"}
}