{
  "type": "Feature",
  "properties": {
    "iso:country":"NZ",
    "sg:address":"254 Richmond Rd Grey Lynn PO Box 47-691 Ponsonby ",
    "sg:city":"Auckland",
    "sg:orig_category":"Shopping: Accessories: Sunglasses",
    "sg:phone":"+64 9-360 3520",
    "sg:province":"Nelson",
    "wof:name":"Optical Holdings Ltd",
    "wof:placetype":"venue"
},
  "geometry": {"coordinates":[174.74241599999999,-36.85326],"type":"Point"}
}