{
  "type": "Feature",
  "properties": {
    "addr:full":"PO Box 143 Ngongotaha  Rotorua Bay of Plenty",
    "addr:housenumber":"po",
    "addr:street":"Box 143",
    "iso:country":"NZ",
    "sg:address":"PO Box 143 Ngongotaha ",
    "sg:city":"Rotorua",
    "sg:classifiers":[
        {
            "category":"Food & Beverages",
            "subcategory":"Candy",
            "type":"Retail Goods"
        }
    ],
    "sg:phone":"+64 7-357 2755",
    "sg:province":"Bay of Plenty",
    "sg:tags":[
        "confectioner",
        "drink",
        "-"
    ],
    "wof:name":"Bliss Confectionery Ltd",
    "wof:placetype":"venue"
},
  "geometry": {"coordinates":[176.215317,-38.079964],"type":"Point"}
}