{
  "type": "Feature",
  "properties": {
    "addr:full":"20 Rosecamp Rd Beach Haven  Auckland Auckland",
    "addr:housenumber":"20",
    "addr:street":"Rosecamp Rd",
    "iso:country":"NZ",
    "sg:address":"20 Rosecamp Rd Beach Haven ",
    "sg:city":"Auckland",
    "sg:orig_category":"Industrial: Engineering: Engineers - Manufacturing",
    "sg:phone":"+64 9-483 7540",
    "sg:province":"Auckland",
    "wof:name":"Wilkin W L",
    "wof:placetype":"venue"
},
  "geometry": {"coordinates":[174.68948399999999,-36.802029],"type":"Point"}
}