{
  "type": "Feature",
  "properties": {
    "addr:full":"6a Cardrona Rd  Hamilton Waikato",
    "addr:housenumber":"6a",
    "addr:street":"Cardrona Rd",
    "iso:country":"NZ",
    "sg:address":"6a Cardrona Rd ",
    "sg:city":"Hamilton",
    "sg:orig_category":"Sports And Leisure: Entertainment: Entertainers",
    "sg:phone":"+64 21 2949 191",
    "sg:province":"Waikato",
    "wof:name":"A1 Party on Promotions",
    "wof:placetype":"venue"
},
  "geometry": {"coordinates":[-87.988968,34.142426],"type":"Point"}
}