{
  "type": "Feature",
  "properties": {
    "iso:country":"NZ",
    "sg:address":"Puketona Rd Haruru Falls ",
    "sg:city":"Paihia",
    "sg:classifiers":[
        {
            "category":"Home & Garden",
            "subcategory":"Home Furnishings",
            "type":"Retail Goods"
        }
    ],
    "sg:phone":"+64 9-402 8326",
    "sg:province":"Northland",
    "sg:tags":[
        "furniture/furnishings",
        "upholstery",
        "supply"
    ],
    "wof:name":"Bay of Islands Upholstery",
    "wof:placetype":"venue"
},
  "geometry": {"coordinates":[174.082077,-35.278614],"type":"Point"}
}