{
  "type": "Feature",
  "properties": {
    "addr:full":"31 Avon St Island Bay  Wellington Wellington",
    "addr:housenumber":"31",
    "addr:street":"Avon St",
    "iso:country":"NZ",
    "sg:address":"31 Avon St Island Bay ",
    "sg:city":"Wellington",
    "sg:classifiers":[
        {
            "category":"Banks & Credit Unions",
            "subcategory":"Investment Brokerage",
            "type":"Services"
        }
    ],
    "sg:phone":"+64 4-383 9682",
    "sg:province":"Wellington",
    "sg:tags":[
        "educational",
        "education",
        "training"
    ],
    "sg:website":"http://www.tlc.ac.nz",
    "wof:name":"The Learning Connexion",
    "wof:placetype":"venue"
},
  "geometry": {"coordinates":[174.77615399999999,-41.333443],"type":"Point"}
}