{
  "type": "Feature",
  "properties": {
    "addr:full":"12 Reaby St Burwood  Christchurch Canterbury",
    "addr:housenumber":"12",
    "addr:street":"Reaby St",
    "iso:country":"NZ",
    "sg:address":"12 Reaby St Burwood ",
    "sg:city":"Christchurch",
    "sg:classifiers":[
        {
            "category":"Education",
            "subcategory":"Special Training",
            "type":"Public Place"
        }
    ],
    "sg:phone":"+64 3-385 4757",
    "sg:province":"Canterbury",
    "sg:tags":[
        "therapist",
        "speech",
        "language"
    ],
    "wof:name":"SLT Services Christchurch",
    "wof:placetype":"venue"
},
  "geometry": {"coordinates":[172.67863500000001,-43.502426],"type":"Point"}
}