{
  "type": "Feature",
  "properties": {
    "iso:country":"NZ",
    "sg:address":"cnr Somerset & Devon Sts ",
    "sg:city":"Hamilton",
    "sg:classifiers":[
        {
            "category":"Sports & Exercise",
            "subcategory":"Swimming Pool",
            "type":"Entertainment"
        }
    ],
    "sg:phone":"+64 7-848 2223",
    "sg:province":"Waikato",
    "sg:tags":[
        "home",
        "outdoor",
        "garden",
        "spa"
    ],
    "wof:name":"Heat Pool & Spa",
    "wof:placetype":"venue"
},
  "geometry": {"coordinates":[175.276993,-37.783211],"type":"Point"}
}