{
  "type": "Feature",
  "properties": {
    "iso:country":"NZ",
    "sg:address":"62 Gloucester St ",
    "sg:city":"Christchurch",
    "sg:orig_category":"Automotive: General Services: Rental Vehicles",
    "sg:phone":"+64 800 549 4227",
    "sg:province":"Canterbury",
    "sg:website":"http://www.carrentals.co.nz",
    "wof:name":"KiwiCar Car Rentals",
    "wof:placetype":"venue"
},
  "geometry": {"coordinates":[-76.537834,37.605659],"type":"Point"}
}