{
  "type": "Feature",
  "properties": {
    "addr:full":"3 Beaver Road East R D 2 Pokeno  Pukekohe Marlborough",
    "addr:housenumber":"3;2",
    "addr:street":"Beaver Road East R D",
    "iso:country":"NZ",
    "sg:address":"3 Beaver Road East R D 2 Pokeno ",
    "sg:city":"Pukekohe",
    "sg:classifiers":[
        {
            "category":"Home & Garden",
            "subcategory":"Garden Supply",
            "type":"Retail Goods"
        }
    ],
    "sg:phone":"+64 9-236 0661",
    "sg:province":"Marlborough",
    "sg:tags":[
        "pet",
        "transport",
        "pets"
    ],
    "wof:name":"Beaver Rd Pet Motel",
    "wof:placetype":"venue"
},
  "geometry": {"coordinates":[175.02304100000001,-37.243099],"type":"Point"}
}