{
  "type": "Feature",
  "properties": {
    "addr:full":"Main Rd  Tairua",
    "addr:street":"Main Rd",
    "iso:country":"NZ",
    "sg:address":"Main Rd ",
    "sg:city":"Tairua",
    "sg:classifiers":[
        {
            "category":"Restaurant",
            "type":"Food & Drink"
        }
    ],
    "sg:phone":"+64 7-864 8811",
    "sg:tags":[
        "wining",
        "dining"
    ],
    "wof:name":"Shells Restaurant & Bar",
    "wof:placetype":"venue"
},
  "geometry": {"coordinates":[175.848465,-37.009243],"type":"Point"}
}