{
  "type": "Feature",
  "properties": {
    "iso:country":"NZ",
    "sg:address":"10 Gresson St ",
    "sg:city":"Greymouth",
    "sg:classifiers":[
        {
            "category":"Bars & Pubs",
            "subcategory":"Lounge",
            "type":"Food & Drink"
        }
    ],
    "sg:phone":"+64 3-768 5862",
    "sg:province":"West Coast",
    "sg:tags":[
        "baker",
        "-"
    ],
    "wof:name":"Phil's Bakery",
    "wof:placetype":"venue"
},
  "geometry": {"coordinates":[171.20668000000001,-42.448112],"type":"Point"}
}