{
  "type": "Feature",
  "properties": {
    "addr:full":"17 C Rylock Pl Pakuranga  Auckland Auckland",
    "addr:housenumber":"17 c rylock",
    "addr:street":"Pl",
    "iso:country":"NZ",
    "sg:address":"17 C Rylock Pl Pakuranga ",
    "sg:city":"Auckland",
    "sg:classifiers":[
        {
            "category":"Arts & Performance",
            "subcategory":"Art Gallery",
            "type":"Entertainment"
        }
    ],
    "sg:phone":"+64 9-577 1118",
    "sg:province":"Auckland",
    "sg:tags":[
        "arts",
        "sport",
        "leisure"
    ],
    "wof:name":"Matopo Gallery Ltd",
    "wof:placetype":"venue"
},
  "geometry": {"coordinates":[174.899506,-36.918537],"type":"Point"}
}