{
  "type": "Feature",
  "properties": {
    "addr:full":"1 Strathallan St  Timaru Canterbury",
    "addr:housenumber":"1",
    "addr:street":"Strathallan St",
    "iso:country":"NZ",
    "sg:address":"1 Strathallan St ",
    "sg:city":"Timaru",
    "sg:orig_category":"Transport: Boats And Marine: Shipping: Stevedores",
    "sg:phone":"+64 3-684 5184",
    "sg:province":"Canterbury",
    "wof:name":"Turnbull Stevedoring",
    "wof:placetype":"venue"
},
  "geometry": {"coordinates":[171.25477599999999,-44.395004],"type":"Point"}
}