{
  "type": "Feature",
  "properties": {
    "iso:country":"NZ",
    "sg:address":"175 High St ",
    "sg:city":"Christchurch",
    "sg:classifiers":[
        {
            "category":"Shopping",
            "subcategory":"Bicycles & Sporting Goods",
            "type":"Retail Goods"
        }
    ],
    "sg:phone":"+64 3-379 5007",
    "sg:province":"Canterbury",
    "sg:tags":[
        "equipment",
        "sport",
        "tramping",
        "leisure",
        "camping"
    ],
    "wof:name":"Billens & Son Ltd",
    "wof:placetype":"venue"
},
  "geometry": {"coordinates":[-76.537834,37.605659],"type":"Point"}
}