{
  "type": "Feature",
  "properties": {
    "addr:full":"PO Box 12135 Chartwell  Hamilton Waikato",
    "addr:housenumber":"po box 12135",
    "iso:country":"NZ",
    "sg:address":"PO Box 12135 Chartwell ",
    "sg:city":"Hamilton",
    "sg:orig_category":"Industrial: Services: Gasfitters",
    "sg:phone":"+64 7-847 9959",
    "sg:province":"Waikato",
    "wof:name":"Cant C J Plumbing",
    "wof:placetype":"venue"
},
  "geometry": {"coordinates":[175.27124000000001,-37.763653],"type":"Point"}
}