{
  "type": "Feature",
  "properties": {
    "iso:country":"NZ",
    "sg:address":"Ellis St ",
    "sg:city":"Brightwater",
    "sg:orig_category":"Home And Garden: Gardening: Products: Outdoor Furniture",
    "sg:phone":"+64 3-542 3356",
    "wof:name":"Reco Wrought Iron Ltd",
    "wof:placetype":"venue"
},
  "geometry": {"coordinates":[173.111526,-41.377419],"type":"Point"}
}