{
  "type": "Feature",
  "properties": {
    "iso:country":"NZ",
    "sg:address":"4/1 Canon Pl Pakuranga ",
    "sg:city":"Auckland",
    "sg:classifiers":[
        {
            "category":"Retail",
            "subcategory":"Auto Repair",
            "type":"Services"
        }
    ],
    "sg:phone":"+64 9-576 0223",
    "sg:province":"Auckland",
    "sg:tags":[
        "automotive",
        "panel",
        "servicing",
        "beater"
    ],
    "wof:name":"Quality Panel & Paint",
    "wof:placetype":"venue"
},
  "geometry": {"coordinates":[174.898361,-36.915783],"type":"Point"}
}