{
  "type": "Feature",
  "properties": {
    "addr:full":"16-18 View Rd Mt Eden  Auckland Auckland",
    "addr:housenumber":"16-18",
    "addr:street":"View Rd",
    "iso:country":"NZ",
    "sg:address":"16-18 View Rd Mt Eden ",
    "sg:city":"Auckland",
    "sg:classifiers":[
        {
            "category":"Travel",
            "subcategory":"Hotels & Motels",
            "type":"Entertainment"
        }
    ],
    "sg:phone":"+64 9-630 0635",
    "sg:province":"Auckland",
    "sg:tags":[
        "tourism",
        "-",
        "rental",
        "accommodation"
    ],
    "wof:name":"Mt View Lodge",
    "wof:placetype":"venue"
},
  "geometry": {"coordinates":[174.75904800000001,-36.87365],"type":"Point"}
}