{
  "type": "Feature",
  "properties": {
    "iso:country":"NZ",
    "sg:address":"Rotorua R D ",
    "sg:city":"1",
    "sg:orig_category":"Farming: Supplies: Stock Foods",
    "sg:phone":"+64 7-333 2121",
    "wof:name":"The Great Hage Co NZ Ltd",
    "wof:placetype":"venue"
},
  "geometry": {"coordinates":[176.244995,-38.1418],"type":"Point"}
}