{
  "type": "Feature",
  "properties": {
    "addr:full":"State Highway 16 PO Box 149 Waimauku  Auckland Auckland",
    "addr:housenumber":"box 149",
    "addr:street":"State Highway 16 Po",
    "iso:country":"NZ",
    "sg:address":"State Highway 16 PO Box 149 Waimauku ",
    "sg:city":"Auckland",
    "sg:classifiers":[
        {
            "category":"Farming",
            "subcategory":"Farm & Veterinary Services",
            "type":"Manufacturing & Wholesale Goods"
        }
    ],
    "sg:phone":"+64 9-411 8767",
    "sg:province":"Auckland",
    "sg:tags":[
        "supplies",
        "supply"
    ],
    "wof:name":"Agri Centre Limited",
    "wof:placetype":"venue"
},
  "geometry": {"coordinates":[174.77041600000001,-36.884109],"type":"Point"}
}