{
  "type": "Feature",
  "properties": {
    "addr:full":"14-16 Auburn St Grafton  Auckland Auckland",
    "addr:housenumber":"14-16",
    "addr:street":"Auburn St",
    "iso:country":"NZ",
    "sg:address":"14-16 Auburn St Grafton ",
    "sg:city":"Auckland",
    "sg:classifiers":[
        {
            "category":"Manufacturing",
            "subcategory":"Rubber & Plastics",
            "type":"Manufacturing & Wholesale Goods"
        }
    ],
    "sg:phone":"+64 9-379 5716",
    "sg:province":"Auckland",
    "sg:tags":[
        "industrial",
        "-",
        "machinery",
        "goods"
    ],
    "wof:name":"Tasman Machinery Ltd",
    "wof:placetype":"venue"
},
  "geometry": {"coordinates":[174.76617400000001,-36.866146],"type":"Point"}
}