{
  "type": "Feature",
  "properties": {
    "iso:country":"NZ",
    "sg:address":"19 Royal Arc ",
    "sg:city":"Timaru",
    "sg:orig_category":"Shopping: Accessories: Jewellers And Watchmakers",
    "sg:phone":"+64 3-684 4815",
    "sg:province":"Canterbury",
    "wof:name":"Arcade Jewellers Ltd",
    "wof:placetype":"venue"
},
  "geometry": {"coordinates":[171.25262499999999,-44.396484],"type":"Point"}
}