{
  "type": "Feature",
  "properties": {
    "iso:country":"NZ",
    "sg:address":"1-7 Jean Batten St Rongotai ",
    "sg:city":"Wellington",
    "sg:classifiers":[
        {
            "category":"Manufacturing",
            "subcategory":"Metals",
            "type":"Manufacturing & Wholesale Goods"
        }
    ],
    "sg:phone":"+64 4-387 7009",
    "sg:province":"Wellington",
    "sg:tags":[
        "-",
        "engineering",
        "industrial",
        "sheet",
        "engineer"
    ],
    "sg:website":"http://www.aetilley.co.nz",
    "wof:name":"Tilley A E Limited",
    "wof:placetype":"venue"
},
  "geometry": {"coordinates":[174.80607599999999,-41.31797],"type":"Point"}
}