{
  "type": "Feature",
  "properties": {
    "iso:country":"NZ",
    "sg:address":"394 Pembroke Rd ",
    "sg:city":"Stratford",
    "sg:orig_category":"Farming: Agriculture",
    "sg:phone":"+64 6-765 5735",
    "wof:name":"Hintz Contracting",
    "wof:placetype":"venue"
},
  "geometry": {"coordinates":[174.295975,-39.330315],"type":"Point"}
}