{
  "type": "Feature",
  "properties": {
    "addr:full":"Milford Shopping Centre, Milford  Auckland Auckland",
    "iso:country":"NZ",
    "sg:address":"Milford Shopping Centre, Milford ",
    "sg:city":"Auckland",
    "sg:classifiers":[
        {
            "category":"Home & Garden",
            "subcategory":"Home Furnishings",
            "type":"Retail Goods"
        }
    ],
    "sg:phone":"+64 9-489 3553",
    "sg:province":"Auckland",
    "sg:tags":[
        "furniture/furnishings",
        "bedding",
        "bed"
    ],
    "wof:name":"The Linen Cupboard",
    "wof:placetype":"venue"
},
  "geometry": {"coordinates":[174.764984,-36.771812],"type":"Point"}
}