{
  "type": "Feature",
  "properties": {
    "addr:full":"All Enquiries Palmerston  Palmerston North Manawatu-Wanganui",
    "addr:street":"Palmerston",
    "iso:country":"NZ",
    "sg:address":"All Enquiries Palmerston ",
    "sg:city":"Palmerston North",
    "sg:classifiers":[
        {
            "category":"Home & Garden",
            "subcategory":"Garden Supply",
            "type":"Retail Goods"
        }
    ],
    "sg:phone":"+64 6-358 7705",
    "sg:province":"Manawatu-Wanganui",
    "sg:tags":[
        "fencing",
        "outdoor",
        "contractor"
    ],
    "wof:name":"A B Fences",
    "wof:placetype":"venue"
},
  "geometry": {"coordinates":[175.611481,-40.357422],"type":"Point"}
}