{
  "type": "Feature",
  "properties": {
    "addr:full":"11 Croucher St Richmond  Nelson Nelson",
    "addr:housenumber":"11",
    "addr:street":"Croucher St",
    "iso:country":"NZ",
    "sg:address":"11 Croucher St Richmond ",
    "sg:city":"Nelson",
    "sg:classifiers":[
        {
            "category":"Home & Garden",
            "subcategory":"Kitchen Supply",
            "type":"Retail Goods"
        }
    ],
    "sg:phone":"+64 3-544 4379",
    "sg:province":"Nelson",
    "sg:tags":[
        "shop",
        "pet",
        "pets"
    ],
    "wof:name":"Four Paws Pantry",
    "wof:placetype":"venue"
},
  "geometry": {"coordinates":[173.185349,-41.338428],"type":"Point"}
}