{
  "type": "Feature",
  "properties": {
    "iso:country":"NZ",
    "sg:address":"Unit 2 28 Anvil Rd Silverdale Hibiscus ",
    "sg:city":"Hibiscus Coast",
    "sg:classifiers":[
        {
            "category":"Education",
            "subcategory":"College",
            "type":"Public Place"
        }
    ],
    "sg:phone":"+64 9-426 9703",
    "sg:province":"Auckland",
    "sg:tags":[
        "specialist",
        "vacuum",
        "industrial",
        "machinery",
        "equipment"
    ],
    "sg:website":"http://www.4ways.co.nz",
    "wof:name":"4 Way's Ltd",
    "wof:placetype":"venue"
},
  "geometry": {"coordinates":[174.677231,-36.623222],"type":"Point"}
}