{
  "type": "Feature",
  "properties": {
    "addr:full":"98 Brougham St  Westport West Coast",
    "addr:housenumber":"98",
    "addr:street":"Brougham St",
    "iso:country":"NZ",
    "sg:address":"98 Brougham St ",
    "sg:city":"Westport",
    "sg:classifiers":[
        {
            "category":"Shopping",
            "subcategory":"Pets & Pet Supplies",
            "type":"Retail Goods"
        }
    ],
    "sg:phone":"+64 3-789 8605",
    "sg:province":"West Coast",
    "sg:tags":[
        "boarding",
        "garden",
        "pets",
        "catteries",
        "home",
        "kennel"
    ],
    "wof:name":"KLS Vet Clinic & Cattery",
    "wof:placetype":"venue"
},
  "geometry": {"coordinates":[171.62005600000001,-41.752739],"type":"Point"}
}