{
  "type": "Feature",
  "properties": {
    "addr:full":"Level 11, 36 Customhouse Quay Wellington  Central Wellington",
    "addr:housenumber":"36",
    "addr:street":"Customhouse Quay",
    "iso:country":"NZ",
    "sg:address":"Level 11, 36 Customhouse Quay Wellington ",
    "sg:city":"Central",
    "sg:classifiers":[
        {
            "category":"Autos & Motor Vehicles",
            "subcategory":"Automobile Sales",
            "type":"Retail Goods"
        }
    ],
    "sg:phone":"+64 800 822 213",
    "sg:province":"Wellington",
    "sg:tags":[
        "car",
        "management",
        "leasing",
        "fleet",
        "automotive"
    ],
    "wof:name":"LeasePlan New Zealand Ltd",
    "wof:placetype":"venue"
},
  "geometry": {"coordinates":[174.77809099999999,-41.283321],"type":"Point"}
}