{
  "type": "Feature",
  "properties": {
    "iso:country":"NZ",
    "sg:address":"Pall Mall Arcade cnr Spey & Dee Sts ",
    "sg:city":"Invercargill",
    "sg:orig_category":"Clothing And Fabric: Clothing: Uniforms",
    "sg:phone":"+64 3-218 2901",
    "sg:province":"Southland",
    "wof:name":"Wilson Corporate Wear",
    "wof:placetype":"venue"
},
  "geometry": {"coordinates":[168.352173,-46.41185],"type":"Point"}
}