{
  "type": "Feature",
  "properties": {
    "addr:full":"34 A Sydney St Petone Lower  Hutt Wellington",
    "addr:housenumber":"34",
    "addr:street":"A Sydney St",
    "iso:country":"NZ",
    "sg:address":"34 A Sydney St Petone Lower ",
    "sg:city":"Hutt",
    "sg:orig_category":"Home And Garden: Furniture/Furnishings: Cabinetmakers",
    "sg:phone":"+64 4-568 5503",
    "sg:province":"Wellington",
    "wof:name":"Stunell's Cabinetmaking & Joinery",
    "wof:placetype":"venue"
},
  "geometry": {"coordinates":[174.875381,-41.225468],"type":"Point"}
}