{
  "type": "Feature",
  "properties": {
    "iso:country":"NZ",
    "sg:address":"54 Weston Rd ",
    "sg:city":"Oamaru",
    "sg:classifiers":[
        {
            "category":"Retail",
            "subcategory":"Funeral Services",
            "type":"Services"
        }
    ],
    "sg:phone":"+64 3-434 8812",
    "sg:province":"Otago",
    "sg:tags":[
        "arrangements",
        "arrangement"
    ],
    "wof:name":"Whitestone Funeral Services",
    "wof:placetype":"venue"
},
  "geometry": {"coordinates":[170.931076,-45.095753],"type":"Point"}
}