{
  "type": "Feature",
  "properties": {
    "addr:full":"117 Ruahine St Palmerston  Palmerston North Manawatu-Wanganui",
    "addr:housenumber":"117",
    "addr:street":"Ruahine St Palmerston",
    "iso:country":"NZ",
    "sg:address":"117 Ruahine St Palmerston ",
    "sg:city":"Palmerston North",
    "sg:classifiers":[
        {
            "category":"Food Court",
            "type":"Food & Drink"
        }
    ],
    "sg:phone":"+64 6-357 1009",
    "sg:province":"Manawatu-Wanganui",
    "sg:tags":[
        "packer",
        "processing",
        "processor"
    ],
    "wof:name":"Prepared Foods Ltd",
    "wof:placetype":"venue"
},
  "geometry": {"coordinates":[175.62350499999999,-40.341309],"type":"Point"}
}