{
  "type": "Feature",
  "properties": {
    "addr:full":"Ormond Rd  Gisborne Gisborne",
    "addr:street":"Ormond Rd",
    "iso:country":"NZ",
    "sg:address":"Ormond Rd ",
    "sg:city":"Gisborne",
    "sg:orig_category":"Health And Beauty: Medical: Hospitals",
    "sg:phone":"+64 6-869 0500",
    "sg:province":"Gisborne",
    "wof:name":"Gisborne Hospital",
    "wof:placetype":"venue"
},
  "geometry": {"coordinates":[178.00657699999999,-38.641193],"type":"Point"}
}