{
  "type": "Feature",
  "properties": {
    "addr:full":"69 Worcester Bvd PO Box 1300  Christchurch Canterbury",
    "addr:housenumber":"69;box 1300",
    "addr:street":"Worcester Bvd Po;Christchurch",
    "iso:country":"NZ",
    "sg:address":"69 Worcester Bvd PO Box 1300 ",
    "sg:city":"Christchurch",
    "sg:classifiers":[
        {
            "category":"Education",
            "subcategory":"University",
            "type":"Public Place"
        }
    ],
    "sg:phone":"+64 3-365 6022",
    "sg:province":"Canterbury",
    "sg:tags":[
        "training",
        "instruction",
        "language"
    ],
    "wof:name":"Southern English Schools",
    "wof:placetype":"venue"
},
  "geometry": {"coordinates":[-76.537834,37.605659],"type":"Point"}
}