{
  "type": "Feature",
  "properties": {
    "addr:full":"State Highway 1 Hukerenui  Whakapara",
    "addr:street":"State Highway 1 Hukerenui Whakapara",
    "iso:country":"NZ",
    "sg:address":"State Highway 1 Hukerenui ",
    "sg:city":"Whakapara",
    "sg:orig_category":"Travel And Tourism: Accommodation: Backpackers",
    "sg:phone":"+64 9-433 9745",
    "wof:name":"Hukerenui- The",
    "wof:placetype":"venue"
},
  "geometry": {"coordinates":[174.20164500000001,-35.50951],"type":"Point"}
}