{
  "type": "Feature",
  "properties": {
    "iso:country":"NZ",
    "sg:address":"Top Floor Wakefield St Market ",
    "sg:city":"Wellington",
    "sg:classifiers":[
        {
            "category":"Landmark",
            "subcategory":"Tourist Information",
            "type":"Public Place"
        }
    ],
    "sg:phone":"+64 4-471 1945",
    "sg:province":"Wellington",
    "sg:tags":[
        "services",
        "travel",
        "tourism"
    ],
    "wof:name":"i4info.co.nz",
    "wof:placetype":"venue"
},
  "geometry": {"coordinates":[-85.910454,33.827946],"type":"Point"}
}