{
  "type": "Feature",
  "properties": {
    "addr:full":"234 Rongotai Rd Kilbirnie  Wellington Wellington",
    "addr:housenumber":"234",
    "addr:street":"Rongotai Rd",
    "iso:country":"NZ",
    "sg:address":"234 Rongotai Rd Kilbirnie ",
    "sg:city":"Wellington",
    "sg:classifiers":[
        {
            "category":"Shopping",
            "subcategory":"Beauty & Cosmetics",
            "type":"Retail Goods"
        }
    ],
    "sg:phone":"+64 4-387 8210",
    "sg:province":"Wellington",
    "sg:tags":[
        "sanitary",
        "hygiene",
        "health",
        "products"
    ],
    "wof:name":"New Zealand Hygiene",
    "wof:placetype":"venue"
},
  "geometry": {"coordinates":[174.801773,-41.31918],"type":"Point"}
}