{
  "type": "Feature",
  "properties": {
    "iso:country":"NZ",
    "sg:address":"34 Buckingham St ",
    "sg:city":"Arrowtown",
    "sg:classifiers":[
        {
            "category":"Shopping",
            "subcategory":"Crafts & Fabrics",
            "type":"Retail Goods"
        }
    ],
    "sg:phone":"+64 3-442 1797",
    "sg:province":"Otago",
    "sg:tags":[
        "leather",
        "clothing",
        "suede"
    ],
    "wof:name":"High Country Run Ltd",
    "wof:placetype":"venue"
},
  "geometry": {"coordinates":[168.83200099999999,-44.938648],"type":"Point"}
}