{
  "type": "Feature",
  "properties": {
    "addr:full":"278 Wooldridge Rd Harewood  Christchurch Canterbury",
    "addr:housenumber":"278",
    "addr:street":"Wooldridge Rd",
    "iso:country":"NZ",
    "sg:address":"278 Wooldridge Rd Harewood ",
    "sg:city":"Christchurch",
    "sg:orig_category":"Farming: Agriculture: Agricultural Contractors",
    "sg:phone":"+64 3-359 8366",
    "sg:province":"Canterbury",
    "wof:name":"B A Murray Ltd",
    "wof:placetype":"venue"
},
  "geometry": {"coordinates":[172.56629899999999,-43.488319],"type":"Point"}
}