{
  "type": "Feature",
  "properties": {
    "addr:full":"8A Vogel St Naenae  Wellington Wellington",
    "addr:housenumber":"8a",
    "addr:street":"Vogel St",
    "iso:country":"NZ",
    "sg:address":"8A Vogel St Naenae ",
    "sg:city":"Wellington",
    "sg:classifiers":[
        {
            "category":"Home & Garden",
            "subcategory":"Kitchen Supply",
            "type":"Retail Goods"
        }
    ],
    "sg:phone":"+64 4-577 0889",
    "sg:province":"Wellington",
    "sg:tags":[
        "food",
        "equipment",
        "drink",
        "catering"
    ],
    "wof:name":"D & G Stainless Ltd",
    "wof:placetype":"venue"
},
  "geometry": {"coordinates":[174.94627399999999,-41.199612],"type":"Point"}
}