{
  "type": "Feature",
  "properties": {
    "addr:full":"5 Hutton Pl Mt  Maunganui Bay of Plenty",
    "addr:housenumber":"5",
    "addr:street":"Hutton Pl Mt Maunganui",
    "iso:country":"NZ",
    "sg:address":"5 Hutton Pl Mt ",
    "sg:city":"Maunganui",
    "sg:classifiers":[
        {
            "category":"Food Court",
            "type":"Food & Drink"
        }
    ],
    "sg:phone":"+64 7-575 9285",
    "sg:province":"Bay of Plenty",
    "sg:tags":[
        "packer",
        "processing",
        "processor"
    ],
    "wof:name":"Bakels Edible Oils (NZ) Ltd",
    "wof:placetype":"venue"
},
  "geometry": {"coordinates":[176.18627900000001,-37.641048],"type":"Point"}
}