{
  "type": "Feature",
  "properties": {
    "iso:country":"NZ",
    "sg:address":"80 St Lukes Rd Mt Albert ",
    "sg:city":"Auckland",
    "sg:classifiers":[
        {
            "category":"Shopping Center",
            "type":"Public Place"
        }
    ],
    "sg:phone":"+64 9-978 6000",
    "sg:province":"Auckland",
    "sg:tags":[
        "mall",
        "retail",
        "stores"
    ],
    "wof:name":"Westfield Manukau",
    "wof:placetype":"venue"
},
  "geometry": {"coordinates":[174.714798,-36.88784],"type":"Point"}
}