{
  "type": "Feature",
  "properties": {
    "iso:country":"NZ",
    "sg:address":"152-158 Kimbolton Rd ",
    "sg:city":"Feilding",
    "sg:classifiers":[
        {
            "category":"Food & Beverages",
            "subcategory":"Liquor & Beverages",
            "type":"Retail Goods"
        }
    ],
    "sg:phone":"+64 6-323 4263",
    "sg:province":"Manawatu-Wanganui",
    "sg:tags":[
        "drink",
        "outlet"
    ],
    "wof:name":"Liquorland",
    "wof:placetype":"venue"
},
  "geometry": {"coordinates":[175.547195,-40.224236],"type":"Point"}
}