{
  "type": "Feature",
  "properties": {
    "addr:full":"Worcester Boulevard  Christchurch Canterbury",
    "addr:street":"Worcester Boulevard",
    "iso:country":"NZ",
    "sg:address":"Worcester Boulevard ",
    "sg:city":"Christchurch",
    "sg:classifiers":[
        {
            "category":"Shopping",
            "subcategory":"Crafts & Fabrics",
            "type":"Retail Goods"
        }
    ],
    "sg:phone":"+64 3-366 1143",
    "sg:province":"Canterbury",
    "sg:tags":[
        "leather",
        "clothing",
        "suede"
    ],
    "wof:name":"Arts Centre Leather Shop",
    "wof:placetype":"venue"
},
  "geometry": {"coordinates":[172.637314,-43.531315],"type":"Point"}
}