{
  "type": "Feature",
  "properties": {
    "iso:country":"NZ",
    "sg:address":"Manawatu, Levin",
    "sg:city":"Bulls",
    "sg:classifiers":[
        {
            "category":"Manufacturing",
            "subcategory":"Rubber & Plastics",
            "type":"Manufacturing & Wholesale Goods"
        }
    ],
    "sg:phone":"+64 800 627 539",
    "sg:province":"Wellington",
    "sg:tags":[
        "industrial"
    ],
    "sg:website":"http://www.marley.co.nz",
    "wof:name":"Marley New Zealand Ltd",
    "wof:placetype":"venue"
},
  "geometry": {"coordinates":[175.854187,-40.018021],"type":"Point"}
}