{
  "type": "Feature",
  "properties": {
    "iso:country":"NZ",
    "sg:address":"11 Bairds Rd Otara ",
    "sg:city":"Auckland",
    "sg:orig_category":"Industrial: Metal: Scrap Metal Dealers",
    "sg:phone":"+64 9-270 3107",
    "sg:province":"Auckland",
    "wof:name":"Cash For Scrap Ltd",
    "wof:placetype":"venue"
},
  "geometry": {"coordinates":[174.857407,-36.958454],"type":"Point"}
}