{
  "type": "Feature",
  "properties": {
    "addr:full":"11 Bairds Rd Otara  Auckland Auckland",
    "addr:housenumber":"11",
    "addr:street":"Bairds Rd",
    "iso:country":"NZ",
    "sg:address":"11 Bairds Rd Otara ",
    "sg:city":"Auckland",
    "sg:orig_category":"Industrial: Metal: Scrap Metal Dealers",
    "sg:phone":"+64 9-270 3107",
    "sg:province":"Auckland",
    "wof:name":"Cash For Scrap Ltd",
    "wof:placetype":"venue"
},
  "geometry": {"coordinates":[174.85740699999999,-36.958454],"type":"Point"}
}