{
  "type": "Feature",
  "properties": {
    "iso:country":"NZ",
    "sg:address":"The Rock Shop Plaza 57-59 Manners St ",
    "sg:city":"Wellington",
    "sg:orig_category":"Travel And Tourism: Accommodation: Apartments",
    "sg:phone":"+64 4-494 9690",
    "sg:province":"Wellington",
    "sg:website":"http://www.whatsnew.co.nz",
    "wof:name":"Whats New Limited",
    "wof:placetype":"venue"
},
  "geometry": {"coordinates":[-93.968239,39.104004],"type":"Point"}
}