{
  "type": "Feature",
  "properties": {
    "iso:country":"NZ",
    "sg:address":"Auckland PO Box 8225 Symonds St ",
    "sg:city":"Auckland",
    "sg:classifiers":[
        {
            "category":"Health Services",
            "subcategory":"Health Practitioner",
            "type":"Services"
        }
    ],
    "sg:phone":"+64 9-361 3964",
    "sg:province":"Auckland",
    "sg:tags":[
        "consultant",
        "medical",
        "beauty"
    ],
    "wof:name":"The Body Corporate Ltd",
    "wof:placetype":"venue"
},
  "geometry": {"coordinates":[174.77041600000001,-36.884109],"type":"Point"}
}