{
  "type": "Feature",
  "properties": {
    "addr:full":"18 B Birmingham Dve PO Box 8561 Riccarton  Christchurch Canterbury",
    "addr:housenumber":"18;box",
    "addr:postcode":"8561",
    "addr:street":"B;Dve Po;Christchurch",
    "iso:country":"NZ",
    "sg:address":"18 B Birmingham Dve PO Box 8561 Riccarton ",
    "sg:city":"Christchurch",
    "sg:classifiers":[
        {
            "category":"Communications",
            "subcategory":"Television Station",
            "type":"Services"
        }
    ],
    "sg:phone":"+64 800 774 6388",
    "sg:province":"Canterbury",
    "sg:tags":[
        "broadcasting"
    ],
    "wof:name":"Prime Television New Zealand Limited",
    "wof:placetype":"venue"
},
  "geometry": {"coordinates":[172.597351,-43.532143],"type":"Point"}
}