{
  "type": "Feature",
  "properties": {
    "addr:full":"Rangiuru St  Rotorua Bay of Plenty",
    "addr:street":"Rangiuru St",
    "iso:country":"NZ",
    "sg:address":"Rangiuru St ",
    "sg:city":"Rotorua",
    "sg:classifiers":[
        {
            "category":"Education",
            "subcategory":"Special Training",
            "type":"Public Place"
        }
    ],
    "sg:phone":"+64 7-348 3738",
    "sg:province":"Bay of Plenty",
    "sg:tags":[
        "aid",
        "medical",
        "health",
        "beauty",
        "first"
    ],
    "wof:name":"New Zealand Red Cross Inc",
    "wof:placetype":"venue"
},
  "geometry": {"coordinates":[176.25007600000001,-38.134388],"type":"Point"}
}