{
  "type": "Feature",
  "properties": {
    "addr:full":"4 Maniapoto Street  Otorohanga Northland",
    "addr:housenumber":"4",
    "addr:street":"Maniapoto Street",
    "iso:country":"NZ",
    "sg:address":"4 Maniapoto Street ",
    "sg:city":"Otorohanga",
    "sg:classifiers":[
        {
            "category":"Retail",
            "subcategory":"Auto Repair",
            "type":"Services"
        }
    ],
    "sg:phone":"+64 7-873 7373",
    "sg:province":"Northland",
    "sg:tags":[
        "automotive",
        "electric",
        "servicing"
    ],
    "wof:name":"Deane Mark Auto Electrical Ltd",
    "wof:placetype":"venue"
},
  "geometry": {"coordinates":[175.211243,-38.186565],"type":"Point"}
}