{
  "type": "Feature",
  "properties": {
    "iso:country":"NZ",
    "sg:address":"Arnold Valley Rd Moana ",
    "sg:city":"Greymouth",
    "sg:classifiers":[
        {
            "category":"Retail",
            "subcategory":"Auto Repair",
            "type":"Services"
        }
    ],
    "sg:phone":"+64 3-738 0029",
    "sg:province":"West Coast",
    "sg:tags":[
        "automotive",
        "servicing"
    ],
    "wof:name":"Lake Brunner Service Centre",
    "wof:placetype":"venue"
},
  "geometry": {"coordinates":[171.209885,-42.451618],"type":"Point"}
}