{
  "type": "Feature",
  "properties": {
    "iso:country":"NZ",
    "sg:address":"PO Box 14037 ",
    "sg:city":"Hastings",
    "sg:classifiers":[
        {
            "category":"Autos & Motor Vehicles",
            "subcategory":"Automobile Sales",
            "type":"Retail Goods"
        }
    ],
    "sg:phone":"+64 6-878 3797",
    "sg:province":"Hawke's Bay",
    "sg:tags":[
        "home",
        "caravan",
        "leasing",
        "automotive"
    ],
    "wof:name":"Adele Stationary Caravan Hire",
    "wof:placetype":"venue"
},
  "geometry": {"coordinates":[-92.772423,44.710861],"type":"Point"}
}