{
  "type": "Feature",
  "properties": {
    "iso:country":"NZ",
    "sg:address":"Refer Our Main Ad Under Wedding Arrangements R D 3",
    "sg:city":"Pahiatua",
    "sg:classifiers":[
        {
            "category":"Shopping",
            "subcategory":"Bridal",
            "type":"Retail Goods"
        }
    ],
    "sg:phone":"+64 6-376 7126",
    "sg:tags":[
        "arrangements",
        "wear",
        "wedding"
    ],
    "wof:name":"Four Seasons Bridal Gowns",
    "wof:placetype":"venue"
},
  "geometry": {"coordinates":[175.839355,-40.455097],"type":"Point"}
}