{
  "type": "Feature",
  "properties": {
    "addr:full":"33 Owens Rd Epsom  Auckland Auckland",
    "addr:housenumber":"33",
    "addr:street":"Owens Rd",
    "iso:country":"NZ",
    "sg:address":"33 Owens Rd Epsom ",
    "sg:city":"Auckland",
    "sg:orig_category":"Health And Beauty: Mental: Psychotherapy",
    "sg:phone":"+64 9-638 7632",
    "sg:province":"Auckland",
    "wof:name":"Auckland Family Counselling & Psychotherapy Centre Inc",
    "wof:placetype":"venue"
},
  "geometry": {"coordinates":[174.77319299999999,-36.878181],"type":"Point"}
}