{
  "type": "Feature",
  "properties": {
    "iso:country":"NZ",
    "sg:address":"5/115 Great South Road Otahuhu ",
    "sg:city":"Auckland",
    "sg:classifiers":[
        {
            "category":"Home & Garden",
            "subcategory":"Home Furnishings",
            "type":"Retail Goods"
        }
    ],
    "sg:phone":"+64 9-270 0871",
    "sg:province":"Wellington",
    "sg:tags":[
        "accessory"
    ],
    "wof:name":"Greenworld Ezyway Products Ltd",
    "wof:placetype":"venue"
},
  "geometry": {"coordinates":[174.83807400000001,-36.938522],"type":"Point"}
}