{
  "type": "Feature",
  "properties": {
    "addr:full":"Ruataniwha St  Waipukurau",
    "addr:street":"Ruataniwha St",
    "iso:country":"NZ",
    "sg:address":"Ruataniwha St ",
    "sg:city":"Waipukurau",
    "sg:classifiers":[
        {
            "category":"Shopping",
            "subcategory":"Pharmacy",
            "type":"Retail Goods"
        }
    ],
    "sg:phone":"+64 6-858 8908",
    "sg:tags":[
        "product",
        "health"
    ],
    "wof:name":"Food for Thought Health",
    "wof:placetype":"venue"
},
  "geometry": {"coordinates":[176.55548099999999,-39.995388],"type":"Point"}
}