{
  "type": "Feature",
  "properties": {
    "iso:country":"NZ",
    "sg:address":"15 Pohutukawa Ave ",
    "sg:city":"Whakatane",
    "sg:orig_category":"Health And Beauty: Specialists: Osteopaths",
    "sg:phone":"+64 7-312 5796",
    "sg:province":"Bay of Plenty",
    "wof:name":"Dianne Reid-Naturopath/Osteopath",
    "wof:placetype":"venue"
},
  "geometry": {"coordinates":[177.03559899999999,-37.964138],"type":"Point"}
}