{
  "type": "Feature",
  "properties": {
    "addr:full":"17-19 Broderick Rd Johnsonville  Wellington Wellington",
    "addr:housenumber":"17-19",
    "addr:street":"Broderick Rd",
    "iso:country":"NZ",
    "sg:address":"17-19 Broderick Rd Johnsonville ",
    "sg:city":"Wellington",
    "sg:classifiers":[
        {
            "category":"Professional",
            "type":"Services"
        }
    ],
    "sg:phone":"+64 4-477 7000",
    "sg:province":"Wellington",
    "sg:tags":[
        "home",
        "cleaning",
        "help",
        "garden"
    ],
    "wof:name":"WellCare Home Support",
    "wof:placetype":"venue"
},
  "geometry": {"coordinates":[174.806183,-41.224758],"type":"Point"}
}