{
  "type": "Feature",
  "properties": {
    "addr:full":"145 Morrin Rd Panmure  Auckland Auckland",
    "addr:housenumber":"145",
    "addr:street":"Morrin Rd",
    "iso:country":"NZ",
    "sg:address":"145 Morrin Rd Panmure ",
    "sg:city":"Auckland",
    "sg:classifiers":[
        {
            "category":"Autos & Motor Vehicles",
            "subcategory":"Motorcycle Sales",
            "type":"Retail Goods"
        }
    ],
    "sg:phone":"+64 9-527 6713",
    "sg:province":"Auckland",
    "sg:tags":[
        "automotive",
        "scooter",
        "leasing"
    ],
    "wof:name":"Panmure Motorcycles",
    "wof:placetype":"venue"
},
  "geometry": {"coordinates":[174.85749799999999,-36.90181],"type":"Point"}
}