{
  "type": "Feature",
  "properties": {
    "addr:full":"25 Coronation Rd Mangere Bridge  Auckland Auckland",
    "addr:housenumber":"25",
    "addr:street":"Coronation Rd",
    "iso:country":"NZ",
    "sg:address":"25 Coronation Rd Mangere Bridge ",
    "sg:city":"Auckland",
    "sg:orig_category":"Health And Beauty: Products: Pharmacies",
    "sg:phone":"+64 9-636 4249",
    "sg:province":"Auckland",
    "wof:name":"Mangere Bridge Pharmacy",
    "wof:placetype":"venue"
},
  "geometry": {"coordinates":[174.78727699999999,-36.941795],"type":"Point"}
}