{
  "type": "Feature",
  "properties": {
    "addr:full":"Fencourt Rd  Cambridge Waikato",
    "addr:street":"Fencourt Rd",
    "iso:country":"NZ",
    "sg:address":"Fencourt Rd ",
    "sg:city":"Cambridge",
    "sg:orig_category":"Transport: Land: Horse Transport",
    "sg:phone":"+64 7-827 5028",
    "sg:province":"Waikato",
    "wof:name":"Majestic Horse Floats Ltd",
    "wof:placetype":"venue"
},
  "geometry": {"coordinates":[175.489304,-37.863377],"type":"Point"}
}