{
  "type": "Feature",
  "properties": {
    "iso:country":"NZ",
    "sg:address":"Birds Rd Clifton ",
    "sg:city":"Takaka",
    "sg:classifiers":[
        {
            "category":"Sports & Exercise",
            "subcategory":"Sports Center",
            "type":"Entertainment"
        }
    ],
    "sg:phone":"+64 3-525 9887",
    "sg:tags":[
        "health",
        "beauty",
        "fitness"
    ],
    "wof:name":"Anahata Retreat Centre",
    "wof:placetype":"venue"
},
  "geometry": {"coordinates":[-109.29393,33.047569],"type":"Point"}
}