{
  "type": "Feature",
  "properties": {
    "iso:country":"NZ",
    "sg:address":"PO Box 201 Auckland City ",
    "sg:city":"Auckland",
    "sg:classifiers":[
        {
            "category":"Building & Trades",
            "subcategory":"Electrical",
            "type":"Services"
        }
    ],
    "sg:phone":"+64 9-358 0232",
    "sg:province":"Auckland",
    "sg:tags":[
        "industrial",
        "refrigeration"
    ],
    "wof:name":"A A C & R - ALPINE",
    "wof:placetype":"venue"
},
  "geometry": {"coordinates":[174.7845,-37.006058],"type":"Point"}
}