{
  "type": "Feature",
  "properties": {
    "iso:country":"NZ",
    "sg:address":"184 Waihi Rd ",
    "sg:city":"Hawera",
    "sg:classifiers":[
        {
            "category":"Personal",
            "subcategory":"Beauty Salon",
            "type":"Services"
        }
    ],
    "sg:phone":"+64 6-278 5945",
    "sg:province":"Taranaki",
    "sg:tags":[
        "therapy",
        "health"
    ],
    "wof:name":"Central Beauty Clinic",
    "wof:placetype":"venue"
},
  "geometry": {"coordinates":[174.271561,-39.575325],"type":"Point"}
}