{
  "type": "Feature",
  "properties": {
    "addr:full":"184 Waihi Rd  Hawera Taranaki",
    "addr:housenumber":"184",
    "addr:street":"Waihi Rd",
    "iso:country":"NZ",
    "sg:address":"184 Waihi Rd ",
    "sg:city":"Hawera",
    "sg:classifiers":[
        {
            "category":"Personal",
            "subcategory":"Beauty Salon",
            "type":"Services"
        }
    ],
    "sg:phone":"+64 6-278 5945",
    "sg:province":"Taranaki",
    "sg:tags":[
        "therapy",
        "health"
    ],
    "wof:name":"Central Beauty Clinic",
    "wof:placetype":"venue"
},
  "geometry": {"coordinates":[174.27156099999999,-39.575325],"type":"Point"}
}