{
  "type": "Feature",
  "properties": {
    "addr:full":"23 Cheltenham Rd Devonport  Auckland Auckland",
    "addr:housenumber":"23",
    "addr:street":"Cheltenham Rd",
    "iso:country":"NZ",
    "sg:address":"23 Cheltenham Rd Devonport ",
    "sg:city":"Auckland",
    "sg:classifiers":[
        {
            "category":"Travel",
            "subcategory":"Bed & Breakfast",
            "type":"Entertainment"
        }
    ],
    "sg:phone":"+64 9-445 2472",
    "sg:province":"Auckland",
    "sg:tags":[
        "tourism",
        "accommodation"
    ],
    "wof:name":"Garden Room The",
    "wof:placetype":"venue"
},
  "geometry": {"coordinates":[174.79956100000001,-36.824425],"type":"Point"}
}