{
  "type": "Feature",
  "properties": {
    "iso:country":"NZ",
    "sg:address":"9 Mahinui St ",
    "sg:city":"Feilding",
    "sg:classifiers":[
        {
            "category":"Manufacturing",
            "subcategory":"Metals",
            "type":"Manufacturing & Wholesale Goods"
        }
    ],
    "sg:phone":"+64 6-323 3777",
    "sg:province":"Manawatu-Wanganui",
    "sg:tags":[
        "-",
        "engineering",
        "industrial",
        "sheet",
        "engineer"
    ],
    "wof:name":"Mobile Sheetmetals",
    "wof:placetype":"venue"
},
  "geometry": {"coordinates":[175.57904099999999,-40.234226],"type":"Point"}
}