{
  "type": "Feature",
  "properties": {
    "addr:full":"Waipapa West Rd  Kerikeri Northland",
    "addr:street":"West Rd",
    "iso:country":"NZ",
    "sg:address":"Waipapa West Rd ",
    "sg:city":"Kerikeri",
    "sg:classifiers":[
        {
            "category":"Travel",
            "subcategory":"Bed & Breakfast",
            "type":"Entertainment"
        }
    ],
    "sg:phone":"+64 9-407 9737",
    "sg:province":"Northland",
    "sg:tags":[
        "tourism",
        "accommodation"
    ],
    "wof:name":"Waterford Garden Stay",
    "wof:placetype":"venue"
},
  "geometry": {"coordinates":[173.89999399999999,-35.181915],"type":"Point"}
}