{
  "type": "Feature",
  "properties": {
    "iso:country":"NZ",
    "sg:address":"The Rotorua Rehabilitation Clinic 82 Pererika St ",
    "sg:city":"Rotorua",
    "sg:classifiers":[
        {
            "category":"Health Services",
            "subcategory":"Chiropractor",
            "type":"Services"
        }
    ],
    "sg:phone":"+64 7-349 2025",
    "sg:province":"Bay of Plenty",
    "sg:tags":[
        "specialists",
        "occupational",
        "therapist",
        "beauty"
    ],
    "wof:name":"Joanne Smith +",
    "wof:placetype":"venue"
},
  "geometry": {"coordinates":[176.24499499999999,-38.1418],"type":"Point"}
}