{
  "type": "Feature",
  "properties": {
    "addr:full":"37 Tainui St  Greymouth West Coast",
    "addr:housenumber":"37",
    "addr:street":"Tainui St",
    "iso:country":"NZ",
    "sg:address":"37 Tainui St ",
    "sg:city":"Greymouth",
    "sg:classifiers":[
        {
            "category":"Bars & Pubs",
            "subcategory":"Wine Bar",
            "type":"Food & Drink"
        }
    ],
    "sg:phone":"+64 3-768 6468",
    "sg:province":"West Coast",
    "sg:tags":[
        "wining",
        "dining",
        "cafe"
    ],
    "wof:name":"Jones's Licensed Cafe & Bar",
    "wof:placetype":"venue"
},
  "geometry": {"coordinates":[171.21121199999999,-42.449165],"type":"Point"}
}