{
  "type": "Feature",
  "properties": {
    "addr:full":"7 Sefton St Ohauiti  Tauranga Bay of Plenty",
    "addr:housenumber":"7",
    "addr:street":"Sefton St",
    "iso:country":"NZ",
    "sg:address":"7 Sefton St Ohauiti ",
    "sg:city":"Tauranga",
    "sg:classifiers":[
        {
            "category":"Education",
            "subcategory":"Dance Studio",
            "type":"Public Place"
        }
    ],
    "sg:phone":"+64 7-544 4371",
    "sg:province":"Bay of Plenty",
    "sg:tags":[
        "school",
        "dancing",
        "-",
        "leisure",
        "sports",
        "sport"
    ],
    "wof:name":"Deanna Bowden School of Dance",
    "wof:placetype":"venue"
},
  "geometry": {"coordinates":[176.16197199999999,-37.740509],"type":"Point"}
}