{
  "type": "Feature",
  "properties": {
    "addr:full":"325 c Great South Rd Takanini  Auckland Auckland",
    "addr:housenumber":"325 c",
    "addr:street":"Great South Rd",
    "iso:country":"NZ",
    "sg:address":"325 c Great South Rd Takanini ",
    "sg:city":"Auckland",
    "sg:classifiers":[
        {
            "category":"Personal",
            "subcategory":"Adult",
            "type":"Services"
        }
    ],
    "sg:phone":"+64 9-296 5030",
    "sg:province":"Auckland",
    "sg:tags":[
        "sport",
        "leisure"
    ],
    "wof:name":"V.I.P Club",
    "wof:placetype":"venue"
},
  "geometry": {"coordinates":[174.930328,-37.051899],"type":"Point"}
}