{
  "type": "Feature",
  "properties": {
    "iso:country":"NZ",
    "sg:address":"381 Halswell Rd ",
    "sg:city":"Christchurch",
    "sg:orig_category":"Shopping: Retail Stores: Books: Libraries",
    "sg:phone":"+64 3-941 7944",
    "sg:province":"Canterbury",
    "wof:name":"Christchurch City Libraries",
    "wof:placetype":"venue"
},
  "geometry": {"coordinates":[172.570694,-43.584793],"type":"Point"}
}