{
  "type": "Feature",
  "properties": {
    "addr:full":"68 b Lunn Ave Mt Wellington  Auckland Auckland",
    "addr:housenumber":"68",
    "addr:street":"B Lunn Ave",
    "iso:country":"NZ",
    "sg:address":"68 b Lunn Ave Mt Wellington ",
    "sg:city":"Auckland",
    "sg:classifiers":[
        {
            "category":"Home & Garden",
            "subcategory":"Garden Supply",
            "type":"Retail Goods"
        }
    ],
    "sg:phone":"+64 9-570 0188",
    "sg:province":"Auckland",
    "sg:tags":[
        "outdoor"
    ],
    "sg:website":"http://www.spapool.co.nz",
    "wof:name":"Spa International Ltd",
    "wof:placetype":"venue"
},
  "geometry": {"coordinates":[174.835083,-36.891361],"type":"Point"}
}