{
  "type": "Feature",
  "properties": {
    "addr:full":"PO Box 3035 Ohope  Whakatane Bay of Plenty",
    "addr:housenumber":"po",
    "addr:postcode":"3035",
    "addr:street":"Box;Whakatane",
    "iso:country":"NZ",
    "sg:address":"PO Box 3035 Ohope ",
    "sg:city":"Whakatane",
    "sg:classifiers":[
        {
            "category":"Home & Garden",
            "subcategory":"Home Furnishings",
            "type":"Retail Goods"
        }
    ],
    "sg:phone":"+64 7-312 4425",
    "sg:province":"Bay of Plenty",
    "sg:tags":[
        "furniture/furnishings",
        "bedding",
        "bed"
    ],
    "wof:name":"Tilt-Away Beds of NZ Ltd",
    "wof:placetype":"venue"
},
  "geometry": {"coordinates":[177.05609100000001,-37.97113],"type":"Point"}
}