{
  "type": "Feature",
  "properties": {
    "iso:country":"NZ",
    "sg:address":"8 Neidpath Rd Mornington ",
    "sg:city":"Dunedin",
    "sg:classifiers":[
        {
            "category":"Health Services",
            "subcategory":"Dentist",
            "type":"Services"
        }
    ],
    "sg:phone":"+64 3-453 4641",
    "sg:province":"Otago",
    "sg:tags":[
        "dental",
        "beauty"
    ],
    "wof:name":"Carter Dental Ceramics",
    "wof:placetype":"venue"
},
  "geometry": {"coordinates":[170.48786899999999,-45.884399],"type":"Point"}
}