{
  "type": "Feature",
  "properties": {
    "addr:full":"9 St Andrew St  Dunedin Otago",
    "addr:housenumber":"9",
    "addr:street":"St Andrew St",
    "iso:country":"NZ",
    "sg:address":"9 St Andrew St ",
    "sg:city":"Dunedin",
    "sg:classifiers":[
        {
            "category":"Home & Garden",
            "subcategory":"Home Furnishings",
            "type":"Retail Goods"
        }
    ],
    "sg:phone":"+64 3-477 5673",
    "sg:province":"Otago",
    "sg:tags":[
        "furniture/furnishings",
        "-",
        "secondhand",
        "furniture"
    ],
    "wof:name":"St Andrew Street Traders",
    "wof:placetype":"venue"
},
  "geometry": {"coordinates":[170.50376900000001,-45.871399],"type":"Point"}
}