{
  "type": "Feature",
  "properties": {
    "iso:country":"NZ",
    "sg:address":"64 Eliot St New ",
    "sg:city":"Plymouth",
    "sg:classifiers":[
        {
            "category":"Shopping",
            "type":"Retail Goods"
        }
    ],
    "sg:phone":"+64 6-753 4792",
    "sg:province":"Taranaki",
    "sg:website":"http://www.yellowpages.co.nz/for/tshaudiovideo/dp42743.html",
    "wof:name":"TSH Audio and Video",
    "wof:placetype":"venue"
},
  "geometry": {"coordinates":[-116.819725,43.97221],"type":"Point"}
}