{
  "type": "Feature",
  "properties": {
    "iso:country":"NZ",
    "sg:address":"91 Crinan St ",
    "sg:city":"Invercargill",
    "sg:classifiers":[
        {
            "category":"Bus Charters",
            "type":"Transportation"
        }
    ],
    "sg:phone":"+64 3-214 4981",
    "sg:province":"Southland",
    "sg:tags":[
        "services",
        "travel",
        "tourism"
    ],
    "wof:name":"Maia Travel",
    "wof:placetype":"venue"
},
  "geometry": {"coordinates":[168.34646599999999,-46.422543],"type":"Point"}
}