{
  "type": "Feature",
  "properties": {
    "iso:country":"NZ",
    "sg:address":"14-17 Tory St Petone Lower ",
    "sg:city":"Hutt",
    "sg:orig_category":"Clothing And Fabric: Clothing: Uniforms",
    "sg:phone":"+64 4-568 5179",
    "sg:province":"Wellington",
    "sg:website":"http://www.nzts.co.nz",
    "wof:name":"NZTS",
    "wof:placetype":"venue"
},
  "geometry": {"coordinates":[174.8829498291,-41.2288360596],"type":"Point"}
}