{
  "type": "Feature",
  "properties": {
    "addr:full":"43 High St  Blenheim Marlborough",
    "addr:housenumber":"43",
    "addr:street":"High St",
    "iso:country":"NZ",
    "sg:address":"43 High St ",
    "sg:city":"Blenheim",
    "sg:classifiers":[
        {
            "category":"Banks & Credit Unions",
            "subcategory":"Investment Brokerage",
            "type":"Services"
        }
    ],
    "sg:phone":"+64 3-578 9869",
    "sg:province":"Marlborough",
    "sg:tags":[
        "personal",
        "accountant",
        "chartered",
        "-",
        "finance"
    ],
    "wof:name":"Startup S W",
    "wof:placetype":"venue"
},
  "geometry": {"coordinates":[-79.65303,34.510719],"type":"Point"}
}