{
  "type": "Feature",
  "properties": {
    "iso:country":"NZ",
    "sg:address":"114 Onerahi Rd Onerahi ",
    "sg:city":"Whangarei",
    "sg:classifiers":[
        {
            "category":"Bars & Pubs",
            "subcategory":"Lounge",
            "type":"Food & Drink"
        }
    ],
    "sg:phone":"+64 9-436 0611",
    "sg:province":"Northland",
    "sg:tags":[
        "baker",
        "-"
    ],
    "wof:name":"Onerahi Bakery",
    "wof:placetype":"venue"
},
  "geometry": {"coordinates":[174.36821,-35.75478],"type":"Point"}
}