{
  "type": "Feature",
  "properties": {
    "addr:full":"4 B Averton Pl East Tamaki  Auckland Auckland",
    "addr:housenumber":"4",
    "addr:street":"B Averton Pl",
    "iso:country":"NZ",
    "sg:address":"4 B Averton Pl East Tamaki ",
    "sg:city":"Auckland",
    "sg:orig_category":"Transport: Transportation: Carriers",
    "sg:phone":"+64 9-292 9200",
    "sg:province":"Auckland",
    "wof:name":"Bert Tarry Carriers",
    "wof:placetype":"venue"
},
  "geometry": {"coordinates":[174.87951699999999,-36.945312],"type":"Point"}
}