{
  "type": "Feature",
  "properties": {
    "addr:full":"99 a Queen St  Masterton Wellington",
    "addr:housenumber":"99",
    "addr:street":"A Queen St",
    "iso:country":"NZ",
    "sg:address":"99 a Queen St ",
    "sg:city":"Masterton",
    "sg:classifiers":[
        {
            "category":"Shopping",
            "subcategory":"Gifts & Souvenirs",
            "type":"Retail Goods"
        }
    ],
    "sg:phone":"+64 6-377 3874",
    "sg:province":"Wellington",
    "sg:tags":[
        "shop",
        "gifts",
        "supplier"
    ],
    "wof:name":"Everything $2 Masterton",
    "wof:placetype":"venue"
},
  "geometry": {"coordinates":[175.66197199999999,-40.949745],"type":"Point"}
}