{
  "type": "Feature",
  "properties": {
    "addr:full":"123 Mackay St  Greymouth West Coast",
    "addr:housenumber":"123",
    "addr:street":"Mackay St",
    "iso:country":"NZ",
    "sg:address":"123 Mackay St ",
    "sg:city":"Greymouth",
    "sg:orig_category":"Shopping: Sports Retailers: Sports Goods: Sporting Goods",
    "sg:phone":"+64 3-768 6175",
    "sg:province":"West Coast",
    "wof:name":"Greymouth Sports",
    "wof:placetype":"venue"
},
  "geometry": {"coordinates":[171.21238700000001,-42.448616],"type":"Point"}
}