{
  "type": "Feature",
  "properties": {
    "addr:full":"235 Ridge Rd Albany  Auckland Auckland",
    "addr:housenumber":"235",
    "addr:street":"Ridge Rd",
    "iso:country":"NZ",
    "sg:address":"235 Ridge Rd Albany ",
    "sg:city":"Auckland",
    "sg:orig_category":"Home And Garden: Gardening: Services: Lawnmowing Services",
    "sg:phone":"+64 9-415 4492",
    "sg:province":"Auckland",
    "wof:name":"Blockbusters Enviroworks",
    "wof:placetype":"venue"
},
  "geometry": {"coordinates":[174.661652,-36.733921],"type":"Point"}
}