{
  "type": "Feature",
  "properties": {
    "iso:country":"NZ",
    "sg:address":"150 Hutt Rd ",
    "sg:city":"Wellington",
    "sg:classifiers":[
        {
            "category":"Banks & Credit Unions",
            "subcategory":"Investment Brokerage",
            "type":"Services"
        }
    ],
    "sg:phone":"+64 800 535 500",
    "sg:province":"Wellington",
    "sg:tags":[
        "automotive",
        "leasing",
        "sale"
    ],
    "sg:website":"http://www.yellowpages.co.nz/for/acetouristrentals/dp33603.html",
    "wof:name":"Ace Tourist Rentals (NZ) Ltd",
    "wof:placetype":"venue"
},
  "geometry": {"coordinates":[-85.910454,33.827946],"type":"Point"}
}