{
  "type": "Feature",
  "properties": {
    "iso:country":"NZ",
    "sg:address":"74 Robert St ",
    "sg:city":"Whangarei",
    "sg:classifiers":[
        {
            "category":"Home & Garden",
            "subcategory":"Building Materials",
            "type":"Retail Goods"
        }
    ],
    "sg:phone":"+64 9-438 6342",
    "sg:province":"Northland",
    "sg:tags":[
        "fittings",
        "staircase",
        "handrail"
    ],
    "wof:name":"Superior Balustrades (Whangarei) Ltd",
    "wof:placetype":"venue"
},
  "geometry": {"coordinates":[174.32519500000001,-35.727093],"type":"Point"}
}