{
  "type": "Feature",
  "properties": {
    "addr:full":"5 Rogers La  Masterton Wellington",
    "addr:housenumber":"5",
    "addr:street":"Rogers La",
    "iso:country":"NZ",
    "sg:address":"5 Rogers La ",
    "sg:city":"Masterton",
    "sg:classifiers":[
        {
            "category":"Building & Trades",
            "subcategory":"Plumbing",
            "type":"Services"
        }
    ],
    "sg:phone":"+64 6-377 0111",
    "sg:province":"Wellington",
    "sg:tags":[
        "home",
        "plumber",
        "garden",
        "related"
    ],
    "wof:name":"Masterton Plumbing Services Ltd",
    "wof:placetype":"venue"
},
  "geometry": {"coordinates":[175.660889,-40.95261],"type":"Point"}
}