{
  "type": "Feature",
  "properties": {
    "iso:country":"NZ",
    "sg:address":"32 Leonard St ",
    "sg:city":"Greymouth",
    "sg:orig_category":"Industrial: Packaging: Packaging - General",
    "sg:phone":"+64 3-768 9323",
    "sg:province":"West Coast",
    "wof:name":"Packaging House",
    "wof:placetype":"venue"
},
  "geometry": {"coordinates":[171.204865,-42.450317],"type":"Point"}
}