{
  "type": "Feature",
  "properties": {
    "addr:full":"131 Tidal Rd Mangere  Auckland Auckland",
    "addr:housenumber":"131",
    "addr:street":"Tidal Rd",
    "iso:country":"NZ",
    "sg:address":"131 Tidal Rd Mangere ",
    "sg:city":"Auckland",
    "sg:orig_category":"Home And Garden: Gardening: Services: Lawnmowing Services",
    "sg:phone":"+64 9-256 0988",
    "sg:province":"Auckland",
    "wof:name":"Sen Lawnmowing Services",
    "wof:placetype":"venue"
},
  "geometry": {"coordinates":[174.82699600000001,-36.981434],"type":"Point"}
}