{
  "type": "Feature",
  "properties": {
    "iso:country":"NZ",
    "sg:address":"19 Klondyke Drive Hornby ",
    "sg:city":"Christchurch",
    "sg:classifiers":[
        {
            "category":"Bars & Pubs",
            "subcategory":"Lounge",
            "type":"Food & Drink"
        }
    ],
    "sg:phone":"+64 3-344 0257",
    "sg:province":"Canterbury",
    "sg:tags":[
        "-"
    ],
    "sg:website":"http://www.thorntonsicecream.co.nz",
    "wof:name":"Thorntons Ice Cream Limited",
    "wof:placetype":"venue"
},
  "geometry": {"coordinates":[172.53633099999999,-43.534431],"type":"Point"}
}