{
  "type": "Feature",
  "properties": {
    "iso:country":"NZ",
    "sg:address":"Rewarewa Rd ",
    "sg:city":"Whangarei",
    "sg:classifiers":[
        {
            "category":"Utilities",
            "subcategory":"Sewage",
            "type":"Services"
        }
    ],
    "sg:phone":"+64 9-438 5565",
    "sg:province":"Northland",
    "sg:tags":[
        "home",
        "tank",
        "garden",
        "septic"
    ],
    "wof:name":"Liquid Waste Treatment NZ Ltd",
    "wof:placetype":"venue"
},
  "geometry": {"coordinates":[174.315186,-35.752209],"type":"Point"}
}