{
  "type": "Feature",
  "properties": {
    "iso:country":"NZ",
    "sg:address":"PO Box 5028 Port Nelson ",
    "sg:city":"Nelson",
    "sg:orig_category":"Transport: Boats And Marine: Shipping: Shipping Companies",
    "sg:phone":"+64 3-548 1055",
    "sg:province":"Nelson",
    "wof:name":"Owens Services-Nelson",
    "wof:placetype":"venue"
},
  "geometry": {"coordinates":[173.276215,-41.2621],"type":"Point"}
}