{
  "type": "Feature",
  "properties": {
    "addr:full":"Cnr Karangahape Rd & Ponsonby Rd Newton  Auckland Auckland",
    "addr:street":"Cnr Karangahape Rd & Ponsonby Rd",
    "iso:country":"NZ",
    "sg:address":"Cnr Karangahape Rd & Ponsonby Rd Newton ",
    "sg:city":"Auckland",
    "sg:orig_category":"Shopping: Sports Retailers: Cycles",
    "sg:phone":"+64 9-309 6444",
    "sg:province":"Auckland",
    "sg:website":"http://www.yellowpages.co.nz/pages/201600137/dp39623.html",
    "wof:name":"R & R Sport",
    "wof:placetype":"venue"
},
  "geometry": {"coordinates":[174.754807,-36.860142],"type":"Point"}
}