{
  "type": "Feature",
  "properties": {
    "addr:full":"15 Wallace St  Featherston",
    "addr:housenumber":"15",
    "addr:street":"Wallace St",
    "iso:country":"NZ",
    "sg:address":"15 Wallace St ",
    "sg:city":"Featherston",
    "sg:classifiers":[
        {
            "category":"Health Services",
            "subcategory":"Hospital",
            "type":"Services"
        }
    ],
    "sg:phone":"+64 6-308 9767",
    "sg:tags":[
        "medical",
        "beauty"
    ],
    "wof:name":"Plunket Nurses",
    "wof:placetype":"venue"
},
  "geometry": {"coordinates":[175.32693499999999,-41.1213],"type":"Point"}
}