{
  "type": "Feature",
  "properties": {
    "iso:country":"NZ",
    "sg:address":"Walkers Rd Palmerston ",
    "sg:city":"Palmerston North",
    "sg:classifiers":[
        {
            "category":"Food & Beverages",
            "subcategory":"Candy",
            "type":"Retail Goods"
        }
    ],
    "sg:phone":"+64 6-356 5323",
    "sg:province":"Manawatu-Wanganui",
    "sg:tags":[
        "confectioner",
        "drink",
        "-"
    ],
    "wof:name":"Sweetline Ltd",
    "wof:placetype":"venue"
},
  "geometry": {"coordinates":[175.55967699999999,-40.390213],"type":"Point"}
}