{
  "type": "Feature",
  "properties": {
    "addr:full":"230 Cambridge Tce Naenae  Wellington Wellington",
    "addr:housenumber":"230",
    "addr:street":"Cambridge Tce",
    "iso:country":"NZ",
    "sg:address":"230 Cambridge Tce Naenae ",
    "sg:city":"Wellington",
    "sg:classifiers":[
        {
            "category":"Home & Garden",
            "subcategory":"Building Materials",
            "type":"Retail Goods"
        }
    ],
    "sg:phone":"+64 4-567 5198",
    "sg:province":"Wellington",
    "sg:tags":[
        "design",
        "fitting",
        "fittings",
        "kitchen"
    ],
    "sg:website":"http://www.trethewey.co.nz",
    "wof:name":"Trethewey Granite & Marble",
    "wof:placetype":"venue"
},
  "geometry": {"coordinates":[174.950165,-41.195786],"type":"Point"}
}