{
  "type": "Feature",
  "properties": {
    "iso:country":"NZ",
    "sg:address":"38-40 Waione St Petone Lower ",
    "sg:city":"Hutt",
    "sg:classifiers":[
        {
            "category":"Wholesale",
            "subcategory":"Auto Parts",
            "type":"Manufacturing & Wholesale Goods"
        }
    ],
    "sg:phone":"+64 4-568 7453",
    "sg:province":"Wellington",
    "sg:tags":[
        "automotive",
        "supplies"
    ],
    "wof:name":"Universal Trucks & Equipment Ltd",
    "wof:placetype":"venue"
},
  "geometry": {"coordinates":[174.89387500000001,-41.232182],"type":"Point"}
}