{
  "type": "Feature",
  "properties": {
    "addr:full":"86 Christian Rd Swanson  Auckland Auckland",
    "addr:housenumber":"86",
    "addr:street":"Christian Rd",
    "iso:country":"NZ",
    "sg:address":"86 Christian Rd Swanson ",
    "sg:city":"Auckland",
    "sg:orig_category":"Farming: Services: Hedge Cutting Contractors",
    "sg:phone":"+64 9-833 6722",
    "sg:province":"Auckland",
    "wof:name":"K & R Shelterbelt Trimmers",
    "wof:placetype":"venue"
},
  "geometry": {"coordinates":[174.56724500000001,-36.88187],"type":"Point"}
}