{
  "type": "Feature",
  "properties": {
    "addr:full":"46 Fitzherbert St  Hokitika West Coast",
    "addr:housenumber":"46",
    "addr:street":"Fitzherbert St",
    "iso:country":"NZ",
    "sg:address":"46 Fitzherbert St ",
    "sg:city":"Hokitika",
    "sg:classifiers":[
        {
            "category":"Retail",
            "subcategory":"Auto Repair",
            "type":"Services"
        }
    ],
    "sg:phone":"+64 3-755 8346",
    "sg:province":"West Coast",
    "sg:tags":[
        "automotive",
        "servicing"
    ],
    "wof:name":"Hokitika Service Station (1992) Ltd",
    "wof:placetype":"venue"
},
  "geometry": {"coordinates":[170.97219799999999,-42.711411],"type":"Point"}
}