{
  "type": "Feature",
  "properties": {
    "iso:country":"NZ",
    "sg:address":"9 Hurstmere Rd Takapuna ",
    "sg:city":"Auckland",
    "sg:classifiers":[
        {
            "category":"Food & Beverages",
            "subcategory":"Candy",
            "type":"Retail Goods"
        }
    ],
    "sg:phone":"+64 9-489 8337",
    "sg:province":"Auckland",
    "sg:tags":[
        "confectioner",
        "drink",
        "-"
    ],
    "wof:name":"Chocolate Heaven",
    "wof:placetype":"venue"
},
  "geometry": {"coordinates":[174.772552,-36.78886],"type":"Point"}
}