{
  "type": "Feature",
  "properties": {
    "addr:full":"41 Queen Victoria St  Motueka Tasman",
    "addr:housenumber":"41",
    "addr:street":"Queen Victoria St",
    "iso:country":"NZ",
    "sg:address":"41 Queen Victoria St ",
    "sg:city":"Motueka",
    "sg:classifiers":[
        {
            "category":"Retail",
            "subcategory":"Driving School",
            "type":"Services"
        }
    ],
    "sg:phone":"+64 3-528 8241",
    "sg:province":"Tasman",
    "sg:tags":[
        "training",
        "education",
        "driver"
    ],
    "wof:name":"Driver Licence Endorsements",
    "wof:placetype":"venue"
},
  "geometry": {"coordinates":[172.99525499999999,-41.116432],"type":"Point"}
}