{
  "type": "Feature",
  "properties": {
    "addr:full":"207 Main South Rd Sockburn  Christchurch Canterbury",
    "addr:housenumber":"207",
    "addr:street":"Main South Rd",
    "iso:country":"NZ",
    "sg:address":"207 Main South Rd Sockburn ",
    "sg:city":"Christchurch",
    "sg:classifiers":[
        {
            "category":"Autos & Motor Vehicles",
            "subcategory":"Automobile Sales",
            "type":"Retail Goods"
        }
    ],
    "sg:phone":"+64 3-343 3877",
    "sg:province":"Canterbury",
    "sg:tags":[
        "bus",
        "leasing",
        "truck",
        "automotive"
    ],
    "wof:name":"Simply Trucks",
    "wof:placetype":"venue"
},
  "geometry": {"coordinates":[172.55032299999999,-43.54092],"type":"Point"}
}