{
  "type": "Feature",
  "properties": {
    "addr:full":"11 James St  Lincoln",
    "addr:housenumber":"11",
    "addr:street":"James St",
    "iso:country":"NZ",
    "sg:address":"11 James St ",
    "sg:city":"Lincoln",
    "sg:classifiers":[
        {
            "category":"Personal",
            "type":"Services"
        }
    ],
    "sg:phone":"+64 3-325 6262",
    "sg:tags":[
        "celebrant",
        "arrangements",
        "marriage",
        "wedding"
    ],
    "wof:name":"Blanche Beverley",
    "wof:placetype":"venue"
},
  "geometry": {"coordinates":[-86.102081,33.608395],"type":"Point"}
}