{
  "type": "Feature",
  "properties": {
    "iso:country":"NZ",
    "sg:address":"16 Bay Park Pl Beach Haven ",
    "sg:city":"Auckland",
    "sg:orig_category":"Industrial: Metal: Stainless Steel",
    "sg:phone":"+64 9-482 1330",
    "sg:province":"Auckland",
    "wof:name":"Designer Stainless",
    "wof:placetype":"venue"
},
  "geometry": {"coordinates":[174.68959000000001,-36.790905],"type":"Point"}
}