{
  "type": "Feature",
  "properties": {
    "addr:full":"23 Perth St  Oamaru Otago",
    "addr:housenumber":"23",
    "addr:street":"Perth St",
    "iso:country":"NZ",
    "sg:address":"23 Perth St ",
    "sg:city":"Oamaru",
    "sg:classifiers":[
        {
            "category":"Professional",
            "subcategory":"Art Services",
            "type":"Services"
        }
    ],
    "sg:phone":"+64 3-434 8086",
    "sg:province":"Otago",
    "sg:tags":[
        "picture",
        "arts",
        "sport",
        "framing",
        "leisure"
    ],
    "wof:name":"Studio Picture Framing",
    "wof:placetype":"venue"
},
  "geometry": {"coordinates":[170.96083100000001,-45.110683],"type":"Point"}
}