{
  "type": "Feature",
  "properties": {
    "addr:full":"15 Washington Ave Glendowie  Auckland Auckland",
    "addr:housenumber":"15",
    "addr:street":"Washington Ave",
    "iso:country":"NZ",
    "sg:address":"15 Washington Ave Glendowie ",
    "sg:city":"Auckland",
    "sg:orig_category":"Home And Garden: Gardening: Services: Landscape Design",
    "sg:phone":"+64 9-521 3923",
    "sg:province":"Auckland",
    "wof:name":"Gardens by Max - Max Jaffe",
    "wof:placetype":"venue"
},
  "geometry": {"coordinates":[174.865646,-36.868458],"type":"Point"}
}