{
  "type": "Feature",
  "properties": {
    "iso:country":"NZ",
    "sg:address":"300 Gladstone Rd ",
    "sg:city":"Gisborne",
    "sg:orig_category":"Automotive: General Services: Service Stations",
    "sg:phone":"+64 6-868 5082",
    "sg:province":"Gisborne",
    "wof:name":"Shell Midway",
    "wof:placetype":"venue"
},
  "geometry": {"coordinates":[178.021042,-38.662998],"type":"Point"}
}