{
  "type": "Feature",
  "properties": {
    "iso:country":"NZ",
    "sg:address":"Ethel Gulliver Bell Block New ",
    "sg:city":"Plymouth",
    "sg:orig_category":"Shopping: Retail Stores: Florists",
    "sg:phone":"+64 6-755 3995",
    "sg:province":"Taranaki",
    "wof:name":"Gully's Flowers",
    "wof:placetype":"venue"
},
  "geometry": {"coordinates":[174.14274599999999,-39.032024],"type":"Point"}
}