{
  "type": "Feature",
  "properties": {
    "iso:country":"NZ",
    "sg:address":"11 Stadium Dve ",
    "sg:city":"Pukekohe",
    "sg:classifiers":[
        {
            "category":"Retail",
            "subcategory":"Auto Repair",
            "type":"Services"
        }
    ],
    "sg:phone":"+64 9-238 6398",
    "sg:province":"Auckland",
    "sg:tags":[
        "muffler",
        "exhaust",
        "servicing",
        "automotive"
    ],
    "wof:name":"Knight Mufflers",
    "wof:placetype":"venue"
},
  "geometry": {"coordinates":[174.9302520752,-37.195728302],"type":"Point"}
}