{
  "type": "Feature",
  "properties": {
    "iso:country":"NZ",
    "sg:address":"102 Vickerman St Port Nelson ",
    "sg:city":"Nelson",
    "sg:orig_category":"Automotive: General Services: Engine Importers/Dealers",
    "sg:phone":"+64 3-546 9200",
    "sg:province":"Nelson",
    "wof:name":"Nalder & Biddle (Nelson) Ltd",
    "wof:placetype":"venue"
},
  "geometry": {"coordinates":[173.27989199999999,-41.260784],"type":"Point"}
}