{
  "type": "Feature",
  "properties": {
    "iso:country":"NZ",
    "sg:address":"23 Sundown Ave Manly Hibiscus ",
    "sg:city":"Hibiscus Coast",
    "sg:orig_category":"Industrial: Parts: Pipes, Tubes And Cabling: Cables",
    "sg:phone":"+64 9-424 3652",
    "sg:province":"Auckland",
    "wof:name":"Coastal Cabling Solutions",
    "wof:placetype":"venue"
},
  "geometry": {"coordinates":[-93.201332,43.284019],"type":"Point"}
}