{
  "type": "Feature",
  "properties": {
    "addr:full":"Stedman Rd Taieri Airport  Dunedin Otago",
    "addr:street":"Stedman Rd",
    "iso:country":"NZ",
    "sg:address":"Stedman Rd Taieri Airport ",
    "sg:city":"Dunedin",
    "sg:orig_category":"Sports And Leisure: Sports: Aerial",
    "sg:phone":"+64 3-489 6158",
    "sg:province":"Otago",
    "wof:name":"Otago Aero Club Inc",
    "wof:placetype":"venue"
},
  "geometry": {"coordinates":[170.344223,-45.839268],"type":"Point"}
}