{
  "type": "Feature",
  "properties": {
    "addr:full":"6 Lucas La  Christchurch Canterbury",
    "addr:housenumber":"6",
    "addr:street":"Lucas La Christchurch",
    "iso:country":"NZ",
    "sg:address":"6 Lucas La ",
    "sg:city":"Christchurch",
    "sg:orig_category":"Industrial: Services: Gasfitters",
    "sg:phone":"+64 25329307",
    "sg:province":"Canterbury",
    "wof:name":"Craftsman Gas Services Ltd",
    "wof:placetype":"venue"
},
  "geometry": {"coordinates":[172.66885400000001,-43.565277],"type":"Point"}
}