{
  "type": "Feature",
  "properties": {
    "addr:full":"21 Currie Ave Mt Roskill  Auckland Auckland",
    "addr:housenumber":"21",
    "addr:street":"Currie Ave",
    "iso:country":"NZ",
    "sg:address":"21 Currie Ave Mt Roskill ",
    "sg:city":"Auckland",
    "sg:orig_category":"Home And Garden: Children",
    "sg:phone":"+64 9-624 1021",
    "sg:province":"Auckland",
    "wof:name":"Playcentres",
    "wof:placetype":"venue"
},
  "geometry": {"coordinates":[174.74276699999999,-36.905895],"type":"Point"}
}