{
  "type": "Feature",
  "properties": {
    "addr:full":"1238 Tutanekai St  Rotorua Bay of Plenty",
    "addr:housenumber":"1238",
    "addr:street":"Tutanekai St",
    "iso:country":"NZ",
    "sg:address":"1238 Tutanekai St ",
    "sg:city":"Rotorua",
    "sg:orig_category":"Shopping: Retail Stores: Books: Bookshops",
    "sg:phone":"+64 7-348 3699",
    "sg:province":"Bay of Plenty",
    "wof:name":"Whitcoulls",
    "wof:placetype":"venue"
},
  "geometry": {"coordinates":[176.25174000000001,-38.137489],"type":"Point"}
}