{
  "type": "Feature",
  "properties": {
    "iso:country":"NZ",
    "sg:address":"Baycourt Bay Rd ",
    "sg:city":"Wellington",
    "sg:classifiers":[
        {
            "category":"Travel",
            "subcategory":"Hotels & Motels",
            "type":"Entertainment"
        }
    ],
    "sg:phone":"+64 4-387 1600",
    "sg:province":"Wellington",
    "sg:tags":[
        "tourism",
        "-",
        "rental",
        "accommodation"
    ],
    "wof:name":"Housing New Zealand Corporation",
    "wof:placetype":"venue"
},
  "geometry": {"coordinates":[-85.910454,33.827946],"type":"Point"}
}