{
  "type": "Feature",
  "properties": {
    "addr:full":"19 Hill Rd  Manurewa Auckland",
    "addr:housenumber":"19",
    "addr:street":"Hill Rd",
    "iso:country":"NZ",
    "sg:address":"19 Hill Rd ",
    "sg:city":"Manurewa",
    "sg:classifiers":[
        {
            "category":"Home & Garden",
            "subcategory":"Garden Supply",
            "type":"Retail Goods"
        }
    ],
    "sg:phone":"+64 252875571",
    "sg:province":"Auckland",
    "sg:tags":[
        "products",
        "lawn",
        "gardening",
        "turf"
    ],
    "wof:name":"Green As Grass",
    "wof:placetype":"venue"
},
  "geometry": {"coordinates":[174.91696200000001,-37.021488],"type":"Point"}
}