{
  "type": "Feature",
  "properties": {
    "addr:full":"4/56 Hayton Rd Sockburn  Christchurch Canterbury",
    "addr:housenumber":"4 / 56",
    "addr:street":"Hayton Rd",
    "iso:country":"NZ",
    "sg:address":"4/56 Hayton Rd Sockburn ",
    "sg:city":"Christchurch",
    "sg:orig_category":"Industrial: Parts: Fasteners - Industrial",
    "sg:phone":"+64 3-343 6740",
    "sg:province":"Canterbury",
    "wof:name":"MSL Ltd",
    "wof:placetype":"venue"
},
  "geometry": {"coordinates":[172.55043000000001,-43.534966],"type":"Point"}
}