{
  "type": "Feature",
  "properties": {
    "iso:country":"NZ",
    "sg:address":"PO Box 21-426 Henderson Auckland ",
    "sg:city":"Auckland",
    "sg:orig_category":"Home And Garden: Gardening: Products",
    "sg:phone":"+64 800 694 7336",
    "sg:province":"Auckland",
    "sg:website":"http://www.sog.co.nz",
    "wof:name":"Switched On Gardener",
    "wof:placetype":"venue"
},
  "geometry": {"coordinates":[174.61364746090001,-36.8975791931],"type":"Point"}
}