{
  "type": "Feature",
  "properties": {
    "addr:full":"11 Gow St Mosgiel  Dunedin Otago",
    "addr:housenumber":"11",
    "addr:street":"Gow St",
    "iso:country":"NZ",
    "sg:address":"11 Gow St Mosgiel ",
    "sg:city":"Dunedin",
    "sg:classifiers":[
        {
            "category":"Building & Trades",
            "subcategory":"Electrical",
            "type":"Services"
        }
    ],
    "sg:phone":"+64 3-489 7093",
    "sg:province":"Otago",
    "sg:tags":[
        "industrial",
        "refrigeration"
    ],
    "wof:name":"Allan Terry Engineering Ltd",
    "wof:placetype":"venue"
},
  "geometry": {"coordinates":[170.350876,-45.887936],"type":"Point"}
}