{
  "type": "Feature",
  "properties": {
    "iso:country":"NZ",
    "sg:address":"PO Box 76-378 Manukau City ",
    "sg:city":"Auckland",
    "sg:classifiers":[
        {
            "category":"Manufacturing",
            "subcategory":"Rubber & Plastics",
            "type":"Manufacturing & Wholesale Goods"
        }
    ],
    "sg:phone":"+64 9-262 3773",
    "sg:province":"Auckland",
    "sg:tags":[
        "industrial",
        "goods"
    ],
    "sg:website":"http://www.plasticsnz.com",
    "wof:name":"Plastics New Zealand Incorporated",
    "wof:placetype":"venue"
},
  "geometry": {"coordinates":[174.881454,-36.98967],"type":"Point"}
}