{
  "type": "Feature",
  "properties": {
    "iso:country":"NZ",
    "sg:address":"41 B Birmingham Dve Middleton ",
    "sg:city":"Christchurch",
    "sg:orig_category":"Home And Garden: Furniture/Furnishings: Blinds",
    "sg:phone":"+64 3-338 2229",
    "sg:province":"Canterbury",
    "wof:name":"Christchurch Window Coverings Ltd",
    "wof:placetype":"venue"
},
  "geometry": {"coordinates":[172.58560199999999,-43.543633],"type":"Point"}
}