{
  "type": "Feature",
  "properties": {
    "iso:country":"NZ",
    "sg:address":"Shop 11 Piccadilly Arcade Grey St ",
    "sg:city":"Tauranga",
    "sg:classifiers":[
        {
            "category":"Internet Cafe",
            "subcategory":"None",
            "type":"Food & Drink"
        }
    ],
    "sg:phone":"+64 7-578 7303",
    "sg:province":"Bay of Plenty",
    "sg:tags":[
        "wining",
        "dining"
    ],
    "wof:name":"Cybersurf",
    "wof:placetype":"venue"
},
  "geometry": {"coordinates":[176.144745,-37.703156],"type":"Point"}
}