{
  "type": "Feature",
  "properties": {
    "addr:full":"192 Featherston St Palmerston  Palmerston North Manawatu-Wanganui",
    "addr:housenumber":"192",
    "addr:street":"Featherston St Palmerston",
    "iso:country":"NZ",
    "sg:address":"192 Featherston St Palmerston ",
    "sg:city":"Palmerston North",
    "sg:classifiers":[
        {
            "category":"Food Court",
            "type":"Food & Drink"
        }
    ],
    "sg:phone":"+64 6-353 3355",
    "sg:province":"Manawatu-Wanganui",
    "sg:tags":[
        "brew",
        "home",
        "supply"
    ],
    "wof:name":"Brewcraft (PN)",
    "wof:placetype":"venue"
},
  "geometry": {"coordinates":[175.60311899999999,-40.351463],"type":"Point"}
}