{
  "type": "Feature",
  "properties": {
    "addr:full":"328 Lytton Rd  Gisborne Gisborne",
    "addr:housenumber":"328",
    "addr:street":"Lytton Rd",
    "iso:country":"NZ",
    "sg:address":"328 Lytton Rd ",
    "sg:city":"Gisborne",
    "sg:classifiers":[
        {
            "category":"Coffee & Tea",
            "type":"Food & Drink"
        }
    ],
    "sg:phone":"+64 6-868 8822",
    "sg:province":"Gisborne",
    "sg:tags":[
        "vegetable",
        "fruit",
        "veges"
    ],
    "wof:name":"Fruit Case Company",
    "wof:placetype":"venue"
},
  "geometry": {"coordinates":[177.99305699999999,-38.666023],"type":"Point"}
}