{
  "type": "Feature",
  "properties": {
    "iso:country":"NZ",
    "sg:address":"265 Kuku Rd East ",
    "sg:city":"Manakau",
    "sg:classifiers":[
        {
            "category":"Recreation",
            "type":"Entertainment"
        }
    ],
    "sg:phone":"+64 6-362 6968",
    "sg:province":"Wellington",
    "sg:tags":[
        "trek",
        "travel",
        "horse",
        "tour",
        "tourism",
        "sightseeing"
    ],
    "wof:name":"Te Angiora",
    "wof:placetype":"venue"
},
  "geometry": {"coordinates":[175.2173,-40.716663],"type":"Point"}
}