{
  "type": "Feature",
  "properties": {
    "addr:full":"30 Euclid Ave Te Rapa  Hamilton Waikato",
    "addr:housenumber":"30",
    "addr:street":"Euclid Ave",
    "iso:country":"NZ",
    "sg:address":"30 Euclid Ave Te Rapa ",
    "sg:city":"Hamilton",
    "sg:classifiers":[
        {
            "category":"Manufacturing",
            "subcategory":"Metals",
            "type":"Manufacturing & Wholesale Goods"
        }
    ],
    "sg:phone":"+64 7-850 4177",
    "sg:province":"Waikato",
    "sg:tags":[
        "-",
        "engineering",
        "industrial",
        "sheet",
        "engineer"
    ],
    "wof:name":"United Sheetmetals Ltd",
    "wof:placetype":"venue"
},
  "geometry": {"coordinates":[175.25108299999999,-37.757858],"type":"Point"}
}