{
  "type": "Feature",
  "properties": {
    "addr:full":"71 Broadway  Matamata Manawatu-Wanganui",
    "addr:housenumber":"71",
    "addr:street":"Broadway",
    "iso:country":"NZ",
    "sg:address":"71 Broadway ",
    "sg:city":"Matamata",
    "sg:classifiers":[
        {
            "category":"Sports & Exercise",
            "subcategory":"Ski Resort",
            "type":"Entertainment"
        }
    ],
    "sg:phone":"+64 7-888 7854",
    "sg:province":"Manawatu-Wanganui",
    "sg:tags":[
        "hobbies",
        "photographic",
        "leisure",
        "developing"
    ],
    "wof:name":"Kodak Express",
    "wof:placetype":"venue"
},
  "geometry": {"coordinates":[175.77778599999999,-37.81144],"type":"Point"}
}