{
  "type": "Feature",
  "properties": {
    "addr:full":"267 Ponsonby Rd Ponsonby  Auckland Auckland",
    "addr:housenumber":"267",
    "addr:street":"Ponsonby Rd",
    "iso:country":"NZ",
    "sg:address":"267 Ponsonby Rd Ponsonby ",
    "sg:city":"Auckland",
    "sg:classifiers":[
        {
            "category":"Deli",
            "type":"Food & Drink"
        }
    ],
    "sg:phone":"+64 9-376 5260",
    "sg:province":"Auckland",
    "sg:tags":[
        "delicatessen",
        "-"
    ],
    "wof:name":"Lord Ponsonbys Delicatessen",
    "wof:placetype":"venue"
},
  "geometry": {"coordinates":[174.74411000000001,-36.849003],"type":"Point"}
}