{
  "type": "Feature",
  "properties": {
    "iso:country":"NZ",
    "sg:address":"16 East St PO Box 72-535 Papakura ",
    "sg:city":"Auckland",
    "sg:orig_category":"Clothing And Fabric: Clothing: Clothing - Specialty",
    "sg:phone":"+64 9-297 7863",
    "sg:province":"Auckland",
    "wof:name":"Chances Surf & Street Wear",
    "wof:placetype":"venue"
},
  "geometry": {"coordinates":[174.959457,-37.059521],"type":"Point"}
}