{
  "type": "Feature",
  "properties": {
    "addr:full":"389 Queen St  Masterton Wellington",
    "addr:housenumber":"389",
    "addr:street":"Queen St",
    "iso:country":"NZ",
    "sg:address":"389 Queen St ",
    "sg:city":"Masterton",
    "sg:classifiers":[
        {
            "category":"Autos & Motor Vehicles",
            "subcategory":"Automobile Sales",
            "type":"Retail Goods"
        }
    ],
    "sg:phone":"+64 6-370 3876",
    "sg:province":"Wellington",
    "sg:tags":[
        "car",
        "-used",
        "leasing",
        "truck",
        "automotive"
    ],
    "wof:name":"Supreme European",
    "wof:placetype":"venue"
},
  "geometry": {"coordinates":[175.65228300000001,-40.955879],"type":"Point"}
}