{
  "type": "Feature",
  "properties": {
    "addr:full":"113 Gemstone Dve Upper  Hutt Wellington",
    "addr:housenumber":"113",
    "addr:street":"Gemstone Dve",
    "iso:country":"NZ",
    "sg:address":"113 Gemstone Dve Upper ",
    "sg:city":"Hutt",
    "sg:classifiers":[
        {
            "category":"Wholesale",
            "subcategory":"Machinery & Supplies",
            "type":"Manufacturing & Wholesale Goods"
        }
    ],
    "sg:phone":"+64 25420882",
    "sg:province":"Wellington",
    "sg:tags":[
        "equipment",
        "crane",
        "industrial",
        "hoist",
        "lifting"
    ],
    "wof:name":"Hammond Crane & Cartage Ltd",
    "wof:placetype":"venue"
},
  "geometry": {"coordinates":[175.069031,-41.12458],"type":"Point"}
}