{
  "type": "Feature",
  "properties": {
    "addr:full":"Whangaparaoa Rd Whangaparaoa Hibiscus  Hibiscus Coast Auckland",
    "addr:street":"Whangaparaoa Rd",
    "iso:country":"NZ",
    "sg:address":"Whangaparaoa Rd Whangaparaoa Hibiscus ",
    "sg:city":"Hibiscus Coast",
    "sg:orig_category":"Health And Beauty: Medical: Hospitals",
    "sg:phone":"+64 9-426 3131",
    "sg:province":"Auckland",
    "wof:name":"NorthHaven Medical Hospital",
    "wof:placetype":"venue"
},
  "geometry": {"coordinates":[174.76622,-36.630104],"type":"Point"}
}