{
  "type": "Feature",
  "properties": {
    "iso:country":"NZ",
    "sg:address":"18 Old Coach Rd ",
    "sg:city":"Havelock",
    "sg:classifiers":[
        {
            "category":"Organizations",
            "subcategory":"Labor Organization",
            "type":"Services"
        }
    ],
    "sg:phone":"+64 3-574 2434",
    "sg:tags":[
        "services",
        "charter",
        "tourism",
        "travel",
        "boat"
    ],
    "wof:name":"Johnson's Barge Service Ltd",
    "wof:placetype":"venue"
},
  "geometry": {"coordinates":[-94.701714,42.834831],"type":"Point"}
}