{
  "type": "Feature",
  "properties": {
    "iso:country":"NZ",
    "sg:address":"25 Koromiko St ",
    "sg:city":"Tauranga",
    "sg:classifiers":[
        {
            "category":"Manufacturing",
            "subcategory":"Furniture",
            "type":"Manufacturing & Wholesale Goods"
        }
    ],
    "sg:phone":"+64 7-577 6138",
    "sg:province":"Bay of Plenty",
    "sg:tags":[
        "furniture/furnishings",
        "home",
        "garden",
        "manufacturer"
    ],
    "sg:website":"http://www.cintesi.co.nz",
    "wof:name":"Cintesi",
    "wof:placetype":"venue"
},
  "geometry": {"coordinates":[176.151001,-37.699417],"type":"Point"}
}