{
  "type": "Feature",
  "properties": {
    "addr:full":"115 a Memorial Dve Riverside  Whangarei Nelson",
    "addr:housenumber":"115 a",
    "addr:street":"Dve",
    "iso:country":"NZ",
    "sg:address":"115 a Memorial Dve Riverside ",
    "sg:city":"Whangarei",
    "sg:classifiers":[
        {
            "category":"Personal",
            "type":"Services"
        }
    ],
    "sg:phone":"+64 9-438 5005",
    "sg:province":"Nelson",
    "sg:tags":[
        "celebrant",
        "arrangements",
        "marriage",
        "wedding"
    ],
    "wof:name":"Cobb-Martin Lynda",
    "wof:placetype":"venue"
},
  "geometry": {"coordinates":[174.32772800000001,-35.721958],"type":"Point"}
}