{
  "type": "Feature",
  "properties": {
    "iso:country":"NZ",
    "sg:address":"4726 Makirikiri Rd ",
    "sg:city":"Marton",
    "sg:classifiers":[
        {
            "category":"Shopping",
            "subcategory":"Pets & Pet Supplies",
            "type":"Retail Goods"
        }
    ],
    "sg:phone":"+64 6-327 7755",
    "sg:tags":[
        "boarding",
        "garden",
        "pets",
        "catteries",
        "home",
        "kennel"
    ],
    "wof:name":"Bark Royal Dog & Cat Lodge, Marton",
    "wof:placetype":"venue"
},
  "geometry": {"coordinates":[175.395172,-40.102409],"type":"Point"}
}