{
  "type": "Feature",
  "properties": {
    "iso:country":"NZ",
    "sg:address":"23 Acorn Clo St Martins ",
    "sg:city":"Christchurch",
    "sg:classifiers":[
        {
            "category":"Transit Center",
            "subcategory":"Freight",
            "type":"Transportation"
        }
    ],
    "sg:phone":"+64 3-337 9919",
    "sg:province":"Canterbury",
    "sg:tags":[
        "distribution",
        "-",
        "transport"
    ],
    "wof:name":"Online Marketing",
    "wof:placetype":"venue"
},
  "geometry": {"coordinates":[172.652374,-43.555965],"type":"Point"}
}