{
  "type": "Feature",
  "properties": {
    "iso:country":"NZ",
    "sg:address":"52 Sandyford St Sydenham ",
    "sg:city":"Christchurch",
    "sg:classifiers":[
        {
            "category":"Professional",
            "subcategory":"Detective & Security Services",
            "type":"Services"
        }
    ],
    "sg:phone":"+64 3-366 2685",
    "sg:province":"Canterbury",
    "sg:tags":[
        "services",
        "automotive",
        "warrant",
        "fitness"
    ],
    "wof:name":"Autocare Service Centre",
    "wof:placetype":"venue"
},
  "geometry": {"coordinates":[172.635651,-43.542744],"type":"Point"}
}