{
  "type": "Feature",
  "properties": {
    "iso:country":"NZ",
    "sg:address":"State Hwy 25 Whangamata ",
    "sg:city":"Coromandel",
    "sg:orig_category":"Sports And Leisure: Sports: Equestrian",
    "sg:phone":"+64 7-864 7078",
    "wof:name":"Pine Treks Horse Trekking",
    "wof:placetype":"venue"
},
  "geometry": {"coordinates":[175.503036,-36.754349],"type":"Point"}
}