{
  "type": "Feature",
  "properties": {
    "iso:country":"NZ",
    "sg:address":"31 Fitzroy St Papatoetoe ",
    "sg:city":"Auckland",
    "sg:orig_category":"Transport: Transportation: Carriers",
    "sg:phone":"+64 9-277 7509",
    "sg:province":"Taranaki",
    "wof:name":"Brownies Cartage Limited",
    "wof:placetype":"venue"
},
  "geometry": {"coordinates":[174.867157,-36.971188],"type":"Point"}
}