{
  "type": "Feature",
  "properties": {
    "addr:full":"31 Fitzroy St Papatoetoe  Auckland Taranaki",
    "addr:housenumber":"31",
    "addr:street":"Fitzroy St",
    "iso:country":"NZ",
    "sg:address":"31 Fitzroy St Papatoetoe ",
    "sg:city":"Auckland",
    "sg:orig_category":"Transport: Transportation: Carriers",
    "sg:phone":"+64 9-277 7509",
    "sg:province":"Taranaki",
    "wof:name":"Brownies Cartage Limited",
    "wof:placetype":"venue"
},
  "geometry": {"coordinates":[174.86715699999999,-36.971188],"type":"Point"}
}