{
  "type": "Feature",
  "properties": {
    "addr:full":"cnr Horgans & McNamaras Rds  Waimate",
    "addr:street":"Cnr Horgans & Mcnamaras Rds",
    "iso:country":"NZ",
    "sg:address":"cnr Horgans & McNamaras Rds ",
    "sg:city":"Waimate",
    "sg:classifiers":[
        {
            "category":"Home & Garden",
            "subcategory":"Garden Supply",
            "type":"Retail Goods"
        }
    ],
    "sg:phone":"+64 3-689 8928",
    "sg:tags":[
        "products",
        "nursery",
        "gardening"
    ],
    "wof:name":"Matai Nurseries",
    "wof:placetype":"venue"
},
  "geometry": {"coordinates":[171.04248000000001,-44.733082],"type":"Point"}
}