{
  "type": "Feature",
  "properties": {
    "iso:country":"NZ",
    "sg:address":"Unit 13 45 Sonter Rd Sockburn ",
    "sg:city":"Christchurch",
    "sg:classifiers":[
        {
            "category":"Manufacturing",
            "subcategory":"Food",
            "type":"Manufacturing & Wholesale Goods"
        }
    ],
    "sg:phone":"+64 3-343 4107",
    "sg:province":"Canterbury",
    "sg:tags":[
        "drink",
        "-",
        "manufacturer"
    ],
    "wof:name":"La Toscana Pasta Limited",
    "wof:placetype":"venue"
},
  "geometry": {"coordinates":[172.55043000000001,-43.534966],"type":"Point"}
}