{
  "type": "Feature",
  "properties": {
    "addr:full":"210 Main Rd Tawa  Wellington Wellington",
    "addr:housenumber":"210",
    "addr:street":"Main Rd",
    "iso:country":"NZ",
    "sg:address":"210 Main Rd Tawa ",
    "sg:city":"Wellington",
    "sg:classifiers":[
        {
            "category":"Health Services",
            "subcategory":"Doctor",
            "type":"Services"
        }
    ],
    "sg:phone":"+64 4-232 7942",
    "sg:province":"Wellington",
    "sg:tags":[
        "services",
        "reflexology",
        "beauty"
    ],
    "wof:name":"Evans Gwyneth",
    "wof:placetype":"venue"
},
  "geometry": {"coordinates":[174.825165,-41.16951],"type":"Point"}
}