{
  "type": "Feature",
  "properties": {
    "addr:full":"318 Thames Hwy  Oamaru Otago",
    "addr:housenumber":"318",
    "addr:street":"Thames Hwy",
    "iso:country":"NZ",
    "sg:address":"318 Thames Hwy ",
    "sg:city":"Oamaru",
    "sg:classifiers":[
        {
            "category":"Social Services",
            "subcategory":"Retirement Home",
            "type":"Services"
        }
    ],
    "sg:phone":"+64 3-437 2180",
    "sg:province":"Otago",
    "sg:tags":[
        "elderly",
        "convalescent",
        "garden",
        "rest",
        "care"
    ],
    "wof:name":"Northanjer Rest Home",
    "wof:placetype":"venue"
},
  "geometry": {"coordinates":[170.97860700000001,-45.084488],"type":"Point"}
}