{
  "type": "Feature",
  "properties": {
    "iso:country":"NZ",
    "sg:address":"cnr Osterley Way & Putney Way Manukau City ",
    "sg:city":"Auckland",
    "sg:classifiers":[
        {
            "category":"Banks & Credit Unions",
            "subcategory":"Investment Brokerage",
            "type":"Services"
        }
    ],
    "sg:phone":"+64 9-262 1954",
    "sg:province":"Auckland",
    "sg:tags":[
        "personal",
        "-",
        "finance"
    ],
    "wof:name":"Public Trust",
    "wof:placetype":"venue"
},
  "geometry": {"coordinates":[174.881439,-36.98967],"type":"Point"}
}