{
  "type": "Feature",
  "properties": {
    "addr:full":"PO Box 89 Papakura  Auckland Auckland",
    "addr:housenumber":"po box 89",
    "iso:country":"NZ",
    "sg:address":"PO Box 89 Papakura ",
    "sg:city":"Auckland",
    "sg:classifiers":[
        {
            "category":"Recreation",
            "type":"Entertainment"
        }
    ],
    "sg:phone":"+64 9-294 8705",
    "sg:province":"Auckland",
    "sg:tags":[
        "sport",
        "leisure"
    ],
    "sg:website":"http://www.yellowpages.co.nz/pages/201400635/dp34845.html",
    "wof:name":"Boulder Park Amusements",
    "wof:placetype":"venue"
},
  "geometry": {"coordinates":[174.95945699999999,-37.059521],"type":"Point"}
}