{
  "type": "Feature",
  "properties": {
    "iso:country":"NZ",
    "sg:address":"Christchurch Canterbury ",
    "sg:city":"Christchurch",
    "sg:classifiers":[
        {
            "category":"Organizations",
            "subcategory":"Labor Organization",
            "type":"Services"
        }
    ],
    "sg:phone":"+64 800 808 767",
    "sg:province":"Canterbury",
    "sg:tags":[
        "travel",
        "tourism"
    ],
    "sg:website":"http://www.qantas.com.au",
    "wof:name":"Qantas Airways Ltd",
    "wof:placetype":"venue"
},
  "geometry": {"coordinates":[172.636642,-43.532585],"type":"Point"}
}