{
  "type": "Feature",
  "properties": {
    "addr:full":"St Andrews R D 4  Blenheim Marlborough",
    "addr:housenumber":"4",
    "addr:street":"R D;Blenheim",
    "iso:country":"NZ",
    "sg:address":"St Andrews R D 4 ",
    "sg:city":"Blenheim",
    "sg:orig_category":"Travel And Tourism: Accommodation: Backpackers",
    "sg:phone":"+64 3-578 8193",
    "sg:province":"Marlborough",
    "wof:name":"Crispin T P",
    "wof:placetype":"venue"
},
  "geometry": {"coordinates":[173.957291,-41.513084],"type":"Point"}
}