{
  "type": "Feature",
  "properties": {
    "iso:country":"NZ",
    "sg:address":"Waimate R D 10 ",
    "sg:city":"Morven",
    "sg:orig_category":"Education And Training: General: Schools",
    "sg:phone":"+64 3-689 4717",
    "wof:name":"Morven School",
    "wof:placetype":"venue"
},
  "geometry": {"coordinates":[171.04248,-44.733082],"type":"Point"}
}