{
  "type": "Feature",
  "properties": {
    "iso:country":"NZ",
    "sg:address":"84 Tongariro St ",
    "sg:city":"Taupo",
    "sg:orig_category":"Shopping: Accessories: Lingerie - Retail",
    "sg:phone":"+64 7-378 8941",
    "sg:province":"Waikato",
    "wof:name":"Sheer Magic Lingerie",
    "wof:placetype":"venue"
},
  "geometry": {"coordinates":[176.069748,-38.68071],"type":"Point"}
}