{
  "type": "Feature",
  "properties": {
    "addr:full":"1 Lunns Rd  Christchurch Canterbury",
    "addr:housenumber":"1",
    "addr:street":"Lunns Rd",
    "iso:country":"NZ",
    "sg:address":"1 Lunns Rd ",
    "sg:city":"Christchurch",
    "sg:classifiers":[
        {
            "category":"Professional",
            "subcategory":"Engineering",
            "type":"Services"
        }
    ],
    "sg:phone":"+64 3-348 0859",
    "sg:province":"Canterbury",
    "sg:tags":[
        "industrial"
    ],
    "sg:website":"http://www.yellowpages.co.nz/for/ab/dp59883.html",
    "wof:name":"AB Equipment Ltd",
    "wof:placetype":"venue"
},
  "geometry": {"coordinates":[-76.537834,37.605659],"type":"Point"}
}