{
  "type": "Feature",
  "properties": {
    "iso:country":"NZ",
    "sg:address":"99 Ridgway St ",
    "sg:city":"Wanganui",
    "sg:orig_category":"Farming: Machinery: Milking Machinery",
    "sg:phone":"+64 6-348 9239",
    "sg:province":"Manawatu-Wanganui",
    "wof:name":"Machinery Maintenance - Pump House",
    "wof:placetype":"venue"
},
  "geometry": {"coordinates":[175.051819,-39.936256],"type":"Point"}
}