{
  "type": "Feature",
  "properties": {
    "addr:full":"Lomond Ave  Tokoroa",
    "addr:street":"Lomond Ave",
    "iso:country":"NZ",
    "sg:address":"Lomond Ave ",
    "sg:city":"Tokoroa",
    "sg:classifiers":[
        {
            "category":"Food & Beverages",
            "subcategory":"Bakery",
            "type":"Retail Goods"
        }
    ],
    "sg:phone":"+64 7-886 8715",
    "sg:tags":[
        "shop",
        "cake",
        "drink",
        "-"
    ],
    "wof:name":"Lomond Home Cookery 1994",
    "wof:placetype":"venue"
},
  "geometry": {"coordinates":[175.86317399999999,-38.232662],"type":"Point"}
}