{
  "type": "Feature",
  "properties": {
    "iso:country":"NZ",
    "sg:address":"309 Rangitikei St Palmerston ",
    "sg:city":"Palmerston North",
    "sg:classifiers":[
        {
            "category":"Home & Garden",
            "subcategory":"Building Materials",
            "type":"Retail Goods"
        }
    ],
    "sg:phone":"+64 6-354 2150",
    "sg:province":"Manawatu-Wanganui",
    "sg:tags":[
        "design",
        "fitting",
        "fittings",
        "kitchen"
    ],
    "wof:name":"Plumbing World",
    "wof:placetype":"venue"
},
  "geometry": {"coordinates":[175.594666,-40.337257],"type":"Point"}
}