{
  "type": "Feature",
  "properties": {
    "addr:full":"419 Herbert St  Invercargill Southland",
    "addr:housenumber":"419",
    "addr:street":"Herbert St",
    "iso:country":"NZ",
    "sg:address":"419 Herbert St ",
    "sg:city":"Invercargill",
    "sg:classifiers":[
        {
            "category":"Health Services",
            "subcategory":"Health Practitioner",
            "type":"Services"
        }
    ],
    "sg:phone":"+64 800 121 268",
    "sg:province":"Southland",
    "sg:tags":[
        "services",
        "beauty",
        "acupuncturists"
    ],
    "wof:name":"Mei's Traditional Chinese Medical Centre",
    "wof:placetype":"venue"
},
  "geometry": {"coordinates":[168.37617499999999,-46.394901],"type":"Point"}
}