{
  "type": "Feature",
  "properties": {
    "addr:full":"PO Box 4477 Kamo  Whangarei Northland",
    "addr:housenumber":"po;kamo",
    "addr:street":"Box 4477",
    "iso:country":"NZ",
    "sg:address":"PO Box 4477 Kamo ",
    "sg:city":"Whangarei",
    "sg:classifiers":[
        {
            "category":"Utilities",
            "subcategory":"Refuse",
            "type":"Services"
        }
    ],
    "sg:phone":"+64 9-435 2259",
    "sg:province":"Northland",
    "sg:tags":[
        "bin",
        "hire",
        "garden",
        "cleaning",
        "rubbish",
        "home"
    ],
    "wof:name":"Kiwi Bins",
    "wof:placetype":"venue"
},
  "geometry": {"coordinates":[174.30720500000001,-35.680759],"type":"Point"}
}