{
  "type": "Feature",
  "properties": {
    "addr:full":"130 St Georges Rd Avondale  Auckland Auckland",
    "addr:housenumber":"130",
    "addr:street":"St Georges Rd",
    "iso:country":"NZ",
    "sg:address":"130 St Georges Rd Avondale ",
    "sg:city":"Auckland",
    "sg:classifiers":[
        {
            "category":"Home & Garden",
            "subcategory":"Furniture",
            "type":"Retail Goods"
        }
    ],
    "sg:phone":"+64 9-828 6852",
    "sg:province":"Auckland",
    "sg:tags":[
        "fitting"
    ],
    "sg:website":"http://www.yellowpages.co.nz/for/cooper/dp34844.html",
    "wof:name":"Cooper H J (1993) Ltd",
    "wof:placetype":"venue"
},
  "geometry": {"coordinates":[174.696564,-36.906116],"type":"Point"}
}