{
  "type": "Feature",
  "properties": {
    "iso:country":"NZ",
    "sg:address":"121 Riccarton Rd Riccarton ",
    "sg:city":"Christchurch",
    "sg:classifiers":[
        {
            "category":"Social Services",
            "subcategory":"Child Care",
            "type":"Services"
        }
    ],
    "sg:phone":"+64 3-348 5068",
    "sg:province":"Canterbury",
    "sg:tags":[
        "baby",
        "home",
        "product",
        "garden",
        "children"
    ],
    "wof:name":"Baby Factory",
    "wof:placetype":"venue"
},
  "geometry": {"coordinates":[172.59863300000001,-43.529903],"type":"Point"}
}