{
  "type": "Feature",
  "properties": {
    "addr:full":"Remuera  Auckland Auckland",
    "iso:country":"NZ",
    "sg:address":"Remuera ",
    "sg:city":"Auckland",
    "sg:classifiers":[
        {
            "category":"Home & Garden",
            "subcategory":"Building Materials",
            "type":"Retail Goods"
        }
    ],
    "sg:phone":"+64 9-522 1536",
    "sg:province":"Auckland",
    "sg:tags":[
        "fittings",
        "door",
        "garage"
    ],
    "wof:name":"About Doors Repairs",
    "wof:placetype":"venue"
},
  "geometry": {"coordinates":[174.804947,-36.869678],"type":"Point"}
}