{
  "type": "Feature",
  "properties": {
    "addr:full":"14 Edgar St Frankton  Hamilton Waikato",
    "addr:housenumber":"14",
    "addr:street":"Edgar St",
    "iso:country":"NZ",
    "sg:address":"14 Edgar St Frankton ",
    "sg:city":"Hamilton",
    "sg:classifiers":[
        {
            "category":"Utilities",
            "subcategory":"Refuse",
            "type":"Services"
        }
    ],
    "sg:phone":"+64 7-847 8316",
    "sg:province":"Waikato",
    "sg:tags":[
        "bin",
        "hire",
        "garden",
        "cleaning",
        "rubbish",
        "home"
    ],
    "wof:name":"Waste Management NZ Ltd",
    "wof:placetype":"venue"
},
  "geometry": {"coordinates":[175.26365699999999,-37.786728],"type":"Point"}
}