{
  "type": "Feature",
  "properties": {
    "addr:full":"Kerikeri Rd  Kerikeri Northland",
    "addr:street":"Kerikeri Rd",
    "iso:country":"NZ",
    "sg:address":"Kerikeri Rd ",
    "sg:city":"Kerikeri",
    "sg:orig_category":"Clothing And Fabric: Clothing: Women'S Fashions",
    "sg:phone":"+64 9-407 7541",
    "sg:province":"Northland",
    "wof:name":"Pre-Loved Clothing",
    "wof:placetype":"venue"
},
  "geometry": {"coordinates":[173.943848,-35.233288],"type":"Point"}
}