{
  "type": "Feature",
  "properties": {
    "addr:full":"2/26 Orchard Rd Browns Bay  Auckland Auckland",
    "addr:housenumber":"2 / 26",
    "addr:street":"Orchard Rd",
    "iso:country":"NZ",
    "sg:address":"2/26 Orchard Rd Browns Bay ",
    "sg:city":"Auckland",
    "sg:classifiers":[
        {
            "category":"Retail",
            "subcategory":"Driving School",
            "type":"Services"
        }
    ],
    "sg:phone":"+64 9-478 7054",
    "sg:province":"Auckland",
    "sg:tags":[
        "training",
        "education",
        "driver"
    ],
    "wof:name":"Russell Walton",
    "wof:placetype":"venue"
},
  "geometry": {"coordinates":[174.74432400000001,-36.714409],"type":"Point"}
}