{
  "type": "Feature",
  "properties": {
    "addr:full":"49 Vaughan Rd  Rotorua Bay of Plenty",
    "addr:housenumber":"49",
    "addr:street":"Vaughan Rd",
    "iso:country":"NZ",
    "sg:address":"49 Vaughan Rd ",
    "sg:city":"Rotorua",
    "sg:orig_category":"Industrial: Abrasives: Abrasive Blasting",
    "sg:phone":"+64 7-345 6986",
    "sg:province":"Bay of Plenty",
    "wof:name":"Rotorua Bead Blasting",
    "wof:placetype":"venue"
},
  "geometry": {"coordinates":[176.27735899999999,-38.143887],"type":"Point"}
}