{
  "type": "Feature",
  "properties": {
    "addr:full":"111 Hutt Park Rd Seaview Lower  Hutt Wellington",
    "addr:housenumber":"111",
    "addr:street":"Hutt Park Rd",
    "iso:country":"NZ",
    "sg:address":"111 Hutt Park Rd Seaview Lower ",
    "sg:city":"Hutt",
    "sg:orig_category":"Industrial: Packaging: Boxes And Cases",
    "sg:phone":"+64 4-568 6898",
    "sg:province":"Wellington",
    "wof:name":"Haines Pallet Co",
    "wof:placetype":"venue"
},
  "geometry": {"coordinates":[174.89956699999999,-41.246059],"type":"Point"}
}