{
  "type": "Feature",
  "properties": {
    "addr:full":"1115 Haupapa St  Rotorua Bay of Plenty",
    "addr:housenumber":"1115",
    "addr:street":"Haupapa St",
    "iso:country":"NZ",
    "sg:address":"1115 Haupapa St ",
    "sg:city":"Rotorua",
    "sg:orig_category":"Industrial: Electrical/Electronic: Radio Engineers",
    "sg:phone":"+64 7-346 0370",
    "sg:province":"Bay of Plenty",
    "wof:name":"Radio Spectrum Management",
    "wof:placetype":"venue"
},
  "geometry": {"coordinates":[176.25323499999999,-38.135708],"type":"Point"}
}