{
  "type": "Feature",
  "properties": {
    "iso:country":"NZ",
    "sg:address":"Centre Point Mall cnr High & Market Sts ",
    "sg:city":"Blenheim",
    "sg:orig_category":"Food And Drink: Catering: Caterers",
    "sg:phone":"+64 3-578 0694",
    "sg:province":"Marlborough",
    "wof:name":"Centre Point Cafe & Catering",
    "wof:placetype":"venue"
},
  "geometry": {"coordinates":[-79.654518,34.510391],"type":"Point"}
}