{
  "type": "Feature",
  "properties": {
    "addr:full":"Marlborough  Blenheim Marlborough",
    "iso:country":"NZ",
    "sg:address":"Marlborough ",
    "sg:city":"Blenheim",
    "sg:classifiers":[
        {
            "category":"Wholesale",
            "subcategory":"Auto Parts",
            "type":"Manufacturing & Wholesale Goods"
        }
    ],
    "sg:phone":"+64 800 489 737",
    "sg:province":"Marlborough",
    "sg:tags":[
        "automotive",
        "supply"
    ],
    "sg:website":"http://www.beaurepaires.co.nz",
    "wof:name":"Beaurepaires for Tyres",
    "wof:placetype":"venue"
},
  "geometry": {"coordinates":[173.95727500000001,-41.513081],"type":"Point"}
}