{
  "type": "Feature",
  "properties": {
    "iso:country":"NZ",
    "sg:address":"38 Blaydon St ",
    "sg:city":"Waikaia",
    "sg:classifiers":[
        {
            "category":"Travel",
            "subcategory":"Hotels & Motels",
            "type":"Entertainment"
        }
    ],
    "sg:phone":"+64 3-202 7821",
    "sg:tags":[
        "tavern",
        "tourism",
        "accommodation"
    ],
    "wof:name":"Waikaia Commercial Hotel",
    "wof:placetype":"venue"
},
  "geometry": {"coordinates":[168.84892300000001,-45.724712],"type":"Point"}
}