{
  "type": "Feature",
  "properties": {
    "addr:full":"51 Windsor St  Invercargill Southland",
    "addr:housenumber":"51",
    "addr:street":"Windsor St",
    "iso:country":"NZ",
    "sg:address":"51 Windsor St ",
    "sg:city":"Invercargill",
    "sg:orig_category":"Shopping: Retail Stores: Supermarkets",
    "sg:phone":"+64 3-217 7175",
    "sg:province":"Southland",
    "wof:name":"Windsor New World",
    "wof:placetype":"venue"
},
  "geometry": {"coordinates":[168.36570699999999,-46.395794],"type":"Point"}
}