{
  "type": "Feature",
  "properties": {
    "addr:full":"Christchurch  Airport",
    "iso:country":"NZ",
    "sg:address":"Christchurch ",
    "sg:city":"Airport",
    "sg:orig_category":"Automotive: General Services: Car Storage",
    "sg:phone":"+64 800 727 548",
    "wof:name":"Craddocks Airport Car Storage",
    "wof:placetype":"venue"
},
  "geometry": {"coordinates":[172.53401199999999,-43.485931],"type":"Point"}
}