{
  "type": "Feature",
  "properties": {
    "addr:full":"125 Queen St  Auckland Auckland",
    "addr:housenumber":"125",
    "addr:street":"Queen St",
    "iso:country":"NZ",
    "sg:address":"125 Queen St ",
    "sg:city":"Auckland",
    "sg:classifiers":[
        {
            "category":"Travel",
            "subcategory":"Travel Agent",
            "type":"Entertainment"
        }
    ],
    "sg:phone":"+64 9-359 9907",
    "sg:province":"Auckland",
    "sg:tags":[
        "good",
        "tourism"
    ],
    "sg:website":"http://www.snowgum.com.au",
    "wof:name":"Snowgum",
    "wof:placetype":"venue"
},
  "geometry": {"coordinates":[174.76594499999999,-36.846504],"type":"Point"}
}