{
  "type": "Feature",
  "properties": {
    "iso:country":"NZ",
    "sg:address":"AMP Centre Hastings St ",
    "sg:city":"Napier",
    "sg:classifiers":[
        {
            "category":"Health Services",
            "subcategory":"Doctor",
            "type":"Services"
        }
    ],
    "sg:phone":"+64 6-835 3320",
    "sg:province":"Hawke's Bay",
    "sg:tags":[
        "specialists",
        "surgery",
        "cosmetic",
        "beauty"
    ],
    "wof:name":"CACI Clinic",
    "wof:placetype":"venue"
},
  "geometry": {"coordinates":[151.210266,-33.86451],"type":"Point"}
}