{
  "type": "Feature",
  "properties": {
    "addr:full":"35 Nukuhau Rd  Taupo Waikato",
    "addr:housenumber":"35",
    "addr:street":"Nukuhau Rd",
    "iso:country":"NZ",
    "sg:address":"35 Nukuhau Rd ",
    "sg:city":"Taupo",
    "sg:orig_category":"Transport: Boats And Marine: Boats: Boat Dealers",
    "sg:phone":"+64 7-377 2298",
    "sg:province":"Waikato",
    "wof:name":"Taupo Marine",
    "wof:placetype":"venue"
},
  "geometry": {"coordinates":[176.071335,-38.68259],"type":"Point"}
}