{
  "type": "Feature",
  "properties": {
    "iso:country":"NZ",
    "sg:address":"15a Bruce Mclaren Rd Henderson ",
    "sg:city":"Auckland",
    "sg:orig_category":"Automotive: Accessories: Motor Accessories",
    "sg:phone":"+64 9-837 0980",
    "sg:province":"Auckland",
    "wof:name":"TSU 4WD Services Ltd",
    "wof:placetype":"venue"
},
  "geometry": {"coordinates":[174.630295,-36.891895],"type":"Point"}
}