{
  "type": "Feature",
  "properties": {
    "iso:country":"NZ",
    "sg:address":"86 Seddon St ",
    "sg:city":"Raetihi",
    "sg:classifiers":[
        {
            "category":"Home & Garden",
            "subcategory":"Building Materials",
            "type":"Retail Goods"
        }
    ],
    "sg:phone":"+64 6-385 4376",
    "sg:tags":[
        "builder",
        "related"
    ],
    "wof:name":"Black Neil",
    "wof:placetype":"venue"
},
  "geometry": {"coordinates":[175.282181,-39.427719],"type":"Point"}
}