{
  "type": "Feature",
  "properties": {
    "iso:country":"NZ",
    "sg:address":"88 Bryant St Palmerston ",
    "sg:city":"Palmerston North",
    "sg:classifiers":[
        {
            "category":"Retail",
            "subcategory":"Auto Repair",
            "type":"Services"
        }
    ],
    "sg:phone":"+64 6-354 7263",
    "sg:province":"Manawatu-Wanganui",
    "sg:tags":[
        "automotive",
        "restoration",
        "servicing",
        "car"
    ],
    "wof:name":"CPS Services",
    "wof:placetype":"venue"
},
  "geometry": {"coordinates":[175.599884,-40.360828],"type":"Point"}
}