{
  "type": "Feature",
  "properties": {
    "addr:full":"265 A Grey St  Gisborne Gisborne",
    "addr:housenumber":"265 a",
    "addr:street":"Grey St",
    "iso:country":"NZ",
    "sg:address":"265 A Grey St ",
    "sg:city":"Gisborne",
    "sg:orig_category":"Industrial: Metal: Scrap Metal Dealers",
    "sg:phone":"+64 6-867 7393",
    "sg:province":"Gisborne",
    "wof:name":"Gisborne Bottle & Scrap Metal Recyclers",
    "wof:placetype":"venue"
},
  "geometry": {"coordinates":[178.01899700000001,-38.668682],"type":"Point"}
}