{
  "type": "Feature",
  "properties": {
    "addr:full":"7 Trotter Ave Waiomu Te  Puru",
    "addr:housenumber":"7",
    "addr:street":"Trotter Ave Waiomu",
    "iso:country":"NZ",
    "sg:address":"7 Trotter Ave Waiomu Te ",
    "sg:city":"Puru",
    "sg:classifiers":[
        {
            "category":"Personal",
            "subcategory":"Piercing",
            "type":"Services"
        }
    ],
    "sg:phone":"+64 7-868 2918",
    "sg:tags":[
        "body",
        "ear",
        "health",
        "nose",
        "beauty"
    ],
    "wof:name":"The Crystal Ball Clinic",
    "wof:placetype":"venue"
},
  "geometry": {"coordinates":[175.51994300000001,-37.04686],"type":"Point"}
}