{
  "type": "Feature",
  "properties": {
    "iso:country":"NZ",
    "sg:address":"5 Lincoln St Ponsonby ",
    "sg:city":"Auckland",
    "sg:orig_category":"Industrial: Products: Rags - Cleaning",
    "sg:phone":"+64 9-376 1111",
    "sg:province":"Auckland",
    "wof:name":"Baker Rag Service",
    "wof:placetype":"venue"
},
  "geometry": {"coordinates":[174.745407,-36.854149],"type":"Point"}
}