{
  "type": "Feature",
  "properties": {
    "iso:country":"NZ",
    "sg:address":"253 Jackson St Petone ",
    "sg:city":"Wellington",
    "sg:orig_category":"Health And Beauty: Specialists: Physiotherapists",
    "sg:phone":"+64 4-939 4331",
    "sg:province":"Wellington",
    "wof:name":"Petone Physiotherapy Centre",
    "wof:placetype":"venue"
},
  "geometry": {"coordinates":[174.88163800000001,-41.226131],"type":"Point"}
}