{
  "type": "Feature",
  "properties": {
    "iso:country":"NZ",
    "sg:address":"32 Hatrick St ",
    "sg:city":"Wanganui",
    "sg:classifiers":[
        {
            "category":"Retail",
            "subcategory":"Auto Repair",
            "type":"Services"
        }
    ],
    "sg:phone":"+64 6-348 3535",
    "sg:province":"Manawatu-Wanganui",
    "sg:tags":[
        "transmission",
        "automotive",
        "servicing"
    ],
    "sg:website":"http://www.yellowpages.co.nz/for/chriscarrick/dp43503.html",
    "wof:name":"Chris Carrick Reconditioners",
    "wof:placetype":"venue"
},
  "geometry": {"coordinates":[175.04406700000001,-39.935837],"type":"Point"}
}