{
  "type": "Feature",
  "properties": {
    "addr:full":"25 Liardet St New  Plymouth Taranaki",
    "addr:housenumber":"25",
    "addr:street":"Liardet St",
    "iso:country":"NZ",
    "sg:address":"25 Liardet St New ",
    "sg:city":"Plymouth",
    "sg:classifiers":[
        {
            "category":"Bus Charters",
            "type":"Transportation"
        }
    ],
    "sg:phone":"+64 6-758 3338",
    "sg:province":"Taranaki",
    "sg:tags":[
        "services",
        "travel",
        "tourism"
    ],
    "wof:name":"White Star (City to City) Passenger & Freight Services Ltd",
    "wof:placetype":"venue"
},
  "geometry": {"coordinates":[174.07609600000001,-39.056934],"type":"Point"}
}