{
  "type": "Feature",
  "properties": {
    "iso:country":"NZ",
    "sg:address":"174 Lincoln Rd Henderson ",
    "sg:city":"Auckland",
    "sg:orig_category":"Health And Beauty: Specialists: Chiropractors",
    "sg:phone":"+64 9-836 0505",
    "sg:province":"Auckland",
    "wof:name":"Henderson Chiropractic Clinic",
    "wof:placetype":"venue"
},
  "geometry": {"coordinates":[174.62823499999999,-36.870419],"type":"Point"}
}