{
  "type": "Feature",
  "properties": {
    "iso:country":"NZ",
    "sg:address":"Victoria St ",
    "sg:city":"Hamilton",
    "sg:classifiers":[
        {
            "category":"Personal",
            "subcategory":"Shoe Repair & Shine",
            "type":"Services"
        }
    ],
    "sg:phone":"+64 7-839 3807",
    "sg:province":"Waikato",
    "sg:tags":[
        "foot",
        "clothing",
        "fabric",
        "wear"
    ],
    "wof:name":"Mister Minit New Zealand Ltd",
    "wof:placetype":"venue"
},
  "geometry": {"coordinates":[142.02546699999999,-37.734207],"type":"Point"}
}