{
  "type": "Feature",
  "properties": {
    "addr:full":"37 Peka Peka Rd  Waikanae",
    "addr:housenumber":"37",
    "addr:street":"Peka Peka Rd",
    "iso:country":"NZ",
    "sg:address":"37 Peka Peka Rd ",
    "sg:city":"Waikanae",
    "sg:classifiers":[
        {
            "category":"Home & Garden",
            "subcategory":"Garden Supply",
            "type":"Retail Goods"
        }
    ],
    "sg:phone":"+64 4-293 1394",
    "sg:tags":[
        "pet",
        "food",
        "pets"
    ],
    "wof:name":"Oliver Robert & Pat",
    "wof:placetype":"venue"
},
  "geometry": {"coordinates":[175.06102000000001,-40.873184],"type":"Point"}
}