{
  "type": "Feature",
  "properties": {
    "addr:full":"43 Bridge St  Tokoroa",
    "addr:housenumber":"43",
    "addr:street":"Bridge St",
    "iso:country":"NZ",
    "sg:address":"43 Bridge St ",
    "sg:city":"Tokoroa",
    "sg:orig_category":"Health And Beauty: Products: Pharmacies",
    "sg:phone":"+64 7-886 8260",
    "wof:name":"Spectrum Amcal Chemist & Photo Centre",
    "wof:placetype":"venue"
},
  "geometry": {"coordinates":[175.87051399999999,-38.218361],"type":"Point"}
}