{
  "type": "Feature",
  "properties": {
    "iso:country":"NZ",
    "sg:address":"284 Pakuranga Hwy Pakuranga ",
    "sg:city":"Auckland",
    "sg:orig_category":"Transport: Transportation: Furniture Removal/Packers",
    "sg:phone":"+64 9-272 2902",
    "sg:province":"Auckland",
    "wof:name":"AAAAA Cut Price Furniture Removals",
    "wof:placetype":"venue"
},
  "geometry": {"coordinates":[174.893143,-36.904205],"type":"Point"}
}