{
  "type": "Feature",
  "properties": {
    "iso:country":"NZ",
    "sg:address":"11 Puriri St ",
    "sg:city":"Inglewood",
    "sg:orig_category":"Automotive: Sales And Leasing: Cars - Kitset",
    "sg:phone":"+64 6-756 7664",
    "wof:name":"SIDCO Manufacturing",
    "wof:placetype":"venue"
},
  "geometry": {"coordinates":[-118.356224,33.961781],"type":"Point"}
}