{
  "type": "Feature",
  "properties": {
    "addr:full":"37 Cairnfield Rd  Whangarei Northland",
    "addr:housenumber":"37",
    "addr:street":"Cairnfield Rd",
    "iso:country":"NZ",
    "sg:address":"37 Cairnfield Rd ",
    "sg:city":"Whangarei",
    "sg:classifiers":[
        {
            "category":"Sports & Exercise",
            "subcategory":"Sports Center",
            "type":"Entertainment"
        }
    ],
    "sg:phone":"+64 9-437 1877",
    "sg:province":"Northland",
    "sg:tags":[
        "health",
        "beauty",
        "fitness"
    ],
    "wof:name":"Fit 2 Go Ltd",
    "wof:placetype":"venue"
},
  "geometry": {"coordinates":[174.32347100000001,-35.701832],"type":"Point"}
}