{
  "type": "Feature",
  "properties": {
    "iso:country":"NZ",
    "sg:address":"502 Hutt Rd Lower ",
    "sg:city":"Hutt",
    "sg:classifiers":[
        {
            "category":"Autos & Motor Vehicles",
            "subcategory":"Motorcycle Sales",
            "type":"Retail Goods"
        }
    ],
    "sg:phone":"+64 4-589 5106",
    "sg:province":"Wellington",
    "sg:tags":[
        "automotive",
        "scooter",
        "leasing"
    ],
    "sg:website":"http://www.motomart.co.nz",
    "wof:name":"Motomart Limited",
    "wof:placetype":"venue"
},
  "geometry": {"coordinates":[174.904526,-41.208431],"type":"Point"}
}