{
  "type": "Feature",
  "properties": {
    "addr:full":"247-251 Dyers Rd Bromley  Christchurch Canterbury",
    "addr:postcode":"247-251",
    "addr:street":"Dyers Rd;Christchurch",
    "iso:country":"NZ",
    "sg:address":"247-251 Dyers Rd Bromley ",
    "sg:city":"Christchurch",
    "sg:orig_category":"Transport: Boats And Marine: Boats: Boat Dealers",
    "sg:phone":"+64 3-384 2726",
    "sg:province":"Canterbury",
    "wof:name":"Mr Boats",
    "wof:placetype":"venue"
},
  "geometry": {"coordinates":[172.703003,-43.538826],"type":"Point"}
}