{
  "type": "Feature",
  "properties": {
    "iso:country":"NZ",
    "sg:address":"PO Box 147-276 ",
    "sg:city":"Ponsonby",
    "sg:classifiers":[
        {
            "category":"Winery",
            "type":"Food & Drink"
        }
    ],
    "sg:phone":"+64 508 722 733",
    "sg:province":"Auckland",
    "sg:tags":[
        "wining",
        "vineyard",
        "dining"
    ],
    "wof:name":"Sacred Hill Wines Ltd",
    "wof:placetype":"venue"
},
  "geometry": {"coordinates":[174.74241599999999,-36.85326],"type":"Point"}
}