{
  "type": "Feature",
  "properties": {
    "iso:country":"NZ",
    "sg:address":"Solander St ",
    "sg:city":"Gisborne",
    "sg:orig_category":"Transport: Transportation: Transport Operators",
    "sg:phone":"+64 6-868 5340",
    "sg:province":"Gisborne",
    "wof:name":"Farmers Transport Limited",
    "wof:placetype":"venue"
},
  "geometry": {"coordinates":[178.00116,-38.667488],"type":"Point"}
}