{
  "type": "Feature",
  "properties": {
    "iso:country":"NZ",
    "sg:address":"392 a Riccarton Rd Upper Riccarton ",
    "sg:city":"Christchurch",
    "sg:orig_category":"Shopping: Retail Stores: Books: Books - Secondhand",
    "sg:phone":"+64 3-348 8748",
    "sg:province":"Canterbury",
    "wof:name":"Church Corner Book Exchange",
    "wof:placetype":"venue"
},
  "geometry": {"coordinates":[172.572495,-43.531765],"type":"Point"}
}