{
  "type": "Feature",
  "properties": {
    "addr:full":"10 B Lambie Dve  Manukau",
    "addr:housenumber":"10",
    "addr:street":"B Lambie Dve",
    "iso:country":"NZ",
    "sg:address":"10 B Lambie Dve ",
    "sg:city":"Manukau",
    "sg:classifiers":[
        {
            "category":"Wholesale",
            "subcategory":"Hardware",
            "type":"Manufacturing & Wholesale Goods"
        }
    ],
    "sg:phone":"+64 800 478 445",
    "sg:tags":[
        "gardening",
        "garden",
        "chainsaw",
        "products",
        "brush",
        "home",
        "cutter"
    ],
    "wof:name":"Stihl Limited",
    "wof:placetype":"venue"
},
  "geometry": {"coordinates":[173.203003,-35.221741],"type":"Point"}
}