{
  "type": "Feature",
  "properties": {
    "iso:country":"NZ",
    "sg:address":"14 Halwyn Dve Hornby ",
    "sg:city":"Christchurch",
    "sg:orig_category":"Transport: Transportation: Freight",
    "sg:phone":"+64 3-349 3173",
    "sg:province":"Canterbury",
    "wof:name":"Accord International Freight Ltd",
    "wof:placetype":"venue"
},
  "geometry": {"coordinates":[172.534042,-43.533882],"type":"Point"}
}