{
  "type": "Feature",
  "properties": {
    "iso:country":"NZ",
    "sg:address":"88 b Riccarton Rd Riccarton ",
    "sg:city":"Christchurch",
    "sg:classifiers":[
        {
            "category":"Personal",
            "subcategory":"Shoe Repair & Shine",
            "type":"Services"
        }
    ],
    "sg:phone":"+64 3-343 1367",
    "sg:province":"Canterbury",
    "sg:tags":[
        "foot",
        "clothing",
        "fabric",
        "wear"
    ],
    "wof:name":"Happy Feet",
    "wof:placetype":"venue"
},
  "geometry": {"coordinates":[172.602325,-43.529446],"type":"Point"}
}