{
  "type": "Feature",
  "properties": {
    "iso:country":"NZ",
    "sg:address":"49 Willis St ",
    "sg:city":"Wellington",
    "sg:classifiers":[
        {
            "category":"Shopping",
            "subcategory":"Crafts & Fabrics",
            "type":"Retail Goods"
        }
    ],
    "sg:phone":"+64 4-472 7228",
    "sg:province":"Wellington",
    "sg:tags":[
        "leather",
        "clothing",
        "suede"
    ],
    "wof:name":"Kingston Leathergoods",
    "wof:placetype":"venue"
},
  "geometry": {"coordinates":[174.77578700000001,-41.287624],"type":"Point"}
}