{
  "type": "Feature",
  "properties": {
    "addr:full":"Shopping Centre High St Renwick  Blenheim Marlborough",
    "addr:street":"Shopping;High St",
    "iso:country":"NZ",
    "sg:address":"Shopping Centre High St Renwick ",
    "sg:city":"Blenheim",
    "sg:classifiers":[
        {
            "category":"Shopping",
            "subcategory":"Crafts & Fabrics",
            "type":"Retail Goods"
        }
    ],
    "sg:phone":"+64 3-572 9615",
    "sg:province":"Marlborough",
    "sg:tags":[
        "clothing"
    ],
    "wof:name":"Renwick Nic Nacs",
    "wof:placetype":"venue"
},
  "geometry": {"coordinates":[173.828461,-41.510769],"type":"Point"}
}