{
  "type": "Feature",
  "properties": {
    "iso:country":"NZ",
    "sg:address":"RD 1 Papakura ",
    "sg:city":"Auckland",
    "sg:classifiers":[
        {
            "category":"Building & Trades",
            "subcategory":"Landscaping Services",
            "type":"Services"
        }
    ],
    "sg:phone":"+64 9-292 7751",
    "sg:province":"Auckland",
    "sg:tags":[
        "personal",
        "home",
        "garden"
    ],
    "sg:website":"http://www.thepicturemaker.net",
    "wof:name":"Keith Birch Photographer",
    "wof:placetype":"venue"
},
  "geometry": {"coordinates":[174.770416,-36.884109],"type":"Point"}
}