{
  "type": "Feature",
  "properties": {
    "iso:country":"NZ",
    "sg:address":"51 Nayland St Sumner ",
    "sg:city":"Christchurch",
    "sg:classifiers":[
        {
            "category":"Manufacturing",
            "subcategory":"Textiles",
            "type":"Manufacturing & Wholesale Goods"
        }
    ],
    "sg:phone":"+64 3-326 6821",
    "sg:province":"Canterbury",
    "sg:tags":[
        "clothing",
        "fabric",
        "manufacturer"
    ],
    "wof:name":"Sundown",
    "wof:placetype":"venue"
},
  "geometry": {"coordinates":[172.759933,-43.569839],"type":"Point"}
}