{
  "type": "Feature",
  "properties": {
    "iso:country":"NZ",
    "sg:address":"2 Devonport Rd ",
    "sg:city":"Tauranga",
    "sg:orig_category":"Shopping: Retail Stores: Books: Bookshops",
    "sg:phone":"+64 7-578 8847",
    "sg:province":"Auckland",
    "wof:name":"ISIS Bookstore",
    "wof:placetype":"venue"
},
  "geometry": {"coordinates":[176.169968,-37.684589],"type":"Point"}
}