{
  "type": "Feature",
  "properties": {
    "addr:full":"28 Alexandra St Howick  Auckland Auckland",
    "addr:housenumber":"28",
    "addr:street":"Alexandra St",
    "iso:country":"NZ",
    "sg:address":"28 Alexandra St Howick ",
    "sg:city":"Auckland",
    "sg:classifiers":[
        {
            "category":"Education",
            "subcategory":"Music School",
            "type":"Public Place"
        }
    ],
    "sg:phone":"+64 9-535 3473",
    "sg:province":"Auckland",
    "sg:tags":[
        "sport",
        "teacher",
        "leisure"
    ],
    "wof:name":"Fret'Tech",
    "wof:placetype":"venue"
},
  "geometry": {"coordinates":[174.916946,-36.894379],"type":"Point"}
}