{
  "type": "Feature",
  "properties": {
    "iso:country":"NZ",
    "sg:address":"Mark Tisdall Palmerston ",
    "sg:city":"Palmerston North",
    "sg:classifiers":[
        {
            "category":"Education",
            "subcategory":"Special Training",
            "type":"Public Place"
        }
    ],
    "sg:phone":"+64 21 2928 139",
    "sg:province":"Manawatu-Wanganui",
    "sg:website":"http://www.yellowpages.co.nz/for/pukeko/dp48425.html",
    "wof:name":"Pukeko",
    "wof:placetype":"venue"
},
  "geometry": {"coordinates":[175.620071,-40.386757],"type":"Point"}
}