{
  "type": "Feature",
  "properties": {
    "addr:full":"37 River St Waikiwi  Invercargill Southland",
    "addr:housenumber":"37",
    "addr:street":"River St",
    "iso:country":"NZ",
    "sg:address":"37 River St Waikiwi ",
    "sg:city":"Invercargill",
    "sg:orig_category":"Industrial: Engineering: Engineers - Precision",
    "sg:phone":"+64 3-215 4351",
    "sg:province":"Southland",
    "wof:name":"Comprehensive Plant Maintenance",
    "wof:placetype":"venue"
},
  "geometry": {"coordinates":[168.35223400000001,-46.387611],"type":"Point"}
}