{
  "type": "Feature",
  "properties": {
    "iso:country":"NZ",
    "sg:address":"54 Peel St ",
    "sg:city":"Gisborne",
    "sg:classifiers":[
        {
            "category":"Banks & Credit Unions",
            "subcategory":"Investment Brokerage",
            "type":"Services"
        }
    ],
    "sg:phone":"+64 6-868 1119",
    "sg:province":"Gisborne",
    "sg:tags":[
        "personal",
        "-",
        "finance"
    ],
    "wof:name":"Money Managers Gisborne",
    "wof:placetype":"venue"
},
  "geometry": {"coordinates":[178.025879,-38.666653],"type":"Point"}
}