{
  "type": "Feature",
  "properties": {
    "addr:full":"29 Gladstone St  Dargaville Northland",
    "addr:housenumber":"29",
    "addr:street":"Gladstone St",
    "iso:country":"NZ",
    "sg:address":"29 Gladstone St ",
    "sg:city":"Dargaville",
    "sg:classifiers":[
        {
            "category":"Home & Garden",
            "subcategory":"Kitchen Supply",
            "type":"Retail Goods"
        }
    ],
    "sg:phone":"+64 9-439 8386",
    "sg:province":"Northland",
    "sg:tags":[
        "shop",
        "pet",
        "pets"
    ],
    "wof:name":"Duck Creek Garden And Bird Centre",
    "wof:placetype":"venue"
},
  "geometry": {"coordinates":[173.870621,-35.937279],"type":"Point"}
}