{
  "type": "Feature",
  "properties": {
    "addr:full":"Private Bag 2017 New  Plymouth Taranaki",
    "addr:housenumber":"2017",
    "addr:street":"Private Bag",
    "iso:country":"NZ",
    "sg:address":"Private Bag 2017 New ",
    "sg:city":"Plymouth",
    "sg:classifiers":[
        {
            "category":"Banks & Credit Unions",
            "subcategory":"Investment Brokerage",
            "type":"Services"
        }
    ],
    "sg:phone":"+64 800 803 939",
    "sg:province":"Taranaki",
    "sg:tags":[
        "chemical",
        "industrial",
        "-",
        "compounds"
    ],
    "wof:name":"Dow AgroSciences (NZ) Ltd",
    "wof:placetype":"venue"
},
  "geometry": {"coordinates":[-116.81972500000001,43.97221],"type":"Point"}
}