{
  "type": "Feature",
  "properties": {
    "iso:country":"NZ",
    "sg:address":"228 Wellington St Howick ",
    "sg:city":"Auckland",
    "sg:classifiers":[
        {
            "category":"Manufacturing",
            "subcategory":"Furniture",
            "type":"Manufacturing & Wholesale Goods"
        }
    ],
    "sg:phone":"+64 9-537 3400",
    "sg:province":"Auckland",
    "sg:tags":[
        "furniture/furnishings",
        "home",
        "garden",
        "manufacturer"
    ],
    "wof:name":"Homestead Furniture",
    "wof:placetype":"venue"
},
  "geometry": {"coordinates":[174.9248046875,-36.9034881592],"type":"Point"}
}