{
  "type": "Feature",
  "properties": {
    "addr:full":"Fitzherbert Ave  Wanganui Manawatu-Wanganui",
    "addr:street":"Fitzherbert Ave",
    "iso:country":"NZ",
    "sg:address":"Fitzherbert Ave ",
    "sg:city":"Wanganui",
    "sg:orig_category":"Shopping: Sports Retailers: Cycles",
    "sg:phone":"+64 6-344 6702",
    "sg:province":"Manawatu-Wanganui",
    "wof:name":"Hedgehog Skateboards, Clothing & Accessories (Wanganui Branch Only)",
    "wof:placetype":"venue"
},
  "geometry": {"coordinates":[175.02410900000001,-39.932323],"type":"Point"}
}