{
  "type": "Feature",
  "properties": {
    "addr:full":"21 Sargood Dve  Wanaka Otago",
    "addr:housenumber":"21",
    "addr:street":"Sargood Dve",
    "iso:country":"NZ",
    "sg:address":"21 Sargood Dve ",
    "sg:city":"Wanaka",
    "sg:classifiers":[
        {
            "category":"Travel",
            "subcategory":"Bed & Breakfast",
            "type":"Entertainment"
        }
    ],
    "sg:phone":"+64 3-443 1933",
    "sg:province":"Otago",
    "sg:tags":[
        "tourism",
        "accommodation"
    ],
    "wof:name":"Wanaka Stonehouse",
    "wof:placetype":"venue"
},
  "geometry": {"coordinates":[169.13845800000001,-44.693981],"type":"Point"}
}