{
  "type": "Feature",
  "properties": {
    "iso:country":"NZ",
    "sg:address":"36 Raleigh St ",
    "sg:city":"Cambridge",
    "sg:orig_category":"Clothing And Fabric: Clothing: Dressmakers",
    "sg:phone":"+64 7-827 5017",
    "sg:province":"Waikato",
    "wof:name":"Sew In Style",
    "wof:placetype":"venue"
},
  "geometry": {"coordinates":[-116.67604799999999,44.572186],"type":"Point"}
}