{
  "type": "Feature",
  "properties": {
    "iso:country":"NZ",
    "sg:address":"22 Sefton St ",
    "sg:city":"Timaru",
    "sg:orig_category":"Health And Beauty: Mental: Psychology",
    "sg:phone":"+64 3-688 9291",
    "sg:province":"Canterbury",
    "wof:name":"Johnston Lee-Anna",
    "wof:placetype":"venue"
},
  "geometry": {"coordinates":[171.246155,-44.393238],"type":"Point"}
}