{
  "type": "Feature",
  "properties": {
    "addr:full":"22 Sefton St  Timaru Canterbury",
    "addr:housenumber":"22",
    "addr:street":"Sefton St",
    "iso:country":"NZ",
    "sg:address":"22 Sefton St ",
    "sg:city":"Timaru",
    "sg:orig_category":"Health And Beauty: Mental: Psychology",
    "sg:phone":"+64 3-688 9291",
    "sg:province":"Canterbury",
    "wof:name":"Johnston Lee-Anna",
    "wof:placetype":"venue"
},
  "geometry": {"coordinates":[171.24615499999999,-44.393238],"type":"Point"}
}