{
  "type": "Feature",
  "properties": {
    "iso:country":"NZ",
    "sg:address":"Cnr of Marine Pde & New Brighton Mall ",
    "sg:city":"Christchurch",
    "sg:classifiers":[
        {
            "category":"Bars & Pubs",
            "type":"Food & Drink"
        }
    ],
    "sg:phone":"+64 3-382 3353",
    "sg:province":"Canterbury",
    "sg:tags":[
        "wining",
        "dining",
        "brasserie"
    ],
    "wof:name":"Brighton Bars 2000 Ltd",
    "wof:placetype":"venue"
},
  "geometry": {"coordinates":[-76.537834,37.605659],"type":"Point"}
}