{
  "type": "Feature",
  "properties": {
    "addr:full":"Kamo  Whangarei Northland",
    "addr:housenumber":"kamo",
    "iso:country":"NZ",
    "sg:address":"Kamo ",
    "sg:city":"Whangarei",
    "sg:classifiers":[
        {
            "category":"Manufacturing",
            "subcategory":"Glass & Minerals",
            "type":"Manufacturing & Wholesale Goods"
        }
    ],
    "sg:phone":"+64 9-435 0196",
    "sg:province":"Northland",
    "sg:tags":[
        "raw",
        "industrial",
        "quarry",
        "materials"
    ],
    "wof:name":"Bay of Islands Contracting",
    "wof:placetype":"venue"
},
  "geometry": {"coordinates":[174.30029300000001,-35.68219],"type":"Point"}
}