{
  "type": "Feature",
  "properties": {
    "addr:full":"55 Osier Rd Greenmeadows  Napier Hawke's Bay",
    "addr:housenumber":"55",
    "addr:street":"Osier Rd",
    "iso:country":"NZ",
    "sg:address":"55 Osier Rd Greenmeadows ",
    "sg:city":"Napier",
    "sg:classifiers":[
        {
            "category":"Social Services",
            "subcategory":"Child Care",
            "type":"Services"
        }
    ],
    "sg:phone":"+64 6-844 4741",
    "sg:province":"Hawke's Bay",
    "sg:tags":[
        "home",
        "garden",
        "children"
    ],
    "wof:name":"Bumble-Bee Childrens Centre",
    "wof:placetype":"venue"
},
  "geometry": {"coordinates":[176.85360700000001,-39.52494],"type":"Point"}
}