{
  "type": "Feature",
  "properties": {
    "iso:country":"NZ",
    "sg:address":"27 Charters St Kaikorai ",
    "sg:city":"Dunedin",
    "sg:orig_category":"Home And Garden: General: Handyman'S Services",
    "sg:phone":"+64 3-476 3348",
    "sg:province":"Otago",
    "wof:name":"Mr Fixit",
    "wof:placetype":"venue"
},
  "geometry": {"coordinates":[170.45895400000001,-45.890236],"type":"Point"}
}