{
  "type": "Feature",
  "properties": {
    "addr:full":"123 Riccarton Rd Riccarton  Christchurch Canterbury",
    "addr:housenumber":"123",
    "addr:street":"Riccarton Rd;Christchurch",
    "iso:country":"NZ",
    "sg:address":"123 Riccarton Rd Riccarton ",
    "sg:city":"Christchurch",
    "sg:orig_category":"Clothing And Fabric: Clothing: Women'S Fashions",
    "sg:phone":"+64 3-348 5910",
    "sg:province":"Canterbury",
    "wof:name":"Diva Fashion Warehouse",
    "wof:placetype":"venue"
},
  "geometry": {"coordinates":[172.59841900000001,-43.529968],"type":"Point"}
}