{
  "type": "Feature",
  "properties": {
    "iso:country":"NZ",
    "sg:address":"134 Cuba St ",
    "sg:city":"Wellington",
    "sg:classifiers":[
        {
            "category":"Personal",
            "subcategory":"Beauty Salon",
            "type":"Services"
        }
    ],
    "sg:phone":"+64 4-385 6000",
    "sg:province":"Wellington",
    "sg:tags":[
        "yoga",
        "health",
        "fitness"
    ],
    "wof:name":"Wellington Hatha Yoga Centre",
    "wof:placetype":"venue"
},
  "geometry": {"coordinates":[-85.910454,33.827946],"type":"Point"}
}