{
  "type": "Feature",
  "properties": {
    "addr:full":"4 Rathbone St  Whangarei Northland",
    "addr:housenumber":"4",
    "addr:street":"Rathbone St",
    "iso:country":"NZ",
    "sg:address":"4 Rathbone St ",
    "sg:city":"Whangarei",
    "sg:orig_category":"Shopping: Sports Retailers: Sports Goods: Sportswear",
    "sg:phone":"+64 9-438 6958",
    "sg:province":"Northland",
    "wof:name":"Canterbury Of Whangarei",
    "wof:placetype":"venue"
},
  "geometry": {"coordinates":[174.32049599999999,-35.725101],"type":"Point"}
}