{
  "type": "Feature",
  "properties": {
    "addr:full":"14 Te Pai Pl Henderson  Auckland Auckland",
    "addr:housenumber":"14",
    "addr:street":"Te Pai Pl",
    "iso:country":"NZ",
    "sg:address":"14 Te Pai Pl Henderson ",
    "sg:city":"Auckland",
    "sg:orig_category":"Automotive: Accessories: Towbars",
    "sg:phone":"+64 9-838 5592",
    "sg:province":"Auckland",
    "wof:name":"Henderson Towbars",
    "wof:placetype":"venue"
},
  "geometry": {"coordinates":[174.63294999999999,-36.877289],"type":"Point"}
}