{
  "type": "Feature",
  "properties": {
    "addr:full":"511 Queen St  Thames Waikato",
    "addr:housenumber":"511",
    "addr:street":"Queen St",
    "iso:country":"NZ",
    "sg:address":"511 Queen St ",
    "sg:city":"Thames",
    "sg:classifiers":[
        {
            "category":"Shopping",
            "subcategory":"Crafts & Fabrics",
            "type":"Retail Goods"
        }
    ],
    "sg:phone":"+64 7-867 9350",
    "sg:province":"Waikato",
    "sg:tags":[
        "-",
        "protective",
        "clothing"
    ],
    "wof:name":"Thames Industrial Laundry (1980) Ltd",
    "wof:placetype":"venue"
},
  "geometry": {"coordinates":[175.543961,-37.145443],"type":"Point"}
}