{
  "type": "Feature",
  "properties": {
    "iso:country":"NZ",
    "sg:address":"Shop 25 10 Huron St Takapuna ",
    "sg:city":"Auckland",
    "sg:classifiers":[
        {
            "category":"Bars & Pubs",
            "subcategory":"Lounge",
            "type":"Food & Drink"
        }
    ],
    "sg:phone":"+64 9-488 0072",
    "sg:province":"Auckland",
    "sg:tags":[
        "baker",
        "-"
    ],
    "wof:name":"Richmond Bakery",
    "wof:placetype":"venue"
},
  "geometry": {"coordinates":[174.77049299999999,-36.789345],"type":"Point"}
}