{
  "type": "Feature",
  "properties": {
    "addr:full":"46 D Tohunga Cre Parnell  Auckland Auckland",
    "addr:housenumber":"46;cre",
    "addr:street":"D Tohunga",
    "iso:country":"NZ",
    "sg:address":"46 D Tohunga Cre Parnell ",
    "sg:city":"Auckland",
    "sg:orig_category":"Home And Garden: General",
    "sg:phone":"+64 9-379 5184",
    "sg:province":"Auckland",
    "sg:website":"http://www.daphnebrown.co.nz",
    "wof:name":"Daphne Brown & Associates",
    "wof:placetype":"venue"
},
  "geometry": {"coordinates":[174.78801000000001,-36.859058],"type":"Point"}
}