{
  "type": "Feature",
  "properties": {
    "addr:full":"35 Edinburgh St Waihi Beach  Waihi",
    "addr:housenumber":"35",
    "addr:street":"Edinburgh St",
    "iso:country":"NZ",
    "sg:address":"35 Edinburgh St Waihi Beach ",
    "sg:city":"Waihi",
    "sg:orig_category":"Health And Beauty: Specialists: Midwives",
    "sg:phone":"+64 7-863 5597",
    "wof:name":"Alison Nelson",
    "wof:placetype":"venue"
},
  "geometry": {"coordinates":[175.94399999999999,-37.410843],"type":"Point"}
}