{
  "type": "Feature",
  "properties": {
    "addr:full":"22 Devonport Rd  Tauranga Auckland",
    "addr:housenumber":"22",
    "addr:street":"Devonport Rd",
    "iso:country":"NZ",
    "sg:address":"22 Devonport Rd ",
    "sg:city":"Tauranga",
    "sg:orig_category":"Shopping: Retail Stores: Books: Bookshops",
    "sg:phone":"+64 7-578 7803",
    "sg:province":"Auckland",
    "wof:name":"Paper Plus",
    "wof:placetype":"venue"
},
  "geometry": {"coordinates":[176.16987599999999,-37.684956],"type":"Point"}
}