{
  "type": "Feature",
  "properties": {
    "addr:full":"Bldg 2/4 Rennie Dve Mangere Airport  Auckland Auckland",
    "addr:housenumber":"4;mangere airport",
    "addr:street":"Rennie Dve",
    "iso:country":"NZ",
    "sg:address":"Bldg 2/4 Rennie Dve Mangere Airport ",
    "sg:city":"Auckland",
    "sg:orig_category":"Automotive: Accessories: Car Security Systems",
    "sg:phone":"+64 9-275 1903",
    "sg:province":"Auckland",
    "wof:name":"Airport Auto Electrics",
    "wof:placetype":"venue"
},
  "geometry": {"coordinates":[174.82380699999999,-36.96891],"type":"Point"}
}