{
  "type": "Feature",
  "properties": {
    "addr:full":"277 Neilson St Onehunga  Auckland Auckland",
    "addr:housenumber":"277",
    "addr:street":"Neilson St",
    "iso:country":"NZ",
    "sg:address":"277 Neilson St Onehunga ",
    "sg:city":"Auckland",
    "sg:classifiers":[
        {
            "category":"Home & Garden",
            "subcategory":"Furniture",
            "type":"Retail Goods"
        }
    ],
    "sg:phone":"+64 9-636 5216",
    "sg:province":"Auckland",
    "sg:tags":[
        "furniture/furnishings",
        "furnishing"
    ],
    "sg:website":"http://www.yellowpages.co.nz/for/cabramanufacturingltd/dp10039.html",
    "wof:name":"Cabra Manufacturing Ltd",
    "wof:placetype":"venue"
},
  "geometry": {"coordinates":[174.792496,-36.926411],"type":"Point"}
}