{
  "type": "Feature",
  "properties": {
    "addr:full":"130 Maleme St Greerton  Tauranga Bay of Plenty",
    "addr:housenumber":"130",
    "addr:street":"Maleme St",
    "iso:country":"NZ",
    "sg:address":"130 Maleme St Greerton ",
    "sg:city":"Tauranga",
    "sg:orig_category":"Home And Garden: Furniture/Furnishings",
    "sg:phone":"+64 7-543 3660",
    "sg:province":"Bay of Plenty",
    "sg:website":"http://www.dm.co.nz",
    "wof:name":"Design Mobel NZ Ltd",
    "wof:placetype":"venue"
},
  "geometry": {"coordinates":[176.127792,-37.734863],"type":"Point"}
}