{
  "type": "Feature",
  "properties": {
    "addr:full":"Nobs Lin New  Plymouth Taranaki",
    "iso:country":"NZ",
    "sg:address":"Nobs Lin New ",
    "sg:city":"Plymouth",
    "sg:classifiers":[
        {
            "category":"Recreation",
            "type":"Entertainment"
        }
    ],
    "sg:phone":"+64 6-757 2267",
    "sg:province":"Taranaki",
    "sg:tags":[
        "sport",
        "leisure"
    ],
    "wof:name":"East End Leisure World",
    "wof:placetype":"venue"
},
  "geometry": {"coordinates":[-116.81972500000001,43.97221],"type":"Point"}
}