{
  "type": "Feature",
  "properties": {
    "addr:full":"1/41 Lansford Cre Avondale  Auckland Auckland",
    "addr:housenumber":"1 / 41;cre",
    "iso:country":"NZ",
    "sg:address":"1/41 Lansford Cre Avondale ",
    "sg:city":"Auckland",
    "sg:orig_category":"Industrial: Instruments: Industrial Instruments",
    "sg:phone":"+64 9-828 5327",
    "sg:province":"Auckland",
    "wof:name":"Instrumentation Control Manufacturing Ltd",
    "wof:placetype":"venue"
},
  "geometry": {"coordinates":[174.69816599999999,-36.905315],"type":"Point"}
}