{
  "type": "Feature",
  "properties": {
    "iso:country":"NZ",
    "sg:address":"50 Arrow St ",
    "sg:city":"Wakefield",
    "sg:orig_category":"Home And Garden: General: Handyman'S Services",
    "sg:phone":"+64 252478891",
    "wof:name":"Ian & Nicky's Property Care",
    "wof:placetype":"venue"
},
  "geometry": {"coordinates":[-97.014755249,39.2172660828],"type":"Point"}
}