{
  "type": "Feature",
  "properties": {
    "iso:country":"NZ",
    "sg:address":"72-74 Lake Rd ",
    "sg:city":"Hamilton",
    "sg:classifiers":[
        {
            "category":"Utilities",
            "subcategory":"Water",
            "type":"Services"
        }
    ],
    "sg:phone":"+64 7-847 3179",
    "sg:province":"Waikato",
    "sg:tags":[
        "storage"
    ],
    "wof:name":"Mico Pipelines",
    "wof:placetype":"venue"
},
  "geometry": {"coordinates":[-75.535851,42.832897],"type":"Point"}
}