{
  "type": "Feature",
  "properties": {
    "addr:full":"11 Hall St  Pukekohe Auckland",
    "addr:housenumber":"11",
    "addr:street":"Hall St",
    "iso:country":"NZ",
    "sg:address":"11 Hall St ",
    "sg:city":"Pukekohe",
    "sg:classifiers":[
        {
            "category":"Health Services",
            "subcategory":"Clinic",
            "type":"Services"
        }
    ],
    "sg:phone":"+64 9-238 6696",
    "sg:province":"Auckland",
    "sg:tags":[
        "medical",
        "beauty"
    ],
    "wof:name":"Pukekohe Family Doctors",
    "wof:placetype":"venue"
},
  "geometry": {"coordinates":[174.930252,-37.195728],"type":"Point"}
}