{
  "type": "Feature",
  "properties": {
    "addr:full":"21 Parkinson St  Gisborne Gisborne",
    "addr:housenumber":"21",
    "addr:street":"Parkinson St",
    "iso:country":"NZ",
    "sg:address":"21 Parkinson St ",
    "sg:city":"Gisborne",
    "sg:classifiers":[
        {
            "category":"Food & Beverages",
            "subcategory":"Groceries & Convenience Stores",
            "type":"Retail Goods"
        }
    ],
    "sg:phone":"+64 6-867 3599",
    "sg:province":"Gisborne",
    "sg:tags":[
        "foodstuff",
        "drink",
        "-"
    ],
    "wof:name":"Seafood Specialists Wholesale",
    "wof:placetype":"venue"
},
  "geometry": {"coordinates":[177.994598,-38.665489],"type":"Point"}
}