{
  "type": "Feature",
  "properties": {
    "addr:full":"42 Maria Pl Ext  Wanganui Manawatu-Wanganui",
    "addr:housenumber":"42",
    "addr:street":"Maria Pl Ext",
    "iso:country":"NZ",
    "sg:address":"42 Maria Pl Ext ",
    "sg:city":"Wanganui",
    "sg:classifiers":[
        {
            "category":"Autos & Motor Vehicles",
            "subcategory":"Motorcycle Sales",
            "type":"Retail Goods"
        }
    ],
    "sg:phone":"+64 6-345 7499",
    "sg:province":"Manawatu-Wanganui",
    "sg:tags":[
        "automotive",
        "scooter",
        "leasing"
    ],
    "wof:name":"Brian Thorley Motorcycle Repairs",
    "wof:placetype":"venue"
},
  "geometry": {"coordinates":[175.049194,-39.93515],"type":"Point"}
}