{
  "type": "Feature",
  "properties": {
    "iso:country":"NZ",
    "sg:address":"Shop 1 Dress Smart Factory Outlet Centre 403 Main South, Rd Hornby ",
    "sg:city":"Christchurch",
    "sg:orig_category":"Shopping: Retail Stores: Cds, Cassettes And Records",
    "sg:phone":"+64 3-349 7020",
    "sg:province":"Canterbury",
    "wof:name":"ECM Music",
    "wof:placetype":"venue"
},
  "geometry": {"coordinates":[172.536331,-43.534431],"type":"Point"}
}