{
  "type": "Feature",
  "properties": {
    "addr:full":"76 McAlpine St  Christchurch Canterbury",
    "addr:housenumber":"76",
    "addr:street":"Mcalpine St",
    "iso:country":"NZ",
    "sg:address":"76 McAlpine St ",
    "sg:city":"Christchurch",
    "sg:classifiers":[
        {
            "category":"Ice Cream",
            "type":"Food & Drink"
        }
    ],
    "sg:phone":"+64 3-343 3916",
    "sg:province":"Canterbury",
    "sg:tags":[
        "frozen",
        "-"
    ],
    "wof:name":"Associated Distributors",
    "wof:placetype":"venue"
},
  "geometry": {"coordinates":[-76.537834,37.605659],"type":"Point"}
}