{
  "type": "Feature",
  "properties": {
    "addr:full":"119 Harbour View Rd  Omokoroa",
    "addr:housenumber":"119",
    "addr:street":"Harbour View Rd",
    "iso:country":"NZ",
    "sg:address":"119 Harbour View Rd ",
    "sg:city":"Omokoroa",
    "sg:orig_category":"Home And Garden: Gardening: Products: Fertilisers",
    "sg:phone":"+64 800 878 745",
    "wof:name":"Vitec Fertilisers",
    "wof:placetype":"venue"
},
  "geometry": {"coordinates":[176.051636,-37.629601],"type":"Point"}
}