{
  "type": "Feature",
  "properties": {
    "addr:full":"3 Cornwall St  Masterton Wellington",
    "addr:housenumber":"3",
    "addr:street":"Cornwall St",
    "iso:country":"NZ",
    "sg:address":"3 Cornwall St ",
    "sg:city":"Masterton",
    "sg:classifiers":[
        {
            "category":"Social Services",
            "subcategory":"Retirement Home",
            "type":"Services"
        }
    ],
    "sg:phone":"+64 6-377 4165",
    "sg:province":"Wellington",
    "sg:tags":[
        "elderly",
        "convalescent",
        "garden",
        "rest",
        "care"
    ],
    "wof:name":"Cornwall Rest Homes",
    "wof:placetype":"venue"
},
  "geometry": {"coordinates":[175.65063499999999,-40.954815],"type":"Point"}
}