{
  "type": "Feature",
  "properties": {
    "iso:country":"NZ",
    "sg:address":"2 Leek St Newmarket ",
    "sg:city":"Auckland",
    "sg:orig_category":"Clothing And Fabric: Fabric: Textiles",
    "sg:phone":"+64 9-520 2043",
    "sg:province":"Auckland",
    "wof:name":"Maxwell Fabrics Ltd",
    "wof:placetype":"venue"
},
  "geometry": {"coordinates":[174.779831,-36.865341],"type":"Point"}
}