{
  "type": "Feature",
  "properties": {
    "addr:full":"24 Cairnfield Rd Kensington  Whangarei Northland",
    "addr:housenumber":"24",
    "addr:street":"Cairnfield Rd",
    "iso:country":"NZ",
    "sg:address":"24 Cairnfield Rd Kensington ",
    "sg:city":"Whangarei",
    "sg:orig_category":"Health And Beauty: Mental: Psychology",
    "sg:phone":"+64 9-437 5405",
    "sg:province":"Northland",
    "wof:name":"Smith Richard",
    "wof:placetype":"venue"
},
  "geometry": {"coordinates":[174.32015999999999,-35.708782],"type":"Point"}
}