{
  "type": "Feature",
  "properties": {
    "addr:full":"48-50 Dublin St  Wanganui Manawatu-Wanganui",
    "addr:housenumber":"48-50",
    "addr:street":"Dublin St",
    "iso:country":"NZ",
    "sg:address":"48-50 Dublin St ",
    "sg:city":"Wanganui",
    "sg:classifiers":[
        {
            "category":"Autos & Motor Vehicles",
            "subcategory":"Automobile Sales",
            "type":"Retail Goods"
        }
    ],
    "sg:phone":"+64 6-345 0233",
    "sg:province":"Manawatu-Wanganui",
    "sg:tags":[
        "leasing",
        "car",
        "-",
        "truck",
        "automotive",
        "new"
    ],
    "sg:website":"http://www.harveyround.co.nz",
    "wof:name":"Harvey Round Motors Ltd",
    "wof:placetype":"venue"
},
  "geometry": {"coordinates":[175.04632599999999,-39.924911],"type":"Point"}
}