{
  "type": "Feature",
  "properties": {
    "addr:full":"District Health Centre 12 Brown St  Inglewood",
    "addr:housenumber":"12",
    "addr:street":"Brown St",
    "iso:country":"NZ",
    "sg:address":"District Health Centre 12 Brown St ",
    "sg:city":"Inglewood",
    "sg:classifiers":[
        {
            "category":"Health Services",
            "subcategory":"Clinic",
            "type":"Services"
        }
    ],
    "sg:phone":"+64 6-756 7227",
    "sg:tags":[
        "medical",
        "beauty"
    ],
    "wof:name":"Fonseka Dr Marie",
    "wof:placetype":"venue"
},
  "geometry": {"coordinates":[174.20588699999999,-39.156784],"type":"Point"}
}