{
  "type": "Feature",
  "properties": {
    "addr:full":"Manukau City Centre  Auckland Auckland",
    "iso:country":"NZ",
    "sg:address":"Manukau City Centre ",
    "sg:city":"Auckland",
    "sg:classifiers":[
        {
            "category":"Shopping",
            "subcategory":"Crafts & Fabrics",
            "type":"Retail Goods"
        }
    ],
    "sg:phone":"+64 9-263 8851",
    "sg:province":"Auckland",
    "sg:tags":[
        "foot",
        "clothing",
        "retailer",
        "footwear",
        "wear"
    ],
    "wof:name":"Andrea Biani Shoes Ltd",
    "wof:placetype":"venue"
},
  "geometry": {"coordinates":[174.88145399999999,-36.98967],"type":"Point"}
}