{
  "type": "Feature",
  "properties": {
    "iso:country":"NZ",
    "sg:address":"222 Greenlane Rd Greenlane ",
    "sg:city":"Auckland",
    "sg:classifiers":[
        {
            "category":"Travel",
            "subcategory":"Hotels & Motels",
            "type":"Entertainment"
        }
    ],
    "sg:phone":"+64 9-630 2602",
    "sg:province":"Auckland",
    "sg:tags":[
        "lodge",
        "tourism",
        "accommodation"
    ],
    "sg:website":"http://www.yellowpages.co.nz/pages/200018253/dp43003.html",
    "wof:name":"Parklane (Greenlane) Motor Lodge",
    "wof:placetype":"venue"
},
  "geometry": {"coordinates":[174.791916,-36.892967],"type":"Point"}
}