{
  "type": "Feature",
  "properties": {
    "iso:country":"NZ",
    "sg:address":"115 Cashel St ",
    "sg:city":"Christchurch",
    "sg:orig_category":"Clothing And Fabric: Clothing: Tailors",
    "sg:phone":"+64 3-366 1486",
    "sg:province":"Canterbury",
    "wof:name":"Mike's Tailoring Service",
    "wof:placetype":"venue"
},
  "geometry": {"coordinates":[172.6362,-43.532944],"type":"Point"}
}