{
  "type": "Feature",
  "properties": {
    "iso:country":"NZ",
    "sg:address":"Oreti Rd Otatara ",
    "sg:city":"Invercargill",
    "sg:orig_category":"Farming: Services: Farm Consultants",
    "sg:phone":"+64 3-213 1021",
    "sg:province":"Southland",
    "wof:name":"FarmAssist Dairy Consultant",
    "wof:placetype":"venue"
},
  "geometry": {"coordinates":[168.29161099999999,-46.439835],"type":"Point"}
}