{
  "type": "Feature",
  "properties": {
    "addr:full":"35 High St Auckland Central  Auckland Auckland",
    "addr:housenumber":"35",
    "addr:street":"High St",
    "iso:country":"NZ",
    "sg:address":"35 High St Auckland Central ",
    "sg:city":"Auckland",
    "sg:orig_category":"Clothing And Fabric: Clothing: Jeans",
    "sg:phone":"+64 9-303 0111",
    "sg:province":"Auckland",
    "wof:name":"The Bronx",
    "wof:placetype":"venue"
},
  "geometry": {"coordinates":[174.76638800000001,-36.847958],"type":"Point"}
}