{
  "type": "Feature",
  "properties": {
    "iso:country":"NZ",
    "sg:address":"146 Ranginui Rd R D 5 ",
    "sg:city":"Tauranga",
    "sg:classifiers":[
        {
            "category":"Autos & Motor Vehicles",
            "subcategory":"Automobile Sales",
            "type":"Retail Goods"
        }
    ],
    "sg:phone":"+64 7-544 3990",
    "sg:province":"Bay of Plenty",
    "sg:tags":[
        "home",
        "caravan",
        "leasing",
        "automotive"
    ],
    "wof:name":"John McCracken Caravan Rentals",
    "wof:placetype":"venue"
},
  "geometry": {"coordinates":[176.144745,-37.703156],"type":"Point"}
}