{
  "type": "Feature",
  "properties": {
    "iso:country":"NZ",
    "sg:address":"Preston St Waikiwi ",
    "sg:city":"Invercargill",
    "sg:orig_category":"Transport: Transportation: Courier Services",
    "sg:phone":"+64 3-215 4387",
    "sg:province":"Southland",
    "wof:name":"PBT Couriers Limited",
    "wof:placetype":"venue"
},
  "geometry": {"coordinates":[168.351791,-46.386303],"type":"Point"}
}