{
  "type": "Feature",
  "properties": {
    "addr:full":"Lower Cameron St  Whangarei Northland",
    "addr:street":"Lower Cameron St",
    "iso:country":"NZ",
    "sg:address":"Lower Cameron St ",
    "sg:city":"Whangarei",
    "sg:orig_category":"Industrial: Engineering: Engineers: Engineers Supplies",
    "sg:phone":"+64 9-438 8802",
    "sg:province":"Northland",
    "wof:name":"Paykels",
    "wof:placetype":"venue"
},
  "geometry": {"coordinates":[174.320526,-35.725399],"type":"Point"}
}