{
  "type": "Feature",
  "properties": {
    "iso:country":"NZ",
    "sg:address":"R D 14 ",
    "sg:city":"Pohangina",
    "sg:classifiers":[
        {
            "category":"Banks & Credit Unions",
            "subcategory":"Investment Brokerage",
            "type":"Services"
        }
    ],
    "sg:phone":"+64 6-329 4065",
    "sg:tags":[
        "educational",
        "education",
        "training"
    ],
    "wof:name":"Writers' Ink",
    "wof:placetype":"venue"
},
  "geometry": {"coordinates":[175.79269400000001,-40.171829],"type":"Point"}
}