{
  "type": "Feature",
  "properties": {
    "iso:country":"NZ",
    "sg:address":"Andersons Lin ",
    "sg:city":"Carterton",
    "sg:orig_category":"Automotive: Parts And Supplies: Tyres",
    "sg:phone":"+64 6-379 6505",
    "wof:name":"Wairarapa Tyre Services",
    "wof:placetype":"venue"
},
  "geometry": {"coordinates":[-82.190933,36.941956],"type":"Point"}
}