{
  "type": "Feature",
  "properties": {
    "iso:country":"NZ",
    "sg:address":"28 Findlay St Ellerslie ",
    "sg:city":"Auckland",
    "sg:orig_category":"Sports And Leisure: General: Halls",
    "sg:phone":"+64 9-379 2030",
    "sg:province":"Auckland",
    "wof:name":"Leicester Hall",
    "wof:placetype":"venue"
},
  "geometry": {"coordinates":[174.811081,-36.899509],"type":"Point"}
}