{
  "type": "Feature",
  "properties": {
    "iso:country":"NZ",
    "sg:address":"100 Railside Ave Henderson ",
    "sg:city":"Auckland",
    "sg:orig_category":"Transport: Boats And Marine: Boats: Boat Design",
    "sg:phone":"+64 9-837 1447",
    "sg:province":"Auckland",
    "wof:name":"Given Ron",
    "wof:placetype":"venue"
},
  "geometry": {"coordinates":[174.631699,-36.886482],"type":"Point"}
}