{
  "type": "Feature",
  "properties": {
    "iso:country":"NZ",
    "sg:address":"Cnr Wordsworth St & Waltham Rd Sydenham ",
    "sg:city":"Christchurch",
    "sg:classifiers":[
        {
            "category":"Banks & Credit Unions",
            "subcategory":"Investment Brokerage",
            "type":"Services"
        }
    ],
    "sg:phone":"+64 3-379 4307",
    "sg:province":"Canterbury",
    "sg:tags":[
        "services",
        "industrial",
        "refrigeration",
        "servicing"
    ],
    "wof:name":"Christchurch Refrigeration & Electrical (CRE) Ltd",
    "wof:placetype":"venue"
},
  "geometry": {"coordinates":[172.637482,-43.547421],"type":"Point"}
}