{
  "type": "Feature",
  "properties": {
    "addr:full":"80 Bureta Rd  Tauranga Bay of Plenty",
    "addr:housenumber":"80",
    "addr:street":"Bureta Rd",
    "iso:country":"NZ",
    "sg:address":"80 Bureta Rd ",
    "sg:city":"Tauranga",
    "sg:orig_category":"Shopping: Retail Stores: Books: Bookshops",
    "sg:phone":"+64 7-576 9602",
    "sg:province":"Bay of Plenty",
    "wof:name":"Bureta Bookshop",
    "wof:placetype":"venue"
},
  "geometry": {"coordinates":[176.152512,-37.671345],"type":"Point"}
}