{
  "type": "Feature",
  "properties": {
    "iso:country":"NZ",
    "sg:address":"State Highway 12 Waimamaku ",
    "sg:city":"Kaikohe",
    "sg:classifiers":[
        {
            "category":"Brewery",
            "type":"Food & Drink"
        }
    ],
    "sg:phone":"+64 9-405 8681",
    "sg:tags":[
        "brewer"
    ],
    "wof:name":"Hokianga Breweries Ltd",
    "wof:placetype":"venue"
},
  "geometry": {"coordinates":[173.79710399999999,-35.40649],"type":"Point"}
}