{
  "type": "Feature",
  "properties": {
    "iso:country":"NZ",
    "sg:address":"Level 2 85 The Terrace ",
    "sg:city":"Wellington",
    "sg:orig_category":"Transport: Boats And Marine: Shipping: Shipping Companies",
    "sg:phone":"+64 4-471 0204",
    "sg:province":"Waikato",
    "wof:name":"Hartrodt A (NZ) Ltd",
    "wof:placetype":"venue"
},
  "geometry": {"coordinates":[-87.675285,40.541164],"type":"Point"}
}