{
  "type": "Feature",
  "properties": {
    "iso:country":"NZ",
    "sg:address":"Lilybrook Village ",
    "sg:city":"Rangiora",
    "sg:classifiers":[
        {
            "category":"Professional",
            "type":"Services"
        }
    ],
    "sg:phone":"+64 3-313 1188",
    "sg:province":"Canterbury",
    "sg:tags":[
        "home",
        "cleaning",
        "help",
        "garden"
    ],
    "wof:name":"Access Homehealth",
    "wof:placetype":"venue"
},
  "geometry": {"coordinates":[172.590302,-43.302959],"type":"Point"}
}