{
  "type": "Feature",
  "properties": {
    "iso:country":"NZ",
    "sg:address":"PO Box 185 ",
    "sg:city":"Waihi",
    "sg:orig_category":"Industrial: Metal: Stainless Steel",
    "sg:phone":"+64 7-863 7836",
    "wof:name":"CMC Engineering Ltd",
    "wof:placetype":"venue"
},
  "geometry": {"coordinates":[175.83845500000001,-37.388897],"type":"Point"}
}