{
  "type": "Feature",
  "properties": {
    "addr:full":"140 Bank St  Whangarei Northland",
    "addr:housenumber":"140",
    "addr:street":"Bank St",
    "iso:country":"NZ",
    "sg:address":"140 Bank St ",
    "sg:city":"Whangarei",
    "sg:classifiers":[
        {
            "category":"Shopping",
            "subcategory":"Stationery & Office Supplies",
            "type":"Retail Goods"
        }
    ],
    "sg:phone":"+64 9-438 7568",
    "sg:province":"Northland",
    "sg:tags":[
        "map",
        "chart"
    ],
    "wof:name":"Lands & Survey Ltd",
    "wof:placetype":"venue"
},
  "geometry": {"coordinates":[174.32139599999999,-35.719692],"type":"Point"}
}