{
  "type": "Feature",
  "properties": {
    "iso:country":"NZ",
    "sg:address":"Level 3 Chamber of Commerce House 20 Daly St Lower, Hutt ",
    "sg:city":"Wellington",
    "sg:classifiers":[
        {
            "category":"Health Services",
            "subcategory":"Hospital",
            "type":"Services"
        }
    ],
    "sg:phone":"+64 4-939 1175",
    "sg:province":"Wellington",
    "sg:tags":[
        "beauty",
        "fitness"
    ],
    "wof:name":"Hutt Valley Therapeutic Massage Clinic",
    "wof:placetype":"venue"
},
  "geometry": {"coordinates":[-87.679619,40.541962],"type":"Point"}
}