{
  "type": "Feature",
  "properties": {
    "iso:country":"NZ",
    "sg:address":"38 Tasman Rd ",
    "sg:city":"Twizel",
    "sg:orig_category":"Health And Beauty: Specialists: Physiotherapists",
    "sg:phone":"+64 3-435 0822",
    "wof:name":"Twizel Physiotherapy",
    "wof:placetype":"venue"
},
  "geometry": {"coordinates":[6.09018,53.231682],"type":"Point"}
}