{
  "type": "Feature",
  "properties": {
    "addr:full":"1 Exeter Rd Morningside  Auckland Auckland",
    "addr:housenumber":"1",
    "addr:street":"Exeter Rd",
    "iso:country":"NZ",
    "sg:address":"1 Exeter Rd Morningside ",
    "sg:city":"Auckland",
    "sg:classifiers":[
        {
            "category":"Shopping",
            "subcategory":"Pharmacy",
            "type":"Retail Goods"
        }
    ],
    "sg:phone":"+64 9-845 2005",
    "sg:province":"Auckland",
    "sg:tags":[
        "products",
        "medical",
        "health",
        "beauty",
        "supply"
    ],
    "wof:name":"Zepter International New Zealand Ltd",
    "wof:placetype":"venue"
},
  "geometry": {"coordinates":[174.732697,-36.878799],"type":"Point"}
}