{
  "type": "Feature",
  "properties": {
    "iso:country":"NZ",
    "sg:address":"Shop 22 Downtown Complex Broadway Ave Palmerston ",
    "sg:city":"Palmerston North",
    "sg:orig_category":"Shopping: Sports Retailers: Sports Goods: Sportswear",
    "sg:phone":"+64 6-356 4899",
    "sg:province":"Manawatu-Wanganui",
    "wof:name":"Shine Sportswear",
    "wof:placetype":"venue"
},
  "geometry": {"coordinates":[175.611481,-40.357418],"type":"Point"}
}