{
  "type": "Feature",
  "properties": {
    "iso:country":"NZ",
    "sg:address":"8 Mountain Rd Epsom ",
    "sg:city":"Auckland",
    "sg:orig_category":"Clothing And Fabric: Clothing: Uniforms",
    "sg:phone":"+64 9-303 0085",
    "sg:province":"Auckland",
    "wof:name":"Chefshop",
    "wof:placetype":"venue"
},
  "geometry": {"coordinates":[174.769745,-36.86871],"type":"Point"}
}