{
  "type": "Feature",
  "properties": {
    "iso:country":"NZ",
    "sg:address":"6 Wither Rd Taylor Pass ",
    "sg:city":"Blenheim",
    "sg:classifiers":[
        {
            "category":"Food & Beverages",
            "subcategory":"Candy",
            "type":"Retail Goods"
        }
    ],
    "sg:phone":"+64 3-577 8337",
    "sg:province":"Marlborough",
    "sg:tags":[
        "confectioner",
        "drink",
        "-"
    ],
    "wof:name":"Campanella Confectionery Ltd",
    "wof:placetype":"venue"
},
  "geometry": {"coordinates":[-74.459564,42.468643],"type":"Point"}
}