{
  "type": "Feature",
  "properties": {
    "addr:full":"8 Te Puni St Petone Lower  Hutt Wellington",
    "addr:housenumber":"8",
    "addr:street":"Te Puni St",
    "iso:country":"NZ",
    "sg:address":"8 Te Puni St Petone Lower ",
    "sg:city":"Hutt",
    "sg:classifiers":[
        {
            "category":"Shopping",
            "subcategory":"Stationery & Office Supplies",
            "type":"Retail Goods"
        }
    ],
    "sg:phone":"+64 4-568 8855",
    "sg:province":"Wellington",
    "sg:tags":[
        "supplies",
        "educational",
        "material",
        "education",
        "training"
    ],
    "wof:name":"Potter Interior Systems Ltd",
    "wof:placetype":"venue"
},
  "geometry": {"coordinates":[174.86875900000001,-41.224972],"type":"Point"}
}