{
  "type": "Feature",
  "properties": {
    "iso:country":"NZ",
    "sg:address":"213 Queen St Richmond ",
    "sg:city":"Nelson",
    "sg:classifiers":[
        {
            "category":"Sports & Exercise",
            "subcategory":"Climbing Gym",
            "type":"Entertainment"
        }
    ],
    "sg:phone":"+64 3-544 8290",
    "sg:province":"Nelson",
    "sg:tags":[
        "-",
        "leisure",
        "sports"
    ],
    "sg:website":"http://www.sportsworld.co.nz",
    "wof:name":"Sportsworld Richmond-The Great Outdoors Centre",
    "wof:placetype":"venue"
},
  "geometry": {"coordinates":[-121.765488,39.553471],"type":"Point"}
}