{
  "type": "Feature",
  "properties": {
    "addr:full":"15 Marshland Rd Shirley  Christchurch Canterbury",
    "addr:housenumber":"15",
    "addr:street":"Marshland Rd",
    "iso:country":"NZ",
    "sg:address":"15 Marshland Rd Shirley ",
    "sg:city":"Christchurch",
    "sg:classifiers":[
        {
            "category":"Shopping",
            "subcategory":"Pets & Pet Supplies",
            "type":"Retail Goods"
        }
    ],
    "sg:phone":"+64 3-385 6156",
    "sg:province":"Canterbury",
    "sg:tags":[
        "home",
        "grooming",
        "garden",
        "pets"
    ],
    "wof:name":"Dogs By Design At Shirley",
    "wof:placetype":"venue"
},
  "geometry": {"coordinates":[172.66258199999999,-43.506783],"type":"Point"}
}