{
  "type": "Feature",
  "properties": {
    "iso:country":"NZ",
    "sg:address":"59 East Tamaki Rd Papatoetoe ",
    "sg:city":"Auckland",
    "sg:classifiers":[
        {
            "category":"Bars & Pubs",
            "subcategory":"Lounge",
            "type":"Food & Drink"
        }
    ],
    "sg:phone":"+64 9-278 3731",
    "sg:province":"Auckland",
    "sg:tags":[
        "baker",
        "-"
    ],
    "wof:name":"Hunters Corner Bakery",
    "wof:placetype":"venue"
},
  "geometry": {"coordinates":[174.861679,-36.967762],"type":"Point"}
}