{
  "type": "Feature",
  "properties": {
    "addr:full":"93 Clyde  St",
    "addr:housenumber":"93",
    "addr:street":"Clyde St",
    "iso:country":"NZ",
    "sg:address":"93 Clyde ",
    "sg:city":"St",
    "sg:classifiers":[
        {
            "category":"Manufacturing",
            "subcategory":"Tools & Machinery",
            "type":"Manufacturing & Wholesale Goods"
        }
    ],
    "sg:phone":"+64 3-218 7263",
    "sg:tags":[
        "equipment",
        "industrial",
        "hydraulic"
    ],
    "wof:name":"Engineering Wholesalers Ltd",
    "wof:placetype":"venue"
},
  "geometry": {"coordinates":[169.32557700000001,-45.189011],"type":"Point"}
}