{
  "type": "Feature",
  "properties": {
    "addr:full":"1 A Rakino Way Mt Wellington  Auckland Auckland",
    "addr:housenumber":"1",
    "addr:street":"A Rakino Way",
    "iso:country":"NZ",
    "sg:address":"1 A Rakino Way Mt Wellington ",
    "sg:city":"Auckland",
    "sg:classifiers":[
        {
            "category":"Social Services",
            "subcategory":"Child Care",
            "type":"Services"
        }
    ],
    "sg:phone":"+64 9-276 1040",
    "sg:province":"Auckland",
    "sg:tags":[
        "baby",
        "home",
        "product",
        "garden",
        "children"
    ],
    "wof:name":"IGC NZ",
    "wof:placetype":"venue"
},
  "geometry": {"coordinates":[174.85531599999999,-36.923336],"type":"Point"}
}