{
  "type": "Feature",
  "properties": {
    "addr:full":"153 Brittan St  Hokitika West Coast",
    "addr:housenumber":"153",
    "addr:street":"Brittan St",
    "iso:country":"NZ",
    "sg:address":"153 Brittan St ",
    "sg:city":"Hokitika",
    "sg:classifiers":[
        {
            "category":"Professional",
            "subcategory":"Art Services",
            "type":"Services"
        }
    ],
    "sg:phone":"+64 3-755 6711",
    "sg:province":"West Coast",
    "sg:tags":[
        "picture",
        "arts",
        "sport",
        "framing",
        "leisure"
    ],
    "wof:name":"Studio Frames Irene Richards",
    "wof:placetype":"venue"
},
  "geometry": {"coordinates":[170.97262599999999,-42.71669],"type":"Point"}
}