{
  "type": "Feature",
  "properties": {
    "addr:full":"PO Box 56528 Dominion  Road",
    "addr:housenumber":"po box 56528",
    "addr:street":"Dominion Road",
    "iso:country":"NZ",
    "sg:address":"PO Box 56528 Dominion ",
    "sg:city":"Road",
    "sg:classifiers":[
        {
            "category":"Manufacturing",
            "subcategory":"Motor Vehicles & Parts",
            "type":"Manufacturing & Wholesale Goods"
        }
    ],
    "sg:phone":"+64 25846321",
    "sg:tags":[
        "air conditioning",
        "automotive",
        "supplies"
    ],
    "wof:name":"European Auto Air",
    "wof:placetype":"venue"
},
  "geometry": {"coordinates":[-95.787468,46.521141],"type":"Point"}
}