{
  "type": "Feature",
  "properties": {
    "iso:country":"NZ",
    "sg:address":"cnr Alexander St & Karamu Rd Nth ",
    "sg:city":"Hastings",
    "sg:orig_category":"Transport: Boats And Marine: Products",
    "sg:phone":"+64 6-878 8325",
    "sg:province":"Hawke's Bay",
    "wof:name":"Louis Marine",
    "wof:placetype":"venue"
},
  "geometry": {"coordinates":[176.844818,-39.64167],"type":"Point"}
}