{
  "type": "Feature",
  "properties": {
    "addr:full":"260 E Swanson Rd Henderson  Auckland Auckland",
    "addr:housenumber":"260",
    "addr:street":"E Swanson Rd",
    "iso:country":"NZ",
    "sg:address":"260 E Swanson Rd Henderson ",
    "sg:city":"Auckland",
    "sg:classifiers":[
        {
            "category":"Sports & Exercise",
            "subcategory":"Playing Field",
            "type":"Entertainment"
        }
    ],
    "sg:phone":"+64 9-836 1111",
    "sg:province":"Auckland",
    "sg:tags":[
        "hobby",
        "hobbies",
        "leisure",
        "supply"
    ],
    "wof:name":"Rob's Model World",
    "wof:placetype":"venue"
},
  "geometry": {"coordinates":[174.62051399999999,-36.871212],"type":"Point"}
}