{
  "type": "Feature",
  "properties": {
    "iso:country":"NZ",
    "sg:address":"52 Tennyson St ",
    "sg:city":"Dunedin",
    "sg:classifiers":[
        {
            "category":"Travel",
            "subcategory":"Bed & Breakfast",
            "type":"Entertainment"
        }
    ],
    "sg:phone":"+64 3-477 5319",
    "sg:province":"Otago",
    "sg:tags":[
        "tourism",
        "accommodation"
    ],
    "sg:website":"http://www.yellowpages.co.nz/for/hulmes_court/dp3461.html",
    "wof:name":"Hulmes Court Bed & Breakfast",
    "wof:placetype":"venue"
},
  "geometry": {"coordinates":[-82.784721,28.013355],"type":"Point"}
}