{
  "type": "Feature",
  "properties": {
    "iso:country":"NZ",
    "sg:address":"55 Treadwell St Naenae Lower ",
    "sg:city":"Hutt",
    "sg:classifiers":[
        {
            "category":"Communications",
            "subcategory":"Film & Video Production",
            "type":"Services"
        }
    ],
    "sg:phone":"+64 4-567 7286",
    "sg:province":"Wellington",
    "sg:tags":[
        "sport",
        "leisure",
        "library",
        "entertainment"
    ],
    "wof:name":"Amalgamated Video",
    "wof:placetype":"venue"
},
  "geometry": {"coordinates":[174.948364,-41.198132],"type":"Point"}
}