{
  "type": "Feature",
  "properties": {
    "iso:country":"NZ",
    "sg:address":"24 Ashford St Glenfield ",
    "sg:city":"Auckland",
    "sg:classifiers":[
        {
            "category":"Organizations",
            "subcategory":"Religious Organization",
            "type":"Services"
        }
    ],
    "sg:phone":"+64 9-444 4830",
    "sg:province":"Auckland",
    "sg:tags":[
        "arrangements",
        "tent",
        "marquee",
        "wedding"
    ],
    "wof:name":"DaRBi Accessories",
    "wof:placetype":"venue"
},
  "geometry": {"coordinates":[174.728622,-36.784813],"type":"Point"}
}