{
  "type": "Feature",
  "properties": {
    "iso:country":"NZ",
    "sg:address":"Ramshaw La ",
    "sg:city":"Arrowtown",
    "sg:classifiers":[
        {
            "category":"Food & Beverages",
            "subcategory":"Liquor & Beverages",
            "type":"Retail Goods"
        }
    ],
    "sg:phone":"+64 3-442 1026",
    "sg:province":"Otago",
    "sg:tags":[
        "drink",
        "outlet"
    ],
    "wof:name":"Allan Hamilton Wine Cellars",
    "wof:placetype":"venue"
},
  "geometry": {"coordinates":[168.831497,-44.938118],"type":"Point"}
}