{
  "type": "Feature",
  "properties": {
    "addr:full":"26 c Taradale Rd  Napier Hawke's Bay",
    "addr:housenumber":"26 c",
    "addr:street":"Taradale Rd",
    "iso:country":"NZ",
    "sg:address":"26 c Taradale Rd ",
    "sg:city":"Napier",
    "sg:classifiers":[
        {
            "category":"Bars & Pubs",
            "subcategory":"Lounge",
            "type":"Food & Drink"
        }
    ],
    "sg:phone":"+64 6-843 4818",
    "sg:province":"Hawke's Bay",
    "sg:tags":[
        "baker",
        "-"
    ],
    "wof:name":"Upper Crust Bakery",
    "wof:placetype":"venue"
},
  "geometry": {"coordinates":[176.87443500000001,-39.514668],"type":"Point"}
}