{
  "type": "Feature",
  "properties": {
    "iso:country":"NZ",
    "sg:address":"Otago St ",
    "sg:city":"Picton",
    "sg:orig_category":"Education And Training: General: Schools",
    "sg:phone":"+64 3-573 6895",
    "sg:province":"Marlborough",
    "wof:name":"St Josephs School",
    "wof:placetype":"venue"
},
  "geometry": {"coordinates":[174.009003,-41.293903],"type":"Point"}
}