{
  "type": "Feature",
  "properties": {
    "iso:country":"NZ",
    "sg:address":"53 Mill Bay Rd ",
    "sg:city":"Mangonui",
    "sg:classifiers":[
        {
            "category":"Organizations",
            "subcategory":"Labor Organization",
            "type":"Services"
        }
    ],
    "sg:phone":"+64 9-406 1554",
    "sg:tags":[
        "services",
        "charter",
        "tourism",
        "travel",
        "boat"
    ],
    "wof:name":"Teddy Bear Sailing Charters",
    "wof:placetype":"venue"
},
  "geometry": {"coordinates":[173.521851,-34.990158],"type":"Point"}
}