{
  "type": "Feature",
  "properties": {
    "iso:country":"NZ",
    "sg:address":"610 Dominion Rd Balmoral ",
    "sg:city":"Auckland",
    "sg:classifiers":[
        {
            "category":"Recreation",
            "type":"Entertainment"
        }
    ],
    "sg:phone":"+64 9-630 5522",
    "sg:province":"Auckland",
    "sg:tags":[
        "sport",
        "tramping",
        "leisure",
        "camping"
    ],
    "sg:website":"http://www.rocknasium.co.nz",
    "wof:name":"The Rocknasium",
    "wof:placetype":"venue"
},
  "geometry": {"coordinates":[174.747467,-36.886997],"type":"Point"}
}