{
  "type": "Feature",
  "properties": {
    "iso:country":"NZ",
    "sg:address":"249 Wicksteed St ",
    "sg:city":"Wanganui",
    "sg:classifiers":[
        {
            "category":"Building & Trades",
            "subcategory":"Plumbing",
            "type":"Services"
        }
    ],
    "sg:phone":"+64 6-349 0888",
    "sg:province":"Manawatu-Wanganui",
    "sg:tags":[
        "home",
        "plumber",
        "garden",
        "related"
    ],
    "wof:name":"Markhams MRI Wanganui Ltd",
    "wof:placetype":"venue"
},
  "geometry": {"coordinates":[175.046738,-39.92852],"type":"Point"}
}