{
  "type": "Feature",
  "properties": {
    "addr:full":"The Mall  Wainuiomata Wellington",
    "addr:street":"Mall",
    "iso:country":"NZ",
    "sg:address":"The Mall ",
    "sg:city":"Wainuiomata",
    "sg:classifiers":[
        {
            "category":"Health Services",
            "subcategory":"Podiatrist",
            "type":"Services"
        }
    ],
    "sg:phone":"+64 4-564 8057",
    "sg:province":"Wellington",
    "sg:tags":[
        "lens",
        "optical",
        "contact",
        "beauty"
    ],
    "wof:name":"Mills Moss & O'Connor Optometrists: Capitaleyes",
    "wof:placetype":"venue"
},
  "geometry": {"coordinates":[174.883759,-41.394157],"type":"Point"}
}