{
  "type": "Feature",
  "properties": {
    "iso:country":"NZ",
    "sg:address":"PO Box 1045 ",
    "sg:city":"Wellington",
    "sg:classifiers":[
        {
            "category":"Home & Garden",
            "subcategory":"Home Furnishings",
            "type":"Retail Goods"
        }
    ],
    "sg:phone":"+64 4-478 3318",
    "sg:province":"Wellington",
    "sg:tags":[
        "accessory"
    ],
    "sg:website":"http://www.thegrateplace.co.nz",
    "wof:name":"C W Martin Ltd",
    "wof:placetype":"venue"
},
  "geometry": {"coordinates":[174.767151,-41.28054],"type":"Point"}
}