{
  "type": "Feature",
  "properties": {
    "iso:country":"NZ",
    "sg:address":"393 Princes St ",
    "sg:city":"Dunedin",
    "sg:orig_category":"Shopping: Retail Stores: Secondhand Dealers",
    "sg:phone":"+64 3-477 8798",
    "sg:province":"Otago",
    "wof:name":"Anderson & Paul Antique Dealers & Restorers",
    "wof:placetype":"venue"
},
  "geometry": {"coordinates":[-82.784721,28.013355],"type":"Point"}
}