{
  "type": "Feature",
  "properties": {
    "iso:country":"NZ",
    "sg:address":"312 Rolleston St ",
    "sg:city":"Thames",
    "sg:classifiers":[
        {
            "category":"Social Services",
            "subcategory":"Retirement Home",
            "type":"Services"
        }
    ],
    "sg:phone":"+64 7-868 7867",
    "sg:province":"Waikato",
    "sg:tags":[
        "elderly",
        "convalescent",
        "garden",
        "rest",
        "care"
    ],
    "wof:name":"Robin's Nest Resthome",
    "wof:placetype":"venue"
},
  "geometry": {"coordinates":[175.550354,-37.146534],"type":"Point"}
}