{
  "type": "Feature",
  "properties": {
    "iso:country":"NZ",
    "sg:address":"419 Pine Hill Rd Pine Hill ",
    "sg:city":"Dunedin",
    "sg:classifiers":[
        {
            "category":"Retail",
            "subcategory":"Repair Shop",
            "type":"Services"
        }
    ],
    "sg:phone":"+64 3-473 0504",
    "sg:province":"Otago",
    "sg:tags":[
        "clothing",
        "fabric",
        "cleaning"
    ],
    "wof:name":"Looking Good",
    "wof:placetype":"venue"
},
  "geometry": {"coordinates":[170.520706,-45.839832],"type":"Point"}
}