{
  "type": "Feature",
  "properties": {
    "iso:country":"NZ",
    "sg:address":"Wanganui ",
    "sg:city":"Wanganui",
    "sg:orig_category":"Automotive: Parts And Supplies: Windscreens",
    "sg:phone":"+64 6-347 6222",
    "sg:province":"Manawatu-Wanganui",
    "wof:name":"Novus Autocare Wanganui",
    "wof:placetype":"venue"
},
  "geometry": {"coordinates":[175.047562,-39.928844],"type":"Point"}
}