{
  "type": "Feature",
  "properties": {
    "iso:country":"NZ",
    "sg:address":"33 New Regent St ",
    "sg:city":"Christchurch",
    "sg:classifiers":[
        {
            "category":"Shopping",
            "subcategory":"Crafts & Fabrics",
            "type":"Retail Goods"
        }
    ],
    "sg:phone":"+64 3-379 3323",
    "sg:province":"Canterbury",
    "sg:tags":[
        "clothing"
    ],
    "sg:website":"http://www.kildonan.hispeed.com/index.html",
    "wof:name":"Kildonan Highland House Ltd",
    "wof:placetype":"venue"
},
  "geometry": {"coordinates":[172.638504,-43.529057],"type":"Point"}
}