{
  "type": "Feature",
  "properties": {
    "addr:full":"8 The Promenade Takapuna  Auckland Auckland",
    "addr:housenumber":"8",
    "addr:street":"The Promenade",
    "iso:country":"NZ",
    "sg:address":"8 The Promenade Takapuna ",
    "sg:city":"Auckland",
    "sg:orig_category":"Home And Garden: Furniture/Furnishings: Curtains",
    "sg:phone":"+64 9-486 4370",
    "sg:province":"Auckland",
    "wof:name":"North Shore Curtains",
    "wof:placetype":"venue"
},
  "geometry": {"coordinates":[174.77304100000001,-36.783295],"type":"Point"}
}