{
  "type": "Feature",
  "properties": {
    "addr:full":"1 Link Drive Wairau Park Dve  Auckland Auckland",
    "addr:housenumber":"1",
    "addr:street":"Link Drive Wairau Park",
    "iso:country":"NZ",
    "sg:address":"1 Link Drive Wairau Park Dve ",
    "sg:city":"Auckland",
    "sg:orig_category":"Home And Garden: Furniture/Furnishings: Blinds",
    "sg:phone":"+64 9-443 8437",
    "sg:province":"Auckland",
    "wof:name":"Levene",
    "wof:placetype":"venue"
},
  "geometry": {"coordinates":[174.737122,-36.768631],"type":"Point"}
}