{
  "type": "Feature",
  "properties": {
    "iso:country":"NZ",
    "sg:address":"PO Box 5575 Lambton Quay ",
    "sg:city":"Wellington",
    "sg:orig_category":"Shopping: Sports Retailers: Sports Goods",
    "sg:phone":"+64 4-383 5265",
    "sg:province":"Wellington",
    "sg:website":"http://www.kickbike.co.nz",
    "wof:name":"Kickbike New Zealand",
    "wof:placetype":"venue"
},
  "geometry": {"coordinates":[174.77543600000001,-41.283409],"type":"Point"}
}