{
  "type": "Feature",
  "properties": {
    "addr:full":"18 Harrison St Brooklyn  Wellington Wellington",
    "addr:housenumber":"18",
    "addr:street":"Harrison St",
    "iso:country":"NZ",
    "sg:address":"18 Harrison St Brooklyn ",
    "sg:city":"Wellington",
    "sg:orig_category":"Sports And Leisure: General: Halls",
    "sg:phone":"+64 4-384 6799",
    "sg:province":"Wellington",
    "wof:name":"Brooklyn Community Centre",
    "wof:placetype":"venue"
},
  "geometry": {"coordinates":[174.76507599999999,-41.305626],"type":"Point"}
}