{
  "type": "Feature",
  "properties": {
    "addr:full":"19 Link Dve Glenfield  Auckland Auckland",
    "addr:housenumber":"19",
    "addr:street":"Link Dve",
    "iso:country":"NZ",
    "sg:address":"19 Link Dve Glenfield ",
    "sg:city":"Auckland",
    "sg:classifiers":[
        {
            "category":"Sports & Exercise",
            "subcategory":"Sports Center",
            "type":"Entertainment"
        }
    ],
    "sg:phone":"+64 9-442 2469",
    "sg:province":"Auckland",
    "sg:tags":[
        "indoor",
        "-",
        "leisure",
        "sports"
    ],
    "wof:name":"Tenpin Wairau Park",
    "wof:placetype":"venue"
},
  "geometry": {"coordinates":[174.728622,-36.784813],"type":"Point"}
}