{
  "type": "Feature",
  "properties": {
    "iso:country":"NZ",
    "sg:address":"cnr Leonard Rd & Sophia St Penrose ",
    "sg:city":"Auckland",
    "sg:classifiers":[
        {
            "category":"Autos & Motor Vehicles",
            "subcategory":"Automobile Sales",
            "type":"Retail Goods"
        }
    ],
    "sg:phone":"+64 9-580 9316",
    "sg:province":"Auckland",
    "sg:tags":[
        "bus",
        "leasing",
        "truck",
        "automotive"
    ],
    "wof:name":"Turners Truck Auctions",
    "wof:placetype":"venue"
},
  "geometry": {"coordinates":[174.81016540530001,-36.9116210938],"type":"Point"}
}