{
  "type": "Feature",
  "properties": {
    "addr:full":"81 Ingestre St  Wanganui Manawatu-Wanganui",
    "addr:housenumber":"81",
    "addr:street":"Ingestre St",
    "iso:country":"NZ",
    "sg:address":"81 Ingestre St ",
    "sg:city":"Wanganui",
    "sg:classifiers":[
        {
            "category":"Retail",
            "subcategory":"Auto Repair",
            "type":"Services"
        }
    ],
    "sg:phone":"+64 6-345 5454",
    "sg:province":"Manawatu-Wanganui",
    "sg:tags":[
        "automotive",
        "electric",
        "servicing"
    ],
    "wof:name":"Wanganui Auto Services Ltd",
    "wof:placetype":"venue"
},
  "geometry": {"coordinates":[175.04748499999999,-39.930759],"type":"Point"}
}