{
  "type": "Feature",
  "properties": {
    "iso:country":"NZ",
    "sg:address":"57 Fort St Auckland Central ",
    "sg:city":"Auckland",
    "sg:classifiers":[
        {
            "category":"Professional",
            "subcategory":"Management & Consulting",
            "type":"Services"
        }
    ],
    "sg:phone":"+64 9-307 0883",
    "sg:province":"Auckland",
    "sg:tags":[
        "consultant",
        "training",
        "education"
    ],
    "wof:name":"Insight Education Ltd",
    "wof:placetype":"venue"
},
  "geometry": {"coordinates":[174.76889,-36.846367],"type":"Point"}
}