{
  "type": "Feature",
  "properties": {
    "iso:country":"NZ",
    "sg:address":"27 Boons Valley Rd ",
    "sg:city":"Picton",
    "sg:classifiers":[
        {
            "category":"Organizations",
            "subcategory":"Labor Organization",
            "type":"Services"
        }
    ],
    "sg:phone":"+64 3-573 6155",
    "sg:province":"Marlborough",
    "sg:tags":[
        "services",
        "charter",
        "tourism",
        "travel",
        "boat"
    ],
    "wof:name":"Kenny Barging Ltd",
    "wof:placetype":"venue"
},
  "geometry": {"coordinates":[174.033295,-41.275112],"type":"Point"}
}