{
  "type": "Feature",
  "properties": {
    "addr:full":"132-164 High St Lower Hutt  Wellington Wellington",
    "addr:housenumber":"132-164",
    "addr:street":"High St",
    "iso:country":"NZ",
    "sg:address":"132-164 High St Lower Hutt ",
    "sg:city":"Wellington",
    "sg:classifiers":[
        {
            "category":"Sports & Exercise",
            "subcategory":"Golf",
            "type":"Entertainment"
        }
    ],
    "sg:phone":"+64 4-920 4653",
    "sg:province":"Wellington",
    "sg:tags":[
        "club",
        "equipment",
        "leisure",
        "sports"
    ],
    "wof:name":"Golf Discount Ltd",
    "wof:placetype":"venue"
},
  "geometry": {"coordinates":[174.90266399999999,-41.209663],"type":"Point"}
}