{
  "type": "Feature",
  "properties": {
    "addr:full":"22 Ponderosa Dve Browns Bay  Auckland Auckland",
    "addr:housenumber":"22",
    "addr:street":"Ponderosa Dve",
    "iso:country":"NZ",
    "sg:address":"22 Ponderosa Dve Browns Bay ",
    "sg:city":"Auckland",
    "sg:classifiers":[
        {
            "category":"Professional",
            "subcategory":"Management & Consulting",
            "type":"Services"
        }
    ],
    "sg:phone":"+64 9-478 3688",
    "sg:province":"Auckland",
    "sg:tags":[
        "consultant",
        "training",
        "education"
    ],
    "wof:name":"China NZ Cultural Exchange Centre",
    "wof:placetype":"venue"
},
  "geometry": {"coordinates":[174.77041600000001,-36.884109],"type":"Point"}
}