{
  "type": "Feature",
  "properties": {
    "addr:full":"355 Kapanga Rd  Coromandel",
    "addr:housenumber":"355",
    "addr:street":"Kapanga Rd",
    "iso:country":"NZ",
    "sg:address":"355 Kapanga Rd ",
    "sg:city":"Coromandel",
    "sg:classifiers":[
        {
            "category":"Landmark",
            "subcategory":"Tourist Information",
            "type":"Public Place"
        }
    ],
    "sg:phone":"+64 7-866 8598",
    "sg:tags":[
        "services",
        "travel",
        "tourism"
    ],
    "wof:name":"Coromandel Information Centre",
    "wof:placetype":"venue"
},
  "geometry": {"coordinates":[175.49778699999999,-36.759533],"type":"Point"}
}