{
  "type": "Feature",
  "properties": {
    "addr:full":"267 Great North Rd Grey Lynn  Auckland Auckland",
    "addr:housenumber":"267",
    "addr:street":"Great North Rd",
    "iso:country":"NZ",
    "sg:address":"267 Great North Rd Grey Lynn ",
    "sg:city":"Auckland",
    "sg:classifiers":[
        {
            "category":"Manufacturing",
            "subcategory":"Motor Vehicles & Parts",
            "type":"Manufacturing & Wholesale Goods"
        }
    ],
    "sg:phone":"+64 9-376 6691",
    "sg:province":"Auckland",
    "sg:tags":[
        "air conditioning",
        "automotive",
        "supplies"
    ],
    "wof:name":"Coolcar Air-Conditioning Centre",
    "wof:placetype":"venue"
},
  "geometry": {"coordinates":[174.74558999999999,-36.864849],"type":"Point"}
}