{
  "type": "Feature",
  "properties": {
    "addr:full":"101 Beaumont St Auckland Central  Auckland Auckland",
    "addr:housenumber":"101",
    "addr:street":"Beaumont St",
    "iso:country":"NZ",
    "sg:address":"101 Beaumont St Auckland Central ",
    "sg:city":"Auckland",
    "sg:orig_category":"Transport: Boats And Marine: Boats: Inflatable Boats",
    "sg:phone":"+64 9-303 4502",
    "sg:province":"Auckland",
    "wof:name":"Force Four (NZ) Ltd",
    "wof:placetype":"venue"
},
  "geometry": {"coordinates":[174.75335699999999,-36.844574],"type":"Point"}
}