{
  "type": "Feature",
  "properties": {
    "iso:country":"NZ",
    "sg:address":"80 Carbine Rd Mt Wellington ",
    "sg:city":"Auckland",
    "sg:classifiers":[
        {
            "category":"Home & Garden",
            "subcategory":"Garden Supply",
            "type":"Retail Goods"
        }
    ],
    "sg:phone":"+64 9-573 5720",
    "sg:province":"Auckland",
    "sg:tags":[
        "cleaning"
    ],
    "sg:website":"http://www.machine.co.nz",
    "wof:name":"MacDonald Machinery Ltd",
    "wof:placetype":"venue"
},
  "geometry": {"coordinates":[174.847702,-36.919136],"type":"Point"}
}