{
  "type": "Feature",
  "properties": {
    "addr:full":"3 Courtney Rd  Tauranga Bay of Plenty",
    "addr:housenumber":"3",
    "addr:street":"Courtney Rd",
    "iso:country":"NZ",
    "sg:address":"3 Courtney Rd ",
    "sg:city":"Tauranga",
    "sg:orig_category":"Industrial: Products: Window Control Gear",
    "sg:phone":"+64 7-571 1152",
    "sg:province":"Bay of Plenty",
    "wof:name":"Affordable Aluminium Joinery Repairs & Security",
    "wof:placetype":"venue"
},
  "geometry": {"coordinates":[176.14359999999999,-37.713898],"type":"Point"}
}