{
  "type": "Feature",
  "properties": {
    "iso:country":"NZ",
    "sg:address":"Old Renwick Rd ",
    "sg:city":"Blenheim",
    "sg:classifiers":[
        {
            "category":"Shopping",
            "subcategory":"Discount & Variety Stores",
            "type":"Retail Goods"
        }
    ],
    "sg:phone":"+64 3-578 2648",
    "sg:province":"Marlborough",
    "sg:tags":[
        "storage",
        "cool"
    ],
    "wof:name":"Provincial Coldstores Ltd",
    "wof:placetype":"venue"
},
  "geometry": {"coordinates":[173.951721,-41.49826],"type":"Point"}
}