{
  "type": "Feature",
  "properties": {
    "addr:full":"Cnr Broadway Ave & Princess St Palmerston  Palmerston North Manawatu-Wanganui",
    "addr:street":"Cnr Broadway Ave & Princess St",
    "iso:country":"NZ",
    "sg:address":"Cnr Broadway Ave & Princess St Palmerston ",
    "sg:city":"Palmerston North",
    "sg:classifiers":[
        {
            "category":"Travel",
            "subcategory":"Travel Agent",
            "type":"Entertainment"
        }
    ],
    "sg:phone":"+64 6-356 4800",
    "sg:province":"Manawatu-Wanganui",
    "sg:tags":[
        "tourism",
        "broker"
    ],
    "wof:name":"Harvey World Travel",
    "wof:placetype":"venue"
},
  "geometry": {"coordinates":[175.611481,-40.357422],"type":"Point"}
}