{
  "type": "Feature",
  "properties": {
    "iso:country":"NZ",
    "sg:address":"371 Gt North Rd Henderson ",
    "sg:city":"Auckland",
    "sg:classifiers":[
        {
            "category":"Shopping",
            "subcategory":"Shoes",
            "type":"Retail Goods"
        }
    ],
    "sg:phone":"+64 9-836 4533",
    "sg:province":"Auckland",
    "sg:tags":[
        "foot",
        "clothing",
        "fabric",
        "wear"
    ],
    "wof:name":"West City Shoes",
    "wof:placetype":"venue"
},
  "geometry": {"coordinates":[174.63227800000001,-36.879505],"type":"Point"}
}