{
  "type": "Feature",
  "properties": {
    "iso:country":"NZ",
    "sg:address":"484 Remuera Rd Remuera ",
    "sg:city":"Auckland",
    "sg:classifiers":[
        {
            "category":"Shopping",
            "subcategory":"Beauty & Cosmetics",
            "type":"Retail Goods"
        }
    ],
    "sg:phone":"+64 9-522 2012",
    "sg:province":"Auckland",
    "sg:tags":[
        "medical",
        "health"
    ],
    "sg:website":"http://www.e-health.co.nz",
    "wof:name":"E-Health Ltd",
    "wof:placetype":"venue"
},
  "geometry": {"coordinates":[174.80317700000001,-36.881145],"type":"Point"}
}