{
  "type": "Feature",
  "properties": {
    "addr:full":"32 Raupo St Bromley  Christchurch Canterbury",
    "addr:housenumber":"32",
    "addr:street":"Raupo St;Christchurch",
    "iso:country":"NZ",
    "sg:address":"32 Raupo St Bromley ",
    "sg:city":"Christchurch",
    "sg:orig_category":"Transport: Land: Taxis",
    "sg:phone":"+64 3-981 8897",
    "sg:province":"Canterbury",
    "wof:name":"Ace City Cabs Buses Shuttles & Limos Ltd",
    "wof:placetype":"venue"
},
  "geometry": {"coordinates":[172.68997200000001,-43.540516],"type":"Point"}
}