{
  "type": "Feature",
  "properties": {
    "addr:full":"301 Miller St  Hastings Hawke's Bay",
    "addr:housenumber":"301",
    "addr:street":"Miller St",
    "iso:country":"NZ",
    "sg:address":"301 Miller St ",
    "sg:city":"Hastings",
    "sg:classifiers":[
        {
            "category":"Health Services",
            "subcategory":"Health Practitioner",
            "type":"Services"
        }
    ],
    "sg:phone":"+64 6-878 0101",
    "sg:province":"Hawke's Bay",
    "sg:tags":[
        "consultant",
        "medical",
        "beauty"
    ],
    "wof:name":"Buteyko NZ",
    "wof:placetype":"venue"
},
  "geometry": {"coordinates":[176.849594,-39.644299],"type":"Point"}
}