{
  "type": "Feature",
  "properties": {
    "addr:full":"Main Hway  Otaki",
    "addr:street":"Hway",
    "iso:country":"NZ",
    "sg:address":"Main Hway ",
    "sg:city":"Otaki",
    "sg:orig_category":"Automotive: General Services: Service Stations",
    "sg:phone":"+64 6-364 5190",
    "wof:name":"Mobil Otaki",
    "wof:placetype":"venue"
},
  "geometry": {"coordinates":[175.14880400000001,-40.75914],"type":"Point"}
}