{
  "type": "Feature",
  "properties": {
    "iso:country":"NZ",
    "sg:address":"60 Fisk St Naenae Lower ",
    "sg:city":"Hutt",
    "sg:orig_category":"Industrial: Packaging: Packaging - General",
    "sg:phone":"+64 4-567 7730",
    "sg:province":"Wellington",
    "wof:name":"Disabled Resources Trust",
    "wof:placetype":"venue"
},
  "geometry": {"coordinates":[174.940887,-41.202377],"type":"Point"}
}