{
  "type": "Feature",
  "properties": {
    "addr:full":"Broadway  Stratford Manawatu-Wanganui",
    "addr:street":"Broadway",
    "iso:country":"NZ",
    "sg:address":"Broadway ",
    "sg:city":"Stratford",
    "sg:orig_category":"Health And Beauty: Specialists: Podiatrists",
    "sg:phone":"+64 6-765 6470",
    "sg:province":"Manawatu-Wanganui",
    "wof:name":"Ladd L P",
    "wof:placetype":"venue"
},
  "geometry": {"coordinates":[-73.129524,41.192841],"type":"Point"}
}