{
  "type": "Feature",
  "properties": {
    "addr:full":"12 Monteath  Pl",
    "addr:housenumber":"12",
    "addr:street":"Monteath Pl",
    "iso:country":"NZ",
    "sg:address":"12 Monteath ",
    "sg:city":"Pl",
    "sg:classifiers":[
        {
            "category":"Building & Trades",
            "subcategory":"Plumbing",
            "type":"Services"
        }
    ],
    "sg:phone":"+64 274 350 231",
    "sg:tags":[
        "home",
        "plumber",
        "garden",
        "related"
    ],
    "wof:name":"Alf Thorpe Plumbing",
    "wof:placetype":"venue"
},
  "geometry": {"coordinates":[170.36663799999999,-43.587711],"type":"Point"}
}