{
  "type": "Feature",
  "properties": {
    "addr:full":"4/87 Ocean View Rd Northcote  Auckland Auckland",
    "addr:housenumber":"4 / 87",
    "addr:street":"Ocean View Rd",
    "iso:country":"NZ",
    "sg:address":"4/87 Ocean View Rd Northcote ",
    "sg:city":"Auckland",
    "sg:classifiers":[
        {
            "category":"Professional",
            "subcategory":"Engineering",
            "type":"Services"
        }
    ],
    "sg:phone":"+64 9-480 7333",
    "sg:province":"Auckland",
    "sg:tags":[
        "industrial"
    ],
    "sg:website":"http://www.yellowpages.co.nz/for/check-point/dp38683.html",
    "wof:name":"Checkpoint Time & Business Systems Ltd",
    "wof:placetype":"venue"
},
  "geometry": {"coordinates":[174.747849,-36.801125],"type":"Point"}
}