{
  "type": "Feature",
  "properties": {
    "iso:country":"NZ",
    "sg:address":"PO Box 26-094 Newlands ",
    "sg:city":"Wellington",
    "sg:orig_category":"Food And Drink: Catering: Caterers",
    "sg:phone":"+64 4-477 0486",
    "sg:province":"Wellington",
    "sg:website":"http://www.inhousecatering.co.nz",
    "wof:name":"In House Catering Services Ltd",
    "wof:placetype":"venue"
},
  "geometry": {"coordinates":[174.819489,-41.225929],"type":"Point"}
}