{
  "type": "Feature",
  "properties": {
    "addr:full":"267 Crinan St  Invercargill Southland",
    "addr:housenumber":"267",
    "addr:street":"Crinan St",
    "iso:country":"NZ",
    "sg:address":"267 Crinan St ",
    "sg:city":"Invercargill",
    "sg:orig_category":"Education And Training: General: Schools",
    "sg:phone":"+64 3-218 6303",
    "sg:province":"Southland",
    "wof:name":"South School",
    "wof:placetype":"venue"
},
  "geometry": {"coordinates":[168.35922199999999,-46.422466],"type":"Point"}
}