{
  "type": "Feature",
  "properties": {
    "iso:country":"NZ",
    "sg:address":"4b Angle St Onehunga ",
    "sg:city":"Auckland",
    "sg:classifiers":[
        {
            "category":"Banks & Credit Unions",
            "subcategory":"Investment Brokerage",
            "type":"Services"
        }
    ],
    "sg:phone":"+64 9-634 4465",
    "sg:province":"Auckland",
    "sg:tags":[
        "funeral",
        "arrangements",
        "headstone"
    ],
    "wof:name":"Monument",
    "wof:placetype":"venue"
},
  "geometry": {"coordinates":[174.783661,-36.909973],"type":"Point"}
}