{
  "type": "Feature",
  "properties": {
    "iso:country":"NZ",
    "sg:address":"99 Gillies Ave Epsom ",
    "sg:city":"Auckland",
    "sg:classifiers":[
        {
            "category":"Arena",
            "subcategory":"Sports Club",
            "type":"Entertainment"
        }
    ],
    "sg:phone":"+64 9-524 0872",
    "sg:province":"Auckland",
    "sg:tags":[
        "-",
        "leisure",
        "sports"
    ],
    "wof:name":"Auckland Badminton Assoc. & Hall",
    "wof:placetype":"venue"
},
  "geometry": {"coordinates":[174.773483,-36.874569],"type":"Point"}
}