{
  "type": "Feature",
  "properties": {
    "iso:country":"NZ",
    "sg:address":"41 Selwyn St Onehunga ",
    "sg:city":"Auckland",
    "sg:classifiers":[
        {
            "category":"Retail",
            "subcategory":"Auto Repair",
            "type":"Services"
        }
    ],
    "sg:phone":"+64 9-636 6622",
    "sg:province":"Auckland",
    "sg:tags":[
        "muffler",
        "exhaust",
        "servicing",
        "automotive"
    ],
    "wof:name":"Mr Muffler NZ Ltd",
    "wof:placetype":"venue"
},
  "geometry": {"coordinates":[174.78329467770001,-36.9236068726],"type":"Point"}
}