{
  "type": "Feature",
  "properties": {
    "addr:full":"90 Greenlane Rd Remuera  Auckland Auckland",
    "addr:housenumber":"90",
    "addr:street":"Greenlane Rd",
    "iso:country":"NZ",
    "sg:address":"90 Greenlane Rd Remuera ",
    "sg:city":"Auckland",
    "sg:classifiers":[
        {
            "category":"Health Services",
            "subcategory":"Clinic",
            "type":"Services"
        }
    ],
    "sg:phone":"+64 9-520 9555",
    "sg:province":"Auckland",
    "sg:tags":[
        "medical",
        "e",
        "beauty"
    ],
    "wof:name":"Ascot Accident & Medical Clinic - 24 Hours",
    "wof:placetype":"venue"
},
  "geometry": {"coordinates":[174.80886799999999,-36.869381],"type":"Point"}
}