{
  "type": "Feature",
  "properties": {
    "iso:country":"NZ",
    "sg:address":"PO Box 100-134 North Shore Mail Cen ",
    "sg:city":"Auckland",
    "sg:orig_category":"Sports And Leisure: Entertainment: Balloons",
    "sg:phone":"+64 9-414 4094",
    "sg:province":"Auckland",
    "wof:name":"Balloonatics",
    "wof:placetype":"venue"
},
  "geometry": {"coordinates":[174.747498,-36.819668],"type":"Point"}
}