{
  "type": "Feature",
  "properties": {
    "iso:country":"NZ",
    "sg:address":"2 Monowai Pl ",
    "sg:city":"Glenwood",
    "sg:classifiers":[
        {
            "category":"Home & Garden",
            "subcategory":"Building Materials",
            "type":"Retail Goods"
        }
    ],
    "sg:phone":"+64 274 462 585",
    "sg:tags":[
        "builder",
        "related"
    ],
    "wof:name":"Ivan Patterson Builder",
    "wof:placetype":"venue"
},
  "geometry": {"coordinates":[-86.172333,31.665775],"type":"Point"}
}