{
  "type": "Feature",
  "properties": {
    "iso:country":"NZ",
    "sg:address":"1 Ayr St Parnell ",
    "sg:city":"Auckland",
    "sg:orig_category":"Clothing And Fabric: Clothing: Dressmakers",
    "sg:phone":"+64 9-379 9200",
    "sg:province":"Auckland",
    "wof:name":"Dress Sense",
    "wof:placetype":"venue"
},
  "geometry": {"coordinates":[174.78208900000001,-36.862057],"type":"Point"}
}