{
  "type": "Feature",
  "properties": {
    "iso:country":"NZ",
    "sg:address":"11 College St ",
    "sg:city":"Wellington",
    "sg:orig_category":"Industrial: Services",
    "sg:phone":"+64 4-381 8550",
    "sg:province":"Wellington",
    "sg:website":"http://www.scanning.co.nz",
    "wof:name":"Digital Filing Solutions Ltd",
    "wof:placetype":"venue"
},
  "geometry": {"coordinates":[174.78117399999999,-41.296471],"type":"Point"}
}