{
  "type": "Feature",
  "properties": {
    "addr:full":"1244 Rewi St Te  Awamutu Waikato",
    "addr:housenumber":"1244",
    "addr:street":"Rewi St",
    "iso:country":"NZ",
    "sg:address":"1244 Rewi St Te ",
    "sg:city":"Awamutu",
    "sg:orig_category":"Sports And Leisure: Sports: Equestrian: Equestrian Supplies",
    "sg:phone":"+64 7-871 3997",
    "sg:province":"Waikato",
    "wof:name":"Merg Equestrian Wear",
    "wof:placetype":"venue"
},
  "geometry": {"coordinates":[175.308258,-38.01104],"type":"Point"}
}