{
  "type": "Feature",
  "properties": {
    "iso:country":"NZ",
    "sg:address":"Okau R D 9 Masterton ",
    "sg:city":"Tinui",
    "sg:classifiers":[
        {
            "category":"Travel",
            "subcategory":"Travel Agent",
            "type":"Entertainment"
        }
    ],
    "sg:phone":"+64 6-372 6892",
    "sg:tags":[
        "tour",
        "tourism",
        "adventure",
        "sightseeing"
    ],
    "sg:website":"http://www.nzhunt.com",
    "wof:name":"Okau Wilderness Park",
    "wof:placetype":"venue"
},
  "geometry": {"coordinates":[176.07193,-40.877029],"type":"Point"}
}