{
  "type": "Feature",
  "properties": {
    "iso:country":"NZ",
    "sg:address":"500 Cranford St St Albans ",
    "sg:city":"Christchurch",
    "sg:orig_category":"Automotive: Sales And Leasing: Trailers",
    "sg:phone":"+64 3-352 8705",
    "sg:province":"Canterbury",
    "wof:name":"Caltex Cranford Street",
    "wof:placetype":"venue"
},
  "geometry": {"coordinates":[172.636185,-43.511974],"type":"Point"}
}