{
  "type": "Feature",
  "properties": {
    "iso:country":"NZ",
    "sg:address":"71 Great South Rd Newmarket ",
    "sg:city":"Auckland",
    "sg:orig_category":"Industrial: Services: Specialist Services: Laboratories",
    "sg:phone":"+64 9-917 5000",
    "sg:province":"Auckland",
    "sg:website":"http://www.harrisongrierson.com",
    "wof:name":"Harrison Grierson Consultants Limited",
    "wof:placetype":"venue"
},
  "geometry": {"coordinates":[174.773758,-36.867878],"type":"Point"}
}