{
  "type": "Feature",
  "properties": {
    "iso:country":"NZ",
    "sg:address":"17 Cornwall Park Ave Epsom ",
    "sg:city":"Auckland",
    "sg:orig_category":"Health And Beauty: Medical: Hospitals",
    "sg:phone":"+64 9-524 4429",
    "sg:province":"Auckland",
    "wof:name":"Cornwall Park Hospital",
    "wof:placetype":"venue"
},
  "geometry": {"coordinates":[174.77356,-36.876179],"type":"Point"}
}