{
  "type": "Feature",
  "properties": {
    "iso:country":"NZ",
    "sg:address":"25 Beaumont Rd ",
    "sg:city":"Rotorua",
    "sg:classifiers":[
        {
            "category":"Home & Garden",
            "subcategory":"Building Materials",
            "type":"Retail Goods"
        }
    ],
    "sg:phone":"+64 7-357 2087",
    "sg:province":"Bay of Plenty",
    "sg:tags":[
        "gate",
        "fitting",
        "outdoor"
    ],
    "sg:website":"http://www.yellowpages.co.nz/for/cotterillsecurityfencing/dp39103.html",
    "wof:name":"Cotterill Steve & Sharon",
    "wof:placetype":"venue"
},
  "geometry": {"coordinates":[176.215225,-38.08493],"type":"Point"}
}