{
  "type": "Feature",
  "properties": {
    "iso:country":"NZ",
    "sg:address":"6 Harrisville Rd Tuakau ",
    "sg:city":"Pukekohe",
    "sg:classifiers":[
        {
            "category":"Retail",
            "subcategory":"Auto Repair",
            "type":"Services"
        }
    ],
    "sg:phone":"+64 9-236 8386",
    "sg:province":"Auckland",
    "sg:tags":[
        "breakdown",
        "automotive",
        "towing",
        "servicing"
    ],
    "wof:name":"Miller Motors",
    "wof:placetype":"venue"
},
  "geometry": {"coordinates":[174.948242,-37.255878],"type":"Point"}
}