{
  "type": "Feature",
  "properties": {
    "addr:full":"46 Onslow St  Invercargill Southland",
    "addr:housenumber":"46",
    "addr:street":"Onslow St",
    "iso:country":"NZ",
    "sg:address":"46 Onslow St ",
    "sg:city":"Invercargill",
    "sg:orig_category":"Home And Garden: Accessories: Linen",
    "sg:phone":"+64 3-216 4884",
    "sg:province":"Southland",
    "wof:name":"Taylors Linen Hire",
    "wof:placetype":"venue"
},
  "geometry": {"coordinates":[168.345169,-46.602699],"type":"Point"}
}