{
  "type": "Feature",
  "properties": {
    "addr:full":"26 Rununga St  Taupo Waikato",
    "addr:housenumber":"26",
    "addr:street":"Rununga St",
    "iso:country":"NZ",
    "sg:address":"26 Rununga St ",
    "sg:city":"Taupo",
    "sg:classifiers":[
        {
            "category":"Personal",
            "subcategory":"Tattoo Parlor",
            "type":"Services"
        }
    ],
    "sg:phone":"+64 7-378 2498",
    "sg:province":"Waikato",
    "sg:tags":[
        "services",
        "home",
        "tattooists",
        "garden"
    ],
    "wof:name":"Contrary To Ordinary Tattoo's",
    "wof:placetype":"venue"
},
  "geometry": {"coordinates":[176.07360800000001,-38.682571],"type":"Point"}
}