{
  "type": "Feature",
  "properties": {
    "addr:full":"PO Box 50163  Porirua Wellington",
    "addr:housenumber":"po box",
    "addr:postcode":"50163",
    "iso:country":"NZ",
    "sg:address":"PO Box 50163 ",
    "sg:city":"Porirua",
    "sg:orig_category":"Shopping: Sports Retailers: Sports Goods: Sportswear",
    "sg:phone":"+64 4-238 4710",
    "sg:province":"Wellington",
    "wof:name":"Canterbury of New Zealand",
    "wof:placetype":"venue"
},
  "geometry": {"coordinates":[174.85223400000001,-41.138294],"type":"Point"}
}