{
  "type": "Feature",
  "properties": {
    "iso:country":"NZ",
    "sg:address":"Main Rd Grovetown ",
    "sg:city":"Blenheim",
    "sg:classifiers":[
        {
            "category":"Autos & Motor Vehicles",
            "subcategory":"Automobile Sales",
            "type":"Retail Goods"
        }
    ],
    "sg:phone":"+64 3-579 1444",
    "sg:province":"Marlborough",
    "sg:tags":[
        "home",
        "caravan",
        "leasing",
        "automotive"
    ],
    "sg:website":"http://www.yellowpages.co.nz/for/rentalmotorhomes/dp43483.html",
    "wof:name":"New Zealand Motor Home Rentals",
    "wof:placetype":"venue"
},
  "geometry": {"coordinates":[173.962524,-41.481834],"type":"Point"}
}