{
  "type": "Feature",
  "properties": {
    "iso:country":"NZ",
    "sg:address":"34 Kauri St ",
    "sg:city":"Timaru",
    "sg:classifiers":[
        {
            "category":"Building & Trades",
            "subcategory":"Construction",
            "type":"Services"
        }
    ],
    "sg:phone":"+64 21 323 734",
    "sg:province":"Canterbury",
    "sg:tags":[
        "home",
        "garden",
        "related",
        "plasterer"
    ],
    "wof:name":"Todd Mudie Plastering",
    "wof:placetype":"venue"
},
  "geometry": {"coordinates":[171.21530200000001,-44.392017],"type":"Point"}
}