{
  "type": "Feature",
  "properties": {
    "iso:country":"NZ",
    "sg:address":"Suite 12a Marinoto Clinic Newington Ave Maori Hill",
    "sg:city":"Dunedin",
    "sg:classifiers":[
        {
            "category":"Shopping Center",
            "type":"Public Place"
        }
    ],
    "sg:phone":"+64 3-467 2223",
    "sg:province":"Otago",
    "sg:tags":[
        "health",
        "surgery",
        "optical",
        "eye",
        "beauty"
    ],
    "wof:name":"Keillor Dr R B",
    "wof:placetype":"venue"
},
  "geometry": {"coordinates":[170.502701,-45.859348],"type":"Point"}
}