{
  "type": "Feature",
  "properties": {
    "addr:full":"3 Sophia St  Timaru Canterbury",
    "addr:housenumber":"3",
    "addr:street":"Sophia St",
    "iso:country":"NZ",
    "sg:address":"3 Sophia St ",
    "sg:city":"Timaru",
    "sg:orig_category":"Automotive: General Services: Rental Vehicles",
    "sg:phone":"+64 3-684 4020",
    "sg:province":"Canterbury",
    "wof:name":"New Zealand Rent A Car",
    "wof:placetype":"venue"
},
  "geometry": {"coordinates":[171.253052,-44.397247],"type":"Point"}
}