{
  "type": "Feature",
  "properties": {
    "iso:country":"NZ",
    "sg:address":"96 Sunnybrae Rd Hillcrest ",
    "sg:city":"Auckland",
    "sg:orig_category":"Automotive: Parts And Supplies: Turbochargers",
    "sg:phone":"+64 9-410 5468",
    "sg:province":"Waikato",
    "wof:name":"A 1 Turbo Reconditioners",
    "wof:placetype":"venue"
},
  "geometry": {"coordinates":[174.743271,-36.793854],"type":"Point"}
}