{
  "type": "Feature",
  "properties": {
    "addr:full":"17 Plummers Point Rd Omokoroa  Tauranga Bay of Plenty",
    "addr:housenumber":"17",
    "addr:street":"Plummers Point Rd",
    "iso:country":"NZ",
    "sg:address":"17 Plummers Point Rd Omokoroa ",
    "sg:city":"Tauranga",
    "sg:orig_category":"Sports And Leisure: Sports: Equestrian: Riding Schools",
    "sg:phone":"+64 7-548 0404",
    "sg:province":"Bay of Plenty",
    "wof:name":"World of Horses",
    "wof:placetype":"venue"
},
  "geometry": {"coordinates":[176.14475999999999,-37.703152],"type":"Point"}
}