{
  "type": "Feature",
  "properties": {
    "iso:country":"NZ",
    "sg:address":"169 Wainui Rd PO Box 2137 ",
    "sg:city":"Gisborne",
    "sg:orig_category":"Transport: Boats And Marine: Shipping",
    "sg:phone":"+64 6-868 0860",
    "sg:province":"Gisborne",
    "wof:name":"Olsen Shipping (Gisborne) Ltd",
    "wof:placetype":"venue"
},
  "geometry": {"coordinates":[178.024475,-38.66597],"type":"Point"}
}