{
  "type": "Feature",
  "properties": {
    "iso:country":"NZ",
    "sg:address":"Bristol St Riverlands ",
    "sg:city":"Blenheim",
    "sg:orig_category":"Transport: Transportation: Furniture Removal/Packers",
    "sg:phone":"+64 3-578 8308",
    "sg:province":"Marlborough",
    "wof:name":"Kirbys Furniture Removals",
    "wof:placetype":"venue"
},
  "geometry": {"coordinates":[174.01097100000001,-41.530647],"type":"Point"}
}