{
  "type": "Feature",
  "properties": {
    "iso:country":"NZ",
    "sg:address":"170 Ocean Beach Rd ",
    "sg:city":"Bluff",
    "sg:classifiers":[
        {
            "category":"Home & Garden",
            "subcategory":"Building Materials",
            "type":"Retail Goods"
        }
    ],
    "sg:phone":"+64 3-212 7837",
    "sg:tags":[
        "design",
        "fitting",
        "fittings",
        "kitchen"
    ],
    "wof:name":"Versatile Joinery Southland Ltd",
    "wof:placetype":"venue"
},
  "geometry": {"coordinates":[-109.546745,37.286579],"type":"Point"}
}