{
  "type": "Feature",
  "properties": {
    "addr:full":"17 C George Tce Onehunga  Auckland Auckland",
    "addr:housenumber":"17 c",
    "addr:street":"George Tce",
    "iso:country":"NZ",
    "sg:address":"17 C George Tce Onehunga ",
    "sg:city":"Auckland",
    "sg:orig_category":"Shopping: Retail Stores: Stationery",
    "sg:phone":"+64 9-634 2370",
    "sg:province":"Auckland",
    "wof:name":"K Kurtovich Products Ltd",
    "wof:placetype":"venue"
},
  "geometry": {"coordinates":[174.77911399999999,-36.924412],"type":"Point"}
}