{
  "type": "Feature",
  "properties": {
    "iso:country":"NZ",
    "sg:address":"51 Tukapa St New ",
    "sg:city":"Plymouth",
    "sg:classifiers":[
        {
            "category":"Bars & Pubs",
            "subcategory":"Lounge",
            "type":"Food & Drink"
        }
    ],
    "sg:phone":"+64 6-753 4499",
    "sg:province":"Taranaki",
    "sg:tags":[
        "baker",
        "-"
    ],
    "wof:name":"West Town Hot Bread",
    "wof:placetype":"venue"
},
  "geometry": {"coordinates":[-116.819725,43.97221],"type":"Point"}
}