{
  "type": "Feature",
  "properties": {
    "addr:full":"14 Ted Gillard Pl Johnsonville  Wellington Wellington",
    "addr:housenumber":"14",
    "addr:street":"Ted Gillard Pl",
    "iso:country":"NZ",
    "sg:address":"14 Ted Gillard Pl Johnsonville ",
    "sg:city":"Wellington",
    "sg:classifiers":[
        {
            "category":"Shopping",
            "subcategory":"Pets & Pet Supplies",
            "type":"Retail Goods"
        }
    ],
    "sg:phone":"+64 4-478 6638",
    "sg:province":"Wellington",
    "sg:tags":[
        "boarding",
        "garden",
        "pets",
        "catteries",
        "home",
        "kennel"
    ],
    "wof:name":"Prefurred Pet Feeding Services",
    "wof:placetype":"venue"
},
  "geometry": {"coordinates":[174.80178799999999,-41.222324],"type":"Point"}
}