{
  "type": "Feature",
  "properties": {
    "addr:full":"261 Ferguson St Palmerston  Palmerston North Manawatu-Wanganui",
    "addr:housenumber":"261",
    "addr:street":"Ferguson St Palmerston",
    "iso:country":"NZ",
    "sg:address":"261 Ferguson St Palmerston ",
    "sg:city":"Palmerston North",
    "sg:orig_category":"Sports And Leisure: General: Halls",
    "sg:phone":"+64 6-359 0977",
    "sg:province":"Manawatu-Wanganui",
    "wof:name":"SDA Hall & Seminar Rooms",
    "wof:placetype":"venue"
},
  "geometry": {"coordinates":[175.60839799999999,-40.361603],"type":"Point"}
}