{
  "type": "Feature",
  "properties": {
    "iso:country":"NZ",
    "sg:address":"129 Riccarton Rd Riccarton ",
    "sg:city":"Christchurch",
    "sg:orig_category":"Shopping: Accessories: Handbags",
    "sg:phone":"+64 3-343 2403",
    "sg:province":"Canterbury",
    "wof:name":"Strandbags",
    "wof:placetype":"venue"
},
  "geometry": {"coordinates":[172.598206,-43.530033],"type":"Point"}
}