{
  "type": "Feature",
  "properties": {
    "iso:country":"NZ",
    "sg:address":"35 Treadwell St ",
    "sg:city":"Wanganui",
    "sg:classifiers":[
        {
            "category":"Social Services",
            "subcategory":"Retirement Home",
            "type":"Services"
        }
    ],
    "sg:phone":"+64 6-345 3974",
    "sg:province":"Manawatu-Wanganui",
    "sg:tags":[
        "elderly",
        "convalescent",
        "garden",
        "rest",
        "care"
    ],
    "wof:name":"Wattle Downs",
    "wof:placetype":"venue"
},
  "geometry": {"coordinates":[175.02887000000001,-39.922337],"type":"Point"}
}