{
  "type": "Feature",
  "properties": {
    "iso:country":"NZ",
    "sg:address":"4 Waipuna Rd Mt Wellington ",
    "sg:city":"Auckland",
    "sg:orig_category":"Transport: Boats And Marine: Shipping: Shipping Companies",
    "sg:phone":"+64 9-570 4088",
    "sg:province":"Auckland",
    "wof:name":"RFL International",
    "wof:placetype":"venue"
},
  "geometry": {"coordinates":[174.8396,-36.908661],"type":"Point"}
}