{
  "type": "Feature",
  "properties": {
    "addr:full":"unit G 121 Rosedale Rd Albany  Auckland Auckland",
    "addr:housenumber":"unit g 121",
    "addr:street":"Rosedale Rd",
    "iso:country":"NZ",
    "sg:address":"unit G 121 Rosedale Rd Albany ",
    "sg:city":"Auckland",
    "sg:classifiers":[
        {
            "category":"Education",
            "subcategory":"Special Training",
            "type":"Public Place"
        }
    ],
    "sg:phone":"+64 9-478 3418",
    "sg:province":"Auckland",
    "sg:tags":[
        "charter",
        "shopping",
        "dive",
        "tuition",
        "water",
        "sports",
        "retailers",
        "sport"
    ],
    "wof:name":"Dive HQ Northshore",
    "wof:placetype":"venue"
},
  "geometry": {"coordinates":[174.709686,-36.720142],"type":"Point"}
}