{
  "type": "Feature",
  "properties": {
    "iso:country":"NZ",
    "sg:address":"Phone Hamilton ",
    "sg:city":"Hamilton",
    "sg:orig_category":"Shopping: Retail Stores: Florists",
    "sg:phone":"+64 7-823 6266",
    "sg:province":"Waikato",
    "wof:name":"Simply Elegant Flowers",
    "wof:placetype":"venue"
},
  "geometry": {"coordinates":[-88.41184199999999,33.748112],"type":"Point"}
}