{
  "type": "Feature",
  "properties": {
    "addr:full":"Gimblett Rd Flaxmere  Hastings Hawke's Bay",
    "addr:street":"Gimblett Rd",
    "iso:country":"NZ",
    "sg:address":"Gimblett Rd Flaxmere ",
    "sg:city":"Hastings",
    "sg:classifiers":[
        {
            "category":"Winery",
            "type":"Food & Drink"
        }
    ],
    "sg:phone":"+64 6-879 5897",
    "sg:province":"Hawke's Bay",
    "sg:tags":[
        "wining",
        "vineyard",
        "dining"
    ],
    "wof:name":"Stony Bay Vineyard",
    "wof:placetype":"venue"
},
  "geometry": {"coordinates":[176.78324900000001,-39.622997],"type":"Point"}
}