{
  "type": "Feature",
  "properties": {
    "iso:country":"NZ",
    "sg:address":"409 Cameron Rd ",
    "sg:city":"Tauranga",
    "sg:orig_category":"Industrial: Abrasives: Water Blasting",
    "sg:phone":"+64 7-578 2263",
    "sg:province":"Bay of Plenty",
    "sg:website":"http://www.actionequipment.co.nz",
    "wof:name":"Action Equipment Ltd",
    "wof:placetype":"venue"
},
  "geometry": {"coordinates":[176.161789,-37.694252],"type":"Point"}
}