{
  "type": "Feature",
  "properties": {
    "iso:country":"NZ",
    "sg:address":"Lunns Rd Upper Riccarton ",
    "sg:city":"Christchurch",
    "sg:classifiers":[
        {
            "category":"Marine",
            "type":"Transportation"
        }
    ],
    "sg:phone":"+64 3-343 7505",
    "sg:province":"Canterbury",
    "sg:tags":[
        "transport",
        "boat"
    ],
    "sg:website":"http://www.hamjet.co.nz",
    "wof:name":"Hamilton C W F & Co Ltd",
    "wof:placetype":"venue"
},
  "geometry": {"coordinates":[172.597351,-43.532143],"type":"Point"}
}