{
  "type": "Feature",
  "properties": {
    "addr:full":"Hutt Valley Lower  Hutt Wellington",
    "iso:country":"NZ",
    "sg:address":"Hutt Valley Lower ",
    "sg:city":"Hutt",
    "sg:classifiers":[
        {
            "category":"Education",
            "subcategory":"Music School",
            "type":"Public Place"
        }
    ],
    "sg:phone":"+64 4-586 2049",
    "sg:province":"Wellington",
    "sg:tags":[
        "sport",
        "teacher",
        "leisure"
    ],
    "wof:name":"Newton Day Music",
    "wof:placetype":"venue"
},
  "geometry": {"coordinates":[174.904526,-41.208431],"type":"Point"}
}