{
  "type": "Feature",
  "properties": {
    "addr:full":"PO Box 17 155, Greenlane, 1130, Local  Agent Auckland",
    "addr:housenumber":"po box 17 155",
    "addr:postcode":"1130",
    "iso:country":"NZ",
    "sg:address":"PO Box 17 155, Greenlane, 1130, Local ",
    "sg:city":"Agent",
    "sg:classifiers":[
        {
            "category":"Retail",
            "subcategory":"Auto Repair",
            "type":"Services"
        }
    ],
    "sg:phone":"+64 800 100 710",
    "sg:province":"Auckland",
    "sg:tags":[
        "automotive",
        "servicing"
    ],
    "wof:name":"FLN Automotive Supplies",
    "wof:placetype":"venue"
},
  "geometry": {"coordinates":[174.79191599999999,-36.89296],"type":"Point"}
}