{
  "type": "Feature",
  "properties": {
    "addr:full":"Cooper Rd Ramarama  Auckland Auckland",
    "addr:street":"Cooper Rd",
    "iso:country":"NZ",
    "sg:address":"Cooper Rd Ramarama ",
    "sg:city":"Auckland",
    "sg:classifiers":[
        {
            "category":"Home & Garden",
            "subcategory":"Garden Supply",
            "type":"Retail Goods"
        }
    ],
    "sg:phone":"+64 9-294 8771",
    "sg:province":"Auckland",
    "sg:tags":[
        "gardening"
    ],
    "sg:website":"http://www.rainbowpark.co.nz",
    "wof:name":"Rainbow Park Nurseries Ltd",
    "wof:placetype":"venue"
},
  "geometry": {"coordinates":[174.662521,-37.178825],"type":"Point"}
}