{
  "type": "Feature",
  "properties": {
    "addr:full":"106 Sunnybrae Rd Glenfield  Auckland Auckland",
    "addr:housenumber":"106",
    "addr:street":"Sunnybrae Rd",
    "iso:country":"NZ",
    "sg:address":"106 Sunnybrae Rd Glenfield ",
    "sg:city":"Auckland",
    "sg:classifiers":[
        {
            "category":"Retail",
            "subcategory":"Auto Repair",
            "type":"Services"
        }
    ],
    "sg:phone":"+64 9-441 4579",
    "sg:province":"Auckland",
    "sg:tags":[
        "automotive",
        "servicing"
    ],
    "sg:website":"http://www.yellowpages.co.nz/for/handyrentalsnorthshoreltd/dp22522.html",
    "wof:name":"Handy Rentals North Shore",
    "wof:placetype":"venue"
},
  "geometry": {"coordinates":[174.728622,-36.784813],"type":"Point"}
}