{
  "type": "Feature",
  "properties": {
    "addr:full":"E//13 Ride Way Albany  Auckland Auckland",
    "addr:housenumber":"13",
    "addr:street":"E / /;Ride Way",
    "iso:country":"NZ",
    "sg:address":"E//13 Ride Way Albany ",
    "sg:city":"Auckland",
    "sg:orig_category":"Transport: Distribution - General: Distributors",
    "sg:phone":"+64 9-415 5623",
    "sg:province":"Auckland",
    "wof:name":"BTT (NZ) LTD",
    "wof:placetype":"venue"
},
  "geometry": {"coordinates":[174.709686,-36.720142],"type":"Point"}
}