{
  "type": "Feature",
  "properties": {
    "addr:full":"18 Wickman Way Mangere  Auckland Auckland",
    "addr:housenumber":"18",
    "addr:street":"Wickman Way",
    "iso:country":"NZ",
    "sg:address":"18 Wickman Way Mangere ",
    "sg:city":"Auckland",
    "sg:orig_category":"Shopping: Retail Stores: Supermarkets",
    "sg:phone":"+64 9-275 7046",
    "sg:province":"Auckland",
    "wof:name":"Wickman Way Price Cutter",
    "wof:placetype":"venue"
},
  "geometry": {"coordinates":[174.81457499999999,-36.962833],"type":"Point"}
}