{
  "type": "Feature",
  "properties": {
    "addr:full":"106 Barbara Ave PO Box 6  Whangamata",
    "addr:housenumber":"106;6",
    "addr:street":"Barbara Ave Po Box",
    "iso:country":"NZ",
    "sg:address":"106 Barbara Ave PO Box 6 ",
    "sg:city":"Whangamata",
    "sg:classifiers":[
        {
            "category":"Travel",
            "subcategory":"Hotels & Motels",
            "type":"Entertainment"
        }
    ],
    "sg:phone":"+64 7-865 8250",
    "sg:tags":[
        "holiday",
        "tourism",
        "accommodation"
    ],
    "sg:website":"http://www.whangamatamotel.co.nz",
    "wof:name":"Whangamata Motel",
    "wof:placetype":"venue"
},
  "geometry": {"coordinates":[175.87124600000001,-37.211914],"type":"Point"}
}