{
  "type": "Feature",
  "properties": {
    "iso:country":"NZ",
    "sg:address":"11 Beach Rd ",
    "sg:city":"Paekakariki",
    "sg:orig_category":"Shopping: Retail Stores: Supermarkets",
    "sg:phone":"+64 4-292 8020",
    "wof:name":"Paekakariki Village Grocery Store",
    "wof:placetype":"venue"
},
  "geometry": {"coordinates":[174.951508,-40.988373],"type":"Point"}
}