{
  "type": "Feature",
  "properties": {
    "iso:country":"NZ",
    "sg:address":"Cnr Old North Rd & State Highway 16 Kumeu ",
    "sg:city":"Auckland",
    "sg:classifiers":[
        {
            "category":"Professional",
            "type":"Services"
        }
    ],
    "sg:phone":"+64 9-412 7206",
    "sg:province":"Auckland",
    "sg:tags":[
        "function",
        "entertainment",
        "leisure",
        "planning",
        "party",
        "sport"
    ],
    "sg:website":"http://www.allelyhouse.co.nz",
    "wof:name":"Allely House The Vineyard Restaurant & Bar",
    "wof:placetype":"venue"
},
  "geometry": {"coordinates":[174.56019599999999,-36.777271],"type":"Point"}
}