{
  "type": "Feature",
  "properties": {
    "iso:country":"NZ",
    "sg:address":"Far North Rd Awanui ",
    "sg:city":"Kaitaia",
    "sg:classifiers":[
        {
            "category":"Farming",
            "subcategory":"Farm & Veterinary Services",
            "type":"Manufacturing & Wholesale Goods"
        }
    ],
    "sg:phone":"+64 9-406 7793",
    "sg:province":"Northland",
    "sg:tags":[
        "supplies",
        "supply"
    ],
    "wof:name":"Mangonui Groundspread",
    "wof:placetype":"venue"
},
  "geometry": {"coordinates":[173.19210799999999,-34.978191],"type":"Point"}
}