{
  "type": "Feature",
  "properties": {
    "iso:country":"NZ",
    "sg:address":"59 D Morrin Rd Mt Wellington ",
    "sg:city":"Auckland",
    "sg:classifiers":[
        {
            "category":"Home & Garden",
            "subcategory":"Building Materials",
            "type":"Retail Goods"
        }
    ],
    "sg:phone":"+64 9-527 2310",
    "sg:province":"Auckland",
    "sg:tags":[
        "gate",
        "fitting",
        "outdoor"
    ],
    "wof:name":"Force Fabrications",
    "wof:placetype":"venue"
},
  "geometry": {"coordinates":[174.84985399999999,-36.888645],"type":"Point"}
}