{
  "type": "Feature",
  "properties": {
    "iso:country":"NZ",
    "sg:address":"29 Rewarewa Rd ",
    "sg:city":"Whangarei",
    "sg:orig_category":"Farming: Forestry: Logging Services",
    "sg:phone":"+64 9-430 0575",
    "sg:province":"Northland",
    "wof:name":"Paragon Haulage Limited",
    "wof:placetype":"venue"
},
  "geometry": {"coordinates":[174.313828,-35.752098],"type":"Point"}
}