{
  "type": "Feature",
  "properties": {
    "addr:full":"2/11 Tauhinu Rd Miramar  Wellington Wellington",
    "addr:housenumber":"2 / 11",
    "addr:street":"Tauhinu Rd",
    "iso:country":"NZ",
    "sg:address":"2/11 Tauhinu Rd Miramar ",
    "sg:city":"Wellington",
    "sg:classifiers":[
        {
            "category":"Home & Garden",
            "subcategory":"Building Materials",
            "type":"Retail Goods"
        }
    ],
    "sg:phone":"+64 4-388 8607",
    "sg:province":"Wellington",
    "sg:tags":[
        "fittings",
        "staircase",
        "handrail"
    ],
    "wof:name":"Te Aro Joinery Ltd",
    "wof:placetype":"venue"
},
  "geometry": {"coordinates":[174.81388899999999,-41.314194],"type":"Point"}
}