{
  "type": "Feature",
  "properties": {
    "addr:full":"Level 1 Dalmuir House 114 The Terrace  Wellington Waikato",
    "addr:housenumber":"level 1;114",
    "addr:street":"The Terrace",
    "iso:country":"NZ",
    "sg:address":"Level 1 Dalmuir House 114 The Terrace ",
    "sg:city":"Wellington",
    "sg:classifiers":[
        {
            "category":"Health Services",
            "subcategory":"Doctor",
            "type":"Services"
        }
    ],
    "sg:phone":"+64 800 800 157",
    "sg:province":"Waikato",
    "sg:tags":[
        "specialists",
        "surgery",
        "cosmetic",
        "beauty"
    ],
    "wof:name":"Cosmedic Clinic",
    "wof:placetype":"venue"
},
  "geometry": {"coordinates":[-87.68029799999999,40.537846],"type":"Point"}
}