{
  "type": "Feature",
  "properties": {
    "addr:full":"100 Hunt Rd  Whangamata",
    "addr:housenumber":"100",
    "addr:street":"Hunt Rd",
    "iso:country":"NZ",
    "sg:address":"100 Hunt Rd ",
    "sg:city":"Whangamata",
    "sg:classifiers":[
        {
            "category":"Travel",
            "subcategory":"Hotels & Motels",
            "type":"Entertainment"
        }
    ],
    "sg:phone":"+64 7-865 7040",
    "sg:tags":[
        "tourism",
        "-",
        "rental",
        "accommodation"
    ],
    "wof:name":"Luck At Last Restaurant & Bar",
    "wof:placetype":"venue"
},
  "geometry": {"coordinates":[175.87428299999999,-37.204075],"type":"Point"}
}