{
  "type": "Feature",
  "properties": {
    "addr:full":"PO Box 58-031 Whitby  Wellington Wellington",
    "addr:housenumber":"po box",
    "addr:street":"58-031",
    "iso:country":"NZ",
    "sg:address":"PO Box 58-031 Whitby ",
    "sg:city":"Wellington",
    "sg:classifiers":[
        {
            "category":"Shopping",
            "subcategory":"Stationery & Office Supplies",
            "type":"Retail Goods"
        }
    ],
    "sg:phone":"+64 4-234 7832",
    "sg:province":"Wellington",
    "sg:tags":[
        "map",
        "chart"
    ],
    "wof:name":"Explorer Graphics Ltd",
    "wof:placetype":"venue"
},
  "geometry": {"coordinates":[174.88902300000001,-41.111603],"type":"Point"}
}