{
  "type": "Feature",
  "properties": {
    "addr:full":"1224 Fenton St  Rotorua Bay of Plenty",
    "addr:housenumber":"1224",
    "addr:street":"Fenton St",
    "iso:country":"NZ",
    "sg:address":"1224 Fenton St ",
    "sg:city":"Rotorua",
    "sg:classifiers":[
        {
            "category":"Sports & Exercise",
            "subcategory":"Tennis Court",
            "type":"Entertainment"
        }
    ],
    "sg:phone":"+64 7-347 7701",
    "sg:province":"Bay of Plenty",
    "sg:tags":[
        "escort",
        "agency",
        "adult",
        "leisure"
    ],
    "wof:name":"Bobby-Lee's Massage",
    "wof:placetype":"venue"
},
  "geometry": {"coordinates":[176.25401299999999,-38.137142],"type":"Point"}
}