{
  "type": "Feature",
  "properties": {
    "iso:country":"NZ",
    "sg:address":"Cracroft St ",
    "sg:city":"Waitara",
    "sg:orig_category":"Education And Training: General: Schools",
    "sg:phone":"+64 6-754 7716",
    "wof:name":"Waitara Central School",
    "wof:placetype":"venue"
},
  "geometry": {"coordinates":[174.231155,-39.002483],"type":"Point"}
}