{
  "type": "Feature",
  "properties": {
    "addr:full":"33 Knighton Rd Hillcrest  Hamilton Waikato",
    "addr:housenumber":"33",
    "addr:street":"Knighton Rd",
    "iso:country":"NZ",
    "sg:address":"33 Knighton Rd Hillcrest ",
    "sg:city":"Hamilton",
    "sg:classifiers":[
        {
            "category":"Building & Trades",
            "subcategory":"Construction",
            "type":"Services"
        }
    ],
    "sg:phone":"+64 7-856 4411",
    "sg:province":"Waikato",
    "sg:tags":[
        "home",
        "garden",
        "related",
        "plasterer"
    ],
    "wof:name":"Lyn Ashton",
    "wof:placetype":"venue"
},
  "geometry": {"coordinates":[175.311508,-37.795254],"type":"Point"}
}