{
  "type": "Feature",
  "properties": {
    "addr:full":"14 Ranier St Ellerslie  Auckland Auckland",
    "addr:housenumber":"14",
    "addr:street":"Ranier St",
    "iso:country":"NZ",
    "sg:address":"14 Ranier St Ellerslie ",
    "sg:city":"Auckland",
    "sg:orig_category":"Industrial: Engineering: Engineers - Steam",
    "sg:phone":"+64 9-579 5607",
    "sg:province":"Auckland",
    "wof:name":"Mattson W Ltd",
    "wof:placetype":"venue"
},
  "geometry": {"coordinates":[174.819061,-36.900387],"type":"Point"}
}