{
  "type": "Feature",
  "properties": {
    "addr:full":"290 Karangahape Rd Newton  Auckland Auckland",
    "addr:housenumber":"290",
    "addr:street":"Karangahape Rd",
    "iso:country":"NZ",
    "sg:address":"290 Karangahape Rd Newton ",
    "sg:city":"Auckland",
    "sg:classifiers":[
        {
            "category":"Bars & Pubs",
            "subcategory":"Lounge",
            "type":"Food & Drink"
        }
    ],
    "sg:phone":"+64 9-373 2299",
    "sg:province":"Auckland",
    "sg:tags":[
        "-",
        "asian"
    ],
    "wof:name":"Gans Asian Foods",
    "wof:placetype":"venue"
},
  "geometry": {"coordinates":[174.75817900000001,-36.857738],"type":"Point"}
}