{
  "type": "Feature",
  "properties": {
    "iso:country":"NZ",
    "sg:address":"82 a Ellice Rd Glenfield ",
    "sg:city":"Auckland",
    "sg:classifiers":[
        {
            "category":"Health Services",
            "subcategory":"Hospital",
            "type":"Services"
        }
    ],
    "sg:phone":"+64 9-444 3078",
    "sg:province":"Auckland",
    "sg:tags":[
        "beauty",
        "fitness"
    ],
    "wof:name":"World Gym",
    "wof:placetype":"venue"
},
  "geometry": {"coordinates":[174.728622,-36.784813],"type":"Point"}
}