{
  "type": "Feature",
  "properties": {
    "addr:full":"Wainoni Rd  Christchurch Canterbury",
    "addr:street":"Wainoni Rd",
    "iso:country":"NZ",
    "sg:address":"Wainoni Rd ",
    "sg:city":"Christchurch",
    "sg:orig_category":"Sports And Leisure: Sports: Golf: Golf Courses",
    "sg:phone":"+64 3-388 2675",
    "sg:province":"Canterbury",
    "wof:name":"Avondale Golf Club Inc",
    "wof:placetype":"venue"
},
  "geometry": {"coordinates":[172.68995699999999,-43.520218],"type":"Point"}
}