{
  "type": "Feature",
  "properties": {
    "addr:full":"5 High St Auckland Central  Auckland Auckland",
    "addr:housenumber":"5",
    "addr:street":"High St",
    "iso:country":"NZ",
    "sg:address":"5 High St Auckland Central ",
    "sg:city":"Auckland",
    "sg:orig_category":"Clothing And Fabric: Clothing: Women'S Fashions",
    "sg:phone":"+64 9-366 4528",
    "sg:province":"Auckland",
    "wof:name":"Fabric",
    "wof:placetype":"venue"
},
  "geometry": {"coordinates":[174.766876,-36.846558],"type":"Point"}
}