{
  "type": "Feature",
  "properties": {
    "iso:country":"NZ",
    "sg:address":"State Highway 1 ",
    "sg:city":"Tokoroa",
    "sg:orig_category":"Automotive: General Services: Service Stations",
    "sg:phone":"+64 7-886 8039",
    "wof:name":"BP Oil",
    "wof:placetype":"venue"
},
  "geometry": {"coordinates":[175.87930299999999,-38.232109],"type":"Point"}
}