{
  "type": "Feature",
  "properties": {
    "iso:country":"NZ",
    "sg:address":"4/28 Porana Rd Takapuna ",
    "sg:city":"Auckland",
    "sg:classifiers":[
        {
            "category":"Home & Garden",
            "subcategory":"Furniture",
            "type":"Retail Goods"
        }
    ],
    "sg:phone":"+64 9-444 9473",
    "sg:province":"Auckland",
    "sg:tags":[
        "furniture/furnishings",
        "repair",
        "finishing"
    ],
    "wof:name":"Ballantyne R (French Polisher)",
    "wof:placetype":"venue"
},
  "geometry": {"coordinates":[174.767883,-36.787838],"type":"Point"}
}