{
  "type": "Feature",
  "properties": {
    "iso:country":"NZ",
    "sg:address":"7 Shakespeare Rd Waltham ",
    "sg:city":"Christchurch",
    "sg:classifiers":[
        {
            "category":"Restaurant",
            "type":"Food & Drink"
        }
    ],
    "sg:phone":"+64 3-366 0576",
    "sg:province":"Canterbury",
    "sg:tags":[
        "merchant",
        "fish",
        "sea"
    ],
    "wof:name":"Psarobazaro The",
    "wof:placetype":"venue"
},
  "geometry": {"coordinates":[172.647491,-43.544975],"type":"Point"}
}