{
  "type": "Feature",
  "properties": {
    "addr:full":"Upper  Hutt Wellington",
    "iso:country":"NZ",
    "sg:address":"Upper ",
    "sg:city":"Hutt",
    "sg:classifiers":[
        {
            "category":"Home & Garden",
            "subcategory":"Home Furnishings",
            "type":"Retail Goods"
        }
    ],
    "sg:phone":"+64 800 866 688",
    "sg:province":"Wellington",
    "sg:tags":[
        "accessory"
    ],
    "wof:name":"Aurora Candles NZ Ltd",
    "wof:placetype":"venue"
},
  "geometry": {"coordinates":[175.069031,-41.12458],"type":"Point"}
}