{
  "type": "Feature",
  "properties": {
    "iso:country":"NZ",
    "sg:address":"11 Moturoa St New ",
    "sg:city":"Plymouth",
    "sg:orig_category":"Automotive: General Services: Rental Vehicles",
    "sg:phone":"+64 6-757 5757",
    "sg:province":"Taranaki",
    "wof:name":"Cross Country Rentals (LNI) Ltd",
    "wof:placetype":"venue"
},
  "geometry": {"coordinates":[174.034988,-39.0625],"type":"Point"}
}