{
  "type": "Feature",
  "properties": {
    "iso:country":"NZ",
    "sg:address":"92 Riri St ",
    "sg:city":"Rotorua",
    "sg:orig_category":"Industrial: Parts: Bearings",
    "sg:phone":"+64 7-349 2613",
    "sg:province":"Bay of Plenty",
    "wof:name":"Farrell Bearings Ltd",
    "wof:placetype":"venue"
},
  "geometry": {"coordinates":[176.228302,-38.133316],"type":"Point"}
}