{
  "type": "Feature",
  "properties": {
    "iso:country":"NZ",
    "sg:address":"Cain St ",
    "sg:city":"Timaru",
    "sg:orig_category":"Education And Training: General: Schools",
    "sg:phone":"+64 3-688 1122",
    "sg:province":"Canterbury",
    "wof:name":"Timaru Girls High School",
    "wof:placetype":"venue"
},
  "geometry": {"coordinates":[171.249207,-44.411327],"type":"Point"}
}