{
  "type": "Feature",
  "properties": {
    "addr:full":"53 Mackay St  Greymouth West Coast",
    "addr:housenumber":"53",
    "addr:street":"Mackay St",
    "iso:country":"NZ",
    "sg:address":"53 Mackay St ",
    "sg:city":"Greymouth",
    "sg:orig_category":"Shopping: Sports Retailers: Sports Goods",
    "sg:phone":"+64 3-768 4060",
    "sg:province":"West Coast",
    "wof:name":"Coll Sports World",
    "wof:placetype":"venue"
},
  "geometry": {"coordinates":[171.20953399999999,-42.448582],"type":"Point"}
}