{
  "type": "Feature",
  "properties": {
    "iso:country":"NZ",
    "sg:address":"50 Bryson Rd Otatara ",
    "sg:city":"Invercargill",
    "sg:orig_category":"Home And Garden: Gardening: Services: Lawnmowing Services",
    "sg:phone":"+64 3-214 0774",
    "sg:province":"Southland",
    "wof:name":"Green Acres Lawnmowing",
    "wof:placetype":"venue"
},
  "geometry": {"coordinates":[168.314819,-46.442268],"type":"Point"}
}