{
  "type": "Feature",
  "properties": {
    "iso:country":"NZ",
    "sg:address":"12 Puketapu Rd Taradale ",
    "sg:city":"Napier",
    "sg:classifiers":[
        {
            "category":"Retail",
            "subcategory":"Auto Repair",
            "type":"Services"
        }
    ],
    "sg:phone":"+64 6-844 0551",
    "sg:province":"Hawke's Bay",
    "sg:tags":[
        "automotive",
        "electric",
        "servicing"
    ],
    "wof:name":"Arrow Auto Electrix & Alarms",
    "wof:placetype":"venue"
},
  "geometry": {"coordinates":[176.846741,-39.537064],"type":"Point"}
}