{
  "type": "Feature",
  "properties": {
    "iso:country":"NZ",
    "sg:address":"14 A Yardley St Avonhead ",
    "sg:city":"Christchurch",
    "sg:orig_category":"Health And Beauty: Beauty: Manicurists",
    "sg:phone":"+64 3-342 3949",
    "sg:province":"Canterbury",
    "wof:name":"NZ Nail Institute Ltd",
    "wof:placetype":"venue"
},
  "geometry": {"coordinates":[172.545761,-43.519779],"type":"Point"}
}