{
  "type": "Feature",
  "properties": {
    "iso:country":"NZ",
    "sg:address":"272 Parnell Rd Parnell ",
    "sg:city":"Auckland",
    "sg:orig_category":"Transport: Boats And Marine: Shipping: Shipping Companies",
    "sg:phone":"+64 9-309 2415",
    "sg:province":"Auckland",
    "sg:website":"http://www.freightraders.co.nz",
    "wof:name":"Freight Traders Ltd",
    "wof:placetype":"venue"
},
  "geometry": {"coordinates":[174.78105199999999,-36.85619],"type":"Point"}
}