{
  "type": "Feature",
  "properties": {
    "iso:country":"NZ",
    "sg:address":"Manuka St ",
    "sg:city":"Taupo",
    "sg:orig_category":"Storage: Storage",
    "sg:phone":"+64 7-378 5363",
    "sg:province":"Waikato",
    "wof:name":"Central Moving & Storage",
    "wof:placetype":"venue"
},
  "geometry": {"coordinates":[176.10745199999999,-38.689674],"type":"Point"}
}