{
  "type": "Feature",
  "properties": {
    "addr:full":"718 Dominion Rd Balmoral  Auckland Auckland",
    "addr:housenumber":"718",
    "addr:street":"Dominion Rd",
    "iso:country":"NZ",
    "sg:address":"718 Dominion Rd Balmoral ",
    "sg:city":"Auckland",
    "sg:classifiers":[
        {
            "category":"Professional",
            "subcategory":"Management & Consulting",
            "type":"Services"
        }
    ],
    "sg:phone":"+64 9-638 7525",
    "sg:province":"Auckland",
    "sg:tags":[
        "consultant",
        "training",
        "education"
    ],
    "wof:name":"Bridge Education NZ Ltd",
    "wof:placetype":"venue"
},
  "geometry": {"coordinates":[174.747467,-36.886997],"type":"Point"}
}