{
  "type": "Feature",
  "properties": {
    "addr:full":"Braemar Lauriston Rd R D 6 Ashburton  Winchmore",
    "addr:housenumber":"6",
    "addr:street":"Braemar Lauriston Rd R D",
    "iso:country":"NZ",
    "sg:address":"Braemar Lauriston Rd R D 6 Ashburton ",
    "sg:city":"Winchmore",
    "sg:orig_category":"Farming: Agriculture: Agricultural Contractors",
    "sg:phone":"+64 3-302 4897",
    "wof:name":"Watson Contracting",
    "wof:placetype":"venue"
},
  "geometry": {"coordinates":[171.75379899999999,-43.896198],"type":"Point"}
}