{
  "type": "Feature",
  "properties": {
    "iso:country":"NZ",
    "sg:address":"9 A Dearsley St Linwood ",
    "sg:city":"Christchurch",
    "sg:classifiers":[
        {
            "category":"Bars & Pubs",
            "subcategory":"Lounge",
            "type":"Food & Drink"
        }
    ],
    "sg:phone":"+64 3-389 8519",
    "sg:province":"Canterbury",
    "sg:tags":[
        "baker",
        "-"
    ],
    "wof:name":"I.B Gourmet Pies",
    "wof:placetype":"venue"
},
  "geometry": {"coordinates":[172.66214,-43.53146],"type":"Point"}
}