{
  "type": "Feature",
  "properties": {
    "addr:full":"276 Henwood Rd RD 2 New  Plymouth Taranaki",
    "addr:housenumber":"276;2",
    "addr:street":"Henwood Rd Rd",
    "iso:country":"NZ",
    "sg:address":"276 Henwood Rd RD 2 New ",
    "sg:city":"Plymouth",
    "sg:classifiers":[
        {
            "category":"Building & Trades",
            "subcategory":"Plumbing",
            "type":"Services"
        }
    ],
    "sg:phone":"+64 6-755 1272",
    "sg:province":"Taranaki",
    "sg:tags":[
        "home",
        "plumber",
        "garden",
        "related"
    ],
    "wof:name":"Bill Crowe Plumbing Ltd",
    "wof:placetype":"venue"
},
  "geometry": {"coordinates":[-86.31512499999999,41.341209],"type":"Point"}
}