{
  "type": "Feature",
  "properties": {
    "addr:full":"153 Rangitikei St Palmerston  Palmerston North Manawatu-Wanganui",
    "addr:housenumber":"153",
    "addr:street":"Rangitikei St Palmerston",
    "iso:country":"NZ",
    "sg:address":"153 Rangitikei St Palmerston ",
    "sg:city":"Palmerston North",
    "sg:classifiers":[
        {
            "category":"Personal",
            "subcategory":"Beauty Salon",
            "type":"Services"
        }
    ],
    "sg:phone":"+64 6-358 1203",
    "sg:province":"Manawatu-Wanganui",
    "sg:tags":[
        "incontinence",
        "product",
        "health",
        "products"
    ],
    "wof:name":"Manawatu Home Healthcare & Mobility Centre",
    "wof:placetype":"venue"
},
  "geometry": {"coordinates":[175.59466599999999,-40.337257],"type":"Point"}
}