{
  "type": "Feature",
  "properties": {
    "iso:country":"NZ",
    "sg:address":"99 Clarence St Riccarton ",
    "sg:city":"Christchurch",
    "sg:orig_category":"Shopping: Accessories: Accessories - Clothing",
    "sg:phone":"+64 3-348 4434",
    "sg:province":"Canterbury",
    "wof:name":"Peers W & Co Ltd",
    "wof:placetype":"venue"
},
  "geometry": {"coordinates":[172.603394,-43.537586],"type":"Point"}
}