{
  "type": "Feature",
  "properties": {
    "addr:full":"9 Terrelle St North New Brighton  Christchurch Canterbury",
    "addr:housenumber":"9",
    "addr:street":"Terrelle St",
    "iso:country":"NZ",
    "sg:address":"9 Terrelle St North New Brighton ",
    "sg:city":"Christchurch",
    "sg:classifiers":[
        {
            "category":"Food & Beverages",
            "subcategory":"Bakery",
            "type":"Retail Goods"
        }
    ],
    "sg:phone":"+64 3-382 0308",
    "sg:province":"Canterbury",
    "sg:tags":[
        "shop",
        "cake",
        "drink",
        "-"
    ],
    "wof:name":"Creative Home Cake Decorating",
    "wof:placetype":"venue"
},
  "geometry": {"coordinates":[172.707367,-43.499718],"type":"Point"}
}