{
  "type": "Feature",
  "properties": {
    "addr:full":"17 Clarence St Devonport  Auckland Auckland",
    "addr:housenumber":"17",
    "addr:street":"Clarence St",
    "iso:country":"NZ",
    "sg:address":"17 Clarence St Devonport ",
    "sg:city":"Auckland",
    "sg:orig_category":"Health And Beauty: Health Services: Naturopathy",
    "sg:phone":"+64 9-446 3131",
    "sg:province":"Auckland",
    "wof:name":"Jarvis Health",
    "wof:placetype":"venue"
},
  "geometry": {"coordinates":[174.79628,-36.830402],"type":"Point"}
}