{
  "type": "Feature",
  "properties": {
    "iso:country":"NZ",
    "sg:address":"27 Mersey St ",
    "sg:city":"Invercargill",
    "sg:classifiers":[
        {
            "category":"Professional",
            "subcategory":"Detective & Security Services",
            "type":"Services"
        }
    ],
    "sg:phone":"+64 3-214 1235",
    "sg:province":"Southland",
    "sg:tags":[
        "services",
        "automotive",
        "warrant",
        "fitness"
    ],
    "wof:name":"Vehicle Testing NZ Ltd",
    "wof:placetype":"venue"
},
  "geometry": {"coordinates":[168.34201,-46.407234],"type":"Point"}
}