{
  "type": "Feature",
  "properties": {
    "iso:country":"NZ",
    "sg:address":"Level 1 15 Walter St ",
    "sg:city":"Wellington",
    "sg:classifiers":[
        {
            "category":"Manufacturing",
            "subcategory":"Textiles",
            "type":"Manufacturing & Wholesale Goods"
        }
    ],
    "sg:phone":"+64 4-499 3370",
    "sg:province":"Wellington",
    "sg:tags":[
        "clothing",
        "fabric",
        "manufacturer"
    ],
    "wof:name":"Tiffany Jane Fashions Ltd",
    "wof:placetype":"venue"
},
  "geometry": {"coordinates":[-87.683342,40.539139],"type":"Point"}
}