{
  "type": "Feature",
  "properties": {
    "iso:country":"NZ",
    "sg:address":"General Enquiries ",
    "sg:city":"Whangarei",
    "sg:classifiers":[
        {
            "category":"Building & Trades",
            "subcategory":"Landscaping Services",
            "type":"Services"
        }
    ],
    "sg:phone":"+64 800 800 021",
    "sg:province":"Northland",
    "sg:tags":[
        "personal",
        "home",
        "garden"
    ],
    "sg:website":"http://www.vodafone.co.nz",
    "wof:name":"Vodafone New Zealand Limited",
    "wof:placetype":"venue"
},
  "geometry": {"coordinates":[174.320526,-35.725399],"type":"Point"}
}