{
  "type": "Feature",
  "properties": {
    "iso:country":"NZ",
    "sg:address":"13 Thames St ",
    "sg:city":"Riverton",
    "sg:classifiers":[
        {
            "category":"Manufacturing",
            "subcategory":"Glass & Minerals",
            "type":"Manufacturing & Wholesale Goods"
        }
    ],
    "sg:phone":"+64 256086410",
    "sg:tags":[
        "chemical",
        "fibre",
        "industrial",
        "compounds"
    ],
    "wof:name":"Cory Ward Boat Builder",
    "wof:placetype":"venue"
},
  "geometry": {"coordinates":[-73.025848,41.957958],"type":"Point"}
}