{
  "type": "Feature",
  "properties": {
    "iso:country":"NZ",
    "sg:address":"Otahuhu ",
    "sg:city":"Auckland",
    "sg:classifiers":[
        {
            "category":"Wholesale",
            "subcategory":"Auto Parts",
            "type":"Manufacturing & Wholesale Goods"
        }
    ],
    "sg:phone":"+64 9-276 0410",
    "sg:province":"Auckland",
    "sg:tags":[
        "automotive",
        "supply"
    ],
    "sg:website":"http://www.licensys.com",
    "wof:name":"Licensys NZ Limited",
    "wof:placetype":"venue"
},
  "geometry": {"coordinates":[174.844604,-36.943748],"type":"Point"}
}