{
  "type": "Feature",
  "properties": {
    "addr:full":"9 Park Rd Waiheke  Island",
    "addr:housenumber":"9",
    "addr:street":"Park Rd",
    "iso:country":"NZ",
    "sg:address":"9 Park Rd Waiheke ",
    "sg:city":"Island",
    "sg:classifiers":[
        {
            "category":"Personal",
            "subcategory":"Piercing",
            "type":"Services"
        }
    ],
    "sg:phone":"+64 9-372 3037",
    "sg:tags":[
        "body",
        "ear",
        "health",
        "nose",
        "beauty"
    ],
    "sg:website":"http://www.parkroadclinic.co.nz",
    "wof:name":"Park Road Ocean Clinic",
    "wof:placetype":"venue"
},
  "geometry": {"coordinates":[175.026093,-36.788338],"type":"Point"}
}