{
  "type": "Feature",
  "properties": {
    "iso:country":"NZ",
    "sg:address":"43 a Seven Mile Rd ",
    "sg:city":"Runanga",
    "sg:classifiers":[
        {
            "category":"Food & Beverages",
            "subcategory":"Liquor & Beverages",
            "type":"Retail Goods"
        }
    ],
    "sg:phone":"+64 3-762 7764",
    "sg:tags":[
        "drink",
        "outlet"
    ],
    "wof:name":"Runanga Discount Bottle Store",
    "wof:placetype":"venue"
},
  "geometry": {"coordinates":[171.246262,-42.402477],"type":"Point"}
}