{
  "type": "Feature",
  "properties": {
    "addr:full":"14 Ross Reid Pl East Tamaki  Auckland Auckland",
    "addr:housenumber":"14",
    "addr:street":"Ross Reid Pl",
    "iso:country":"NZ",
    "sg:address":"14 Ross Reid Pl East Tamaki ",
    "sg:city":"Auckland",
    "sg:orig_category":"Industrial: Services: Specialist Services: Electroplating/Polishing",
    "sg:phone":"+64 9-274 4308",
    "sg:province":"Auckland",
    "wof:name":"Metal Protection Ltd",
    "wof:placetype":"venue"
},
  "geometry": {"coordinates":[174.88647499999999,-36.942211],"type":"Point"}
}