{
  "type": "Feature",
  "properties": {
    "addr:full":"22 Station Rd Otahuhu  Auckland Auckland",
    "addr:housenumber":"22",
    "addr:street":"Station Rd",
    "iso:country":"NZ",
    "sg:address":"22 Station Rd Otahuhu ",
    "sg:city":"Auckland",
    "sg:orig_category":"Clothing And Fabric: Clothing: Dressmakers",
    "sg:phone":"+64 9-270 2167",
    "sg:province":"Auckland",
    "wof:name":"Rose Creations",
    "wof:placetype":"venue"
},
  "geometry": {"coordinates":[174.84082000000001,-36.942757],"type":"Point"}
}