{
  "type": "Feature",
  "properties": {
    "addr:full":"11 Brett Ave Papatoetoe  Auckland Auckland",
    "addr:housenumber":"11",
    "addr:street":"Brett Ave",
    "iso:country":"NZ",
    "sg:address":"11 Brett Ave Papatoetoe ",
    "sg:city":"Auckland",
    "sg:classifiers":[
        {
            "category":"Building & Trades",
            "subcategory":"Electrical",
            "type":"Services"
        }
    ],
    "sg:phone":"+64 9-278 3300",
    "sg:province":"Auckland",
    "sg:tags":[
        "industrial",
        "refrigeration"
    ],
    "wof:name":"Shannon Refrigeration Services",
    "wof:placetype":"venue"
},
  "geometry": {"coordinates":[174.86715699999999,-36.971188],"type":"Point"}
}