{
  "type": "Feature",
  "properties": {
    "iso:country":"NZ",
    "sg:address":"11 Te Apunga Pl Mt Wellington ",
    "sg:city":"Auckland",
    "sg:orig_category":"Industrial: Instruments: Industrial Instruments",
    "sg:phone":"+64 9-270 0100",
    "sg:province":"Auckland",
    "wof:name":"W Arthur Fisher Ltd",
    "wof:placetype":"venue"
},
  "geometry": {"coordinates":[174.85022,-36.92445],"type":"Point"}
}