{
  "type": "Feature",
  "properties": {
    "iso:country":"NZ",
    "sg:address":"Level 3 200 Cashel Street ",
    "sg:city":"Christchurch",
    "sg:classifiers":[
        {
            "category":"Real Estate",
            "subcategory":"Real Estate Services",
            "type":"Services"
        }
    ],
    "sg:phone":"+64 3-963 5780",
    "sg:province":"Canterbury",
    "sg:tags":[
        "home",
        "garden"
    ],
    "sg:website":"http://www.aahousechecks.co.nz",
    "wof:name":"AA House Checks - Canterbury",
    "wof:placetype":"venue"
},
  "geometry": {"coordinates":[-76.537834,37.605659],"type":"Point"}
}