{
  "type": "Feature",
  "properties": {
    "iso:country":"NZ",
    "sg:address":"143 a King St ",
    "sg:city":"Timaru",
    "sg:orig_category":"Industrial: Abrasives: Water Blasting",
    "sg:phone":"+64 3-684 5196",
    "sg:province":"Canterbury",
    "wof:name":"Jenkins Wallace & Co",
    "wof:placetype":"venue"
},
  "geometry": {"coordinates":[171.247437,-44.414444],"type":"Point"}
}