{
  "type": "Feature",
  "properties": {
    "addr:full":"79 Beach Rd  Kaikoura",
    "addr:housenumber":"79",
    "addr:street":"Beach Rd",
    "iso:country":"NZ",
    "sg:address":"79 Beach Rd ",
    "sg:city":"Kaikoura",
    "sg:classifiers":[
        {
            "category":"Retail",
            "subcategory":"Auto Repair",
            "type":"Services"
        }
    ],
    "sg:phone":"+64 3-319 5750",
    "sg:tags":[
        "automotive",
        "electric",
        "servicing"
    ],
    "wof:name":"Kaikoura Auto Electric",
    "wof:placetype":"venue"
},
  "geometry": {"coordinates":[173.67919900000001,-42.391628],"type":"Point"}
}