{
  "type": "Feature",
  "properties": {
    "iso:country":"NZ",
    "sg:address":"3 Mallard Pl Mosgiel ",
    "sg:city":"Dunedin",
    "sg:classifiers":[
        {
            "category":"Home & Garden",
            "subcategory":"Building Materials",
            "type":"Retail Goods"
        }
    ],
    "sg:phone":"+64 3-489 4462",
    "sg:province":"Otago",
    "sg:tags":[
        "brick",
        "outdoor",
        "paving"
    ],
    "wof:name":"Jeff Wilson Paving",
    "wof:placetype":"venue"
},
  "geometry": {"coordinates":[170.33363299999999,-45.875935],"type":"Point"}
}