{
  "type": "Feature",
  "properties": {
    "iso:country":"NZ",
    "sg:address":"90 Main North Rd Westshore ",
    "sg:city":"Napier",
    "sg:classifiers":[
        {
            "category":"Travel",
            "subcategory":"Bed & Breakfast",
            "type":"Entertainment"
        }
    ],
    "sg:phone":"+64 6-835 6490",
    "sg:province":"Hawke's Bay",
    "sg:tags":[
        "tourism",
        "accommodation"
    ],
    "wof:name":"Airport Gardens Bed & Breakfast",
    "wof:placetype":"venue"
},
  "geometry": {"coordinates":[176.87574799999999,-39.468582],"type":"Point"}
}