{
  "type": "Feature",
  "properties": {
    "iso:country":"NZ",
    "sg:address":"R D 3 Sandy Bay ",
    "sg:city":"Whangarei",
    "sg:classifiers":[
        {
            "category":"Travel",
            "subcategory":"Travel Agent",
            "type":"Entertainment"
        }
    ],
    "sg:phone":"+64 9-434 3443",
    "sg:province":"Northland",
    "sg:tags":[
        "tour",
        "tourism",
        "adventure",
        "sightseeing"
    ],
    "wof:name":"Surf & Adventure New Zealand",
    "wof:placetype":"venue"
},
  "geometry": {"coordinates":[174.320526,-35.725399],"type":"Point"}
}