{
  "type": "Feature",
  "properties": {
    "addr:full":"30 Belmont Rd  Paeroa",
    "addr:housenumber":"30",
    "addr:street":"Belmont Rd",
    "iso:country":"NZ",
    "sg:address":"30 Belmont Rd ",
    "sg:city":"Paeroa",
    "sg:classifiers":[
        {
            "category":"Shopping",
            "subcategory":"Bicycles & Sporting Goods",
            "type":"Retail Goods"
        }
    ],
    "sg:phone":"+64 7-862 7061",
    "sg:tags":[
        "cycle",
        "sport",
        "sale",
        "retailers",
        "cycles"
    ],
    "wof:name":"Paeroa Marine & Cycle Centre Ltd",
    "wof:placetype":"venue"
},
  "geometry": {"coordinates":[175.667877,-37.376759],"type":"Point"}
}