{
  "type": "Feature",
  "properties": {
    "addr:full":"10 Albert St  Rangiora Canterbury",
    "addr:housenumber":"10",
    "addr:street":"Albert St",
    "iso:country":"NZ",
    "sg:address":"10 Albert St ",
    "sg:city":"Rangiora",
    "sg:orig_category":"Transport: Boats And Marine: Products: Outboard Motors",
    "sg:phone":"+64 3-313 4593",
    "sg:province":"Canterbury",
    "wof:name":"Rangiora Motorcycles Ltd",
    "wof:placetype":"venue"
},
  "geometry": {"coordinates":[172.59742700000001,-43.302486],"type":"Point"}
}