{
  "type": "Feature",
  "properties": {
    "addr:full":"203 Lincoln Rd Henderson  Auckland Auckland",
    "addr:housenumber":"203",
    "addr:street":"Lincoln Rd",
    "iso:country":"NZ",
    "sg:address":"203 Lincoln Rd Henderson ",
    "sg:city":"Auckland",
    "sg:classifiers":[
        {
            "category":"Recreation",
            "type":"Entertainment"
        }
    ],
    "sg:phone":"+64 9-836 0440",
    "sg:province":"Auckland",
    "sg:tags":[
        "sport",
        "leisure"
    ],
    "sg:website":"http://www.yellowpages.co.nz/for/bartonmcgillltd/dp339.html",
    "wof:name":"Barton McGill Limited",
    "wof:placetype":"venue"
},
  "geometry": {"coordinates":[174.62823499999999,-36.870419],"type":"Point"}
}