{
  "type": "Feature",
  "properties": {
    "iso:country":"NZ",
    "sg:address":"Unit F 5 Lorien Pl East Tamaki ",
    "sg:city":"Auckland",
    "sg:classifiers":[
        {
            "category":"Shopping",
            "subcategory":"Crafts & Fabrics",
            "type":"Retail Goods"
        }
    ],
    "sg:phone":"+64 9-272 8507",
    "sg:province":"Auckland",
    "sg:tags":[
        "clothing",
        "elastic",
        "manufacturer"
    ],
    "wof:name":"Webbing & Trimming (NZ) Ltd",
    "wof:placetype":"venue"
},
  "geometry": {"coordinates":[174.861771,-36.891823],"type":"Point"}
}