{
  "type": "Feature",
  "properties": {
    "iso:country":"NZ",
    "sg:address":"Unit 1 Beach Rd Waikawa Bay ",
    "sg:city":"Picton",
    "sg:orig_category":"Industrial: Engineering: Engineers: Engineers - General",
    "sg:phone":"+64 3-573 8953",
    "sg:province":"Marlborough",
    "wof:name":"Waikawa Engineering Ltd",
    "wof:placetype":"venue"
},
  "geometry": {"coordinates":[174.034088,-41.271091],"type":"Point"}
}