{
  "type": "Feature",
  "properties": {
    "iso:country":"NZ",
    "sg:address":"27 Beach Rd Auckland Central ",
    "sg:city":"Auckland",
    "sg:orig_category":"Automotive: Parts And Supplies: Tyres",
    "sg:phone":"+64 9-377 6648",
    "sg:province":"Auckland",
    "wof:name":"Pits/ Pneumatico Performance Tyre Shop",
    "wof:placetype":"venue"
},
  "geometry": {"coordinates":[174.772079,-36.846046],"type":"Point"}
}