{
  "type": "Feature",
  "properties": {
    "iso:country":"NZ",
    "sg:address":"7/298 Neilson St Onehunga ",
    "sg:city":"Auckland",
    "sg:orig_category":"Industrial: Engineering: Engineers - Manufacturing",
    "sg:phone":"+64 9-636 0962",
    "sg:province":"Auckland",
    "wof:name":"Switec Engineering Limited",
    "wof:placetype":"venue"
},
  "geometry": {"coordinates":[174.792572,-36.9263],"type":"Point"}
}