{
  "type": "Feature",
  "properties": {
    "addr:full":"45 Cameron St  Whangarei Northland",
    "addr:housenumber":"45",
    "addr:street":"Cameron St",
    "iso:country":"NZ",
    "sg:address":"45 Cameron St ",
    "sg:city":"Whangarei",
    "sg:orig_category":"Clothing And Fabric: Clothing: Menswear",
    "sg:phone":"+64 9-438 1616",
    "sg:province":"Northland",
    "wof:name":"Hallensteins",
    "wof:placetype":"venue"
},
  "geometry": {"coordinates":[174.32101399999999,-35.725941],"type":"Point"}
}