{
  "type": "Feature",
  "properties": {
    "addr:full":"25-31 Elizabeth Knox Pl Panmure  Auckland Auckland",
    "addr:housenumber":"25-31",
    "addr:street":"Elizabeth Knox Pl",
    "iso:country":"NZ",
    "sg:address":"25-31 Elizabeth Knox Pl Panmure ",
    "sg:city":"Auckland",
    "sg:classifiers":[
        {
            "category":"Restaurant",
            "type":"Food & Drink"
        }
    ],
    "sg:phone":"+64 9-570 4805",
    "sg:province":"Auckland",
    "sg:tags":[
        "equipment",
        "machinery"
    ],
    "wof:name":"Millbank Technology (NZ) Ltd",
    "wof:placetype":"venue"
},
  "geometry": {"coordinates":[174.85749799999999,-36.90181],"type":"Point"}
}