{
  "type": "Feature",
  "properties": {
    "addr:full":"19 - 25 Taonui St Palmerston  Palmerston North Manawatu-Wanganui",
    "addr:housenumber":"25",
    "addr:street":"Taonui St Palmerston",
    "iso:country":"NZ",
    "sg:address":"19 - 25 Taonui St Palmerston ",
    "sg:city":"Palmerston North",
    "sg:classifiers":[
        {
            "category":"Sports & Exercise",
            "subcategory":"Golf",
            "type":"Entertainment"
        }
    ],
    "sg:phone":"+64 6-357 4749",
    "sg:province":"Manawatu-Wanganui",
    "sg:tags":[
        "club",
        "equipment",
        "leisure",
        "sports"
    ],
    "wof:name":"Golf Importers & Distributors",
    "wof:placetype":"venue"
},
  "geometry": {"coordinates":[175.605469,-40.351479],"type":"Point"}
}