{
  "type": "Feature",
  "properties": {
    "addr:full":"153 Clyde St  Invercargill Southland",
    "addr:housenumber":"153",
    "addr:street":"Clyde St",
    "iso:country":"NZ",
    "sg:address":"153 Clyde St ",
    "sg:city":"Invercargill",
    "sg:orig_category":"Industrial: Packaging: Packaging - General",
    "sg:phone":"+64 3-215 6230",
    "sg:province":"Southland",
    "wof:name":"B & F Suppliers",
    "wof:placetype":"venue"
},
  "geometry": {"coordinates":[168.34754899999999,-46.420326],"type":"Point"}
}