{
  "type": "Feature",
  "properties": {
    "iso:country":"NZ",
    "sg:address":"Mar Haldon Station Office Haldon Rd Haldon Station, Lake ",
    "sg:city":"Tekapo",
    "sg:classifiers":[
        {
            "category":"Farming",
            "subcategory":"Farm & Veterinary Services",
            "type":"Manufacturing & Wholesale Goods"
        }
    ],
    "sg:phone":"+64 3-680 6649",
    "sg:tags":[
        "supplies",
        "supply"
    ],
    "wof:name":"Haldon Station 91 Ltd",
    "wof:placetype":"venue"
},
  "geometry": {"coordinates":[170.48287999999999,-44.00576],"type":"Point"}
}