{
  "type": "Feature",
  "properties": {
    "iso:country":"NZ",
    "sg:address":"Garden Place ",
    "sg:city":"Hamilton",
    "sg:orig_category":"Shopping: Retail Stores: Books: Libraries",
    "sg:phone":"+64 7-838 6826",
    "sg:province":"Otago",
    "wof:name":"Hamilton City Libraries",
    "wof:placetype":"venue"
},
  "geometry": {"coordinates":[-114.202576,46.324554],"type":"Point"}
}