{
  "type": "Feature",
  "properties": {
    "iso:country":"NZ",
    "sg:address":"Golf Links Rd ",
    "sg:city":"Hokitika",
    "sg:classifiers":[
        {
            "category":"Travel",
            "subcategory":"Hotels & Motels",
            "type":"Entertainment"
        }
    ],
    "sg:phone":"+64 3-755 6467",
    "sg:province":"West Coast",
    "sg:tags":[
        "holiday",
        "tourism",
        "accommodation"
    ],
    "sg:website":"http://www.mahinapualodge.co.nz",
    "wof:name":"Country View Homestays",
    "wof:placetype":"venue"
},
  "geometry": {"coordinates":[170.972214,-42.719032],"type":"Point"}
}