{
  "type": "Feature",
  "properties": {
    "addr:full":"The Production Village 26 Wright St Mt Cook  Wellington Wellington",
    "addr:housenumber":"26",
    "addr:street":"Wright St",
    "iso:country":"NZ",
    "sg:address":"The Production Village 26 Wright St Mt Cook ",
    "sg:city":"Wellington",
    "sg:classifiers":[
        {
            "category":"Shopping",
            "subcategory":"Hobbies, Toys, & Games",
            "type":"Retail Goods"
        }
    ],
    "sg:phone":"+64 4-384 4192",
    "sg:province":"Wellington",
    "sg:tags":[
        "hobby"
    ],
    "sg:website":"http://www.panavision.co.nz",
    "wof:name":"Panavision NZ Limited",
    "wof:placetype":"venue"
},
  "geometry": {"coordinates":[174.772842,-41.301388],"type":"Point"}
}