{
  "type": "Feature",
  "properties": {
    "iso:country":"NZ",
    "sg:address":"31 O'Shannessey St Papakura ",
    "sg:city":"Auckland",
    "sg:classifiers":[
        {
            "category":"Shopping",
            "subcategory":"Shoes",
            "type":"Retail Goods"
        }
    ],
    "sg:phone":"+64 9-299 9708",
    "sg:province":"Auckland",
    "sg:tags":[
        "foot",
        "clothing",
        "fabric",
        "wear"
    ],
    "wof:name":"Peverley Shoe Repair",
    "wof:placetype":"venue"
},
  "geometry": {"coordinates":[174.943924,-37.065418],"type":"Point"}
}