{
  "type": "Feature",
  "properties": {
    "addr:full":"1086 Papamoa Beach Rd  Papamoa",
    "addr:housenumber":"1086",
    "addr:street":"Papamoa Beach Rd",
    "iso:country":"NZ",
    "sg:address":"1086 Papamoa Beach Rd ",
    "sg:city":"Papamoa",
    "sg:orig_category":"Shopping: Retail Stores: Books: Books - Secondhand",
    "sg:phone":"+64 7-542 0549",
    "wof:name":"Oasis Superette",
    "wof:placetype":"venue"
},
  "geometry": {"coordinates":[176.33223000000001,-37.713829],"type":"Point"}
}