{
  "type": "Feature",
  "properties": {
    "iso:country":"NZ",
    "sg:address":"Cnr Old West Coast & Weedons Rd West Melton ",
    "sg:city":"Christchurch",
    "sg:classifiers":[
        {
            "category":"Wholesale",
            "subcategory":"Medical Equipment & Supplies",
            "type":"Manufacturing & Wholesale Goods"
        }
    ],
    "sg:phone":"+64 3-347 7472",
    "sg:province":"Canterbury",
    "sg:tags":[
        "health",
        "disability",
        "products",
        "beauty",
        "aid"
    ],
    "wof:name":"Claddagh Haven Trust",
    "wof:placetype":"venue"
},
  "geometry": {"coordinates":[172.36790500000001,-43.522072],"type":"Point"}
}