{
  "type": "Feature",
  "properties": {
    "addr:full":"30 Mill Rd  Whangarei Northland",
    "addr:housenumber":"30",
    "addr:street":"Mill Rd",
    "iso:country":"NZ",
    "sg:address":"30 Mill Rd ",
    "sg:city":"Whangarei",
    "sg:classifiers":[
        {
            "category":"Travel",
            "subcategory":"Bed & Breakfast",
            "type":"Entertainment"
        }
    ],
    "sg:phone":"+64 9-437 6898",
    "sg:province":"Northland",
    "sg:tags":[
        "tourism"
    ],
    "sg:website":"http://www.yellowpages.co.nz/for/stonehavenmotel/dp22683.html",
    "wof:name":"Stonehaven Motel",
    "wof:placetype":"venue"
},
  "geometry": {"coordinates":[174.323883,-35.7132],"type":"Point"}
}