{
  "type": "Feature",
  "properties": {
    "iso:country":"NZ",
    "sg:address":"3/9 Downer St Lower ",
    "sg:city":"Hutt",
    "sg:orig_category":"Transport: Boats And Marine: Boats: Boat Maintenance",
    "sg:phone":"+64 4-570 1596",
    "sg:province":"Wellington",
    "sg:website":"http://www.glassshoppe.co.nz",
    "wof:name":"Glass Shoppe The",
    "wof:placetype":"venue"
},
  "geometry": {"coordinates":[174.912079,-41.205677],"type":"Point"}
}