{
  "type": "Feature",
  "properties": {
    "addr:full":"18 Manuka St Ravensbourne  Dunedin Otago",
    "addr:housenumber":"18",
    "addr:street":"Manuka St",
    "iso:country":"NZ",
    "sg:address":"18 Manuka St Ravensbourne ",
    "sg:city":"Dunedin",
    "sg:orig_category":"Home And Garden: Gardening: Services: Tree Services",
    "sg:phone":"+64 3-471 0770",
    "sg:province":"Otago",
    "wof:name":"Cutting Edge Contracting",
    "wof:placetype":"venue"
},
  "geometry": {"coordinates":[170.54852299999999,-45.86512],"type":"Point"}
}