{
  "type": "Feature",
  "properties": {
    "addr:full":"215A Rosebery St  Tokoroa",
    "addr:housenumber":"215a",
    "addr:street":"Rosebery St",
    "iso:country":"NZ",
    "sg:address":"215A Rosebery St ",
    "sg:city":"Tokoroa",
    "sg:classifiers":[
        {
            "category":"Retail",
            "subcategory":"Repair Shop",
            "type":"Services"
        }
    ],
    "sg:phone":"+64 7-886 5678",
    "sg:tags":[
        "clothing",
        "fabric",
        "cleaning"
    ],
    "wof:name":"Tokoroa Clothing Clinic",
    "wof:placetype":"venue"
},
  "geometry": {"coordinates":[175.872086,-38.218418],"type":"Point"}
}