{
  "type": "Feature",
  "properties": {
    "addr:full":"1094 Shands Rd Lincoln  Christchurch Canterbury",
    "addr:housenumber":"1094",
    "addr:street":"Shands Rd",
    "iso:country":"NZ",
    "sg:address":"1094 Shands Rd Lincoln ",
    "sg:city":"Christchurch",
    "sg:classifiers":[
        {
            "category":"Shopping",
            "type":"Retail Goods"
        }
    ],
    "sg:phone":"+64 3-325 2621",
    "sg:province":"Canterbury",
    "sg:tags":[
        "store"
    ],
    "sg:website":"http://www.broadfieldflowers.co.nz",
    "wof:name":"Broadfield Flowers",
    "wof:placetype":"venue"
},
  "geometry": {"coordinates":[172.48481799999999,-43.64016],"type":"Point"}
}