{
  "type": "Feature",
  "properties": {
    "iso:country":"NZ",
    "sg:address":"5 Irk St ",
    "sg:city":"Gore",
    "sg:orig_category":"Health And Beauty: Dental: Dentists",
    "sg:phone":"+64 3-208 7413",
    "sg:province":"Southland",
    "wof:name":"Perkins R M",
    "wof:placetype":"venue"
},
  "geometry": {"coordinates":[168.942444,-46.10004],"type":"Point"}
}