{
  "type": "Feature",
  "properties": {
    "addr:full":"Regina La  Oamaru Otago",
    "addr:street":"Regina",
    "iso:country":"NZ",
    "sg:address":"Regina La ",
    "sg:city":"Oamaru",
    "sg:classifiers":[
        {
            "category":"Utilities",
            "subcategory":"Refuse",
            "type":"Services"
        }
    ],
    "sg:phone":"+64 3-437 1458",
    "sg:province":"Otago",
    "sg:tags":[
        "bin",
        "hire",
        "garden",
        "cleaning",
        "rubbish",
        "home"
    ],
    "wof:name":"Peter Murdoch Transport Ltd",
    "wof:placetype":"venue"
},
  "geometry": {"coordinates":[170.989563,-45.0788],"type":"Point"}
}