{
  "type": "Feature",
  "properties": {
    "addr:full":"5 Gloucester St Greenmeadows  Napier Hawke's Bay",
    "addr:housenumber":"5",
    "addr:street":"Gloucester St",
    "iso:country":"NZ",
    "sg:address":"5 Gloucester St Greenmeadows ",
    "sg:city":"Napier",
    "sg:classifiers":[
        {
            "category":"Shopping",
            "subcategory":"Bicycles & Sporting Goods",
            "type":"Retail Goods"
        }
    ],
    "sg:phone":"+64 6-844 2418",
    "sg:province":"Hawke's Bay",
    "sg:tags":[
        "cycle",
        "sport",
        "sale",
        "retailers",
        "cycles"
    ],
    "wof:name":"Total Mower Services HB Ltd",
    "wof:placetype":"venue"
},
  "geometry": {"coordinates":[176.863068,-39.524876],"type":"Point"}
}