{
  "type": "Feature",
  "properties": {
    "addr:full":"Nisbet Rd  Whangarei Northland",
    "addr:street":"Nisbet Rd",
    "iso:country":"NZ",
    "sg:address":"Nisbet Rd ",
    "sg:city":"Whangarei",
    "sg:classifiers":[
        {
            "category":"Restaurant",
            "type":"Food & Drink"
        }
    ],
    "sg:phone":"+64 9-434 7288",
    "sg:province":"Northland",
    "sg:tags":[
        "fruit",
        "veges"
    ],
    "sg:website":"http://www.teoranga.nzco.net",
    "wof:name":"Te Oranga",
    "wof:placetype":"venue"
},
  "geometry": {"coordinates":[174.320526,-35.725399],"type":"Point"}
}