{
  "type": "Feature",
  "properties": {
    "addr:full":"10 Gorge Rd  Queenstown Otago",
    "addr:housenumber":"10",
    "addr:street":"Gorge Rd",
    "iso:country":"NZ",
    "sg:address":"10 Gorge Rd ",
    "sg:city":"Queenstown",
    "sg:orig_category":"Shopping: Retail Stores: Books: Libraries",
    "sg:phone":"+64 3-442 7668",
    "sg:province":"Otago",
    "wof:name":"Queenstown Library",
    "wof:placetype":"venue"
},
  "geometry": {"coordinates":[-76.157791,38.990379],"type":"Point"}
}