{
  "type": "Feature",
  "properties": {
    "iso:country":"NZ",
    "sg:address":"Unit 3 29 Ashfield St Glenfield ",
    "sg:city":"Auckland",
    "sg:orig_category":"Home And Garden: Furniture/Furnishings: Blinds",
    "sg:phone":"+64 9-444 9777",
    "sg:province":"Auckland",
    "wof:name":"North Shore Blinds & Screens Ltd",
    "wof:placetype":"venue"
},
  "geometry": {"coordinates":[174.73001099999999,-36.7733],"type":"Point"}
}