{
  "type": "Feature",
  "properties": {
    "addr:full":"PO Box 874  Whakatane Bay of Plenty",
    "addr:housenumber":"po",
    "addr:street":"Box 874 Whakatane Bay",
    "iso:country":"NZ",
    "sg:address":"PO Box 874 ",
    "sg:city":"Whakatane",
    "sg:orig_category":"Industrial: Energy And Utilities: Gas",
    "sg:phone":"+64 7-308 2124",
    "sg:province":"Bay of Plenty",
    "wof:name":"Bob's Home Gas",
    "wof:placetype":"venue"
},
  "geometry": {"coordinates":[176.98419200000001,-37.965305],"type":"Point"}
}