{
  "type": "Feature",
  "properties": {
    "iso:country":"NZ",
    "sg:address":"Johnsonville Shopping Centre Johnsonville ",
    "sg:city":"Wellington",
    "sg:orig_category":"Clothing And Fabric: Clothing: Jeans",
    "sg:phone":"+64 4-478 2537",
    "sg:province":"Wellington",
    "wof:name":"Just Jeans",
    "wof:placetype":"venue"
},
  "geometry": {"coordinates":[174.80178799999999,-41.222324],"type":"Point"}
}