{
  "type": "Feature",
  "properties": {
    "iso:country":"NZ",
    "sg:address":"Thames Arcade 203 Thames St ",
    "sg:city":"Oamaru",
    "sg:classifiers":[
        {
            "category":"Education",
            "subcategory":"Special Training",
            "type":"Public Place"
        }
    ],
    "sg:phone":"+64 3-434 9586",
    "sg:province":"Otago",
    "sg:tags":[
        "tutor",
        "coach",
        "teacher"
    ],
    "wof:name":"Kip McGrath Education Centre",
    "wof:placetype":"venue"
},
  "geometry": {"coordinates":[170.96902499999999,-45.097145],"type":"Point"}
}