{
  "type": "Feature",
  "properties": {
    "addr:full":"Monahan St  Motueka Tasman",
    "addr:street":"Monahan St",
    "iso:country":"NZ",
    "sg:address":"Monahan St ",
    "sg:city":"Motueka",
    "sg:classifiers":[
        {
            "category":"Bus Charters",
            "type":"Transportation"
        }
    ],
    "sg:phone":"+64 3-528 7040",
    "sg:province":"Tasman",
    "sg:tags":[
        "services",
        "travel",
        "tourism"
    ],
    "wof:name":"Motueka Bus Co Ltd",
    "wof:placetype":"venue"
},
  "geometry": {"coordinates":[173.01236,-41.122547],"type":"Point"}
}