{
  "type": "Feature",
  "properties": {
    "iso:country":"NZ",
    "sg:address":"109 Clyde St ",
    "sg:city":"Balclutha",
    "sg:orig_category":"Industrial: Electrical/Electronic: Radio Engineers",
    "sg:phone":"+64 3-418 1177",
    "wof:name":"Peter Electronics Ltd",
    "wof:placetype":"venue"
},
  "geometry": {"coordinates":[169.73457300000001,-46.239868],"type":"Point"}
}