{
  "type": "Feature",
  "properties": {
    "addr:full":"22 Thames St Pandora  Napier Hawke's Bay",
    "addr:housenumber":"22",
    "addr:street":"Thames St",
    "iso:country":"NZ",
    "sg:address":"22 Thames St Pandora ",
    "sg:city":"Napier",
    "sg:orig_category":"Shopping: Gifts: Sheepskins",
    "sg:phone":"+64 6-835 9662",
    "sg:province":"Hawke's Bay",
    "wof:name":"Classic Sheepskins Tannery",
    "wof:placetype":"venue"
},
  "geometry": {"coordinates":[176.88836699999999,-39.489136],"type":"Point"}
}