{
  "type": "Feature",
  "properties": {
    "iso:country":"NZ",
    "sg:address":"33 Scott Ave Mangere ",
    "sg:city":"Auckland",
    "sg:orig_category":"Home And Garden: Children: Child Related: Children'S Entertainment",
    "sg:phone":"+64 9-636 4822",
    "sg:province":"Auckland",
    "wof:name":"Abracadabra Magic Co",
    "wof:placetype":"venue"
},
  "geometry": {"coordinates":[174.823807,-36.96891],"type":"Point"}
}