{
  "type": "Feature",
  "properties": {
    "iso:country":"NZ",
    "sg:address":"69 Taupo Qy ",
    "sg:city":"Wanganui",
    "sg:classifiers":[
        {
            "category":"Sports & Exercise",
            "subcategory":"Sports Center",
            "type":"Entertainment"
        }
    ],
    "sg:phone":"+64 6-345 3070",
    "sg:province":"Manawatu-Wanganui",
    "sg:tags":[
        "art",
        "leisure"
    ],
    "sg:website":"http://www.galleryforte.co.nz",
    "wof:name":"Gallery Forte",
    "wof:placetype":"venue"
},
  "geometry": {"coordinates":[175.05358899999999,-39.936928],"type":"Point"}
}