{
  "type": "Feature",
  "properties": {
    "addr:full":"115 Mays Rd Te Papapa  Auckland Auckland",
    "addr:housenumber":"115",
    "addr:street":"Mays Rd",
    "iso:country":"NZ",
    "sg:address":"115 Mays Rd Te Papapa ",
    "sg:city":"Auckland",
    "sg:classifiers":[
        {
            "category":"Manufacturing",
            "subcategory":"Metals",
            "type":"Manufacturing & Wholesale Goods"
        }
    ],
    "sg:phone":"+64 9-622 2139",
    "sg:province":"Auckland",
    "sg:tags":[
        "-",
        "engineering",
        "industrial",
        "sheet",
        "engineer"
    ],
    "wof:name":"Alround Sheet Metals Ltd",
    "wof:placetype":"venue"
},
  "geometry": {"coordinates":[174.80256700000001,-36.920414],"type":"Point"}
}