{
  "type": "Feature",
  "properties": {
    "addr:full":"Sundell Pl  Opotiki",
    "addr:street":"Sundell Pl",
    "iso:country":"NZ",
    "sg:address":"Sundell Pl ",
    "sg:city":"Opotiki",
    "sg:orig_category":"Farming: Agriculture",
    "sg:phone":"+64 7-315 7386",
    "wof:name":"Cawte Barry",
    "wof:placetype":"venue"
},
  "geometry": {"coordinates":[177.26623499999999,-38.017212],"type":"Point"}
}