{
  "type": "Feature",
  "properties": {
    "iso:country":"NZ",
    "sg:address":"187 Riccarton Rd Riccarton ",
    "sg:city":"Christchurch",
    "sg:orig_category":"Health And Beauty: Specialists: Physiotherapists",
    "sg:phone":"+64 3-348 5359",
    "sg:province":"Canterbury",
    "wof:name":"Pierce Katherine",
    "wof:placetype":"venue"
},
  "geometry": {"coordinates":[172.592331,-43.530476],"type":"Point"}
}