{
  "type": "Feature",
  "properties": {
    "addr:full":"31 Bright St  Gisborne Gisborne",
    "addr:housenumber":"31",
    "addr:street":"Bright St",
    "iso:country":"NZ",
    "sg:address":"31 Bright St ",
    "sg:city":"Gisborne",
    "sg:classifiers":[
        {
            "category":"Home & Garden",
            "subcategory":"Garden Supply",
            "type":"Retail Goods"
        }
    ],
    "sg:phone":"+64 6-867 7648",
    "sg:province":"Gisborne",
    "sg:tags":[
        "products",
        "nursery",
        "gardening"
    ],
    "wof:name":"Avalon Toys & Garden Centre",
    "wof:placetype":"venue"
},
  "geometry": {"coordinates":[178.025452,-38.66497],"type":"Point"}
}