{
  "type": "Feature",
  "properties": {
    "addr:full":"Totara North Rd R D 2  Kaeo Auckland",
    "addr:housenumber":"2 kaeo",
    "addr:street":"Totara North Rd R D",
    "iso:country":"NZ",
    "sg:address":"Totara North Rd R D 2 ",
    "sg:city":"Kaeo",
    "sg:classifiers":[
        {
            "category":"Home & Garden",
            "subcategory":"Building Materials",
            "type":"Retail Goods"
        }
    ],
    "sg:phone":"+64 9-405 1855",
    "sg:province":"Auckland",
    "sg:tags":[
        "fittings",
        "staircase",
        "handrail"
    ],
    "wof:name":"McIntosh R C Joiners",
    "wof:placetype":"venue"
},
  "geometry": {"coordinates":[173.77413899999999,-35.098103],"type":"Point"}
}