{
  "type": "Feature",
  "properties": {
    "iso:country":"NZ",
    "sg:address":"15 Whitelaw Pl Kamo ",
    "sg:city":"Whangarei",
    "sg:orig_category":"Transport: Transportation: Courier Services",
    "sg:phone":"+64 9-435 2658",
    "sg:province":"Northland",
    "wof:name":"Tutukaka Freight Services",
    "wof:placetype":"venue"
},
  "geometry": {"coordinates":[174.295807,-35.6786],"type":"Point"}
}