{
  "type": "Feature",
  "properties": {
    "iso:country":"NZ",
    "sg:address":"148 Oriental Pde Oriental Bay ",
    "sg:city":"Wellington",
    "sg:classifiers":[
        {
            "category":"Bars & Pubs",
            "subcategory":"Wine Bar",
            "type":"Food & Drink"
        }
    ],
    "sg:phone":"+64 4-939 3935",
    "sg:province":"Wellington",
    "sg:tags":[
        "wining",
        "dining",
        "cafe"
    ],
    "wof:name":"Parade Cafe",
    "wof:placetype":"venue"
},
  "geometry": {"coordinates":[174.791779,-41.290928],"type":"Point"}
}