{
  "type": "Feature",
  "properties": {
    "addr:full":"27 Latter St  Timaru Canterbury",
    "addr:housenumber":"27",
    "addr:street":"Latter St",
    "iso:country":"NZ",
    "sg:address":"27 Latter St ",
    "sg:city":"Timaru",
    "sg:classifiers":[
        {
            "category":"Retail",
            "subcategory":"Auto Repair",
            "type":"Services"
        }
    ],
    "sg:phone":"+64 3-684 7161",
    "sg:province":"Canterbury",
    "sg:tags":[
        "muffler",
        "exhaust",
        "servicing",
        "automotive"
    ],
    "wof:name":"Vaughan Motors",
    "wof:placetype":"venue"
},
  "geometry": {"coordinates":[171.25262499999999,-44.398342],"type":"Point"}
}