{
  "type": "Feature",
  "properties": {
    "addr:full":"Brown Rd Bell Block New  Plymouth Taranaki",
    "addr:street":"Brown Rd",
    "iso:country":"NZ",
    "sg:address":"Brown Rd Bell Block New ",
    "sg:city":"Plymouth",
    "sg:classifiers":[
        {
            "category":"Bars & Pubs",
            "subcategory":"Wine Bar",
            "type":"Food & Drink"
        }
    ],
    "sg:phone":"+64 6-755 0720",
    "sg:province":"Taranaki",
    "sg:tags":[
        "wining",
        "dining",
        "cafe"
    ],
    "wof:name":"Airport Cafe",
    "wof:placetype":"venue"
},
  "geometry": {"coordinates":[174.14274599999999,-39.032024],"type":"Point"}
}