{
  "type": "Feature",
  "properties": {
    "addr:full":"Wellington PO Box 13753 Johnsonville  Wellington Wellington",
    "addr:housenumber":"box 13753",
    "addr:street":"Wellington",
    "iso:country":"NZ",
    "sg:address":"Wellington PO Box 13753 Johnsonville ",
    "sg:city":"Wellington",
    "sg:orig_category":"Industrial: Parts: Pipes, Tubes And Cabling: Cables",
    "sg:phone":"+64 4-461 6991",
    "sg:province":"Wellington",
    "wof:name":"A B Computer Support Limited",
    "wof:placetype":"venue"
},
  "geometry": {"coordinates":[174.76715100000001,-41.28054],"type":"Point"}
}