{
  "type": "Feature",
  "properties": {
    "iso:country":"NZ",
    "sg:address":"602 Halswell Rd Halswell ",
    "sg:city":"Christchurch",
    "sg:classifiers":[
        {
            "category":"Home & Garden",
            "subcategory":"Building Materials",
            "type":"Retail Goods"
        }
    ],
    "sg:phone":"+64 3-365 3353",
    "sg:province":"Canterbury",
    "sg:tags":[
        "fittings",
        "door",
        "garage"
    ],
    "wof:name":"Bob Gardiner Garage Doors",
    "wof:placetype":"venue"
},
  "geometry": {"coordinates":[172.56362899999999,-43.593845],"type":"Point"}
}