{
  "type": "Feature",
  "properties": {
    "addr:full":"83 Aro St  Wellington Wellington",
    "addr:housenumber":"83",
    "addr:street":"Aro St",
    "iso:country":"NZ",
    "sg:address":"83 Aro St ",
    "sg:city":"Wellington",
    "sg:classifiers":[
        {
            "category":"Food & Beverages",
            "subcategory":"Bakery",
            "type":"Retail Goods"
        }
    ],
    "sg:phone":"+64 4-384 5473",
    "sg:province":"Wellington",
    "sg:tags":[
        "shop",
        "cake",
        "drink",
        "-"
    ],
    "wof:name":"Arobake",
    "wof:placetype":"venue"
},
  "geometry": {"coordinates":[-85.910454,33.827946],"type":"Point"}
}