{
  "type": "Feature",
  "properties": {
    "addr:full":"73 Wiri Station Rd Wiri  Auckland Auckland",
    "addr:housenumber":"73",
    "addr:street":"Wiri Station Rd",
    "iso:country":"NZ",
    "sg:address":"73 Wiri Station Rd Wiri ",
    "sg:city":"Auckland",
    "sg:orig_category":"Industrial: Equipment And Machinery: Furnaces, Kilns And Ovens: Furnaces",
    "sg:phone":"+64 9-263 8026",
    "sg:province":"Auckland",
    "wof:name":"The Electric Furnace Co Ltd",
    "wof:placetype":"venue"
},
  "geometry": {"coordinates":[174.86731,-37.001328],"type":"Point"}
}