{
  "type": "Feature",
  "properties": {
    "iso:country":"NZ",
    "sg:address":"22 Rauhato St ",
    "sg:city":"Taupo",
    "sg:orig_category":"Transport: Boats And Marine: Boats: Boat Maintenance",
    "sg:phone":"+64 7-378 8655",
    "sg:province":"Waikato",
    "wof:name":"Taupo Boat Painters",
    "wof:placetype":"venue"
},
  "geometry": {"coordinates":[176.084351,-38.689285],"type":"Point"}
}