{
  "type": "Feature",
  "properties": {
    "iso:country":"NZ",
    "sg:address":"11 Olive Rd Penrose ",
    "sg:city":"Auckland",
    "sg:orig_category":"Transport: Transportation: Furniture Removal/Packers",
    "sg:phone":"+64 9-579 2855",
    "sg:province":"Auckland",
    "sg:website":"http://www.yellowpages.co.nz/pages/103423032/dp33803.html",
    "wof:name":"Grace Removals Group",
    "wof:placetype":"venue"
},
  "geometry": {"coordinates":[174.81246899999999,-36.911636],"type":"Point"}
}