{
  "type": "Feature",
  "properties": {
    "addr:full":"PO Box 545  Auckland Auckland",
    "addr:housenumber":"po;545",
    "addr:street":"Box",
    "iso:country":"NZ",
    "sg:address":"PO Box 545 ",
    "sg:city":"Auckland",
    "sg:classifiers":[
        {
            "category":"Home & Garden",
            "subcategory":"Kitchen Supply",
            "type":"Retail Goods"
        }
    ],
    "sg:phone":"+64 800 500 031",
    "sg:province":"Auckland",
    "sg:tags":[
        "motel",
        "industrial",
        "products",
        "hotel"
    ],
    "wof:name":"Commercial Linen Co Ltd",
    "wof:placetype":"venue"
},
  "geometry": {"coordinates":[174.77041600000001,-36.884109],"type":"Point"}
}