{
  "type": "Feature",
  "properties": {
    "addr:full":"112 Antigua St Sydenham  Christchurch Canterbury",
    "addr:housenumber":"112",
    "addr:street":"Antigua St",
    "iso:country":"NZ",
    "sg:address":"112 Antigua St Sydenham ",
    "sg:city":"Christchurch",
    "sg:classifiers":[
        {
            "category":"Bars & Pubs",
            "subcategory":"Lounge",
            "type":"Food & Drink"
        }
    ],
    "sg:phone":"+64 3-366 2039",
    "sg:province":"Canterbury",
    "sg:tags":[
        "-"
    ],
    "wof:name":"New Zealand Food Group (1992) Ltd",
    "wof:placetype":"venue"
},
  "geometry": {"coordinates":[172.62806699999999,-43.543545],"type":"Point"}
}