{
  "type": "Feature",
  "properties": {
    "iso:country":"NZ",
    "sg:address":"Rickit Rd Te ",
    "sg:city":"Awamutu",
    "sg:classifiers":[
        {
            "category":"Health Services",
            "subcategory":"Hospital",
            "type":"Services"
        }
    ],
    "sg:phone":"+64 7-871 3535",
    "sg:province":"Waikato",
    "sg:tags":[
        "beauty",
        "fitness"
    ],
    "wof:name":"Marty's Gym",
    "wof:placetype":"venue"
},
  "geometry": {"coordinates":[175.332077,-38.012405],"type":"Point"}
}