{
  "type": "Feature",
  "properties": {
    "iso:country":"NZ",
    "sg:address":"105 Jackson St Petone Lower ",
    "sg:city":"Hutt",
    "sg:classifiers":[
        {
            "category":"Fast Food",
            "type":"Food & Drink"
        }
    ],
    "sg:phone":"+64 4-568 6161",
    "sg:province":"Wellington",
    "sg:tags":[
        "wining",
        "dining",
        "takeaway"
    ],
    "wof:name":"Shakey's Burger Bar",
    "wof:placetype":"venue"
},
  "geometry": {"coordinates":[174.87532,-41.22422],"type":"Point"}
}