{
  "type": "Feature",
  "properties": {
    "addr:full":"26 Dacre St Newton  Auckland Auckland",
    "addr:housenumber":"26",
    "addr:street":"Dacre St",
    "iso:country":"NZ",
    "sg:address":"26 Dacre St Newton ",
    "sg:city":"Auckland",
    "sg:orig_category":"Industrial: Parts: Pipes, Tubes And Cabling: Fibre Optics",
    "sg:phone":"+64 9-309 9618",
    "sg:province":"Auckland",
    "wof:name":"Fibreoptic Light & Design Ltd",
    "wof:placetype":"venue"
},
  "geometry": {"coordinates":[174.75914,-36.861382],"type":"Point"}
}