{
  "type": "Feature",
  "properties": {
    "iso:country":"NZ",
    "sg:address":"6 Tenahaun Pl ",
    "sg:city":"Sockburn",
    "sg:classifiers":[
        {
            "category":"Food Court",
            "type":"Food & Drink"
        }
    ],
    "sg:phone":"+64 800 327 893",
    "sg:province":"Canterbury",
    "sg:tags":[
        "manufacturer"
    ],
    "wof:name":"East West Brewery Ltd",
    "wof:placetype":"venue"
},
  "geometry": {"coordinates":[172.55043000000001,-43.534966],"type":"Point"}
}