{
  "type": "Feature",
  "properties": {
    "addr:full":"1241 Fenton St  Rotorua Bay of Plenty",
    "addr:housenumber":"1241",
    "addr:street":"Fenton St",
    "iso:country":"NZ",
    "sg:address":"1241 Fenton St ",
    "sg:city":"Rotorua",
    "sg:classifiers":[
        {
            "category":"Shopping",
            "subcategory":"Gifts & Souvenirs",
            "type":"Retail Goods"
        }
    ],
    "sg:phone":"+64 7-349 3434",
    "sg:province":"Bay of Plenty",
    "sg:tags":[
        "travel",
        "tourism"
    ],
    "wof:name":"Albert Leather Fashion",
    "wof:placetype":"venue"
},
  "geometry": {"coordinates":[176.25367700000001,-38.137547],"type":"Point"}
}