{
  "type": "Feature",
  "properties": {
    "addr:full":"97 Keith St Palmerston  Palmerston North Manawatu-Wanganui",
    "addr:housenumber":"97",
    "addr:street":"Keith St Palmerston",
    "iso:country":"NZ",
    "sg:address":"97 Keith St Palmerston ",
    "sg:city":"Palmerston North",
    "sg:orig_category":"Automotive: Parts And Supplies: Automotive Dismantlers",
    "sg:phone":"+64 6-357 5888",
    "sg:province":"Manawatu-Wanganui",
    "wof:name":"Manawatu Commercial & 4X4 Dismantlers",
    "wof:placetype":"venue"
},
  "geometry": {"coordinates":[175.640762,-40.337212],"type":"Point"}
}