{
  "type": "Feature",
  "properties": {
    "iso:country":"NZ",
    "sg:address":"67 Courtney St New ",
    "sg:city":"Plymouth",
    "sg:orig_category":"Shopping: Retail Stores: Department Stores",
    "sg:phone":"+64 6-758 2125",
    "sg:province":"Taranaki",
    "wof:name":"The Warehouse Ltd",
    "wof:placetype":"venue"
},
  "geometry": {"coordinates":[-116.819725,43.97221],"type":"Point"}
}