{
  "type": "Feature",
  "properties": {
    "addr:full":"774 Waikare Rd Te  Kauwhata",
    "addr:housenumber":"774",
    "addr:street":"Waikare Rd",
    "iso:country":"NZ",
    "sg:address":"774 Waikare Rd Te ",
    "sg:city":"Kauwhata",
    "sg:classifiers":[
        {
            "category":"Home & Garden",
            "subcategory":"Building Materials",
            "type":"Retail Goods"
        }
    ],
    "sg:phone":"+64 7-826 3135",
    "sg:tags":[
        "electrician",
        "related"
    ],
    "wof:name":"Ellmers Farm & Electrical Ltd",
    "wof:placetype":"venue"
},
  "geometry": {"coordinates":[175.14735400000001,-37.403275],"type":"Point"}
}