{
  "type": "Feature",
  "properties": {
    "addr:full":"122 Crawford St  Dunedin Otago",
    "addr:housenumber":"122",
    "addr:street":"Crawford St",
    "iso:country":"NZ",
    "sg:address":"122 Crawford St ",
    "sg:city":"Dunedin",
    "sg:orig_category":"Automotive: Accessories: Car Security Systems",
    "sg:phone":"+64 3-474 0537",
    "sg:province":"Otago",
    "wof:name":"Installer Services",
    "wof:placetype":"venue"
},
  "geometry": {"coordinates":[-82.784721,28.013355],"type":"Point"}
}