{
  "type": "Feature",
  "properties": {
    "addr:full":"PO Box 13405  Tauranga Bay of Plenty",
    "addr:housenumber":"po box",
    "addr:postcode":"13405",
    "iso:country":"NZ",
    "sg:address":"PO Box 13405 ",
    "sg:city":"Tauranga",
    "sg:classifiers":[
        {
            "category":"Home & Garden",
            "subcategory":"Building Materials",
            "type":"Retail Goods"
        }
    ],
    "sg:phone":"+64 800 237 843",
    "sg:province":"Bay of Plenty",
    "sg:tags":[
        "builder",
        "related"
    ],
    "sg:website":"http://www.certifiedbuilders.org.nz",
    "wof:name":"NZ Certified Builders Assn Inc",
    "wof:placetype":"venue"
},
  "geometry": {"coordinates":[176.144745,-37.703156],"type":"Point"}
}