{
  "type": "Feature",
  "properties": {
    "iso:country":"NZ",
    "sg:address":"Lower Cameron St ",
    "sg:city":"Whangarei",
    "sg:classifiers":[
        {
            "category":"Retail",
            "subcategory":"Auto Repair",
            "type":"Services"
        }
    ],
    "sg:phone":"+64 9-438 5115",
    "sg:province":"Northland",
    "sg:tags":[
        "wheel",
        "automotive",
        "servicing",
        "alignment"
    ],
    "wof:name":"Trans-Tune Wheel Alignment Centre",
    "wof:placetype":"venue"
},
  "geometry": {"coordinates":[174.320526,-35.725399],"type":"Point"}
}