{
  "type": "Feature",
  "properties": {
    "iso:country":"NZ",
    "sg:address":"E Opua Industrial Estate Opua ",
    "sg:city":"Paihia",
    "sg:classifiers":[
        {
            "category":"Home & Garden",
            "subcategory":"Building Materials",
            "type":"Retail Goods"
        }
    ],
    "sg:phone":"+64 9-402 6885",
    "sg:province":"Northland",
    "sg:tags":[
        "design",
        "fitting",
        "fittings",
        "kitchen"
    ],
    "wof:name":"Ark Productions",
    "wof:placetype":"venue"
},
  "geometry": {"coordinates":[174.091064,-35.283691],"type":"Point"}
}