{
  "type": "Feature",
  "properties": {
    "addr:full":"47 Meadows Rd Washdyke  Timaru Canterbury",
    "addr:housenumber":"47",
    "addr:street":"Meadows Rd",
    "iso:country":"NZ",
    "sg:address":"47 Meadows Rd Washdyke ",
    "sg:city":"Timaru",
    "sg:orig_category":"Industrial: Packaging",
    "sg:phone":"+64 3-688 2336",
    "sg:province":"Canterbury",
    "wof:name":"Wilson Bros Timber Ltd",
    "wof:placetype":"venue"
},
  "geometry": {"coordinates":[171.24449200000001,-44.35672],"type":"Point"}
}