{
  "type": "Feature",
  "properties": {
    "addr:full":"2/26 Parkinson St  Gisborne Gisborne",
    "addr:housenumber":"2 / 26",
    "addr:street":"Parkinson St",
    "iso:country":"NZ",
    "sg:address":"2/26 Parkinson St ",
    "sg:city":"Gisborne",
    "sg:orig_category":"Shopping: Dispensing: Vending Machines",
    "sg:phone":"+64 6-867 6681",
    "sg:province":"Gisborne",
    "wof:name":"Tasman Suppliers Ltd",
    "wof:placetype":"venue"
},
  "geometry": {"coordinates":[177.99551399999999,-38.665726],"type":"Point"}
}