{
  "type": "Feature",
  "properties": {
    "iso:country":"NZ",
    "sg:address":"Pitama Rd Palmerston ",
    "sg:city":"Palmerston North",
    "sg:classifiers":[
        {
            "category":"Restaurant",
            "type":"Food & Drink"
        }
    ],
    "sg:phone":"+64 6-354 1880",
    "sg:province":"Manawatu-Wanganui",
    "sg:tags":[
        "wining",
        "dining"
    ],
    "wof:name":"McGuigans Restaurant & Bar",
    "wof:placetype":"venue"
},
  "geometry": {"coordinates":[175.59567300000001,-40.376438],"type":"Point"}
}