{
  "type": "Feature",
  "properties": {
    "iso:country":"NZ",
    "sg:address":"178 Glasgow St ",
    "sg:city":"Wanganui",
    "sg:classifiers":[
        {
            "category":"Home & Garden",
            "subcategory":"Furniture",
            "type":"Retail Goods"
        }
    ],
    "sg:phone":"+64 6-345 4764",
    "sg:province":"Manawatu-Wanganui",
    "sg:tags":[
        "furniture/furnishings",
        "furnishing"
    ],
    "wof:name":"Kitchen Creations",
    "wof:placetype":"venue"
},
  "geometry": {"coordinates":[175.036865,-39.926743],"type":"Point"}
}