{
  "type": "Feature",
  "properties": {
    "iso:country":"NZ",
    "sg:address":"23 B Ganges Rd Khandallah ",
    "sg:city":"Wellington",
    "sg:orig_category":"Shopping: Retail Stores: Secondhand Dealers",
    "sg:phone":"+64 4-479 9161",
    "sg:province":"Wellington",
    "sg:website":"http://www.usedphoneco.com",
    "wof:name":"Used Phone Company Ltd",
    "wof:placetype":"venue"
},
  "geometry": {"coordinates":[174.791824,-41.247292],"type":"Point"}
}