{
  "type": "Feature",
  "properties": {
    "iso:country":"NZ",
    "sg:address":"PO Box 6290 Upper Riccarton ",
    "sg:city":"Christchurch",
    "sg:orig_category":"Industrial: Engineering: Engineers - Automation",
    "sg:phone":"+64 3-341 6204",
    "sg:province":"Canterbury",
    "wof:name":"Industrial Electron Services",
    "wof:placetype":"venue"
},
  "geometry": {"coordinates":[172.577133,-43.530991],"type":"Point"}
}