{
  "type": "Feature",
  "properties": {
    "iso:country":"NZ",
    "sg:address":"PO Box 51-125 Tawa ",
    "sg:city":"Porirua",
    "sg:orig_category":"Home And Garden: Furniture/Furnishings: Curtains",
    "sg:phone":"+64 4-237 3039",
    "sg:province":"Wellington",
    "wof:name":"Lewis's Home Fabrics Ltd",
    "wof:placetype":"venue"
},
  "geometry": {"coordinates":[174.824203,-41.17149],"type":"Point"}
}