{
  "type": "Feature",
  "properties": {
    "iso:country":"NZ",
    "sg:address":"PO Box 31363 Milford ",
    "sg:city":"Auckland",
    "sg:orig_category":"Farming: Supplies: Veterinary Supplies",
    "sg:phone":"+64 9-444 9012",
    "sg:province":"Auckland",
    "wof:name":"Phoenix Pharm Distributors Ltd",
    "wof:placetype":"venue"
},
  "geometry": {"coordinates":[174.764984,-36.771812],"type":"Point"}
}