{
  "type": "Feature",
  "properties": {
    "addr:full":"38 Main Rd Waikanae  Paraparaumu Wellington",
    "addr:housenumber":"38",
    "addr:street":"Main Rd",
    "iso:country":"NZ",
    "sg:address":"38 Main Rd Waikanae ",
    "sg:city":"Paraparaumu",
    "sg:orig_category":"Home And Garden: Accessories: Hardware",
    "sg:phone":"+64 9026501",
    "sg:province":"Wellington",
    "wof:name":"Waikanae Hammer Hardware",
    "wof:placetype":"venue"
},
  "geometry": {"coordinates":[175.06100499999999,-40.87318],"type":"Point"}
}