{
  "type": "Feature",
  "properties": {
    "addr:full":"Shop 5 & 6 McMillan Ct Newlands  Wellington Wellington",
    "addr:housenumber":"shop 5 & 6",
    "addr:street":"Mcmillan Ct",
    "iso:country":"NZ",
    "sg:address":"Shop 5 & 6 McMillan Ct Newlands ",
    "sg:city":"Wellington",
    "sg:classifiers":[
        {
            "category":"Food & Beverages",
            "subcategory":"Groceries & Convenience Stores",
            "type":"Retail Goods"
        }
    ],
    "sg:phone":"+64 4-939 2424",
    "sg:province":"Wellington",
    "sg:tags":[
        "foodstuff",
        "drink",
        "-"
    ],
    "wof:name":"J N S Eastern Traders Ltd",
    "wof:placetype":"venue"
},
  "geometry": {"coordinates":[174.81947299999999,-41.225929],"type":"Point"}
}