{
  "type": "Feature",
  "properties": {
    "addr:full":"5 D Tenehaum Pl Middleton  Christchurch Canterbury",
    "addr:housenumber":"5",
    "addr:street":"D Tenehaum Pl",
    "iso:country":"NZ",
    "sg:address":"5 D Tenehaum Pl Middleton ",
    "sg:city":"Christchurch",
    "sg:orig_category":"Industrial: Services: Toolmakers And Designers",
    "sg:phone":"+64 3-343 5156",
    "sg:province":"Canterbury",
    "wof:name":"McClay Tooling",
    "wof:placetype":"venue"
},
  "geometry": {"coordinates":[172.568207,-43.543259],"type":"Point"}
}