{
  "type": "Feature",
  "properties": {
    "addr:full":"Wellington  Wellington Wellington",
    "iso:country":"NZ",
    "sg:address":"Wellington ",
    "sg:city":"Wellington",
    "sg:classifiers":[
        {
            "category":"Banks & Credit Unions",
            "subcategory":"Financial Services",
            "type":"Services"
        }
    ],
    "sg:phone":"+64 800 379 9466",
    "sg:province":"Wellington",
    "sg:tags":[
        "finance"
    ],
    "sg:website":"http://www.advantagefinance.co.nz",
    "wof:name":"Advantage Finance Ltd",
    "wof:placetype":"venue"
},
  "geometry": {"coordinates":[174.82162500000001,-41.325909],"type":"Point"}
}