{
  "type": "Feature",
  "properties": {
    "addr:full":"Hamilton Central Shopping Centre Bryce St  Hamilton Waikato",
    "addr:street":"Bryce St",
    "iso:country":"NZ",
    "sg:address":"Hamilton Central Shopping Centre Bryce St ",
    "sg:city":"Hamilton",
    "sg:classifiers":[
        {
            "category":"Ice Cream",
            "type":"Food & Drink"
        }
    ],
    "sg:phone":"+64 7-839 5393",
    "sg:province":"Waikato",
    "sg:tags":[
        "-"
    ],
    "wof:name":"Wendy's Supa Sundaes",
    "wof:placetype":"venue"
},
  "geometry": {"coordinates":[-87.988968,34.142426],"type":"Point"}
}