{
  "type": "Feature",
  "properties": {
    "iso:country":"NZ",
    "sg:address":"Victoria St ",
    "sg:city":"Thames",
    "sg:orig_category":"Travel And Tourism: Accommodation: Backpackers",
    "sg:phone":"+64 7-868 7308",
    "sg:province":"Waikato",
    "sg:website":"http://www.dicksonpark.co.nz",
    "wof:name":"Dickson Holiday Park Thames",
    "wof:placetype":"venue"
},
  "geometry": {"coordinates":[-72.112679,41.394623],"type":"Point"}
}