{
  "type": "Feature",
  "properties": {
    "iso:country":"NZ",
    "sg:address":"Washdyke ",
    "sg:city":"Timaru",
    "sg:classifiers":[
        {
            "category":"Food & Beverages",
            "subcategory":"Dairy",
            "type":"Retail Goods"
        }
    ],
    "sg:phone":"+64 3-688 2011",
    "sg:province":"Canterbury",
    "sg:tags":[
        "-",
        "drink",
        "vendor",
        "milk"
    ],
    "wof:name":"Timaru Milk Co Ltd",
    "wof:placetype":"venue"
},
  "geometry": {"coordinates":[171.239853,-44.351528],"type":"Point"}
}