{
  "type": "Feature",
  "properties": {
    "iso:country":"NZ",
    "sg:address":"32 Clark St New Lynn ",
    "sg:city":"Auckland",
    "sg:classifiers":[
        {
            "category":"Building & Trades",
            "subcategory":"Electrical",
            "type":"Services"
        }
    ],
    "sg:phone":"+64 9-827 4407",
    "sg:province":"Auckland",
    "sg:tags":[
        "industrial",
        "refrigeration"
    ],
    "wof:name":"Comfort Zone Ltd",
    "wof:placetype":"venue"
},
  "geometry": {"coordinates":[174.688934,-36.910152],"type":"Point"}
}