{
  "type": "Feature",
  "properties": {
    "addr:full":"Treble Ct  Gisborne Gisborne",
    "addr:street":"Treble Ct",
    "iso:country":"NZ",
    "sg:address":"Treble Ct ",
    "sg:city":"Gisborne",
    "sg:orig_category":"Health And Beauty: Products: Pharmacies",
    "sg:phone":"+64 6-868 8362",
    "sg:province":"Gisborne",
    "wof:name":"Treble Court Pharmacy",
    "wof:placetype":"venue"
},
  "geometry": {"coordinates":[178.024475,-38.66597],"type":"Point"}
}