{
  "type": "Feature",
  "properties": {
    "iso:country":"NZ",
    "sg:address":"52 Cole St ",
    "sg:city":"Masterton",
    "sg:classifiers":[
        {
            "category":"Social Services",
            "subcategory":"Retirement Home",
            "type":"Services"
        }
    ],
    "sg:phone":"+64 6-378 2904",
    "sg:province":"Wellington",
    "sg:tags":[
        "elderly",
        "convalescent",
        "garden",
        "rest",
        "care"
    ],
    "wof:name":"Lyndale Rest Home",
    "wof:placetype":"venue"
},
  "geometry": {"coordinates":[175.65522799999999,-40.948647],"type":"Point"}
}