{
  "type": "Feature",
  "properties": {
    "addr:full":"Point  Chevalier",
    "iso:country":"NZ",
    "sg:address":"Point ",
    "sg:city":"Chevalier",
    "sg:classifiers":[
        {
            "category":"Home & Garden",
            "subcategory":"Building Materials",
            "type":"Retail Goods"
        }
    ],
    "sg:phone":"+64 252702275",
    "sg:tags":[
        "electrician",
        "related"
    ],
    "wof:name":"Kirk Electrical",
    "wof:placetype":"venue"
},
  "geometry": {"coordinates":[174.70526100000001,-36.863762],"type":"Point"}
}