{
  "type": "Feature",
  "properties": {
    "iso:country":"NZ",
    "sg:address":"103 Norton Rd ",
    "sg:city":"Hamilton",
    "sg:orig_category":"Shopping: Sports Retailers: Sports Goods: Canvas Goods",
    "sg:phone":"+64 800 483 727",
    "sg:province":"Waikato",
    "wof:name":"Hamilton Canvas Co",
    "wof:placetype":"venue"
},
  "geometry": {"coordinates":[-74.701759,40.203304],"type":"Point"}
}