{
  "type": "Feature",
  "properties": {
    "addr:full":"47 Main St  Manaia Wellington",
    "addr:housenumber":"47",
    "addr:street":"Main St",
    "iso:country":"NZ",
    "sg:address":"47 Main St ",
    "sg:city":"Manaia",
    "sg:orig_category":"Health And Beauty: Products: Pharmacies",
    "sg:phone":"+64 6-274 8200",
    "sg:province":"Wellington",
    "wof:name":"Manaia Pharmacy",
    "wof:placetype":"venue"
},
  "geometry": {"coordinates":[174.12503100000001,-39.550308],"type":"Point"}
}