{
  "type": "Feature",
  "properties": {
    "addr:full":"1 Waiwera Rd Waiwera Hibiscus  Hibiscus Coast Auckland",
    "addr:housenumber":"1",
    "addr:street":"Waiwera Rd",
    "iso:country":"NZ",
    "sg:address":"1 Waiwera Rd Waiwera Hibiscus ",
    "sg:city":"Hibiscus Coast",
    "sg:classifiers":[
        {
            "category":"Travel",
            "subcategory":"Bed & Breakfast",
            "type":"Entertainment"
        }
    ],
    "sg:phone":"+64 9-426 4792",
    "sg:province":"Auckland",
    "sg:tags":[
        "tourism"
    ],
    "sg:website":"http://www.yellowpages.co.nz/for/waiweralodge/dp15481.html",
    "wof:name":"Waiwera Coach Trail Villas",
    "wof:placetype":"venue"
},
  "geometry": {"coordinates":[174.704117,-36.543694],"type":"Point"}
}