{
  "type": "Feature",
  "properties": {
    "iso:country":"NZ",
    "sg:address":"743 A Rosebank Rd Avondale ",
    "sg:city":"Auckland",
    "sg:orig_category":"Industrial: Equipment And Machinery: Machinery",
    "sg:phone":"+64 9-828 1509",
    "sg:province":"Auckland",
    "wof:name":"Machinery Equipment Ltd",
    "wof:placetype":"venue"
},
  "geometry": {"coordinates":[174.685684,-36.888668],"type":"Point"}
}