{
  "type": "Feature",
  "properties": {
    "addr:full":"10 Toroa Pl  Tokoroa",
    "addr:housenumber":"10",
    "addr:street":"Toroa Pl",
    "iso:country":"NZ",
    "sg:address":"10 Toroa Pl ",
    "sg:city":"Tokoroa",
    "sg:classifiers":[
        {
            "category":"Retail",
            "subcategory":"Auto Repair",
            "type":"Services"
        }
    ],
    "sg:phone":"+64 800 479 869",
    "sg:tags":[
        "breakdown",
        "automotive",
        "towing",
        "servicing"
    ],
    "wof:name":"South Waikato Towing",
    "wof:placetype":"venue"
},
  "geometry": {"coordinates":[175.86041299999999,-38.238754],"type":"Point"}
}