{
  "type": "Feature",
  "properties": {
    "iso:country":"NZ",
    "sg:address":"22 Bridgman St South Dunedin ",
    "sg:city":"Dunedin",
    "sg:orig_category":"Transport: Transportation: Transport Operators",
    "sg:phone":"+64 3-455 1112",
    "sg:province":"Otago",
    "wof:name":"Foote H A Haulage Ltd",
    "wof:placetype":"venue"
},
  "geometry": {"coordinates":[170.49951200000001,-45.890186],"type":"Point"}
}