{
  "type": "Feature",
  "properties": {
    "iso:country":"NZ",
    "sg:address":"Level 2, Reid House 150 Hobson St Auckland Central",
    "sg:city":"Auckland",
    "sg:classifiers":[
        {
            "category":"Banks & Credit Unions",
            "subcategory":"Investment Brokerage",
            "type":"Services"
        }
    ],
    "sg:phone":"+64 9-373 5510",
    "sg:province":"Auckland",
    "sg:tags":[
        "educational",
        "education",
        "training"
    ],
    "sg:website":"http://www.itc.co.nz",
    "wof:name":"The International Travel College Of New Zealand Ltd",
    "wof:placetype":"venue"
},
  "geometry": {"coordinates":[174.764542,-36.848358],"type":"Point"}
}