{
  "type": "Feature",
  "properties": {
    "addr:full":"52 Prestons Rd  Greymouth West Coast",
    "addr:housenumber":"52",
    "addr:street":"Prestons Rd",
    "iso:country":"NZ",
    "sg:address":"52 Prestons Rd ",
    "sg:city":"Greymouth",
    "sg:orig_category":"Industrial: Engineering: Engineers: Engineers - General",
    "sg:phone":"+64 272 948 990",
    "sg:province":"West Coast",
    "wof:name":"Steve O Engineering Ltd",
    "wof:placetype":"venue"
},
  "geometry": {"coordinates":[171.19773900000001,-42.452484],"type":"Point"}
}