{
  "type": "Feature",
  "properties": {
    "addr:full":"110 Bond St West Invercargill  Invercargill Southland",
    "addr:housenumber":"110",
    "addr:street":"Bond St",
    "iso:country":"NZ",
    "sg:address":"110 Bond St West Invercargill ",
    "sg:city":"Invercargill",
    "sg:classifiers":[
        {
            "category":"Manufacturing",
            "subcategory":"Metals",
            "type":"Manufacturing & Wholesale Goods"
        }
    ],
    "sg:phone":"+64 3-218 1201",
    "sg:province":"Southland",
    "sg:tags":[
        "-",
        "engineering",
        "industrial",
        "sheet",
        "engineer"
    ],
    "wof:name":"Southland Sheetmetal",
    "wof:placetype":"venue"
},
  "geometry": {"coordinates":[168.34034700000001,-46.410923],"type":"Point"}
}