{
  "type": "Feature",
  "properties": {
    "addr:full":"1 Kingsford St Burwood  Christchurch Canterbury",
    "addr:housenumber":"1",
    "addr:street":"Kingsford St",
    "iso:country":"NZ",
    "sg:address":"1 Kingsford St Burwood ",
    "sg:city":"Christchurch",
    "sg:classifiers":[
        {
            "category":"Utilities",
            "subcategory":"Refuse",
            "type":"Services"
        }
    ],
    "sg:phone":"+64 3-386 1280",
    "sg:province":"Canterbury",
    "sg:tags":[
        "bin",
        "hire",
        "garden",
        "cleaning",
        "rubbish",
        "home"
    ],
    "wof:name":"Avon City Bin Hire",
    "wof:placetype":"venue"
},
  "geometry": {"coordinates":[172.67674299999999,-43.507465],"type":"Point"}
}