{
  "type": "Feature",
  "properties": {
    "iso:country":"NZ",
    "sg:address":"32 Vestey Dve Mt Wellington ",
    "sg:city":"Auckland",
    "sg:classifiers":[
        {
            "category":"Home & Garden",
            "subcategory":"Furniture",
            "type":"Retail Goods"
        }
    ],
    "sg:phone":"+64 9-276 0800",
    "sg:province":"Auckland",
    "sg:tags":[
        "fitting"
    ],
    "sg:website":"http://www.CavitySliders.co.nz",
    "wof:name":"CS Cavity Sliders",
    "wof:placetype":"venue"
},
  "geometry": {"coordinates":[174.83029199999999,-36.909569],"type":"Point"}
}