{
  "type": "Feature",
  "properties": {
    "addr:full":"177 A Long Dve St Heliers  Auckland Auckland",
    "addr:housenumber":"177",
    "addr:street":"A Long Dve",
    "iso:country":"NZ",
    "sg:address":"177 A Long Dve St Heliers ",
    "sg:city":"Auckland",
    "sg:classifiers":[
        {
            "category":"Food & Beverages",
            "subcategory":"Groceries & Convenience Stores",
            "type":"Retail Goods"
        }
    ],
    "sg:phone":"+64 9-575 3203",
    "sg:province":"Auckland",
    "sg:tags":[
        "foodstuff",
        "drink",
        "-"
    ],
    "wof:name":"Zebra Zu",
    "wof:placetype":"venue"
},
  "geometry": {"coordinates":[174.862976,-36.856163],"type":"Point"}
}