{
  "type": "Feature",
  "properties": {
    "iso:country":"NZ",
    "sg:address":"66 James St ",
    "sg:city":"Whangarei",
    "sg:classifiers":[
        {
            "category":"Retail",
            "subcategory":"Laundry & Dry Cleaning",
            "type":"Services"
        }
    ],
    "sg:phone":"+64 9-430 0520",
    "sg:province":"Northland",
    "sg:tags":[
        "repair",
        "clothing",
        "fabric"
    ],
    "wof:name":"James St Laundromat",
    "wof:placetype":"venue"
},
  "geometry": {"coordinates":[174.323654,-35.723331],"type":"Point"}
}