{
  "type": "Feature",
  "properties": {
    "iso:country":"NZ",
    "sg:address":"4/242 Queen St Auckland City ",
    "sg:city":"Auckland",
    "sg:classifiers":[
        {
            "category":"Education",
            "subcategory":"University",
            "type":"Public Place"
        }
    ],
    "sg:phone":"+64 9-379 3777",
    "sg:province":"Auckland",
    "sg:tags":[
        "training",
        "instruction",
        "language"
    ],
    "wof:name":"Auckland English Academy",
    "wof:placetype":"venue"
},
  "geometry": {"coordinates":[174.765137,-36.849865],"type":"Point"}
}