{
  "type": "Feature",
  "properties": {
    "addr:full":"Main Rd PakiPaki  Hastings Hawke's Bay",
    "addr:street":"Main Rd",
    "iso:country":"NZ",
    "sg:address":"Main Rd PakiPaki ",
    "sg:city":"Hastings",
    "sg:classifiers":[
        {
            "category":"Manufacturing",
            "subcategory":"Glass & Minerals",
            "type":"Manufacturing & Wholesale Goods"
        }
    ],
    "sg:phone":"+64 6-878 9228",
    "sg:province":"Hawke's Bay",
    "sg:tags":[
        "lime",
        "raw",
        "industrial",
        "materials"
    ],
    "wof:name":"Firth Industries",
    "wof:placetype":"venue"
},
  "geometry": {"coordinates":[176.792374,-39.697292],"type":"Point"}
}