{
  "type": "Feature",
  "properties": {
    "iso:country":"NZ",
    "sg:address":"7 Nicolaus St Upper ",
    "sg:city":"Hutt",
    "sg:orig_category":"Farming: Agriculture: Agricultural Contractors",
    "sg:phone":"+64 4-527 9419",
    "sg:province":"Wellington",
    "wof:name":"Agricontracts Hutt Ltd",
    "wof:placetype":"venue"
},
  "geometry": {"coordinates":[175.069031,-41.12458],"type":"Point"}
}