{
  "type": "Feature",
  "properties": {
    "iso:country":"NZ",
    "sg:address":"1/225 Henderson Valley Rd Henderson ",
    "sg:city":"Auckland",
    "sg:classifiers":[
        {
            "category":"Winery",
            "type":"Food & Drink"
        }
    ],
    "sg:phone":"+64 9-836 4949",
    "sg:province":"Auckland",
    "sg:tags":[
        "wining",
        "vineyard",
        "dining"
    ],
    "wof:name":"Artisan Wines Ltd",
    "wof:placetype":"venue"
},
  "geometry": {"coordinates":[174.614151,-36.897072],"type":"Point"}
}