{
  "type": "Feature",
  "properties": {
    "iso:country":"NZ",
    "sg:address":"52-54 Union St ",
    "sg:city":"Milton",
    "sg:orig_category":"Sports And Leisure: General: Clubs",
    "sg:phone":"+64 3-417 8456",
    "wof:name":"Bruce Country Club Inc",
    "wof:placetype":"venue"
},
  "geometry": {"coordinates":[-71.096184,42.260254],"type":"Point"}
}