{
  "type": "Feature",
  "properties": {
    "addr:full":"18 Albert St  Rangiora Canterbury",
    "addr:housenumber":"18",
    "addr:street":"Albert St",
    "iso:country":"NZ",
    "sg:address":"18 Albert St ",
    "sg:city":"Rangiora",
    "sg:classifiers":[
        {
            "category":"Retail",
            "subcategory":"Funeral Services",
            "type":"Services"
        }
    ],
    "sg:phone":"+64 3-313 8222",
    "sg:province":"Canterbury",
    "sg:tags":[
        "arrangements",
        "arrangement"
    ],
    "wof:name":"Gulliver & Tyler Ltd",
    "wof:placetype":"venue"
},
  "geometry": {"coordinates":[172.59732099999999,-43.302036],"type":"Point"}
}