{
  "type": "Feature",
  "properties": {
    "addr:full":"112 Hamurana Rd  Omokoroa",
    "addr:housenumber":"112",
    "addr:street":"Hamurana Rd",
    "iso:country":"NZ",
    "sg:address":"112 Hamurana Rd ",
    "sg:city":"Omokoroa",
    "sg:classifiers":[
        {
            "category":"Building & Trades",
            "subcategory":"Construction",
            "type":"Services"
        }
    ],
    "sg:phone":"+64 272 805 722",
    "sg:tags":[
        "home",
        "garden",
        "related",
        "plasterer"
    ],
    "wof:name":"Paradise Coatings",
    "wof:placetype":"venue"
},
  "geometry": {"coordinates":[176.03967299999999,-37.63847],"type":"Point"}
}