{
  "type": "Feature",
  "properties": {
    "iso:country":"NZ",
    "sg:address":"61 Tukapa St New ",
    "sg:city":"Plymouth",
    "sg:classifiers":[
        {
            "category":"Fast Food",
            "type":"Food & Drink"
        }
    ],
    "sg:phone":"+64 6-753 9316",
    "sg:province":"Taranaki",
    "sg:tags":[
        "wining",
        "dining",
        "takeaway"
    ],
    "wof:name":"Westown Fish Supplies",
    "wof:placetype":"venue"
},
  "geometry": {"coordinates":[-116.819725,43.97221],"type":"Point"}
}