{
  "type": "Feature",
  "properties": {
    "iso:country":"NZ",
    "sg:address":"Connett Rd East Bell Block New ",
    "sg:city":"Plymouth",
    "sg:classifiers":[
        {
            "category":"Professional",
            "subcategory":"Engineering",
            "type":"Services"
        }
    ],
    "sg:phone":"+64 6-755 1177",
    "sg:province":"Taranaki",
    "sg:tags":[
        "industrial"
    ],
    "sg:website":"http://www.yellowpages.co.nz/for/c-o-concrete/dp29324.html",
    "wof:name":"C & O Concrete Products Ltd",
    "wof:placetype":"venue"
},
  "geometry": {"coordinates":[174.14274599999999,-39.032024],"type":"Point"}
}