{
  "type": "Feature",
  "properties": {
    "addr:full":"12 Miller Ave Allenton  Ashburton Canterbury",
    "addr:housenumber":"12",
    "addr:street":"Miller Ave",
    "iso:country":"NZ",
    "sg:address":"12 Miller Ave Allenton ",
    "sg:city":"Ashburton",
    "sg:classifiers":[
        {
            "category":"Personal",
            "subcategory":"Tanning Parlor",
            "type":"Services"
        }
    ],
    "sg:phone":"+64 3-308 0274",
    "sg:province":"Canterbury",
    "sg:tags":[
        "sun",
        "health",
        "beauty"
    ],
    "wof:name":"Allentan Sunbeds",
    "wof:placetype":"venue"
},
  "geometry": {"coordinates":[171.74023399999999,-43.894146],"type":"Point"}
}