{
  "type": "Feature",
  "properties": {
    "addr:full":"Shop 7 10 Worley Pl  Hamilton Waikato",
    "addr:housenumber":"shop 7 10",
    "addr:street":"Worley Pl",
    "iso:country":"NZ",
    "sg:address":"Shop 7 10 Worley Pl ",
    "sg:city":"Hamilton",
    "sg:classifiers":[
        {
            "category":"Shopping",
            "subcategory":"Gifts & Souvenirs",
            "type":"Retail Goods"
        }
    ],
    "sg:phone":"+64 7-839 4750",
    "sg:province":"Waikato",
    "sg:tags":[
        "travel",
        "tourism"
    ],
    "wof:name":"The New Zealand Nature Company (1995) Ltd",
    "wof:placetype":"venue"
},
  "geometry": {"coordinates":[-77.671082,39.136196],"type":"Point"}
}