{
  "type": "Feature",
  "properties": {
    "iso:country":"NZ",
    "sg:address":"Bristol St Riverlands ",
    "sg:city":"Blenheim",
    "sg:classifiers":[
        {
            "category":"Sports & Exercise",
            "subcategory":"Tennis Court",
            "type":"Entertainment"
        }
    ],
    "sg:phone":"+64 3-578 3316",
    "sg:province":"Marlborough",
    "sg:tags":[
        "hobby",
        "leisure"
    ],
    "sg:website":"http://www.norski.co.nz",
    "wof:name":"Norski Holdings/ Norski Fibreglass Products Ltd",
    "wof:placetype":"venue"
},
  "geometry": {"coordinates":[174.01097100000001,-41.530647],"type":"Point"}
}