{
  "type": "Feature",
  "properties": {
    "iso:country":"NZ",
    "sg:address":"Centreplace Shopping Centre Victoria St ",
    "sg:city":"Hamilton",
    "sg:orig_category":"Clothing And Fabric: Clothing: Menswear",
    "sg:phone":"+64 7-838 3608",
    "sg:province":"Waikato",
    "wof:name":"H.B.K.",
    "wof:placetype":"venue"
},
  "geometry": {"coordinates":[175.276993,-37.783215],"type":"Point"}
}