{
  "type": "Feature",
  "properties": {
    "addr:full":"228 West Parkdale St  Tokoroa",
    "addr:housenumber":"228",
    "addr:street":"West Parkdale St",
    "iso:country":"NZ",
    "sg:address":"228 West Parkdale St ",
    "sg:city":"Tokoroa",
    "sg:orig_category":"Farming: Services: Livestock Related: Livestock Buyers/Brokers",
    "sg:phone":"+64 7-886 4944",
    "wof:name":"South Waikato Cattle Brokers Ltd",
    "wof:placetype":"venue"
},
  "geometry": {"coordinates":[175.866333,-38.226044],"type":"Point"}
}