{
  "type": "Feature",
  "properties": {
    "addr:full":"154 Queen St  Masterton Wellington",
    "addr:housenumber":"154",
    "addr:street":"Queen St",
    "iso:country":"NZ",
    "sg:address":"154 Queen St ",
    "sg:city":"Masterton",
    "sg:orig_category":"Home And Garden: Accessories: Linen",
    "sg:phone":"+64 6-377 5647",
    "sg:province":"Wellington",
    "wof:name":"Carters Linen",
    "wof:placetype":"venue"
},
  "geometry": {"coordinates":[175.66076699999999,-40.950188],"type":"Point"}
}