{
  "type": "Feature",
  "properties": {
    "addr:full":"Fire # 18, Miki Miki Rd RD 1  Masterton Wellington",
    "addr:housenumber":"1",
    "addr:street":"Miki Miki Rd Rd",
    "iso:country":"NZ",
    "sg:address":"Fire # 18, Miki Miki Rd RD 1 ",
    "sg:city":"Masterton",
    "sg:classifiers":[
        {
            "category":"Shopping",
            "subcategory":"Gifts & Souvenirs",
            "type":"Retail Goods"
        }
    ],
    "sg:phone":"+64 25575133",
    "sg:province":"Wellington",
    "sg:tags":[
        "shop",
        "gifts",
        "supplier"
    ],
    "wof:name":"Larkspur Lane",
    "wof:placetype":"venue"
},
  "geometry": {"coordinates":[175.65733299999999,-40.94931],"type":"Point"}
}