{
  "type": "Feature",
  "properties": {
    "addr:full":"Stoneycreek Rd  Opotiki",
    "addr:street":"Stoneycreek Rd",
    "iso:country":"NZ",
    "sg:address":"Stoneycreek Rd ",
    "sg:city":"Opotiki",
    "sg:orig_category":"Farming: Services: Packhouses",
    "sg:phone":"+64 7-315 5226",
    "wof:name":"EastPack Limited",
    "wof:placetype":"venue"
},
  "geometry": {"coordinates":[177.28680399999999,-38.025028],"type":"Point"}
}