{
  "type": "Feature",
  "properties": {
    "addr:full":"263 Stafford St  Timaru Canterbury",
    "addr:housenumber":"263",
    "addr:street":"Stafford St",
    "iso:country":"NZ",
    "sg:address":"263 Stafford St ",
    "sg:city":"Timaru",
    "sg:orig_category":"Clothing And Fabric: Clothing: Women'S Fashions",
    "sg:phone":"+64 3-688 1553",
    "sg:province":"Canterbury",
    "wof:name":"Zinnias",
    "wof:placetype":"venue"
},
  "geometry": {"coordinates":[171.251801,-44.394508],"type":"Point"}
}