{
  "type": "Feature",
  "properties": {
    "iso:country":"NZ",
    "sg:address":"59 MacKay St ",
    "sg:city":"Greymouth",
    "sg:orig_category":"Shopping: Sports Retailers: Sports Goods: Sporting Goods",
    "sg:phone":"+64 3-768 6513",
    "sg:province":"West Coast",
    "wof:name":"Westside Surf & Ski",
    "wof:placetype":"venue"
},
  "geometry": {"coordinates":[171.21005199999999,-42.44865],"type":"Point"}
}