{
  "type": "Feature",
  "properties": {
    "addr:full":"Lower  Hutt Wellington",
    "iso:country":"NZ",
    "sg:address":"Lower ",
    "sg:city":"Hutt",
    "sg:orig_category":"Home And Garden: Children: Child Related: Children'S Entertainment",
    "sg:phone":"+64 4-563 5891",
    "sg:province":"Wellington",
    "wof:name":"Edward Hall Magician",
    "wof:placetype":"venue"
},
  "geometry": {"coordinates":[174.904526,-41.208431],"type":"Point"}
}