{
  "type": "Feature",
  "properties": {
    "addr:full":"89 Brighams Creek Rd Whenuapai  Auckland Auckland",
    "addr:housenumber":"89",
    "addr:street":"Brighams Creek Rd",
    "iso:country":"NZ",
    "sg:address":"89 Brighams Creek Rd Whenuapai ",
    "sg:city":"Auckland",
    "sg:orig_category":"Shopping: Retail Stores: Supermarkets",
    "sg:phone":"+64 9-416 8813",
    "sg:province":"Auckland",
    "wof:name":"Shree Superette",
    "wof:placetype":"venue"
},
  "geometry": {"coordinates":[174.616455,-36.793461],"type":"Point"}
}