{
  "type": "Feature",
  "properties": {
    "addr:full":"6/12 Maleme St Greerton  Tauranga Bay of Plenty",
    "addr:housenumber":"6 / 12",
    "addr:street":"Maleme St",
    "iso:country":"NZ",
    "sg:address":"6/12 Maleme St Greerton ",
    "sg:city":"Tauranga",
    "sg:orig_category":"Industrial: Packaging: Packaging - General",
    "sg:phone":"+64 7-541 0011",
    "sg:province":"Bay of Plenty",
    "wof:name":"Busy Bee Cartons Ltd",
    "wof:placetype":"venue"
},
  "geometry": {"coordinates":[176.14082300000001,-37.736813],"type":"Point"}
}