{
  "type": "Feature",
  "properties": {
    "addr:full":"6 Turnbull St  Timaru Canterbury",
    "addr:housenumber":"6",
    "addr:street":"Turnbull St",
    "iso:country":"NZ",
    "sg:address":"6 Turnbull St ",
    "sg:city":"Timaru",
    "sg:classifiers":[
        {
            "category":"Manufacturing",
            "subcategory":"Motor Vehicles & Parts",
            "type":"Manufacturing & Wholesale Goods"
        }
    ],
    "sg:phone":"+64 3-688 6148",
    "sg:province":"Canterbury",
    "sg:tags":[
        "air conditioning",
        "automotive",
        "supplies"
    ],
    "wof:name":"Masterchill Refrigeration-Airconditioning Ltd",
    "wof:placetype":"venue"
},
  "geometry": {"coordinates":[171.25732400000001,-44.400002],"type":"Point"}
}