{
  "type": "Feature",
  "properties": {
    "addr:full":"79 Grafton Rd  Grafton",
    "addr:housenumber":"79",
    "addr:street":"Grafton Rd",
    "iso:country":"NZ",
    "sg:address":"79 Grafton Rd ",
    "sg:city":"Grafton",
    "sg:orig_category":"Farming: Farms - General: Poultry",
    "sg:phone":"+64 800 246 657",
    "wof:name":"Friis Distributors Ltd",
    "wof:placetype":"venue"
},
  "geometry": {"coordinates":[-71.68487500000001,42.205925],"type":"Point"}
}