{
  "type": "Feature",
  "properties": {
    "iso:country":"NZ",
    "sg:address":"PO Box 47 ",
    "sg:city":"Waipapa",
    "sg:orig_category":"Transport: Transportation: Heavy Haulage",
    "sg:phone":"+64 274 741 955",
    "wof:name":"Bay Boat Haul",
    "wof:placetype":"venue"
},
  "geometry": {"coordinates":[176.591797,-39.942024],"type":"Point"}
}