{
  "type": "Feature",
  "properties": {
    "addr:full":"120 Queens Dve Lower Hutt  Wellington Wellington",
    "addr:housenumber":"120",
    "addr:street":"Queens Dve Lower",
    "iso:country":"NZ",
    "sg:address":"120 Queens Dve Lower Hutt ",
    "sg:city":"Wellington",
    "sg:orig_category":"Shopping: Retail Stores: Antiques",
    "sg:phone":"+64 4-566 6072",
    "sg:province":"Wellington",
    "wof:name":"20th Century Collectables & Antiques",
    "wof:placetype":"venue"
},
  "geometry": {"coordinates":[174.90649400000001,-41.208679],"type":"Point"}
}