{
  "type": "Feature",
  "properties": {
    "iso:country":"NZ",
    "sg:address":"84 Houghton Bay Rd Houghton Bay ",
    "sg:city":"Wellington",
    "sg:classifiers":[
        {
            "category":"Social Services",
            "subcategory":"Child Care",
            "type":"Services"
        }
    ],
    "sg:phone":"+64 4-387 7614",
    "sg:province":"Wellington",
    "sg:tags":[
        "home",
        "garden",
        "children"
    ],
    "wof:name":"Wellington Playcentre Association",
    "wof:placetype":"venue"
},
  "geometry": {"coordinates":[174.78804,-41.332561],"type":"Point"}
}