{
  "type": "Feature",
  "properties": {
    "iso:country":"NZ",
    "sg:address":"5 North St ",
    "sg:city":"Timaru",
    "sg:classifiers":[
        {
            "category":"Retail",
            "subcategory":"Auto Repair",
            "type":"Services"
        }
    ],
    "sg:phone":"+64 3-688 9538",
    "sg:province":"Canterbury",
    "sg:tags":[
        "automotive",
        "panel",
        "servicing",
        "beater"
    ],
    "wof:name":"Noel Brady & Co Ltd",
    "wof:placetype":"venue"
},
  "geometry": {"coordinates":[171.257111,-44.400295],"type":"Point"}
}