{
  "type": "Feature",
  "properties": {
    "addr:full":"103//239 Queen St Auckland Central  Auckland Auckland",
    "addr:housenumber":"103 / / 239",
    "addr:street":"Queen St",
    "iso:country":"NZ",
    "sg:address":"103//239 Queen St Auckland Central ",
    "sg:city":"Auckland",
    "sg:classifiers":[
        {
            "category":"Shopping",
            "subcategory":"Gifts & Souvenirs",
            "type":"Retail Goods"
        }
    ],
    "sg:phone":"+64 9-309 8148",
    "sg:province":"Auckland",
    "sg:tags":[
        "shop",
        "gifts",
        "supplier"
    ],
    "wof:name":"Sunday Gift Shop",
    "wof:placetype":"venue"
},
  "geometry": {"coordinates":[174.76480100000001,-36.849861],"type":"Point"}
}