{
  "type": "Feature",
  "properties": {
    "iso:country":"NZ",
    "sg:address":"81 Brick Bay Dve Sandspit ",
    "sg:city":"Warkworth",
    "sg:classifiers":[
        {
            "category":"Banks & Credit Unions",
            "subcategory":"Investment Brokerage",
            "type":"Services"
        }
    ],
    "sg:phone":"+64 9-425 9910",
    "sg:province":"Auckland",
    "sg:tags":[
        "services",
        "industrial",
        "refrigeration",
        "servicing"
    ],
    "wof:name":"Finnemore Refrigeration Ltd",
    "wof:placetype":"venue"
},
  "geometry": {"coordinates":[174.723312,-36.39341],"type":"Point"}
}