{
  "type": "Feature",
  "properties": {
    "iso:country":"NZ",
    "sg:address":"136 Worcester St ",
    "sg:city":"Christchurch",
    "sg:classifiers":[
        {
            "category":"Shopping",
            "subcategory":"Pharmacy",
            "type":"Retail Goods"
        }
    ],
    "sg:phone":"+64 3-379 3793",
    "sg:province":"Canterbury",
    "sg:tags":[
        "products",
        "medical",
        "health",
        "beauty",
        "supply"
    ],
    "wof:name":"A R Harris Co Ltd",
    "wof:placetype":"venue"
},
  "geometry": {"coordinates":[172.640396,-43.531078],"type":"Point"}
}