{
  "type": "Feature",
  "properties": {
    "iso:country":"NZ",
    "sg:address":"111 Dent St ",
    "sg:city":"Whangarei",
    "sg:classifiers":[
        {
            "category":"Professional",
            "subcategory":"Management & Consulting",
            "type":"Services"
        }
    ],
    "sg:phone":"+64 9-438 1269",
    "sg:province":"Northland",
    "sg:tags":[
        "consultant",
        "training",
        "education"
    ],
    "wof:name":"Kip McGrath Education Centre",
    "wof:placetype":"venue"
},
  "geometry": {"coordinates":[174.327225,-35.726109],"type":"Point"}
}