{
  "type": "Feature",
  "properties": {
    "iso:country":"NZ",
    "sg:address":"7a Norfolk Road, R D 2 ",
    "sg:city":"Morrinsville",
    "sg:orig_category":"Automotive: Accessories: Motor Accessories",
    "sg:phone":"+64 7-889 3573",
    "sg:province":"Waikato",
    "wof:name":"Style Boyz",
    "wof:placetype":"venue"
},
  "geometry": {"coordinates":[-79.884201,41.141449],"type":"Point"}
}