{
  "type": "Feature",
  "properties": {
    "iso:country":"NZ",
    "sg:address":"55 Carthew St ",
    "sg:city":"Okato",
    "sg:orig_category":"Home And Garden: Accessories: Kitchenware",
    "sg:phone":"+64 6-752 4455",
    "wof:name":"Kitchen Adventures Ltd",
    "wof:placetype":"venue"
},
  "geometry": {"coordinates":[173.87876900000001,-39.190113],"type":"Point"}
}