{
  "type": "Feature",
  "properties": {
    "addr:full":"305 High St South  Carterton",
    "addr:housenumber":"305",
    "addr:street":"High St South",
    "iso:country":"NZ",
    "sg:address":"305 High St South ",
    "sg:city":"Carterton",
    "sg:orig_category":"Industrial: Engineering: Engineers: Engineers - General",
    "sg:phone":"+64 6-379 8435",
    "wof:name":"De Schot & Son",
    "wof:placetype":"venue"
},
  "geometry": {"coordinates":[-82.190933,36.941956],"type":"Point"}
}