{
  "type": "Feature",
  "properties": {
    "addr:full":"38 Queen St  Waimate",
    "addr:housenumber":"38",
    "addr:street":"Queen St",
    "iso:country":"NZ",
    "sg:address":"38 Queen St ",
    "sg:city":"Waimate",
    "sg:orig_category":"Shopping: Retail Stores: Florist Accessories",
    "sg:phone":"+64 3-689 7046",
    "wof:name":"Margaret's Flower Shoppe",
    "wof:placetype":"venue"
},
  "geometry": {"coordinates":[171.04478499999999,-44.735359],"type":"Point"}
}