{
  "type": "Feature",
  "properties": {
    "addr:full":"10 Montgomery Ave Murrays Bay  Auckland Auckland",
    "addr:housenumber":"10",
    "addr:street":"Montgomery Ave",
    "iso:country":"NZ",
    "sg:address":"10 Montgomery Ave Murrays Bay ",
    "sg:city":"Auckland",
    "sg:orig_category":"Health And Beauty: Specialists: Physiotherapists",
    "sg:phone":"+64 9-479 6240",
    "sg:province":"Auckland",
    "wof:name":"Bomer Wendelien",
    "wof:placetype":"venue"
},
  "geometry": {"coordinates":[174.74894699999999,-36.726219],"type":"Point"}
}