{
  "type": "Feature",
  "properties": {
    "addr:full":"575 Dominion Rd Balmoral  Auckland Auckland",
    "addr:housenumber":"575",
    "addr:street":"Dominion Rd",
    "iso:country":"NZ",
    "sg:address":"575 Dominion Rd Balmoral ",
    "sg:city":"Auckland",
    "sg:classifiers":[
        {
            "category":"Personal",
            "subcategory":"Beauty Salon",
            "type":"Services"
        }
    ],
    "sg:phone":"+64 9-630 7133",
    "sg:province":"Auckland",
    "sg:tags":[
        "therapy",
        "health"
    ],
    "wof:name":"Natural Beauty",
    "wof:placetype":"venue"
},
  "geometry": {"coordinates":[174.74821499999999,-36.884689],"type":"Point"}
}