{
  "type": "Feature",
  "properties": {
    "addr:full":"Kauri Heights Farm Miranda RD 1 Pokeno  Pukekohe Auckland",
    "addr:street":"Kauri Heights Farm Miranda Rd 1 Pokeno",
    "iso:country":"NZ",
    "sg:address":"Kauri Heights Farm Miranda RD 1 Pokeno ",
    "sg:city":"Pukekohe",
    "sg:orig_category":"Home And Garden: Gardening: Services: Landscape Architects",
    "sg:phone":"+64 9-232 7733",
    "sg:province":"Auckland",
    "wof:name":"Country Landscape Architect",
    "wof:placetype":"venue"
},
  "geometry": {"coordinates":[174.930252,-37.195728],"type":"Point"}
}