{
  "type": "Feature",
  "properties": {
    "addr:full":"PO Box 2374  Tauranga Bay of Plenty",
    "addr:housenumber":"po;2374",
    "addr:street":"Box",
    "iso:country":"NZ",
    "sg:address":"PO Box 2374 ",
    "sg:city":"Tauranga",
    "sg:classifiers":[
        {
            "category":"Retail",
            "subcategory":"Laundry & Dry Cleaning",
            "type":"Services"
        }
    ],
    "sg:phone":"+64 7-552 0234",
    "sg:province":"Bay of Plenty",
    "sg:tags":[
        "product",
        "wool",
        "clothing",
        "fabric"
    ],
    "wof:name":"Cashmere Processors 2000 Ltd",
    "wof:placetype":"venue"
},
  "geometry": {"coordinates":[176.144745,-37.703156],"type":"Point"}
}