{
  "type": "Feature",
  "properties": {
    "addr:full":"122 Grange Rd Otumoetai  Tauranga Bay of Plenty",
    "addr:housenumber":"122",
    "addr:street":"Grange Rd",
    "iso:country":"NZ",
    "sg:address":"122 Grange Rd Otumoetai ",
    "sg:city":"Tauranga",
    "sg:classifiers":[
        {
            "category":"Food & Beverages",
            "subcategory":"Bakery",
            "type":"Retail Goods"
        }
    ],
    "sg:phone":"+64 7-576 0075",
    "sg:province":"Bay of Plenty",
    "sg:tags":[
        "shop",
        "cake",
        "drink",
        "-"
    ],
    "wof:name":"Cakecraft & Decorating Supplies",
    "wof:placetype":"venue"
},
  "geometry": {"coordinates":[176.147018,-37.676498],"type":"Point"}
}