{
  "type": "Feature",
  "properties": {
    "addr:full":"20 Victoria St Petone Lower  Hutt Wellington",
    "addr:housenumber":"20",
    "addr:street":"Victoria St",
    "iso:country":"NZ",
    "sg:address":"20 Victoria St Petone Lower ",
    "sg:city":"Hutt",
    "sg:orig_category":"Industrial: Metal: Services: Anodisers",
    "sg:phone":"+64 4-568 5440",
    "sg:province":"Wellington",
    "wof:name":"Interlock Anodising",
    "wof:placetype":"venue"
},
  "geometry": {"coordinates":[174.87321499999999,-41.225971],"type":"Point"}
}