{
  "type": "Feature",
  "properties": {
    "addr:full":"72 Mowbray St Waltham  Christchurch Canterbury",
    "addr:housenumber":"72",
    "addr:street":"Mowbray St",
    "iso:country":"NZ",
    "sg:address":"72 Mowbray St Waltham ",
    "sg:city":"Christchurch",
    "sg:orig_category":"Industrial: Equipment And Machinery: Generators",
    "sg:phone":"+64 3-374 3211",
    "sg:province":"Canterbury",
    "wof:name":"Electro-Tech Services Ltd",
    "wof:placetype":"venue"
},
  "geometry": {"coordinates":[172.65130600000001,-43.545254],"type":"Point"}
}