{
  "type": "Feature",
  "properties": {
    "addr:full":"97 Manukau Rd Epsom  Auckland Auckland",
    "addr:housenumber":"97",
    "addr:street":"Manukau Rd",
    "iso:country":"NZ",
    "sg:address":"97 Manukau Rd Epsom ",
    "sg:city":"Auckland",
    "sg:classifiers":[
        {
            "category":"Education",
            "subcategory":"Special Training",
            "type":"Public Place"
        }
    ],
    "sg:phone":"+64 9-631 5252",
    "sg:province":"Auckland",
    "sg:tags":[
        "tutor",
        "coach",
        "teacher"
    ],
    "wof:name":"Epsom Institute of Education",
    "wof:placetype":"venue"
},
  "geometry": {"coordinates":[174.776352,-36.87851],"type":"Point"}
}