{
  "type": "Feature",
  "properties": {
    "iso:country":"NZ",
    "sg:address":"27 Shotover St ",
    "sg:city":"Queenstown",
    "sg:classifiers":[
        {
            "category":"Shopping",
            "subcategory":"Bicycles & Sporting Goods",
            "type":"Retail Goods"
        }
    ],
    "sg:phone":"+64 3-442 4884",
    "sg:province":"Otago",
    "sg:tags":[
        "sport",
        "retailer"
    ],
    "sg:website":"http://www.queststore.co.nz",
    "wof:name":"Quest",
    "wof:placetype":"venue"
},
  "geometry": {"coordinates":[-76.157791,38.990379],"type":"Point"}
}