{
  "type": "Feature",
  "properties": {
    "addr:full":"Unit/43a Linwood Ave Mt Albert  Auckland Canterbury",
    "addr:housenumber":"/ 43a",
    "addr:street":"Linwood Ave",
    "iso:country":"NZ",
    "sg:address":"Unit/43a Linwood Ave Mt Albert ",
    "sg:city":"Auckland",
    "sg:classifiers":[
        {
            "category":"Food & Beverages",
            "subcategory":"Fruits & Vegetables",
            "type":"Retail Goods"
        }
    ],
    "sg:phone":"+64 9-815 0010",
    "sg:province":"Canterbury",
    "sg:tags":[
        "product",
        "drink",
        "organic",
        "veges"
    ],
    "wof:name":"Organic Home Delivery",
    "wof:placetype":"venue"
},
  "geometry": {"coordinates":[174.725021,-36.872482],"type":"Point"}
}