{
  "type": "Feature",
  "properties": {
    "iso:country":"NZ",
    "sg:address":"61 Clyde St ",
    "sg:city":"Ohakune",
    "sg:orig_category":"Automotive: Parts And Supplies: Tyres",
    "sg:phone":"+64 6-385 9440",
    "wof:name":"Ruapehu Tyres 2000",
    "wof:placetype":"venue"
},
  "geometry": {"coordinates":[175.39721700000001,-39.414413],"type":"Point"}
}