{
  "type": "Feature",
  "properties": {
    "addr:full":"PO Box 20046 Wellington South  Wellington Wellington",
    "addr:housenumber":"po box 20046",
    "iso:country":"NZ",
    "sg:address":"PO Box 20046 Wellington South ",
    "sg:city":"Wellington",
    "sg:classifiers":[
        {
            "category":"Utilities",
            "subcategory":"Sewage",
            "type":"Services"
        }
    ],
    "sg:phone":"+64 4-383 6023",
    "sg:province":"Wellington",
    "sg:tags":[
        "home",
        "tank",
        "garden",
        "septic"
    ],
    "wof:name":"Wellington Liquid Waste",
    "wof:placetype":"venue"
},
  "geometry": {"coordinates":[174.980042,-40.930645],"type":"Point"}
}