{
  "type": "Feature",
  "properties": {
    "iso:country":"NZ",
    "sg:address":"105 Grandview Rd Nawton ",
    "sg:city":"Hamilton",
    "sg:orig_category":"Shopping: Retail Stores: Secondhand Dealers",
    "sg:phone":"+64 7-846 3353",
    "sg:province":"Waikato",
    "wof:name":"Western Community Centre HHFS",
    "wof:placetype":"venue"
},
  "geometry": {"coordinates":[175.23764,-37.780216],"type":"Point"}
}