{
  "type": "Feature",
  "properties": {
    "iso:country":"NZ",
    "sg:address":"Arawa St ",
    "sg:city":"Rotorua",
    "sg:classifiers":[
        {
            "category":"Health Services",
            "subcategory":"Doctor",
            "type":"Services"
        }
    ],
    "sg:phone":"+64 7-348 1000",
    "sg:province":"Bay of Plenty",
    "sg:tags":[
        "specialists",
        "surgery",
        "cosmetic",
        "beauty"
    ],
    "wof:name":"Weaver Dr Paul R",
    "wof:placetype":"venue"
},
  "geometry": {"coordinates":[176.255249,-38.134884],"type":"Point"}
}