{
  "type": "Feature",
  "properties": {
    "iso:country":"NZ",
    "sg:address":"489 Blenheim Rd Sockburn ",
    "sg:city":"Christchurch",
    "sg:orig_category":"Industrial: Metal: Scrap Metal Dealers",
    "sg:phone":"+64 3-348 3191",
    "sg:province":"Canterbury",
    "wof:name":"Cupra Recovery Ltd",
    "wof:placetype":"venue"
},
  "geometry": {"coordinates":[172.564667,-43.539417],"type":"Point"}
}