{
  "type": "Feature",
  "properties": {
    "addr:full":"Unit 4 5 Manga Rd Silverdale Hibiscus  Hibiscus Coast Auckland",
    "addr:housenumber":"unit;5",
    "addr:street":"Manga Rd",
    "iso:country":"NZ",
    "sg:address":"Unit 4 5 Manga Rd Silverdale Hibiscus ",
    "sg:city":"Hibiscus Coast",
    "sg:orig_category":"Transport: Boats And Marine: Products",
    "sg:phone":"+64 9-426 0014",
    "sg:province":"Auckland",
    "wof:name":"Coastal Outboards & Spares",
    "wof:placetype":"venue"
},
  "geometry": {"coordinates":[174.68138099999999,-36.621834],"type":"Point"}
}