{
  "type": "Feature",
  "properties": {
    "iso:country":"NZ",
    "sg:address":"Unit 4 5 Manga Rd Silverdale Hibiscus ",
    "sg:city":"Hibiscus Coast",
    "sg:orig_category":"Transport: Boats And Marine: Products",
    "sg:phone":"+64 9-426 0014",
    "sg:province":"Auckland",
    "wof:name":"Coastal Outboards & Spares",
    "wof:placetype":"venue"
},
  "geometry": {"coordinates":[174.681381,-36.621834],"type":"Point"}
}