{
  "type": "Feature",
  "properties": {
    "addr:full":"Hereford St Linwood  Christchurch Canterbury",
    "addr:street":"Hereford St",
    "iso:country":"NZ",
    "sg:address":"Hereford St Linwood ",
    "sg:city":"Christchurch",
    "sg:classifiers":[
        {
            "category":"Banks & Credit Unions",
            "subcategory":"Bureau De Change",
            "type":"Services"
        }
    ],
    "sg:phone":"+64 3-381 1196",
    "sg:province":"Canterbury",
    "sg:tags":[
        "product",
        "arrangements",
        "funeral",
        "memorial"
    ],
    "wof:name":"The Keepsake Company",
    "wof:placetype":"venue"
},
  "geometry": {"coordinates":[172.66329999999999,-43.531994],"type":"Point"}
}