{
  "type": "Feature",
  "properties": {
    "iso:country":"NZ",
    "sg:address":"87 Main Hwy Ellerslie ",
    "sg:city":"Auckland",
    "sg:classifiers":[
        {
            "category":"Banks & Credit Unions",
            "subcategory":"Bureau De Change",
            "type":"Services"
        }
    ],
    "sg:phone":"+64 9-525 0484",
    "sg:province":"Auckland",
    "sg:tags":[
        "stamp",
        "games",
        "shopping",
        "hobby"
    ],
    "wof:name":"East City Stamps Limited",
    "wof:placetype":"venue"
},
  "geometry": {"coordinates":[174.80867,-36.897812],"type":"Point"}
}