{
  "type": "Feature",
  "properties": {
    "iso:country":"NZ",
    "sg:address":"Vogel St ",
    "sg:city":"Gisborne",
    "sg:orig_category":"Sports And Leisure: Arts: Theatres",
    "sg:phone":"+64 6-863 1603",
    "sg:province":"Gisborne",
    "wof:name":"Lawson Field Theatre",
    "wof:placetype":"venue"
},
  "geometry": {"coordinates":[178.03079199999999,-38.665844],"type":"Point"}
}