{
  "type": "Feature",
  "properties": {
    "addr:full":"Bridge St  Opotiki",
    "addr:street":"Bridge",
    "iso:country":"NZ",
    "sg:address":"Bridge St ",
    "sg:city":"Opotiki",
    "sg:classifiers":[
        {
            "category":"Retail",
            "subcategory":"Auto Repair",
            "type":"Services"
        }
    ],
    "sg:phone":"+64 7-315 6603",
    "sg:tags":[
        "breakdown",
        "automotive",
        "towing",
        "servicing"
    ],
    "wof:name":"Opotiki Towing & Storage",
    "wof:placetype":"venue"
},
  "geometry": {"coordinates":[177.275879,-38.012253],"type":"Point"}
}