{
  "type": "Feature",
  "properties": {
    "iso:country":"NZ",
    "sg:address":"11 Cam Rd ",
    "sg:city":"Kaiapoi",
    "sg:classifiers":[
        {
            "category":"Building & Trades",
            "subcategory":"Construction",
            "type":"Services"
        }
    ],
    "sg:phone":"+64 3-327 8344",
    "sg:tags":[
        "home",
        "garden",
        "related",
        "plasterer"
    ],
    "wof:name":"Miller's Plastering & Tiling Ltd",
    "wof:placetype":"venue"
},
  "geometry": {"coordinates":[172.64849899999999,-43.373055],"type":"Point"}
}