{
  "type": "Feature",
  "properties": {
    "addr:full":"585 Tremaine Ave Palmerston  Palmerston North Manawatu-Wanganui",
    "addr:housenumber":"585",
    "addr:street":"Tremaine Ave",
    "iso:country":"NZ",
    "sg:address":"585 Tremaine Ave Palmerston ",
    "sg:city":"Palmerston North",
    "sg:orig_category":"Industrial: Packaging: Cups And Containers",
    "sg:phone":"+64 6-358 5505",
    "sg:province":"Manawatu-Wanganui",
    "wof:name":"Propak Supplies",
    "wof:placetype":"venue"
},
  "geometry": {"coordinates":[175.60365300000001,-40.34227],"type":"Point"}
}