{
  "type": "Feature",
  "properties": {
    "addr:full":"295 Downs Road, R D 3 Wyndham  Edendale Canterbury",
    "addr:housenumber":"295;3",
    "addr:street":"Downs Road R D",
    "iso:country":"NZ",
    "sg:address":"295 Downs Road, R D 3 Wyndham ",
    "sg:city":"Edendale",
    "sg:classifiers":[
        {
            "category":"Professional",
            "subcategory":"Art Services",
            "type":"Services"
        }
    ],
    "sg:phone":"+64 3-206 6024",
    "sg:province":"Canterbury",
    "sg:tags":[
        "personal",
        "photographer",
        "services",
        "garden",
        "home"
    ],
    "wof:name":"Vicki Mae Stenton-Photographer",
    "wof:placetype":"venue"
},
  "geometry": {"coordinates":[168.786484,-46.314644],"type":"Point"}
}