{
  "type": "Feature",
  "properties": {
    "addr:full":"9 Chelmer St  Oamaru Otago",
    "addr:housenumber":"9",
    "addr:street":"Chelmer St",
    "iso:country":"NZ",
    "sg:address":"9 Chelmer St ",
    "sg:city":"Oamaru",
    "sg:classifiers":[
        {
            "category":"Home & Garden",
            "subcategory":"Building Materials",
            "type":"Retail Goods"
        }
    ],
    "sg:phone":"+64 3-434 1166",
    "sg:province":"Otago",
    "sg:tags":[
        "electrician",
        "related"
    ],
    "wof:name":"First Call Electrical",
    "wof:placetype":"venue"
},
  "geometry": {"coordinates":[170.96380600000001,-45.098335],"type":"Point"}
}