{
  "type": "Feature",
  "properties": {
    "addr:full":"Henderson  Auckland Auckland",
    "iso:country":"NZ",
    "sg:address":"Henderson ",
    "sg:city":"Auckland",
    "sg:orig_category":"Home And Garden: Gardening: Services: Tree Services",
    "sg:phone":"+64 800 865 487",
    "sg:province":"Auckland",
    "wof:name":"Toki Tree Services",
    "wof:placetype":"venue"
},
  "geometry": {"coordinates":[174.631226,-36.881828],"type":"Point"}
}