{
  "type": "Feature",
  "properties": {
    "iso:country":"NZ",
    "sg:address":"Nationwide ",
    "sg:city":"Waikanae",
    "sg:classifiers":[
        {
            "category":"Health Services",
            "subcategory":"Clinic",
            "type":"Services"
        }
    ],
    "sg:phone":"+64 4-293 8884",
    "sg:tags":[
        "services",
        "therapy",
        "natural",
        "beauty"
    ],
    "wof:name":"Bowen (BOWTECH) Training",
    "wof:placetype":"venue"
},
  "geometry": {"coordinates":[175.061005,-40.87318],"type":"Point"}
}