{
  "type": "Feature",
  "properties": {
    "iso:country":"NZ",
    "sg:address":"George St Palmerston ",
    "sg:city":"Palmerston North",
    "sg:orig_category":"Clothing And Fabric: Clothing: Dressmakers",
    "sg:phone":"+64 6-359 3875",
    "sg:province":"Manawatu-Wanganui",
    "wof:name":"Astoria 'Made to Measure' Studio",
    "wof:placetype":"venue"
},
  "geometry": {"coordinates":[175.60882599999999,-40.356529],"type":"Point"}
}