{
  "type": "Feature",
  "properties": {
    "iso:country":"NZ",
    "sg:address":"27 Corinna St Welcome Bay ",
    "sg:city":"Tauranga",
    "sg:classifiers":[
        {
            "category":"Autos & Motor Vehicles",
            "subcategory":"Motorcycle Sales",
            "type":"Retail Goods"
        }
    ],
    "sg:phone":"+64 7-544 4548",
    "sg:province":"Bay of Plenty",
    "sg:tags":[
        "automotive",
        "scooter",
        "leasing"
    ],
    "wof:name":"The Motorbike Shop",
    "wof:placetype":"venue"
},
  "geometry": {"coordinates":[176.20019500000001,-37.725769],"type":"Point"}
}