{
  "type": "Feature",
  "properties": {
    "addr:full":"59 B Austin St Onekawa  Napier Hawke's Bay",
    "addr:housenumber":"59",
    "addr:street":"B Austin St",
    "iso:country":"NZ",
    "sg:address":"59 B Austin St Onekawa ",
    "sg:city":"Napier",
    "sg:classifiers":[
        {
            "category":"Manufacturing",
            "subcategory":"Metals",
            "type":"Manufacturing & Wholesale Goods"
        }
    ],
    "sg:phone":"+64 6-842 1132",
    "sg:province":"Hawke's Bay",
    "sg:tags":[
        "-",
        "engineering",
        "industrial",
        "sheet",
        "engineer"
    ],
    "wof:name":"Elite Metalcraft",
    "wof:placetype":"venue"
},
  "geometry": {"coordinates":[176.879974,-39.500435],"type":"Point"}
}