{
  "type": "Feature",
  "properties": {
    "addr:full":"Spotlight Plaza Colombo St  Christchurch Canterbury",
    "addr:housenumber":"colombo",
    "addr:street":"St",
    "iso:country":"NZ",
    "sg:address":"Spotlight Plaza Colombo St ",
    "sg:city":"Christchurch",
    "sg:orig_category":"Home And Garden: Accessories: Linen",
    "sg:phone":"+64 3-365 5808",
    "sg:province":"Canterbury",
    "wof:name":"Arbuckles",
    "wof:placetype":"venue"
},
  "geometry": {"coordinates":[-76.537834,37.605659],"type":"Point"}
}