{
  "type": "Feature",
  "properties": {
    "iso:country":"NZ",
    "sg:address":"78 Coates Ave Orakei ",
    "sg:city":"Auckland",
    "sg:orig_category":"Health And Beauty: Dental: Dentists",
    "sg:phone":"+64 9-524 7705",
    "sg:province":"Auckland",
    "wof:name":"Tanner John M",
    "wof:placetype":"venue"
},
  "geometry": {"coordinates":[174.815002,-36.856316],"type":"Point"}
}