{
  "type": "Feature",
  "properties": {
    "iso:country":"NZ",
    "sg:address":"2 Ocean View Rd Cable Bay ",
    "sg:city":"Mangonui",
    "sg:classifiers":[
        {
            "category":"Home & Garden",
            "subcategory":"Carpets & Floor Coverings",
            "type":"Retail Goods"
        }
    ],
    "sg:phone":"+64 9-406 0739",
    "sg:tags":[
        "cleaning",
        "furniture"
    ],
    "wof:name":"Sell S R & C D",
    "wof:placetype":"venue"
},
  "geometry": {"coordinates":[173.529739,-34.992889],"type":"Point"}
}