{
  "type": "Feature",
  "properties": {
    "iso:country":"NZ",
    "sg:address":"PO Box 68295 Newton ",
    "sg:city":"Auckland",
    "sg:classifiers":[
        {
            "category":"Professional",
            "subcategory":"Art Services",
            "type":"Services"
        }
    ],
    "sg:phone":"+64 9-358 0550",
    "sg:province":"Auckland",
    "sg:tags":[
        "arts",
        "performing",
        "sport",
        "leisure"
    ],
    "wof:name":"Black Grace Dance Co Ltd",
    "wof:placetype":"venue"
},
  "geometry": {"coordinates":[174.754822,-36.860138],"type":"Point"}
}