{
  "type": "Feature",
  "properties": {
    "addr:full":"L3, Chamber of Commerce House, 20 Daly Street, P.O.Box 30-653, Lower Hutt 6009 Wellington",
    "addr:housenumber":"20",
    "addr:postcode":"30-653;6009",
    "addr:street":"Daly Street",
    "iso:country":"NZ",
    "sg:address":"L3, Chamber of Commerce House, 20 Daly Street, P.O.Box 30-653, Lower Hutt",
    "sg:city":"6009",
    "sg:classifiers":[
        {
            "category":"Shopping",
            "subcategory":"Computers & Home Electronics",
            "type":"Retail Goods"
        }
    ],
    "sg:phone":"+64 4-939 9821",
    "sg:province":"Wellington",
    "sg:tags":[
        "chamber",
        "commerce"
    ],
    "sg:website":"www.hutt-chamber.org.nz",
    "wof:name":"Hutt Valley Chamber of Commerce & Industry Inc",
    "wof:placetype":"venue"
},
  "geometry": {"coordinates":[174.935745,-41.191471],"type":"Point"}
}