{
  "type": "Feature",
  "properties": {
    "iso:country":"NZ",
    "sg:address":"373 St Asaph St Christchurch PO Box 22-532 ",
    "sg:city":"Christchurch",
    "sg:classifiers":[
        {
            "category":"Retail",
            "subcategory":"Storage",
            "type":"Services"
        }
    ],
    "sg:phone":"+64 3-379 3631",
    "sg:province":"Canterbury",
    "wof:name":"Coolrite Refrigeration & Air Conditioning Ltd",
    "wof:placetype":"venue"
},
  "geometry": {"coordinates":[-76.537834,37.605659],"type":"Point"}
}