{
  "type": "Feature",
  "properties": {
    "addr:full":"73 B Victoria St  Cambridge Waikato",
    "addr:housenumber":"73 b",
    "addr:street":"Victoria St",
    "iso:country":"NZ",
    "sg:address":"73 B Victoria St ",
    "sg:city":"Cambridge",
    "sg:classifiers":[
        {
            "category":"Shopping",
            "subcategory":"Crafts & Fabrics",
            "type":"Retail Goods"
        }
    ],
    "sg:phone":"+64 7-827 5000",
    "sg:province":"Waikato",
    "sg:tags":[
        "knitting",
        "wool",
        "clothing"
    ],
    "wof:name":"Busy Needles",
    "wof:placetype":"venue"
},
  "geometry": {"coordinates":[175.46868900000001,-37.89378],"type":"Point"}
}