{
  "type": "Feature",
  "properties": {
    "addr:full":"Gisborne  Gisborne Gisborne",
    "iso:country":"NZ",
    "sg:address":"Gisborne ",
    "sg:city":"Gisborne",
    "sg:classifiers":[
        {
            "category":"Airline",
            "type":"Transportation"
        }
    ],
    "sg:phone":"+64 6-867 4684",
    "sg:province":"Gisborne",
    "sg:tags":[
        "services",
        "travel",
        "tourism"
    ],
    "wof:name":"Air Gisborne Ltd",
    "wof:placetype":"venue"
},
  "geometry": {"coordinates":[178.016785,-38.663258],"type":"Point"}
}