{
  "type": "Feature",
  "properties": {
    "addr:full":"1 Accent Dve East Tamaki  Auckland Auckland",
    "addr:housenumber":"1",
    "addr:street":"Dve",
    "iso:country":"NZ",
    "sg:address":"1 Accent Dve East Tamaki ",
    "sg:city":"Auckland",
    "sg:classifiers":[
        {
            "category":"Manufacturing",
            "subcategory":"Food",
            "type":"Manufacturing & Wholesale Goods"
        }
    ],
    "sg:phone":"+64 9-274 6168",
    "sg:province":"Auckland",
    "sg:tags":[
        "drink",
        "-",
        "manufacturer"
    ],
    "sg:website":"http://www.icecream.co.nz",
    "wof:name":"Chateau Ice Cream Company",
    "wof:placetype":"venue"
},
  "geometry": {"coordinates":[174.899551,-36.949169],"type":"Point"}
}