{
  "type": "Feature",
  "properties": {
    "addr:full":"11 Napier Rd Havelock North  Hastings Hawke's Bay",
    "addr:housenumber":"11",
    "addr:street":"Napier Rd",
    "iso:country":"NZ",
    "sg:address":"11 Napier Rd Havelock North ",
    "sg:city":"Hastings",
    "sg:classifiers":[
        {
            "category":"Fast Food",
            "type":"Food & Drink"
        }
    ],
    "sg:phone":"+64 6-877 9100",
    "sg:province":"Hawke's Bay",
    "sg:tags":[
        "wining",
        "dining",
        "takeaway"
    ],
    "wof:name":"Country Fried Chicken",
    "wof:placetype":"venue"
},
  "geometry": {"coordinates":[176.87768600000001,-39.669476],"type":"Point"}
}