{
  "type": "Feature",
  "properties": {
    "iso:country":"NZ",
    "sg:address":"20 Tennyson Ave PO Box 33-1012 Takapuna ",
    "sg:city":"Auckland",
    "sg:orig_category":"Sports And Leisure: Entertainment: Entertainers",
    "sg:phone":"+64 9-486 0800",
    "sg:province":"Auckland",
    "wof:name":"Greg Lay Entertainment Ltd",
    "wof:placetype":"venue"
},
  "geometry": {"coordinates":[174.770416,-36.884109],"type":"Point"}
}