{
  "type": "Feature",
  "properties": {
    "addr:full":"265 Gt South Rd Papakura  Auckland Auckland",
    "addr:housenumber":"265",
    "addr:street":"Gt South Rd",
    "iso:country":"NZ",
    "sg:address":"265 Gt South Rd Papakura ",
    "sg:city":"Auckland",
    "sg:orig_category":"Health And Beauty: Specialists: Chiropractors",
    "sg:phone":"+64 9-299 9015",
    "sg:province":"Auckland",
    "wof:name":"Papakura South Chiropractic Clinic",
    "wof:placetype":"venue"
},
  "geometry": {"coordinates":[174.94369499999999,-37.064838],"type":"Point"}
}