{
  "type": "Feature",
  "properties": {
    "iso:country":"NZ",
    "sg:address":"40 A Victoria Rd ",
    "sg:city":"Auckland",
    "sg:classifiers":[
        {
            "category":"Health Services",
            "subcategory":"Health Practitioner",
            "type":"Services"
        }
    ],
    "sg:phone":"+64 9-445 1069",
    "sg:province":"Auckland",
    "sg:tags":[
        "services",
        "beauty",
        "acupuncturists"
    ],
    "wof:name":"Robb Peter",
    "wof:placetype":"venue"
},
  "geometry": {"coordinates":[-119.104576,36.597755],"type":"Point"}
}