{
  "type": "Feature",
  "properties": {
    "iso:country":"NZ",
    "sg:address":"611 Gt South Rd Manukau City ",
    "sg:city":"Auckland",
    "sg:classifiers":[
        {
            "category":"Retail",
            "subcategory":"Auto Repair",
            "type":"Services"
        }
    ],
    "sg:phone":"+64 9-262 3684",
    "sg:province":"Auckland",
    "sg:tags":[
        "automotive",
        "absorber",
        "shock",
        "servicing"
    ],
    "wof:name":"SAS Manukau",
    "wof:placetype":"venue"
},
  "geometry": {"coordinates":[174.88031000000001,-36.98595],"type":"Point"}
}