{
  "type": "Feature",
  "properties": {
    "iso:country":"NZ",
    "sg:address":"348 St Georges Rd North Hastings R D ",
    "sg:city":"2",
    "sg:orig_category":"Farming: Agriculture: Agricultural Spraying",
    "sg:phone":"+64 6-877 3322",
    "wof:name":"Bay Spray Ltd",
    "wof:placetype":"venue"
},
  "geometry": {"coordinates":[-6.117551,53.261539],"type":"Point"}
}