{
  "type": "Feature",
  "properties": {
    "iso:country":"NZ",
    "sg:address":"R.D. 4 ",
    "sg:city":"Hikurangi",
    "sg:orig_category":"Food And Drink: Meats: Butchers",
    "sg:phone":"+64 9-433 9833",
    "wof:name":"Home Kill Services",
    "wof:placetype":"venue"
},
  "geometry": {"coordinates":[174.285995,-35.596413],"type":"Point"}
}