{
  "type": "Feature",
  "properties": {
    "iso:country":"NZ",
    "sg:address":"Level 3, Pfizer House, 14 Normanby Rd PO Box 3998 Mt, Eden ",
    "sg:city":"Auckland",
    "sg:orig_category":"Farming: Supplies: Veterinary Supplies",
    "sg:phone":"+64 9-638 0000",
    "sg:province":"Auckland",
    "wof:name":"Pfizer Animal Health Group",
    "wof:placetype":"venue"
},
  "geometry": {"coordinates":[-111.2724,47.269852],"type":"Point"}
}