{
  "type": "Feature",
  "properties": {
    "addr:full":"503 Mt Wellington Hwy Mt Wellington  Auckland Auckland",
    "addr:housenumber":"503",
    "addr:street":"Mt Wellington Hwy",
    "iso:country":"NZ",
    "sg:address":"503 Mt Wellington Hwy Mt Wellington ",
    "sg:city":"Auckland",
    "sg:orig_category":"Industrial: Packaging: Bags",
    "sg:phone":"+64 9-573 5007",
    "sg:province":"Auckland",
    "wof:name":"American Luggage Ltd",
    "wof:placetype":"venue"
},
  "geometry": {"coordinates":[174.84123199999999,-36.924202],"type":"Point"}
}