{
  "type": "Feature",
  "properties": {
    "iso:country":"NZ",
    "sg:address":"503 Mt Wellington Hwy Mt Wellington ",
    "sg:city":"Auckland",
    "sg:orig_category":"Industrial: Packaging: Bags",
    "sg:phone":"+64 9-573 5007",
    "sg:province":"Auckland",
    "wof:name":"American Luggage Ltd",
    "wof:placetype":"venue"
},
  "geometry": {"coordinates":[174.841232,-36.924202],"type":"Point"}
}