{
  "type": "Feature",
  "properties": {
    "addr:full":"Manawatu Mail  Centre Wellington",
    "iso:country":"NZ",
    "sg:address":"Manawatu Mail ",
    "sg:city":"Centre",
    "sg:orig_category":"Home And Garden: Children: Child Related",
    "sg:phone":"+64 800 628 827",
    "sg:province":"Wellington",
    "wof:name":"Matta Products Ltd",
    "wof:placetype":"venue"
},
  "geometry": {"coordinates":[175.854187,-40.018021],"type":"Point"}
}