{
  "type": "Feature",
  "properties": {
    "addr:full":"Designer Court 370 Queen St  Masterton Wellington",
    "addr:housenumber":"370",
    "addr:street":"Designer;Queen St",
    "iso:country":"NZ",
    "sg:address":"Designer Court 370 Queen St ",
    "sg:city":"Masterton",
    "sg:orig_category":"Home And Garden: Furniture/Furnishings: Curtains",
    "sg:phone":"+64 6-377 4433",
    "sg:province":"Wellington",
    "wof:name":"Expressions",
    "wof:placetype":"venue"
},
  "geometry": {"coordinates":[175.65733299999999,-40.94931],"type":"Point"}
}