{
  "type": "Feature",
  "properties": {
    "addr:full":"State Highway 26  Morrinsville Waikato",
    "addr:street":"State Highway 26 Morrinsville",
    "iso:country":"NZ",
    "sg:address":"State Highway 26 ",
    "sg:city":"Morrinsville",
    "sg:orig_category":"Sports And Leisure: Sports: Equestrian: Horse Floats",
    "sg:phone":"+64 7-889 1947",
    "sg:province":"Waikato",
    "wof:name":"Horse Power Engineering",
    "wof:placetype":"venue"
},
  "geometry": {"coordinates":[175.53009,-37.658936],"type":"Point"}
}