{
  "type": "Feature",
  "properties": {
    "iso:country":"NZ",
    "sg:address":"62 Gore St ",
    "sg:city":"Bluff",
    "sg:classifiers":[
        {
            "category":"Bars & Pubs",
            "subcategory":"Wine Bar",
            "type":"Food & Drink"
        }
    ],
    "sg:phone":"+64 3-212 8856",
    "sg:tags":[
        "wining",
        "dining",
        "cafe"
    ],
    "wof:name":"Bluff Bakery",
    "wof:placetype":"venue"
},
  "geometry": {"coordinates":[-109.546745,37.286579],"type":"Point"}
}