{
  "type": "Feature",
  "properties": {
    "addr:full":"Wellington  Wellington Wellington",
    "iso:country":"NZ",
    "sg:address":"Wellington ",
    "sg:city":"Wellington",
    "sg:orig_category":"Home And Garden: Furniture/Furnishings: Blinds",
    "sg:phone":"+64 4-477 5594",
    "sg:province":"Wellington",
    "wof:name":"Stain Busters - Curtain Cleaning",
    "wof:placetype":"venue"
},
  "geometry": {"coordinates":[174.82162500000001,-41.325909],"type":"Point"}
}