{
  "type": "Feature",
  "properties": {
    "iso:country":"NZ",
    "sg:address":"235 Brougham St Sydenham ",
    "sg:city":"Christchurch",
    "sg:orig_category":"Industrial: Electrical/Electronic: Printed Circuits",
    "sg:phone":"+64 3-365 3884",
    "sg:province":"Canterbury",
    "wof:name":"Huntsbury Circuits",
    "wof:placetype":"venue"
},
  "geometry": {"coordinates":[172.63365200000001,-43.547428],"type":"Point"}
}