{
  "type": "Feature",
  "properties": {
    "iso:country":"NZ",
    "sg:address":"21 Heads Rd ",
    "sg:city":"Wanganui",
    "sg:classifiers":[
        {
            "category":"Autos & Motor Vehicles",
            "subcategory":"Automobile Sales",
            "type":"Retail Goods"
        }
    ],
    "sg:phone":"+64 6-345 5955",
    "sg:province":"Manawatu-Wanganui",
    "sg:tags":[
        "car",
        "-used",
        "leasing",
        "truck",
        "automotive"
    ],
    "wof:name":"Clive Spencer Motors Limited",
    "wof:placetype":"venue"
},
  "geometry": {"coordinates":[175.0457,-39.940166],"type":"Point"}
}