{
  "type": "Feature",
  "properties": {
    "iso:country":"NZ",
    "sg:address":"16 Main St ",
    "sg:city":"Blenheim",
    "sg:classifiers":[
        {
            "category":"Restaurant",
            "type":"Food & Drink"
        }
    ],
    "sg:phone":"+64 3-578 1118",
    "sg:province":"Marlborough",
    "sg:tags":[
        "wining",
        "dining"
    ],
    "wof:name":"Bamboo Garden Oriental Restaurant",
    "wof:placetype":"venue"
},
  "geometry": {"coordinates":[-79.6527099609,34.5135688782],"type":"Point"}
}