{
  "type": "Feature",
  "properties": {
    "addr:full":"348 South Rd  Hawera Taranaki",
    "addr:housenumber":"348",
    "addr:street":"South Rd",
    "iso:country":"NZ",
    "sg:address":"348 South Rd ",
    "sg:city":"Hawera",
    "sg:orig_category":"Storage: Storage",
    "sg:phone":"+64 6-278 7974",
    "sg:province":"Taranaki",
    "wof:name":"Storage & Equipment Hire",
    "wof:placetype":"venue"
},
  "geometry": {"coordinates":[174.26638800000001,-39.590435],"type":"Point"}
}