{
  "type": "Feature",
  "properties": {
    "iso:country":"NZ",
    "sg:address":"348 South Rd ",
    "sg:city":"Hawera",
    "sg:orig_category":"Storage: Storage",
    "sg:phone":"+64 6-278 7974",
    "sg:province":"Taranaki",
    "wof:name":"Storage & Equipment Hire",
    "wof:placetype":"venue"
},
  "geometry": {"coordinates":[174.266388,-39.590435],"type":"Point"}
}