{
  "type": "Feature",
  "properties": {
    "addr:full":"130 State Highway 16 Kumeu  Auckland Auckland",
    "addr:housenumber":"130",
    "addr:street":"State Highway 16",
    "iso:country":"NZ",
    "sg:address":"130 State Highway 16 Kumeu ",
    "sg:city":"Auckland",
    "sg:orig_category":"Transport: Air",
    "sg:phone":"+64 9-412 5006",
    "sg:province":"Auckland",
    "wof:name":"Associated Industries NZ Limited",
    "wof:placetype":"venue"
},
  "geometry": {"coordinates":[174.56019599999999,-36.777271],"type":"Point"}
}