{
  "type": "Feature",
  "properties": {
    "iso:country":"NZ",
    "sg:address":"The Strand ",
    "sg:city":"Whangarei",
    "sg:orig_category":"Clothing And Fabric: Clothing: Uniforms",
    "sg:phone":"+64 9-438 6566",
    "sg:province":"Auckland",
    "wof:name":"Bethells Uniforms",
    "wof:placetype":"venue"
},
  "geometry": {"coordinates":[-76.61488300000001,39.286469],"type":"Point"}
}