{
  "type": "Feature",
  "properties": {
    "iso:country":"NZ",
    "sg:address":"7 A Airdrie Rd Ranui ",
    "sg:city":"Auckland",
    "sg:classifiers":[
        {
            "category":"Farming",
            "subcategory":"Farm",
            "type":"Manufacturing & Wholesale Goods"
        }
    ],
    "sg:phone":"+64 9-833 7483",
    "sg:province":"Auckland",
    "sg:website":"http://www.yellowpages.co.nz/for/dtp/dp20342.html",
    "wof:name":"Discount Tractor Parts",
    "wof:placetype":"venue"
},
  "geometry": {"coordinates":[174.594437,-36.866119],"type":"Point"}
}