{
  "type": "Feature",
  "properties": {
    "addr:full":"PO Box 202  Katikati",
    "addr:housenumber":"po",
    "addr:street":"Box 202",
    "iso:country":"NZ",
    "sg:address":"PO Box 202 ",
    "sg:city":"Katikati",
    "sg:classifiers":[
        {
            "category":"Banks & Credit Unions",
            "subcategory":"Investment Brokerage",
            "type":"Services"
        }
    ],
    "sg:phone":"+64 7-549 0977",
    "sg:tags":[
        "personal",
        "accountant",
        "chartered",
        "-",
        "finance"
    ],
    "wof:name":"Knyvett Robert B",
    "wof:placetype":"venue"
},
  "geometry": {"coordinates":[175.92105100000001,-37.555534],"type":"Point"}
}