{
  "type": "Feature",
  "properties": {
    "iso:country":"NZ",
    "sg:address":"141 Ruahine St Palmerston ",
    "sg:city":"Palmerston North",
    "sg:orig_category":"Health And Beauty: Specialists: Chiropractors",
    "sg:phone":"+64 6-357 9784",
    "sg:province":"Manawatu-Wanganui",
    "wof:name":"Nolan Clinic of Chiropractic",
    "wof:placetype":"venue"
},
  "geometry": {"coordinates":[175.62460327150001,-40.3427085876],"type":"Point"}
}