{
  "type": "Feature",
  "properties": {
    "addr:full":"25 Bristol St Riverlands  Blenheim Marlborough",
    "addr:housenumber":"25",
    "addr:street":"Bristol St",
    "iso:country":"NZ",
    "sg:address":"25 Bristol St Riverlands ",
    "sg:city":"Blenheim",
    "sg:orig_category":"Farming: Forestry",
    "sg:phone":"+64 3-579 3563",
    "sg:province":"Marlborough",
    "sg:website":"http://www.rimuengineering.co.nz",
    "wof:name":"Rimu Portable Sawmill Systems",
    "wof:placetype":"venue"
},
  "geometry": {"coordinates":[174.010864,-41.530479],"type":"Point"}
}