{
  "type": "Feature",
  "properties": {
    "addr:full":"23/10 Airborne Rd Albany  Auckland Auckland",
    "addr:housenumber":"23 / 10",
    "addr:street":"Airborne Rd",
    "iso:country":"NZ",
    "sg:address":"23/10 Airborne Rd Albany ",
    "sg:city":"Auckland",
    "sg:orig_category":"Health And Beauty: Specialists: Podiatrists",
    "sg:phone":"+64 9-415 2003",
    "sg:province":"Auckland",
    "wof:name":"Albany Foot Health Centre",
    "wof:placetype":"venue"
},
  "geometry": {"coordinates":[174.70202599999999,-36.744118],"type":"Point"}
}