{
  "type": "Feature",
  "properties": {
    "addr:full":"Geoff Scurr  Waikouaiti",
    "iso:country":"NZ",
    "sg:address":"Geoff Scurr ",
    "sg:city":"Waikouaiti",
    "sg:classifiers":[
        {
            "category":"Manufacturing",
            "subcategory":"Glass & Minerals",
            "type":"Manufacturing & Wholesale Goods"
        }
    ],
    "sg:phone":"+64 3-465 7953",
    "sg:tags":[
        "raw",
        "industrial",
        "quarry",
        "materials"
    ],
    "wof:name":"Kilmog Quarry",
    "wof:placetype":"venue"
},
  "geometry": {"coordinates":[170.680847,-45.599018],"type":"Point"}
}