{
  "type": "Feature",
  "properties": {
    "addr:full":"157 O'Hara St  Invercargill Southland",
    "addr:housenumber":"157",
    "addr:street":"O'Hara St",
    "iso:country":"NZ",
    "sg:address":"157 O'Hara St ",
    "sg:city":"Invercargill",
    "sg:classifiers":[
        {
            "category":"Retail",
            "subcategory":"Driving School",
            "type":"Services"
        }
    ],
    "sg:phone":"+64 3-214 6123",
    "sg:province":"Southland",
    "sg:tags":[
        "training",
        "education",
        "driver"
    ],
    "wof:name":"Motorcycle and Commercial Driver Training",
    "wof:placetype":"venue"
},
  "geometry": {"coordinates":[168.35217299999999,-46.41185],"type":"Point"}
}