{
  "type": "Feature",
  "properties": {
    "iso:country":"NZ",
    "sg:address":"57 Higgins Rd ",
    "sg:city":"Hamilton",
    "sg:classifiers":[
        {
            "category":"Bus Charters",
            "type":"Transportation"
        }
    ],
    "sg:phone":"+64 7-846 1975",
    "sg:province":"Waikato",
    "sg:tags":[
        "services",
        "travel",
        "tourism"
    ],
    "wof:name":"Hamilton City Buses Ltd",
    "wof:placetype":"venue"
},
  "geometry": {"coordinates":[-87.988968,34.142426],"type":"Point"}
}