{
  "type": "Feature",
  "properties": {
    "iso:country":"NZ",
    "sg:address":"226 Main Rd ",
    "sg:city":"Tairua",
    "sg:orig_category":"Health And Beauty: Products: Pharmacies",
    "sg:phone":"+64 7-864 8660",
    "wof:name":"Tairua Pharmacy",
    "wof:placetype":"venue"
},
  "geometry": {"coordinates":[175.848465,-37.009243],"type":"Point"}
}