{
  "type": "Feature",
  "properties": {
    "addr:full":"75 Beatty St Stoke  Nelson Nelson",
    "addr:housenumber":"75",
    "addr:street":"Beatty St",
    "iso:country":"NZ",
    "sg:address":"75 Beatty St Stoke ",
    "sg:city":"Nelson",
    "sg:orig_category":"Industrial: Consultancy",
    "sg:phone":"+64 3-547 7347",
    "sg:province":"Nelson",
    "sg:website":"http://www.appliedresearch.co.nz",
    "wof:name":"Applied Research Services Ltd",
    "wof:placetype":"venue"
},
  "geometry": {"coordinates":[173.23419200000001,-41.312859],"type":"Point"}
}