{
  "type": "Feature",
  "properties": {
    "iso:country":"NZ",
    "sg:address":"75 Beatty St Stoke ",
    "sg:city":"Nelson",
    "sg:orig_category":"Industrial: Consultancy",
    "sg:phone":"+64 3-547 7347",
    "sg:province":"Nelson",
    "sg:website":"http://www.appliedresearch.co.nz",
    "wof:name":"Applied Research Services Ltd",
    "wof:placetype":"venue"
},
  "geometry": {"coordinates":[173.234192,-41.312859],"type":"Point"}
}