{
  "type": "Feature",
  "properties": {
    "addr:full":"251 Stafford St  Timaru Canterbury",
    "addr:housenumber":"251",
    "addr:street":"Stafford St",
    "iso:country":"NZ",
    "sg:address":"251 Stafford St ",
    "sg:city":"Timaru",
    "sg:classifiers":[
        {
            "category":"Shopping Center",
            "type":"Public Place"
        }
    ],
    "sg:phone":"+64 3-688 1526",
    "sg:province":"Canterbury",
    "sg:tags":[
        "mall",
        "retail",
        "stores"
    ],
    "wof:name":"Stafford Mall Administration",
    "wof:placetype":"venue"
},
  "geometry": {"coordinates":[171.25204500000001,-44.394726],"type":"Point"}
}