{
  "type": "Feature",
  "properties": {
    "addr:full":"Montgomery Square 117 G Hardy St  Nelson Nelson",
    "addr:housenumber":"117 g",
    "addr:street":"Montgomery Square;Hardy St",
    "iso:country":"NZ",
    "sg:address":"Montgomery Square 117 G Hardy St ",
    "sg:city":"Nelson",
    "sg:orig_category":"Clothing And Fabric: Clothing: Women'S Fashions",
    "sg:phone":"+64 3-548 7123",
    "sg:province":"Nelson",
    "wof:name":"Sue Edwards Boutique & Gallery",
    "wof:placetype":"venue"
},
  "geometry": {"coordinates":[-121.765488,39.553471],"type":"Point"}
}