{
  "type": "Feature",
  "properties": {
    "iso:country":"NZ",
    "sg:address":"Longacre Rd R D 12 ",
    "sg:city":"Wanganui",
    "sg:orig_category":"Home And Garden: Gardening: Products",
    "sg:phone":"+64 274 378 316",
    "sg:province":"Manawatu-Wanganui",
    "wof:name":"Calix Wholesale Nursery",
    "wof:placetype":"venue"
},
  "geometry": {"coordinates":[175.052841,-39.933369],"type":"Point"}
}