{
  "type": "Feature",
  "properties": {
    "iso:country":"NZ",
    "sg:address":"100 John St Pukekohe ",
    "sg:city":"Auckland",
    "sg:orig_category":"Sports And Leisure: Sports: Equestrian: Equestrian Supplies",
    "sg:phone":"+64 9-238 4555",
    "sg:province":"Auckland",
    "wof:name":"Hermans Saddlery Ltd",
    "wof:placetype":"venue"
},
  "geometry": {"coordinates":[-119.104576,36.597755],"type":"Point"}
}