{
  "type": "Feature",
  "properties": {
    "iso:country":"NZ",
    "sg:address":"35 Stoneden Dve East Tamaki ",
    "sg:city":"Auckland",
    "sg:classifiers":[
        {
            "category":"Home & Garden",
            "subcategory":"Building Materials",
            "type":"Retail Goods"
        }
    ],
    "sg:phone":"+64 9-273 4970",
    "sg:province":"Auckland",
    "sg:tags":[
        "door",
        "fitting",
        "fittings"
    ],
    "sg:website":"http://www.acedoors.co.nz",
    "wof:name":"Ace Doors Ltd",
    "wof:placetype":"venue"
},
  "geometry": {"coordinates":[174.887436,-36.956711],"type":"Point"}
}