{
  "type": "Feature",
  "properties": {
    "addr:full":"301 Wakefield Qy  Nelson Nelson",
    "addr:housenumber":"301",
    "addr:street":"Wakefield Qy",
    "iso:country":"NZ",
    "sg:address":"301 Wakefield Qy ",
    "sg:city":"Nelson",
    "sg:orig_category":"Shopping: Retail Stores: Secondhand Dealers",
    "sg:phone":"+64 3-548 7150",
    "sg:province":"Nelson",
    "wof:name":"Port Nelson House Parts",
    "wof:placetype":"venue"
},
  "geometry": {"coordinates":[-121.765488,39.553471],"type":"Point"}
}