{
  "type": "Feature",
  "properties": {
    "addr:full":"18 Hewlett St  Whangarei Northland",
    "addr:housenumber":"18",
    "addr:street":"Hewlett St",
    "iso:country":"NZ",
    "sg:address":"18 Hewlett St ",
    "sg:city":"Whangarei",
    "sg:classifiers":[
        {
            "category":"Marine",
            "type":"Transportation"
        }
    ],
    "sg:phone":"+64 9-459 7507",
    "sg:province":"Northland",
    "sg:tags":[
        "boats",
        "builder",
        "yacht",
        "transport",
        "boat"
    ],
    "wof:name":"Fibre Glass Concepts",
    "wof:placetype":"venue"
},
  "geometry": {"coordinates":[174.344482,-35.741795],"type":"Point"}
}