{
  "type": "Feature",
  "properties": {
    "addr:full":"355 Ricket Rd Te  Awamutu Waikato",
    "addr:housenumber":"355",
    "addr:street":"Ricket Rd",
    "iso:country":"NZ",
    "sg:address":"355 Ricket Rd Te ",
    "sg:city":"Awamutu",
    "sg:orig_category":"Farming: Machinery",
    "sg:phone":"+64 7-871 4701",
    "sg:province":"Waikato",
    "wof:name":"Mitchell Farm Services",
    "wof:placetype":"venue"
},
  "geometry": {"coordinates":[175.319244,-38.009647],"type":"Point"}
}