{
  "type": "Feature",
  "properties": {
    "iso:country":"NZ",
    "sg:address":"746 Te Rapa Rd ",
    "sg:city":"Hamilton",
    "sg:classifiers":[
        {
            "category":"Wholesale",
            "subcategory":"Hardware",
            "type":"Manufacturing & Wholesale Goods"
        }
    ],
    "sg:phone":"+64 7-849 4445",
    "sg:province":"Waikato",
    "sg:tags":[
        "gardening",
        "garden",
        "chainsaw",
        "products",
        "brush",
        "home",
        "cutter"
    ],
    "wof:name":"Te Rapa Mowers & Chainsaws",
    "wof:placetype":"venue"
},
  "geometry": {"coordinates":[175.241592,-37.753159],"type":"Point"}
}