{
  "type": "Feature",
  "properties": {
    "iso:country":"NZ",
    "sg:address":"59 Awapuni Rd ",
    "sg:city":"Gisborne",
    "sg:orig_category":"Industrial: Parts",
    "sg:phone":"+64 6-869 0170",
    "sg:province":"Manawatu-Wanganui",
    "wof:name":"McCannics",
    "wof:placetype":"venue"
},
  "geometry": {"coordinates":[177.998932,-38.669556],"type":"Point"}
}