{
  "type": "Feature",
  "properties": {
    "iso:country":"NZ",
    "sg:address":"PO BOX 275 ",
    "sg:city":"Whangarei",
    "sg:classifiers":[
        {
            "category":"Home & Garden",
            "subcategory":"Building Materials",
            "type":"Retail Goods"
        }
    ],
    "sg:phone":"+64 25722369",
    "sg:province":"Northland",
    "sg:tags":[
        "related"
    ],
    "sg:website":"http://www.wireit.co.nz",
    "wof:name":"David Capey Electrical",
    "wof:placetype":"venue"
},
  "geometry": {"coordinates":[174.320526,-35.725399],"type":"Point"}
}