{
  "type": "Feature",
  "properties": {
    "addr:full":"Cate Rd Rototuna  Hamilton Waikato",
    "addr:street":"Cate Rd",
    "iso:country":"NZ",
    "sg:address":"Cate Rd Rototuna ",
    "sg:city":"Hamilton",
    "sg:classifiers":[
        {
            "category":"Real Estate",
            "subcategory":"Real Estate Services",
            "type":"Services"
        }
    ],
    "sg:phone":"+64 7-854 3788",
    "sg:province":"Waikato",
    "sg:tags":[
        "home",
        "garden"
    ],
    "wof:name":"Eden Park Estate Limited",
    "wof:placetype":"venue"
},
  "geometry": {"coordinates":[175.26741000000001,-37.73196],"type":"Point"}
}