{
  "type": "Feature",
  "properties": {
    "iso:country":"NZ",
    "sg:address":"Ferry Rd ",
    "sg:city":"Ngatea",
    "sg:orig_category":"Home And Garden: Gardening: Products: Fertilisers",
    "sg:phone":"+64 7-867 7684",
    "wof:name":"Ravensdown Fertiliser Co-op Ltd",
    "wof:placetype":"venue"
},
  "geometry": {"coordinates":[175.493713,-37.273788],"type":"Point"}
}