{
  "type": "Feature",
  "properties": {
    "addr:full":"32 b Sheffield Cre Russley  Christchurch Canterbury",
    "addr:housenumber":"32",
    "addr:postcode":"cre;christchurch",
    "addr:street":"B",
    "iso:country":"NZ",
    "sg:address":"32 b Sheffield Cre Russley ",
    "sg:city":"Christchurch",
    "sg:orig_category":"Farming: Services: Farm Consultants",
    "sg:phone":"+64 3-358 9807",
    "sg:province":"Canterbury",
    "wof:name":"Lamb D H",
    "wof:placetype":"venue"
},
  "geometry": {"coordinates":[172.54385400000001,-43.52],"type":"Point"}
}