{
  "type": "Feature",
  "properties": {
    "addr:full":"19 Mowat St Springlands  Blenheim Marlborough",
    "addr:housenumber":"19",
    "addr:street":"Mowat St",
    "iso:country":"NZ",
    "sg:address":"19 Mowat St Springlands ",
    "sg:city":"Blenheim",
    "sg:orig_category":"Farming: Agriculture: Agricultural Contractors",
    "sg:phone":"+64 25447931",
    "sg:province":"Marlborough",
    "wof:name":"Horizon Contracting",
    "wof:placetype":"venue"
},
  "geometry": {"coordinates":[173.94009399999999,-41.502308],"type":"Point"}
}