{
  "type": "Feature",
  "properties": {
    "addr:full":"2 Island View Heights  Whakatane Bay of Plenty",
    "addr:housenumber":"2",
    "addr:street":"Island",
    "iso:country":"NZ",
    "sg:address":"2 Island View Heights ",
    "sg:city":"Whakatane",
    "sg:classifiers":[
        {
            "category":"Shopping",
            "subcategory":"Bicycles & Sporting Goods",
            "type":"Retail Goods"
        }
    ],
    "sg:phone":"+64 7-307 2258",
    "sg:province":"Bay of Plenty",
    "sg:tags":[
        "sport",
        "fishing",
        "hunting",
        "retailers"
    ],
    "wof:name":"Tuna-Too Charters",
    "wof:placetype":"venue"
},
  "geometry": {"coordinates":[176.98419200000001,-37.965305],"type":"Point"}
}