{
  "type": "Feature",
  "properties": {
    "addr:full":"Takahe St  Ahipara",
    "iso:country":"NZ",
    "sg:address":"Takahe St ",
    "sg:city":"Ahipara",
    "sg:classifiers":[
        {
            "category":"Utilities",
            "subcategory":"Sewage",
            "type":"Services"
        }
    ],
    "sg:phone":"+64 9-409 4814",
    "sg:tags":[
        "home",
        "tank",
        "garden",
        "septic"
    ],
    "wof:name":"Masters L R Bob",
    "wof:placetype":"venue"
},
  "geometry": {"coordinates":[173.15327500000001,-35.171341],"type":"Point"}
}