{
  "type": "Feature",
  "properties": {
    "addr:full":"158 York Ave Greenmeadows  Napier Hawke's Bay",
    "addr:housenumber":"158",
    "addr:street":"York Ave",
    "iso:country":"NZ",
    "sg:address":"158 York Ave Greenmeadows ",
    "sg:city":"Napier",
    "sg:classifiers":[
        {
            "category":"Building & Trades",
            "subcategory":"Construction",
            "type":"Services"
        }
    ],
    "sg:phone":"+64 6-844 6475",
    "sg:province":"Hawke's Bay",
    "sg:tags":[
        "home",
        "garden",
        "related",
        "plasterer"
    ],
    "wof:name":"APACS",
    "wof:placetype":"venue"
},
  "geometry": {"coordinates":[176.861313,-39.525143],"type":"Point"}
}