{
  "type": "Feature",
  "properties": {
    "iso:country":"NZ",
    "sg:address":"62 Rototuna Rd R D 1 ",
    "sg:city":"Hamilton",
    "sg:classifiers":[
        {
            "category":"Home & Garden",
            "subcategory":"Garden Supply",
            "type":"Retail Goods"
        }
    ],
    "sg:phone":"+64 7-854 0743",
    "sg:province":"Waikato",
    "sg:tags":[
        "products",
        "nursery",
        "gardening"
    ],
    "wof:name":"Hukanui Commercial Seedlings",
    "wof:placetype":"venue"
},
  "geometry": {"coordinates":[-84.910286,41.538616],"type":"Point"}
}