{
  "type": "Feature",
  "properties": {
    "addr:full":"26 E Portage Rd New Lynn  Auckland Auckland",
    "addr:housenumber":"26",
    "addr:street":"E Portage Rd",
    "iso:country":"NZ",
    "sg:address":"26 E Portage Rd New Lynn ",
    "sg:city":"Auckland",
    "sg:classifiers":[
        {
            "category":"Transit Center",
            "subcategory":"Freight",
            "type":"Transportation"
        }
    ],
    "sg:phone":"+64 9-827 8883",
    "sg:province":"Auckland",
    "sg:tags":[
        "distribution",
        "-",
        "transport"
    ],
    "wof:name":"Nippon South Pacific Limited",
    "wof:placetype":"venue"
},
  "geometry": {"coordinates":[174.69073499999999,-36.906403],"type":"Point"}
}