{
  "type": "Feature",
  "properties": {
    "iso:country":"NZ",
    "sg:address":"3 Pretoria St Lower ",
    "sg:city":"Hutt",
    "sg:classifiers":[
        {
            "category":"Home & Garden",
            "subcategory":"Kitchen Supply",
            "type":"Retail Goods"
        }
    ],
    "sg:phone":"+64 4-569 8861",
    "sg:province":"Wellington",
    "sg:tags":[
        "shop",
        "pet",
        "pets"
    ],
    "wof:name":"Hutt Pet Centre",
    "wof:placetype":"venue"
},
  "geometry": {"coordinates":[174.909882,-41.206421],"type":"Point"}
}