{
  "type": "Feature",
  "properties": {
    "iso:country":"NZ",
    "sg:address":"PO Box 21113 Flagstaff ",
    "sg:city":"Hamilton",
    "sg:orig_category":"Home And Garden: Gardening: Services: Landscape Design",
    "sg:phone":"+64 7-854 0775",
    "sg:province":"Waikato",
    "wof:name":"iSpy",
    "wof:placetype":"venue"
},
  "geometry": {"coordinates":[175.257019,-37.739288],"type":"Point"}
}