{
  "type": "Feature",
  "properties": {
    "addr:full":"PO Box 21113 Flagstaff  Hamilton Waikato",
    "addr:housenumber":"po box",
    "addr:postcode":"21113",
    "iso:country":"NZ",
    "sg:address":"PO Box 21113 Flagstaff ",
    "sg:city":"Hamilton",
    "sg:orig_category":"Home And Garden: Gardening: Services: Landscape Design",
    "sg:phone":"+64 7-854 0775",
    "sg:province":"Waikato",
    "wof:name":"iSpy",
    "wof:placetype":"venue"
},
  "geometry": {"coordinates":[175.25701900000001,-37.739288],"type":"Point"}
}