{
  "type": "Feature",
  "properties": {
    "addr:full":"PO Box 82308 Highland Park  Auckland Auckland",
    "addr:housenumber":"po box 82308",
    "iso:country":"NZ",
    "sg:address":"PO Box 82308 Highland Park ",
    "sg:city":"Auckland",
    "sg:classifiers":[
        {
            "category":"Arts & Performance",
            "subcategory":"Music",
            "type":"Entertainment"
        }
    ],
    "sg:phone":"+64 9-534 2747",
    "sg:province":"Auckland",
    "sg:tags":[
        "mobile",
        "sport",
        "-",
        "leisure",
        "disco"
    ],
    "wof:name":"Andy Wilsons Disco Roadshow Supply Company Ltd",
    "wof:placetype":"venue"
},
  "geometry": {"coordinates":[174.90278599999999,-36.902538],"type":"Point"}
}