{
  "type": "Feature",
  "properties": {
    "iso:country":"NZ",
    "sg:address":"2 Moore St Howick ",
    "sg:city":"Auckland",
    "sg:classifiers":[
        {
            "category":"Shopping",
            "subcategory":"Bicycles & Sporting Goods",
            "type":"Retail Goods"
        }
    ],
    "sg:phone":"+64 9-534 6773",
    "sg:province":"Auckland",
    "sg:tags":[
        "cycle",
        "sport",
        "sale",
        "retailers",
        "cycles"
    ],
    "wof:name":"Howick Mower & Cycle Centre",
    "wof:placetype":"venue"
},
  "geometry": {"coordinates":[174.932907,-36.89513],"type":"Point"}
}