{
  "type": "Feature",
  "properties": {
    "addr:full":"Cnr Victoria & Vivian St  Wellington Wellington",
    "addr:street":"Cnr Victoria & Vivian St",
    "iso:country":"NZ",
    "sg:address":"Cnr Victoria & Vivian St ",
    "sg:city":"Wellington",
    "sg:classifiers":[
        {
            "category":"Shopping",
            "subcategory":"Stationery & Office Supplies",
            "type":"Retail Goods"
        }
    ],
    "sg:phone":"+64 4-385 1462",
    "sg:province":"Wellington",
    "sg:tags":[
        "map",
        "chart"
    ],
    "wof:name":"The Map Shop",
    "wof:placetype":"venue"
},
  "geometry": {"coordinates":[174.76713599999999,-41.28054],"type":"Point"}
}