{
  "type": "Feature",
  "properties": {
    "addr:full":"15 Walter Prk  Whakatane Bay of Plenty",
    "addr:housenumber":"15",
    "addr:street":"Walter;Whakatane",
    "iso:country":"NZ",
    "sg:address":"15 Walter Prk ",
    "sg:city":"Whakatane",
    "sg:classifiers":[
        {
            "category":"Banks & Credit Unions",
            "subcategory":"Financial Services",
            "type":"Services"
        }
    ],
    "sg:phone":"+64 7-308 5557",
    "sg:province":"Bay of Plenty",
    "sg:tags":[
        "livestock",
        "related",
        "agent",
        "services",
        "farming",
        "stock"
    ],
    "wof:name":"Ruegg Livestock Ltd",
    "wof:placetype":"venue"
},
  "geometry": {"coordinates":[176.98419200000001,-37.965305],"type":"Point"}
}