{
  "type": "Feature",
  "properties": {
    "addr:full":"29 B Bath St Parnell  Auckland Auckland",
    "addr:housenumber":"29 b",
    "addr:street":"Bath St",
    "iso:country":"NZ",
    "sg:address":"29 B Bath St Parnell ",
    "sg:city":"Auckland",
    "sg:classifiers":[
        {
            "category":"Personal",
            "subcategory":"Piercing",
            "type":"Services"
        }
    ],
    "sg:phone":"+64 9-366 6699",
    "sg:province":"Auckland",
    "sg:tags":[
        "body",
        "ear",
        "health",
        "nose",
        "beauty"
    ],
    "wof:name":"Glamuzina Corporation Ltd",
    "wof:placetype":"venue"
},
  "geometry": {"coordinates":[174.77912900000001,-36.852066],"type":"Point"}
}