{
  "type": "Feature",
  "properties": {
    "addr:full":"16 Braco Pl Burnside  Christchurch Canterbury",
    "addr:housenumber":"16",
    "addr:street":"Braco Pl",
    "iso:country":"NZ",
    "sg:address":"16 Braco Pl Burnside ",
    "sg:city":"Christchurch",
    "sg:classifiers":[
        {
            "category":"Personal",
            "type":"Services"
        }
    ],
    "sg:phone":"+64 3-358 7309",
    "sg:province":"Canterbury",
    "sg:tags":[
        "celebrant",
        "arrangements",
        "marriage",
        "wedding"
    ],
    "wof:name":"Cargo Allan",
    "wof:placetype":"venue"
},
  "geometry": {"coordinates":[172.57107500000001,-43.508305],"type":"Point"}
}