{
  "type": "Feature",
  "properties": {
    "iso:country":"NZ",
    "sg:address":"64 Paora Hapi St ",
    "sg:city":"Taupo",
    "sg:orig_category":"Health And Beauty: Specialists: Chiropractors",
    "sg:phone":"+64 7-378 8142",
    "sg:province":"Waikato",
    "wof:name":"McMaster Chiropractic Centre",
    "wof:placetype":"venue"
},
  "geometry": {"coordinates":[176.075211,-38.685139],"type":"Point"}
}