{
  "type": "Feature",
  "properties": {
    "addr:full":"56 Fifteenth Ave  Tauranga Bay of Plenty",
    "addr:housenumber":"56",
    "addr:street":"Fifteenth Ave",
    "iso:country":"NZ",
    "sg:address":"56 Fifteenth Ave ",
    "sg:city":"Tauranga",
    "sg:orig_category":"Industrial: Parts: Bolts And Nuts",
    "sg:phone":"+64 7-578 4405",
    "sg:province":"Bay of Plenty",
    "wof:name":"Bolt Shop",
    "wof:placetype":"venue"
},
  "geometry": {"coordinates":[176.16310100000001,-37.709621],"type":"Point"}
}