{
  "type": "Feature",
  "properties": {
    "iso:country":"NZ",
    "sg:address":"Bayfair Shopping Centre Mt ",
    "sg:city":"Maunganui",
    "sg:orig_category":"Shopping: Accessories: Bags - Fashion",
    "sg:phone":"+64 7-575 8040",
    "sg:province":"Bay of Plenty",
    "wof:name":"Modern Bags",
    "wof:placetype":"venue"
},
  "geometry": {"coordinates":[176.218826,-37.67791],"type":"Point"}
}