{
  "type": "Feature",
  "properties": {
    "addr:full":"Wellington  Wellington Wellington",
    "iso:country":"NZ",
    "sg:address":"Wellington ",
    "sg:city":"Wellington",
    "sg:orig_category":"Farming: Farms - General: Beekeeping",
    "sg:phone":"+64 25905435",
    "sg:province":"Wellington",
    "wof:name":"Lindsay's Apiaries",
    "wof:placetype":"venue"
},
  "geometry": {"coordinates":[174.82162500000001,-41.325909],"type":"Point"}
}