{
  "type": "Feature",
  "properties": {
    "addr:full":"Te  Aroha",
    "iso:country":"NZ",
    "sg:address":"Te ",
    "sg:city":"Aroha",
    "sg:classifiers":[
        {
            "category":"Bus Charters",
            "type":"Transportation"
        }
    ],
    "sg:phone":"+64 7-884 8208",
    "sg:tags":[
        "services",
        "travel",
        "tourism"
    ],
    "wof:name":"Turley Motors",
    "wof:placetype":"venue"
},
  "geometry": {"coordinates":[175.707718,-37.534805],"type":"Point"}
}