{
  "type": "Feature",
  "properties": {
    "iso:country":"NZ",
    "sg:address":"28 Barry's Pt Rd Takapuna ",
    "sg:city":"Auckland",
    "sg:classifiers":[
        {
            "category":"Retail",
            "subcategory":"Auto Repair",
            "type":"Services"
        }
    ],
    "sg:phone":"+64 9-486 0586",
    "sg:province":"Auckland",
    "sg:tags":[
        "wheel",
        "automotive",
        "servicing",
        "alignment"
    ],
    "wof:name":"Shore Performance Tyres",
    "wof:placetype":"venue"
},
  "geometry": {"coordinates":[174.767883,-36.787842],"type":"Point"}
}