{
  "type": "Feature",
  "properties": {
    "iso:country":"NZ",
    "sg:address":"60 Durham St ",
    "sg:city":"Tauranga",
    "sg:orig_category":"Industrial: Engineering: Engineers: Engineers - Consulting",
    "sg:phone":"+64 7-577 1549",
    "sg:province":"Bay of Plenty",
    "wof:name":"Design & Civil Management Ltd",
    "wof:placetype":"venue"
},
  "geometry": {"coordinates":[176.167496,-37.68391],"type":"Point"}
}