{
  "type": "Feature",
  "properties": {
    "addr:full":"80 London St  Hamilton Waikato",
    "addr:housenumber":"80",
    "addr:street":"London St",
    "iso:country":"NZ",
    "sg:address":"80 London St ",
    "sg:city":"Hamilton",
    "sg:orig_category":"Farming: Agriculture: Dairy Companies",
    "sg:phone":"+64 7-839 8398",
    "sg:province":"Waikato",
    "wof:name":"NZMP",
    "wof:placetype":"venue"
},
  "geometry": {"coordinates":[-84.57627100000001,39.395847],"type":"Point"}
}