{
  "type": "Feature",
  "properties": {
    "addr:full":"356 Neilson St Penrose  Auckland Auckland",
    "addr:housenumber":"356",
    "addr:street":"Neilson St",
    "iso:country":"NZ",
    "sg:address":"356 Neilson St Penrose ",
    "sg:city":"Auckland",
    "sg:classifiers":[
        {
            "category":"Wholesale",
            "subcategory":"Hardware",
            "type":"Manufacturing & Wholesale Goods"
        }
    ],
    "sg:phone":"+64 9-636 6770",
    "sg:province":"Auckland",
    "sg:tags":[
        "gardening",
        "garden",
        "chainsaw",
        "products",
        "brush",
        "home",
        "cutter"
    ],
    "wof:name":"Auckland Machinery Centre Ltd",
    "wof:placetype":"venue"
},
  "geometry": {"coordinates":[174.811508,-36.922707],"type":"Point"}
}