{
  "type": "Feature",
  "properties": {
    "addr:full":"DFS Galleria 22 Customs St W Auckland Central  Auckland Auckland",
    "addr:housenumber":"22",
    "addr:street":"Galleria;Customs St W",
    "iso:country":"NZ",
    "sg:address":"DFS Galleria 22 Customs St W Auckland Central ",
    "sg:city":"Auckland",
    "sg:classifiers":[
        {
            "category":"Travel",
            "subcategory":"Travel Agent",
            "type":"Entertainment"
        }
    ],
    "sg:phone":"+64 9-358 4488",
    "sg:province":"Auckland",
    "sg:tags":[
        "good",
        "tourism"
    ],
    "wof:name":"Louis Vuitton New Zealand Ltd",
    "wof:placetype":"venue"
},
  "geometry": {"coordinates":[174.76454200000001,-36.848358],"type":"Point"}
}