{
  "type": "Feature",
  "properties": {
    "iso:country":"NZ",
    "sg:address":"7 Scott St ",
    "sg:city":"Blenheim",
    "sg:classifiers":[
        {
            "category":"Home & Garden",
            "subcategory":"Home Furnishings",
            "type":"Retail Goods"
        }
    ],
    "sg:phone":"+64 3-577 9506",
    "sg:province":"Marlborough",
    "sg:tags":[
        "furniture/furnishings",
        "bedding",
        "bed"
    ],
    "wof:name":"Lynfords",
    "wof:placetype":"venue"
},
  "geometry": {"coordinates":[-74.459564,42.468643],"type":"Point"}
}