{
  "type": "Feature",
  "properties": {
    "addr:full":"Northcote  Auckland Auckland",
    "iso:country":"NZ",
    "sg:address":"Northcote ",
    "sg:city":"Auckland",
    "sg:classifiers":[
        {
            "category":"Personal",
            "subcategory":"Beauty Salon",
            "type":"Services"
        }
    ],
    "sg:phone":"+64 9-419 8079",
    "sg:province":"Auckland",
    "sg:tags":[
        "new age",
        "health",
        "services",
        "professional"
    ],
    "wof:name":"Michele Carter Psychic",
    "wof:placetype":"venue"
},
  "geometry": {"coordinates":[174.747849,-36.801125],"type":"Point"}
}