{
  "type": "Feature",
  "properties": {
    "addr:full":"25 Totara St Mt  Maunganui Auckland",
    "addr:housenumber":"25",
    "addr:street":"Totara St",
    "iso:country":"NZ",
    "sg:address":"25 Totara St Mt ",
    "sg:city":"Maunganui",
    "sg:orig_category":"Automotive: General Services: Rental Vehicles",
    "sg:phone":"+64 800 250 251",
    "sg:province":"Auckland",
    "wof:name":"Rite Price Car Rentals Ltd",
    "wof:placetype":"venue"
},
  "geometry": {"coordinates":[176.18615700000001,-37.644562],"type":"Point"}
}