{
  "type": "Feature",
  "properties": {
    "iso:country":"NZ",
    "sg:address":"492 Queen St Auckland Central ",
    "sg:city":"Auckland",
    "sg:classifiers":[
        {
            "category":"Personal",
            "subcategory":"Adult",
            "type":"Services"
        }
    ],
    "sg:phone":"+64 9-302 2539",
    "sg:province":"Auckland",
    "sg:tags":[
        "sport",
        "parlour",
        "massage",
        "leisure"
    ],
    "wof:name":"City Angel's",
    "wof:placetype":"venue"
},
  "geometry": {"coordinates":[174.762131,-36.856747],"type":"Point"}
}