{
  "type": "Feature",
  "properties": {
    "addr:full":"492 Queen St Auckland Central  Auckland Auckland",
    "addr:housenumber":"492",
    "addr:street":"Queen St",
    "iso:country":"NZ",
    "sg:address":"492 Queen St Auckland Central ",
    "sg:city":"Auckland",
    "sg:classifiers":[
        {
            "category":"Personal",
            "subcategory":"Adult",
            "type":"Services"
        }
    ],
    "sg:phone":"+64 9-302 2539",
    "sg:province":"Auckland",
    "sg:tags":[
        "sport",
        "parlour",
        "massage",
        "leisure"
    ],
    "wof:name":"City Angel's",
    "wof:placetype":"venue"
},
  "geometry": {"coordinates":[174.76213100000001,-36.856747],"type":"Point"}
}