{
  "type": "Feature",
  "properties": {
    "iso:country":"NZ",
    "sg:address":"80 A Beach Rd ",
    "sg:city":"Kaikoura",
    "sg:classifiers":[
        {
            "category":"Restaurant",
            "type":"Food & Drink"
        }
    ],
    "sg:phone":"+64 3-319 7531",
    "sg:tags":[
        "sea"
    ],
    "wof:name":"Kina New Zealand",
    "wof:placetype":"venue"
},
  "geometry": {"coordinates":[173.67930603030001,-42.3944473267],"type":"Point"}
}