{
  "type": "Feature",
  "properties": {
    "iso:country":"NZ",
    "sg:address":"105 Church St ",
    "sg:city":"Opotiki",
    "sg:orig_category":"Shopping: Retail Stores: Toys",
    "sg:phone":"+64 7-315 5584",
    "wof:name":"Toyworld Opotiki",
    "wof:placetype":"venue"
},
  "geometry": {"coordinates":[177.28454600000001,-38.003643],"type":"Point"}
}