{
  "type": "Feature",
  "properties": {
    "iso:country":"NZ",
    "sg:address":"19 Wallscourt Pl Normanby ",
    "sg:city":"Hawera",
    "sg:orig_category":"Food And Drink: Meats: Homekill Services",
    "sg:phone":"+64 6-272 8272",
    "sg:province":"Taranaki",
    "wof:name":"Taranaki Meat Masters Ltd",
    "wof:placetype":"venue"
},
  "geometry": {"coordinates":[174.274612,-39.542484],"type":"Point"}
}