{
  "type": "Feature",
  "properties": {
    "addr:full":"8-14 McCormack Place Ngauranga Gorge  Wellington Wellington",
    "addr:housenumber":"8-14",
    "addr:street":"Mccormack Place Ngauranga Gorge",
    "iso:country":"NZ",
    "sg:address":"8-14 McCormack Place Ngauranga Gorge ",
    "sg:city":"Wellington",
    "sg:orig_category":"Transport: Transportation",
    "sg:phone":"+64 4-472 1134",
    "sg:province":"Wellington",
    "sg:website":"http://www.yellowpages.co.nz/for/alliedpickfords/dp16940.html",
    "wof:name":"Allied Pickfords",
    "wof:placetype":"venue"
},
  "geometry": {"coordinates":[174.812622,-41.246174],"type":"Point"}
}