{
  "type": "Feature",
  "properties": {
    "addr:full":"60 Hobson St Auckland City  Auckland Auckland",
    "addr:housenumber":"60",
    "addr:street":"Hobson St",
    "iso:country":"NZ",
    "sg:address":"60 Hobson St Auckland City ",
    "sg:city":"Auckland",
    "sg:classifiers":[
        {
            "category":"Travel",
            "subcategory":"Travel Agent",
            "type":"Entertainment"
        }
    ],
    "sg:phone":"+64 9-631 1111",
    "sg:province":"Auckland",
    "sg:tags":[
        "tour",
        "tourism",
        "sightseeing"
    ],
    "sg:website":"http://www.corporatecabs.co.nz",
    "wof:name":"Corporate Cabs",
    "wof:placetype":"venue"
},
  "geometry": {"coordinates":[174.7621,-36.847439],"type":"Point"}
}