{
  "type": "Feature",
  "properties": {
    "addr:full":"57 Grey St  Gisborne Gisborne",
    "addr:housenumber":"57",
    "addr:street":"Grey St",
    "iso:country":"NZ",
    "sg:address":"57 Grey St ",
    "sg:city":"Gisborne",
    "sg:classifiers":[
        {
            "category":"Bars & Pubs",
            "subcategory":"Wine Bar",
            "type":"Food & Drink"
        }
    ],
    "sg:phone":"+64 6-867 6085",
    "sg:province":"Gisborne",
    "sg:tags":[
        "wining",
        "dining",
        "cafe"
    ],
    "wof:name":"Palms Cafe The",
    "wof:placetype":"venue"
},
  "geometry": {"coordinates":[178.02475000000001,-38.663891],"type":"Point"}
}