{
  "type": "Feature",
  "properties": {
    "addr:full":"2 Lenihan Dve Te  Puke Bay of Plenty",
    "addr:housenumber":"2",
    "addr:street":"Lenihan Dve",
    "iso:country":"NZ",
    "sg:address":"2 Lenihan Dve Te ",
    "sg:city":"Puke",
    "sg:classifiers":[
        {
            "category":"Health Services",
            "subcategory":"Hospital",
            "type":"Services"
        }
    ],
    "sg:phone":"+64 7-573 8039",
    "sg:province":"Bay of Plenty",
    "sg:tags":[
        "medical",
        "beauty"
    ],
    "wof:name":"Waitaha Hauoranga",
    "wof:placetype":"venue"
},
  "geometry": {"coordinates":[176.32008400000001,-37.786819],"type":"Point"}
}