{
  "type": "Feature",
  "properties": {
    "iso:country":"NZ",
    "sg:address":"186 Ponsonby Rd Ponsonby ",
    "sg:city":"Auckland",
    "sg:classifiers":[
        {
            "category":"Organizations",
            "subcategory":"Labor Organization",
            "type":"Services"
        }
    ],
    "sg:phone":"+64 9-376 3985",
    "sg:province":"Auckland",
    "sg:tags":[
        "cake",
        "arrangements",
        "wedding"
    ],
    "wof:name":"The City Cake Company Ltd",
    "wof:placetype":"venue"
},
  "geometry": {"coordinates":[174.745483,-36.853966],"type":"Point"}
}