{
  "type": "Feature",
  "properties": {
    "iso:country":"NZ",
    "sg:address":"546 Mt Albert Rd Mt Roskill ",
    "sg:city":"Auckland",
    "sg:orig_category":"Shopping: Retail Stores: Books: Libraries",
    "sg:phone":"+64 9-625 7625",
    "sg:province":"Auckland",
    "wof:name":"Mt Roskill",
    "wof:placetype":"venue"
},
  "geometry": {"coordinates":[174.742767,-36.905895],"type":"Point"}
}