{
  "type": "Feature",
  "properties": {
    "iso:country":"NZ",
    "sg:address":"2 C Bell Rd South Gracefield Lower ",
    "sg:city":"Hutt",
    "sg:orig_category":"Transport: Transportation: Transport Operators",
    "sg:phone":"+64 4-566 6699",
    "sg:province":"Wellington",
    "sg:website":"http://www.yellowpages.co.nz/for/barlowsfreight/dp52004.html",
    "wof:name":"Barlow's Freight Services Ltd",
    "wof:placetype":"venue"
},
  "geometry": {"coordinates":[174.914886,-41.234272],"type":"Point"}
}