{
  "type": "Feature",
  "properties": {
    "addr:full":"49 Cape Horn Rd Hillsborough  Auckland Auckland",
    "addr:housenumber":"49",
    "addr:street":"Cape Horn Rd",
    "iso:country":"NZ",
    "sg:address":"49 Cape Horn Rd Hillsborough ",
    "sg:city":"Auckland",
    "sg:classifiers":[
        {
            "category":"Professional",
            "subcategory":"Management & Consulting",
            "type":"Services"
        }
    ],
    "sg:phone":"+64 9-626 3263",
    "sg:province":"Auckland",
    "sg:tags":[
        "consultant",
        "training",
        "education"
    ],
    "wof:name":"Maxim Institute",
    "wof:placetype":"venue"
},
  "geometry": {"coordinates":[174.753342,-36.925343],"type":"Point"}
}