{
  "type": "Feature",
  "properties": {
    "addr:full":"49 Princess St Palmerston  Palmerston North Manawatu-Wanganui",
    "addr:housenumber":"49",
    "addr:street":"Princess St",
    "iso:country":"NZ",
    "sg:address":"49 Princess St Palmerston ",
    "sg:city":"Palmerston North",
    "sg:classifiers":[
        {
            "category":"Insurance",
            "subcategory":"Health Insurance",
            "type":"Services"
        }
    ],
    "sg:phone":"+64 6-357 6757",
    "sg:province":"Manawatu-Wanganui",
    "sg:tags":[
        "beauty"
    ],
    "wof:name":"The Cutting Edge",
    "wof:placetype":"venue"
},
  "geometry": {"coordinates":[175.61552399999999,-40.354359],"type":"Point"}
}