{
  "type": "Feature",
  "properties": {
    "addr:full":"6 Clemow Dve Mt Wellington  Auckland Auckland",
    "addr:housenumber":"6",
    "addr:street":"Clemow Dve",
    "iso:country":"NZ",
    "sg:address":"6 Clemow Dve Mt Wellington ",
    "sg:city":"Auckland",
    "sg:classifiers":[
        {
            "category":"Manufacturing",
            "subcategory":"Motor Vehicles & Parts",
            "type":"Manufacturing & Wholesale Goods"
        }
    ],
    "sg:phone":"+64 9-573 3399",
    "sg:province":"Auckland",
    "sg:tags":[
        "air conditioning",
        "automotive",
        "supplies"
    ],
    "wof:name":"Auckland Auto Air Ltd",
    "wof:placetype":"venue"
},
  "geometry": {"coordinates":[174.83029199999999,-36.909569],"type":"Point"}
}