{
  "type": "Feature",
  "properties": {
    "iso:country":"NZ",
    "sg:address":"Keith Allen Drive Sulphur Point ",
    "sg:city":"Tauranga",
    "sg:classifiers":[
        {
            "category":"Personal",
            "type":"Services"
        }
    ],
    "sg:phone":"+64 7-578 5512",
    "sg:province":"Bay of Plenty",
    "sg:tags":[
        "arrangements",
        "wedding"
    ],
    "sg:website":"http://www.yacht.org.nz",
    "wof:name":"Tauranga Yacht & Power Boat Club Inc",
    "wof:placetype":"venue"
},
  "geometry": {"coordinates":[176.16696200000001,-37.669525],"type":"Point"}
}