{
  "type": "Feature",
  "properties": {
    "addr:full":"Husheer Pl Onekawa  Napier Hawke's Bay",
    "addr:street":"Husheer Pl",
    "iso:country":"NZ",
    "sg:address":"Husheer Pl Onekawa ",
    "sg:city":"Napier",
    "sg:classifiers":[
        {
            "category":"Shopping",
            "subcategory":"Crafts & Fabrics",
            "type":"Retail Goods"
        }
    ],
    "sg:phone":"+64 6-843 3174",
    "sg:province":"Hawke's Bay",
    "sg:tags":[
        "knitting",
        "wool",
        "clothing"
    ],
    "wof:name":"Knitters Factory Shop",
    "wof:placetype":"venue"
},
  "geometry": {"coordinates":[176.876846,-39.502892],"type":"Point"}
}