{
  "type": "Feature",
  "properties": {
    "addr:full":"170 a Maunu Rd  Whangarei Northland",
    "addr:housenumber":"170 a",
    "addr:street":"Maunu Rd",
    "iso:country":"NZ",
    "sg:address":"170 a Maunu Rd ",
    "sg:city":"Whangarei",
    "sg:orig_category":"Industrial: Services: Gasfitters",
    "sg:phone":"+64 9-438 0192",
    "sg:province":"Northland",
    "wof:name":"Plumbing and Gasfitting Services",
    "wof:placetype":"venue"
},
  "geometry": {"coordinates":[174.312073,-35.730747],"type":"Point"}
}