{
  "type": "Feature",
  "properties": {
    "addr:full":"27 Reeve St  Levin Manawatu-Wanganui",
    "addr:housenumber":"27",
    "addr:street":"Reeve St",
    "iso:country":"NZ",
    "sg:address":"27 Reeve St ",
    "sg:city":"Levin",
    "sg:classifiers":[
        {
            "category":"Fast Food",
            "type":"Food & Drink"
        }
    ],
    "sg:phone":"+64 6-368 7972",
    "sg:province":"Manawatu-Wanganui",
    "sg:tags":[
        "wining",
        "dining",
        "takeaway"
    ],
    "wof:name":"The Tuck Shop",
    "wof:placetype":"venue"
},
  "geometry": {"coordinates":[175.275116,-40.630196],"type":"Point"}
}