{
  "type": "Feature",
  "properties": {
    "addr:full":"224 Khyber Pass Rd Newmarket  Auckland Auckland",
    "addr:housenumber":"224",
    "addr:street":"Khyber Pass Rd",
    "iso:country":"NZ",
    "sg:address":"224 Khyber Pass Rd Newmarket ",
    "sg:city":"Auckland",
    "sg:classifiers":[
        {
            "category":"Social Services",
            "subcategory":"Retirement Home",
            "type":"Services"
        }
    ],
    "sg:phone":"+64 9-303 3178",
    "sg:province":"Auckland",
    "sg:tags":[
        "elderly",
        "convalescent",
        "garden",
        "rest",
        "care"
    ],
    "wof:name":"Classic Handles & Hardware Ltd",
    "wof:placetype":"venue"
},
  "geometry": {"coordinates":[174.768417,-36.865459],"type":"Point"}
}