{
  "type": "Feature",
  "properties": {
    "iso:country":"NZ",
    "sg:address":"115 Hilton Hwy Washdyke ",
    "sg:city":"Timaru",
    "sg:orig_category":"Automotive: Parts And Supplies: Tyres",
    "sg:phone":"+64 3-688 2447",
    "sg:province":"Canterbury",
    "wof:name":"Timaru Honda",
    "wof:placetype":"venue"
},
  "geometry": {"coordinates":[171.23788500000001,-44.352978],"type":"Point"}
}