{
  "type": "Feature",
  "properties": {
    "addr:full":"34 Wairere Rd Wainui Beach  Gisborne Gisborne",
    "addr:housenumber":"34",
    "addr:street":"Wairere Rd",
    "iso:country":"NZ",
    "sg:address":"34 Wairere Rd Wainui Beach ",
    "sg:city":"Gisborne",
    "sg:classifiers":[
        {
            "category":"Travel",
            "subcategory":"Hotels & Motels",
            "type":"Entertainment"
        }
    ],
    "sg:phone":"+64 6-868 5882",
    "sg:province":"Gisborne",
    "sg:tags":[
        "holiday",
        "tourism",
        "accommodation"
    ],
    "wof:name":"Wainui Beach Motel",
    "wof:placetype":"venue"
},
  "geometry": {"coordinates":[178.073364,-38.68589],"type":"Point"}
}