{
  "type": "Feature",
  "properties": {
    "addr:full":"PO Box 60203 Titirangi  Auckland Auckland",
    "addr:housenumber":"po box",
    "addr:postcode":"60203",
    "iso:country":"NZ",
    "sg:address":"PO Box 60203 Titirangi ",
    "sg:city":"Auckland",
    "sg:classifiers":[
        {
            "category":"Shopping",
            "subcategory":"Crafts & Fabrics",
            "type":"Retail Goods"
        }
    ],
    "sg:phone":"+64 9-817 4524",
    "sg:province":"Auckland",
    "sg:tags":[
        "clothing",
        "maternity",
        "wear"
    ],
    "wof:name":"Preggy Band",
    "wof:placetype":"venue"
},
  "geometry": {"coordinates":[174.66279599999999,-36.926861],"type":"Point"}
}