{
  "type": "Feature",
  "properties": {
    "iso:country":"NZ",
    "sg:address":"cnr Rosedale & Airborne Rd Albany ",
    "sg:city":"Auckland",
    "sg:classifiers":[
        {
            "category":"Transit Center",
            "subcategory":"Freight",
            "type":"Transportation"
        }
    ],
    "sg:phone":"+64 9-415 4700",
    "sg:province":"Auckland",
    "sg:tags":[
        "distribution",
        "-",
        "transport"
    ],
    "sg:website":"http://www.penguin.co.nz",
    "wof:name":"Penguin Books NZ Ltd",
    "wof:placetype":"venue"
},
  "geometry": {"coordinates":[174.698914,-36.727741],"type":"Point"}
}