{
  "type": "Feature",
  "properties": {
    "addr:full":"89 Nith St  Invercargill Southland",
    "addr:housenumber":"89",
    "addr:street":"Nith St",
    "iso:country":"NZ",
    "sg:address":"89 Nith St ",
    "sg:city":"Invercargill",
    "sg:orig_category":"Food And Drink: Meats: Butchers",
    "sg:phone":"+64 3-214 2261",
    "sg:province":"Southland",
    "wof:name":"Southern City Meats",
    "wof:placetype":"venue"
},
  "geometry": {"coordinates":[168.35041799999999,-46.418362],"type":"Point"}
}