{
  "type": "Feature",
  "properties": {
    "iso:country":"NZ",
    "sg:address":"Burnham School Rd ",
    "sg:city":"Burnham",
    "sg:classifiers":[
        {
            "category":"Food & Beverages",
            "subcategory":"Liquor & Beverages",
            "type":"Retail Goods"
        }
    ],
    "sg:phone":"+64 3-347 6729",
    "sg:tags":[
        "drink",
        "maker",
        "wine"
    ],
    "wof:name":"Giesen Wine Estate Canterbury Ltd",
    "wof:placetype":"venue"
},
  "geometry": {"coordinates":[172.30806000000001,-43.613522],"type":"Point"}
}