{
  "type": "Feature",
  "properties": {
    "addr:full":"Unit C, 357-359 Albany Hwy Albany  Auckland Auckland",
    "addr:housenumber":"unit c 357-359",
    "addr:street":"Albany Hwy",
    "iso:country":"NZ",
    "sg:address":"Unit C, 357-359 Albany Hwy Albany ",
    "sg:city":"Auckland",
    "sg:classifiers":[
        {
            "category":"Food & Beverages",
            "subcategory":"Liquor & Beverages",
            "type":"Retail Goods"
        }
    ],
    "sg:phone":"+64 9-444 9998",
    "sg:province":"Auckland",
    "sg:tags":[
        "drink",
        "outlet"
    ],
    "wof:name":"Liquorland",
    "wof:placetype":"venue"
},
  "geometry": {"coordinates":[174.709686,-36.720142],"type":"Point"}
}