{
  "type": "Feature",
  "properties": {
    "addr:full":"14 Ngapipi St Orakei  Auckland Auckland",
    "addr:housenumber":"14",
    "addr:street":"Ngapipi St",
    "iso:country":"NZ",
    "sg:address":"14 Ngapipi St Orakei ",
    "sg:city":"Auckland",
    "sg:orig_category":"Automotive: General Services: Car Consultants",
    "sg:phone":"+64 9-520 5900",
    "sg:province":"Auckland",
    "wof:name":"Redbook New Zealand",
    "wof:placetype":"venue"
},
  "geometry": {"coordinates":[174.80954,-36.855404],"type":"Point"}
}