{
  "type": "Feature",
  "properties": {
    "iso:country":"NZ",
    "sg:address":"25 Main Rd South ",
    "sg:city":"Levin",
    "sg:classifiers":[
        {
            "category":"Marine",
            "type":"Transportation"
        }
    ],
    "sg:phone":"+64 6-367 3888",
    "sg:province":"Manawatu-Wanganui",
    "sg:tags":[
        "boats",
        "builder",
        "yacht",
        "transport",
        "boat"
    ],
    "wof:name":"Orca Boats & Pools Ltd",
    "wof:placetype":"venue"
},
  "geometry": {"coordinates":[175.285324,-40.625278],"type":"Point"}
}