{
  "type": "Feature",
  "properties": {
    "iso:country":"NZ",
    "sg:address":"62 Main St ",
    "sg:city":"Blenheim",
    "sg:classifiers":[
        {
            "category":"Bars & Pubs",
            "subcategory":"Wine Bar",
            "type":"Food & Drink"
        }
    ],
    "sg:phone":"+64 3-579 1195",
    "sg:province":"Marlborough",
    "sg:tags":[
        "wining",
        "dining",
        "cafe"
    ],
    "wof:name":"Sweet As Cafe",
    "wof:placetype":"venue"
},
  "geometry": {"coordinates":[-79.65271,34.513569],"type":"Point"}
}