{
  "type": "Feature",
  "properties": {
    "iso:country":"NZ",
    "sg:address":"191B Archers Rd Glenfield ",
    "sg:city":"Auckland",
    "sg:orig_category":"Industrial: Parts: Bolts And Nuts",
    "sg:phone":"+64 9-441 9425",
    "sg:province":"Auckland",
    "wof:name":"The Bolt Shop",
    "wof:placetype":"venue"
},
  "geometry": {"coordinates":[174.73800700000001,-36.78204],"type":"Point"}
}