{
  "type": "Feature",
  "properties": {
    "addr:full":"Pakuranga Plaza Pakuranga  Auckland Auckland",
    "iso:country":"NZ",
    "sg:address":"Pakuranga Plaza Pakuranga ",
    "sg:city":"Auckland",
    "sg:classifiers":[
        {
            "category":"Shopping Center",
            "type":"Public Place"
        }
    ],
    "sg:phone":"+64 9-576 9193",
    "sg:province":"Auckland",
    "sg:tags":[
        "mall",
        "retail",
        "stores"
    ],
    "wof:name":"Pakuranga Market Place Ltd",
    "wof:placetype":"venue"
},
  "geometry": {"coordinates":[174.89497399999999,-36.903515],"type":"Point"}
}