{
  "type": "Feature",
  "properties": {
    "addr:full":"Smeed Quarry Rd Pukekawa R D 1 Tuakau  Pukekohe Auckland",
    "addr:housenumber":"1",
    "addr:street":"Smeed Quarry Rd;R D",
    "iso:country":"NZ",
    "sg:address":"Smeed Quarry Rd Pukekawa R D 1 Tuakau ",
    "sg:city":"Pukekohe",
    "sg:orig_category":"Sports And Leisure: Sports: Equestrian: Stud Farms",
    "sg:phone":"+64 9-233 4771",
    "sg:province":"Auckland",
    "wof:name":"Glenmorgan Farm Ltd",
    "wof:placetype":"venue"
},
  "geometry": {"coordinates":[174.945877,-37.26025],"type":"Point"}
}