{
  "type": "Feature",
  "properties": {
    "iso:country":"NZ",
    "sg:address":"Office Level 2 87 Devon St East New ",
    "sg:city":"Plymouth",
    "sg:classifiers":[
        {
            "category":"Communications",
            "subcategory":"Radio Station",
            "type":"Services"
        }
    ],
    "sg:phone":"+64 6-757 9932",
    "sg:province":"Taranaki",
    "sg:tags":[
        "broadcasting"
    ],
    "wof:name":"Radioworks The",
    "wof:placetype":"venue"
},
  "geometry": {"coordinates":[-116.868042,43.996387],"type":"Point"}
}