{
  "type": "Feature",
  "properties": {
    "addr:full":"9 Moore St Howick  Auckland Auckland",
    "addr:housenumber":"9",
    "addr:street":"Moore St",
    "iso:country":"NZ",
    "sg:address":"9 Moore St Howick ",
    "sg:city":"Auckland",
    "sg:orig_category":"Clothing And Fabric: Clothing: Menswear",
    "sg:phone":"+64 9-534 9373",
    "sg:province":"Auckland",
    "wof:name":"John Russell Menswear",
    "wof:placetype":"venue"
},
  "geometry": {"coordinates":[174.93249499999999,-36.895092],"type":"Point"}
}