{
  "type": "Feature",
  "properties": {
    "iso:country":"NZ",
    "sg:address":"35 Ellis St Frankton ",
    "sg:city":"Hamilton",
    "sg:orig_category":"Industrial: Metal: Scrap Metal Dealers",
    "sg:phone":"+64 7-847 9430",
    "sg:province":"Waikato",
    "wof:name":"Waikato Waste Metals 1998 Ltd",
    "wof:placetype":"venue"
},
  "geometry": {"coordinates":[175.264267,-37.793262],"type":"Point"}
}