{
  "type": "Feature",
  "properties": {
    "addr:full":"2 Hoskings Plaza 81 Cameron St  Whangarei Northland",
    "addr:housenumber":"2;81",
    "addr:street":"Hoskings Plaza;Cameron St",
    "iso:country":"NZ",
    "sg:address":"2 Hoskings Plaza 81 Cameron St ",
    "sg:city":"Whangarei",
    "sg:orig_category":"Shopping: Retail Stores: Lotto Outlets",
    "sg:phone":"+64 9-438 2800",
    "sg:province":"Northland",
    "wof:name":"Hoskings Plaza Lotto (1996) Ltd",
    "wof:placetype":"venue"
},
  "geometry": {"coordinates":[174.320526,-35.725399],"type":"Point"}
}