{
  "type": "Feature",
  "properties": {
    "addr:full":"Harper Rd Waerengaahika  Gisborne Gisborne",
    "addr:street":"Harper Rd",
    "iso:country":"NZ",
    "sg:address":"Harper Rd Waerengaahika ",
    "sg:city":"Gisborne",
    "sg:classifiers":[
        {
            "category":"Home & Garden",
            "subcategory":"Garden Supply",
            "type":"Retail Goods"
        }
    ],
    "sg:phone":"+64 6-862 5402",
    "sg:province":"Gisborne",
    "sg:tags":[
        "products",
        "nursery",
        "gardening"
    ],
    "wof:name":"Amberly Perennial Nursery & Indoor Plant Barn",
    "wof:placetype":"venue"
},
  "geometry": {"coordinates":[177.93553199999999,-38.605427],"type":"Point"}
}