{
  "type": "Feature",
  "properties": {
    "addr:full":"1085 State Highway 25 RD1  Whitianga",
    "addr:housenumber":"1085;rd1",
    "addr:street":"State Highway 25",
    "iso:country":"NZ",
    "sg:address":"1085 State Highway 25 RD1 ",
    "sg:city":"Whitianga",
    "sg:orig_category":"Health And Beauty: Specialists: Midwives",
    "sg:phone":"+64 7-866 3362",
    "wof:name":"Williamson Lorraine - Midwife",
    "wof:placetype":"venue"
},
  "geometry": {"coordinates":[175.699524,-36.821472],"type":"Point"}
}