{
  "type": "Feature",
  "properties": {
    "iso:country":"NZ",
    "sg:address":"1296 Coatesville Hwy Kumeu ",
    "sg:city":"Auckland",
    "sg:orig_category":"Farming: Farms - General: Farms",
    "sg:phone":"+64 9-412 9556",
    "sg:province":"Auckland",
    "wof:name":"Puckett Bros",
    "wof:placetype":"venue"
},
  "geometry": {"coordinates":[174.56019599999999,-36.777271],"type":"Point"}
}