{
  "type": "Feature",
  "properties": {
    "iso:country":"NZ",
    "sg:address":"119 Thames St ",
    "sg:city":"Oamaru",
    "sg:classifiers":[
        {
            "category":"Personal",
            "type":"Services"
        }
    ],
    "sg:phone":"+64 3-434 9184",
    "sg:province":"Otago",
    "sg:tags":[
        "arrangements",
        "wedding"
    ],
    "wof:name":"Oamaru Silk Centre",
    "wof:placetype":"venue"
},
  "geometry": {"coordinates":[170.970718,-45.098602],"type":"Point"}
}