{
  "type": "Feature",
  "properties": {
    "addr:full":"250 Broadway Newmarket  Auckland Manawatu-Wanganui",
    "addr:housenumber":"250",
    "addr:street":"Broadway",
    "iso:country":"NZ",
    "sg:address":"250 Broadway Newmarket ",
    "sg:city":"Auckland",
    "sg:classifiers":[
        {
            "category":"Sports & Exercise",
            "subcategory":"Ski Resort",
            "type":"Entertainment"
        }
    ],
    "sg:phone":"+64 9-524 5750",
    "sg:province":"Manawatu-Wanganui",
    "sg:tags":[
        "hobbies",
        "photographic",
        "leisure",
        "developing"
    ],
    "wof:name":"Yellow Camera Co Ltd",
    "wof:placetype":"venue"
},
  "geometry": {"coordinates":[174.77783199999999,-36.869545],"type":"Point"}
}