{
  "type": "Feature",
  "properties": {
    "iso:country":"NZ",
    "sg:address":"13 K Ryan Pl Manukau City ",
    "sg:city":"Auckland",
    "sg:classifiers":[
        {
            "category":"Wholesale",
            "subcategory":"Machinery & Supplies",
            "type":"Manufacturing & Wholesale Goods"
        }
    ],
    "sg:phone":"+64 9-262 1156",
    "sg:province":"Auckland",
    "sg:tags":[
        "equipment",
        "industrial"
    ],
    "sg:website":"http://www.yellowpages.co.nz/for/sewingmachinewarehouse/dp1340.html",
    "wof:name":"Sewing Machine Warehouse Ltd",
    "wof:placetype":"venue"
},
  "geometry": {"coordinates":[174.87586999999999,-36.986263],"type":"Point"}
}