{
  "type": "Feature",
  "properties": {
    "iso:country":"NZ",
    "sg:address":"5 View Rd Te ",
    "sg:city":"Kuiti",
    "sg:orig_category":"Home And Garden: Gardening: Services: Landscape Design",
    "sg:phone":"+64 7-878 8033",
    "wof:name":"Enviroscape",
    "wof:placetype":"venue"
},
  "geometry": {"coordinates":[175.16424599999999,-38.321228],"type":"Point"}
}