{
  "type": "Feature",
  "properties": {
    "iso:country":"NZ",
    "sg:address":"10 B Stonedon Dve East Tamaki ",
    "sg:city":"Auckland",
    "sg:orig_category":"Industrial: Packaging: Paper And Cardboard",
    "sg:phone":"+64 9-273 5825",
    "sg:province":"Auckland",
    "wof:name":"Yenom (NZ) Ltd",
    "wof:placetype":"venue"
},
  "geometry": {"coordinates":[174.884323,-36.934158],"type":"Point"}
}