{
  "type": "Feature",
  "properties": {
    "iso:country":"NZ",
    "sg:address":"Homestead Rd ",
    "sg:city":"Kerikeri",
    "sg:orig_category":"Automotive: General Services: Rental Vehicles",
    "sg:phone":"+64 9-407 7783",
    "sg:province":"Northland",
    "wof:name":"Rent-A Cheepy Rentals",
    "wof:placetype":"venue"
},
  "geometry": {"coordinates":[173.947174,-35.227131],"type":"Point"}
}