{
  "type": "Feature",
  "properties": {
    "addr:full":"PO Box 535 Ashburton  Wakanui",
    "addr:housenumber":"po",
    "addr:street":"Box 535",
    "iso:country":"NZ",
    "sg:address":"PO Box 535 Ashburton ",
    "sg:city":"Wakanui",
    "sg:classifiers":[
        {
            "category":"Food Court",
            "type":"Food & Drink"
        }
    ],
    "sg:phone":"+64 3-302 3817",
    "sg:tags":[
        "packer",
        "processing",
        "processor"
    ],
    "wof:name":"Canterbury Dried Foods",
    "wof:placetype":"venue"
},
  "geometry": {"coordinates":[171.81660500000001,-43.964668],"type":"Point"}
}