{
  "type": "Feature",
  "properties": {
    "addr:full":"139 High St  Carterton",
    "addr:housenumber":"139",
    "addr:street":"High St",
    "iso:country":"NZ",
    "sg:address":"139 High St ",
    "sg:city":"Carterton",
    "sg:classifiers":[
        {
            "category":"Restaurant",
            "type":"Food & Drink"
        }
    ],
    "sg:phone":"+64 6-379 8754",
    "sg:tags":[
        "wining",
        "dining"
    ],
    "wof:name":"Empire Restaurant",
    "wof:placetype":"venue"
},
  "geometry": {"coordinates":[-82.190933,36.941956],"type":"Point"}
}