{
  "type": "Feature",
  "properties": {
    "iso:country":"NZ",
    "sg:address":"Midway Shopping Centre 282 Maunganui Rd Mt ",
    "sg:city":"Maunganui",
    "sg:orig_category":"Home And Garden: Furniture/Furnishings: Curtains",
    "sg:phone":"+64 7-575 5008",
    "sg:province":"Bay of Plenty",
    "wof:name":"Prestige Curtains",
    "wof:placetype":"venue"
},
  "geometry": {"coordinates":[176.186279,-37.641048],"type":"Point"}
}