{
  "type": "Feature",
  "properties": {
    "iso:country":"NZ",
    "sg:address":"275-281 Upper Cuba St ",
    "sg:city":"Wellington",
    "sg:orig_category":"Industrial: Consultancy: Metallurgy Consultants",
    "sg:phone":"+64 4-382 9666",
    "sg:province":"Wellington",
    "wof:name":"SGS M&I Safety Inspection Services",
    "wof:placetype":"venue"
},
  "geometry": {"coordinates":[-85.910454,33.827946],"type":"Point"}
}