{
  "type": "Feature",
  "properties": {
    "iso:country":"NZ",
    "sg:address":"Hadlow R D 4 ",
    "sg:city":"Timaru",
    "sg:classifiers":[
        {
            "category":"Shopping",
            "subcategory":"Pharmacy",
            "type":"Retail Goods"
        }
    ],
    "sg:phone":"+64 3-686 1069",
    "sg:province":"Canterbury",
    "sg:tags":[
        "product",
        "health"
    ],
    "wof:name":"Davidsons Apiaries Ltd",
    "wof:placetype":"venue"
},
  "geometry": {"coordinates":[171.23741100000001,-44.395428],"type":"Point"}
}