{
  "type": "Feature",
  "properties": {
    "addr:full":"PO Box 48179 Blockhouse Bay  Auckland Auckland",
    "addr:housenumber":"po box",
    "addr:postcode":"48179",
    "iso:country":"NZ",
    "sg:address":"PO Box 48179 Blockhouse Bay ",
    "sg:city":"Auckland",
    "sg:classifiers":[
        {
            "category":"Shopping",
            "subcategory":"Clothing, Apparel, & Fashions",
            "type":"Retail Goods"
        }
    ],
    "sg:phone":"+64 9-627 9377",
    "sg:province":"Auckland",
    "sg:tags":[
        "school",
        "clothing",
        "fabric",
        "uniform"
    ],
    "wof:name":"Lively Lad Clothing",
    "wof:placetype":"venue"
},
  "geometry": {"coordinates":[174.70472699999999,-36.919312],"type":"Point"}
}