{
  "type": "Feature",
  "properties": {
    "addr:full":"33 C Connal St Woolston  Christchurch Canterbury",
    "addr:housenumber":"33 c",
    "addr:street":"Connal St",
    "iso:country":"NZ",
    "sg:address":"33 C Connal St Woolston ",
    "sg:city":"Christchurch",
    "sg:classifiers":[
        {
            "category":"Manufacturing",
            "subcategory":"Food",
            "type":"Manufacturing & Wholesale Goods"
        }
    ],
    "sg:phone":"+64 3-384 4039",
    "sg:province":"Canterbury",
    "sg:tags":[
        "drink",
        "-",
        "manufacturer"
    ],
    "wof:name":"Golden Goose Products (1996) Ltd",
    "wof:placetype":"venue"
},
  "geometry": {"coordinates":[172.682571,-43.553146],"type":"Point"}
}