{
  "type": "Feature",
  "properties": {
    "addr:full":"61 Main North Rd  Kaiapoi",
    "addr:housenumber":"61",
    "addr:street":"Main North Rd",
    "iso:country":"NZ",
    "sg:address":"61 Main North Rd ",
    "sg:city":"Kaiapoi",
    "sg:orig_category":"Industrial: Services: Drillers",
    "sg:phone":"+64 3-327 6631",
    "wof:name":"Canterbury Groundwater (1997) Ltd",
    "wof:placetype":"venue"
},
  "geometry": {"coordinates":[172.646164,-43.405674],"type":"Point"}
}