{
  "type": "Feature",
  "properties": {
    "iso:country":"NZ",
    "sg:address":"20 Raroa Rd, Lower ",
    "sg:city":"Hutt",
    "sg:classifiers":[
        {
            "category":"Banks & Credit Unions",
            "subcategory":"Bank",
            "type":"Services"
        }
    ],
    "sg:phone":"+64 4693133",
    "sg:province":"Wellington",
    "wof:name":"UDC Finance Ltd",
    "wof:placetype":"venue"
},
  "geometry": {"coordinates":[174.90965299999999,-41.20752],"type":"Point"}
}