{
  "type": "Feature",
  "properties": {
    "addr:full":"11/46 Ellice Rd Glenfield  Auckland Auckland",
    "addr:housenumber":"11 / 46",
    "addr:street":"Ellice Rd",
    "iso:country":"NZ",
    "sg:address":"11/46 Ellice Rd Glenfield ",
    "sg:city":"Auckland",
    "sg:classifiers":[
        {
            "category":"Shopping",
            "subcategory":"Crafts & Fabrics",
            "type":"Retail Goods"
        }
    ],
    "sg:phone":"+64 9-441 6040",
    "sg:province":"Auckland",
    "sg:tags":[
        "sewing",
        "clothing",
        "supply"
    ],
    "wof:name":"Korbond Industries Ltd",
    "wof:placetype":"venue"
},
  "geometry": {"coordinates":[174.728622,-36.784813],"type":"Point"}
}