{
  "type": "Feature",
  "properties": {
    "addr:full":"Falveys Rd RD 4 Seadown  Timaru Canterbury",
    "addr:street":"Falveys Rd Rd 4 Seadown",
    "iso:country":"NZ",
    "sg:address":"Falveys Rd RD 4 Seadown ",
    "sg:city":"Timaru",
    "sg:classifiers":[
        {
            "category":"Home & Garden",
            "subcategory":"Garden Supply",
            "type":"Retail Goods"
        }
    ],
    "sg:phone":"+64 3-688 2200",
    "sg:province":"Canterbury",
    "sg:tags":[
        "plant",
        "accessories",
        "artificial"
    ],
    "wof:name":"Prestige Silk Plants",
    "wof:placetype":"venue"
},
  "geometry": {"coordinates":[171.23741100000001,-44.395428],"type":"Point"}
}