{
  "type": "Feature",
  "properties": {
    "iso:country":"NZ",
    "sg:address":"11/372 Rosedale Rd Albany ",
    "sg:city":"Auckland",
    "sg:orig_category":"Health And Beauty: Mental: Psychology",
    "sg:phone":"+64 9-414 6601",
    "sg:province":"Auckland",
    "wof:name":"Johnson Jan",
    "wof:placetype":"venue"
},
  "geometry": {"coordinates":[174.69631999999999,-36.742638],"type":"Point"}
}