{
  "type": "Feature",
  "properties": {
    "iso:country":"NZ",
    "sg:address":"205 Archers Rd Glenfield ",
    "sg:city":"Auckland",
    "sg:classifiers":[
        {
            "category":"Manufacturing",
            "subcategory":"Rubber & Plastics",
            "type":"Manufacturing & Wholesale Goods"
        }
    ],
    "sg:phone":"+64 9-444 5553",
    "sg:province":"Auckland",
    "sg:tags":[
        "welder",
        "industrial",
        "-",
        "goods"
    ],
    "wof:name":"Grille & Bumper Exchange Ltd",
    "wof:placetype":"venue"
},
  "geometry": {"coordinates":[174.73919699999999,-36.781139],"type":"Point"}
}