{
  "type": "Feature",
  "properties": {
    "iso:country":"NZ",
    "sg:address":"3 Goodman Pl Penrose ",
    "sg:city":"Auckland",
    "sg:classifiers":[
        {
            "category":"Transit Center",
            "subcategory":"Freight",
            "type":"Transportation"
        }
    ],
    "sg:phone":"+64 9-622 4220",
    "sg:province":"Auckland",
    "sg:tags":[
        "distribution",
        "-",
        "transport"
    ],
    "sg:website":"http://www.distributioncentre.co.nz",
    "wof:name":"The Distribution Centre",
    "wof:placetype":"venue"
},
  "geometry": {"coordinates":[174.80729700000001,-36.919353],"type":"Point"}
}