{
  "type": "Feature",
  "properties": {
    "addr:full":"25 Wellington St Howick  Auckland Auckland",
    "addr:housenumber":"25",
    "addr:street":"Wellington St",
    "iso:country":"NZ",
    "sg:address":"25 Wellington St Howick ",
    "sg:city":"Auckland",
    "sg:orig_category":"Sports And Leisure: General: Clubs",
    "sg:phone":"+64 9-534 9302",
    "sg:province":"Auckland",
    "wof:name":"Returned Services Association",
    "wof:placetype":"venue"
},
  "geometry": {"coordinates":[174.92944299999999,-36.894135],"type":"Point"}
}