{
  "type": "Feature",
  "properties": {
    "addr:full":"PO Box 100433 North Shore Mail Cen  Auckland Auckland",
    "addr:housenumber":"po;100433",
    "addr:street":"Box",
    "iso:country":"NZ",
    "sg:address":"PO Box 100433 North Shore Mail Cen ",
    "sg:city":"Auckland",
    "sg:orig_category":"Sports And Leisure: Entertainment: Balloons",
    "sg:phone":"+64 9-443 6138",
    "sg:province":"Auckland",
    "wof:name":"Nationwide Marketing Ltd",
    "wof:placetype":"venue"
},
  "geometry": {"coordinates":[174.92965699999999,-36.917198],"type":"Point"}
}