{
  "type": "Feature",
  "properties": {
    "iso:country":"NZ",
    "sg:address":"40 Prince Albert Rd St Kilda ",
    "sg:city":"Dunedin",
    "sg:classifiers":[
        {
            "category":"Manufacturing",
            "subcategory":"Rubber & Plastics",
            "type":"Manufacturing & Wholesale Goods"
        }
    ],
    "sg:phone":"+64 3-455 3228",
    "sg:province":"Otago",
    "sg:tags":[
        "stamp",
        "industrial",
        "goods"
    ],
    "wof:name":"Marnies Crafts",
    "wof:placetype":"venue"
},
  "geometry": {"coordinates":[170.504608,-45.900902],"type":"Point"}
}