{
  "type": "Feature",
  "properties": {
    "iso:country":"NZ",
    "sg:address":"13 Mahara Pl ",
    "sg:city":"Waikanae",
    "sg:classifiers":[
        {
            "category":"Sports & Exercise",
            "subcategory":"Sports Center",
            "type":"Entertainment"
        }
    ],
    "sg:phone":"+64 4-293 8826",
    "sg:tags":[
        "indoor",
        "-",
        "leisure",
        "sports"
    ],
    "wof:name":"Kapiti Coast Bowling Centre Inc",
    "wof:placetype":"venue"
},
  "geometry": {"coordinates":[175.06452899999999,-40.876793],"type":"Point"}
}