{
  "type": "Feature",
  "properties": {
    "iso:country":"NZ",
    "sg:address":"281 Jordan Rd ",
    "sg:city":"Kaukapakapa",
    "sg:classifiers":[
        {
            "category":"Retail",
            "subcategory":"Auto Repair",
            "type":"Services"
        }
    ],
    "sg:phone":"+64 9-420 4509",
    "sg:tags":[
        "automotive",
        "restoration",
        "servicing",
        "car"
    ],
    "wof:name":"Kaipara Enterprises Ltd",
    "wof:placetype":"venue"
},
  "geometry": {"coordinates":[174.502365,-36.618408],"type":"Point"}
}