{
  "type": "Feature",
  "properties": {
    "addr:full":"25 Francella Pl Bromley  Christchurch Canterbury",
    "addr:housenumber":"25",
    "addr:street":"Francella Pl",
    "iso:country":"NZ",
    "sg:address":"25 Francella Pl Bromley ",
    "sg:city":"Christchurch",
    "sg:orig_category":"Industrial: Services: Drillers",
    "sg:phone":"+64 3-384 1255",
    "sg:province":"Canterbury",
    "wof:name":"Texco Drilling Ltd",
    "wof:placetype":"venue"
},
  "geometry": {"coordinates":[172.70223999999999,-43.535713],"type":"Point"}
}