{
  "type": "Feature",
  "properties": {
    "addr:full":"Tupaea St  Gisborne Gisborne",
    "addr:street":"St",
    "iso:country":"NZ",
    "sg:address":"Tupaea St ",
    "sg:city":"Gisborne",
    "sg:classifiers":[
        {
            "category":"Shopping",
            "subcategory":"Discount & Variety Stores",
            "type":"Retail Goods"
        }
    ],
    "sg:phone":"+64 6-867 2508",
    "sg:province":"Gisborne",
    "sg:tags":[
        "storage",
        "cool"
    ],
    "wof:name":"Fenn Refrigeration Ltd",
    "wof:placetype":"venue"
},
  "geometry": {"coordinates":[177.99588,-38.664375],"type":"Point"}
}