{
  "type": "Feature",
  "properties": {
    "addr:full":"59 Portage Rd New Lynn  Auckland Auckland",
    "addr:housenumber":"59",
    "addr:street":"Portage Rd",
    "iso:country":"NZ",
    "sg:address":"59 Portage Rd New Lynn ",
    "sg:city":"Auckland",
    "sg:classifiers":[
        {
            "category":"Education",
            "subcategory":"Dance Studio",
            "type":"Public Place"
        }
    ],
    "sg:phone":"+64 9-827 8838",
    "sg:province":"Auckland",
    "sg:tags":[
        "school",
        "dancing",
        "-",
        "leisure",
        "sports",
        "sport"
    ],
    "wof:name":"Auckland Academy Of Dance",
    "wof:placetype":"venue"
},
  "geometry": {"coordinates":[174.689774,-36.912693],"type":"Point"}
}