{
  "type": "Feature",
  "properties": {
    "addr:full":"276 C Wai-Iti Rd Glenwood  Timaru Canterbury",
    "addr:housenumber":"276 c",
    "addr:street":"Wai-Iti Rd",
    "iso:country":"NZ",
    "sg:address":"276 C Wai-Iti Rd Glenwood ",
    "sg:city":"Timaru",
    "sg:classifiers":[
        {
            "category":"Insurance",
            "subcategory":"Health Insurance",
            "type":"Services"
        }
    ],
    "sg:phone":"+64 3-686 1915",
    "sg:province":"Canterbury",
    "sg:tags":[
        "mental",
        "beauty"
    ],
    "wof:name":"Antics Ltd",
    "wof:placetype":"venue"
},
  "geometry": {"coordinates":[171.212616,-44.389183],"type":"Point"}
}