{
  "type": "Feature",
  "properties": {
    "addr:full":"William St  Paeroa",
    "addr:street":"William St",
    "iso:country":"NZ",
    "sg:address":"William St ",
    "sg:city":"Paeroa",
    "sg:classifiers":[
        {
            "category":"Manufacturing",
            "subcategory":"Glass & Minerals",
            "type":"Manufacturing & Wholesale Goods"
        }
    ],
    "sg:phone":"+64 7-862 8609",
    "sg:tags":[
        "raw",
        "industrial",
        "quarry",
        "materials"
    ],
    "wof:name":"Hauraki District Council",
    "wof:placetype":"venue"
},
  "geometry": {"coordinates":[175.66700700000001,-37.379189],"type":"Point"}
}