{
  "type": "Feature",
  "properties": {
    "iso:country":"NZ",
    "sg:address":"95 A Overtoun Tce Hataitai ",
    "sg:city":"Wellington",
    "sg:classifiers":[
        {
            "category":"Sports & Exercise",
            "subcategory":"Sports Center",
            "type":"Entertainment"
        }
    ],
    "sg:phone":"+64 4-386 2166",
    "sg:province":"Wellington",
    "sg:tags":[
        "repair",
        "piano",
        "music",
        "leisure",
        "tuner"
    ],
    "wof:name":"Anne Couper Piano Tuner",
    "wof:placetype":"venue"
},
  "geometry": {"coordinates":[174.79599,-41.309624],"type":"Point"}
}