{
  "type": "Feature",
  "properties": {
    "iso:country":"NZ",
    "sg:address":"771 Cameron Rd ",
    "sg:city":"Tauranga",
    "sg:orig_category":"Health And Beauty: Mental: Psychology",
    "sg:phone":"+64 7-578 9698",
    "sg:province":"Bay of Plenty",
    "wof:name":"Hans Laven Clinical Psychologist",
    "wof:placetype":"venue"
},
  "geometry": {"coordinates":[176.152084,-37.705505],"type":"Point"}
}