{
  "type": "Feature",
  "properties": {
    "addr:full":"PO Box 47609  Ponsonby Auckland",
    "addr:housenumber":"po box",
    "addr:postcode":"47609",
    "iso:country":"NZ",
    "sg:address":"PO Box 47609 ",
    "sg:city":"Ponsonby",
    "sg:orig_category":"Shopping: Retail Stores: Cds, Cassettes And Records",
    "sg:phone":"+64 9-376 7057",
    "sg:province":"Auckland",
    "wof:name":"monkey records",
    "wof:placetype":"venue"
},
  "geometry": {"coordinates":[174.74241599999999,-36.85326],"type":"Point"}
}