{
  "type": "Feature",
  "properties": {
    "iso:country":"NZ",
    "sg:address":"40 Helwick St ",
    "sg:city":"Wanaka",
    "sg:orig_category":"Shopping: Accessories: Jewellers And Watchmakers",
    "sg:phone":"+64 3-443 7037",
    "sg:province":"Otago",
    "wof:name":"The Jeweller Ltd",
    "wof:placetype":"venue"
},
  "geometry": {"coordinates":[169.137024,-44.697044],"type":"Point"}
}