{
  "type": "Feature",
  "properties": {
    "addr:full":"1 Taylors Rd Morningside  Auckland Auckland",
    "addr:housenumber":"1",
    "addr:street":"Taylors Rd",
    "iso:country":"NZ",
    "sg:address":"1 Taylors Rd Morningside ",
    "sg:city":"Auckland",
    "sg:orig_category":"Shopping: Accessories: Handbags",
    "sg:phone":"+64 9-849 7850",
    "sg:province":"Auckland",
    "wof:name":"Modern Bags",
    "wof:placetype":"venue"
},
  "geometry": {"coordinates":[174.735535,-36.875843],"type":"Point"}
}