{
  "type": "Feature",
  "properties": {
    "addr:full":"Bright St  Gisborne Gisborne",
    "addr:street":"Bright St",
    "iso:country":"NZ",
    "sg:address":"Bright St ",
    "sg:city":"Gisborne",
    "sg:classifiers":[
        {
            "category":"Shopping",
            "subcategory":"Stationery & Office Supplies",
            "type":"Retail Goods"
        }
    ],
    "sg:phone":"+64 6-867 9769",
    "sg:province":"Gisborne",
    "sg:tags":[
        "supplies",
        "educational",
        "material",
        "education",
        "training"
    ],
    "wof:name":"Education Centre",
    "wof:placetype":"venue"
},
  "geometry": {"coordinates":[178.02310199999999,-38.667126],"type":"Point"}
}