{
  "type": "Feature",
  "properties": {
    "iso:country":"NZ",
    "sg:address":"42 B Porana Rd Glenfield ",
    "sg:city":"Auckland",
    "sg:orig_category":"Shopping: Sports Retailers: Sports Goods: Canvas Goods",
    "sg:phone":"+64 9-444 5308",
    "sg:province":"Auckland",
    "wof:name":"Marine Trimmers Ltd",
    "wof:placetype":"venue"
},
  "geometry": {"coordinates":[174.728622,-36.784813],"type":"Point"}
}