{
  "type": "Feature",
  "properties": {
    "addr:full":"Manchester Street, Riverlands Trading Estate  Blenheim Wellington",
    "addr:housenumber":"estate",
    "addr:street":"Manchester Street;Trading",
    "iso:country":"NZ",
    "sg:address":"Manchester Street, Riverlands Trading Estate ",
    "sg:city":"Blenheim",
    "sg:orig_category":"Transport: Transportation: Transport Operators",
    "sg:phone":"+64 3-579 2110",
    "sg:province":"Wellington",
    "wof:name":"Trans Otway Ltd",
    "wof:placetype":"venue"
},
  "geometry": {"coordinates":[174.01031499999999,-41.53009],"type":"Point"}
}