{
  "type": "Feature",
  "properties": {
    "addr:full":"164-188 Beaumont St Freemans Bay PO Box 8789 Symonds, St  Auckland Auckland",
    "addr:housenumber":"164-188;po box 8789",
    "addr:street":"Beaumont St;Symonds St",
    "iso:country":"NZ",
    "sg:address":"164-188 Beaumont St Freemans Bay PO Box 8789 Symonds, St ",
    "sg:city":"Auckland",
    "sg:classifiers":[
        {
            "category":"Banks & Credit Unions",
            "subcategory":"Investment Brokerage",
            "type":"Services"
        }
    ],
    "sg:phone":"+64 9-302 9172",
    "sg:province":"Auckland",
    "sg:tags":[
        "chemical",
        "industrial",
        "-",
        "compounds"
    ],
    "wof:name":"ExxonMobil Chemical New Zealand Limited",
    "wof:placetype":"venue"
},
  "geometry": {"coordinates":[174.77041600000001,-36.884109],"type":"Point"}
}