{
  "type": "Feature",
  "properties": {
    "iso:country":"NZ",
    "sg:address":"2-22 Cambridge St South ",
    "sg:city":"Levin",
    "sg:classifiers":[
        {
            "category":"Coffee & Tea",
            "type":"Food & Drink"
        }
    ],
    "sg:phone":"+64 6-367 8301",
    "sg:province":"Manawatu-Wanganui",
    "sg:tags":[
        "vegetable",
        "fruit",
        "veges"
    ],
    "wof:name":"Wilcox A S & Sons Ltd",
    "wof:placetype":"venue"
},
  "geometry": {"coordinates":[-89.084503,37.193748],"type":"Point"}
}