{
  "type": "Feature",
  "properties": {
    "iso:country":"NZ",
    "sg:address":"3 Delta Dve Renwick ",
    "sg:city":"Blenheim",
    "sg:classifiers":[
        {
            "category":"Sports & Exercise",
            "subcategory":"Sports Center",
            "type":"Entertainment"
        }
    ],
    "sg:phone":"+64 3-572 9180",
    "sg:province":"Marlborough",
    "sg:tags":[
        "health",
        "beauty",
        "fitness"
    ],
    "wof:name":"Body Zone Yoga Fitness Centre",
    "wof:placetype":"venue"
},
  "geometry": {"coordinates":[173.828461,-41.510769],"type":"Point"}
}