{
  "type": "Feature",
  "properties": {
    "addr:full":"Cnr Cornwall St & Kings Cre Lower  Hutt Wellington",
    "addr:street":"Cnr Cornwall St & Kings Cre",
    "iso:country":"NZ",
    "sg:address":"Cnr Cornwall St & Kings Cre Lower ",
    "sg:city":"Hutt",
    "sg:orig_category":"Clothing And Fabric: Clothing: Children'S Wear",
    "sg:phone":"+64 4-566 8401",
    "sg:province":"Wellington",
    "wof:name":"Baby Factory",
    "wof:placetype":"venue"
},
  "geometry": {"coordinates":[174.904526,-41.208431],"type":"Point"}
}