{
  "type": "Feature",
  "properties": {
    "addr:full":"108 Hutt Rd Petone Lower  Hutt Wellington",
    "addr:housenumber":"108",
    "addr:street":"Hutt Rd",
    "iso:country":"NZ",
    "sg:address":"108 Hutt Rd Petone Lower ",
    "sg:city":"Hutt",
    "sg:classifiers":[
        {
            "category":"Retail",
            "subcategory":"Auto Repair",
            "type":"Services"
        }
    ],
    "sg:phone":"+64 4-568 3428",
    "sg:province":"Wellington",
    "sg:tags":[
        "automotive",
        "absorber",
        "shock",
        "servicing"
    ],
    "wof:name":"Tyrepower Hutt Rd Ltd",
    "wof:placetype":"venue"
},
  "geometry": {"coordinates":[174.87416099999999,-41.221539],"type":"Point"}
}