{
  "type": "Feature",
  "properties": {
    "iso:country":"NZ",
    "sg:address":"Dowco Associates Ltd 169 Main Hwy ",
    "sg:city":"Otaki",
    "sg:classifiers":[
        {
            "category":"Banks & Credit Unions",
            "subcategory":"Investment Brokerage",
            "type":"Services"
        }
    ],
    "sg:phone":"+64 6-364 5767",
    "sg:tags":[
        "industrial",
        "cleaning",
        "maintenance"
    ],
    "wof:name":"Soapbox",
    "wof:placetype":"venue"
},
  "geometry": {"coordinates":[175.148788,-40.759144],"type":"Point"}
}