{
  "type": "Feature",
  "properties": {
    "addr:full":"Mt Roskill/Titirangi  Auckland Auckland",
    "addr:housenumber":"titirangi",
    "iso:country":"NZ",
    "sg:address":"Mt Roskill/Titirangi ",
    "sg:city":"Auckland",
    "sg:classifiers":[
        {
            "category":"Arena",
            "subcategory":"Sports Club",
            "type":"Entertainment"
        }
    ],
    "sg:phone":"+64 9-818 4689",
    "sg:province":"Auckland",
    "sg:tags":[
        "martial art",
        "-",
        "leisure",
        "sports"
    ],
    "wof:name":"Bushido Ju Jutsu",
    "wof:placetype":"venue"
},
  "geometry": {"coordinates":[174.74276699999999,-36.905895],"type":"Point"}
}