{
  "type": "Feature",
  "properties": {
    "addr:full":"97 Oreti Rd Otatara  Invercargill Southland",
    "addr:housenumber":"97",
    "addr:street":"Oreti Rd",
    "iso:country":"NZ",
    "sg:address":"97 Oreti Rd Otatara ",
    "sg:city":"Invercargill",
    "sg:orig_category":"Farming: Services: Aerial Photographers",
    "sg:phone":"+64 3-213 1515",
    "sg:province":"Southland",
    "wof:name":"Sonya Crook",
    "wof:placetype":"venue"
},
  "geometry": {"coordinates":[168.29719499999999,-46.435978],"type":"Point"}
}