{
  "type": "Feature",
  "properties": {
    "iso:country":"NZ",
    "sg:address":"152 Lansford Cre Avondale ",
    "sg:city":"Auckland",
    "sg:classifiers":[
        {
            "category":"Sports & Exercise",
            "subcategory":"Climbing Gym",
            "type":"Entertainment"
        }
    ],
    "sg:phone":"+64 9-828 1188",
    "sg:province":"Auckland",
    "sg:tags":[
        "-",
        "leisure",
        "sports"
    ],
    "sg:website":"http://www.yellowpages.co.nz/for/cardwellracing/dp109.html",
    "wof:name":"Cardwell Racing Supplies",
    "wof:placetype":"venue"
},
  "geometry": {"coordinates":[174.69935599999999,-36.905937],"type":"Point"}
}