{
  "type": "Feature",
  "properties": {
    "addr:full":"59 Woodside Rd Northcote  Auckland Auckland",
    "addr:housenumber":"59",
    "addr:street":"Woodside Rd",
    "iso:country":"NZ",
    "sg:address":"59 Woodside Rd Northcote ",
    "sg:city":"Auckland",
    "sg:orig_category":"Transport: Boats And Marine: Products: Marine Electronics",
    "sg:phone":"+64 9-480 2308",
    "sg:province":"Auckland",
    "wof:name":"Webster Electronic Services Ltd",
    "wof:placetype":"venue"
},
  "geometry": {"coordinates":[174.740768,-36.805565],"type":"Point"}
}