{
  "type": "Feature",
  "properties": {
    "addr:full":"171 Rolleston St  Hokitika West Coast",
    "addr:housenumber":"171",
    "addr:street":"Rolleston St",
    "iso:country":"NZ",
    "sg:address":"171 Rolleston St ",
    "sg:city":"Hokitika",
    "sg:classifiers":[
        {
            "category":"Building & Trades",
            "subcategory":"Pest Control",
            "type":"Services"
        }
    ],
    "sg:phone":"+64 3-755 8530",
    "sg:province":"West Coast",
    "sg:tags":[
        "home",
        "garden"
    ],
    "wof:name":"Hokitika Cleaning Services",
    "wof:placetype":"venue"
},
  "geometry": {"coordinates":[170.975098,-42.71801],"type":"Point"}
}