{
  "type": "Feature",
  "properties": {
    "iso:country":"NZ",
    "sg:address":"cnrs of Wellesley Rd Latham St & Monroe St ",
    "sg:city":"Napier",
    "sg:orig_category":"Storage: Storage",
    "sg:phone":"+64 6-835 7575",
    "sg:province":"Hawke's Bay",
    "wof:name":"Napier Self Storage",
    "wof:placetype":"venue"
},
  "geometry": {"coordinates":[-71.289749,42.297779],"type":"Point"}
}