{
  "type": "Feature",
  "properties": {
    "iso:country":"NZ",
    "sg:address":"50 McLean St ",
    "sg:city":"Waitara",
    "sg:classifiers":[
        {
            "category":"Banks & Credit Unions",
            "subcategory":"Investment Brokerage",
            "type":"Services"
        }
    ],
    "sg:phone":"+64 6-754 7496",
    "sg:tags":[
        "personal",
        "accountant",
        "chartered",
        "-",
        "finance"
    ],
    "wof:name":"Vanburwray Chartered Accountants Limited",
    "wof:placetype":"venue"
},
  "geometry": {"coordinates":[174.2395324707,-39.0000228882],"type":"Point"}
}