{
  "type": "Feature",
  "properties": {
    "addr:full":"110 Park Rd Grafton  Auckland Auckland",
    "addr:housenumber":"110",
    "addr:street":"Park Rd",
    "iso:country":"NZ",
    "sg:address":"110 Park Rd Grafton ",
    "sg:city":"Auckland",
    "sg:orig_category":"Clothing And Fabric: Fabric: Textiles",
    "sg:phone":"+64 9-309 2818",
    "sg:province":"Auckland",
    "wof:name":"Mawson Textiles Ltd",
    "wof:placetype":"venue"
},
  "geometry": {"coordinates":[174.76547199999999,-36.862892],"type":"Point"}
}