{
  "type": "Feature",
  "properties": {
    "iso:country":"NZ",
    "sg:address":"Level 2 Lopdell House 418 Titirangi Road Titirangi",
    "sg:city":"Auckland",
    "sg:classifiers":[
        {
            "category":"Personal",
            "type":"Services"
        }
    ],
    "sg:phone":"+64 9-817 4628",
    "sg:province":"Auckland",
    "sg:tags":[
        "services",
        "home",
        "garden",
        "counselling"
    ],
    "sg:website":"http://www.yellowpages.co.nz/pages/214101301/dp53503.html",
    "wof:name":"Knowings",
    "wof:placetype":"venue"
},
  "geometry": {"coordinates":[174.662796,-36.926861],"type":"Point"}
}