{
  "type": "Feature",
  "properties": {
    "addr:full":"PO Box 54220 Bucklands Beach  Auckland Auckland",
    "addr:housenumber":"po box",
    "addr:postcode":"54220",
    "iso:country":"NZ",
    "sg:address":"PO Box 54220 Bucklands Beach ",
    "sg:city":"Auckland",
    "sg:orig_category":"Industrial: Equipment And Machinery: Specialist Equipment: Machinery: Sewing Machines",
    "sg:phone":"+64 9-535 8847",
    "sg:province":"Auckland",
    "wof:name":"Angie Spong Machine Embroidery Designs",
    "wof:placetype":"venue"
},
  "geometry": {"coordinates":[174.90318300000001,-36.858368],"type":"Point"}
}