{
  "type": "Feature",
  "properties": {
    "addr:full":"PO Box 10111  Hamilton Waikato",
    "addr:housenumber":"po box 10111",
    "iso:country":"NZ",
    "sg:address":"PO Box 10111 ",
    "sg:city":"Hamilton",
    "sg:orig_category":"Automotive: Accessories: Motor Accessories",
    "sg:phone":"+64 7-849 6609",
    "sg:province":"Waikato",
    "wof:name":"Perei Group NZ Ltd",
    "wof:placetype":"venue"
},
  "geometry": {"coordinates":[-87.988968,34.142426],"type":"Point"}
}