{
  "type": "Feature",
  "properties": {
    "iso:country":"NZ",
    "sg:address":"26 Montgomery Cre Upper ",
    "sg:city":"Hutt",
    "sg:orig_category":"Industrial: Parts: Valves",
    "sg:phone":"+64 4-526 4415",
    "sg:province":"Wellington",
    "wof:name":"Hydra-Cell Pumps Limited",
    "wof:placetype":"venue"
},
  "geometry": {"coordinates":[175.069031,-41.12458],"type":"Point"}
}