{
  "type": "Feature",
  "properties": {
    "addr:full":"134 Burma Rd Khandallah  Wellington Wellington",
    "addr:housenumber":"134",
    "addr:street":"Burma Rd",
    "iso:country":"NZ",
    "sg:address":"134 Burma Rd Khandallah ",
    "sg:city":"Wellington",
    "sg:classifiers":[
        {
            "category":"Social Services",
            "subcategory":"Retirement Home",
            "type":"Services"
        }
    ],
    "sg:phone":"+64 4-478 3754",
    "sg:province":"Wellington",
    "sg:tags":[
        "care",
        "garden",
        "elderly",
        "village"
    ],
    "wof:name":"Malvina Major Retirement Village Ltd",
    "wof:placetype":"venue"
},
  "geometry": {"coordinates":[174.79724100000001,-41.238708],"type":"Point"}
}