{
  "type": "Feature",
  "properties": {
    "iso:country":"NZ",
    "sg:address":"4/977 Heaphy Tce ",
    "sg:city":"Hamilton",
    "sg:classifiers":[
        {
            "category":"Personal",
            "subcategory":"Tattoo Parlor",
            "type":"Services"
        }
    ],
    "sg:phone":"+64 7-855 7633",
    "sg:province":"Waikato",
    "sg:tags":[
        "services",
        "home",
        "tattooists",
        "garden"
    ],
    "wof:name":"Skinks Professional Tattoo & Piercing Studio",
    "wof:placetype":"venue"
},
  "geometry": {"coordinates":[175.276993,-37.783215],"type":"Point"}
}