{
  "type": "Feature",
  "properties": {
    "iso:country":"NZ",
    "sg:address":"136 Larnach Rd Waverley ",
    "sg:city":"Dunedin",
    "sg:orig_category":"Home And Garden: Gardening: Services: Lawnmowing Services",
    "sg:phone":"+64 3-454 5045",
    "sg:province":"Otago",
    "wof:name":"Howard's Way",
    "wof:placetype":"venue"
},
  "geometry": {"coordinates":[170.53379799999999,-45.883518],"type":"Point"}
}