{
  "type": "Feature",
  "properties": {
    "addr:full":"Lvl 3, Tourism & Travel House 79 Boulcott St  Wellington Wellington",
    "addr:housenumber":"lvl 3;79",
    "addr:street":"Boulcott St",
    "iso:country":"NZ",
    "sg:address":"Lvl 3, Tourism & Travel House 79 Boulcott St ",
    "sg:city":"Wellington",
    "sg:classifiers":[
        {
            "category":"Banks & Credit Unions",
            "subcategory":"Investment Brokerage",
            "type":"Services"
        }
    ],
    "sg:phone":"+64 4-471 0662",
    "sg:province":"Wellington",
    "sg:tags":[
        "personal",
        "-",
        "finance"
    ],
    "sg:website":"http://www.creatingwealth.co.nz",
    "wof:name":"Creating Wealth Investments Ltd",
    "wof:placetype":"venue"
},
  "geometry": {"coordinates":[174.92103599999999,-41.202091],"type":"Point"}
}