{
  "type": "Feature",
  "properties": {
    "iso:country":"NZ",
    "sg:address":"9 Alfred St ",
    "sg:city":"Nelson",
    "sg:classifiers":[
        {
            "category":"Health Services",
            "subcategory":"Health Practitioner",
            "type":"Services"
        }
    ],
    "sg:phone":"+64 3-546 8733",
    "sg:province":"Nelson",
    "sg:tags":[
        "services",
        "beauty",
        "acupuncturists"
    ],
    "wof:name":"Black John",
    "wof:placetype":"venue"
},
  "geometry": {"coordinates":[-121.765488,39.553471],"type":"Point"}
}