{
  "type": "Feature",
  "properties": {
    "iso:country":"NZ",
    "sg:address":"16 Main St ",
    "sg:city":"Gore",
    "sg:classifiers":[
        {
            "category":"Banks & Credit Unions",
            "subcategory":"Investment Brokerage",
            "type":"Services"
        }
    ],
    "sg:phone":"+64 3-208 9390",
    "sg:province":"Southland",
    "sg:tags":[
        "personal",
        "accountant",
        "chartered",
        "-",
        "finance"
    ],
    "wof:name":"Macdonald & Associates Chartered Accountants Ltd",
    "wof:placetype":"venue"
},
  "geometry": {"coordinates":[-95.117569,35.52932],"type":"Point"}
}