{
  "type": "Feature",
  "properties": {
    "iso:country":"NZ",
    "sg:address":"13 Rust Ave ",
    "sg:city":"Whangarei",
    "sg:classifiers":[
        {
            "category":"Banks & Credit Unions",
            "subcategory":"Investment Brokerage",
            "type":"Services"
        }
    ],
    "sg:phone":"+64 9-438 7046",
    "sg:province":"Northland",
    "sg:tags":[
        "personal",
        "accountant",
        "chartered",
        "-",
        "finance"
    ],
    "wof:name":"O'Neill Graeme",
    "wof:placetype":"venue"
},
  "geometry": {"coordinates":[174.31733700000001,-35.723305],"type":"Point"}
}