{
  "type": "Feature",
  "properties": {
    "iso:country":"NZ",
    "sg:address":"18 Cross Rd Sulphur Pt ",
    "sg:city":"Tauranga",
    "sg:classifiers":[
        {
            "category":"Farming",
            "subcategory":"Fish & Marine Products",
            "type":"Manufacturing & Wholesale Goods"
        }
    ],
    "sg:phone":"+64 7-578 9593",
    "sg:province":"Bay of Plenty",
    "sg:tags":[
        "boats",
        "yacht",
        "transport",
        "boat",
        "supply"
    ],
    "wof:name":"Steve's Marine Supplies Ltd",
    "wof:placetype":"venue"
},
  "geometry": {"coordinates":[176.169144,-37.672024],"type":"Point"}
}