{
  "type": "Feature",
  "properties": {
    "iso:country":"NZ",
    "sg:address":"2 Graham St Pukekohe ",
    "sg:city":"Auckland",
    "sg:orig_category":"Industrial: Packaging: Packaging - General",
    "sg:phone":"+64 9-239 0580",
    "sg:province":"Auckland",
    "wof:name":"New Zealand Packaging & Tape Supplies Ltd",
    "wof:placetype":"venue"
},
  "geometry": {"coordinates":[-119.104576,36.597755],"type":"Point"}
}