{
  "type": "Feature",
  "properties": {
    "addr:full":"70 Union St  Hawera Taranaki",
    "addr:housenumber":"70",
    "addr:street":"Union St",
    "iso:country":"NZ",
    "sg:address":"70 Union St ",
    "sg:city":"Hawera",
    "sg:orig_category":"Automotive: Parts And Supplies: Windscreens",
    "sg:phone":"+64 6-278 6630",
    "sg:province":"Taranaki",
    "wof:name":"Hilford Panelbeaters",
    "wof:placetype":"venue"
},
  "geometry": {"coordinates":[174.28372200000001,-39.585564],"type":"Point"}
}