{
  "type": "Feature",
  "properties": {
    "iso:country":"NZ",
    "sg:address":"70 Union St ",
    "sg:city":"Hawera",
    "sg:orig_category":"Automotive: Parts And Supplies: Windscreens",
    "sg:phone":"+64 6-278 6630",
    "sg:province":"Taranaki",
    "wof:name":"Hilford Panelbeaters",
    "wof:placetype":"venue"
},
  "geometry": {"coordinates":[174.283722,-39.585564],"type":"Point"}
}