{
  "type": "Feature",
  "properties": {
    "addr:full":"45 Vickerman St Port Nelson  Nelson Nelson",
    "addr:housenumber":"45",
    "addr:street":"Vickerman St",
    "iso:country":"NZ",
    "sg:address":"45 Vickerman St Port Nelson ",
    "sg:city":"Nelson",
    "sg:classifiers":[
        {
            "category":"Retail",
            "subcategory":"Repair Shop",
            "type":"Services"
        }
    ],
    "sg:phone":"+64 3-548 4431",
    "sg:province":"Nelson",
    "sg:tags":[
        "machine",
        "equipment",
        "industrial",
        "machinery"
    ],
    "wof:name":"Trojan Engineering Ltd",
    "wof:placetype":"venue"
},
  "geometry": {"coordinates":[173.27810700000001,-41.263725],"type":"Point"}
}