{
  "type": "Feature",
  "properties": {
    "iso:country":"NZ",
    "sg:address":"45 Vickerman St Port Nelson ",
    "sg:city":"Nelson",
    "sg:classifiers":[
        {
            "category":"Retail",
            "subcategory":"Repair Shop",
            "type":"Services"
        }
    ],
    "sg:phone":"+64 3-548 4431",
    "sg:province":"Nelson",
    "sg:tags":[
        "machine",
        "equipment",
        "industrial",
        "machinery"
    ],
    "wof:name":"Trojan Engineering Ltd",
    "wof:placetype":"venue"
},
  "geometry": {"coordinates":[173.278107,-41.263725],"type":"Point"}
}