{
  "type": "Feature",
  "properties": {
    "addr:full":"St Heliers  Auckland Auckland",
    "iso:country":"NZ",
    "sg:address":"St Heliers ",
    "sg:city":"Auckland",
    "sg:classifiers":[
        {
            "category":"Personal",
            "subcategory":"Massage",
            "type":"Services"
        }
    ],
    "sg:phone":"+64 9-575 3383",
    "sg:province":"Auckland",
    "sg:tags":[
        "services",
        "health",
        "-",
        "beauty",
        "fitness"
    ],
    "wof:name":"Julie Harris Body Therapies",
    "wof:placetype":"venue"
},
  "geometry": {"coordinates":[174.860275,-36.858349],"type":"Point"}
}