{
  "type": "Feature",
  "properties": {
    "iso:country":"NZ",
    "sg:address":"9 Jayne Pl Torbay ",
    "sg:city":"Auckland",
    "sg:orig_category":"Shopping: Retail Stores: Toys",
    "sg:phone":"+64 9-473 9099",
    "sg:province":"Auckland",
    "wof:name":"L A Marketing",
    "wof:placetype":"venue"
},
  "geometry": {"coordinates":[174.74299600000001,-36.693329],"type":"Point"}
}