{
  "type": "Feature",
  "properties": {
    "addr:full":"111 Hereford St  Christchurch Canterbury",
    "addr:housenumber":"111",
    "addr:street":"Hereford St",
    "iso:country":"NZ",
    "sg:address":"111 Hereford St ",
    "sg:city":"Christchurch",
    "sg:orig_category":"Shopping: Accessories: Bags - Fashion",
    "sg:phone":"+64 3-377 4463",
    "sg:province":"Canterbury",
    "wof:name":"Saks & Such",
    "wof:placetype":"venue"
},
  "geometry": {"coordinates":[-76.537834,37.605659],"type":"Point"}
}