{
  "type": "Feature",
  "properties": {
    "iso:country":"NZ",
    "sg:address":"30 Jackson Way R D 3 Silverdale Hibiscus ",
    "sg:city":"Hibiscus Coast",
    "sg:orig_category":"Farming: Horticulture: Flowers",
    "sg:phone":"+64 9-426 8858",
    "sg:province":"Auckland",
    "wof:name":"Genesis Propagation Ltd",
    "wof:placetype":"venue"
},
  "geometry": {"coordinates":[174.67579699999999,-36.6208],"type":"Point"}
}