{
  "type": "Feature",
  "properties": {
    "addr:full":"PO Box 893  Rotorua Bay of Plenty",
    "addr:housenumber":"po;893",
    "addr:street":"Box",
    "iso:country":"NZ",
    "sg:address":"PO Box 893 ",
    "sg:city":"Rotorua",
    "sg:orig_category":"Shopping: Tobacco: Tobacco Outlets",
    "sg:phone":"+64 7-348 2919",
    "sg:province":"Bay of Plenty",
    "wof:name":"British American Tobacco (NZ) Limited",
    "wof:placetype":"venue"
},
  "geometry": {"coordinates":[176.24499499999999,-38.1418],"type":"Point"}
}