{
  "type": "Feature",
  "properties": {
    "iso:country":"NZ",
    "sg:address":"11 Disraeli St Addington ",
    "sg:city":"Christchurch",
    "sg:classifiers":[
        {
            "category":"Building & Trades",
            "subcategory":"Electrical",
            "type":"Services"
        }
    ],
    "sg:phone":"+64 3-366 0399",
    "sg:province":"Canterbury",
    "sg:tags":[
        "industrial",
        "refrigeration"
    ],
    "wof:name":"Hawkins Refrigeration Ltd",
    "wof:placetype":"venue"
},
  "geometry": {"coordinates":[172.622757,-43.542091],"type":"Point"}
}