{
  "type": "Feature",
  "properties": {
    "addr:full":"24 Bridge St  Mataura",
    "addr:housenumber":"24",
    "addr:street":"Bridge St",
    "iso:country":"NZ",
    "sg:address":"24 Bridge St ",
    "sg:city":"Mataura",
    "sg:orig_category":"Health And Beauty: Products: Pharmacies",
    "sg:phone":"+64 3-203 8044",
    "wof:name":"Mataura Pharmacy Ltd",
    "wof:placetype":"venue"
},
  "geometry": {"coordinates":[168.86674500000001,-46.194504],"type":"Point"}
}