{
  "type": "Feature",
  "properties": {
    "iso:country":"NZ",
    "sg:address":"45 Queens Dve ",
    "sg:city":"Invercargill",
    "sg:classifiers":[
        {
            "category":"Personal",
            "type":"Services"
        }
    ],
    "sg:phone":"+64 3-217 8292",
    "sg:province":"Southland",
    "sg:tags":[
        "celebrant",
        "arrangements",
        "marriage",
        "wedding"
    ],
    "wof:name":"Robinson Iris JP",
    "wof:placetype":"venue"
},
  "geometry": {"coordinates":[-73.831261,40.703781],"type":"Point"}
}