{
  "type": "Feature",
  "properties": {
    "iso:country":"NZ",
    "sg:address":"Dressmart Mall Galway St Onehunga ",
    "sg:city":"Auckland",
    "sg:orig_category":"Shopping: Accessories: Handbags",
    "sg:phone":"+64 9-622 2606",
    "sg:province":"Auckland",
    "wof:name":"Modern Bags",
    "wof:placetype":"venue"
},
  "geometry": {"coordinates":[174.783661,-36.909973],"type":"Point"}
}