{
  "type": "Feature",
  "properties": {
    "addr:full":"6 Stanley St Sydenham  Christchurch Canterbury",
    "addr:housenumber":"6",
    "addr:street":"Stanley St",
    "iso:country":"NZ",
    "sg:address":"6 Stanley St Sydenham ",
    "sg:city":"Christchurch",
    "sg:orig_category":"Shopping: Dispensing: Vending Machines",
    "sg:phone":"+64 3-377 2336",
    "sg:province":"Canterbury",
    "wof:name":"HL Marketing",
    "wof:placetype":"venue"
},
  "geometry": {"coordinates":[172.63417100000001,-43.547096],"type":"Point"}
}