{
  "type": "Feature",
  "properties": {
    "iso:country":"NZ",
    "sg:address":"Gibbston Queenstown R D ",
    "sg:city":"1",
    "sg:classifiers":[
        {
            "category":"Bars & Pubs",
            "type":"Food & Drink"
        }
    ],
    "sg:phone":"+64 3-442 6910",
    "sg:website":"http://www.gvwines.co.nz/",
    "wof:name":"Gibbston Valley Wines",
    "wof:placetype":"venue"
},
  "geometry": {"coordinates":[-76.157791,38.990379],"type":"Point"}
}