{
  "type": "Feature",
  "properties": {
    "iso:country":"NZ",
    "sg:address":"Grasslands Pl ",
    "sg:city":"Hamilton",
    "sg:classifiers":[
        {
            "category":"Home & Garden",
            "subcategory":"Furniture",
            "type":"Retail Goods"
        }
    ],
    "sg:phone":"+64 7-847 0609",
    "sg:province":"Waikato",
    "sg:tags":[
        "fitting"
    ],
    "sg:website":"http://www.yellowpages.co.nz/pages/102661787/dp23843.html",
    "wof:name":"Hamilton Plumbing Co Ltd",
    "wof:placetype":"venue"
},
  "geometry": {"coordinates":[175.262695,-37.80537],"type":"Point"}
}