{
  "type": "Feature",
  "properties": {
    "addr:full":"121 Main St  Pahiatua",
    "addr:housenumber":"121",
    "addr:street":"Main St",
    "iso:country":"NZ",
    "sg:address":"121 Main St ",
    "sg:city":"Pahiatua",
    "sg:classifiers":[
        {
            "category":"Landmark",
            "subcategory":"Tourist Information",
            "type":"Public Place"
        }
    ],
    "sg:phone":"+64 6-376 6619",
    "sg:tags":[
        "services",
        "travel",
        "tourism"
    ],
    "wof:name":"Pahiatua Information Centre",
    "wof:placetype":"venue"
},
  "geometry": {"coordinates":[175.83583100000001,-40.458637],"type":"Point"}
}