{
  "type": "Feature",
  "properties": {
    "iso:country":"NZ",
    "sg:address":"Ngahina St ",
    "sg:city":"Paraparaumu",
    "sg:classifiers":[
        {
            "category":"Social Services",
            "subcategory":"Child Care",
            "type":"Services"
        }
    ],
    "sg:phone":"+64 4-298 6298",
    "sg:province":"Wellington",
    "sg:tags":[
        "home",
        "garden",
        "children"
    ],
    "wof:name":"Wellington Region Free Kindergarten Association",
    "wof:placetype":"venue"
},
  "geometry": {"coordinates":[175.003418,-40.913158],"type":"Point"}
}