{
  "type": "Feature",
  "properties": {
    "addr:full":"37 King St  Rangiora Canterbury",
    "addr:housenumber":"37",
    "addr:street":"King St",
    "iso:country":"NZ",
    "sg:address":"37 King St ",
    "sg:city":"Rangiora",
    "sg:classifiers":[
        {
            "category":"Home & Garden",
            "subcategory":"Home Furnishings",
            "type":"Retail Goods"
        }
    ],
    "sg:phone":"+64 3-313 8826",
    "sg:province":"Canterbury",
    "sg:tags":[
        "furniture/furnishings",
        "upholstery",
        "supply"
    ],
    "wof:name":"Cole P C",
    "wof:placetype":"venue"
},
  "geometry": {"coordinates":[172.59291099999999,-43.31522],"type":"Point"}
}