{
  "type": "Feature",
  "properties": {
    "addr:full":"cnr Barrington & Bewdley Sts Spreydon  Christchurch Canterbury",
    "addr:street":"Cnr",
    "iso:country":"NZ",
    "sg:address":"cnr Barrington & Bewdley Sts Spreydon ",
    "sg:city":"Christchurch",
    "sg:orig_category":"Shopping: Sports Retailers: Sports Goods: Canvas Goods",
    "sg:phone":"+64 3-338 5243",
    "sg:province":"Canterbury",
    "wof:name":"MacFarlane Sunblinds",
    "wof:placetype":"venue"
},
  "geometry": {"coordinates":[172.616196,-43.553249],"type":"Point"}
}