{
  "type": "Feature",
  "properties": {
    "addr:full":"31 Union St  Milton",
    "addr:housenumber":"31",
    "addr:street":"Union St",
    "iso:country":"NZ",
    "sg:address":"31 Union St ",
    "sg:city":"Milton",
    "sg:orig_category":"Sports And Leisure: General: Clubs",
    "sg:phone":"+64 3-417 8927",
    "wof:name":"Milton Bruce RSA",
    "wof:placetype":"venue"
},
  "geometry": {"coordinates":[-71.096558,42.260109],"type":"Point"}
}