{
  "type": "Feature",
  "properties": {
    "addr:full":"Taieri Ferry Rd RD1  Outram",
    "addr:postcode":"rd1",
    "addr:street":"Ferry Rd",
    "iso:country":"NZ",
    "sg:address":"Taieri Ferry Rd RD1 ",
    "sg:city":"Outram",
    "sg:orig_category":"Shopping: Sports Retailers: Water Sports: Personal Watercraft",
    "sg:phone":"+64 3-417 8993",
    "wof:name":"Otago Personal Watercraft",
    "wof:placetype":"venue"
},
  "geometry": {"coordinates":[170.28147899999999,-45.912197],"type":"Point"}
}