{
  "type": "Feature",
  "properties": {
    "addr:full":"134 Durham St  Tauranga Bay of Plenty",
    "addr:housenumber":"134",
    "addr:street":"Durham St",
    "iso:country":"NZ",
    "sg:address":"134 Durham St ",
    "sg:city":"Tauranga",
    "sg:classifiers":[
        {
            "category":"Retail",
            "subcategory":"Auto Repair",
            "type":"Services"
        }
    ],
    "sg:phone":"+64 7-578 4502",
    "sg:province":"Bay of Plenty",
    "sg:tags":[
        "automotive",
        "servicing"
    ],
    "sg:website":"http://www.frankallentyres.co.nz",
    "wof:name":"Frank Allen Tyres",
    "wof:placetype":"venue"
},
  "geometry": {"coordinates":[176.16726700000001,-37.685879],"type":"Point"}
}