{
  "type": "Feature",
  "properties": {
    "iso:country":"NZ",
    "sg:address":"537 Kamo Rd Kamo ",
    "sg:city":"Whangarei",
    "sg:classifiers":[
        {
            "category":"Sports & Exercise",
            "subcategory":"Swimming Pool",
            "type":"Entertainment"
        }
    ],
    "sg:phone":"+64 9-435 0174",
    "sg:province":"Northland",
    "sg:tags":[
        "home",
        "outdoor",
        "garden",
        "spa"
    ],
    "wof:name":"Kamo Unichem Pharmacy",
    "wof:placetype":"venue"
},
  "geometry": {"coordinates":[174.30055200000001,-35.682968],"type":"Point"}
}