{
  "type": "Feature",
  "properties": {
    "iso:country":"NZ",
    "sg:address":"Christchurch ",
    "sg:city":"Christchurch",
    "sg:orig_category":"Sports And Leisure: Entertainment: Entertainers",
    "sg:phone":"+64 3-365 8115",
    "sg:province":"Canterbury",
    "wof:name":"Bagpiper",
    "wof:placetype":"venue"
},
  "geometry": {"coordinates":[-1.77656,50.73407],"type":"Point"}
}