{
  "type": "Feature",
  "properties": {
    "iso:country":"NZ",
    "sg:address":"Mangakahia Rd ",
    "sg:city":"Kaikohe",
    "sg:classifiers":[
        {
            "category":"Bus Charters",
            "type":"Transportation"
        }
    ],
    "sg:phone":"+64 9-401 0193",
    "sg:tags":[
        "services",
        "travel",
        "tourism"
    ],
    "wof:name":"Kaikohe Bus Company",
    "wof:placetype":"venue"
},
  "geometry": {"coordinates":[173.80603,-35.410667],"type":"Point"}
}