{
  "type": "Feature",
  "properties": {
    "iso:country":"NZ",
    "sg:address":"122 Seaview Rd Piha ",
    "sg:city":"Auckland",
    "sg:orig_category":"Shopping: Sports Retailers: Water Sports",
    "sg:phone":"+64 9-812 8723",
    "sg:province":"Auckland",
    "wof:name":"Piha Surf",
    "wof:placetype":"venue"
},
  "geometry": {"coordinates":[174.47820999999999,-36.957489],"type":"Point"}
}