{
  "type": "Feature",
  "properties": {
    "iso:country":"NZ",
    "sg:address":"Seymour Building cnr Wellington St & Fencible Dve, Howick ",
    "sg:city":"Auckland",
    "sg:classifiers":[
        {
            "category":"Education",
            "subcategory":"Special Training",
            "type":"Public Place"
        }
    ],
    "sg:phone":"+64 9-534 1619",
    "sg:province":"Auckland",
    "sg:tags":[
        "tutor",
        "coach",
        "teacher"
    ],
    "wof:name":"Kip McGrath Education Centres (NZ) Ltd",
    "wof:placetype":"venue"
},
  "geometry": {"coordinates":[174.928055,-36.89695],"type":"Point"}
}