{
  "type": "Feature",
  "properties": {
    "addr:full":"71 Duke St  Cambridge Waikato",
    "addr:housenumber":"71",
    "addr:street":"Duke St",
    "iso:country":"NZ",
    "sg:address":"71 Duke St ",
    "sg:city":"Cambridge",
    "sg:orig_category":"Health And Beauty: Specialists: Podiatrists",
    "sg:phone":"+64 7-823 4042",
    "sg:province":"Waikato",
    "wof:name":"Cambridge Foot Clinic",
    "wof:placetype":"venue"
},
  "geometry": {"coordinates":[175.47122200000001,-37.89497],"type":"Point"}
}