{
  "type": "Feature",
  "properties": {
    "addr:full":"35 Hampshire St Aranui  Christchurch Auckland",
    "addr:housenumber":"35",
    "addr:street":"Hampshire St",
    "iso:country":"NZ",
    "sg:address":"35 Hampshire St Aranui ",
    "sg:city":"Christchurch",
    "sg:classifiers":[
        {
            "category":"Bars & Pubs",
            "subcategory":"Wine Bar",
            "type":"Food & Drink"
        }
    ],
    "sg:phone":"+64 3-382 2951",
    "sg:province":"Auckland",
    "sg:tags":[
        "wining",
        "dining"
    ],
    "wof:name":"Aranui Cafe & Bar",
    "wof:placetype":"venue"
},
  "geometry": {"coordinates":[172.70088200000001,-43.511543],"type":"Point"}
}