{
  "type": "Feature",
  "properties": {
    "addr:full":"35 Edith St  Masterton Wellington",
    "addr:housenumber":"35",
    "addr:street":"Edith St",
    "iso:country":"NZ",
    "sg:address":"35 Edith St ",
    "sg:city":"Masterton",
    "sg:classifiers":[
        {
            "category":"Social Services",
            "subcategory":"Retirement Home",
            "type":"Services"
        }
    ],
    "sg:phone":"+64 6-378 7391",
    "sg:province":"Wellington",
    "sg:tags":[
        "care",
        "garden",
        "elderly",
        "village"
    ],
    "wof:name":"Masonic Village-Wairarapa",
    "wof:placetype":"venue"
},
  "geometry": {"coordinates":[175.63504,-40.942017],"type":"Point"}
}