{
  "type": "Feature",
  "properties": {
    "addr:full":"85 Innes St West  Gisborne Gisborne",
    "addr:housenumber":"85",
    "addr:street":"Innes St",
    "iso:country":"NZ",
    "sg:address":"85 Innes St West ",
    "sg:city":"Gisborne",
    "sg:orig_category":"Automotive: Parts And Supplies: Automotive Dismantlers",
    "sg:phone":"+64 6-867 6329",
    "sg:province":"Gisborne",
    "wof:name":"Gisborne PartsWorld",
    "wof:placetype":"venue"
},
  "geometry": {"coordinates":[177.995071,-38.664089],"type":"Point"}
}