{
  "type": "Feature",
  "properties": {
    "iso:country":"NZ",
    "sg:address":"Randwick Rd Moera Lower Hutt ",
    "sg:city":"Wellington",
    "sg:classifiers":[
        {
            "category":"Sports & Exercise",
            "subcategory":"Golf",
            "type":"Entertainment"
        }
    ],
    "sg:phone":"+64 4-939 8000",
    "sg:province":"Wellington",
    "sg:tags":[
        "club",
        "equipment",
        "leisure",
        "sports"
    ],
    "wof:name":"Hutt Park Golf Centre",
    "wof:placetype":"venue"
},
  "geometry": {"coordinates":[174.904694,-41.230545],"type":"Point"}
}