{
  "type": "Feature",
  "properties": {
    "iso:country":"NZ",
    "sg:address":"Midgley Rd ",
    "sg:city":"Mangonui",
    "sg:classifiers":[
        {
            "category":"Wholesale",
            "subcategory":"Auto Parts",
            "type":"Manufacturing & Wholesale Goods"
        }
    ],
    "sg:phone":"+64 9-406 0770",
    "sg:tags":[
        "automotive",
        "supplies"
    ],
    "wof:name":"Machine-Tech Mangonui",
    "wof:placetype":"venue"
},
  "geometry": {"coordinates":[173.568451,-35.024765],"type":"Point"}
}