{
  "type": "Feature",
  "properties": {
    "iso:country":"NZ",
    "sg:address":"229 Lower Port Rd ",
    "sg:city":"Whangarei",
    "sg:classifiers":[
        {
            "category":"Retail",
            "subcategory":"Auto Repair",
            "type":"Services"
        }
    ],
    "sg:phone":"+64 9-438 2814",
    "sg:province":"Northland",
    "sg:tags":[
        "engine",
        "automotive",
        "servicing"
    ],
    "wof:name":"Neil Shaw Automotive Ltd",
    "wof:placetype":"venue"
},
  "geometry": {"coordinates":[174.320526,-35.725399],"type":"Point"}
}