{
  "type": "Feature",
  "properties": {
    "addr:full":"27 Queen St Upper  Hutt Wellington",
    "addr:housenumber":"27",
    "addr:street":"Queen St",
    "iso:country":"NZ",
    "sg:address":"27 Queen St Upper ",
    "sg:city":"Hutt",
    "sg:orig_category":"Automotive: Parts And Supplies: Tyres",
    "sg:phone":"+64 4-528 5685",
    "sg:province":"Wellington",
    "wof:name":"Firestone Direct",
    "wof:placetype":"venue"
},
  "geometry": {"coordinates":[175.072968,-41.122807],"type":"Point"}
}