{
  "type": "Feature",
  "properties": {
    "addr:full":"Unit 8 29 Parkers Rd Tahunanui  Nelson Nelson",
    "addr:housenumber":"unit;29",
    "addr:street":"Parkers Rd",
    "iso:country":"NZ",
    "sg:address":"Unit 8 29 Parkers Rd Tahunanui ",
    "sg:city":"Nelson",
    "sg:orig_category":"Industrial: Instruments: Scales/Weighing Machines",
    "sg:phone":"+64 3-546 4525",
    "sg:province":"Nelson",
    "wof:name":"Wedderburn Scales",
    "wof:placetype":"venue"
},
  "geometry": {"coordinates":[173.245575,-41.29211],"type":"Point"}
}