{
  "type": "Feature",
  "properties": {
    "iso:country":"NZ",
    "sg:address":"49 Tallyho St ",
    "sg:city":"Rotorua",
    "sg:classifiers":[
        {
            "category":"Home & Garden",
            "subcategory":"Building Materials",
            "type":"Retail Goods"
        }
    ],
    "sg:phone":"+64 7-346 0717",
    "sg:province":"Bay of Plenty",
    "sg:tags":[
        "design",
        "fitting",
        "fittings",
        "kitchen"
    ],
    "wof:name":"Paul Sparke Cabinetmakers",
    "wof:placetype":"venue"
},
  "geometry": {"coordinates":[176.230469,-38.130619],"type":"Point"}
}