{
  "type": "Feature",
  "properties": {
    "addr:full":"48 Wordsworth St Sydenham  Christchurch Canterbury",
    "addr:housenumber":"48",
    "addr:street":"Wordsworth St",
    "iso:country":"NZ",
    "sg:address":"48 Wordsworth St Sydenham ",
    "sg:city":"Christchurch",
    "sg:classifiers":[
        {
            "category":"Shopping",
            "subcategory":"Gifts & Souvenirs",
            "type":"Retail Goods"
        }
    ],
    "sg:phone":"+64 3-372 9372",
    "sg:province":"Canterbury",
    "sg:tags":[
        "travel",
        "tourism"
    ],
    "wof:name":"Rata Leathercrafts Ltd",
    "wof:placetype":"venue"
},
  "geometry": {"coordinates":[172.63563500000001,-43.544926],"type":"Point"}
}