{
  "type": "Feature",
  "properties": {
    "iso:country":"NZ",
    "sg:address":"33 Vaughan Rd ",
    "sg:city":"Rotorua",
    "sg:classifiers":[
        {
            "category":"Retail",
            "subcategory":"Auto Repair",
            "type":"Services"
        }
    ],
    "sg:phone":"+64 7-345 6913",
    "sg:province":"Bay of Plenty",
    "sg:tags":[
        "automotive",
        "electric",
        "servicing"
    ],
    "wof:name":"Buckton Bob Auto Electrical",
    "wof:placetype":"venue"
},
  "geometry": {"coordinates":[176.275848,-38.145737],"type":"Point"}
}