{
  "type": "Feature",
  "properties": {
    "iso:country":"NZ",
    "sg:address":"230 St Asaph St ",
    "sg:city":"Christchurch",
    "sg:classifiers":[
        {
            "category":"Professional",
            "subcategory":"Art Services",
            "type":"Services"
        }
    ],
    "sg:phone":"+64 3-366 0330",
    "sg:province":"Canterbury",
    "sg:tags":[
        "fashion",
        "clothing",
        "fabric",
        "designer"
    ],
    "wof:name":"Alaska Design",
    "wof:placetype":"venue"
},
  "geometry": {"coordinates":[-76.537834,37.605659],"type":"Point"}
}