{
  "type": "Feature",
  "properties": {
    "addr:full":"Hazelburn R D 12 Pleasant Point  Timaru Canterbury",
    "addr:housenumber":"12",
    "addr:street":"R D",
    "iso:country":"NZ",
    "sg:address":"Hazelburn R D 12 Pleasant Point ",
    "sg:city":"Timaru",
    "sg:orig_category":"Home And Garden: Gardening: Products: Fertilisers",
    "sg:phone":"+64 3-614 7144",
    "sg:province":"Canterbury",
    "wof:name":"McHaffie W G",
    "wof:placetype":"venue"
},
  "geometry": {"coordinates":[171.23741100000001,-44.395428],"type":"Point"}
}