{
  "type": "Feature",
  "properties": {
    "iso:country":"NZ",
    "sg:address":"45 - 47 Ngongotaha Rd Ngongotaha ",
    "sg:city":"Rotorua",
    "sg:orig_category":"Home And Garden: Gardening: Products: Garden Supplies",
    "sg:phone":"+64 7-357 5690",
    "sg:province":"Bay of Plenty",
    "wof:name":"Ngongotaha Landscape Supplies Limited",
    "wof:placetype":"venue"
},
  "geometry": {"coordinates":[176.209305,-38.075066],"type":"Point"}
}