{
  "type": "Feature",
  "properties": {
    "iso:country":"NZ",
    "sg:address":"123 Edgewater Dve Pakuranga ",
    "sg:city":"Auckland",
    "sg:orig_category":"Health And Beauty: Beauty: Manicurists",
    "sg:phone":"+64 21 462 457",
    "sg:province":"Auckland",
    "wof:name":"Liz Dove Nails",
    "wof:placetype":"venue"
},
  "geometry": {"coordinates":[174.892807,-36.901218],"type":"Point"}
}