{
  "type": "Feature",
  "properties": {
    "iso:country":"NZ",
    "sg:address":"Wawa Rd Kinleith ",
    "sg:city":"Tokoroa",
    "sg:orig_category":"Transport: Transportation: Heavy Haulage",
    "sg:phone":"+64 7-886 4589",
    "wof:name":"Richards Heavy Haulage Tokoroa Ltd",
    "wof:placetype":"venue"
},
  "geometry": {"coordinates":[175.887634,-38.30822],"type":"Point"}
}