{
  "type": "Feature",
  "properties": {
    "iso:country":"NZ",
    "sg:address":"231 Dee St ",
    "sg:city":"Invercargill",
    "sg:classifiers":[
        {
            "category":"Banks & Credit Unions",
            "subcategory":"Investment Brokerage",
            "type":"Services"
        }
    ],
    "sg:phone":"+64 3-214 5588",
    "sg:province":"Southland",
    "sg:tags":[
        "personal",
        "-",
        "finance"
    ],
    "wof:name":"Money Managers",
    "wof:placetype":"venue"
},
  "geometry": {"coordinates":[168.347534,-46.403831],"type":"Point"}
}