{
  "type": "Feature",
  "properties": {
    "iso:country":"NZ",
    "sg:address":"PO Box 37078 ",
    "sg:city":"Christchurch",
    "sg:classifiers":[
        {
            "category":"Retail",
            "subcategory":"Funeral Services",
            "type":"Services"
        }
    ],
    "sg:phone":"+64 3-322 5226",
    "sg:province":"Canterbury",
    "sg:tags":[
        "arrangements",
        "arrangement"
    ],
    "wof:name":"Gordon Kelly & Associates Funeral Services",
    "wof:placetype":"venue"
},
  "geometry": {"coordinates":[-76.537834,37.605659],"type":"Point"}
}