{
  "type": "Feature",
  "properties": {
    "iso:country":"NZ",
    "sg:address":"23 - 27 Ellis St ",
    "sg:city":"Hamilton",
    "sg:orig_category":"Industrial: Services: Lubrication Services",
    "sg:phone":"+64 7-846 0745",
    "sg:province":"Waikato",
    "wof:name":"Oilshop -",
    "wof:placetype":"venue"
},
  "geometry": {"coordinates":[-88.441643,43.755672],"type":"Point"}
}