{
  "type": "Feature",
  "properties": {
    "iso:country":"NZ",
    "sg:address":"PO Box 12555 Penrose ",
    "sg:city":"Auckland",
    "sg:classifiers":[
        {
            "category":"Shopping",
            "subcategory":"Beauty & Cosmetics",
            "type":"Retail Goods"
        }
    ],
    "sg:phone":"+64 9-526 5318",
    "sg:province":"Auckland",
    "sg:tags":[
        "health",
        "perfumery"
    ],
    "wof:name":"Grace Cosmetics",
    "wof:placetype":"venue"
},
  "geometry": {"coordinates":[174.81016500000001,-36.911617],"type":"Point"}
}