{
  "type": "Feature",
  "properties": {
    "iso:country":"NZ",
    "sg:address":"94 Church St ",
    "sg:city":"Opotiki",
    "sg:classifiers":[
        {
            "category":"Health Services",
            "subcategory":"Health Practitioner",
            "type":"Services"
        }
    ],
    "sg:phone":"+64 7-315 6307",
    "sg:tags":[
        "specialist",
        "medical",
        "beauty",
        "specialists"
    ],
    "wof:name":"Church Street Surgery",
    "wof:placetype":"venue"
},
  "geometry": {"coordinates":[177.284546,-38.003643],"type":"Point"}
}