{
  "type": "Feature",
  "properties": {
    "iso:country":"NZ",
    "sg:address":"Kairangi Rd ",
    "sg:city":"Cambridge",
    "sg:orig_category":"Home And Garden: Gardening: Services: Landscaping",
    "sg:phone":"+64 21 505 117",
    "sg:province":"Waikato",
    "wof:name":"Kairangi Landscapes",
    "wof:placetype":"venue"
},
  "geometry": {"coordinates":[-116.67604799999999,44.572186],"type":"Point"}
}