{
  "type": "Feature",
  "properties": {
    "iso:country":"NZ",
    "sg:address":"17 Stokes Rd Mt Eden ",
    "sg:city":"Auckland",
    "sg:classifiers":[
        {
            "category":"Arena",
            "subcategory":"Sports Club",
            "type":"Entertainment"
        }
    ],
    "sg:phone":"+64 9-630 0427",
    "sg:province":"Nelson",
    "sg:tags":[
        "-",
        "leisure",
        "sports"
    ],
    "wof:name":"Mt Eden Bowls Incorporated",
    "wof:placetype":"venue"
},
  "geometry": {"coordinates":[174.764374,-36.881493],"type":"Point"}
}