{
  "type": "Feature",
  "properties": {
    "addr:full":"313 Rangitikei St PO Box 4148 Palmerston  Palmerston North Manawatu-Wanganui",
    "addr:housenumber":"313",
    "addr:postcode":"box",
    "addr:street":"Rangitikei St Po;4148 Palmerston",
    "iso:country":"NZ",
    "sg:address":"313 Rangitikei St PO Box 4148 Palmerston ",
    "sg:city":"Palmerston North",
    "sg:classifiers":[
        {
            "category":"Retail",
            "subcategory":"Auto Repair",
            "type":"Services"
        }
    ],
    "sg:phone":"+64 6-356 1814",
    "sg:province":"Manawatu-Wanganui",
    "sg:tags":[
        "automotive",
        "servicing"
    ],
    "sg:website":"http://www.manawatunissan.co.nz",
    "wof:name":"Manawatu Nissan LMVD",
    "wof:placetype":"venue"
},
  "geometry": {"coordinates":[175.611481,-40.357418],"type":"Point"}
}