{
  "type": "Feature",
  "properties": {
    "iso:country":"NZ",
    "sg:address":"Taieri Cre Lower ",
    "sg:city":"Hutt",
    "sg:classifiers":[
        {
            "category":"Health Services",
            "subcategory":"Dentist",
            "type":"Services"
        }
    ],
    "sg:phone":"+64 4-565 0803",
    "sg:province":"Wellington",
    "sg:tags":[
        "dental",
        "clinic",
        "beauty"
    ],
    "wof:name":"Kelson Primary School Dental Clinic",
    "wof:placetype":"venue"
},
  "geometry": {"coordinates":[170.503845,-45.8745],"type":"Point"}
}