{
  "type": "Feature",
  "properties": {
    "iso:country":"NZ",
    "sg:address":"93 Thames St ",
    "sg:city":"Oamaru",
    "sg:classifiers":[
        {
            "category":"Shopping",
            "subcategory":"Musical Instruments",
            "type":"Retail Goods"
        }
    ],
    "sg:phone":"+64 3-434 8839",
    "sg:province":"Otago",
    "sg:tags":[
        "sport",
        "music",
        "leisure"
    ],
    "wof:name":"Begg's Musical Centre (OU) Ltd",
    "wof:placetype":"venue"
},
  "geometry": {"coordinates":[170.97039799999999,-45.099319],"type":"Point"}
}