{
  "type": "Feature",
  "properties": {
    "iso:country":"NZ",
    "sg:address":"41 King St ",
    "sg:city":"Pukekohe",
    "sg:orig_category":"Clothing And Fabric: Clothing: Menswear",
    "sg:phone":"+64 9-238 7885",
    "sg:province":"Auckland",
    "wof:name":"Lewis' Fashion For Men",
    "wof:placetype":"venue"
},
  "geometry": {"coordinates":[174.930252,-37.195728],"type":"Point"}
}