{
  "type": "Feature",
  "properties": {
    "iso:country":"NZ",
    "sg:address":"550 State Highway 16 Kumeu ",
    "sg:city":"Auckland",
    "sg:classifiers":[
        {
            "category":"Food & Beverages",
            "subcategory":"Liquor & Beverages",
            "type":"Retail Goods"
        }
    ],
    "sg:phone":"+64 9-412 8415",
    "sg:province":"Auckland",
    "sg:tags":[
        "drink",
        "maker",
        "wine"
    ],
    "wof:name":"Kumeu River Wines Ltd",
    "wof:placetype":"venue"
},
  "geometry": {"coordinates":[174.56019599999999,-36.777271],"type":"Point"}
}