{
  "type": "Feature",
  "properties": {
    "addr:full":"24 Edinburgh St Spreydon  Christchurch Canterbury",
    "addr:housenumber":"24",
    "addr:street":"Edinburgh St",
    "iso:country":"NZ",
    "sg:address":"24 Edinburgh St Spreydon ",
    "sg:city":"Christchurch",
    "sg:orig_category":"Home And Garden: Children: Child Related: Children'S Entertainment",
    "sg:phone":"+64 3-942 3445",
    "sg:province":"Canterbury",
    "wof:name":"Adam Allsorts",
    "wof:placetype":"venue"
},
  "geometry": {"coordinates":[172.61621099999999,-43.553249],"type":"Point"}
}