{
  "type": "Feature",
  "properties": {
    "addr:full":"Lake Taupo Pier  Taupo Waikato",
    "iso:country":"NZ",
    "sg:address":"Lake Taupo Pier ",
    "sg:city":"Taupo",
    "sg:classifiers":[
        {
            "category":"Shopping",
            "subcategory":"Bicycles & Sporting Goods",
            "type":"Retail Goods"
        }
    ],
    "sg:phone":"+64 274 717 650",
    "sg:province":"Waikato",
    "sg:tags":[
        "sport",
        "fishing",
        "hunting",
        "retailers"
    ],
    "wof:name":"Bravado III",
    "wof:placetype":"venue"
},
  "geometry": {"coordinates":[176.07725500000001,-38.684868],"type":"Point"}
}