{
  "type": "Feature",
  "properties": {
    "addr:full":"54 Shotover St  Queenstown Otago",
    "addr:housenumber":"54",
    "addr:street":"Shotover St",
    "iso:country":"NZ",
    "sg:address":"54 Shotover St ",
    "sg:city":"Queenstown",
    "sg:classifiers":[
        {
            "category":"Personal",
            "subcategory":"Tattoo Parlor",
            "type":"Services"
        }
    ],
    "sg:phone":"+64 274 442 887",
    "sg:province":"Otago",
    "sg:tags":[
        "services",
        "home",
        "tattooists",
        "garden"
    ],
    "wof:name":"Queenstown Tattoo & Piercing Studio",
    "wof:placetype":"venue"
},
  "geometry": {"coordinates":[168.65872200000001,-45.032154],"type":"Point"}
}