{
  "type": "Feature",
  "properties": {
    "iso:country":"NZ",
    "sg:address":"59 Tongariro St ",
    "sg:city":"Taupo",
    "sg:orig_category":"Clothing And Fabric: Clothing: Women'S Fashions",
    "sg:phone":"+64 7-377 6004",
    "sg:province":"Waikato",
    "wof:name":"Walkin In London",
    "wof:placetype":"venue"
},
  "geometry": {"coordinates":[176.069748,-38.68071],"type":"Point"}
}