{
  "type": "Feature",
  "properties": {
    "iso:country":"NZ",
    "sg:address":"Unit 13 5 Wakefield St Alicetown Lower ",
    "sg:city":"Hutt",
    "sg:orig_category":"Automotive: Parts And Supplies: Turbochargers",
    "sg:phone":"+64 4-939 0947",
    "sg:province":"Wellington",
    "wof:name":"Speedtech Motorsport Ltd",
    "wof:placetype":"venue"
},
  "geometry": {"coordinates":[174.883377,-41.217449],"type":"Point"}
}