{
  "type": "Feature",
  "properties": {
    "addr:full":"Memorial Square  Carterton Wellington",
    "addr:street":"Memorial Square",
    "iso:country":"NZ",
    "sg:address":"Memorial Square ",
    "sg:city":"Carterton",
    "sg:classifiers":[
        {
            "category":"Wholesale",
            "subcategory":"Auto Parts",
            "type":"Manufacturing & Wholesale Goods"
        }
    ],
    "sg:phone":"+64 6-379 7706",
    "sg:province":"Wellington",
    "sg:tags":[
        "automotive",
        "supplies"
    ],
    "wof:name":"Peter O'Leary Motors",
    "wof:placetype":"venue"
},
  "geometry": {"coordinates":[-82.190933,36.941956],"type":"Point"}
}