{
  "type": "Feature",
  "properties": {
    "addr:full":"3016 Gt North Rd New Lynn  Auckland Auckland",
    "addr:housenumber":"3016",
    "addr:street":"Gt North Rd",
    "iso:country":"NZ",
    "sg:address":"3016 Gt North Rd New Lynn ",
    "sg:city":"Auckland",
    "sg:orig_category":"Automotive: General Services: Rental Vehicles",
    "sg:phone":"+64 9-827 7620",
    "sg:province":"Auckland",
    "wof:name":"Auckland Vehicle Rentals Ltd",
    "wof:placetype":"venue"
},
  "geometry": {"coordinates":[174.68806499999999,-36.904243],"type":"Point"}
}