{
  "type": "Feature",
  "properties": {
    "iso:country":"NZ",
    "sg:address":"Horomatangi St ",
    "sg:city":"Taupo",
    "sg:orig_category":"Sports And Leisure: Arts: Theatres",
    "sg:phone":"+64 7-378 7515",
    "sg:province":"Waikato",
    "wof:name":"Starlight Cinema",
    "wof:placetype":"venue"
},
  "geometry": {"coordinates":[176.076141,-38.688004],"type":"Point"}
}