{
  "type": "Feature",
  "properties": {
    "iso:country":"NZ",
    "sg:address":"3 Monarch Ave Birkenhead ",
    "sg:city":"Auckland",
    "sg:classifiers":[
        {
            "category":"Home & Garden",
            "subcategory":"Kitchen Supply",
            "type":"Retail Goods"
        }
    ],
    "sg:phone":"+64 9-480 0557",
    "sg:province":"Auckland",
    "sg:tags":[
        "motel",
        "industrial",
        "products",
        "hotel"
    ],
    "sg:website":"http://www.yellowpages.co.nz/pages/202358521/dp50744.html",
    "wof:name":"Easelcraft",
    "wof:placetype":"venue"
},
  "geometry": {"coordinates":[174.734467,-36.818214],"type":"Point"}
}