{
  "type": "Feature",
  "properties": {
    "iso:country":"NZ",
    "sg:address":"15 Hardy St Waterloo Lower ",
    "sg:city":"Hutt",
    "sg:orig_category":"Food And Drink: Meats: Butchers",
    "sg:phone":"+64 4-566 7939",
    "sg:province":"Wellington",
    "wof:name":"Hardy Street Quality Meats 2000",
    "wof:placetype":"venue"
},
  "geometry": {"coordinates":[174.92295799999999,-41.214344],"type":"Point"}
}