{
  "type": "Feature",
  "properties": {
    "iso:country":"NZ",
    "sg:address":"Thames ",
    "sg:city":"Hamilton",
    "sg:classifiers":[
        {
            "category":"Wholesale",
            "subcategory":"Machinery & Supplies",
            "type":"Manufacturing & Wholesale Goods"
        }
    ],
    "sg:phone":"+64 800 616 188",
    "sg:province":"Waikato",
    "sg:tags":[
        "equipment",
        "industrial"
    ],
    "sg:website":"http://www.yellowpages.co.nz/for/readyhire/dp38646.html",
    "wof:name":"Ready Hire",
    "wof:placetype":"venue"
},
  "geometry": {"coordinates":[175.54679899999999,-37.13969],"type":"Point"}
}