{
  "type": "Feature",
  "properties": {
    "iso:country":"NZ",
    "sg:address":"11 Dalgety Dve Wiri ",
    "sg:city":"Auckland",
    "sg:orig_category":"Industrial: Parts: Gaskets",
    "sg:phone":"+64 9-268 3624",
    "sg:province":"Auckland",
    "wof:name":"Klinger Ltd",
    "wof:placetype":"venue"
},
  "geometry": {"coordinates":[174.87678500000001,-37.012486],"type":"Point"}
}