{
  "type": "Feature",
  "properties": {
    "iso:country":"NZ",
    "sg:address":"136-142 Fanshawe St Auckland Central ",
    "sg:city":"Auckland",
    "sg:classifiers":[
        {
            "category":"Ice Cream",
            "type":"Food & Drink"
        }
    ],
    "sg:phone":"+64 9-377 2473",
    "sg:province":"Auckland",
    "sg:tags":[
        "-"
    ],
    "wof:name":"Kapiti Cheeses Ltd",
    "wof:placetype":"venue"
},
  "geometry": {"coordinates":[174.75735499999999,-36.846306],"type":"Point"}
}