{
  "type": "Feature",
  "properties": {
    "iso:country":"NZ",
    "sg:address":"21 Frimley St Palmerston ",
    "sg:city":"Palmerston North",
    "sg:classifiers":[
        {
            "category":"Social Services",
            "subcategory":"Retirement Home",
            "type":"Services"
        }
    ],
    "sg:phone":"+64 6-354 0883",
    "sg:province":"Manawatu-Wanganui",
    "sg:tags":[
        "automotive"
    ],
    "sg:website":"http://www.yellowpages.co.nz/for/portofinorentals/dp22082.html",
    "wof:name":"Portofino Rentals",
    "wof:placetype":"venue"
},
  "geometry": {"coordinates":[175.589493,-40.378742],"type":"Point"}
}