{
  "type": "Feature",
  "properties": {
    "iso:country":"NZ",
    "sg:address":"52 A Victoria St ",
    "sg:city":"Kaponga",
    "sg:orig_category":"Industrial: Engineering: Engineers: Engineers - General",
    "sg:phone":"+64 6-764 6872",
    "wof:name":"Stevens J T",
    "wof:placetype":"venue"
},
  "geometry": {"coordinates":[174.15303,-39.428944],"type":"Point"}
}