{
  "type": "Feature",
  "properties": {
    "iso:country":"NZ",
    "sg:address":"35 Wallace St ",
    "sg:city":"Motueka",
    "sg:orig_category":"Farming: Services: Veterinarians",
    "sg:phone":"+64 3-528 8459",
    "sg:province":"Tasman",
    "wof:name":"Motueka Veterinary Services",
    "wof:placetype":"venue"
},
  "geometry": {"coordinates":[173.012756,-41.111904],"type":"Point"}
}