{
  "type": "Feature",
  "properties": {
    "iso:country":"NZ",
    "sg:address":"598 Main St Palmerston ",
    "sg:city":"Palmerston North",
    "sg:classifiers":[
        {
            "category":"Banks & Credit Unions",
            "subcategory":"Financial Services",
            "type":"Services"
        }
    ],
    "sg:phone":"+64 6-355 5495",
    "sg:province":"Manawatu-Wanganui",
    "sg:tags":[
        "personal",
        "loan",
        "-",
        "finance",
        "mortgage"
    ],
    "wof:name":"AMP Viking Financial Services",
    "wof:placetype":"venue"
},
  "geometry": {"coordinates":[175.615524,-40.354359],"type":"Point"}
}