{
  "type": "Feature",
  "properties": {
    "addr:full":"1 A Moran St Redwoodtown  Blenheim Marlborough",
    "addr:housenumber":"1 a",
    "addr:street":"St",
    "iso:country":"NZ",
    "sg:address":"1 A Moran St Redwoodtown ",
    "sg:city":"Blenheim",
    "sg:orig_category":"Transport: Boats And Marine: Boats: Boat Maintenance",
    "sg:phone":"+64 3-578 3863",
    "sg:province":"Marlborough",
    "wof:name":"Propeller Repairs",
    "wof:placetype":"venue"
},
  "geometry": {"coordinates":[173.961502,-41.532047],"type":"Point"}
}