{
  "type": "Feature",
  "properties": {
    "addr:full":"PO Box 58927  Greenmount Auckland",
    "addr:housenumber":"po box",
    "addr:postcode":"58927",
    "iso:country":"NZ",
    "sg:address":"PO Box 58927 ",
    "sg:city":"Greenmount",
    "sg:orig_category":"Home And Garden: Accessories: Glassware",
    "sg:phone":"+64 9-272 2693",
    "sg:province":"Auckland",
    "wof:name":"Cospak NZ Ltd",
    "wof:placetype":"venue"
},
  "geometry": {"coordinates":[174.90057400000001,-36.934368],"type":"Point"}
}