{
  "type": "Feature",
  "properties": {
    "iso:country":"NZ",
    "sg:address":"911 Karamu Rd North ",
    "sg:city":"Hastings",
    "sg:orig_category":"Automotive: Accessories: Car Care Products",
    "sg:phone":"+64 800 263 535",
    "sg:province":"Hawke's Bay",
    "wof:name":"Auto Shine Car Care Products Ltd",
    "wof:placetype":"venue"
},
  "geometry": {"coordinates":[176.854919,-39.637016],"type":"Point"}
}