{
  "type": "Feature",
  "properties": {
    "iso:country":"NZ",
    "sg:address":"5-7 McKillop St ",
    "sg:city":"Porirua",
    "sg:orig_category":"Sports And Leisure: General: Clubs",
    "sg:phone":"+64 4-237 7695",
    "sg:province":"Wellington",
    "wof:name":"Returned Services' Associations",
    "wof:placetype":"venue"
},
  "geometry": {"coordinates":[174.848907,-41.137875],"type":"Point"}
}