{
  "type": "Feature",
  "properties": {
    "addr:full":"66 Esk St  Invercargill Southland",
    "addr:housenumber":"66",
    "addr:street":"Esk St",
    "iso:country":"NZ",
    "sg:address":"66 Esk St ",
    "sg:city":"Invercargill",
    "sg:classifiers":[
        {
            "category":"Professional",
            "subcategory":"Art Services",
            "type":"Services"
        }
    ],
    "sg:phone":"+64 3-218 9922",
    "sg:province":"Southland",
    "sg:tags":[
        "picture",
        "arts",
        "sport",
        "framing",
        "leisure"
    ],
    "wof:name":"Jag Print & Frames",
    "wof:placetype":"venue"
},
  "geometry": {"coordinates":[168.34996000000001,-46.411663],"type":"Point"}
}