{
  "type": "Feature",
  "properties": {
    "addr:full":"23 England St Freemans Bay  Auckland Auckland",
    "addr:housenumber":"23",
    "addr:street":"England St",
    "iso:country":"NZ",
    "sg:address":"23 England St Freemans Bay ",
    "sg:city":"Auckland",
    "sg:orig_category":"Home And Garden: Children: Child Related",
    "sg:phone":"+64 9-378 1080",
    "sg:province":"Auckland",
    "wof:name":"Antique Doll Restorers",
    "wof:placetype":"venue"
},
  "geometry": {"coordinates":[174.74854999999999,-36.850227],"type":"Point"}
}