{
  "type": "Feature",
  "properties": {
    "iso:country":"NZ",
    "sg:address":"23 England St Freemans Bay ",
    "sg:city":"Auckland",
    "sg:orig_category":"Home And Garden: Children: Child Related",
    "sg:phone":"+64 9-378 1080",
    "sg:province":"Auckland",
    "wof:name":"Antique Doll Restorers",
    "wof:placetype":"venue"
},
  "geometry": {"coordinates":[174.74855,-36.850227],"type":"Point"}
}