{
  "type": "Feature",
  "properties": {
    "addr:full":"325 Queen St  Masterton Wellington",
    "addr:housenumber":"325",
    "addr:street":"Queen St",
    "iso:country":"NZ",
    "sg:address":"325 Queen St ",
    "sg:city":"Masterton",
    "sg:classifiers":[
        {
            "category":"Retail",
            "subcategory":"Auto Repair",
            "type":"Services"
        }
    ],
    "sg:phone":"+64 6-370 2905",
    "sg:province":"Wellington",
    "sg:tags":[
        "automotive",
        "servicing"
    ],
    "wof:name":"Krivan Autos",
    "wof:placetype":"venue"
},
  "geometry": {"coordinates":[175.65626499999999,-40.953388],"type":"Point"}
}