{
  "type": "Feature",
  "properties": {
    "iso:country":"NZ",
    "sg:address":"Wellington ",
    "sg:city":"Christchurch",
    "sg:classifiers":[
        {
            "category":"Shopping",
            "subcategory":"Crafts & Fabrics",
            "type":"Retail Goods"
        }
    ],
    "sg:phone":"+64 3-379 1868",
    "sg:province":"Canterbury",
    "sg:tags":[
        "clothing"
    ],
    "sg:website":"http://www.stitches.co.nz",
    "wof:name":"Stitches - Elna",
    "wof:placetype":"venue"
},
  "geometry": {"coordinates":[172.63729900000001,-43.531311],"type":"Point"}
}