{
  "type": "Feature",
  "properties": {
    "iso:country":"NZ",
    "sg:address":"Main North Road ",
    "sg:city":"Oamaru",
    "sg:classifiers":[
        {
            "category":"Home & Garden",
            "subcategory":"Garden Supply",
            "type":"Retail Goods"
        }
    ],
    "sg:phone":"+64 3-437 1005",
    "sg:province":"Northland",
    "sg:tags":[
        "products",
        "nursery",
        "gardening"
    ],
    "wof:name":"Boundary Creek Nurseries",
    "wof:placetype":"venue"
},
  "geometry": {"coordinates":[171.00344799999999,-45.057823],"type":"Point"}
}