{
  "type": "Feature",
  "properties": {
    "addr:full":"4 Broadway Papakura  Auckland Manawatu-Wanganui",
    "addr:housenumber":"4",
    "iso:country":"NZ",
    "sg:address":"4 Broadway Papakura ",
    "sg:city":"Auckland",
    "sg:classifiers":[
        {
            "category":"Shopping",
            "subcategory":"Clothing, Apparel, & Fashions",
            "type":"Retail Goods"
        }
    ],
    "sg:phone":"+64 9-296 6063",
    "sg:province":"Manawatu-Wanganui",
    "sg:tags":[
        "school",
        "clothing",
        "fabric",
        "uniform"
    ],
    "wof:name":"Underwood's The Uniform Shoppe",
    "wof:placetype":"venue"
},
  "geometry": {"coordinates":[174.942215,-37.062195],"type":"Point"}
}