{
  "type": "Feature",
  "properties": {
    "iso:country":"NZ",
    "sg:address":"Lynden Court Chartwell ",
    "sg:city":"Hamilton",
    "sg:orig_category":"Home And Garden: Accessories: Linen",
    "sg:phone":"+64 7-853 8127",
    "sg:province":"Waikato",
    "wof:name":"Arbuckles",
    "wof:placetype":"venue"
},
  "geometry": {"coordinates":[175.27124000000001,-37.763653],"type":"Point"}
}