{
  "type": "Feature",
  "properties": {
    "iso:country":"NZ",
    "sg:address":"Hewlett Packard House, 186-190 Willis St ",
    "sg:city":"Wellington",
    "sg:classifiers":[
        {
            "category":"Sports & Exercise",
            "subcategory":"Sports Center",
            "type":"Entertainment"
        }
    ],
    "sg:phone":"+64 4-384 6447",
    "sg:province":"Wellington",
    "sg:tags":[
        "art",
        "leisure"
    ],
    "sg:website":"http://www.write.co.nz",
    "wof:name":"Write Group Limited",
    "wof:placetype":"venue"
},
  "geometry": {"coordinates":[-82.337372,41.197285],"type":"Point"}
}