{
  "type": "Feature",
  "properties": {
    "iso:country":"NZ",
    "sg:address":"Awamoa Rd ",
    "sg:city":"Oamaru",
    "sg:orig_category":"Education And Training: General: Schools",
    "sg:phone":"+64 3-434 6215",
    "sg:province":"Otago",
    "wof:name":"Awamoa",
    "wof:placetype":"venue"
},
  "geometry": {"coordinates":[170.936722,-45.129288],"type":"Point"}
}