{
  "type": "Feature",
  "properties": {
    "addr:full":"150 Taradale Rd  Napier Hawke's Bay",
    "addr:housenumber":"150",
    "addr:street":"Taradale Rd",
    "iso:country":"NZ",
    "sg:address":"150 Taradale Rd ",
    "sg:city":"Napier",
    "sg:orig_category":"Home And Garden: Furniture/Furnishings: Blinds",
    "sg:phone":"+64 6-843 9123",
    "sg:province":"Hawke's Bay",
    "wof:name":"Weathermaster",
    "wof:placetype":"venue"
},
  "geometry": {"coordinates":[176.87605300000001,-39.511169],"type":"Point"}
}