{
  "type": "Feature",
  "properties": {
    "iso:country":"NZ",
    "sg:address":"17 Gillies St ",
    "sg:city":"Kawakawa",
    "sg:classifiers":[
        {
            "category":"Bars & Pubs",
            "subcategory":"Lounge",
            "type":"Food & Drink"
        }
    ],
    "sg:phone":"+64 9-404 0689",
    "sg:tags":[
        "baker",
        "-"
    ],
    "wof:name":"Bay Of Islands Bakeries Ltd",
    "wof:placetype":"venue"
},
  "geometry": {"coordinates":[174.068024,-35.3801],"type":"Point"}
}