{
  "type": "Feature",
  "properties": {
    "addr:full":"State Highway 1  Manakau Wellington",
    "addr:street":"State Highway 1 Manakau",
    "iso:country":"NZ",
    "sg:address":"State Highway 1 ",
    "sg:city":"Manakau",
    "sg:orig_category":"Farming: Services: Veterinarians",
    "sg:phone":"+64 6-362 6515",
    "sg:province":"Wellington",
    "wof:name":"Bassett D J BVSc",
    "wof:placetype":"venue"
},
  "geometry": {"coordinates":[175.203552,-40.730976],"type":"Point"}
}