{
  "type": "Feature",
  "properties": {
    "addr:full":"190 Gt South Rd Remuera  Auckland Auckland",
    "addr:housenumber":"190",
    "addr:street":"Gt South Rd",
    "iso:country":"NZ",
    "sg:address":"190 Gt South Rd Remuera ",
    "sg:city":"Auckland",
    "sg:classifiers":[
        {
            "category":"Travel",
            "subcategory":"Travel Agent",
            "type":"Entertainment"
        }
    ],
    "sg:phone":"+64 9-520 5418",
    "sg:province":"Auckland",
    "sg:tags":[
        "tourism",
        "-",
        "accommodation",
        "booking"
    ],
    "wof:name":"Best Western Administration & Reservations",
    "wof:placetype":"venue"
},
  "geometry": {"coordinates":[174.80886799999999,-36.869381],"type":"Point"}
}