{
  "type": "Feature",
  "properties": {
    "iso:country":"NZ",
    "sg:address":"Glenmore Dve ",
    "sg:city":"Warkworth",
    "sg:classifiers":[
        {
            "category":"Retail",
            "subcategory":"Auto Repair",
            "type":"Services"
        }
    ],
    "sg:phone":"+64 9-425 9315",
    "sg:province":"Auckland",
    "sg:tags":[
        "engine",
        "automotive",
        "servicing"
    ],
    "wof:name":"Autobore Engine Reconditioners",
    "wof:placetype":"venue"
},
  "geometry": {"coordinates":[174.66511499999999,-36.401459],"type":"Point"}
}