{
  "type": "Feature",
  "properties": {
    "iso:country":"NZ",
    "sg:address":"Johnsonville Shopping Centre Johnsonville ",
    "sg:city":"Wellington",
    "sg:classifiers":[
        {
            "category":"Arts & Performance",
            "subcategory":"Art Gallery",
            "type":"Entertainment"
        }
    ],
    "sg:phone":"+64 4-478 5070",
    "sg:province":"Wellington",
    "sg:tags":[
        "arts",
        "sport",
        "leisure"
    ],
    "wof:name":"Art for Arts Sake",
    "wof:placetype":"venue"
},
  "geometry": {"coordinates":[174.80178799999999,-41.222324],"type":"Point"}
}