{
  "type": "Feature",
  "properties": {
    "addr:full":"11 Ilford Pl Palmerston  Palmerston North Manawatu-Wanganui",
    "addr:housenumber":"11",
    "addr:street":"Ilford Pl",
    "iso:country":"NZ",
    "sg:address":"11 Ilford Pl Palmerston ",
    "sg:city":"Palmerston North",
    "sg:classifiers":[
        {
            "category":"Health Services",
            "subcategory":"Health Practitioner",
            "type":"Services"
        }
    ],
    "sg:phone":"+64 6-355 4207",
    "sg:province":"Manawatu-Wanganui",
    "sg:tags":[
        "consultant",
        "medical",
        "beauty"
    ],
    "wof:name":"Injury Compensation Services Ltd",
    "wof:placetype":"venue"
},
  "geometry": {"coordinates":[175.596115,-40.368664],"type":"Point"}
}