{
  "type": "Feature",
  "properties": {
    "addr:full":"19 Thames St  Morrinsville Waikato",
    "addr:housenumber":"19",
    "addr:street":"Thames St",
    "iso:country":"NZ",
    "sg:address":"19 Thames St ",
    "sg:city":"Morrinsville",
    "sg:classifiers":[
        {
            "category":"Marine",
            "type":"Transportation"
        }
    ],
    "sg:phone":"+64 7-889 7083",
    "sg:province":"Waikato",
    "sg:tags":[
        "boats",
        "builder",
        "yacht",
        "transport",
        "boat"
    ],
    "wof:name":"Marco Boats",
    "wof:placetype":"venue"
},
  "geometry": {"coordinates":[175.52577199999999,-37.658939],"type":"Point"}
}