{
  "type": "Feature",
  "properties": {
    "iso:country":"NZ",
    "sg:address":"Main Rd ",
    "sg:city":"Ruatoria",
    "sg:orig_category":"Shopping: Retail Stores: Supermarkets",
    "sg:phone":"+64 6-864 8450",
    "wof:name":"Hikurangi Foodmarket",
    "wof:placetype":"venue"
},
  "geometry": {"coordinates":[178.318069,-37.894249],"type":"Point"}
}