{
  "type": "Feature",
  "properties": {
    "addr:full":"Cnr Old Taupo & View Rd  Rotorua Bay of Plenty",
    "addr:street":"Cnr Old;View Rd",
    "iso:country":"NZ",
    "sg:address":"Cnr Old Taupo & View Rd ",
    "sg:city":"Rotorua",
    "sg:classifiers":[
        {
            "category":"Retail",
            "subcategory":"Auto Repair",
            "type":"Services"
        }
    ],
    "sg:phone":"+64 7-348 6408",
    "sg:province":"Bay of Plenty",
    "sg:tags":[
        "automotive",
        "absorber",
        "shock",
        "servicing"
    ],
    "wof:name":"Pit Stop",
    "wof:placetype":"venue"
},
  "geometry": {"coordinates":[176.24499499999999,-38.1418],"type":"Point"}
}