{
  "type": "Feature",
  "properties": {
    "addr:full":"6 a Koromiko Ave Stoke  Nelson Nelson",
    "addr:housenumber":"6",
    "addr:street":"A Koromiko Ave",
    "iso:country":"NZ",
    "sg:address":"6 a Koromiko Ave Stoke ",
    "sg:city":"Nelson",
    "sg:classifiers":[
        {
            "category":"Education",
            "subcategory":"Special Training",
            "type":"Public Place"
        }
    ],
    "sg:phone":"+64 3-547 4807",
    "sg:province":"Nelson",
    "sg:tags":[
        "charter",
        "shopping",
        "dive",
        "tuition",
        "water",
        "sports",
        "retailers",
        "sport"
    ],
    "wof:name":"Diving Nelson",
    "wof:placetype":"venue"
},
  "geometry": {"coordinates":[173.23419200000001,-41.312859],"type":"Point"}
}