{
  "type": "Feature",
  "properties": {
    "iso:country":"NZ",
    "sg:address":"142 Main St ",
    "sg:city":"Gore",
    "sg:orig_category":"Industrial: Parts: Bolts And Nuts",
    "sg:phone":"+64 3-208 4628",
    "sg:province":"Southland",
    "wof:name":"Kelvin House 1995 Ltd",
    "wof:placetype":"venue"
},
  "geometry": {"coordinates":[-95.117165,35.52951],"type":"Point"}
}