{
  "type": "Feature",
  "properties": {
    "addr:full":"cnr Main South & Halswell Junction Rds Hornby  Christchurch Canterbury",
    "addr:street":"Cnr Main South &",
    "iso:country":"NZ",
    "sg:address":"cnr Main South & Halswell Junction Rds Hornby ",
    "sg:city":"Christchurch",
    "sg:orig_category":"Industrial: Engineering: Engineers: Civil Engineering Contractors",
    "sg:phone":"+64 3-349 7039",
    "sg:province":"Canterbury",
    "sg:website":"http://www.fh.co.nz/",
    "wof:name":"Fulton Hogan Canterbury",
    "wof:placetype":"venue"
},
  "geometry": {"coordinates":[172.525665,-43.543461],"type":"Point"}
}