{
  "type": "Feature",
  "properties": {
    "iso:country":"NZ",
    "sg:address":"Anglesea Clinic Physiotherapy Cnr Anglesea & Thackeray, Sts ",
    "sg:city":"Hamilton",
    "sg:classifiers":[
        {
            "category":"Sports & Exercise",
            "subcategory":"Tennis Court",
            "type":"Entertainment"
        }
    ],
    "sg:phone":"+64 7-858 0788",
    "sg:province":"Waikato",
    "sg:tags":[
        "medicine",
        "specialists",
        "health",
        "beauty"
    ],
    "wof:name":"Shepherd Dennis J",
    "wof:placetype":"venue"
},
  "geometry": {"coordinates":[-87.988968,34.142426],"type":"Point"}
}