{
  "type": "Feature",
  "properties": {
    "iso:country":"NZ",
    "sg:address":"31 Totara St Mt ",
    "sg:city":"Maunganui",
    "sg:orig_category":"Transport: Transportation: Container Services",
    "sg:phone":"+64 7-575 4936",
    "sg:province":"Auckland",
    "wof:name":"Bay of Plenty Refrigerated Container Services Ltd",
    "wof:placetype":"venue"
},
  "geometry": {"coordinates":[176.186234,-37.644943],"type":"Point"}
}