{
  "type": "Feature",
  "properties": {
    "addr:full":"25 Albert St Palmerston  Palmerston North Manawatu-Wanganui",
    "addr:housenumber":"25",
    "addr:street":"Albert St Palmerston",
    "iso:country":"NZ",
    "sg:address":"25 Albert St Palmerston ",
    "sg:city":"Palmerston North",
    "sg:classifiers":[
        {
            "category":"Health Services",
            "subcategory":"Health Practitioner",
            "type":"Services"
        }
    ],
    "sg:phone":"+64 6-357 7348",
    "sg:province":"Manawatu-Wanganui",
    "sg:tags":[
        "services",
        "beauty",
        "acupuncturists"
    ],
    "wof:name":"Ling Shu Acupuncture Clinic",
    "wof:placetype":"venue"
},
  "geometry": {"coordinates":[175.62072800000001,-40.345371],"type":"Point"}
}