{
  "type": "Feature",
  "properties": {
    "iso:country":"NZ",
    "sg:address":"8/1 Portage Rd New Lynn ",
    "sg:city":"Auckland",
    "sg:orig_category":"Shopping: Gifts: Sheepskins",
    "sg:phone":"+64 9-827 5987",
    "sg:province":"Auckland",
    "wof:name":"Comfyfit Sheepskin Products",
    "wof:placetype":"venue"
},
  "geometry": {"coordinates":[174.689056,-36.904026],"type":"Point"}
}