{
  "type": "Feature",
  "properties": {
    "addr:full":"PO Box 10064  Rotorua Bay of Plenty",
    "addr:housenumber":"po box",
    "addr:postcode":"10064",
    "iso:country":"NZ",
    "sg:address":"PO Box 10064 ",
    "sg:city":"Rotorua",
    "sg:classifiers":[
        {
            "category":"Health Services",
            "subcategory":"Health Practitioner",
            "type":"Services"
        }
    ],
    "sg:phone":"+64 7-348 9992",
    "sg:province":"Bay of Plenty",
    "sg:tags":[
        "equipment",
        "beauty",
        "fitness"
    ],
    "wof:name":"Life Is 4 Living Limited",
    "wof:placetype":"venue"
},
  "geometry": {"coordinates":[176.24499499999999,-38.1418],"type":"Point"}
}