{
  "type": "Feature",
  "properties": {
    "addr:full":"46 Clyde Rd Browns Bay  Auckland Auckland",
    "addr:housenumber":"46",
    "addr:street":"Clyde Rd",
    "iso:country":"NZ",
    "sg:address":"46 Clyde Rd Browns Bay ",
    "sg:city":"Auckland",
    "sg:classifiers":[
        {
            "category":"Shopping",
            "subcategory":"Photographic Equipment",
            "type":"Retail Goods"
        }
    ],
    "sg:phone":"+64 9-479 7440",
    "sg:province":"Auckland",
    "sg:tags":[
        "sport",
        "leisure",
        "hobbies"
    ],
    "wof:name":"Camera & Camera",
    "wof:placetype":"venue"
},
  "geometry": {"coordinates":[174.74809300000001,-36.715137],"type":"Point"}
}