{
  "type": "Feature",
  "properties": {
    "addr:full":"6 Pope St Riccarton  Christchurch Canterbury",
    "addr:housenumber":"6",
    "addr:street":"Pope St;Christchurch",
    "iso:country":"NZ",
    "sg:address":"6 Pope St Riccarton ",
    "sg:city":"Christchurch",
    "sg:classifiers":[
        {
            "category":"Restaurant",
            "type":"Food & Drink"
        }
    ],
    "sg:phone":"+64 3-348 2191",
    "sg:province":"Canterbury",
    "sg:tags":[
        "merchant",
        "fish",
        "sea"
    ],
    "wof:name":"Akaroa Salmon (NZ) Ltd",
    "wof:placetype":"venue"
},
  "geometry": {"coordinates":[172.609283,-43.53677],"type":"Point"}
}