{
  "type": "Feature",
  "properties": {
    "iso:country":"NZ",
    "sg:address":"477 Kamo Rd Kamo ",
    "sg:city":"Whangarei",
    "sg:classifiers":[
        {
            "category":"Food & Beverages",
            "subcategory":"Liquor & Beverages",
            "type":"Retail Goods"
        }
    ],
    "sg:phone":"+64 9-435 1277",
    "sg:province":"Northland",
    "sg:tags":[
        "drink",
        "outlet"
    ],
    "wof:name":"Liquorland",
    "wof:placetype":"venue"
},
  "geometry": {"coordinates":[174.301575,-35.684841],"type":"Point"}
}