{
  "type": "Feature",
  "properties": {
    "addr:full":"33 North Rd North East Valley  Dunedin Otago",
    "addr:housenumber":"33",
    "addr:street":"North Rd",
    "iso:country":"NZ",
    "sg:address":"33 North Rd North East Valley ",
    "sg:city":"Dunedin",
    "sg:classifiers":[
        {
            "category":"Shopping",
            "subcategory":"Thrift Store",
            "type":"Retail Goods"
        }
    ],
    "sg:phone":"+64 3-473 9359",
    "sg:province":"Otago",
    "sg:tags":[
        "-",
        "clothing",
        "secondhand",
        "fabric"
    ],
    "wof:name":"Inside Out",
    "wof:placetype":"venue"
},
  "geometry": {"coordinates":[170.519913,-45.854317],"type":"Point"}
}