{
  "type": "Feature",
  "properties": {
    "addr:full":"2/9 Westward Ho Rd Kelston  Auckland Auckland",
    "addr:housenumber":"2 / 9",
    "addr:street":"Westward Ho Rd",
    "iso:country":"NZ",
    "sg:address":"2/9 Westward Ho Rd Kelston ",
    "sg:city":"Auckland",
    "sg:orig_category":"Industrial: Packaging: Bags",
    "sg:phone":"+64 9-818 0055",
    "sg:province":"Auckland",
    "wof:name":"Morley Adams & Co",
    "wof:placetype":"venue"
},
  "geometry": {"coordinates":[174.66717499999999,-36.899097],"type":"Point"}
}