{
  "type": "Feature",
  "properties": {
    "addr:full":"180 C Raumati Rd  Paraparaumu Wellington",
    "addr:housenumber":"180 c",
    "addr:street":"Raumati Rd",
    "iso:country":"NZ",
    "sg:address":"180 C Raumati Rd ",
    "sg:city":"Paraparaumu",
    "sg:classifiers":[
        {
            "category":"Shopping",
            "subcategory":"Stationery & Office Supplies",
            "type":"Retail Goods"
        }
    ],
    "sg:phone":"+64 4-902 6331",
    "sg:province":"Wellington",
    "sg:tags":[
        "supplies",
        "educational",
        "material",
        "education",
        "training"
    ],
    "wof:name":"Ryan Partnership",
    "wof:placetype":"venue"
},
  "geometry": {"coordinates":[175.00799599999999,-40.910465],"type":"Point"}
}