{
  "type": "Feature",
  "properties": {
    "addr:full":"208 Victoria St W Auckland Central  Auckland Auckland",
    "addr:housenumber":"208",
    "addr:street":"Victoria St W",
    "iso:country":"NZ",
    "sg:address":"208 Victoria St W Auckland Central ",
    "sg:city":"Auckland",
    "sg:orig_category":"Clothing And Fabric: Clothing: Clothing - Specialty",
    "sg:phone":"+64 9-373 2119",
    "sg:province":"Auckland",
    "wof:name":"Fern Tees",
    "wof:placetype":"venue"
},
  "geometry": {"coordinates":[174.75604200000001,-36.848221],"type":"Point"}
}