{
  "type": "Feature",
  "properties": {
    "iso:country":"NZ",
    "sg:address":"146-148 Princess St Palmerston ",
    "sg:city":"Palmerston North",
    "sg:orig_category":"Automotive: Parts And Supplies: Windscreens",
    "sg:phone":"+64 6-358 7095",
    "sg:province":"Manawatu-Wanganui",
    "wof:name":"Manawatu Auto Screens",
    "wof:placetype":"venue"
},
  "geometry": {"coordinates":[175.61741599999999,-40.357063],"type":"Point"}
}