{
  "type": "Feature",
  "properties": {
    "addr:full":"Bedford Rd Renwick  Blenheim Marlborough",
    "addr:street":"Bedford Rd",
    "iso:country":"NZ",
    "sg:address":"Bedford Rd Renwick ",
    "sg:city":"Blenheim",
    "sg:classifiers":[
        {
            "category":"Shopping",
            "subcategory":"Pets & Pet Supplies",
            "type":"Retail Goods"
        }
    ],
    "sg:phone":"+64 3-572 8982",
    "sg:province":"Marlborough",
    "sg:tags":[
        "boarding",
        "garden",
        "pets",
        "catteries",
        "home",
        "kennel"
    ],
    "wof:name":"Willoway-The Feline Retreat",
    "wof:placetype":"venue"
},
  "geometry": {"coordinates":[173.828461,-41.510769],"type":"Point"}
}