{
  "type": "Feature",
  "properties": {
    "iso:country":"NZ",
    "sg:address":"12 Richard St Titahi Bay ",
    "sg:city":"Porirua",
    "sg:classifiers":[
        {
            "category":"Banks & Credit Unions",
            "subcategory":"Investment Brokerage",
            "type":"Services"
        }
    ],
    "sg:phone":"+64 25493462",
    "sg:province":"Wellington",
    "sg:tags":[
        "services",
        "industrial",
        "refrigeration",
        "servicing"
    ],
    "wof:name":"J L W Engineering",
    "wof:placetype":"venue"
},
  "geometry": {"coordinates":[174.836838,-41.10154],"type":"Point"}
}