{
  "type": "Feature",
  "properties": {
    "iso:country":"NZ",
    "sg:address":"Manchester St Riverlands ",
    "sg:city":"Blenheim",
    "sg:classifiers":[
        {
            "category":"Retail",
            "subcategory":"Auto Repair",
            "type":"Services"
        }
    ],
    "sg:phone":"+64 3-577 5651",
    "sg:province":"Marlborough",
    "sg:tags":[
        "automotive",
        "servicing"
    ],
    "wof:name":"Riverlands Estate Motors",
    "wof:placetype":"venue"
},
  "geometry": {"coordinates":[174.01031499999999,-41.53009],"type":"Point"}
}