{
  "type": "Feature",
  "properties": {
    "addr:full":"104 Broadway  Kaikohe Manawatu-Wanganui",
    "addr:housenumber":"104",
    "addr:street":"Broadway",
    "iso:country":"NZ",
    "sg:address":"104 Broadway ",
    "sg:city":"Kaikohe",
    "sg:classifiers":[
        {
            "category":"Wholesale",
            "subcategory":"Auto Parts",
            "type":"Manufacturing & Wholesale Goods"
        }
    ],
    "sg:phone":"+64 9-401 0210",
    "sg:province":"Manawatu-Wanganui",
    "sg:tags":[
        "automotive",
        "supplies"
    ],
    "wof:name":"Northland Parts & Accessories Ltd",
    "wof:placetype":"venue"
},
  "geometry": {"coordinates":[173.80107100000001,-35.407009],"type":"Point"}
}