{
  "type": "Feature",
  "properties": {
    "iso:country":"NZ",
    "sg:address":"156 Bealey Avenue ",
    "sg:city":"Christchurch",
    "sg:classifiers":[
        {
            "category":"Personal",
            "type":"Services"
        }
    ],
    "sg:phone":"+64 3-366 0620",
    "sg:province":"Canterbury",
    "sg:tags":[
        "health",
        "beauty",
        "diet"
    ],
    "wof:name":"Jane Owers Dietitian and Sports Nutritionist",
    "wof:placetype":"venue"
},
  "geometry": {"coordinates":[172.63765,-43.521107],"type":"Point"}
}