{
  "type": "Feature",
  "properties": {
    "iso:country":"NZ",
    "sg:address":"1/429 Parnell Rd Parnell ",
    "sg:city":"Auckland",
    "sg:classifiers":[
        {
            "category":"Shopping",
            "subcategory":"Hobbies, Toys, & Games",
            "type":"Retail Goods"
        }
    ],
    "sg:phone":"+64 9-309 4995",
    "sg:province":"Auckland",
    "sg:tags":[
        "hobby"
    ],
    "wof:name":"Aromaworks Ltd",
    "wof:placetype":"venue"
},
  "geometry": {"coordinates":[174.782791,-36.859447],"type":"Point"}
}