{
  "type": "Feature",
  "properties": {
    "iso:country":"NZ",
    "sg:address":"71 Glenbrook-Waiuku Rd Waiuku ",
    "sg:city":"Auckland",
    "sg:classifiers":[
        {
            "category":"Restaurant",
            "type":"Food & Drink"
        }
    ],
    "sg:phone":"+64 9-235 5004",
    "sg:province":"Auckland",
    "sg:tags":[
        "fruit",
        "veges"
    ],
    "wof:name":"Tom Veges",
    "wof:placetype":"venue"
},
  "geometry": {"coordinates":[174.74968000000001,-37.23735],"type":"Point"}
}