{
  "type": "Feature",
  "properties": {
    "addr:full":"Two Mile R D 2  Hokitika West Coast",
    "addr:housenumber":"2",
    "addr:street":"Hokitika",
    "iso:country":"NZ",
    "sg:address":"Two Mile R D 2 ",
    "sg:city":"Hokitika",
    "sg:classifiers":[
        {
            "category":"Personal",
            "type":"Services"
        }
    ],
    "sg:phone":"+64 3-755 7510",
    "sg:province":"West Coast",
    "sg:tags":[
        "celebrant",
        "arrangements",
        "marriage",
        "wedding"
    ],
    "wof:name":"Wilson Megan",
    "wof:placetype":"venue"
},
  "geometry": {"coordinates":[170.97221400000001,-42.719032],"type":"Point"}
}