{
  "type": "Feature",
  "properties": {
    "iso:country":"NZ",
    "sg:address":"Broadway ",
    "sg:city":"Kaikohe",
    "sg:classifiers":[
        {
            "category":"Restaurant",
            "type":"Food & Drink"
        }
    ],
    "sg:phone":"+64 9-401 1244",
    "sg:province":"Manawatu-Wanganui",
    "sg:tags":[
        "greengrocer",
        "fruiterer",
        "fruit",
        "veges"
    ],
    "wof:name":"North Fresh Produce",
    "wof:placetype":"venue"
},
  "geometry": {"coordinates":[173.80107100000001,-35.407009],"type":"Point"}
}