{
  "type": "Feature",
  "properties": {
    "iso:country":"NZ",
    "sg:address":"88 a Riccarton Rd Riccarton ",
    "sg:city":"Christchurch",
    "sg:orig_category":"Shopping: Sports Retailers: Sports Goods: Dance Supplies",
    "sg:phone":"+64 3-348 7572",
    "sg:province":"Canterbury",
    "wof:name":"Dancing Queen/Enigma Bodywear",
    "wof:placetype":"venue"
},
  "geometry": {"coordinates":[172.59733600000001,-43.532139],"type":"Point"}
}