{
  "type": "Feature",
  "properties": {
    "addr:full":"17 A Pascal St Palmerston  Palmerston North Manawatu-Wanganui",
    "addr:housenumber":"17",
    "addr:street":"A Pascal St Palmerston",
    "iso:country":"NZ",
    "sg:address":"17 A Pascal St Palmerston ",
    "sg:city":"Palmerston North",
    "sg:classifiers":[
        {
            "category":"Sports & Exercise",
            "subcategory":"Sports Center",
            "type":"Entertainment"
        }
    ],
    "sg:phone":"+64 6-356 6322",
    "sg:province":"Manawatu-Wanganui",
    "sg:tags":[
        "sporting",
        "sports",
        "-",
        "leisure",
        "facility"
    ],
    "wof:name":"Marist Sports Club (PN) Inc",
    "wof:placetype":"venue"
},
  "geometry": {"coordinates":[175.59788499999999,-40.354946],"type":"Point"}
}