{
  "type": "Feature",
  "properties": {
    "addr:full":"17 March Pl  Belfast Canterbury",
    "addr:housenumber":"17",
    "addr:street":"March Pl",
    "iso:country":"NZ",
    "sg:address":"17 March Pl ",
    "sg:city":"Belfast",
    "sg:classifiers":[
        {
            "category":"Home & Garden",
            "subcategory":"Building Materials",
            "type":"Retail Goods"
        }
    ],
    "sg:phone":"+64 3-323 7304",
    "sg:province":"Canterbury",
    "sg:tags":[
        "fittings",
        "door",
        "garage"
    ],
    "wof:name":"Bowmans Garage Doors",
    "wof:placetype":"venue"
},
  "geometry": {"coordinates":[-69.00797300000001,44.425869],"type":"Point"}
}