{
  "type": "Feature",
  "properties": {
    "addr:full":"85 Aberfeldy Ave Highland Park  Auckland Auckland",
    "addr:housenumber":"85",
    "addr:street":"Aberfeldy Ave",
    "iso:country":"NZ",
    "sg:address":"85 Aberfeldy Ave Highland Park ",
    "sg:city":"Auckland",
    "sg:classifiers":[
        {
            "category":"Arts & Performance",
            "subcategory":"Art Gallery",
            "type":"Entertainment"
        }
    ],
    "sg:phone":"+64 9-537 2440",
    "sg:province":"Auckland",
    "sg:tags":[
        "arts",
        "sport",
        "leisure"
    ],
    "wof:name":"Giles Peterson Pacific Age Art",
    "wof:placetype":"venue"
},
  "geometry": {"coordinates":[174.90570099999999,-36.906765],"type":"Point"}
}