{
  "type": "Feature",
  "properties": {
    "addr:full":"Hastings, Havelock North, Dannevirke  Napier Hawke's Bay",
    "iso:country":"NZ",
    "sg:address":"Hastings, Havelock North, Dannevirke ",
    "sg:city":"Napier",
    "sg:classifiers":[
        {
            "category":"Banks & Credit Unions",
            "subcategory":"Financial Services",
            "type":"Services"
        }
    ],
    "sg:phone":"+64 800 639 8769",
    "sg:province":"Hawke's Bay",
    "sg:tags":[
        "personal",
        "loan",
        "-",
        "finance",
        "mortgage"
    ],
    "wof:name":"Nexus NZ Financial Services Ltd",
    "wof:placetype":"venue"
},
  "geometry": {"coordinates":[176.844818,-39.64167],"type":"Point"}
}