{
  "type": "Feature",
  "properties": {
    "addr:full":"454 Colombo St Sydenham  Christchurch Canterbury",
    "addr:housenumber":"454",
    "addr:street":"Colombo St",
    "iso:country":"NZ",
    "sg:address":"454 Colombo St Sydenham ",
    "sg:city":"Christchurch",
    "sg:classifiers":[
        {
            "category":"Shopping",
            "type":"Retail Goods"
        }
    ],
    "sg:phone":"+64 3-365 4684",
    "sg:province":"Canterbury",
    "sg:tags":[
        "store"
    ],
    "sg:website":"http://www.yellowpages.co.nz/pages/100735793/dp48443.html",
    "wof:name":"Old Syd'nham Town",
    "wof:placetype":"venue"
},
  "geometry": {"coordinates":[172.636841,-43.543003],"type":"Point"}
}