{
  "type": "Feature",
  "properties": {
    "addr:full":"610 Colombo St  Christchurch Canterbury",
    "addr:housenumber":"610",
    "addr:street":"Colombo St",
    "iso:country":"NZ",
    "sg:address":"610 Colombo St ",
    "sg:city":"Christchurch",
    "sg:classifiers":[
        {
            "category":"Shopping",
            "subcategory":"Clothing, Apparel, & Fashions",
            "type":"Retail Goods"
        }
    ],
    "sg:phone":"+64 3-379 7091",
    "sg:province":"Canterbury",
    "sg:tags":[
        "clothing",
        "fabric"
    ],
    "wof:name":"Deans Suit Hire",
    "wof:placetype":"venue"
},
  "geometry": {"coordinates":[172.63674900000001,-43.535954],"type":"Point"}
}