{
  "type": "Feature",
  "properties": {
    "iso:country":"NZ",
    "sg:address":"328 White Rd ",
    "sg:city":"Waipawa",
    "sg:orig_category":"Sports And Leisure: Sports: Equestrian: Riding Schools",
    "sg:phone":"+64 6-857 7068",
    "wof:name":"Taurimu Riding School",
    "wof:placetype":"venue"
},
  "geometry": {"coordinates":[-80.091103,36.195801],"type":"Point"}
}