{
  "type": "Feature",
  "properties": {
    "addr:full":"77 Powderham St New  Plymouth Taranaki",
    "addr:housenumber":"77",
    "addr:street":"Powderham St",
    "iso:country":"NZ",
    "sg:address":"77 Powderham St New ",
    "sg:city":"Plymouth",
    "sg:orig_category":"Shopping: Gifts: Gift Baskets",
    "sg:phone":"+64 6-758 3187",
    "sg:province":"Taranaki",
    "sg:website":"http://www.yellowpages.co.nz/for/briarrose/dp29004.html",
    "wof:name":"Briar Rose Florist",
    "wof:placetype":"venue"
},
  "geometry": {"coordinates":[-116.81972500000001,43.97221],"type":"Point"}
}