{
  "type": "Feature",
  "properties": {
    "iso:country":"NZ",
    "sg:address":"52 Cooper St ",
    "sg:city":"Karori",
    "sg:orig_category":"Home And Garden: Furniture/Furnishings: Cabinetmakers",
    "sg:phone":"+64 252488140",
    "sg:province":"Wellington",
    "wof:name":"Barker David",
    "wof:placetype":"venue"
},
  "geometry": {"coordinates":[174.744492,-41.287262],"type":"Point"}
}