{
  "type": "Feature",
  "properties": {
    "iso:country":"NZ",
    "sg:address":"319B Hibiscus Coast Highway Orewa ",
    "sg:city":"Auckland",
    "sg:orig_category":"Transport: Land: Shuttle Services",
    "sg:phone":"+64 9-426 1151",
    "sg:province":"Auckland",
    "wof:name":"Simply the Best Shuttles & Tours",
    "wof:placetype":"venue"
},
  "geometry": {"coordinates":[175.23999000000001,-36.958897],"type":"Point"}
}