{
  "type": "Feature",
  "properties": {
    "addr:full":"8 McIlroy Ave Hillsborough  Auckland Auckland",
    "addr:housenumber":"8",
    "addr:street":"Mcilroy Ave",
    "iso:country":"NZ",
    "sg:address":"8 McIlroy Ave Hillsborough ",
    "sg:city":"Auckland",
    "sg:orig_category":"Industrial: Parts: Pipes, Tubes And Cabling: Cables",
    "sg:phone":"+64 9-624 2000",
    "sg:province":"Auckland",
    "wof:name":"Electrocom Ltd",
    "wof:placetype":"venue"
},
  "geometry": {"coordinates":[174.762833,-36.92268],"type":"Point"}
}