{
  "type": "Feature",
  "properties": {
    "addr:full":"17 Lombard St Palmerston  Palmerston North Manawatu-Wanganui",
    "addr:housenumber":"17",
    "addr:street":"Lombard St Palmerston",
    "iso:country":"NZ",
    "sg:address":"17 Lombard St Palmerston ",
    "sg:city":"Palmerston North",
    "sg:classifiers":[
        {
            "category":"Sports & Exercise",
            "subcategory":"Sports Center",
            "type":"Entertainment"
        }
    ],
    "sg:phone":"+64 6-358 0747",
    "sg:province":"Manawatu-Wanganui",
    "sg:tags":[
        "machine",
        "amusement",
        "leisure"
    ],
    "wof:name":"Amusement Machine Supplies",
    "wof:placetype":"venue"
},
  "geometry": {"coordinates":[175.604523,-40.351971],"type":"Point"}
}