{
  "type": "Feature",
  "properties": {
    "iso:country":"NZ",
    "sg:address":"158 Bush Rd Albany ",
    "sg:city":"Auckland",
    "sg:orig_category":"Home And Garden: Accessories: Hardware",
    "sg:phone":"+64 9-415 2400",
    "sg:province":"Auckland",
    "wof:name":"ATC Tools NZ",
    "wof:placetype":"venue"
},
  "geometry": {"coordinates":[174.705139,-36.746384],"type":"Point"}
}