{
  "type": "Feature",
  "properties": {
    "addr:full":"PO Box 1192  Gisborne Gisborne",
    "addr:housenumber":"po;1192",
    "addr:street":"Box",
    "iso:country":"NZ",
    "sg:address":"PO Box 1192 ",
    "sg:city":"Gisborne",
    "sg:classifiers":[
        {
            "category":"Home & Garden",
            "subcategory":"Building Materials",
            "type":"Retail Goods"
        }
    ],
    "sg:phone":"+64 25527817",
    "sg:province":"Gisborne",
    "sg:tags":[
        "builder",
        "related"
    ],
    "wof:name":"Cameron Construction Ltd",
    "wof:placetype":"venue"
},
  "geometry": {"coordinates":[178.024475,-38.66597],"type":"Point"}
}