{
  "type": "Feature",
  "properties": {
    "addr:full":"368 Onions Rd R D 8  Hamilton Waikato",
    "addr:housenumber":"368;8",
    "addr:street":"Onions Rd R D",
    "iso:country":"NZ",
    "sg:address":"368 Onions Rd R D 8 ",
    "sg:city":"Hamilton",
    "sg:orig_category":"Farming: Farms - General: Poultry",
    "sg:phone":"+64 7-849 2462",
    "sg:province":"Waikato",
    "wof:name":"Farmyard Products Ltd",
    "wof:placetype":"venue"
},
  "geometry": {"coordinates":[-84.948166,41.500038],"type":"Point"}
}