{
  "type": "Feature",
  "properties": {
    "iso:country":"NZ",
    "sg:address":"4 Dalefield Dve Cashmere ",
    "sg:city":"Christchurch",
    "sg:orig_category":"Farming: Agriculture: Agricultural Consultants",
    "sg:phone":"+64 3-332 4945",
    "sg:province":"Canterbury",
    "wof:name":"NZ Horticultural Advisory Service Ltd",
    "wof:placetype":"venue"
},
  "geometry": {"coordinates":[172.645737,-43.577835],"type":"Point"}
}