{
  "type": "Feature",
  "properties": {
    "iso:country":"NZ",
    "sg:address":"10 a George ",
    "sg:city":"St",
    "sg:classifiers":[
        {
            "category":"Autos & Motor Vehicles",
            "subcategory":"Automobile Sales",
            "type":"Retail Goods"
        }
    ],
    "sg:phone":"+64 25401004",
    "sg:tags":[
        "automotive"
    ],
    "sg:website":"http://www.yellowpages.co.nz/pages/104068555/dp52463.html",
    "wof:name":"Petroleum Engineering Services Nelson Ltd",
    "wof:placetype":"venue"
},
  "geometry": {"coordinates":[170.366638,-43.587711],"type":"Point"}
}