{
  "type": "Feature",
  "properties": {
    "addr:full":"New Lynn LynnMall Shopping Centre New Lynn  Auckland Auckland",
    "iso:country":"NZ",
    "sg:address":"New Lynn LynnMall Shopping Centre New Lynn ",
    "sg:city":"Auckland",
    "sg:orig_category":"Clothing And Fabric: Clothing: Clothing - Specialty",
    "sg:phone":"+64 9-827 1637",
    "sg:province":"Auckland",
    "wof:name":"Arizona",
    "wof:placetype":"venue"
},
  "geometry": {"coordinates":[174.68308999999999,-36.920143],"type":"Point"}
}