{
  "type": "Feature",
  "properties": {
    "iso:country":"NZ",
    "sg:address":"14 Viaduct Harbour Ave Auckland Central ",
    "sg:city":"Auckland",
    "sg:classifiers":[
        {
            "category":"Travel",
            "subcategory":"Travel Agent",
            "type":"Entertainment"
        }
    ],
    "sg:phone":"+64 9-358 9189",
    "sg:province":"Auckland",
    "sg:tags":[
        "tourism",
        "broker"
    ],
    "wof:name":"Art of Travel Ltd",
    "wof:placetype":"venue"
},
  "geometry": {"coordinates":[174.758499,-36.845257],"type":"Point"}
}