{
  "type": "Feature",
  "properties": {
    "iso:country":"NZ",
    "sg:address":"447 Maunganui Rd Mt ",
    "sg:city":"Maunganui",
    "sg:classifiers":[
        {
            "category":"Travel",
            "subcategory":"Hotels & Motels",
            "type":"Entertainment"
        }
    ],
    "sg:phone":"+64 7-572 3120",
    "sg:province":"Bay of Plenty",
    "sg:tags":[
        "holiday",
        "tourism",
        "accommodation"
    ],
    "sg:website":"http://www.yellowpages.co.nz/for/aquarius/dp12320.html",
    "wof:name":"Aquarius Motor Inn",
    "wof:placetype":"venue"
},
  "geometry": {"coordinates":[176.19245900000001,-37.649456],"type":"Point"}
}