{
  "type": "Feature",
  "properties": {
    "addr:full":"98 Amohia St  Paraparaumu Wellington",
    "addr:housenumber":"98",
    "addr:street":"Amohia St",
    "iso:country":"NZ",
    "sg:address":"98 Amohia St ",
    "sg:city":"Paraparaumu",
    "sg:classifiers":[
        {
            "category":"Utilities",
            "subcategory":"Refuse",
            "type":"Services"
        }
    ],
    "sg:phone":"+64 4-298 4006",
    "sg:province":"Wellington",
    "sg:tags":[
        "bin",
        "hire",
        "garden",
        "cleaning",
        "rubbish",
        "home"
    ],
    "wof:name":"Coastal Bin Hire",
    "wof:placetype":"venue"
},
  "geometry": {"coordinates":[175.00799599999999,-40.910465],"type":"Point"}
}