{
  "type": "Feature",
  "properties": {
    "iso:country":"NZ",
    "sg:address":"Main Rd Pleasant ",
    "sg:city":"Point",
    "sg:classifiers":[
        {
            "category":"Food & Beverages",
            "subcategory":"Meat & Fish",
            "type":"Retail Goods"
        }
    ],
    "sg:phone":"+64 800 757 288",
    "sg:tags":[
        "drink"
    ],
    "sg:website":"http://www.yellowpages.co.nz/for/exportmeat/dp24570.html",
    "wof:name":"Export Meat Warehouse (Pleasant Point Butchery)",
    "wof:placetype":"venue"
},
  "geometry": {"coordinates":[171.12676999999999,-44.260223],"type":"Point"}
}