{
  "type": "Feature",
  "properties": {
    "addr:full":"Old Taupo Rd  Tokoroa",
    "addr:street":"Old Taupo Rd",
    "iso:country":"NZ",
    "sg:address":"Old Taupo Rd ",
    "sg:city":"Tokoroa",
    "sg:orig_category":"Non-Classified Establishments",
    "sg:phone":"+64 7-886 8682",
    "wof:name":"Les O'Leary Ltd",
    "wof:placetype":"venue"
},
  "geometry": {"coordinates":[175.866333,-38.226044],"type":"Point"}
}