{
  "type": "Feature",
  "properties": {
    "iso:country":"NZ",
    "sg:address":"220 Cumnor Tce Woolston ",
    "sg:city":"Christchurch",
    "sg:classifiers":[
        {
            "category":"Transit Center",
            "subcategory":"Freight",
            "type":"Transportation"
        }
    ],
    "sg:phone":"+64 3-389 6367",
    "sg:province":"Canterbury",
    "sg:tags":[
        "distribution",
        "-",
        "transport"
    ],
    "wof:name":"Options",
    "wof:placetype":"venue"
},
  "geometry": {"coordinates":[172.685989,-43.560574],"type":"Point"}
}