{
  "type": "Feature",
  "properties": {
    "iso:country":"NZ",
    "sg:address":"43 B Kilmarnock St Riccarton ",
    "sg:city":"Christchurch",
    "sg:classifiers":[
        {
            "category":"Travel",
            "subcategory":"Bed & Breakfast",
            "type":"Entertainment"
        }
    ],
    "sg:phone":"+64 3-343 1377",
    "sg:province":"Canterbury",
    "sg:tags":[
        "tourism",
        "accommodation"
    ],
    "sg:website":"http://www.greatstay.co.nz",
    "wof:name":"Greatstay Bed & Breakfast",
    "wof:placetype":"venue"
},
  "geometry": {"coordinates":[172.60583500000001,-43.527111],"type":"Point"}
}