{
  "type": "Feature",
  "properties": {
    "iso:country":"NZ",
    "sg:address":"Huapai ",
    "sg:city":"Auckland",
    "sg:classifiers":[
        {
            "category":"Home & Garden",
            "subcategory":"Garden Supply",
            "type":"Retail Goods"
        }
    ],
    "sg:phone":"+64 9-412 8693",
    "sg:province":"Auckland",
    "sg:tags":[
        "gardening"
    ],
    "sg:website":"http://www.gardenmaintenance.co.nz",
    "wof:name":"Garden Maintenance Professional Services",
    "wof:placetype":"venue"
},
  "geometry": {"coordinates":[174.536224,-36.76432],"type":"Point"}
}