{
  "type": "Feature",
  "properties": {
    "addr:full":"Unit H 2 29 Keeling Rd Henderson  Auckland Auckland",
    "addr:housenumber":"29",
    "addr:street":"Keeling Rd",
    "iso:country":"NZ",
    "sg:address":"Unit H 2 29 Keeling Rd Henderson ",
    "sg:city":"Auckland",
    "sg:classifiers":[
        {
            "category":"Professional",
            "subcategory":"Art Services",
            "type":"Services"
        }
    ],
    "sg:phone":"+64 9-835 1182",
    "sg:province":"Auckland",
    "sg:tags":[
        "equipment",
        "arts",
        "sport",
        "film",
        "leisure"
    ],
    "wof:name":"Uni-Rig Ltd",
    "wof:placetype":"venue"
},
  "geometry": {"coordinates":[174.63294999999999,-36.877289],"type":"Point"}
}