{
  "type": "Feature",
  "properties": {
    "iso:country":"NZ",
    "sg:address":"PO Box 1188 ",
    "sg:city":"Hamilton",
    "sg:orig_category":"Transport: Transportation: Courier Services",
    "sg:phone":"+64 7-834 9990",
    "sg:province":"Waikato",
    "wof:name":"City Sprint Couriers Ltd",
    "wof:placetype":"venue"
},
  "geometry": {"coordinates":[-88.067299,34.201847],"type":"Point"}
}