{
  "type": "Feature",
  "properties": {
    "iso:country":"NZ",
    "sg:address":"Main Rd Makarora ",
    "sg:city":"Wanaka",
    "sg:classifiers":[
        {
            "category":"Recreation",
            "type":"Entertainment"
        }
    ],
    "sg:phone":"+64 3-443 9234",
    "sg:province":"Otago",
    "sg:tags":[
        "shopping",
        "hunting",
        "fishing",
        "retailers",
        "sport",
        "trip"
    ],
    "wof:name":"Wanaka Lakeland Fishing",
    "wof:placetype":"venue"
},
  "geometry": {"coordinates":[169.138443,-44.693981],"type":"Point"}
}