{
  "type": "Feature",
  "properties": {
    "addr:full":"13 Gordon Rd Morningside  Auckland Auckland",
    "addr:housenumber":"13",
    "addr:street":"Gordon Rd",
    "iso:country":"NZ",
    "sg:address":"13 Gordon Rd Morningside ",
    "sg:city":"Auckland",
    "sg:classifiers":[
        {
            "category":"Banks & Credit Unions",
            "subcategory":"Financial Services",
            "type":"Services"
        }
    ],
    "sg:phone":"+64 9-846 1867",
    "sg:province":"Auckland",
    "sg:tags":[
        "services",
        "die",
        "industrial",
        "maker",
        "sinker"
    ],
    "wof:name":"Guillotine Ltd",
    "wof:placetype":"venue"
},
  "geometry": {"coordinates":[174.68377699999999,-37.194908],"type":"Point"}
}