{
  "type": "Feature",
  "properties": {
    "addr:full":"64 Eliot St New  Plymouth Taranaki",
    "addr:housenumber":"64",
    "addr:street":"Eliot St",
    "iso:country":"NZ",
    "sg:address":"64 Eliot St New ",
    "sg:city":"Plymouth",
    "sg:classifiers":[
        {
            "category":"Sports & Exercise",
            "subcategory":"Tennis Court",
            "type":"Entertainment"
        }
    ],
    "sg:phone":"+64 6-757 4329",
    "sg:province":"Taranaki",
    "sg:tags":[
        "hire",
        "-",
        "leisure"
    ],
    "wof:name":"The Production Co",
    "wof:placetype":"venue"
},
  "geometry": {"coordinates":[-116.81972500000001,43.97221],"type":"Point"}
}