{
  "type": "Feature",
  "properties": {
    "addr:full":"36 Townhead Cre  Tauranga Bay of Plenty",
    "addr:housenumber":"36;cre",
    "addr:street":"Townhead",
    "iso:country":"NZ",
    "sg:address":"36 Townhead Cre ",
    "sg:city":"Tauranga",
    "sg:classifiers":[
        {
            "category":"Personal",
            "subcategory":"Massage",
            "type":"Services"
        }
    ],
    "sg:phone":"+64 7-578 6963",
    "sg:province":"Bay of Plenty",
    "sg:tags":[
        "services",
        "health",
        "-",
        "beauty",
        "fitness"
    ],
    "wof:name":"Coburn Faye-Massage Therapist",
    "wof:placetype":"venue"
},
  "geometry": {"coordinates":[176.130493,-37.705193],"type":"Point"}
}