{
  "type": "Feature",
  "properties": {
    "iso:country":"NZ",
    "sg:address":"Unit 2 35 Woodcocks Rd ",
    "sg:city":"Warkworth",
    "sg:classifiers":[
        {
            "category":"Professional",
            "type":"Services"
        }
    ],
    "sg:phone":"+64 9-425 9996",
    "sg:province":"Auckland",
    "sg:tags":[
        "services",
        "car",
        "valet",
        "automotive"
    ],
    "wof:name":"Paragon Valet",
    "wof:placetype":"venue"
},
  "geometry": {"coordinates":[174.65460200000001,-36.407074],"type":"Point"}
}