{
  "type": "Feature",
  "properties": {
    "addr:full":"54 Fergusson St  Feilding Manawatu-Wanganui",
    "addr:housenumber":"54",
    "addr:street":"Fergusson St",
    "iso:country":"NZ",
    "sg:address":"54 Fergusson St ",
    "sg:city":"Feilding",
    "sg:classifiers":[
        {
            "category":"Professional",
            "subcategory":"Art Services",
            "type":"Services"
        }
    ],
    "sg:phone":"+64 6-323 5357",
    "sg:province":"Manawatu-Wanganui",
    "sg:tags":[
        "picture",
        "arts",
        "sport",
        "framing",
        "leisure"
    ],
    "wof:name":"Svendsen Photography",
    "wof:placetype":"venue"
},
  "geometry": {"coordinates":[175.56553600000001,-40.227299],"type":"Point"}
}