{
  "type": "Feature",
  "properties": {
    "iso:country":"NZ",
    "sg:address":"154 Stafford St ",
    "sg:city":"Hokitika",
    "sg:classifiers":[
        {
            "category":"Home & Garden",
            "subcategory":"Building Materials",
            "type":"Retail Goods"
        }
    ],
    "sg:phone":"+64 272 293 857",
    "sg:province":"West Coast",
    "sg:tags":[
        "builder",
        "related"
    ],
    "wof:name":"Peter Blight Builders",
    "wof:placetype":"venue"
},
  "geometry": {"coordinates":[170.964691,-42.716328],"type":"Point"}
}