{
  "type": "Feature",
  "properties": {
    "addr:full":"257 a Hillside Rd South Dunedin  Dunedin Otago",
    "addr:housenumber":"257 a",
    "addr:street":"Hillside Rd",
    "iso:country":"NZ",
    "sg:address":"257 a Hillside Rd South Dunedin ",
    "sg:city":"Dunedin",
    "sg:classifiers":[
        {
            "category":"Home & Garden",
            "subcategory":"Building Materials",
            "type":"Retail Goods"
        }
    ],
    "sg:phone":"+64 3-456 4530",
    "sg:province":"Otago",
    "sg:tags":[
        "electrician",
        "related"
    ],
    "sg:website":"http://www.laserelectrical.co.nz",
    "wof:name":"Laser Electrical Dunedin",
    "wof:placetype":"venue"
},
  "geometry": {"coordinates":[170.495407,-45.894615],"type":"Point"}
}