{
  "type": "Feature",
  "properties": {
    "iso:country":"NZ",
    "sg:address":"www.minicoach.co.nz ",
    "sg:city":"Auckland",
    "sg:orig_category":"Automotive: General Services: Rental Vehicles",
    "sg:phone":"+64 9-300 3200",
    "sg:province":"Auckland",
    "sg:website":"http://www.minicoach.co.nz",
    "wof:name":"New Zealand Mini-Coach Rentals",
    "wof:placetype":"venue"
},
  "geometry": {"coordinates":[-119.10457599999999,36.597755],"type":"Point"}
}