{
  "type": "Feature",
  "properties": {
    "addr:full":"2 Landor Com  Rolleston",
    "addr:housenumber":"2",
    "iso:country":"NZ",
    "sg:address":"2 Landor Com ",
    "sg:city":"Rolleston",
    "sg:orig_category":"Industrial: Chemicals And Compounds: Silicones",
    "sg:phone":"+64 3-347 4454",
    "wof:name":"Hydrochem Surface Treatments",
    "wof:placetype":"venue"
},
  "geometry": {"coordinates":[172.38494900000001,-43.5942],"type":"Point"}
}