{
  "type": "Feature",
  "properties": {
    "addr:full":"8 Newry Clo Howick  Auckland Auckland",
    "addr:housenumber":"8;clo",
    "addr:street":"Newry",
    "iso:country":"NZ",
    "sg:address":"8 Newry Clo Howick ",
    "sg:city":"Auckland",
    "sg:classifiers":[
        {
            "category":"Farming",
            "subcategory":"Fish & Marine Products",
            "type":"Manufacturing & Wholesale Goods"
        }
    ],
    "sg:phone":"+64 9-272 9128",
    "sg:province":"Auckland",
    "sg:tags":[
        "boats",
        "yacht",
        "transport",
        "boat",
        "supply"
    ],
    "wof:name":"Auckland Marine Trimmers",
    "wof:placetype":"venue"
},
  "geometry": {"coordinates":[174.916946,-36.894379],"type":"Point"}
}