{
  "type": "Feature",
  "properties": {
    "iso:country":"NZ",
    "sg:address":"PO Box 158 New ",
    "sg:city":"Plymouth",
    "sg:classifiers":[
        {
            "category":"Wholesale",
            "subcategory":"Machinery & Supplies",
            "type":"Manufacturing & Wholesale Goods"
        }
    ],
    "sg:phone":"+64 6-755 1380",
    "sg:province":"Taranaki",
    "sg:tags":[
        "equipment",
        "industrial"
    ],
    "sg:website":"http://www.yellowpages.co.nz/for/corrocoat/dp29863.html",
    "wof:name":"Corrocoat Engineering Services Ltd",
    "wof:placetype":"venue"
},
  "geometry": {"coordinates":[-116.81972500000001,43.97221],"type":"Point"}
}