{
  "type": "Feature",
  "properties": {
    "addr:full":"Flower Pot-Glory Rd Pitt Island Chatham  Islands",
    "addr:street":"Pot-Glory Rd",
    "iso:country":"NZ",
    "sg:address":"Flower Pot-Glory Rd Pitt Island Chatham ",
    "sg:city":"Islands",
    "sg:classifiers":[
        {
            "category":"Restaurant",
            "type":"Food & Drink"
        }
    ],
    "sg:phone":"+64 3-305 0464",
    "sg:tags":[
        "sea"
    ],
    "wof:name":"RJW Lanauze Fishing",
    "wof:placetype":"venue"
},
  "geometry": {"coordinates":[-176.20799299999999,-44.294441],"type":"Point"}
}