{
  "type": "Feature",
  "properties": {
    "iso:country":"NZ",
    "sg:address":"25 Intermediate St ",
    "sg:city":"Masterton",
    "sg:classifiers":[
        {
            "category":"Personal",
            "type":"Services"
        }
    ],
    "sg:phone":"+64 6-377 5716",
    "sg:province":"Wellington",
    "sg:tags":[
        "services",
        "home",
        "garden",
        "counselling"
    ],
    "wof:name":"Sedgley Family Centre",
    "wof:placetype":"venue"
},
  "geometry": {"coordinates":[175.64167800000001,-40.958237],"type":"Point"}
}