{
  "type": "Feature",
  "properties": {
    "iso:country":"NZ",
    "sg:address":"Menzies Building 1 Esk St ",
    "sg:city":"Invercargill",
    "sg:classifiers":[
        {
            "category":"Personal",
            "subcategory":"Beauty Salon",
            "type":"Services"
        }
    ],
    "sg:phone":"+64 3-214 9341",
    "sg:province":"Southland",
    "sg:tags":[
        "specialists",
        "health",
        "treatment",
        "skin"
    ],
    "wof:name":"Psoriasis Resource Centre",
    "wof:placetype":"venue"
},
  "geometry": {"coordinates":[168.352173,-46.411854],"type":"Point"}
}