{
  "type": "Feature",
  "properties": {
    "addr:full":"Kennington Rd  Invercargill Southland",
    "addr:street":"Kennington Rd",
    "iso:country":"NZ",
    "sg:address":"Kennington Rd ",
    "sg:city":"Invercargill",
    "sg:classifiers":[
        {
            "category":"Restaurant",
            "type":"Food & Drink"
        }
    ],
    "sg:phone":"+64 3-230 4390",
    "sg:province":"Southland",
    "sg:tags":[
        "merchant",
        "fish",
        "sea"
    ],
    "wof:name":"Seafood Direct Ltd",
    "wof:placetype":"venue"
},
  "geometry": {"coordinates":[168.44619800000001,-46.392315],"type":"Point"}
}