{
  "type": "Feature",
  "properties": {
    "addr:full":"29 B Barrys Point Rd Takapuna  Auckland Auckland",
    "addr:housenumber":"29 b",
    "addr:street":"Barrys Point Rd",
    "iso:country":"NZ",
    "sg:address":"29 B Barrys Point Rd Takapuna ",
    "sg:city":"Auckland",
    "sg:orig_category":"Automotive: General Services: Vehicle Inspection",
    "sg:phone":"+64 508 864 387",
    "sg:province":"Auckland",
    "wof:name":"Smartcheck Inspection Services",
    "wof:placetype":"venue"
},
  "geometry": {"coordinates":[174.76480100000001,-36.791691],"type":"Point"}
}