{
  "type": "Feature",
  "properties": {
    "addr:full":"Shop 3 152 Tuhikaramea Rd  Hamilton Waikato",
    "addr:housenumber":"shop 3",
    "addr:postcode":"152",
    "addr:street":"Tuhikaramea Rd",
    "iso:country":"NZ",
    "sg:address":"Shop 3 152 Tuhikaramea Rd ",
    "sg:city":"Hamilton",
    "sg:orig_category":"Clothing And Fabric: Clothing: Menswear",
    "sg:phone":"+64 7-846 2560",
    "sg:province":"Waikato",
    "wof:name":"Bassline",
    "wof:placetype":"venue"
},
  "geometry": {"coordinates":[175.244888,-37.802303],"type":"Point"}
}