{
  "type": "Feature",
  "properties": {
    "addr:full":"State H'Way 30 R D 4 Lake Rotoiti  Rotoiti",
    "addr:housenumber":"30;4",
    "addr:street":"R D;Lake Rotoiti Rotoiti",
    "iso:country":"NZ",
    "sg:address":"State H'Way 30 R D 4 Lake Rotoiti ",
    "sg:city":"Rotoiti",
    "sg:classifiers":[
        {
            "category":"Travel",
            "subcategory":"Hotels & Motels",
            "type":"Entertainment"
        }
    ],
    "sg:phone":"+64 7-362 7823",
    "sg:tags":[
        "tavern",
        "tourism",
        "accommodation"
    ],
    "sg:website":"http://www.mooselodge.co.nz",
    "wof:name":"Moose Lodge & Golf Resort",
    "wof:placetype":"venue"
},
  "geometry": {"coordinates":[176.47079500000001,-38.054199],"type":"Point"}
}