{
  "type": "Feature",
  "properties": {
    "iso:country":"NZ",
    "sg:address":"499 E Moorhouse Ave Waltham ",
    "sg:city":"Christchurch",
    "sg:orig_category":"Industrial: Electrical/Electronic: Electrical Switchgear",
    "sg:phone":"+64 3-379 0844",
    "sg:province":"Canterbury",
    "wof:name":"Switchcon Systems",
    "wof:placetype":"venue"
},
  "geometry": {"coordinates":[172.65100100000001,-43.539791],"type":"Point"}
}