{
  "type": "Feature",
  "properties": {
    "addr:full":"80 Rutherford St Woolston  Christchurch Canterbury",
    "addr:housenumber":"80",
    "addr:street":"Rutherford St",
    "iso:country":"NZ",
    "sg:address":"80 Rutherford St Woolston ",
    "sg:city":"Christchurch",
    "sg:orig_category":"Automotive: Accessories",
    "sg:phone":"+64 3-384 9695",
    "sg:province":"Canterbury",
    "wof:name":"Mr Muffler",
    "wof:placetype":"venue"
},
  "geometry": {"coordinates":[172.677719,-43.54937],"type":"Point"}
}