{
  "type": "Feature",
  "properties": {
    "addr:full":"75a Wiri Station Rd Manukau  Auckland Auckland",
    "addr:housenumber":"75a",
    "addr:street":"Wiri Station Rd",
    "iso:country":"NZ",
    "sg:address":"75a Wiri Station Rd Manukau ",
    "sg:city":"Auckland",
    "sg:classifiers":[
        {
            "category":"Autos & Motor Vehicles",
            "subcategory":"Automobile Sales",
            "type":"Retail Goods"
        }
    ],
    "sg:phone":"+64 9-262 0027",
    "sg:province":"Auckland",
    "sg:tags":[
        "bus",
        "leasing",
        "truck",
        "automotive"
    ],
    "wof:name":"LDV Van Centre",
    "wof:placetype":"venue"
},
  "geometry": {"coordinates":[174.876251,-36.997879],"type":"Point"}
}