{
  "type": "Feature",
  "properties": {
    "addr:full":"Waverley St  Karamea",
    "addr:street":"Waverley St",
    "iso:country":"NZ",
    "sg:address":"Waverley St ",
    "sg:city":"Karamea",
    "sg:classifiers":[
        {
            "category":"Travel",
            "subcategory":"Hotels & Motels",
            "type":"Entertainment"
        }
    ],
    "sg:phone":"+64 3-782 6800",
    "sg:tags":[
        "tavern",
        "tourism",
        "accommodation"
    ],
    "wof:name":"Karamea Village Hotel",
    "wof:placetype":"venue"
},
  "geometry": {"coordinates":[172.12084999999999,-41.249405],"type":"Point"}
}