{
  "type": "Feature",
  "properties": {
    "addr:full":"370 Bushmere Rd  Gisborne Gisborne",
    "addr:housenumber":"370",
    "addr:street":"Bushmere Rd",
    "iso:country":"NZ",
    "sg:address":"370 Bushmere Rd ",
    "sg:city":"Gisborne",
    "sg:orig_category":"Farming: Machinery: Farm Machinery",
    "sg:phone":"+64 6-863 2612",
    "sg:province":"Gisborne",
    "wof:name":"Williams D P Repairs & Servicing",
    "wof:placetype":"venue"
},
  "geometry": {"coordinates":[177.942307,-38.645187],"type":"Point"}
}