{
  "type": "Feature",
  "properties": {
    "addr:full":"230 Mt Albert Rd Mt Albert  Auckland Auckland",
    "addr:housenumber":"230",
    "addr:street":"Mt Albert Rd",
    "iso:country":"NZ",
    "sg:address":"230 Mt Albert Rd Mt Albert ",
    "sg:city":"Auckland",
    "sg:classifiers":[
        {
            "category":"Health Services",
            "subcategory":"Health Practitioner",
            "type":"Services"
        }
    ],
    "sg:phone":"+64 9-629 2088",
    "sg:province":"Auckland",
    "sg:tags":[
        "specialist",
        "medical",
        "beauty",
        "specialists"
    ],
    "wof:name":"Alberton Medical Practice",
    "wof:placetype":"venue"
},
  "geometry": {"coordinates":[174.714798,-36.88784],"type":"Point"}
}