{
  "type": "Feature",
  "properties": {
    "iso:country":"NZ",
    "sg:address":"235 Broadway Newmarket ",
    "sg:city":"Auckland",
    "sg:orig_category":"Clothing And Fabric: Fabric: Drapers",
    "sg:phone":"+64 9-522 4161",
    "sg:province":"Manawatu-Wanganui",
    "wof:name":"AB Fabrics Ltd",
    "wof:placetype":"venue"
},
  "geometry": {"coordinates":[174.777512,-36.869747],"type":"Point"}
}