{
  "type": "Feature",
  "properties": {
    "iso:country":"NZ",
    "sg:address":"19 Derby St ",
    "sg:city":"Gisborne",
    "sg:classifiers":[
        {
            "category":"Health Services",
            "subcategory":"Dentist",
            "type":"Services"
        }
    ],
    "sg:phone":"+64 6-867 9108",
    "sg:province":"Gisborne",
    "sg:tags":[
        "dental",
        "beauty"
    ],
    "wof:name":"Bennett Robin J BDS",
    "wof:placetype":"venue"
},
  "geometry": {"coordinates":[178.024902,-38.662109],"type":"Point"}
}