{
  "type": "Feature",
  "properties": {
    "addr:full":"PO Box 40282 Upper  Hutt Wellington",
    "addr:housenumber":"po box",
    "addr:street":"40282 Upper",
    "iso:country":"NZ",
    "sg:address":"PO Box 40282 Upper ",
    "sg:city":"Hutt",
    "sg:classifiers":[
        {
            "category":"Sports & Exercise",
            "subcategory":"Sports Center",
            "type":"Entertainment"
        }
    ],
    "sg:phone":"+64 4-526 2990",
    "sg:province":"Wellington",
    "sg:tags":[
        "health",
        "beauty",
        "fitness"
    ],
    "wof:name":"Rimutaka Gymnastics Inc. Society",
    "wof:placetype":"venue"
},
  "geometry": {"coordinates":[175.07037399999999,-41.124439],"type":"Point"}
}