{
  "type": "Feature",
  "properties": {
    "addr:full":"3/855 Wairakei Rd  Christchurch Canterbury",
    "addr:housenumber":"3 / 855",
    "addr:street":"Wairakei Rd",
    "iso:country":"NZ",
    "sg:address":"3/855 Wairakei Rd ",
    "sg:city":"Christchurch",
    "sg:orig_category":"Transport: Transportation: Freight",
    "sg:phone":"+64 3-358 0269",
    "sg:province":"Canterbury",
    "wof:name":"Kuehne & Nagel Ltd",
    "wof:placetype":"venue"
},
  "geometry": {"coordinates":[-76.537834,37.605659],"type":"Point"}
}