{
  "type": "Feature",
  "properties": {
    "addr:full":"36 Grand View Rd Remuera  Auckland Auckland",
    "addr:housenumber":"36",
    "addr:street":"Grand View Rd",
    "iso:country":"NZ",
    "sg:address":"36 Grand View Rd Remuera ",
    "sg:city":"Auckland",
    "sg:classifiers":[
        {
            "category":"Home & Garden",
            "subcategory":"Garden Supply",
            "type":"Retail Goods"
        }
    ],
    "sg:phone":"+64 9-520 5214",
    "sg:province":"Auckland",
    "sg:tags":[
        "trainer",
        "breeder",
        "/",
        "pets",
        "animal"
    ],
    "sg:website":"http://www.ragdolls.co.nz",
    "wof:name":"Kiwimagic Ragdolls",
    "wof:placetype":"venue"
},
  "geometry": {"coordinates":[174.80886799999999,-36.869381],"type":"Point"}
}