{
  "type": "Feature",
  "properties": {
    "iso:country":"NZ",
    "sg:address":"370 Tuam St ",
    "sg:city":"Christchurch",
    "sg:classifiers":[
        {
            "category":"Wholesale",
            "subcategory":"Auto Parts",
            "type":"Manufacturing & Wholesale Goods"
        }
    ],
    "sg:phone":"+64 3-379 4493",
    "sg:province":"Canterbury",
    "sg:tags":[
        "automotive",
        "supplies"
    ],
    "wof:name":"Fully Equipped Canterbury",
    "wof:placetype":"venue"
},
  "geometry": {"coordinates":[-76.537834,37.605659],"type":"Point"}
}