{
  "type": "Feature",
  "properties": {
    "addr:full":"9 Tui Rd School Cnr Papatoetoe  Auckland Auckland",
    "addr:housenumber":"9;cnr",
    "addr:street":"Tui Rd",
    "iso:country":"NZ",
    "sg:address":"9 Tui Rd School Cnr Papatoetoe ",
    "sg:city":"Auckland",
    "sg:classifiers":[
        {
            "category":"Retail",
            "subcategory":"Auto Repair",
            "type":"Services"
        }
    ],
    "sg:phone":"+64 9-278 8147",
    "sg:province":"Auckland",
    "sg:tags":[
        "automotive",
        "electric",
        "servicing"
    ],
    "wof:name":"Papatoetoe Auto Electrical Ltd",
    "wof:placetype":"venue"
},
  "geometry": {"coordinates":[174.86473100000001,-36.973701],"type":"Point"}
}