{
  "type": "Feature",
  "properties": {
    "iso:country":"NZ",
    "sg:address":"PO Box 561 ",
    "sg:city":"Tokoroa",
    "sg:orig_category":"Farming: Forestry",
    "sg:phone":"+64 7-886 6054",
    "wof:name":"Pine Technicians Ltd",
    "wof:placetype":"venue"
},
  "geometry": {"coordinates":[175.866333,-38.226044],"type":"Point"}
}