{
  "type": "Feature",
  "properties": {
    "iso:country":"NZ",
    "sg:address":"24 Heu Heu St ",
    "sg:city":"Taupo",
    "sg:orig_category":"Shopping: Accessories: Bags - Fashion",
    "sg:phone":"+64 7-378 9673",
    "sg:province":"Waikato",
    "wof:name":"Taupo Luggage",
    "wof:placetype":"venue"
},
  "geometry": {"coordinates":[176.070572,-38.687756],"type":"Point"}
}