{
  "type": "Feature",
  "properties": {
    "addr:full":"Lake Rd R D 1 Taupiri  Hamilton Waikato",
    "addr:housenumber":"1",
    "addr:street":"Lake Rd R D",
    "iso:country":"NZ",
    "sg:address":"Lake Rd R D 1 Taupiri ",
    "sg:city":"Hamilton",
    "sg:orig_category":"Shopping: Accessories",
    "sg:phone":"+64 7-847 9902",
    "sg:province":"Waikato",
    "sg:website":"http://www.reijewellery.co.nz",
    "wof:name":"Rei Jewellery Ltd",
    "wof:placetype":"venue"
},
  "geometry": {"coordinates":[175.18974299999999,-37.613838],"type":"Point"}
}