{
  "type": "Feature",
  "properties": {
    "iso:country":"NZ",
    "sg:address":"19 Borrell Ave New ",
    "sg:city":"Plymouth",
    "sg:orig_category":"Automotive: Accessories: Towbars",
    "sg:phone":"+64 6-753 3994",
    "sg:province":"Taranaki",
    "wof:name":"R & I Engineering",
    "wof:placetype":"venue"
},
  "geometry": {"coordinates":[-116.819725,43.97221],"type":"Point"}
}