{
  "type": "Feature",
  "properties": {
    "iso:country":"NZ",
    "sg:address":"41 KeriKeri Rd ",
    "sg:city":"Kerikeri",
    "sg:classifiers":[
        {
            "category":"Arena",
            "subcategory":"Sports Club",
            "type":"Entertainment"
        }
    ],
    "sg:phone":"+64 9-407 5585",
    "sg:province":"Northland",
    "sg:tags":[
        "leisure"
    ],
    "sg:website":"http://www.yellowpages.co.nz/pages/214024625/dp43583.html",
    "wof:name":"Bay Dive & Fishing Tackle",
    "wof:placetype":"venue"
},
  "geometry": {"coordinates":[173.943848,-35.233288],"type":"Point"}
}