{
  "type": "Feature",
  "properties": {
    "iso:country":"NZ",
    "sg:address":"28 Arney St ",
    "sg:city":"Greymouth",
    "sg:classifiers":[
        {
            "category":"Wholesale",
            "subcategory":"Auto Parts",
            "type":"Manufacturing & Wholesale Goods"
        }
    ],
    "sg:phone":"+64 3-768 5711",
    "sg:province":"West Coast",
    "sg:tags":[
        "automotive",
        "supplies"
    ],
    "wof:name":"Smiths Speed & Spares",
    "wof:placetype":"venue"
},
  "geometry": {"coordinates":[171.20387299999999,-42.448627],"type":"Point"}
}