{
  "type": "Feature",
  "properties": {
    "addr:full":"West City Ctr Henderson  Auckland Auckland",
    "addr:street":"West",
    "iso:country":"NZ",
    "sg:address":"West City Ctr Henderson ",
    "sg:city":"Auckland",
    "sg:classifiers":[
        {
            "category":"Shopping",
            "subcategory":"Crafts & Fabrics",
            "type":"Retail Goods"
        }
    ],
    "sg:phone":"+64 9-836 3481",
    "sg:province":"Auckland",
    "sg:tags":[
        "foot",
        "clothing",
        "retailer",
        "footwear",
        "wear"
    ],
    "wof:name":"Wild Pair Ltd",
    "wof:placetype":"venue"
},
  "geometry": {"coordinates":[174.63294999999999,-36.877289],"type":"Point"}
}