{
  "type": "Feature",
  "properties": {
    "addr:full":"87 Queen St Auckland City  Auckland Auckland",
    "addr:housenumber":"87",
    "addr:street":"Queen St",
    "iso:country":"NZ",
    "sg:address":"87 Queen St Auckland City ",
    "sg:city":"Auckland",
    "sg:orig_category":"Health And Beauty: Specialists: Osteopaths",
    "sg:phone":"+64 9-366 1996",
    "sg:province":"Auckland",
    "wof:name":"Queen Street Osteopaths",
    "wof:placetype":"venue"
},
  "geometry": {"coordinates":[174.76618999999999,-36.845516],"type":"Point"}
}