{
  "type": "Feature",
  "properties": {
    "addr:full":"1B 945 Ferry Rd  Christchurch Canterbury",
    "addr:housenumber":"1b 945",
    "addr:street":"Ferry Rd",
    "iso:country":"NZ",
    "sg:address":"1B 945 Ferry Rd ",
    "sg:city":"Christchurch",
    "sg:orig_category":"Farming: Horticulture: Grain And Seed",
    "sg:phone":"+64 3-384 2593",
    "sg:province":"Canterbury",
    "sg:website":"http://www.smithseeds.co.nz/",
    "wof:name":"Smith Seeds Ltd",
    "wof:placetype":"venue"
},
  "geometry": {"coordinates":[-76.537834,37.605659],"type":"Point"}
}