{
  "type": "Feature",
  "properties": {
    "addr:full":"Redfern St  Dannevirke",
    "addr:street":"Redfern St",
    "iso:country":"NZ",
    "sg:address":"Redfern St ",
    "sg:city":"Dannevirke",
    "sg:classifiers":[
        {
            "category":"Arena",
            "subcategory":"Sports Club",
            "type":"Entertainment"
        }
    ],
    "sg:phone":"+64 6-374 6745",
    "sg:tags":[
        "-",
        "leisure",
        "sports"
    ],
    "wof:name":"Rangitane Sports Club",
    "wof:placetype":"venue"
},
  "geometry": {"coordinates":[-98.60567500000001,41.329346],"type":"Point"}
}