{
  "type": "Feature",
  "properties": {
    "addr:full":"11D/20 Oriental Tce Oriental Bay  Wellington Wellington",
    "addr:housenumber":"11d / 20",
    "addr:street":"Oriental Tce",
    "iso:country":"NZ",
    "sg:address":"11D/20 Oriental Tce Oriental Bay ",
    "sg:city":"Wellington",
    "sg:orig_category":"Farming: Forestry: Forestry Consultants",
    "sg:phone":"+64 4-384 2104",
    "sg:province":"Wellington",
    "wof:name":"S Strand & Associates Limited",
    "wof:placetype":"venue"
},
  "geometry": {"coordinates":[174.79222100000001,-41.291897],"type":"Point"}
}