{
  "type": "Feature",
  "properties": {
    "iso:country":"NZ",
    "sg:address":"PO Box 15784 New Lynn ",
    "sg:city":"Auckland",
    "sg:classifiers":[
        {
            "category":"Home & Garden",
            "subcategory":"Building Materials",
            "type":"Retail Goods"
        }
    ],
    "sg:phone":"+64 9-815 8392",
    "sg:province":"Auckland",
    "sg:tags":[
        "door",
        "fitting",
        "fittings"
    ],
    "wof:name":"The Doorman Ltd",
    "wof:placetype":"venue"
},
  "geometry": {"coordinates":[174.68309,-36.920143],"type":"Point"}
}