{
  "type": "Feature",
  "properties": {
    "addr:full":"G/11 Piermark Dve Albany  Auckland Auckland",
    "addr:housenumber":"/ 11",
    "addr:street":"Dve",
    "iso:country":"NZ",
    "sg:address":"G/11 Piermark Dve Albany ",
    "sg:city":"Auckland",
    "sg:classifiers":[
        {
            "category":"Sports & Exercise",
            "subcategory":"Golf",
            "type":"Entertainment"
        }
    ],
    "sg:phone":"+64 9-415 0012",
    "sg:province":"Auckland",
    "sg:tags":[
        "club",
        "equipment",
        "leisure",
        "sports"
    ],
    "wof:name":"Arboc Holdings Ltd",
    "wof:placetype":"venue"
},
  "geometry": {"coordinates":[174.68959000000001,-36.790905],"type":"Point"}
}