{
  "type": "Feature",
  "properties": {
    "addr:full":"13 Moody Ave  Whangarei Northland",
    "addr:housenumber":"13",
    "addr:street":"Moody Ave",
    "iso:country":"NZ",
    "sg:address":"13 Moody Ave ",
    "sg:city":"Whangarei",
    "sg:classifiers":[
        {
            "category":"Shopping",
            "subcategory":"Bicycles & Sporting Goods",
            "type":"Retail Goods"
        }
    ],
    "sg:phone":"+64 9-437 3632",
    "sg:province":"Northland",
    "sg:tags":[
        "sport",
        "retailer"
    ],
    "sg:website":"http://www.divenz.co.nz",
    "wof:name":"Pacific Hideaway Charters",
    "wof:placetype":"venue"
},
  "geometry": {"coordinates":[174.31648300000001,-35.701584],"type":"Point"}
}