{
  "type": "Feature",
  "properties": {
    "iso:country":"NZ",
    "sg:address":"18 Berkshire Drive Avonhead ",
    "sg:city":"Christchurch",
    "sg:classifiers":[
        {
            "category":"Banks & Credit Unions",
            "subcategory":"Investment Brokerage",
            "type":"Services"
        }
    ],
    "sg:phone":"+64 3-357 1168",
    "sg:province":"Canterbury",
    "sg:tags":[
        "educational",
        "education",
        "training"
    ],
    "wof:name":"International Education Corporation",
    "wof:placetype":"venue"
},
  "geometry": {"coordinates":[172.548889,-43.515011],"type":"Point"}
}