{
  "type": "Feature",
  "properties": {
    "iso:country":"NZ",
    "sg:address":"90 Buchan St Sydenham ",
    "sg:city":"Christchurch",
    "sg:classifiers":[
        {
            "category":"Shopping",
            "subcategory":"Shoes",
            "type":"Retail Goods"
        }
    ],
    "sg:phone":"+64 3-377 6102",
    "sg:province":"Canterbury",
    "sg:tags":[
        "foot",
        "clothing",
        "fabric",
        "wear"
    ],
    "wof:name":"Shoetech Industries",
    "wof:placetype":"venue"
},
  "geometry": {"coordinates":[172.63841199999999,-43.542938],"type":"Point"}
}