{
  "type": "Feature",
  "properties": {
    "iso:country":"NZ",
    "sg:address":"29 Main North Rd Papanui ",
    "sg:city":"Christchurch",
    "sg:orig_category":"Home And Garden: Accessories: Linen",
    "sg:phone":"+64 3-352 5711",
    "sg:province":"Canterbury",
    "wof:name":"Arbuckles",
    "wof:placetype":"venue"
},
  "geometry": {"coordinates":[172.608505,-43.49551],"type":"Point"}
}