{
  "type": "Feature",
  "properties": {
    "iso:country":"NZ",
    "sg:address":"50 Ngarua Rd Waitoa ",
    "sg:city":"Morrinsville",
    "sg:classifiers":[
        {
            "category":"Retail",
            "subcategory":"Animal Services",
            "type":"Services"
        }
    ],
    "sg:phone":"+64 7-887 1885",
    "sg:province":"Waikato",
    "sg:tags":[
        "pet",
        "home",
        "garden",
        "pets"
    ],
    "wof:name":"Corbi Creations",
    "wof:placetype":"venue"
},
  "geometry": {"coordinates":[175.528717,-37.65411],"type":"Point"}
}