{
  "type": "Feature",
  "properties": {
    "addr:full":"35 Patterson Tce Halswell  Christchurch Canterbury",
    "addr:housenumber":"35",
    "addr:street":"Patterson Tce",
    "iso:country":"NZ",
    "sg:address":"35 Patterson Tce Halswell ",
    "sg:city":"Christchurch",
    "sg:orig_category":"Home And Garden: Children: Child Related",
    "sg:phone":"+64 3-322 8874",
    "sg:province":"Canterbury",
    "wof:name":"Surefire Products New Zealand",
    "wof:placetype":"venue"
},
  "geometry": {"coordinates":[172.56651299999999,-43.579105],"type":"Point"}
}