{
  "type": "Feature",
  "properties": {
    "iso:country":"NZ",
    "sg:address":"66 Beach Rd ",
    "sg:city":"Kaikoura",
    "sg:orig_category":"Automotive: Sales And Leasing: Trailers",
    "sg:phone":"+64 800 667 733",
    "wof:name":"Mudgway Trailers",
    "wof:placetype":"venue"
},
  "geometry": {"coordinates":[173.679306,-42.394447],"type":"Point"}
}