{
  "type": "Feature",
  "properties": {
    "addr:full":"Old P.O. Bldg Patumahoe Rd Patumahoe  Pukekohe Auckland",
    "addr:street":"Old;Patumahoe Rd",
    "iso:country":"NZ",
    "sg:address":"Old P.O. Bldg Patumahoe Rd Patumahoe ",
    "sg:city":"Pukekohe",
    "sg:orig_category":"Home And Garden: Children: Child Related",
    "sg:phone":"+64 9-236 3970",
    "sg:province":"Auckland",
    "wof:name":"Sanfred Porcelain Products & Dolls",
    "wof:placetype":"venue"
},
  "geometry": {"coordinates":[174.82908599999999,-37.187679],"type":"Point"}
}