{
  "type": "Feature",
  "properties": {
    "addr:full":"Unit 1 80 Paul Matthews Rd Albany  Auckland Auckland",
    "addr:housenumber":"unit;80",
    "addr:street":"Paul Matthews Rd",
    "iso:country":"NZ",
    "sg:address":"Unit 1 80 Paul Matthews Rd Albany ",
    "sg:city":"Auckland",
    "sg:classifiers":[
        {
            "category":"Shopping",
            "subcategory":"Clothing, Apparel, & Fashions",
            "type":"Retail Goods"
        }
    ],
    "sg:phone":"+64 9-414 4692",
    "sg:province":"Auckland",
    "sg:tags":[
        "school",
        "clothing",
        "fabric",
        "uniform"
    ],
    "wof:name":"Yarntons",
    "wof:placetype":"venue"
},
  "geometry": {"coordinates":[174.709686,-36.720142],"type":"Point"}
}