{
  "type": "Feature",
  "properties": {
    "addr:full":"PO Box 65180 Mairangi Bay  Auckland Auckland",
    "addr:housenumber":"po box",
    "addr:postcode":"65180",
    "iso:country":"NZ",
    "sg:address":"PO Box 65180 Mairangi Bay ",
    "sg:city":"Auckland",
    "sg:classifiers":[
        {
            "category":"Shopping",
            "subcategory":"Beauty & Cosmetics",
            "type":"Retail Goods"
        }
    ],
    "sg:phone":"+64 9-479 6467",
    "sg:province":"Auckland",
    "sg:tags":[
        "health",
        "perfumery"
    ],
    "wof:name":"Good Health Products Ltd",
    "wof:placetype":"venue"
},
  "geometry": {"coordinates":[174.74816899999999,-36.738461],"type":"Point"}
}