{
  "type": "Feature",
  "properties": {
    "iso:country":"NZ",
    "sg:address":"10 Manchester Sq ",
    "sg:city":"Feilding",
    "sg:classifiers":[
        {
            "category":"Landmark",
            "subcategory":"Tourist Information",
            "type":"Public Place"
        }
    ],
    "sg:phone":"+64 6-323 3318",
    "sg:province":"Manawatu-Wanganui",
    "sg:tags":[
        "services",
        "travel",
        "tourism"
    ],
    "wof:name":"Feilding & District Information Centre",
    "wof:placetype":"venue"
},
  "geometry": {"coordinates":[175.563583,-40.225971],"type":"Point"}
}