{
  "type": "Feature",
  "properties": {
    "addr:full":"Sunrise Valley Rd Sunrise Valley Upper  Moutere",
    "addr:street":"Sunrise Valley Rd",
    "iso:country":"NZ",
    "sg:address":"Sunrise Valley Rd Sunrise Valley Upper ",
    "sg:city":"Moutere",
    "sg:classifiers":[
        {
            "category":"Health Services",
            "subcategory":"Doctor",
            "type":"Services"
        }
    ],
    "sg:phone":"+64 3-543 2015",
    "sg:tags":[
        "beauty"
    ],
    "sg:website":"http://www.yellowpages.co.nz/for/sunrisecleaning/dp37065.html",
    "wof:name":"Sunrise Cleaning Services Ltd",
    "wof:placetype":"venue"
},
  "geometry": {"coordinates":[172.99685700000001,-41.214348],"type":"Point"}
}