{
  "type": "Feature",
  "properties": {
    "iso:country":"NZ",
    "sg:address":"74 Old Taupo Rd ",
    "sg:city":"Rotorua",
    "sg:orig_category":"Home And Garden: Outdoor: Barbecues",
    "sg:phone":"+64 7-348 1101",
    "sg:province":"Bay of Plenty",
    "wof:name":"Rotorua Heat & Gas Centre",
    "wof:placetype":"venue"
},
  "geometry": {"coordinates":[176.238663,-38.147594],"type":"Point"}
}