{
  "type": "Feature",
  "properties": {
    "iso:country":"NZ",
    "sg:address":"11 Melrose St Newmarket ",
    "sg:city":"Auckland",
    "sg:classifiers":[
        {
            "category":"Manufacturing",
            "subcategory":"Motor Vehicles & Parts",
            "type":"Manufacturing & Wholesale Goods"
        }
    ],
    "sg:phone":"+64 9-522 3300",
    "sg:province":"Auckland",
    "sg:tags":[
        "air conditioning",
        "automotive",
        "supplies"
    ],
    "sg:website":"http://www.autotemp.co.nz",
    "wof:name":"Auto Temp",
    "wof:placetype":"venue"
},
  "geometry": {"coordinates":[174.77417,-36.867481],"type":"Point"}
}