{
  "type": "Feature",
  "properties": {
    "addr:full":"Level 4, Tower B 100 Carlton Gore Rd Newmarket  Auckland Auckland",
    "addr:housenumber":"level 4 tower b 100",
    "addr:street":"Carlton Gore Rd",
    "iso:country":"NZ",
    "sg:address":"Level 4, Tower B 100 Carlton Gore Rd Newmarket ",
    "sg:city":"Auckland",
    "sg:orig_category":"Farming: Farms - General: Poultry",
    "sg:phone":"+64 9-379 1700",
    "sg:province":"Auckland",
    "wof:name":"Tegel Foods Ltd",
    "wof:placetype":"venue"
},
  "geometry": {"coordinates":[174.77375799999999,-36.867878],"type":"Point"}
}