{
  "type": "Feature",
  "properties": {
    "addr:full":"222 Studholme St  Morrinsville Waikato",
    "addr:housenumber":"222",
    "addr:street":"Studholme St",
    "iso:country":"NZ",
    "sg:address":"222 Studholme St ",
    "sg:city":"Morrinsville",
    "sg:orig_category":"Health And Beauty: Medical: Hospitals",
    "sg:phone":"+64 7-889 7039",
    "sg:province":"Waikato",
    "wof:name":"Rhoda Read Hospital",
    "wof:placetype":"venue"
},
  "geometry": {"coordinates":[175.53045700000001,-37.660732],"type":"Point"}
}