{
  "type": "Feature",
  "properties": {
    "addr:full":"44 Pharazyn St  Feilding Manawatu-Wanganui",
    "addr:housenumber":"44",
    "addr:street":"Pharazyn St",
    "iso:country":"NZ",
    "sg:address":"44 Pharazyn St ",
    "sg:city":"Feilding",
    "sg:orig_category":"Food And Drink: Catering: Caterers",
    "sg:phone":"+64 6-323 0005",
    "sg:province":"Manawatu-Wanganui",
    "wof:name":"Cuisine Caterers",
    "wof:placetype":"venue"
},
  "geometry": {"coordinates":[175.58412200000001,-40.213806],"type":"Point"}
}