{
  "type": "Feature",
  "properties": {
    "iso:country":"NZ",
    "sg:address":"44 Main St ",
    "sg:city":"Pahiatua",
    "sg:classifiers":[
        {
            "category":"Autos & Motor Vehicles",
            "subcategory":"Automobile Sales",
            "type":"Retail Goods"
        }
    ],
    "sg:phone":"+64 6-376 7498",
    "sg:tags":[
        "leasing",
        "car",
        "-",
        "truck",
        "automotive",
        "new"
    ],
    "wof:name":"Hoffman Ford",
    "wof:placetype":"venue"
},
  "geometry": {"coordinates":[175.835831,-40.458637],"type":"Point"}
}