{
  "type": "Feature",
  "properties": {
    "addr:full":"50 C Mokoia Rd Birkenhead  Auckland Auckland",
    "addr:housenumber":"50 c",
    "addr:street":"Mokoia Rd",
    "iso:country":"NZ",
    "sg:address":"50 C Mokoia Rd Birkenhead ",
    "sg:city":"Auckland",
    "sg:classifiers":[
        {
            "category":"Fast Food",
            "type":"Food & Drink"
        }
    ],
    "sg:phone":"+64 9-480 1049",
    "sg:province":"Auckland",
    "sg:tags":[
        "wining",
        "dining",
        "takeaway"
    ],
    "wof:name":"Mal's Place",
    "wof:placetype":"venue"
},
  "geometry": {"coordinates":[174.72439600000001,-36.812092],"type":"Point"}
}