{
  "type": "Feature",
  "properties": {
    "iso:country":"NZ",
    "sg:address":"49 Reynolds Ave Bishopdale ",
    "sg:city":"Christchurch",
    "sg:orig_category":"Transport: Consultancy: Traffic Management",
    "sg:phone":"+64 3-359 9012",
    "sg:province":"Canterbury",
    "wof:name":"Traffic Counting Services",
    "wof:placetype":"venue"
},
  "geometry": {"coordinates":[172.591354,-43.486748],"type":"Point"}
}