{
  "type": "Feature",
  "properties": {
    "addr:full":"309 Seaview Rd Waiheke Island  Auckland Auckland",
    "addr:housenumber":"309",
    "addr:street":"Seaview Rd Waiheke",
    "iso:country":"NZ",
    "sg:address":"309 Seaview Rd Waiheke Island ",
    "sg:city":"Auckland",
    "sg:classifiers":[
        {
            "category":"Education",
            "subcategory":"Special Training",
            "type":"Public Place"
        }
    ],
    "sg:phone":"+64 9-372 2247",
    "sg:province":"Auckland",
    "sg:tags":[
        "tutor",
        "coach",
        "teacher"
    ],
    "wof:name":"Kip McGrath Education Centres (NZ) Ltd",
    "wof:placetype":"venue"
},
  "geometry": {"coordinates":[175.05941799999999,-36.784565],"type":"Point"}
}