{
  "type": "Feature",
  "properties": {
    "addr:full":"27 Bath St Parnell  Auckland Auckland",
    "addr:housenumber":"27",
    "addr:street":"Bath St",
    "iso:country":"NZ",
    "sg:address":"27 Bath St Parnell ",
    "sg:city":"Auckland",
    "sg:classifiers":[
        {
            "category":"Wholesale",
            "subcategory":"Meat",
            "type":"Manufacturing & Wholesale Goods"
        }
    ],
    "sg:phone":"+64 9-307 3115",
    "sg:province":"Auckland",
    "sg:tags":[
        "food",
        "distributor",
        "drink",
        "meats"
    ],
    "wof:name":"Advance Marketing Ltd",
    "wof:placetype":"venue"
},
  "geometry": {"coordinates":[174.77900700000001,-36.851868],"type":"Point"}
}