{
  "type": "Feature",
  "properties": {
    "addr:full":"68 Hokianga Rd  Dargaville Northland",
    "addr:housenumber":"68",
    "addr:street":"Hokianga Rd",
    "iso:country":"NZ",
    "sg:address":"68 Hokianga Rd ",
    "sg:city":"Dargaville",
    "sg:classifiers":[
        {
            "category":"Sports & Exercise",
            "subcategory":"Sports Center",
            "type":"Entertainment"
        }
    ],
    "sg:phone":"+64 9-438 2229",
    "sg:province":"Northland",
    "sg:tags":[
        "repair",
        "piano",
        "music",
        "leisure",
        "tuner"
    ],
    "wof:name":"Chris Davidson Piano Tuner",
    "wof:placetype":"venue"
},
  "geometry": {"coordinates":[173.86338799999999,-35.937065],"type":"Point"}
}