{
  "type": "Feature",
  "properties": {
    "iso:country":"NZ",
    "sg:address":"179 McLeod Rd Te Atatu ",
    "sg:city":"Auckland",
    "sg:orig_category":"Clothing And Fabric: Fabric: Tanners/Tanners Supplies",
    "sg:phone":"+64 9-838 4991",
    "sg:province":"Auckland",
    "wof:name":"Shamrock Group Ltd",
    "wof:placetype":"venue"
},
  "geometry": {"coordinates":[174.649887,-36.845284],"type":"Point"}
}