{
  "type": "Feature",
  "properties": {
    "addr:full":"148 Queen St  Levin Manawatu-Wanganui",
    "addr:housenumber":"148",
    "addr:street":"Queen St",
    "iso:country":"NZ",
    "sg:address":"148 Queen St ",
    "sg:city":"Levin",
    "sg:classifiers":[
        {
            "category":"Shopping",
            "subcategory":"Crafts & Fabrics",
            "type":"Retail Goods"
        }
    ],
    "sg:phone":"+64 6-368 2058",
    "sg:province":"Manawatu-Wanganui",
    "sg:tags":[
        "clothing"
    ],
    "sg:website":"http://www.kiwiconnect.co.nz/alison",
    "wof:name":"Alison's Knitted Toys",
    "wof:placetype":"venue"
},
  "geometry": {"coordinates":[175.286652,-40.621895],"type":"Point"}
}