{
  "type": "Feature",
  "properties": {
    "addr:full":"Pall Mall Arc 102 Dee St  Invercargill Southland",
    "addr:housenumber":"102",
    "addr:street":"Pall Mall Arc;Dee St",
    "iso:country":"NZ",
    "sg:address":"Pall Mall Arc 102 Dee St ",
    "sg:city":"Invercargill",
    "sg:classifiers":[
        {
            "category":"Professional",
            "subcategory":"Art Services",
            "type":"Services"
        }
    ],
    "sg:phone":"+64 3-218 2344",
    "sg:province":"Southland",
    "sg:tags":[
        "picture",
        "arts",
        "sport",
        "framing",
        "leisure"
    ],
    "wof:name":"Framework",
    "wof:placetype":"venue"
},
  "geometry": {"coordinates":[168.35217299999999,-46.411854],"type":"Point"}
}