{
  "type": "Feature",
  "properties": {
    "addr:full":"1 Marine Pde Mt  Maunganui Bay of Plenty",
    "addr:housenumber":"1",
    "addr:street":"Marine Pde;Maunganui Bay",
    "iso:country":"NZ",
    "sg:address":"1 Marine Pde Mt ",
    "sg:city":"Maunganui",
    "sg:classifiers":[
        {
            "category":"Ice Cream",
            "type":"Food & Drink"
        }
    ],
    "sg:phone":"+64 7-574 9690",
    "sg:province":"Bay of Plenty",
    "sg:tags":[
        "-"
    ],
    "wof:name":"Oceanside Ice-Cream Parlour",
    "wof:placetype":"venue"
},
  "geometry": {"coordinates":[176.180893,-37.632938],"type":"Point"}
}