{
  "type": "Feature",
  "properties": {
    "addr:full":"Three Mile Bush Rd Kamo PO Box 518  Whangarei Northland",
    "addr:housenumber":"po box 518",
    "addr:street":"Three Mile Bush Rd",
    "iso:country":"NZ",
    "sg:address":"Three Mile Bush Rd Kamo PO Box 518 ",
    "sg:city":"Whangarei",
    "sg:classifiers":[
        {
            "category":"Manufacturing",
            "subcategory":"Glass & Minerals",
            "type":"Manufacturing & Wholesale Goods"
        }
    ],
    "sg:phone":"+64 9-435 2616",
    "sg:province":"Northland",
    "sg:tags":[
        "raw",
        "industrial",
        "quarry",
        "materials"
    ],
    "wof:name":"Kamo Scoria",
    "wof:placetype":"venue"
},
  "geometry": {"coordinates":[174.29367099999999,-35.686363],"type":"Point"}
}