{
  "type": "Feature",
  "properties": {
    "addr:full":"85 Bremworth Ave  Hamilton Waikato",
    "addr:housenumber":"85",
    "addr:street":"Bremworth Ave",
    "iso:country":"NZ",
    "sg:address":"85 Bremworth Ave ",
    "sg:city":"Hamilton",
    "sg:classifiers":[
        {
            "category":"Farming",
            "subcategory":"Fish & Marine Products",
            "type":"Manufacturing & Wholesale Goods"
        }
    ],
    "sg:phone":"+64 7-847 7443",
    "sg:province":"Waikato",
    "sg:tags":[
        "equipment",
        "medical",
        "health",
        "products",
        "beauty"
    ],
    "wof:name":"Dental & Medical Servicing",
    "wof:placetype":"venue"
},
  "geometry": {"coordinates":[175.23545799999999,-37.798306],"type":"Point"}
}