{
  "type": "Feature",
  "properties": {
    "iso:country":"NZ",
    "sg:address":"20i Sylvia Park Road, Mt Wellington ",
    "sg:city":"Auckland",
    "sg:classifiers":[
        {
            "category":"Retail",
            "subcategory":"Auto Repair",
            "type":"Services"
        }
    ],
    "sg:phone":"+64 9-573 1330",
    "sg:province":"Auckland",
    "sg:tags":[
        "automotive",
        "absorber",
        "shock",
        "servicing"
    ],
    "wof:name":"Automotive Drive-Line Ltd",
    "wof:placetype":"venue"
},
  "geometry": {"coordinates":[174.834427,-36.924309],"type":"Point"}
}