{
  "type": "Feature",
  "properties": {
    "iso:country":"NZ",
    "sg:address":"55 Cobham Rd ",
    "sg:city":"Kerikeri",
    "sg:classifiers":[
        {
            "category":"Retail",
            "subcategory":"Auto Repair",
            "type":"Services"
        }
    ],
    "sg:phone":"+64 9-407 6627",
    "sg:province":"Northland",
    "sg:tags":[
        "automotive",
        "servicing"
    ],
    "wof:name":"Ron Kelly Automotive Ltd",
    "wof:placetype":"venue"
},
  "geometry": {"coordinates":[173.94973754879999,-35.228263855],"type":"Point"}
}