{
  "type": "Feature",
  "properties": {
    "iso:country":"NZ",
    "sg:address":"42 Tahunanui Dve ",
    "sg:city":"Nelson",
    "sg:classifiers":[
        {
            "category":"Autos & Motor Vehicles",
            "subcategory":"Automobile Sales",
            "type":"Retail Goods"
        }
    ],
    "sg:phone":"+64 800 500 569",
    "sg:province":"Nelson",
    "sg:tags":[
        "home",
        "caravan",
        "leasing",
        "automotive"
    ],
    "wof:name":"Tahuna Caravans",
    "wof:placetype":"venue"
},
  "geometry": {"coordinates":[173.283966,-41.27227],"type":"Point"}
}