{
  "type": "Feature",
  "properties": {
    "addr:full":"42 Walton St  Whangarei Northland",
    "addr:housenumber":"42",
    "addr:street":"Walton St",
    "iso:country":"NZ",
    "sg:address":"42 Walton St ",
    "sg:city":"Whangarei",
    "sg:orig_category":"Shopping: Retail Stores: Books: Books - Secondhand",
    "sg:phone":"+64 9-438 5481",
    "sg:province":"Northland",
    "wof:name":"Hard to Find (But worth the effort) Quality Secondhand Books 'Piggery' Bookshop Ltd",
    "wof:placetype":"venue"
},
  "geometry": {"coordinates":[174.31994599999999,-35.727474],"type":"Point"}
}