{
  "type": "Feature",
  "properties": {
    "iso:country":"NZ",
    "sg:address":"4 James St Mangere East ",
    "sg:city":"Auckland",
    "sg:orig_category":"Health And Beauty: Medical: Hospitals",
    "sg:phone":"+64 9-256 0092",
    "sg:province":"Auckland",
    "wof:name":"Culverden Retirement Centre",
    "wof:placetype":"venue"
},
  "geometry": {"coordinates":[174.82029700000001,-36.969982],"type":"Point"}
}