{
  "type": "Feature",
  "properties": {
    "addr:full":"96 Queen St  Masterton Wellington",
    "addr:housenumber":"96",
    "addr:street":"Queen St",
    "iso:country":"NZ",
    "sg:address":"96 Queen St ",
    "sg:city":"Masterton",
    "sg:classifiers":[
        {
            "category":"Communications",
            "subcategory":"Radio Station",
            "type":"Services"
        }
    ],
    "sg:phone":"+64 6-378 0255",
    "sg:province":"Wellington",
    "sg:tags":[
        "broadcasting"
    ],
    "wof:name":"Arrow FM",
    "wof:placetype":"venue"
},
  "geometry": {"coordinates":[175.66213999999999,-40.949314],"type":"Point"}
}