{
  "type": "Feature",
  "properties": {
    "iso:country":"NZ",
    "sg:address":"76 Tennyson St ",
    "sg:city":"Napier",
    "sg:orig_category":"Shopping: Hobbies And Games: Handcrafts",
    "sg:phone":"+64 6-835 4488",
    "sg:province":"Hawke's Bay",
    "wof:name":"St Beads Limited",
    "wof:placetype":"venue"
},
  "geometry": {"coordinates":[-80.588562,38.790821],"type":"Point"}
}