{
  "type": "Feature",
  "properties": {
    "addr:full":"47 Tanner St Woolston  Christchurch Canterbury",
    "addr:housenumber":"47",
    "addr:street":"Tanner St",
    "iso:country":"NZ",
    "sg:address":"47 Tanner St Woolston ",
    "sg:city":"Christchurch",
    "sg:classifiers":[
        {
            "category":"Sports & Exercise",
            "subcategory":"Swimming Pool",
            "type":"Entertainment"
        }
    ],
    "sg:phone":"+64 3-389 9135",
    "sg:province":"Canterbury",
    "sg:tags":[
        "kayak",
        "shopping",
        "canoe",
        "sports",
        "water",
        "retailers"
    ],
    "wof:name":"Action Fibreglass",
    "wof:placetype":"venue"
},
  "geometry": {"coordinates":[172.67936700000001,-43.558189],"type":"Point"}
}