{
  "type": "Feature",
  "properties": {
    "addr:full":"Terracehaven Chapel 697 Main St Palmerston  Palmerston North Manawatu-Wanganui",
    "addr:housenumber":"697",
    "addr:street":"Main St",
    "iso:country":"NZ",
    "sg:address":"Terracehaven Chapel 697 Main St Palmerston ",
    "sg:city":"Palmerston North",
    "sg:classifiers":[
        {
            "category":"Banks & Credit Unions",
            "subcategory":"Investment Brokerage",
            "type":"Services"
        }
    ],
    "sg:phone":"+64 6-355 2529",
    "sg:province":"Manawatu-Wanganui",
    "sg:tags":[
        "director",
        "funeral",
        "arrangements"
    ],
    "sg:website":"http://www.funeral-link.co.nz/Clients/Robert_cotton.htm",
    "wof:name":"Cotton Robert J & Sons Ltd",
    "wof:placetype":"venue"
},
  "geometry": {"coordinates":[175.611481,-40.357418],"type":"Point"}
}