{
  "type": "Feature",
  "properties": {
    "addr:full":"479 Gladstone Rd  Gisborne Gisborne",
    "addr:housenumber":"479",
    "addr:street":"Gladstone Rd",
    "iso:country":"NZ",
    "sg:address":"479 Gladstone Rd ",
    "sg:city":"Gisborne",
    "sg:classifiers":[
        {
            "category":"Travel",
            "subcategory":"Hotels & Motels",
            "type":"Entertainment"
        }
    ],
    "sg:phone":"+64 6-867 7157",
    "sg:province":"Gisborne",
    "sg:tags":[
        "lodge",
        "tourism",
        "accommodation"
    ],
    "sg:website":"http://www.teal.co.nz",
    "wof:name":"Teal Motor Lodge",
    "wof:placetype":"venue"
},
  "geometry": {"coordinates":[178.013428,-38.6576],"type":"Point"}
}