{
  "type": "Feature",
  "properties": {
    "addr:full":"25 Anzac Rd Browns Bay  Auckland Auckland",
    "addr:housenumber":"25",
    "addr:street":"Anzac Rd",
    "iso:country":"NZ",
    "sg:address":"25 Anzac Rd Browns Bay ",
    "sg:city":"Auckland",
    "sg:classifiers":[
        {
            "category":"Bars & Pubs",
            "subcategory":"Wine Bar",
            "type":"Food & Drink"
        }
    ],
    "sg:phone":"+64 9-478 5454",
    "sg:province":"Auckland",
    "sg:tags":[
        "wining",
        "dining",
        "cafe"
    ],
    "wof:name":"Coffee Club",
    "wof:placetype":"venue"
},
  "geometry": {"coordinates":[174.74697900000001,-36.716709],"type":"Point"}
}