{
  "type": "Feature",
  "properties": {
    "iso:country":"NZ",
    "sg:address":"Level 2, Bledisloe Building 24 Wellesley St West Auckland, Central ",
    "sg:city":"Auckland",
    "sg:classifiers":[
        {
            "category":"Education",
            "subcategory":"Special Training",
            "type":"Public Place"
        }
    ],
    "sg:phone":"+64 9-377 0518",
    "sg:province":"Auckland",
    "sg:website":"http://www.yellowpages.co.nz/for/tricias/dp38163.html",
    "wof:name":"New Zealand Hospitality Management Academy Ltd",
    "wof:placetype":"venue"
},
  "geometry": {"coordinates":[-119.104576,36.597755],"type":"Point"}
}