{
  "type": "Feature",
  "properties": {
    "addr:full":"266 Maunu Rd  Whangarei Northland",
    "addr:housenumber":"266",
    "addr:street":"Maunu Rd",
    "iso:country":"NZ",
    "sg:address":"266 Maunu Rd ",
    "sg:city":"Whangarei",
    "sg:classifiers":[
        {
            "category":"Building & Trades",
            "subcategory":"Construction",
            "type":"Services"
        }
    ],
    "sg:phone":"+64 21 965 152",
    "sg:province":"Northland",
    "sg:tags":[
        "home",
        "hire",
        "garden"
    ],
    "wof:name":"Northland Computer Rentals",
    "wof:placetype":"venue"
},
  "geometry": {"coordinates":[174.312073,-35.730747],"type":"Point"}
}