{
  "type": "Feature",
  "properties": {
    "iso:country":"NZ",
    "sg:address":"Hansen Rd ",
    "sg:city":"Gisborne",
    "sg:orig_category":"Transport: Transportation: Transport Operators",
    "sg:phone":"+64 6-867 3859",
    "sg:province":"Gisborne",
    "wof:name":"Brian Richards",
    "wof:placetype":"venue"
},
  "geometry": {"coordinates":[177.989746,-38.632545],"type":"Point"}
}