{
  "type": "Feature",
  "properties": {
    "iso:country":"NZ",
    "sg:address":"Bishopdale Mall ",
    "sg:city":"Christchurch",
    "sg:classifiers":[
        {
            "category":"Education",
            "subcategory":"University",
            "type":"Public Place"
        }
    ],
    "sg:phone":"+64 3-359 1525",
    "sg:province":"Canterbury",
    "sg:tags":[
        "training",
        "instruction",
        "language"
    ],
    "wof:name":"Alpha Educational Institute",
    "wof:placetype":"venue"
},
  "geometry": {"coordinates":[172.586075,-43.487144],"type":"Point"}
}