{
  "type": "Feature",
  "properties": {
    "addr:full":"159-161 Gt South Rd Greenlane  Auckland Auckland",
    "addr:housenumber":"159-161",
    "addr:street":"Gt South Rd",
    "iso:country":"NZ",
    "sg:address":"159-161 Gt South Rd Greenlane ",
    "sg:city":"Auckland",
    "sg:classifiers":[
        {
            "category":"Travel",
            "subcategory":"Hotels & Motels",
            "type":"Entertainment"
        }
    ],
    "sg:phone":"+64 9-524 7988",
    "sg:province":"Auckland",
    "sg:tags":[
        "tourism",
        "accommodation"
    ],
    "sg:website":"http://www.yellowpages.co.nz/for/royalparklodge/dp25006.html",
    "wof:name":"Royal Park Lodge",
    "wof:placetype":"venue"
},
  "geometry": {"coordinates":[174.790527,-36.888039],"type":"Point"}
}