{
  "type": "Feature",
  "properties": {
    "addr:full":"28 Maria Pl  Wanganui Manawatu-Wanganui",
    "addr:housenumber":"28",
    "addr:street":"Maria Pl",
    "iso:country":"NZ",
    "sg:address":"28 Maria Pl ",
    "sg:city":"Wanganui",
    "sg:classifiers":[
        {
            "category":"Personal",
            "subcategory":"Adult",
            "type":"Services"
        }
    ],
    "sg:phone":"+64 6-345 9020",
    "sg:province":"Manawatu-Wanganui",
    "sg:tags":[
        "sport",
        "parlour",
        "massage",
        "leisure"
    ],
    "wof:name":"Club 28",
    "wof:placetype":"venue"
},
  "geometry": {"coordinates":[175.051041,-39.933296],"type":"Point"}
}