{
  "type": "Feature",
  "properties": {
    "addr:full":"50 Reece Cre  Wanaka Otago",
    "addr:housenumber":"50",
    "addr:street":"Reece Cre",
    "iso:country":"NZ",
    "sg:address":"50 Reece Cre ",
    "sg:city":"Wanaka",
    "sg:orig_category":"Transport: Distribution - General: Distributors",
    "sg:phone":"+64 3-443 4181",
    "sg:province":"Otago",
    "wof:name":"Wanaka Wholesale Market",
    "wof:placetype":"venue"
},
  "geometry": {"coordinates":[169.143326,-44.690105],"type":"Point"}
}