{
  "type": "Feature",
  "properties": {
    "iso:country":"NZ",
    "sg:address":"106 Ridgway St ",
    "sg:city":"Wanganui",
    "sg:classifiers":[
        {
            "category":"Manufacturing",
            "subcategory":"Metals",
            "type":"Manufacturing & Wholesale Goods"
        }
    ],
    "sg:phone":"+64 6-347 1824",
    "sg:province":"Manawatu-Wanganui",
    "sg:tags":[
        "-",
        "engineering",
        "industrial",
        "sheet",
        "engineer"
    ],
    "wof:name":"Whiteout Maintenance Services",
    "wof:placetype":"venue"
},
  "geometry": {"coordinates":[175.051376,-39.936253],"type":"Point"}
}