{
  "type": "Feature",
  "properties": {
    "iso:country":"NZ",
    "sg:address":"356 Thames Highway ",
    "sg:city":"Oamaru",
    "sg:orig_category":"Shopping: Retail Stores: Secondhand Dealers",
    "sg:phone":"+64 3-437 2003",
    "sg:province":"Otago",
    "wof:name":"Oamaru Trade In Centre",
    "wof:placetype":"venue"
},
  "geometry": {"coordinates":[170.98168899999999,-45.081223],"type":"Point"}
}