{
  "type": "Feature",
  "properties": {
    "iso:country":"NZ",
    "sg:address":"Hamilton ",
    "sg:city":"Hamilton",
    "sg:classifiers":[
        {
            "category":"Marine",
            "type":"Transportation"
        }
    ],
    "sg:phone":"+64 7-846 0490",
    "sg:province":"Waikato",
    "sg:tags":[
        "transport",
        "boat"
    ],
    "sg:website":"http://www.yellowpages.co.nz/pages/108086817/dp58863.html",
    "wof:name":"New Zealand Van Lines Ltd",
    "wof:placetype":"venue"
},
  "geometry": {"coordinates":[175.282578,-37.788349],"type":"Point"}
}