{
  "type": "Feature",
  "properties": {
    "iso:country":"NZ",
    "sg:address":"360 Devon St East New ",
    "sg:city":"Plymouth",
    "sg:classifiers":[
        {
            "category":"Insurance",
            "subcategory":"Health Insurance",
            "type":"Services"
        }
    ],
    "sg:phone":"+64 6-757 2257",
    "sg:province":"Taranaki",
    "sg:tags":[
        "beauty"
    ],
    "wof:name":"Devon House Of Beauty Therapy",
    "wof:placetype":"venue"
},
  "geometry": {"coordinates":[-116.819725,43.97221],"type":"Point"}
}