{
  "type": "Feature",
  "properties": {
    "iso:country":"NZ",
    "sg:address":"3 Hardy St Johnsonville ",
    "sg:city":"Wellington",
    "sg:classifiers":[
        {
            "category":"Farming",
            "subcategory":"Farm",
            "type":"Manufacturing & Wholesale Goods"
        }
    ],
    "sg:phone":"+64 4-939 0191",
    "sg:province":"Wellington",
    "sg:website":"http://www.yellowpages.co.nz/for/mctsl/dp24234.html",
    "wof:name":"Microbiology Consultancy & Testing Services Ltd",
    "wof:placetype":"venue"
},
  "geometry": {"coordinates":[174.81257600000001,-41.22102],"type":"Point"}
}