{
  "type": "Feature",
  "properties": {
    "iso:country":"NZ",
    "sg:address":"43 Queen St ",
    "sg:city":"Cambridge",
    "sg:classifiers":[
        {
            "category":"Shopping",
            "subcategory":"Thrift Store",
            "type":"Retail Goods"
        }
    ],
    "sg:phone":"+64 7-823 1653",
    "sg:province":"Waikato",
    "sg:tags":[
        "-",
        "clothing",
        "secondhand",
        "fabric"
    ],
    "wof:name":"Union Parish Op Shop",
    "wof:placetype":"venue"
},
  "geometry": {"coordinates":[-85.134209,39.814236],"type":"Point"}
}