{
  "type": "Feature",
  "properties": {
    "iso:country":"NZ",
    "sg:address":"10 Fleur La ",
    "sg:city":"Akaroa",
    "sg:classifiers":[
        {
            "category":"Utilities",
            "subcategory":"Refuse",
            "type":"Services"
        }
    ],
    "sg:phone":"+64 3-304 7463",
    "sg:province":"Canterbury",
    "sg:tags":[
        "bin",
        "hire",
        "garden",
        "cleaning",
        "rubbish",
        "home"
    ],
    "wof:name":"Akaroa Mini Skips",
    "wof:placetype":"venue"
},
  "geometry": {"coordinates":[172.965424,-43.811691],"type":"Point"}
}