{
  "type": "Feature",
  "properties": {
    "iso:country":"NZ",
    "sg:address":"49 Ottawa Rd Ngaio ",
    "sg:city":"Wellington",
    "sg:classifiers":[
        {
            "category":"Professional",
            "subcategory":"Detective & Security Services",
            "type":"Services"
        }
    ],
    "sg:phone":"+64 4-939 9531",
    "sg:province":"Wellington",
    "sg:tags":[
        "services",
        "automotive",
        "warrant",
        "fitness"
    ],
    "wof:name":"Autostop Group Ltd",
    "wof:placetype":"venue"
},
  "geometry": {"coordinates":[174.774445,-41.248493],"type":"Point"}
}