{
  "type": "Feature",
  "properties": {
    "iso:country":"NZ",
    "sg:address":"202 West Coast Rd Glen Eden ",
    "sg:city":"Auckland",
    "sg:classifiers":[
        {
            "category":"Shopping",
            "subcategory":"Gifts & Souvenirs",
            "type":"Retail Goods"
        }
    ],
    "sg:phone":"+64 9-818 9124",
    "sg:province":"Auckland",
    "sg:tags":[
        "trophy",
        "award"
    ],
    "wof:name":"Trophy Key & Cobble Limited",
    "wof:placetype":"venue"
},
  "geometry": {"coordinates":[174.652542,-36.910595],"type":"Point"}
}