{
  "type": "Feature",
  "properties": {
    "iso:country":"NZ",
    "sg:address":"Pukete Industrial Estate Maui St ",
    "sg:city":"Hamilton",
    "sg:classifiers":[
        {
            "category":"Wholesale",
            "subcategory":"Machinery & Supplies",
            "type":"Manufacturing & Wholesale Goods"
        }
    ],
    "sg:phone":"+64 7-849 4839",
    "sg:province":"Waikato",
    "sg:tags":[
        "equipment",
        "industrial"
    ],
    "sg:website":"http://www.yellowpages.co.nz/pages/102745788/dp39503.html",
    "wof:name":"TRT-Tidd Ross Todd Ltd",
    "wof:placetype":"venue"
},
  "geometry": {"coordinates":[175.276993,-37.783215],"type":"Point"}
}