{
  "type": "Feature",
  "properties": {
    "addr:full":"New Gallery Building Cnr Lorne & Wellesley Sts, Auckland Central  Auckland Auckland",
    "addr:street":"Cnr Lorne & Wellesley",
    "iso:country":"NZ",
    "sg:address":"New Gallery Building Cnr Lorne & Wellesley Sts, Auckland Central ",
    "sg:city":"Auckland",
    "sg:classifiers":[
        {
            "category":"Arts & Performance",
            "subcategory":"Art Gallery",
            "type":"Entertainment"
        }
    ],
    "sg:phone":"+64 9-358 1660",
    "sg:province":"Auckland",
    "sg:tags":[
        "arts",
        "sport",
        "leisure"
    ],
    "wof:name":"Newton Andrews",
    "wof:placetype":"venue"
},
  "geometry": {"coordinates":[174.76454200000001,-36.848358],"type":"Point"}
}