{
  "type": "Feature",
  "properties": {
    "addr:full":"24 Coleridge St Sydenham  Christchurch Canterbury",
    "addr:housenumber":"24",
    "addr:street":"Coleridge St",
    "iso:country":"NZ",
    "sg:address":"24 Coleridge St Sydenham ",
    "sg:city":"Christchurch",
    "sg:classifiers":[
        {
            "category":"Home & Garden",
            "subcategory":"Building Materials",
            "type":"Retail Goods"
        }
    ],
    "sg:phone":"+64 3-379 2400",
    "sg:province":"Canterbury",
    "sg:tags":[
        "fittings",
        "staircase",
        "handrail"
    ],
    "wof:name":"Tetral Industries Ltd",
    "wof:placetype":"venue"
},
  "geometry": {"coordinates":[172.64056400000001,-43.545948],"type":"Point"}
}