{
  "type": "Feature",
  "properties": {
    "addr:full":"6 Nandina Ave East Tamaki  Auckland Auckland",
    "addr:housenumber":"6",
    "addr:street":"Nandina Ave",
    "iso:country":"NZ",
    "sg:address":"6 Nandina Ave East Tamaki ",
    "sg:city":"Auckland",
    "sg:orig_category":"Farming: Supplies: Veterinary Supplies",
    "sg:phone":"+64 9-920 4440",
    "sg:province":"Auckland",
    "wof:name":"Provet NZ Pty Ltd",
    "wof:placetype":"venue"
},
  "geometry": {"coordinates":[174.90034499999999,-36.930222],"type":"Point"}
}