{
  "type": "Feature",
  "properties": {
    "iso:country":"NZ",
    "sg:address":"PO Box 31751 ",
    "sg:city":"Auckland",
    "sg:classifiers":[
        {
            "category":"Building & Trades",
            "subcategory":"Pest Control",
            "type":"Services"
        }
    ],
    "sg:phone":"+64 800 472 269",
    "sg:province":"Auckland",
    "sg:tags":[
        "home",
        "garden"
    ],
    "wof:name":"Pest Control Association of NZ Inc",
    "wof:placetype":"venue"
},
  "geometry": {"coordinates":[-119.10457599999999,36.597755],"type":"Point"}
}