{
  "type": "Feature",
  "properties": {
    "addr:full":"69 Moehau St Te  Puke Bay of Plenty",
    "addr:housenumber":"69",
    "addr:street":"Moehau St",
    "iso:country":"NZ",
    "sg:address":"69 Moehau St Te ",
    "sg:city":"Puke",
    "sg:classifiers":[
        {
            "category":"Social Services",
            "subcategory":"Retirement Home",
            "type":"Services"
        }
    ],
    "sg:phone":"+64 7-573 7317",
    "sg:province":"Bay of Plenty",
    "sg:tags":[
        "elderly",
        "convalescent",
        "garden",
        "rest",
        "care"
    ],
    "wof:name":"Carter House",
    "wof:placetype":"venue"
},
  "geometry": {"coordinates":[176.32269299999999,-37.788277],"type":"Point"}
}