{
  "type": "Feature",
  "properties": {
    "iso:country":"NZ",
    "sg:address":"75 North Avon Rd ",
    "sg:city":"Christchurch",
    "sg:orig_category":"Shopping: Retail Stores: Florists",
    "sg:phone":"+64 3-381 1177",
    "sg:province":"Canterbury",
    "sg:website":"http://www.tallpoppiesflorist.co.nz",
    "wof:name":"Tall Poppies Florist",
    "wof:placetype":"venue"
},
  "geometry": {"coordinates":[-76.537834,37.605659],"type":"Point"}
}