{
  "type": "Feature",
  "properties": {
    "addr:full":"399 Gloucester St Linwood  Christchurch Canterbury",
    "addr:housenumber":"399",
    "addr:street":"Gloucester St",
    "iso:country":"NZ",
    "sg:address":"399 Gloucester St Linwood ",
    "sg:city":"Christchurch",
    "sg:classifiers":[
        {
            "category":"Shopping",
            "subcategory":"Crafts & Fabrics",
            "type":"Retail Goods"
        }
    ],
    "sg:phone":"+64 3-980 0767",
    "sg:province":"Canterbury",
    "sg:tags":[
        "sport",
        "art",
        "leisure",
        "hobbies"
    ],
    "wof:name":"African Arts & Jewellery",
    "wof:placetype":"venue"
},
  "geometry": {"coordinates":[172.65419,-43.529701],"type":"Point"}
}