{
  "type": "Feature",
  "properties": {
    "iso:country":"NZ",
    "sg:address":"93 East Tamaki Rd Papatoetoe ",
    "sg:city":"Auckland",
    "sg:orig_category":"Farming: Services: Veterinarians",
    "sg:phone":"+64 9-278 5343",
    "sg:province":"Auckland",
    "wof:name":"Merchant S C",
    "wof:placetype":"venue"
},
  "geometry": {"coordinates":[174.864441,-36.966492],"type":"Point"}
}