{
  "type": "Feature",
  "properties": {
    "iso:country":"NZ",
    "sg:address":"38 Sincliar Rd Hunua ",
    "sg:city":"Auckland",
    "sg:classifiers":[
        {
            "category":"Shopping",
            "subcategory":"Stationery & Office Supplies",
            "type":"Retail Goods"
        }
    ],
    "sg:phone":"+64 9-292 4948",
    "sg:province":"Auckland",
    "sg:tags":[
        "supplies",
        "educational",
        "material",
        "education",
        "training"
    ],
    "wof:name":"InfoMedia",
    "wof:placetype":"venue"
},
  "geometry": {"coordinates":[-119.104576,36.597755],"type":"Point"}
}