{
  "type": "Feature",
  "properties": {
    "iso:country":"NZ",
    "sg:address":"193 High St Motueka ",
    "sg:city":"Nelson",
    "sg:classifiers":[
        {
            "category":"Travel",
            "subcategory":"Travel Agent",
            "type":"Entertainment"
        }
    ],
    "sg:phone":"+64 3-528 1122",
    "sg:province":"Nelson",
    "sg:tags":[
        "tourism",
        "broker"
    ],
    "sg:website":"http://www.KroupaAndBourke.HouseOfTravel.co.nz",
    "wof:name":"Kroupa & Bourke House Of Travel",
    "wof:placetype":"venue"
},
  "geometry": {"coordinates":[173.013443,-41.108101],"type":"Point"}
}