{
  "type": "Feature",
  "properties": {
    "addr:full":"PO Box 576  Paraparaumu Wellington",
    "addr:housenumber":"po",
    "addr:street":"Box 576",
    "iso:country":"NZ",
    "sg:address":"PO Box 576 ",
    "sg:city":"Paraparaumu",
    "sg:classifiers":[
        {
            "category":"Home & Garden",
            "subcategory":"Garden Supply",
            "type":"Retail Goods"
        }
    ],
    "sg:phone":"+64 800 288 333",
    "sg:province":"Wellington",
    "sg:tags":[
        "products",
        "lawn",
        "gardening",
        "turf"
    ],
    "wof:name":"Professor Turf",
    "wof:placetype":"venue"
},
  "geometry": {"coordinates":[175.00799599999999,-40.910465],"type":"Point"}
}