{
  "type": "Feature",
  "properties": {
    "addr:full":"137 Pascoe St Stoke  Nelson Nelson",
    "addr:housenumber":"137",
    "addr:street":"Pascoe St",
    "iso:country":"NZ",
    "sg:address":"137 Pascoe St Stoke ",
    "sg:city":"Nelson",
    "sg:orig_category":"Transport: Transportation: Furniture Removal/Packers",
    "sg:phone":"+64 3-547 6884",
    "sg:province":"Nelson",
    "wof:name":"Nelson Furniture Removals Ltd",
    "wof:placetype":"venue"
},
  "geometry": {"coordinates":[173.23419200000001,-41.312859],"type":"Point"}
}