{
  "type": "Feature",
  "properties": {
    "addr:full":"7 Purnell St  Wanganui Manawatu-Wanganui",
    "addr:housenumber":"7",
    "addr:street":"Purnell St",
    "iso:country":"NZ",
    "sg:address":"7 Purnell St ",
    "sg:city":"Wanganui",
    "sg:classifiers":[
        {
            "category":"Autos & Motor Vehicles",
            "subcategory":"Automobile Sales",
            "type":"Retail Goods"
        }
    ],
    "sg:phone":"+64 6-347 7565",
    "sg:province":"Manawatu-Wanganui",
    "sg:tags":[
        "car",
        "-used",
        "leasing",
        "truck",
        "automotive"
    ],
    "sg:website":"http://www.customerdirect.co.nz",
    "wof:name":"City Cars Wanganui",
    "wof:placetype":"venue"
},
  "geometry": {"coordinates":[175.045074,-39.935417],"type":"Point"}
}