{
  "type": "Feature",
  "properties": {
    "addr:full":"Taonui Airfield  Feilding Manawatu-Wanganui",
    "iso:country":"NZ",
    "sg:address":"Taonui Airfield ",
    "sg:city":"Feilding",
    "sg:orig_category":"Farming: Services: Top Dressing",
    "sg:phone":"+64 6-323 7235",
    "sg:province":"Manawatu-Wanganui",
    "wof:name":"Rural Air Services 1986 Ltd",
    "wof:placetype":"venue"
},
  "geometry": {"coordinates":[175.60560599999999,-40.261379],"type":"Point"}
}