{
  "type": "Feature",
  "properties": {
    "iso:country":"NZ",
    "sg:address":"26 Rutherford St Melling Lower ",
    "sg:city":"Hutt",
    "sg:classifiers":[
        {
            "category":"Home & Garden",
            "subcategory":"Kitchen Supply",
            "type":"Retail Goods"
        }
    ],
    "sg:phone":"+64 4-566 6415",
    "sg:province":"Wellington",
    "sg:tags":[
        "shop",
        "pet",
        "pets"
    ],
    "wof:name":"Animates",
    "wof:placetype":"venue"
},
  "geometry": {"coordinates":[174.908661,-41.205036],"type":"Point"}
}