{
  "type": "Feature",
  "properties": {
    "addr:full":"2 Saunders Rd Mosgiel  Dunedin Otago",
    "addr:housenumber":"2",
    "addr:street":"Saunders Rd",
    "iso:country":"NZ",
    "sg:address":"2 Saunders Rd Mosgiel ",
    "sg:city":"Dunedin",
    "sg:orig_category":"Sports And Leisure: General: Clubs",
    "sg:phone":"+64 3-489 7024",
    "sg:province":"Otago",
    "wof:name":"North Taieri Tavern",
    "wof:placetype":"venue"
},
  "geometry": {"coordinates":[170.35960399999999,-45.853718],"type":"Point"}
}