{
  "type": "Feature",
  "properties": {
    "iso:country":"NZ",
    "sg:address":"64 a Windermere Rd Papanui ",
    "sg:city":"Christchurch",
    "sg:orig_category":"Health And Beauty: Specialists: Podiatrists",
    "sg:phone":"+64 3-352 7565",
    "sg:province":"Canterbury",
    "wof:name":"Jenkins W G",
    "wof:placetype":"venue"
},
  "geometry": {"coordinates":[172.602493,-43.499634],"type":"Point"}
}