{
  "type": "Feature",
  "properties": {
    "iso:country":"NZ",
    "sg:address":"310 No 1 Rd Te ",
    "sg:city":"Puke",
    "sg:classifiers":[
        {
            "category":"Shopping",
            "subcategory":"Discount & Variety Stores",
            "type":"Retail Goods"
        }
    ],
    "sg:phone":"+64 7-573 8750",
    "sg:province":"Bay of Plenty",
    "sg:tags":[
        "storage",
        "cool"
    ],
    "wof:name":"Trevelyan's Pack & Cool Ltd",
    "wof:placetype":"venue"
},
  "geometry": {"coordinates":[176.33377100000001,-37.792152],"type":"Point"}
}