{
  "type": "Feature",
  "properties": {
    "addr:full":"94 Princes St Onehunga  Auckland Auckland",
    "addr:housenumber":"94",
    "addr:street":"Princes St",
    "iso:country":"NZ",
    "sg:address":"94 Princes St Onehunga ",
    "sg:city":"Auckland",
    "sg:classifiers":[
        {
            "category":"Retail",
            "subcategory":"Auto Repair",
            "type":"Services"
        }
    ],
    "sg:phone":"+64 9-634 1071",
    "sg:province":"Auckland",
    "sg:tags":[
        "automotive",
        "panel",
        "servicing",
        "beater"
    ],
    "sg:website":"http://www.bumper.co.nz",
    "wof:name":"Bumper Replacements (NZ) Ltd",
    "wof:placetype":"venue"
},
  "geometry": {"coordinates":[174.79054300000001,-36.924522],"type":"Point"}
}