{
  "type": "Feature",
  "properties": {
    "addr:full":"16 Tavern Rd Silverdale  Auckland Auckland",
    "addr:housenumber":"16",
    "addr:street":"Tavern Rd",
    "iso:country":"NZ",
    "sg:address":"16 Tavern Rd Silverdale ",
    "sg:city":"Auckland",
    "sg:classifiers":[
        {
            "category":"Professional",
            "subcategory":"Engineering",
            "type":"Services"
        }
    ],
    "sg:phone":"+64 9-426 7636",
    "sg:province":"Auckland",
    "sg:tags":[
        "industrial"
    ],
    "sg:website":"http://www.yellowpages.co.nz/pages/202028588/dp48523.html",
    "wof:name":"Monocrane NZ",
    "wof:placetype":"venue"
},
  "geometry": {"coordinates":[174.67515599999999,-36.622166],"type":"Point"}
}