{
  "type": "Feature",
  "properties": {
    "addr:full":"6 Panorama Dve  Paraparaumu Wellington",
    "addr:housenumber":"6",
    "addr:street":"Panorama Dve",
    "iso:country":"NZ",
    "sg:address":"6 Panorama Dve ",
    "sg:city":"Paraparaumu",
    "sg:classifiers":[
        {
            "category":"Personal",
            "subcategory":"Beauty Salon",
            "type":"Services"
        }
    ],
    "sg:phone":"+64 9028559",
    "sg:province":"Wellington",
    "sg:tags":[
        "therapy",
        "health"
    ],
    "sg:website":"http://www.yellowpages.co.nz/pages/225803029/dp47963.html",
    "wof:name":"Woodcote Lodge Beauty Therapy",
    "wof:placetype":"venue"
},
  "geometry": {"coordinates":[175.005798,-40.924877],"type":"Point"}
}