{
  "type": "Feature",
  "properties": {
    "iso:country":"NZ",
    "sg:address":"550 Te Atatu Rd Te Atatu Peninsula ",
    "sg:city":"Auckland",
    "sg:orig_category":"Transport: Transportation: Postal Services",
    "sg:phone":"+64 9-834 9646",
    "sg:province":"Auckland",
    "wof:name":"Te Atatu Post Shop",
    "wof:placetype":"venue"
},
  "geometry": {"coordinates":[174.651581,-36.842327],"type":"Point"}
}