{
  "type": "Feature",
  "properties": {
    "addr:full":"PO Box 41137 St  Lukes",
    "addr:housenumber":"po box 41137",
    "iso:country":"NZ",
    "sg:address":"PO Box 41137 St ",
    "sg:city":"Lukes",
    "sg:orig_category":"Clothing And Fabric: Clothing: Uniforms",
    "sg:phone":"+64 800 929 272",
    "wof:name":"Career Classics",
    "wof:placetype":"venue"
},
  "geometry": {"coordinates":[174.728973,-36.877918],"type":"Point"}
}