{
  "type": "Feature",
  "properties": {
    "iso:country":"NZ",
    "sg:address":"90 Clyde St ",
    "sg:city":"Balclutha",
    "sg:classifiers":[
        {
            "category":"Retail",
            "subcategory":"Auto Repair",
            "type":"Services"
        }
    ],
    "sg:phone":"+64 3-418 2111",
    "sg:tags":[
        "automotive",
        "electric",
        "servicing"
    ],
    "wof:name":"Barclay Auto Electrical",
    "wof:placetype":"venue"
},
  "geometry": {"coordinates":[169.73457300000001,-46.239868],"type":"Point"}
}