{
  "type": "Feature",
  "properties": {
    "iso:country":"NZ",
    "sg:address":"R D 2 ",
    "sg:city":"Woodville",
    "sg:orig_category":"Education And Training: General: Schools",
    "sg:phone":"+64 6-376 5355",
    "wof:name":"Papatawa School",
    "wof:placetype":"venue"
},
  "geometry": {"coordinates":[-76.233643,43.818947],"type":"Point"}
}