{
  "type": "Feature",
  "properties": {
    "addr:full":"561 Kaikorai Valley Rd  Dunedin Otago",
    "addr:housenumber":"561",
    "addr:street":"Kaikorai Valley Rd",
    "iso:country":"NZ",
    "sg:address":"561 Kaikorai Valley Rd ",
    "sg:city":"Dunedin",
    "sg:classifiers":[
        {
            "category":"Social Services",
            "subcategory":"Retirement Home",
            "type":"Services"
        }
    ],
    "sg:phone":"+64 3-488 5961",
    "sg:province":"Otago",
    "sg:tags":[
        "automotive"
    ],
    "sg:website":"http://www.classicjaguar.co.nz",
    "wof:name":"Classic Jaguar Limousines",
    "wof:placetype":"venue"
},
  "geometry": {"coordinates":[170.462357,-45.889175],"type":"Point"}
}