{
  "type": "Feature",
  "properties": {
    "iso:country":"NZ",
    "sg:address":"172 Hereford St ",
    "sg:city":"Christchurch",
    "sg:orig_category":"Industrial: Packaging: Packaging - General",
    "sg:phone":"+64 3-365 5066",
    "sg:province":"Canterbury",
    "sg:website":"http://www.span-trust.co.nz",
    "wof:name":"SPAN Charitable Trust 1991 Vocational Centre",
    "wof:placetype":"venue"
},
  "geometry": {"coordinates":[-76.537834,37.605659],"type":"Point"}
}