{
  "type": "Feature",
  "properties": {
    "iso:country":"NZ",
    "sg:address":"89 Eatwell Ave ",
    "sg:city":"Paraparaumu",
    "sg:orig_category":"Clothing And Fabric: Clothing: Swimwear",
    "sg:phone":"+64 4-902 0889",
    "sg:province":"Wellington",
    "wof:name":"S.Swimwear",
    "wof:placetype":"venue"
},
  "geometry": {"coordinates":[174.993256,-40.893913],"type":"Point"}
}