{
  "type": "Feature",
  "properties": {
    "addr:full":"cnr Gasson & Kingsley Sts Sydenham  Christchurch Canterbury",
    "addr:street":"Cnr Gasson &;Sts",
    "iso:country":"NZ",
    "sg:address":"cnr Gasson & Kingsley Sts Sydenham ",
    "sg:city":"Christchurch",
    "sg:classifiers":[
        {
            "category":"Wholesale",
            "subcategory":"Auto Parts",
            "type":"Manufacturing & Wholesale Goods"
        }
    ],
    "sg:phone":"+64 3-366 7455",
    "sg:province":"Canterbury",
    "sg:tags":[
        "automotive",
        "supplies"
    ],
    "wof:name":"Scotts Motors (Chch) Ltd",
    "wof:placetype":"venue"
},
  "geometry": {"coordinates":[172.63748200000001,-43.547421],"type":"Point"}
}