{
  "type": "Feature",
  "properties": {
    "addr:full":"61 Rossiters Rd R D 2 Rangiora  Loburn",
    "addr:housenumber":"61;2",
    "addr:street":"Rossiters Rd R D",
    "iso:country":"NZ",
    "sg:address":"61 Rossiters Rd R D 2 Rangiora ",
    "sg:city":"Loburn",
    "sg:classifiers":[
        {
            "category":"Manufacturing",
            "subcategory":"Furniture",
            "type":"Manufacturing & Wholesale Goods"
        }
    ],
    "sg:phone":"+64 3-312 8738",
    "sg:tags":[
        "furniture/furnishings",
        "home",
        "garden",
        "manufacturer"
    ],
    "wof:name":"Loburn Furniture Ltd",
    "wof:placetype":"venue"
},
  "geometry": {"coordinates":[172.539917,-43.252686],"type":"Point"}
}