{
  "type": "Feature",
  "properties": {
    "iso:country":"NZ",
    "sg:address":"62 George St Palmerston ",
    "sg:city":"Palmerston North",
    "sg:orig_category":"Clothing And Fabric: Clothing: Women'S Fashions",
    "sg:phone":"+64 6-359 3933",
    "sg:province":"Manawatu-Wanganui",
    "wof:name":"Indigo Clothing",
    "wof:placetype":"venue"
},
  "geometry": {"coordinates":[175.60870399999999,-40.356632],"type":"Point"}
}