{
  "type": "Feature",
  "properties": {
    "iso:country":"NZ",
    "sg:address":"3 Wanganella Pl Lynfield ",
    "sg:city":"Auckland",
    "sg:classifiers":[
        {
            "category":"Shopping",
            "subcategory":"Computers & Home Electronics",
            "type":"Retail Goods"
        }
    ],
    "sg:phone":"+64 9-626 4615",
    "sg:province":"Auckland",
    "sg:tags":[
        "recording",
        "equipment",
        "sport",
        "music",
        "leisure"
    ],
    "wof:name":"Larry Killip Music",
    "wof:placetype":"venue"
},
  "geometry": {"coordinates":[174.716934,-36.926575],"type":"Point"}
}