{
  "type": "Feature",
  "properties": {
    "iso:country":"NZ",
    "sg:address":"Rapaura Rd R D 3 Rapaura ",
    "sg:city":"Blenheim",
    "sg:orig_category":"Shopping: Hobbies And Games: Handcrafts",
    "sg:phone":"+64 3-572 7240",
    "sg:province":"Marlborough",
    "wof:name":"The Quilters Barn",
    "wof:placetype":"venue"
},
  "geometry": {"coordinates":[173.957291,-41.513084],"type":"Point"}
}