{
  "type": "Feature",
  "properties": {
    "addr:full":"Bond Rd Te  Awamutu Waikato",
    "addr:street":"Bond Rd",
    "iso:country":"NZ",
    "sg:address":"Bond Rd Te ",
    "sg:city":"Awamutu",
    "sg:classifiers":[
        {
            "category":"Retail",
            "subcategory":"Laundry & Dry Cleaning",
            "type":"Services"
        }
    ],
    "sg:phone":"+64 7-871 4398",
    "sg:province":"Waikato",
    "sg:tags":[
        "product",
        "wool",
        "clothing",
        "fabric"
    ],
    "wof:name":"Les Candy Wools Ltd",
    "wof:placetype":"venue"
},
  "geometry": {"coordinates":[175.33239699999999,-38.000809],"type":"Point"}
}