{
  "type": "Feature",
  "properties": {
    "addr:full":"85 Pururu St  Rotorua Bay of Plenty",
    "addr:housenumber":"85",
    "addr:street":"Pururu St",
    "iso:country":"NZ",
    "sg:address":"85 Pururu St ",
    "sg:city":"Rotorua",
    "sg:orig_category":"Industrial: Services: Gasfitters",
    "sg:phone":"+64 7-348 8661",
    "sg:province":"Bay of Plenty",
    "wof:name":"Bill Rawlinson & Company Ltd",
    "wof:placetype":"venue"
},
  "geometry": {"coordinates":[176.22880599999999,-38.133156],"type":"Point"}
}