{
  "type": "Feature",
  "properties": {
    "addr:full":"Castlepoint  Tinui",
    "iso:country":"NZ",
    "sg:address":"Castlepoint ",
    "sg:city":"Tinui",
    "sg:classifiers":[
        {
            "category":"Recreation",
            "type":"Entertainment"
        }
    ],
    "sg:phone":"+64 6-372 6613",
    "sg:tags":[
        "shopping",
        "hunting",
        "fishing",
        "retailers",
        "sport",
        "trip"
    ],
    "wof:name":"Legionaire Fishing Charters",
    "wof:placetype":"venue"
},
  "geometry": {"coordinates":[176.22155799999999,-40.899078],"type":"Point"}
}