{
  "type": "Feature",
  "properties": {
    "addr:full":"31 Kelvin St  Invercargill Southland",
    "addr:housenumber":"31",
    "addr:street":"Kelvin St",
    "iso:country":"NZ",
    "sg:address":"31 Kelvin St ",
    "sg:city":"Invercargill",
    "sg:orig_category":"Clothing And Fabric: Clothing: Women'S Fashions",
    "sg:phone":"+64 3-218 7757",
    "sg:province":"Southland",
    "wof:name":"Julie Bryce Fashion Emporium Ltd",
    "wof:placetype":"venue"
},
  "geometry": {"coordinates":[168.350739,-46.411236],"type":"Point"}
}