{
  "type": "Feature",
  "properties": {
    "iso:country":"NZ",
    "sg:address":"PO Box 8044 ",
    "sg:city":"Dunedin",
    "sg:orig_category":"Shopping: Accessories",
    "sg:phone":"+64 3-467 9299",
    "sg:province":"Otago",
    "sg:website":"http://www.artifact.co.nz",
    "wof:name":"Artifact Ltd",
    "wof:placetype":"venue"
},
  "geometry": {"coordinates":[-82.784721,28.013355],"type":"Point"}
}