{
  "type": "Feature",
  "properties": {
    "addr:full":"122 Disraeli St  Gisborne Gisborne",
    "addr:housenumber":"122",
    "addr:street":"Disraeli St",
    "iso:country":"NZ",
    "sg:address":"122 Disraeli St ",
    "sg:city":"Gisborne",
    "sg:classifiers":[
        {
            "category":"Sports & Exercise",
            "subcategory":"Swimming Pool",
            "type":"Entertainment"
        }
    ],
    "sg:phone":"+64 6-867 1613",
    "sg:province":"Gisborne",
    "sg:tags":[
        "home",
        "outdoor",
        "garden",
        "spa"
    ],
    "wof:name":"Hansen & Tomlinson 2001 Ltd",
    "wof:placetype":"venue"
},
  "geometry": {"coordinates":[178.016144,-38.661072],"type":"Point"}
}