{
  "type": "Feature",
  "properties": {
    "addr:full":"Unit 4, 4 Glover St Ngauranga  Wellington Wellington",
    "addr:housenumber":"unit;4",
    "addr:street":"Glover St",
    "iso:country":"NZ",
    "sg:address":"Unit 4, 4 Glover St Ngauranga ",
    "sg:city":"Wellington",
    "sg:orig_category":"Industrial: Packaging: Paper Products",
    "sg:phone":"+64 4-918 3190",
    "sg:province":"Wellington",
    "wof:name":"Ecolab Hygiene",
    "wof:placetype":"venue"
},
  "geometry": {"coordinates":[174.81336999999999,-41.241772],"type":"Point"}
}