{
  "type": "Feature",
  "properties": {
    "addr:full":"38 St George St Papatoetoe  Auckland Auckland",
    "addr:housenumber":"38",
    "addr:street":"St George St",
    "iso:country":"NZ",
    "sg:address":"38 St George St Papatoetoe ",
    "sg:city":"Auckland",
    "sg:classifiers":[
        {
            "category":"Shopping",
            "subcategory":"Gifts & Souvenirs",
            "type":"Retail Goods"
        }
    ],
    "sg:phone":"+64 9-279 8182",
    "sg:province":"Auckland",
    "sg:tags":[
        "shop",
        "gifts",
        "supplier"
    ],
    "wof:name":"Fulsun",
    "wof:placetype":"venue"
},
  "geometry": {"coordinates":[174.852859,-36.979507],"type":"Point"}
}