{
  "type": "Feature",
  "properties": {
    "addr:full":"Grasslands Pl  Hamilton Waikato",
    "addr:street":"Grasslands Pl",
    "iso:country":"NZ",
    "sg:address":"Grasslands Pl ",
    "sg:city":"Hamilton",
    "sg:classifiers":[
        {
            "category":"Ice Cream",
            "type":"Food & Drink"
        }
    ],
    "sg:phone":"+64 7-847 9532",
    "sg:province":"Waikato",
    "sg:tags":[
        "frozen",
        "-"
    ],
    "wof:name":"Mooloo Products Ltd",
    "wof:placetype":"venue"
},
  "geometry": {"coordinates":[-87.988968,34.142426],"type":"Point"}
}