{
  "type": "Feature",
  "properties": {
    "addr:full":"110 Broadway  Matamata Manawatu-Wanganui",
    "addr:housenumber":"110",
    "addr:street":"Broadway",
    "iso:country":"NZ",
    "sg:address":"110 Broadway ",
    "sg:city":"Matamata",
    "sg:orig_category":"Shopping: Retail Stores: Secondhand Dealers",
    "sg:phone":"+64 7-888 4847",
    "sg:province":"Manawatu-Wanganui",
    "wof:name":"Broadway Second-Hand Traders",
    "wof:placetype":"venue"
},
  "geometry": {"coordinates":[175.77778599999999,-37.81144],"type":"Point"}
}