{
  "type": "Feature",
  "properties": {
    "iso:country":"NZ",
    "sg:address":"46 King St New ",
    "sg:city":"Plymouth",
    "sg:orig_category":"Shopping: Hobbies And Games: Handcrafts",
    "sg:phone":"+64 6-757 8697",
    "sg:province":"Taranaki",
    "wof:name":"Expressions Crafts & Gifts",
    "wof:placetype":"venue"
},
  "geometry": {"coordinates":[-116.81972500000001,43.97221],"type":"Point"}
}