{
  "type": "Feature",
  "properties": {
    "addr:full":"30 Queen St Pareora  Timaru Canterbury",
    "addr:housenumber":"30",
    "addr:street":"Queen St",
    "iso:country":"NZ",
    "sg:address":"30 Queen St Pareora ",
    "sg:city":"Timaru",
    "sg:orig_category":"Sports And Leisure: General: Clubs",
    "sg:phone":"+64 3-612 6720",
    "sg:province":"Canterbury",
    "wof:name":"Pareora Country Club Inc",
    "wof:placetype":"venue"
},
  "geometry": {"coordinates":[171.19331399999999,-44.385014],"type":"Point"}
}