{
  "type": "Feature",
  "properties": {
    "addr:full":"302 Gt North Rd Grey Lynn  Auckland Auckland",
    "addr:housenumber":"302",
    "addr:street":"Gt North Rd",
    "iso:country":"NZ",
    "sg:address":"302 Gt North Rd Grey Lynn ",
    "sg:city":"Auckland",
    "sg:classifiers":[
        {
            "category":"Autos & Motor Vehicles",
            "subcategory":"Motorcycle Sales",
            "type":"Retail Goods"
        }
    ],
    "sg:phone":"+64 9-360 0886",
    "sg:province":"Auckland",
    "sg:tags":[
        "automotive",
        "scooter",
        "leasing"
    ],
    "wof:name":"Scooterworld LMVD",
    "wof:placetype":"venue"
},
  "geometry": {"coordinates":[174.73474100000001,-36.861408],"type":"Point"}
}