{
  "type": "Feature",
  "properties": {
    "iso:country":"NZ",
    "sg:address":"Belmont Rd ",
    "sg:city":"Wanganui",
    "sg:classifiers":[
        {
            "category":"Coffee & Tea",
            "type":"Food & Drink"
        }
    ],
    "sg:phone":"+64 6-345 5015",
    "sg:province":"Manawatu-Wanganui",
    "sg:tags":[
        "vegetable",
        "fruit",
        "veges"
    ],
    "wof:name":"Wanganui Mushrooms Ltd",
    "wof:placetype":"venue"
},
  "geometry": {"coordinates":[175.005981,-39.916855],"type":"Point"}
}