{
  "type": "Feature",
  "properties": {
    "iso:country":"NZ",
    "sg:address":"Behind Plumbing World Main Rd S ",
    "sg:city":"Levin",
    "sg:orig_category":"Industrial: Services: Drillers",
    "sg:phone":"+64 6-368 5829",
    "sg:province":"Manawatu-Wanganui",
    "wof:name":"Nevill Webb & Sons Ltd",
    "wof:placetype":"venue"
},
  "geometry": {"coordinates":[175.285324,-40.625278],"type":"Point"}
}