{
  "type": "Feature",
  "properties": {
    "iso:country":"NZ",
    "sg:address":"PO Box 37-107 Wellington Lower ",
    "sg:city":"Hutt",
    "sg:orig_category":"Clothing And Fabric: Clothing: Clothing - Specialty",
    "sg:phone":"+64 4-563 9364",
    "sg:province":"Wellington",
    "wof:name":"Accessorio Di Moda",
    "wof:placetype":"venue"
},
  "geometry": {"coordinates":[174.90838600000001,-41.206631],"type":"Point"}
}