{
  "type": "Feature",
  "properties": {
    "addr:full":"3 Charlemont St  Ranfurly",
    "addr:housenumber":"3",
    "addr:street":"Charlemont St",
    "iso:country":"NZ",
    "sg:address":"3 Charlemont St ",
    "sg:city":"Ranfurly",
    "sg:classifiers":[
        {
            "category":"Communications",
            "subcategory":"Radio Station",
            "type":"Services"
        }
    ],
    "sg:phone":"+64 3-444 9729",
    "sg:tags":[
        "broadcasting"
    ],
    "wof:name":"Classic Gold Radio 729 AM",
    "wof:placetype":"venue"
},
  "geometry": {"coordinates":[170.098938,-45.129498],"type":"Point"}
}