{
  "type": "Feature",
  "properties": {
    "iso:country":"NZ",
    "sg:address":"Stadium Rd Western Springs ",
    "sg:city":"Auckland",
    "sg:classifiers":[
        {
            "category":"Sports & Exercise",
            "subcategory":"Sports Center",
            "type":"Entertainment"
        }
    ],
    "sg:phone":"+64 9-849 3807",
    "sg:province":"Auckland",
    "sg:tags":[
        "sporting",
        "sports",
        "-",
        "leisure",
        "facility"
    ],
    "wof:name":"Western Springs Stadium",
    "wof:placetype":"venue"
},
  "geometry": {"coordinates":[174.721603,-36.854465],"type":"Point"}
}