{
  "type": "Feature",
  "properties": {
    "iso:country":"NZ",
    "sg:address":"193 Rutherford St ",
    "sg:city":"Nelson",
    "sg:orig_category":"Health And Beauty: Dental: Dentists",
    "sg:phone":"+64 3-548 8840",
    "sg:province":"Nelson",
    "wof:name":"Meffan Andrew",
    "wof:placetype":"venue"
},
  "geometry": {"coordinates":[173.280838,-41.278469],"type":"Point"}
}