{
  "type": "Feature",
  "properties": {
    "iso:country":"NZ",
    "sg:address":"207 High St ",
    "sg:city":"Motueka",
    "sg:orig_category":"Shopping: Retail Stores: Books: Bookshops",
    "sg:phone":"+64 3-528 6600",
    "sg:province":"Tasman",
    "wof:name":"Books & More",
    "wof:placetype":"venue"
},
  "geometry": {"coordinates":[173.010269,-41.126648],"type":"Point"}
}