{
  "type": "Feature",
  "properties": {
    "iso:country":"NZ",
    "sg:address":"140 Main St ",
    "sg:city":"Greytown",
    "sg:classifiers":[
        {
            "category":"Fast Food",
            "type":"Food & Drink"
        }
    ],
    "sg:phone":"+64 6-304 9366",
    "sg:tags":[
        "wining",
        "dining",
        "takeaway"
    ],
    "wof:name":"Pitt Stop Takeaways",
    "wof:placetype":"venue"
},
  "geometry": {"coordinates":[-83.942429,41.370983],"type":"Point"}
}