{
  "type": "Feature",
  "properties": {
    "addr:full":"1 Koheroa Rd Mercer  Pukekohe Auckland",
    "addr:housenumber":"1",
    "addr:street":"Koheroa Rd",
    "iso:country":"NZ",
    "sg:address":"1 Koheroa Rd Mercer ",
    "sg:city":"Pukekohe",
    "sg:orig_category":"Home And Garden: Gardening: Products: Hydroponics Supplies",
    "sg:phone":"+64 9-232 6500",
    "sg:province":"Auckland",
    "wof:name":"Breeze Craft Aeropod Ltd",
    "wof:placetype":"venue"
},
  "geometry": {"coordinates":[174.90362500000001,-37.20063],"type":"Point"}
}