{
  "type": "Feature",
  "properties": {
    "addr:full":"78 A Victoria Ave  Wanganui Manawatu-Wanganui",
    "addr:housenumber":"78 a",
    "addr:street":"Victoria Ave",
    "iso:country":"NZ",
    "sg:address":"78 A Victoria Ave ",
    "sg:city":"Wanganui",
    "sg:orig_category":"Shopping: Tobacco: Tobacco Outlets",
    "sg:phone":"+64 6-345 3475",
    "sg:province":"Manawatu-Wanganui",
    "wof:name":"Avenue Tobacconist",
    "wof:placetype":"venue"
},
  "geometry": {"coordinates":[175.05287200000001,-39.933224],"type":"Point"}
}