{
  "type": "Feature",
  "properties": {
    "addr:full":"PO Box 100 Drury  Auckland Auckland",
    "addr:housenumber":"po;100",
    "addr:street":"Box",
    "iso:country":"NZ",
    "sg:address":"PO Box 100 Drury ",
    "sg:city":"Auckland",
    "sg:orig_category":"Sports And Leisure: Sports: Golf: Golf Professionals",
    "sg:phone":"+64 9-358 0889",
    "sg:province":"Auckland",
    "wof:name":"Golf Holidays New Zealand Ltd",
    "wof:placetype":"venue"
},
  "geometry": {"coordinates":[174.950851,-37.102348],"type":"Point"}
}