{
  "type": "Feature",
  "properties": {
    "addr:full":"7 Victoria Ave  Wanganui Manawatu-Wanganui",
    "addr:housenumber":"7",
    "addr:street":"Victoria Ave",
    "iso:country":"NZ",
    "sg:address":"7 Victoria Ave ",
    "sg:city":"Wanganui",
    "sg:classifiers":[
        {
            "category":"Banks & Credit Unions",
            "subcategory":"Investment Brokerage",
            "type":"Services"
        }
    ],
    "sg:phone":"+64 6-348 7042",
    "sg:province":"Manawatu-Wanganui",
    "sg:tags":[
        "personal",
        "-",
        "finance"
    ],
    "wof:name":"Kelly Thiele Moffat",
    "wof:placetype":"venue"
},
  "geometry": {"coordinates":[175.05496199999999,-39.934792],"type":"Point"}
}