{
  "type": "Feature",
  "properties": {
    "iso:country":"NZ",
    "sg:address":"50 Sierra St Glendowie ",
    "sg:city":"Auckland",
    "sg:orig_category":"Transport: Land: Limousines And Chauffeurs",
    "sg:phone":"+64 9-575 6905",
    "sg:province":"Auckland",
    "wof:name":"Douglas Bridal Limousines",
    "wof:placetype":"venue"
},
  "geometry": {"coordinates":[174.861404,-36.864456],"type":"Point"}
}