{
  "type": "Feature",
  "properties": {
    "iso:country":"NZ",
    "sg:address":"112 Parkers Rd Tahunanui ",
    "sg:city":"Nelson",
    "sg:classifiers":[
        {
            "category":"Social Services",
            "subcategory":"Child Care",
            "type":"Services"
        }
    ],
    "sg:phone":"+64 3-546 4321",
    "sg:province":"Nelson",
    "sg:tags":[
        "home",
        "garden",
        "children"
    ],
    "wof:name":"Kids And Families Preschool Are Us Ltd",
    "wof:placetype":"venue"
},
  "geometry": {"coordinates":[173.2379,-41.287865],"type":"Point"}
}