{
  "type": "Feature",
  "properties": {
    "addr:full":"116 Hewletts Rd Mt  Maunganui Bay of Plenty",
    "addr:housenumber":"116",
    "addr:street":"Hewletts Rd;Maunganui",
    "iso:country":"NZ",
    "sg:address":"116 Hewletts Rd Mt ",
    "sg:city":"Maunganui",
    "sg:classifiers":[
        {
            "category":"Autos & Motor Vehicles",
            "subcategory":"Automobile Sales",
            "type":"Retail Goods"
        }
    ],
    "sg:phone":"+64 7-574 5393",
    "sg:province":"Bay of Plenty",
    "sg:tags":[
        "bus",
        "leasing",
        "truck",
        "automotive"
    ],
    "wof:name":"Transport Commercial (Tga) 97 Ltd Isuzu LMVD",
    "wof:placetype":"venue"
},
  "geometry": {"coordinates":[176.18627900000001,-37.641048],"type":"Point"}
}