{
  "type": "Feature",
  "properties": {
    "addr:full":"10 Wakefield Ave Sumner  Christchurch Canterbury",
    "addr:housenumber":"10",
    "addr:street":"Wakefield Ave",
    "iso:country":"NZ",
    "sg:address":"10 Wakefield Ave Sumner ",
    "sg:city":"Christchurch",
    "sg:classifiers":[
        {
            "category":"Professional",
            "subcategory":"Art Services",
            "type":"Services"
        }
    ],
    "sg:phone":"+64 3-326 5265",
    "sg:province":"Canterbury",
    "sg:tags":[
        "fashion",
        "clothing",
        "fabric",
        "designer"
    ],
    "wof:name":"NancyRaine Designer Clothing",
    "wof:placetype":"venue"
},
  "geometry": {"coordinates":[172.75891100000001,-43.568954],"type":"Point"}
}