{
  "type": "Feature",
  "properties": {
    "iso:country":"NZ",
    "sg:address":"Unit 4 23 Napier Rd Havelock North ",
    "sg:city":"Hastings",
    "sg:orig_category":"Shopping: Gifts: Gift Baskets",
    "sg:phone":"+64 6-877 5938",
    "sg:province":"Hawke's Bay",
    "wof:name":"A Taste of Hawke's Bay",
    "wof:placetype":"venue"
},
  "geometry": {"coordinates":[176.878952,-39.66827],"type":"Point"}
}