{
  "type": "Feature",
  "properties": {
    "addr:full":"16 Auburn St Takapuna  Auckland Auckland",
    "addr:housenumber":"16",
    "addr:street":"Auburn St",
    "iso:country":"NZ",
    "sg:address":"16 Auburn St Takapuna ",
    "sg:city":"Auckland",
    "sg:classifiers":[
        {
            "category":"Personal",
            "type":"Services"
        }
    ],
    "sg:phone":"+64 9-488 9395",
    "sg:province":"Auckland",
    "sg:tags":[
        "health",
        "beauty",
        "diet"
    ],
    "sg:website":"http://www.slenderform.co.nz",
    "wof:name":"Slenderform",
    "wof:placetype":"venue"
},
  "geometry": {"coordinates":[174.76818800000001,-36.788425],"type":"Point"}
}