{
  "type": "Feature",
  "properties": {
    "addr:full":"Unit C / 187 Ohoka Rd  Kaiapoi",
    "addr:housenumber":"unit c",
    "addr:street":"/ 187 Ohoka Rd",
    "iso:country":"NZ",
    "sg:address":"Unit C / 187 Ohoka Rd ",
    "sg:city":"Kaiapoi",
    "sg:orig_category":"Clothing And Fabric: Clothing: Children'S Wear",
    "sg:phone":"+64 3-327 2965",
    "wof:name":"Ok Kid Childrenswear Ltd",
    "wof:placetype":"venue"
},
  "geometry": {"coordinates":[172.65931699999999,-43.366875],"type":"Point"}
}