{
  "type": "Feature",
  "properties": {
    "addr:full":"Maadi Rd Onekawa  Napier Hawke's Bay",
    "addr:street":"Maadi Rd",
    "iso:country":"NZ",
    "sg:address":"Maadi Rd Onekawa ",
    "sg:city":"Napier",
    "sg:orig_category":"Health And Beauty: Products: Pharmacies",
    "sg:phone":"+64 6-843 8749",
    "sg:province":"Hawke's Bay",
    "wof:name":"Andrew Spence Pharmacy",
    "wof:placetype":"venue"
},
  "geometry": {"coordinates":[176.88720699999999,-39.508003],"type":"Point"}
}