{
  "type": "Feature",
  "properties": {
    "iso:country":"NZ",
    "sg:address":"Maadi Rd Onekawa ",
    "sg:city":"Napier",
    "sg:orig_category":"Health And Beauty: Products: Pharmacies",
    "sg:phone":"+64 6-843 8749",
    "sg:province":"Hawke's Bay",
    "wof:name":"Andrew Spence Pharmacy",
    "wof:placetype":"venue"
},
  "geometry": {"coordinates":[176.887207,-39.508003],"type":"Point"}
}