{
  "type": "Feature",
  "properties": {
    "iso:country":"NZ",
    "sg:address":"PO Box ",
    "sg:city":"4330",
    "sg:classifiers":[
        {
            "category":"Building & Trades",
            "subcategory":"Plumbing",
            "type":"Services"
        }
    ],
    "sg:phone":"+64 25961283",
    "sg:tags":[
        "home",
        "plumber",
        "garden",
        "related"
    ],
    "wof:name":"Mount Plumbing",
    "wof:placetype":"venue"
},
  "geometry": {"coordinates":[10.17257,44.243561],"type":"Point"}
}