{
  "type": "Feature",
  "properties": {
    "addr:full":"Shop 1 444 Glenfield Rd Glenfield  Auckland Auckland",
    "addr:housenumber":"shop 1 444",
    "addr:street":"Glenfield Rd",
    "iso:country":"NZ",
    "sg:address":"Shop 1 444 Glenfield Rd Glenfield ",
    "sg:city":"Auckland",
    "sg:classifiers":[
        {
            "category":"Shopping",
            "subcategory":"Photographic Equipment",
            "type":"Retail Goods"
        }
    ],
    "sg:phone":"+64 9-444 9960",
    "sg:province":"Auckland",
    "sg:tags":[
        "sport",
        "leisure",
        "hobbies"
    ],
    "wof:name":"Glenfield Photo Shop",
    "wof:placetype":"venue"
},
  "geometry": {"coordinates":[174.721542,-36.780708],"type":"Point"}
}