{
  "type": "Feature",
  "properties": {
    "addr:full":"Maungatapu Rd  Tauranga Bay of Plenty",
    "addr:street":"Maungatapu Rd",
    "iso:country":"NZ",
    "sg:address":"Maungatapu Rd ",
    "sg:city":"Tauranga",
    "sg:orig_category":"Health And Beauty: Products: Pharmacies",
    "sg:phone":"+64 7-544 0771",
    "sg:province":"Bay of Plenty",
    "wof:name":"Maungatapu Pharmacy",
    "wof:placetype":"venue"
},
  "geometry": {"coordinates":[176.18090799999999,-37.717045],"type":"Point"}
}