{
  "type": "Feature",
  "properties": {
    "iso:country":"NZ",
    "sg:address":"524 Blenheim Rd Riccarton ",
    "sg:city":"Christchurch",
    "sg:classifiers":[
        {
            "category":"Home & Garden",
            "subcategory":"Building Materials",
            "type":"Retail Goods"
        }
    ],
    "sg:phone":"+64 3-343 0097",
    "sg:province":"Canterbury",
    "sg:tags":[
        "gate",
        "fitting",
        "outdoor"
    ],
    "wof:name":"Aabaas Industries",
    "wof:placetype":"venue"
},
  "geometry": {"coordinates":[172.58625799999999,-43.538269],"type":"Point"}
}