{
  "type": "Feature",
  "properties": {
    "iso:country":"NZ",
    "sg:address":"Old Railway Rd Kumeu ",
    "sg:city":"Auckland",
    "sg:classifiers":[
        {
            "category":"Shopping",
            "subcategory":"Discount & Variety Stores",
            "type":"Retail Goods"
        }
    ],
    "sg:phone":"+64 9-412 7474",
    "sg:province":"Auckland",
    "sg:tags":[
        "storage",
        "cool"
    ],
    "wof:name":"Hortifresh C.A Coolstores Ltd",
    "wof:placetype":"venue"
},
  "geometry": {"coordinates":[174.571259,-36.777611],"type":"Point"}
}