{
  "type": "Feature",
  "properties": {
    "addr:full":"PO Box 113-105 Newmarket  Auckland Auckland",
    "addr:housenumber":"po;113-105",
    "addr:street":"Box",
    "iso:country":"NZ",
    "sg:address":"PO Box 113-105 Newmarket ",
    "sg:city":"Auckland",
    "sg:orig_category":"Farming: Supplies: Stock Foods",
    "sg:phone":"+64 9-520 1566",
    "sg:province":"Auckland",
    "wof:name":"Ngahiwi Farms Ltd",
    "wof:placetype":"venue"
},
  "geometry": {"coordinates":[174.77375799999999,-36.867878],"type":"Point"}
}