{
  "type": "Feature",
  "properties": {
    "iso:country":"NZ",
    "sg:address":"PO Box 36507 Northcote ",
    "sg:city":"Auckland",
    "sg:orig_category":"Home And Garden: Accessories: Linen",
    "sg:phone":"+64 9-270 4094",
    "sg:province":"Auckland",
    "wof:name":"McNair Import & Distribution Ltd",
    "wof:placetype":"venue"
},
  "geometry": {"coordinates":[174.747849,-36.801125],"type":"Point"}
}