{
  "type": "Feature",
  "properties": {
    "iso:country":"NZ",
    "sg:address":"644 Main St Palmerston ",
    "sg:city":"Palmerston North",
    "sg:orig_category":"Automotive: General Services: Rental Vehicles",
    "sg:phone":"+64 6-355 0332",
    "sg:province":"Manawatu-Wanganui",
    "wof:name":"Affordable Rentals",
    "wof:placetype":"venue"
},
  "geometry": {"coordinates":[175.615524,-40.354359],"type":"Point"}
}