{
  "type": "Feature",
  "properties": {
    "addr:full":"689 Ferry Rd Woolston  Christchurch Canterbury",
    "addr:housenumber":"689",
    "addr:street":"Ferry Rd",
    "iso:country":"NZ",
    "sg:address":"689 Ferry Rd Woolston ",
    "sg:city":"Christchurch",
    "sg:orig_category":"Shopping: Retail Stores: Books: Libraries",
    "sg:phone":"+64 3-384 7378",
    "sg:province":"Canterbury",
    "wof:name":"Woolston Community Library",
    "wof:placetype":"venue"
},
  "geometry": {"coordinates":[172.68306000000001,-43.549206],"type":"Point"}
}