{
  "type": "Feature",
  "properties": {
    "iso:country":"NZ",
    "sg:address":"PO Box 92 ",
    "sg:city":"Queenstown",
    "sg:classifiers":[
        {
            "category":"Communications",
            "subcategory":"Radio Station",
            "type":"Services"
        }
    ],
    "sg:phone":"+64 3-441 3968",
    "sg:province":"Otago",
    "sg:tags":[
        "broadcasting"
    ],
    "wof:name":"The Studio 96.8 FM",
    "wof:placetype":"venue"
},
  "geometry": {"coordinates":[-76.18094600000001,38.898491],"type":"Point"}
}