{
  "type": "Feature",
  "properties": {
    "iso:country":"NZ",
    "sg:address":"Tarras ",
    "sg:city":"Cromwell",
    "sg:orig_category":"Farming: Services: Livestock Related: Breeding Services",
    "sg:phone":"+64 3-445 2833",
    "wof:name":"Forest Range Station",
    "wof:placetype":"venue"
},
  "geometry": {"coordinates":[169.201553,-45.0439],"type":"Point"}
}