{
  "type": "Feature",
  "properties": {
    "addr:full":"69 Third Ave  Tauranga Bay of Plenty",
    "addr:housenumber":"69",
    "addr:street":"Third Ave",
    "iso:country":"NZ",
    "sg:address":"69 Third Ave ",
    "sg:city":"Tauranga",
    "sg:classifiers":[
        {
            "category":"Retail",
            "subcategory":"Auto Repair",
            "type":"Services"
        }
    ],
    "sg:phone":"+64 7-578 3102",
    "sg:province":"Bay of Plenty",
    "sg:tags":[
        "transmission",
        "automotive",
        "servicing"
    ],
    "wof:name":"Automatic Service Centre",
    "wof:placetype":"venue"
},
  "geometry": {"coordinates":[176.16563400000001,-37.689938],"type":"Point"}
}