{
  "type": "Feature",
  "properties": {
    "iso:country":"NZ",
    "sg:address":"400 St Asaph St ",
    "sg:city":"Christchurch",
    "sg:classifiers":[
        {
            "category":"Manufacturing",
            "subcategory":"Textiles",
            "type":"Manufacturing & Wholesale Goods"
        }
    ],
    "sg:phone":"+64 3-366 8827",
    "sg:province":"Canterbury",
    "sg:tags":[
        "clothing",
        "fabric",
        "manufacturer"
    ],
    "wof:name":"Kauri Clothing Limited",
    "wof:placetype":"venue"
},
  "geometry": {"coordinates":[172.652435,-43.536514],"type":"Point"}
}