{
  "type": "Feature",
  "properties": {
    "addr:full":"PO Box 14 486  Kilbirnie Wellington",
    "addr:housenumber":"po box 14",
    "addr:postcode":"486",
    "iso:country":"NZ",
    "sg:address":"PO Box 14 486 ",
    "sg:city":"Kilbirnie",
    "sg:orig_category":"Industrial: Coatings",
    "sg:phone":"+64 274 437 831",
    "sg:province":"Wellington",
    "wof:name":"Haven Residential Ltd",
    "wof:placetype":"venue"
},
  "geometry": {"coordinates":[174.794678,-41.318909],"type":"Point"}
}