{
  "type": "Feature",
  "properties": {
    "addr:full":"PO Box 11054 Papamoa Mt  Maunganui Bay of Plenty",
    "addr:housenumber":"po box",
    "addr:postcode":"11054",
    "addr:street":"Maunganui Bay",
    "iso:country":"NZ",
    "sg:address":"PO Box 11054 Papamoa Mt ",
    "sg:city":"Maunganui",
    "sg:classifiers":[
        {
            "category":"Social Services",
            "subcategory":"Retirement Home",
            "type":"Services"
        }
    ],
    "sg:phone":"+64 7-572 4500",
    "sg:province":"Bay of Plenty",
    "sg:tags":[
        "personal",
        "services",
        "garden",
        "elderly",
        "care"
    ],
    "wof:name":"Helping Hands Agency NZ Ltd",
    "wof:placetype":"venue"
},
  "geometry": {"coordinates":[176.29817199999999,-37.73291],"type":"Point"}
}