{
  "type": "Feature",
  "properties": {
    "addr:full":"19 Beach Rd Tahunanui  Nelson Nelson",
    "addr:housenumber":"19",
    "addr:street":"Beach Rd",
    "iso:country":"NZ",
    "sg:address":"19 Beach Rd Tahunanui ",
    "sg:city":"Nelson",
    "sg:classifiers":[
        {
            "category":"Travel",
            "subcategory":"Bed & Breakfast",
            "type":"Entertainment"
        }
    ],
    "sg:phone":"+64 3-546 4000",
    "sg:province":"Nelson",
    "sg:tags":[
        "tourism",
        "accommodation"
    ],
    "wof:name":"Aloha Lodge Bed & Breakfast",
    "wof:placetype":"venue"
},
  "geometry": {"coordinates":[173.248413,-41.281471],"type":"Point"}
}