{
  "type": "Feature",
  "properties": {
    "addr:full":"Unit 4/65 Nelson St Petone Lower  Hutt Wellington",
    "addr:housenumber":"unit 4 / 65",
    "addr:street":"Nelson St",
    "iso:country":"NZ",
    "sg:address":"Unit 4/65 Nelson St Petone Lower ",
    "sg:city":"Hutt",
    "sg:orig_category":"Industrial: Metal: Products: Aluminium Products",
    "sg:phone":"+64 4-586 5090",
    "sg:province":"Wellington",
    "wof:name":"Valley Omega",
    "wof:placetype":"venue"
},
  "geometry": {"coordinates":[174.877487,-41.223125],"type":"Point"}
}