{
  "type": "Feature",
  "properties": {
    "addr:full":"7 Racecourse Rd  Waipukurau",
    "addr:housenumber":"7",
    "addr:street":"Racecourse Rd",
    "iso:country":"NZ",
    "sg:address":"7 Racecourse Rd ",
    "sg:city":"Waipukurau",
    "sg:classifiers":[
        {
            "category":"Sports & Exercise",
            "subcategory":"Sports Center",
            "type":"Entertainment"
        }
    ],
    "sg:phone":"+64 6-858 8952",
    "sg:tags":[
        "health",
        "beauty",
        "fitness"
    ],
    "wof:name":"Major Fitness",
    "wof:placetype":"venue"
},
  "geometry": {"coordinates":[176.54612700000001,-40.00119],"type":"Point"}
}