{
  "type": "Feature",
  "properties": {
    "iso:country":"NZ",
    "sg:address":"146 Rockfield Rd ",
    "sg:city":"Penrose",
    "sg:classifiers":[
        {
            "category":"Manufacturing",
            "subcategory":"Tools & Machinery",
            "type":"Manufacturing & Wholesale Goods"
        }
    ],
    "sg:phone":"+64 800 765 279",
    "sg:province":"Auckland",
    "sg:tags":[
        "specialist",
        "energy",
        "industrial",
        "solar",
        "equipment"
    ],
    "wof:name":"Zane Solar Pool Heating",
    "wof:placetype":"venue"
},
  "geometry": {"coordinates":[-105.024071,38.431049],"type":"Point"}
}