{
  "type": "Feature",
  "properties": {
    "iso:country":"NZ",
    "sg:address":"129 Gt South Rd Papakura ",
    "sg:city":"Auckland",
    "sg:orig_category":"Clothing And Fabric: Clothing: Children'S Wear",
    "sg:phone":"+64 9-298 1305",
    "sg:province":"Auckland",
    "wof:name":"T & T Childrenswear",
    "wof:placetype":"venue"
},
  "geometry": {"coordinates":[174.941345,-37.061703],"type":"Point"}
}