{
  "type": "Feature",
  "properties": {
    "iso:country":"NZ",
    "sg:address":"New ",
    "sg:city":"Plymouth",
    "sg:classifiers":[
        {
            "category":"Home & Garden",
            "subcategory":"Carpets & Floor Coverings",
            "type":"Retail Goods"
        }
    ],
    "sg:phone":"+64 800 692 969",
    "sg:province":"Taranaki",
    "sg:tags":[
        "cleaning",
        "furniture"
    ],
    "wof:name":"Carpet Cleaning Services",
    "wof:placetype":"venue"
},
  "geometry": {"coordinates":[174.074005,-39.058292],"type":"Point"}
}