{
  "type": "Feature",
  "properties": {
    "addr:full":"5 Watts Rd Sockburn  Christchurch Canterbury",
    "addr:housenumber":"5",
    "addr:street":"Watts Rd",
    "iso:country":"NZ",
    "sg:address":"5 Watts Rd Sockburn ",
    "sg:city":"Christchurch",
    "sg:classifiers":[
        {
            "category":"Shopping",
            "subcategory":"Thrift Store",
            "type":"Retail Goods"
        }
    ],
    "sg:phone":"+64 3-348 8211",
    "sg:province":"Canterbury",
    "sg:tags":[
        "-",
        "clothing",
        "secondhand",
        "fabric"
    ],
    "wof:name":"Just Browsing",
    "wof:placetype":"venue"
},
  "geometry": {"coordinates":[172.56050099999999,-43.536716],"type":"Point"}
}