{
  "type": "Feature",
  "properties": {
    "iso:country":"NZ",
    "sg:address":"11 Ngaio Rd Waikanae ",
    "sg:city":"Paraparaumu",
    "sg:classifiers":[
        {
            "category":"Shopping",
            "subcategory":"Thrift Store",
            "type":"Retail Goods"
        }
    ],
    "sg:phone":"+64 9025155",
    "sg:province":"Wellington",
    "sg:tags":[
        "-",
        "clothing",
        "secondhand",
        "fabric"
    ],
    "wof:name":"Encore",
    "wof:placetype":"venue"
},
  "geometry": {"coordinates":[175.063919,-40.875252],"type":"Point"}
}