{
  "type": "Feature",
  "properties": {
    "addr:full":"P O Box 530 Te  Puke Bay of Plenty",
    "addr:housenumber":"530",
    "addr:street":"P O Box",
    "iso:country":"NZ",
    "sg:address":"P O Box 530 Te ",
    "sg:city":"Puke",
    "sg:classifiers":[
        {
            "category":"Banks & Credit Unions",
            "subcategory":"Investment Brokerage",
            "type":"Services"
        }
    ],
    "sg:phone":"+64 25803932",
    "sg:province":"Bay of Plenty",
    "sg:tags":[
        "services",
        "ferry",
        "travel",
        "tourism"
    ],
    "wof:name":"Forest Lady Barge",
    "wof:placetype":"venue"
},
  "geometry": {"coordinates":[176.32008400000001,-37.786819],"type":"Point"}
}