{
  "type": "Feature",
  "properties": {
    "iso:country":"NZ",
    "sg:address":"41 Morrin Rd Mt Wellington ",
    "sg:city":"Auckland",
    "sg:classifiers":[
        {
            "category":"Recreation",
            "type":"Entertainment"
        }
    ],
    "sg:phone":"+64 9-570 6944",
    "sg:province":"Auckland",
    "sg:tags":[
        "sport",
        "leisure"
    ],
    "wof:name":"City Side Skatepark Ltd",
    "wof:placetype":"venue"
},
  "geometry": {"coordinates":[174.851257,-36.889526],"type":"Point"}
}