{
  "type": "Feature",
  "properties": {
    "addr:full":"Head Office, First Floor, 40 Hurstmere Rd Takapuna Auckland Auckland",
    "addr:housenumber":"first floor 40",
    "addr:street":"Hurstmere Rd",
    "iso:country":"NZ",
    "sg:address":"Head Office, First Floor, 40 Hurstmere Rd Takapuna",
    "sg:city":"Auckland",
    "sg:classifiers":[
        {
            "category":"Health Services",
            "subcategory":"Dentist",
            "type":"Services"
        }
    ],
    "sg:phone":"+64 9-486 5460",
    "sg:province":"Auckland",
    "sg:tags":[
        "dental",
        "beauty"
    ],
    "sg:website":"http://www.yellowpages.co.nz/for/geddesdental/dp58583.html",
    "wof:name":"Geddes Dental Group",
    "wof:placetype":"venue"
},
  "geometry": {"coordinates":[174.76788300000001,-36.787838],"type":"Point"}
}