{
  "type": "Feature",
  "properties": {
    "addr:full":"16 Fairmont Tce  Tauranga Bay of Plenty",
    "addr:housenumber":"16",
    "addr:street":"Fairmont Tce",
    "iso:country":"NZ",
    "sg:address":"16 Fairmont Tce ",
    "sg:city":"Tauranga",
    "sg:classifiers":[
        {
            "category":"Professional",
            "subcategory":"Art Services",
            "type":"Services"
        }
    ],
    "sg:phone":"+64 7-576 7020",
    "sg:province":"Bay of Plenty",
    "sg:tags":[
        "personal",
        "photographer",
        "services",
        "garden",
        "home"
    ],
    "wof:name":"Peter Wakelin Photography",
    "wof:placetype":"venue"
},
  "geometry": {"coordinates":[176.13916,-37.676849],"type":"Point"}
}