{
  "type": "Feature",
  "properties": {
    "iso:country":"NZ",
    "sg:address":"Hautapu St ",
    "sg:city":"Taihape",
    "sg:orig_category":"Clothing And Fabric: Clothing: Menswear",
    "sg:phone":"+64 6-388 0311",
    "wof:name":"McSweeney F & Co",
    "wof:placetype":"venue"
},
  "geometry": {"coordinates":[175.79930100000001,-39.678398],"type":"Point"}
}