{
  "type": "Feature",
  "properties": {
    "addr:full":"Unit A7 35 Keeling Rd Henderson  Auckland Auckland",
    "addr:housenumber":"a7 35",
    "addr:street":"Keeling Rd",
    "iso:country":"NZ",
    "sg:address":"Unit A7 35 Keeling Rd Henderson ",
    "sg:city":"Auckland",
    "sg:orig_category":"Transport: Distribution - General: Distributors",
    "sg:phone":"+64 9-836 8245",
    "sg:province":"Auckland",
    "wof:name":"Tri Distributors",
    "wof:placetype":"venue"
},
  "geometry": {"coordinates":[174.62451200000001,-36.885254],"type":"Point"}
}