{
  "type": "Feature",
  "properties": {
    "addr:full":"PO Box 47262 Ponsonby  Auckland Auckland",
    "addr:housenumber":"po box",
    "addr:postcode":"47262",
    "iso:country":"NZ",
    "sg:address":"PO Box 47262 Ponsonby ",
    "sg:city":"Auckland",
    "sg:classifiers":[
        {
            "category":"Retail",
            "subcategory":"Driving School",
            "type":"Services"
        }
    ],
    "sg:phone":"+64 9-376 1322",
    "sg:province":"Auckland",
    "sg:tags":[
        "sailing",
        "boating",
        "transport",
        "boats",
        "marine",
        "boat"
    ],
    "wof:name":"Penny Whiting Sailing School",
    "wof:placetype":"venue"
},
  "geometry": {"coordinates":[174.74241599999999,-36.85326],"type":"Point"}
}