{
  "type": "Feature",
  "properties": {
    "iso:country":"NZ",
    "sg:address":"5 Robin Mann Pl Christchurch Airport ",
    "sg:city":"Christchurch",
    "sg:classifiers":[
        {
            "category":"Manufacturing",
            "subcategory":"Chemicals & Compounds",
            "type":"Manufacturing & Wholesale Goods"
        }
    ],
    "sg:phone":"+64 3-357 1273",
    "sg:province":"Canterbury",
    "sg:tags":[
        "soap",
        "industrial",
        "washing",
        "powder",
        "compounds"
    ],
    "wof:name":"Aquados NZ Ltd",
    "wof:placetype":"venue"
},
  "geometry": {"coordinates":[172.548233,-43.493351],"type":"Point"}
}