{
  "type": "Feature",
  "properties": {
    "addr:full":"cnr Racecourse Rd & Tay St  Invercargill Southland",
    "addr:street":"Cnr Racecourse Rd & Tay St",
    "iso:country":"NZ",
    "sg:address":"cnr Racecourse Rd & Tay St ",
    "sg:city":"Invercargill",
    "sg:classifiers":[
        {
            "category":"Bars & Pubs",
            "subcategory":"Wine Bar",
            "type":"Food & Drink"
        }
    ],
    "sg:phone":"+64 3-217 6195",
    "sg:province":"Southland",
    "sg:tags":[
        "wining",
        "dining",
        "cafe"
    ],
    "wof:name":"Invercargill Licensing Trust",
    "wof:placetype":"venue"
},
  "geometry": {"coordinates":[168.35217299999999,-46.41185],"type":"Point"}
}