{
  "type": "Feature",
  "properties": {
    "iso:country":"NZ",
    "sg:address":"12 Park Rd Glenfield ",
    "sg:city":"Auckland",
    "sg:classifiers":[
        {
            "category":"Arena",
            "subcategory":"Sports Club",
            "type":"Entertainment"
        }
    ],
    "sg:phone":"+64 9-444 3340",
    "sg:province":"Auckland",
    "sg:tags":[
        "martial art",
        "-",
        "leisure",
        "sports"
    ],
    "wof:name":"Academy of Chen Style Tai Chi",
    "wof:placetype":"venue"
},
  "geometry": {"coordinates":[174.721436,-36.791592],"type":"Point"}
}