{
  "type": "Feature",
  "properties": {
    "addr:full":"38 Monmouth St Grey Lynn  Auckland Auckland",
    "addr:housenumber":"38",
    "addr:street":"Monmouth St",
    "iso:country":"NZ",
    "sg:address":"38 Monmouth St Grey Lynn ",
    "sg:city":"Auckland",
    "sg:classifiers":[
        {
            "category":"Arena",
            "subcategory":"Sports Club",
            "type":"Entertainment"
        }
    ],
    "sg:phone":"+64 9-361 1347",
    "sg:province":"Auckland",
    "sg:tags":[
        "martial art",
        "-",
        "leisure",
        "sports"
    ],
    "wof:name":"Aikido Lynch Dojo",
    "wof:placetype":"venue"
},
  "geometry": {"coordinates":[174.73474100000001,-36.861408],"type":"Point"}
}