{
  "type": "Feature",
  "properties": {
    "addr:full":"R D 2 Carterton  Gladstone",
    "addr:housenumber":"2",
    "addr:street":"R D",
    "iso:country":"NZ",
    "sg:address":"R D 2 Carterton ",
    "sg:city":"Gladstone",
    "sg:classifiers":[
        {
            "category":"Travel",
            "subcategory":"Hotels & Motels",
            "type":"Entertainment"
        }
    ],
    "sg:phone":"+64 6-372 7866",
    "sg:tags":[
        "tavern",
        "tourism",
        "accommodation"
    ],
    "wof:name":"Gladstone Inn",
    "wof:placetype":"venue"
},
  "geometry": {"coordinates":[175.523819,-41.02393],"type":"Point"}
}