{
  "type": "Feature",
  "properties": {
    "iso:country":"NZ",
    "sg:address":"134 a Plunket Ave Manukau City ",
    "sg:city":"Auckland",
    "sg:orig_category":"Transport: Transportation: Heavy Haulage",
    "sg:phone":"+64 9-263 9900",
    "sg:province":"Auckland",
    "wof:name":"Tranzcarr Heavy Haulage Ltd",
    "wof:placetype":"venue"
},
  "geometry": {"coordinates":[174.881454,-36.98967],"type":"Point"}
}