{
  "type": "Feature",
  "properties": {
    "addr:full":"357 Lower Queen St Richmond  Nelson Nelson",
    "addr:housenumber":"357",
    "addr:street":"Lower Queen St",
    "iso:country":"NZ",
    "sg:address":"357 Lower Queen St Richmond ",
    "sg:city":"Nelson",
    "sg:orig_category":"Health And Beauty: Medical: Hospitals",
    "sg:phone":"+64 3-543 9708",
    "sg:province":"Nelson",
    "wof:name":"Metlifecare Oakwoods",
    "wof:placetype":"venue"
},
  "geometry": {"coordinates":[173.18867499999999,-41.33989],"type":"Point"}
}