{
  "type": "Feature",
  "properties": {
    "addr:full":"C/O 11 SunnyView Dve Upper  Hutt Wellington",
    "addr:housenumber":"11",
    "addr:street":"C / O;Dve",
    "iso:country":"NZ",
    "sg:address":"C/O 11 SunnyView Dve Upper ",
    "sg:city":"Hutt",
    "sg:classifiers":[
        {
            "category":"Sports & Exercise",
            "subcategory":"Sports Center",
            "type":"Entertainment"
        }
    ],
    "sg:phone":"+64 4-526 4022",
    "sg:province":"Wellington",
    "sg:tags":[
        "sporting",
        "sports",
        "-",
        "leisure",
        "facility"
    ],
    "wof:name":"Upper Hutt Darts Association",
    "wof:placetype":"venue"
},
  "geometry": {"coordinates":[175.069031,-41.12458],"type":"Point"}
}