{
  "type": "Feature",
  "properties": {
    "iso:country":"NZ",
    "sg:address":"259 King Edward St South Dunedin ",
    "sg:city":"Dunedin",
    "sg:orig_category":"Health And Beauty: Specialists: Podiatrists",
    "sg:phone":"+64 3-455 0290",
    "sg:province":"Otago",
    "wof:name":"Dunedin Podiatry",
    "wof:placetype":"venue"
},
  "geometry": {"coordinates":[170.50032,-45.895885],"type":"Point"}
}