{
  "type": "Feature",
  "properties": {
    "iso:country":"NZ",
    "sg:address":"Napier ",
    "sg:city":"Napier",
    "sg:classifiers":[
        {
            "category":"Home & Garden",
            "subcategory":"Garden Supply",
            "type":"Retail Goods"
        }
    ],
    "sg:phone":"+64 6-843 8085",
    "sg:province":"Hawke's Bay",
    "sg:tags":[
        "fencing",
        "outdoor",
        "contractor"
    ],
    "wof:name":"Landscape Construction",
    "wof:placetype":"venue"
},
  "geometry": {"coordinates":[19.905689,-34.47776],"type":"Point"}
}