{
  "type": "Feature",
  "properties": {
    "addr:full":"77 Broadway Newmarket  Auckland Manawatu-Wanganui",
    "addr:housenumber":"77",
    "addr:street":"Broadway",
    "iso:country":"NZ",
    "sg:address":"77 Broadway Newmarket ",
    "sg:city":"Auckland",
    "sg:classifiers":[
        {
            "category":"Arena",
            "subcategory":"Sports Club",
            "type":"Entertainment"
        }
    ],
    "sg:phone":"+64 9-522 4414",
    "sg:province":"Manawatu-Wanganui",
    "sg:tags":[
        "leisure"
    ],
    "sg:website":"http://www.olympicpools.co.nz",
    "wof:name":"Olympic Pools & Fitness Centre",
    "wof:placetype":"venue"
},
  "geometry": {"coordinates":[174.77848800000001,-36.866379],"type":"Point"}
}