{
  "type": "Feature",
  "properties": {
    "iso:country":"NZ",
    "sg:address":"Level 1 Cable Car La Lambton Quay ",
    "sg:city":"Wellington",
    "sg:classifiers":[
        {
            "category":"Coffee & Tea",
            "type":"Food & Drink"
        }
    ],
    "sg:phone":"+64 4-472 3479",
    "sg:province":"Wellington",
    "sg:tags":[
        "merchant"
    ],
    "wof:name":"Jura Center",
    "wof:placetype":"venue"
},
  "geometry": {"coordinates":[174.775085,-41.284248],"type":"Point"}
}