{
  "type": "Feature",
  "properties": {
    "iso:country":"NZ",
    "sg:address":"State Highway 6 Hira ",
    "sg:city":"Nelson",
    "sg:classifiers":[
        {
            "category":"Shopping",
            "subcategory":"Pets & Pet Supplies",
            "type":"Retail Goods"
        }
    ],
    "sg:phone":"+64 3-545 1554",
    "sg:province":"Nelson",
    "sg:tags":[
        "boarding",
        "garden",
        "pets",
        "catteries",
        "home",
        "kennel"
    ],
    "wof:name":"Abbeyblyth Boarding Kennel & Cattery",
    "wof:placetype":"venue"
},
  "geometry": {"coordinates":[173.395782,-41.213982],"type":"Point"}
}