{
  "type": "Feature",
  "properties": {
    "addr:full":"64 c Parker St Springlands  Blenheim Marlborough",
    "addr:housenumber":"64 c",
    "addr:street":"Parker St",
    "iso:country":"NZ",
    "sg:address":"64 c Parker St Springlands ",
    "sg:city":"Blenheim",
    "sg:classifiers":[
        {
            "category":"Personal",
            "type":"Services"
        }
    ],
    "sg:phone":"+64 3-578 8226",
    "sg:province":"Marlborough",
    "sg:tags":[
        "services",
        "home",
        "garden",
        "counselling"
    ],
    "wof:name":"Margret Saul",
    "wof:placetype":"venue"
},
  "geometry": {"coordinates":[173.94567900000001,-41.507465],"type":"Point"}
}