{
  "type": "Feature",
  "properties": {
    "addr:full":"Winery Cairnmuir Rd Bannockburn  Cromwell",
    "addr:street":"Cairnmuir Rd",
    "iso:country":"NZ",
    "sg:address":"Winery Cairnmuir Rd Bannockburn ",
    "sg:city":"Cromwell",
    "sg:classifiers":[
        {
            "category":"Restaurant",
            "type":"Food & Drink"
        }
    ],
    "sg:phone":"+64 3-445 0897",
    "sg:tags":[
        "wining",
        "dining"
    ],
    "sg:website":"http://www.akarua.com",
    "wof:name":"Akarua",
    "wof:placetype":"venue"
},
  "geometry": {"coordinates":[169.20155299999999,-45.0439],"type":"Point"}
}