{
  "type": "Feature",
  "properties": {
    "addr:full":"PO Box 7305 Taradale  Napier Hawke's Bay",
    "addr:housenumber":"po",
    "addr:postcode":"7305",
    "addr:street":"Box",
    "iso:country":"NZ",
    "sg:address":"PO Box 7305 Taradale ",
    "sg:city":"Napier",
    "sg:classifiers":[
        {
            "category":"Utilities",
            "subcategory":"Refuse",
            "type":"Services"
        }
    ],
    "sg:phone":"+64 6-844 1060",
    "sg:province":"Hawke's Bay",
    "sg:tags":[
        "bin",
        "hire",
        "garden",
        "cleaning",
        "rubbish",
        "home"
    ],
    "wof:name":"Clean Earth Ltd",
    "wof:placetype":"venue"
},
  "geometry": {"coordinates":[176.84719799999999,-39.534081],"type":"Point"}
}