{
  "type": "Feature",
  "properties": {
    "iso:country":"NZ",
    "sg:address":"6 Jellicoe St Te ",
    "sg:city":"Puke",
    "sg:classifiers":[
        {
            "category":"Retail",
            "subcategory":"Auto Repair",
            "type":"Services"
        }
    ],
    "sg:phone":"+64 7-573 7551",
    "sg:province":"Bay of Plenty",
    "sg:tags":[
        "automotive",
        "panel",
        "servicing",
        "beater"
    ],
    "wof:name":"Peake Panel & Paint 2000",
    "wof:placetype":"venue"
},
  "geometry": {"coordinates":[176.33049,-37.785503],"type":"Point"}
}