{
  "type": "Feature",
  "properties": {
    "addr:full":"211 Archers Rd Glenfield  Auckland Auckland",
    "addr:housenumber":"211",
    "addr:street":"Archers Rd",
    "iso:country":"NZ",
    "sg:address":"211 Archers Rd Glenfield ",
    "sg:city":"Auckland",
    "sg:orig_category":"Industrial: Engineering: Engineers - Precision",
    "sg:phone":"+64 9-444 4366",
    "sg:province":"Auckland",
    "wof:name":"Metpresco Engineering Ltd",
    "wof:placetype":"venue"
},
  "geometry": {"coordinates":[174.73971599999999,-36.780754],"type":"Point"}
}