{
  "type": "Feature",
  "properties": {
    "iso:country":"NZ",
    "sg:address":"211 Archers Rd Glenfield ",
    "sg:city":"Auckland",
    "sg:orig_category":"Industrial: Engineering: Engineers - Precision",
    "sg:phone":"+64 9-444 4366",
    "sg:province":"Auckland",
    "wof:name":"Metpresco Engineering Ltd",
    "wof:placetype":"venue"
},
  "geometry": {"coordinates":[174.739716,-36.780754],"type":"Point"}
}