{
  "type": "Feature",
  "properties": {
    "addr:full":"PO Box 100642 North Shore Mail Cen  Auckland Auckland",
    "addr:housenumber":"po;100642",
    "addr:street":"Box",
    "iso:country":"NZ",
    "sg:address":"PO Box 100642 North Shore Mail Cen ",
    "sg:city":"Auckland",
    "sg:orig_category":"Clothing And Fabric: Clothing: Uniforms",
    "sg:phone":"+64 9-414 7000",
    "sg:province":"Auckland",
    "wof:name":"Yakka Apparel Solutions Ltd",
    "wof:placetype":"venue"
},
  "geometry": {"coordinates":[174.92965699999999,-36.917198],"type":"Point"}
}