{
  "type": "Feature",
  "properties": {
    "addr:full":"8 Latimer Sq  Christchurch Canterbury",
    "addr:housenumber":"8",
    "addr:street":"Latimer Sq",
    "iso:country":"NZ",
    "sg:address":"8 Latimer Sq ",
    "sg:city":"Christchurch",
    "sg:orig_category":"Health And Beauty: Specialists: Chiropractors",
    "sg:phone":"+64 3-366 7674",
    "sg:province":"Canterbury",
    "wof:name":"B M Craig & Associates",
    "wof:placetype":"venue"
},
  "geometry": {"coordinates":[172.64347799999999,-43.531612],"type":"Point"}
}