{
  "type": "Feature",
  "properties": {
    "addr:full":"360 Te Rapa Rd Hamilton PO Box  10507 Waikato",
    "addr:housenumber":"360;po box",
    "addr:postcode":"10507",
    "addr:street":"Te Rapa Rd",
    "iso:country":"NZ",
    "sg:address":"360 Te Rapa Rd Hamilton PO Box ",
    "sg:city":"10507",
    "sg:classifiers":[
        {
            "category":"Autos & Motor Vehicles",
            "subcategory":"Automobile Sales",
            "type":"Retail Goods"
        }
    ],
    "sg:phone":"+64 7-849 5300",
    "sg:province":"Waikato",
    "sg:tags":[
        "home",
        "caravan",
        "leasing",
        "automotive"
    ],
    "wof:name":"Paradise Motorhome Rentals",
    "wof:placetype":"venue"
},
  "geometry": {"coordinates":[175.23936499999999,-37.752701],"type":"Point"}
}