{
  "type": "Feature",
  "properties": {
    "iso:country":"NZ",
    "sg:address":"402 Broadway Newmarket ",
    "sg:city":"Auckland",
    "sg:orig_category":"Clothing And Fabric: Clothing: Tailors",
    "sg:phone":"+64 9-524 4534",
    "sg:province":"Manawatu-Wanganui",
    "wof:name":"Broadway Tailoring",
    "wof:placetype":"venue"
},
  "geometry": {"coordinates":[174.777206,-36.872753],"type":"Point"}
}