{
  "type": "Feature",
  "properties": {
    "addr:full":"402 Broadway Newmarket  Auckland Manawatu-Wanganui",
    "addr:housenumber":"402",
    "addr:street":"Broadway",
    "iso:country":"NZ",
    "sg:address":"402 Broadway Newmarket ",
    "sg:city":"Auckland",
    "sg:orig_category":"Clothing And Fabric: Clothing: Tailors",
    "sg:phone":"+64 9-524 4534",
    "sg:province":"Manawatu-Wanganui",
    "wof:name":"Broadway Tailoring",
    "wof:placetype":"venue"
},
  "geometry": {"coordinates":[174.77720600000001,-36.872753],"type":"Point"}
}