{
  "type": "Feature",
  "properties": {
    "iso:country":"NZ",
    "sg:address":"Chertsey Rd ",
    "sg:city":"Methven",
    "sg:orig_category":"Home And Garden: Gardening: Products: Fertilisers",
    "sg:phone":"+64 3-302 8087",
    "wof:name":"Ravensdown Fertiliser Co-op Ltd",
    "wof:placetype":"venue"
},
  "geometry": {"coordinates":[171.72203099999999,-43.664062],"type":"Point"}
}