{
  "type": "Feature",
  "properties": {
    "iso:country":"NZ",
    "sg:address":"57 Lake Rd ",
    "sg:city":"Hamilton",
    "sg:classifiers":[
        {
            "category":"Autos & Motor Vehicles",
            "subcategory":"Automobile Sales",
            "type":"Retail Goods"
        }
    ],
    "sg:phone":"+64 7-847 0511",
    "sg:province":"Waikato",
    "sg:tags":[
        "automotive"
    ],
    "sg:website":"http://www.yellowpages.co.nz/pages/102661005/dp9761.html",
    "wof:name":"Carspot",
    "wof:placetype":"venue"
},
  "geometry": {"coordinates":[-75.536018,42.831947],"type":"Point"}
}