{
  "type": "Feature",
  "properties": {
    "addr:full":"Cnr High St & Queens Rd Wellington Wellington",
    "addr:street":"Cnr High St & Queens Rd",
    "iso:country":"NZ",
    "sg:address":"Cnr High St & Queens Rd",
    "sg:city":"Wellington",
    "sg:classifiers":[
        {
            "category":"Banks & Credit Unions",
            "subcategory":"Bank",
            "type":"Services"
        }
    ],
    "sg:phone":"+64 4661589",
    "sg:province":"Wellington",
    "wof:name":"National Bank of NZ Ltd",
    "wof:placetype":"venue"
},
  "geometry": {"coordinates":[-80.27001199999999,26.643909],"type":"Point"}
}