{
  "type": "Feature",
  "properties": {
    "iso:country":"NZ",
    "sg:address":"501 A Blenheim Rd Upper Riccarton ",
    "sg:city":"Christchurch",
    "sg:orig_category":"Automotive: General Services: Rental Vehicles",
    "sg:phone":"+64 3-348 8219",
    "sg:province":"Canterbury",
    "sg:website":"http://www.rhodesrentals.co.nz",
    "wof:name":"Rhodes Rental Group",
    "wof:placetype":"venue"
},
  "geometry": {"coordinates":[172.586792,-43.538479],"type":"Point"}
}