{
  "type": "Feature",
  "properties": {
    "iso:country":"NZ",
    "sg:address":"181 Thames St ",
    "sg:city":"Oamaru",
    "sg:orig_category":"Shopping: Retail Stores: Stationery",
    "sg:phone":"+64 3-434 7498",
    "sg:province":"Otago",
    "wof:name":"Oamaru Paper Plus",
    "wof:placetype":"venue"
},
  "geometry": {"coordinates":[170.97160299999999,-45.097],"type":"Point"}
}