{
  "type": "Feature",
  "properties": {
    "iso:country":"NZ",
    "sg:address":"www.streaminfo.co.nz ",
    "sg:city":"Wellington",
    "sg:orig_category":"Industrial: Instruments: Measuring Instruments",
    "sg:phone":"+64 508 463 569",
    "sg:province":"Wellington",
    "sg:website":"http://www.yellowpages.co.nz/pages/400007962/dp46343.html",
    "wof:name":"Stream Information",
    "wof:placetype":"venue"
},
  "geometry": {"coordinates":[-85.910454,33.827946],"type":"Point"}
}