{
  "type": "Feature",
  "properties": {
    "addr:full":"15 Kiwi Cre Tawa  Wellington Wellington",
    "addr:housenumber":"15",
    "addr:street":"Kiwi Cre",
    "iso:country":"NZ",
    "sg:address":"15 Kiwi Cre Tawa ",
    "sg:city":"Wellington",
    "sg:orig_category":"Home And Garden: Children: Child Related: Children'S Entertainment",
    "sg:phone":"+64 4-232 9389",
    "sg:province":"Wellington",
    "wof:name":"Boing Boing Bouncy Castles",
    "wof:placetype":"venue"
},
  "geometry": {"coordinates":[174.817566,-41.173225],"type":"Point"}
}