{
  "type": "Feature",
  "properties": {
    "addr:full":"Cnr Wakefield & Victoria St Alicetown  Wellington Wellington",
    "addr:street":"Cnr Wakefield & Victoria St",
    "iso:country":"NZ",
    "sg:address":"Cnr Wakefield & Victoria St Alicetown ",
    "sg:city":"Wellington",
    "sg:classifiers":[
        {
            "category":"Retail",
            "subcategory":"Auto Repair",
            "type":"Services"
        }
    ],
    "sg:phone":"+64 4-939 4444",
    "sg:province":"Wellington",
    "sg:tags":[
        "automotive",
        "panel",
        "servicing",
        "beater"
    ],
    "wof:name":"Custom Auto Bodies 1985 Ltd",
    "wof:placetype":"venue"
},
  "geometry": {"coordinates":[174.889038,-41.214451],"type":"Point"}
}