{
  "type": "Feature",
  "properties": {
    "iso:country":"NZ",
    "sg:address":"67 Maunu Rd Maunu ",
    "sg:city":"Whangarei",
    "sg:classifiers":[
        {
            "category":"Health Services",
            "subcategory":"Doctor",
            "type":"Services"
        }
    ],
    "sg:phone":"+64 9-438 1550",
    "sg:province":"Northland",
    "sg:tags":[
        "specialists",
        "surgery",
        "cosmetic",
        "beauty"
    ],
    "wof:name":"Chapman-Smith Dr Peter",
    "wof:placetype":"venue"
},
  "geometry": {"coordinates":[174.28280599999999,-35.739098],"type":"Point"}
}