{
  "type": "Feature",
  "properties": {
    "addr:full":"175 Pakuranga Rd Pakuranga  Auckland Auckland",
    "addr:housenumber":"175",
    "addr:street":"Pakuranga Rd",
    "iso:country":"NZ",
    "sg:address":"175 Pakuranga Rd Pakuranga ",
    "sg:city":"Auckland",
    "sg:classifiers":[
        {
            "category":"Health Services",
            "subcategory":"Dentist",
            "type":"Services"
        }
    ],
    "sg:phone":"+64 9-576 6720",
    "sg:province":"Auckland",
    "sg:tags":[
        "dental",
        "beauty"
    ],
    "wof:name":"Woodward Denis BDS",
    "wof:placetype":"venue"
},
  "geometry": {"coordinates":[174.875,-36.9109],"type":"Point"}
}