{
  "type": "Feature",
  "properties": {
    "addr:full":"PO Box 573 Whangaparapara Hibiscus  Hibiscus Coast Auckland",
    "addr:housenumber":"po",
    "addr:street":"Box 573 Whangaparapara",
    "iso:country":"NZ",
    "sg:address":"PO Box 573 Whangaparapara Hibiscus ",
    "sg:city":"Hibiscus Coast",
    "sg:orig_category":"Shopping: Hobbies And Games: Needlework",
    "sg:phone":"+64 9-424 0523",
    "sg:province":"Auckland",
    "wof:name":"N Z in Stitches",
    "wof:placetype":"venue"
},
  "geometry": {"coordinates":[174.70623800000001,-36.636581],"type":"Point"}
}