{
  "type": "Feature",
  "properties": {
    "addr:full":"70 Musselburgh Rse  Dunedin Otago",
    "addr:housenumber":"70;rse",
    "addr:street":"Musselburgh",
    "iso:country":"NZ",
    "sg:address":"70 Musselburgh Rse ",
    "sg:city":"Dunedin",
    "sg:orig_category":"Shopping: Retail Stores: Florists",
    "sg:phone":"+64 3-456 0550",
    "sg:province":"Otago",
    "sg:website":"http://www.simplyflowers.net.nz",
    "wof:name":"Simply Flowers",
    "wof:placetype":"venue"
},
  "geometry": {"coordinates":[170.51672400000001,-45.897865],"type":"Point"}
}