{
  "type": "Feature",
  "properties": {
    "addr:full":"79 Kemp Rd Massey  Auckland Auckland",
    "addr:housenumber":"79",
    "addr:street":"Kemp Rd",
    "iso:country":"NZ",
    "sg:address":"79 Kemp Rd Massey ",
    "sg:city":"Auckland",
    "sg:orig_category":"Sports And Leisure: Entertainment: Entertainers",
    "sg:phone":"+64 9-833 4119",
    "sg:province":"Auckland",
    "wof:name":"Carousel DJ's",
    "wof:placetype":"venue"
},
  "geometry": {"coordinates":[174.61309800000001,-36.834721],"type":"Point"}
}