{
  "type": "Feature",
  "properties": {
    "addr:full":"Cnr Crayne & Chapel Sts  Masterton Wellington",
    "addr:housenumber":"sts",
    "addr:street":"Cnr Crayne &",
    "iso:country":"NZ",
    "sg:address":"Cnr Crayne & Chapel Sts ",
    "sg:city":"Masterton",
    "sg:classifiers":[
        {
            "category":"Fast Food",
            "type":"Food & Drink"
        }
    ],
    "sg:phone":"+64 6-370 8261",
    "sg:province":"Wellington",
    "sg:tags":[
        "wining",
        "dining",
        "takeaway"
    ],
    "wof:name":"KFC",
    "wof:placetype":"venue"
},
  "geometry": {"coordinates":[175.65733299999999,-40.94931],"type":"Point"}
}