{
  "type": "Feature",
  "properties": {
    "iso:country":"NZ",
    "sg:address":"96 Blighs Rd Papanui ",
    "sg:city":"Christchurch",
    "sg:classifiers":[
        {
            "category":"Home & Garden",
            "subcategory":"Garden Supply",
            "type":"Retail Goods"
        }
    ],
    "sg:phone":"+64 3-352 8514",
    "sg:province":"Canterbury",
    "sg:tags":[
        "plant",
        "accessories",
        "artificial"
    ],
    "wof:name":"Gallery 96",
    "wof:placetype":"venue"
},
  "geometry": {"coordinates":[172.60427899999999,-43.503384],"type":"Point"}
}