{
  "type": "Feature",
  "properties": {
    "iso:country":"NZ",
    "sg:address":"11 Gloucester Park Rd Onehunga ",
    "sg:city":"Auckland",
    "sg:orig_category":"Transport: Boats And Marine: Boats: Boat Storage",
    "sg:phone":"+64 9-622 3366",
    "sg:province":"Auckland",
    "sg:website":"http://www.yellowpages.co.nz/for/locallockup/dp24205.html",
    "wof:name":"The Local Lockup Ltd",
    "wof:placetype":"venue"
},
  "geometry": {"coordinates":[174.782135,-36.927601],"type":"Point"}
}