{
  "type": "Feature",
  "properties": {
    "iso:country":"NZ",
    "sg:address":"60 A Wakefield St Onekawa ",
    "sg:city":"Napier",
    "sg:classifiers":[
        {
            "category":"Retail",
            "subcategory":"Auto Repair",
            "type":"Services"
        }
    ],
    "sg:phone":"+64 6-843 2789",
    "sg:province":"Hawke's Bay",
    "sg:tags":[
        "automotive",
        "panel",
        "servicing",
        "beater"
    ],
    "wof:name":"Bay Panel & Paint",
    "wof:placetype":"venue"
},
  "geometry": {"coordinates":[176.88159200000001,-39.501701],"type":"Point"}
}