{
  "type": "Feature",
  "properties": {
    "addr:full":"223 Ngatai Rd  Otumoetai",
    "addr:housenumber":"223",
    "addr:street":"Ngatai Rd",
    "iso:country":"NZ",
    "sg:address":"223 Ngatai Rd ",
    "sg:city":"Otumoetai",
    "sg:classifiers":[
        {
            "category":"Banks & Credit Unions",
            "subcategory":"Investment Brokerage",
            "type":"Services"
        }
    ],
    "sg:phone":"+64 25828599",
    "sg:tags":[
        "services",
        "industrial",
        "refrigeration",
        "servicing"
    ],
    "wof:name":"Mobile Refrigeration Specialists",
    "wof:placetype":"venue"
},
  "geometry": {"coordinates":[176.144958,-37.666126],"type":"Point"}
}