{
  "type": "Feature",
  "properties": {
    "addr:full":"14 Gloucester St Greenmeadows  Napier Hawke's Bay",
    "addr:housenumber":"14",
    "addr:street":"Gloucester St",
    "iso:country":"NZ",
    "sg:address":"14 Gloucester St Greenmeadows ",
    "sg:city":"Napier",
    "sg:orig_category":"Automotive: Accessories: Car Audio Systems",
    "sg:phone":"+64 6-844 1295",
    "sg:province":"Hawke's Bay",
    "wof:name":"Remac",
    "wof:placetype":"venue"
},
  "geometry": {"coordinates":[176.86296100000001,-39.525291],"type":"Point"}
}