{
  "type": "Feature",
  "properties": {
    "addr:full":"7 Vernon St Papakura  Auckland Auckland",
    "addr:housenumber":"7",
    "addr:street":"Vernon St",
    "iso:country":"NZ",
    "sg:address":"7 Vernon St Papakura ",
    "sg:city":"Auckland",
    "sg:orig_category":"Transport: Transportation: Carriers",
    "sg:phone":"+64 9-299 7909",
    "sg:province":"Auckland",
    "wof:name":"Auckland South Removals",
    "wof:placetype":"venue"
},
  "geometry": {"coordinates":[174.94508400000001,-37.060097],"type":"Point"}
}