{
  "type": "Feature",
  "properties": {
    "addr:full":"North Eyre Rd West Eyreton  Ohoka",
    "addr:street":"North Eyre Rd West;Ohoka",
    "iso:country":"NZ",
    "sg:address":"North Eyre Rd West Eyreton ",
    "sg:city":"Ohoka",
    "sg:orig_category":"Sports And Leisure: General: Halls",
    "sg:phone":"+64 3-312 5409",
    "wof:name":"West Eyreton Hall",
    "wof:placetype":"venue"
},
  "geometry": {"coordinates":[172.55763200000001,-43.367352],"type":"Point"}
}