{
  "type": "Feature",
  "properties": {
    "addr:full":"26 Ngahere Vws Orewa Hibiscus  Hibiscus Coast Auckland",
    "addr:housenumber":"26",
    "addr:street":"Ngahere Vws",
    "iso:country":"NZ",
    "sg:address":"26 Ngahere Vws Orewa Hibiscus ",
    "sg:city":"Hibiscus Coast",
    "sg:classifiers":[
        {
            "category":"Wholesale",
            "subcategory":"Electrical",
            "type":"Manufacturing & Wholesale Goods"
        }
    ],
    "sg:phone":"+64 9-426 9728",
    "sg:province":"Auckland",
    "sg:tags":[
        "wire",
        "electrical/electronic",
        "industrial",
        "electric",
        "cable"
    ],
    "wof:name":"Certified Cable Imports Ltd",
    "wof:placetype":"venue"
},
  "geometry": {"coordinates":[174.69012499999999,-36.582741],"type":"Point"}
}