{
  "type": "Feature",
  "properties": {
    "addr:full":"Unit I/21 Lorien Pl East Tamaki  Auckland Auckland",
    "addr:housenumber":"21",
    "addr:street":"Lorien Pl",
    "iso:country":"NZ",
    "sg:address":"Unit I/21 Lorien Pl East Tamaki ",
    "sg:city":"Auckland",
    "sg:orig_category":"Home And Garden: Furniture/Furnishings: Cabinetmakers",
    "sg:phone":"+64 9-274 6507",
    "sg:province":"Auckland",
    "wof:name":"Woodcare Cabinetmakers Ltd",
    "wof:placetype":"venue"
},
  "geometry": {"coordinates":[174.861771,-36.891823],"type":"Point"}
}