{
  "type": "Feature",
  "properties": {
    "addr:full":"3/56 Victoria St  Wellington Wellington",
    "addr:housenumber":"3 / 56",
    "addr:street":"Victoria St",
    "iso:country":"NZ",
    "sg:address":"3/56 Victoria St ",
    "sg:city":"Wellington",
    "sg:classifiers":[
        {
            "category":"Manufacturing",
            "subcategory":"Furniture",
            "type":"Manufacturing & Wholesale Goods"
        }
    ],
    "sg:phone":"+64 4-471 1065",
    "sg:province":"Wellington",
    "sg:tags":[
        "furniture/furnishings",
        "home",
        "garden",
        "manufacturer"
    ],
    "wof:name":"Furniture Works Ltd",
    "wof:placetype":"venue"
},
  "geometry": {"coordinates":[-2.513207,52.700092],"type":"Point"}
}