{
  "type": "Feature",
  "properties": {
    "addr:full":"10 Lilburn Cre Massey  Auckland Auckland",
    "addr:housenumber":"10;cre",
    "iso:country":"NZ",
    "sg:address":"10 Lilburn Cre Massey ",
    "sg:city":"Auckland",
    "sg:classifiers":[
        {
            "category":"Farming",
            "subcategory":"Fish & Marine Products",
            "type":"Manufacturing & Wholesale Goods"
        }
    ],
    "sg:phone":"+64 9-833 3154",
    "sg:province":"Auckland",
    "sg:tags":[
        "health",
        "beauty"
    ],
    "sg:website":"http://www.susan.mynuskin.com",
    "wof:name":"Healthy Options for you",
    "wof:placetype":"venue"
},
  "geometry": {"coordinates":[174.61833200000001,-36.845013],"type":"Point"}
}