{
  "type": "Feature",
  "properties": {
    "addr:full":"30 Rata St  Matamata Waikato",
    "addr:housenumber":"30",
    "addr:street":"Rata St",
    "iso:country":"NZ",
    "sg:address":"30 Rata St ",
    "sg:city":"Matamata",
    "sg:orig_category":"Transport: Transportation: Furniture Removal/Packers",
    "sg:phone":"+64 7-888 4413",
    "sg:province":"Waikato",
    "wof:name":"Matamata Furniture Movers",
    "wof:placetype":"venue"
},
  "geometry": {"coordinates":[175.77333100000001,-37.819366],"type":"Point"}
}