{
  "type": "Feature",
  "properties": {
    "addr:full":"10 Main Rd RD 1 Te  Kauwhata",
    "addr:housenumber":"10;1",
    "addr:street":"Main Rd Rd",
    "iso:country":"NZ",
    "sg:address":"10 Main Rd RD 1 Te ",
    "sg:city":"Kauwhata",
    "sg:classifiers":[
        {
            "category":"Deli",
            "type":"Food & Drink"
        }
    ],
    "sg:phone":"+64 7-826 4134",
    "sg:tags":[
        "delicatessen",
        "-"
    ],
    "wof:name":"The City Deli",
    "wof:placetype":"venue"
},
  "geometry": {"coordinates":[175.14735400000001,-37.403275],"type":"Point"}
}