{
  "type": "Feature",
  "properties": {
    "iso:country":"NZ",
    "sg:address":"Unit 11 8 Ulric St Plimmerton ",
    "sg:city":"Wellington",
    "sg:orig_category":"Industrial: Metal: Products: Aluminium Products",
    "sg:phone":"+64 4-233 2401",
    "sg:province":"Wellington",
    "wof:name":"Conservatory King Ltd",
    "wof:placetype":"venue"
},
  "geometry": {"coordinates":[174.86991900000001,-41.079834],"type":"Point"}
}