{
  "type": "Feature",
  "properties": {
    "iso:country":"NZ",
    "sg:address":"241 Foreshore Rd ",
    "sg:city":"Bluff",
    "sg:classifiers":[
        {
            "category":"Sports & Exercise",
            "subcategory":"Skate Park",
            "type":"Entertainment"
        }
    ],
    "sg:phone":"+64 3-212 7534",
    "sg:tags":[
        "arts",
        "museum",
        "leisure",
        "gallery"
    ],
    "wof:name":"Bluff Maritime Museum",
    "wof:placetype":"venue"
},
  "geometry": {"coordinates":[-109.546745,37.286579],"type":"Point"}
}