{
  "type": "Feature",
  "properties": {
    "iso:country":"NZ",
    "sg:address":"87 C Norton Rd ",
    "sg:city":"Hamilton",
    "sg:classifiers":[
        {
            "category":"Professional",
            "type":"Services"
        }
    ],
    "sg:phone":"+64 7-847 2734",
    "sg:province":"Waikato",
    "sg:tags":[
        "services",
        "car",
        "valet",
        "automotive"
    ],
    "wof:name":"Auto Grooming Services 2000",
    "wof:placetype":"venue"
},
  "geometry": {"coordinates":[-74.701767,40.203659],"type":"Point"}
}