{
  "type": "Feature",
  "properties": {
    "iso:country":"NZ",
    "sg:address":"3/715 Mt Albert Rd Royal Oak ",
    "sg:city":"Auckland",
    "sg:classifiers":[
        {
            "category":"Restaurant",
            "type":"Food & Drink"
        }
    ],
    "sg:phone":"+64 9-625 9809",
    "sg:province":"Auckland",
    "sg:tags":[
        "equipment",
        "machinery"
    ],
    "wof:name":"Trans Tasman Engineering Ltd",
    "wof:placetype":"venue"
},
  "geometry": {"coordinates":[174.77351379390001,-36.9100189209],"type":"Point"}
}