{
  "type": "Feature",
  "properties": {
    "iso:country":"NZ",
    "sg:address":"52 Princes St ",
    "sg:city":"Hawera",
    "sg:orig_category":"Automotive: Sales And Leasing: Trailers",
    "sg:phone":"+64 6-278 8644",
    "sg:province":"Taranaki",
    "wof:name":"Midwest Machinery",
    "wof:placetype":"venue"
},
  "geometry": {"coordinates":[174.283279,-39.591007],"type":"Point"}
}