{
  "type": "Feature",
  "properties": {
    "iso:country":"NZ",
    "sg:address":"6 B Yukon Pl Islington ",
    "sg:city":"Christchurch",
    "sg:orig_category":"Transport: Boats And Marine: Boats: Boat Maintenance",
    "sg:phone":"+64 3-349 5749",
    "sg:province":"Canterbury",
    "wof:name":"Jet Boat Base (The)",
    "wof:placetype":"venue"
},
  "geometry": {"coordinates":[172.516144,-43.55645],"type":"Point"}
}