{
  "type": "Feature",
  "properties": {
    "iso:country":"NZ",
    "sg:address":"89 Colombo St ",
    "sg:city":"Hamilton",
    "sg:orig_category":"Industrial: Metal: Stainless Steel",
    "sg:phone":"+64 7-846 0213",
    "sg:province":"Waikato",
    "wof:name":"Mercer Stainless Ltd",
    "wof:placetype":"venue"
},
  "geometry": {"coordinates":[-87.988968,34.142426],"type":"Point"}
}