{
  "type": "Feature",
  "properties": {
    "addr:full":"13 Memorial Ave Mt Roskill  Auckland Auckland",
    "addr:housenumber":"13",
    "addr:street":"Memorial Ave",
    "iso:country":"NZ",
    "sg:address":"13 Memorial Ave Mt Roskill ",
    "sg:city":"Auckland",
    "sg:classifiers":[
        {
            "category":"Autos & Motor Vehicles",
            "subcategory":"Automobile Sales",
            "type":"Retail Goods"
        }
    ],
    "sg:phone":"+64 9-620 5946",
    "sg:province":"Auckland",
    "sg:tags":[
        "home",
        "caravan",
        "leasing",
        "automotive"
    ],
    "wof:name":"Affordable Caravan Rentals",
    "wof:placetype":"venue"
},
  "geometry": {"coordinates":[174.740692,-36.906017],"type":"Point"}
}