{
  "type": "Feature",
  "properties": {
    "addr:full":"251 Blenhiem Rd Middleton  Christchurch Canterbury",
    "addr:housenumber":"251",
    "addr:street":"Blenhiem Rd",
    "iso:country":"NZ",
    "sg:address":"251 Blenhiem Rd Middleton ",
    "sg:city":"Christchurch",
    "sg:orig_category":"Industrial: Electrical/Electronic: Electric Motors",
    "sg:phone":"+64 3-343 3911",
    "sg:province":"Canterbury",
    "wof:name":"Maud Kirk Machinery Ltd",
    "wof:placetype":"venue"
},
  "geometry": {"coordinates":[172.58024599999999,-43.542606],"type":"Point"}
}