{
  "type": "Feature",
  "properties": {
    "iso:country":"NZ",
    "sg:address":"cnr Racecourse Rd & Tay St ",
    "sg:city":"Invercargill",
    "sg:classifiers":[
        {
            "category":"Travel",
            "subcategory":"Hotels & Motels",
            "type":"Entertainment"
        }
    ],
    "sg:phone":"+64 3-217 6195",
    "sg:province":"Southland",
    "sg:tags":[
        "holiday",
        "tourism",
        "accommodation"
    ],
    "wof:name":"Invercargill Licensing Trust",
    "wof:placetype":"venue"
},
  "geometry": {"coordinates":[168.352173,-46.41185],"type":"Point"}
}