{
  "type": "Feature",
  "properties": {
    "iso:country":"NZ",
    "sg:address":"7-11 Enterprise St Birkenhead ",
    "sg:city":"Auckland",
    "sg:classifiers":[
        {
            "category":"Shopping",
            "subcategory":"Clothing, Apparel, & Fashions",
            "type":"Retail Goods"
        }
    ],
    "sg:phone":"+64 9-480 6287",
    "sg:province":"Auckland",
    "sg:tags":[
        "knitted",
        "clothing",
        "fabric"
    ],
    "wof:name":"Vantage Knitwear NZ Ltd",
    "wof:placetype":"venue"
},
  "geometry": {"coordinates":[174.727982,-36.813007],"type":"Point"}
}