{
  "type": "Feature",
  "properties": {
    "iso:country":"NZ",
    "sg:address":"120 The Terrace ",
    "sg:city":"Wellington",
    "sg:orig_category":"Travel And Tourism: Accommodation: Apartments",
    "sg:phone":"+64 4-470 1820",
    "sg:province":"Waikato",
    "wof:name":"Allfields The Wellingtonian",
    "wof:placetype":"venue"
},
  "geometry": {"coordinates":[-85.910454,33.827946],"type":"Point"}
}