{
  "type": "Feature",
  "properties": {
    "addr:full":"31 Rata St  Inglewood",
    "addr:housenumber":"31",
    "addr:street":"Rata St",
    "iso:country":"NZ",
    "sg:address":"31 Rata St ",
    "sg:city":"Inglewood",
    "sg:orig_category":"Shopping: Retail Stores: Books: Bookshops",
    "sg:phone":"+64 6-756 7032",
    "wof:name":"Inglewood Book Centre",
    "wof:placetype":"venue"
},
  "geometry": {"coordinates":[-118.356224,33.961781],"type":"Point"}
}