{
  "type": "Feature",
  "properties": {
    "addr:full":"4 McDougall Ave Merivale  Christchurch Canterbury",
    "addr:housenumber":"4",
    "addr:street":"Mcdougall Ave",
    "iso:country":"NZ",
    "sg:address":"4 McDougall Ave Merivale ",
    "sg:city":"Christchurch",
    "sg:classifiers":[
        {
            "category":"Social Services",
            "subcategory":"Retirement Home",
            "type":"Services"
        }
    ],
    "sg:phone":"+64 3-355 5888",
    "sg:province":"Canterbury",
    "sg:tags":[
        "care",
        "garden",
        "elderly",
        "village"
    ],
    "wof:name":"Fitzroy on McDougall",
    "wof:placetype":"venue"
},
  "geometry": {"coordinates":[172.620758,-43.514442],"type":"Point"}
}