{
  "type": "Feature",
  "properties": {
    "iso:country":"NZ",
    "sg:address":"PO Box 60352 Titirangi ",
    "sg:city":"Auckland",
    "sg:classifiers":[
        {
            "category":"Education",
            "subcategory":"Music School",
            "type":"Public Place"
        }
    ],
    "sg:phone":"+64 9-536 6529",
    "sg:province":"Auckland",
    "sg:tags":[
        "sport",
        "teacher",
        "leisure"
    ],
    "wof:name":"Institute of Registered Music Teachers - Auckland",
    "wof:placetype":"venue"
},
  "geometry": {"coordinates":[174.66279599999999,-36.926861],"type":"Point"}
}