{
  "type": "Feature",
  "properties": {
    "iso:country":"NZ",
    "sg:address":"32 Scott Rd Papakura ",
    "sg:city":"Auckland",
    "sg:classifiers":[
        {
            "category":"Health Services",
            "subcategory":"Hospital",
            "type":"Services"
        }
    ],
    "sg:phone":"+64 9-298 1543",
    "sg:province":"Auckland",
    "sg:tags":[
        "beauty",
        "fitness"
    ],
    "wof:name":"Mind Training Centre Ltd",
    "wof:placetype":"venue"
},
  "geometry": {"coordinates":[174.956284,-37.064148],"type":"Point"}
}