{
  "type": "Feature",
  "properties": {
    "iso:country":"NZ",
    "sg:address":"70 Stuart St ",
    "sg:city":"Dunedin",
    "sg:classifiers":[
        {
            "category":"Sports & Exercise",
            "subcategory":"Ski Slope",
            "type":"Entertainment"
        }
    ],
    "sg:phone":"+64 3-474 1211",
    "sg:province":"Otago",
    "sg:tags":[
        "equipment",
        "snowboard",
        "goods",
        "shopping",
        "retailers"
    ],
    "sg:website":"http://www.yellowpages.co.nz/pages/201600137/dp39963.html",
    "wof:name":"R & R Sport",
    "wof:placetype":"venue"
},
  "geometry": {"coordinates":[-82.784721,28.013355],"type":"Point"}
}