{
  "type": "Feature",
  "properties": {
    "addr:full":"Bishopdale Shopping Centre Bishopdale  Christchurch Canterbury",
    "addr:street":"Centre Bishopdale Christchurch",
    "iso:country":"NZ",
    "sg:address":"Bishopdale Shopping Centre Bishopdale ",
    "sg:city":"Christchurch",
    "sg:classifiers":[
        {
            "category":"Home & Garden",
            "subcategory":"Kitchen Supply",
            "type":"Retail Goods"
        }
    ],
    "sg:phone":"+64 3-359 5118",
    "sg:province":"Canterbury",
    "sg:tags":[
        "shop",
        "pet",
        "pets"
    ],
    "wof:name":"Taffs Pet Plaza",
    "wof:placetype":"venue"
},
  "geometry": {"coordinates":[172.58607499999999,-43.487144],"type":"Point"}
}