{
  "type": "Feature",
  "properties": {
    "addr:full":"74 Spartan Rd Takanini  Auckland Auckland",
    "addr:housenumber":"74",
    "addr:street":"Spartan Rd",
    "iso:country":"NZ",
    "sg:address":"74 Spartan Rd Takanini ",
    "sg:city":"Auckland",
    "sg:classifiers":[
        {
            "category":"Home & Garden",
            "subcategory":"Hardware",
            "type":"Retail Goods"
        }
    ],
    "sg:phone":"+64 9-268 1880",
    "sg:province":"Auckland",
    "sg:tags":[
        "window",
        "fitting"
    ],
    "sg:website":"http://www.yellowpages.co.nz/pages/200668851/dp16180.html",
    "wof:name":"Total Look Blinds",
    "wof:placetype":"venue"
},
  "geometry": {"coordinates":[174.91630599999999,-37.03495],"type":"Point"}
}