{
  "type": "Feature",
  "properties": {
    "addr:full":"Broker House 1st Floor 14 Vulcan La Auckland Central Auckland Auckland",
    "addr:housenumber":"1st floor 14",
    "addr:street":"Vulcan La Auckland",
    "iso:country":"NZ",
    "sg:address":"Broker House 1st Floor 14 Vulcan La Auckland Central",
    "sg:city":"Auckland",
    "sg:orig_category":"Shopping: Sports Retailers: Sports Goods: Sportswear",
    "sg:phone":"+64 9-379 9285",
    "sg:province":"Auckland",
    "wof:name":"Bunny Boutique",
    "wof:placetype":"venue"
},
  "geometry": {"coordinates":[174.76454200000001,-36.848358],"type":"Point"}
}