{
  "type": "Feature",
  "properties": {
    "iso:country":"NZ",
    "sg:address":"204 Mangorei Rd New ",
    "sg:city":"Plymouth",
    "sg:classifiers":[
        {
            "category":"Professional",
            "subcategory":"Detective & Security Services",
            "type":"Services"
        }
    ],
    "sg:phone":"+64 6-758 8723",
    "sg:province":"Taranaki",
    "sg:tags":[
        "services",
        "automotive",
        "warrant",
        "fitness"
    ],
    "wof:name":"Merrilands Motors",
    "wof:placetype":"venue"
},
  "geometry": {"coordinates":[174.10307299999999,-39.067081],"type":"Point"}
}