{
  "type": "Feature",
  "properties": {
    "addr:full":"447 a Lake Rd Takapuna  Auckland Auckland",
    "addr:housenumber":"447 a",
    "addr:street":"Lake Rd",
    "iso:country":"NZ",
    "sg:address":"447 a Lake Rd Takapuna ",
    "sg:city":"Auckland",
    "sg:classifiers":[
        {
            "category":"Deli",
            "type":"Food & Drink"
        }
    ],
    "sg:phone":"+64 9-489 9903",
    "sg:province":"Auckland",
    "sg:tags":[
        "delicatessen",
        "-"
    ],
    "wof:name":"La Cucina",
    "wof:placetype":"venue"
},
  "geometry": {"coordinates":[174.77307099999999,-36.79044],"type":"Point"}
}