{
  "type": "Feature",
  "properties": {
    "addr:full":"30 Ben Lomond Cre Pakuranga  Auckland Auckland",
    "addr:housenumber":"30",
    "iso:country":"NZ",
    "sg:address":"30 Ben Lomond Cre Pakuranga ",
    "sg:city":"Auckland",
    "sg:classifiers":[
        {
            "category":"Sports & Exercise",
            "subcategory":"Sports Center",
            "type":"Entertainment"
        }
    ],
    "sg:phone":"+64 9-576 9685",
    "sg:province":"Auckland",
    "sg:tags":[
        "indoor",
        "-",
        "leisure",
        "sports"
    ],
    "wof:name":"Pakuranga Indoor Sports",
    "wof:placetype":"venue"
},
  "geometry": {"coordinates":[174.899033,-36.91547],"type":"Point"}
}