{
  "type": "Feature",
  "properties": {
    "addr:full":"65 Leach St New  Plymouth Taranaki",
    "addr:housenumber":"65",
    "addr:street":"Leach St",
    "iso:country":"NZ",
    "sg:address":"65 Leach St New ",
    "sg:city":"Plymouth",
    "sg:orig_category":"Automotive: General Services: Rental Vehicles",
    "sg:phone":"+64 6-757 8255",
    "sg:province":"Taranaki",
    "sg:website":"http://www.yellowpages.co.nz/for/smartcarrentals/dp21065.html",
    "wof:name":"Smart Car Rentals",
    "wof:placetype":"venue"
},
  "geometry": {"coordinates":[-116.81972500000001,43.97221],"type":"Point"}
}