{
  "type": "Feature",
  "properties": {
    "iso:country":"NZ",
    "sg:address":"51-55 Ruataniwha St ",
    "sg:city":"Waipawa",
    "sg:orig_category":"Home And Garden: Accessories: Hardware",
    "sg:phone":"+64 6-857 8051",
    "wof:name":"Mitre 10",
    "wof:placetype":"venue"
},
  "geometry": {"coordinates":[176.580994,-39.943665],"type":"Point"}
}