{
  "type": "Feature",
  "properties": {
    "iso:country":"NZ",
    "sg:address":"276 Great South Rd Otahuhu ",
    "sg:city":"Auckland",
    "sg:orig_category":"Shopping: Retail Stores: Cds, Cassettes And Records",
    "sg:phone":"+64 9-270 4083",
    "sg:province":"Auckland",
    "wof:name":"Music Hut",
    "wof:placetype":"venue"
},
  "geometry": {"coordinates":[174.842514,-36.942741],"type":"Point"}
}