{
  "type": "Feature",
  "properties": {
    "addr:full":"Five Cross Rds  Hamilton Waikato",
    "iso:country":"NZ",
    "sg:address":"Five Cross Rds ",
    "sg:city":"Hamilton",
    "sg:classifiers":[
        {
            "category":"Fast Food",
            "type":"Food & Drink"
        }
    ],
    "sg:phone":"+64 7-855 5728",
    "sg:province":"Waikato",
    "sg:tags":[
        "wining",
        "dining",
        "takeaway"
    ],
    "wof:name":"Macao Takeaways",
    "wof:placetype":"venue"
},
  "geometry": {"coordinates":[-74.756958,40.222664],"type":"Point"}
}