{
  "type": "Feature",
  "properties": {
    "iso:country":"NZ",
    "sg:address":"20 Williamson Ave Ponsonby ",
    "sg:city":"Auckland",
    "sg:orig_category":"Sports And Leisure: Sports: Equestrian",
    "sg:phone":"+64 9-360 0961",
    "sg:province":"Auckland",
    "sg:website":"http://www.petvet.co.nz",
    "wof:name":"Ponsonby Veterinary Centre",
    "wof:placetype":"venue"
},
  "geometry": {"coordinates":[174.742416,-36.85326],"type":"Point"}
}