{
  "type": "Feature",
  "properties": {
    "addr:full":"cnr Vale St & Bureta Rd Otumoetai  Tauranga Bay of Plenty",
    "addr:street":"Cnr Vale St & Bureta Rd",
    "iso:country":"NZ",
    "sg:address":"cnr Vale St & Bureta Rd Otumoetai ",
    "sg:city":"Tauranga",
    "sg:classifiers":[
        {
            "category":"Food & Beverages",
            "subcategory":"Liquor & Beverages",
            "type":"Retail Goods"
        }
    ],
    "sg:phone":"+64 7-576 6116",
    "sg:province":"Bay of Plenty",
    "sg:tags":[
        "drink",
        "outlet"
    ],
    "wof:name":"Birds Liquorsave",
    "wof:placetype":"venue"
},
  "geometry": {"coordinates":[176.14771999999999,-37.670521],"type":"Point"}
}