{
  "type": "Feature",
  "properties": {
    "iso:country":"NZ",
    "sg:address":"6 Kiwi St St Leonards ",
    "sg:city":"Dunedin",
    "sg:classifiers":[
        {
            "category":"Travel",
            "subcategory":"Bed & Breakfast",
            "type":"Entertainment"
        }
    ],
    "sg:phone":"+64 3-471 0690",
    "sg:province":"Otago",
    "sg:tags":[
        "tourism",
        "accommodation"
    ],
    "wof:name":"Harbourside Homestay",
    "wof:placetype":"venue"
},
  "geometry": {"coordinates":[170.577332,-45.84959],"type":"Point"}
}