{
  "type": "Feature",
  "properties": {
    "iso:country":"NZ",
    "sg:address":"Centennial Dve New ",
    "sg:city":"Plymouth",
    "sg:orig_category":"Storage: Storage",
    "sg:phone":"+64 6-751 3371",
    "sg:province":"Taranaki",
    "wof:name":"Bulk Storage Terminals Ltd",
    "wof:placetype":"venue"
},
  "geometry": {"coordinates":[-116.819725,43.97221],"type":"Point"}
}