{
  "type": "Feature",
  "properties": {
    "iso:country":"NZ",
    "sg:address":"33 Meeanee Qy Westshore ",
    "sg:city":"Napier",
    "sg:classifiers":[
        {
            "category":"Travel",
            "subcategory":"Hotels & Motels",
            "type":"Entertainment"
        }
    ],
    "sg:phone":"+64 6-835 4108",
    "sg:province":"Hawke's Bay",
    "sg:tags":[
        "lodge",
        "tourism",
        "accommodation"
    ],
    "wof:name":"Reef Motel",
    "wof:placetype":"venue"
},
  "geometry": {"coordinates":[176.88130200000001,-39.478134],"type":"Point"}
}