{
  "type": "Feature",
  "properties": {
    "iso:country":"NZ",
    "sg:address":"PO Box 41072 St Lukes ",
    "sg:city":"Auckland",
    "sg:orig_category":"Industrial: Parts: Pipes, Tubes And Cabling: Heating Cable And Tubes",
    "sg:phone":"+64 9-849 6568",
    "sg:province":"Auckland",
    "wof:name":"Wirsbo NZ Ltd",
    "wof:placetype":"venue"
},
  "geometry": {"coordinates":[174.728973,-36.877918],"type":"Point"}
}