{
  "type": "Feature",
  "properties": {
    "iso:country":"NZ",
    "sg:address":"201 C D Farm Rd ",
    "sg:city":"Levin",
    "sg:classifiers":[
        {
            "category":"Utilities",
            "subcategory":"Sewage",
            "type":"Services"
        }
    ],
    "sg:phone":"+64 800 442 628",
    "sg:province":"Manawatu-Wanganui",
    "sg:tags":[
        "home",
        "tank",
        "garden",
        "septic"
    ],
    "wof:name":"JB's Septic Tank Cleaning",
    "wof:placetype":"venue"
},
  "geometry": {"coordinates":[175.285324,-40.625278],"type":"Point"}
}