{
  "type": "Feature",
  "properties": {
    "iso:country":"NZ",
    "sg:address":"25 La Veta Ave Mt Albert ",
    "sg:city":"Auckland",
    "sg:classifiers":[
        {
            "category":"Home & Garden",
            "subcategory":"Building Materials",
            "type":"Retail Goods"
        }
    ],
    "sg:phone":"+64 9-849 6228",
    "sg:province":"Auckland",
    "sg:tags":[
        "related"
    ],
    "sg:website":"http://www.designandbuild.co.nz",
    "wof:name":"Design & Build Co Ltd",
    "wof:placetype":"venue"
},
  "geometry": {"coordinates":[174.71792600000001,-36.891903],"type":"Point"}
}