{
  "type": "Feature",
  "properties": {
    "iso:country":"NZ",
    "sg:address":"1 Malvern St Te Papapa ",
    "sg:city":"Auckland",
    "sg:orig_category":"Automotive: Accessories: Motor Accessories",
    "sg:phone":"+64 9-634 7707",
    "sg:province":"Auckland",
    "wof:name":"G & T Autos",
    "wof:placetype":"venue"
},
  "geometry": {"coordinates":[174.801727,-36.921162],"type":"Point"}
}