{
  "type": "Feature",
  "properties": {
    "iso:country":"NZ",
    "sg:address":"Christchurch ",
    "sg:city":"Christchurch",
    "sg:orig_category":"Shopping: Retail Stores: Dolls",
    "sg:phone":"+64 3-366 4851",
    "sg:province":"Canterbury",
    "wof:name":"Dolls City Hospital",
    "wof:placetype":"venue"
},
  "geometry": {"coordinates":[-1.77656,50.73407],"type":"Point"}
}