{
  "type": "Feature",
  "properties": {
    "addr:full":"174 Clarkin Rd Fairfield  Hamilton Waikato",
    "addr:housenumber":"174",
    "addr:street":"Clarkin Rd",
    "iso:country":"NZ",
    "sg:address":"174 Clarkin Rd Fairfield ",
    "sg:city":"Hamilton",
    "sg:classifiers":[
        {
            "category":"Food & Beverages",
            "subcategory":"Liquor & Beverages",
            "type":"Retail Goods"
        }
    ],
    "sg:phone":"+64 7-855 5713",
    "sg:province":"Waikato",
    "sg:tags":[
        "drink",
        "outlet"
    ],
    "wof:name":"Clarky's Wines Ales & Spirits",
    "wof:placetype":"venue"
},
  "geometry": {"coordinates":[175.28022799999999,-37.764851],"type":"Point"}
}