{
  "type": "Feature",
  "properties": {
    "iso:country":"NZ",
    "sg:address":"Main Rd Awatoto PO Box 110 Clive ",
    "sg:city":"Napier",
    "sg:classifiers":[
        {
            "category":"Restaurant",
            "type":"Food & Drink"
        }
    ],
    "sg:phone":"+64 6-834 0998",
    "sg:province":"Hawke's Bay",
    "sg:tags":[
        "sea"
    ],
    "wof:name":"Deco Seafoods - A Division of HBA Aquaculture Ltd",
    "wof:placetype":"venue"
},
  "geometry": {"coordinates":[176.917801,-39.541538],"type":"Point"}
}