{
  "type": "Feature",
  "properties": {
    "iso:country":"NZ",
    "sg:address":"27 Vialou St ",
    "sg:city":"Hamilton",
    "sg:classifiers":[
        {
            "category":"Personal",
            "type":"Services"
        }
    ],
    "sg:phone":"+64 7-834 1197",
    "sg:province":"Waikato",
    "sg:tags":[
        "arrangement",
        "wedding"
    ],
    "sg:website":"http://www.yellowpages.co.nz/for/utting/dp16740.html",
    "wof:name":"Utting Sound",
    "wof:placetype":"venue"
},
  "geometry": {"coordinates":[-87.988968,34.142426],"type":"Point"}
}