{
  "type": "Feature",
  "properties": {
    "addr:full":"12 Kopanga Rd Havelock North  Hastings Hawke's Bay",
    "addr:housenumber":"12",
    "addr:street":"Kopanga Rd",
    "iso:country":"NZ",
    "sg:address":"12 Kopanga Rd Havelock North ",
    "sg:city":"Hastings",
    "sg:classifiers":[
        {
            "category":"Health Services",
            "subcategory":"Clinic",
            "type":"Services"
        }
    ],
    "sg:phone":"+64 6-877 2359",
    "sg:province":"Hawke's Bay",
    "sg:tags":[
        "services",
        "therapy",
        "natural",
        "beauty"
    ],
    "wof:name":"Hellerwork Hawkes Bay",
    "wof:placetype":"venue"
},
  "geometry": {"coordinates":[176.88061500000001,-39.681347],"type":"Point"}
}