{
  "type": "Feature",
  "properties": {
    "iso:country":"NZ",
    "sg:address":"82 Albert St Palmerston ",
    "sg:city":"Palmerston North",
    "sg:classifiers":[
        {
            "category":"Home & Garden",
            "subcategory":"Kitchen Supply",
            "type":"Retail Goods"
        }
    ],
    "sg:phone":"+64 6-357 2007",
    "sg:province":"Manawatu-Wanganui",
    "sg:tags":[
        "shop",
        "pet",
        "pets"
    ],
    "wof:name":"Pet Essentials",
    "wof:placetype":"venue"
},
  "geometry": {"coordinates":[175.622818,-40.348724],"type":"Point"}
}