{
  "type": "Feature",
  "properties": {
    "iso:country":"NZ",
    "sg:address":"PO Box 36293 Northcote ",
    "sg:city":"Auckland",
    "sg:classifiers":[
        {
            "category":"Health Services",
            "subcategory":"Clinic",
            "type":"Services"
        }
    ],
    "sg:phone":"+64 9-418 4151",
    "sg:province":"Auckland",
    "sg:tags":[
        "trainer",
        "personal",
        "beauty",
        "fitness"
    ],
    "wof:name":"Balance Pt Ltd",
    "wof:placetype":"venue"
},
  "geometry": {"coordinates":[174.747849,-36.801125],"type":"Point"}
}