{
  "type": "Feature",
  "properties": {
    "addr:full":"Argyle St Mosgiel  Dunedin Otago",
    "addr:street":"Argyle St",
    "iso:country":"NZ",
    "sg:address":"Argyle St Mosgiel ",
    "sg:city":"Dunedin",
    "sg:classifiers":[
        {
            "category":"Social Services",
            "subcategory":"Retirement Home",
            "type":"Services"
        }
    ],
    "sg:phone":"+64 3-489 7712",
    "sg:province":"Otago",
    "sg:tags":[
        "elderly",
        "convalescent",
        "garden",
        "rest",
        "care"
    ],
    "wof:name":"Mossbrae Hospital",
    "wof:placetype":"venue"
},
  "geometry": {"coordinates":[170.346664,-45.879505],"type":"Point"}
}