{
  "type": "Feature",
  "properties": {
    "addr:full":"78 Russell St  Dunedin Otago",
    "addr:housenumber":"78",
    "addr:street":"Russell St",
    "iso:country":"NZ",
    "sg:address":"78 Russell St ",
    "sg:city":"Dunedin",
    "sg:classifiers":[
        {
            "category":"Social Services",
            "subcategory":"Child Care",
            "type":"Services"
        }
    ],
    "sg:phone":"+64 3-477 9186",
    "sg:province":"Otago",
    "sg:tags":[
        "home",
        "garden",
        "children"
    ],
    "sg:website":"http://www.yellowpages.co.nz/for/dunedinchildcare/dp659.html",
    "wof:name":"Dunedin Community Childcare Assn",
    "wof:placetype":"venue"
},
  "geometry": {"coordinates":[-82.784721,28.013355],"type":"Point"}
}