{
  "type": "Feature",
  "properties": {
    "addr:full":"31 Carluke St Paparangi  Wellington Wellington",
    "addr:housenumber":"31",
    "addr:street":"Carluke St",
    "iso:country":"NZ",
    "sg:address":"31 Carluke St Paparangi ",
    "sg:city":"Wellington",
    "sg:classifiers":[
        {
            "category":"Retail",
            "subcategory":"Auto Repair",
            "type":"Services"
        }
    ],
    "sg:phone":"+64 4-973 3947",
    "sg:province":"Wellington",
    "sg:tags":[
        "automotive",
        "electric",
        "servicing"
    ],
    "wof:name":"Berry P D",
    "wof:placetype":"venue"
},
  "geometry": {"coordinates":[174.818512,-41.218582],"type":"Point"}
}