{
  "type": "Feature",
  "properties": {
    "addr:full":"68-72 Normanby St  Dargaville Northland",
    "addr:housenumber":"68-72",
    "addr:street":"Normanby St",
    "iso:country":"NZ",
    "sg:address":"68-72 Normanby St ",
    "sg:city":"Dargaville",
    "sg:classifiers":[
        {
            "category":"Social Services",
            "subcategory":"Retirement Home",
            "type":"Services"
        }
    ],
    "sg:phone":"+64 9-439 6214",
    "sg:province":"Northland",
    "sg:tags":[
        "elderly",
        "convalescent",
        "garden",
        "rest",
        "care"
    ],
    "wof:name":"Norfolk Court Rest Home",
    "wof:placetype":"venue"
},
  "geometry": {"coordinates":[173.872986,-35.937576],"type":"Point"}
}