{
  "type": "Feature",
  "properties": {
    "addr:full":"12 Coronation St Belmont  Auckland Auckland",
    "addr:housenumber":"12",
    "addr:street":"Coronation St",
    "iso:country":"NZ",
    "sg:address":"12 Coronation St Belmont ",
    "sg:city":"Auckland",
    "sg:orig_category":"Health And Beauty: Medical: Hospitals",
    "sg:phone":"+64 9-489 7292",
    "sg:province":"Auckland",
    "wof:name":"Belmont Hospital (Takapuna)",
    "wof:placetype":"venue"
},
  "geometry": {"coordinates":[174.784515,-36.804943],"type":"Point"}
}