{
  "type": "Feature",
  "properties": {
    "addr:full":"31 York Pl  Dunedin Otago",
    "addr:housenumber":"31",
    "addr:street":"York Pl",
    "iso:country":"NZ",
    "sg:address":"31 York Pl ",
    "sg:city":"Dunedin",
    "sg:classifiers":[
        {
            "category":"Education",
            "subcategory":"Special Training",
            "type":"Public Place"
        }
    ],
    "sg:phone":"+64 3-477 1527",
    "sg:province":"Otago",
    "sg:tags":[
        "aid",
        "medical",
        "health",
        "beauty",
        "first"
    ],
    "wof:name":"Red Cross",
    "wof:placetype":"venue"
},
  "geometry": {"coordinates":[170.50225800000001,-45.871468],"type":"Point"}
}