{
  "type": "Feature",
  "properties": {
    "addr:full":"52 A Bellevue Rd Bellevue  Tauranga Bay of Plenty",
    "addr:housenumber":"52",
    "addr:street":"A Bellevue Rd",
    "iso:country":"NZ",
    "sg:address":"52 A Bellevue Rd Bellevue ",
    "sg:city":"Tauranga",
    "sg:classifiers":[
        {
            "category":"Insurance",
            "subcategory":"Health Insurance",
            "type":"Services"
        }
    ],
    "sg:phone":"+64 7-576 9659",
    "sg:province":"Bay of Plenty",
    "sg:tags":[
        "specialist",
        "beauty"
    ],
    "wof:name":"Bellevue Osteopathic Practice",
    "wof:placetype":"venue"
},
  "geometry": {"coordinates":[176.12910500000001,-37.685863],"type":"Point"}
}