{
  "type": "Feature",
  "properties": {
    "addr:full":"1880 Gt North Rd Avondale  Auckland Auckland",
    "addr:housenumber":"1880",
    "addr:street":"Gt North Rd",
    "iso:country":"NZ",
    "sg:address":"1880 Gt North Rd Avondale ",
    "sg:city":"Auckland",
    "sg:classifiers":[
        {
            "category":"Bars & Pubs",
            "subcategory":"Lounge",
            "type":"Food & Drink"
        }
    ],
    "sg:phone":"+64 9-820 0040",
    "sg:province":"Auckland",
    "sg:tags":[
        "baker",
        "-"
    ],
    "wof:name":"Avondale Home Bakery",
    "wof:placetype":"venue"
},
  "geometry": {"coordinates":[174.69686899999999,-36.894958],"type":"Point"}
}