{
  "type": "Feature",
  "properties": {
    "addr:full":"PO Box 348  Hawera Taranaki",
    "addr:housenumber":"po",
    "addr:postcode":"348",
    "addr:street":"Box",
    "iso:country":"NZ",
    "sg:address":"PO Box 348 ",
    "sg:city":"Hawera",
    "sg:classifiers":[
        {
            "category":"Home & Garden",
            "subcategory":"Building Materials",
            "type":"Retail Goods"
        }
    ],
    "sg:phone":"+64 6-278 8324",
    "sg:province":"Taranaki",
    "sg:tags":[
        "electrician",
        "related"
    ],
    "wof:name":"Mark Frost Electrical Ltd",
    "wof:placetype":"venue"
},
  "geometry": {"coordinates":[174.27131700000001,-39.57584],"type":"Point"}
}