{
  "type": "Feature",
  "properties": {
    "addr:full":"PO Box 113  Methven",
    "addr:housenumber":"po",
    "addr:street":"Box 113",
    "iso:country":"NZ",
    "sg:address":"PO Box 113 ",
    "sg:city":"Methven",
    "sg:orig_category":"Farming: Horticulture: Grain And Seed",
    "sg:phone":"+64 3-302 8115",
    "wof:name":"South Pacific Seeds (NZ) Ltd",
    "wof:placetype":"venue"
},
  "geometry": {"coordinates":[171.644272,-43.631443],"type":"Point"}
}