{
  "type": "Feature",
  "properties": {
    "iso:country":"NZ",
    "sg:address":"Mowhanau Beach Kai ",
    "sg:city":"Iwi",
    "sg:orig_category":"Automotive: Parts And Supplies: Windscreens",
    "sg:phone":"+64 25535814",
    "wof:name":"Carson John Windscreen Repairs",
    "wof:placetype":"venue"
},
  "geometry": {"coordinates":[174.904922,-39.887192],"type":"Point"}
}