{
  "type": "Feature",
  "properties": {
    "iso:country":"NZ",
    "sg:address":"Marahau Beach RD2 ",
    "sg:city":"Motueka",
    "sg:classifiers":[
        {
            "category":"Travel",
            "subcategory":"Travel Agent",
            "type":"Entertainment"
        }
    ],
    "sg:province":"Tasman",
    "sg:tags":[
        "tour",
        "tourism",
        "adventure",
        "sightseeing"
    ],
    "wof:name":"Abel Tasman Kayaks",
    "wof:placetype":"venue"
},
  "geometry": {"coordinates":[173.013443,-41.108101],"type":"Point"}
}