{
  "type": "Feature",
  "properties": {
    "iso:country":"NZ",
    "sg:address":"12 B East St Papakura ",
    "sg:city":"Auckland",
    "sg:orig_category":"Food And Drink: Meats: Butchers",
    "sg:phone":"+64 9-298 0219",
    "sg:province":"Auckland",
    "wof:name":"The Butchers Hook",
    "wof:placetype":"venue"
},
  "geometry": {"coordinates":[174.94072,-37.062439],"type":"Point"}
}