{
  "type": "Feature",
  "properties": {
    "iso:country":"NZ",
    "sg:address":"82 Coleridge St Sydenham ",
    "sg:city":"Christchurch",
    "sg:classifiers":[
        {
            "category":"Manufacturing",
            "subcategory":"Tools & Machinery",
            "type":"Manufacturing & Wholesale Goods"
        }
    ],
    "sg:phone":"+64 3-365 2506",
    "sg:province":"Canterbury",
    "sg:tags":[
        "equipment",
        "industrial",
        "label"
    ],
    "wof:name":"Foilprint Labels Limited",
    "wof:placetype":"venue"
},
  "geometry": {"coordinates":[172.644226,-43.545994],"type":"Point"}
}