{
  "type": "Feature",
  "properties": {
    "addr:full":"49 Harrington St Port  Chalmers",
    "addr:housenumber":"49",
    "addr:street":"Harrington St",
    "iso:country":"NZ",
    "sg:address":"49 Harrington St Port ",
    "sg:city":"Chalmers",
    "sg:orig_category":"Industrial: Services: Gasfitters",
    "sg:phone":"+64 3-472 7346",
    "wof:name":"Otago Gas Contracting",
    "wof:placetype":"venue"
},
  "geometry": {"coordinates":[170.61805699999999,-45.824066],"type":"Point"}
}