{
  "type": "Feature",
  "properties": {
    "iso:country":"NZ",
    "sg:address":"49 Harrington St Port ",
    "sg:city":"Chalmers",
    "sg:orig_category":"Industrial: Services: Gasfitters",
    "sg:phone":"+64 3-472 7346",
    "wof:name":"Otago Gas Contracting",
    "wof:placetype":"venue"
},
  "geometry": {"coordinates":[170.618057,-45.824066],"type":"Point"}
}