{
  "type": "Feature",
  "properties": {
    "iso:country":"NZ",
    "sg:address":"35 Mansfield Ave ",
    "sg:city":"Christchurch",
    "sg:classifiers":[
        {
            "category":"Social Services",
            "subcategory":"Retirement Home",
            "type":"Services"
        }
    ],
    "sg:phone":"+64 3-355 0074",
    "sg:province":"Canterbury",
    "sg:tags":[
        "personal",
        "services",
        "garden",
        "elderly",
        "care"
    ],
    "wof:name":"Nurse Maude Association",
    "wof:placetype":"venue"
},
  "geometry": {"coordinates":[-76.537834,37.605659],"type":"Point"}
}