{
  "type": "Feature",
  "properties": {
    "addr:full":"47 Helwick St  Wanaka Otago",
    "addr:housenumber":"47",
    "addr:street":"Helwick St",
    "iso:country":"NZ",
    "sg:address":"47 Helwick St ",
    "sg:city":"Wanaka",
    "sg:classifiers":[
        {
            "category":"Food & Beverages",
            "subcategory":"Liquor & Beverages",
            "type":"Retail Goods"
        }
    ],
    "sg:phone":"+64 3-443 7818",
    "sg:province":"Otago",
    "sg:tags":[
        "drink",
        "outlet"
    ],
    "wof:name":"Pembroke Wines & Spirits",
    "wof:placetype":"venue"
},
  "geometry": {"coordinates":[169.137024,-44.697044],"type":"Point"}
}