{
  "type": "Feature",
  "properties": {
    "iso:country":"NZ",
    "sg:address":"461 A Jackson St Petone Lower ",
    "sg:city":"Hutt",
    "sg:classifiers":[
        {
            "category":"Shopping",
            "type":"Retail Goods"
        }
    ],
    "sg:phone":"+64 4-568 6605",
    "sg:province":"Wellington",
    "sg:tags":[
        "chemical",
        "industrial",
        "cleaning",
        "maintenance"
    ],
    "wof:name":"Space Industries Ltd",
    "wof:placetype":"venue"
},
  "geometry": {"coordinates":[174.896042,-41.230465],"type":"Point"}
}