{
  "type": "Feature",
  "properties": {
    "iso:country":"NZ",
    "sg:address":"111 Dalrymple St ",
    "sg:city":"Invercargill",
    "sg:orig_category":"Health And Beauty: Beauty: Hairdressers",
    "sg:phone":"+64 3-214 4570",
    "sg:province":"Southland",
    "wof:name":"Salon Triple One",
    "wof:placetype":"venue"
},
  "geometry": {"coordinates":[168.358597,-46.426064],"type":"Point"}
}