{
  "type": "Feature",
  "properties": {
    "addr:full":"8 C Queen St Waiuku  Pukekohe Auckland",
    "addr:housenumber":"8 c",
    "addr:street":"Queen St",
    "iso:country":"NZ",
    "sg:address":"8 C Queen St Waiuku ",
    "sg:city":"Pukekohe",
    "sg:classifiers":[
        {
            "category":"Bars & Pubs",
            "subcategory":"Lounge",
            "type":"Food & Drink"
        }
    ],
    "sg:phone":"+64 9-235 8868",
    "sg:province":"Auckland",
    "sg:tags":[
        "baker",
        "-"
    ],
    "wof:name":"Bread-Crumb Bakery",
    "wof:placetype":"venue"
},
  "geometry": {"coordinates":[174.901321,-37.200748],"type":"Point"}
}