{
  "type": "Feature",
  "properties": {
    "iso:country":"NZ",
    "sg:address":"15 Margaret Pl ",
    "sg:city":"Frankton",
    "sg:orig_category":"Industrial: Parts: Pipes, Tubes And Cabling: Pipes",
    "sg:phone":"+64 3-441 4740",
    "sg:province":"Waikato",
    "wof:name":"Mico Pipelines",
    "wof:placetype":"venue"
},
  "geometry": {"coordinates":[-85.766556,40.219994],"type":"Point"}
}