{
  "type": "Feature",
  "properties": {
    "iso:country":"NZ",
    "sg:address":"27 Elizabeth St ",
    "sg:city":"Gore",
    "sg:orig_category":"Home And Garden: Gardening: Services: Lawnmowing Services",
    "sg:phone":"+64 3-208 9354",
    "sg:province":"Southland",
    "wof:name":"Mr Green Home Services.",
    "wof:placetype":"venue"
},
  "geometry": {"coordinates":[-95.116547,35.530331],"type":"Point"}
}