{
  "type": "Feature",
  "properties": {
    "addr:full":"41 Motupipi St  Takaka",
    "addr:housenumber":"41",
    "addr:street":"Motupipi St",
    "iso:country":"NZ",
    "sg:address":"41 Motupipi St ",
    "sg:city":"Takaka",
    "sg:orig_category":"Automotive: Parts And Supplies: Tyres",
    "sg:phone":"+64 3-525 8809",
    "wof:name":"Knoxys Tyres",
    "wof:placetype":"venue"
},
  "geometry": {"coordinates":[172.81320199999999,-40.856056],"type":"Point"}
}