{
  "type": "Feature",
  "properties": {
    "iso:country":"NZ",
    "sg:address":"1171 Coatsville Riverhead Hwy 28 ",
    "sg:city":"Auckland",
    "sg:classifiers":[
        {
            "category":"Brewery",
            "type":"Food & Drink"
        }
    ],
    "sg:phone":"+64 9-412 5555",
    "sg:province":"Auckland",
    "sg:tags":[
        "brewer"
    ],
    "wof:name":"Pilot Bay Brewing Company",
    "wof:placetype":"venue"
},
  "geometry": {"coordinates":[174.770416,-36.884109],"type":"Point"}
}