{
  "type": "Feature",
  "properties": {
    "addr:full":"cnr Matthews Av & Empire St  Kaitaia Northland",
    "addr:housenumber":"cnr",
    "addr:street":"Matthews Av & Empire St",
    "iso:country":"NZ",
    "sg:address":"cnr Matthews Av & Empire St ",
    "sg:city":"Kaitaia",
    "sg:classifiers":[
        {
            "category":"Utilities",
            "subcategory":"Water",
            "type":"Services"
        }
    ],
    "sg:phone":"+64 9-408 2660",
    "sg:province":"Northland",
    "sg:tags":[
        "storage"
    ],
    "wof:name":"Rogers & Rogers Plumbers",
    "wof:placetype":"venue"
},
  "geometry": {"coordinates":[173.259445,-35.114208],"type":"Point"}
}