{
  "type": "Feature",
  "properties": {
    "addr:full":"200 Victoria St W Auckland Central  Auckland Auckland",
    "addr:housenumber":"200",
    "addr:street":"Victoria St W",
    "iso:country":"NZ",
    "sg:address":"200 Victoria St W Auckland Central ",
    "sg:city":"Auckland",
    "sg:classifiers":[
        {
            "category":"Sports & Exercise",
            "subcategory":"Winter Sports",
            "type":"Entertainment"
        }
    ],
    "sg:phone":"+64 9-309 6102",
    "sg:province":"Auckland",
    "sg:tags":[
        "equestrian",
        "-",
        "leisure",
        "sports",
        "animal",
        "insurance"
    ],
    "wof:name":"Pet Medicare Ltd",
    "wof:placetype":"venue"
},
  "geometry": {"coordinates":[174.75654599999999,-36.848282],"type":"Point"}
}