{
  "type": "Feature",
  "properties": {
    "iso:country":"NZ",
    "sg:address":"2 Bryant St Tinwald ",
    "sg:city":"Ashburton",
    "sg:classifiers":[
        {
            "category":"Manufacturing",
            "subcategory":"Furniture",
            "type":"Manufacturing & Wholesale Goods"
        }
    ],
    "sg:phone":"+64 3-308 2557",
    "sg:province":"Canterbury",
    "sg:tags":[
        "furniture/furnishings",
        "home",
        "garden",
        "manufacturer"
    ],
    "wof:name":"Pine Time Furniture",
    "wof:placetype":"venue"
},
  "geometry": {"coordinates":[171.71444700000001,-43.921505],"type":"Point"}
}