{
  "type": "Feature",
  "properties": {
    "iso:country":"NZ",
    "sg:address":"122 Musselburgh Rse ",
    "sg:city":"Dunedin",
    "sg:classifiers":[
        {
            "category":"Social Services",
            "subcategory":"Child Care",
            "type":"Services"
        }
    ],
    "sg:phone":"+64 3-455 6045",
    "sg:province":"Otago",
    "sg:tags":[
        "home",
        "garden",
        "children"
    ],
    "wof:name":"Family Ties Educare",
    "wof:placetype":"venue"
},
  "geometry": {"coordinates":[170.519821,-45.897797],"type":"Point"}
}