{
  "type": "Feature",
  "properties": {
    "iso:country":"NZ",
    "sg:address":"277 Broadway ",
    "sg:city":"Newmarket",
    "sg:classifiers":[
        {
            "category":"Shopping Center",
            "type":"Public Place"
        }
    ],
    "sg:phone":"+64 800 746 7277",
    "sg:province":"Manawatu-Wanganui",
    "sg:tags":[
        "mall",
        "retail",
        "stores"
    ],
    "wof:name":"Two Double Seven",
    "wof:placetype":"venue"
},
  "geometry": {"coordinates":[-93.352074,44.575508],"type":"Point"}
}