{
  "type": "Feature",
  "properties": {
    "iso:country":"NZ",
    "sg:address":"cnr Queen St & Main Rd Kopu ",
    "sg:city":"Thames",
    "sg:orig_category":"Industrial: Products",
    "sg:phone":"+64 7-868 9149",
    "sg:province":"Waikato",
    "wof:name":"Fisher Coromandel",
    "wof:placetype":"venue"
},
  "geometry": {"coordinates":[175.546799,-37.13969],"type":"Point"}
}