{
  "type": "Feature",
  "properties": {
    "addr:full":"Mill St  Marton",
    "addr:street":"Mill St",
    "iso:country":"NZ",
    "sg:address":"Mill St ",
    "sg:city":"Marton",
    "sg:classifiers":[
        {
            "category":"Social Services",
            "subcategory":"Child Care",
            "type":"Services"
        }
    ],
    "sg:phone":"+64 6-327 8418",
    "sg:tags":[
        "home",
        "garden",
        "children"
    ],
    "wof:name":"Marton",
    "wof:placetype":"venue"
},
  "geometry": {"coordinates":[175.377274,-40.078644],"type":"Point"}
}