{
  "type": "Feature",
  "properties": {
    "addr:full":"5 Oreti St West Gore  Gore Southland",
    "addr:housenumber":"5",
    "addr:street":"Oreti St",
    "iso:country":"NZ",
    "sg:address":"5 Oreti St West Gore ",
    "sg:city":"Gore",
    "sg:orig_category":"Farming: Machinery: Tractors",
    "sg:phone":"+64 3-208 6895",
    "sg:province":"Southland",
    "wof:name":"Waimea Truck & Tractor Ltd",
    "wof:placetype":"venue"
},
  "geometry": {"coordinates":[168.926941,-46.115513],"type":"Point"}
}