{
  "type": "Feature",
  "properties": {
    "iso:country":"NZ",
    "sg:address":"651 Dominion Rd Balmoral ",
    "sg:city":"Auckland",
    "sg:orig_category":"Health And Beauty: Dental: Dentists",
    "sg:phone":"+64 9-630 0205",
    "sg:province":"Auckland",
    "wof:name":"Alderson K S",
    "wof:placetype":"venue"
},
  "geometry": {"coordinates":[174.747467,-36.886997],"type":"Point"}
}