{
  "type": "Feature",
  "properties": {
    "addr:full":"24 A London St  Dunedin Otago",
    "addr:housenumber":"24",
    "addr:street":"A London St",
    "iso:country":"NZ",
    "sg:address":"24 A London St ",
    "sg:city":"Dunedin",
    "sg:orig_category":"Health And Beauty: Beauty: Hairdressers",
    "sg:phone":"+64 3-477 2411",
    "sg:province":"Otago",
    "wof:name":"The Head of London St",
    "wof:placetype":"venue"
},
  "geometry": {"coordinates":[-82.784721,28.013355],"type":"Point"}
}