{
  "type": "Feature",
  "properties": {
    "iso:country":"NZ",
    "sg:address":"392 Colombo St Sydenham ",
    "sg:city":"Christchurch",
    "sg:classifiers":[
        {
            "category":"Shopping",
            "subcategory":"Hobbies, Toys, & Games",
            "type":"Retail Goods"
        }
    ],
    "sg:phone":"+64 3-377 3779",
    "sg:province":"Canterbury",
    "sg:tags":[
        "hobby"
    ],
    "wof:name":"Images Ltd",
    "wof:placetype":"venue"
},
  "geometry": {"coordinates":[172.63679500000001,-43.54528],"type":"Point"}
}