{
  "type": "Feature",
  "properties": {
    "addr:full":"35 Monmouth St  Tauranga Bay of Plenty",
    "addr:housenumber":"35",
    "addr:street":"Monmouth St",
    "iso:country":"NZ",
    "sg:address":"35 Monmouth St ",
    "sg:city":"Tauranga",
    "sg:orig_category":"Industrial: Engineering: Engineers: Engineers - Consulting",
    "sg:phone":"+64 7-578 8071",
    "sg:province":"Bay of Plenty",
    "wof:name":"Fairclough & King Consultants Ltd",
    "wof:placetype":"venue"
},
  "geometry": {"coordinates":[176.167328,-37.679932],"type":"Point"}
}