{
  "type": "Feature",
  "properties": {
    "addr:full":"23 North Rd Waikiwi  Invercargill Southland",
    "addr:housenumber":"23",
    "addr:street":"North Rd",
    "iso:country":"NZ",
    "sg:address":"23 North Rd Waikiwi ",
    "sg:city":"Invercargill",
    "sg:classifiers":[
        {
            "category":"Manufacturing",
            "subcategory":"Tools & Machinery",
            "type":"Manufacturing & Wholesale Goods"
        }
    ],
    "sg:phone":"+64 3-215 9049",
    "sg:province":"Southland",
    "sg:tags":[
        "equipment",
        "industrial",
        "hydraulic"
    ],
    "wof:name":"Wilson Geo W & Sons Ltd",
    "wof:placetype":"venue"
},
  "geometry": {"coordinates":[168.34761,-46.388763],"type":"Point"}
}