{
  "type": "Feature",
  "properties": {
    "iso:country":"NZ",
    "sg:address":"34 c Liffiton St ",
    "sg:city":"Wanganui",
    "sg:classifiers":[
        {
            "category":"Personal",
            "type":"Services"
        }
    ],
    "sg:phone":"+64 6-348 7011",
    "sg:province":"Manawatu-Wanganui",
    "sg:tags":[
        "celebrant",
        "arrangements",
        "marriage",
        "wedding"
    ],
    "wof:name":"Joll Tom JP",
    "wof:placetype":"venue"
},
  "geometry": {"coordinates":[175.040817,-39.940788],"type":"Point"}
}