{
  "type": "Feature",
  "properties": {
    "addr:full":"997 Matakana Rd Matakana  Warkworth Auckland",
    "addr:housenumber":"997",
    "addr:street":"Matakana Rd",
    "iso:country":"NZ",
    "sg:address":"997 Matakana Rd Matakana ",
    "sg:city":"Warkworth",
    "sg:orig_category":"Automotive: General Services: Service Stations",
    "sg:phone":"+64 9-422 7105",
    "sg:province":"Auckland",
    "wof:name":"Matakana Motors Ltd",
    "wof:placetype":"venue"
},
  "geometry": {"coordinates":[174.714325,-36.348728],"type":"Point"}
}