{
  "type": "Feature",
  "properties": {
    "addr:full":"95 A Main South Rd  Christchurch Canterbury",
    "addr:housenumber":"95",
    "addr:street":"A Main South Rd",
    "iso:country":"NZ",
    "sg:address":"95 A Main South Rd ",
    "sg:city":"Christchurch",
    "sg:classifiers":[
        {
            "category":"Home & Garden",
            "subcategory":"Home Furnishings",
            "type":"Retail Goods"
        }
    ],
    "sg:phone":"+64 800 861 300",
    "sg:province":"Canterbury",
    "sg:tags":[
        "furniture/furnishings",
        "bedding",
        "bed"
    ],
    "wof:name":"Waterbed Components",
    "wof:placetype":"venue"
},
  "geometry": {"coordinates":[-76.537834,37.605659],"type":"Point"}
}