{
  "type": "Feature",
  "properties": {
    "iso:country":"NZ",
    "sg:address":"29 Leitrim St Redwoodtown ",
    "sg:city":"Blenheim",
    "sg:orig_category":"Sports And Leisure: Entertainment: Entertainers",
    "sg:phone":"+64 3-578 9400",
    "sg:province":"Marlborough",
    "wof:name":"Grace",
    "wof:placetype":"venue"
},
  "geometry": {"coordinates":[173.944427,-41.523991],"type":"Point"}
}