{
  "type": "Feature",
  "properties": {
    "addr:full":"29 Leitrim St Redwoodtown  Blenheim Marlborough",
    "addr:housenumber":"29",
    "addr:street":"Leitrim St",
    "iso:country":"NZ",
    "sg:address":"29 Leitrim St Redwoodtown ",
    "sg:city":"Blenheim",
    "sg:orig_category":"Sports And Leisure: Entertainment: Entertainers",
    "sg:phone":"+64 3-578 9400",
    "sg:province":"Marlborough",
    "wof:name":"Grace",
    "wof:placetype":"venue"
},
  "geometry": {"coordinates":[173.94442699999999,-41.523991],"type":"Point"}
}