{
  "type": "Feature",
  "properties": {
    "iso:country":"NZ",
    "sg:address":"State Highway 1 ",
    "sg:city":"Otaki",
    "sg:classifiers":[
        {
            "category":"Shopping",
            "subcategory":"Pets & Pet Supplies",
            "type":"Retail Goods"
        }
    ],
    "sg:phone":"+64 6-364 3397",
    "sg:tags":[
        "boarding",
        "garden",
        "pets",
        "catteries",
        "home",
        "kennel"
    ],
    "wof:name":"Zaminka Dog Motels Premier Boarding Kennels",
    "wof:placetype":"venue"
},
  "geometry": {"coordinates":[175.203552,-40.730976],"type":"Point"}
}