{
  "type": "Feature",
  "properties": {
    "iso:country":"NZ",
    "sg:address":"PO Box 11272 Sockburn ",
    "sg:city":"Christchurch",
    "sg:classifiers":[
        {
            "category":"Transit Center",
            "subcategory":"Freight",
            "type":"Transportation"
        }
    ],
    "sg:phone":"+64 3-349 2402",
    "sg:province":"Canterbury",
    "sg:tags":[
        "distribution",
        "-",
        "transport"
    ],
    "wof:name":"Procter & Gamble NPD Inc",
    "wof:placetype":"venue"
},
  "geometry": {"coordinates":[172.55043,-43.534966],"type":"Point"}
}