{
  "type": "Feature",
  "properties": {
    "addr:full":"3 Keyte St  Whangarei Northland",
    "addr:housenumber":"3",
    "addr:street":"Keyte St",
    "iso:country":"NZ",
    "sg:address":"3 Keyte St ",
    "sg:city":"Whangarei",
    "sg:classifiers":[
        {
            "category":"Personal",
            "type":"Services"
        }
    ],
    "sg:phone":"+64 9-437 5563",
    "sg:province":"Northland",
    "sg:tags":[
        "services",
        "home",
        "garden",
        "counselling"
    ],
    "wof:name":"Centre for Self Empowerment",
    "wof:placetype":"venue"
},
  "geometry": {"coordinates":[174.318375,-35.704182],"type":"Point"}
}