{
  "type": "Feature",
  "properties": {
    "addr:full":"105 Princess St Palmerston  Palmerston North Manawatu-Wanganui",
    "addr:housenumber":"105",
    "addr:street":"Princess St",
    "iso:country":"NZ",
    "sg:address":"105 Princess St Palmerston ",
    "sg:city":"Palmerston North",
    "sg:classifiers":[
        {
            "category":"Building & Trades",
            "subcategory":"Cleaning & Sanitation",
            "type":"Services"
        }
    ],
    "sg:phone":"+64 6-354 8031",
    "sg:province":"Manawatu-Wanganui",
    "sg:tags":[
        "equipment",
        "industrial",
        "maintenance"
    ],
    "wof:name":"Crystal Health NZ Ltd",
    "wof:placetype":"venue"
},
  "geometry": {"coordinates":[175.61734000000001,-40.356434],"type":"Point"}
}