{
  "type": "Feature",
  "properties": {
    "addr:full":"7 Gibbons St Upper  Hutt Wellington",
    "addr:housenumber":"7",
    "addr:street":"Gibbons St",
    "iso:country":"NZ",
    "sg:address":"7 Gibbons St Upper ",
    "sg:city":"Hutt",
    "sg:classifiers":[
        {
            "category":"Travel",
            "subcategory":"Hotels & Motels",
            "type":"Entertainment"
        }
    ],
    "sg:phone":"+64 4-528 3612",
    "sg:province":"Wellington",
    "sg:tags":[
        "tourism",
        "-",
        "rental",
        "accommodation"
    ],
    "wof:name":"Purdy Property Management Ltd MREINZ",
    "wof:placetype":"venue"
},
  "geometry": {"coordinates":[175.069031,-41.12458],"type":"Point"}
}