{
  "type": "Feature",
  "properties": {
    "iso:country":"NZ",
    "sg:address":"1 Main St ",
    "sg:city":"Greytown",
    "sg:classifiers":[
        {
            "category":"Retail",
            "subcategory":"Auto Repair",
            "type":"Services"
        }
    ],
    "sg:phone":"+64 6-304 9898",
    "sg:tags":[
        "automotive",
        "panel",
        "servicing",
        "beater"
    ],
    "wof:name":"Ross Smash Repairs",
    "wof:placetype":"venue"
},
  "geometry": {"coordinates":[-71.990334,41.325802],"type":"Point"}
}