{
  "type": "Feature",
  "properties": {
    "addr:full":"87 Old Highway Rd Omokoroa  Tauranga Bay of Plenty",
    "addr:housenumber":"87",
    "addr:street":"Old Highway Rd",
    "iso:country":"NZ",
    "sg:address":"87 Old Highway Rd Omokoroa ",
    "sg:city":"Tauranga",
    "sg:orig_category":"Farming: Horticulture: Flowers",
    "sg:phone":"+64 7-548 1250",
    "sg:province":"Bay of Plenty",
    "wof:name":"Bennett P & D",
    "wof:placetype":"venue"
},
  "geometry": {"coordinates":[176.14475999999999,-37.703152],"type":"Point"}
}