{
  "type": "Feature",
  "properties": {
    "iso:country":"NZ",
    "sg:address":"PO Box 4311 Mt Maunganui South ",
    "sg:city":"Tauranga",
    "sg:classifiers":[
        {
            "category":"Farming",
            "subcategory":"Farm",
            "type":"Manufacturing & Wholesale Goods"
        }
    ],
    "sg:phone":"+64 7-543 1173",
    "sg:province":"Bay of Plenty",
    "sg:tags":[
        "-",
        "ostrich"
    ],
    "wof:name":"Bay Of Plenty Ostriches Ltd",
    "wof:placetype":"venue"
},
  "geometry": {"coordinates":[176.186279,-37.641052],"type":"Point"}
}