{
  "type": "Feature",
  "properties": {
    "iso:country":"NZ",
    "sg:address":"Bayfair Mall ",
    "sg:city":"Tauranga",
    "sg:classifiers":[
        {
            "category":"Retail",
            "subcategory":"Laundry & Dry Cleaning",
            "type":"Services"
        }
    ],
    "sg:phone":"+64 7-575 9000",
    "sg:province":"Auckland",
    "sg:tags":[
        "repair",
        "clothing",
        "fabric",
        "cleaner"
    ],
    "wof:name":"Bayfair Drycleaners",
    "wof:placetype":"venue"
},
  "geometry": {"coordinates":[176.144745,-37.703156],"type":"Point"}
}