{
  "type": "Feature",
  "properties": {
    "addr:full":"3/182 Jervois Rd Herne Bay  Auckland Auckland",
    "addr:housenumber":"3 / 182",
    "addr:street":"Jervois Rd",
    "iso:country":"NZ",
    "sg:address":"3/182 Jervois Rd Herne Bay ",
    "sg:city":"Auckland",
    "sg:classifiers":[
        {
            "category":"Education",
            "subcategory":"Special Training",
            "type":"Public Place"
        }
    ],
    "sg:phone":"+64 9-360 8928",
    "sg:province":"Auckland",
    "sg:tags":[
        "tutor",
        "coach",
        "teacher"
    ],
    "wof:name":"Kip McGrath Education Centres (NZ) Ltd",
    "wof:placetype":"venue"
},
  "geometry": {"coordinates":[174.730164,-36.848415],"type":"Point"}
}