{
  "type": "Feature",
  "properties": {
    "iso:country":"NZ",
    "sg:address":"1 Melrose St Newmarket ",
    "sg:city":"Auckland",
    "sg:orig_category":"Industrial: Parts: Pipes, Tubes And Cabling: Cables",
    "sg:phone":"+64 9-523 3256",
    "sg:province":"Auckland",
    "wof:name":"Hi-Tech Brake & Clutch Services",
    "wof:placetype":"venue"
},
  "geometry": {"coordinates":[174.774338,-36.867004],"type":"Point"}
}