{
  "type": "Feature",
  "properties": {
    "iso:country":"NZ",
    "sg:address":"25 Davis Cre Newmarket ",
    "sg:city":"Auckland",
    "sg:classifiers":[
        {
            "category":"Coffee & Tea",
            "type":"Food & Drink"
        }
    ],
    "sg:phone":"+64 9-522 2822",
    "sg:province":"Auckland",
    "sg:tags":[
        "vegetable",
        "fruit",
        "veges"
    ],
    "wof:name":"Primor Produce Ltd",
    "wof:placetype":"venue"
},
  "geometry": {"coordinates":[174.77763400000001,-36.865864],"type":"Point"}
}