{
  "type": "Feature",
  "properties": {
    "addr:full":"573 Worcester St Linwood  Christchurch Canterbury",
    "addr:housenumber":"573",
    "addr:street":"Worcester St",
    "iso:country":"NZ",
    "sg:address":"573 Worcester St Linwood ",
    "sg:city":"Christchurch",
    "sg:classifiers":[
        {
            "category":"Shopping",
            "subcategory":"Pets & Pet Supplies",
            "type":"Retail Goods"
        }
    ],
    "sg:phone":"+64 3-381 1949",
    "sg:province":"Canterbury",
    "sg:tags":[
        "home",
        "grooming",
        "garden",
        "pets"
    ],
    "wof:name":"Barbies Pet Salon",
    "wof:placetype":"venue"
},
  "geometry": {"coordinates":[172.668182,-43.530724],"type":"Point"}
}