{
  "type": "Feature",
  "properties": {
    "addr:full":"Benhar RD 2  Balclutha",
    "addr:street":"Benhar Rd 2",
    "iso:country":"NZ",
    "sg:address":"Benhar RD 2 ",
    "sg:city":"Balclutha",
    "sg:classifiers":[
        {
            "category":"Travel",
            "subcategory":"Bed & Breakfast",
            "type":"Entertainment"
        }
    ],
    "sg:phone":"+64 3-418 2507",
    "sg:tags":[
        "tourism",
        "accommodation"
    ],
    "wof:name":"Lesmahagow Bed and Breakfast",
    "wof:placetype":"venue"
},
  "geometry": {"coordinates":[169.74681100000001,-46.234802],"type":"Point"}
}