{
  "type": "Feature",
  "properties": {
    "iso:country":"NZ",
    "sg:address":"235 Commerce St ",
    "sg:city":"Kaitaia",
    "sg:orig_category":"Travel And Tourism: Accommodation: Backpackers",
    "sg:phone":"+64 9-408 1275",
    "sg:province":"Northland",
    "wof:name":"Main Street Backpackers",
    "wof:placetype":"venue"
},
  "geometry": {"coordinates":[173.26226800000001,-35.112064],"type":"Point"}
}