{
  "type": "Feature",
  "properties": {
    "addr:full":"Level 19 Coopers & Lybrand Tower 23-29 Albert St, Auckland Central  Auckland Auckland",
    "addr:housenumber":"19;23-29",
    "addr:street":"Coopers &;Albert St",
    "iso:country":"NZ",
    "sg:address":"Level 19 Coopers & Lybrand Tower 23-29 Albert St, Auckland Central ",
    "sg:city":"Auckland",
    "sg:classifiers":[
        {
            "category":"Banks & Credit Unions",
            "subcategory":"Investment Brokerage",
            "type":"Services"
        }
    ],
    "sg:phone":"+64 9-356 9300",
    "sg:province":"Auckland",
    "sg:tags":[
        "chemical",
        "industrial",
        "-",
        "compounds"
    ],
    "wof:name":"Methanex New Zealand Limited",
    "wof:placetype":"venue"
},
  "geometry": {"coordinates":[174.76454200000001,-36.848358],"type":"Point"}
}