{
  "type": "Feature",
  "properties": {
    "addr:full":"31 Puriri Rd Whenuapai  Auckland Auckland",
    "addr:housenumber":"31",
    "addr:street":"Puriri Rd",
    "iso:country":"NZ",
    "sg:address":"31 Puriri Rd Whenuapai ",
    "sg:city":"Auckland",
    "sg:orig_category":"Transport: Boats And Marine: Boats: Boat Maintenance",
    "sg:phone":"+64 9-416 8469",
    "sg:province":"Auckland",
    "wof:name":"Pilkington Boats Limited",
    "wof:placetype":"venue"
},
  "geometry": {"coordinates":[174.62333699999999,-36.78857],"type":"Point"}
}