{
  "type": "Feature",
  "properties": {
    "addr:full":"205 St Aubyn St E  Hastings Hawke's Bay",
    "addr:housenumber":"205",
    "addr:street":"St Aubyn St E",
    "iso:country":"NZ",
    "sg:address":"205 St Aubyn St E ",
    "sg:city":"Hastings",
    "sg:classifiers":[
        {
            "category":"Retail",
            "subcategory":"Auto Repair",
            "type":"Services"
        }
    ],
    "sg:phone":"+64 6-878 6664",
    "sg:province":"Hawke's Bay",
    "sg:tags":[
        "automotive",
        "panel",
        "servicing",
        "beater"
    ],
    "wof:name":"Olympic Panel & Spray",
    "wof:placetype":"venue"
},
  "geometry": {"coordinates":[-81.508163,29.711214],"type":"Point"}
}