{
  "type": "Feature",
  "properties": {
    "addr:full":"Shop 11, 1st Floor Downtown Shopping Centre Queen St, Auckland Central  Auckland Auckland",
    "addr:housenumber":"11 1st",
    "addr:street":"Floor;Queen St",
    "iso:country":"NZ",
    "sg:address":"Shop 11, 1st Floor Downtown Shopping Centre Queen St, Auckland Central ",
    "sg:city":"Auckland",
    "sg:classifiers":[
        {
            "category":"Health Services",
            "subcategory":"Podiatrist",
            "type":"Services"
        }
    ],
    "sg:phone":"+64 9-379 4662",
    "sg:province":"Auckland",
    "sg:tags":[
        "lens",
        "optical",
        "contact",
        "beauty"
    ],
    "wof:name":"Eye Worx Optometrists Downtown",
    "wof:placetype":"venue"
},
  "geometry": {"coordinates":[174.76454200000001,-36.848358],"type":"Point"}
}