{
  "type": "Feature",
  "properties": {
    "iso:country":"NZ",
    "sg:address":"27 Lincoln St ",
    "sg:city":"Hamilton",
    "sg:classifiers":[
        {
            "category":"Home & Garden",
            "subcategory":"Building Materials",
            "type":"Retail Goods"
        }
    ],
    "sg:phone":"+64 7-847 1032",
    "sg:province":"Waikato",
    "sg:tags":[
        "fittings",
        "door",
        "garage"
    ],
    "wof:name":"Dominator Garage Door Centre",
    "wof:placetype":"venue"
},
  "geometry": {"coordinates":[-70.882339,42.620861],"type":"Point"}
}