{
  "type": "Feature",
  "properties": {
    "iso:country":"NZ",
    "sg:address":"2 Mountain Rd Opononi ",
    "sg:city":"Kaikohe",
    "sg:classifiers":[
        {
            "category":"Travel",
            "subcategory":"Bed & Breakfast",
            "type":"Entertainment"
        }
    ],
    "sg:phone":"+64 9-405 8815",
    "sg:tags":[
        "tourism",
        "accommodation"
    ],
    "wof:name":"Okopako Lodge & Horse Trekking Y.H.A Hostel",
    "wof:placetype":"venue"
},
  "geometry": {"coordinates":[173.390335,-35.506851],"type":"Point"}
}