{
  "type": "Feature",
  "properties": {
    "iso:country":"NZ",
    "sg:address":"468 Pollen St ",
    "sg:city":"Thames",
    "sg:orig_category":"Industrial: Equipment And Machinery: Specialist Equipment: Machinery: Sewing Machines",
    "sg:phone":"+64 7-868 8190",
    "sg:province":"Waikato",
    "wof:name":"Christies Sewing Centre & Linen Closet",
    "wof:placetype":"venue"
},
  "geometry": {"coordinates":[-104.41848,20.632469],"type":"Point"}
}