{
  "type": "Feature",
  "properties": {
    "addr:full":"103 b Riccarton Rd Riccarton  Christchurch Canterbury",
    "addr:housenumber":"103 b",
    "addr:street":"Riccarton Rd;Christchurch",
    "iso:country":"NZ",
    "sg:address":"103 b Riccarton Rd Riccarton ",
    "sg:city":"Christchurch",
    "sg:classifiers":[
        {
            "category":"Shopping",
            "subcategory":"Musical Instruments",
            "type":"Retail Goods"
        }
    ],
    "sg:phone":"+64 3-348 6357",
    "sg:province":"Canterbury",
    "sg:tags":[
        "sport",
        "music",
        "leisure"
    ],
    "wof:name":"Sedley Wells (1988) Ltd",
    "wof:placetype":"venue"
},
  "geometry": {"coordinates":[172.60116600000001,-43.529804],"type":"Point"}
}