{
  "type": "Feature",
  "properties": {
    "addr:full":"40 Ascot Ave Remuera  Auckland Auckland",
    "addr:housenumber":"40",
    "addr:street":"Ascot Ave",
    "iso:country":"NZ",
    "sg:address":"40 Ascot Ave Remuera ",
    "sg:city":"Auckland",
    "sg:classifiers":[
        {
            "category":"Insurance",
            "subcategory":"Health Insurance",
            "type":"Services"
        }
    ],
    "sg:phone":"+64 9-529 4123",
    "sg:province":"Auckland",
    "sg:tags":[
        "beauty",
        "supply"
    ],
    "wof:name":"The Nail Studio",
    "wof:placetype":"venue"
},
  "geometry": {"coordinates":[174.80190999999999,-36.884617],"type":"Point"}
}