{
  "type": "Feature",
  "properties": {
    "iso:country":"NZ",
    "sg:address":"Plaza Mall Centennial Ave ",
    "sg:city":"Alexandra",
    "sg:classifiers":[
        {
            "category":"Sports & Exercise",
            "subcategory":"Sports Center",
            "type":"Entertainment"
        }
    ],
    "sg:phone":"+64 3-448 6591",
    "sg:province":"Otago",
    "sg:tags":[
        "health",
        "beauty",
        "fitness"
    ],
    "wof:name":"APEx Fitness Centre",
    "wof:placetype":"venue"
},
  "geometry": {"coordinates":[-89.973328,30.03299],"type":"Point"}
}