{
  "type": "Feature",
  "properties": {
    "addr:full":"1292 Cameron Rd  Tauranga Bay of Plenty",
    "addr:housenumber":"1292",
    "addr:street":"Cameron Rd",
    "iso:country":"NZ",
    "sg:address":"1292 Cameron Rd ",
    "sg:city":"Tauranga",
    "sg:classifiers":[
        {
            "category":"Sports & Exercise",
            "subcategory":"Ski Resort",
            "type":"Entertainment"
        }
    ],
    "sg:phone":"+64 7-571 0909",
    "sg:province":"Bay of Plenty",
    "sg:tags":[
        "hobbies",
        "photographic",
        "leisure",
        "developing"
    ],
    "wof:name":"Greerton Photo Express",
    "wof:placetype":"venue"
},
  "geometry": {"coordinates":[176.133499,-37.725437],"type":"Point"}
}