{
  "type": "Feature",
  "properties": {
    "addr:full":"264 Manukau Rd Epsom  Auckland Auckland",
    "addr:housenumber":"264",
    "addr:street":"Manukau Rd",
    "iso:country":"NZ",
    "sg:address":"264 Manukau Rd Epsom ",
    "sg:city":"Auckland",
    "sg:orig_category":"Health And Beauty: Specialists: Physiotherapists",
    "sg:phone":"+64 9-524 0624",
    "sg:province":"Auckland",
    "wof:name":"Active Physio",
    "wof:placetype":"venue"
},
  "geometry": {"coordinates":[174.775757,-36.885841],"type":"Point"}
}