{
  "type": "Feature",
  "properties": {
    "iso:country":"NZ",
    "sg:address":"78 Gladstone Rd ",
    "sg:city":"Gisborne",
    "sg:classifiers":[
        {
            "category":"Home & Garden",
            "subcategory":"Building Materials",
            "type":"Retail Goods"
        }
    ],
    "sg:phone":"+64 6-867 3243",
    "sg:province":"Gisborne",
    "sg:tags":[
        "decorative",
        "glass",
        "window",
        "fittings"
    ],
    "wof:name":"The Watch Shop",
    "wof:placetype":"venue"
},
  "geometry": {"coordinates":[178.026184,-38.666767],"type":"Point"}
}