{
  "type": "Feature",
  "properties": {
    "iso:country":"NZ",
    "sg:address":"196 Whitaker St Te ",
    "sg:city":"Aroha",
    "sg:classifiers":[
        {
            "category":"Fast Food",
            "type":"Food & Drink"
        }
    ],
    "sg:phone":"+64 7-884 9463",
    "sg:tags":[
        "wining",
        "dining",
        "takeaway"
    ],
    "wof:name":"PJ's Burger Bar & Mexican",
    "wof:placetype":"venue"
},
  "geometry": {"coordinates":[175.713608,-37.544464],"type":"Point"}
}