{
  "type": "Feature",
  "properties": {
    "addr:full":"PO Box 53-040 Auckland Airport  Auckland Auckland",
    "addr:housenumber":"po box 53-040",
    "iso:country":"NZ",
    "sg:address":"PO Box 53-040 Auckland Airport ",
    "sg:city":"Auckland",
    "sg:classifiers":[
        {
            "category":"Health Services",
            "subcategory":"Hospital",
            "type":"Services"
        }
    ],
    "sg:phone":"+64 9-275 5747",
    "sg:province":"Auckland",
    "sg:tags":[
        "beauty",
        "fitness"
    ],
    "sg:website":"http://www.healthandfitness.co.nz",
    "wof:name":"Flying Fit Health Club",
    "wof:placetype":"venue"
},
  "geometry": {"coordinates":[174.78450000000001,-37.006058],"type":"Point"}
}