{
  "type": "Feature",
  "properties": {
    "addr:full":"6/10 Colway Pl Glenfield  Auckland Auckland",
    "addr:housenumber":"6 / 10",
    "addr:street":"Colway Pl",
    "iso:country":"NZ",
    "sg:address":"6/10 Colway Pl Glenfield ",
    "sg:city":"Auckland",
    "sg:classifiers":[
        {
            "category":"Manufacturing",
            "subcategory":"Tools & Machinery",
            "type":"Manufacturing & Wholesale Goods"
        }
    ],
    "sg:phone":"+64 9-444 1401",
    "sg:province":"Auckland",
    "sg:tags":[
        "equipment",
        "hot",
        "industrial",
        "stamping"
    ],
    "wof:name":"D C B Pacific Foiling Ltd",
    "wof:placetype":"venue"
},
  "geometry": {"coordinates":[174.731583,-36.774662],"type":"Point"}
}