{
  "type": "Feature",
  "properties": {
    "addr:full":"6 High St  Timaru Canterbury",
    "addr:housenumber":"6",
    "addr:street":"High St",
    "iso:country":"NZ",
    "sg:address":"6 High St ",
    "sg:city":"Timaru",
    "sg:orig_category":"Transport: Boats And Marine: Boats: Boat Dealers",
    "sg:phone":"+64 3-684 8440",
    "sg:province":"Canterbury",
    "wof:name":"Aqualite Marine Ltd",
    "wof:placetype":"venue"
},
  "geometry": {"coordinates":[171.25663800000001,-44.403465],"type":"Point"}
}