{
  "type": "Feature",
  "properties": {
    "addr:full":"42 Quarantine Rd Stoke  Nelson Nelson",
    "addr:housenumber":"42",
    "addr:street":"Quarantine Rd",
    "iso:country":"NZ",
    "sg:address":"42 Quarantine Rd Stoke ",
    "sg:city":"Nelson",
    "sg:classifiers":[
        {
            "category":"Winery",
            "type":"Food & Drink"
        }
    ],
    "sg:phone":"+64 3-547 6456",
    "sg:province":"Nelson",
    "sg:tags":[
        "making",
        "wine",
        "supply"
    ],
    "wof:name":"Winson Sheet Metal Products Ltd",
    "wof:placetype":"venue"
},
  "geometry": {"coordinates":[173.23419200000001,-41.312859],"type":"Point"}
}