{
  "type": "Feature",
  "properties": {
    "iso:country":"NZ",
    "sg:address":"121 Grafton Rd ",
    "sg:city":"Auckland",
    "sg:classifiers":[
        {
            "category":"Travel",
            "subcategory":"Hotels & Motels",
            "type":"Entertainment"
        }
    ],
    "sg:phone":"+64 9-309 0167",
    "sg:province":"Auckland",
    "sg:tags":[
        "tavern",
        "tourism",
        "accommodation"
    ],
    "wof:name":"Grafton Oaks Hotel",
    "wof:placetype":"venue"
},
  "geometry": {"coordinates":[174.76709,-36.860039],"type":"Point"}
}