{
  "type": "Feature",
  "properties": {
    "addr:full":"27 Firth St Drury  Auckland Auckland",
    "addr:housenumber":"27",
    "addr:street":"Firth St",
    "iso:country":"NZ",
    "sg:address":"27 Firth St Drury ",
    "sg:city":"Auckland",
    "sg:orig_category":"Industrial: Engineering: Engineers: Engineers Supplies",
    "sg:phone":"+64 9-294 9350",
    "sg:province":"Auckland",
    "wof:name":"A 2 Z Trading",
    "wof:placetype":"venue"
},
  "geometry": {"coordinates":[174.94816599999999,-37.103809],"type":"Point"}
}