{
  "type": "Feature",
  "properties": {
    "iso:country":"NZ",
    "sg:address":"Bush Road Medical Centre Kamo ",
    "sg:city":"Whangarei",
    "sg:orig_category":"Health And Beauty: Specialists: Podiatrists",
    "sg:phone":"+64 9-435 0692",
    "sg:province":"Northland",
    "wof:name":"Podiatry North",
    "wof:placetype":"venue"
},
  "geometry": {"coordinates":[174.296539,-35.684765],"type":"Point"}
}