{
  "type": "Feature",
  "properties": {
    "addr:full":"131 Lincoln Rd Henderson  Auckland Auckland",
    "addr:housenumber":"131",
    "addr:street":"Lincoln Rd",
    "iso:country":"NZ",
    "sg:address":"131 Lincoln Rd Henderson ",
    "sg:city":"Auckland",
    "sg:orig_category":"Health And Beauty: Products: Pharmacies",
    "sg:phone":"+64 9-838 8404",
    "sg:province":"Auckland",
    "wof:name":"Medi-Centre Pharmacy Ltd",
    "wof:placetype":"venue"
},
  "geometry": {"coordinates":[174.62823499999999,-36.870419],"type":"Point"}
}