{
  "type": "Feature",
  "properties": {
    "iso:country":"NZ",
    "sg:address":"85 Battery Rd Ahuriri ",
    "sg:city":"Napier",
    "sg:orig_category":"Farming: Forestry: Logging Services",
    "sg:phone":"+64 6-835 0162",
    "sg:province":"Hawke's Bay",
    "wof:name":"Rotorua Forest Haulage Ltd",
    "wof:placetype":"venue"
},
  "geometry": {"coordinates":[176.90152,-39.484039],"type":"Point"}
}