{
  "type": "Feature",
  "properties": {
    "iso:country":"NZ",
    "sg:address":"33 Northfield Rd Redwood ",
    "sg:city":"Christchurch",
    "sg:classifiers":[
        {
            "category":"Personal",
            "type":"Services"
        }
    ],
    "sg:phone":"+64 3-352 9597",
    "sg:province":"Canterbury",
    "sg:tags":[
        "celebrant",
        "arrangements",
        "marriage",
        "wedding"
    ],
    "wof:name":"Bragg Sandy M",
    "wof:placetype":"venue"
},
  "geometry": {"coordinates":[172.62553399999999,-43.467388],"type":"Point"}
}