{
  "type": "Feature",
  "properties": {
    "iso:country":"NZ",
    "sg:address":"Motueka 219 High St ",
    "sg:city":"Nelson",
    "sg:classifiers":[
        {
            "category":"Travel",
            "subcategory":"Hotels & Motels",
            "type":"Entertainment"
        }
    ],
    "sg:phone":"+64 3-528 8881",
    "sg:province":"Nelson",
    "sg:tags":[
        "tourism",
        "-",
        "rental",
        "accommodation"
    ],
    "wof:name":"First National Real Estate",
    "wof:placetype":"venue"
},
  "geometry": {"coordinates":[173.283966,-41.27227],"type":"Point"}
}