{
  "type": "Feature",
  "properties": {
    "iso:country":"NZ",
    "sg:address":"Cobham Rd ",
    "sg:city":"Kerikeri",
    "sg:classifiers":[
        {
            "category":"Shopping",
            "subcategory":"Bicycles & Sporting Goods",
            "type":"Retail Goods"
        }
    ],
    "sg:phone":"+64 9-407 7040",
    "sg:province":"Northland",
    "sg:tags":[
        "cycle",
        "sport",
        "sale",
        "retailers",
        "cycles"
    ],
    "wof:name":"Keri Mowers Saws & Cycles",
    "wof:placetype":"venue"
},
  "geometry": {"coordinates":[173.949738,-35.228264],"type":"Point"}
}