{
  "type": "Feature",
  "properties": {
    "addr:full":"47 B Dublin St  Wanganui Manawatu-Wanganui",
    "addr:housenumber":"47",
    "addr:street":"B Dublin St",
    "iso:country":"NZ",
    "sg:address":"47 B Dublin St ",
    "sg:city":"Wanganui",
    "sg:orig_category":"Food And Drink: Meats: Butchers",
    "sg:phone":"+64 6-348 8084",
    "sg:province":"Manawatu-Wanganui",
    "wof:name":"Dublin St Butchery",
    "wof:placetype":"venue"
},
  "geometry": {"coordinates":[175.04679899999999,-39.924877],"type":"Point"}
}