{
  "type": "Feature",
  "properties": {
    "iso:country":"NZ",
    "sg:address":"31 Sheffield Cre Burnside ",
    "sg:city":"Christchurch",
    "sg:orig_category":"Transport: Boats And Marine: Boats: Boat Dealers",
    "sg:phone":"+64 3-358 2317",
    "sg:province":"Canterbury",
    "wof:name":"Cresta Craft",
    "wof:placetype":"venue"
},
  "geometry": {"coordinates":[172.561768,-43.489582],"type":"Point"}
}