{
  "type": "Feature",
  "properties": {
    "addr:full":"29 A Dragon St Grenada North  Wellington Wellington",
    "addr:housenumber":"29 a",
    "addr:street":"Dragon St",
    "iso:country":"NZ",
    "sg:address":"29 A Dragon St Grenada North ",
    "sg:city":"Wellington",
    "sg:orig_category":"Farming: Horticulture: Flowers",
    "sg:phone":"+64 4-232 2361",
    "sg:province":"Wellington",
    "wof:name":"Central Flower Wholesalers Ltd",
    "wof:placetype":"venue"
},
  "geometry": {"coordinates":[174.83982800000001,-41.183887],"type":"Point"}
}