{
  "type": "Feature",
  "properties": {
    "iso:country":"NZ",
    "sg:address":"55 Second Ave ",
    "sg:city":"Tauranga",
    "sg:classifiers":[
        {
            "category":"Retail",
            "subcategory":"Auto Repair",
            "type":"Services"
        }
    ],
    "sg:phone":"+64 7-578 5966",
    "sg:province":"Bay of Plenty",
    "sg:tags":[
        "clutch",
        "brake",
        "servicing",
        "automotive"
    ],
    "wof:name":"Pit Stop",
    "wof:placetype":"venue"
},
  "geometry": {"coordinates":[176.16722100000001,-37.689129],"type":"Point"}
}