{
  "type": "Feature",
  "properties": {
    "iso:country":"NZ",
    "sg:address":"Old Hautere Rd Te Horo ",
    "sg:city":"Otaki",
    "sg:classifiers":[
        {
            "category":"Home & Garden",
            "subcategory":"Building Materials",
            "type":"Retail Goods"
        }
    ],
    "sg:phone":"+64 6-364 3364",
    "sg:tags":[
        "builder",
        "related"
    ],
    "wof:name":"Ralph P & L Building",
    "wof:placetype":"venue"
},
  "geometry": {"coordinates":[175.146927,-40.790955],"type":"Point"}
}