{
  "type": "Feature",
  "properties": {
    "addr:full":"Emerson St  Napier Hawke's Bay",
    "addr:street":"Emerson St",
    "iso:country":"NZ",
    "sg:address":"Emerson St ",
    "sg:city":"Napier",
    "sg:classifiers":[
        {
            "category":"Fast Food",
            "type":"Food & Drink"
        }
    ],
    "sg:phone":"+64 6-834 4288",
    "sg:province":"Hawke's Bay",
    "sg:tags":[
        "wining",
        "dining",
        "takeaway"
    ],
    "wof:name":"McDonalds Family Restaurant",
    "wof:placetype":"venue"
},
  "geometry": {"coordinates":[-80.588562,38.790821],"type":"Point"}
}