{
  "type": "Feature",
  "properties": {
    "addr:full":"63 A Millard Ave  Masterton Wellington",
    "addr:housenumber":"63",
    "addr:street":"A Millard Ave",
    "iso:country":"NZ",
    "sg:address":"63 A Millard Ave ",
    "sg:city":"Masterton",
    "sg:classifiers":[
        {
            "category":"Home & Garden",
            "subcategory":"Building Materials",
            "type":"Retail Goods"
        }
    ],
    "sg:phone":"+64 6-377 2187",
    "sg:province":"Wellington",
    "sg:tags":[
        "design",
        "fitting",
        "fittings",
        "kitchen"
    ],
    "wof:name":"Millard Joinery Ltd",
    "wof:placetype":"venue"
},
  "geometry": {"coordinates":[175.648651,-40.967121],"type":"Point"}
}