{
  "type": "Feature",
  "properties": {
    "iso:country":"NZ",
    "sg:address":"Turangi-Taupo ",
    "sg:city":"Turangi",
    "sg:classifiers":[
        {
            "category":"Building & Trades",
            "subcategory":"Pest Control",
            "type":"Services"
        }
    ],
    "sg:phone":"+64 7-386 6866",
    "sg:tags":[
        "home",
        "garden"
    ],
    "wof:name":"Prevent-A-Pest Limited",
    "wof:placetype":"venue"
},
  "geometry": {"coordinates":[176.08433500000001,-38.689281],"type":"Point"}
}