{
  "type": "Feature",
  "properties": {
    "addr:full":"Lakeview Nursery 23 Perkins Rd  Queenstown Otago",
    "addr:housenumber":"23",
    "addr:street":"Perkins Rd",
    "iso:country":"NZ",
    "sg:address":"Lakeview Nursery 23 Perkins Rd ",
    "sg:city":"Queenstown",
    "sg:classifiers":[
        {
            "category":"Retail",
            "subcategory":"Animal Services",
            "type":"Services"
        }
    ],
    "sg:phone":"+64 3-442 3044",
    "sg:province":"Otago",
    "sg:tags":[
        "pet",
        "home",
        "garden",
        "pets"
    ],
    "wof:name":"Perkins S G",
    "wof:placetype":"venue"
},
  "geometry": {"coordinates":[168.66325399999999,-45.031445],"type":"Point"}
}