{
  "type": "Feature",
  "properties": {
    "iso:country":"NZ",
    "sg:address":"Downtown New Plymouth 40 Devon St West New ",
    "sg:city":"Plymouth",
    "sg:orig_category":"Clothing And Fabric: Clothing: Women'S Fashions",
    "sg:phone":"+64 6-758 1648",
    "sg:province":"Taranaki",
    "wof:name":"Canterbury Clothing",
    "wof:placetype":"venue"
},
  "geometry": {"coordinates":[-66.628403,45.967709],"type":"Point"}
}