{
  "type": "Feature",
  "properties": {
    "iso:country":"NZ",
    "sg:address":"140 Bourke St ",
    "sg:city":"Invercargill",
    "sg:classifiers":[
        {
            "category":"Home & Garden",
            "subcategory":"Building Materials",
            "type":"Retail Goods"
        }
    ],
    "sg:phone":"+64 3-217 7555",
    "sg:province":"Southland",
    "sg:tags":[
        "electrician",
        "related"
    ],
    "wof:name":"Harrington Electrical",
    "wof:placetype":"venue"
},
  "geometry": {"coordinates":[168.370926,-46.397331],"type":"Point"}
}