{
  "type": "Feature",
  "properties": {
    "iso:country":"NZ",
    "sg:address":"289 Gt South Rd Papakura ",
    "sg:city":"Auckland",
    "sg:classifiers":[
        {
            "category":"Health Services",
            "subcategory":"Clinic",
            "type":"Services"
        }
    ],
    "sg:phone":"+64 9-298 5502",
    "sg:province":"Auckland",
    "sg:tags":[
        "medical",
        "beauty"
    ],
    "wof:name":"Nayar Dr R",
    "wof:placetype":"venue"
},
  "geometry": {"coordinates":[174.943787,-37.065117],"type":"Point"}
}