{
  "type": "Feature",
  "properties": {
    "addr:full":"20 Vine St  Whangarei Northland",
    "addr:housenumber":"20",
    "addr:street":"Vine St",
    "iso:country":"NZ",
    "sg:address":"20 Vine St ",
    "sg:city":"Whangarei",
    "sg:classifiers":[
        {
            "category":"Communications",
            "subcategory":"Film & Video Production",
            "type":"Services"
        }
    ],
    "sg:phone":"+64 9-438 2098",
    "sg:province":"Northland",
    "sg:tags":[
        "sport",
        "leisure",
        "library",
        "entertainment"
    ],
    "wof:name":"Video Ezy Whangarei",
    "wof:placetype":"venue"
},
  "geometry": {"coordinates":[174.31977800000001,-35.726196],"type":"Point"}
}