{
  "type": "Feature",
  "properties": {
    "addr:full":"Lintas House 25 Vivian St  Wellington Wellington",
    "addr:housenumber":"25",
    "addr:street":"Vivian St",
    "iso:country":"NZ",
    "sg:address":"Lintas House 25 Vivian St ",
    "sg:city":"Wellington",
    "sg:orig_category":"Transport: Transportation: Freight",
    "sg:phone":"+64 4-802 3550",
    "sg:province":"Wellington",
    "wof:name":"Mondiale Freight Services Ltd",
    "wof:placetype":"venue"
},
  "geometry": {"coordinates":[-104.99284400000001,40.751411],"type":"Point"}
}