{
  "type": "Feature",
  "properties": {
    "iso:country":"NZ",
    "sg:address":"5 Te Apunga Pl Mt Wellington ",
    "sg:city":"Auckland",
    "sg:classifiers":[
        {
            "category":"Food & Beverages",
            "subcategory":"Meat & Fish",
            "type":"Retail Goods"
        }
    ],
    "sg:phone":"+64 9-276 7000",
    "sg:province":"Auckland",
    "sg:tags":[
        "drink"
    ],
    "wof:name":"Jarvis Equipment NZ Ltd",
    "wof:placetype":"venue"
},
  "geometry": {"coordinates":[174.849747,-36.924488],"type":"Point"}
}