{
  "type": "Feature",
  "properties": {
    "addr:full":"61 Karen Cre Dinsdale  Hamilton Waikato",
    "addr:housenumber":"61;cre",
    "addr:street":"Karen",
    "iso:country":"NZ",
    "sg:address":"61 Karen Cre Dinsdale ",
    "sg:city":"Hamilton",
    "sg:classifiers":[
        {
            "category":"Home & Garden",
            "subcategory":"Building Materials",
            "type":"Retail Goods"
        }
    ],
    "sg:phone":"+64 7-846 2441",
    "sg:province":"Waikato",
    "sg:tags":[
        "brick",
        "outdoor",
        "paving"
    ],
    "wof:name":"Kruger (Michael) Paving",
    "wof:placetype":"venue"
},
  "geometry": {"coordinates":[175.247253,-37.803833],"type":"Point"}
}