{
  "type": "Feature",
  "properties": {
    "iso:country":"NZ",
    "sg:address":"Cnr Waterloo Quay & Bunny St ",
    "sg:city":"Wellington",
    "sg:classifiers":[
        {
            "category":"Bars & Pubs",
            "type":"Food & Drink"
        }
    ],
    "sg:phone":"+64 4-499 4485",
    "sg:province":"Wellington",
    "sg:tags":[
        "wining",
        "dining",
        "brasserie"
    ],
    "wof:name":"Ferrymans Bar & Cafe",
    "wof:placetype":"venue"
},
  "geometry": {"coordinates":[174.921539,-41.214111],"type":"Point"}
}