{
  "type": "Feature",
  "properties": {
    "addr:full":"36 State Highway 34 R D 2  Whakatane Bay of Plenty",
    "addr:housenumber":"36;2",
    "addr:street":"State Highway 34 R D;Bay",
    "iso:country":"NZ",
    "sg:address":"36 State Highway 34 R D 2 ",
    "sg:city":"Whakatane",
    "sg:classifiers":[
        {
            "category":"Coffee & Tea",
            "type":"Food & Drink"
        }
    ],
    "sg:phone":"+64 7-322 8872",
    "sg:province":"Bay of Plenty",
    "sg:tags":[
        "vegetable",
        "fruit",
        "veges"
    ],
    "sg:website":"http://www.yellowpages.co.nz/for/marconolives/dp36263.html",
    "wof:name":"Marcon Olives",
    "wof:placetype":"venue"
},
  "geometry": {"coordinates":[176.98419200000001,-37.965305],"type":"Point"}
}