{
  "type": "Feature",
  "properties": {
    "iso:country":"NZ",
    "sg:address":"Linwood ",
    "sg:city":"Christchurch",
    "sg:classifiers":[
        {
            "category":"Food & Beverages",
            "subcategory":"Cheese",
            "type":"Retail Goods"
        }
    ],
    "sg:phone":"+64 3-389 8028",
    "sg:province":"Canterbury",
    "sg:tags":[
        "merchant",
        "drink",
        "-"
    ],
    "wof:name":"Canterbury Cheesemongers",
    "wof:placetype":"venue"
},
  "geometry": {"coordinates":[172.66213999999999,-43.53146],"type":"Point"}
}