{
  "type": "Feature",
  "properties": {
    "addr:full":"134 Colombo St Beckenham  Christchurch Canterbury",
    "addr:housenumber":"134",
    "addr:street":"Colombo St",
    "iso:country":"NZ",
    "sg:address":"134 Colombo St Beckenham ",
    "sg:city":"Christchurch",
    "sg:classifiers":[
        {
            "category":"Restaurant",
            "type":"Food & Drink"
        }
    ],
    "sg:phone":"+64 3-337 9528",
    "sg:province":"Canterbury",
    "sg:tags":[
        "wining",
        "dining",
        "pizza"
    ],
    "wof:name":"Pizza Haven",
    "wof:placetype":"venue"
},
  "geometry": {"coordinates":[172.63699299999999,-43.557796],"type":"Point"}
}