{
  "type": "Feature",
  "properties": {
    "iso:country":"NZ",
    "sg:address":"cnr Durham & Armagh Sts ",
    "sg:city":"Christchurch",
    "sg:classifiers":[
        {
            "category":"Sports & Exercise",
            "subcategory":"Sports Center",
            "type":"Entertainment"
        }
    ],
    "sg:phone":"+64 3-379 9099",
    "sg:province":"Canterbury",
    "sg:tags":[
        "health",
        "beauty",
        "fitness"
    ],
    "wof:name":"Contours Health & Fitness Centre",
    "wof:placetype":"venue"
},
  "geometry": {"coordinates":[-76.537834,37.605659],"type":"Point"}
}