{
  "type": "Feature",
  "properties": {
    "addr:full":"81 View Rd  Rotorua Bay of Plenty",
    "addr:housenumber":"81",
    "addr:street":"View Rd",
    "iso:country":"NZ",
    "sg:address":"81 View Rd ",
    "sg:city":"Rotorua",
    "sg:classifiers":[
        {
            "category":"Manufacturing",
            "subcategory":"Metals",
            "type":"Manufacturing & Wholesale Goods"
        }
    ],
    "sg:phone":"+64 7-349 2977",
    "sg:province":"Bay of Plenty",
    "sg:tags":[
        "-",
        "engineering",
        "industrial",
        "sheet",
        "engineer"
    ],
    "wof:name":"Orca Engineering & Marine Ltd",
    "wof:placetype":"venue"
},
  "geometry": {"coordinates":[176.227936,-38.130402],"type":"Point"}
}