{
  "type": "Feature",
  "properties": {
    "iso:country":"NZ",
    "sg:address":"84 Carr Rd Mt Roskill ",
    "sg:city":"Auckland",
    "sg:classifiers":[
        {
            "category":"Wholesale",
            "subcategory":"Machinery & Supplies",
            "type":"Manufacturing & Wholesale Goods"
        }
    ],
    "sg:phone":"+64 9-621 0350",
    "sg:province":"Auckland",
    "sg:tags":[
        "equipment",
        "industrial"
    ],
    "sg:website":"http://www.yellowpages.co.nz/for/foxair/dp21583.html",
    "wof:name":"Fox Air Specialists Ltd",
    "wof:placetype":"venue"
},
  "geometry": {"coordinates":[174.742767,-36.905895],"type":"Point"}
}