{
  "type": "Feature",
  "properties": {
    "iso:country":"NZ",
    "sg:address":"Brickworks Main West Rd ",
    "sg:city":"Darfield",
    "sg:classifiers":[
        {
            "category":"Home & Garden",
            "subcategory":"Building Materials",
            "type":"Retail Goods"
        }
    ],
    "sg:phone":"+64 3-318 8203",
    "sg:tags":[
        "brick",
        "outdoor",
        "paving"
    ],
    "wof:name":"Canterbury Clay Bricks",
    "wof:placetype":"venue"
},
  "geometry": {"coordinates":[-104.250458,40.291191],"type":"Point"}
}