{
  "type": "Feature",
  "properties": {
    "addr:full":"1/4 Cain Rd Penrose  Auckland Auckland",
    "addr:housenumber":"1 / 4",
    "addr:street":"Cain Rd",
    "iso:country":"NZ",
    "sg:address":"1/4 Cain Rd Penrose ",
    "sg:city":"Auckland",
    "sg:orig_category":"Industrial: Instruments: Industrial Instruments",
    "sg:phone":"+64 9-525 1969",
    "sg:province":"Auckland",
    "wof:name":"Hivolt Services Ltd",
    "wof:placetype":"venue"
},
  "geometry": {"coordinates":[174.81016500000001,-36.911617],"type":"Point"}
}