{
  "type": "Feature",
  "properties": {
    "iso:country":"NZ",
    "sg:address":"Loop Rd Otaika ",
    "sg:city":"Whangarei",
    "sg:classifiers":[
        {
            "category":"Home & Garden",
            "subcategory":"Building Materials",
            "type":"Retail Goods"
        }
    ],
    "sg:phone":"+64 9-432 2456",
    "sg:province":"Northland",
    "sg:tags":[
        "brick",
        "outdoor",
        "paving"
    ],
    "wof:name":"Gourmet Gardens",
    "wof:placetype":"venue"
},
  "geometry": {"coordinates":[174.301666,-35.784943],"type":"Point"}
}