{
  "type": "Feature",
  "properties": {
    "iso:country":"NZ",
    "sg:address":"12 Nick Johnson Dve Church Bay Waiheke ",
    "sg:city":"Island",
    "sg:classifiers":[
        {
            "category":"Winery",
            "type":"Food & Drink"
        }
    ],
    "sg:phone":"+64 9-372 5889",
    "sg:tags":[
        "wining",
        "vineyard",
        "dining"
    ],
    "wof:name":"Cable Bay Vineyards Ltd",
    "wof:placetype":"venue"
},
  "geometry": {"coordinates":[175.021713,-36.810303],"type":"Point"}
}