{
  "type": "Feature",
  "properties": {
    "iso:country":"NZ",
    "sg:address":"1 C Sunset Tce East Tamaki ",
    "sg:city":"Auckland",
    "sg:orig_category":"Health And Beauty: Specialists: Physiotherapists",
    "sg:phone":"+64 9-272 9182",
    "sg:province":"Auckland",
    "wof:name":"Physio Limited",
    "wof:placetype":"venue"
},
  "geometry": {"coordinates":[174.861771,-36.891823],"type":"Point"}
}