{
  "type": "Feature",
  "properties": {
    "iso:country":"NZ",
    "sg:address":"PO Box 9972 Wellington ",
    "sg:city":"Central",
    "sg:classifiers":[
        {
            "category":"Ice Cream",
            "type":"Food & Drink"
        }
    ],
    "sg:phone":"+64 25530038",
    "sg:tags":[
        "-"
    ],
    "wof:name":"La Felicita Enterprises NZ Ltd",
    "wof:placetype":"venue"
},
  "geometry": {"coordinates":[-144.80354299999999,65.57208300000001],"type":"Point"}
}