{
  "type": "Feature",
  "properties": {
    "addr:full":"129 Ponsonby Rd Ponsonby  Auckland Auckland",
    "addr:housenumber":"129",
    "addr:street":"Ponsonby Rd",
    "iso:country":"NZ",
    "sg:address":"129 Ponsonby Rd Ponsonby ",
    "sg:city":"Auckland",
    "sg:classifiers":[
        {
            "category":"Restaurant",
            "type":"Food & Drink"
        }
    ],
    "sg:phone":"+64 9-376 5329",
    "sg:province":"Auckland",
    "sg:tags":[
        "fruit",
        "veges"
    ],
    "wof:name":"Bhana Bros",
    "wof:placetype":"venue"
},
  "geometry": {"coordinates":[174.74653599999999,-36.855476],"type":"Point"}
}