{
  "type": "Feature",
  "properties": {
    "addr:full":"1188 Arawa St  Rotorua Bay of Plenty",
    "addr:housenumber":"1188",
    "addr:street":"Arawa St",
    "iso:country":"NZ",
    "sg:address":"1188 Arawa St ",
    "sg:city":"Rotorua",
    "sg:classifiers":[
        {
            "category":"Communications",
            "subcategory":"Film & Video Production",
            "type":"Services"
        }
    ],
    "sg:phone":"+64 7-347 0755",
    "sg:province":"Bay of Plenty",
    "sg:tags":[
        "sport",
        "leisure",
        "library",
        "entertainment"
    ],
    "wof:name":"Civic Video",
    "wof:placetype":"venue"
},
  "geometry": {"coordinates":[176.250854,-38.135052],"type":"Point"}
}