{
  "type": "Feature",
  "properties": {
    "addr:full":"Unit7/41 Sir William Ave East Tamaki  Auckland Auckland",
    "addr:housenumber":"41",
    "addr:street":"Sir William Ave",
    "iso:country":"NZ",
    "sg:address":"Unit7/41 Sir William Ave East Tamaki ",
    "sg:city":"Auckland",
    "sg:classifiers":[
        {
            "category":"Home & Garden",
            "subcategory":"Home Furnishings",
            "type":"Retail Goods"
        }
    ],
    "sg:phone":"+64 9-273 4580",
    "sg:province":"Auckland",
    "sg:tags":[
        "furniture/furnishings",
        "upholstery",
        "supply"
    ],
    "wof:name":"Upholstery Services",
    "wof:placetype":"venue"
},
  "geometry": {"coordinates":[174.861771,-36.891823],"type":"Point"}
}