{
  "type": "Feature",
  "properties": {
    "addr:full":"5 Helios Pl Titirangi  Auckland Auckland",
    "addr:housenumber":"5",
    "addr:street":"Helios Pl",
    "iso:country":"NZ",
    "sg:address":"5 Helios Pl Titirangi ",
    "sg:city":"Auckland",
    "sg:orig_category":"Education And Training: General: Schools",
    "sg:phone":"+64 9-817 4386",
    "sg:province":"Auckland",
    "wof:name":"Titirangi Rudolf Steiner School",
    "wof:placetype":"venue"
},
  "geometry": {"coordinates":[174.66279599999999,-36.926861],"type":"Point"}
}