{
  "type": "Feature",
  "properties": {
    "iso:country":"NZ",
    "sg:address":"32 Tirau St ",
    "sg:city":"Putaruru",
    "sg:orig_category":"Health And Beauty: Specialists: Physiotherapists",
    "sg:phone":"+64 7-883 3313",
    "wof:name":"South Waikato Physiotherapy Clinic",
    "wof:placetype":"venue"
},
  "geometry": {"coordinates":[175.781937,-38.045063],"type":"Point"}
}