{
  "type": "Feature",
  "properties": {
    "iso:country":"NZ",
    "sg:address":"National Bank Towers cnr Queen & Darby Sts ",
    "sg:city":"Auckland",
    "sg:classifiers":[
        {
            "category":"Airline",
            "type":"Transportation"
        }
    ],
    "sg:phone":"+64 9-309 6171",
    "sg:province":"Auckland",
    "sg:tags":[
        "services",
        "travel",
        "tourism"
    ],
    "wof:name":"Flight Centre",
    "wof:placetype":"venue"
},
  "geometry": {"coordinates":[-119.10457599999999,36.597755],"type":"Point"}
}