{
  "type": "Feature",
  "properties": {
    "addr:full":"Chartwell  Hamilton Waikato",
    "iso:country":"NZ",
    "sg:address":"Chartwell ",
    "sg:city":"Hamilton",
    "sg:classifiers":[
        {
            "category":"Banks & Credit Unions",
            "subcategory":"Financial Services",
            "type":"Services"
        }
    ],
    "sg:phone":"+64 800 855 667",
    "sg:province":"Waikato",
    "sg:tags":[
        "finance"
    ],
    "sg:website":"http://www.yellowpages.co.nz/for/cbamortgages/dp45365.html",
    "wof:name":"CBA Mortgages & Loans",
    "wof:placetype":"venue"
},
  "geometry": {"coordinates":[175.27124000000001,-37.763653],"type":"Point"}
}