{
  "type": "Feature",
  "properties": {
    "iso:country":"NZ",
    "sg:address":"54 - 56 Miro St ",
    "sg:city":"Taupo",
    "sg:orig_category":"Shopping: Accessories: Embroidery And Monograms",
    "sg:phone":"+64 7-378 0032",
    "sg:province":"Waikato",
    "wof:name":"Stitchable Effects",
    "wof:placetype":"venue"
},
  "geometry": {"coordinates":[176.105698,-38.688374],"type":"Point"}
}