{
  "type": "Feature",
  "properties": {
    "addr:full":"108 Cuba St Petone Lower  Hutt Wellington",
    "addr:housenumber":"108",
    "addr:street":"Cuba St",
    "iso:country":"NZ",
    "sg:address":"108 Cuba St Petone Lower ",
    "sg:city":"Hutt",
    "sg:orig_category":"Shopping: Engravers",
    "sg:phone":"+64 4-568 8807",
    "sg:province":"Wellington",
    "wof:name":"Campbell Peter",
    "wof:placetype":"venue"
},
  "geometry": {"coordinates":[174.88746599999999,-41.222729],"type":"Point"}
}