{
  "type": "Feature",
  "properties": {
    "iso:country":"NZ",
    "sg:address":"PO Box 8561 Symonds ",
    "sg:city":"Street",
    "sg:orig_category":"Transport: Transportation: Courier Services",
    "sg:phone":"+64 800 501 502",
    "wof:name":"Pace Couriers Limited",
    "wof:placetype":"venue"
},
  "geometry": {"coordinates":[170.36663799999999,-43.587711],"type":"Point"}
}