{
  "type": "Feature",
  "properties": {
    "iso:country":"NZ",
    "sg:address":"Unit D 580 Rosebank Rd Avondale ",
    "sg:city":"Auckland",
    "sg:orig_category":"Industrial: Electrical/Electronic: Electrical Switchgear",
    "sg:phone":"+64 9-828 1101",
    "sg:province":"Auckland",
    "wof:name":"C H New Zealand Ltd",
    "wof:placetype":"venue"
},
  "geometry": {"coordinates":[174.690933,-36.8932],"type":"Point"}
}