{
  "type": "Feature",
  "properties": {
    "iso:country":"NZ",
    "sg:address":"Martins Rd ",
    "sg:city":"Martinborough",
    "sg:classifiers":[
        {
            "category":"Winery",
            "type":"Food & Drink"
        }
    ],
    "sg:phone":"+64 6-306 9122",
    "sg:tags":[
        "wining",
        "vineyard",
        "dining"
    ],
    "wof:name":"Te Kairanga Wines",
    "wof:placetype":"venue"
},
  "geometry": {"coordinates":[175.488922,-41.224411],"type":"Point"}
}