{
  "type": "Feature",
  "properties": {
    "iso:country":"NZ",
    "sg:address":"Ruahine St ",
    "sg:city":"Paraparaumu",
    "sg:classifiers":[
        {
            "category":"Manufacturing",
            "subcategory":"Glass & Minerals",
            "type":"Manufacturing & Wholesale Goods"
        }
    ],
    "sg:phone":"+64 4-298 7046",
    "sg:province":"Wellington",
    "sg:tags":[
        "raw",
        "industrial",
        "quarry",
        "materials"
    ],
    "wof:name":"Higgins Aggregates Ltd",
    "wof:placetype":"venue"
},
  "geometry": {"coordinates":[175.012466,-40.917759],"type":"Point"}
}