{
  "type": "Feature",
  "properties": {
    "addr:full":"www.biketrader.co.nz  Oakura",
    "iso:country":"NZ",
    "sg:address":"www.biketrader.co.nz ",
    "sg:city":"Oakura",
    "sg:classifiers":[
        {
            "category":"Autos & Motor Vehicles",
            "subcategory":"Motorcycle Sales",
            "type":"Retail Goods"
        }
    ],
    "sg:phone":"+64 6-752 7052",
    "sg:tags":[
        "automotive",
        "scooter",
        "leasing"
    ],
    "wof:name":"Biketrader",
    "wof:placetype":"venue"
},
  "geometry": {"coordinates":[173.95230100000001,-39.115391],"type":"Point"}
}