{
  "type": "Feature",
  "properties": {
    "iso:country":"NZ",
    "sg:address":"Wellington/Hutt Valley/Porirua Lower ",
    "sg:city":"Hutt",
    "sg:orig_category":"Home And Garden: General",
    "sg:phone":"+64 4-567 0871",
    "sg:province":"Wellington",
    "sg:website":"http://www.preventapest.co.nz",
    "wof:name":"Prevent A Pest Limited",
    "wof:placetype":"venue"
},
  "geometry": {"coordinates":[174.840714,-41.138359],"type":"Point"}
}