{
  "type": "Feature",
  "properties": {
    "iso:country":"NZ",
    "sg:address":"cnr Cameron Rd & Eleventh Ave ",
    "sg:city":"Tauranga",
    "sg:orig_category":"Shopping: Hobbies And Games: Handcrafts",
    "sg:phone":"+64 7-578 3447",
    "sg:province":"Bay of Plenty",
    "wof:name":"Tauranga Sewing Centre Ltd",
    "wof:placetype":"venue"
},
  "geometry": {"coordinates":[176.14476,-37.703152],"type":"Point"}
}