{
  "type": "Feature",
  "properties": {
    "iso:country":"NZ",
    "sg:address":"Westbank Rd R D 1 Motueka ",
    "sg:city":"Ngatimoti",
    "sg:classifiers":[
        {
            "category":"Shopping",
            "subcategory":"Pets & Pet Supplies",
            "type":"Retail Goods"
        }
    ],
    "sg:phone":"+64 3-526 8776",
    "sg:tags":[
        "boarding",
        "garden",
        "pets",
        "catteries",
        "home",
        "kennel"
    ],
    "wof:name":"Fourfoot Lodge Pet Boarding Centre",
    "wof:placetype":"venue"
},
  "geometry": {"coordinates":[172.885223,-41.193302],"type":"Point"}
}