{
  "type": "Feature",
  "properties": {
    "addr:full":"23 Puketea St Blockhouse Bay  Auckland Auckland",
    "addr:housenumber":"23",
    "addr:street":"Puketea St",
    "iso:country":"NZ",
    "sg:address":"23 Puketea St Blockhouse Bay ",
    "sg:city":"Auckland",
    "sg:classifiers":[
        {
            "category":"Banks & Credit Unions",
            "subcategory":"Financial Services",
            "type":"Services"
        }
    ],
    "sg:phone":"+64 9-626 7826",
    "sg:province":"Auckland",
    "sg:tags":[
        "personal",
        "loan",
        "-",
        "finance",
        "mortgage"
    ],
    "wof:name":"Bay Mortgages",
    "wof:placetype":"venue"
},
  "geometry": {"coordinates":[174.70472699999999,-36.919312],"type":"Point"}
}