{
  "type": "Feature",
  "properties": {
    "iso:country":"NZ",
    "sg:address":"Kaimoana St ",
    "sg:city":"Wairoa",
    "sg:orig_category":"Farming: Forestry",
    "sg:phone":"+64 6-838 9030",
    "wof:name":"Quality Roading and Services (Wairoa) Ltd",
    "wof:placetype":"venue"
},
  "geometry": {"coordinates":[177.409012,-39.022903],"type":"Point"}
}