{
  "type": "Feature",
  "properties": {
    "iso:country":"NZ",
    "sg:address":"6-8 Kiwi St ",
    "sg:city":"Pahiatua",
    "sg:classifiers":[
        {
            "category":"Retail",
            "subcategory":"Auto Repair",
            "type":"Services"
        }
    ],
    "sg:phone":"+64 6-376 8348",
    "sg:tags":[
        "automotive",
        "panel",
        "servicing",
        "beater"
    ],
    "wof:name":"Hunter Panel & Paint",
    "wof:placetype":"venue"
},
  "geometry": {"coordinates":[175.84301757809999,-40.4560775757],"type":"Point"}
}