{
  "type": "Feature",
  "properties": {
    "addr:full":"77 Nairn St Mt Cook  Wellington Wellington",
    "addr:housenumber":"77",
    "addr:street":"Nairn St",
    "iso:country":"NZ",
    "sg:address":"77 Nairn St Mt Cook ",
    "sg:city":"Wellington",
    "sg:classifiers":[
        {
            "category":"Banks & Credit Unions",
            "subcategory":"Investment Brokerage",
            "type":"Services"
        }
    ],
    "sg:phone":"+64 4-385 7051",
    "sg:province":"Wellington",
    "sg:tags":[
        "personal",
        "accountant",
        "chartered",
        "-",
        "finance"
    ],
    "wof:name":"Levy & Company Ltd",
    "wof:placetype":"venue"
},
  "geometry": {"coordinates":[174.77053799999999,-41.300114],"type":"Point"}
}