{
  "type": "Feature",
  "properties": {
    "addr:full":"PO Box 9023  Annesbrook Nelson",
    "addr:housenumber":"po",
    "addr:street":"Box 9023 Annesbrook",
    "iso:country":"NZ",
    "sg:address":"PO Box 9023 ",
    "sg:city":"Annesbrook",
    "sg:classifiers":[
        {
            "category":"Utilities",
            "subcategory":"Refuse",
            "type":"Services"
        }
    ],
    "sg:phone":"+64 3-547 0642",
    "sg:province":"Nelson",
    "sg:tags":[
        "bin",
        "hire",
        "garden",
        "cleaning",
        "rubbish",
        "home"
    ],
    "wof:name":"Can Plan",
    "wof:placetype":"venue"
},
  "geometry": {"coordinates":[173.242493,-41.298843],"type":"Point"}
}