{
  "type": "Feature",
  "properties": {
    "addr:full":"3/550 Te Rapa Rd  Hamilton Waikato",
    "addr:housenumber":"3 / 550",
    "addr:street":"Te Rapa Rd",
    "iso:country":"NZ",
    "sg:address":"3/550 Te Rapa Rd ",
    "sg:city":"Hamilton",
    "sg:orig_category":"Industrial: Engineering: Engineers - Precision",
    "sg:phone":"+64 7-849 8338",
    "sg:province":"Waikato",
    "wof:name":"Solutions Engineering Ltd",
    "wof:placetype":"venue"
},
  "geometry": {"coordinates":[175.24821499999999,-37.759644],"type":"Point"}
}