{
  "type": "Feature",
  "properties": {
    "addr:full":"Kyleston R D 2 Ashley  Rangiora Canterbury",
    "addr:housenumber":"2",
    "addr:street":"R D",
    "iso:country":"NZ",
    "sg:address":"Kyleston R D 2 Ashley ",
    "sg:city":"Rangiora",
    "sg:orig_category":"Farming: Agriculture: Agricultural Contractors",
    "sg:phone":"+64 3-313 7296",
    "sg:province":"Canterbury",
    "wof:name":"Robertson D R",
    "wof:placetype":"venue"
},
  "geometry": {"coordinates":[172.59030200000001,-43.302963],"type":"Point"}
}