{
  "type": "Feature",
  "properties": {
    "iso:country":"NZ",
    "sg:address":"Matai St ",
    "sg:city":"Taupo",
    "sg:classifiers":[
        {
            "category":"Shopping",
            "subcategory":"Clothing, Apparel, & Fashions",
            "type":"Retail Goods"
        }
    ],
    "sg:phone":"+64 7-378 7969",
    "sg:province":"Waikato",
    "sg:tags":[
        "-",
        "hire",
        "clothing",
        "fabric"
    ],
    "wof:name":"Centre Stage Taupo The Playhouse",
    "wof:placetype":"venue"
},
  "geometry": {"coordinates":[176.10575900000001,-38.686893],"type":"Point"}
}