{
  "type": "Feature",
  "properties": {
    "addr:full":"Cnr Heaphy Tce & O'Neill St Claudelands  Hamilton Waikato",
    "addr:street":"Cnr Heaphy Tce &;St",
    "iso:country":"NZ",
    "sg:address":"Cnr Heaphy Tce & O'Neill St Claudelands ",
    "sg:city":"Hamilton",
    "sg:classifiers":[
        {
            "category":"Personal",
            "subcategory":"Beauty Salon",
            "type":"Services"
        }
    ],
    "sg:phone":"+64 7-855 7917",
    "sg:province":"Waikato",
    "sg:tags":[
        "therapy",
        "health"
    ],
    "wof:name":"Ngaire Pye Sun & Beauty House",
    "wof:placetype":"venue"
},
  "geometry": {"coordinates":[175.28656000000001,-37.777809],"type":"Point"}
}