{
  "type": "Feature",
  "properties": {
    "addr:full":"68 Ranfurly St  Waitara",
    "addr:housenumber":"68",
    "addr:street":"Ranfurly St",
    "iso:country":"NZ",
    "sg:address":"68 Ranfurly St ",
    "sg:city":"Waitara",
    "sg:orig_category":"Industrial: Engineering: Engineers - Manufacturing",
    "sg:phone":"+64 6-754 7460",
    "wof:name":"MLB Manufacturers",
    "wof:placetype":"venue"
},
  "geometry": {"coordinates":[174.223602,-39.00388],"type":"Point"}
}