{
  "type": "Feature",
  "properties": {
    "addr:full":"Fraser St  Whangarei Northland",
    "addr:street":"Fraser St",
    "iso:country":"NZ",
    "sg:address":"Fraser St ",
    "sg:city":"Whangarei",
    "sg:orig_category":"Transport: Boats And Marine: Shipping",
    "sg:phone":"+64 9-438 2219",
    "sg:province":"Northland",
    "sg:website":"http://www.yellowpages.co.nz/for/shipconstructors/dp6779.html",
    "wof:name":"Ship Constructors Ltd",
    "wof:placetype":"venue"
},
  "geometry": {"coordinates":[174.34501599999999,-35.742939],"type":"Point"}
}