{
  "type": "Feature",
  "properties": {
    "iso:country":"NZ",
    "sg:address":"305 Neilsen St Onehunga ",
    "sg:city":"Auckland",
    "sg:orig_category":"Industrial: Equipment And Machinery: Compressors",
    "sg:phone":"+64 9-622 2976",
    "sg:province":"Auckland",
    "wof:name":"Precision Air",
    "wof:placetype":"venue"
},
  "geometry": {"coordinates":[174.783661,-36.909973],"type":"Point"}
}