{
  "type": "Feature",
  "properties": {
    "addr:full":"21 Penton Rd Stanmore Bay Hibiscus  Hibiscus Coast Auckland",
    "addr:housenumber":"21",
    "addr:street":"Penton Rd",
    "iso:country":"NZ",
    "sg:address":"21 Penton Rd Stanmore Bay Hibiscus ",
    "sg:city":"Hibiscus Coast",
    "sg:orig_category":"Automotive: Servicing And Repair: Car Trimming/Upholstery",
    "sg:phone":"+64 9-424 2257",
    "sg:province":"Auckland",
    "wof:name":"Mint Condition",
    "wof:placetype":"venue"
},
  "geometry": {"coordinates":[174.73968500000001,-36.632717],"type":"Point"}
}