{
  "type": "Feature",
  "properties": {
    "addr:full":"Hamilton/Cambridge Hwy  Hamilton Waikato",
    "addr:street":"Hwy",
    "iso:country":"NZ",
    "sg:address":"Hamilton/Cambridge Hwy ",
    "sg:city":"Hamilton",
    "sg:classifiers":[
        {
            "category":"Manufacturing",
            "subcategory":"Glass & Minerals",
            "type":"Manufacturing & Wholesale Goods"
        }
    ],
    "sg:phone":"+64 7-827 7106",
    "sg:province":"Waikato",
    "sg:tags":[
        "raw",
        "industrial",
        "quarry",
        "materials"
    ],
    "wof:name":"Winstone Aggregates",
    "wof:placetype":"venue"
},
  "geometry": {"coordinates":[175.278076,-37.804459],"type":"Point"}
}