{
  "type": "Feature",
  "properties": {
    "addr:full":"3089 Gt North Rd New Lynn  Auckland Auckland",
    "addr:postcode":"3089 gt",
    "addr:street":"North Rd",
    "iso:country":"NZ",
    "sg:address":"3089 Gt North Rd New Lynn ",
    "sg:city":"Auckland",
    "sg:classifiers":[
        {
            "category":"Professional",
            "subcategory":"Management & Consulting",
            "type":"Services"
        }
    ],
    "sg:phone":"+64 9-827 8224",
    "sg:province":"Auckland",
    "sg:tags":[
        "consultant",
        "training",
        "education"
    ],
    "wof:name":"Bounce Back Training Ltd",
    "wof:placetype":"venue"
},
  "geometry": {"coordinates":[174.68069499999999,-36.908936],"type":"Point"}
}