{
  "type": "Feature",
  "properties": {
    "iso:country":"NZ",
    "sg:address":"206 Main Hwy ",
    "sg:city":"Otaki",
    "sg:classifiers":[
        {
            "category":"Shopping",
            "subcategory":"Gifts & Souvenirs",
            "type":"Retail Goods"
        }
    ],
    "sg:phone":"+64 6-364 0064",
    "sg:tags":[
        "travel",
        "tourism"
    ],
    "wof:name":"Tama Prints",
    "wof:placetype":"venue"
},
  "geometry": {"coordinates":[175.148788,-40.759144],"type":"Point"}
}