{
  "type": "Feature",
  "properties": {
    "iso:country":"NZ",
    "sg:address":"59 Higgins Rd ",
    "sg:city":"Hamilton",
    "sg:classifiers":[
        {
            "category":"Manufacturing",
            "subcategory":"Rubber & Plastics",
            "type":"Manufacturing & Wholesale Goods"
        }
    ],
    "sg:phone":"+64 7-846 0417",
    "sg:province":"Waikato",
    "sg:tags":[
        "industrial",
        "goods"
    ],
    "wof:name":"Sharp Concepts Ltd",
    "wof:placetype":"venue"
},
  "geometry": {"coordinates":[-87.988968,34.142426],"type":"Point"}
}