{
  "type": "Feature",
  "properties": {
    "iso:country":"NZ",
    "sg:address":"3 Landel Pl ",
    "sg:city":"Whitianga",
    "sg:classifiers":[
        {
            "category":"Shopping",
            "subcategory":"Bicycles & Sporting Goods",
            "type":"Retail Goods"
        }
    ],
    "sg:phone":"+64 7-866 5760",
    "sg:tags":[
        "sport",
        "fishing",
        "hunting",
        "retailers"
    ],
    "wof:name":"Waters Edge Motor Lodge",
    "wof:placetype":"venue"
},
  "geometry": {"coordinates":[175.702667,-36.796497],"type":"Point"}
}