{
  "type": "Feature",
  "properties": {
    "iso:country":"NZ",
    "sg:address":"130 A Riccarton Rd Riccarton ",
    "sg:city":"Christchurch",
    "sg:classifiers":[
        {
            "category":"Professional",
            "subcategory":"Art Services",
            "type":"Services"
        }
    ],
    "sg:phone":"+64 3-348 6600",
    "sg:province":"Canterbury",
    "sg:tags":[
        "picture",
        "arts",
        "sport",
        "framing",
        "leisure"
    ],
    "wof:name":"Art & Frame",
    "wof:placetype":"venue"
},
  "geometry": {"coordinates":[172.598099,-43.52977],"type":"Point"}
}