{
  "type": "Feature",
  "properties": {
    "iso:country":"NZ",
    "sg:address":"7 Rue Lavaud ",
    "sg:city":"Akaroa",
    "sg:classifiers":[
        {
            "category":"Communications",
            "subcategory":"Radio Station",
            "type":"Services"
        }
    ],
    "sg:phone":"+64 3-304 7350",
    "sg:province":"Canterbury",
    "sg:tags":[
        "broadcasting"
    ],
    "wof:name":"Akaroa Bay Radio",
    "wof:placetype":"venue"
},
  "geometry": {"coordinates":[172.970444,-43.800922],"type":"Point"}
}