{
  "type": "Feature",
  "properties": {
    "addr:full":"305 Heads Rd  Wanganui Manawatu-Wanganui",
    "addr:housenumber":"305",
    "addr:street":"Heads Rd",
    "iso:country":"NZ",
    "sg:address":"305 Heads Rd ",
    "sg:city":"Wanganui",
    "sg:classifiers":[
        {
            "category":"Retail",
            "subcategory":"Laundry & Dry Cleaning",
            "type":"Services"
        }
    ],
    "sg:phone":"+64 6-344 7333",
    "sg:province":"Manawatu-Wanganui",
    "sg:tags":[
        "product",
        "wool",
        "clothing",
        "fabric"
    ],
    "wof:name":"NZ Wool Testing Authority Ltd",
    "wof:placetype":"venue"
},
  "geometry": {"coordinates":[175.01817299999999,-39.949146],"type":"Point"}
}