{
  "type": "Feature",
  "properties": {
    "addr:full":"255 Sparks Rd Prebbleton  Christchurch Canterbury",
    "addr:housenumber":"255",
    "addr:street":"Sparks Rd",
    "iso:country":"NZ",
    "sg:address":"255 Sparks Rd Prebbleton ",
    "sg:city":"Christchurch",
    "sg:classifiers":[
        {
            "category":"Shopping",
            "subcategory":"Stationery & Office Supplies",
            "type":"Retail Goods"
        }
    ],
    "sg:phone":"+64 3-339 0633",
    "sg:province":"Canterbury",
    "sg:tags":[
        "supplies",
        "educational",
        "material",
        "education",
        "training"
    ],
    "sg:website":"http://www.classysisters.co.nz",
    "wof:name":"Sisters",
    "wof:placetype":"venue"
},
  "geometry": {"coordinates":[172.51194799999999,-43.578697],"type":"Point"}
}