{
  "type": "Feature",
  "properties": {
    "iso:country":"NZ",
    "sg:address":"201 Gt South Rd",
    "sg:city":"Papakura",
    "sg:classifiers":[
        {
            "category":"Banks & Credit Unions",
            "subcategory":"Bank",
            "type":"Services"
        }
    ],
    "sg:phone":"+64 9-298 7144",
    "wof:name":"ANZ Banking Group (New Zealand) Ltd",
    "wof:placetype":"venue"
},
  "geometry": {"coordinates":[174.959457,-37.059521],"type":"Point"}
}