{
  "type": "Feature",
  "properties": {
    "iso:country":"NZ",
    "sg:address":"6 Waione St Petone ",
    "sg:city":"Wellington",
    "sg:classifiers":[
        {
            "category":"Farming",
            "subcategory":"Fish & Marine Products",
            "type":"Manufacturing & Wholesale Goods"
        }
    ],
    "sg:phone":"+64 4-589 4332",
    "sg:province":"Wellington",
    "sg:tags":[
        "health",
        "beauty"
    ],
    "wof:name":"Safe & Secure Ltd",
    "wof:placetype":"venue"
},
  "geometry": {"coordinates":[174.890564,-41.232014],"type":"Point"}
}