{
  "type": "Feature",
  "properties": {
    "iso:country":"NZ",
    "sg:address":"832 Tremaine Ave Palmerston ",
    "sg:city":"Palmerston North",
    "sg:classifiers":[
        {
            "category":"Manufacturing",
            "subcategory":"Tools & Machinery",
            "type":"Manufacturing & Wholesale Goods"
        }
    ],
    "sg:phone":"+64 6-356 2815",
    "sg:province":"Manawatu-Wanganui",
    "sg:tags":[
        "equipment",
        "industrial",
        "pneumatic",
        "tools"
    ],
    "wof:name":"Combined Industrial Services Group",
    "wof:placetype":"venue"
},
  "geometry": {"coordinates":[175.62159700000001,-40.334541],"type":"Point"}
}