{
  "type": "Feature",
  "properties": {
    "addr:full":"Cnr Omahi St & Kapanui Rd  Waikanae",
    "addr:street":"Cnr Omahi St & Kapanui Rd",
    "iso:country":"NZ",
    "sg:address":"Cnr Omahi St & Kapanui Rd ",
    "sg:city":"Waikanae",
    "sg:classifiers":[
        {
            "category":"Banks & Credit Unions",
            "subcategory":"Investment Brokerage",
            "type":"Services"
        }
    ],
    "sg:phone":"+64 4-293 6844",
    "sg:tags":[
        "director",
        "funeral",
        "arrangements"
    ],
    "wof:name":"Waikanae Funeral Home",
    "wof:placetype":"venue"
},
  "geometry": {"coordinates":[175.06100499999999,-40.87318],"type":"Point"}
}