{
  "type": "Feature",
  "properties": {
    "iso:country":"NZ",
    "sg:address":"2G Rothwell Ave ",
    "sg:city":"Albany",
    "sg:orig_category":"Home And Garden: Furniture/Furnishings: Blinds",
    "sg:phone":"+64 9-415 1596",
    "sg:province":"Auckland",
    "wof:name":"Mr Sparkel",
    "wof:placetype":"venue"
},
  "geometry": {"coordinates":[-122.298004,37.887283],"type":"Point"}
}