{
  "type": "Feature",
  "properties": {
    "iso:country":"NZ",
    "sg:address":"137 Molesworth St New ",
    "sg:city":"Plymouth",
    "sg:orig_category":"Industrial: Metal: Products: Aluminium Products",
    "sg:phone":"+64 6-759 9120",
    "sg:province":"Taranaki",
    "wof:name":"Ullrich Aluminium Co Ltd",
    "wof:placetype":"venue"
},
  "geometry": {"coordinates":[-116.819725,43.97221],"type":"Point"}
}