{
  "type": "Feature",
  "properties": {
    "iso:country":"NZ",
    "sg:address":"Bracken Court 480 Moray Pl ",
    "sg:city":"Dunedin",
    "sg:classifiers":[
        {
            "category":"Professional",
            "subcategory":"Art Services",
            "type":"Services"
        }
    ],
    "sg:phone":"+64 25358500",
    "sg:province":"Otago",
    "sg:tags":[
        "personal",
        "photographer",
        "services",
        "garden",
        "home"
    ],
    "wof:name":"Elizabeth Goodall",
    "wof:placetype":"venue"
},
  "geometry": {"coordinates":[-82.784721,28.013355],"type":"Point"}
}