{
  "type": "Feature",
  "properties": {
    "addr:full":"PO Box 302  Taupo Waikato",
    "addr:housenumber":"po;302",
    "addr:street":"Box",
    "iso:country":"NZ",
    "sg:address":"PO Box 302 ",
    "sg:city":"Taupo",
    "sg:classifiers":[
        {
            "category":"Home & Garden",
            "subcategory":"Carpets & Floor Coverings",
            "type":"Retail Goods"
        }
    ],
    "sg:phone":"+64 7-378 3700",
    "sg:province":"Waikato",
    "sg:tags":[
        "cleaning",
        "furniture"
    ],
    "wof:name":"ZZ Best Carpet & Upholstery Cleaning",
    "wof:placetype":"venue"
},
  "geometry": {"coordinates":[176.084351,-38.689285],"type":"Point"}
}