{
  "type": "Feature",
  "properties": {
    "addr:full":"12 Fitzherbert St  Hokitika West Coast",
    "addr:housenumber":"12",
    "addr:street":"Fitzherbert St",
    "iso:country":"NZ",
    "sg:address":"12 Fitzherbert St ",
    "sg:city":"Hokitika",
    "sg:classifiers":[
        {
            "category":"Travel",
            "subcategory":"Hotels & Motels",
            "type":"Entertainment"
        }
    ],
    "sg:phone":"+64 3-755 8098",
    "sg:province":"West Coast",
    "sg:tags":[
        "holiday",
        "tourism",
        "accommodation"
    ],
    "sg:website":"http://www.minidata.co.nz/heritage/",
    "wof:name":"Heritage Highway Motel Hokitika",
    "wof:placetype":"venue"
},
  "geometry": {"coordinates":[170.97219799999999,-42.711411],"type":"Point"}
}