{
  "type": "Feature",
  "properties": {
    "addr:full":"Hautapu St  Taihape",
    "addr:street":"Hautapu St",
    "iso:country":"NZ",
    "sg:address":"Hautapu St ",
    "sg:city":"Taihape",
    "sg:orig_category":"Automotive: General Services: Service Stations",
    "sg:phone":"+64 6-388 0481",
    "wof:name":"BP Oil",
    "wof:placetype":"venue"
},
  "geometry": {"coordinates":[175.79930100000001,-39.678398],"type":"Point"}
}