{
  "type": "Feature",
  "properties": {
    "addr:full":"23 Tasman St Mt Cook  Wellington Wellington",
    "addr:housenumber":"23",
    "addr:street":"Tasman St",
    "iso:country":"NZ",
    "sg:address":"23 Tasman St Mt Cook ",
    "sg:city":"Wellington",
    "sg:classifiers":[
        {
            "category":"Shopping",
            "subcategory":"Pets & Pet Supplies",
            "type":"Retail Goods"
        }
    ],
    "sg:phone":"+64 4-385 7773",
    "sg:province":"Wellington",
    "sg:tags":[
        "boarding",
        "garden",
        "pets",
        "catteries",
        "home",
        "kennel"
    ],
    "wof:name":"Tasman St Veterinary Clinic",
    "wof:placetype":"venue"
},
  "geometry": {"coordinates":[174.77816799999999,-41.299683],"type":"Point"}
}