{
  "type": "Feature",
  "properties": {
    "iso:country":"NZ",
    "sg:address":"2B/1 William Pickering Dve Albany ",
    "sg:city":"Auckland",
    "sg:classifiers":[
        {
            "category":"Banks & Credit Unions",
            "subcategory":"Financial Services",
            "type":"Services"
        }
    ],
    "sg:phone":"+64 9-414 1288",
    "sg:province":"Auckland",
    "sg:tags":[
        "finance"
    ],
    "sg:website":"http://www.yellowpages.co.nz/for/accountingnorth/dp23074.html",
    "wof:name":"Accounting North Ltd",
    "wof:placetype":"venue"
},
  "geometry": {"coordinates":[174.707062,-36.753628],"type":"Point"}
}