{
  "type": "Feature",
  "properties": {
    "iso:country":"NZ",
    "sg:address":"2/5 Joval Pl Manukau ",
    "sg:city":"Auckland",
    "sg:orig_category":"Automotive: Parts And Supplies: Wheels",
    "sg:phone":"+64 9-262 0510",
    "sg:province":"Auckland",
    "wof:name":"Sharrock Engineers",
    "wof:placetype":"venue"
},
  "geometry": {"coordinates":[-119.10457599999999,36.597755],"type":"Point"}
}