{
  "type": "Feature",
  "properties": {
    "addr:full":"92 Commerce St  Kaitaia Northland",
    "addr:housenumber":"92",
    "addr:street":"Commerce St",
    "iso:country":"NZ",
    "sg:address":"92 Commerce St ",
    "sg:city":"Kaitaia",
    "sg:classifiers":[
        {
            "category":"Bars & Pubs",
            "subcategory":"Wine Bar",
            "type":"Food & Drink"
        }
    ],
    "sg:phone":"+64 9-408 1160",
    "sg:province":"Northland",
    "sg:tags":[
        "wining",
        "dining",
        "cafe"
    ],
    "wof:name":"The Gecko Cafe",
    "wof:placetype":"venue"
},
  "geometry": {"coordinates":[173.26226800000001,-35.112064],"type":"Point"}
}