{
  "type": "Feature",
  "properties": {
    "iso:country":"NZ",
    "sg:address":"Office & Chapel 36 Maich Rd Manurewa ",
    "sg:city":"Auckland",
    "sg:classifiers":[
        {
            "category":"Banks & Credit Unions",
            "subcategory":"Investment Brokerage",
            "type":"Services"
        }
    ],
    "sg:phone":"+64 9-266 6177",
    "sg:province":"Auckland",
    "sg:tags":[
        "director",
        "funeral",
        "arrangements"
    ],
    "wof:name":"Manukau City Funeral Services",
    "wof:placetype":"venue"
},
  "geometry": {"coordinates":[174.895905,-37.021271],"type":"Point"}
}