{
  "type": "Feature",
  "properties": {
    "addr:full":"7 Hill Rd Manurewa  Auckland Auckland",
    "addr:housenumber":"7",
    "addr:street":"Hill Rd",
    "iso:country":"NZ",
    "sg:address":"7 Hill Rd Manurewa ",
    "sg:city":"Auckland",
    "sg:classifiers":[
        {
            "category":"Professional",
            "subcategory":"Art Services",
            "type":"Services"
        }
    ],
    "sg:phone":"+64 9-267 7843",
    "sg:province":"Auckland",
    "sg:tags":[
        "picture",
        "arts",
        "sport",
        "framing",
        "leisure"
    ],
    "wof:name":"G n L Limited",
    "wof:placetype":"venue"
},
  "geometry": {"coordinates":[174.91696200000001,-37.021488],"type":"Point"}
}