{
  "type": "Feature",
  "properties": {
    "iso:country":"NZ",
    "sg:address":"42 Allens Rd East Tamaki ",
    "sg:city":"Auckland",
    "sg:classifiers":[
        {
            "category":"Manufacturing",
            "subcategory":"Tools & Machinery",
            "type":"Manufacturing & Wholesale Goods"
        }
    ],
    "sg:phone":"+64 9-274 7530",
    "sg:province":"Auckland",
    "sg:tags":[
        "equipment",
        "industrial",
        "hydraulic"
    ],
    "wof:name":"North Hydraulics",
    "wof:placetype":"venue"
},
  "geometry": {"coordinates":[174.888214,-36.942081],"type":"Point"}
}