{
  "type": "Feature",
  "properties": {
    "iso:country":"NZ",
    "sg:address":"cnr Mahia Ave & Bridge St ",
    "sg:city":"Wairoa",
    "sg:classifiers":[
        {
            "category":"Farming",
            "subcategory":"Farm & Veterinary Services",
            "type":"Manufacturing & Wholesale Goods"
        }
    ],
    "sg:phone":"+64 6-838 7209",
    "sg:tags":[
        "supplies",
        "supply"
    ],
    "wof:name":"Farmlands Trading Society Ltd",
    "wof:placetype":"venue"
},
  "geometry": {"coordinates":[177.427032,-39.038639],"type":"Point"}
}