{
  "type": "Feature",
  "properties": {
    "addr:full":"5 Rose Rd Ponsonby  Auckland Auckland",
    "addr:housenumber":"5",
    "addr:street":"Rose Rd",
    "iso:country":"NZ",
    "sg:address":"5 Rose Rd Ponsonby ",
    "sg:city":"Auckland",
    "sg:classifiers":[
        {
            "category":"Shopping",
            "subcategory":"Gifts & Souvenirs",
            "type":"Retail Goods"
        }
    ],
    "sg:phone":"+64 9-360 1909",
    "sg:province":"Auckland",
    "sg:tags":[
        "shop",
        "gifts",
        "supplier"
    ],
    "wof:name":"Chan Andreassend Retail Studio",
    "wof:placetype":"venue"
},
  "geometry": {"coordinates":[174.74241599999999,-36.85326],"type":"Point"}
}