{
  "type": "Feature",
  "properties": {
    "iso:country":"NZ",
    "sg:address":"Lido Arc Manukau Rd Epsom ",
    "sg:city":"Auckland",
    "sg:orig_category":"Shopping: Accessories: Jewellers And Watchmakers",
    "sg:phone":"+64 9-631 5243",
    "sg:province":"Auckland",
    "wof:name":"AVA Swiss Watch Co Ltd",
    "wof:placetype":"venue"
},
  "geometry": {"coordinates":[174.77356,-36.876179],"type":"Point"}
}