{
  "type": "Feature",
  "properties": {
    "iso:country":"NZ",
    "sg:address":"10th Floor 111 The Terrace PO Box 10169 ",
    "sg:city":"Wellington",
    "sg:classifiers":[
        {
            "category":"Airline",
            "type":"Transportation"
        }
    ],
    "sg:phone":"+64 800 777 747",
    "sg:province":"Waikato",
    "sg:tags":[
        "services",
        "travel",
        "tourism"
    ],
    "wof:name":"Malaysia Airlines",
    "wof:placetype":"venue"
},
  "geometry": {"coordinates":[-100.21779600000001,34.85413],"type":"Point"}
}