{
  "type": "Feature",
  "properties": {
    "addr:full":"22 Victoria Ave Palmerston  Palmerston North Manawatu-Wanganui",
    "addr:housenumber":"22",
    "addr:street":"Victoria Ave",
    "iso:country":"NZ",
    "sg:address":"22 Victoria Ave Palmerston ",
    "sg:city":"Palmerston North",
    "sg:orig_category":"Health And Beauty: Specialists: Podiatrists",
    "sg:phone":"+64 6-355 3300",
    "sg:province":"Manawatu-Wanganui",
    "wof:name":"Aitken K A J",
    "wof:placetype":"venue"
},
  "geometry": {"coordinates":[175.618134,-40.3503],"type":"Point"}
}