{
  "type": "Feature",
  "properties": {
    "iso:country":"NZ",
    "sg:address":"45 Northumberland St ",
    "sg:city":"Tapanui",
    "sg:orig_category":"Clothing And Fabric: Fabric: Drapers",
    "sg:phone":"+64 3-204 8369",
    "wof:name":"Seasons",
    "wof:placetype":"venue"
},
  "geometry": {"coordinates":[169.265137,-45.943466],"type":"Point"}
}