{
  "type": "Feature",
  "properties": {
    "iso:country":"NZ",
    "sg:address":"145 Waihi Rd ",
    "sg:city":"Tauranga",
    "sg:classifiers":[
        {
            "category":"Building & Trades",
            "subcategory":"Electrical",
            "type":"Services"
        }
    ],
    "sg:phone":"+64 7-578 9045",
    "sg:province":"Bay of Plenty",
    "sg:tags":[
        "industrial",
        "refrigeration"
    ],
    "wof:name":"Johns Refrigeration Services",
    "wof:placetype":"venue"
},
  "geometry": {"coordinates":[176.143204,-37.695366],"type":"Point"}
}