{
  "type": "Feature",
  "properties": {
    "addr:full":"111 Tasman St  Opunake",
    "addr:housenumber":"111",
    "addr:street":"Tasman St",
    "iso:country":"NZ",
    "sg:address":"111 Tasman St ",
    "sg:city":"Opunake",
    "sg:classifiers":[
        {
            "category":"Retail",
            "subcategory":"Auto Repair",
            "type":"Services"
        }
    ],
    "sg:phone":"+64 6-761 8502",
    "sg:tags":[
        "automotive",
        "servicing"
    ],
    "wof:name":"Ihaia Motors Ltd",
    "wof:placetype":"venue"
},
  "geometry": {"coordinates":[173.845947,-39.448475],"type":"Point"}
}