{
  "type": "Feature",
  "properties": {
    "addr:full":"Kingsway Mall PO Box 2090  Whakatane Auckland",
    "addr:housenumber":"po;2090",
    "addr:street":"Kingsway",
    "iso:country":"NZ",
    "sg:address":"Kingsway Mall PO Box 2090 ",
    "sg:city":"Whakatane",
    "sg:classifiers":[
        {
            "category":"Communications",
            "subcategory":"Radio Station",
            "type":"Services"
        }
    ],
    "sg:phone":"+64 7-308 0403",
    "sg:province":"Auckland",
    "sg:tags":[
        "broadcasting"
    ],
    "wof:name":"Sun 98 FM",
    "wof:placetype":"venue"
},
  "geometry": {"coordinates":[176.98419200000001,-37.965305],"type":"Point"}
}