{
  "type": "Feature",
  "properties": {
    "addr:full":"4 Cargill St Mosgiel  Dunedin Otago",
    "addr:housenumber":"4",
    "addr:street":"Cargill St",
    "iso:country":"NZ",
    "sg:address":"4 Cargill St Mosgiel ",
    "sg:city":"Dunedin",
    "sg:orig_category":"Farming: Services: Veterinarians",
    "sg:phone":"+64 3-489 4753",
    "sg:province":"Otago",
    "wof:name":"Mosgiel Veterinary Services",
    "wof:placetype":"venue"
},
  "geometry": {"coordinates":[170.350266,-45.876305],"type":"Point"}
}