{
  "type": "Feature",
  "properties": {
    "iso:country":"NZ",
    "sg:address":"268 Main South Rd Hornby ",
    "sg:city":"Christchurch",
    "sg:classifiers":[
        {
            "category":"Autos & Motor Vehicles",
            "subcategory":"Automobile Sales",
            "type":"Retail Goods"
        }
    ],
    "sg:phone":"+64 3-349 2614",
    "sg:province":"Canterbury",
    "sg:tags":[
        "car",
        "-used",
        "leasing",
        "truck",
        "automotive"
    ],
    "sg:website":"http://www.bussales.co.nz",
    "wof:name":"City South Commercials Ltd",
    "wof:placetype":"venue"
},
  "geometry": {"coordinates":[172.542419,-43.54314],"type":"Point"}
}