{
  "type": "Feature",
  "properties": {
    "iso:country":"NZ",
    "sg:address":"320 Rosedale Rd Albany ",
    "sg:city":"Auckland",
    "sg:classifiers":[
        {
            "category":"Manufacturing",
            "subcategory":"Rubber & Plastics",
            "type":"Manufacturing & Wholesale Goods"
        }
    ],
    "sg:phone":"+64 9-415 2800",
    "sg:province":"Auckland",
    "sg:tags":[
        "industrial"
    ],
    "sg:website":"http://www.psp.co.nz",
    "wof:name":"PSP Ltd",
    "wof:placetype":"venue"
},
  "geometry": {"coordinates":[174.70396400000001,-36.741528],"type":"Point"}
}