{
  "type": "Feature",
  "properties": {
    "addr:full":"178 Papanui Rd Merivale  Christchurch Canterbury",
    "addr:housenumber":"178",
    "addr:street":"Papanui Rd",
    "iso:country":"NZ",
    "sg:address":"178 Papanui Rd Merivale ",
    "sg:city":"Christchurch",
    "sg:classifiers":[
        {
            "category":"Shopping",
            "subcategory":"Crafts & Fabrics",
            "type":"Retail Goods"
        }
    ],
    "sg:phone":"+64 3-355 5942",
    "sg:province":"Canterbury",
    "sg:tags":[
        "leather",
        "clothing",
        "suede"
    ],
    "wof:name":"Moores Dry Cleaners Ltd",
    "wof:placetype":"venue"
},
  "geometry": {"coordinates":[172.62223800000001,-43.512768],"type":"Point"}
}