{
  "type": "Feature",
  "properties": {
    "iso:country":"NZ",
    "sg:address":"Five Cross Roads ",
    "sg:city":"Hamilton",
    "sg:classifiers":[
        {
            "category":"Insurance",
            "subcategory":"Health Insurance",
            "type":"Services"
        }
    ],
    "sg:phone":"+64 7-855 9821",
    "sg:province":"Waikato",
    "sg:tags":[
        "beauty"
    ],
    "wof:name":"Hairline",
    "wof:placetype":"venue"
},
  "geometry": {"coordinates":[-74.658821,40.202126],"type":"Point"}
}