{
  "type": "Feature",
  "properties": {
    "addr:full":"Plaza Shopping Centre Eleventh Ave  Tauranga Bay of Plenty",
    "addr:street":"Centre Eleventh Ave",
    "iso:country":"NZ",
    "sg:address":"Plaza Shopping Centre Eleventh Ave ",
    "sg:city":"Tauranga",
    "sg:classifiers":[
        {
            "category":"Fast Food",
            "type":"Food & Drink"
        }
    ],
    "sg:phone":"+64 7-578 3918",
    "sg:province":"Bay of Plenty",
    "sg:tags":[
        "seafood",
        "sea"
    ],
    "wof:name":"Delking Prawn Dist",
    "wof:placetype":"venue"
},
  "geometry": {"coordinates":[176.159378,-37.698418],"type":"Point"}
}