{
  "type": "Feature",
  "properties": {
    "addr:full":"50 Hobson Street - Thorndon -  Wellington Wellington",
    "addr:housenumber":"50",
    "addr:street":"Hobson Street",
    "iso:country":"NZ",
    "sg:address":"50 Hobson Street - Thorndon - ",
    "sg:city":"Wellington",
    "sg:classifiers":[
        {
            "category":"Professional",
            "subcategory":"Art Services",
            "type":"Services"
        }
    ],
    "sg:phone":"+64 6444729848",
    "sg:province":"Wellington",
    "sg:tags":[
        "export-import"
    ],
    "wof:name":"Philippines Embassy",
    "wof:placetype":"venue"
},
  "geometry": {"coordinates":[174.781082,-41.272552],"type":"Point"}
}