{
  "type": "Feature",
  "properties": {
    "iso:country":"NZ",
    "sg:address":"174-182 View Rd ",
    "sg:city":"Rotorua",
    "sg:orig_category":"Transport: Land: Taxis",
    "sg:phone":"+64 7-348 1111",
    "sg:province":"Bay of Plenty",
    "wof:name":"Rotorua Taxi's",
    "wof:placetype":"venue"
},
  "geometry": {"coordinates":[176.22341900000001,-38.13298],"type":"Point"}
}