{
  "type": "Feature",
  "properties": {
    "addr:full":"357 Jackson St Petone Lower  Hutt Wellington",
    "addr:housenumber":"357",
    "addr:street":"Jackson St",
    "iso:country":"NZ",
    "sg:address":"357 Jackson St Petone Lower ",
    "sg:city":"Hutt",
    "sg:classifiers":[
        {
            "category":"Shopping",
            "subcategory":"Photographic Equipment",
            "type":"Retail Goods"
        }
    ],
    "sg:phone":"+64 4-568 6782",
    "sg:province":"Wellington",
    "sg:tags":[
        "sport",
        "leisure",
        "hobbies"
    ],
    "wof:name":"Phil Jacobs",
    "wof:placetype":"venue"
},
  "geometry": {"coordinates":[174.88566599999999,-41.227417],"type":"Point"}
}