{
  "type": "Feature",
  "properties": {
    "iso:country":"NZ",
    "sg:address":"55 McLean St ",
    "sg:city":"Waitara",
    "sg:orig_category":"Shopping: Retail Stores: Books: Bookshops",
    "sg:phone":"+64 6-754 8262",
    "wof:name":"Thelma's Post & Lotto",
    "wof:placetype":"venue"
},
  "geometry": {"coordinates":[174.239532,-39.000023],"type":"Point"}
}