{
  "type": "Feature",
  "properties": {
    "addr:full":"301 Racecourse Road  Cambridge Gisborne",
    "addr:housenumber":"301",
    "addr:street":"Racecourse Road",
    "iso:country":"NZ",
    "sg:address":"301 Racecourse Road ",
    "sg:city":"Cambridge",
    "sg:orig_category":"Sports And Leisure: Sports: Equestrian: Saddlers",
    "sg:phone":"+64 7-823 4561",
    "sg:province":"Gisborne",
    "wof:name":"New Zealand Horse Shoe Company Ltd",
    "wof:placetype":"venue"
},
  "geometry": {"coordinates":[-116.67604799999999,44.572186],"type":"Point"}
}