{
  "type": "Feature",
  "properties": {
    "addr:full":"Railway St  Helensville Auckland",
    "addr:street":"Railway St",
    "iso:country":"NZ",
    "sg:address":"Railway St ",
    "sg:city":"Helensville",
    "sg:classifiers":[
        {
            "category":"Wholesale",
            "subcategory":"Hardware",
            "type":"Manufacturing & Wholesale Goods"
        }
    ],
    "sg:phone":"+64 9-420 8569",
    "sg:province":"Auckland",
    "sg:tags":[
        "gardening",
        "garden",
        "chainsaw",
        "products",
        "brush",
        "home",
        "cutter"
    ],
    "wof:name":"Hayes Chainsaws & Mowers Ltd",
    "wof:placetype":"venue"
},
  "geometry": {"coordinates":[174.45124799999999,-36.667206],"type":"Point"}
}