{
  "type": "Feature",
  "properties": {
    "addr:full":"26 Te Aroha St  Hamilton Waikato",
    "addr:housenumber":"26",
    "addr:street":"Te Aroha St",
    "iso:country":"NZ",
    "sg:address":"26 Te Aroha St ",
    "sg:city":"Hamilton",
    "sg:classifiers":[
        {
            "category":"Retail",
            "subcategory":"Laundry & Dry Cleaning",
            "type":"Services"
        }
    ],
    "sg:phone":"+64 7-854 9772",
    "sg:province":"Waikato",
    "sg:tags":[
        "repair",
        "clothing",
        "fabric"
    ],
    "wof:name":"Claudelands Laundromat",
    "wof:placetype":"venue"
},
  "geometry": {"coordinates":[175.28919999999999,-37.782932],"type":"Point"}
}