{
  "type": "Feature",
  "properties": {
    "addr:full":"72 King St  Timaru Canterbury",
    "addr:housenumber":"72",
    "addr:street":"King St",
    "iso:country":"NZ",
    "sg:address":"72 King St ",
    "sg:city":"Timaru",
    "sg:classifiers":[
        {
            "category":"Home & Garden",
            "subcategory":"Garden Supply",
            "type":"Retail Goods"
        }
    ],
    "sg:phone":"+64 3-688 9440",
    "sg:province":"Canterbury",
    "sg:tags":[
        "products",
        "nursery",
        "gardening"
    ],
    "wof:name":"Timaru Wholesale Plants",
    "wof:placetype":"venue"
},
  "geometry": {"coordinates":[171.24745200000001,-44.41478],"type":"Point"}
}