{
  "type": "Feature",
  "properties": {
    "addr:full":"606 Hillside Rd South Dunedin  Dunedin Otago",
    "addr:housenumber":"606",
    "addr:street":"Hillside Rd",
    "iso:country":"NZ",
    "sg:address":"606 Hillside Rd South Dunedin ",
    "sg:city":"Dunedin",
    "sg:classifiers":[
        {
            "category":"Home & Garden",
            "subcategory":"Building Materials",
            "type":"Retail Goods"
        }
    ],
    "sg:phone":"+64 3-455 1485",
    "sg:province":"Otago",
    "sg:tags":[
        "electrician",
        "related"
    ],
    "wof:name":"Brown Victor Electrical (1977) Ltd",
    "wof:placetype":"venue"
},
  "geometry": {"coordinates":[170.49006700000001,-45.896667],"type":"Point"}
}