{
  "type": "Feature",
  "properties": {
    "addr:full":"82 Cameron St  Whangarei Northland",
    "addr:housenumber":"82",
    "addr:street":"Cameron St",
    "iso:country":"NZ",
    "sg:address":"82 Cameron St ",
    "sg:city":"Whangarei",
    "sg:classifiers":[
        {
            "category":"Fast Food",
            "type":"Food & Drink"
        }
    ],
    "sg:phone":"+64 9-459 7536",
    "sg:province":"Northland",
    "sg:tags":[
        "wining",
        "dining",
        "takeaway"
    ],
    "wof:name":"Real Kebabs",
    "wof:placetype":"venue"
},
  "geometry": {"coordinates":[174.32250999999999,-35.726681],"type":"Point"}
}