{
  "type": "Feature",
  "properties": {
    "addr:full":"Napier  Napier Hawke's Bay",
    "iso:country":"NZ",
    "sg:address":"Napier ",
    "sg:city":"Napier",
    "sg:classifiers":[
        {
            "category":"Building & Trades",
            "subcategory":"Pest Control",
            "type":"Services"
        }
    ],
    "sg:phone":"+64 6-844 2008",
    "sg:province":"Hawke's Bay",
    "sg:tags":[
        "home",
        "garden"
    ],
    "wof:name":"Basil Brush Chimney Cleaning & Pest Control",
    "wof:placetype":"venue"
},
  "geometry": {"coordinates":[19.905689,-34.47776],"type":"Point"}
}