{
  "type": "Feature",
  "properties": {
    "addr:full":"43 Western Hills Dve Kensington  Whangarei Northland",
    "addr:housenumber":"43",
    "addr:street":"Western",
    "iso:country":"NZ",
    "sg:address":"43 Western Hills Dve Kensington ",
    "sg:city":"Whangarei",
    "sg:classifiers":[
        {
            "category":"Health Services",
            "subcategory":"Clinic",
            "type":"Services"
        }
    ],
    "sg:phone":"+64 9-437 5750",
    "sg:province":"Northland",
    "sg:tags":[
        "medical",
        "beauty"
    ],
    "wof:name":"Ambulance",
    "wof:placetype":"venue"
},
  "geometry": {"coordinates":[174.3125,-35.703903],"type":"Point"}
}