{
  "type": "Feature",
  "properties": {
    "addr:full":"Jenny Barnett  (NZROHA)",
    "iso:country":"NZ",
    "sg:address":"Jenny Barnett ",
    "sg:city":"(NZROHA)",
    "sg:orig_category":"Shopping: Hobbies And Games: Aromatherapy",
    "sg:phone":"+64 3-476 2826",
    "wof:name":"Touch Techniques",
    "wof:placetype":"venue"
},
  "geometry": {"coordinates":[-92.67437700000001,38.378864],"type":"Point"}
}