{
  "type": "Feature",
  "properties": {
    "iso:country":"NZ",
    "sg:address":"820 Colombo St ",
    "sg:city":"Christchurch",
    "sg:orig_category":"Health And Beauty: Beauty: Manicurists",
    "sg:phone":"+64 3-366 2510",
    "sg:province":"Canterbury",
    "wof:name":"MC For Nails",
    "wof:placetype":"venue"
},
  "geometry": {"coordinates":[172.63674900000001,-43.525707],"type":"Point"}
}