{
  "type": "Feature",
  "properties": {
    "addr:full":"10 Agency La Silverdale  Auckland Auckland",
    "addr:housenumber":"10",
    "addr:street":"Agency La",
    "iso:country":"NZ",
    "sg:address":"10 Agency La Silverdale ",
    "sg:city":"Auckland",
    "sg:orig_category":"Transport: Boats And Marine: Boats: Boat Dealers",
    "sg:phone":"+64 9-426 5087",
    "sg:province":"Auckland",
    "wof:name":"Silverdale Marine",
    "wof:placetype":"venue"
},
  "geometry": {"coordinates":[174.67791700000001,-36.617527],"type":"Point"}
}