{
  "type": "Feature",
  "properties": {
    "addr:full":"Top of the Hill Albany  Auckland Auckland",
    "iso:country":"NZ",
    "sg:address":"Top of the Hill Albany ",
    "sg:city":"Auckland",
    "sg:classifiers":[
        {
            "category":"Retail",
            "subcategory":"Auto Repair",
            "type":"Services"
        }
    ],
    "sg:phone":"+64 9-415 9892",
    "sg:province":"Auckland",
    "sg:tags":[
        "wheel",
        "automotive",
        "servicing",
        "alignment"
    ],
    "wof:name":"Albany Tyres & Alignment",
    "wof:placetype":"venue"
},
  "geometry": {"coordinates":[174.78376800000001,-36.900364],"type":"Point"}
}