{
  "type": "Feature",
  "properties": {
    "iso:country":"NZ",
    "sg:address":"31 Algernon Rd RD 2 ",
    "sg:city":"Hastings",
    "sg:orig_category":"Shopping: Accessories: Accessories - Clothing",
    "sg:phone":"+64 6-878 8571",
    "sg:province":"Hawke's Bay",
    "wof:name":"Jan's Silks",
    "wof:placetype":"venue"
},
  "geometry": {"coordinates":[-98.368942,40.583874],"type":"Point"}
}