{
  "type": "Feature",
  "properties": {
    "iso:country":"NZ",
    "sg:address":"97 View Rd ",
    "sg:city":"Rotorua",
    "sg:orig_category":"Transport: Transportation: Heavy Haulage",
    "sg:phone":"+64 7-348 2860",
    "sg:province":"Bay of Plenty",
    "wof:name":"Landtec Ltd",
    "wof:placetype":"venue"
},
  "geometry": {"coordinates":[176.226242,-38.131252],"type":"Point"}
}