{
  "type": "Feature",
  "properties": {
    "addr:full":"97 View Rd  Rotorua Bay of Plenty",
    "addr:housenumber":"97",
    "addr:street":"View Rd",
    "iso:country":"NZ",
    "sg:address":"97 View Rd ",
    "sg:city":"Rotorua",
    "sg:orig_category":"Transport: Transportation: Heavy Haulage",
    "sg:phone":"+64 7-348 2860",
    "sg:province":"Bay of Plenty",
    "wof:name":"Landtec Ltd",
    "wof:placetype":"venue"
},
  "geometry": {"coordinates":[176.22624200000001,-38.131252],"type":"Point"}
}