{
  "type": "Feature",
  "properties": {
    "addr:full":"cnr Eruera & Hinemaru Sts  Rotorua Bay of Plenty",
    "addr:street":"Cnr Eruera & Hinemaru Sts",
    "iso:country":"NZ",
    "sg:address":"cnr Eruera & Hinemaru Sts ",
    "sg:city":"Rotorua",
    "sg:classifiers":[
        {
            "category":"Shopping",
            "subcategory":"Gifts & Souvenirs",
            "type":"Retail Goods"
        }
    ],
    "sg:phone":"+64 7-346 1610",
    "sg:province":"Bay of Plenty",
    "sg:tags":[
        "travel",
        "tourism"
    ],
    "wof:name":"Aotea New Zealand Souvenirs (Rotorua) Ltd",
    "wof:placetype":"venue"
},
  "geometry": {"coordinates":[176.24499499999999,-38.1418],"type":"Point"}
}