{
  "type": "Feature",
  "properties": {
    "iso:country":"NZ",
    "sg:address":"76 Reserve Tce ",
    "sg:city":"Lyttelton",
    "sg:classifiers":[
        {
            "category":"Professional",
            "subcategory":"Art Services",
            "type":"Services"
        }
    ],
    "sg:phone":"+64 3-328 7350",
    "sg:tags":[
        "picture",
        "arts",
        "sport",
        "framing",
        "leisure"
    ],
    "wof:name":"Lyttelton Picture Framing",
    "wof:placetype":"venue"
},
  "geometry": {"coordinates":[172.72688299999999,-43.599735],"type":"Point"}
}