{
  "type": "Feature",
  "properties": {
    "iso:country":"NZ",
    "sg:address":"Cumberland St Leigh ",
    "sg:city":"Warkworth",
    "sg:classifiers":[
        {
            "category":"Restaurant",
            "type":"Food & Drink"
        }
    ],
    "sg:phone":"+64 9-422 6035",
    "sg:province":"Auckland",
    "sg:tags":[
        "sea"
    ],
    "wof:name":"Leigh Fish and Chips",
    "wof:placetype":"venue"
},
  "geometry": {"coordinates":[174.803085,-36.290005],"type":"Point"}
}