{
  "type": "Feature",
  "properties": {
    "iso:country":"NZ",
    "sg:address":"308 Broadway ",
    "sg:city":"Stratford",
    "sg:classifiers":[
        {
            "category":"Communications",
            "subcategory":"Film & Video Production",
            "type":"Services"
        }
    ],
    "sg:phone":"+64 6-765 6863",
    "sg:province":"Manawatu-Wanganui",
    "sg:tags":[
        "sport",
        "leisure",
        "library",
        "entertainment"
    ],
    "wof:name":"Video Ezy Stratford",
    "wof:placetype":"venue"
},
  "geometry": {"coordinates":[-73.123322,41.189938],"type":"Point"}
}