{
  "type": "Feature",
  "properties": {
    "addr:full":"1255 Hinemaru St  Rotorua Bay of Plenty",
    "addr:housenumber":"1255",
    "addr:street":"Hinemaru St",
    "iso:country":"NZ",
    "sg:address":"1255 Hinemaru St ",
    "sg:city":"Rotorua",
    "sg:classifiers":[
        {
            "category":"Travel",
            "subcategory":"Bed & Breakfast",
            "type":"Entertainment"
        }
    ],
    "sg:phone":"+64 7-347 0366",
    "sg:province":"Bay of Plenty",
    "sg:tags":[
        "house",
        "tourism",
        "guest",
        "accommodation"
    ],
    "wof:name":"Eaton Hall Guest House",
    "wof:placetype":"venue"
},
  "geometry": {"coordinates":[176.255402,-38.138092],"type":"Point"}
}