{
  "type": "Feature",
  "properties": {
    "addr:full":"5a Liverpool St  Kawerau",
    "addr:housenumber":"5a",
    "addr:street":"Liverpool St",
    "iso:country":"NZ",
    "sg:address":"5a Liverpool St ",
    "sg:city":"Kawerau",
    "sg:orig_category":"Industrial: Manufacturing",
    "sg:phone":"+64 7-323 8256",
    "wof:name":"Audio Antennas Ltd",
    "wof:placetype":"venue"
},
  "geometry": {"coordinates":[176.70216400000001,-38.083813],"type":"Point"}
}