{
  "type": "Feature",
  "properties": {
    "addr:full":"Main Rd  Haast",
    "addr:street":"Main Rd",
    "iso:country":"NZ",
    "sg:address":"Main Rd ",
    "sg:city":"Haast",
    "sg:classifiers":[
        {
            "category":"Travel",
            "subcategory":"Hotels & Motels",
            "type":"Entertainment"
        }
    ],
    "sg:phone":"+64 3-750 0828",
    "sg:tags":[
        "tavern",
        "tourism",
        "accommodation"
    ],
    "wof:name":"Haast World Heritage Hotel",
    "wof:placetype":"venue"
},
  "geometry": {"coordinates":[169.04364000000001,-43.881626],"type":"Point"}
}