{
  "type": "Feature",
  "properties": {
    "iso:country":"NZ",
    "sg:address":"Level 1, Mid City Centre 18 Manners St ",
    "sg:city":"Wellington",
    "sg:classifiers":[
        {
            "category":"Sports & Exercise",
            "subcategory":"Sports Center",
            "type":"Entertainment"
        }
    ],
    "sg:phone":"+64 4-385 2196",
    "sg:province":"Wellington",
    "sg:tags":[
        "machine",
        "amusement",
        "leisure"
    ],
    "wof:name":"Games Arena",
    "wof:placetype":"venue"
},
  "geometry": {"coordinates":[-87.683342,40.539139],"type":"Point"}
}