{
  "type": "Feature",
  "properties": {
    "iso:country":"NZ",
    "sg:address":"3 Goldfinch St ",
    "sg:city":"Ohakune",
    "sg:orig_category":"Health And Beauty: Specialists: Physiotherapists",
    "sg:phone":"+64 6-385 8799",
    "wof:name":"Don Allomes Physiotherapist",
    "wof:placetype":"venue"
},
  "geometry": {"coordinates":[175.40168800000001,-39.41486],"type":"Point"}
}