{
  "type": "Feature",
  "properties": {
    "addr:full":"25 Saleyards Rd Otahuhu  Auckland Auckland",
    "addr:housenumber":"25",
    "addr:street":"Saleyards Rd",
    "iso:country":"NZ",
    "sg:address":"25 Saleyards Rd Otahuhu ",
    "sg:city":"Auckland",
    "sg:orig_category":"Transport: Transportation: Freight",
    "sg:phone":"+64 9-276 7740",
    "sg:province":"Auckland",
    "wof:name":"Total Freight Solutions Ltd",
    "wof:placetype":"venue"
},
  "geometry": {"coordinates":[174.83360300000001,-36.940678],"type":"Point"}
}