{
  "type": "Feature",
  "properties": {
    "iso:country":"NZ",
    "sg:address":"PO Box 30 201 Lower ",
    "sg:city":"Hutt",
    "sg:orig_category":"Farming: Forestry: Forestry Consultants",
    "sg:phone":"+64 4-570 0232",
    "sg:province":"Wellington",
    "wof:name":"Alan Bell & Associates",
    "wof:placetype":"venue"
},
  "geometry": {"coordinates":[174.90838600000001,-41.206631],"type":"Point"}
}