{
  "type": "Feature",
  "properties": {
    "addr:full":"508 A Karamu Rd Nth  Hastings Hawke's Bay",
    "addr:housenumber":"508",
    "addr:street":"A Karamu Rd",
    "iso:country":"NZ",
    "sg:address":"508 A Karamu Rd Nth ",
    "sg:city":"Hastings",
    "sg:orig_category":"Automotive: Accessories: Car Audio Systems",
    "sg:phone":"+64 6-878 6623",
    "sg:province":"Hawke's Bay",
    "wof:name":"Ansin & Monteith (1987) Ltd",
    "wof:placetype":"venue"
},
  "geometry": {"coordinates":[176.87951699999999,-39.669403],"type":"Point"}
}