{
  "type": "Feature",
  "properties": {
    "addr:full":"350 Albert St Palmerston  Palmerston North Manawatu-Wanganui",
    "addr:housenumber":"350",
    "addr:street":"Albert St Palmerston",
    "iso:country":"NZ",
    "sg:address":"350 Albert St Palmerston ",
    "sg:city":"Palmerston North",
    "sg:classifiers":[
        {
            "category":"Bars & Pubs",
            "subcategory":"Wine Bar",
            "type":"Food & Drink"
        }
    ],
    "sg:phone":"+64 6-357 0779",
    "sg:province":"Manawatu-Wanganui",
    "sg:tags":[
        "shop"
    ],
    "wof:name":"Village Wine Trader",
    "wof:placetype":"venue"
},
  "geometry": {"coordinates":[175.63357500000001,-40.362812],"type":"Point"}
}