{
  "type": "Feature",
  "properties": {
    "iso:country":"NZ",
    "sg:address":"38 Miles La ",
    "sg:city":"Tauranga",
    "sg:orig_category":"Automotive: Parts And Supplies: Windscreens",
    "sg:phone":"+64 800 809 020",
    "sg:province":"Bay of Plenty",
    "wof:name":"Bay of Plenty Windscreens",
    "wof:placetype":"venue"
},
  "geometry": {"coordinates":[176.10337799999999,-37.724323],"type":"Point"}
}