{
  "type": "Feature",
  "properties": {
    "iso:country":"NZ",
    "sg:address":"220 George St ",
    "sg:city":"Dunedin",
    "sg:orig_category":"Clothing And Fabric: Clothing: Menswear",
    "sg:phone":"+64 3-477 8702",
    "sg:province":"Otago",
    "wof:name":"Hamels Menswear",
    "wof:placetype":"venue"
},
  "geometry": {"coordinates":[-82.784721,28.013355],"type":"Point"}
}