{
  "type": "Feature",
  "properties": {
    "addr:full":"500 Mt Wellington Highway Mt Wellington  Auckland Auckland",
    "addr:housenumber":"500",
    "addr:street":"Mt Wellington Highway",
    "iso:country":"NZ",
    "sg:address":"500 Mt Wellington Highway Mt Wellington ",
    "sg:city":"Auckland",
    "sg:orig_category":"Farming: Horticulture: Flowers",
    "sg:phone":"+64 9-573 2300",
    "sg:province":"Auckland",
    "wof:name":"United Flower Auction Ltd",
    "wof:placetype":"venue"
},
  "geometry": {"coordinates":[174.84144599999999,-36.923672],"type":"Point"}
}