{
  "type": "Feature",
  "properties": {
    "iso:country":"NZ",
    "sg:address":"56 Shearman St ",
    "sg:city":"Waimate",
    "sg:classifiers":[
        {
            "category":"Retail",
            "subcategory":"Auto Repair",
            "type":"Services"
        }
    ],
    "sg:phone":"+64 3-689 7302",
    "sg:tags":[
        "muffler",
        "exhaust",
        "servicing",
        "automotive"
    ],
    "wof:name":"Waimate Motor Garage",
    "wof:placetype":"venue"
},
  "geometry": {"coordinates":[171.04722599999999,-44.731689],"type":"Point"}
}