{
  "type": "Feature",
  "properties": {
    "iso:country":"NZ",
    "sg:address":"Arimu Pl Papakura ",
    "sg:city":"Auckland",
    "sg:classifiers":[
        {
            "category":"Community Center",
            "subcategory":"Senior",
            "type":"Public Place"
        }
    ],
    "sg:phone":"+64 9-299 6348",
    "sg:province":"Auckland",
    "sg:tags":[
        "arrangements",
        "room",
        "reception",
        "wedding"
    ],
    "wof:name":"McLennan Park Function Centre",
    "wof:placetype":"venue"
},
  "geometry": {"coordinates":[174.943512,-37.05608],"type":"Point"}
}