{
  "type": "Feature",
  "properties": {
    "addr:full":"33 Fellbrook St Manurewa  Auckland Auckland",
    "addr:housenumber":"33",
    "addr:street":"Fellbrook St",
    "iso:country":"NZ",
    "sg:address":"33 Fellbrook St Manurewa ",
    "sg:city":"Auckland",
    "sg:classifiers":[
        {
            "category":"Shopping",
            "subcategory":"Photographic Equipment",
            "type":"Retail Goods"
        }
    ],
    "sg:phone":"+64 9-267 5295",
    "sg:province":"Auckland",
    "sg:tags":[
        "sport",
        "leisure",
        "hobbies"
    ],
    "wof:name":"Peter Boles Pharmacy & Photo",
    "wof:placetype":"venue"
},
  "geometry": {"coordinates":[174.91696200000001,-37.021488],"type":"Point"}
}