{
  "type": "Feature",
  "properties": {
    "addr:full":"85 Byron St Sydenham  Christchurch Canterbury",
    "addr:housenumber":"85",
    "addr:street":"Byron St",
    "iso:country":"NZ",
    "sg:address":"85 Byron St Sydenham ",
    "sg:city":"Christchurch",
    "sg:classifiers":[
        {
            "category":"Manufacturing",
            "subcategory":"Tools & Machinery",
            "type":"Manufacturing & Wholesale Goods"
        }
    ],
    "sg:phone":"+64 3-377 0025",
    "sg:province":"Canterbury",
    "sg:tags":[
        "specialist",
        "industrial",
        "vibrating",
        "equipment"
    ],
    "wof:name":"Fisher R R & Co Ltd",
    "wof:placetype":"venue"
},
  "geometry": {"coordinates":[172.64444,-43.542362],"type":"Point"}
}