{
  "type": "Feature",
  "properties": {
    "addr:full":"Level 1 8 St Martins La Auckland Central  Auckland Canterbury",
    "addr:housenumber":"level;8",
    "addr:street":"St Martins La Auckland",
    "iso:country":"NZ",
    "sg:address":"Level 1 8 St Martins La Auckland Central ",
    "sg:city":"Auckland",
    "sg:classifiers":[
        {
            "category":"Transit Center",
            "subcategory":"Freight",
            "type":"Transportation"
        }
    ],
    "sg:phone":"+64 9-377 8445",
    "sg:province":"Canterbury",
    "sg:tags":[
        "distribution",
        "-",
        "transport"
    ],
    "wof:name":"Primary Distributors NZ Ltd",
    "wof:placetype":"venue"
},
  "geometry": {"coordinates":[174.76454200000001,-36.848358],"type":"Point"}
}