{
  "type": "Feature",
  "properties": {
    "iso:country":"NZ",
    "sg:address":"Wansbeck St ",
    "sg:city":"Oamaru",
    "sg:orig_category":"Health And Beauty: Beauty: Hairdressers",
    "sg:phone":"+64 3-434 8761",
    "sg:province":"Otago",
    "wof:name":"Junction Hair Design",
    "wof:placetype":"venue"
},
  "geometry": {"coordinates":[170.942368,-45.101299],"type":"Point"}
}