{
  "type": "Feature",
  "properties": {
    "addr:full":"Lake Matheson Rd Fox  Glacier",
    "addr:street":"Lake Matheson Rd",
    "iso:country":"NZ",
    "sg:address":"Lake Matheson Rd Fox ",
    "sg:city":"Glacier",
    "sg:classifiers":[
        {
            "category":"Bars & Pubs",
            "subcategory":"Wine Bar",
            "type":"Food & Drink"
        }
    ],
    "sg:phone":"+64 3-751 0878",
    "sg:tags":[
        "wining",
        "dining",
        "cafe"
    ],
    "wof:name":"Cafe Lake Matheson",
    "wof:placetype":"venue"
},
  "geometry": {"coordinates":[169.96443199999999,-43.439331],"type":"Point"}
}