{
  "type": "Feature",
  "properties": {
    "iso:country":"NZ",
    "sg:address":"62 Carnarvon St ",
    "sg:city":"Gisborne",
    "sg:classifiers":[
        {
            "category":"Retail",
            "subcategory":"Auto Repair",
            "type":"Services"
        }
    ],
    "sg:phone":"+64 6-867 9444",
    "sg:province":"Gisborne",
    "sg:tags":[
        "automotive",
        "panel",
        "servicing",
        "beater"
    ],
    "wof:name":"Eastland Motors Ltd",
    "wof:placetype":"venue"
},
  "geometry": {"coordinates":[178.020096,-38.660686],"type":"Point"}
}