{
  "type": "Feature",
  "properties": {
    "addr:full":"UNT 62 Regency Park Estate Brent Rd Owhata PO Box 1588 Rotorua Bay of Plenty",
    "addr:housenumber":"62;po box 1588",
    "addr:street":"Unt;Park Estate Brent Rd",
    "iso:country":"NZ",
    "sg:address":"UNT 62 Regency Park Estate Brent Rd Owhata PO Box 1588",
    "sg:city":"Rotorua",
    "sg:classifiers":[
        {
            "category":"Social Services",
            "subcategory":"Retirement Home",
            "type":"Services"
        }
    ],
    "sg:phone":"+64 7-345 5836",
    "sg:province":"Bay of Plenty",
    "sg:tags":[
        "care",
        "garden",
        "elderly",
        "village"
    ],
    "wof:name":"Regency Park Estate",
    "wof:placetype":"venue"
},
  "geometry": {"coordinates":[176.24499499999999,-38.1418],"type":"Point"}
}