{
  "type": "Feature",
  "properties": {
    "addr:full":"Lake Front  Wanaka Otago",
    "addr:street":"Lake;Otago",
    "iso:country":"NZ",
    "sg:address":"Lake Front ",
    "sg:city":"Wanaka",
    "sg:classifiers":[
        {
            "category":"Bars & Pubs",
            "subcategory":"Lounge",
            "type":"Food & Drink"
        }
    ],
    "sg:phone":"+64 3-443 7290",
    "sg:province":"Otago",
    "sg:tags":[
        "baker",
        "-"
    ],
    "wof:name":"Doughbin Bakery",
    "wof:placetype":"venue"
},
  "geometry": {"coordinates":[169.138443,-44.693981],"type":"Point"}
}