{
  "type": "Feature",
  "properties": {
    "iso:country":"NZ",
    "sg:address":"77 Bond St ",
    "sg:city":"Invercargill",
    "sg:orig_category":"Industrial: Metal: Services: Steel Processing",
    "sg:phone":"+64 3-211 0375",
    "sg:province":"Southland",
    "wof:name":"Vulcan Steel Ltd",
    "wof:placetype":"venue"
},
  "geometry": {"coordinates":[168.33995100000001,-46.409222],"type":"Point"}
}