{
  "type": "Feature",
  "properties": {
    "iso:country":"NZ",
    "sg:address":"11 Fairy Springs Rd ",
    "sg:city":"Rotorua",
    "sg:classifiers":[
        {
            "category":"Travel",
            "subcategory":"Travel Agent",
            "type":"Entertainment"
        }
    ],
    "sg:phone":"+64 7-350 2405",
    "sg:province":"Bay of Plenty",
    "sg:tags":[
        "tour",
        "tourism",
        "sightseeing"
    ],
    "sg:website":"http://www.abalonepearl.com",
    "wof:name":"Ocean Pearl Farm Ltd",
    "wof:placetype":"venue"
},
  "geometry": {"coordinates":[176.23101800000001,-38.12397],"type":"Point"}
}