{
  "type": "Feature",
  "properties": {
    "iso:country":"NZ",
    "sg:address":"Main West Coast Rd Yaldhurst ",
    "sg:city":"Christchurch",
    "sg:classifiers":[
        {
            "category":"Retail",
            "subcategory":"Laundry & Dry Cleaning",
            "type":"Services"
        }
    ],
    "sg:phone":"+64 3-342 9863",
    "sg:province":"Canterbury",
    "sg:tags":[
        "product",
        "wool",
        "clothing",
        "fabric"
    ],
    "wof:name":"Highland Wool",
    "wof:placetype":"venue"
},
  "geometry": {"coordinates":[172.47685200000001,-43.508896],"type":"Point"}
}