{
  "type": "Feature",
  "properties": {
    "iso:country":"NZ",
    "sg:address":"24 Rothery Rd Manurewa ",
    "sg:city":"Auckland",
    "sg:classifiers":[
        {
            "category":"Retail",
            "subcategory":"Animal Services",
            "type":"Services"
        }
    ],
    "sg:phone":"+64 9-266 5002",
    "sg:province":"Auckland",
    "sg:tags":[
        "pet",
        "home",
        "garden",
        "pets"
    ],
    "wof:name":"Kimbo's Pet Wear",
    "wof:placetype":"venue"
},
  "geometry": {"coordinates":[174.916962,-37.021488],"type":"Point"}
}