{
  "type": "Feature",
  "properties": {
    "addr:full":"The Plaza Church St Palmerston  Palmerston North Manawatu-Wanganui",
    "addr:street":"St",
    "iso:country":"NZ",
    "sg:address":"The Plaza Church St Palmerston ",
    "sg:city":"Palmerston North",
    "sg:classifiers":[
        {
            "category":"Shopping",
            "subcategory":"Clothing, Apparel, & Fashions",
            "type":"Retail Goods"
        }
    ],
    "sg:phone":"+64 6-358 1997",
    "sg:province":"Manawatu-Wanganui",
    "sg:tags":[
        "-",
        "hire",
        "clothing",
        "fabric"
    ],
    "wof:name":"Hugh Wright Ltd",
    "wof:placetype":"venue"
},
  "geometry": {"coordinates":[175.611481,-40.357422],"type":"Point"}
}