{
  "type": "Feature",
  "properties": {
    "addr:full":"PO Box 49-090 Mt Roskill South  Auckland Auckland",
    "addr:housenumber":"po box 49-090",
    "iso:country":"NZ",
    "sg:address":"PO Box 49-090 Mt Roskill South ",
    "sg:city":"Auckland",
    "sg:classifiers":[
        {
            "category":"Shopping",
            "subcategory":"Pharmacy",
            "type":"Retail Goods"
        }
    ],
    "sg:phone":"+64 9-627 9596",
    "sg:province":"Auckland",
    "sg:tags":[
        "products",
        "medical",
        "health",
        "beauty",
        "supply"
    ],
    "wof:name":"High Tech Bodywear Ltd",
    "wof:placetype":"venue"
},
  "geometry": {"coordinates":[174.74276699999999,-36.905895],"type":"Point"}
}