{
  "type": "Feature",
  "properties": {
    "addr:full":"PO Box 100-339 North Shore Mail Cen  Auckland Auckland",
    "addr:housenumber":"po;100-339",
    "addr:street":"Box",
    "iso:country":"NZ",
    "sg:address":"PO Box 100-339 North Shore Mail Cen ",
    "sg:city":"Auckland",
    "sg:classifiers":[
        {
            "category":"Health Services",
            "subcategory":"Chiropractor",
            "type":"Services"
        }
    ],
    "sg:phone":"+64 9-415 7030",
    "sg:province":"Auckland",
    "sg:tags":[
        "specialists",
        "occupational",
        "therapist",
        "beauty"
    ],
    "wof:name":"Ergowise Ltd",
    "wof:placetype":"venue"
},
  "geometry": {"coordinates":[174.74749800000001,-36.819668],"type":"Point"}
}