{
  "type": "Feature",
  "properties": {
    "addr:full":"418 Glenfield Rd Glenfield  Auckland Auckland",
    "addr:housenumber":"418",
    "addr:street":"Glenfield Rd",
    "iso:country":"NZ",
    "sg:address":"418 Glenfield Rd Glenfield ",
    "sg:city":"Auckland",
    "sg:orig_category":"Health And Beauty: Specialists: Physiotherapists",
    "sg:phone":"+64 9-444 6841",
    "sg:province":"Auckland",
    "wof:name":"Glenfield Central Physiotherapy - Dean Rhodes",
    "wof:placetype":"venue"
},
  "geometry": {"coordinates":[174.721161,-36.783306],"type":"Point"}
}