{
  "type": "Feature",
  "properties": {
    "iso:country":"NZ",
    "sg:address":"8 Porowini Ave ",
    "sg:city":"Whangarei",
    "sg:orig_category":"Sports And Leisure: General: Clubs",
    "sg:phone":"+64 9-438 4270",
    "sg:province":"Northland",
    "wof:name":"Northland Club Incorporated",
    "wof:placetype":"venue"
},
  "geometry": {"coordinates":[174.316315,-35.729507],"type":"Point"}
}