{
  "type": "Feature",
  "properties": {
    "addr:full":"149 London St  Wanganui Manawatu-Wanganui",
    "addr:housenumber":"149",
    "addr:street":"London St",
    "iso:country":"NZ",
    "sg:address":"149 London St ",
    "sg:city":"Wanganui",
    "sg:orig_category":"Farming: Horticulture: Horticultural Supplies",
    "sg:phone":"+64 6-345 8253",
    "sg:province":"Manawatu-Wanganui",
    "wof:name":"St John's Greenworld",
    "wof:placetype":"venue"
},
  "geometry": {"coordinates":[175.05256700000001,-39.909225],"type":"Point"}
}