{
  "type": "Feature",
  "properties": {
    "addr:full":"Shop 3 571 Great North Rd Grey Lynn  Auckland Auckland",
    "addr:housenumber":"shop 3 571",
    "addr:street":"Great North Rd",
    "iso:country":"NZ",
    "sg:address":"Shop 3 571 Great North Rd Grey Lynn ",
    "sg:city":"Auckland",
    "sg:classifiers":[
        {
            "category":"Personal",
            "subcategory":"Beauty Salon",
            "type":"Services"
        }
    ],
    "sg:phone":"+64 9-360 1834",
    "sg:province":"Auckland",
    "sg:tags":[
        "artist",
        "health",
        "make-up"
    ],
    "wof:name":"Veronica Fox Studio",
    "wof:placetype":"venue"
},
  "geometry": {"coordinates":[174.737503,-36.864491],"type":"Point"}
}