{
  "type": "Feature",
  "properties": {
    "addr:full":"888 New North Rd Mt Albert  Auckland Auckland",
    "addr:housenumber":"888",
    "addr:street":"New North Rd",
    "iso:country":"NZ",
    "sg:address":"888 New North Rd Mt Albert ",
    "sg:city":"Auckland",
    "sg:classifiers":[
        {
            "category":"Education",
            "subcategory":"Vocational School",
            "type":"Public Place"
        }
    ],
    "sg:phone":"+64 9-846 1776",
    "sg:province":"Auckland",
    "sg:tags":[
        "correspondence",
        "training"
    ],
    "wof:name":"PSSM: Bible Discovery",
    "wof:placetype":"venue"
},
  "geometry": {"coordinates":[174.71627799999999,-36.883759],"type":"Point"}
}