{
  "type": "Feature",
  "properties": {
    "addr:full":"250 Queen St  Masterton Wellington",
    "addr:housenumber":"250",
    "addr:street":"Queen St",
    "iso:country":"NZ",
    "sg:address":"250 Queen St ",
    "sg:city":"Masterton",
    "sg:classifiers":[
        {
            "category":"Arts & Performance",
            "subcategory":"Art Gallery",
            "type":"Entertainment"
        }
    ],
    "sg:phone":"+64 6-377 5844",
    "sg:province":"Wellington",
    "sg:tags":[
        "arts",
        "sport",
        "leisure"
    ],
    "wof:name":"Colours",
    "wof:placetype":"venue"
},
  "geometry": {"coordinates":[175.65823399999999,-40.951782],"type":"Point"}
}