{
  "type": "Feature",
  "properties": {
    "iso:country":"NZ",
    "sg:address":"cnr Meachen & Barnes Sts Seaview ",
    "sg:city":"Wellington",
    "sg:classifiers":[
        {
            "category":"Wholesale",
            "subcategory":"Machinery & Supplies",
            "type":"Manufacturing & Wholesale Goods"
        }
    ],
    "sg:phone":"+64 4-939 6001",
    "sg:province":"Wellington",
    "sg:tags":[
        "equipment",
        "crane",
        "industrial",
        "hoist",
        "lifting"
    ],
    "wof:name":"Croft Combined Carriers Ltd",
    "wof:placetype":"venue"
},
  "geometry": {"coordinates":[174.89956699999999,-41.246059],"type":"Point"}
}