{
  "type": "Feature",
  "properties": {
    "addr:full":"205 Queen St Auckland City  Auckland Auckland",
    "addr:housenumber":"205",
    "addr:street":"Queen St",
    "iso:country":"NZ",
    "sg:address":"205 Queen St Auckland City ",
    "sg:city":"Auckland",
    "sg:classifiers":[
        {
            "category":"Shopping",
            "subcategory":"Shoes",
            "type":"Retail Goods"
        }
    ],
    "sg:phone":"+64 9-309 6816",
    "sg:province":"Auckland",
    "sg:tags":[
        "foot",
        "clothing",
        "fabric",
        "wear"
    ],
    "wof:name":"Smith's Sports Shoes",
    "wof:placetype":"venue"
},
  "geometry": {"coordinates":[174.765198,-36.849102],"type":"Point"}
}