{
  "type": "Feature",
  "properties": {
    "iso:country":"NZ",
    "sg:address":"Botany Town Centre Cnr Ti Irirangi & Ti Rakau Dvs",
    "sg:city":"Auckland",
    "sg:classifiers":[
        {
            "category":"Recreation",
            "type":"Entertainment"
        }
    ],
    "sg:phone":"+64 9-273 3222",
    "sg:province":"Southland",
    "sg:tags":[
        "sport",
        "tramping",
        "leisure",
        "camping"
    ],
    "wof:name":"Pack 'N' Pedal",
    "wof:placetype":"venue"
},
  "geometry": {"coordinates":[-119.10457599999999,36.597755],"type":"Point"}
}