{
  "type": "Feature",
  "properties": {
    "addr:full":"John Wickliffe House 265 Princes St PO Box 709  Dunedin Otago",
    "addr:housenumber":"265;box 709",
    "addr:street":"Princes St Po",
    "iso:country":"NZ",
    "sg:address":"John Wickliffe House 265 Princes St PO Box 709 ",
    "sg:city":"Dunedin",
    "sg:orig_category":"Shopping: Retail Stores: Books: Libraries",
    "sg:phone":"+64 3-477 0730",
    "sg:province":"Otago",
    "wof:name":"National Library of New Zealand Te Puna Matauranga o Aotearoa",
    "wof:placetype":"venue"
},
  "geometry": {"coordinates":[-82.784721,28.013355],"type":"Point"}
}