{
  "type": "Feature",
  "properties": {
    "addr:full":"12 Newlands Rd Ngauranga  Wellington Wellington",
    "addr:housenumber":"12",
    "addr:street":"Newlands Rd",
    "iso:country":"NZ",
    "sg:address":"12 Newlands Rd Ngauranga ",
    "sg:city":"Wellington",
    "sg:orig_category":"Transport: Transportation: Transport Operators",
    "sg:phone":"+64 4-477 6710",
    "sg:province":"Wellington",
    "wof:name":"Fliway Transport Group",
    "wof:placetype":"venue"
},
  "geometry": {"coordinates":[174.812836,-41.247177],"type":"Point"}
}