{
  "type": "Feature",
  "properties": {
    "addr:full":"1 St Vincent Ave Remuera  Auckland Auckland",
    "addr:housenumber":"1",
    "addr:street":"St Vincent Ave",
    "iso:country":"NZ",
    "sg:address":"1 St Vincent Ave Remuera ",
    "sg:city":"Auckland",
    "sg:orig_category":"Home And Garden: Furniture/Furnishings",
    "sg:phone":"+64 9-522 2265",
    "sg:province":"Auckland",
    "sg:website":"http://www.jims.co.nz",
    "wof:name":"Jims Blind Cleaning & Repairs",
    "wof:placetype":"venue"
},
  "geometry": {"coordinates":[174.79949999999999,-36.881348],"type":"Point"}
}