{
  "type": "Feature",
  "properties": {
    "iso:country":"NZ",
    "sg:address":"Remarkables Park Shopping Centre Frankton ",
    "sg:city":"Queenstown",
    "sg:orig_category":"Home And Garden: Accessories: Hardware",
    "sg:phone":"+64 3-442 2442",
    "sg:province":"Waikato",
    "wof:name":"Mitre 10 Remarkables Park",
    "wof:placetype":"venue"
},
  "geometry": {"coordinates":[168.73867799999999,-45.028645],"type":"Point"}
}