{
  "type": "Feature",
  "properties": {
    "addr:full":"18-20 Wilson St  Wanganui Manawatu-Wanganui",
    "addr:housenumber":"18-20",
    "addr:street":"Wilson St",
    "iso:country":"NZ",
    "sg:address":"18-20 Wilson St ",
    "sg:city":"Wanganui",
    "sg:classifiers":[
        {
            "category":"Retail",
            "subcategory":"Auto Repair",
            "type":"Services"
        }
    ],
    "sg:phone":"+64 6-345 4272",
    "sg:province":"Manawatu-Wanganui",
    "sg:tags":[
        "automotive",
        "panel",
        "servicing",
        "beater"
    ],
    "wof:name":"Jellyman R A Ltd",
    "wof:placetype":"venue"
},
  "geometry": {"coordinates":[175.050735,-39.936134],"type":"Point"}
}