{
  "type": "Feature",
  "properties": {
    "iso:country":"NZ",
    "sg:address":"141 High St ",
    "sg:city":"Blenheim",
    "sg:orig_category":"Industrial: Engineering: Engineers: Engineers - Consulting",
    "sg:phone":"+64 3-577 8857",
    "sg:province":"Marlborough",
    "wof:name":"Abacus Design Ltd",
    "wof:placetype":"venue"
},
  "geometry": {"coordinates":[-79.650726,34.5112],"type":"Point"}
}