{
  "type": "Feature",
  "properties": {
    "addr:full":"1 Basin View La Panmure  Auckland Auckland",
    "addr:housenumber":"1",
    "addr:street":"Basin View",
    "iso:country":"NZ",
    "sg:address":"1 Basin View La Panmure ",
    "sg:city":"Auckland",
    "sg:classifiers":[
        {
            "category":"Retail",
            "subcategory":"Repair Shop",
            "type":"Services"
        }
    ],
    "sg:phone":"+64 9-570 5123",
    "sg:province":"Auckland",
    "sg:tags":[
        "clothing",
        "fabric",
        "cleaning"
    ],
    "wof:name":"Panmure Tailoring & Alteration Services",
    "wof:placetype":"venue"
},
  "geometry": {"coordinates":[174.85493500000001,-36.899952],"type":"Point"}
}