{
  "type": "Feature",
  "properties": {
    "addr:full":"30 The Octagon PO Box 566  Dunedin Otago",
    "addr:housenumber":"30;box 566",
    "addr:street":"The",
    "iso:country":"NZ",
    "sg:address":"30 The Octagon PO Box 566 ",
    "sg:city":"Dunedin",
    "sg:classifiers":[
        {
            "category":"Sports & Exercise",
            "subcategory":"Skate Park",
            "type":"Entertainment"
        }
    ],
    "sg:phone":"+64 3-474 3250",
    "sg:province":"Otago",
    "sg:tags":[
        "arts",
        "museum",
        "leisure",
        "gallery"
    ],
    "wof:name":"Art Gallery - Dunedin Public",
    "wof:placetype":"venue"
},
  "geometry": {"coordinates":[-82.784721,28.013355],"type":"Point"}
}