{
  "type": "Feature",
  "properties": {
    "addr:full":"Whatuwhiwhi Rd Whatuwhiwhi  Kaitaia Northland",
    "addr:street":"Whatuwhiwhi Rd",
    "iso:country":"NZ",
    "sg:address":"Whatuwhiwhi Rd Whatuwhiwhi ",
    "sg:city":"Kaitaia",
    "sg:classifiers":[
        {
            "category":"Education",
            "subcategory":"Special Training",
            "type":"Public Place"
        }
    ],
    "sg:phone":"+64 9-408 7077",
    "sg:province":"Northland",
    "sg:tags":[
        "charter",
        "shopping",
        "dive",
        "tuition",
        "water",
        "sports",
        "retailers",
        "sport"
    ],
    "wof:name":"A to Z Diving",
    "wof:placetype":"venue"
},
  "geometry": {"coordinates":[173.259445,-35.114208],"type":"Point"}
}