{
  "type": "Feature",
  "properties": {
    "addr:full":"141 Estuary Rd South New Brighton  Christchurch Canterbury",
    "addr:housenumber":"141",
    "addr:street":"Estuary Rd",
    "iso:country":"NZ",
    "sg:address":"141 Estuary Rd South New Brighton ",
    "sg:city":"Christchurch",
    "sg:classifiers":[
        {
            "category":"Personal",
            "type":"Services"
        }
    ],
    "sg:phone":"+64 3-388 5229",
    "sg:province":"Canterbury",
    "sg:tags":[
        "celebrant",
        "arrangements",
        "marriage",
        "wedding"
    ],
    "wof:name":"House David JP",
    "wof:placetype":"venue"
},
  "geometry": {"coordinates":[172.73387099999999,-43.525589],"type":"Point"}
}