{
  "type": "Feature",
  "properties": {
    "iso:country":"NZ",
    "sg:address":"31 Barry Point Rd Takapuna ",
    "sg:city":"Auckland",
    "sg:classifiers":[
        {
            "category":"Shopping",
            "subcategory":"Crafts & Fabrics",
            "type":"Retail Goods"
        }
    ],
    "sg:phone":"+64 9-488 0322",
    "sg:province":"Auckland",
    "sg:tags":[
        "clothing",
        "maternity",
        "wear"
    ],
    "wof:name":"Maternity Essentials",
    "wof:placetype":"venue"
},
  "geometry": {"coordinates":[174.76480100000001,-36.791775],"type":"Point"}
}