{
  "type": "Feature",
  "properties": {
    "iso:country":"NZ",
    "sg:address":"2 Canon Pl Pakuranga ",
    "sg:city":"Auckland",
    "sg:classifiers":[
        {
            "category":"Wholesale",
            "subcategory":"Medical Equipment & Supplies",
            "type":"Manufacturing & Wholesale Goods"
        }
    ],
    "sg:phone":"+64 9-576 1090",
    "sg:province":"Auckland",
    "sg:tags":[
        "health",
        "disability",
        "products",
        "beauty",
        "aid"
    ],
    "wof:name":"VAMCO",
    "wof:placetype":"venue"
},
  "geometry": {"coordinates":[174.898346,-36.916054],"type":"Point"}
}