{
  "type": "Feature",
  "properties": {
    "addr:full":"194 Marua Rd Mt Wellington  Auckland Auckland",
    "addr:housenumber":"194",
    "addr:street":"Marua Rd",
    "iso:country":"NZ",
    "sg:address":"194 Marua Rd Mt Wellington ",
    "sg:city":"Auckland",
    "sg:orig_category":"Home And Garden: Furniture/Furnishings",
    "sg:phone":"+64 9-579 3951",
    "sg:province":"Auckland",
    "sg:website":"http://www.firstedition.co.nz",
    "wof:name":"First Edition Cabinetmakers Ltd",
    "wof:placetype":"venue"
},
  "geometry": {"coordinates":[174.832977,-36.892914],"type":"Point"}
}