{
  "type": "Feature",
  "properties": {
    "addr:full":"Henderson  Auckland Auckland",
    "iso:country":"NZ",
    "sg:address":"Henderson ",
    "sg:city":"Auckland",
    "sg:classifiers":[
        {
            "category":"Arts & Performance",
            "subcategory":"Music",
            "type":"Entertainment"
        }
    ],
    "sg:phone":"+64 9-837 1975",
    "sg:province":"Auckland",
    "sg:tags":[
        "mobile",
        "sport",
        "-",
        "leisure",
        "disco"
    ],
    "wof:name":"Source Entertainment Ltd",
    "wof:placetype":"venue"
},
  "geometry": {"coordinates":[174.631226,-36.881828],"type":"Point"}
}