{
  "type": "Feature",
  "properties": {
    "iso:country":"NZ",
    "sg:address":"18 Senior Pl ",
    "sg:city":"Bromley",
    "sg:orig_category":"Industrial: Metal: Stainless Steel",
    "sg:phone":"+64 3-381 1994",
    "wof:name":"Corus Metals",
    "wof:placetype":"venue"
},
  "geometry": {"coordinates":[-84.562386,39.08276],"type":"Point"}
}