{
  "type": "Feature",
  "properties": {
    "addr:full":"277 High St  Motueka Tasman",
    "addr:housenumber":"277",
    "addr:street":"High St",
    "iso:country":"NZ",
    "sg:address":"277 High St ",
    "sg:city":"Motueka",
    "sg:classifiers":[
        {
            "category":"Shopping",
            "subcategory":"Bicycles & Sporting Goods",
            "type":"Retail Goods"
        }
    ],
    "sg:phone":"+64 3-528 9379",
    "sg:province":"Tasman",
    "sg:tags":[
        "cycle",
        "sport",
        "sale",
        "retailers",
        "cycles"
    ],
    "wof:name":"Hollidays Cycle Centre",
    "wof:placetype":"venue"
},
  "geometry": {"coordinates":[173.01026899999999,-41.126648],"type":"Point"}
}