{
  "type": "Feature",
  "properties": {
    "iso:country":"NZ",
    "sg:address":"Cnr Ormiston Rd & Te Irirangi Dve Botany ",
    "sg:city":"Sth",
    "sg:classifiers":[
        {
            "category":"Retail",
            "subcategory":"Auto Repair",
            "type":"Services"
        }
    ],
    "sg:phone":"+64 800 269 583",
    "sg:tags":[
        "automotive",
        "servicing"
    ],
    "wof:name":"Botany Motor Worx Limited",
    "wof:placetype":"venue"
},
  "geometry": {"coordinates":[175.67970299999999,-39.54171],"type":"Point"}
}