{
  "type": "Feature",
  "properties": {
    "iso:country":"NZ",
    "sg:address":"Cnr Kent & Crowhurst St Newmarket ",
    "sg:city":"Auckland",
    "sg:orig_category":"Industrial: Chemicals And Compounds: Pharmaceuticals",
    "sg:phone":"+64 9-523 1646",
    "sg:province":"Auckland",
    "wof:name":"Janssen-Cilag Pty Ltd",
    "wof:placetype":"venue"
},
  "geometry": {"coordinates":[174.773758,-36.867882],"type":"Point"}
}