{
  "type": "Feature",
  "properties": {
    "addr:full":"1/1726 Cambridge Rd RD5 Te Awamutu  Cambridge Waikato",
    "addr:housenumber":"1 / 1726",
    "addr:street":"Cambridge Rd Rd5 Te Awamutu",
    "iso:country":"NZ",
    "sg:address":"1/1726 Cambridge Rd RD5 Te Awamutu ",
    "sg:city":"Cambridge",
    "sg:orig_category":"Farming: Horticulture: Grain And Seed",
    "sg:phone":"+64 7-871 2730",
    "sg:province":"Waikato",
    "wof:name":"PIONEER brand SEEDS",
    "wof:placetype":"venue"
},
  "geometry": {"coordinates":[-116.67604799999999,44.572186],"type":"Point"}
}