{
  "type": "Feature",
  "properties": {
    "iso:country":"NZ",
    "sg:address":"18-24 Yarrow St ",
    "sg:city":"Invercargill",
    "sg:classifiers":[
        {
            "category":"Autos & Motor Vehicles",
            "subcategory":"Automobile Sales",
            "type":"Retail Goods"
        }
    ],
    "sg:phone":"+64 3-218 2149",
    "sg:province":"Southland",
    "sg:tags":[
        "car",
        "-used",
        "leasing",
        "truck",
        "automotive"
    ],
    "sg:website":"http://www.gwd.co.nz",
    "wof:name":"GWD Russells Ltd LMVD",
    "wof:placetype":"venue"
},
  "geometry": {"coordinates":[168.34895299999999,-46.408459],"type":"Point"}
}