{
  "type": "Feature",
  "properties": {
    "iso:country":"NZ",
    "sg:address":"Bristol St Riverlands ",
    "sg:city":"Blenheim",
    "sg:orig_category":"Transport: Boats And Marine: Shipping: Shipping Companies",
    "sg:phone":"+64 3-577 8838",
    "sg:province":"Marlborough",
    "wof:name":"Allied Movers (NZ) Ltd",
    "wof:placetype":"venue"
},
  "geometry": {"coordinates":[174.010971,-41.530647],"type":"Point"}
}