{
  "type": "Feature",
  "properties": {
    "iso:country":"NZ",
    "sg:address":"293 Dominion Rd Mt Eden ",
    "sg:city":"Auckland",
    "sg:classifiers":[
        {
            "category":"Retail",
            "subcategory":"Repair Shop",
            "type":"Services"
        }
    ],
    "sg:phone":"+64 9-623 0200",
    "sg:province":"Auckland",
    "sg:tags":[
        "clothing",
        "fabric",
        "cleaning"
    ],
    "wof:name":"Vanilla Ink",
    "wof:placetype":"venue"
},
  "geometry": {"coordinates":[174.751022,-36.875999],"type":"Point"}
}