{
  "type": "Feature",
  "properties": {
    "addr:full":"19/233 Queen St Auckland Central  Auckland Auckland",
    "addr:housenumber":"19 / 233",
    "addr:street":"Queen St",
    "iso:country":"NZ",
    "sg:address":"19/233 Queen St Auckland Central ",
    "sg:city":"Auckland",
    "sg:classifiers":[
        {
            "category":"Shopping",
            "subcategory":"Beauty & Cosmetics",
            "type":"Retail Goods"
        }
    ],
    "sg:phone":"+64 9-379 6969",
    "sg:province":"Auckland",
    "sg:tags":[
        "health",
        "perfumery"
    ],
    "wof:name":"Amore City",
    "wof:placetype":"venue"
},
  "geometry": {"coordinates":[174.89975000000001,-37.214302],"type":"Point"}
}