{
  "type": "Feature",
  "properties": {
    "addr:full":"139-141 Featherston St  Wellington Wellington",
    "addr:housenumber":"139-141",
    "addr:street":"Featherston St",
    "iso:country":"NZ",
    "sg:address":"139-141 Featherston St ",
    "sg:city":"Wellington",
    "sg:classifiers":[
        {
            "category":"Insurance",
            "subcategory":"Health Insurance",
            "type":"Services"
        }
    ],
    "sg:phone":"+64 4-473 6275",
    "sg:province":"Wellington",
    "sg:tags":[
        "beauty"
    ],
    "sg:website":"http://www.yellowpages.co.nz/for/mcclellangrimmer/dp9639.html",
    "wof:name":"McClellan & Grimmer",
    "wof:placetype":"venue"
},
  "geometry": {"coordinates":[174.77720600000001,-41.283257],"type":"Point"}
}