{
  "type": "Feature",
  "properties": {
    "iso:country":"NZ",
    "sg:address":"3 A Chums Rd Paraparaumu Beach ",
    "sg:city":"Wellington",
    "sg:classifiers":[
        {
            "category":"Personal",
            "type":"Services"
        }
    ],
    "sg:phone":"+64 800 129 855",
    "sg:province":"Wellington",
    "sg:tags":[
        "diet",
        "reduction",
        "health",
        "beauty",
        "weight"
    ],
    "wof:name":"Herbalife (NZ) Limited",
    "wof:placetype":"venue"
},
  "geometry": {"coordinates":[174.99702500000001,-40.887684],"type":"Point"}
}