{
  "type": "Feature",
  "properties": {
    "addr:full":"Sunnynook Shopg Cen Frsth Auckland Auckland",
    "addr:housenumber":"frsth",
    "iso:country":"NZ",
    "sg:address":"Sunnynook Shopg Cen Frsth",
    "sg:city":"Auckland",
    "sg:classifiers":[
        {
            "category":"Banks & Credit Unions",
            "subcategory":"Bank",
            "type":"Services"
        }
    ],
    "sg:phone":"+64 9-410 6901",
    "sg:province":"Auckland",
    "wof:name":"ASB Bank",
    "wof:placetype":"venue"
},
  "geometry": {"coordinates":[174.73924299999999,-36.754078],"type":"Point"}
}