{
  "type": "Feature",
  "properties": {
    "iso:country":"NZ",
    "sg:address":"9 Allens Rd East Tamaki ",
    "sg:city":"Auckland",
    "sg:classifiers":[
        {
            "category":"Manufacturing",
            "subcategory":"Glass & Minerals",
            "type":"Manufacturing & Wholesale Goods"
        }
    ],
    "sg:phone":"+64 9-273 3041",
    "sg:province":"Auckland",
    "sg:tags":[
        "chemical",
        "paint",
        "industrial",
        "manufacturer",
        "compounds"
    ],
    "wof:name":"Aurora Paint",
    "wof:placetype":"venue"
},
  "geometry": {"coordinates":[174.89198300000001,-36.942917],"type":"Point"}
}