{
  "type": "Feature",
  "properties": {
    "iso:country":"NZ",
    "sg:address":"Factory 6 Weza La Kumeu ",
    "sg:city":"Auckland",
    "sg:orig_category":"Farming: Machinery: Windmills",
    "sg:phone":"+64 9-412 8655",
    "sg:province":"Auckland",
    "wof:name":"Ferguson Windmills Company",
    "wof:placetype":"venue"
},
  "geometry": {"coordinates":[174.56021100000001,-36.777275],"type":"Point"}
}