{
  "type": "Feature",
  "properties": {
    "addr:full":"28 Don St  Invercargill Southland",
    "addr:housenumber":"28",
    "addr:street":"Don St",
    "iso:country":"NZ",
    "sg:address":"28 Don St ",
    "sg:city":"Invercargill",
    "sg:classifiers":[
        {
            "category":"Banks & Credit Unions",
            "subcategory":"Investment Brokerage",
            "type":"Services"
        }
    ],
    "sg:phone":"+64 3-218 7359",
    "sg:province":"Southland",
    "sg:tags":[
        "personal",
        "-",
        "finance"
    ],
    "wof:name":"Public Trust",
    "wof:placetype":"venue"
},
  "geometry": {"coordinates":[168.34892300000001,-46.410645],"type":"Point"}
}