{
  "type": "Feature",
  "properties": {
    "iso:country":"NZ",
    "sg:address":"200 Rangitikei St Palmerston ",
    "sg:city":"Palmerston North",
    "sg:classifiers":[
        {
            "category":"Wholesale",
            "subcategory":"Auto Parts",
            "type":"Manufacturing & Wholesale Goods"
        }
    ],
    "sg:phone":"+64 6-358 1062",
    "sg:province":"Manawatu-Wanganui",
    "sg:tags":[
        "automotive",
        "supplies"
    ],
    "wof:name":"Robertson Motors LMVD",
    "wof:placetype":"venue"
},
  "geometry": {"coordinates":[175.59466599999999,-40.337257],"type":"Point"}
}