{
  "type": "Feature",
  "properties": {
    "iso:country":"NZ",
    "sg:address":"5 Trafalgar Sq Waterloo Lower ",
    "sg:city":"Hutt",
    "sg:classifiers":[
        {
            "category":"Personal",
            "type":"Services"
        }
    ],
    "sg:phone":"+64 4-566 2603",
    "sg:province":"Wellington",
    "sg:tags":[
        "diet",
        "reduction",
        "health",
        "beauty",
        "weight"
    ],
    "wof:name":"Positively Slim Weight Loss & Health Group",
    "wof:placetype":"venue"
},
  "geometry": {"coordinates":[174.922272,-41.214584],"type":"Point"}
}