{
  "type": "Feature",
  "properties": {
    "iso:country":"NZ",
    "sg:address":"17 Eric Paton Way Mt Wellington ",
    "sg:city":"Auckland",
    "sg:classifiers":[
        {
            "category":"Structure",
            "subcategory":"Shopping Mall",
            "type":"Public Place"
        }
    ],
    "sg:phone":"+64 9-570 9040",
    "sg:province":"Auckland",
    "sg:tags":[
        "mail",
        "order"
    ],
    "wof:name":"Wayne Wentworth Mail Order Company",
    "wof:placetype":"venue"
},
  "geometry": {"coordinates":[174.83029199999999,-36.909569],"type":"Point"}
}