{
  "type": "Feature",
  "properties": {
    "addr:full":"64 Victoria Ave  Wanganui Manawatu-Wanganui",
    "addr:housenumber":"64",
    "addr:street":"Victoria Ave",
    "iso:country":"NZ",
    "sg:address":"64 Victoria Ave ",
    "sg:city":"Wanganui",
    "sg:orig_category":"Shopping: Accessories: Jewellers And Watchmakers",
    "sg:phone":"+64 6-345 7889",
    "sg:province":"Manawatu-Wanganui",
    "wof:name":"J Williams & Co Ltd",
    "wof:placetype":"venue"
},
  "geometry": {"coordinates":[175.05332899999999,-39.933491],"type":"Point"}
}