{
  "type": "Feature",
  "properties": {
    "addr:full":"Howick  Auckland Auckland",
    "iso:country":"NZ",
    "sg:address":"Howick ",
    "sg:city":"Auckland",
    "sg:classifiers":[
        {
            "category":"Travel",
            "subcategory":"Travel Agent",
            "type":"Entertainment"
        }
    ],
    "sg:phone":"+64 9-533 6323",
    "sg:province":"Auckland",
    "sg:tags":[
        "tour",
        "tourism",
        "adventure",
        "sightseeing"
    ],
    "wof:name":"New Zealand Scenic Adventures",
    "wof:placetype":"venue"
},
  "geometry": {"coordinates":[174.928055,-36.89695],"type":"Point"}
}