{
  "type": "Feature",
  "properties": {
    "iso:country":"NZ",
    "sg:address":"Wash Building Centreport PO Box 4085 ",
    "sg:city":"Wellington",
    "sg:orig_category":"Transport: Transportation: Container Services",
    "sg:phone":"+64 4-472 1350",
    "sg:province":"Wellington",
    "wof:name":"Independent Reefer Services",
    "wof:placetype":"venue"
},
  "geometry": {"coordinates":[-85.910454,33.827946],"type":"Point"}
}