{
  "type": "Feature",
  "properties": {
    "addr:full":"7 Hewlett St  Whangarei Northland",
    "addr:housenumber":"7",
    "addr:street":"Hewlett St",
    "iso:country":"NZ",
    "sg:address":"7 Hewlett St ",
    "sg:city":"Whangarei",
    "sg:orig_category":"Transport",
    "sg:phone":"+64 9-438 4107",
    "sg:province":"Northland",
    "sg:website":"http://www.yellowpages.co.nz/for/mcraeengineering/dp25186.html",
    "wof:name":"McRae Engineering Ltd",
    "wof:placetype":"venue"
},
  "geometry": {"coordinates":[174.34103400000001,-35.740559],"type":"Point"}
}