{
  "type": "Feature",
  "properties": {
    "addr:full":"130-140 Riverbank Rd Wanganui R D  3",
    "addr:housenumber":"130-140;3",
    "addr:street":"Riverbank Rd;R D",
    "iso:country":"NZ",
    "sg:address":"130-140 Riverbank Rd Wanganui R D ",
    "sg:city":"3",
    "sg:classifiers":[
        {
            "category":"Coffee & Tea",
            "type":"Food & Drink"
        }
    ],
    "sg:phone":"+64 6-343 8277",
    "sg:tags":[
        "vegetable",
        "fruit",
        "veges"
    ],
    "wof:name":"Benefields Orchards",
    "wof:placetype":"venue"
},
  "geometry": {"coordinates":[175.052841,-39.933369],"type":"Point"}
}