{
  "type": "Feature",
  "properties": {
    "iso:country":"NZ",
    "sg:address":"100 Weymouth Rd Manurewa ",
    "sg:city":"Auckland",
    "sg:classifiers":[
        {
            "category":"Health Services",
            "subcategory":"Health Practitioner",
            "type":"Services"
        }
    ],
    "sg:phone":"+64 9-267 1580",
    "sg:province":"Auckland",
    "sg:tags":[
        "specialist",
        "medical",
        "beauty",
        "specialists"
    ],
    "wof:name":"Leabank Health Centre",
    "wof:placetype":"venue"
},
  "geometry": {"coordinates":[174.887894,-37.027493],"type":"Point"}
}