{
  "type": "Feature",
  "properties": {
    "addr:full":"229 Lincoln Rd Henderson  Auckland Auckland",
    "addr:housenumber":"229",
    "addr:street":"Lincoln Rd",
    "iso:country":"NZ",
    "sg:address":"229 Lincoln Rd Henderson ",
    "sg:city":"Auckland",
    "sg:orig_category":"Farming: Horticulture: Flowers",
    "sg:phone":"+64 9-838 8632",
    "sg:province":"Auckland",
    "wof:name":"Bethany Gardens",
    "wof:placetype":"venue"
},
  "geometry": {"coordinates":[174.62823499999999,-36.870419],"type":"Point"}
}