{
  "type": "Feature",
  "properties": {
    "addr:full":"12 Rathbone St  Whangarei Northland",
    "addr:housenumber":"12",
    "addr:street":"Rathbone St",
    "iso:country":"NZ",
    "sg:address":"12 Rathbone St ",
    "sg:city":"Whangarei",
    "sg:classifiers":[
        {
            "category":"Shopping",
            "subcategory":"Crafts & Fabrics",
            "type":"Retail Goods"
        }
    ],
    "sg:phone":"+64 9-438 9831",
    "sg:province":"Northland",
    "sg:tags":[
        "foot",
        "clothing",
        "retailer",
        "footwear",
        "wear"
    ],
    "wof:name":"Uptons Shoes",
    "wof:placetype":"venue"
},
  "geometry": {"coordinates":[174.320999,-35.724655],"type":"Point"}
}