{
  "type": "Feature",
  "properties": {
    "addr:full":"42 Matai St  Taupo Waikato",
    "addr:housenumber":"42",
    "addr:street":"Matai St",
    "iso:country":"NZ",
    "sg:address":"42 Matai St ",
    "sg:city":"Taupo",
    "sg:classifiers":[
        {
            "category":"Professional",
            "subcategory":"Detective & Security Services",
            "type":"Services"
        }
    ],
    "sg:phone":"+64 7-378 6603",
    "sg:province":"Waikato",
    "sg:tags":[
        "services",
        "automotive",
        "warrant",
        "fitness"
    ],
    "wof:name":"Vehicle Testing New Zealand Limited",
    "wof:placetype":"venue"
},
  "geometry": {"coordinates":[176.10351600000001,-38.689354],"type":"Point"}
}