{
  "type": "Feature",
  "properties": {
    "iso:country":"NZ",
    "sg:address":"Quit Smoking ",
    "sg:city":"Wellington",
    "sg:classifiers":[
        {
            "category":"Social Services",
            "subcategory":"Retirement Home",
            "type":"Services"
        }
    ],
    "sg:phone":"+64 800 778 778",
    "sg:province":"Wellington",
    "sg:tags":[
        "personal",
        "services",
        "addiction",
        "garden"
    ],
    "wof:name":"Quitline",
    "wof:placetype":"venue"
},
  "geometry": {"coordinates":[-85.910454,33.827946],"type":"Point"}
}