{
  "type": "Feature",
  "properties": {
    "addr:full":"State Hwy 12 Opononi  Kaikohe",
    "addr:street":"State Hwy 12 Opononi",
    "iso:country":"NZ",
    "sg:address":"State Hwy 12 Opononi ",
    "sg:city":"Kaikohe",
    "sg:orig_category":"Shopping: Retail Stores: Books: Libraries",
    "sg:phone":"+64 9-405 8509",
    "wof:name":"South Hokianga School Community Library",
    "wof:placetype":"venue"
},
  "geometry": {"coordinates":[173.79710399999999,-35.406498],"type":"Point"}
}