{
  "type": "Feature",
  "properties": {
    "addr:full":"Kaka St  Whangarei Northland",
    "addr:street":"Kaka St",
    "iso:country":"NZ",
    "sg:address":"Kaka St ",
    "sg:city":"Whangarei",
    "sg:orig_category":"Industrial: Services: Bridge Building",
    "sg:phone":"+64 9-438 2884",
    "sg:province":"Northland",
    "wof:name":"Kerr Construction Whangarei Ltd",
    "wof:placetype":"venue"
},
  "geometry": {"coordinates":[174.320908,-35.73325],"type":"Point"}
}