{
  "type": "Feature",
  "properties": {
    "addr:full":"54a Lady Ruby Dve East Tamaki  Auckland Auckland",
    "addr:housenumber":"54a",
    "addr:street":"Lady Ruby Dve",
    "iso:country":"NZ",
    "sg:address":"54a Lady Ruby Dve East Tamaki ",
    "sg:city":"Auckland",
    "sg:orig_category":"Industrial: Products: Magnets",
    "sg:phone":"+64 9-277 9713",
    "sg:province":"Auckland",
    "wof:name":"Unimagnets",
    "wof:placetype":"venue"
},
  "geometry": {"coordinates":[174.89932300000001,-36.948387],"type":"Point"}
}