{
  "type": "Feature",
  "properties": {
    "iso:country":"NZ",
    "sg:address":"18 a Fitzroy Rd New ",
    "sg:city":"Plymouth",
    "sg:classifiers":[
        {
            "category":"Farming",
            "subcategory":"Farm & Veterinary Services",
            "type":"Manufacturing & Wholesale Goods"
        }
    ],
    "sg:phone":"+64 6-759 0069",
    "sg:province":"Taranaki",
    "sg:tags":[
        "supplies",
        "supply"
    ],
    "wof:name":"Egmont Farm Bike Services Ltd",
    "wof:placetype":"venue"
},
  "geometry": {"coordinates":[174.10766599999999,-39.043549],"type":"Point"}
}