{
  "type": "Feature",
  "properties": {
    "addr:full":"Miramar  Wellington Wellington",
    "iso:country":"NZ",
    "sg:address":"Miramar ",
    "sg:city":"Wellington",
    "sg:orig_category":"Shopping: Retail Stores: Antiques",
    "sg:phone":"+64 4-972 3341",
    "sg:province":"Wellington",
    "wof:name":"Ardvark Antiques",
    "wof:placetype":"venue"
},
  "geometry": {"coordinates":[174.81802400000001,-41.311909],"type":"Point"}
}