{
  "type": "Feature",
  "properties": {
    "addr:full":"108 Roebuck Rd  Gisborne Gisborne",
    "addr:housenumber":"108",
    "addr:street":"Roebuck Rd",
    "iso:country":"NZ",
    "sg:address":"108 Roebuck Rd ",
    "sg:city":"Gisborne",
    "sg:orig_category":"Farming: Machinery",
    "sg:phone":"+64 6-867 7351",
    "sg:province":"Gisborne",
    "wof:name":"Eastland Automotive & Tractor Service",
    "wof:placetype":"venue"
},
  "geometry": {"coordinates":[178.014343,-38.65955],"type":"Point"}
}