{
  "type": "Feature",
  "properties": {
    "iso:country":"NZ",
    "sg:address":"4 Manchester St ",
    "sg:city":"Paraparaumu",
    "sg:classifiers":[
        {
            "category":"Sports & Exercise",
            "subcategory":"Ice Rink",
            "type":"Entertainment"
        }
    ],
    "sg:phone":"+64 4-902 9270",
    "sg:province":"Wellington",
    "sg:tags":[
        "skating",
        "-",
        "leisure",
        "sports"
    ],
    "wof:name":"Skate N Blade Kapiti",
    "wof:placetype":"venue"
},
  "geometry": {"coordinates":[175.00100699999999,-40.904701],"type":"Point"}
}