{
  "type": "Feature",
  "properties": {
    "addr:full":"3 Mount View Pl Hornby  Christchurch Canterbury",
    "addr:housenumber":"3",
    "addr:street":"Mount View Pl",
    "iso:country":"NZ",
    "sg:address":"3 Mount View Pl Hornby ",
    "sg:city":"Christchurch",
    "sg:orig_category":"Clothing And Fabric: Fabric: Yarn",
    "sg:phone":"+64 3-349 3185",
    "sg:province":"Canterbury",
    "wof:name":"Radford Yarn Technologies Ltd",
    "wof:placetype":"venue"
},
  "geometry": {"coordinates":[172.53633099999999,-43.534431],"type":"Point"}
}