{
  "type": "Feature",
  "properties": {
    "addr:full":"410 A Ness St Kew  Invercargill Southland",
    "addr:housenumber":"410 a",
    "addr:street":"Ness St",
    "iso:country":"NZ",
    "sg:address":"410 A Ness St Kew ",
    "sg:city":"Invercargill",
    "sg:orig_category":"Transport: Transportation: Furniture Removal/Packers",
    "sg:phone":"+64 3-218 9650",
    "sg:province":"Southland",
    "wof:name":"Dee Bill",
    "wof:placetype":"venue"
},
  "geometry": {"coordinates":[168.36019899999999,-46.434837],"type":"Point"}
}