{
  "type": "Feature",
  "properties": {
    "addr:full":"Hamilton Matamata Waikato",
    "iso:country":"NZ",
    "sg:address":"Hamilton",
    "sg:city":"Matamata",
    "sg:classifiers":[
        {
            "category":"Manufacturing",
            "subcategory":"Rubber & Plastics",
            "type":"Manufacturing & Wholesale Goods"
        }
    ],
    "sg:phone":"+64 800 396 272",
    "sg:province":"Waikato",
    "sg:tags":[
        "industrial"
    ],
    "sg:website":"http://www.yellowpages.co.nz/for/svedala/",
    "wof:name":"Metso Minerals (NZ) Ltd",
    "wof:placetype":"venue"
},
  "geometry": {"coordinates":[175.77354399999999,-37.81176],"type":"Point"}
}