{
  "type": "Feature",
  "properties": {
    "iso:country":"NZ",
    "sg:address":"62 Albert St ",
    "sg:city":"Greymouth",
    "sg:classifiers":[
        {
            "category":"Travel",
            "subcategory":"Bed & Breakfast",
            "type":"Entertainment"
        }
    ],
    "sg:phone":"+64 3-768 5605",
    "sg:province":"West Coast",
    "sg:tags":[
        "tourism",
        "accommodation"
    ],
    "wof:name":"Sanford's Guest Lodge",
    "wof:placetype":"venue"
},
  "geometry": {"coordinates":[171.209564,-42.450336],"type":"Point"}
}