{
  "type": "Feature",
  "properties": {
    "iso:country":"NZ",
    "sg:address":"163 B Cranford St St Albans ",
    "sg:city":"Christchurch",
    "sg:classifiers":[
        {
            "category":"Retail",
            "subcategory":"Repair Shop",
            "type":"Services"
        }
    ],
    "sg:phone":"+64 3-356 2162",
    "sg:province":"Canterbury",
    "sg:tags":[
        "clothing",
        "fabric",
        "cleaning"
    ],
    "wof:name":"Chris's Clothing Services",
    "wof:placetype":"venue"
},
  "geometry": {"coordinates":[172.636246,-43.506451],"type":"Point"}
}