{
  "type": "Feature",
  "properties": {
    "iso:country":"NZ",
    "sg:address":"139 Wordsworth St Sydenham ",
    "sg:city":"Christchurch",
    "sg:orig_category":"Industrial: Services: Gasfitters",
    "sg:phone":"+64 3-366 6610",
    "sg:province":"Canterbury",
    "wof:name":"GASLink",
    "wof:placetype":"venue"
},
  "geometry": {"coordinates":[172.64125100000001,-43.544586],"type":"Point"}
}