{
  "type": "Feature",
  "properties": {
    "addr:full":"Mangapai Rd Mangapai  Whangarei Northland",
    "addr:street":"Mangapai Rd",
    "iso:country":"NZ",
    "sg:address":"Mangapai Rd Mangapai ",
    "sg:city":"Whangarei",
    "sg:orig_category":"Transport: Boats And Marine: Services",
    "sg:phone":"+64 9-432 2222",
    "sg:province":"Northland",
    "wof:name":"Navis Design",
    "wof:placetype":"venue"
},
  "geometry": {"coordinates":[174.284943,-35.846169],"type":"Point"}
}