{
  "type": "Feature",
  "properties": {
    "addr:full":"16 Thomas St  Ranfurly",
    "addr:housenumber":"16",
    "addr:street":"Thomas St",
    "iso:country":"NZ",
    "sg:address":"16 Thomas St ",
    "sg:city":"Ranfurly",
    "sg:orig_category":"Farming: Services: Livestock Related: Sheep Shearers",
    "sg:phone":"+64 3-444 9805",
    "wof:name":"Maniototo Shearing Company Ltd",
    "wof:placetype":"venue"
},
  "geometry": {"coordinates":[170.09901400000001,-45.127953],"type":"Point"}
}