{
  "type": "Feature",
  "properties": {
    "addr:full":"147 Conyers St  Invercargill Southland",
    "addr:housenumber":"147",
    "addr:street":"Conyers St",
    "iso:country":"NZ",
    "sg:address":"147 Conyers St ",
    "sg:city":"Invercargill",
    "sg:orig_category":"Home And Garden: General: Handyman'S Services",
    "sg:phone":"+64 3-216 6246",
    "sg:province":"Southland",
    "wof:name":"Osborne's Handyman Services",
    "wof:placetype":"venue"
},
  "geometry": {"coordinates":[168.37455700000001,-46.424633],"type":"Point"}
}