{
  "type": "Feature",
  "properties": {
    "iso:country":"NZ",
    "sg:address":"40 D William Pickering Dve Albany ",
    "sg:city":"Auckland",
    "sg:classifiers":[
        {
            "category":"Utilities",
            "subcategory":"Electric",
            "type":"Services"
        }
    ],
    "sg:phone":"+64 9-415 7652",
    "sg:province":"Auckland",
    "sg:tags":[
        "energy",
        "industrial"
    ],
    "wof:name":"Solahart",
    "wof:placetype":"venue"
},
  "geometry": {"coordinates":[174.69717399999999,-36.744556],"type":"Point"}
}