{
  "type": "Feature",
  "properties": {
    "addr:full":"Unit 2 / 20 Allington Rd Massey  Auckland Auckland",
    "addr:housenumber":"unit 2 / 20",
    "addr:street":"Allington Rd",
    "iso:country":"NZ",
    "sg:address":"Unit 2 / 20 Allington Rd Massey ",
    "sg:city":"Auckland",
    "sg:classifiers":[
        {
            "category":"Retail",
            "subcategory":"Auto Repair",
            "type":"Services"
        }
    ],
    "sg:phone":"+64 9-833 5808",
    "sg:province":"Auckland",
    "sg:tags":[
        "mobile",
        "automotive",
        "servicing",
        "mechanic"
    ],
    "wof:name":"CarFix 2002 Ltd",
    "wof:placetype":"venue"
},
  "geometry": {"coordinates":[174.634918,-36.827538],"type":"Point"}
}