{
  "type": "Feature",
  "properties": {
    "addr:full":"244 Stanley Rd  Gisborne Gisborne",
    "addr:housenumber":"244",
    "addr:street":"Stanley Rd",
    "iso:country":"NZ",
    "sg:address":"244 Stanley Rd ",
    "sg:city":"Gisborne",
    "sg:classifiers":[
        {
            "category":"Manufacturing",
            "subcategory":"Tools & Machinery",
            "type":"Manufacturing & Wholesale Goods"
        }
    ],
    "sg:phone":"+64 6-867 4995",
    "sg:province":"Gisborne",
    "sg:tags":[
        "equipment",
        "industrial",
        "hydraulic"
    ],
    "wof:name":"Fluid Connections",
    "wof:placetype":"venue"
},
  "geometry": {"coordinates":[178.00436400000001,-38.668182],"type":"Point"}
}