{
  "type": "Feature",
  "properties": {
    "addr:full":"68-70 Main St  Otaki",
    "addr:housenumber":"68-70",
    "addr:street":"Main St",
    "iso:country":"NZ",
    "sg:address":"68-70 Main St ",
    "sg:city":"Otaki",
    "sg:classifiers":[
        {
            "category":"Shopping",
            "subcategory":"Crafts & Fabrics",
            "type":"Retail Goods"
        }
    ],
    "sg:phone":"+64 6-364 8019",
    "sg:tags":[
        "foot",
        "clothing",
        "retailer",
        "footwear",
        "wear"
    ],
    "wof:name":"Edhouse H B Ltd",
    "wof:placetype":"venue"
},
  "geometry": {"coordinates":[175.14001500000001,-40.752693],"type":"Point"}
}