{
  "type": "Feature",
  "properties": {
    "addr:full":"Beach Rd  Akaroa Canterbury",
    "addr:street":"Beach Rd",
    "iso:country":"NZ",
    "sg:address":"Beach Rd ",
    "sg:city":"Akaroa",
    "sg:classifiers":[
        {
            "category":"Shopping",
            "subcategory":"Gifts & Souvenirs",
            "type":"Retail Goods"
        }
    ],
    "sg:phone":"+64 3-304 7896",
    "sg:province":"Canterbury",
    "sg:tags":[
        "shop",
        "gifts",
        "supplier"
    ],
    "wof:name":"The Weighbridge",
    "wof:placetype":"venue"
},
  "geometry": {"coordinates":[172.95245399999999,-43.815025],"type":"Point"}
}