{
  "type": "Feature",
  "properties": {
    "iso:country":"NZ",
    "sg:address":"68 G Greenmount Dve East Tamaki ",
    "sg:city":"Auckland",
    "sg:classifiers":[
        {
            "category":"Bars & Pubs",
            "subcategory":"Wine Bar",
            "type":"Food & Drink"
        }
    ],
    "sg:phone":"+64 9-273 3701",
    "sg:province":"Auckland",
    "sg:tags":[
        "distributor"
    ],
    "wof:name":"A Touch Of Italy",
    "wof:placetype":"venue"
},
  "geometry": {"coordinates":[174.90138200000001,-36.931046],"type":"Point"}
}