{
  "type": "Feature",
  "properties": {
    "addr:full":"71 Tongariro St  Taupo Waikato",
    "addr:housenumber":"71",
    "addr:street":"Tongariro St",
    "iso:country":"NZ",
    "sg:address":"71 Tongariro St ",
    "sg:city":"Taupo",
    "sg:classifiers":[
        {
            "category":"Internet Cafe",
            "subcategory":"None",
            "type":"Food & Drink"
        }
    ],
    "sg:phone":"+64 7-376 5901",
    "sg:province":"Waikato",
    "sg:tags":[
        "wining",
        "dining"
    ],
    "wof:name":"Log-On Internet Access",
    "wof:placetype":"venue"
},
  "geometry": {"coordinates":[176.069748,-38.68071],"type":"Point"}
}