{
  "type": "Feature",
  "properties": {
    "addr:full":"68 Michaels Ave Ellerslie  Auckland Auckland",
    "addr:housenumber":"68",
    "addr:street":"Michaels Ave",
    "iso:country":"NZ",
    "sg:address":"68 Michaels Ave Ellerslie ",
    "sg:city":"Auckland",
    "sg:classifiers":[
        {
            "category":"Home & Garden",
            "subcategory":"Building Materials",
            "type":"Retail Goods"
        }
    ],
    "sg:phone":"+64 9-579 2665",
    "sg:province":"Auckland",
    "sg:tags":[
        "electrician",
        "related"
    ],
    "wof:name":"Chamberlain Electrical",
    "wof:placetype":"venue"
},
  "geometry": {"coordinates":[174.819107,-36.893154],"type":"Point"}
}