{
  "type": "Feature",
  "properties": {
    "iso:country":"NZ",
    "sg:address":"100 Carlton Gore Rd Newmarket ",
    "sg:city":"Auckland",
    "sg:orig_category":"Farming: Supplies",
    "sg:phone":"+64 9-379 1703",
    "sg:province":"Auckland",
    "wof:name":"NRM New Zealand",
    "wof:placetype":"venue"
},
  "geometry": {"coordinates":[174.775955,-36.864967],"type":"Point"}
}