{
  "type": "Feature",
  "properties": {
    "iso:country":"NZ",
    "sg:address":"9 Lincoln St ",
    "sg:city":"Hamilton",
    "sg:orig_category":"Home And Garden: Furniture/Furnishings: Curtains",
    "sg:phone":"+64 7-846 9277",
    "sg:province":"Waikato",
    "wof:name":"Curtain Design",
    "wof:placetype":"venue"
},
  "geometry": {"coordinates":[-70.881386,42.621658],"type":"Point"}
}