{
  "type": "Feature",
  "properties": {
    "addr:full":"153 Colombo Rd Waiuku  Auckland Auckland",
    "addr:housenumber":"153",
    "addr:street":"Colombo Rd",
    "iso:country":"NZ",
    "sg:address":"153 Colombo Rd Waiuku ",
    "sg:city":"Auckland",
    "sg:orig_category":"Farming: Horticulture: Flowers",
    "sg:phone":"+64 9-235 7473",
    "sg:province":"Auckland",
    "wof:name":"Hopman Bulbs NZ Ltd",
    "wof:placetype":"venue"
},
  "geometry": {"coordinates":[174.74955700000001,-37.251827],"type":"Point"}
}