{
  "type": "Feature",
  "properties": {
    "iso:country":"NZ",
    "sg:address":"94 Gt South Rd Papakura ",
    "sg:city":"Auckland",
    "sg:classifiers":[
        {
            "category":"Retail",
            "subcategory":"Laundry & Dry Cleaning",
            "type":"Services"
        }
    ],
    "sg:phone":"+64 9-296 2442",
    "sg:province":"Auckland",
    "sg:tags":[
        "repair",
        "clothing",
        "fabric",
        "cleaner"
    ],
    "wof:name":"Roseland's Drycleaners",
    "wof:placetype":"venue"
},
  "geometry": {"coordinates":[174.94053600000001,-37.059261],"type":"Point"}
}