{
  "type": "Feature",
  "properties": {
    "iso:country":"NZ",
    "sg:address":"84 Bank St ",
    "sg:city":"Whangarei",
    "sg:classifiers":[
        {
            "category":"Education",
            "subcategory":"Vocational School",
            "type":"Public Place"
        }
    ],
    "sg:phone":"+64 9-430 0469",
    "sg:province":"Northland",
    "sg:tags":[
        "training",
        "hairdressing"
    ],
    "wof:name":"NZ Academy of Hair Design",
    "wof:placetype":"venue"
},
  "geometry": {"coordinates":[174.320175,-35.722927],"type":"Point"}
}