{
  "type": "Feature",
  "properties": {
    "iso:country":"NZ",
    "sg:address":"197 Old Taupo Rd ",
    "sg:city":"Rotorua",
    "sg:classifiers":[
        {
            "category":"Banks & Credit Unions",
            "subcategory":"Investment Brokerage",
            "type":"Services"
        }
    ],
    "sg:phone":"+64 7-348 3600",
    "sg:province":"Bay of Plenty",
    "sg:tags":[
        "director",
        "funeral",
        "arrangements"
    ],
    "wof:name":"Osbornes Funeral Home",
    "wof:placetype":"venue"
},
  "geometry": {"coordinates":[176.238663,-38.147594],"type":"Point"}
}