{
  "type": "Feature",
  "properties": {
    "iso:country":"NZ",
    "sg:address":"33 Forge Rd Silverdale Hibiscus ",
    "sg:city":"Hibiscus Coast",
    "sg:orig_category":"Transport: Boats And Marine: Products: Propellers",
    "sg:phone":"+64 9-426 7847",
    "sg:province":"Auckland",
    "wof:name":"Seafury Propulsion Systems Ltd",
    "wof:placetype":"venue"
},
  "geometry": {"coordinates":[174.678452,-36.625336],"type":"Point"}
}