{
  "type": "Feature",
  "properties": {
    "addr:full":"Thames Rd  Paeroa",
    "addr:street":"Thames Rd",
    "iso:country":"NZ",
    "sg:address":"Thames Rd ",
    "sg:city":"Paeroa",
    "sg:orig_category":"Sports And Leisure: General: Clubs",
    "sg:phone":"+64 7-862 7246",
    "wof:name":"Paeroa Racing Club",
    "wof:placetype":"venue"
},
  "geometry": {"coordinates":[175.67950400000001,-37.371815],"type":"Point"}
}