{
  "type": "Feature",
  "properties": {
    "iso:country":"NZ",
    "sg:address":"PO Box 909 ",
    "sg:city":"Masterton",
    "sg:classifiers":[
        {
            "category":"Sports & Exercise",
            "subcategory":"Swimming Pool",
            "type":"Entertainment"
        }
    ],
    "sg:phone":"+64 6-377 0344",
    "sg:province":"Wellington",
    "sg:tags":[
        "home",
        "outdoor",
        "garden",
        "spa"
    ],
    "wof:name":"Taylors Pool Service (Wai) Limited",
    "wof:placetype":"venue"
},
  "geometry": {"coordinates":[175.65733299999999,-40.94931],"type":"Point"}
}