{
  "type": "Feature",
  "properties": {
    "iso:country":"NZ",
    "sg:address":"PO Box 106 ",
    "sg:city":"Matamata",
    "sg:orig_category":"Farming: Services: Livestock Related: Bloodstock Agents",
    "sg:phone":"+64 7-888 5127",
    "sg:province":"Waikato",
    "wof:name":"Bloodstock Agents Federation NZ (Inc)",
    "wof:placetype":"venue"
},
  "geometry": {"coordinates":[175.773544,-37.811764],"type":"Point"}
}