{
  "type": "Feature",
  "properties": {
    "addr:full":"Great Barrier  Island",
    "iso:country":"NZ",
    "sg:address":"Great Barrier ",
    "sg:city":"Island",
    "sg:classifiers":[
        {
            "category":"Organizations",
            "subcategory":"Labor Organization",
            "type":"Services"
        }
    ],
    "sg:phone":"+64 25799647",
    "sg:tags":[
        "services",
        "charter",
        "tourism",
        "travel",
        "boat"
    ],
    "wof:name":"Bonaventure Blue Water Safaris",
    "wof:placetype":"venue"
},
  "geometry": {"coordinates":[175.428665,-36.199791],"type":"Point"}
}