{
  "type": "Feature",
  "properties": {
    "iso:country":"NZ",
    "sg:address":"Unit B 101 Cliff View Dve Green Bay ",
    "sg:city":"Auckland",
    "sg:classifiers":[
        {
            "category":"Personal",
            "type":"Services"
        }
    ],
    "sg:phone":"+64 9-827 2586",
    "sg:province":"Auckland",
    "sg:tags":[
        "celebrant",
        "arrangements",
        "marriage",
        "wedding"
    ],
    "wof:name":"Bergquist Jean J P",
    "wof:placetype":"venue"
},
  "geometry": {"coordinates":[174.71894800000001,-36.675575],"type":"Point"}
}