{
  "type": "Feature",
  "properties": {
    "iso:country":"NZ",
    "sg:address":"16 Railway St Newmarket PO Box 90664 Auckland Mail, Centre ",
    "sg:city":"Auckland",
    "sg:orig_category":"Clothing And Fabric: Fabric: Textiles",
    "sg:phone":"+64 9-523 0625",
    "sg:province":"Auckland",
    "wof:name":"Designers International",
    "wof:placetype":"venue"
},
  "geometry": {"coordinates":[174.77041600000001,-36.884109],"type":"Point"}
}