{
  "type": "Feature",
  "properties": {
    "addr:full":"36 Glenlyon Ave Greerton  Tauranga Bay of Plenty",
    "addr:housenumber":"36",
    "addr:street":"Glenlyon Ave",
    "iso:country":"NZ",
    "sg:address":"36 Glenlyon Ave Greerton ",
    "sg:city":"Tauranga",
    "sg:orig_category":"Home And Garden: Gardening: Services: Landscaping",
    "sg:phone":"+64 7-577 6444",
    "sg:province":"Bay of Plenty",
    "wof:name":"CGC Limited Landscape Company",
    "wof:placetype":"venue"
},
  "geometry": {"coordinates":[176.140625,-37.734184],"type":"Point"}
}