{
  "type": "Feature",
  "properties": {
    "iso:country":"NZ",
    "sg:address":"6 Hautu Dve Wiri ",
    "sg:city":"Auckland",
    "sg:orig_category":"Industrial: Metal: Services",
    "sg:phone":"+64 9-277 2700",
    "sg:province":"Auckland",
    "sg:website":"http://www.yellowpages.co.nz/for/kiwisteel/dp11521.html",
    "wof:name":"Kiwi Steel NZ Ltd",
    "wof:placetype":"venue"
},
  "geometry": {"coordinates":[174.855713,-37.011593],"type":"Point"}
}