{
  "type": "Feature",
  "properties": {
    "iso:country":"NZ",
    "sg:address":"137 Montgomery Rd Mangere ",
    "sg:city":"Auckland",
    "sg:orig_category":"Transport: Transportation: Freight",
    "sg:phone":"+64 9-256 2556",
    "sg:province":"Auckland",
    "wof:name":"Pacific Freight Management Limited",
    "wof:placetype":"venue"
},
  "geometry": {"coordinates":[174.77435299999999,-36.977055],"type":"Point"}
}