{
  "type": "Feature",
  "properties": {
    "iso:country":"NZ",
    "sg:address":"134 Park Rd Miramar ",
    "sg:city":"Wellington",
    "sg:classifiers":[
        {
            "category":"Home & Garden",
            "subcategory":"Kitchen Supply",
            "type":"Retail Goods"
        }
    ],
    "sg:phone":"+64 4-939 8840",
    "sg:province":"Wellington",
    "sg:tags":[
        "motel",
        "industrial",
        "products",
        "hotel"
    ],
    "wof:name":"Gilmac Agencies Ltd",
    "wof:placetype":"venue"
},
  "geometry": {"coordinates":[174.821716,-41.308994],"type":"Point"}
}