{
  "type": "Feature",
  "properties": {
    "iso:country":"NZ",
    "sg:address":"Grey St Hamilton East ",
    "sg:city":"Hamilton",
    "sg:classifiers":[
        {
            "category":"Personal",
            "subcategory":"Hair Removal",
            "type":"Services"
        }
    ],
    "sg:phone":"+64 800 698 698",
    "sg:province":"Waikato",
    "sg:tags":[
        "health",
        "beauty"
    ],
    "wof:name":"Caci Clinic",
    "wof:placetype":"venue"
},
  "geometry": {"coordinates":[175.29173299999999,-37.78886],"type":"Point"}
}