{
  "type": "Feature",
  "properties": {
    "addr:full":"321 Swanson Rd  Ranui Auckland",
    "addr:housenumber":"321",
    "addr:street":"Swanson Rd",
    "iso:country":"NZ",
    "sg:address":"321 Swanson Rd ",
    "sg:city":"Ranui",
    "sg:classifiers":[
        {
            "category":"Social Services",
            "subcategory":"Retirement Home",
            "type":"Services"
        }
    ],
    "sg:phone":"+64 21 724 099",
    "sg:province":"Auckland",
    "sg:tags":[
        "sharpening",
        "garden"
    ],
    "wof:name":"Nelson Scissor & Knife",
    "wof:placetype":"venue"
},
  "geometry": {"coordinates":[174.60784899999999,-36.861835],"type":"Point"}
}