{
  "type": "Feature",
  "properties": {
    "iso:country":"NZ",
    "sg:address":"121 Beaconsfield Road R D 2 ",
    "sg:city":"Timaru",
    "sg:orig_category":"Sports And Leisure: Sports: Equestrian",
    "sg:phone":"+64 3-684 3030",
    "sg:province":"Otago",
    "sg:website":"http://www.kishonarabians.co.nz",
    "wof:name":"Kishon Arabians",
    "wof:placetype":"venue"
},
  "geometry": {"coordinates":[171.237411,-44.395428],"type":"Point"}
}