{
  "type": "Feature",
  "properties": {
    "addr:full":"13 Kenepuru Dve  Porirua Wellington",
    "addr:housenumber":"13",
    "addr:street":"Kenepuru Dve",
    "iso:country":"NZ",
    "sg:address":"13 Kenepuru Dve ",
    "sg:city":"Porirua",
    "sg:classifiers":[
        {
            "category":"Food & Beverages",
            "subcategory":"Liquor & Beverages",
            "type":"Retail Goods"
        }
    ],
    "sg:phone":"+64 4-238 9111",
    "sg:province":"Wellington",
    "sg:tags":[
        "drink",
        "outlet"
    ],
    "wof:name":"The Mill Liquorsave",
    "wof:placetype":"venue"
},
  "geometry": {"coordinates":[174.85223400000001,-41.138294],"type":"Point"}
}