{
  "type": "Feature",
  "properties": {
    "addr:full":"16 Waller Avenue Bucklands Beach  Auckland Auckland",
    "addr:housenumber":"16",
    "addr:street":"Waller Avenue",
    "iso:country":"NZ",
    "sg:address":"16 Waller Avenue Bucklands Beach ",
    "sg:city":"Auckland",
    "sg:classifiers":[
        {
            "category":"Shopping",
            "subcategory":"Bicycles & Sporting Goods",
            "type":"Retail Goods"
        }
    ],
    "sg:phone":"+64 21 394 403",
    "sg:province":"Auckland",
    "sg:tags":[
        "sport",
        "fishing",
        "hunting",
        "retailers"
    ],
    "wof:name":"Adventure Boat Charters",
    "wof:placetype":"venue"
},
  "geometry": {"coordinates":[174.90588399999999,-36.865505],"type":"Point"}
}