{
  "type": "Feature",
  "properties": {
    "addr:full":"The Square  Martinborough Wellington",
    "addr:street":"The Square",
    "iso:country":"NZ",
    "sg:address":"The Square ",
    "sg:city":"Martinborough",
    "sg:classifiers":[
        {
            "category":"Food & Beverages",
            "subcategory":"Liquor & Beverages",
            "type":"Retail Goods"
        }
    ],
    "sg:phone":"+64 6-306 9606",
    "sg:province":"Wellington",
    "sg:tags":[
        "drink",
        "outlet"
    ],
    "wof:name":"Pukemanu Wholesale",
    "wof:placetype":"venue"
},
  "geometry": {"coordinates":[175.45996099999999,-41.220089],"type":"Point"}
}