{
  "type": "Feature",
  "properties": {
    "addr:full":"88 Balmoral Rd Mt Eden  Auckland Auckland",
    "addr:housenumber":"88",
    "addr:street":"Balmoral Rd",
    "iso:country":"NZ",
    "sg:address":"88 Balmoral Rd Mt Eden ",
    "sg:city":"Auckland",
    "sg:orig_category":"Industrial: Consultancy",
    "sg:phone":"+64 9-623 2021",
    "sg:province":"Auckland",
    "wof:name":"David Melrose Design",
    "wof:placetype":"venue"
},
  "geometry": {"coordinates":[174.75593599999999,-36.88905],"type":"Point"}
}