{
  "type": "Feature",
  "properties": {
    "addr:full":"8 B Piermark Dve Albany  Auckland Auckland",
    "addr:housenumber":"8 b",
    "addr:street":"Dve",
    "iso:country":"NZ",
    "sg:address":"8 B Piermark Dve Albany ",
    "sg:city":"Auckland",
    "sg:classifiers":[
        {
            "category":"Sports & Exercise",
            "subcategory":"Sports Center",
            "type":"Entertainment"
        }
    ],
    "sg:phone":"+64 800 477 177",
    "sg:province":"Auckland",
    "sg:tags":[
        "game",
        "-",
        "leisure",
        "interactive"
    ],
    "wof:name":"PlayStation Service Centre",
    "wof:placetype":"venue"
},
  "geometry": {"coordinates":[174.70323200000001,-36.748043],"type":"Point"}
}