{
  "type": "Feature",
  "properties": {
    "iso:country":"NZ",
    "sg:address":"4 A Cargill Pl Richmond ",
    "sg:city":"Nelson",
    "sg:classifiers":[
        {
            "category":"Coffee & Tea",
            "type":"Food & Drink"
        }
    ],
    "sg:phone":"+64 3-544 9130",
    "sg:province":"Nelson",
    "sg:tags":[
        "vegetable",
        "fruit",
        "veges"
    ],
    "wof:name":"Cullen's Fruit & Vegies",
    "wof:placetype":"venue"
},
  "geometry": {"coordinates":[-121.765488,39.553471],"type":"Point"}
}