{
  "type": "Feature",
  "properties": {
    "addr:full":"92 G Marua Rd Ellerslie  Auckland Auckland",
    "addr:housenumber":"92 g",
    "addr:street":"Marua Rd",
    "iso:country":"NZ",
    "sg:address":"92 G Marua Rd Ellerslie ",
    "sg:city":"Auckland",
    "sg:orig_category":"Health And Beauty: Specialists: Podiatrists",
    "sg:phone":"+64 9-525 8060",
    "sg:province":"Auckland",
    "wof:name":"Ellerslie Foot & Physio Clinic",
    "wof:placetype":"venue"
},
  "geometry": {"coordinates":[174.822113,-36.89122],"type":"Point"}
}