{
  "type": "Feature",
  "properties": {
    "addr:full":"125 Gordon Rd Mosgiel  Dunedin Otago",
    "addr:housenumber":"125",
    "addr:street":"Gordon Rd",
    "iso:country":"NZ",
    "sg:address":"125 Gordon Rd Mosgiel ",
    "sg:city":"Dunedin",
    "sg:classifiers":[
        {
            "category":"Shopping",
            "subcategory":"Bicycles & Sporting Goods",
            "type":"Retail Goods"
        }
    ],
    "sg:phone":"+64 3-489 7600",
    "sg:province":"Otago",
    "sg:tags":[
        "equipment",
        "sport",
        "tramping",
        "leisure",
        "camping"
    ],
    "wof:name":"Gales Sports Centre",
    "wof:placetype":"venue"
},
  "geometry": {"coordinates":[170.34837300000001,-45.874866],"type":"Point"}
}