{
  "type": "Feature",
  "properties": {
    "addr:full":"39 King St Te  Kuiti",
    "addr:housenumber":"39",
    "addr:street":"King St",
    "iso:country":"NZ",
    "sg:address":"39 King St Te ",
    "sg:city":"Kuiti",
    "sg:classifiers":[
        {
            "category":"Sports & Exercise",
            "subcategory":"Sports Center",
            "type":"Entertainment"
        }
    ],
    "sg:phone":"+64 7-878 7934",
    "sg:tags":[
        "health",
        "beauty",
        "fitness"
    ],
    "wof:name":"Bruce's Fitness Centre",
    "wof:placetype":"venue"
},
  "geometry": {"coordinates":[175.16691599999999,-38.332378],"type":"Point"}
}