{
  "type": "Feature",
  "properties": {
    "iso:country":"NZ",
    "sg:address":"179 Victoria St ",
    "sg:city":"Christchurch",
    "sg:classifiers":[
        {
            "category":"Arts & Performance",
            "subcategory":"Art Gallery",
            "type":"Entertainment"
        }
    ],
    "sg:phone":"+64 3-366 7374",
    "sg:province":"Canterbury",
    "sg:tags":[
        "arts",
        "sport",
        "leisure"
    ],
    "wof:name":"Willo",
    "wof:placetype":"venue"
},
  "geometry": {"coordinates":[-76.537834,37.605659],"type":"Point"}
}