{
  "type": "Feature",
  "properties": {
    "iso:country":"NZ",
    "sg:address":"13 b Riccarton Rd Riccarton ",
    "sg:city":"Christchurch",
    "sg:classifiers":[
        {
            "category":"Personal",
            "subcategory":"Tanning Parlor",
            "type":"Services"
        }
    ],
    "sg:phone":"+64 3-348 8449",
    "sg:province":"Canterbury",
    "sg:tags":[
        "sun",
        "health",
        "beauty"
    ],
    "wof:name":"Riccarton Hair and Body Studio",
    "wof:placetype":"venue"
},
  "geometry": {"coordinates":[172.610947,-43.52903],"type":"Point"}
}