{
  "type": "Feature",
  "properties": {
    "iso:country":"NZ",
    "sg:address":"31 Ihakara St ",
    "sg:city":"Paraparaumu",
    "sg:classifiers":[
        {
            "category":"Home & Garden",
            "subcategory":"Furniture",
            "type":"Retail Goods"
        }
    ],
    "sg:phone":"+64 4-297 0807",
    "sg:province":"Wellington",
    "sg:tags":[
        "furniture/furnishings",
        "repair",
        "finishing"
    ],
    "wof:name":"Antiquity Restoration",
    "wof:placetype":"venue"
},
  "geometry": {"coordinates":[174.99906899999999,-40.918545],"type":"Point"}
}