{
  "type": "Feature",
  "properties": {
    "iso:country":"NZ",
    "sg:address":"21 Achilles Rse Flagstaff ",
    "sg:city":"Hamilton",
    "sg:orig_category":"Clothing And Fabric: Clothing: Clothing - Specialty",
    "sg:phone":"+64 7-854 0565",
    "sg:province":"Waikato",
    "wof:name":"Clothes on the Road",
    "wof:placetype":"venue"
},
  "geometry": {"coordinates":[175.25103799999999,-37.731438],"type":"Point"}
}