{
  "type": "Feature",
  "properties": {
    "addr:full":"West End  Kaikoura Canterbury",
    "iso:country":"NZ",
    "sg:address":"West End ",
    "sg:city":"Kaikoura",
    "sg:classifiers":[
        {
            "category":"Shopping",
            "subcategory":"Crafts & Fabrics",
            "type":"Retail Goods"
        }
    ],
    "sg:phone":"+64 3-319 5028",
    "sg:province":"Canterbury",
    "sg:tags":[
        "foot",
        "clothing",
        "retailer",
        "footwear",
        "wear"
    ],
    "wof:name":"Rose's Shoe Store",
    "wof:placetype":"venue"
},
  "geometry": {"coordinates":[173.679596,-42.399712],"type":"Point"}
}