{
  "type": "Feature",
  "properties": {
    "iso:country":"NZ",
    "sg:address":"130 High St ",
    "sg:city":"Greymouth",
    "sg:classifiers":[
        {
            "category":"Bars & Pubs",
            "subcategory":"Lounge",
            "type":"Food & Drink"
        }
    ],
    "sg:phone":"+64 3-768 9400",
    "sg:province":"West Coast",
    "sg:tags":[
        "baker",
        "-"
    ],
    "wof:name":"Do Duck Inn Bakery",
    "wof:placetype":"venue"
},
  "geometry": {"coordinates":[171.19558699999999,-42.462749],"type":"Point"}
}