{
  "type": "Feature",
  "properties": {
    "iso:country":"NZ",
    "sg:address":"85 Judds Rd ",
    "sg:city":"Masterton",
    "sg:classifiers":[
        {
            "category":"Bars & Pubs",
            "subcategory":"Lounge",
            "type":"Food & Drink"
        }
    ],
    "sg:phone":"+64 6-370 0260",
    "sg:province":"Wellington",
    "sg:tags":[
        "baker",
        "-"
    ],
    "wof:name":"Breadcraft Wairarapa Ltd",
    "wof:placetype":"venue"
},
  "geometry": {"coordinates":[175.62318400000001,-40.955208],"type":"Point"}
}