{
  "type": "Feature",
  "properties": {
    "iso:country":"NZ",
    "sg:address":"443 Hutt Rd Lower ",
    "sg:city":"Hutt",
    "sg:classifiers":[
        {
            "category":"Home & Garden",
            "subcategory":"Home Furnishings",
            "type":"Retail Goods"
        }
    ],
    "sg:phone":"+64 4-566 9746",
    "sg:province":"Wellington",
    "sg:tags":[
        "furniture/furnishings",
        "bedding",
        "bed"
    ],
    "wof:name":"Moera Carpet Beds & Home Appliances",
    "wof:placetype":"venue"
},
  "geometry": {"coordinates":[174.904526,-41.208431],"type":"Point"}
}