{
  "type": "Feature",
  "properties": {
    "addr:full":"80 Taradale Rd  Napier Hawke's Bay",
    "addr:housenumber":"80",
    "addr:street":"Taradale Rd",
    "iso:country":"NZ",
    "sg:address":"80 Taradale Rd ",
    "sg:city":"Napier",
    "sg:classifiers":[
        {
            "category":"Home & Garden",
            "subcategory":"Building Materials",
            "type":"Retail Goods"
        }
    ],
    "sg:phone":"+64 6-843 7319",
    "sg:province":"Hawke's Bay",
    "sg:tags":[
        "design",
        "fitting",
        "fittings",
        "kitchen"
    ],
    "wof:name":"European Designer Kitchens",
    "wof:placetype":"venue"
},
  "geometry": {"coordinates":[176.87443500000001,-39.514668],"type":"Point"}
}