{
  "type": "Feature",
  "properties": {
    "iso:country":"NZ",
    "sg:address":"578 Mt Eden Rd Mt Eden ",
    "sg:city":"Auckland",
    "sg:orig_category":"Health And Beauty: Medical: Hospitals",
    "sg:phone":"+64 9-638 7506",
    "sg:province":"Auckland",
    "wof:name":"Bellevue Hospital",
    "wof:placetype":"venue"
},
  "geometry": {"coordinates":[174.76083399999999,-36.887371],"type":"Point"}
}