{
  "type": "Feature",
  "properties": {
    "addr:full":"Mid City Devonport Rd  Tauranga Auckland",
    "addr:street":"Devonport Rd",
    "iso:country":"NZ",
    "sg:address":"Mid City Devonport Rd ",
    "sg:city":"Tauranga",
    "sg:orig_category":"Health And Beauty: Beauty: Hairdressers",
    "sg:phone":"+64 7-578 4323",
    "sg:province":"Auckland",
    "wof:name":"Rodney Wayne Hairdressing",
    "wof:placetype":"venue"
},
  "geometry": {"coordinates":[-90.09902200000001,29.97122],"type":"Point"}
}