{
  "type": "Feature",
  "properties": {
    "iso:country":"NZ",
    "sg:address":"3 Binsted Rd New Lynn ",
    "sg:city":"Auckland",
    "sg:classifiers":[
        {
            "category":"Professional",
            "subcategory":"Art Services",
            "type":"Services"
        }
    ],
    "sg:phone":"+64 9-826 0536",
    "sg:province":"Auckland",
    "sg:tags":[
        "equipment",
        "arts",
        "sport",
        "film",
        "leisure"
    ],
    "wof:name":"Set Scenarios",
    "wof:placetype":"venue"
},
  "geometry": {"coordinates":[174.683746,-36.903324],"type":"Point"}
}