{
  "type": "Feature",
  "properties": {
    "addr:full":"PO Box 10 060 Halfway Bush  Dunedin Otago",
    "addr:housenumber":"po box 10",
    "addr:postcode":"060",
    "iso:country":"NZ",
    "sg:address":"PO Box 10 060 Halfway Bush ",
    "sg:city":"Dunedin",
    "sg:orig_category":"Home And Garden",
    "sg:phone":"+64 3-476 7711",
    "sg:province":"Otago",
    "sg:website":"http://www.yellowpages.co.nz/for/totalcarpet/dp32304.html",
    "wof:name":"Total Carpet Services",
    "wof:placetype":"venue"
},
  "geometry": {"coordinates":[170.46698000000001,-45.854794],"type":"Point"}
}