{
  "type": "Feature",
  "properties": {
    "iso:country":"NZ",
    "sg:address":"54 Queen St ",
    "sg:city":"Blenheim",
    "sg:classifiers":[
        {
            "category":"Sports & Exercise",
            "subcategory":"Golf",
            "type":"Entertainment"
        }
    ],
    "sg:phone":"+64 3-578 8362",
    "sg:province":"Marlborough",
    "sg:tags":[
        "club",
        "equipment",
        "leisure",
        "sports"
    ],
    "wof:name":"Garth's Golf Shop Ltd",
    "wof:placetype":"venue"
},
  "geometry": {"coordinates":[-74.459564,42.468643],"type":"Point"}
}