{
  "type": "Feature",
  "properties": {
    "addr:full":"Dinsdale Library Court Whatawhata Rd Dinsdale  Hamilton Waikato",
    "addr:street":"Court Whatawhata Rd",
    "iso:country":"NZ",
    "sg:address":"Dinsdale Library Court Whatawhata Rd Dinsdale ",
    "sg:city":"Hamilton",
    "sg:classifiers":[
        {
            "category":"Insurance",
            "subcategory":"Health Insurance",
            "type":"Services"
        }
    ],
    "sg:phone":"+64 7-846 0021",
    "sg:province":"Waikato",
    "sg:tags":[
        "beauty",
        "supply"
    ],
    "wof:name":"Absolute Beauty",
    "wof:placetype":"venue"
},
  "geometry": {"coordinates":[175.24191300000001,-37.795715],"type":"Point"}
}