{
  "type": "Feature",
  "properties": {
    "addr:full":"112 Tanner St  Invercargill Southland",
    "addr:housenumber":"112",
    "addr:street":"Tanner St",
    "iso:country":"NZ",
    "sg:address":"112 Tanner St ",
    "sg:city":"Invercargill",
    "sg:orig_category":"Shopping: Retail Stores: Supermarkets",
    "sg:phone":"+64 3-215 9867",
    "sg:province":"Southland",
    "wof:name":"Grasmere Grocery Ltd",
    "wof:placetype":"venue"
},
  "geometry": {"coordinates":[168.33917199999999,-46.382908],"type":"Point"}
}