{
  "type": "Feature",
  "properties": {
    "iso:country":"NZ",
    "sg:address":"54 Beatrice St ",
    "sg:city":"Invercargill",
    "sg:classifiers":[
        {
            "category":"Personal",
            "subcategory":"Massage",
            "type":"Services"
        }
    ],
    "sg:phone":"+64 3-218 8613",
    "sg:province":"Southland",
    "sg:tags":[
        "services",
        "health",
        "-",
        "beauty",
        "fitness"
    ],
    "wof:name":"Massage Therapy Centre",
    "wof:placetype":"venue"
},
  "geometry": {"coordinates":[168.346115,-46.397678],"type":"Point"}
}