{
  "type": "Feature",
  "properties": {
    "iso:country":"NZ",
    "sg:address":"Lambton Sq ",
    "sg:city":"Wellington",
    "sg:orig_category":"Shopping: Engravers",
    "sg:phone":"+64 4-473 0215",
    "sg:province":"Wellington",
    "wof:name":"Mister Minit NZ Ltd",
    "wof:placetype":"venue"
},
  "geometry": {"coordinates":[174.767151,-41.28054],"type":"Point"}
}