{
  "type": "Feature",
  "properties": {
    "iso:country":"NZ",
    "sg:address":"61 Molesworth St ",
    "sg:city":"Wellington",
    "sg:classifiers":[
        {
            "category":"Personal",
            "subcategory":"Shoe Repair & Shine",
            "type":"Services"
        }
    ],
    "sg:phone":"+64 4-473 6763",
    "sg:province":"Wellington",
    "sg:tags":[
        "foot",
        "clothing",
        "fabric",
        "wear"
    ],
    "wof:name":"Molesworth Shoe & Bag Repairs",
    "wof:placetype":"venue"
},
  "geometry": {"coordinates":[174.960373,-41.173477],"type":"Point"}
}