{
  "type": "Feature",
  "properties": {
    "iso:country":"NZ",
    "sg:address":"24 Tarbert St ",
    "sg:city":"Alexandra",
    "sg:classifiers":[
        {
            "category":"Fast Food",
            "type":"Food & Drink"
        }
    ],
    "sg:phone":"+64 3-448 6638",
    "sg:province":"Otago",
    "sg:tags":[
        "wining",
        "dining",
        "takeaway"
    ],
    "wof:name":"Gobble 'N' Go",
    "wof:placetype":"venue"
},
  "geometry": {"coordinates":[-4.582669,55.988441],"type":"Point"}
}