{
  "type": "Feature",
  "properties": {
    "addr:full":"Katere Rd New  Plymouth Taranaki",
    "addr:street":"Katere Rd",
    "iso:country":"NZ",
    "sg:address":"Katere Rd New ",
    "sg:city":"Plymouth",
    "sg:orig_category":"Home And Garden: Gardening: Products",
    "sg:phone":"+64 6-759 2150",
    "sg:province":"Taranaki",
    "sg:website":"http://www.yellowpages.co.nz/for/fbt/dp31104.html",
    "wof:name":"Freight & Bulk Transport Ltd",
    "wof:placetype":"venue"
},
  "geometry": {"coordinates":[-116.81972500000001,43.97221],"type":"Point"}
}