{
  "type": "Feature",
  "properties": {
    "addr:full":"24 Trafford St  Gore Southland",
    "addr:housenumber":"24",
    "addr:street":"Trafford St",
    "iso:country":"NZ",
    "sg:address":"24 Trafford St ",
    "sg:city":"Gore",
    "sg:orig_category":"Industrial: Products: Window Control Gear",
    "sg:phone":"+64 3-208 4737",
    "sg:province":"Southland",
    "wof:name":"Abell Aluminium Ltd",
    "wof:placetype":"venue"
},
  "geometry": {"coordinates":[-95.116547,35.530331],"type":"Point"}
}