{
  "type": "Feature",
  "properties": {
    "addr:full":"PO Box 924  Taupo Waikato",
    "addr:housenumber":"po;924",
    "addr:street":"Box",
    "iso:country":"NZ",
    "sg:address":"PO Box 924 ",
    "sg:city":"Taupo",
    "sg:classifiers":[
        {
            "category":"Home & Garden",
            "subcategory":"Building Materials",
            "type":"Retail Goods"
        }
    ],
    "sg:phone":"+64 7-377 1914",
    "sg:province":"Waikato",
    "sg:tags":[
        "fittings",
        "door",
        "garage"
    ],
    "wof:name":"Garage Doors (Taupo) Ltd",
    "wof:placetype":"venue"
},
  "geometry": {"coordinates":[176.084351,-38.689285],"type":"Point"}
}