{
  "type": "Feature",
  "properties": {
    "iso:country":"NZ",
    "sg:address":"34 Hunter-Brown St ",
    "sg:city":"Wairoa",
    "sg:classifiers":[
        {
            "category":"Wholesale",
            "subcategory":"Medical Equipment & Supplies",
            "type":"Manufacturing & Wholesale Goods"
        }
    ],
    "sg:phone":"+64 6-838 8368",
    "sg:tags":[
        "health",
        "disability",
        "products",
        "beauty",
        "aid"
    ],
    "wof:name":"Te Wairoa Abilities Enterprise",
    "wof:placetype":"venue"
},
  "geometry": {"coordinates":[177.425949,-39.029865],"type":"Point"}
}