{
  "type": "Feature",
  "properties": {
    "iso:country":"NZ",
    "sg:address":"65 Commerce St ",
    "sg:city":"Whakatane",
    "sg:classifiers":[
        {
            "category":"Autos & Motor Vehicles",
            "subcategory":"Automobile Sales",
            "type":"Retail Goods"
        }
    ],
    "sg:phone":"+64 7-308 8279",
    "sg:province":"Bay of Plenty",
    "sg:tags":[
        "leasing",
        "car",
        "-",
        "truck",
        "automotive",
        "new"
    ],
    "wof:name":"Brown Bros Ford",
    "wof:placetype":"venue"
},
  "geometry": {"coordinates":[176.99563599999999,-37.954769],"type":"Point"}
}