{
  "type": "Feature",
  "properties": {
    "addr:full":"Cnr Dickinson St & Broadway  Kaikohe Manawatu-Wanganui",
    "addr:street":"Cnr Dickinson St & Broadway",
    "iso:country":"NZ",
    "sg:address":"Cnr Dickinson St & Broadway ",
    "sg:city":"Kaikohe",
    "sg:classifiers":[
        {
            "category":"Retail",
            "subcategory":"Repair Shop",
            "type":"Services"
        }
    ],
    "sg:phone":"+64 9-401 0175",
    "sg:province":"Manawatu-Wanganui",
    "sg:tags":[
        "clothing",
        "fabric",
        "cleaning"
    ],
    "wof:name":"La Rose Clothing Alterations & Repairs",
    "wof:placetype":"venue"
},
  "geometry": {"coordinates":[173.79710399999999,-35.40649],"type":"Point"}
}