{
  "type": "Feature",
  "properties": {
    "addr:full":"15 Cook Flat Rd Fox  Glacier",
    "addr:housenumber":"15",
    "addr:street":"Cook Flat Rd",
    "iso:country":"NZ",
    "sg:address":"15 Cook Flat Rd Fox ",
    "sg:city":"Glacier",
    "sg:classifiers":[
        {
            "category":"Travel",
            "subcategory":"Hotels & Motels",
            "type":"Entertainment"
        }
    ],
    "sg:phone":"+64 3-751 0140",
    "sg:tags":[
        "lodge",
        "tourism",
        "accommodation"
    ],
    "wof:name":"Rainforest Motel",
    "wof:placetype":"venue"
},
  "geometry": {"coordinates":[170.00836200000001,-43.462543],"type":"Point"}
}