{
  "type": "Feature",
  "properties": {
    "addr:full":"175 Hinemoa St  Rotorua Bay of Plenty",
    "addr:housenumber":"175",
    "addr:street":"Hinemoa St",
    "iso:country":"NZ",
    "sg:address":"175 Hinemoa St ",
    "sg:city":"Rotorua",
    "sg:orig_category":"Home And Garden: Gardening: Products: Garden Supplies",
    "sg:phone":"+64 7-348 1239",
    "sg:province":"Bay of Plenty",
    "wof:name":"Benfields Garden Centre",
    "wof:placetype":"venue"
},
  "geometry": {"coordinates":[176.25767500000001,-38.137829],"type":"Point"}
}