{
  "type": "Feature",
  "properties": {
    "addr:full":"133 Cheyne Rd Pyes Pa  Tauranga Bay of Plenty",
    "addr:housenumber":"133",
    "addr:street":"Cheyne Rd",
    "iso:country":"NZ",
    "sg:address":"133 Cheyne Rd Pyes Pa ",
    "sg:city":"Tauranga",
    "sg:orig_category":"Industrial: Parts: Fasteners - Industrial",
    "sg:phone":"+64 7-543 3806",
    "sg:province":"Bay of Plenty",
    "wof:name":"Reid Engineering Systems",
    "wof:placetype":"venue"
},
  "geometry": {"coordinates":[176.13244599999999,-37.737865],"type":"Point"}
}