{
  "type": "Feature",
  "properties": {
    "iso:country":"NZ",
    "sg:address":"Welcome Bay ",
    "sg:city":"Tauranga",
    "sg:classifiers":[
        {
            "category":"Personal",
            "type":"Services"
        }
    ],
    "sg:phone":"+64 7-544 1980",
    "sg:province":"Bay of Plenty",
    "sg:tags":[
        "services",
        "home",
        "garden",
        "counselling"
    ],
    "wof:name":"Counselling Services",
    "wof:placetype":"venue"
},
  "geometry": {"coordinates":[176.180771,-37.725822],"type":"Point"}
}