{
  "type": "Feature",
  "properties": {
    "iso:country":"NZ",
    "sg:address":"Unit 18 D 125 The Strand Parnell ",
    "sg:city":"Auckland",
    "sg:orig_category":"Clothing And Fabric: Fabric: Textiles",
    "sg:phone":"+64 9-377 5508",
    "sg:province":"Auckland",
    "wof:name":"New Generation International Ltd",
    "wof:placetype":"venue"
},
  "geometry": {"coordinates":[174.786087,-36.85479],"type":"Point"}
}