{
  "type": "Feature",
  "properties": {
    "iso:country":"NZ",
    "sg:address":"R D 3 Rai ",
    "sg:city":"Valley",
    "sg:classifiers":[
        {
            "category":"Farming",
            "subcategory":"Fish & Marine Products",
            "type":"Manufacturing & Wholesale Goods"
        }
    ],
    "sg:phone":"+64 3-576 5096",
    "sg:tags":[
        "-",
        "boat",
        "transport"
    ],
    "wof:name":"Elaine Bay Aquaculture",
    "wof:placetype":"venue"
},
  "geometry": {"coordinates":[173.58137500000001,-41.23312],"type":"Point"}
}