{
  "type": "Feature",
  "properties": {
    "iso:country":"NZ",
    "sg:address":"Ngaio Rd ",
    "sg:city":"Waikanae",
    "sg:orig_category":"Shopping: Retail Stores: Supermarkets",
    "sg:phone":"+64 4-293 5532",
    "sg:province":"Wellington",
    "wof:name":"Woolworths (NZ) Ltd",
    "wof:placetype":"venue"
},
  "geometry": {"coordinates":[175.05758700000001,-40.87534],"type":"Point"}
}