{
  "type": "Feature",
  "properties": {
    "iso:country":"NZ",
    "sg:address":"646 Gt South Rd Penrose ",
    "sg:city":"Auckland",
    "sg:classifiers":[
        {
            "category":"Utilities",
            "subcategory":"Cable",
            "type":"Services"
        }
    ],
    "sg:phone":"+64 9-571 0025",
    "sg:province":"Auckland",
    "sg:tags":[
        "electricity",
        "energy",
        "industrial",
        "utilities",
        "supply"
    ],
    "wof:name":"Empower",
    "wof:placetype":"venue"
},
  "geometry": {"coordinates":[174.810165,-36.911617],"type":"Point"}
}