{
  "type": "Feature",
  "properties": {
    "iso:country":"NZ",
    "sg:address":"18 A McGiffert St Palmerston ",
    "sg:city":"Palmerston North",
    "sg:classifiers":[
        {
            "category":"Retail",
            "subcategory":"Auto Repair",
            "type":"Services"
        }
    ],
    "sg:phone":"+64 6-357 4386",
    "sg:province":"Manawatu-Wanganui",
    "sg:tags":[
        "automotive",
        "panel",
        "servicing",
        "beater"
    ],
    "sg:website":"http://www.yellowpages.co.nz/for/rightpanelbeaters/dp34223.html",
    "wof:name":"Right Panelbeaters",
    "wof:placetype":"venue"
},
  "geometry": {"coordinates":[175.605667,-40.361336],"type":"Point"}
}