{
  "type": "Feature",
  "properties": {
    "iso:country":"NZ",
    "sg:address":"533 Great South Rd Manukau City ",
    "sg:city":"Auckland",
    "sg:classifiers":[
        {
            "category":"Personal",
            "subcategory":"Beauty Salon",
            "type":"Services"
        }
    ],
    "sg:phone":"+64 9-277 4320",
    "sg:province":"Auckland",
    "sg:tags":[
        "artist",
        "health",
        "make-up"
    ],
    "wof:name":"Polmar International Ltd",
    "wof:placetype":"venue"
},
  "geometry": {"coordinates":[174.877258,-36.981209],"type":"Point"}
}