{
  "type": "Feature",
  "properties": {
    "addr:full":"135 Great North Rd Grey Lynn  Auckland Auckland",
    "addr:housenumber":"135",
    "addr:street":"Great North Rd",
    "iso:country":"NZ",
    "sg:address":"135 Great North Rd Grey Lynn ",
    "sg:city":"Auckland",
    "sg:orig_category":"Home And Garden: Accessories: Linen",
    "sg:phone":"+64 9-376 6753",
    "sg:province":"Auckland",
    "wof:name":"The Linen Factory Shop",
    "wof:placetype":"venue"
},
  "geometry": {"coordinates":[174.749359,-36.862328],"type":"Point"}
}