{
  "type": "Feature",
  "properties": {
    "iso:country":"NZ",
    "sg:address":"38 Victoria Rd Devonport ",
    "sg:city":"Auckland",
    "sg:classifiers":[
        {
            "category":"Shopping",
            "subcategory":"Crafts & Fabrics",
            "type":"Retail Goods"
        }
    ],
    "sg:phone":"+64 9-445 9995",
    "sg:province":"Auckland",
    "sg:tags":[
        "sport",
        "art",
        "leisure",
        "hobbies"
    ],
    "sg:website":"http://www.cushlasvillagefabrics.co.nz",
    "wof:name":"Cushla's Village Fabrics",
    "wof:placetype":"venue"
},
  "geometry": {"coordinates":[174.797974,-36.829456],"type":"Point"}
}