{
  "type": "Feature",
  "properties": {
    "addr:full":"8 Racecourse Rd Washdyke  Timaru Canterbury",
    "addr:housenumber":"8",
    "addr:street":"Racecourse Rd",
    "iso:country":"NZ",
    "sg:address":"8 Racecourse Rd Washdyke ",
    "sg:city":"Timaru",
    "sg:classifiers":[
        {
            "category":"Autos & Motor Vehicles",
            "subcategory":"Automobile Sales",
            "type":"Retail Goods"
        }
    ],
    "sg:phone":"+64 3-688 2244",
    "sg:province":"Canterbury",
    "sg:tags":[
        "car",
        "-used",
        "leasing",
        "truck",
        "automotive"
    ],
    "wof:name":"Washdyke Autos",
    "wof:placetype":"venue"
},
  "geometry": {"coordinates":[171.237503,-44.354263],"type":"Point"}
}