{
  "type": "Feature",
  "properties": {
    "iso:country":"NZ",
    "sg:address":"27 Seaview Rd Seaview ",
    "sg:city":"Wellington",
    "sg:classifiers":[
        {
            "category":"Home & Garden",
            "subcategory":"Furniture",
            "type":"Retail Goods"
        }
    ],
    "sg:phone":"+64 4-566 5836",
    "sg:province":"Wellington",
    "sg:tags":[
        "furniture/furnishings",
        "designer"
    ],
    "wof:name":"Furnace Design Company Limited",
    "wof:placetype":"venue"
},
  "geometry": {"coordinates":[174.905945,-41.236458],"type":"Point"}
}