{
  "type": "Feature",
  "properties": {
    "iso:country":"NZ",
    "sg:address":"Katere Rd New ",
    "sg:city":"Plymouth",
    "sg:orig_category":"Home And Garden: Gardening: Services: Landscaping",
    "sg:phone":"+64 6-758 4400",
    "sg:province":"Taranaki",
    "wof:name":"Sam Sutherland Designer Construction",
    "wof:placetype":"venue"
},
  "geometry": {"coordinates":[174.117569,-39.050549],"type":"Point"}
}