{
  "type": "Feature",
  "properties": {
    "iso:country":"NZ",
    "sg:address":"The Cairn Kuriwao R D 1 ",
    "sg:city":"Clinton",
    "sg:orig_category":"Farming: Agriculture: Agricultural Contractors",
    "sg:phone":"+64 3-415 7299",
    "wof:name":"Lundy Contracting",
    "wof:placetype":"venue"
},
  "geometry": {"coordinates":[169.380615,-46.199898],"type":"Point"}
}