{
  "type": "Feature",
  "properties": {
    "addr:full":"The Cairn Kuriwao R D 1  Clinton",
    "addr:housenumber":"1",
    "addr:street":"R D",
    "iso:country":"NZ",
    "sg:address":"The Cairn Kuriwao R D 1 ",
    "sg:city":"Clinton",
    "sg:orig_category":"Farming: Agriculture: Agricultural Contractors",
    "sg:phone":"+64 3-415 7299",
    "wof:name":"Lundy Contracting",
    "wof:placetype":"venue"
},
  "geometry": {"coordinates":[169.38061500000001,-46.199898],"type":"Point"}
}