{
  "type": "Feature",
  "properties": {
    "iso:country":"NZ",
    "sg:address":"300 Broadway Ave Palmerston ",
    "sg:city":"Palmerston North",
    "sg:classifiers":[
        {
            "category":"Retail",
            "subcategory":"Auto Repair",
            "type":"Services"
        }
    ],
    "sg:phone":"+64 6-357 2600",
    "sg:province":"Manawatu-Wanganui",
    "sg:tags":[
        "automotive",
        "electric",
        "servicing"
    ],
    "wof:name":"Broadway Auto Electrical",
    "wof:placetype":"venue"
},
  "geometry": {"coordinates":[175.62454199999999,-40.348949],"type":"Point"}
}