{
  "type": "Feature",
  "properties": {
    "addr:full":"406 Tomoana Rd  Hastings Hawke's Bay",
    "addr:housenumber":"406",
    "addr:street":"Tomoana Rd",
    "iso:country":"NZ",
    "sg:address":"406 Tomoana Rd ",
    "sg:city":"Hastings",
    "sg:orig_category":"Home And Garden: Furniture/Furnishings: Curtains",
    "sg:phone":"+64 6-876 9308",
    "sg:province":"Hawke's Bay",
    "wof:name":"On Site Curtain & Fabric Cleaning",
    "wof:placetype":"venue"
},
  "geometry": {"coordinates":[176.841354,-39.633884],"type":"Point"}
}