{
  "type": "Feature",
  "properties": {
    "iso:country":"NZ",
    "sg:address":"1432 Korokipo Rd Napier ",
    "sg:city":"RD3",
    "sg:orig_category":"Farming: Agriculture: Agricultural Contractors",
    "sg:phone":"+64 6-844 6771",
    "wof:name":"Wheatley Basil",
    "wof:placetype":"venue"
},
  "geometry": {"coordinates":[-80.588562,38.790821],"type":"Point"}
}