{
  "type": "Feature",
  "properties": {
    "iso:country":"NZ",
    "sg:address":"10 Lincoln Rd Spreydon ",
    "sg:city":"Christchurch",
    "sg:classifiers":[
        {
            "category":"Health Services",
            "subcategory":"Dentist",
            "type":"Services"
        }
    ],
    "sg:phone":"+64 3-338 8210",
    "sg:province":"Canterbury",
    "sg:tags":[
        "dental",
        "beauty"
    ],
    "wof:name":"A.H. York BDS Dental Surgeon",
    "wof:placetype":"venue"
},
  "geometry": {"coordinates":[172.616211,-43.553249],"type":"Point"}
}