{
  "type": "Feature",
  "properties": {
    "addr:full":"529 Glenfield Rd Glenfield  Auckland Auckland",
    "addr:housenumber":"529",
    "addr:street":"Glenfield Rd",
    "iso:country":"NZ",
    "sg:address":"529 Glenfield Rd Glenfield ",
    "sg:city":"Auckland",
    "sg:orig_category":"Home And Garden: Children: Child Related: Children'S Entertainment",
    "sg:phone":"+64 9-441 7446",
    "sg:province":"Auckland",
    "wof:name":"Carmel's Face Painting",
    "wof:placetype":"venue"
},
  "geometry": {"coordinates":[174.721237,-36.773548],"type":"Point"}
}