{
  "type": "Feature",
  "properties": {
    "addr:full":"PO Box 34743 Birkenhead  Auckland Auckland",
    "addr:housenumber":"po box",
    "addr:postcode":"34743",
    "iso:country":"NZ",
    "sg:address":"PO Box 34743 Birkenhead ",
    "sg:city":"Auckland",
    "sg:classifiers":[
        {
            "category":"Manufacturing",
            "subcategory":"Textiles",
            "type":"Manufacturing & Wholesale Goods"
        }
    ],
    "sg:phone":"+64 9-418 1461",
    "sg:province":"Auckland",
    "sg:tags":[
        "clothing",
        "fabric",
        "manufacturer"
    ],
    "wof:name":"North Harbour Apparel Ltd",
    "wof:placetype":"venue"
},
  "geometry": {"coordinates":[174.734467,-36.818214],"type":"Point"}
}