{
  "type": "Feature",
  "properties": {
    "iso:country":"NZ",
    "sg:address":"229 High St Lower ",
    "sg:city":"Hutt",
    "sg:classifiers":[
        {
            "category":"Retail",
            "subcategory":"Laundry & Dry Cleaning",
            "type":"Services"
        }
    ],
    "sg:phone":"+64 4-569 9734",
    "sg:province":"Wellington",
    "sg:tags":[
        "repair",
        "clothing",
        "fabric",
        "cleaner"
    ],
    "wof:name":"Williams 55 Minute Dry Cleaning Ltd",
    "wof:placetype":"venue"
},
  "geometry": {"coordinates":[174.90400700000001,-41.208561],"type":"Point"}
}