{
  "type": "Feature",
  "properties": {
    "addr:full":"Pioneer Hwy Palmerston  Palmerston North Manawatu-Wanganui",
    "addr:street":"Pioneer Hwy",
    "iso:country":"NZ",
    "sg:address":"Pioneer Hwy Palmerston ",
    "sg:city":"Palmerston North",
    "sg:classifiers":[
        {
            "category":"Travel",
            "subcategory":"Hotels & Motels",
            "type":"Entertainment"
        }
    ],
    "sg:phone":"+64 6-354 5181",
    "sg:province":"Manawatu-Wanganui",
    "sg:tags":[
        "tavern",
        "tourism",
        "accommodation"
    ],
    "wof:name":"Awapuni Motor-Hotel (Kia Toa Hotels Limited)",
    "wof:placetype":"venue"
},
  "geometry": {"coordinates":[175.588425,-40.366501],"type":"Point"}
}