{
  "type": "Feature",
  "properties": {
    "addr:full":"421 Mt Eden Rd Mt Eden  Auckland Auckland",
    "addr:housenumber":"421",
    "addr:street":"Mt Eden Rd",
    "iso:country":"NZ",
    "sg:address":"421 Mt Eden Rd Mt Eden ",
    "sg:city":"Auckland",
    "sg:classifiers":[
        {
            "category":"Health Services",
            "subcategory":"Health Practitioner",
            "type":"Services"
        }
    ],
    "sg:phone":"+64 9-630 3168",
    "sg:province":"Auckland",
    "sg:tags":[
        "services",
        "beauty",
        "acupuncturists"
    ],
    "wof:name":"Mt Eden Chinese Medical Centre",
    "wof:placetype":"venue"
},
  "geometry": {"coordinates":[174.76191700000001,-36.881493],"type":"Point"}
}