{
  "type": "Feature",
  "properties": {
    "addr:full":"23 Napier Rd Havelock  Palmerston North Manawatu-Wanganui",
    "addr:housenumber":"23",
    "addr:street":"Napier Rd",
    "iso:country":"NZ",
    "sg:address":"23 Napier Rd Havelock ",
    "sg:city":"Palmerston North",
    "sg:classifiers":[
        {
            "category":"Coffee & Tea",
            "type":"Food & Drink"
        }
    ],
    "sg:phone":"+64 6-877 1113",
    "sg:province":"Manawatu-Wanganui",
    "sg:tags":[
        "merchant"
    ],
    "wof:name":"Hawthorne Coffee Roasters Ltd",
    "wof:placetype":"venue"
},
  "geometry": {"coordinates":[176.878952,-39.66827],"type":"Point"}
}