{
  "type": "Feature",
  "properties": {
    "addr:full":"32 Point Wells Rd Point Wells  Warkworth Auckland",
    "addr:housenumber":"32",
    "addr:street":"Point Wells Rd",
    "iso:country":"NZ",
    "sg:address":"32 Point Wells Rd Point Wells ",
    "sg:city":"Warkworth",
    "sg:orig_category":"Home And Garden: Furniture/Furnishings: Cabinetmakers",
    "sg:phone":"+64 9-422 9320",
    "sg:province":"Auckland",
    "wof:name":"AZZU Woodworking",
    "wof:placetype":"venue"
},
  "geometry": {"coordinates":[174.75495900000001,-36.329411],"type":"Point"}
}