{
  "type": "Feature",
  "properties": {
    "iso:country":"NZ",
    "sg:address":"32 Point Wells Rd Point Wells ",
    "sg:city":"Warkworth",
    "sg:orig_category":"Home And Garden: Furniture/Furnishings: Cabinetmakers",
    "sg:phone":"+64 9-422 9320",
    "sg:province":"Auckland",
    "wof:name":"AZZU Woodworking",
    "wof:placetype":"venue"
},
  "geometry": {"coordinates":[174.754959,-36.329411],"type":"Point"}
}