{
  "type": "Feature",
  "properties": {
    "addr:full":"418 Titirangi Rd Titirangi  Auckland Auckland",
    "addr:housenumber":"418",
    "addr:street":"Titirangi Rd",
    "iso:country":"NZ",
    "sg:address":"418 Titirangi Rd Titirangi ",
    "sg:city":"Auckland",
    "sg:orig_category":"Sports And Leisure: Arts: Theatres",
    "sg:phone":"+64 9-818 6645",
    "sg:province":"Auckland",
    "wof:name":"Titirangi Drama Inc",
    "wof:placetype":"venue"
},
  "geometry": {"coordinates":[174.655136,-36.938313],"type":"Point"}
}