{
  "type": "Feature",
  "properties": {
    "iso:country":"NZ",
    "sg:address":"AMP Bldg 20 Seaview Rd Paraparaumu Beach ",
    "sg:city":"Paraparaumu",
    "sg:orig_category":"Shopping: Accessories: Lingerie - Retail",
    "sg:phone":"+64 4-902 4272",
    "sg:province":"Wellington",
    "wof:name":"Undercover Secrets",
    "wof:placetype":"venue"
},
  "geometry": {"coordinates":[174.98335299999999,-40.890739],"type":"Point"}
}