{
  "type": "Feature",
  "properties": {
    "addr:full":"4 Fraser St  Paeroa",
    "addr:housenumber":"4",
    "addr:street":"Fraser St",
    "iso:country":"NZ",
    "sg:address":"4 Fraser St ",
    "sg:city":"Paeroa",
    "sg:classifiers":[
        {
            "category":"Restaurant",
            "type":"Food & Drink"
        }
    ],
    "sg:phone":"+64 800 732 9333",
    "sg:tags":[
        "fruit",
        "veges"
    ],
    "wof:name":"Ocean Organics Ltd",
    "wof:placetype":"venue"
},
  "geometry": {"coordinates":[175.675522,-37.384644],"type":"Point"}
}