{
  "type": "Feature",
  "properties": {
    "iso:country":"NZ",
    "sg:address":"Palmerston ",
    "sg:city":"Palmerston North",
    "sg:classifiers":[
        {
            "category":"Communications",
            "subcategory":"Television Station",
            "type":"Services"
        }
    ],
    "sg:phone":"+64 25443255",
    "sg:province":"Manawatu-Wanganui",
    "sg:tags":[
        "broadcasting"
    ],
    "wof:name":"Pro Audio Services",
    "wof:placetype":"venue"
},
  "geometry": {"coordinates":[175.611481,-40.357418],"type":"Point"}
}