{
  "type": "Feature",
  "properties": {
    "addr:full":"49 Cryers Rd East Tamaki  Auckland Auckland",
    "addr:housenumber":"49",
    "addr:street":"Cryers Rd",
    "iso:country":"NZ",
    "sg:address":"49 Cryers Rd East Tamaki ",
    "sg:city":"Auckland",
    "sg:classifiers":[
        {
            "category":"Manufacturing",
            "subcategory":"Food",
            "type":"Manufacturing & Wholesale Goods"
        }
    ],
    "sg:phone":"+64 9-273 3879",
    "sg:province":"Auckland",
    "sg:tags":[
        "drink",
        "-",
        "manufacturer"
    ],
    "wof:name":"Food Partners Ltd",
    "wof:placetype":"venue"
},
  "geometry": {"coordinates":[174.88746599999999,-36.933331],"type":"Point"}
}