{
  "type": "Feature",
  "properties": {
    "addr:full":"491 Tremaine Ave Palmerston  Palmerston North Manawatu-Wanganui",
    "addr:housenumber":"491",
    "addr:street":"Tremaine Ave",
    "iso:country":"NZ",
    "sg:address":"491 Tremaine Ave Palmerston ",
    "sg:city":"Palmerston North",
    "sg:classifiers":[
        {
            "category":"Sports & Exercise",
            "subcategory":"Sports Center",
            "type":"Entertainment"
        }
    ],
    "sg:phone":"+64 274 994 093",
    "sg:province":"Manawatu-Wanganui",
    "sg:tags":[
        "sporting",
        "sports",
        "-",
        "leisure",
        "facility"
    ],
    "wof:name":"Sports Central",
    "wof:placetype":"venue"
},
  "geometry": {"coordinates":[175.593842,-40.346676],"type":"Point"}
}