{
  "type": "Feature",
  "properties": {
    "addr:full":"100 Portage Rd Otahuhu  Auckland Auckland",
    "addr:housenumber":"100",
    "addr:street":"Portage Rd",
    "iso:country":"NZ",
    "sg:address":"100 Portage Rd Otahuhu ",
    "sg:city":"Auckland",
    "sg:classifiers":[
        {
            "category":"Retail",
            "subcategory":"Storage",
            "type":"Services"
        }
    ],
    "sg:phone":"+64 9-270 2045",
    "sg:province":"Auckland",
    "wof:name":"Royal Wolf Trading NZ Ltd",
    "wof:placetype":"venue"
},
  "geometry": {"coordinates":[174.834518,-36.936714],"type":"Point"}
}