{
  "type": "Feature",
  "properties": {
    "addr:full":"100 Leven St  Invercargill Southland",
    "addr:housenumber":"100",
    "addr:street":"Leven St",
    "iso:country":"NZ",
    "sg:address":"100 Leven St ",
    "sg:city":"Invercargill",
    "sg:classifiers":[
        {
            "category":"Shopping",
            "subcategory":"Bicycles & Sporting Goods",
            "type":"Retail Goods"
        }
    ],
    "sg:phone":"+64 3-211 0010",
    "sg:province":"Southland",
    "sg:tags":[
        "cycle",
        "sport",
        "sale",
        "retailers",
        "cycles"
    ],
    "wof:name":"Smiths City Ltd",
    "wof:placetype":"venue"
},
  "geometry": {"coordinates":[168.345505,-46.407055],"type":"Point"}
}