{
  "type": "Feature",
  "properties": {
    "iso:country":"NZ",
    "sg:address":"68 Koromiko St Judea ",
    "sg:city":"Tauranga",
    "sg:classifiers":[
        {
            "category":"Food & Beverages",
            "subcategory":"Groceries & Convenience Stores",
            "type":"Retail Goods"
        }
    ],
    "sg:phone":"+64 7-578 0246",
    "sg:province":"Bay of Plenty",
    "sg:tags":[
        "foodstuff",
        "drink",
        "-"
    ],
    "wof:name":"Viking Distributors",
    "wof:placetype":"venue"
},
  "geometry": {"coordinates":[176.14236500000001,-37.695297],"type":"Point"}
}