{
  "type": "Feature",
  "properties": {
    "addr:full":"135 Cuba St Te Aro  Wellington Wellington",
    "addr:housenumber":"135",
    "addr:street":"Cuba St;Wellington",
    "iso:country":"NZ",
    "sg:address":"135 Cuba St Te Aro ",
    "sg:city":"Wellington",
    "sg:classifiers":[
        {
            "category":"Professional",
            "type":"Services"
        }
    ],
    "sg:phone":"+64 4-802 4144",
    "sg:province":"Wellington",
    "sg:tags":[
        "function",
        "entertainment",
        "leisure",
        "planning",
        "party",
        "sport"
    ],
    "wof:name":"Tulsi Contemporary Indian Cuisine",
    "wof:placetype":"venue"
},
  "geometry": {"coordinates":[174.77598599999999,-41.293159],"type":"Point"}
}