{
  "type": "Feature",
  "properties": {
    "addr:full":"PO Box 720 New  Plymouth Taranaki",
    "addr:housenumber":"po;720",
    "addr:street":"Box",
    "iso:country":"NZ",
    "sg:address":"PO Box 720 New ",
    "sg:city":"Plymouth",
    "sg:classifiers":[
        {
            "category":"Sports & Exercise",
            "subcategory":"Ski Slope",
            "type":"Entertainment"
        }
    ],
    "sg:phone":"+64 6-755 2426",
    "sg:province":"Taranaki",
    "sg:tags":[
        "skydiving",
        "parachuting",
        "aerial",
        "leisure",
        "sports"
    ],
    "wof:name":"Skydive Taranaki",
    "wof:placetype":"venue"
},
  "geometry": {"coordinates":[-97.026207,40.262596],"type":"Point"}
}