{
  "type": "Feature",
  "properties": {
    "iso:country":"NZ",
    "sg:address":"18-20 Bell Ave Mt Wellington ",
    "sg:city":"Auckland",
    "sg:orig_category":"Transport: Transportation: Freight",
    "sg:phone":"+64 9-250 0800",
    "sg:province":"Auckland",
    "wof:name":"Peter Baker Transport Limited",
    "wof:placetype":"venue"
},
  "geometry": {"coordinates":[174.832458,-36.931377],"type":"Point"}
}