{
  "type": "Feature",
  "properties": {
    "addr:full":"319 Remuera Rd Remuera  Auckland Auckland",
    "addr:housenumber":"319",
    "addr:street":"Remuera Rd",
    "iso:country":"NZ",
    "sg:address":"319 Remuera Rd Remuera ",
    "sg:city":"Auckland",
    "sg:orig_category":"Health And Beauty: Beauty: Hairdressers",
    "sg:phone":"+64 9-522 1079",
    "sg:province":"Auckland",
    "wof:name":"War Hair Design",
    "wof:placetype":"venue"
},
  "geometry": {"coordinates":[174.79628,-36.880684],"type":"Point"}
}