{
  "type": "Feature",
  "properties": {
    "iso:country":"NZ",
    "sg:address":"PO Box 34-214 Birkenhead ",
    "sg:city":"Auckland",
    "sg:orig_category":"Home And Garden",
    "sg:phone":"+64 9-480 2197",
    "sg:province":"Auckland",
    "sg:website":"http://www.yellowpages.co.nz/for/johnstreeterpools/dp26583.html",
    "wof:name":"John Streeter Pool Construction Ltd",
    "wof:placetype":"venue"
},
  "geometry": {"coordinates":[174.770416,-36.884109],"type":"Point"}
}