{
  "type": "Feature",
  "properties": {
    "addr:full":"cnr Church & Selwyn Sts Onehunga  Auckland Auckland",
    "addr:housenumber":"cnr",
    "addr:street":"&",
    "iso:country":"NZ",
    "sg:address":"cnr Church & Selwyn Sts Onehunga ",
    "sg:city":"Auckland",
    "sg:orig_category":"Shopping: Retail Stores: Supermarkets",
    "sg:phone":"+64 9-634 3689",
    "sg:province":"Auckland",
    "wof:name":"Foodtown Supermarkets",
    "wof:placetype":"venue"
},
  "geometry": {"coordinates":[174.78533899999999,-36.922909],"type":"Point"}
}