{
  "type": "Feature",
  "properties": {
    "addr:full":"500 Andersons Bay Rd  Dunedin Otago",
    "addr:housenumber":"500",
    "addr:street":"Andersons Bay Rd",
    "iso:country":"NZ",
    "sg:address":"500 Andersons Bay Rd ",
    "sg:city":"Dunedin",
    "sg:classifiers":[
        {
            "category":"Wholesale",
            "subcategory":"Auto Parts",
            "type":"Manufacturing & Wholesale Goods"
        }
    ],
    "sg:phone":"+64 3-455 5594",
    "sg:province":"Otago",
    "sg:tags":[
        "automotive",
        "supplies"
    ],
    "sg:website":"http://www.cooke.toyota.co.nz",
    "wof:name":"Cooke Howlison Toyota",
    "wof:placetype":"venue"
},
  "geometry": {"coordinates":[170.50737000000001,-45.895721],"type":"Point"}
}