{
  "type": "Feature",
  "properties": {
    "iso:country":"NZ",
    "sg:address":"2nd Floor 14 Vulcan La Auckland Central ",
    "sg:city":"Auckland",
    "sg:classifiers":[
        {
            "category":"Arts & Performance",
            "subcategory":"Art Gallery",
            "type":"Entertainment"
        }
    ],
    "sg:phone":"+64 9-357 3512",
    "sg:province":"Auckland",
    "sg:tags":[
        "arts",
        "sport",
        "leisure"
    ],
    "wof:name":"McPherson Gallery",
    "wof:placetype":"venue"
},
  "geometry": {"coordinates":[174.76663199999999,-36.847088],"type":"Point"}
}