{
  "type": "Feature",
  "properties": {
    "iso:country":"NZ",
    "sg:address":"244 Queen St Richmond ",
    "sg:city":"Nelson",
    "sg:classifiers":[
        {
            "category":"Bars & Pubs",
            "subcategory":"Wine Bar",
            "type":"Food & Drink"
        }
    ],
    "sg:phone":"+64 3-544 9244",
    "sg:province":"Nelson",
    "sg:tags":[
        "wining",
        "dining"
    ],
    "wof:name":"Cafe 244",
    "wof:placetype":"venue"
},
  "geometry": {"coordinates":[-121.765488,39.553471],"type":"Point"}
}