{
  "type": "Feature",
  "properties": {
    "addr:full":"22A Shamrock Dve Kumeu  Auckland Auckland",
    "addr:housenumber":"22a;kumeu",
    "addr:street":"Shamrock Dve",
    "iso:country":"NZ",
    "sg:address":"22A Shamrock Dve Kumeu ",
    "sg:city":"Auckland",
    "sg:classifiers":[
        {
            "category":"Wholesale",
            "subcategory":"Auto Parts",
            "type":"Manufacturing & Wholesale Goods"
        }
    ],
    "sg:phone":"+64 9-412 7458",
    "sg:province":"Auckland",
    "sg:tags":[
        "automotive",
        "supplies"
    ],
    "wof:name":"Kumeu Mufflers 1996 Ltd",
    "wof:placetype":"venue"
},
  "geometry": {"coordinates":[174.56019599999999,-36.777271],"type":"Point"}
}