{
  "type": "Feature",
  "properties": {
    "addr:full":"54 Commercial Rd  Helensville Auckland",
    "addr:housenumber":"54",
    "addr:street":"Commercial Rd",
    "iso:country":"NZ",
    "sg:address":"54 Commercial Rd ",
    "sg:city":"Helensville",
    "sg:classifiers":[
        {
            "category":"Food & Beverages",
            "subcategory":"Meat & Fish",
            "type":"Retail Goods"
        }
    ],
    "sg:phone":"+64 9-420 8354",
    "sg:province":"Auckland",
    "sg:tags":[
        "drink"
    ],
    "wof:name":"The Traditional Butcher Of Helensville",
    "wof:placetype":"venue"
},
  "geometry": {"coordinates":[174.45043899999999,-36.676758],"type":"Point"}
}