{
  "type": "Feature",
  "properties": {
    "iso:country":"NZ",
    "sg:address":"Level 2 40 Mt Eden Rd Mt Eden ",
    "sg:city":"Auckland",
    "sg:classifiers":[
        {
            "category":"Autos & Motor Vehicles",
            "subcategory":"Automobile Sales",
            "type":"Retail Goods"
        }
    ],
    "sg:phone":"+64 9-623 3108",
    "sg:province":"Auckland",
    "sg:tags":[
        "car",
        "management",
        "leasing",
        "fleet",
        "automotive"
    ],
    "wof:name":"Lease Car Limited",
    "wof:placetype":"venue"
},
  "geometry": {"coordinates":[174.760727,-36.868927],"type":"Point"}
}