{
  "type": "Feature",
  "properties": {
    "iso:country":"NZ",
    "sg:address":"PO Box 9009 Newmarket ",
    "sg:city":"Auckland",
    "sg:orig_category":"Industrial: Parts: Pipes, Tubes And Cabling: Pipes",
    "sg:phone":"+64 9-309 0127",
    "sg:province":"Auckland",
    "wof:name":"Franks Pipe & Valve Fitters",
    "wof:placetype":"venue"
},
  "geometry": {"coordinates":[174.77375799999999,-36.867878],"type":"Point"}
}