{
  "type": "Feature",
  "properties": {
    "iso:country":"NZ",
    "sg:address":"Vickerman St Grovetown ",
    "sg:city":"Blenheim",
    "sg:classifiers":[
        {
            "category":"Manufacturing",
            "subcategory":"Food",
            "type":"Manufacturing & Wholesale Goods"
        }
    ],
    "sg:phone":"+64 3-577 8547",
    "sg:province":"Marlborough",
    "sg:tags":[
        "processing",
        "drink"
    ],
    "wof:name":"New Zealand Garlic Company Limited",
    "wof:placetype":"venue"
},
  "geometry": {"coordinates":[173.968903,-41.481792],"type":"Point"}
}