{
  "type": "Feature",
  "properties": {
    "iso:country":"NZ",
    "sg:address":"Jed St ",
    "sg:city":"Invercargill",
    "sg:classifiers":[
        {
            "category":"Health Services",
            "subcategory":"Dentist",
            "type":"Services"
        }
    ],
    "sg:phone":"+64 3-218 8090",
    "sg:province":"Southland",
    "sg:tags":[
        "dental",
        "clinic",
        "beauty"
    ],
    "wof:name":"Middle School Dental Clinic",
    "wof:placetype":"venue"
},
  "geometry": {"coordinates":[168.35687300000001,-46.408043],"type":"Point"}
}