{
  "type": "Feature",
  "properties": {
    "addr:full":"258 Kawiu Rd  Levin Manawatu-Wanganui",
    "addr:housenumber":"258",
    "addr:street":"Kawiu Rd",
    "iso:country":"NZ",
    "sg:address":"258 Kawiu Rd ",
    "sg:city":"Levin",
    "sg:orig_category":"Home And Garden: General: Handyman'S Services",
    "sg:phone":"+64 6-368 1757",
    "sg:province":"Manawatu-Wanganui",
    "wof:name":"Xtreme Property Care",
    "wof:placetype":"venue"
},
  "geometry": {"coordinates":[175.27989199999999,-40.608459],"type":"Point"}
}