{
  "type": "Feature",
  "properties": {
    "addr:full":"2/82 Hinemoa St  Rotorua Bay of Plenty",
    "addr:housenumber":"2 / 82",
    "addr:street":"Hinemoa St",
    "iso:country":"NZ",
    "sg:address":"2/82 Hinemoa St ",
    "sg:city":"Rotorua",
    "sg:orig_category":"Clothing And Fabric: Clothing: Jeans",
    "sg:phone":"+64 7-349 1700",
    "sg:province":"Bay of Plenty",
    "wof:name":"Jeans West Corporation",
    "wof:placetype":"venue"
},
  "geometry": {"coordinates":[176.25767500000001,-38.137829],"type":"Point"}
}