{
  "type": "Feature",
  "properties": {
    "iso:country":"NZ",
    "sg:address":"cnr Chapel & Marsh Sts ",
    "sg:city":"Tauranga",
    "sg:orig_category":"Automotive: General Services: Service Stations",
    "sg:phone":"+64 7-571 4650",
    "sg:province":"Bay of Plenty",
    "wof:name":"BP Oil",
    "wof:placetype":"venue"
},
  "geometry": {"coordinates":[176.14476,-37.703152],"type":"Point"}
}