{
  "type": "Feature",
  "properties": {
    "addr:full":"91 A Dee St  Invercargill Southland",
    "addr:housenumber":"91",
    "addr:street":"A Dee St",
    "iso:country":"NZ",
    "sg:address":"91 A Dee St ",
    "sg:city":"Invercargill",
    "sg:classifiers":[
        {
            "category":"Shopping",
            "subcategory":"Gifts & Souvenirs",
            "type":"Retail Goods"
        }
    ],
    "sg:phone":"+64 3-214 3945",
    "sg:province":"Southland",
    "sg:tags":[
        "shop",
        "gifts",
        "supplier"
    ],
    "wof:name":"Accent Interiors",
    "wof:placetype":"venue"
},
  "geometry": {"coordinates":[168.34732099999999,-46.392628],"type":"Point"}
}