{
  "type": "Feature",
  "properties": {
    "iso:country":"NZ",
    "sg:address":"Railway Rd ",
    "sg:city":"Whangarei",
    "sg:orig_category":"Transport: Land: Taxis",
    "sg:phone":"+64 9-438 9933",
    "sg:province":"Northland",
    "wof:name":"Phoenix Cabs",
    "wof:placetype":"venue"
},
  "geometry": {"coordinates":[174.322693,-35.730473],"type":"Point"}
}