{
  "type": "Feature",
  "properties": {
    "addr:full":"Strand Arcade 233 Queen St Auckland Central  Auckland Auckland",
    "addr:housenumber":"233",
    "addr:street":"Strand;Queen St",
    "iso:country":"NZ",
    "sg:address":"Strand Arcade 233 Queen St Auckland Central ",
    "sg:city":"Auckland",
    "sg:classifiers":[
        {
            "category":"Personal",
            "subcategory":"Shoe Repair & Shine",
            "type":"Services"
        }
    ],
    "sg:phone":"+64 9-366 6870",
    "sg:province":"Auckland",
    "sg:tags":[
        "foot",
        "clothing",
        "fabric",
        "wear"
    ],
    "wof:name":"The Cobblers In",
    "wof:placetype":"venue"
},
  "geometry": {"coordinates":[174.76454200000001,-36.848358],"type":"Point"}
}