{
  "type": "Feature",
  "properties": {
    "addr:full":"120 Bank St  Whangarei Northland",
    "addr:housenumber":"120",
    "addr:street":"Bank St",
    "iso:country":"NZ",
    "sg:address":"120 Bank St ",
    "sg:city":"Whangarei",
    "sg:orig_category":"Shopping: Sports Retailers: Sports Goods: Sporting Goods",
    "sg:phone":"+64 9-430 2280",
    "sg:province":"Northland",
    "wof:name":"Sportsworld Society Ltd",
    "wof:placetype":"venue"
},
  "geometry": {"coordinates":[174.32089199999999,-35.720989],"type":"Point"}
}