{
  "type": "Feature",
  "properties": {
    "iso:country":"NZ",
    "sg:address":"120 Bank St ",
    "sg:city":"Whangarei",
    "sg:orig_category":"Shopping: Sports Retailers: Sports Goods: Sporting Goods",
    "sg:phone":"+64 9-430 2280",
    "sg:province":"Northland",
    "wof:name":"Sportsworld Society Ltd",
    "wof:placetype":"venue"
},
  "geometry": {"coordinates":[174.320892,-35.720989],"type":"Point"}
}