{
  "type": "Feature",
  "properties": {
    "iso:country":"NZ",
    "sg:address":"25 Toop St Seaview Lower ",
    "sg:city":"Hutt",
    "sg:orig_category":"Transport: Transportation: Carriers",
    "sg:phone":"+64 4-568 8881",
    "sg:province":"Wellington",
    "wof:name":"Inter-Freight Ltd",
    "wof:placetype":"venue"
},
  "geometry": {"coordinates":[174.90379300000001,-41.246132],"type":"Point"}
}