{
  "type": "Feature",
  "properties": {
    "addr:full":"4 Exploration Way Whitby  Wellington Wellington",
    "addr:housenumber":"4",
    "addr:street":"Exploration Way",
    "iso:country":"NZ",
    "sg:address":"4 Exploration Way Whitby ",
    "sg:city":"Wellington",
    "sg:classifiers":[
        {
            "category":"Professional",
            "subcategory":"Art Services",
            "type":"Services"
        }
    ],
    "sg:phone":"+64 4-234 7351",
    "sg:province":"Wellington",
    "sg:tags":[
        "picture",
        "arts",
        "sport",
        "framing",
        "leisure"
    ],
    "wof:name":"Mayfair Picture Framers",
    "wof:placetype":"venue"
},
  "geometry": {"coordinates":[174.893158,-41.119415],"type":"Point"}
}