{
  "type": "Feature",
  "properties": {
    "addr:full":"63 Kerikeri Rd  Kerikeri Northland",
    "addr:housenumber":"63",
    "addr:street":"Kerikeri Rd",
    "iso:country":"NZ",
    "sg:address":"63 Kerikeri Rd ",
    "sg:city":"Kerikeri",
    "sg:orig_category":"Clothing And Fabric: Clothing: Dressmakers",
    "sg:phone":"+64 9-407 7697",
    "sg:province":"Northland",
    "wof:name":"Ace Dress Making & Alterations",
    "wof:placetype":"venue"
},
  "geometry": {"coordinates":[173.943848,-35.233288],"type":"Point"}
}