{
  "type": "Feature",
  "properties": {
    "addr:full":"Station Rd Matamata NthRD  2",
    "addr:housenumber":"2",
    "addr:street":"Station Rd;Nthrd",
    "iso:country":"NZ",
    "sg:address":"Station Rd Matamata NthRD ",
    "sg:city":"2",
    "sg:classifiers":[
        {
            "category":"Travel",
            "subcategory":"Bed & Breakfast",
            "type":"Entertainment"
        }
    ],
    "sg:phone":"+64 7-888 7424",
    "sg:tags":[
        "tourism",
        "accommodation"
    ],
    "wof:name":"Early Century Farmhouse",
    "wof:placetype":"venue"
},
  "geometry": {"coordinates":[175.77354399999999,-37.81176],"type":"Point"}
}