{
  "type": "Feature",
  "properties": {
    "addr:full":"43 Moore St Howick  Auckland Auckland",
    "addr:housenumber":"43",
    "addr:street":"Moore St",
    "iso:country":"NZ",
    "sg:address":"43 Moore St Howick ",
    "sg:city":"Auckland",
    "sg:orig_category":"Health And Beauty: Specialists: Podiatrists",
    "sg:phone":"+64 9-537 0923",
    "sg:province":"Auckland",
    "wof:name":"Howick House Foot Clinic",
    "wof:placetype":"venue"
},
  "geometry": {"coordinates":[174.93142700000001,-36.895828],"type":"Point"}
}