{
  "type": "Feature",
  "properties": {
    "addr:full":"Level 4 88 Division St Riccarton  Christchurch Canterbury",
    "addr:housenumber":"level;88",
    "addr:street":"4;Division St;Christchurch",
    "iso:country":"NZ",
    "sg:address":"Level 4 88 Division St Riccarton ",
    "sg:city":"Christchurch",
    "sg:orig_category":"Farming: Forestry: Forestry Consultants",
    "sg:phone":"+64 3-962 1392",
    "sg:province":"Canterbury",
    "wof:name":"Southern Forestry Ltd",
    "wof:placetype":"venue"
},
  "geometry": {"coordinates":[172.59895299999999,-43.530521],"type":"Point"}
}