{
  "type": "Feature",
  "properties": {
    "iso:country":"NZ",
    "sg:address":"181 Ladies Mile Ellerslie ",
    "sg:city":"Auckland",
    "sg:classifiers":[
        {
            "category":"Bars & Pubs",
            "subcategory":"Lounge",
            "type":"Food & Drink"
        }
    ],
    "sg:phone":"+64 9-579 7126",
    "sg:province":"Auckland",
    "sg:tags":[
        "-",
        "asian"
    ],
    "wof:name":"Mitoku Macrobiotic",
    "wof:placetype":"venue"
},
  "geometry": {"coordinates":[174.80920399999999,-36.897224],"type":"Point"}
}