{
  "type": "Feature",
  "properties": {
    "iso:country":"NZ",
    "sg:address":"Nth Harbour Est 7 Ride Way Albany ",
    "sg:city":"Auckland",
    "sg:orig_category":"Home And Garden: Gardening: Products: Lawnmowers",
    "sg:phone":"+64 9-415 8615",
    "sg:province":"Auckland",
    "wof:name":"Mowac Corporation Ltd",
    "wof:placetype":"venue"
},
  "geometry": {"coordinates":[174.709686,-36.720142],"type":"Point"}
}