{
  "type": "Feature",
  "properties": {
    "addr:full":"Treble Court Peel St  Gisborne Gisborne",
    "addr:street":"Court;St",
    "iso:country":"NZ",
    "sg:address":"Treble Court Peel St ",
    "sg:city":"Gisborne",
    "sg:orig_category":"Health And Beauty: Beauty: Hairdressers",
    "sg:phone":"+64 6-868 8868",
    "sg:province":"Gisborne",
    "wof:name":"Talking Heads",
    "wof:placetype":"venue"
},
  "geometry": {"coordinates":[178.024475,-38.66597],"type":"Point"}
}