{
  "type": "Feature",
  "properties": {
    "iso:country":"NZ",
    "sg:address":"637 Marshlands Rd ",
    "sg:city":"Belfast",
    "sg:orig_category":"Sports And Leisure: Sports: Golf: Golf Courses",
    "sg:phone":"+64 3-323 8641",
    "sg:province":"Canterbury",
    "wof:name":"Everglades Golf Course",
    "wof:placetype":"venue"
},
  "geometry": {"coordinates":[-69.007973,44.425869],"type":"Point"}
}