{
  "type": "Feature",
  "properties": {
    "iso:country":"NZ",
    "sg:address":"31 Parnell St ",
    "sg:city":"Rawene",
    "sg:classifiers":[
        {
            "category":"Health Services",
            "subcategory":"Clinic",
            "type":"Services"
        }
    ],
    "sg:phone":"+64 9-405 7505",
    "sg:province":"Auckland",
    "sg:tags":[
        "services",
        "therapy",
        "natural",
        "beauty"
    ],
    "wof:name":"Michael Glicker",
    "wof:placetype":"venue"
},
  "geometry": {"coordinates":[173.503891,-35.39991],"type":"Point"}
}