{
  "type": "Feature",
  "properties": {
    "addr:full":"31 Parnell St  Rawene Auckland",
    "addr:housenumber":"31",
    "addr:street":"Parnell St",
    "iso:country":"NZ",
    "sg:address":"31 Parnell St ",
    "sg:city":"Rawene",
    "sg:classifiers":[
        {
            "category":"Health Services",
            "subcategory":"Clinic",
            "type":"Services"
        }
    ],
    "sg:phone":"+64 9-405 7505",
    "sg:province":"Auckland",
    "sg:tags":[
        "services",
        "therapy",
        "natural",
        "beauty"
    ],
    "wof:name":"Michael Glicker",
    "wof:placetype":"venue"
},
  "geometry": {"coordinates":[173.50389100000001,-35.39991],"type":"Point"}
}