{
  "type": "Feature",
  "properties": {
    "addr:full":"13 Carpenter Rd East Tamaki  Auckland Auckland",
    "addr:housenumber":"13",
    "addr:street":"Carpenter Rd",
    "iso:country":"NZ",
    "sg:address":"13 Carpenter Rd East Tamaki ",
    "sg:city":"Auckland",
    "sg:orig_category":"Industrial: Parts: Bolts And Nuts",
    "sg:phone":"+64 9-272 4070",
    "sg:province":"Auckland",
    "wof:name":"Manufacturing Suppliers Ltd (M S L)",
    "wof:placetype":"venue"
},
  "geometry": {"coordinates":[174.889893,-36.932747],"type":"Point"}
}