{
  "type": "Feature",
  "properties": {
    "iso:country":"NZ",
    "sg:address":"43 Mascot Ave Mangere ",
    "sg:city":"Auckland",
    "sg:orig_category":"Health And Beauty: Medical: Hospitals",
    "sg:phone":"+64 9-275 8349",
    "sg:province":"Auckland",
    "wof:name":"Christian Healthcare Trust",
    "wof:placetype":"venue"
},
  "geometry": {"coordinates":[174.803452,-36.972824],"type":"Point"}
}