{
  "type": "Feature",
  "properties": {
    "addr:full":"Central Car Park Stoke  Nelson Nelson",
    "addr:street":"Stoke Nelson",
    "iso:country":"NZ",
    "sg:address":"Central Car Park Stoke ",
    "sg:city":"Nelson",
    "sg:classifiers":[
        {
            "category":"Home & Garden",
            "subcategory":"Building Materials",
            "type":"Retail Goods"
        }
    ],
    "sg:phone":"+64 3-547 9623",
    "sg:province":"Nelson",
    "sg:tags":[
        "design",
        "fitting",
        "fittings",
        "kitchen"
    ],
    "wof:name":"Stoke Radio & T V",
    "wof:placetype":"venue"
},
  "geometry": {"coordinates":[173.23419200000001,-41.312859],"type":"Point"}
}