{
  "type": "Feature",
  "properties": {
    "addr:full":"29 Fox St South Dunedin  Dunedin Otago",
    "addr:housenumber":"29",
    "addr:street":"Fox St",
    "iso:country":"NZ",
    "sg:address":"29 Fox St South Dunedin ",
    "sg:city":"Dunedin",
    "sg:classifiers":[
        {
            "category":"Farming",
            "subcategory":"Fish & Marine Products",
            "type":"Manufacturing & Wholesale Goods"
        }
    ],
    "sg:phone":"+64 3-455 2057",
    "sg:province":"Otago",
    "sg:tags":[
        "health",
        "beauty"
    ],
    "sg:website":"http://www.yellowpages.co.nz/for/stewartconstruction/dp1459.html",
    "wof:name":"Stewart Construction Ltd",
    "wof:placetype":"venue"
},
  "geometry": {"coordinates":[170.50625600000001,-45.878353],"type":"Point"}
}