{
  "type": "Feature",
  "properties": {
    "addr:full":"Dekker Dve  Turangi",
    "iso:country":"NZ",
    "sg:address":"Dekker Dve ",
    "sg:city":"Turangi",
    "sg:orig_category":"Home And Garden: Furniture/Furnishings: Cabinetmakers",
    "sg:phone":"+64 7-386 6386",
    "wof:name":"Turangi Cabinetmakers & Tilers",
    "wof:placetype":"venue"
},
  "geometry": {"coordinates":[175.803955,-38.988941],"type":"Point"}
}