{
  "type": "Feature",
  "properties": {
    "addr:full":"199 Lincoln Rd Henderson  Auckland Auckland",
    "addr:housenumber":"199",
    "addr:street":"Lincoln Rd",
    "iso:country":"NZ",
    "sg:address":"199 Lincoln Rd Henderson ",
    "sg:city":"Auckland",
    "sg:orig_category":"Home And Garden: Furniture/Furnishings",
    "sg:phone":"+64 9-836 5101",
    "sg:province":"Auckland",
    "wof:name":"Bedworld",
    "wof:placetype":"venue"
},
  "geometry": {"coordinates":[174.62823499999999,-36.870419],"type":"Point"}
}