{
  "type": "Feature",
  "properties": {
    "iso:country":"NZ",
    "sg:address":"191 King Edward St South Dunedin ",
    "sg:city":"Dunedin",
    "sg:classifiers":[
        {
            "category":"Shopping",
            "subcategory":"Crafts & Fabrics",
            "type":"Retail Goods"
        }
    ],
    "sg:phone":"+64 3-455 4065",
    "sg:province":"Otago",
    "sg:tags":[
        "leather",
        "clothing",
        "suede"
    ],
    "wof:name":"Brocklebanks",
    "wof:placetype":"venue"
},
  "geometry": {"coordinates":[170.499252,-45.894581],"type":"Point"}
}