{
  "type": "Feature",
  "properties": {
    "iso:country":"NZ",
    "sg:address":"PO Box 10-500 ",
    "sg:city":"Wellington",
    "sg:classifiers":[
        {
            "category":"Education",
            "subcategory":"Special Training",
            "type":"Public Place"
        }
    ],
    "sg:phone":"+64 4-472 0788",
    "sg:province":"Wellington",
    "sg:website":"http://www.educationnz.org.nz",
    "wof:name":"Education New Zealand Trust",
    "wof:placetype":"venue"
},
  "geometry": {"coordinates":[-87.692841,40.560177],"type":"Point"}
}