{
  "type": "Feature",
  "properties": {
    "addr:full":"53 Leach St New  Plymouth Taranaki",
    "addr:housenumber":"53",
    "addr:street":"Leach St",
    "iso:country":"NZ",
    "sg:address":"53 Leach St New ",
    "sg:city":"Plymouth",
    "sg:orig_category":"Industrial: Services: Specialist Services: Scanning",
    "sg:phone":"+64 6-758 3709",
    "sg:province":"Taranaki",
    "sg:website":"http://www.plancopy.co.nz",
    "wof:name":"Plan Copy",
    "wof:placetype":"venue"
},
  "geometry": {"coordinates":[-116.81972500000001,43.97221],"type":"Point"}
}