{
  "type": "Feature",
  "properties": {
    "iso:country":"NZ",
    "sg:address":"178 The Strand ",
    "sg:city":"Whakatane",
    "sg:orig_category":"Shopping: Accessories: Jewellers And Watchmakers",
    "sg:phone":"+64 7-307 0739",
    "sg:province":"Auckland",
    "wof:name":"Renshaw's Gemtime Jeweller",
    "wof:placetype":"venue"
},
  "geometry": {"coordinates":[176.995361,-37.951607],"type":"Point"}
}