{
  "type": "Feature",
  "properties": {
    "iso:country":"NZ",
    "sg:address":"Cherrywood Dve Otumoetai ",
    "sg:city":"Tauranga",
    "sg:orig_category":"Shopping: Retail Stores: Books: Bookshops",
    "sg:phone":"+64 7-576 1092",
    "sg:province":"Bay of Plenty",
    "wof:name":"Sunrise Books",
    "wof:placetype":"venue"
},
  "geometry": {"coordinates":[176.147705,-37.670525],"type":"Point"}
}