{
  "type": "Feature",
  "properties": {
    "addr:full":"Judea  Tauranga Bay of Plenty",
    "iso:country":"NZ",
    "sg:address":"Judea ",
    "sg:city":"Tauranga",
    "sg:orig_category":"Automotive: Sales And Leasing: Trailers",
    "sg:phone":"+64 7-577 0677",
    "sg:province":"Bay of Plenty",
    "wof:name":"Gamman Engineering (1996) Ltd",
    "wof:placetype":"venue"
},
  "geometry": {"coordinates":[176.14236500000001,-37.695297],"type":"Point"}
}