{
  "type": "Feature",
  "properties": {
    "addr:full":"41 Terrace St  Invercargill Southland",
    "addr:housenumber":"41",
    "addr:street":"Terrace St",
    "iso:country":"NZ",
    "sg:address":"41 Terrace St ",
    "sg:city":"Invercargill",
    "sg:orig_category":"Industrial: Engineering: Engineers: Engineers - Consulting",
    "sg:phone":"+64 3-217 0019",
    "sg:province":"Southland",
    "wof:name":"Meritec Limited",
    "wof:placetype":"venue"
},
  "geometry": {"coordinates":[168.36232000000001,-46.389229],"type":"Point"}
}