{
  "type": "Feature",
  "properties": {
    "addr:full":"15 Jarden Mile Ngauranga  Wellington Waikato",
    "addr:housenumber":"15",
    "addr:street":"Jarden Mile",
    "iso:country":"NZ",
    "sg:address":"15 Jarden Mile Ngauranga ",
    "sg:city":"Wellington",
    "sg:orig_category":"Farming: Forestry",
    "sg:phone":"+64 4-478 3638",
    "sg:province":"Waikato",
    "wof:name":"Able Tasman Forestry Services Ltd",
    "wof:placetype":"venue"
},
  "geometry": {"coordinates":[174.811432,-41.248047],"type":"Point"}
}