{
  "type": "Feature",
  "properties": {
    "addr:full":"140 Riddiford St Newtown  Wellington Wellington",
    "addr:street":"140 Riddiford St",
    "iso:country":"NZ",
    "sg:address":"140 Riddiford St Newtown ",
    "sg:city":"Wellington",
    "sg:orig_category":"Shopping: Accessories: Lingerie - Retail",
    "sg:phone":"+64 4-389 9820",
    "sg:province":"Wellington",
    "wof:name":"Lorraine Ladieswear Lingerie",
    "wof:placetype":"venue"
},
  "geometry": {"coordinates":[174.77932699999999,-41.312706],"type":"Point"}
}