{
  "type": "Feature",
  "properties": {
    "iso:country":"NZ",
    "sg:address":"54 Otaika Rd ",
    "sg:city":"Whangarei",
    "sg:classifiers":[
        {
            "category":"Travel",
            "subcategory":"Hotels & Motels",
            "type":"Entertainment"
        }
    ],
    "sg:phone":"+64 9-438 4574",
    "sg:province":"Northland",
    "sg:tags":[
        "holiday",
        "tourism",
        "accommodation"
    ],
    "sg:website":"http://www.centralcourtmotel.co.nz",
    "wof:name":"Central Court Motel",
    "wof:placetype":"venue"
},
  "geometry": {"coordinates":[174.31137100000001,-35.735649],"type":"Point"}
}