{
  "type": "Feature",
  "properties": {
    "iso:country":"NZ",
    "sg:address":"122 Cuba Mall ",
    "sg:city":"Wellington",
    "sg:orig_category":"Health And Beauty: Products: Pharmacies",
    "sg:phone":"+64 4-384 6856",
    "sg:province":"Wellington",
    "wof:name":"Amcal Cuba Mall Pharmacy",
    "wof:placetype":"venue"
},
  "geometry": {"coordinates":[-85.910454,33.827946],"type":"Point"}
}