{
  "type": "Feature",
  "properties": {
    "addr:full":"5 Totara St Mt  Maunganui Auckland",
    "addr:housenumber":"5",
    "addr:street":"Totara St",
    "iso:country":"NZ",
    "sg:address":"5 Totara St Mt ",
    "sg:city":"Maunganui",
    "sg:orig_category":"Transport: Boats And Marine: Boats: Inflatable Boats",
    "sg:phone":"+64 7-575 3440",
    "sg:province":"Auckland",
    "wof:name":"Inflatable Boat Company (Manufacturers)",
    "wof:placetype":"venue"
},
  "geometry": {"coordinates":[176.18588299999999,-37.64328],"type":"Point"}
}