{
  "type": "Feature",
  "properties": {
    "iso:country":"NZ",
    "sg:address":"Titirangi ",
    "sg:city":"Auckland",
    "sg:orig_category":"Home And Garden: Children: Child Related: Children'S Entertainment",
    "sg:phone":"+64 9-817 3389",
    "sg:province":"Auckland",
    "wof:name":"Jane's Silk & Shadow Puppets",
    "wof:placetype":"venue"
},
  "geometry": {"coordinates":[174.655869,-36.93795],"type":"Point"}
}