{
  "type": "Feature",
  "properties": {
    "addr:full":"29 Hobson Rd Albany  Auckland Auckland",
    "addr:housenumber":"29",
    "addr:street":"Hobson Rd",
    "iso:country":"NZ",
    "sg:address":"29 Hobson Rd Albany ",
    "sg:city":"Auckland",
    "sg:classifiers":[
        {
            "category":"Sports & Exercise",
            "subcategory":"Playing Field",
            "type":"Entertainment"
        }
    ],
    "sg:phone":"+64 9-415 5593",
    "sg:province":"Auckland",
    "sg:tags":[
        "skiing",
        "ski",
        "leisure",
        "sports"
    ],
    "wof:name":"Pipers Ski Tours Ltd",
    "wof:placetype":"venue"
},
  "geometry": {"coordinates":[174.67773399999999,-36.721058],"type":"Point"}
}