{
  "type": "Feature",
  "properties": {
    "iso:country":"NZ",
    "sg:address":"438-450 Victoria Ave ",
    "sg:city":"Wanganui",
    "sg:orig_category":"Shopping: Retail Stores: Supermarkets",
    "sg:phone":"+64 6-348 7233",
    "sg:province":"Manawatu-Wanganui",
    "wof:name":"Woolworths @ Gull",
    "wof:placetype":"venue"
},
  "geometry": {"coordinates":[175.037796,-39.924301],"type":"Point"}
}