{
  "type": "Feature",
  "properties": {
    "iso:country":"NZ",
    "sg:address":"1 Brown St Upper Hutt ",
    "sg:city":"Wellington",
    "sg:orig_category":"Industrial: Energy And Utilities: Gas",
    "sg:phone":"+64 4-939 6406",
    "sg:province":"Wellington",
    "wof:name":"Ruscoe Auto Services Ltd",
    "wof:placetype":"venue"
},
  "geometry": {"coordinates":[175.069275,-41.125938],"type":"Point"}
}