{
  "type": "Feature",
  "properties": {
    "iso:country":"NZ",
    "sg:address":"106 A Blockhouse Bay Rd Avondale ",
    "sg:city":"Auckland",
    "sg:classifiers":[
        {
            "category":"Travel",
            "subcategory":"Bed & Breakfast",
            "type":"Entertainment"
        }
    ],
    "sg:phone":"+64 9-820 0702",
    "sg:province":"Auckland",
    "sg:tags":[
        "house",
        "tourism",
        "guest",
        "accommodation"
    ],
    "wof:name":"Roberton Lodge",
    "wof:placetype":"venue"
},
  "geometry": {"coordinates":[174.70105000000001,-36.893421],"type":"Point"}
}