{
  "type": "Feature",
  "properties": {
    "iso:country":"NZ",
    "sg:address":"18 Wyndham St Auckland Central ",
    "sg:city":"Auckland",
    "sg:classifiers":[
        {
            "category":"Bars & Pubs",
            "subcategory":"Nightclub",
            "type":"Food & Drink"
        }
    ],
    "sg:phone":"+64 9-373 3433",
    "sg:province":"Auckland",
    "sg:tags":[
        "club",
        "night",
        "sport",
        "leisure",
        "entertainment"
    ],
    "wof:name":"Wyndham Bowling Club",
    "wof:placetype":"venue"
},
  "geometry": {"coordinates":[174.76504499999999,-36.847282],"type":"Point"}
}