{
  "type": "Feature",
  "properties": {
    "addr:full":"7/196a Williams St  Kaiapoi",
    "addr:housenumber":"7 / 196a",
    "addr:street":"Williams St",
    "iso:country":"NZ",
    "sg:address":"7/196a Williams St ",
    "sg:city":"Kaiapoi",
    "sg:classifiers":[
        {
            "category":"Food & Beverages",
            "subcategory":"Liquor & Beverages",
            "type":"Retail Goods"
        }
    ],
    "sg:phone":"+64 3-327 9320",
    "sg:tags":[
        "drink",
        "outlet"
    ],
    "wof:name":"Kaiapoi Liquor Centre",
    "wof:placetype":"venue"
},
  "geometry": {"coordinates":[172.65982099999999,-43.38129],"type":"Point"}
}