{
  "type": "Feature",
  "properties": {
    "addr:full":"Unit 11/9 Barton Tce Thorndon  Wellington Wellington",
    "addr:housenumber":"unit 11 / 9",
    "addr:street":"Barton Tce",
    "iso:country":"NZ",
    "sg:address":"Unit 11/9 Barton Tce Thorndon ",
    "sg:city":"Wellington",
    "sg:classifiers":[
        {
            "category":"Sports & Exercise",
            "subcategory":"Golf",
            "type":"Entertainment"
        }
    ],
    "sg:phone":"+64 4-473 2235",
    "sg:province":"Wellington",
    "sg:tags":[
        "club",
        "equipment",
        "leisure",
        "sports"
    ],
    "wof:name":"Electric Golf Trundlers",
    "wof:placetype":"venue"
},
  "geometry": {"coordinates":[174.76895099999999,-41.277981],"type":"Point"}
}