{
  "type": "Feature",
  "properties": {
    "addr:full":"3 Campbell Pl  Rotorua Bay of Plenty",
    "addr:housenumber":"3",
    "addr:street":"Campbell Pl",
    "iso:country":"NZ",
    "sg:address":"3 Campbell Pl ",
    "sg:city":"Rotorua",
    "sg:classifiers":[
        {
            "category":"Retail",
            "subcategory":"Auto Repair",
            "type":"Services"
        }
    ],
    "sg:phone":"+64 274 516 926",
    "sg:province":"Bay of Plenty",
    "sg:tags":[
        "automotive",
        "electric",
        "servicing"
    ],
    "wof:name":"Rotorua Auto Electrical(2000)Ltd",
    "wof:placetype":"venue"
},
  "geometry": {"coordinates":[176.215149,-38.140301],"type":"Point"}
}