{
  "type": "Feature",
  "properties": {
    "addr:full":"Hillend R D 2  Balclutha",
    "addr:housenumber":"2",
    "iso:country":"NZ",
    "sg:address":"Hillend R D 2 ",
    "sg:city":"Balclutha",
    "sg:classifiers":[
        {
            "category":"Home & Garden",
            "subcategory":"Garden Supply",
            "type":"Retail Goods"
        }
    ],
    "sg:phone":"+64 3-418 2465",
    "sg:tags":[
        "products",
        "nursery",
        "gardening"
    ],
    "wof:name":"Southwell Plants",
    "wof:placetype":"venue"
},
  "geometry": {"coordinates":[169.74681100000001,-46.234802],"type":"Point"}
}