{
  "type": "Feature",
  "properties": {
    "addr:full":"5/43a Linwood Ave Mt Albert  Auckland Canterbury",
    "addr:housenumber":"5 / 43a",
    "addr:street":"Linwood Ave",
    "iso:country":"NZ",
    "sg:address":"5/43a Linwood Ave Mt Albert ",
    "sg:city":"Auckland",
    "sg:classifiers":[
        {
            "category":"Shopping",
            "subcategory":"Clothing, Apparel, & Fashions",
            "type":"Retail Goods"
        }
    ],
    "sg:phone":"+64 9-849 4407",
    "sg:province":"Canterbury",
    "sg:tags":[
        "repair",
        "fabric",
        "-",
        "cleaning",
        "pressers",
        "clothing"
    ],
    "wof:name":"Western Springs Trade Pressers",
    "wof:placetype":"venue"
},
  "geometry": {"coordinates":[174.723297,-36.873463],"type":"Point"}
}