{
  "type": "Feature",
  "properties": {
    "addr:full":"Caldwell Rd RD 2 Ongaonga  Waipukurau",
    "addr:street":"Caldwell Rd Rd 2 Ongaonga",
    "iso:country":"NZ",
    "sg:address":"Caldwell Rd RD 2 Ongaonga ",
    "sg:city":"Waipukurau",
    "sg:classifiers":[
        {
            "category":"Shopping",
            "subcategory":"Pets & Pet Supplies",
            "type":"Retail Goods"
        }
    ],
    "sg:phone":"+64 6-856 6617",
    "sg:tags":[
        "boarding",
        "garden",
        "pets",
        "catteries",
        "home",
        "kennel"
    ],
    "wof:name":"Caldwell Road Canine Boarding Kennels",
    "wof:placetype":"venue"
},
  "geometry": {"coordinates":[176.420807,-39.913952],"type":"Point"}
}