{
  "type": "Feature",
  "properties": {
    "addr:full":"Bongard Centre, Cameron Rd or Windermere Dve  Tauranga Bay of Plenty",
    "addr:street":"Cameron Rd",
    "iso:country":"NZ",
    "sg:address":"Bongard Centre, Cameron Rd or Windermere Dve ",
    "sg:city":"Tauranga",
    "sg:classifiers":[
        {
            "category":"Education",
            "subcategory":"Vocational School",
            "type":"Public Place"
        }
    ],
    "sg:phone":"+64 7-544 0920",
    "sg:province":"Bay of Plenty",
    "sg:tags":[
        "training"
    ],
    "sg:website":"http://www.boppoly.ac.nz",
    "wof:name":"Bay Of Plenty Polytechnic",
    "wof:placetype":"venue"
},
  "geometry": {"coordinates":[176.1474,-37.732861],"type":"Point"}
}