{
  "type": "Feature",
  "properties": {
    "iso:country":"NZ",
    "sg:address":"SH123/24 Main Rd Tawa ",
    "sg:city":"Wellington",
    "sg:orig_category":"Shopping: Discount: Factory Shops",
    "sg:phone":"+64 4-232 2007",
    "sg:province":"Wellington",
    "wof:name":"Pulse",
    "wof:placetype":"venue"
},
  "geometry": {"coordinates":[174.82420300000001,-41.171494],"type":"Point"}
}