{
  "type": "Feature",
  "properties": {
    "addr:full":"3/61 Crooks Rd East Tamaki  Auckland Auckland",
    "addr:housenumber":"3 / 61",
    "addr:street":"Crooks Rd",
    "iso:country":"NZ",
    "sg:address":"3/61 Crooks Rd East Tamaki ",
    "sg:city":"Auckland",
    "sg:classifiers":[
        {
            "category":"Personal",
            "subcategory":"Adult",
            "type":"Services"
        }
    ],
    "sg:phone":"+64 9-272 4230",
    "sg:province":"Auckland",
    "sg:tags":[
        "sport",
        "parlour",
        "massage",
        "leisure"
    ],
    "wof:name":"Geneva's",
    "wof:placetype":"venue"
},
  "geometry": {"coordinates":[174.89212000000001,-36.939438],"type":"Point"}
}