{
  "type": "Feature",
  "properties": {
    "iso:country":"NZ",
    "sg:address":"Cnr Ordsal & Lyne Sts ",
    "sg:city":"Gore",
    "sg:classifiers":[
        {
            "category":"Home & Garden",
            "subcategory":"Building Materials",
            "type":"Retail Goods"
        }
    ],
    "sg:phone":"+64 3-208 6750",
    "sg:province":"Southland",
    "sg:tags":[
        "fittings",
        "door",
        "garage"
    ],
    "wof:name":"Aitken Joinery Ltd",
    "wof:placetype":"venue"
},
  "geometry": {"coordinates":[-95.116547,35.530331],"type":"Point"}
}