{
  "type": "Feature",
  "properties": {
    "addr:full":"117 Bright St Cobden  Greymouth West Coast",
    "addr:housenumber":"117",
    "addr:street":"Bright St",
    "iso:country":"NZ",
    "sg:address":"117 Bright St Cobden ",
    "sg:city":"Greymouth",
    "sg:classifiers":[
        {
            "category":"Bars & Pubs",
            "subcategory":"Lounge",
            "type":"Food & Drink"
        }
    ],
    "sg:phone":"+64 3-762 7627",
    "sg:province":"West Coast",
    "sg:tags":[
        "baker",
        "-"
    ],
    "wof:name":"Party Cakes",
    "wof:placetype":"venue"
},
  "geometry": {"coordinates":[171.21075400000001,-42.441559],"type":"Point"}
}