{
  "type": "Feature",
  "properties": {
    "iso:country":"NZ",
    "sg:address":"62 Stott Ave Birkdale ",
    "sg:city":"Auckland",
    "sg:classifiers":[
        {
            "category":"Manufacturing",
            "subcategory":"Rubber & Plastics",
            "type":"Manufacturing & Wholesale Goods"
        }
    ],
    "sg:phone":"+64 9-483 6240",
    "sg:province":"Auckland",
    "sg:tags":[
        "stamp",
        "industrial",
        "goods"
    ],
    "wof:name":"North Shore Rubber Stamps",
    "wof:placetype":"venue"
},
  "geometry": {"coordinates":[174.699661,-36.802601],"type":"Point"}
}