{
  "type": "Feature",
  "properties": {
    "addr:full":"13 A Gabador Pl Mt Wellington  Auckland Auckland",
    "addr:housenumber":"13",
    "addr:street":"A Gabador Pl",
    "iso:country":"NZ",
    "sg:address":"13 A Gabador Pl Mt Wellington ",
    "sg:city":"Auckland",
    "sg:classifiers":[
        {
            "category":"Home & Garden",
            "subcategory":"Household Appliances",
            "type":"Retail Goods"
        }
    ],
    "sg:phone":"+64 9-276 0832",
    "sg:province":"Auckland",
    "sg:tags":[
        "products",
        "surgical",
        "health",
        "beauty"
    ],
    "wof:name":"DePuy New Zealand Ltd",
    "wof:placetype":"venue"
},
  "geometry": {"coordinates":[174.85493500000001,-36.92057],"type":"Point"}
}