{
  "type": "Feature",
  "properties": {
    "iso:country":"NZ",
    "sg:address":"Anthony St Linden ",
    "sg:city":"Wellington",
    "sg:orig_category":"Home And Garden: Gardening: Products: Garden Supplies",
    "sg:phone":"+64 4-232 7901",
    "sg:province":"Wellington",
    "wof:name":"Go Green Garden Mulch",
    "wof:placetype":"venue"
},
  "geometry": {"coordinates":[174.836838,-41.152126],"type":"Point"}
}