{
  "type": "Feature",
  "properties": {
    "addr:full":"2 Orlando St  Stratford",
    "addr:housenumber":"2",
    "addr:street":"Orlando St",
    "iso:country":"NZ",
    "sg:address":"2 Orlando St ",
    "sg:city":"Stratford",
    "sg:classifiers":[
        {
            "category":"Building & Trades",
            "subcategory":"Pest Control",
            "type":"Services"
        }
    ],
    "sg:phone":"+64 6-765 7038",
    "sg:tags":[
        "home",
        "garden"
    ],
    "wof:name":"Ecomist Finesse Cruserbrown",
    "wof:placetype":"venue"
},
  "geometry": {"coordinates":[-119.824966,36.189419],"type":"Point"}
}