{
  "type": "Feature",
  "properties": {
    "iso:country":"NZ",
    "sg:address":"I.C.E BUILDINGS Ivan Jamieson Place ChCh International, Airport ",
    "sg:city":"Christchurch",
    "sg:classifiers":[
        {
            "category":"Manufacturing",
            "subcategory":"Tools & Machinery",
            "type":"Manufacturing & Wholesale Goods"
        }
    ],
    "sg:phone":"+64 3-366 3200",
    "sg:province":"Canterbury",
    "sg:tags":[
        "equipment",
        "industrial",
        "label"
    ],
    "wof:name":"Walker Datavision",
    "wof:placetype":"venue"
},
  "geometry": {"coordinates":[-76.53782699999999,37.605659],"type":"Point"}
}