{
  "type": "Feature",
  "properties": {
    "iso:country":"NZ",
    "sg:address":"5 Parumoana St ",
    "sg:city":"Porirua",
    "sg:classifiers":[
        {
            "category":"Professional",
            "type":"Services"
        }
    ],
    "sg:phone":"+64 4-237 7161",
    "sg:province":"Wellington",
    "sg:tags":[
        "services",
        "car",
        "valet",
        "automotive"
    ],
    "wof:name":"Vehicle Valet",
    "wof:placetype":"venue"
},
  "geometry": {"coordinates":[174.85223400000001,-41.138294],"type":"Point"}
}