{
  "type": "Feature",
  "properties": {
    "iso:country":"NZ",
    "sg:address":"PO Box 21121 Flagstaff ",
    "sg:city":"Hamilton",
    "sg:orig_category":"Industrial: Parts: Valves",
    "sg:phone":"+64 7-854 0955",
    "sg:province":"Waikato",
    "wof:name":"FCX (Taylors) NZ Ltd",
    "wof:placetype":"venue"
},
  "geometry": {"coordinates":[175.25701900000001,-37.739288],"type":"Point"}
}