{
  "type": "Feature",
  "properties": {
    "addr:full":"Main Rd  Pukerau",
    "addr:street":"Main Rd",
    "iso:country":"NZ",
    "sg:address":"Main Rd ",
    "sg:city":"Pukerau",
    "sg:orig_category":"Farming: Supplies",
    "sg:phone":"+64 3-205 3004",
    "wof:name":"Mainland Minerals (NZ) Ltd",
    "wof:placetype":"venue"
},
  "geometry": {"coordinates":[169.10137900000001,-46.098228],"type":"Point"}
}