{
  "type": "Feature",
  "properties": {
    "addr:full":"refer Hawkes Bay Mazda Suzuki  Hastings Hawke's Bay",
    "iso:country":"NZ",
    "sg:address":"refer Hawkes Bay Mazda Suzuki ",
    "sg:city":"Hastings",
    "sg:classifiers":[
        {
            "category":"Autos & Motor Vehicles",
            "subcategory":"Automobile Sales",
            "type":"Retail Goods"
        }
    ],
    "sg:phone":"+64 6-876 3142",
    "sg:province":"Hawke's Bay",
    "sg:tags":[
        "car",
        "-used",
        "leasing",
        "truck",
        "automotive"
    ],
    "wof:name":"Suzuki",
    "wof:placetype":"venue"
},
  "geometry": {"coordinates":[176.844818,-39.64167],"type":"Point"}
}