{
  "type": "Feature",
  "properties": {
    "iso:country":"NZ",
    "sg:address":"633 Main St Palmerston ",
    "sg:city":"Palmerston North",
    "sg:orig_category":"Home And Garden: General",
    "sg:phone":"+64 6-357 7600",
    "sg:province":"Manawatu-Wanganui",
    "sg:website":"http://www.yellowpages.co.nz/for/chrismarks/dp26404.html",
    "wof:name":"Chris Marks Commercial Realty Ltd",
    "wof:placetype":"venue"
},
  "geometry": {"coordinates":[175.61546325680001,-40.3542671204],"type":"Point"}
}