{
  "type": "Feature",
  "properties": {
    "addr:full":"R D 6  Wanganui Manawatu-Wanganui",
    "addr:housenumber":"6",
    "addr:street":"R D",
    "iso:country":"NZ",
    "sg:address":"R D 6 ",
    "sg:city":"Wanganui",
    "sg:classifiers":[
        {
            "category":"Recreation",
            "type":"Entertainment"
        }
    ],
    "sg:phone":"+64 6-342 8116",
    "sg:province":"Manawatu-Wanganui",
    "sg:tags":[
        "trek",
        "travel",
        "horse",
        "tour",
        "tourism",
        "sightseeing"
    ],
    "wof:name":"Back Country Lifestyle",
    "wof:placetype":"venue"
},
  "geometry": {"coordinates":[175.052841,-39.933369],"type":"Point"}
}