{
  "type": "Feature",
  "properties": {
    "iso:country":"NZ",
    "sg:address":"Domain Rd Hawea Flat ",
    "sg:city":"Wanaka",
    "sg:orig_category":"Farming: Farms - General: Beekeeping",
    "sg:phone":"+64 3-443 1490",
    "sg:province":"Otago",
    "wof:name":"Alpine Honey Specialties",
    "wof:placetype":"venue"
},
  "geometry": {"coordinates":[169.138443,-44.693981],"type":"Point"}
}