{
  "type": "Feature",
  "properties": {
    "iso:country":"NZ",
    "sg:address":"306 Chadwick Rd West ",
    "sg:city":"Tauranga",
    "sg:classifiers":[
        {
            "category":"Manufacturing",
            "subcategory":"Glass & Minerals",
            "type":"Manufacturing & Wholesale Goods"
        }
    ],
    "sg:phone":"+64 7-577 6618",
    "sg:province":"Bay of Plenty",
    "sg:tags":[
        "chemical",
        "fibre",
        "industrial",
        "compounds"
    ],
    "wof:name":"Judea Fibreglass",
    "wof:placetype":"venue"
},
  "geometry": {"coordinates":[176.128036,-37.723808],"type":"Point"}
}