{
  "type": "Feature",
  "properties": {
    "iso:country":"NZ",
    "sg:address":"28 High St ",
    "sg:city":"Tirau",
    "sg:orig_category":"Shopping: Retail Stores: Antiques",
    "sg:phone":"+64 7-883 1666",
    "wof:name":"Cartwells of Tirau Antiques & Collectables",
    "wof:placetype":"venue"
},
  "geometry": {"coordinates":[175.75851399999999,-37.979248],"type":"Point"}
}