{
  "type": "Feature",
  "properties": {
    "addr:full":"PriceWaterhouse Coopers Centre, Lvl 9, 66 Wyndham, PO Box 106 002, Downtown, AUCKLAND 1001",
    "addr:housenumber":"lvl 9 66;po box 106 002",
    "addr:postcode":"1001",
    "addr:street":"Pricewaterhouse",
    "iso:country":"NZ",
    "sg:address":"PriceWaterhouse Coopers Centre, Lvl 9, 66 Wyndham, PO Box 106 002, Downtown, AUCKLAND",
    "sg:city":"1001",
    "sg:classifiers":[
        {
            "category":"Shopping",
            "subcategory":"Computers & Home Electronics",
            "type":"Retail Goods"
        }
    ],
    "sg:phone":"+64 6493099140",
    "sg:tags":[
        "chamber",
        "commerce"
    ],
    "sg:website":"www.amcham.co.nz",
    "wof:name":"American Chamber of Commerce in the New Zealand",
    "wof:placetype":"venue"
},
  "geometry": {"coordinates":[174.76365699999999,-36.854431],"type":"Point"}
}