{
  "type": "Feature",
  "properties": {
    "addr:full":"Port Rd  Whangarei Northland",
    "addr:street":"Port Rd",
    "iso:country":"NZ",
    "sg:address":"Port Rd ",
    "sg:city":"Whangarei",
    "sg:classifiers":[
        {
            "category":"Education",
            "subcategory":"Special Training",
            "type":"Public Place"
        }
    ],
    "sg:phone":"+64 9-430 3868",
    "sg:province":"Northland",
    "sg:tags":[
        "testing",
        "driver",
        "licencing",
        "/"
    ],
    "wof:name":"Driver Education Services NZ",
    "wof:placetype":"venue"
},
  "geometry": {"coordinates":[174.34652700000001,-35.75285],"type":"Point"}
}