{
  "type": "Feature",
  "properties": {
    "addr:full":"21 Argyle St Herne Bay  Auckland Auckland",
    "addr:housenumber":"21",
    "addr:street":"Argyle St",
    "iso:country":"NZ",
    "sg:address":"21 Argyle St Herne Bay ",
    "sg:city":"Auckland",
    "sg:classifiers":[
        {
            "category":"Banks & Credit Unions",
            "subcategory":"Investment Brokerage",
            "type":"Services"
        }
    ],
    "sg:phone":"+64 9-378 9794",
    "sg:province":"Auckland",
    "sg:tags":[
        "chemical",
        "industrial",
        "-",
        "compounds"
    ],
    "wof:name":"Chemagro NZ Ltd",
    "wof:placetype":"venue"
},
  "geometry": {"coordinates":[174.731461,-36.843361],"type":"Point"}
}