{
  "type": "Feature",
  "properties": {
    "iso:country":"NZ",
    "sg:address":"143 Riri St ",
    "sg:city":"Rotorua",
    "sg:classifiers":[
        {
            "category":"Wholesale",
            "subcategory":"Machinery & Supplies",
            "type":"Manufacturing & Wholesale Goods"
        }
    ],
    "sg:phone":"+64 7-347 8116",
    "sg:province":"Bay of Plenty",
    "sg:tags":[
        "equipment",
        "crane",
        "industrial",
        "hoist",
        "lifting"
    ],
    "wof:name":"Concrete Structures (NZ) Ltd",
    "wof:placetype":"venue"
},
  "geometry": {"coordinates":[176.225204,-38.13385],"type":"Point"}
}