{
  "type": "Feature",
  "properties": {
    "iso:country":"NZ",
    "sg:address":"400 Titirangi Rd Titirangi ",
    "sg:city":"Auckland",
    "sg:orig_category":"Shopping: Retail Stores: Books: Books - Secondhand",
    "sg:phone":"+64 9-816 9597",
    "sg:province":"Auckland",
    "wof:name":"Stackstreet Books",
    "wof:placetype":"venue"
},
  "geometry": {"coordinates":[174.657318,-36.93779],"type":"Point"}
}