{
  "type": "Feature",
  "properties": {
    "iso:country":"NZ",
    "sg:address":"15 Lincoln St ",
    "sg:city":"Hamilton",
    "sg:orig_category":"Sports And Leisure: Sports: Equestrian: Equestrian Supplies",
    "sg:phone":"+64 7-847 8286",
    "sg:province":"Waikato",
    "wof:name":"Fountain City Saddlery",
    "wof:placetype":"venue"
},
  "geometry": {"coordinates":[-70.881622,42.621449],"type":"Point"}
}