{
  "type": "Feature",
  "properties": {
    "addr:full":"123 Gordon Rd Mosgiel  Dunedin Otago",
    "addr:housenumber":"123",
    "addr:street":"Gordon Rd",
    "iso:country":"NZ",
    "sg:address":"123 Gordon Rd Mosgiel ",
    "sg:city":"Dunedin",
    "sg:classifiers":[
        {
            "category":"Shopping",
            "subcategory":"Crafts & Fabrics",
            "type":"Retail Goods"
        }
    ],
    "sg:phone":"+64 3-489 6239",
    "sg:province":"Otago",
    "sg:tags":[
        "foot",
        "clothing",
        "retailer",
        "footwear",
        "wear"
    ],
    "wof:name":"Hannahs Shoe Stores",
    "wof:placetype":"venue"
},
  "geometry": {"coordinates":[170.34841900000001,-45.874954],"type":"Point"}
}