{
  "type": "Feature",
  "properties": {
    "iso:country":"NZ",
    "sg:address":"Axa Centre 152-156 Hereford St ",
    "sg:city":"Christchurch",
    "sg:classifiers":[
        {
            "category":"Retail",
            "subcategory":"Repair Shop",
            "type":"Services"
        }
    ],
    "sg:phone":"+64 3-379 7719",
    "sg:province":"Canterbury",
    "sg:tags":[
        "clothing",
        "fabric",
        "cleaning"
    ],
    "wof:name":"Victoria's Closet",
    "wof:placetype":"venue"
},
  "geometry": {"coordinates":[172.637314,-43.531315],"type":"Point"}
}