{
  "type": "Feature",
  "properties": {
    "addr:full":"256 Rosebank Rd Avondale  Auckland Auckland",
    "addr:housenumber":"256",
    "addr:street":"Rosebank Rd",
    "iso:country":"NZ",
    "sg:address":"256 Rosebank Rd Avondale ",
    "sg:city":"Auckland",
    "sg:classifiers":[
        {
            "category":"Health Services",
            "subcategory":"Health Practitioner",
            "type":"Services"
        }
    ],
    "sg:phone":"+64 9-828 3631",
    "sg:province":"Auckland",
    "sg:tags":[
        "specialist",
        "medical",
        "beauty",
        "specialists"
    ],
    "wof:name":"Dhana Dr Raj",
    "wof:placetype":"venue"
},
  "geometry": {"coordinates":[174.68568400000001,-36.888668],"type":"Point"}
}