{
  "type": "Feature",
  "properties": {
    "addr:full":"145 Gt South Rd Greenlane  Auckland Auckland",
    "addr:housenumber":"145",
    "addr:street":"Gt South Rd",
    "iso:country":"NZ",
    "sg:address":"145 Gt South Rd Greenlane ",
    "sg:city":"Auckland",
    "sg:orig_category":"Health And Beauty: Specialists: Podiatrists",
    "sg:phone":"+64 9-524 2599",
    "sg:province":"Auckland",
    "wof:name":"Greenlane Podiatry Clinic",
    "wof:placetype":"venue"
},
  "geometry": {"coordinates":[174.78942900000001,-36.887184],"type":"Point"}
}