{
  "type": "Feature",
  "properties": {
    "addr:full":"60 Lunns Rd Sockburn  Christchurch Canterbury",
    "addr:housenumber":"60",
    "addr:street":"Lunns Rd",
    "iso:country":"NZ",
    "sg:address":"60 Lunns Rd Sockburn ",
    "sg:city":"Christchurch",
    "sg:classifiers":[
        {
            "category":"Utilities",
            "subcategory":"Fuel Oil & Lpg",
            "type":"Services"
        }
    ],
    "sg:phone":"+64 3-348 0736",
    "sg:province":"Canterbury",
    "sg:tags":[
        "coal",
        "energy",
        "industrial",
        "mine",
        "utilities"
    ],
    "wof:name":"Francis Mining Co Ltd",
    "wof:placetype":"venue"
},
  "geometry": {"coordinates":[172.55043000000001,-43.534966],"type":"Point"}
}