{
  "type": "Feature",
  "properties": {
    "addr:full":"PO Box 60  Lyttelton",
    "addr:housenumber":"po box 60",
    "iso:country":"NZ",
    "sg:address":"PO Box 60 ",
    "sg:city":"Lyttelton",
    "sg:orig_category":"Automotive: Accessories: Car Care Products",
    "sg:phone":"+64 256690226",
    "wof:name":"Autoglym Car Care Products -Grose Enterprises",
    "wof:placetype":"venue"
},
  "geometry": {"coordinates":[172.72283899999999,-43.599499],"type":"Point"}
}