{
  "type": "Feature",
  "properties": {
    "iso:country":"NZ",
    "sg:address":"268 The Strand ",
    "sg:city":"Whakatane",
    "sg:classifiers":[
        {
            "category":"Professional",
            "type":"Services"
        }
    ],
    "sg:phone":"+64 7-307 1234",
    "sg:province":"Auckland",
    "sg:tags":[
        "services",
        "car",
        "valet",
        "automotive"
    ],
    "wof:name":"Wally Sutherland Ltd",
    "wof:placetype":"venue"
},
  "geometry": {"coordinates":[176.991364,-37.953106],"type":"Point"}
}