{
  "type": "Feature",
  "properties": {
    "iso:country":"NZ",
    "sg:address":"15 Wickham St Hamilton Te ",
    "sg:city":"Kauwhata",
    "sg:classifiers":[
        {
            "category":"Utilities",
            "subcategory":"Sewage",
            "type":"Services"
        }
    ],
    "sg:phone":"+64 7-826 3242",
    "sg:tags":[
        "home",
        "tank",
        "garden",
        "septic"
    ],
    "wof:name":"Allens United North Waikato Ltd",
    "wof:placetype":"venue"
},
  "geometry": {"coordinates":[175.257645,-37.806442],"type":"Point"}
}