{
  "type": "Feature",
  "properties": {
    "addr:full":"17 Moody Ave  Whangarei Northland",
    "addr:housenumber":"17",
    "addr:street":"Moody Ave",
    "iso:country":"NZ",
    "sg:address":"17 Moody Ave ",
    "sg:city":"Whangarei",
    "sg:classifiers":[
        {
            "category":"Health Services",
            "subcategory":"Dentist",
            "type":"Services"
        }
    ],
    "sg:phone":"+64 9-437 0839",
    "sg:province":"Northland",
    "sg:tags":[
        "dental",
        "clinic",
        "beauty"
    ],
    "wof:name":"Whau Valley School",
    "wof:placetype":"venue"
},
  "geometry": {"coordinates":[174.316574,-35.701256],"type":"Point"}
}