{
  "type": "Feature",
  "properties": {
    "addr:full":"824 Wairakei Rd Extn Christchurch Airport  Christchurch Canterbury",
    "addr:housenumber":"824;christchurch",
    "addr:street":"Wairakei Rd",
    "iso:country":"NZ",
    "sg:address":"824 Wairakei Rd Extn Christchurch Airport ",
    "sg:city":"Christchurch",
    "sg:orig_category":"Transport: Transportation: Freight",
    "sg:phone":"+64 3-357 8600",
    "sg:province":"Canterbury",
    "wof:name":"Bax Global (NZ) Ltd",
    "wof:placetype":"venue"
},
  "geometry": {"coordinates":[172.54724100000001,-43.485062],"type":"Point"}
}