{
  "type": "Feature",
  "properties": {
    "addr:full":"1/19 Ashfield St Glenfield  Auckland Auckland",
    "addr:housenumber":"1 / 19",
    "addr:street":"Ashfield St",
    "iso:country":"NZ",
    "sg:address":"1/19 Ashfield St Glenfield ",
    "sg:city":"Auckland",
    "sg:classifiers":[
        {
            "category":"Health Services",
            "subcategory":"Clinic",
            "type":"Services"
        }
    ],
    "sg:phone":"+64 9-444 3558",
    "sg:province":"Auckland",
    "sg:tags":[
        "optical",
        "beauty",
        "supply"
    ],
    "wof:name":"Chris Day Optical Co Ltd",
    "wof:placetype":"venue"
},
  "geometry": {"coordinates":[174.730896,-36.773445],"type":"Point"}
}