{
  "type": "Feature",
  "properties": {
    "iso:country":"NZ",
    "sg:address":"PO Box 32 ",
    "sg:city":"Manutuke",
    "sg:orig_category":"Home And Garden: Gardening: Services: Landscaping",
    "sg:phone":"+64 274 574 561",
    "wof:name":"Dirtworx (Atkins Kontracting)",
    "wof:placetype":"venue"
},
  "geometry": {"coordinates":[177.912506,-38.682064],"type":"Point"}
}