{
  "type": "Feature",
  "properties": {
    "addr:full":"6 Findlay St Ellerslie  Auckland Auckland",
    "addr:housenumber":"6",
    "addr:street":"Findlay St",
    "iso:country":"NZ",
    "sg:address":"6 Findlay St Ellerslie ",
    "sg:city":"Auckland",
    "sg:classifiers":[
        {
            "category":"Retail",
            "subcategory":"Driving School",
            "type":"Services"
        }
    ],
    "sg:phone":"+64 9-579 0944",
    "sg:province":"Auckland",
    "sg:tags":[
        "riding",
        "training",
        "education",
        "driver",
        "motorcycle"
    ],
    "wof:name":"Auckland Motorcycle Club Inc",
    "wof:placetype":"venue"
},
  "geometry": {"coordinates":[174.80921900000001,-36.898754],"type":"Point"}
}