{
  "type": "Feature",
  "properties": {
    "iso:country":"NZ",
    "sg:address":"cnr Rugby & Mountain Rds ",
    "sg:city":"Tariki",
    "sg:classifiers":[
        {
            "category":"Wholesale",
            "subcategory":"Auto Parts",
            "type":"Manufacturing & Wholesale Goods"
        }
    ],
    "sg:phone":"+64 6-762 4796",
    "sg:tags":[
        "automotive",
        "supply"
    ],
    "sg:website":"http://www.taranakitruckwreckers.co.nz",
    "wof:name":"Taranaki Truck Wreckers Ltd",
    "wof:placetype":"venue"
},
  "geometry": {"coordinates":[174.23223899999999,-39.248798],"type":"Point"}
}