{
  "type": "Feature",
  "properties": {
    "addr:full":"21 Robinson Rd  Whitianga",
    "addr:housenumber":"21",
    "addr:street":"Robinson Rd",
    "iso:country":"NZ",
    "sg:address":"21 Robinson Rd ",
    "sg:city":"Whitianga",
    "sg:classifiers":[
        {
            "category":"Education",
            "subcategory":"University",
            "type":"Public Place"
        }
    ],
    "sg:phone":"+64 7-866 4802",
    "sg:tags":[
        "training",
        "instruction",
        "language"
    ],
    "sg:website":"http://www.activity.co.nz",
    "wof:name":"Coromandel Outdoor Language Centre",
    "wof:placetype":"venue"
},
  "geometry": {"coordinates":[175.698532,-36.843754],"type":"Point"}
}