{
  "type": "Feature",
  "properties": {
    "iso:country":"NZ",
    "sg:address":"PO Box 37996",
    "sg:city":"Parnell",
    "sg:classifiers":[
        {
            "category":"Professional",
            "subcategory":"Computer Services",
            "type":"Services"
        }
    ],
    "sg:postcode":"1052",
    "sg:website":"http://www.gopher.co.nz",
    "wof:name":"Gopher",
    "wof:placetype":"venue"
},
  "geometry": {"coordinates":[174.786381,-36.853476],"type":"Point"}
}