{
  "type": "Feature",
  "properties": {
    "iso:country":"NZ",
    "sg:address":"4 Maniapoto St ",
    "sg:city":"Hamilton",
    "sg:orig_category":"Shopping: Retail Stores: Batteries",
    "sg:phone":"+64 7-873 7373",
    "sg:province":"Waikato",
    "wof:name":"Deane Mark Auto Electrical",
    "wof:placetype":"venue"
},
  "geometry": {"coordinates":[-87.988968,34.142426],"type":"Point"}
}