{
  "type": "Feature",
  "properties": {
    "addr:full":"Old Bank Arcade & Chambers Lambton Quay  Wellington Wellington",
    "addr:street":"Lambton Quay",
    "iso:country":"NZ",
    "sg:address":"Old Bank Arcade & Chambers Lambton Quay ",
    "sg:city":"Wellington",
    "sg:orig_category":"Clothing And Fabric: Clothing: Clothing - Specialty",
    "sg:phone":"+64 4-922 0619",
    "sg:province":"Wellington",
    "wof:name":"QVB Cashmere Collection",
    "wof:placetype":"venue"
},
  "geometry": {"coordinates":[174.77543600000001,-41.283409],"type":"Point"}
}