{
  "type": "Feature",
  "properties": {
    "addr:full":"473 Great South Rd Papatoetoe  Auckland Auckland",
    "addr:housenumber":"473",
    "addr:street":"Great South Rd",
    "iso:country":"NZ",
    "sg:address":"473 Great South Rd Papatoetoe ",
    "sg:city":"Auckland",
    "sg:classifiers":[
        {
            "category":"Organizations",
            "subcategory":"Religious Organization",
            "type":"Services"
        }
    ],
    "sg:phone":"+64 9-277 7375",
    "sg:province":"Auckland",
    "sg:tags":[
        "funeral",
        "arrangement"
    ],
    "wof:name":"Martin Williams & Associates",
    "wof:placetype":"venue"
},
  "geometry": {"coordinates":[174.871567,-36.978191],"type":"Point"}
}