{
  "type": "Feature",
  "properties": {
    "addr:full":"494 Heads Rd  Wanganui Manawatu-Wanganui",
    "addr:housenumber":"494",
    "addr:street":"Heads Rd",
    "iso:country":"NZ",
    "sg:address":"494 Heads Rd ",
    "sg:city":"Wanganui",
    "sg:classifiers":[
        {
            "category":"Retail",
            "subcategory":"Auto Repair",
            "type":"Services"
        }
    ],
    "sg:phone":"+64 6-344 3444",
    "sg:province":"Manawatu-Wanganui",
    "sg:tags":[
        "automotive",
        "panel",
        "servicing",
        "beater"
    ],
    "wof:name":"Rods Repairs",
    "wof:placetype":"venue"
},
  "geometry": {"coordinates":[174.996307,-39.943192],"type":"Point"}
}