{
  "type": "Feature",
  "properties": {
    "iso:country":"NZ",
    "sg:address":"City Centre Arcade Trafalgar St ",
    "sg:city":"Nelson",
    "sg:classifiers":[
        {
            "category":"Personal",
            "subcategory":"Shoe Repair & Shine",
            "type":"Services"
        }
    ],
    "sg:phone":"+64 3-546 9054",
    "sg:province":"Nelson",
    "sg:tags":[
        "foot",
        "clothing",
        "fabric",
        "wear"
    ],
    "wof:name":"Mister Minit",
    "wof:placetype":"venue"
},
  "geometry": {"coordinates":[-121.765488,39.553471],"type":"Point"}
}