{
  "type": "Feature",
  "properties": {
    "addr:full":"Wellington/Hutt Valley/Porirua Lower  Hutt Wellington",
    "iso:country":"NZ",
    "sg:address":"Wellington/Hutt Valley/Porirua Lower ",
    "sg:city":"Hutt",
    "sg:classifiers":[
        {
            "category":"Building & Trades",
            "subcategory":"Pest Control",
            "type":"Services"
        }
    ],
    "sg:phone":"+64 4-567 0871",
    "sg:province":"Wellington",
    "sg:tags":[
        "home",
        "garden"
    ],
    "sg:website":"http://www.preventapest.co.nz",
    "wof:name":"Prevent A Pest Limited",
    "wof:placetype":"venue"
},
  "geometry": {"coordinates":[174.904526,-41.208431],"type":"Point"}
}