{
  "type": "Feature",
  "properties": {
    "iso:country":"NZ",
    "sg:address":"6/41 Elliott St Papakura ",
    "sg:city":"Auckland",
    "sg:classifiers":[
        {
            "category":"Shopping",
            "subcategory":"Clothing, Apparel, & Fashions",
            "type":"Retail Goods"
        }
    ],
    "sg:phone":"+64 9-298 1180",
    "sg:province":"Auckland",
    "sg:tags":[
        "knitted",
        "clothing",
        "fabric"
    ],
    "wof:name":"Knit Affair Ltd",
    "wof:placetype":"venue"
},
  "geometry": {"coordinates":[174.93514999999999,-37.065578],"type":"Point"}
}