{
  "type": "Feature",
  "properties": {
    "addr:full":"194 Station Rd Penrose  Auckland Auckland",
    "addr:housenumber":"194",
    "addr:street":"Station Rd",
    "iso:country":"NZ",
    "sg:address":"194 Station Rd Penrose ",
    "sg:city":"Auckland",
    "sg:orig_category":"Industrial: Coatings",
    "sg:phone":"+64 9-580 1400",
    "sg:province":"Auckland",
    "wof:name":"Trowel Trades Supa-Centre",
    "wof:placetype":"venue"
},
  "geometry": {"coordinates":[174.80775499999999,-36.914433],"type":"Point"}
}