{
  "type": "Feature",
  "properties": {
    "iso:country":"NZ",
    "sg:address":"PO Box 73 ",
    "sg:city":"Russell",
    "sg:classifiers":[
        {
            "category":"Recreation",
            "type":"Entertainment"
        }
    ],
    "sg:phone":"+64 25986720",
    "sg:tags":[
        "shopping",
        "hunting",
        "fishing",
        "retailers",
        "sport",
        "trip"
    ],
    "wof:name":"McGaugheys Sportfishing",
    "wof:placetype":"venue"
},
  "geometry": {"coordinates":[-87.79483,34.550571],"type":"Point"}
}