{
  "type": "Feature",
  "properties": {
    "addr:full":"17 Portage Rd New Lynn  Auckland Auckland",
    "addr:housenumber":"17",
    "addr:street":"Portage Rd",
    "iso:country":"NZ",
    "sg:address":"17 Portage Rd New Lynn ",
    "sg:city":"Auckland",
    "sg:classifiers":[
        {
            "category":"Banks & Credit Unions",
            "subcategory":"Investment Brokerage",
            "type":"Services"
        }
    ],
    "sg:phone":"+64 9-827 8188",
    "sg:province":"Auckland",
    "sg:tags":[
        "industrial",
        "cleaning",
        "maintenance"
    ],
    "wof:name":"Uchem NZ Ltd",
    "wof:placetype":"venue"
},
  "geometry": {"coordinates":[174.690033,-36.905331],"type":"Point"}
}