{
  "type": "Feature",
  "properties": {
    "addr:full":"30 Koromiko St Judea  Tauranga Bay of Plenty",
    "addr:housenumber":"30",
    "addr:street":"Koromiko St",
    "iso:country":"NZ",
    "sg:address":"30 Koromiko St Judea ",
    "sg:city":"Tauranga",
    "sg:orig_category":"Transport: Transportation: Refrigerated Transport",
    "sg:phone":"+64 7-578 9844",
    "sg:province":"Bay of Plenty",
    "wof:name":"B.O.P. Refrigerated Transport Ltd",
    "wof:placetype":"venue"
},
  "geometry": {"coordinates":[176.14236500000001,-37.695297],"type":"Point"}
}