{
  "type": "Feature",
  "properties": {
    "addr:full":"13 Udy St Petone Lower  Hutt Wellington",
    "addr:housenumber":"13",
    "addr:street":"Udy St",
    "iso:country":"NZ",
    "sg:address":"13 Udy St Petone Lower ",
    "sg:city":"Hutt",
    "sg:classifiers":[
        {
            "category":"Home & Garden",
            "subcategory":"Building Materials",
            "type":"Retail Goods"
        }
    ],
    "sg:phone":"+64 4-568 8856",
    "sg:province":"Wellington",
    "sg:tags":[
        "door",
        "fitting",
        "fittings"
    ],
    "wof:name":"Lummis Joinery Ltd",
    "wof:placetype":"venue"
},
  "geometry": {"coordinates":[174.87507600000001,-41.221291],"type":"Point"}
}