{
  "type": "Feature",
  "properties": {
    "addr:full":"15 Herekino St  Whangarei Northland",
    "addr:housenumber":"15",
    "addr:street":"Herekino St",
    "iso:country":"NZ",
    "sg:address":"15 Herekino St ",
    "sg:city":"Whangarei",
    "sg:classifiers":[
        {
            "category":"Banks & Credit Unions",
            "subcategory":"Investment Brokerage",
            "type":"Services"
        }
    ],
    "sg:phone":"+64 9-430 0030",
    "sg:province":"Northland",
    "sg:tags":[
        "automotive",
        "leasing",
        "sale"
    ],
    "sg:website":"http://www.yellowpages.co.nz/for/rowanindustries/dp33763.html",
    "wof:name":"Rowan Industries",
    "wof:placetype":"venue"
},
  "geometry": {"coordinates":[174.328247,-35.728104],"type":"Point"}
}