{
  "type": "Feature",
  "properties": {
    "iso:country":"NZ",
    "sg:address":"Lake Pukaki Lake ",
    "sg:city":"Tekapo",
    "sg:orig_category":"Sports And Leisure: Sports: Golf: Golf Courses",
    "sg:phone":"+64 3-680 6844",
    "wof:name":"Braemar Station Golfcross",
    "wof:placetype":"venue"
},
  "geometry": {"coordinates":[170.48287999999999,-44.00576],"type":"Point"}
}