{
  "type": "Feature",
  "properties": {
    "iso:country":"NZ",
    "sg:address":"54 Shotover St ",
    "sg:city":"Queenstown",
    "sg:classifiers":[
        {
            "category":"Bars & Pubs",
            "subcategory":"Nightclub",
            "type":"Food & Drink"
        }
    ],
    "sg:phone":"+64 3-442 7853",
    "sg:province":"Otago",
    "sg:tags":[
        "club",
        "night",
        "sport",
        "leisure",
        "entertainment"
    ],
    "wof:name":"Casbah Night Club",
    "wof:placetype":"venue"
},
  "geometry": {"coordinates":[-76.157791,38.990379],"type":"Point"}
}