{
  "type": "Feature",
  "properties": {
    "addr:full":"140 Otumoetai Rd Brookfield  Tauranga Bay of Plenty",
    "addr:housenumber":"140",
    "addr:street":"Otumoetai Rd",
    "iso:country":"NZ",
    "sg:address":"140 Otumoetai Rd Brookfield ",
    "sg:city":"Tauranga",
    "sg:classifiers":[
        {
            "category":"Food & Beverages",
            "subcategory":"Liquor & Beverages",
            "type":"Retail Goods"
        }
    ],
    "sg:phone":"+64 7-571 1029",
    "sg:province":"Bay of Plenty",
    "sg:tags":[
        "drink",
        "outlet"
    ],
    "sg:website":"http://www.lk.co.nz",
    "wof:name":"Liquor King",
    "wof:placetype":"venue"
},
  "geometry": {"coordinates":[176.13561999999999,-37.6894],"type":"Point"}
}