{
  "type": "Feature",
  "properties": {
    "addr:full":"PO Box 56377 Dominion Road  Auckland Bay of Plenty",
    "addr:housenumber":"po box",
    "addr:postcode":"56377",
    "addr:street":"Dominion Road",
    "iso:country":"NZ",
    "sg:address":"PO Box 56377 Dominion Road ",
    "sg:city":"Auckland",
    "sg:classifiers":[
        {
            "category":"Retail",
            "subcategory":"Driving School",
            "type":"Services"
        }
    ],
    "sg:phone":"+64 9-302 3456",
    "sg:province":"Bay of Plenty",
    "sg:tags":[
        "training",
        "education",
        "driver"
    ],
    "wof:name":"A 1 Driving School Ltd",
    "wof:placetype":"venue"
},
  "geometry": {"coordinates":[-119.10457599999999,36.597755],"type":"Point"}
}