{
  "type": "Feature",
  "properties": {
    "addr:full":"464 New North Rd Kingsland  Auckland Auckland",
    "addr:housenumber":"464",
    "addr:street":"New North Rd",
    "iso:country":"NZ",
    "sg:address":"464 New North Rd Kingsland ",
    "sg:city":"Auckland",
    "sg:orig_category":"Shopping: Sports Retailers: Sports Goods: Sportswear",
    "sg:phone":"+64 9-815 2020",
    "sg:province":"Auckland",
    "wof:name":"TYT Active Wear Clothing",
    "wof:placetype":"venue"
},
  "geometry": {"coordinates":[174.74400299999999,-36.872387],"type":"Point"}
}