{
  "type": "Feature",
  "properties": {
    "addr:full":"Puketotara Rd R D 2  Kerikeri Auckland",
    "addr:housenumber":"2 kerikeri",
    "addr:street":"Puketotara Rd R D",
    "iso:country":"NZ",
    "sg:address":"Puketotara Rd R D 2 ",
    "sg:city":"Kerikeri",
    "sg:orig_category":"Farming: Agriculture: Agricultural Contractors",
    "sg:phone":"+64 9-407 9464",
    "sg:province":"Auckland",
    "wof:name":"Jacobs Contracting",
    "wof:placetype":"venue"
},
  "geometry": {"coordinates":[173.949905,-35.226269],"type":"Point"}
}