{
  "type": "Feature",
  "properties": {
    "addr:full":"24-46 Collins St Addington  Christchurch Canterbury",
    "addr:housenumber":"24-46",
    "addr:street":"Collins St",
    "iso:country":"NZ",
    "sg:address":"24-46 Collins St Addington ",
    "sg:city":"Christchurch",
    "sg:classifiers":[
        {
            "category":"Home & Garden",
            "subcategory":"Building Materials",
            "type":"Retail Goods"
        }
    ],
    "sg:phone":"+64 3-338 3508",
    "sg:province":"Canterbury",
    "sg:tags":[
        "wooden",
        "product",
        "accessories"
    ],
    "wof:name":"Trewood Enterprises",
    "wof:placetype":"venue"
},
  "geometry": {"coordinates":[172.616882,-43.54594],"type":"Point"}
}