{
  "type": "Feature",
  "properties": {
    "iso:country":"NZ",
    "sg:address":"96 a Harbour View Rd Point Chevalier ",
    "sg:city":"Auckland",
    "sg:classifiers":[
        {
            "category":"Personal",
            "type":"Services"
        }
    ],
    "sg:phone":"+64 9-845 0093",
    "sg:province":"Auckland",
    "sg:tags":[
        "diet",
        "reduction",
        "health",
        "beauty",
        "weight"
    ],
    "wof:name":"Healthy Body Systems",
    "wof:placetype":"venue"
},
  "geometry": {"coordinates":[174.702713,-36.854813],"type":"Point"}
}