{
  "type": "Feature",
  "properties": {
    "addr:full":"140 Hugo Johnston Dve Penrose  Auckland Auckland",
    "addr:housenumber":"140",
    "addr:street":"Hugo Johnston",
    "iso:country":"NZ",
    "sg:address":"140 Hugo Johnston Dve Penrose ",
    "sg:city":"Auckland",
    "sg:classifiers":[
        {
            "category":"Food & Beverages",
            "subcategory":"Meat & Fish",
            "type":"Retail Goods"
        }
    ],
    "sg:phone":"+64 9-525 1459",
    "sg:province":"Auckland",
    "sg:tags":[
        "drink"
    ],
    "wof:name":"Garrett International Meats Ltd",
    "wof:placetype":"venue"
},
  "geometry": {"coordinates":[174.825851,-36.927216],"type":"Point"}
}