{
  "type": "Feature",
  "properties": {
    "addr:full":"Linden, Tawa, Porirua  Wellington Wellington",
    "iso:country":"NZ",
    "sg:address":"Linden, Tawa, Porirua ",
    "sg:city":"Wellington",
    "sg:classifiers":[
        {
            "category":"Professional",
            "type":"Services"
        }
    ],
    "sg:phone":"+64 4-939 8886",
    "sg:province":"Wellington",
    "sg:tags":[
        "home",
        "cleaning",
        "help",
        "garden"
    ],
    "wof:name":"Capital Nursing & Home Care",
    "wof:placetype":"venue"
},
  "geometry": {"coordinates":[174.836197,-41.14204],"type":"Point"}
}