{
  "type": "Feature",
  "properties": {
    "iso:country":"NZ",
    "sg:address":"Dawson St ",
    "sg:city":"Timaru",
    "sg:classifiers":[
        {
            "category":"Farming",
            "subcategory":"Fish & Marine Products",
            "type":"Manufacturing & Wholesale Goods"
        }
    ],
    "sg:phone":"+64 3-684 7159",
    "sg:province":"Canterbury",
    "sg:tags":[
        "-",
        "boat",
        "transport"
    ],
    "wof:name":"Wallace & Cooper Engineering Ltd",
    "wof:placetype":"venue"
},
  "geometry": {"coordinates":[171.26142899999999,-44.392216],"type":"Point"}
}