{
  "type": "Feature",
  "properties": {
    "addr:full":"2/44 Scanlan St Grey Lynn  Auckland Auckland",
    "addr:housenumber":"2 / 44",
    "addr:street":"Scanlan St",
    "iso:country":"NZ",
    "sg:address":"2/44 Scanlan St Grey Lynn ",
    "sg:city":"Auckland",
    "sg:orig_category":"Clothing And Fabric: Fabric: Textiles",
    "sg:phone":"+64 9-360 2968",
    "sg:province":"Auckland",
    "wof:name":"Aradex Holdings NZ Ltd",
    "wof:placetype":"venue"
},
  "geometry": {"coordinates":[174.745926,-36.859409],"type":"Point"}
}