{
  "type": "Feature",
  "properties": {
    "addr:full":"859 Waikari Valley Rd Waikari  Amberley Canterbury",
    "addr:housenumber":"859",
    "addr:street":"Waikari Valley Rd;Amberley",
    "iso:country":"NZ",
    "sg:address":"859 Waikari Valley Rd Waikari ",
    "sg:city":"Amberley",
    "sg:orig_category":"Sports And Leisure: Sports: Equestrian",
    "sg:phone":"+64 3-314 4008",
    "sg:province":"Canterbury",
    "wof:name":"Slade Farm",
    "wof:placetype":"venue"
},
  "geometry": {"coordinates":[172.700806,-42.9678],"type":"Point"}
}