{
  "type": "Feature",
  "properties": {
    "addr:full":"299 B Queen St Richmond  Nelson Nelson",
    "addr:housenumber":"299 b",
    "addr:street":"Queen St",
    "iso:country":"NZ",
    "sg:address":"299 B Queen St Richmond ",
    "sg:city":"Nelson",
    "sg:classifiers":[
        {
            "category":"Home & Garden",
            "subcategory":"Furniture",
            "type":"Retail Goods"
        }
    ],
    "sg:phone":"+64 3-544 7299",
    "sg:province":"Nelson",
    "sg:tags":[
        "furniture/furnishings",
        "furnishing"
    ],
    "wof:name":"Acquisitions Richmond Ltd",
    "wof:placetype":"venue"
},
  "geometry": {"coordinates":[-121.765488,39.553471],"type":"Point"}
}