{
  "type": "Feature",
  "properties": {
    "addr:full":"Rotorua Private Bag 31914 Lower  Hutt Wellington",
    "addr:postcode":"31914",
    "addr:street":"Rotorua;Bag",
    "iso:country":"NZ",
    "sg:address":"Rotorua Private Bag 31914 Lower ",
    "sg:city":"Hutt",
    "sg:classifiers":[
        {
            "category":"Education",
            "subcategory":"University",
            "type":"Public Place"
        }
    ],
    "sg:phone":"+64 508 650 200",
    "sg:province":"Wellington",
    "sg:tags":[
        "training",
        "college"
    ],
    "sg:website":"http://www.openpolytechnic.ac.nz",
    "wof:name":"Open Polytechnic of New Zealand",
    "wof:placetype":"venue"
},
  "geometry": {"coordinates":[174.90838600000001,-41.206631],"type":"Point"}
}