{
  "type": "Feature",
  "properties": {
    "iso:country":"NZ",
    "sg:address":"360 Queen St Auckland Central ",
    "sg:city":"Auckland",
    "sg:orig_category":"Shopping: Retail Stores: Books: Bookshops",
    "sg:phone":"+64 9-377 3496",
    "sg:province":"Auckland",
    "wof:name":"Bennetts Bookshops",
    "wof:placetype":"venue"
},
  "geometry": {"coordinates":[174.76400799999999,-36.852352],"type":"Point"}
}