{
  "type": "Feature",
  "properties": {
    "addr:full":"8 Pukekohatu St  Waitara",
    "addr:housenumber":"8",
    "addr:street":"Pukekohatu St",
    "iso:country":"NZ",
    "sg:address":"8 Pukekohatu St ",
    "sg:city":"Waitara",
    "sg:orig_category":"Shopping: Engravers",
    "sg:phone":"+64 6-754 8207",
    "wof:name":"Egmont Sign Engraving Co",
    "wof:placetype":"venue"
},
  "geometry": {"coordinates":[174.225281,-39.003975],"type":"Point"}
}