{
  "type": "Feature",
  "properties": {
    "addr:full":"PO Box 69173  Glendene Auckland",
    "addr:housenumber":"po box",
    "addr:postcode":"69173",
    "iso:country":"NZ",
    "sg:address":"PO Box 69173 ",
    "sg:city":"Glendene",
    "sg:classifiers":[
        {
            "category":"Sports & Exercise",
            "subcategory":"Athletic Track",
            "type":"Entertainment"
        }
    ],
    "sg:phone":"+64 800 872 243",
    "sg:province":"Auckland",
    "sg:tags":[
        "machine",
        "gaming",
        "leisure"
    ],
    "wof:name":"Pacitic Gaming Pty",
    "wof:placetype":"venue"
},
  "geometry": {"coordinates":[174.65448000000001,-36.886917],"type":"Point"}
}