{
  "type": "Feature",
  "properties": {
    "iso:country":"NZ",
    "sg:address":"PO Box 16-115 Wellington South ",
    "sg:city":"Wellington",
    "sg:classifiers":[
        {
            "category":"Professional",
            "subcategory":"Management & Consulting",
            "type":"Services"
        }
    ],
    "sg:phone":"+64 4-389 6611",
    "sg:province":"Wellington",
    "sg:tags":[
        "consultant",
        "training",
        "education"
    ],
    "wof:name":"Extraskills",
    "wof:placetype":"venue"
},
  "geometry": {"coordinates":[174.980042,-40.930645],"type":"Point"}
}