{
  "type": "Feature",
  "properties": {
    "addr:full":"Cnr Te Ngae & Allen Mills Rds  Rotorua Bay of Plenty",
    "addr:street":"Cnr Te;Mills",
    "iso:country":"NZ",
    "sg:address":"Cnr Te Ngae & Allen Mills Rds ",
    "sg:city":"Rotorua",
    "sg:classifiers":[
        {
            "category":"Professional",
            "subcategory":"Detective & Security Services",
            "type":"Services"
        }
    ],
    "sg:phone":"+64 7-345 9963",
    "sg:province":"Bay of Plenty",
    "sg:tags":[
        "services",
        "automotive",
        "warrant",
        "fitness"
    ],
    "wof:name":"Auto One",
    "wof:placetype":"venue"
},
  "geometry": {"coordinates":[176.24499499999999,-38.1418],"type":"Point"}
}