{
  "type": "Feature",
  "properties": {
    "iso:country":"NZ",
    "sg:address":"Unit F/9 Kellow Pl Manukau City ",
    "sg:city":"Auckland",
    "sg:orig_category":"Shopping: Sports Retailers: Water Sports: Diving Equipment",
    "sg:phone":"+64 9-262 0006",
    "sg:province":"Auckland",
    "wof:name":"Magnum Wetsuits Ltd",
    "wof:placetype":"venue"
},
  "geometry": {"coordinates":[174.881454,-36.98967],"type":"Point"}
}