{
  "type": "Feature",
  "properties": {
    "addr:full":"Refer to main Advert under Conservation & Environment Rotorua Bay of Plenty",
    "iso:country":"NZ",
    "sg:address":"Refer to main Advert under Conservation & Environment",
    "sg:city":"Rotorua",
    "sg:classifiers":[
        {
            "category":"Farming",
            "subcategory":"Fish & Marine Products",
            "type":"Manufacturing & Wholesale Goods"
        }
    ],
    "sg:phone":"+64 25791953",
    "sg:province":"Bay of Plenty",
    "sg:tags":[
        "-",
        "boat",
        "transport"
    ],
    "wof:name":"Aqua-Ag Air Boat Services",
    "wof:placetype":"venue"
},
  "geometry": {"coordinates":[176.24499499999999,-38.1418],"type":"Point"}
}