{
  "type": "Feature",
  "properties": {
    "iso:country":"NZ",
    "sg:address":"Office 2 1st Flr 46 Vickerman St PO Box 1003 ",
    "sg:city":"Nelson",
    "sg:orig_category":"Transport: Transportation: Container Services",
    "sg:phone":"+64 3-546 8487",
    "sg:province":"Nelson",
    "wof:name":"Specialised Container Services (Nelson) Ltd",
    "wof:placetype":"venue"
},
  "geometry": {"coordinates":[-121.765488,39.553471],"type":"Point"}
}