{
  "type": "Feature",
  "properties": {
    "iso:country":"NZ",
    "sg:address":"7 Sims Rd Penrose ",
    "sg:city":"Auckland",
    "sg:classifiers":[
        {
            "category":"Banks & Credit Unions",
            "subcategory":"Investment Brokerage",
            "type":"Services"
        }
    ],
    "sg:phone":"+64 9-579 5855",
    "sg:province":"Auckland",
    "sg:tags":[
        "automotive",
        "leasing",
        "sale"
    ],
    "sg:website":"http://www.yellowpages.co.nz/for/arobrosltd/dp25711.html",
    "wof:name":"Aro Bros Ltd",
    "wof:placetype":"venue"
},
  "geometry": {"coordinates":[174.824265,-36.916016],"type":"Point"}
}