{
  "type": "Feature",
  "properties": {
    "iso:country":"NZ",
    "sg:address":"Pakuranga ",
    "sg:city":"Auckland",
    "sg:orig_category":"Home And Garden: Gardening: Services: Lawnmowing Services",
    "sg:phone":"+64 9-577 4656",
    "sg:province":"Auckland",
    "wof:name":"Meadows Lawns & Landscapes",
    "wof:placetype":"venue"
},
  "geometry": {"coordinates":[174.87904399999999,-36.91584],"type":"Point"}
}