{
  "type": "Feature",
  "properties": {
    "addr:full":"29 Elliott St Papakura  Auckland Auckland",
    "addr:housenumber":"29",
    "addr:street":"Elliott St",
    "iso:country":"NZ",
    "sg:address":"29 Elliott St Papakura ",
    "sg:city":"Auckland",
    "sg:orig_category":"Automotive: Accessories: Car Security Systems",
    "sg:phone":"+64 9-299 7624",
    "sg:province":"Auckland",
    "wof:name":"Morris Auto Electrical",
    "wof:placetype":"venue"
},
  "geometry": {"coordinates":[174.93980400000001,-37.063332],"type":"Point"}
}