{
  "type": "Feature",
  "properties": {
    "iso:country":"NZ",
    "sg:address":"135 Alford Forest Rd ",
    "sg:city":"Ashburton",
    "sg:classifiers":[
        {
            "category":"Farming",
            "subcategory":"Farm",
            "type":"Manufacturing & Wholesale Goods"
        }
    ],
    "sg:phone":"+64 3-308 9419",
    "sg:province":"Canterbury",
    "sg:website":"http://www.kbservices.co.nz",
    "wof:name":"K B Irrigation",
    "wof:placetype":"venue"
},
  "geometry": {"coordinates":[-77.127831,39.012852],"type":"Point"}
}