{
  "type": "Feature",
  "properties": {
    "iso:country":"NZ",
    "sg:address":"5 Martin Pl Havelock North ",
    "sg:city":"Hastings",
    "sg:orig_category":"Industrial: Metal: Stainless Steel",
    "sg:phone":"+64 6-877 8633",
    "sg:province":"Hawke's Bay",
    "wof:name":"Payne Sheet-Metals Ltd",
    "wof:placetype":"venue"
},
  "geometry": {"coordinates":[176.878403,-39.665955],"type":"Point"}
}