{
  "type": "Feature",
  "properties": {
    "addr:full":"21 Puriri St New Lynn  Auckland Auckland",
    "addr:housenumber":"21",
    "addr:street":"Puriri St",
    "iso:country":"NZ",
    "sg:address":"21 Puriri St New Lynn ",
    "sg:city":"Auckland",
    "sg:orig_category":"Industrial: Services: Gasfitters",
    "sg:phone":"+64 9-827 5005",
    "sg:province":"Auckland",
    "wof:name":"King Plumbing",
    "wof:placetype":"venue"
},
  "geometry": {"coordinates":[174.68924000000001,-36.909386],"type":"Point"}
}