{
  "type": "Feature",
  "properties": {
    "addr:full":"830 New North Rd Mt Albert  Auckland Auckland",
    "addr:housenumber":"830",
    "addr:street":"New North Rd",
    "iso:country":"NZ",
    "sg:address":"830 New North Rd Mt Albert ",
    "sg:city":"Auckland",
    "sg:classifiers":[
        {
            "category":"Social Services",
            "subcategory":"Child Care",
            "type":"Services"
        }
    ],
    "sg:phone":"+64 9-846 6909",
    "sg:province":"Auckland",
    "sg:tags":[
        "home",
        "garden",
        "children"
    ],
    "wof:name":"Ferndale Kindergarten",
    "wof:placetype":"venue"
},
  "geometry": {"coordinates":[174.71987899999999,-36.882008],"type":"Point"}
}