{
  "type": "Feature",
  "properties": {
    "addr:full":"34 Taniwha Pl Bethlehem  Tauranga Bay of Plenty",
    "addr:housenumber":"34",
    "addr:street":"Taniwha Pl",
    "iso:country":"NZ",
    "sg:address":"34 Taniwha Pl Bethlehem ",
    "sg:city":"Tauranga",
    "sg:classifiers":[
        {
            "category":"Shopping",
            "subcategory":"Bicycles & Sporting Goods",
            "type":"Retail Goods"
        }
    ],
    "sg:phone":"+64 7-576 4233",
    "sg:province":"Bay of Plenty",
    "sg:tags":[
        "sport",
        "retailer"
    ],
    "sg:website":"http://www.kayaks.co.nz",
    "wof:name":"Waimarino Adventure Park & Kayak Shop",
    "wof:placetype":"venue"
},
  "geometry": {"coordinates":[176.098724,-37.698666],"type":"Point"}
}