{
  "type": "Feature",
  "properties": {
    "iso:country":"NZ",
    "sg:address":"61 Harrison St Allenton ",
    "sg:city":"Ashburton",
    "sg:orig_category":"Transport: Transportation: Postal Services",
    "sg:phone":"+64 3-308 2460",
    "sg:province":"Canterbury",
    "wof:name":"Allenton Post Shop",
    "wof:placetype":"venue"
},
  "geometry": {"coordinates":[171.743011,-43.887623],"type":"Point"}
}