{
  "type": "Feature",
  "properties": {
    "iso:country":"NZ",
    "sg:address":"42 Vestey Dve Mt Wellington ",
    "sg:city":"Auckland",
    "sg:orig_category":"Industrial: Engineering: Engineers - Automation",
    "sg:phone":"+64 9-573 3073",
    "sg:province":"Auckland",
    "sg:website":"http://www.apv.com",
    "wof:name":"APV New Zealand Ltd",
    "wof:placetype":"venue"
},
  "geometry": {"coordinates":[174.83029199999999,-36.909569],"type":"Point"}
}