{
  "type": "Feature",
  "properties": {
    "iso:country":"NZ",
    "sg:address":"23 Gaskin Pl Haumoana ",
    "sg:city":"Hastings",
    "sg:classifiers":[
        {
            "category":"Shopping",
            "subcategory":"Crafts & Fabrics",
            "type":"Retail Goods"
        }
    ],
    "sg:phone":"+64 6-875 0796",
    "sg:province":"Hawke's Bay",
    "sg:tags":[
        "sport",
        "art",
        "leisure",
        "hobbies"
    ],
    "wof:name":"Coastal Crafts",
    "wof:placetype":"venue"
},
  "geometry": {"coordinates":[176.94842499999999,-39.605137],"type":"Point"}
}