{
  "type": "Feature",
  "properties": {
    "iso:country":"NZ",
    "sg:address":"PO Box 706 ",
    "sg:city":"Queenstown",
    "sg:classifiers":[
        {
            "category":"Home & Garden",
            "subcategory":"Carpets & Floor Coverings",
            "type":"Retail Goods"
        }
    ],
    "sg:phone":"+64 3-442 3775",
    "sg:province":"Otago",
    "sg:tags":[
        "cleaning",
        "furniture"
    ],
    "wof:name":"ChemDry Remarkable",
    "wof:placetype":"venue"
},
  "geometry": {"coordinates":[-76.157791,38.990379],"type":"Point"}
}