{
  "type": "Feature",
  "properties": {
    "addr:full":"31 Broadway Ave Palmerston  Palmerston North Manawatu-Wanganui",
    "addr:housenumber":"31",
    "addr:street":"Broadway Ave",
    "iso:country":"NZ",
    "sg:address":"31 Broadway Ave Palmerston ",
    "sg:city":"Palmerston North",
    "sg:orig_category":"Clothing And Fabric: Clothing: Menswear",
    "sg:phone":"+64 6-359 0235",
    "sg:province":"Manawatu-Wanganui",
    "wof:name":"GQ Clothing",
    "wof:placetype":"venue"
},
  "geometry": {"coordinates":[175.61219800000001,-40.354183],"type":"Point"}
}