{
  "type": "Feature",
  "properties": {
    "iso:country":"NZ",
    "sg:address":"75 Birkenhead Ave Birkenhead ",
    "sg:city":"Auckland",
    "sg:orig_category":"Shopping: Accessories: Sunglasses",
    "sg:phone":"+64 9-480 2853",
    "sg:province":"Auckland",
    "wof:name":"Lucky Trent Sunglasses Shop",
    "wof:placetype":"venue"
},
  "geometry": {"coordinates":[174.72583,-36.810394],"type":"Point"}
}