{
  "type": "Feature",
  "properties": {
    "iso:country":"NZ",
    "sg:address":"cnr Austin St & Cadbury Rd Onekawa ",
    "sg:city":"Napier",
    "sg:classifiers":[
        {
            "category":"Home & Garden",
            "subcategory":"Building Materials",
            "type":"Retail Goods"
        }
    ],
    "sg:phone":"+64 6-843 8834",
    "sg:province":"Hawke's Bay",
    "sg:tags":[
        "builder",
        "related"
    ],
    "wof:name":"Homeworx Design & Build Ltd",
    "wof:placetype":"venue"
},
  "geometry": {"coordinates":[176.895981,-39.504452],"type":"Point"}
}