{
  "type": "Feature",
  "properties": {
    "iso:country":"NZ",
    "sg:address":"247 Stuart St ",
    "sg:city":"Dunedin",
    "sg:classifiers":[
        {
            "category":"Shopping",
            "subcategory":"Shoes",
            "type":"Retail Goods"
        }
    ],
    "sg:phone":"+64 3-477 8750",
    "sg:province":"Otago",
    "sg:tags":[
        "foot",
        "clothing",
        "fabric",
        "wear"
    ],
    "wof:name":"Ayers Shoe Repairs",
    "wof:placetype":"venue"
},
  "geometry": {"coordinates":[-82.784721,28.013355],"type":"Point"}
}