{
  "type": "Feature",
  "properties": {
    "iso:country":"NZ",
    "sg:address":"Bryant St Tinwald ",
    "sg:city":"Ashburton",
    "sg:orig_category":"Farming: Supplies: Stock Foods",
    "sg:phone":"+64 3-308 4388",
    "sg:province":"Canterbury",
    "wof:name":"Golden Stock Foods Limited",
    "wof:placetype":"venue"
},
  "geometry": {"coordinates":[171.71440100000001,-43.920185],"type":"Point"}
}