{
  "type": "Feature",
  "properties": {
    "addr:full":"29 Crummer Rd Grey Lynn  Auckland Auckland",
    "addr:housenumber":"29",
    "addr:street":"Crummer Rd",
    "iso:country":"NZ",
    "sg:address":"29 Crummer Rd Grey Lynn ",
    "sg:city":"Auckland",
    "sg:classifiers":[
        {
            "category":"Communications",
            "subcategory":"Television Station",
            "type":"Services"
        }
    ],
    "sg:phone":"+64 9-361 1308",
    "sg:province":"Auckland",
    "sg:tags":[
        "broadcasting"
    ],
    "wof:name":"Littlefish Productions",
    "wof:placetype":"venue"
},
  "geometry": {"coordinates":[174.748459,-36.860081],"type":"Point"}
}