{
  "type": "Feature",
  "properties": {
    "iso:country":"NZ",
    "sg:address":"230 Jervois Rd Herne Bay ",
    "sg:city":"Auckland",
    "sg:orig_category":"Shopping: Retail Stores: Books: Books - Secondhand",
    "sg:phone":"+64 9-376 3978",
    "sg:province":"Auckland",
    "wof:name":"Dominion Books",
    "wof:placetype":"venue"
},
  "geometry": {"coordinates":[174.730164,-36.848415],"type":"Point"}
}