{
  "type": "Feature",
  "properties": {
    "addr:full":"182 Balmoral Rd  Auckland Auckland",
    "addr:housenumber":"182",
    "addr:street":"Balmoral Rd",
    "iso:country":"NZ",
    "sg:address":"182 Balmoral Rd ",
    "sg:city":"Auckland",
    "sg:orig_category":"Shopping: Retail Stores: Department Stores",
    "sg:phone":"+64 9-623 0736",
    "sg:province":"Auckland",
    "wof:name":"The Warehouse Ltd",
    "wof:placetype":"venue"
},
  "geometry": {"coordinates":[174.747849,-36.887333],"type":"Point"}
}