{
  "type": "Feature",
  "properties": {
    "iso:country":"NZ",
    "sg:address":"2 Stone St Miramar ",
    "sg:city":"Wellington",
    "sg:classifiers":[
        {
            "category":"Retail",
            "subcategory":"Auto Repair",
            "type":"Services"
        }
    ],
    "sg:phone":"+64 4-388 1947",
    "sg:province":"Wellington",
    "sg:tags":[
        "automotive",
        "electric",
        "servicing"
    ],
    "wof:name":"Miramar Auto Services 2000 Ltd",
    "wof:placetype":"venue"
},
  "geometry": {"coordinates":[174.81385800000001,-41.318298],"type":"Point"}
}