{
  "type": "Feature",
  "properties": {
    "addr:full":"Finlayson Rd Maramarua  Pukekohe Auckland",
    "addr:street":"Finlayson Rd",
    "iso:country":"NZ",
    "sg:address":"Finlayson Rd Maramarua ",
    "sg:city":"Pukekohe",
    "sg:classifiers":[
        {
            "category":"Utilities",
            "subcategory":"Fuel Oil & Lpg",
            "type":"Services"
        }
    ],
    "sg:phone":"+64 9-232 5649",
    "sg:province":"Auckland",
    "sg:tags":[
        "coal",
        "energy",
        "industrial",
        "mine",
        "utilities"
    ],
    "wof:name":"Glencoal Energy Ltd",
    "wof:placetype":"venue"
},
  "geometry": {"coordinates":[175.18748500000001,-37.281212],"type":"Point"}
}