{
  "type": "Feature",
  "properties": {
    "addr:full":"332/63 Remuera Rd Remuera  Auckland Auckland",
    "addr:housenumber":"332 / 63",
    "addr:street":"Remuera Rd",
    "iso:country":"NZ",
    "sg:address":"332/63 Remuera Rd Remuera ",
    "sg:city":"Auckland",
    "sg:classifiers":[
        {
            "category":"Shopping",
            "subcategory":"Beauty & Cosmetics",
            "type":"Retail Goods"
        }
    ],
    "sg:phone":"+64 9-309 0992",
    "sg:province":"Auckland",
    "sg:tags":[
        "health",
        "perfumery"
    ],
    "sg:website":"http://www.artaface.com",
    "wof:name":"Art A Face Cosmetics Limited",
    "wof:placetype":"venue"
},
  "geometry": {"coordinates":[174.77979999999999,-36.871952],"type":"Point"}
}