{
  "type": "Feature",
  "properties": {
    "iso:country":"NZ",
    "sg:address":"699 Main St Palmerston ",
    "sg:city":"Palmerston North",
    "sg:classifiers":[
        {
            "category":"Food & Beverages",
            "subcategory":"Liquor & Beverages",
            "type":"Retail Goods"
        }
    ],
    "sg:phone":"+64 6-355 0005",
    "sg:province":"Manawatu-Wanganui",
    "sg:tags":[
        "drink",
        "maker",
        "wine"
    ],
    "wof:name":"Montana Wines Limited",
    "wof:placetype":"venue"
},
  "geometry": {"coordinates":[175.615463,-40.354267],"type":"Point"}
}