{
  "type": "Feature",
  "properties": {
    "iso:country":"NZ",
    "sg:address":"Collins Rd ",
    "sg:city":"Hamilton",
    "sg:classifiers":[
        {
            "category":"Home & Garden",
            "subcategory":"Home Furnishings",
            "type":"Retail Goods"
        }
    ],
    "sg:phone":"+64 7-843 3900",
    "sg:province":"Waikato",
    "sg:tags":[
        "furniture/furnishings",
        "bedding",
        "bed"
    ],
    "wof:name":"Restwood NZ Limited Manufacturing",
    "wof:placetype":"venue"
},
  "geometry": {"coordinates":[-75.432205,42.771919],"type":"Point"}
}