{
  "type": "Feature",
  "properties": {
    "addr:full":"450 Mountain Rd Lepperton New  Plymouth Taranaki",
    "addr:housenumber":"450",
    "addr:street":"Mountain Rd",
    "iso:country":"NZ",
    "sg:address":"450 Mountain Rd Lepperton New ",
    "sg:city":"Plymouth",
    "sg:classifiers":[
        {
            "category":"Professional",
            "type":"Services"
        }
    ],
    "sg:phone":"+64 6-752 0809",
    "sg:province":"Taranaki",
    "sg:tags":[
        "function",
        "entertainment",
        "leisure",
        "planning",
        "party",
        "sport"
    ],
    "wof:name":"Tawa Glen Cafe & Garden Centre",
    "wof:placetype":"venue"
},
  "geometry": {"coordinates":[-116.81972500000001,43.97221],"type":"Point"}
}