{
  "type": "Feature",
  "properties": {
    "addr:full":"115 Fitzherbert St  Featherston",
    "addr:housenumber":"115",
    "addr:street":"Fitzherbert St",
    "iso:country":"NZ",
    "sg:address":"115 Fitzherbert St ",
    "sg:city":"Featherston",
    "sg:orig_category":"Sports And Leisure: Entertainment: Entertainers",
    "sg:phone":"+64 6-308 6042",
    "wof:name":"Pai",
    "wof:placetype":"venue"
},
  "geometry": {"coordinates":[-95.472374,35.086483],"type":"Point"}
}