{
  "type": "Feature",
  "properties": {
    "iso:country":"NZ",
    "sg:address":"127 Te Mata Rd Havelock North ",
    "sg:city":"Hastings",
    "sg:classifiers":[
        {
            "category":"Professional",
            "subcategory":"Art Services",
            "type":"Services"
        }
    ],
    "sg:phone":"+64 6-877 7122",
    "sg:province":"Hawke's Bay",
    "sg:tags":[
        "personal",
        "photographer",
        "services",
        "garden",
        "home"
    ],
    "wof:name":"Brenton Hall Photography",
    "wof:placetype":"venue"
},
  "geometry": {"coordinates":[176.89163199999999,-39.666344],"type":"Point"}
}