{
  "type": "Feature",
  "properties": {
    "iso:country":"NZ",
    "sg:address":"59 Broadway ",
    "sg:city":"Kaikohe",
    "sg:orig_category":"Health And Beauty: Specialists: Physiotherapists",
    "sg:phone":"+64 9-401 0750",
    "sg:province":"Manawatu-Wanganui",
    "wof:name":"Physiotherapy North Kaikohe",
    "wof:placetype":"venue"
},
  "geometry": {"coordinates":[173.801071,-35.407009],"type":"Point"}
}