{
  "type": "Feature",
  "properties": {
    "addr:full":"PO Box 65352 Mairangi Bay  Kaukapakapa Auckland",
    "addr:housenumber":"po box",
    "addr:street":"65352",
    "iso:country":"NZ",
    "sg:address":"PO Box 65352 Mairangi Bay ",
    "sg:city":"Kaukapakapa",
    "sg:orig_category":"Industrial: Chemicals And Compounds: Pharmaceuticals",
    "sg:phone":"+64 9-420 4242",
    "sg:province":"Auckland",
    "wof:name":"B & B (Buxton-Bennetts) Marketing",
    "wof:placetype":"venue"
},
  "geometry": {"coordinates":[174.502365,-36.618408],"type":"Point"}
}