{
  "type": "Feature",
  "properties": {
    "iso:country":"NZ",
    "sg:address":"61 Church St Onehunga ",
    "sg:city":"Auckland",
    "sg:classifiers":[
        {
            "category":"Utilities",
            "subcategory":"Sewage",
            "type":"Services"
        }
    ],
    "sg:phone":"+64 9-634 1166",
    "sg:province":"Auckland",
    "sg:tags":[
        "home",
        "tank",
        "garden",
        "septic"
    ],
    "wof:name":"ECO Solutions",
    "wof:placetype":"venue"
},
  "geometry": {"coordinates":[174.782303,-36.923317],"type":"Point"}
}