{
  "type": "Feature",
  "properties": {
    "addr:full":"8 Piermark Dve N.H.I.E Albany  Auckland Auckland",
    "addr:housenumber":"8",
    "addr:street":"Piermark Dve N.H.I.E",
    "iso:country":"NZ",
    "sg:address":"8 Piermark Dve N.H.I.E Albany ",
    "sg:city":"Auckland",
    "sg:classifiers":[
        {
            "category":"Shopping",
            "subcategory":"Pharmacy",
            "type":"Retail Goods"
        }
    ],
    "sg:phone":"+64 9-415 4800",
    "sg:province":"Auckland",
    "sg:tags":[
        "products",
        "medical",
        "health",
        "beauty",
        "supply"
    ],
    "wof:name":"InterMed Medical Ltd",
    "wof:placetype":"venue"
},
  "geometry": {"coordinates":[174.70323200000001,-36.748043],"type":"Point"}
}