{
  "type": "Feature",
  "properties": {
    "iso:country":"NZ",
    "sg:address":"136 Adelaide Rd Newtown ",
    "sg:city":"Wellington",
    "sg:orig_category":"Industrial: Metal: Stainless Steel",
    "sg:phone":"+64 4-380 2000",
    "sg:province":"Wellington",
    "wof:name":"Kia Ora Sheetmetal Ltd",
    "wof:placetype":"venue"
},
  "geometry": {"coordinates":[174.777908,-41.30727],"type":"Point"}
}