{
  "type": "Feature",
  "properties": {
    "iso:country":"NZ",
    "sg:address":"148 Wordsworth St Sydenham ",
    "sg:city":"Christchurch",
    "sg:classifiers":[
        {
            "category":"Manufacturing",
            "subcategory":"Food",
            "type":"Manufacturing & Wholesale Goods"
        }
    ],
    "sg:phone":"+64 3-379 7044",
    "sg:province":"Canterbury",
    "sg:tags":[
        "drink",
        "-",
        "manufacturer"
    ],
    "wof:name":"Food Group Ltd",
    "wof:placetype":"venue"
},
  "geometry": {"coordinates":[172.641907,-43.544857],"type":"Point"}
}