{
  "type": "Feature",
  "properties": {
    "addr:full":"Produce Park, 500 Mt Wellington Hwy Mt Wellington  Auckland Auckland",
    "addr:housenumber":"500",
    "addr:street":"Mt Wellington Hwy",
    "iso:country":"NZ",
    "sg:address":"Produce Park, 500 Mt Wellington Hwy Mt Wellington ",
    "sg:city":"Auckland",
    "sg:classifiers":[
        {
            "category":"Coffee & Tea",
            "type":"Food & Drink"
        }
    ],
    "sg:phone":"+64 9-573 0880",
    "sg:province":"Auckland",
    "sg:tags":[
        "vegetable",
        "fruit",
        "veges"
    ],
    "wof:name":"Freshmax Limited",
    "wof:placetype":"venue"
},
  "geometry": {"coordinates":[174.83029199999999,-36.909569],"type":"Point"}
}