{
  "type": "Feature",
  "properties": {
    "addr:full":"48 Perth St  Oamaru Otago",
    "addr:housenumber":"48",
    "addr:street":"Perth St",
    "iso:country":"NZ",
    "sg:address":"48 Perth St ",
    "sg:city":"Oamaru",
    "sg:classifiers":[
        {
            "category":"Building & Trades",
            "subcategory":"Plumbing",
            "type":"Services"
        }
    ],
    "sg:phone":"+64 3-434 8472",
    "sg:province":"Otago",
    "sg:tags":[
        "home",
        "plumber",
        "garden",
        "related"
    ],
    "wof:name":"Jamieson (Warren) Plumbing",
    "wof:placetype":"venue"
},
  "geometry": {"coordinates":[170.95845,-45.109322],"type":"Point"}
}