{
  "type": "Feature",
  "properties": {
    "iso:country":"NZ",
    "sg:address":"cnr Clyde & Tweed Sts ",
    "sg:city":"Invercargill",
    "sg:orig_category":"Automotive: General Services: Rental Vehicles",
    "sg:phone":"+64 3-214 5179",
    "sg:province":"Southland",
    "sg:website":"http://www.nzrentacar.co.nz",
    "wof:name":"New Zealand Rent A Car",
    "wof:placetype":"venue"
},
  "geometry": {"coordinates":[168.35217299999999,-46.41185],"type":"Point"}
}