{
  "type": "Feature",
  "properties": {
    "iso:country":"NZ",
    "sg:address":"650 Airport Rd ",
    "sg:city":"Hamilton",
    "sg:orig_category":"Transport: Transportation: Transport Operators",
    "sg:phone":"+64 7-856 8511",
    "sg:province":"Waikato",
    "wof:name":"Johnson's House Removal Co Ltd",
    "wof:placetype":"venue"
},
  "geometry": {"coordinates":[-87.996468,34.11792],"type":"Point"}
}