{
  "type": "Feature",
  "properties": {
    "addr:full":"180 Main Rd Redcliffs  Christchurch Canterbury",
    "addr:housenumber":"180",
    "addr:street":"Main Rd",
    "iso:country":"NZ",
    "sg:address":"180 Main Rd Redcliffs ",
    "sg:city":"Christchurch",
    "sg:orig_category":"Farming: Services: Veterinarians",
    "sg:phone":"+64 3-384 4288",
    "sg:province":"Canterbury",
    "wof:name":"Redcliffs Animal Medical Centre",
    "wof:placetype":"venue"
},
  "geometry": {"coordinates":[172.738235,-43.561607],"type":"Point"}
}