{
  "type": "Feature",
  "properties": {
    "iso:country":"NZ",
    "sg:address":"Kimbolton Rd R D 7 Feilding ",
    "sg:city":"Cheltenham",
    "sg:orig_category":"Education And Training: General: Schools",
    "sg:phone":"+64 6-328 9744",
    "wof:name":"Kiwitea School",
    "wof:placetype":"venue"
},
  "geometry": {"coordinates":[175.660645,-40.13839],"type":"Point"}
}