{
  "type": "Feature",
  "properties": {
    "addr:full":"18 Kitchener St  Martinborough",
    "addr:housenumber":"18",
    "addr:street":"Kitchener St",
    "iso:country":"NZ",
    "sg:address":"18 Kitchener St ",
    "sg:city":"Martinborough",
    "sg:classifiers":[
        {
            "category":"Landmark",
            "subcategory":"Tourist Information",
            "type":"Public Place"
        }
    ],
    "sg:phone":"+64 6-306 9043",
    "sg:tags":[
        "services",
        "travel",
        "tourism"
    ],
    "wof:name":"Tourism Wairarapa Visitor Information Centres",
    "wof:placetype":"venue"
},
  "geometry": {"coordinates":[175.456345,-41.21529],"type":"Point"}
}