{
  "type": "Feature",
  "properties": {
    "addr:full":"22 Elizabeth St  Timaru Canterbury",
    "addr:housenumber":"22",
    "addr:street":"Elizabeth St",
    "iso:country":"NZ",
    "sg:address":"22 Elizabeth St ",
    "sg:city":"Timaru",
    "sg:classifiers":[
        {
            "category":"Health Services",
            "subcategory":"Clinic",
            "type":"Services"
        }
    ],
    "sg:phone":"+64 3-688 9815",
    "sg:province":"Canterbury",
    "sg:tags":[
        "medical",
        "beauty"
    ],
    "wof:name":"Family Health Clinic",
    "wof:placetype":"venue"
},
  "geometry": {"coordinates":[171.24662799999999,-44.394917],"type":"Point"}
}