{
  "type": "Feature",
  "properties": {
    "addr:full":"43 Pandora Rd  Napier Hawke's Bay",
    "addr:housenumber":"43",
    "addr:street":"Pandora Rd",
    "iso:country":"NZ",
    "sg:address":"43 Pandora Rd ",
    "sg:city":"Napier",
    "sg:orig_category":"Transport: Boats And Marine: Products: Outboard Motors",
    "sg:phone":"+64 6-835 9718",
    "sg:province":"Hawke's Bay",
    "sg:website":"http://www.firmansmarine.co.nz",
    "wof:name":"Firmans Marine",
    "wof:placetype":"venue"
},
  "geometry": {"coordinates":[176.89063999999999,-39.486584],"type":"Point"}
}