{
  "type": "Feature",
  "properties": {
    "iso:country":"NZ",
    "sg:address":"57 Hanover St ",
    "sg:city":"Dunedin",
    "sg:classifiers":[
        {
            "category":"Professional",
            "subcategory":"Art Services",
            "type":"Services"
        }
    ],
    "sg:phone":"+64 3-477 0211",
    "sg:province":"Otago",
    "sg:tags":[
        "picture",
        "arts",
        "sport",
        "framing",
        "leisure"
    ],
    "sg:website":"http://www.art-zone.co.nz",
    "wof:name":"Art Zone",
    "wof:placetype":"venue"
},
  "geometry": {"coordinates":[-82.783485,28.04352],"type":"Point"}
}