{
  "type": "Feature",
  "properties": {
    "iso:country":"NZ",
    "sg:address":"429 Papanui Rd ",
    "sg:city":"Christchurch",
    "sg:orig_category":"Health And Beauty: Medical: Hospitals",
    "sg:phone":"+64 3-352 6169",
    "sg:province":"Canterbury",
    "wof:name":"Parklands Hospital Ltd",
    "wof:placetype":"venue"
},
  "geometry": {"coordinates":[172.611801,-43.501549],"type":"Point"}
}