{
  "type": "Feature",
  "properties": {
    "addr:full":"429 Papanui Rd  Christchurch Canterbury",
    "addr:housenumber":"429",
    "addr:street":"Papanui Rd",
    "iso:country":"NZ",
    "sg:address":"429 Papanui Rd ",
    "sg:city":"Christchurch",
    "sg:orig_category":"Health And Beauty: Medical: Hospitals",
    "sg:phone":"+64 3-352 6169",
    "sg:province":"Canterbury",
    "wof:name":"Parklands Hospital Ltd",
    "wof:placetype":"venue"
},
  "geometry": {"coordinates":[172.61180100000001,-43.501549],"type":"Point"}
}