{
  "type": "Feature",
  "properties": {
    "iso:country":"NZ",
    "sg:address":"PO Box 12005 ",
    "sg:city":"Dunedin",
    "sg:orig_category":"Food And Drink: Catering: Caterers",
    "sg:phone":"+64 3-467 2900",
    "sg:province":"Otago",
    "wof:name":"Thyme Out Restaurant",
    "wof:placetype":"venue"
},
  "geometry": {"coordinates":[-82.784721,28.013355],"type":"Point"}
}