{
  "type": "Feature",
  "properties": {
    "iso:country":"NZ",
    "sg:address":"227 Port Rd ",
    "sg:city":"Whangarei",
    "sg:classifiers":[
        {
            "category":"Social Services",
            "subcategory":"Job Training",
            "type":"Services"
        }
    ],
    "sg:phone":"+64 9-438 7019",
    "sg:province":"Northland",
    "sg:tags":[
        "education"
    ],
    "wof:name":"Fabrication & Welder Training Ltd (Fabweld)",
    "wof:placetype":"venue"
},
  "geometry": {"coordinates":[174.338699,-35.740723],"type":"Point"}
}