{
  "type": "Feature",
  "properties": {
    "iso:country":"NZ",
    "sg:address":"53 Hobson St Thorndon ",
    "sg:city":"Wellington",
    "sg:orig_category":"Education And Training: General: Schools",
    "sg:phone":"+64 4-473 7160",
    "sg:province":"Wellington",
    "sg:website":"http://www.qmc.school.nz",
    "wof:name":"Queen Margaret College",
    "wof:placetype":"venue"
},
  "geometry": {"coordinates":[174.78066999999999,-41.272518],"type":"Point"}
}