{
  "type": "Feature",
  "properties": {
    "addr:full":"10 Wilson St  Geraldine",
    "addr:housenumber":"10",
    "addr:street":"Wilson St",
    "iso:country":"NZ",
    "sg:address":"10 Wilson St ",
    "sg:city":"Geraldine",
    "sg:classifiers":[
        {
            "category":"Shopping",
            "subcategory":"Clothing, Apparel, & Fashions",
            "type":"Retail Goods"
        }
    ],
    "sg:phone":"+64 3-693 9820",
    "sg:tags":[
        "knitted",
        "clothing",
        "fabric"
    ],
    "wof:name":"The Giant Jersey",
    "wof:placetype":"venue"
},
  "geometry": {"coordinates":[-86.008263,34.360641],"type":"Point"}
}