{
  "type": "Feature",
  "properties": {
    "addr:full":"Chartwell Square  Hamilton Waikato",
    "addr:street":"Chartwell Square",
    "iso:country":"NZ",
    "sg:address":"Chartwell Square ",
    "sg:city":"Hamilton",
    "sg:orig_category":"Shopping: Accessories: Handbags",
    "sg:phone":"+64 7-854 8324",
    "sg:province":"Waikato",
    "wof:name":"Modern Bags",
    "wof:placetype":"venue"
},
  "geometry": {"coordinates":[175.27124000000001,-37.763653],"type":"Point"}
}