{
  "type": "Feature",
  "properties": {
    "iso:country":"NZ",
    "sg:address":"Manukau La ",
    "sg:city":"Pukekohe",
    "sg:orig_category":"Industrial: Metal: Stainless Steel",
    "sg:phone":"+64 9-238 7452",
    "sg:province":"Auckland",
    "wof:name":"Webster Engineering",
    "wof:placetype":"venue"
},
  "geometry": {"coordinates":[174.930252,-37.195728],"type":"Point"}
}