{
  "type": "Feature",
  "properties": {
    "addr:full":"201 Waimairi Rd Burnside  Christchurch Canterbury",
    "addr:housenumber":"201",
    "addr:street":"Waimairi Rd",
    "iso:country":"NZ",
    "sg:address":"201 Waimairi Rd Burnside ",
    "sg:city":"Christchurch",
    "sg:orig_category":"Transport: Transportation: Postal Services",
    "sg:phone":"+64 3-358 3531",
    "sg:province":"Canterbury",
    "wof:name":"Ilam Post Shop",
    "wof:placetype":"venue"
},
  "geometry": {"coordinates":[172.567993,-43.508888],"type":"Point"}
}