{
  "type": "Feature",
  "properties": {
    "addr:full":"Lv 2, 174 Cuba St  Wellington Wellington",
    "addr:housenumber":"174",
    "addr:street":"Cuba St",
    "iso:country":"NZ",
    "sg:address":"Lv 2, 174 Cuba St ",
    "sg:city":"Wellington",
    "sg:orig_category":"Home And Garden: Gardening: Services: Landscape Architects",
    "sg:phone":"+64 4-384 9727",
    "sg:province":"Wellington",
    "sg:website":"http://www.earthwork.co.nz",
    "wof:name":"Earthwork Landscape Architects",
    "wof:placetype":"venue"
},
  "geometry": {"coordinates":[-87.675285,40.541164],"type":"Point"}
}