{
  "type": "Feature",
  "properties": {
    "iso:country":"NZ",
    "sg:address":"Ponsonby ",
    "sg:city":"Auckland",
    "sg:classifiers":[
        {
            "category":"Personal",
            "subcategory":"Massage",
            "type":"Services"
        }
    ],
    "sg:phone":"+64 9-376 4958",
    "sg:province":"Auckland",
    "sg:tags":[
        "services",
        "health",
        "-",
        "beauty",
        "fitness"
    ],
    "wof:name":"Shiatsu for Health & Wellbeing",
    "wof:placetype":"venue"
},
  "geometry": {"coordinates":[174.74241599999999,-36.85326],"type":"Point"}
}