{
  "type": "Feature",
  "properties": {
    "addr:full":"849 Ngaruawahia Rd Te Kowhai  Hamilton Waikato",
    "addr:housenumber":"849",
    "addr:street":"Ngaruawahia Rd",
    "iso:country":"NZ",
    "sg:address":"849 Ngaruawahia Rd Te Kowhai ",
    "sg:city":"Hamilton",
    "sg:orig_category":"Transport: Transportation: Transport Operators",
    "sg:phone":"+64 7-829 7552",
    "sg:province":"Waikato",
    "wof:name":"Heavy Metal Haulage",
    "wof:placetype":"venue"
},
  "geometry": {"coordinates":[175.16984600000001,-37.73859],"type":"Point"}
}