{
  "type": "Feature",
  "properties": {
    "addr:full":"870 Mt Eden Rd Three Kings  Auckland Auckland",
    "addr:housenumber":"870",
    "addr:street":"Mt Eden Rd",
    "iso:country":"NZ",
    "sg:address":"870 Mt Eden Rd Three Kings ",
    "sg:city":"Auckland",
    "sg:orig_category":"Industrial: Services: Specialist Services: Laboratories",
    "sg:phone":"+64 9-625 8200",
    "sg:province":"Auckland",
    "wof:name":"TeleLab Ltd",
    "wof:placetype":"venue"
},
  "geometry": {"coordinates":[174.759094,-36.901539],"type":"Point"}
}