{
  "type": "Feature",
  "properties": {
    "iso:country":"NZ",
    "sg:address":"Lumsden Hospital Garden St ",
    "sg:city":"Lumsden",
    "sg:orig_category":"Health And Beauty: Specialists: Physiotherapists",
    "sg:phone":"+64 3-248 7750",
    "wof:name":"Lumsden Physiotherapy",
    "wof:placetype":"venue"
},
  "geometry": {"coordinates":[168.44451900000001,-45.737198],"type":"Point"}
}