{
  "type": "Feature",
  "properties": {
    "iso:country":"NZ",
    "sg:address":"PO Box 40 425 Upper Hutt ",
    "sg:city":"Wellington",
    "sg:orig_category":"Transport: Boats And Marine: Products: Marine Electronics",
    "sg:phone":"+64 4-939 2882",
    "sg:province":"Wellington",
    "wof:name":"Humminbird",
    "wof:placetype":"venue"
},
  "geometry": {"coordinates":[175.07037399999999,-41.124439],"type":"Point"}
}