{
  "type": "Feature",
  "properties": {
    "addr:full":"359 Oropi Rd R D 3  Tauranga Bay of Plenty",
    "addr:housenumber":"359;3",
    "addr:street":"Oropi Rd R D",
    "iso:country":"NZ",
    "sg:address":"359 Oropi Rd R D 3 ",
    "sg:city":"Tauranga",
    "sg:classifiers":[
        {
            "category":"Shopping",
            "subcategory":"Pets & Pet Supplies",
            "type":"Retail Goods"
        }
    ],
    "sg:phone":"+64 7-541 1411",
    "sg:province":"Bay of Plenty",
    "sg:tags":[
        "boarding",
        "garden",
        "pets",
        "catteries",
        "home",
        "kennel"
    ],
    "wof:name":"A Cat's World",
    "wof:placetype":"venue"
},
  "geometry": {"coordinates":[176.144745,-37.703156],"type":"Point"}
}