{
  "type": "Feature",
  "properties": {
    "addr:full":"PO Box 97181 Wiri  Auckland Auckland",
    "addr:housenumber":"po box 97181",
    "iso:country":"NZ",
    "sg:address":"PO Box 97181 Wiri ",
    "sg:city":"Auckland",
    "sg:classifiers":[
        {
            "category":"Home & Garden",
            "subcategory":"Garden Supply",
            "type":"Retail Goods"
        }
    ],
    "sg:phone":"+64 9-267 2265",
    "sg:province":"Auckland",
    "sg:tags":[
        "fencing",
        "outdoor",
        "contractor"
    ],
    "wof:name":"Electric Security Fencing Ltd",
    "wof:placetype":"venue"
},
  "geometry": {"coordinates":[174.86731,-37.001328],"type":"Point"}
}