{
  "type": "Feature",
  "properties": {
    "iso:country":"NZ",
    "sg:address":"10 Glendale Rd Glen Eden ",
    "sg:city":"Auckland",
    "sg:orig_category":"Shopping: Retail Stores: Books: Books - Secondhand",
    "sg:phone":"+64 9-818 6092",
    "sg:province":"Auckland",
    "wof:name":"Glen Eden Book Exchange",
    "wof:placetype":"venue"
},
  "geometry": {"coordinates":[174.650131,-36.910725],"type":"Point"}
}