{
  "type": "Feature",
  "properties": {
    "iso:country":"NZ",
    "sg:address":"66 Ayrshire Dve ",
    "sg:city":"Hamilton",
    "sg:classifiers":[
        {
            "category":"Home & Garden",
            "subcategory":"Household Appliances",
            "type":"Retail Goods"
        }
    ],
    "sg:phone":"+64 7-846 4920",
    "sg:province":"Waikato",
    "sg:tags":[
        "screen",
        "fittings",
        "insect"
    ],
    "wof:name":"Ahead Aluminium & Screens Ltd",
    "wof:placetype":"venue"
},
  "geometry": {"coordinates":[-4.052891,55.777321],"type":"Point"}
}