{
  "type": "Feature",
  "properties": {
    "iso:country":"NZ",
    "sg:address":"R D 3-O ",
    "sg:city":"Oamaru",
    "sg:orig_category":"Education And Training: General: Schools",
    "sg:phone":"+64 3-434 5940",
    "sg:province":"Otago",
    "wof:name":"Totara School",
    "wof:placetype":"venue"
},
  "geometry": {"coordinates":[170.92617799999999,-45.107178],"type":"Point"}
}