{
  "type": "Feature",
  "properties": {
    "iso:country":"NZ",
    "sg:address":"159 Maleme St ",
    "sg:city":"Tauranga",
    "sg:orig_category":"Farming: Horticulture: Horticultural Supplies",
    "sg:phone":"+64 7-541 2236",
    "sg:province":"Bay of Plenty",
    "wof:name":"Vision Tapes & Packaging Ltd",
    "wof:placetype":"venue"
},
  "geometry": {"coordinates":[176.127075,-37.734371],"type":"Point"}
}