{
  "type": "Feature",
  "properties": {
    "addr:full":"159 Maleme St  Tauranga Bay of Plenty",
    "addr:housenumber":"159",
    "addr:street":"Maleme St",
    "iso:country":"NZ",
    "sg:address":"159 Maleme St ",
    "sg:city":"Tauranga",
    "sg:orig_category":"Farming: Horticulture: Horticultural Supplies",
    "sg:phone":"+64 7-541 2236",
    "sg:province":"Bay of Plenty",
    "wof:name":"Vision Tapes & Packaging Ltd",
    "wof:placetype":"venue"
},
  "geometry": {"coordinates":[176.12707499999999,-37.734371],"type":"Point"}
}