{
  "type": "Feature",
  "properties": {
    "iso:country":"NZ",
    "sg:address":"S1/63 Cuba St ",
    "sg:city":"Wellington",
    "sg:classifiers":[
        {
            "category":"Shopping",
            "subcategory":"Beauty & Cosmetics",
            "type":"Retail Goods"
        }
    ],
    "sg:phone":"+64 4-384 2338",
    "sg:province":"Wellington",
    "sg:tags":[
        "health",
        "perfumery"
    ],
    "wof:name":"The Body Shop",
    "wof:placetype":"venue"
},
  "geometry": {"coordinates":[-85.910454,33.827946],"type":"Point"}
}