{
  "type": "Feature",
  "properties": {
    "iso:country":"NZ",
    "sg:address":"8 Raroa Rd Melling Lower ",
    "sg:city":"Hutt",
    "sg:classifiers":[
        {
            "category":"Banks & Credit Unions",
            "subcategory":"Investment Brokerage",
            "type":"Services"
        }
    ],
    "sg:phone":"+64 4-569 2058",
    "sg:province":"Wellington",
    "sg:tags":[
        "personal",
        "accountant",
        "chartered",
        "-",
        "finance"
    ],
    "wof:name":"Oak Chartered Accountants Limited",
    "wof:placetype":"venue"
},
  "geometry": {"coordinates":[174.90853899999999,-41.207291],"type":"Point"}
}