{
  "type": "Feature",
  "properties": {
    "iso:country":"NZ",
    "sg:address":"Queen St ",
    "sg:city":"Nelson",
    "sg:classifiers":[
        {
            "category":"Sports & Exercise",
            "subcategory":"Ski Resort",
            "type":"Entertainment"
        }
    ],
    "sg:phone":"+64 3-544 5744",
    "sg:province":"Nelson",
    "sg:tags":[
        "hobbies",
        "photographic",
        "leisure",
        "developing"
    ],
    "wof:name":"Photo One",
    "wof:placetype":"venue"
},
  "geometry": {"coordinates":[-121.765488,39.553471],"type":"Point"}
}