{
  "type": "Feature",
  "properties": {
    "iso:country":"NZ",
    "sg:address":"91 Queen St ",
    "sg:city":"Waimate",
    "sg:classifiers":[
        {
            "category":"Professional",
            "subcategory":"Art Services",
            "type":"Services"
        }
    ],
    "sg:phone":"+64 3-689 8149",
    "sg:tags":[
        "personal",
        "photographer",
        "services",
        "garden",
        "home"
    ],
    "wof:name":"Kolourcare Waimate",
    "wof:placetype":"venue"
},
  "geometry": {"coordinates":[171.044785,-44.735359],"type":"Point"}
}