{
  "type": "Feature",
  "properties": {
    "addr:full":"Edward St  Dargaville Northland",
    "addr:street":"Edward St",
    "iso:country":"NZ",
    "sg:address":"Edward St ",
    "sg:city":"Dargaville",
    "sg:classifiers":[
        {
            "category":"Utilities",
            "type":"Services"
        }
    ],
    "sg:phone":"+64 9-439 7257",
    "sg:province":"Northland",
    "sg:tags":[
        "industrial",
        "energy",
        "utilities",
        "coal",
        "wood",
        "coke"
    ],
    "wof:name":"The Woodbox Ltd",
    "wof:placetype":"venue"
},
  "geometry": {"coordinates":[173.859253,-35.939777],"type":"Point"}
}