{
  "type": "Feature",
  "properties": {
    "addr:full":"33 Fitzherbert St Petone Lower  Hutt Wellington",
    "addr:housenumber":"33",
    "addr:street":"Fitzherbert St",
    "iso:country":"NZ",
    "sg:address":"33 Fitzherbert St Petone Lower ",
    "sg:city":"Hutt",
    "sg:orig_category":"Shopping: Retail Stores: Stationery",
    "sg:phone":"+64 4-568 5018",
    "sg:province":"Wellington",
    "sg:website":"http://www.yellowpages.co.nz/for/pnp/dp53303.html",
    "wof:name":"Port Nicholson Packaging Ltd",
    "wof:placetype":"venue"
},
  "geometry": {"coordinates":[174.87417600000001,-41.225269],"type":"Point"}
}