{
  "type": "Feature",
  "properties": {
    "addr:full":"90 A Maleme St Greerton  Tauranga Bay of Plenty",
    "addr:housenumber":"90",
    "addr:street":"A Maleme St",
    "iso:country":"NZ",
    "sg:address":"90 A Maleme St Greerton ",
    "sg:city":"Tauranga",
    "sg:orig_category":"Industrial: Coatings",
    "sg:phone":"+64 7-541 3384",
    "sg:province":"Bay of Plenty",
    "wof:name":"Plaster Centre",
    "wof:placetype":"venue"
},
  "geometry": {"coordinates":[176.130234,-37.735504],"type":"Point"}
}