{
  "type": "Feature",
  "properties": {
    "addr:full":"442 Queen St  Masterton Wellington",
    "addr:housenumber":"442",
    "addr:street":"Queen St",
    "iso:country":"NZ",
    "sg:address":"442 Queen St ",
    "sg:city":"Masterton",
    "sg:orig_category":"Shopping: Retail Stores: Books: Bookshops",
    "sg:phone":"+64 6-377 4774",
    "sg:province":"Wellington",
    "wof:name":"Kuripuni Bookshop",
    "wof:placetype":"venue"
},
  "geometry": {"coordinates":[175.64851400000001,-40.958015],"type":"Point"}
}