{
  "type": "Feature",
  "properties": {
    "addr:full":"337 Ferguson St Palmerston  Palmerston North Manawatu-Wanganui",
    "addr:housenumber":"337",
    "addr:street":"Ferguson St Palmerston",
    "iso:country":"NZ",
    "sg:address":"337 Ferguson St Palmerston ",
    "sg:city":"Palmerston North",
    "sg:classifiers":[
        {
            "category":"Sports & Exercise",
            "subcategory":"Sports Center",
            "type":"Entertainment"
        }
    ],
    "sg:phone":"+64 6-354 9549",
    "sg:province":"Manawatu-Wanganui",
    "sg:tags":[
        "health",
        "beauty",
        "fitness"
    ],
    "wof:name":"Contours Health & Fitness Exclusively For Women",
    "wof:placetype":"venue"
},
  "geometry": {"coordinates":[175.61262500000001,-40.359699],"type":"Point"}
}