{
  "type": "Feature",
  "properties": {
    "iso:country":"NZ",
    "sg:address":"56 Esk Street ",
    "sg:city":"Invercargill",
    "sg:orig_category":"Shopping: Retail Stores: Stationery",
    "sg:phone":"+64 3-218 9337",
    "sg:province":"Southland",
    "wof:name":"Paper Plus",
    "wof:placetype":"venue"
},
  "geometry": {"coordinates":[168.349564,-46.411663],"type":"Point"}
}