{
  "type": "Feature",
  "properties": {
    "iso:country":"NZ",
    "sg:address":"The Production Village 26 Wright St Mt Cook ",
    "sg:city":"Wellington",
    "sg:orig_category":"Industrial: Consultancy",
    "sg:phone":"+64 4-939 2022",
    "sg:province":"Wellington",
    "wof:name":"Adam Simpson Projects",
    "wof:placetype":"venue"
},
  "geometry": {"coordinates":[174.772842,-41.301388],"type":"Point"}
}