{
  "type": "Feature",
  "properties": {
    "addr:full":"Fraser St  Timaru Canterbury",
    "addr:street":"Fraser St",
    "iso:country":"NZ",
    "sg:address":"Fraser St ",
    "sg:city":"Timaru",
    "sg:orig_category":"Farming: Horticulture: Grain And Seed",
    "sg:phone":"+64 3-684 3069",
    "sg:province":"Canterbury",
    "wof:name":"Seed Production (NZ) Ltd",
    "wof:placetype":"venue"
},
  "geometry": {"coordinates":[171.22584499999999,-44.39608],"type":"Point"}
}