{
  "type": "Feature",
  "properties": {
    "addr:full":"38 Solomon Ave Redwood  Christchurch Canterbury",
    "addr:housenumber":"38",
    "addr:street":"Solomon Ave",
    "iso:country":"NZ",
    "sg:address":"38 Solomon Ave Redwood ",
    "sg:city":"Christchurch",
    "sg:orig_category":"Industrial: Engineering: Engineers - Printing",
    "sg:phone":"+64 3-352 2975",
    "sg:province":"Canterbury",
    "wof:name":"Stewart Offset Services (NZ) Ltd",
    "wof:placetype":"venue"
},
  "geometry": {"coordinates":[172.62309300000001,-43.472023],"type":"Point"}
}