{
  "type": "Feature",
  "properties": {
    "iso:country":"NZ",
    "sg:address":"503 Gt South Rd Penrose ",
    "sg:city":"Auckland",
    "sg:orig_category":"Industrial: Cleaning And Maintenance: Casting Repairs",
    "sg:phone":"+64 9-579 8599",
    "sg:province":"Auckland",
    "wof:name":"Metalock N I Ltd",
    "wof:placetype":"venue"
},
  "geometry": {"coordinates":[174.81088299999999,-36.906448],"type":"Point"}
}