{
  "type": "Feature",
  "properties": {
    "addr:full":"2/50C Keeling Rd Henderson  Auckland Auckland",
    "addr:housenumber":"2 / 50c",
    "addr:street":"Keeling Rd",
    "iso:country":"NZ",
    "sg:address":"2/50C Keeling Rd Henderson ",
    "sg:city":"Auckland",
    "sg:classifiers":[
        {
            "category":"Manufacturing",
            "subcategory":"Furniture",
            "type":"Manufacturing & Wholesale Goods"
        }
    ],
    "sg:phone":"+64 9-838 8800",
    "sg:province":"Auckland",
    "sg:tags":[
        "furniture/furnishings",
        "home",
        "garden",
        "manufacturer"
    ],
    "wof:name":"Trim Cost Furniture",
    "wof:placetype":"venue"
},
  "geometry": {"coordinates":[174.62148999999999,-36.884617],"type":"Point"}
}