{
  "type": "Feature",
  "properties": {
    "addr:full":"131 Conyers St  Invercargill Southland",
    "addr:housenumber":"131",
    "addr:street":"Conyers St",
    "iso:country":"NZ",
    "sg:address":"131 Conyers St ",
    "sg:city":"Invercargill",
    "sg:classifiers":[
        {
            "category":"Home & Garden",
            "subcategory":"Building Materials",
            "type":"Retail Goods"
        }
    ],
    "sg:phone":"+64 3-216 8707",
    "sg:province":"Southland",
    "sg:tags":[
        "design",
        "fitting",
        "fittings",
        "kitchen"
    ],
    "wof:name":"A R Joinery",
    "wof:placetype":"venue"
},
  "geometry": {"coordinates":[168.37455700000001,-46.423985],"type":"Point"}
}