{
  "type": "Feature",
  "properties": {
    "iso:country":"NZ",
    "sg:address":"175 Gt South Rd Drury ",
    "sg:city":"Auckland",
    "sg:classifiers":[
        {
            "category":"Insurance",
            "subcategory":"Health Insurance",
            "type":"Services"
        }
    ],
    "sg:phone":"+64 9-294 8630",
    "sg:province":"Auckland",
    "sg:tags":[
        "beauty"
    ],
    "wof:name":"Klaassen Michael F",
    "wof:placetype":"venue"
},
  "geometry": {"coordinates":[174.948624,-37.098129],"type":"Point"}
}