{
  "type": "Feature",
  "properties": {
    "iso:country":"NZ",
    "sg:address":"604 Maunganui Rd Mt ",
    "sg:city":"Maunganui",
    "sg:orig_category":"Transport: Boats And Marine: Shipping",
    "sg:phone":"+64 7-574 7732",
    "sg:province":"Bay of Plenty",
    "wof:name":"Eastern Bay Provedores",
    "wof:placetype":"venue"
},
  "geometry": {"coordinates":[176.192856,-37.650269],"type":"Point"}
}