{
  "type": "Feature",
  "properties": {
    "iso:country":"NZ",
    "sg:address":"22 Grundy St ",
    "sg:city":"Gisborne",
    "sg:classifiers":[
        {
            "category":"Building & Trades",
            "subcategory":"Plumbing",
            "type":"Services"
        }
    ],
    "sg:phone":"+64 6-867 5891",
    "sg:province":"Gisborne",
    "sg:tags":[
        "home",
        "plumber",
        "garden",
        "related"
    ],
    "wof:name":"Watton Russell J & Susanne",
    "wof:placetype":"venue"
},
  "geometry": {"coordinates":[178.01286300000001,-38.649712],"type":"Point"}
}