{
  "type": "Feature",
  "properties": {
    "addr:full":"70 Main Rd South  Levin Manawatu-Wanganui",
    "addr:housenumber":"70",
    "addr:street":"Main Rd South",
    "iso:country":"NZ",
    "sg:address":"70 Main Rd South ",
    "sg:city":"Levin",
    "sg:orig_category":"Shopping: Sports Retailers: Sports Goods: Canvas Goods",
    "sg:phone":"+64 6-368 3428",
    "sg:province":"Manawatu-Wanganui",
    "wof:name":"Levin Canvas Co",
    "wof:placetype":"venue"
},
  "geometry": {"coordinates":[175.285324,-40.625278],"type":"Point"}
}