{
  "type": "Feature",
  "properties": {
    "addr:full":"22 George St  Blenheim Marlborough",
    "addr:housenumber":"22",
    "addr:street":"George St",
    "iso:country":"NZ",
    "sg:address":"22 George St ",
    "sg:city":"Blenheim",
    "sg:classifiers":[
        {
            "category":"Insurance",
            "subcategory":"Health Insurance",
            "type":"Services"
        }
    ],
    "sg:phone":"+64 3-578 8802",
    "sg:province":"Marlborough",
    "sg:tags":[
        "specialist",
        "beauty"
    ],
    "wof:name":"Blenheim Physiotherapy",
    "wof:placetype":"venue"
},
  "geometry": {"coordinates":[173.954849,-41.514305],"type":"Point"}
}