{
  "type": "Feature",
  "properties": {
    "addr:full":"176 Parker Rd Oratia  Auckland Auckland",
    "addr:housenumber":"176",
    "addr:street":"Parker Rd",
    "iso:country":"NZ",
    "sg:address":"176 Parker Rd Oratia ",
    "sg:city":"Auckland",
    "sg:classifiers":[
        {
            "category":"Shopping",
            "subcategory":"Crafts & Fabrics",
            "type":"Retail Goods"
        }
    ],
    "sg:phone":"+64 9-818 5081",
    "sg:province":"Auckland",
    "sg:tags":[
        "pottery",
        "home",
        "accessories",
        "garden",
        "supply"
    ],
    "wof:name":"Country Pots",
    "wof:placetype":"venue"
},
  "geometry": {"coordinates":[174.60566700000001,-36.937325],"type":"Point"}
}