{
  "type": "Feature",
  "properties": {
    "iso:country":"NZ",
    "sg:address":"9 Gunson St Ponsonby ",
    "sg:city":"Auckland",
    "sg:classifiers":[
        {
            "category":"Shopping",
            "subcategory":"Photographic Equipment",
            "type":"Retail Goods"
        }
    ],
    "sg:phone":"+64 9-379 4202",
    "sg:province":"Auckland",
    "sg:tags":[
        "sport",
        "leisure",
        "hobbies"
    ],
    "wof:name":"Polaroid Film Suppliers Camera Hireage",
    "wof:placetype":"venue"
},
  "geometry": {"coordinates":[174.742416,-36.85326],"type":"Point"}
}