{
  "type": "Feature",
  "properties": {
    "addr:full":"Jackson St  Masterton Wellington",
    "addr:street":"Jackson St",
    "iso:country":"NZ",
    "sg:address":"Jackson St ",
    "sg:city":"Masterton",
    "sg:orig_category":"Health And Beauty: Beauty: Hairdressers",
    "sg:phone":"+64 6-370 2228",
    "sg:province":"Wellington",
    "wof:name":"Hair Raizing",
    "wof:placetype":"venue"
},
  "geometry": {"coordinates":[175.65815699999999,-40.95092],"type":"Point"}
}