{
  "type": "Feature",
  "properties": {
    "iso:country":"NZ",
    "sg:address":"Tauranga ",
    "sg:city":"Tauranga",
    "sg:orig_category":"Transport: Land: Shuttle Services",
    "sg:phone":"+64 7-576 8302",
    "sg:province":"Bay of Plenty",
    "wof:name":"Baywide Shuttle Service",
    "wof:placetype":"venue"
},
  "geometry": {"coordinates":[176.166473,-37.686142],"type":"Point"}
}