{
  "type": "Feature",
  "properties": {
    "iso:country":"NZ",
    "sg:address":"12 Mt View Pl Hornby ",
    "sg:city":"Christchurch",
    "sg:orig_category":"Industrial: Metal: Products: Foundry Supplies",
    "sg:phone":"+64 3-349 2168",
    "sg:province":"Canterbury",
    "wof:name":"Foseco NZ Ltd",
    "wof:placetype":"venue"
},
  "geometry": {"coordinates":[172.536331,-43.534431],"type":"Point"}
}