{
  "type": "Feature",
  "properties": {
    "addr:full":"34 Allens Rd East Tamaki  Auckland Auckland",
    "addr:housenumber":"34",
    "addr:street":"Allens Rd",
    "iso:country":"NZ",
    "sg:address":"34 Allens Rd East Tamaki ",
    "sg:city":"Auckland",
    "sg:orig_category":"Farming: Horticulture: Soil Supplies",
    "sg:phone":"+64 9-273 2946",
    "sg:province":"Auckland",
    "wof:name":"H D Masters Ltd",
    "wof:placetype":"venue"
},
  "geometry": {"coordinates":[174.88905299999999,-36.942719],"type":"Point"}
}