{
  "type": "Feature",
  "properties": {
    "iso:country":"NZ",
    "sg:address":"189 Dee St ",
    "sg:city":"Invercargill",
    "sg:classifiers":[
        {
            "category":"Manufacturing",
            "subcategory":"Furniture",
            "type":"Manufacturing & Wholesale Goods"
        }
    ],
    "sg:phone":"+64 25307495",
    "sg:province":"Southland",
    "sg:tags":[
        "furniture/furnishings",
        "home",
        "garden",
        "manufacturer"
    ],
    "wof:name":"Eternal Lines Furniture",
    "wof:placetype":"venue"
},
  "geometry": {"coordinates":[168.347321,-46.392628],"type":"Point"}
}