{
  "type": "Feature",
  "properties": {
    "addr:full":"134 Leeston Rd  Springston",
    "addr:housenumber":"134",
    "addr:street":"Leeston Rd",
    "iso:country":"NZ",
    "sg:address":"134 Leeston Rd ",
    "sg:city":"Springston",
    "sg:orig_category":"Sports And Leisure: Sports: Equestrian",
    "sg:phone":"+64 3-329 5516",
    "wof:name":"Sleek Floats & Trailers",
    "wof:placetype":"venue"
},
  "geometry": {"coordinates":[172.42318700000001,-43.642738],"type":"Point"}
}