{
  "type": "Feature",
  "properties": {
    "addr:full":"Kuaotunu  Whitianga",
    "iso:country":"NZ",
    "sg:address":"Kuaotunu ",
    "sg:city":"Whitianga",
    "sg:classifiers":[
        {
            "category":"Recreation",
            "type":"Entertainment"
        }
    ],
    "sg:phone":"+64 7-866 2850",
    "sg:tags":[
        "shopping",
        "hunting",
        "fishing",
        "retailers",
        "sport",
        "trip"
    ],
    "wof:name":"Coromandel Safaris",
    "wof:placetype":"venue"
},
  "geometry": {"coordinates":[175.699524,-36.821468],"type":"Point"}
}