{
  "type": "Feature",
  "properties": {
    "addr:full":"30 Victoria Rd Devonport  Auckland Auckland",
    "addr:housenumber":"30",
    "addr:street":"Victoria Rd",
    "iso:country":"NZ",
    "sg:address":"30 Victoria Rd Devonport ",
    "sg:city":"Auckland",
    "sg:orig_category":"Shopping: Accessories: Lingerie - Retail",
    "sg:phone":"+64 9-446 0266",
    "sg:province":"Auckland",
    "wof:name":"Lingerie World",
    "wof:placetype":"venue"
},
  "geometry": {"coordinates":[174.79800399999999,-36.8298],"type":"Point"}
}