{
  "type": "Feature",
  "properties": {
    "iso:country":"NZ",
    "sg:address":"22 Marsh St ",
    "sg:city":"Tauranga",
    "sg:classifiers":[
        {
            "category":"Personal",
            "type":"Services"
        }
    ],
    "sg:phone":"+64 7-578 1763",
    "sg:province":"Bay of Plenty",
    "sg:tags":[
        "arrangements",
        "wedding"
    ],
    "wof:name":"Triac Light & Sound",
    "wof:placetype":"venue"
},
  "geometry": {"coordinates":[176.16708399999999,-37.676064],"type":"Point"}
}