{
  "type": "Feature",
  "properties": {
    "iso:country":"NZ",
    "sg:address":"11 Monk St ",
    "sg:city":"Whitianga",
    "sg:orig_category":"Health And Beauty: Beauty: Hairdressers",
    "sg:phone":"+64 7-866 5178",
    "wof:name":"Hair Shop",
    "wof:placetype":"venue"
},
  "geometry": {"coordinates":[175.705429,-36.833466],"type":"Point"}
}