{
  "type": "Feature",
  "properties": {
    "addr:full":"40 Bridge Rd  Bulls",
    "addr:housenumber":"40",
    "addr:street":"Bridge Rd",
    "iso:country":"NZ",
    "sg:address":"40 Bridge Rd ",
    "sg:city":"Bulls",
    "sg:orig_category":"Transport: Land: Horse Transport",
    "sg:phone":"+64 6-322 1776",
    "wof:name":"Inter-Island Horse Transport Ltd",
    "wof:placetype":"venue"
},
  "geometry": {"coordinates":[175.384964,-40.173042],"type":"Point"}
}