{
  "type": "Feature",
  "properties": {
    "addr:full":"59 Commerce St Frankton  Hamilton Waikato",
    "addr:housenumber":"59",
    "addr:street":"Commerce St",
    "iso:country":"NZ",
    "sg:address":"59 Commerce St Frankton ",
    "sg:city":"Hamilton",
    "sg:classifiers":[
        {
            "category":"Manufacturing",
            "subcategory":"Glass & Minerals",
            "type":"Manufacturing & Wholesale Goods"
        }
    ],
    "sg:phone":"+64 7-846 6393",
    "sg:province":"Waikato",
    "sg:tags":[
        "chemical",
        "paint",
        "industrial",
        "manufacturer",
        "compounds"
    ],
    "wof:name":"Protective Paints Ltd",
    "wof:placetype":"venue"
},
  "geometry": {"coordinates":[175.267303,-37.786068],"type":"Point"}
}