{
  "type": "Feature",
  "properties": {
    "iso:country":"NZ",
    "sg:address":"809 Karamu Rd ",
    "sg:city":"Hastings",
    "sg:classifiers":[
        {
            "category":"Home & Garden",
            "subcategory":"Building Materials",
            "type":"Retail Goods"
        }
    ],
    "sg:phone":"+64 6-876 3433",
    "sg:province":"Hawke's Bay",
    "sg:tags":[
        "gate",
        "fitting",
        "outdoor"
    ],
    "wof:name":"Merlin Gate Openers",
    "wof:placetype":"venue"
},
  "geometry": {"coordinates":[176.852982,-39.638023],"type":"Point"}
}