{
  "type": "Feature",
  "properties": {
    "iso:country":"NZ",
    "sg:address":"6th Floor Harbour City Tower cnr Lambton Qy & Brandon, St ",
    "sg:city":"Wellington",
    "sg:orig_category":"Health And Beauty: Specialists: Podiatrists",
    "sg:phone":"+64 4-473 8696",
    "sg:province":"Wellington",
    "wof:name":"Active Feet Podiatry",
    "wof:placetype":"venue"
},
  "geometry": {"coordinates":[174.775436,-41.283409],"type":"Point"}
}