{
  "type": "Feature",
  "properties": {
    "addr:full":"Unit 2/ 4 Glover St Ngauranga  Wellington Wellington",
    "addr:housenumber":"unit 2 / 4",
    "addr:street":"Glover St",
    "iso:country":"NZ",
    "sg:address":"Unit 2/ 4 Glover St Ngauranga ",
    "sg:city":"Wellington",
    "sg:orig_category":"Industrial: Electrical/Electronic: Electronic Equipment",
    "sg:phone":"+64 4-472 5960",
    "sg:province":"Wellington",
    "wof:name":"Precision Technology Ltd",
    "wof:placetype":"venue"
},
  "geometry": {"coordinates":[174.81336999999999,-41.241772],"type":"Point"}
}