{
  "type": "Feature",
  "properties": {
    "addr:full":"134 Grey St Hamilton East  Hamilton Waikato",
    "addr:housenumber":"134",
    "addr:street":"Grey St",
    "iso:country":"NZ",
    "sg:address":"134 Grey St Hamilton East ",
    "sg:city":"Hamilton",
    "sg:classifiers":[
        {
            "category":"Utilities",
            "subcategory":"Electric",
            "type":"Services"
        }
    ],
    "sg:phone":"+64 7-856 7022",
    "sg:province":"Waikato",
    "sg:tags":[
        "energy",
        "industrial"
    ],
    "sg:website":"http://www.yellowpages.co.nz/pages/102919960/dp50923.html",
    "wof:name":"Eastside Cylinder Services",
    "wof:placetype":"venue"
},
  "geometry": {"coordinates":[175.29611199999999,-37.79884],"type":"Point"}
}