{
  "type": "Feature",
  "properties": {
    "iso:country":"NZ",
    "sg:address":"Auckland ",
    "sg:city":"Auckland",
    "sg:classifiers":[
        {
            "category":"Shopping",
            "type":"Retail Goods"
        }
    ],
    "sg:phone":"+64 800 909 090",
    "sg:province":"Auckland",
    "sg:tags":[
        "store"
    ],
    "sg:website":"http://www.teleflora.co.nz",
    "wof:name":"Teleflora Orders",
    "wof:placetype":"venue"
},
  "geometry": {"coordinates":[174.78450000000001,-37.006058],"type":"Point"}
}