{
  "type": "Feature",
  "properties": {
    "addr:full":"PO Box 17079 Greenlane  Auckland Auckland",
    "addr:housenumber":"po box 17079",
    "iso:country":"NZ",
    "sg:address":"PO Box 17079 Greenlane ",
    "sg:city":"Auckland",
    "sg:classifiers":[
        {
            "category":"Sports & Exercise",
            "subcategory":"Swimming Pool",
            "type":"Entertainment"
        }
    ],
    "sg:phone":"+64 9-579 0003",
    "sg:province":"Auckland",
    "sg:tags":[
        "home",
        "outdoor",
        "garden",
        "spa"
    ],
    "wof:name":"Swimming Pool Services Ltd",
    "wof:placetype":"venue"
},
  "geometry": {"coordinates":[174.79191599999999,-36.892967],"type":"Point"}
}