{
  "type": "Feature",
  "properties": {
    "addr:full":"PO Box 373 Mosgiel  Dunedin Otago",
    "addr:housenumber":"po",
    "addr:street":"Box 373",
    "iso:country":"NZ",
    "sg:address":"PO Box 373 Mosgiel ",
    "sg:city":"Dunedin",
    "sg:orig_category":"Transport: Land: Limousines And Chauffeurs",
    "sg:phone":"+64 3-489 8443",
    "sg:province":"Otago",
    "wof:name":"Regency Limousines",
    "wof:placetype":"venue"
},
  "geometry": {"coordinates":[170.352844,-45.876041],"type":"Point"}
}