{
  "type": "Feature",
  "properties": {
    "addr:full":"167 Archers Rd Glenfield  Auckland Auckland",
    "addr:housenumber":"167",
    "addr:street":"Archers Rd",
    "iso:country":"NZ",
    "sg:address":"167 Archers Rd Glenfield ",
    "sg:city":"Auckland",
    "sg:classifiers":[
        {
            "category":"Shopping",
            "subcategory":"Pets & Pet Supplies",
            "type":"Retail Goods"
        }
    ],
    "sg:phone":"+64 9-443 8478",
    "sg:province":"Auckland",
    "sg:tags":[
        "home",
        "grooming",
        "garden",
        "pets"
    ],
    "wof:name":"Doggies Spa & Grooming",
    "wof:placetype":"venue"
},
  "geometry": {"coordinates":[174.737503,-36.78223],"type":"Point"}
}