{
  "type": "Feature",
  "properties": {
    "addr:full":"17, Kabul Street - Khandallah -  Wellington Wellington",
    "addr:housenumber":"17",
    "addr:street":"Kabul Street",
    "iso:country":"NZ",
    "sg:address":"17, Kabul Street - Khandallah - ",
    "sg:city":"Wellington",
    "sg:classifiers":[
        {
            "category":"Professional",
            "subcategory":"Art Services",
            "type":"Services"
        }
    ],
    "sg:phone":"+64 6444792076",
    "sg:province":"Wellington",
    "sg:tags":[
        "export-import"
    ],
    "wof:name":"Singapore High Commission",
    "wof:placetype":"venue"
},
  "geometry": {"coordinates":[174.784729,-41.254639],"type":"Point"}
}