{
  "type": "Feature",
  "properties": {
    "addr:full":"130 A Nelson St Petone  Wellington Wellington",
    "addr:housenumber":"130",
    "addr:street":"A Nelson St",
    "iso:country":"NZ",
    "sg:address":"130 A Nelson St Petone ",
    "sg:city":"Wellington",
    "sg:classifiers":[
        {
            "category":"Home & Garden",
            "subcategory":"Building Materials",
            "type":"Retail Goods"
        }
    ],
    "sg:phone":"+64 4-939 2929",
    "sg:province":"Wellington",
    "sg:tags":[
        "shower",
        "fittings",
        "screen",
        "door"
    ],
    "wof:name":"Bathroom Solutions",
    "wof:placetype":"venue"
},
  "geometry": {"coordinates":[174.879501,-41.220379],"type":"Point"}
}