{
  "type": "Feature",
  "properties": {
    "addr:full":"PO Box 593 Te  Puke Bay of Plenty",
    "addr:housenumber":"po;593",
    "addr:street":"Box",
    "iso:country":"NZ",
    "sg:address":"PO Box 593 Te ",
    "sg:city":"Puke",
    "sg:orig_category":"Industrial: Services: Specialist Services: Vibration Analysis",
    "sg:phone":"+64 7-573 4769",
    "sg:province":"Bay of Plenty",
    "wof:name":"Condition Monitoring Systems Ltd",
    "wof:placetype":"venue"
},
  "geometry": {"coordinates":[176.32008400000001,-37.786819],"type":"Point"}
}