{
  "type": "Feature",
  "properties": {
    "addr:full":"88 Otaki St  Dunedin Otago",
    "addr:housenumber":"88",
    "addr:street":"Otaki St",
    "iso:country":"NZ",
    "sg:address":"88 Otaki St ",
    "sg:city":"Dunedin",
    "sg:classifiers":[
        {
            "category":"Food & Beverages",
            "subcategory":"Groceries & Convenience Stores",
            "type":"Retail Goods"
        }
    ],
    "sg:phone":"+64 3-455 9025",
    "sg:province":"Otago",
    "sg:tags":[
        "foodstuff",
        "drink",
        "-"
    ],
    "wof:name":"Link Food Service Dunedin",
    "wof:placetype":"venue"
},
  "geometry": {"coordinates":[-82.784721,28.013355],"type":"Point"}
}