{
  "type": "Feature",
  "properties": {
    "iso:country":"NZ",
    "sg:address":"18 Andromeda Cre East Tamaki ",
    "sg:city":"Auckland",
    "sg:classifiers":[
        {
            "category":"Retail",
            "subcategory":"Driving School",
            "type":"Services"
        }
    ],
    "sg:phone":"+64 9-274 4069",
    "sg:province":"Auckland",
    "sg:tags":[
        "training",
        "education",
        "driver"
    ],
    "wof:name":"Crown Equipment Ltd",
    "wof:placetype":"venue"
},
  "geometry": {"coordinates":[174.887466,-36.949226],"type":"Point"}
}