{
  "type": "Feature",
  "properties": {
    "iso:country":"NZ",
    "sg:address":"18 Shetland St Titirangi ",
    "sg:city":"Auckland",
    "sg:classifiers":[
        {
            "category":"Manufacturing",
            "subcategory":"Rubber & Plastics",
            "type":"Manufacturing & Wholesale Goods"
        }
    ],
    "sg:phone":"+64 9-818 6194",
    "sg:province":"Auckland",
    "sg:tags":[
        "stamp",
        "industrial",
        "goods"
    ],
    "wof:name":"Easy Stamp NZ Ltd",
    "wof:placetype":"venue"
},
  "geometry": {"coordinates":[174.662796,-36.926861],"type":"Point"}
}