{
  "type": "Feature",
  "properties": {
    "addr:full":"Auckland St  Picton Marlborough",
    "addr:street":"Auckland St",
    "iso:country":"NZ",
    "sg:address":"Auckland St ",
    "sg:city":"Picton",
    "sg:orig_category":"Transport: Boats And Marine: Shipping: Port Services",
    "sg:phone":"+64 3-573 8000",
    "sg:province":"Marlborough",
    "wof:name":"Port Marlborough New Zealand Limited",
    "wof:placetype":"venue"
},
  "geometry": {"coordinates":[174.005753,-41.291809],"type":"Point"}
}