{
  "type": "Feature",
  "properties": {
    "addr:full":"Waihekau Rd Te  Aroha",
    "addr:street":"Waihekau Rd",
    "iso:country":"NZ",
    "sg:address":"Waihekau Rd Te ",
    "sg:city":"Aroha",
    "sg:orig_category":"Farming: Agriculture",
    "sg:phone":"+64 7-884 6060",
    "wof:name":"Rural Improvements",
    "wof:placetype":"venue"
},
  "geometry": {"coordinates":[175.72309899999999,-37.599113],"type":"Point"}
}