{
  "type": "Feature",
  "properties": {
    "addr:full":"34 Huia St  Taumarunui",
    "addr:housenumber":"34",
    "addr:street":"Huia St",
    "iso:country":"NZ",
    "sg:address":"34 Huia St ",
    "sg:city":"Taumarunui",
    "sg:classifiers":[
        {
            "category":"Banks & Credit Unions",
            "subcategory":"Investment Brokerage",
            "type":"Services"
        }
    ],
    "sg:phone":"+64 7-895 7420",
    "sg:tags":[
        "director",
        "funeral",
        "arrangements"
    ],
    "wof:name":"Taumarunui Funeral Services Ltd",
    "wof:placetype":"venue"
},
  "geometry": {"coordinates":[175.26026899999999,-38.885445],"type":"Point"}
}