{
  "type": "Feature",
  "properties": {
    "addr:full":"Studio 48 Aviation Ave Mt  Maunganui Bay of Plenty",
    "addr:housenumber":"48",
    "addr:street":"Aviation Ave;Maunganui Bay",
    "iso:country":"NZ",
    "sg:address":"Studio 48 Aviation Ave Mt ",
    "sg:city":"Maunganui",
    "sg:classifiers":[
        {
            "category":"Education",
            "subcategory":"Dance Studio",
            "type":"Public Place"
        }
    ],
    "sg:phone":"+64 7-572 2174",
    "sg:province":"Bay of Plenty",
    "sg:tags":[
        "school",
        "dancing",
        "-",
        "leisure",
        "sports",
        "sport"
    ],
    "wof:name":"Mt Maunganui Dance Academy",
    "wof:placetype":"venue"
},
  "geometry": {"coordinates":[176.18627900000001,-37.641048],"type":"Point"}
}