{
  "type": "Feature",
  "properties": {
    "addr:full":"26 Veronica St New Lynn  Auckland Auckland",
    "addr:housenumber":"26",
    "addr:street":"Veronica St",
    "iso:country":"NZ",
    "sg:address":"26 Veronica St New Lynn ",
    "sg:city":"Auckland",
    "sg:classifiers":[
        {
            "category":"Sports & Exercise",
            "subcategory":"Sports Center",
            "type":"Entertainment"
        }
    ],
    "sg:phone":"+64 9-827 1367",
    "sg:province":"Auckland",
    "sg:tags":[
        "indoor",
        "-",
        "leisure",
        "sports"
    ],
    "wof:name":"Western Indoor Sports Ltd",
    "wof:placetype":"venue"
},
  "geometry": {"coordinates":[174.68495200000001,-36.904766],"type":"Point"}
}