{
  "type": "Feature",
  "properties": {
    "iso:country":"NZ",
    "sg:address":"Pheny Rd RD 4 New ",
    "sg:city":"Plymouth",
    "sg:classifiers":[
        {
            "category":"Shopping",
            "subcategory":"Computers & Home Electronics",
            "type":"Retail Goods"
        }
    ],
    "sg:phone":"+64 6-751 3825",
    "sg:province":"Taranaki",
    "sg:tags":[
        "recording",
        "equipment",
        "sport",
        "music",
        "leisure"
    ],
    "wof:name":"Avalanche Audio",
    "wof:placetype":"venue"
},
  "geometry": {"coordinates":[-82.317566,39.329933],"type":"Point"}
}