{
  "type": "Feature",
  "properties": {
    "addr:full":"671 Cameron Rd  Tauranga Bay of Plenty",
    "addr:housenumber":"671",
    "addr:street":"Cameron Rd",
    "iso:country":"NZ",
    "sg:address":"671 Cameron Rd ",
    "sg:city":"Tauranga",
    "sg:classifiers":[
        {
            "category":"Recreation",
            "type":"Entertainment"
        }
    ],
    "sg:phone":"+64 7-578 0072",
    "sg:province":"Bay of Plenty",
    "sg:tags":[
        "sport",
        "leisure"
    ],
    "wof:name":"Action Station Internet Lounge & Interactive Games Centre",
    "wof:placetype":"venue"
},
  "geometry": {"coordinates":[176.155914,-37.701492],"type":"Point"}
}