{
  "type": "Feature",
  "properties": {
    "iso:country":"NZ",
    "sg:address":"82 Foundry Rd Silverdale Hibiscus ",
    "sg:city":"Hibiscus Coast",
    "sg:orig_category":"Industrial: Services",
    "sg:phone":"+64 9-426 5035",
    "sg:province":"Auckland",
    "sg:website":"http://www.yellowpages.co.nz/for/polespecialists/dp37783.html",
    "wof:name":"Pole Specialists Ltd",
    "wof:placetype":"venue"
},
  "geometry": {"coordinates":[174.68292199999999,-36.62244],"type":"Point"}
}