{
  "type": "Feature",
  "properties": {
    "iso:country":"NZ",
    "sg:address":"137 Spey St ",
    "sg:city":"Invercargill",
    "sg:classifiers":[
        {
            "category":"Professional",
            "type":"Services"
        }
    ],
    "sg:phone":"+64 3-214 5000",
    "sg:province":"Southland",
    "sg:tags":[
        "home",
        "cleaning",
        "help",
        "garden"
    ],
    "wof:name":"Disabilities Resource Centre Southland Inc",
    "wof:placetype":"venue"
},
  "geometry": {"coordinates":[168.351456,-46.409874],"type":"Point"}
}