{
  "type": "Feature",
  "properties": {
    "addr:full":"20-34 Railway Ave Lower  Hutt Wellington",
    "addr:housenumber":"20-34",
    "addr:street":"Railway Ave",
    "iso:country":"NZ",
    "sg:address":"20-34 Railway Ave Lower ",
    "sg:city":"Hutt",
    "sg:orig_category":"Automotive: General Services: Service Stations",
    "sg:phone":"+64 4-570 2544",
    "sg:province":"Wellington",
    "wof:name":"Challenge Petroleum Ltd",
    "wof:placetype":"venue"
},
  "geometry": {"coordinates":[174.904526,-41.208431],"type":"Point"}
}