{
  "type": "Feature",
  "properties": {
    "iso:country":"NZ",
    "sg:address":"31 London St ",
    "sg:city":"Hampden",
    "sg:orig_category":"Shopping: Retail Stores: Supermarkets",
    "sg:phone":"+64 3-439 4706",
    "wof:name":"Hilltop Store",
    "wof:placetype":"venue"
},
  "geometry": {"coordinates":[-68.848923,44.745285],"type":"Point"}
}