{
  "type": "Feature",
  "properties": {
    "addr:full":"Kiosk 2 Merivale Mall Merivale  Christchurch Canterbury",
    "addr:housenumber":"2;mall",
    "addr:street":"Merivale",
    "iso:country":"NZ",
    "sg:address":"Kiosk 2 Merivale Mall Merivale ",
    "sg:city":"Christchurch",
    "sg:classifiers":[
        {
            "category":"Food & Beverages",
            "subcategory":"Candy",
            "type":"Retail Goods"
        }
    ],
    "sg:phone":"+64 3-355 3086",
    "sg:province":"Canterbury",
    "sg:tags":[
        "confectioner",
        "drink",
        "-"
    ],
    "wof:name":"Mary Gray Confections",
    "wof:placetype":"venue"
},
  "geometry": {"coordinates":[172.620758,-43.514442],"type":"Point"}
}