{
  "type": "Feature",
  "properties": {
    "addr:full":"8 Hall St  Pukekohe Auckland",
    "addr:housenumber":"8",
    "addr:street":"Hall St",
    "iso:country":"NZ",
    "sg:address":"8 Hall St ",
    "sg:city":"Pukekohe",
    "sg:orig_category":"Clothing And Fabric: Clothing: Children'S Wear",
    "sg:phone":"+64 9-238 1189",
    "sg:province":"Auckland",
    "wof:name":"Kidz Ragz",
    "wof:placetype":"venue"
},
  "geometry": {"coordinates":[174.930252,-37.195728],"type":"Point"}
}