{
  "type": "Feature",
  "properties": {
    "addr:full":"18 Connolly Pl Palmerston  Palmerston North Manawatu-Wanganui",
    "addr:housenumber":"18",
    "addr:street":"Connolly Pl",
    "iso:country":"NZ",
    "sg:address":"18 Connolly Pl Palmerston ",
    "sg:city":"Palmerston North",
    "sg:classifiers":[
        {
            "category":"Sports & Exercise",
            "subcategory":"Swimming Pool",
            "type":"Entertainment"
        }
    ],
    "sg:phone":"+64 6-357 1624",
    "sg:province":"Manawatu-Wanganui",
    "sg:tags":[
        "home",
        "outdoor",
        "garden",
        "spa"
    ],
    "wof:name":"BioSan NZ Ltd",
    "wof:placetype":"venue"
},
  "geometry": {"coordinates":[175.599808,-40.336388],"type":"Point"}
}