{
  "type": "Feature",
  "properties": {
    "addr:full":"36 Weston Rd Weston  Oamaru Otago",
    "addr:housenumber":"36",
    "addr:street":"Weston Rd",
    "iso:country":"NZ",
    "sg:address":"36 Weston Rd Weston ",
    "sg:city":"Oamaru",
    "sg:orig_category":"Farming: Machinery: Tractors",
    "sg:phone":"+64 3-433 1214",
    "sg:province":"Otago",
    "wof:name":"North Otago Ag Centre Ltd",
    "wof:placetype":"venue"
},
  "geometry": {"coordinates":[170.936218,-45.097168],"type":"Point"}
}