{
  "type": "Feature",
  "properties": {
    "addr:full":"Kowhai Ave Edgecumbe  Whakatane Bay of Plenty",
    "addr:street":"Kowhai Ave Edgecumbe Whakatane Bay",
    "iso:country":"NZ",
    "sg:address":"Kowhai Ave Edgecumbe ",
    "sg:city":"Whakatane",
    "sg:orig_category":"Industrial: Engineering: Engineers - Steam",
    "sg:phone":"+64 7-304 8216",
    "sg:province":"Bay of Plenty",
    "wof:name":"McKenzie & Ridley Ltd",
    "wof:placetype":"venue"
},
  "geometry": {"coordinates":[176.825333,-37.976841],"type":"Point"}
}