{
  "type": "Feature",
  "properties": {
    "addr:full":"525 Ellerslie Panmure Hwy Mt Wellington  Auckland Auckland",
    "addr:housenumber":"525",
    "addr:street":"Panmure Hwy",
    "iso:country":"NZ",
    "sg:address":"525 Ellerslie Panmure Hwy Mt Wellington ",
    "sg:city":"Auckland",
    "sg:classifiers":[
        {
            "category":"Bars & Pubs",
            "type":"Food & Drink"
        }
    ],
    "sg:phone":"+64 9-527 5468",
    "sg:province":"Auckland",
    "sg:tags":[
        "wining",
        "dining",
        "brasserie"
    ],
    "wof:name":"Miss Q's Pool Bar & Cafe",
    "wof:placetype":"venue"
},
  "geometry": {"coordinates":[174.84835799999999,-36.898411],"type":"Point"}
}