{
  "type": "Feature",
  "properties": {
    "addr:full":"52 Vine St  Whangarei Northland",
    "addr:housenumber":"52",
    "addr:street":"Vine St",
    "iso:country":"NZ",
    "sg:address":"52 Vine St ",
    "sg:city":"Whangarei",
    "sg:orig_category":"Shopping: Retail Stores: Books",
    "sg:phone":"+64 9-430 0213",
    "sg:province":"Northland",
    "sg:website":"http://www.yellowpages.co.nz/for/beaumonts/dp35205.html",
    "wof:name":"Beaumonts Business Bureau & Book Shop",
    "wof:placetype":"venue"
},
  "geometry": {"coordinates":[174.32041899999999,-35.726681],"type":"Point"}
}