{
  "type": "Feature",
  "properties": {
    "addr:full":"111 Maxwells Rd  Tauranga Bay of Plenty",
    "addr:housenumber":"111",
    "addr:street":"Maxwells Rd",
    "iso:country":"NZ",
    "sg:address":"111 Maxwells Rd ",
    "sg:city":"Tauranga",
    "sg:classifiers":[
        {
            "category":"Home & Garden",
            "subcategory":"Home Furnishings",
            "type":"Retail Goods"
        }
    ],
    "sg:phone":"+64 800 644 464",
    "sg:province":"Bay of Plenty",
    "sg:tags":[
        "accessory"
    ],
    "wof:name":"The Wholesale Matting Company",
    "wof:placetype":"venue"
},
  "geometry": {"coordinates":[176.15763899999999,-37.673027],"type":"Point"}
}