{
  "type": "Feature",
  "properties": {
    "iso:country":"NZ",
    "sg:address":"51 Sewell St ",
    "sg:city":"Hokitika",
    "sg:orig_category":"Farming: Supplies",
    "sg:phone":"+64 3-756 8112",
    "sg:province":"West Coast",
    "wof:name":"Hokitika Pumps & Filtration Ltd",
    "wof:placetype":"venue"
},
  "geometry": {"coordinates":[170.963287,-42.718655],"type":"Point"}
}