{
  "type": "Feature",
  "properties": {
    "addr:full":"Settlers Rd  Reporoa",
    "addr:street":"Settlers Rd",
    "iso:country":"NZ",
    "sg:address":"Settlers Rd ",
    "sg:city":"Reporoa",
    "sg:classifiers":[
        {
            "category":"Health Services",
            "subcategory":"Dentist",
            "type":"Services"
        }
    ],
    "sg:phone":"+64 7-333 8339",
    "sg:tags":[
        "dental",
        "clinic",
        "beauty"
    ],
    "wof:name":"Reporoa Primary School",
    "wof:placetype":"venue"
},
  "geometry": {"coordinates":[176.34553500000001,-38.424908],"type":"Point"}
}