{
  "type": "Feature",
  "properties": {
    "iso:country":"NZ",
    "sg:address":"24 Wilson St ",
    "sg:city":"Geraldine",
    "sg:classifiers":[
        {
            "category":"Professional",
            "subcategory":"Art Services",
            "type":"Services"
        }
    ],
    "sg:phone":"+64 3-693 9767",
    "sg:tags":[
        "picture",
        "arts",
        "sport",
        "framing",
        "leisure"
    ],
    "wof:name":"Allison Art",
    "wof:placetype":"venue"
},
  "geometry": {"coordinates":[-86.008263,34.360641],"type":"Point"}
}