{
  "type": "Feature",
  "properties": {
    "iso:country":"NZ",
    "sg:address":"PricewaterhouseCoopers Centre 119 Armagh Street, Chch",
    "sg:city":"Christchurch",
    "sg:classifiers":[
        {
            "category":"Travel",
            "subcategory":"Hotels & Motels",
            "type":"Entertainment"
        }
    ],
    "sg:phone":"+64 3-379 6280",
    "sg:province":"Waikato",
    "sg:tags":[
        "tourism",
        "-",
        "rental",
        "accommodation"
    ],
    "wof:name":"Livingstone H G Ltd",
    "wof:placetype":"venue"
},
  "geometry": {"coordinates":[-76.537834,37.605659],"type":"Point"}
}