{
  "type": "Feature",
  "properties": {
    "iso:country":"NZ",
    "sg:address":"Otiria Rd Moerewa ",
    "sg:city":"Kawakawa",
    "sg:classifiers":[
        {
            "category":"Health Services",
            "subcategory":"Dentist",
            "type":"Services"
        }
    ],
    "sg:phone":"+64 9-404 0596",
    "sg:tags":[
        "dental",
        "clinic",
        "beauty"
    ],
    "wof:name":"Otiria School Dental Clinic",
    "wof:placetype":"venue"
},
  "geometry": {"coordinates":[173.991791,-35.399796],"type":"Point"}
}