{
  "type": "Feature",
  "properties": {
    "iso:country":"NZ",
    "sg:address":"18 Karepiro Dve Whangaparaoa Hibiscus ",
    "sg:city":"Hibiscus Coast",
    "sg:classifiers":[
        {
            "category":"Retail",
            "subcategory":"Storage",
            "type":"Services"
        }
    ],
    "sg:phone":"+64 9-424 2214",
    "sg:province":"Auckland",
    "wof:name":"Whangaparaoa Storage Ltd",
    "wof:placetype":"venue"
},
  "geometry": {"coordinates":[174.749161,-36.634239],"type":"Point"}
}