{
  "type": "Feature",
  "properties": {
    "iso:country":"NZ",
    "sg:address":"Anchormart Bldg White St ",
    "sg:city":"Rotorua",
    "sg:orig_category":"Farming: Agriculture: Dairy Companies",
    "sg:phone":"+64 7-346 1258",
    "sg:province":"Bay of Plenty",
    "wof:name":"New Zealand Milk Corporation Ltd",
    "wof:placetype":"venue"
},
  "geometry": {"coordinates":[176.24499499999999,-38.1418],"type":"Point"}
}