{
  "type": "Feature",
  "properties": {
    "addr:full":"11 Hutchison Rd Newtown  Wellington Wellington",
    "addr:housenumber":"11",
    "addr:street":"Hutchison Rd",
    "iso:country":"NZ",
    "sg:address":"11 Hutchison Rd Newtown ",
    "sg:city":"Wellington",
    "sg:classifiers":[
        {
            "category":"Sports & Exercise",
            "subcategory":"Sports Center",
            "type":"Entertainment"
        }
    ],
    "sg:phone":"+64 4-389 0996",
    "sg:province":"Wellington",
    "sg:tags":[
        "art",
        "leisure"
    ],
    "sg:website":"http://www.tewhaea.org.nz",
    "wof:name":"New Zealand School of Dance",
    "wof:placetype":"venue"
},
  "geometry": {"coordinates":[174.779022,-41.314163],"type":"Point"}
}