{
  "type": "Feature",
  "properties": {
    "addr:full":"1014 Omahu Rd  Hastings Hawke's Bay",
    "addr:housenumber":"1014",
    "addr:street":"Omahu Rd",
    "iso:country":"NZ",
    "sg:address":"1014 Omahu Rd ",
    "sg:city":"Hastings",
    "sg:orig_category":"Industrial: Products: Window Control Gear",
    "sg:phone":"+64 6-879 8700",
    "sg:province":"Hawke's Bay",
    "wof:name":"Hastings Aluminium Company",
    "wof:placetype":"venue"
},
  "geometry": {"coordinates":[176.81462099999999,-39.619545],"type":"Point"}
}