{
  "type": "Feature",
  "properties": {
    "iso:country":"NZ",
    "sg:address":"Cnr Roscommon & Browns Rd Manurewa ",
    "sg:city":"Auckland",
    "sg:classifiers":[
        {
            "category":"Food & Beverages",
            "subcategory":"Liquor & Beverages",
            "type":"Retail Goods"
        }
    ],
    "sg:phone":"+64 9-267 5854",
    "sg:province":"Auckland",
    "sg:tags":[
        "drink",
        "outlet"
    ],
    "wof:name":"Roscommon Liquor",
    "wof:placetype":"venue"
},
  "geometry": {"coordinates":[174.895905,-37.021271],"type":"Point"}
}