{
  "type": "Feature",
  "properties": {
    "addr:full":"39 North St  Timaru Canterbury",
    "addr:housenumber":"39",
    "addr:street":"North St",
    "iso:country":"NZ",
    "sg:address":"39 North St ",
    "sg:city":"Timaru",
    "sg:classifiers":[
        {
            "category":"Food & Beverages",
            "subcategory":"Liquor & Beverages",
            "type":"Retail Goods"
        }
    ],
    "sg:phone":"+64 3-684 6107",
    "sg:province":"Canterbury",
    "sg:tags":[
        "drink",
        "maker",
        "wine"
    ],
    "wof:name":"Montana Wines Limited",
    "wof:placetype":"venue"
},
  "geometry": {"coordinates":[171.25091599999999,-44.400291],"type":"Point"}
}