{
  "type": "Feature",
  "properties": {
    "addr:full":"Unit 7, 251 Lincoln Rd Henderson  Auckland Auckland",
    "addr:housenumber":"unit 7 251",
    "addr:street":"Lincoln Rd",
    "iso:country":"NZ",
    "sg:address":"Unit 7, 251 Lincoln Rd Henderson ",
    "sg:city":"Auckland",
    "sg:orig_category":"Industrial: Products: Filters And Filtration",
    "sg:phone":"+64 9-838 5515",
    "sg:province":"Auckland",
    "wof:name":"Aqua Dynamics",
    "wof:placetype":"venue"
},
  "geometry": {"coordinates":[174.62823499999999,-36.870419],"type":"Point"}
}