{
  "type": "Feature",
  "properties": {
    "addr:full":"89 Preston St Waikiwi  Invercargill Southland",
    "addr:housenumber":"89",
    "addr:street":"Preston St",
    "iso:country":"NZ",
    "sg:address":"89 Preston St Waikiwi ",
    "sg:city":"Invercargill",
    "sg:orig_category":"Transport: Transportation: Transport Operators",
    "sg:phone":"+64 3-215 8115",
    "sg:province":"Southland",
    "wof:name":"Wilder Transport Ltd",
    "wof:placetype":"venue"
},
  "geometry": {"coordinates":[168.35140999999999,-46.378384],"type":"Point"}
}