{
  "type": "Feature",
  "properties": {
    "addr:full":"42 Ridgway St  Wanganui Manawatu-Wanganui",
    "addr:housenumber":"42",
    "addr:street":"Ridgway St",
    "iso:country":"NZ",
    "sg:address":"42 Ridgway St ",
    "sg:city":"Wanganui",
    "sg:orig_category":"Home And Garden: Furniture/Furnishings: Blinds",
    "sg:phone":"+64 6-345 6119",
    "sg:province":"Manawatu-Wanganui",
    "wof:name":"Owens Curtain Service",
    "wof:placetype":"venue"
},
  "geometry": {"coordinates":[175.05415300000001,-39.933449],"type":"Point"}
}