{
  "type": "Feature",
  "properties": {
    "addr:full":"8 Coopers Rd Burwood  Christchurch Canterbury",
    "addr:housenumber":"8",
    "addr:street":"Coopers Rd",
    "iso:country":"NZ",
    "sg:address":"8 Coopers Rd Burwood ",
    "sg:city":"Christchurch",
    "sg:orig_category":"Home And Garden: Outdoor: Stonemasons",
    "sg:phone":"+64 3-385 3969",
    "sg:province":"Canterbury",
    "wof:name":"Alexandra Schist Stone",
    "wof:placetype":"venue"
},
  "geometry": {"coordinates":[172.68199200000001,-43.494564],"type":"Point"}
}