{
  "type": "Feature",
  "properties": {
    "addr:full":"Mt Albert cnr Alberton Ave & New North Rd  Auckland Auckland",
    "addr:street":"Cnr Alberton Ave & New North Rd",
    "iso:country":"NZ",
    "sg:address":"Mt Albert cnr Alberton Ave & New North Rd ",
    "sg:city":"Auckland",
    "sg:classifiers":[
        {
            "category":"Coffee & Tea",
            "type":"Food & Drink"
        }
    ],
    "sg:phone":"+64 9-849 4681",
    "sg:province":"Auckland",
    "sg:tags":[
        "vegetable",
        "fruit",
        "veges"
    ],
    "wof:name":"Produce Leader",
    "wof:placetype":"venue"
},
  "geometry": {"coordinates":[174.714798,-36.88784],"type":"Point"}
}