{
  "type": "Feature",
  "properties": {
    "iso:country":"NZ",
    "sg:address":"Northlands Shopping Centre Papanui ",
    "sg:city":"Christchurch",
    "sg:classifiers":[
        {
            "category":"Sports & Exercise",
            "subcategory":"Ski Resort",
            "type":"Entertainment"
        }
    ],
    "sg:phone":"+64 3-354 3909",
    "sg:province":"Canterbury",
    "sg:tags":[
        "hobbies",
        "photographic",
        "leisure",
        "developing"
    ],
    "wof:name":"Camera House",
    "wof:placetype":"venue"
},
  "geometry": {"coordinates":[172.599869,-43.496452],"type":"Point"}
}