{
  "type": "Feature",
  "properties": {
    "addr:full":"33 Wellington St  Picton Marlborough",
    "addr:housenumber":"33",
    "addr:street":"Wellington St",
    "iso:country":"NZ",
    "sg:address":"33 Wellington St ",
    "sg:city":"Picton",
    "sg:classifiers":[
        {
            "category":"Bars & Pubs",
            "subcategory":"Wine Bar",
            "type":"Food & Drink"
        }
    ],
    "sg:phone":"+64 3-573 6566",
    "sg:province":"Marlborough",
    "sg:tags":[
        "wining",
        "dining",
        "cafe"
    ],
    "wof:name":"Settlers Arms Bar & Cafe",
    "wof:placetype":"venue"
},
  "geometry": {"coordinates":[174.00756799999999,-41.293434],"type":"Point"}
}