{
  "type": "Feature",
  "properties": {
    "addr:full":"52 A Dublin St  Wanganui Manawatu-Wanganui",
    "addr:housenumber":"52",
    "addr:street":"A Dublin St",
    "iso:country":"NZ",
    "sg:address":"52 A Dublin St ",
    "sg:city":"Wanganui",
    "sg:orig_category":"Shopping: Retail Stores: Secondhand Dealers",
    "sg:phone":"+64 6-345 5442",
    "sg:province":"Manawatu-Wanganui",
    "wof:name":"Stop N Look",
    "wof:placetype":"venue"
},
  "geometry": {"coordinates":[175.046188,-39.925053],"type":"Point"}
}