{
  "type": "Feature",
  "properties": {
    "iso:country":"NZ",
    "sg:address":"49-51 Wilson St ",
    "sg:city":"Wanganui",
    "sg:classifiers":[
        {
            "category":"Manufacturing",
            "subcategory":"Tools & Machinery",
            "type":"Manufacturing & Wholesale Goods"
        }
    ],
    "sg:phone":"+64 6-348 8035",
    "sg:province":"Manawatu-Wanganui",
    "sg:tags":[
        "equipment",
        "industrial",
        "welding"
    ],
    "wof:name":"BOC",
    "wof:placetype":"venue"
},
  "geometry": {"coordinates":[175.04814099999999,-39.93494],"type":"Point"}
}