{
  "type": "Feature",
  "properties": {
    "addr:full":"717 Manukau Rd Royal Oak  Auckland Auckland",
    "addr:housenumber":"717",
    "addr:street":"Manukau Rd",
    "iso:country":"NZ",
    "sg:address":"717 Manukau Rd Royal Oak ",
    "sg:city":"Auckland",
    "sg:classifiers":[
        {
            "category":"Shopping",
            "subcategory":"Beauty & Cosmetics",
            "type":"Retail Goods"
        }
    ],
    "sg:phone":"+64 9-625 4921",
    "sg:province":"Auckland",
    "sg:tags":[
        "supply",
        "health",
        "hairdressing"
    ],
    "wof:name":"Dome New Zealand",
    "wof:placetype":"venue"
},
  "geometry": {"coordinates":[174.77593999999999,-36.911701],"type":"Point"}
}