{
  "type": "Feature",
  "properties": {
    "iso:country":"NZ",
    "sg:address":"136 Dee St ",
    "sg:city":"Invercargill",
    "sg:classifiers":[
        {
            "category":"Restaurant",
            "type":"Food & Drink"
        }
    ],
    "sg:phone":"+64 3-218 4381",
    "sg:province":"Southland",
    "sg:tags":[
        "merchant",
        "fish",
        "sea"
    ],
    "wof:name":"Superior Oysters Limited",
    "wof:placetype":"venue"
},
  "geometry": {"coordinates":[168.34732099999999,-46.392628],"type":"Point"}
}