{
  "type": "Feature",
  "properties": {
    "iso:country":"NZ",
    "sg:address":"407 Welcome Bay Rd Welcome Bay ",
    "sg:city":"Tauranga",
    "sg:classifiers":[
        {
            "category":"Food & Beverages",
            "subcategory":"Candy",
            "type":"Retail Goods"
        }
    ],
    "sg:phone":"+64 7-544 5074",
    "sg:province":"Bay of Plenty",
    "sg:tags":[
        "confectioner",
        "drink",
        "-"
    ],
    "wof:name":"Chocolates Galore",
    "wof:placetype":"venue"
},
  "geometry": {"coordinates":[176.20285000000001,-37.727306],"type":"Point"}
}