{
  "type": "Feature",
  "properties": {
    "addr:full":"11 A View Rd Henderson  Auckland Auckland",
    "addr:housenumber":"11",
    "addr:street":"A View Rd",
    "iso:country":"NZ",
    "sg:address":"11 A View Rd Henderson ",
    "sg:city":"Auckland",
    "sg:classifiers":[
        {
            "category":"Building & Trades",
            "subcategory":"Plumbing",
            "type":"Services"
        }
    ],
    "sg:phone":"+64 9-828 1735",
    "sg:province":"Auckland",
    "sg:tags":[
        "home",
        "plumber",
        "garden",
        "related"
    ],
    "wof:name":"Heron B H Ltd",
    "wof:placetype":"venue"
},
  "geometry": {"coordinates":[174.632812,-36.886375],"type":"Point"}
}