{
  "type": "Feature",
  "properties": {
    "addr:full":"73 Vanguard St  Nelson Nelson",
    "addr:housenumber":"73",
    "addr:street":"Vanguard St",
    "iso:country":"NZ",
    "sg:address":"73 Vanguard St ",
    "sg:city":"Nelson",
    "sg:classifiers":[
        {
            "category":"Manufacturing",
            "subcategory":"Furniture",
            "type":"Manufacturing & Wholesale Goods"
        }
    ],
    "sg:phone":"+64 3-546 8393",
    "sg:province":"Nelson",
    "sg:tags":[
        "furniture/furnishings",
        "home",
        "garden",
        "manufacturer"
    ],
    "wof:name":"Safari Furniture",
    "wof:placetype":"venue"
},
  "geometry": {"coordinates":[-121.765488,39.553471],"type":"Point"}
}