{
  "type": "Feature",
  "properties": {
    "iso:country":"NZ",
    "sg:address":"39 Glover Rd ",
    "sg:city":"Hawera",
    "sg:classifiers":[
        {
            "category":"Restaurant",
            "type":"Food & Drink"
        }
    ],
    "sg:phone":"+64 6-278 8566",
    "sg:province":"Taranaki",
    "sg:tags":[
        "fruit",
        "veges"
    ],
    "wof:name":"Prestidge Produce",
    "wof:placetype":"venue"
},
  "geometry": {"coordinates":[174.284027,-39.583309],"type":"Point"}
}