{
  "type": "Feature",
  "properties": {
    "iso:country":"NZ",
    "sg:address":"60 Whangapoua Rd ",
    "sg:city":"Coromandel",
    "sg:orig_category":"Travel And Tourism: Accommodation: Backpackers",
    "sg:phone":"+64 7-866 8237",
    "wof:name":"Tui Lodge Backpackers",
    "wof:placetype":"venue"
},
  "geometry": {"coordinates":[175.53694200000001,-36.749237],"type":"Point"}
}