{
  "type": "Feature",
  "properties": {
    "addr:full":"46 Marshland Rd Shirley  Christchurch Canterbury",
    "addr:housenumber":"46",
    "addr:street":"Marshland Rd",
    "iso:country":"NZ",
    "sg:address":"46 Marshland Rd Shirley ",
    "sg:city":"Christchurch",
    "sg:classifiers":[
        {
            "category":"Shopping",
            "subcategory":"Pharmacy",
            "type":"Retail Goods"
        }
    ],
    "sg:phone":"+64 3-385 2110",
    "sg:province":"Canterbury",
    "sg:tags":[
        "products",
        "medical",
        "health",
        "beauty",
        "supply"
    ],
    "wof:name":"Natural Advantage Ltd",
    "wof:placetype":"venue"
},
  "geometry": {"coordinates":[172.66270399999999,-43.50441],"type":"Point"}
}