{
  "type": "Feature",
  "properties": {
    "addr:full":"cnr Oxford & Queen Sts Richmond  Nelson Nelson",
    "addr:street":"Cnr",
    "iso:country":"NZ",
    "sg:address":"cnr Oxford & Queen Sts Richmond ",
    "sg:city":"Nelson",
    "sg:orig_category":"Automotive: General Services: Service Stations",
    "sg:phone":"+64 3-543 9231",
    "sg:province":"Nelson",
    "wof:name":"BP Service Stations",
    "wof:placetype":"venue"
},
  "geometry": {"coordinates":[-77.433418,37.54055],"type":"Point"}
}