{
  "type": "Feature",
  "properties": {
    "addr:full":"42 High St  Rangiora Canterbury",
    "addr:housenumber":"42",
    "addr:street":"High St",
    "iso:country":"NZ",
    "sg:address":"42 High St ",
    "sg:city":"Rangiora",
    "sg:classifiers":[
        {
            "category":"Health Services",
            "subcategory":"Optometrist",
            "type":"Services"
        }
    ],
    "sg:phone":"+64 3-313 8811",
    "sg:province":"Canterbury",
    "sg:tags":[
        "optical",
        "optician",
        "beauty"
    ],
    "wof:name":"Rangiora Optometrists",
    "wof:placetype":"venue"
},
  "geometry": {"coordinates":[172.59683200000001,-43.303104],"type":"Point"}
}