{
  "type": "Feature",
  "properties": {
    "iso:country":"NZ",
    "sg:address":"The Mall 65 St George St Papatoetoe ",
    "sg:city":"Auckland",
    "sg:classifiers":[
        {
            "category":"Education",
            "subcategory":"Special Training",
            "type":"Public Place"
        }
    ],
    "sg:phone":"+64 9-278 8503",
    "sg:province":"Otago",
    "sg:tags":[
        "tutor",
        "coach",
        "teacher"
    ],
    "wof:name":"Kip McGrath Education Centres (NZ) Ltd",
    "wof:placetype":"venue"
},
  "geometry": {"coordinates":[174.867157,-36.971188],"type":"Point"}
}