{
  "type": "Feature",
  "properties": {
    "iso:country":"NZ",
    "sg:address":"127 Greenlane Rd Greenlane ",
    "sg:city":"Auckland",
    "sg:classifiers":[
        {
            "category":"Professional",
            "type":"Services"
        }
    ],
    "sg:phone":"+64 9-373 4031",
    "sg:province":"Auckland",
    "sg:tags":[
        "services",
        "car",
        "valet",
        "automotive"
    ],
    "wof:name":"Washworld Services (Auckland) Ltd",
    "wof:placetype":"venue"
},
  "geometry": {"coordinates":[174.79191599999999,-36.892967],"type":"Point"}
}