{
  "type": "Feature",
  "properties": {
    "addr:full":"Wigram Airfield  Christchurch Canterbury",
    "iso:country":"NZ",
    "sg:address":"Wigram Airfield ",
    "sg:city":"Christchurch",
    "sg:orig_category":"Transport: Boats And Marine: Boats: Boat Maintenance",
    "sg:phone":"+64 3-341 5272",
    "sg:province":"Canterbury",
    "wof:name":"Mobile Mechanical Services Ltd",
    "wof:placetype":"venue"
},
  "geometry": {"coordinates":[172.54637099999999,-43.54747],"type":"Point"}
}