{
  "type": "Feature",
  "properties": {
    "iso:country":"NZ",
    "sg:address":"154 Lincoln Rd Henderson ",
    "sg:city":"Auckland",
    "sg:classifiers":[
        {
            "category":"Deli",
            "type":"Food & Drink"
        }
    ],
    "sg:phone":"+64 9-836 9922",
    "sg:province":"Auckland",
    "sg:tags":[
        "delicatessen",
        "-"
    ],
    "wof:name":"Bentru Foods Ltd",
    "wof:placetype":"venue"
},
  "geometry": {"coordinates":[174.628235,-36.870419],"type":"Point"}
}