{
  "type": "Feature",
  "properties": {
    "iso:country":"NZ",
    "sg:address":"Promed House Cnr Tenth Avenue & Edgecumbe Rd ",
    "sg:city":"Tauranga",
    "sg:classifiers":[
        {
            "category":"Personal",
            "subcategory":"Beauty Salon",
            "type":"Services"
        }
    ],
    "sg:phone":"+64 800 741 321",
    "sg:province":"Bay of Plenty",
    "sg:tags":[
        "specialists",
        "health",
        "treatment",
        "skin"
    ],
    "wof:name":"Skin Specialist Centre-Dr Kevin McKerrow",
    "wof:placetype":"venue"
},
  "geometry": {"coordinates":[176.14476,-37.703152],"type":"Point"}
}