{
  "type": "Feature",
  "properties": {
    "iso:country":"NZ",
    "sg:address":"10 Caernarvon St ",
    "sg:city":"Arrowtown",
    "sg:classifiers":[
        {
            "category":"Travel",
            "subcategory":"Hotels & Motels",
            "type":"Entertainment"
        }
    ],
    "sg:phone":"+64 3-442 0025",
    "sg:province":"Otago",
    "sg:tags":[
        "lodge",
        "tourism",
        "accommodation"
    ],
    "sg:website":"http://www.arrowtownhouse.co.nz",
    "wof:name":"Arrowtown House",
    "wof:placetype":"venue"
},
  "geometry": {"coordinates":[168.829315,-44.940113],"type":"Point"}
}