{
  "type": "Feature",
  "properties": {
    "iso:country":"NZ",
    "sg:address":"6 Greenhithe Rd Greenhithe ",
    "sg:city":"Auckland",
    "sg:orig_category":"Transport: Boats And Marine: Products: Outboard Motors",
    "sg:phone":"+64 9-413 9515",
    "sg:province":"Auckland",
    "wof:name":"Greenhithe Automotive & Marine",
    "wof:placetype":"venue"
},
  "geometry": {"coordinates":[174.669983,-36.776199],"type":"Point"}
}