{
  "type": "Feature",
  "properties": {
    "iso:country":"NZ",
    "sg:address":"Shop 9/721 High St Lower ",
    "sg:city":"Hutt",
    "sg:classifiers":[
        {
            "category":"Personal",
            "subcategory":"Hair Removal",
            "type":"Services"
        }
    ],
    "sg:phone":"+64 4-567 0474",
    "sg:province":"Wellington",
    "sg:tags":[
        "health",
        "beauty"
    ],
    "wof:name":"Beverley's House of Beauty",
    "wof:placetype":"venue"
},
  "geometry": {"coordinates":[174.904526,-41.208431],"type":"Point"}
}