{
  "type": "Feature",
  "properties": {
    "addr:full":"Town Basin Marina, Whangarei  Whangarei Northland",
    "iso:country":"NZ",
    "sg:address":"Town Basin Marina, Whangarei ",
    "sg:city":"Whangarei",
    "sg:classifiers":[
        {
            "category":"Restaurant",
            "type":"Food & Drink"
        }
    ],
    "sg:phone":"+64 9-438 8969",
    "sg:province":"Northland",
    "sg:tags":[
        "wining",
        "dining"
    ],
    "sg:website":"http://www.yellowpages.co.nz/pages/100199497/dp18620.html",
    "wof:name":"Reva's On The Waterfront",
    "wof:placetype":"venue"
},
  "geometry": {"coordinates":[174.34652700000001,-35.75285],"type":"Point"}
}