{
  "type": "Feature",
  "properties": {
    "iso:country":"NZ",
    "sg:address":"25 Birmingham Dve Middleton ",
    "sg:city":"Christchurch",
    "sg:classifiers":[
        {
            "category":"Manufacturing",
            "subcategory":"Tools & Machinery",
            "type":"Manufacturing & Wholesale Goods"
        }
    ],
    "sg:phone":"+64 3-338 7576",
    "sg:province":"Canterbury",
    "sg:tags":[
        "industrial",
        "equipment",
        "diamond",
        "tools"
    ],
    "wof:name":"A R Wylie Sales",
    "wof:placetype":"venue"
},
  "geometry": {"coordinates":[172.588943,-43.543518],"type":"Point"}
}