{
  "type": "Feature",
  "properties": {
    "iso:country":"NZ",
    "sg:address":"6 Colway Pl Glenfield ",
    "sg:city":"Auckland",
    "sg:classifiers":[
        {
            "category":"Retail",
            "subcategory":"Auto Repair",
            "type":"Services"
        }
    ],
    "sg:phone":"+64 9-443 2714",
    "sg:province":"Auckland",
    "sg:tags":[
        "automotive",
        "electric",
        "servicing"
    ],
    "wof:name":"A J Auto Electrical Limited",
    "wof:placetype":"venue"
},
  "geometry": {"coordinates":[174.73185699999999,-36.77441],"type":"Point"}
}