{
  "type": "Feature",
  "properties": {
    "iso:country":"NZ",
    "sg:address":"35 Bridge St Lower ",
    "sg:city":"Hutt",
    "sg:classifiers":[
        {
            "category":"Ice Cream",
            "type":"Food & Drink"
        }
    ],
    "sg:phone":"+64 4-589 3337",
    "sg:province":"Wellington",
    "sg:tags":[
        "frozen",
        "-"
    ],
    "wof:name":"Service Foods (Wgtn) Ltd",
    "wof:placetype":"venue"
},
  "geometry": {"coordinates":[174.904526,-41.208431],"type":"Point"}
}