{
  "type": "Feature",
  "properties": {
    "iso:country":"NZ",
    "sg:address":"241 Annex Rd Middleton ",
    "sg:city":"Christchurch",
    "sg:classifiers":[
        {
            "category":"Manufacturing",
            "subcategory":"Metals",
            "type":"Manufacturing & Wholesale Goods"
        }
    ],
    "sg:phone":"+64 3-341 6558",
    "sg:province":"Canterbury",
    "sg:tags":[
        "-",
        "engineering",
        "industrial",
        "sheet",
        "engineer"
    ],
    "sg:website":"http://www.cromptons.co.nz",
    "wof:name":"Cromptons Sheet Metal Industries Ltd",
    "wof:placetype":"venue"
},
  "geometry": {"coordinates":[172.580002,-43.54261],"type":"Point"}
}