{
  "type": "Feature",
  "properties": {
    "addr:full":"Parnell  Auckland Auckland",
    "iso:country":"NZ",
    "sg:address":"Parnell ",
    "sg:city":"Auckland",
    "sg:classifiers":[
        {
            "category":"Arts & Performance",
            "subcategory":"Music",
            "type":"Entertainment"
        }
    ],
    "sg:phone":"+64 9-303 4757",
    "sg:province":"Auckland",
    "sg:tags":[
        "mobile",
        "sport",
        "-",
        "leisure",
        "disco"
    ],
    "wof:name":"Discomix Professional DJs",
    "wof:placetype":"venue"
},
  "geometry": {"coordinates":[174.78608700000001,-36.85479],"type":"Point"}
}