{
  "type": "Feature",
  "properties": {
    "iso:country":"NZ",
    "sg:address":"Te Wahapu Rd ",
    "sg:city":"Russell",
    "sg:classifiers":[
        {
            "category":"Recreation",
            "type":"Entertainment"
        }
    ],
    "sg:phone":"+64 9-403 7770",
    "sg:tags":[
        "shopping",
        "hunting",
        "fishing",
        "retailers",
        "sport",
        "trip"
    ],
    "wof:name":"Mako Lodge & Fishing Charters",
    "wof:placetype":"venue"
},
  "geometry": {"coordinates":[116.27932,37.446011],"type":"Point"}
}