{
  "type": "Feature",
  "properties": {
    "iso:country":"NZ",
    "sg:address":"59 Taylor Rd Waimauku ",
    "sg:city":"Auckland",
    "sg:orig_category":"Shopping: Hobbies And Games: Aromatherapy",
    "sg:phone":"+64 9-411 7470",
    "sg:province":"Auckland",
    "wof:name":"Essential Dreamtime",
    "wof:placetype":"venue"
},
  "geometry": {"coordinates":[174.494232,-36.754848],"type":"Point"}
}