{
  "type": "Feature",
  "properties": {
    "iso:country":"NZ",
    "sg:address":"Waikato & Bay of Plenty Serving the Central North",
    "sg:city":"Island",
    "sg:classifiers":[
        {
            "category":"Farming",
            "subcategory":"Farm",
            "type":"Manufacturing & Wholesale Goods"
        }
    ],
    "sg:phone":"+64 800 928 886",
    "sg:website":"http://www.groundspread.co.nz",
    "wof:name":"Wealleans Groundspread",
    "wof:placetype":"venue"
},
  "geometry": {"coordinates":[176.956741,-38.188862],"type":"Point"}
}