{
  "type": "Feature",
  "properties": {
    "iso:country":"NZ",
    "sg:address":"BNZ Centre 1 Willis St ",
    "sg:city":"Wellington",
    "sg:classifiers":[
        {
            "category":"Food & Beverages",
            "subcategory":"Candy",
            "type":"Retail Goods"
        }
    ],
    "sg:phone":"+64 4-472 7000",
    "sg:province":"Wellington",
    "sg:tags":[
        "confectioner",
        "drink",
        "-"
    ],
    "wof:name":"Kirbies Candies & Lotto",
    "wof:placetype":"venue"
},
  "geometry": {"coordinates":[-87.683342,40.539139],"type":"Point"}
}