{
  "type": "Feature",
  "properties": {
    "iso:country":"NZ",
    "sg:address":"14 Melrose St Newmarket ",
    "sg:city":"Auckland",
    "sg:classifiers":[
        {
            "category":"Wholesale",
            "subcategory":"Hardware",
            "type":"Manufacturing & Wholesale Goods"
        }
    ],
    "sg:phone":"+64 9-520 3889",
    "sg:province":"Auckland",
    "sg:tags":[
        "gardening",
        "garden",
        "chainsaw",
        "products",
        "brush",
        "home",
        "cutter"
    ],
    "wof:name":"Newmarket Mowers & Machinery",
    "wof:placetype":"venue"
},
  "geometry": {"coordinates":[174.774475,-36.867645],"type":"Point"}
}