{
  "type": "Feature",
  "properties": {
    "addr:full":"Westpac Plaza Moana Ave Orewa Hibiscus  Hibiscus Coast Auckland",
    "addr:street":"Moana Ave",
    "iso:country":"NZ",
    "sg:address":"Westpac Plaza Moana Ave Orewa Hibiscus ",
    "sg:city":"Hibiscus Coast",
    "sg:classifiers":[
        {
            "category":"Shopping",
            "subcategory":"Crafts & Fabrics",
            "type":"Retail Goods"
        }
    ],
    "sg:phone":"+64 9-427 5666",
    "sg:province":"Auckland",
    "sg:tags":[
        "sport",
        "art",
        "leisure",
        "hobbies"
    ],
    "wof:name":"Work In Progress Artist Supplies",
    "wof:placetype":"venue"
},
  "geometry": {"coordinates":[174.69012499999999,-36.582741],"type":"Point"}
}