{
  "type": "Feature",
  "properties": {
    "addr:full":"18 Selwyn St Onehunga  Auckland Auckland",
    "addr:housenumber":"18",
    "addr:street":"Selwyn St",
    "iso:country":"NZ",
    "sg:address":"18 Selwyn St Onehunga ",
    "sg:city":"Auckland",
    "sg:classifiers":[
        {
            "category":"Retail",
            "subcategory":"Auto Repair",
            "type":"Services"
        }
    ],
    "sg:phone":"+64 9-634 3437",
    "sg:province":"Auckland",
    "sg:tags":[
        "automotive",
        "panel",
        "servicing",
        "beater"
    ],
    "wof:name":"Longley Panelbeaters Ltd",
    "wof:placetype":"venue"
},
  "geometry": {"coordinates":[174.78332499999999,-36.925995],"type":"Point"}
}