{
  "type": "Feature",
  "properties": {
    "iso:country":"NZ",
    "sg:address":"18 Selwyn St Onehunga ",
    "sg:city":"Auckland",
    "sg:classifiers":[
        {
            "category":"Retail",
            "subcategory":"Auto Repair",
            "type":"Services"
        }
    ],
    "sg:phone":"+64 9-634 3437",
    "sg:province":"Auckland",
    "sg:tags":[
        "automotive",
        "panel",
        "servicing",
        "beater"
    ],
    "wof:name":"Longley Panelbeaters Ltd",
    "wof:placetype":"venue"
},
  "geometry": {"coordinates":[174.783325,-36.925995],"type":"Point"}
}