{
  "type": "Feature",
  "properties": {
    "addr:full":"8 Volkner Pl North Harbour  Auckland Auckland",
    "addr:housenumber":"8",
    "addr:street":"Volkner Pl North",
    "iso:country":"NZ",
    "sg:address":"8 Volkner Pl North Harbour ",
    "sg:city":"Auckland",
    "sg:classifiers":[
        {
            "category":"Marine",
            "type":"Transportation"
        }
    ],
    "sg:phone":"+64 9-415 8774",
    "sg:province":"Auckland",
    "sg:tags":[
        "transport",
        "boat"
    ],
    "sg:website":"http://www.customyachtsnz.com",
    "wof:name":"Custom Yachts Ltd",
    "wof:placetype":"venue"
},
  "geometry": {"coordinates":[174.630798,-36.818272],"type":"Point"}
}