{
  "type": "Feature",
  "properties": {
    "addr:full":"2/65 Aerodrome Rd Mt  Maunganui Bay of Plenty",
    "addr:housenumber":"2 / 65",
    "addr:street":"Aerodrome Rd;Maunganui",
    "iso:country":"NZ",
    "sg:address":"2/65 Aerodrome Rd Mt ",
    "sg:city":"Maunganui",
    "sg:orig_category":"Transport: Boats And Marine: Boats: Boat Maintenance",
    "sg:phone":"+64 7-574 1116",
    "sg:province":"Bay of Plenty",
    "wof:name":"B & J Marine Screens & Glass",
    "wof:placetype":"venue"
},
  "geometry": {"coordinates":[176.18627900000001,-37.641048],"type":"Point"}
}