{
  "type": "Feature",
  "properties": {
    "iso:country":"NZ",
    "sg:address":"35 Sheffield Cre ",
    "sg:city":"Christchurch",
    "sg:classifiers":[
        {
            "category":"Airport",
            "type":"Transportation"
        }
    ],
    "sg:phone":"+64 3-358 7816",
    "sg:province":"Canterbury",
    "sg:tags":[
        "aircraft",
        "transport",
        "sale",
        "maintenance",
        "air"
    ],
    "wof:name":"Aviation Support Services Ltd",
    "wof:placetype":"venue"
},
  "geometry": {"coordinates":[172.562286,-43.489048],"type":"Point"}
}