{
  "type": "Feature",
  "properties": {
    "addr:full":"104 Tennyson St  Napier Hawke's Bay",
    "addr:housenumber":"104",
    "addr:street":"Tennyson St",
    "iso:country":"NZ",
    "sg:address":"104 Tennyson St ",
    "sg:city":"Napier",
    "sg:classifiers":[
        {
            "category":"Health Services",
            "subcategory":"Optometrist",
            "type":"Services"
        }
    ],
    "sg:phone":"+64 6-835 2020",
    "sg:province":"Hawke's Bay",
    "sg:tags":[
        "optical",
        "optician",
        "beauty"
    ],
    "wof:name":"Herb Maynard Optometrist",
    "wof:placetype":"venue"
},
  "geometry": {"coordinates":[-80.588562,38.790821],"type":"Point"}
}