{
  "type": "Feature",
  "properties": {
    "iso:country":"NZ",
    "sg:address":"118 Yarrow St ",
    "sg:city":"Invercargill",
    "sg:classifiers":[
        {
            "category":"Recreation",
            "subcategory":"Gun Range",
            "type":"Entertainment"
        }
    ],
    "sg:phone":"+64 3-218 4271",
    "sg:province":"Southland",
    "sg:tags":[
        "sports",
        "sport",
        "-",
        "leisure",
        "gunsmith"
    ],
    "wof:name":"Bargain Corner Ltd",
    "wof:placetype":"venue"
},
  "geometry": {"coordinates":[168.355484,-46.408394],"type":"Point"}
}