{
  "type": "Feature",
  "properties": {
    "addr:full":"M/35 Maurice Rd Penrose  Auckland Auckland",
    "addr:housenumber":"35",
    "addr:street":"M;Maurice Rd",
    "iso:country":"NZ",
    "sg:address":"M/35 Maurice Rd Penrose ",
    "sg:city":"Auckland",
    "sg:orig_category":"Industrial: Equipment And Machinery: Compressors",
    "sg:phone":"+64 9-636 1031",
    "sg:province":"Auckland",
    "wof:name":"Hoerbiger N Z Ltd",
    "wof:placetype":"venue"
},
  "geometry": {"coordinates":[174.81016500000001,-36.911617],"type":"Point"}
}