{
  "type": "Feature",
  "properties": {
    "addr:full":"PO Box 71112 Avondale  Auckland Auckland",
    "addr:housenumber":"po box 71112",
    "iso:country":"NZ",
    "sg:address":"PO Box 71112 Avondale ",
    "sg:city":"Auckland",
    "sg:classifiers":[
        {
            "category":"Utilities",
            "subcategory":"Fuel Oil & Lpg",
            "type":"Services"
        }
    ],
    "sg:phone":"+64 9-828 3255",
    "sg:province":"Auckland",
    "sg:tags":[
        "petrol",
        "energy",
        "industrial",
        "utilities"
    ],
    "wof:name":"Fuchs Lubricants (Australasia) Pty Ltd",
    "wof:placetype":"venue"
},
  "geometry": {"coordinates":[174.690933,-36.8932],"type":"Point"}
}