{
  "type": "Feature",
  "properties": {
    "addr:full":"115 Harris Rd East Tamaki  Auckland Auckland",
    "addr:housenumber":"115",
    "addr:street":"Harris Rd",
    "iso:country":"NZ",
    "sg:address":"115 Harris Rd East Tamaki ",
    "sg:city":"Auckland",
    "sg:orig_category":"Home And Garden: Outdoor: Driveways",
    "sg:phone":"+64 9-274 6357",
    "sg:province":"Auckland",
    "sg:website":"http://www.yellowpages.co.nz/pages/201097465/dp51584.html",
    "wof:name":"The Cobblestone Factory",
    "wof:placetype":"venue"
},
  "geometry": {"coordinates":[174.89651499999999,-36.932922],"type":"Point"}
}