{
  "type": "Feature",
  "properties": {
    "addr:full":"1 Conical Hill Rd Hanmer  Springs",
    "addr:housenumber":"1",
    "addr:street":"Conical Hill Rd",
    "iso:country":"NZ",
    "sg:address":"1 Conical Hill Rd Hanmer ",
    "sg:city":"Springs",
    "sg:classifiers":[
        {
            "category":"Travel",
            "subcategory":"Hotels & Motels",
            "type":"Entertainment"
        }
    ],
    "sg:phone":"+64 3-315 7021",
    "sg:tags":[
        "tourism",
        "accommodation"
    ],
    "sg:website":"http://www.heritagehotels.co.nz",
    "wof:name":"Heritage Hanmer Springs",
    "wof:placetype":"venue"
},
  "geometry": {"coordinates":[172.829498,-42.52071],"type":"Point"}
}