{
  "type": "Feature",
  "properties": {
    "addr:full":"215 Queen St East  Hastings Hawke's Bay",
    "addr:housenumber":"215",
    "addr:street":"Queen St East",
    "iso:country":"NZ",
    "sg:address":"215 Queen St East ",
    "sg:city":"Hastings",
    "sg:classifiers":[
        {
            "category":"Manufacturing",
            "subcategory":"Textiles",
            "type":"Manufacturing & Wholesale Goods"
        }
    ],
    "sg:phone":"+64 6-878 1800",
    "sg:province":"Hawke's Bay",
    "sg:tags":[
        "clothing",
        "fabric",
        "manufacturer"
    ],
    "wof:name":"Brandlab Ltd",
    "wof:placetype":"venue"
},
  "geometry": {"coordinates":[-81.508163,29.711214],"type":"Point"}
}