{
  "type": "Feature",
  "properties": {
    "addr:full":"Enquiries Longburn Palmerston  Palmerston North Manawatu-Wanganui",
    "addr:street":"Palmerston",
    "iso:country":"NZ",
    "sg:address":"Enquiries Longburn Palmerston ",
    "sg:city":"Palmerston North",
    "sg:classifiers":[
        {
            "category":"Home & Garden",
            "subcategory":"Garden Supply",
            "type":"Retail Goods"
        }
    ],
    "sg:phone":"+64 6-353 6002",
    "sg:province":"Manawatu-Wanganui",
    "sg:tags":[
        "trainer",
        "breeder",
        "/",
        "pets",
        "animal"
    ],
    "wof:name":"Tararua Allbreeds Dog Training Club",
    "wof:placetype":"venue"
},
  "geometry": {"coordinates":[175.53750600000001,-40.386024],"type":"Point"}
}