{
  "type": "Feature",
  "properties": {
    "addr:full":"186 Te Irirangi Dve East Tamaki  Auckland Auckland",
    "addr:housenumber":"186",
    "addr:street":"Te Irirangi Dve",
    "iso:country":"NZ",
    "sg:address":"186 Te Irirangi Dve East Tamaki ",
    "sg:city":"Auckland",
    "sg:classifiers":[
        {
            "category":"Food & Beverages",
            "subcategory":"Liquor & Beverages",
            "type":"Retail Goods"
        }
    ],
    "sg:phone":"+64 9-274 7890",
    "sg:province":"Auckland",
    "sg:tags":[
        "drink",
        "outlet"
    ],
    "wof:name":"The Mill Liquorsave",
    "wof:placetype":"venue"
},
  "geometry": {"coordinates":[174.90419,-36.956623],"type":"Point"}
}