{
  "type": "Feature",
  "properties": {
    "iso:country":"NZ",
    "sg:address":"20 Octavius Pl New ",
    "sg:city":"Plymouth",
    "sg:classifiers":[
        {
            "category":"Professional",
            "type":"Services"
        }
    ],
    "sg:phone":"+64 6-758 5190",
    "sg:province":"Taranaki",
    "sg:tags":[
        "home",
        "cleaning",
        "help",
        "garden"
    ],
    "wof:name":"Presbyterian Support Central",
    "wof:placetype":"venue"
},
  "geometry": {"coordinates":[-116.81972500000001,43.97221],"type":"Point"}
}