{
  "type": "Feature",
  "properties": {
    "addr:full":"Abel Tasman National Park Marahau Beach Marahau  Motueka Tasman",
    "addr:street":"Abel;Tasman",
    "iso:country":"NZ",
    "sg:address":"Abel Tasman National Park Marahau Beach Marahau ",
    "sg:city":"Motueka",
    "sg:classifiers":[
        {
            "category":"Travel",
            "subcategory":"Hotels & Motels",
            "type":"Entertainment"
        }
    ],
    "sg:phone":"+64 3-527 8250",
    "sg:province":"Tasman",
    "sg:tags":[
        "holiday",
        "tourism",
        "accommodation"
    ],
    "sg:website":"http://www.AbelTasmanMarahauLodge.co.nz",
    "wof:name":"Abel Tasman Marahau Lodge",
    "wof:placetype":"venue"
},
  "geometry": {"coordinates":[173.008759,-41.00827],"type":"Point"}
}