{
  "type": "Feature",
  "properties": {
    "iso:country":"NZ",
    "sg:address":"2 Freyberg St Lyall Bay ",
    "sg:city":"Wellington",
    "sg:classifiers":[
        {
            "category":"Health Services",
            "subcategory":"Dentist",
            "type":"Services"
        }
    ],
    "sg:phone":"+64 4-387 8820",
    "sg:province":"Wellington",
    "sg:tags":[
        "dental",
        "clinic",
        "beauty"
    ],
    "wof:name":"Lyall Bay School Dental Clinic",
    "wof:placetype":"venue"
},
  "geometry": {"coordinates":[174.79341099999999,-41.329029],"type":"Point"}
}