{
  "type": "Feature",
  "properties": {
    "addr:full":"13 McGlashen Ave Richmond  Nelson Nelson",
    "addr:housenumber":"13",
    "addr:street":"Mcglashen Ave",
    "iso:country":"NZ",
    "sg:address":"13 McGlashen Ave Richmond ",
    "sg:city":"Nelson",
    "sg:classifiers":[
        {
            "category":"Professional",
            "subcategory":"Detective & Security Services",
            "type":"Services"
        }
    ],
    "sg:phone":"+64 3-544 9111",
    "sg:province":"Nelson",
    "sg:tags":[
        "services",
        "automotive",
        "warrant",
        "fitness"
    ],
    "wof:name":"Richmond Vehicle Testing Station",
    "wof:placetype":"venue"
},
  "geometry": {"coordinates":[-121.765488,39.553471],"type":"Point"}
}