{
  "type": "Feature",
  "properties": {
    "iso:country":"NZ",
    "sg:address":"Transrail Building Humber St ",
    "sg:city":"Oamaru",
    "sg:orig_category":"Transport: Transportation: Transport Operators",
    "sg:phone":"+64 3-434 9804",
    "sg:province":"Otago",
    "wof:name":"QBL Transport",
    "wof:placetype":"venue"
},
  "geometry": {"coordinates":[170.969025,-45.097145],"type":"Point"}
}