{
  "type": "Feature",
  "properties": {
    "iso:country":"NZ",
    "sg:address":"PO Box 7023 Wellesley Street ",
    "sg:city":"Auckland",
    "sg:classifiers":[
        {
            "category":"Arena",
            "subcategory":"Sports Club",
            "type":"Entertainment"
        }
    ],
    "sg:phone":"+64 9-575 1973",
    "sg:province":"Manawatu-Wanganui",
    "sg:tags":[
        "arts",
        "writer",
        "leisure",
        "author"
    ],
    "wof:name":"K W Barron-Afeaki",
    "wof:placetype":"venue"
},
  "geometry": {"coordinates":[-119.104576,36.597755],"type":"Point"}
}