{
  "type": "Feature",
  "properties": {
    "addr:full":"477 Te Atatu Rd Te Atatu Peninsula  Auckland Auckland",
    "addr:housenumber":"477",
    "addr:street":"Te Atatu Rd",
    "iso:country":"NZ",
    "sg:address":"477 Te Atatu Rd Te Atatu Peninsula ",
    "sg:city":"Auckland",
    "sg:classifiers":[
        {
            "category":"Retail",
            "subcategory":"Auto Repair",
            "type":"Services"
        }
    ],
    "sg:phone":"+64 9-834 6024",
    "sg:province":"Auckland",
    "sg:tags":[
        "automotive",
        "panel",
        "servicing",
        "beater"
    ],
    "wof:name":"Autocourt Service Centre",
    "wof:placetype":"venue"
},
  "geometry": {"coordinates":[174.65164200000001,-36.846275],"type":"Point"}
}