{
  "type": "Feature",
  "properties": {
    "addr:full":"50 Douglas Rd Annesbrook  Nelson Nelson",
    "addr:housenumber":"50",
    "addr:street":"Douglas Rd",
    "iso:country":"NZ",
    "sg:address":"50 Douglas Rd Annesbrook ",
    "sg:city":"Nelson",
    "sg:orig_category":"Farming: Horticulture: Flowers",
    "sg:phone":"+64 3-546 4677",
    "sg:province":"Nelson",
    "wof:name":"Global Flowers",
    "wof:placetype":"venue"
},
  "geometry": {"coordinates":[173.24923699999999,-41.296108],"type":"Point"}
}