{
  "type": "Feature",
  "properties": {
    "iso:country":"NZ",
    "sg:address":"56 Te Puna Rd Te Puna ",
    "sg:city":"Tauranga",
    "sg:orig_category":"Home And Garden: Gardening: Services: Tree Services",
    "sg:phone":"+64 7-552 6477",
    "sg:province":"Bay of Plenty",
    "wof:name":"Steve's Stump Grinding & Garden Maintenance",
    "wof:placetype":"venue"
},
  "geometry": {"coordinates":[176.073334,-37.692341],"type":"Point"}
}