{
  "type": "Feature",
  "properties": {
    "addr:full":"164 Broadway  Stratford Manawatu-Wanganui",
    "addr:housenumber":"164",
    "addr:street":"Broadway",
    "iso:country":"NZ",
    "sg:address":"164 Broadway ",
    "sg:city":"Stratford",
    "sg:orig_category":"Sports And Leisure: Sports: Equestrian: Equestrian Supplies",
    "sg:phone":"+64 6-765 7769",
    "sg:province":"Manawatu-Wanganui",
    "wof:name":"Golden Tan Saddlery",
    "wof:placetype":"venue"
},
  "geometry": {"coordinates":[-73.123062,41.189896],"type":"Point"}
}