{
  "type": "Feature",
  "properties": {
    "iso:country":"NZ",
    "sg:address":"274 Lincoln Rd Addington ",
    "sg:city":"Christchurch",
    "sg:classifiers":[
        {
            "category":"Recreation",
            "type":"Entertainment"
        }
    ],
    "sg:phone":"+64 3-338 9766",
    "sg:province":"Canterbury",
    "sg:tags":[
        "sport",
        "tramping",
        "leisure",
        "camping"
    ],
    "wof:name":"Challenge Yachts",
    "wof:placetype":"venue"
},
  "geometry": {"coordinates":[172.61035200000001,-43.544521],"type":"Point"}
}