{
  "type": "Feature",
  "properties": {
    "iso:country":"NZ",
    "sg:address":"9/69 Portage Rd Otahuhu ",
    "sg:city":"Auckland",
    "sg:classifiers":[
        {
            "category":"Retail",
            "subcategory":"Auto Repair",
            "type":"Services"
        }
    ],
    "sg:phone":"+64 9-276 3917",
    "sg:province":"Auckland",
    "sg:tags":[
        "automotive",
        "panel",
        "servicing",
        "beater"
    ],
    "wof:name":"Owen Shaw Panelbeaters",
    "wof:placetype":"venue"
},
  "geometry": {"coordinates":[174.83805799999999,-36.935528],"type":"Point"}
}