{
  "type": "Feature",
  "properties": {
    "addr:full":"Norfolk Rd Carterton  Masterton Wellington",
    "addr:street":"Norfolk Rd",
    "iso:country":"NZ",
    "sg:address":"Norfolk Rd Carterton ",
    "sg:city":"Masterton",
    "sg:classifiers":[
        {
            "category":"Personal",
            "subcategory":"Massage",
            "type":"Services"
        }
    ],
    "sg:phone":"+64 6-370 2625",
    "sg:province":"Wellington",
    "sg:tags":[
        "services",
        "health",
        "-",
        "beauty",
        "fitness"
    ],
    "wof:name":"Judith Stehr Massage Therapist",
    "wof:placetype":"venue"
},
  "geometry": {"coordinates":[175.55990600000001,-40.928875],"type":"Point"}
}