{
  "type": "Feature",
  "properties": {
    "iso:country":"NZ",
    "sg:address":"22 North Rd Waikiwi ",
    "sg:city":"Invercargill",
    "sg:classifiers":[
        {
            "category":"Utilities",
            "subcategory":"Electric",
            "type":"Services"
        }
    ],
    "sg:phone":"+64 3-215 9671",
    "sg:province":"Southland",
    "sg:tags":[
        "energy",
        "industrial"
    ],
    "wof:name":"Invercargill Sump Cleaning",
    "wof:placetype":"venue"
},
  "geometry": {"coordinates":[168.34761,-46.388798],"type":"Point"}
}