{
  "type": "Feature",
  "properties": {
    "addr:full":"7-21 Walls Rd Penrose  Auckland Auckland",
    "addr:housenumber":"7-21",
    "addr:street":"Walls Rd",
    "iso:country":"NZ",
    "sg:address":"7-21 Walls Rd Penrose ",
    "sg:city":"Auckland",
    "sg:orig_category":"Industrial: Packaging: Packaging Machinery",
    "sg:phone":"+64 9-579 3939",
    "sg:province":"Auckland",
    "wof:name":"Walls Machinery NZ Ltd",
    "wof:placetype":"venue"
},
  "geometry": {"coordinates":[174.810394,-36.909195],"type":"Point"}
}