{
  "type": "Feature",
  "properties": {
    "addr:full":"Dunedin Airport  Dunedin Otago",
    "iso:country":"NZ",
    "sg:address":"Dunedin Airport ",
    "sg:city":"Dunedin",
    "sg:classifiers":[
        {
            "category":"Airline",
            "type":"Transportation"
        }
    ],
    "sg:phone":"+64 800 486 228",
    "sg:province":"Otago",
    "sg:tags":[
        "services",
        "travel",
        "tourism"
    ],
    "wof:name":"Alpine Air Services Ltd",
    "wof:placetype":"venue"
},
  "geometry": {"coordinates":[170.19851700000001,-45.928661],"type":"Point"}
}