{
  "type": "Feature",
  "properties": {
    "addr:full":"25 Gill St New  Plymouth Taranaki",
    "addr:housenumber":"25",
    "addr:street":"Gill St",
    "iso:country":"NZ",
    "sg:address":"25 Gill St New ",
    "sg:city":"Plymouth",
    "sg:classifiers":[
        {
            "category":"Health Services",
            "subcategory":"Health Practitioner",
            "type":"Services"
        }
    ],
    "sg:phone":"+64 6-759 1810",
    "sg:province":"Taranaki",
    "sg:tags":[
        "specialist",
        "medical",
        "beauty",
        "specialists"
    ],
    "sg:website":"http://www.doctorglobal.com",
    "wof:name":"Doctor Global Ltd",
    "wof:placetype":"venue"
},
  "geometry": {"coordinates":[174.07508899999999,-39.056343],"type":"Point"}
}