{
  "type": "Feature",
  "properties": {
    "iso:country":"NZ",
    "sg:address":"cnr Avalon Dv & Foreman Rd Te Rapa ",
    "sg:city":"Hamilton",
    "sg:orig_category":"Industrial: Packaging: Packaging - General",
    "sg:phone":"+64 7-850 0100",
    "sg:province":"Waikato",
    "wof:name":"Cryovac / Sealed Air (New Zealand) Ltd",
    "wof:placetype":"venue"
},
  "geometry": {"coordinates":[175.239365,-37.752701],"type":"Point"}
}