{
  "type": "Feature",
  "properties": {
    "addr:full":"12 B Normans Rd Papanui  Christchurch Canterbury",
    "addr:housenumber":"12 b",
    "addr:street":"Normans Rd",
    "iso:country":"NZ",
    "sg:address":"12 B Normans Rd Papanui ",
    "sg:city":"Christchurch",
    "sg:orig_category":"Home And Garden: Gardening: Products: Lawnmowers",
    "sg:phone":"+64 3-355 9323",
    "sg:province":"Canterbury",
    "wof:name":"Martyn's Cycles & Mowers",
    "wof:placetype":"venue"
},
  "geometry": {"coordinates":[172.609421,-43.50901],"type":"Point"}
}