{
  "type": "Feature",
  "properties": {
    "addr:full":"Sky High Rd Hunua R D 3 Papakura  Auckland Auckland",
    "addr:housenumber":"3",
    "addr:street":"High Rd;R D",
    "iso:country":"NZ",
    "sg:address":"Sky High Rd Hunua R D 3 Papakura ",
    "sg:city":"Auckland",
    "sg:orig_category":"Farming: Services: Irrigation",
    "sg:phone":"+64 9-292 4797",
    "sg:province":"Auckland",
    "wof:name":"Imagescapers",
    "wof:placetype":"venue"
},
  "geometry": {"coordinates":[174.95945699999999,-37.059521],"type":"Point"}
}