{
  "type": "Feature",
  "properties": {
    "addr:full":"PO Box 17-486  Greenlane Auckland",
    "addr:housenumber":"po box 17-486",
    "iso:country":"NZ",
    "sg:address":"PO Box 17-486 ",
    "sg:city":"Greenlane",
    "sg:classifiers":[
        {
            "category":"Restaurant",
            "type":"Food & Drink"
        }
    ],
    "sg:phone":"+64 9-522 4221",
    "sg:province":"Auckland",
    "sg:tags":[
        "health",
        "auditor"
    ],
    "wof:name":"Verification New Zealand Ltd",
    "wof:placetype":"venue"
},
  "geometry": {"coordinates":[174.79191599999999,-36.892967],"type":"Point"}
}