{
  "type": "Feature",
  "properties": {
    "addr:full":"1 Lancaster St Waltham  Christchurch Canterbury",
    "addr:housenumber":"1",
    "addr:street":"Lancaster St",
    "iso:country":"NZ",
    "sg:address":"1 Lancaster St Waltham ",
    "sg:city":"Christchurch",
    "sg:orig_category":"Shopping: Accessories: Accessories - Clothing",
    "sg:phone":"+64 3-377 2552",
    "sg:province":"Canterbury",
    "wof:name":"Corozo Buttons",
    "wof:placetype":"venue"
},
  "geometry": {"coordinates":[172.654312,-43.540977],"type":"Point"}
}