{
  "type": "Feature",
  "properties": {
    "iso:country":"NZ",
    "sg:address":"Christchurch Adaroa Rd Tai ",
    "sg:city":"Tapu",
    "sg:orig_category":"Home And Garden: Gardening: Products: Lawnmowers",
    "sg:phone":"+64 3-329 6800",
    "wof:name":"Tai Tapu Mower & Hire Centre",
    "wof:placetype":"venue"
},
  "geometry": {"coordinates":[172.547821,-43.663319],"type":"Point"}
}