{
  "type": "Feature",
  "properties": {
    "addr:full":"381 Heads Rd  Wanganui Manawatu-Wanganui",
    "addr:housenumber":"381",
    "addr:street":"Heads Rd",
    "iso:country":"NZ",
    "sg:address":"381 Heads Rd ",
    "sg:city":"Wanganui",
    "sg:orig_category":"Farming: Forestry: Logging Services",
    "sg:phone":"+64 6-344 4398",
    "sg:province":"Manawatu-Wanganui",
    "wof:name":"Ali Arc Trailers Ltd",
    "wof:placetype":"venue"
},
  "geometry": {"coordinates":[175.01130699999999,-39.948151],"type":"Point"}
}