{
  "type": "Feature",
  "properties": {
    "iso:country":"NZ",
    "sg:address":"Mornington Mall 45 Mailer St Mornington ",
    "sg:city":"Dunedin",
    "sg:classifiers":[
        {
            "category":"Personal",
            "subcategory":"Shoe Repair & Shine",
            "type":"Services"
        }
    ],
    "sg:phone":"+64 3-453 5571",
    "sg:province":"Otago",
    "sg:tags":[
        "foot",
        "clothing",
        "fabric",
        "wear"
    ],
    "wof:name":"Country Cobbler Shoe Repairs",
    "wof:placetype":"venue"
},
  "geometry": {"coordinates":[170.477402,-45.885113],"type":"Point"}
}