{
  "type": "Feature",
  "properties": {
    "iso:country":"NZ",
    "sg:address":"16 Mohuia Cre Elsdon ",
    "sg:city":"Porirua",
    "sg:orig_category":"Industrial: Energy And Utilities: Gas",
    "sg:phone":"+64 4-237 7448",
    "sg:province":"Wellington",
    "wof:name":"Porirua Cylinder Testing Laboratory",
    "wof:placetype":"venue"
},
  "geometry": {"coordinates":[174.831879,-41.131401],"type":"Point"}
}