{
  "type": "Feature",
  "properties": {
    "addr:full":"1 Herd St Oriental Bay PO Box 14644 Kilbirnie  Wellington Wellington",
    "addr:housenumber":"1;po box",
    "addr:postcode":"14644",
    "addr:street":"Herd St Oriental Bay",
    "iso:country":"NZ",
    "sg:address":"1 Herd St Oriental Bay PO Box 14644 Kilbirnie ",
    "sg:city":"Wellington",
    "sg:orig_category":"Shopping: Sports Retailers: Sports Goods: Canvas Goods",
    "sg:phone":"+64 4-384 3554",
    "sg:province":"Wellington",
    "sg:website":"http://www.portnicholsonsails.co.nz",
    "wof:name":"Port Nicholson Sails Wgtn",
    "wof:placetype":"venue"
},
  "geometry": {"coordinates":[174.76715100000001,-41.28054],"type":"Point"}
}