{
  "type": "Feature",
  "properties": {
    "addr:full":"Office R D 1  Morrinsville Waikato",
    "addr:housenumber":"1",
    "iso:country":"NZ",
    "sg:address":"Office R D 1 ",
    "sg:city":"Morrinsville",
    "sg:orig_category":"Home And Garden: Gardening: Products: Fertilisers",
    "sg:phone":"+64 7-887 4000",
    "sg:province":"Waikato",
    "wof:name":"Computerised Bulk Spreaders Ltd",
    "wof:placetype":"venue"
},
  "geometry": {"coordinates":[175.52873199999999,-37.65411],"type":"Point"}
}