{
  "type": "Feature",
  "properties": {
    "addr:full":"4 Huron St Takapuna  Auckland Auckland",
    "addr:housenumber":"4",
    "addr:street":"Huron St",
    "iso:country":"NZ",
    "sg:address":"4 Huron St Takapuna ",
    "sg:city":"Auckland",
    "sg:classifiers":[
        {
            "category":"Shopping",
            "subcategory":"Thrift Store",
            "type":"Retail Goods"
        }
    ],
    "sg:phone":"+64 9-489 5638",
    "sg:province":"Auckland",
    "sg:tags":[
        "-",
        "clothing",
        "secondhand",
        "fabric"
    ],
    "wof:name":"Boobs Recycle Boutique",
    "wof:placetype":"venue"
},
  "geometry": {"coordinates":[174.771255,-36.788967],"type":"Point"}
}