{
  "type": "Feature",
  "properties": {
    "iso:country":"NZ",
    "sg:address":"Oamaru Depot & Workshop ",
    "sg:city":"Oamaru",
    "sg:classifiers":[
        {
            "category":"Bus Charters",
            "type":"Transportation"
        }
    ],
    "sg:phone":"+64 3-434 7964",
    "sg:province":"Otago",
    "sg:tags":[
        "services",
        "travel",
        "tourism"
    ],
    "wof:name":"Ritchies Coachlines",
    "wof:placetype":"venue"
},
  "geometry": {"coordinates":[170.96904000000001,-45.097141],"type":"Point"}
}