{
  "type": "Feature",
  "properties": {
    "iso:country":"NZ",
    "sg:address":"100 Cable St ",
    "sg:city":"Wellington",
    "sg:classifiers":[
        {
            "category":"Bars & Pubs",
            "subcategory":"Lounge",
            "type":"Food & Drink"
        }
    ],
    "sg:phone":"+64 4-384 6622",
    "sg:province":"Wellington",
    "sg:tags":[
        "-",
        "asian"
    ],
    "wof:name":"Mr Chan's",
    "wof:placetype":"venue"
},
  "geometry": {"coordinates":[-85.910454,33.827946],"type":"Point"}
}