{
  "type": "Feature",
  "properties": {
    "addr:full":"off Hewlett Rd Ext  Greymouth West Coast",
    "addr:street":"Off Hewlett Rd Ext Greymouth",
    "iso:country":"NZ",
    "sg:address":"off Hewlett Rd Ext ",
    "sg:city":"Greymouth",
    "sg:classifiers":[
        {
            "category":"Manufacturing",
            "subcategory":"Glass & Minerals",
            "type":"Manufacturing & Wholesale Goods"
        }
    ],
    "sg:phone":"+64 3-768 4928",
    "sg:province":"West Coast",
    "sg:tags":[
        "chemical",
        "fibre",
        "industrial",
        "compounds"
    ],
    "wof:name":"Westland Fibreglass",
    "wof:placetype":"venue"
},
  "geometry": {"coordinates":[171.20988500000001,-42.451618],"type":"Point"}
}