{
  "type": "Feature",
  "properties": {
    "iso:country":"NZ",
    "sg:address":"PO Box 6877 Marion Square ",
    "sg:city":"Wellington",
    "sg:classifiers":[
        {
            "category":"Shopping",
            "subcategory":"Stationery & Office Supplies",
            "type":"Retail Goods"
        }
    ],
    "sg:phone":"+64 4-977 4735",
    "sg:province":"Wellington",
    "sg:tags":[
        "supplies",
        "educational",
        "material",
        "education",
        "training"
    ],
    "wof:name":"Lunchrapz",
    "wof:placetype":"venue"
},
  "geometry": {"coordinates":[-85.910454,33.827946],"type":"Point"}
}