{
  "type": "Feature",
  "properties": {
    "addr:full":"Studio 33 Allen St  Christchurch Canterbury",
    "addr:housenumber":"33",
    "addr:street":"Allen St",
    "iso:country":"NZ",
    "sg:address":"Studio 33 Allen St ",
    "sg:city":"Christchurch",
    "sg:classifiers":[
        {
            "category":"Communications",
            "subcategory":"Television Station",
            "type":"Services"
        }
    ],
    "sg:phone":"+64 3-940 8653",
    "sg:province":"Canterbury",
    "sg:tags":[
        "broadcasting"
    ],
    "wof:name":"Plains TV",
    "wof:placetype":"venue"
},
  "geometry": {"coordinates":[-76.547432,37.60841],"type":"Point"}
}