{
  "type": "Feature",
  "properties": {
    "iso:country":"NZ",
    "sg:address":"PO Box 34 ",
    "sg:city":"Waitara",
    "sg:orig_category":"Transport: Transportation: Transport Operators",
    "sg:phone":"+64 6-754 7522",
    "wof:name":"Q-Transport",
    "wof:placetype":"venue"
},
  "geometry": {"coordinates":[174.244781,-38.996071],"type":"Point"}
}