{
  "type": "Feature",
  "properties": {
    "addr:full":"PO Box 34  Waitara",
    "addr:housenumber":"po box 34",
    "iso:country":"NZ",
    "sg:address":"PO Box 34 ",
    "sg:city":"Waitara",
    "sg:orig_category":"Transport: Transportation: Transport Operators",
    "sg:phone":"+64 6-754 7522",
    "wof:name":"Q-Transport",
    "wof:placetype":"venue"
},
  "geometry": {"coordinates":[174.24478099999999,-38.996071],"type":"Point"}
}