{
  "type": "Feature",
  "properties": {
    "iso:country":"NZ",
    "sg:address":"49 A Lake View Rd Takapuna ",
    "sg:city":"Auckland",
    "sg:classifiers":[
        {
            "category":"Food & Beverages",
            "subcategory":"Fruits & Vegetables",
            "type":"Retail Goods"
        }
    ],
    "sg:phone":"+64 9-489 9952",
    "sg:province":"Auckland",
    "sg:tags":[
        "product",
        "drink",
        "organic",
        "veges"
    ],
    "wof:name":"Global Organics New Zealand Ltd",
    "wof:placetype":"venue"
},
  "geometry": {"coordinates":[174.761261,-36.784794],"type":"Point"}
}