{
  "type": "Feature",
  "properties": {
    "addr:full":"1 Lydia Way Karori  Wellington Wellington",
    "addr:housenumber":"1",
    "addr:street":"Lydia Way",
    "iso:country":"NZ",
    "sg:address":"1 Lydia Way Karori ",
    "sg:city":"Wellington",
    "sg:orig_category":"Health And Beauty: Specialists: Midwives",
    "sg:phone":"+64 4-476 3644",
    "sg:province":"Wellington",
    "wof:name":"Glass Sarah",
    "wof:placetype":"venue"
},
  "geometry": {"coordinates":[174.723251,-41.291756],"type":"Point"}
}