{
  "type": "Feature",
  "properties": {
    "addr:full":"PO Box 535 Kumeu  Auckland Auckland",
    "addr:housenumber":"po",
    "addr:street":"Box 535",
    "iso:country":"NZ",
    "sg:address":"PO Box 535 Kumeu ",
    "sg:city":"Auckland",
    "sg:classifiers":[
        {
            "category":"Banks & Credit Unions",
            "subcategory":"Investment Brokerage",
            "type":"Services"
        }
    ],
    "sg:phone":"+64 9-412 9817",
    "sg:province":"Auckland",
    "sg:tags":[
        "chemical",
        "industrial",
        "-",
        "compounds"
    ],
    "wof:name":"Adria New Zealand Ltd",
    "wof:placetype":"venue"
},
  "geometry": {"coordinates":[174.56019599999999,-36.777271],"type":"Point"}
}