{
  "type": "Feature",
  "properties": {
    "addr:full":"60 Littlebourne Rd Maori Hill  Dunedin Otago",
    "addr:housenumber":"60",
    "addr:street":"Littlebourne Rd",
    "iso:country":"NZ",
    "sg:address":"60 Littlebourne Rd Maori Hill ",
    "sg:city":"Dunedin",
    "sg:classifiers":[
        {
            "category":"Education",
            "subcategory":"Special Training",
            "type":"Public Place"
        }
    ],
    "sg:phone":"+64 3-474 0990",
    "sg:province":"Otago",
    "sg:tags":[
        "school",
        "swimming"
    ],
    "wof:name":"Duncan Laing Swim School",
    "wof:placetype":"venue"
},
  "geometry": {"coordinates":[170.502701,-45.859348],"type":"Point"}
}