{
  "type": "Feature",
  "properties": {
    "iso:country":"NZ",
    "sg:address":"cnr Ti Rakau Dve & Pakuranga Rd Pakuranga ",
    "sg:city":"Auckland",
    "sg:classifiers":[
        {
            "category":"Shopping Center",
            "type":"Public Place"
        }
    ],
    "sg:phone":"+64 9-978 9100",
    "sg:province":"Auckland",
    "sg:tags":[
        "mall",
        "retail",
        "stores"
    ],
    "wof:name":"Westfield ShoppingTown Pakuranga",
    "wof:placetype":"venue"
},
  "geometry": {"coordinates":[174.879044,-36.91584],"type":"Point"}
}