{
  "type": "Feature",
  "properties": {
    "addr:full":"The Church 43 Jervois Rd Ponsonby  Auckland Auckland",
    "addr:housenumber":"43",
    "addr:street":"Jervois Rd",
    "iso:country":"NZ",
    "sg:address":"The Church 43 Jervois Rd Ponsonby ",
    "sg:city":"Auckland",
    "sg:classifiers":[
        {
            "category":"Shopping",
            "subcategory":"Bridal",
            "type":"Retail Goods"
        }
    ],
    "sg:phone":"+64 9-376 9919",
    "sg:province":"Auckland",
    "sg:tags":[
        "arrangements",
        "wear",
        "wedding"
    ],
    "sg:website":"http://www.imagemakers.co.nz",
    "wof:name":"Imagemakers Ltd",
    "wof:placetype":"venue"
},
  "geometry": {"coordinates":[174.74241599999999,-36.85326],"type":"Point"}
}