{
  "type": "Feature",
  "properties": {
    "addr:full":"227 Omahu Rd  Hastings Hawke's Bay",
    "addr:housenumber":"227",
    "addr:street":"Omahu Rd",
    "iso:country":"NZ",
    "sg:address":"227 Omahu Rd ",
    "sg:city":"Hastings",
    "sg:orig_category":"Health And Beauty: Beauty: Hairdressers",
    "sg:phone":"+64 6-876 5657",
    "sg:province":"Hawke's Bay",
    "wof:name":"Hair Co The",
    "wof:placetype":"venue"
},
  "geometry": {"coordinates":[-81.508163,29.711214],"type":"Point"}
}