{
  "type": "Feature",
  "properties": {
    "addr:full":"North Harbour  Auckland Auckland",
    "addr:housenumber":"harbour",
    "addr:street":"North",
    "iso:country":"NZ",
    "sg:address":"North Harbour ",
    "sg:city":"Auckland",
    "sg:classifiers":[
        {
            "category":"Home & Garden",
            "subcategory":"Garden Supply",
            "type":"Retail Goods"
        }
    ],
    "sg:phone":"+64 800 766 576",
    "sg:province":"Auckland",
    "sg:tags":[
        "fencing",
        "outdoor",
        "contractor"
    ],
    "wof:name":"Pool Solutions",
    "wof:placetype":"venue"
},
  "geometry": {"coordinates":[174.69986,-36.748421],"type":"Point"}
}