{
  "type": "Feature",
  "properties": {
    "addr:full":"11 The Anchorage  Paihia Marlborough",
    "addr:housenumber":"11",
    "addr:street":"The;Paihia",
    "iso:country":"NZ",
    "sg:address":"11 The Anchorage ",
    "sg:city":"Paihia",
    "sg:classifiers":[
        {
            "category":"Social Services",
            "subcategory":"Job Training",
            "type":"Services"
        }
    ],
    "sg:phone":"+64 9-402 8264",
    "sg:province":"Marlborough",
    "sg:tags":[
        "education"
    ],
    "wof:name":"JayBee Consultants",
    "wof:placetype":"venue"
},
  "geometry": {"coordinates":[174.09106399999999,-35.283699],"type":"Point"}
}