{
  "type": "Feature",
  "properties": {
    "addr:full":"PO Box 28849 Remuera  Auckland Auckland",
    "addr:housenumber":"po box",
    "addr:postcode":"28849",
    "iso:country":"NZ",
    "sg:address":"PO Box 28849 Remuera ",
    "sg:city":"Auckland",
    "sg:classifiers":[
        {
            "category":"Shopping",
            "subcategory":"Stationery & Office Supplies",
            "type":"Retail Goods"
        }
    ],
    "sg:phone":"+64 9-579 0616",
    "sg:province":"Auckland",
    "sg:tags":[
        "supplies",
        "educational",
        "material",
        "education",
        "training"
    ],
    "wof:name":"Books In Homes",
    "wof:placetype":"venue"
},
  "geometry": {"coordinates":[174.80886799999999,-36.869381],"type":"Point"}
}