{
  "type": "Feature",
  "properties": {
    "addr:full":"34 Portside Dve Mt  Maunganui Bay of Plenty",
    "addr:housenumber":"34",
    "addr:street":"Portside Dve Mt Maunganui",
    "iso:country":"NZ",
    "sg:address":"34 Portside Dve Mt ",
    "sg:city":"Maunganui",
    "sg:classifiers":[
        {
            "category":"Shopping",
            "subcategory":"Discount & Variety Stores",
            "type":"Retail Goods"
        }
    ],
    "sg:phone":"+64 7-572 9378",
    "sg:province":"Bay of Plenty",
    "sg:tags":[
        "storage",
        "cool"
    ],
    "wof:name":"Pelcold Storage Limited",
    "wof:placetype":"venue"
},
  "geometry": {"coordinates":[176.18627900000001,-37.641048],"type":"Point"}
}