{
  "type": "Feature",
  "properties": {
    "addr:full":"509 a Horotiu Rd  Hamilton Waikato",
    "addr:housenumber":"509",
    "addr:street":"A Horotiu Rd",
    "iso:country":"NZ",
    "sg:address":"509 a Horotiu Rd ",
    "sg:city":"Hamilton",
    "sg:orig_category":"Automotive: Servicing And Repair: Car Trimming/Upholstery",
    "sg:phone":"+64 7-829 7011",
    "sg:province":"Waikato",
    "wof:name":"Auto Trimming & Window Tinting",
    "wof:placetype":"venue"
},
  "geometry": {"coordinates":[175.276993,-37.783215],"type":"Point"}
}