{
  "type": "Feature",
  "properties": {
    "addr:full":"169 London Street  Hamilton Gisborne",
    "addr:housenumber":"169",
    "addr:street":"London Street",
    "iso:country":"NZ",
    "sg:address":"169 London Street ",
    "sg:city":"Hamilton",
    "sg:orig_category":"Transport: Air",
    "sg:phone":"+64 7-834 2071",
    "sg:province":"Gisborne",
    "wof:name":"Airclaims New Zealand Limited",
    "wof:placetype":"venue"
},
  "geometry": {"coordinates":[175.27578700000001,-37.785419],"type":"Point"}
}