{
  "type": "Feature",
  "properties": {
    "addr:full":"4 Lynch St  Greymouth West Coast",
    "addr:housenumber":"4",
    "addr:street":"Lynch St",
    "iso:country":"NZ",
    "sg:address":"4 Lynch St ",
    "sg:city":"Greymouth",
    "sg:classifiers":[
        {
            "category":"Building & Trades",
            "subcategory":"Construction",
            "type":"Services"
        }
    ],
    "sg:phone":"+64 3-768 9277",
    "sg:province":"West Coast",
    "sg:tags":[
        "home",
        "garden",
        "related",
        "plasterer"
    ],
    "wof:name":"Colin Waterman Interior Plasterer & Roof Resurfacer",
    "wof:placetype":"venue"
},
  "geometry": {"coordinates":[171.20744300000001,-42.433556],"type":"Point"}
}