{
  "type": "Feature",
  "properties": {
    "addr:full":"Flaxmere Shopping Center Flaxmere  Hastings Hawke's Bay",
    "addr:street":"Flaxmere",
    "iso:country":"NZ",
    "sg:address":"Flaxmere Shopping Center Flaxmere ",
    "sg:city":"Hastings",
    "sg:classifiers":[
        {
            "category":"Communications",
            "subcategory":"Film & Video Production",
            "type":"Services"
        }
    ],
    "sg:phone":"+64 6-879 6444",
    "sg:province":"Hawke's Bay",
    "sg:tags":[
        "sport",
        "leisure",
        "library",
        "entertainment"
    ],
    "wof:name":"United Video Flaxmere",
    "wof:placetype":"venue"
},
  "geometry": {"coordinates":[176.78324900000001,-39.622997],"type":"Point"}
}