{
  "type": "Feature",
  "properties": {
    "addr:full":"4 Crown Cre Otara  Auckland Auckland",
    "addr:housenumber":"4;otara",
    "addr:street":"Crown Cre",
    "iso:country":"NZ",
    "sg:address":"4 Crown Cre Otara ",
    "sg:city":"Auckland",
    "sg:classifiers":[
        {
            "category":"Shopping",
            "subcategory":"Pets & Pet Supplies",
            "type":"Retail Goods"
        }
    ],
    "sg:phone":"+64 9-274 4780",
    "sg:province":"Auckland",
    "sg:tags":[
        "home",
        "grooming",
        "garden",
        "pets"
    ],
    "wof:name":"Dirty Dogs Mobile Dog Valet Service",
    "wof:placetype":"venue"
},
  "geometry": {"coordinates":[174.87943999999999,-36.965015],"type":"Point"}
}