{
  "type": "Feature",
  "properties": {
    "addr:full":"1 Amokura Dve  Kerikeri Northland",
    "addr:housenumber":"1",
    "addr:street":"Amokura Dve;Northland",
    "iso:country":"NZ",
    "sg:address":"1 Amokura Dve ",
    "sg:city":"Kerikeri",
    "sg:classifiers":[
        {
            "category":"Retail",
            "subcategory":"Driving School",
            "type":"Services"
        }
    ],
    "sg:phone":"+64 9-407 7569",
    "sg:province":"Northland",
    "sg:tags":[
        "training",
        "education",
        "driver"
    ],
    "wof:name":"Mid North Driving School",
    "wof:placetype":"venue"
},
  "geometry": {"coordinates":[173.949905,-35.226269],"type":"Point"}
}