{
  "type": "Feature",
  "properties": {
    "addr:full":"R D 9 Feilding  Halcombe",
    "addr:housenumber":"9",
    "addr:street":"R D",
    "iso:country":"NZ",
    "sg:address":"R D 9 Feilding ",
    "sg:city":"Halcombe",
    "sg:classifiers":[
        {
            "category":"Manufacturing",
            "subcategory":"Textiles",
            "type":"Manufacturing & Wholesale Goods"
        }
    ],
    "sg:phone":"+64 6-328 8856",
    "sg:tags":[
        "clothing",
        "fabric",
        "manufacturer"
    ],
    "wof:name":"Rangitikei Cotton Products Ltd",
    "wof:placetype":"venue"
},
  "geometry": {"coordinates":[175.56854200000001,-40.224361],"type":"Point"}
}