{
  "type": "Feature",
  "properties": {
    "iso:country":"NZ",
    "sg:address":"31 Porana Rd Glenfield ",
    "sg:city":"Auckland",
    "sg:classifiers":[
        {
            "category":"Home & Garden",
            "subcategory":"Home Furnishings",
            "type":"Retail Goods"
        }
    ],
    "sg:phone":"+64 9-294 7211",
    "sg:province":"Auckland",
    "sg:tags":[
        "accessory"
    ],
    "sg:website":"http://www.yellowpages.co.nz/for/stmgroup/dp50103.html",
    "wof:name":"Malco Fittings 1986 Ltd",
    "wof:placetype":"venue"
},
  "geometry": {"coordinates":[174.728622,-36.784813],"type":"Point"}
}