{
  "type": "Feature",
  "properties": {
    "iso:country":"NZ",
    "sg:address":"7 Stadium Dve ",
    "sg:city":"Pukekohe",
    "sg:classifiers":[
        {
            "category":"Home & Garden",
            "subcategory":"Furniture",
            "type":"Retail Goods"
        }
    ],
    "sg:phone":"+64 9-238 0775",
    "sg:province":"Auckland",
    "sg:tags":[
        "furniture/furnishings",
        "furnishing"
    ],
    "wof:name":"Urban Country Furniture Co",
    "wof:placetype":"venue"
},
  "geometry": {"coordinates":[174.930252,-37.195728],"type":"Point"}
}