{
  "type": "Feature",
  "properties": {
    "addr:full":"32 Nelson St  Hawera Taranaki",
    "addr:housenumber":"32",
    "addr:street":"Nelson St",
    "iso:country":"NZ",
    "sg:address":"32 Nelson St ",
    "sg:city":"Hawera",
    "sg:classifiers":[
        {
            "category":"Home & Garden",
            "subcategory":"Furniture",
            "type":"Retail Goods"
        }
    ],
    "sg:phone":"+64 6-278 6113",
    "sg:province":"Taranaki",
    "sg:tags":[
        "furniture/furnishings",
        "furnishing"
    ],
    "wof:name":"Gibson Meads Ltd",
    "wof:placetype":"venue"
},
  "geometry": {"coordinates":[174.281418,-39.587177],"type":"Point"}
}