{
  "type": "Feature",
  "properties": {
    "addr:full":"362 King Edward St South Dunedin  Dunedin Otago",
    "addr:housenumber":"362",
    "addr:street":"King Edward St",
    "iso:country":"NZ",
    "sg:address":"362 King Edward St South Dunedin ",
    "sg:city":"Dunedin",
    "sg:orig_category":"Automotive: General Services: Service Stations",
    "sg:phone":"+64 3-455 3516",
    "sg:province":"Otago",
    "wof:name":"Caltex Favorit Service Centre",
    "wof:placetype":"venue"
},
  "geometry": {"coordinates":[170.502533,-45.898041],"type":"Point"}
}