{
  "type": "Feature",
  "properties": {
    "addr:full":"8 Cleveland Rd Parnell  Auckland Auckland",
    "addr:housenumber":"8",
    "addr:street":"Cleveland Rd",
    "iso:country":"NZ",
    "sg:address":"8 Cleveland Rd Parnell ",
    "sg:city":"Auckland",
    "sg:classifiers":[
        {
            "category":"Home & Garden",
            "subcategory":"Home Furnishings",
            "type":"Retail Goods"
        }
    ],
    "sg:phone":"+64 9-357 0889",
    "sg:province":"Auckland",
    "sg:tags":[
        "accessory"
    ],
    "wof:name":"Bloomsbury",
    "wof:placetype":"venue"
},
  "geometry": {"coordinates":[174.78286700000001,-36.85183],"type":"Point"}
}