{
  "type": "Feature",
  "properties": {
    "addr:full":"122 Elstree Ave Glen Innes  Auckland Auckland",
    "addr:housenumber":"122",
    "addr:street":"Elstree Ave",
    "iso:country":"NZ",
    "sg:address":"122 Elstree Ave Glen Innes ",
    "sg:city":"Auckland",
    "sg:classifiers":[
        {
            "category":"Sports & Exercise",
            "subcategory":"Sports Center",
            "type":"Entertainment"
        }
    ],
    "sg:phone":"+64 9-527 3260",
    "sg:province":"Auckland",
    "sg:tags":[
        "sporting",
        "sports",
        "-",
        "leisure",
        "facility"
    ],
    "wof:name":"Auckland City Swimming Pools",
    "wof:placetype":"venue"
},
  "geometry": {"coordinates":[174.86604299999999,-36.879459],"type":"Point"}
}