{
  "type": "Feature",
  "properties": {
    "addr:full":"Pascal St Palmerston  Palmerston North Manawatu-Wanganui",
    "addr:street":"Pascal St Palmerston",
    "iso:country":"NZ",
    "sg:address":"Pascal St Palmerston ",
    "sg:city":"Palmerston North",
    "sg:classifiers":[
        {
            "category":"Recreation",
            "type":"Entertainment"
        }
    ],
    "sg:phone":"+64 6-356 1505",
    "sg:province":"Manawatu-Wanganui",
    "sg:tags":[
        "sport",
        "leisure"
    ],
    "wof:name":"Arena Manawatu",
    "wof:placetype":"venue"
},
  "geometry": {"coordinates":[175.59750399999999,-40.354725],"type":"Point"}
}