{
  "type": "Feature",
  "properties": {
    "iso:country":"NZ",
    "sg:address":"PO Box 531 Kumeu ",
    "sg:city":"Auckland",
    "sg:classifiers":[
        {
            "category":"Sports & Exercise",
            "subcategory":"Ski Slope",
            "type":"Entertainment"
        }
    ],
    "sg:phone":"+64 9-412 6117",
    "sg:province":"Auckland",
    "sg:tags":[
        "equipment",
        "snowboard",
        "goods",
        "shopping",
        "retailers"
    ],
    "wof:name":"Anzacs Snow Boards",
    "wof:placetype":"venue"
},
  "geometry": {"coordinates":[174.560196,-36.777271],"type":"Point"}
}