{
  "type": "Feature",
  "properties": {
    "iso:country":"NZ",
    "sg:address":"794 State Highway 7 Dobson ",
    "sg:city":"Greymouth",
    "sg:orig_category":"Farming: Machinery: Farm Machinery",
    "sg:phone":"+64 3-762 5060",
    "sg:province":"West Coast",
    "wof:name":"Tractor & Diesel Tech Limited",
    "wof:placetype":"venue"
},
  "geometry": {"coordinates":[171.30775499999999,-42.45322],"type":"Point"}
}