{
  "type": "Feature",
  "properties": {
    "iso:country":"NZ",
    "sg:address":"4 A Florio Tce Tawa ",
    "sg:city":"Wellington",
    "sg:classifiers":[
        {
            "category":"Home & Garden",
            "subcategory":"Building Materials",
            "type":"Retail Goods"
        }
    ],
    "sg:phone":"+64 4-232 8468",
    "sg:province":"Wellington",
    "sg:tags":[
        "electrician",
        "related"
    ],
    "wof:name":"Sole Electrical",
    "wof:placetype":"venue"
},
  "geometry": {"coordinates":[174.82777400000001,-41.1824],"type":"Point"}
}