{
  "type": "Feature",
  "properties": {
    "addr:full":"Runciman Rd Drury  Pukekohe Auckland",
    "addr:street":"Runciman Rd",
    "iso:country":"NZ",
    "sg:address":"Runciman Rd Drury ",
    "sg:city":"Pukekohe",
    "sg:orig_category":"Farming: Farms - General: Farms",
    "sg:phone":"+64 9-238 7316",
    "sg:province":"Auckland",
    "wof:name":"Kempton P J",
    "wof:placetype":"venue"
},
  "geometry": {"coordinates":[174.94885300000001,-37.193508],"type":"Point"}
}