{
  "type": "Feature",
  "properties": {
    "addr:full":"88 Armagh St  Christchurch Canterbury",
    "addr:housenumber":"88",
    "addr:street":"Armagh St",
    "iso:country":"NZ",
    "sg:address":"88 Armagh St ",
    "sg:city":"Christchurch",
    "sg:classifiers":[
        {
            "category":"Bars & Pubs",
            "subcategory":"Nightclub",
            "type":"Food & Drink"
        }
    ],
    "sg:phone":"+64 3-377 1007",
    "sg:province":"Canterbury",
    "sg:tags":[
        "club",
        "night",
        "sport",
        "leisure",
        "entertainment"
    ],
    "wof:name":"The Club",
    "wof:placetype":"venue"
},
  "geometry": {"coordinates":[-76.537834,37.605659],"type":"Point"}
}