{
  "type": "Feature",
  "properties": {
    "addr:full":"377 Palmerston Rd  Gisborne Gisborne",
    "addr:housenumber":"377",
    "addr:street":"Palmerston Rd",
    "iso:country":"NZ",
    "sg:address":"377 Palmerston Rd ",
    "sg:city":"Gisborne",
    "sg:classifiers":[
        {
            "category":"Retail",
            "subcategory":"Auto Repair",
            "type":"Services"
        }
    ],
    "sg:phone":"+64 6-868 9194",
    "sg:province":"Gisborne",
    "sg:tags":[
        "clutch",
        "brake",
        "servicing",
        "automotive"
    ],
    "wof:name":"Gisborne Brake & Clutch Service",
    "wof:placetype":"venue"
},
  "geometry": {"coordinates":[178.019745,-38.659481],"type":"Point"}
}