{
  "type": "Feature",
  "properties": {
    "addr:full":"PO Box 33 104  Petone Wellington",
    "addr:housenumber":"po box 33 104",
    "iso:country":"NZ",
    "sg:address":"PO Box 33 104 ",
    "sg:city":"Petone",
    "sg:classifiers":[
        {
            "category":"Manufacturing",
            "subcategory":"Food",
            "type":"Manufacturing & Wholesale Goods"
        }
    ],
    "sg:phone":"+64 4-568 2689",
    "sg:province":"Wellington",
    "sg:tags":[
        "processing",
        "drink"
    ],
    "wof:name":"Goulds Fine Foods",
    "wof:placetype":"venue"
},
  "geometry": {"coordinates":[174.87507600000001,-41.221294],"type":"Point"}
}