{
  "type": "Feature",
  "properties": {
    "iso:country":"NZ",
    "sg:address":"cnr Omahu & Henderson Rds ",
    "sg:city":"Hastings",
    "sg:classifiers":[
        {
            "category":"Retail",
            "subcategory":"Auto Repair",
            "type":"Services"
        }
    ],
    "sg:phone":"+64 6-879 5220",
    "sg:province":"Auckland",
    "sg:tags":[
        "automotive",
        "electric",
        "servicing"
    ],
    "wof:name":"Newport Auto Electrical",
    "wof:placetype":"venue"
},
  "geometry": {"coordinates":[-98.392372,40.585651],"type":"Point"}
}