{
  "type": "Feature",
  "properties": {
    "addr:full":"34 Logan St  Tokoroa",
    "addr:housenumber":"34",
    "addr:street":"Logan St",
    "iso:country":"NZ",
    "sg:address":"34 Logan St ",
    "sg:city":"Tokoroa",
    "sg:classifiers":[
        {
            "category":"Sports & Exercise",
            "subcategory":"Sports Center",
            "type":"Entertainment"
        }
    ],
    "sg:phone":"+64 7-886 6554",
    "sg:tags":[
        "art",
        "leisure"
    ],
    "wof:name":"Tokoroa Cinema 3",
    "wof:placetype":"venue"
},
  "geometry": {"coordinates":[175.87042199999999,-38.21685],"type":"Point"}
}