{
  "type": "Feature",
  "properties": {
    "addr:full":"Cnr Kelvin & Spey Sts  Invercargill Southland",
    "addr:housenumber":"cnr",
    "addr:street":"Kelvin & Spey",
    "iso:country":"NZ",
    "sg:address":"Cnr Kelvin & Spey Sts ",
    "sg:city":"Invercargill",
    "sg:classifiers":[
        {
            "category":"Banks & Credit Unions",
            "subcategory":"Financial Services",
            "type":"Services"
        }
    ],
    "sg:phone":"+64 3-218 4167",
    "sg:province":"Southland",
    "sg:tags":[
        "personal",
        "superannuation",
        "-",
        "finance"
    ],
    "wof:name":"Greenslades Limited",
    "wof:placetype":"venue"
},
  "geometry": {"coordinates":[168.35217299999999,-46.41185],"type":"Point"}
}