{
  "type": "Feature",
  "properties": {
    "iso:country":"NZ",
    "sg:address":"8 Henry Rose Pl Albany ",
    "sg:city":"Auckland",
    "sg:orig_category":"Industrial: Engineering",
    "sg:phone":"+64 9-415 7229",
    "sg:province":"Auckland",
    "sg:website":"http://www.yellowpages.co.nz/for/richmondindustries/dp55363.html",
    "wof:name":"Richmond Associates Ltd",
    "wof:placetype":"venue"
},
  "geometry": {"coordinates":[174.714554,-36.739822],"type":"Point"}
}