{
  "type": "Feature",
  "properties": {
    "addr:full":"PO Box 296 New  Plymouth Taranaki",
    "addr:housenumber":"po;296",
    "addr:street":"Box",
    "iso:country":"NZ",
    "sg:address":"PO Box 296 New ",
    "sg:city":"Plymouth",
    "sg:classifiers":[
        {
            "category":"Restaurant",
            "type":"Food & Drink"
        }
    ],
    "sg:phone":"+64 252783447",
    "sg:province":"Taranaki",
    "sg:tags":[
        "catering",
        "supply"
    ],
    "wof:name":"Cookright Vat Filtering Service",
    "wof:placetype":"venue"
},
  "geometry": {"coordinates":[-82.61039700000001,41.053471],"type":"Point"}
}