{
  "type": "Feature",
  "properties": {
    "addr:full":"Tuakau Rd  Pukekohe Auckland",
    "addr:street":"Tuakau Rd",
    "iso:country":"NZ",
    "sg:address":"Tuakau Rd ",
    "sg:city":"Pukekohe",
    "sg:orig_category":"Farming: Horticulture: Horticultural Supplies",
    "sg:phone":"+64 9-238 7620",
    "sg:province":"Auckland",
    "wof:name":"Manga J & Son",
    "wof:placetype":"venue"
},
  "geometry": {"coordinates":[174.907928,-37.225018],"type":"Point"}
}