{
  "type": "Feature",
  "properties": {
    "iso:country":"NZ",
    "sg:address":"197 Thornton Rd ",
    "sg:city":"Cambridge",
    "sg:classifiers":[
        {
            "category":"Social Services",
            "subcategory":"Child Care",
            "type":"Services"
        }
    ],
    "sg:phone":"+64 7-827 5081",
    "sg:province":"Waikato",
    "sg:tags":[
        "home",
        "garden",
        "children"
    ],
    "sg:website":"http://www.yellowpages.co.nz/for/bunnies/dp48943.html",
    "wof:name":"Bunnies Licensed Childcare & Pre-School",
    "wof:placetype":"venue"
},
  "geometry": {"coordinates":[-116.676048,44.572186],"type":"Point"}
}