{
  "type": "Feature",
  "properties": {
    "addr:full":"193 Talbot St  Geraldine",
    "addr:housenumber":"193",
    "addr:street":"Talbot St",
    "iso:country":"NZ",
    "sg:address":"193 Talbot St ",
    "sg:city":"Geraldine",
    "sg:classifiers":[
        {
            "category":"Fast Food",
            "type":"Food & Drink"
        }
    ],
    "sg:phone":"+64 3-693 9899",
    "sg:tags":[
        "wining",
        "dining",
        "takeaway"
    ],
    "wof:name":"Colonial Kitchen",
    "wof:placetype":"venue"
},
  "geometry": {"coordinates":[-86.008263,34.360641],"type":"Point"}
}