{
  "type": "Feature",
  "properties": {
    "addr:full":"1/188 Broadway Newmarket  Auckland Manawatu-Wanganui",
    "addr:housenumber":"1 / 188",
    "addr:street":"Broadway",
    "iso:country":"NZ",
    "sg:address":"1/188 Broadway Newmarket ",
    "sg:city":"Auckland",
    "sg:classifiers":[
        {
            "category":"Insurance",
            "subcategory":"Health Insurance",
            "type":"Services"
        }
    ],
    "sg:phone":"+64 9-520 6948",
    "sg:province":"Manawatu-Wanganui",
    "sg:tags":[
        "beauty",
        "supply"
    ],
    "wof:name":"The Beauty Connection",
    "wof:placetype":"venue"
},
  "geometry": {"coordinates":[174.77041600000001,-36.884109],"type":"Point"}
}