{
  "type": "Feature",
  "properties": {
    "addr:full":"25 Birmingham Dve Riccarton  Christchurch Canterbury",
    "addr:housenumber":"25;dve",
    "addr:street":"Birmingham",
    "iso:country":"NZ",
    "sg:address":"25 Birmingham Dve Riccarton ",
    "sg:city":"Christchurch",
    "sg:classifiers":[
        {
            "category":"Manufacturing",
            "subcategory":"Food",
            "type":"Manufacturing & Wholesale Goods"
        }
    ],
    "sg:phone":"+64 3-338 9705",
    "sg:province":"Canterbury",
    "sg:tags":[
        "drink",
        "-",
        "manufacturer"
    ],
    "wof:name":"Fresha Donuts",
    "wof:placetype":"venue"
},
  "geometry": {"coordinates":[172.597351,-43.532143],"type":"Point"}
}