{
  "type": "Feature",
  "properties": {
    "iso:country":"NZ",
    "sg:address":"481 Main Waihi Rd Te ",
    "sg:city":"Puna",
    "sg:classifiers":[
        {
            "category":"Shopping",
            "subcategory":"Pets & Pet Supplies",
            "type":"Retail Goods"
        }
    ],
    "sg:phone":"+64 272 464 040",
    "sg:tags":[
        "home",
        "grooming",
        "garden",
        "pets"
    ],
    "wof:name":"Prestige Dog Grooming",
    "wof:placetype":"venue"
},
  "geometry": {"coordinates":[176.07333399999999,-37.692345],"type":"Point"}
}