{
  "type": "Feature",
  "properties": {
    "iso:country":"NZ",
    "sg:address":"199 Jervois Rd Herne Bay ",
    "sg:city":"Auckland",
    "sg:classifiers":[
        {
            "category":"Retail",
            "subcategory":"Repair Shop",
            "type":"Services"
        }
    ],
    "sg:phone":"+64 9-376 3800",
    "sg:province":"Auckland",
    "sg:tags":[
        "clothing",
        "fabric",
        "cleaning"
    ],
    "wof:name":"Impeccable Fitz",
    "wof:placetype":"venue"
},
  "geometry": {"coordinates":[174.731033,-36.848259],"type":"Point"}
}