{
  "type": "Feature",
  "properties": {
    "iso:country":"NZ",
    "sg:address":"14/11 Hurley Rd ",
    "sg:city":"Paraparaumu",
    "sg:classifiers":[
        {
            "category":"Retail",
            "subcategory":"Animal Services",
            "type":"Services"
        }
    ],
    "sg:phone":"+64 25421781",
    "sg:province":"Wellington",
    "sg:tags":[
        "pet",
        "home",
        "garden",
        "pets"
    ],
    "wof:name":"Des Groves Dog Kennels",
    "wof:placetype":"venue"
},
  "geometry": {"coordinates":[174.98756399999999,-40.896328],"type":"Point"}
}