{
  "type": "Feature",
  "properties": {
    "addr:full":"157 Dee St  Invercargill Southland",
    "addr:housenumber":"157",
    "addr:street":"Dee St",
    "iso:country":"NZ",
    "sg:address":"157 Dee St ",
    "sg:city":"Invercargill",
    "sg:classifiers":[
        {
            "category":"Shopping",
            "subcategory":"Crafts & Fabrics",
            "type":"Retail Goods"
        }
    ],
    "sg:phone":"+64 3-218 8598",
    "sg:province":"Southland",
    "sg:tags":[
        "knitting",
        "wool",
        "clothing"
    ],
    "wof:name":"Stitch 'n' Knit",
    "wof:placetype":"venue"
},
  "geometry": {"coordinates":[168.34732099999999,-46.392628],"type":"Point"}
}