{
  "type": "Feature",
  "properties": {
    "addr:full":"Okowai Rd Papakowhai  Porirua Wellington",
    "addr:street":"Okowai Rd",
    "iso:country":"NZ",
    "sg:address":"Okowai Rd Papakowhai ",
    "sg:city":"Porirua",
    "sg:classifiers":[
        {
            "category":"Personal",
            "type":"Services"
        }
    ],
    "sg:phone":"+64 4-237 8540",
    "sg:province":"Wellington",
    "sg:tags":[
        "arrangements",
        "wedding"
    ],
    "sg:website":"http://www.yellowpages.co.nz/for/gearhomestead/dp23655.html",
    "wof:name":"Historic Gear Homestead",
    "wof:placetype":"venue"
},
  "geometry": {"coordinates":[174.85441599999999,-41.12402],"type":"Point"}
}