{
  "type": "Feature",
  "properties": {
    "iso:country":"NZ",
    "sg:address":"389 Heads Rd ",
    "sg:city":"Wanganui",
    "sg:orig_category":"Transport: Consultancy: Transport - Consultants",
    "sg:phone":"+64 6-344 5476",
    "sg:province":"Manawatu-Wanganui",
    "wof:name":"K & A Design Ltd",
    "wof:placetype":"venue"
},
  "geometry": {"coordinates":[175.010513,-39.947952],"type":"Point"}
}