{
  "type": "Feature",
  "properties": {
    "addr:full":"276 Cuba St  Wellington Wellington",
    "addr:housenumber":"276",
    "addr:street":"Cuba St",
    "iso:country":"NZ",
    "sg:address":"276 Cuba St ",
    "sg:city":"Wellington",
    "sg:classifiers":[
        {
            "category":"Shopping",
            "subcategory":"Crafts & Fabrics",
            "type":"Retail Goods"
        }
    ],
    "sg:phone":"+64 4-385 7228",
    "sg:province":"Wellington",
    "sg:tags":[
        "sport",
        "art",
        "leisure",
        "hobbies"
    ],
    "wof:name":"McLeod Mary",
    "wof:placetype":"venue"
},
  "geometry": {"coordinates":[-85.910454,33.827946],"type":"Point"}
}