{
  "type": "Feature",
  "properties": {
    "addr:full":"Devon Rd Bell Block New  Plymouth Taranaki",
    "addr:street":"Devon Rd",
    "iso:country":"NZ",
    "sg:address":"Devon Rd Bell Block New ",
    "sg:city":"Plymouth",
    "sg:orig_category":"Sports And Leisure: Sports: Golf: Golf Courses",
    "sg:phone":"+64 6-755 1349",
    "sg:province":"Taranaki",
    "wof:name":"New Plymouth Golf Club (Inc)",
    "wof:placetype":"venue"
},
  "geometry": {"coordinates":[174.15020799999999,-39.034698],"type":"Point"}
}