{
  "type": "Feature",
  "properties": {
    "iso:country":"NZ",
    "sg:address":"3/39 Sir William Ave East Tamaki ",
    "sg:city":"Auckland",
    "sg:classifiers":[
        {
            "category":"Restaurant",
            "type":"Food & Drink"
        }
    ],
    "sg:phone":"+64 9-274 3514",
    "sg:province":"Auckland",
    "sg:tags":[
        "equipment",
        "machinery"
    ],
    "wof:name":"Production Techniques Ltd",
    "wof:placetype":"venue"
},
  "geometry": {"coordinates":[174.895355,-36.946007],"type":"Point"}
}