{
  "type": "Feature",
  "properties": {
    "iso:country":"NZ",
    "sg:address":"Torea St Utiku ",
    "sg:city":"Taihape",
    "sg:classifiers":[
        {
            "category":"Shopping",
            "subcategory":"Crafts & Fabrics",
            "type":"Retail Goods"
        }
    ],
    "sg:phone":"+64 6-388 0400",
    "sg:tags":[
        "clothing"
    ],
    "wof:name":"Gordon Riach Ltd",
    "wof:placetype":"venue"
},
  "geometry": {"coordinates":[175.845993,-39.732128],"type":"Point"}
}