{
  "type": "Feature",
  "properties": {
    "addr:full":"13 Bow St  Raglan",
    "addr:housenumber":"13",
    "addr:street":"Bow St",
    "iso:country":"NZ",
    "sg:address":"13 Bow St ",
    "sg:city":"Raglan",
    "sg:orig_category":"Clothing And Fabric: Clothing: Clothing - Specialty",
    "sg:phone":"+64 7-825 7417",
    "wof:name":"Urchin Original Clothing",
    "wof:placetype":"venue"
},
  "geometry": {"coordinates":[174.86773700000001,-37.799641],"type":"Point"}
}