{
  "type": "Feature",
  "properties": {
    "addr:full":"75 Ellice Rd Glenfield PO Box 100441 North Shore Mail, Cen  Auckland Auckland",
    "addr:housenumber":"75;po box 100441",
    "addr:street":"Ellice Rd",
    "iso:country":"NZ",
    "sg:address":"75 Ellice Rd Glenfield PO Box 100441 North Shore Mail, Cen ",
    "sg:city":"Auckland",
    "sg:orig_category":"Industrial: Engineering: Engineers: Civil Engineering Contractors",
    "sg:phone":"+64 9-444 1901",
    "sg:province":"Auckland",
    "wof:name":"Auckland Civil Ltd",
    "wof:placetype":"venue"
},
  "geometry": {"coordinates":[174.74749800000001,-36.819668],"type":"Point"}
}