{
  "type": "Feature",
  "properties": {
    "iso:country":"NZ",
    "sg:address":"11 Main North Rd Papanui ",
    "sg:city":"Christchurch",
    "sg:classifiers":[
        {
            "category":"Social Services",
            "subcategory":"Child Care",
            "type":"Services"
        }
    ],
    "sg:phone":"+64 3-352 2195",
    "sg:province":"Canterbury",
    "sg:tags":[
        "baby",
        "home",
        "product",
        "garden",
        "children"
    ],
    "wof:name":"Baby City",
    "wof:placetype":"venue"
},
  "geometry": {"coordinates":[172.60775799999999,-43.496574],"type":"Point"}
}