{
  "type": "Feature",
  "properties": {
    "iso:country":"NZ",
    "sg:address":"Level 1 5 Newton Rd Auckland Central ",
    "sg:city":"Auckland",
    "sg:orig_category":"Sports And Leisure: Entertainment: Entertainers",
    "sg:phone":"+64 9-361 5480",
    "sg:province":"Auckland",
    "wof:name":"BLP Ltd",
    "wof:placetype":"venue"
},
  "geometry": {"coordinates":[174.76454200000001,-36.848358],"type":"Point"}
}