{
  "type": "Feature",
  "properties": {
    "addr:full":"Raymond St  Timaru Canterbury",
    "addr:street":"Raymond St",
    "iso:country":"NZ",
    "sg:address":"Raymond St ",
    "sg:city":"Timaru",
    "sg:orig_category":"Education And Training: General: Schools",
    "sg:phone":"+64 3-684 3706",
    "sg:province":"Canterbury",
    "wof:name":"Timaru West School",
    "wof:placetype":"venue"
},
  "geometry": {"coordinates":[171.228317,-44.397869],"type":"Point"}
}