{
  "type": "Feature",
  "properties": {
    "iso:country":"NZ",
    "sg:address":"219 High St ",
    "sg:city":"Motueka",
    "sg:orig_category":"Home And Garden: General",
    "sg:phone":"+64 3-528 8881",
    "sg:province":"Tasman",
    "sg:website":"http://www.baasfirstnational.co.nz",
    "wof:name":"Baas First National Ltd",
    "wof:placetype":"venue"
},
  "geometry": {"coordinates":[173.010269,-41.126648],"type":"Point"}
}