{
  "type": "Feature",
  "properties": {
    "iso:country":"NZ",
    "sg:address":"Unit N/ 20 Sylvia Park Rd Mt Wellington ",
    "sg:city":"Auckland",
    "sg:orig_category":"Industrial: Parts: Bearings",
    "sg:phone":"+64 9-573 1154",
    "sg:province":"Auckland",
    "wof:name":"SKF New Zealand Ltd",
    "wof:placetype":"venue"
},
  "geometry": {"coordinates":[174.83029199999999,-36.909569],"type":"Point"}
}