{
  "type": "Feature",
  "properties": {
    "iso:country":"NZ",
    "sg:address":"111 Taupaki Rd R D 2 ",
    "sg:city":"Henderson",
    "sg:classifiers":[
        {
            "category":"Home & Garden",
            "subcategory":"Building Materials",
            "type":"Retail Goods"
        }
    ],
    "sg:phone":"+64 800 428 348",
    "sg:province":"Auckland",
    "sg:tags":[
        "gate",
        "fitting",
        "outdoor"
    ],
    "wof:name":"Cotswood Traditional Timber Gates",
    "wof:placetype":"venue"
},
  "geometry": {"coordinates":[-76.24788700000001,43.81736],"type":"Point"}
}