{
  "type": "Feature",
  "properties": {
    "addr:full":"99 A Bassett Rd Remuera  Auckland Auckland",
    "addr:housenumber":"99 a",
    "addr:street":"Bassett Rd",
    "iso:country":"NZ",
    "sg:address":"99 A Bassett Rd Remuera ",
    "sg:city":"Auckland",
    "sg:orig_category":"Shopping: Accessories",
    "sg:phone":"+64 9-524 8315",
    "sg:province":"Auckland",
    "wof:name":"Garrett J & L",
    "wof:placetype":"venue"
},
  "geometry": {"coordinates":[174.78385900000001,-36.867851],"type":"Point"}
}