{
  "type": "Feature",
  "properties": {
    "addr:full":"384 Hills Rd Shirley  Christchurch Canterbury",
    "addr:housenumber":"384",
    "addr:street":"Hills Rd",
    "iso:country":"NZ",
    "sg:address":"384 Hills Rd Shirley ",
    "sg:city":"Christchurch",
    "sg:classifiers":[
        {
            "category":"Utilities",
            "subcategory":"Sewage",
            "type":"Services"
        }
    ],
    "sg:phone":"+64 3-385 3776",
    "sg:province":"Canterbury",
    "sg:tags":[
        "home",
        "tank",
        "garden",
        "septic"
    ],
    "wof:name":"Drainage Services South Island Ltd",
    "wof:placetype":"venue"
},
  "geometry": {"coordinates":[172.661621,-43.502872],"type":"Point"}
}