{
  "type": "Feature",
  "properties": {
    "addr:full":"Hillside Rd Surfdale  Auckland Auckland",
    "addr:street":"Hillside Rd",
    "iso:country":"NZ",
    "sg:address":"Hillside Rd Surfdale ",
    "sg:city":"Auckland",
    "sg:classifiers":[
        {
            "category":"Health Services",
            "subcategory":"Health Practitioner",
            "type":"Services"
        }
    ],
    "sg:phone":"+64 9-372 5492",
    "sg:province":"Auckland",
    "sg:tags":[
        "consultant",
        "medical",
        "beauty"
    ],
    "wof:name":"Qigong (John Freear)",
    "wof:placetype":"venue"
},
  "geometry": {"coordinates":[174.67579699999999,-36.6208],"type":"Point"}
}