{
  "type": "Feature",
  "properties": {
    "addr:full":"40 Benmore St Waikiwi  Invercargill Southland",
    "addr:housenumber":"40",
    "addr:street":"Benmore St",
    "iso:country":"NZ",
    "sg:address":"40 Benmore St Waikiwi ",
    "sg:city":"Invercargill",
    "sg:classifiers":[
        {
            "category":"Wholesale",
            "subcategory":"Machinery & Supplies",
            "type":"Manufacturing & Wholesale Goods"
        }
    ],
    "sg:phone":"+64 3-215 4517",
    "sg:province":"Southland",
    "sg:tags":[
        "equipment",
        "crane",
        "industrial",
        "hoist",
        "lifting"
    ],
    "wof:name":"Smith Crane & Construction Ltd",
    "wof:placetype":"venue"
},
  "geometry": {"coordinates":[168.349976,-46.384117],"type":"Point"}
}