{
  "type": "Feature",
  "properties": {
    "iso:country":"NZ",
    "sg:address":"1 Hurstmere Rd ",
    "sg:city":"Auckland",
    "sg:classifiers":[
        {
            "category":"Retail",
            "subcategory":"Laundry & Dry Cleaning",
            "type":"Services"
        }
    ],
    "sg:phone":"+64 9-489 6859",
    "sg:province":"Auckland",
    "sg:tags":[
        "repair",
        "clothing",
        "fabric"
    ],
    "wof:name":"New Zealand Drycleaners",
    "wof:placetype":"venue"
},
  "geometry": {"coordinates":[174.77250699999999,-36.789055],"type":"Point"}
}