{
  "type": "Feature",
  "properties": {
    "addr:full":"18 Maich Rd Manurewa  Auckland Auckland",
    "addr:housenumber":"18",
    "addr:street":"Maich Rd",
    "iso:country":"NZ",
    "sg:address":"18 Maich Rd Manurewa ",
    "sg:city":"Auckland",
    "sg:classifiers":[
        {
            "category":"Retail",
            "subcategory":"Auto Repair",
            "type":"Services"
        }
    ],
    "sg:phone":"+64 9-267 2221",
    "sg:province":"Auckland",
    "sg:tags":[
        "engine",
        "automotive",
        "diesel",
        "servicing"
    ],
    "wof:name":"Hytech Engines Ltd",
    "wof:placetype":"venue"
},
  "geometry": {"coordinates":[174.893066,-37.020378],"type":"Point"}
}