{
  "type": "Feature",
  "properties": {
    "addr:full":"431 Te Rapa Rd  Hamilton Waikato",
    "addr:housenumber":"431",
    "addr:street":"Te Rapa Rd",
    "iso:country":"NZ",
    "sg:address":"431 Te Rapa Rd ",
    "sg:city":"Hamilton",
    "sg:classifiers":[
        {
            "category":"Shopping",
            "subcategory":"Pharmacy",
            "type":"Retail Goods"
        }
    ],
    "sg:phone":"+64 7-849 3766",
    "sg:province":"Waikato",
    "sg:tags":[
        "products",
        "medical",
        "health",
        "beauty",
        "supply"
    ],
    "wof:name":"Keyport",
    "wof:placetype":"venue"
},
  "geometry": {"coordinates":[175.25086999999999,-37.762959],"type":"Point"}
}