{
  "type": "Feature",
  "properties": {
    "addr:full":"Albany Village Medical Centre Albany  Auckland Auckland",
    "iso:country":"NZ",
    "sg:address":"Albany Village Medical Centre Albany ",
    "sg:city":"Auckland",
    "sg:classifiers":[
        {
            "category":"Personal",
            "type":"Services"
        }
    ],
    "sg:phone":"+64 9-415 6966",
    "sg:province":"Auckland",
    "sg:tags":[
        "diet",
        "reduction",
        "health",
        "beauty",
        "weight"
    ],
    "wof:name":"Albany - Diet Therapy Clinic",
    "wof:placetype":"venue"
},
  "geometry": {"coordinates":[174.68403599999999,-36.709885],"type":"Point"}
}