{
  "type": "Feature",
  "properties": {
    "iso:country":"NZ",
    "sg:address":"108 Victoria St ",
    "sg:city":"Ashburton",
    "sg:classifiers":[
        {
            "category":"Retail",
            "subcategory":"Laundry & Dry Cleaning",
            "type":"Services"
        }
    ],
    "sg:phone":"+64 800 808 820",
    "sg:province":"Canterbury",
    "sg:tags":[
        "repair",
        "clothing",
        "fabric",
        "cleaner"
    ],
    "wof:name":"Elite Embroidery & Graphics",
    "wof:placetype":"venue"
},
  "geometry": {"coordinates":[145.077271,-37.863121],"type":"Point"}
}