{
  "type": "Feature",
  "properties": {
    "iso:country":"NZ",
    "sg:address":"R64 Panorama Dve ",
    "sg:city":"Tauranga",
    "sg:classifiers":[
        {
            "category":"Farming",
            "subcategory":"Fish & Marine Products",
            "type":"Manufacturing & Wholesale Goods"
        }
    ],
    "sg:phone":"+64 7-544 2882",
    "sg:province":"Bay of Plenty",
    "sg:tags":[
        "health",
        "beauty"
    ],
    "sg:website":"http://www.pacificharvest.co.nz",
    "wof:name":"Pacific Harvest",
    "wof:placetype":"venue"
},
  "geometry": {"coordinates":[176.14476013180001,-37.7031517029],"type":"Point"}
}