{
  "type": "Feature",
  "properties": {
    "addr:full":"21 Tancred St  Hokitika West Coast",
    "addr:housenumber":"21",
    "addr:street":"Tancred St",
    "iso:country":"NZ",
    "sg:address":"21 Tancred St ",
    "sg:city":"Hokitika",
    "sg:classifiers":[
        {
            "category":"Shopping",
            "subcategory":"Gifts & Souvenirs",
            "type":"Retail Goods"
        }
    ],
    "sg:phone":"+64 3-756 8093",
    "sg:province":"West Coast",
    "sg:tags":[
        "shop",
        "gifts",
        "supplier"
    ],
    "wof:name":"Accent of NZ",
    "wof:placetype":"venue"
},
  "geometry": {"coordinates":[170.96336400000001,-42.716789],"type":"Point"}
}