{
  "type": "Feature",
  "properties": {
    "iso:country":"NZ",
    "sg:address":"PO Box 17155 ",
    "sg:city":"Greenlane",
    "sg:classifiers":[
        {
            "category":"Manufacturing",
            "subcategory":"Rubber & Plastics",
            "type":"Manufacturing & Wholesale Goods"
        }
    ],
    "sg:phone":"+64 800 100 710",
    "sg:province":"Auckland",
    "sg:tags":[
        "product",
        "industrial",
        "goods"
    ],
    "wof:name":"FLN & Associates",
    "wof:placetype":"venue"
},
  "geometry": {"coordinates":[174.791916,-36.892967],"type":"Point"}
}