{
  "type": "Feature",
  "properties": {
    "addr:full":"BNZ Tower 125 Queen St Level 1 Auckland Central  Auckland Auckland",
    "addr:housenumber":"125;1",
    "addr:street":"Queen St Level",
    "iso:country":"NZ",
    "sg:address":"BNZ Tower 125 Queen St Level 1 Auckland Central ",
    "sg:city":"Auckland",
    "sg:classifiers":[
        {
            "category":"Insurance",
            "subcategory":"Health Insurance",
            "type":"Services"
        }
    ],
    "sg:phone":"+64 9-379 4333",
    "sg:province":"Auckland",
    "sg:tags":[
        "beauty"
    ],
    "sg:website":"http://www.yellowpages.co.nz/for/bijou/dp50963.html",
    "wof:name":"Bijou Skin & Health Care",
    "wof:placetype":"venue"
},
  "geometry": {"coordinates":[174.76454200000001,-36.848358],"type":"Point"}
}