{
  "type": "Feature",
  "properties": {
    "iso:country":"NZ",
    "sg:address":"126-128 Kennedy Rd ",
    "sg:city":"Napier",
    "sg:orig_category":"Health And Beauty: Products: Pharmacies",
    "sg:phone":"+64 6-843 9629",
    "sg:province":"Hawke's Bay",
    "wof:name":"Marewa Unichem Pharmacy",
    "wof:placetype":"venue"
},
  "geometry": {"coordinates":[176.903946,-39.49929],"type":"Point"}
}