{
  "type": "Feature",
  "properties": {
    "addr:full":"13 Coonoor Rd Watlington  Timaru Canterbury",
    "addr:housenumber":"13",
    "addr:street":"Coonoor Rd",
    "iso:country":"NZ",
    "sg:address":"13 Coonoor Rd Watlington ",
    "sg:city":"Timaru",
    "sg:classifiers":[
        {
            "category":"Personal",
            "type":"Services"
        }
    ],
    "sg:phone":"+64 3-684 3040",
    "sg:province":"Canterbury",
    "sg:tags":[
        "celebrant",
        "arrangements",
        "marriage",
        "wedding"
    ],
    "wof:name":"Dunn Les R",
    "wof:placetype":"venue"
},
  "geometry": {"coordinates":[171.23333700000001,-44.405384],"type":"Point"}
}