{
  "type": "Feature",
  "properties": {
    "iso:country":"NZ",
    "sg:address":"Waipapa Rd ",
    "sg:city":"Kerikeri",
    "sg:orig_category":"Food And Drink: Meats: Homekill Services",
    "sg:phone":"+64 9-407 8725",
    "sg:province":"Northland",
    "wof:name":"Pete's Home Kill",
    "wof:placetype":"venue"
},
  "geometry": {"coordinates":[173.926895,-35.206783],"type":"Point"}
}