{
  "type": "Feature",
  "properties": {
    "iso:country":"NZ",
    "sg:address":"103 Cowper St Greymouth South ",
    "sg:city":"Greymouth",
    "sg:classifiers":[
        {
            "category":"Health Services",
            "subcategory":"Hospital",
            "type":"Services"
        }
    ],
    "sg:phone":"+64 3-768 9066",
    "sg:province":"West Coast",
    "sg:tags":[
        "beauty",
        "fitness"
    ],
    "wof:name":"Cowper St Natural Health Clinic",
    "wof:placetype":"venue"
},
  "geometry": {"coordinates":[171.19515999999999,-42.462215],"type":"Point"}
}