{
  "type": "Feature",
  "properties": {
    "iso:country":"NZ",
    "sg:address":"Z6603/1 Masonic Dve ",
    "sg:city":"Wanganui",
    "sg:classifiers":[
        {
            "category":"Social Services",
            "subcategory":"Retirement Home",
            "type":"Services"
        }
    ],
    "sg:phone":"+64 6-343 8477",
    "sg:province":"Manawatu-Wanganui",
    "sg:tags":[
        "elderly",
        "convalescent",
        "garden",
        "rest",
        "care"
    ],
    "wof:name":"Masonic Court Home for the Elderly",
    "wof:placetype":"venue"
},
  "geometry": {"coordinates":[175.052841,-39.933369],"type":"Point"}
}