{
  "type": "Feature",
  "properties": {
    "addr:full":"23A Seventeenth Ave  Tauranga Bay of Plenty",
    "addr:housenumber":"23a",
    "addr:street":"Seventeenth Ave",
    "iso:country":"NZ",
    "sg:address":"23A Seventeenth Ave ",
    "sg:city":"Tauranga",
    "sg:classifiers":[
        {
            "category":"Personal",
            "subcategory":"Beauty Salon",
            "type":"Services"
        }
    ],
    "sg:phone":"+64 7-579 4090",
    "sg:province":"Bay of Plenty",
    "sg:tags":[
        "therapy",
        "health"
    ],
    "wof:name":"Burgundy's",
    "wof:placetype":"venue"
},
  "geometry": {"coordinates":[176.15907300000001,-37.711159],"type":"Point"}
}