{
  "type": "Feature",
  "properties": {
    "addr:full":"PO Box 15188 Dinsdale  Hamilton Waikato",
    "addr:housenumber":"po box",
    "addr:postcode":"15188",
    "iso:country":"NZ",
    "sg:address":"PO Box 15188 Dinsdale ",
    "sg:city":"Hamilton",
    "sg:orig_category":"Home And Garden: Gardening: Services: Tree Services",
    "sg:phone":"+64 7-846 5248",
    "sg:province":"Waikato",
    "wof:name":"Marc Doyle Treework",
    "wof:placetype":"venue"
},
  "geometry": {"coordinates":[175.24191300000001,-37.795715],"type":"Point"}
}