{
  "type": "Feature",
  "properties": {
    "iso:country":"NZ",
    "sg:address":"Terminal Building Airport Dve Palmerston ",
    "sg:city":"Palmerston North",
    "sg:orig_category":"Transport: Air: Airport Services",
    "sg:phone":"+64 6-351 4415",
    "sg:province":"Manawatu-Wanganui",
    "wof:name":"Palmerston North Airport Ltd",
    "wof:placetype":"venue"
},
  "geometry": {"coordinates":[175.611481,-40.357422],"type":"Point"}
}