{
  "type": "Feature",
  "properties": {
    "iso:country":"NZ",
    "sg:address":"Rawhiti Rd Manly Hibiscus ",
    "sg:city":"Hibiscus Coast",
    "sg:orig_category":"Health And Beauty: Specialists: Physiotherapists",
    "sg:phone":"+64 9-424 1309",
    "sg:province":"Auckland",
    "wof:name":"Manly Physiotherapy Clinic",
    "wof:placetype":"venue"
},
  "geometry": {"coordinates":[-93.20133199999999,43.284019],"type":"Point"}
}