{
  "type": "Feature",
  "properties": {
    "iso:country":"NZ",
    "sg:address":"6th Floor, John Wickcliffe House 265 Princes St ",
    "sg:city":"Dunedin",
    "sg:classifiers":[
        {
            "category":"Marine",
            "type":"Transportation"
        }
    ],
    "sg:phone":"+64 3-477 8711",
    "sg:province":"Otago",
    "sg:tags":[
        "transport",
        "boat"
    ],
    "sg:website":"http://www.yellowpages.co.nz/pages/222897194/dp57623.html",
    "wof:name":"International Freight Logistics NZ Limited",
    "wof:placetype":"venue"
},
  "geometry": {"coordinates":[-82.784721,28.013355],"type":"Point"}
}