{
  "type": "Feature",
  "properties": {
    "iso:country":"NZ",
    "sg:address":"80 Tainui St ",
    "sg:city":"Greymouth",
    "sg:orig_category":"Home And Garden: Gardening: Products: Lawnmowers",
    "sg:phone":"+64 3-768 9669",
    "sg:province":"West Coast",
    "wof:name":"Greymouth Equipment Centre",
    "wof:placetype":"venue"
},
  "geometry": {"coordinates":[171.209976,-42.451218],"type":"Point"}
}