{
  "type": "Feature",
  "properties": {
    "iso:country":"NZ",
    "sg:address":"Ocean Beach Complex 7 Oneroa Rd Wainui ",
    "sg:city":"Gisborne",
    "sg:classifiers":[
        {
            "category":"Restaurant",
            "type":"Food & Drink"
        }
    ],
    "sg:phone":"+64 6-868 6828",
    "sg:province":"Gisborne",
    "sg:tags":[
        "wining",
        "dining"
    ],
    "wof:name":"Sandbar Beach Cafe",
    "wof:placetype":"venue"
},
  "geometry": {"coordinates":[178.07183800000001,-38.685856],"type":"Point"}
}