{
  "type": "Feature",
  "properties": {
    "addr:full":"6/43 A Linwood Ave St Lukes  Auckland Auckland",
    "addr:housenumber":"6 / 43 a",
    "addr:street":"Linwood Ave",
    "iso:country":"NZ",
    "sg:address":"6/43 A Linwood Ave St Lukes ",
    "sg:city":"Auckland",
    "sg:classifiers":[
        {
            "category":"Professional",
            "subcategory":"Art Services",
            "type":"Services"
        }
    ],
    "sg:phone":"+64 9-845 2900",
    "sg:province":"Auckland",
    "sg:tags":[
        "hire",
        "sport",
        "leisure",
        "arts",
        "consultancy"
    ],
    "wof:name":"Practical Studio Supplies Ltd",
    "wof:placetype":"venue"
},
  "geometry": {"coordinates":[174.728973,-36.877918],"type":"Point"}
}