{
  "type": "Feature",
  "properties": {
    "iso:country":"NZ",
    "sg:address":"State Highway 6 Gibbston ",
    "sg:city":"Arrowtown",
    "sg:classifiers":[
        {
            "category":"Travel",
            "subcategory":"Travel Agent",
            "type":"Entertainment"
        }
    ],
    "sg:phone":"+64 3-442 1177",
    "sg:province":"Otago",
    "sg:tags":[
        "tour",
        "tourism",
        "adventure",
        "sightseeing"
    ],
    "wof:name":"A J Hackett Bungy Queenstown",
    "wof:placetype":"venue"
},
  "geometry": {"coordinates":[168.838959,-44.94305],"type":"Point"}
}