{
  "type": "Feature",
  "properties": {
    "iso:country":"NZ",
    "sg:address":"49 Sullivan Ave Mangere Bridge ",
    "sg:city":"Auckland",
    "sg:classifiers":[
        {
            "category":"Manufacturing",
            "subcategory":"Tools & Machinery",
            "type":"Manufacturing & Wholesale Goods"
        }
    ],
    "sg:phone":"+64 9-622 1156",
    "sg:province":"Auckland",
    "sg:tags":[
        "equipment",
        "industrial",
        "label"
    ],
    "wof:name":"Abel Labels",
    "wof:placetype":"venue"
},
  "geometry": {"coordinates":[174.774857,-36.944584],"type":"Point"}
}