{
  "type": "Feature",
  "properties": {
    "addr:full":"9 Kitchener St  Martinborough",
    "addr:housenumber":"9",
    "addr:street":"Kitchener St",
    "iso:country":"NZ",
    "sg:address":"9 Kitchener St ",
    "sg:city":"Martinborough",
    "sg:orig_category":"Food And Drink: Catering: Caterers",
    "sg:phone":"+64 6-306 9965",
    "wof:name":"Cafe Medici",
    "wof:placetype":"venue"
},
  "geometry": {"coordinates":[175.456345,-41.21529],"type":"Point"}
}