{
  "type": "Feature",
  "properties": {
    "addr:full":"440 Church St East Penrose  Auckland Auckland",
    "addr:housenumber":"440",
    "addr:street":"Church St",
    "iso:country":"NZ",
    "sg:address":"440 Church St East Penrose ",
    "sg:city":"Auckland",
    "sg:classifiers":[
        {
            "category":"Retail",
            "subcategory":"Auto Repair",
            "type":"Services"
        }
    ],
    "sg:phone":"+64 9-579 1156",
    "sg:province":"Auckland",
    "sg:tags":[
        "automotive",
        "electric",
        "servicing"
    ],
    "wof:name":"Simms Electrical Services Ltd",
    "wof:placetype":"venue"
},
  "geometry": {"coordinates":[174.824738,-36.918831],"type":"Point"}
}