{
  "type": "Feature",
  "properties": {
    "iso:country":"NZ",
    "sg:address":"153 Blue Mountains Rd Blue Mountains ",
    "sg:city":"Wellington",
    "sg:classifiers":[
        {
            "category":"Utilities",
            "type":"Services"
        }
    ],
    "sg:phone":"+64 4-528 2867",
    "sg:province":"Wellington",
    "sg:tags":[
        "industrial",
        "energy",
        "utilities",
        "coal",
        "wood",
        "coke"
    ],
    "wof:name":"Blue Mountains Firewood",
    "wof:placetype":"venue"
},
  "geometry": {"coordinates":[175.026245,-41.166637],"type":"Point"}
}