{
  "type": "Feature",
  "properties": {
    "addr:full":"78 A Nelson St Petone Lower  Hutt Wellington",
    "addr:housenumber":"78",
    "addr:street":"A Nelson St",
    "iso:country":"NZ",
    "sg:address":"78 A Nelson St Petone Lower ",
    "sg:city":"Hutt",
    "sg:orig_category":"Industrial: Engineering: Engineers: Engineers Supplies",
    "sg:phone":"+64 4-568 4941",
    "sg:province":"Wellington",
    "wof:name":"Allways-Mannings Ltd",
    "wof:placetype":"venue"
},
  "geometry": {"coordinates":[174.878128,-41.222698],"type":"Point"}
}