{
  "type": "Feature",
  "properties": {
    "addr:full":"100 Waitikiri Dve Burwood  Christchurch Canterbury",
    "addr:housenumber":"100",
    "addr:street":"Waitikiri Dve",
    "iso:country":"NZ",
    "sg:address":"100 Waitikiri Dve Burwood ",
    "sg:city":"Christchurch",
    "sg:orig_category":"Industrial: Consultancy: Industrial Consultants",
    "sg:phone":"+64 3-383 9395",
    "sg:province":"Canterbury",
    "wof:name":"Industry Solutions Limited",
    "wof:placetype":"venue"
},
  "geometry": {"coordinates":[172.68199200000001,-43.494564],"type":"Point"}
}