{
  "type": "Feature",
  "properties": {
    "iso:country":"NZ",
    "sg:address":"459 High St Lower ",
    "sg:city":"Hutt",
    "sg:classifiers":[
        {
            "category":"Fast Food",
            "type":"Food & Drink"
        }
    ],
    "sg:phone":"+64 4-566 1604",
    "sg:province":"Wellington",
    "sg:tags":[
        "wining",
        "dining",
        "takeaway"
    ],
    "wof:name":"Laxmi's Food Bar",
    "wof:placetype":"venue"
},
  "geometry": {"coordinates":[174.910461,-41.205536],"type":"Point"}
}