{
  "type": "Feature",
  "properties": {
    "iso:country":"NZ",
    "sg:address":"Whatipu Rd Whatipu ",
    "sg:city":"Auckland",
    "sg:orig_category":"Travel And Tourism: Accommodation: Hostels",
    "sg:phone":"+64 9-811 8860",
    "sg:province":"Auckland",
    "wof:name":"Whatipu Lodge",
    "wof:placetype":"venue"
},
  "geometry": {"coordinates":[174.70047,-36.877575],"type":"Point"}
}