{
  "type": "Feature",
  "properties": {
    "iso:country":"NZ",
    "sg:address":"8 Vulcan Pl Riccarton ",
    "sg:city":"Christchurch",
    "sg:orig_category":"Industrial: Engineering: Engineers - Automation",
    "sg:phone":"+64 3-338 5165",
    "sg:province":"Canterbury",
    "wof:name":"Electropar Ltd",
    "wof:placetype":"venue"
},
  "geometry": {"coordinates":[172.597351,-43.532143],"type":"Point"}
}