{
  "type": "Feature",
  "properties": {
    "addr:full":"Cnr Tarewa Rd & Porowini Ave  Whangarei Northland",
    "addr:street":"Cnr Tarewa Rd & Porowini Ave",
    "iso:country":"NZ",
    "sg:address":"Cnr Tarewa Rd & Porowini Ave ",
    "sg:city":"Whangarei",
    "sg:orig_category":"Home And Garden: General",
    "sg:phone":"+64 9-430 3300",
    "sg:province":"Northland",
    "sg:website":"http://www.allenswhg.co.nz",
    "wof:name":"Allens Goode Leith Realty Ltd-MREINZ",
    "wof:placetype":"venue"
},
  "geometry": {"coordinates":[-70.604202,-26.329201],"type":"Point"}
}