{
  "type": "Feature",
  "properties": {
    "iso:country":"NZ",
    "sg:address":"56 Teviot St South Dunedin ",
    "sg:city":"Dunedin",
    "sg:classifiers":[
        {
            "category":"Professional",
            "subcategory":"Art Services",
            "type":"Services"
        }
    ],
    "sg:phone":"+64 3-455 2220",
    "sg:province":"Otago",
    "sg:tags":[
        "picture",
        "arts",
        "sport",
        "framing",
        "leisure"
    ],
    "wof:name":"Southern Paper Products",
    "wof:placetype":"venue"
},
  "geometry": {"coordinates":[170.51362599999999,-45.893139],"type":"Point"}
}