{
  "type": "Feature",
  "properties": {
    "iso:country":"NZ",
    "sg:address":"22 Totara Ave New Lynn ",
    "sg:city":"Auckland",
    "sg:classifiers":[
        {
            "category":"Restaurant",
            "type":"Food & Drink"
        }
    ],
    "sg:phone":"+64 9-827 1443",
    "sg:province":"Auckland",
    "sg:tags":[
        "sea"
    ],
    "wof:name":"Fish World Ltd",
    "wof:placetype":"venue"
},
  "geometry": {"coordinates":[174.682648,-36.909313],"type":"Point"}
}