{
  "type": "Feature",
  "properties": {
    "addr:full":"RD6  Whangarei Northland",
    "iso:country":"NZ",
    "sg:address":"RD6 ",
    "sg:city":"Whangarei",
    "sg:classifiers":[
        {
            "category":"Personal",
            "subcategory":"Beauty Salon",
            "type":"Services"
        }
    ],
    "sg:phone":"+64 256100299",
    "sg:province":"Northland",
    "sg:tags":[
        "new age",
        "health",
        "services",
        "professional"
    ],
    "wof:name":"Lennon-Barnes Susanne",
    "wof:placetype":"venue"
},
  "geometry": {"coordinates":[174.26042200000001,-35.235981],"type":"Point"}
}