{
  "type": "Feature",
  "properties": {
    "iso:country":"NZ",
    "sg:address":"140 Great North Rd ",
    "sg:city":"Wanganui",
    "sg:classifiers":[
        {
            "category":"Social Services",
            "subcategory":"Retirement Home",
            "type":"Services"
        }
    ],
    "sg:phone":"+64 6-345 6477",
    "sg:province":"Manawatu-Wanganui",
    "sg:tags":[
        "elderly",
        "convalescent",
        "garden",
        "rest",
        "care"
    ],
    "wof:name":"Arranmore",
    "wof:placetype":"venue"
},
  "geometry": {"coordinates":[175.02593999999999,-39.910255],"type":"Point"}
}