{
  "type": "Feature",
  "properties": {
    "iso:country":"NZ",
    "sg:address":"Green Island ",
    "sg:city":"Dunedin",
    "sg:orig_category":"Transport: Land: Shuttle Services",
    "sg:phone":"+64 3-488 2616",
    "sg:province":"Otago",
    "wof:name":"Edinburgh Shuttles",
    "wof:placetype":"venue"
},
  "geometry": {"coordinates":[170.439133,-45.903397],"type":"Point"}
}