{
  "type": "Feature",
  "properties": {
    "addr:full":"Coastlands Paraparaumu Wellington",
    "iso:country":"NZ",
    "sg:address":"Coastlands",
    "sg:city":"Paraparaumu",
    "sg:classifiers":[
        {
            "category":"Banks & Credit Unions",
            "subcategory":"Bank",
            "type":"Services"
        }
    ],
    "sg:phone":"+64 5884629",
    "sg:province":"Wellington",
    "wof:name":"Westpac Banking Corp.",
    "wof:placetype":"venue"
},
  "geometry": {"coordinates":[175.00799599999999,-40.910461],"type":"Point"}
}