{
  "type": "Feature",
  "properties": {
    "addr:full":"3rd Floor 52 Symonds St Auckland Central  Auckland Auckland",
    "addr:housenumber":"3rd floor 52",
    "addr:street":"Symonds St",
    "iso:country":"NZ",
    "sg:address":"3rd Floor 52 Symonds St Auckland Central ",
    "sg:city":"Auckland",
    "sg:orig_category":"Transport: Boats And Marine: Shipping: Shipping Companies",
    "sg:phone":"+64 9-356 2333",
    "sg:province":"Auckland",
    "sg:website":"http://www.pflnz.co.nz",
    "wof:name":"Pacific Forum Line (NZ) Ltd",
    "wof:placetype":"venue"
},
  "geometry": {"coordinates":[174.767166,-36.855331],"type":"Point"}
}