{
  "type": "Feature",
  "properties": {
    "addr:full":"Flaxmore Rd Harakeke Upper  Moutere",
    "addr:street":"Flaxmore Rd Harakeke Upper",
    "iso:country":"NZ",
    "sg:address":"Flaxmore Rd Harakeke Upper ",
    "sg:city":"Moutere",
    "sg:orig_category":"Farming: Machinery: Farm Machinery",
    "sg:phone":"+64 3-543 2350",
    "wof:name":"Mike Eggers Ltd",
    "wof:placetype":"venue"
},
  "geometry": {"coordinates":[173.03062399999999,-41.222656],"type":"Point"}
}