{
  "type": "Feature",
  "properties": {
    "addr:full":"29 Lunns Rd Sockburn  Christchurch Canterbury",
    "addr:housenumber":"29",
    "addr:street":"Lunns Rd",
    "iso:country":"NZ",
    "sg:address":"29 Lunns Rd Sockburn ",
    "sg:city":"Christchurch",
    "sg:classifiers":[
        {
            "category":"Home & Garden",
            "subcategory":"Building Materials",
            "type":"Retail Goods"
        }
    ],
    "sg:phone":"+64 3-348 3010",
    "sg:province":"Canterbury",
    "sg:tags":[
        "door",
        "fitting",
        "fittings"
    ],
    "wof:name":"NZ Doors Ltd",
    "wof:placetype":"venue"
},
  "geometry": {"coordinates":[172.55043000000001,-43.534966],"type":"Point"}
}