{
  "type": "Feature",
  "properties": {
    "addr:full":"95 Wordsworth St Sydenham  Christchurch Canterbury",
    "addr:housenumber":"95",
    "addr:street":"Wordsworth St",
    "iso:country":"NZ",
    "sg:address":"95 Wordsworth St Sydenham ",
    "sg:city":"Christchurch",
    "sg:orig_category":"Sports And Leisure: Sports: Golf",
    "sg:phone":"+64 3-366 8308",
    "sg:province":"Canterbury",
    "wof:name":"Fairway Golf (Powerbilt) Centre",
    "wof:placetype":"venue"
},
  "geometry": {"coordinates":[172.63801599999999,-43.544598],"type":"Point"}
}