{
  "type": "Feature",
  "properties": {
    "addr:full":"64 Hector St  Seatoun",
    "addr:housenumber":"64",
    "addr:street":"Hector St",
    "iso:country":"NZ",
    "sg:address":"64 Hector St ",
    "sg:city":"Seatoun",
    "sg:orig_category":"Home And Garden: Gardening: Services: Landscape Design",
    "sg:phone":"+64 252484964",
    "wof:name":"Renaissance Designer Gardens",
    "wof:placetype":"venue"
},
  "geometry": {"coordinates":[174.83384699999999,-41.327332],"type":"Point"}
}