{
  "type": "Feature",
  "properties": {
    "addr:full":"146 A Harris Rd East Tamaki  Auckland Auckland",
    "addr:housenumber":"146",
    "addr:street":"A Harris Rd",
    "iso:country":"NZ",
    "sg:address":"146 A Harris Rd East Tamaki ",
    "sg:city":"Auckland",
    "sg:orig_category":"Transport: Boats And Marine: Products: Marine Electronics",
    "sg:phone":"+64 9-274 4062",
    "sg:province":"Auckland",
    "wof:name":"Icom Communications NZ LTD",
    "wof:placetype":"venue"
},
  "geometry": {"coordinates":[174.89695699999999,-36.929916],"type":"Point"}
}