{
  "type": "Feature",
  "properties": {
    "addr:full":"301 Heads Rd  Wanganui Manawatu-Wanganui",
    "addr:housenumber":"301",
    "addr:street":"Heads Rd",
    "iso:country":"NZ",
    "sg:address":"301 Heads Rd ",
    "sg:city":"Wanganui",
    "sg:classifiers":[
        {
            "category":"Arena",
            "subcategory":"Sports Club",
            "type":"Entertainment"
        }
    ],
    "sg:phone":"+64 6-344 5964",
    "sg:province":"Manawatu-Wanganui",
    "sg:tags":[
        "-",
        "leisure",
        "sports"
    ],
    "wof:name":"Castlecliff United (Sports Club)",
    "wof:placetype":"venue"
},
  "geometry": {"coordinates":[175.01850899999999,-39.949066],"type":"Point"}
}