{
  "type": "Feature",
  "properties": {
    "addr:full":"69 Victoria Ave  Wanganui Manawatu-Wanganui",
    "addr:housenumber":"69",
    "addr:street":"Victoria Ave",
    "iso:country":"NZ",
    "sg:address":"69 Victoria Ave ",
    "sg:city":"Wanganui",
    "sg:orig_category":"Clothing And Fabric: Clothing: Women'S Fashions",
    "sg:phone":"+64 6-342 1776",
    "sg:province":"Manawatu-Wanganui",
    "wof:name":"Stardust Creations",
    "wof:placetype":"venue"
},
  "geometry": {"coordinates":[175.05291700000001,-39.93359],"type":"Point"}
}