{
  "type": "Feature",
  "properties": {
    "iso:country":"NZ",
    "sg:address":"607 Settlers Rd ",
    "sg:city":"Reporoa",
    "sg:orig_category":"Farming: Supplies",
    "sg:phone":"+64 7-333 8338",
    "sg:website":"http://www.reporoa.co.nz",
    "wof:name":"Reporoa Valley Traders Ltd",
    "wof:placetype":"venue"
},
  "geometry": {"coordinates":[176.345535,-38.424908],"type":"Point"}
}