{
  "type": "Feature",
  "properties": {
    "addr:full":"9 Carpenter Rd East Tamaki  Auckland Auckland",
    "addr:housenumber":"9",
    "addr:street":"Carpenter Rd",
    "iso:country":"NZ",
    "sg:address":"9 Carpenter Rd East Tamaki ",
    "sg:city":"Auckland",
    "sg:classifiers":[
        {
            "category":"Home & Garden",
            "subcategory":"Building Materials",
            "type":"Retail Goods"
        }
    ],
    "sg:phone":"+64 9-273 3699",
    "sg:province":"Auckland",
    "sg:tags":[
        "door",
        "fitting",
        "fittings"
    ],
    "wof:name":"Owairoa Joinery Ltd",
    "wof:placetype":"venue"
},
  "geometry": {"coordinates":[174.889984,-36.932392],"type":"Point"}
}