{
  "type": "Feature",
  "properties": {
    "iso:country":"NZ",
    "sg:address":"9 a Hobson Heights Rd Albany ",
    "sg:city":"Auckland",
    "sg:orig_category":"Home And Garden: Gardening: Services: Landscape Architects",
    "sg:phone":"+64 9-441 3453",
    "sg:province":"Auckland",
    "wof:name":"Belcher M J",
    "wof:placetype":"venue"
},
  "geometry": {"coordinates":[174.68002319339999,-36.7244567871],"type":"Point"}
}