{
  "type": "Feature",
  "properties": {
    "addr:full":"Queen St East  Levin Manawatu-Wanganui",
    "addr:street":"Queen St",
    "iso:country":"NZ",
    "sg:address":"Queen St East ",
    "sg:city":"Levin",
    "sg:classifiers":[
        {
            "category":"Farming",
            "subcategory":"Farm & Veterinary Services",
            "type":"Manufacturing & Wholesale Goods"
        }
    ],
    "sg:phone":"+64 6-368 6129",
    "sg:province":"Manawatu-Wanganui",
    "sg:tags":[
        "supplies",
        "supply"
    ],
    "wof:name":"AllFarms Ltd",
    "wof:placetype":"venue"
},
  "geometry": {"coordinates":[175.302368,-40.628624],"type":"Point"}
}