{
  "type": "Feature",
  "properties": {
    "iso:country":"NZ",
    "sg:address":"30 Alexandra St Te ",
    "sg:city":"Awamutu",
    "sg:orig_category":"Home And Garden: Outdoor: Barbecues",
    "sg:phone":"+64 7-871 4995",
    "sg:province":"Waikato",
    "wof:name":"Heathcote Appliances 100%",
    "wof:placetype":"venue"
},
  "geometry": {"coordinates":[175.32540893550001,-38.0098648071],"type":"Point"}
}