{
  "type": "Feature",
  "properties": {
    "iso:country":"NZ",
    "sg:address":"17 Sheffield Cre Burnside ",
    "sg:city":"Christchurch",
    "sg:classifiers":[
        {
            "category":"Shopping",
            "subcategory":"Pharmacy",
            "type":"Retail Goods"
        }
    ],
    "sg:phone":"+64 3-358 7899",
    "sg:province":"Canterbury",
    "sg:tags":[
        "product",
        "health"
    ],
    "wof:name":"Bionutrient S.G Ltd",
    "wof:placetype":"venue"
},
  "geometry": {"coordinates":[172.567551,-43.502163],"type":"Point"}
}