{
  "type": "Feature",
  "properties": {
    "iso:country":"NZ",
    "sg:address":"PO Box 5371 Palmerston ",
    "sg:city":"Palmerston North",
    "sg:classifiers":[
        {
            "category":"Home & Garden",
            "subcategory":"Carpets & Floor Coverings",
            "type":"Retail Goods"
        }
    ],
    "sg:phone":"+64 6-354 6203",
    "sg:province":"Manawatu-Wanganui",
    "sg:tags":[
        "cleaning",
        "furniture"
    ],
    "wof:name":"JAE Carpet & Pest Control Services",
    "wof:placetype":"venue"
},
  "geometry": {"coordinates":[175.611481,-40.357418],"type":"Point"}
}