{
  "type": "Feature",
  "properties": {
    "iso:country":"NZ",
    "sg:address":"128 Gordon Rd Mosgiel ",
    "sg:city":"Dunedin",
    "sg:orig_category":"Shopping: Hobbies And Games: Handcrafts",
    "sg:phone":"+64 3-489 8121",
    "sg:province":"Otago",
    "wof:name":"Wool 'N' Stitches",
    "wof:placetype":"venue"
},
  "geometry": {"coordinates":[170.348129,-45.875164],"type":"Point"}
}