{
  "type": "Feature",
  "properties": {
    "addr:full":"62 Ponsonby Rd Ponsonby  Auckland Auckland",
    "addr:housenumber":"62",
    "addr:street":"Ponsonby Rd",
    "iso:country":"NZ",
    "sg:address":"62 Ponsonby Rd Ponsonby ",
    "sg:city":"Auckland",
    "sg:orig_category":"Shopping: Accessories: Handbags",
    "sg:phone":"+64 9-360 9931",
    "sg:province":"Auckland",
    "wof:name":"Faben",
    "wof:placetype":"venue"
},
  "geometry": {"coordinates":[174.74676500000001,-36.856407],"type":"Point"}
}