{
  "type": "Feature",
  "properties": {
    "iso:country":"NZ",
    "sg:address":"55 McBratneys Rd ",
    "sg:city":"Dallington",
    "sg:classifiers":[
        {
            "category":"Sports & Exercise",
            "subcategory":"Race Track",
            "type":"Entertainment"
        }
    ],
    "sg:phone":"+64 25334267",
    "sg:tags":[
        "-",
        "leisure",
        "sports",
        "billiard",
        "table",
        "pool"
    ],
    "wof:name":"A.R.Smith Ltd",
    "wof:placetype":"venue"
},
  "geometry": {"coordinates":[0.357477,50.947426],"type":"Point"}
}