{
  "type": "Feature",
  "properties": {
    "iso:country":"NZ",
    "sg:address":"52 Parawai Rd ",
    "sg:city":"Rotorua",
    "sg:orig_category":"Automotive: Parts And Supplies: Windscreens",
    "sg:phone":"+64 7-357 2324",
    "sg:province":"Bay of Plenty",
    "wof:name":"T K Auto Glass",
    "wof:placetype":"venue"
},
  "geometry": {"coordinates":[176.218216,-38.087563],"type":"Point"}
}