{
  "type": "Feature",
  "properties": {
    "iso:country":"NZ",
    "sg:address":"1300 Tutanekai St ",
    "sg:city":"Rotorua",
    "sg:classifiers":[
        {
            "category":"Food & Beverages",
            "subcategory":"Bakery",
            "type":"Retail Goods"
        }
    ],
    "sg:phone":"+64 7-346 0375",
    "sg:province":"Bay of Plenty",
    "sg:tags":[
        "shop",
        "cake",
        "drink",
        "-"
    ],
    "wof:name":"Patrick's Patisserie",
    "wof:placetype":"venue"
},
  "geometry": {"coordinates":[176.25174000000001,-38.139381],"type":"Point"}
}