{
  "type": "Feature",
  "properties": {
    "iso:country":"NZ",
    "sg:address":"Thames St ",
    "sg:city":"Morrinsville",
    "sg:classifiers":[
        {
            "category":"Shopping",
            "subcategory":"Gifts & Souvenirs",
            "type":"Retail Goods"
        }
    ],
    "sg:phone":"+64 7-889 6721",
    "sg:province":"Waikato",
    "sg:tags":[
        "shop",
        "gifts",
        "supplier"
    ],
    "sg:website":"http://www.stevensgifts.co.nz",
    "wof:name":"Stevens Gift Centre",
    "wof:placetype":"venue"
},
  "geometry": {"coordinates":[175.525772,-37.658939],"type":"Point"}
}