{
  "type": "Feature",
  "properties": {
    "addr:full":"PO Box 2029  Wanganui Manawatu-Wanganui",
    "addr:housenumber":"po",
    "addr:postcode":"2029",
    "addr:street":"Box",
    "iso:country":"NZ",
    "sg:address":"PO Box 2029 ",
    "sg:city":"Wanganui",
    "sg:orig_category":"Industrial: Coatings",
    "sg:phone":"+64 800 800 890",
    "sg:province":"Manawatu-Wanganui",
    "wof:name":"Spectrum Coating",
    "wof:placetype":"venue"
},
  "geometry": {"coordinates":[175.052841,-39.933369],"type":"Point"}
}