{
  "type": "Feature",
  "properties": {
    "iso:country":"NZ",
    "sg:address":"51 Matai St ",
    "sg:city":"Taupo",
    "sg:orig_category":"Automotive: Accessories: Towbars",
    "sg:phone":"+64 7-378 6775",
    "sg:province":"Waikato",
    "wof:name":"Welding Services",
    "wof:placetype":"venue"
},
  "geometry": {"coordinates":[176.102783,-38.68903],"type":"Point"}
}