{
  "type": "Feature",
  "properties": {
    "iso:country":"NZ",
    "sg:address":"490 Pakuranga Highway ",
    "sg:city":"Auckland",
    "sg:classifiers":[
        {
            "category":"Restaurant",
            "type":"Food & Drink"
        }
    ],
    "sg:phone":"+64 9-537 1319",
    "sg:province":"Auckland",
    "sg:tags":[
        "wining",
        "dining",
        "pizza"
    ],
    "wof:name":"Pizza Hut",
    "wof:placetype":"venue"
},
  "geometry": {"coordinates":[174.90154999999999,-36.899315],"type":"Point"}
}