{
  "type": "Feature",
  "properties": {
    "addr:full":"Musselburgh Medical Centre 59 a Musselburgh Rse  Dunedin Otago",
    "addr:housenumber":"59 a",
    "iso:country":"NZ",
    "sg:address":"Musselburgh Medical Centre 59 a Musselburgh Rse ",
    "sg:city":"Dunedin",
    "sg:orig_category":"Health And Beauty: Specialists: Physiotherapists",
    "sg:phone":"+64 3-455 4085",
    "sg:province":"Otago",
    "wof:name":"Moginie Graeme",
    "wof:placetype":"venue"
},
  "geometry": {"coordinates":[170.50384500000001,-45.8745],"type":"Point"}
}