{
  "type": "Feature",
  "properties": {
    "iso:country":"NZ",
    "sg:address":"Level 1 National Bank Building 90 Kerikeri Rd ",
    "sg:city":"Kerikeri",
    "sg:orig_category":"Industrial: Engineering: Engineers: Engineers - Consulting",
    "sg:phone":"+64 9-407 3255",
    "sg:province":"Northland",
    "wof:name":"P K Engineering",
    "wof:placetype":"venue"
},
  "geometry": {"coordinates":[173.949905,-35.226269],"type":"Point"}
}