{
  "type": "Feature",
  "properties": {
    "addr:full":"Mace Rd R D 1 Te  Aroha",
    "addr:housenumber":"1",
    "addr:street":"Mace Rd R D",
    "iso:country":"NZ",
    "sg:address":"Mace Rd R D 1 Te ",
    "sg:city":"Aroha",
    "sg:orig_category":"Farming: Agriculture",
    "sg:phone":"+64 7-884 7974",
    "wof:name":"Combined Contractors",
    "wof:placetype":"venue"
},
  "geometry": {"coordinates":[175.707718,-37.534805],"type":"Point"}
}