{
  "type": "Feature",
  "properties": {
    "addr:full":"G2/125 Queen St Auckland Central  Auckland Auckland",
    "addr:housenumber":"125",
    "addr:street":"Queen St",
    "iso:country":"NZ",
    "sg:address":"G2/125 Queen St Auckland Central ",
    "sg:city":"Auckland",
    "sg:classifiers":[
        {
            "category":"Retail",
            "subcategory":"Laundry & Dry Cleaning",
            "type":"Services"
        }
    ],
    "sg:phone":"+64 9-309 6676",
    "sg:province":"Auckland",
    "sg:tags":[
        "repair",
        "clothing",
        "fabric",
        "cleaner"
    ],
    "wof:name":"Sparkle Fine Drycleaners",
    "wof:placetype":"venue"
},
  "geometry": {"coordinates":[174.76454200000001,-36.848358],"type":"Point"}
}