{
  "type": "Feature",
  "properties": {
    "addr:full":"8 Kelvin St  Invercargill Southland",
    "addr:housenumber":"8",
    "addr:street":"Kelvin St",
    "iso:country":"NZ",
    "sg:address":"8 Kelvin St ",
    "sg:city":"Invercargill",
    "sg:orig_category":"Shopping: Accessories: Embroidery And Monograms",
    "sg:phone":"+64 3-214 0054",
    "sg:province":"Southland",
    "wof:name":"McCallum J A & Son Ltd",
    "wof:placetype":"venue"
},
  "geometry": {"coordinates":[168.35047900000001,-46.412548],"type":"Point"}
}