{
  "type": "Feature",
  "properties": {
    "addr:full":"113 Dee St  Invercargill Southland",
    "addr:housenumber":"113",
    "addr:street":"Dee St",
    "iso:country":"NZ",
    "sg:address":"113 Dee St ",
    "sg:city":"Invercargill",
    "sg:orig_category":"Clothing And Fabric: Clothing: Menswear",
    "sg:phone":"+64 3-218 6092",
    "sg:province":"Southland",
    "wof:name":"Fredricks Menswear",
    "wof:placetype":"venue"
},
  "geometry": {"coordinates":[168.34732099999999,-46.392628],"type":"Point"}
}