{
  "type": "Feature",
  "properties": {
    "iso:country":"NZ",
    "sg:address":"www.countrytouch.co.nz Royal ",
    "sg:city":"Oak",
    "sg:orig_category":"Health And Beauty: Beauty: Manicurists",
    "sg:phone":"+64 9-625 4635",
    "wof:name":"A Country Touch Beauty Therapy",
    "wof:placetype":"venue"
},
  "geometry": {"coordinates":[174.77351400000001,-36.910019],"type":"Point"}
}