{
  "type": "Feature",
  "properties": {
    "addr:full":"10 Flinders Pl Welcome  Bay",
    "addr:housenumber":"10",
    "addr:street":"Flinders Pl",
    "iso:country":"NZ",
    "sg:address":"10 Flinders Pl Welcome ",
    "sg:city":"Bay",
    "sg:classifiers":[
        {
            "category":"Wholesale",
            "subcategory":"Machinery & Supplies",
            "type":"Manufacturing & Wholesale Goods"
        }
    ],
    "sg:phone":"+64 25905778",
    "sg:tags":[
        "equipment",
        "crane",
        "industrial",
        "hoist",
        "lifting"
    ],
    "wof:name":"Cherry Picker Services",
    "wof:placetype":"venue"
},
  "geometry": {"coordinates":[176.202789,-37.725883],"type":"Point"}
}