{
  "type": "Feature",
  "properties": {
    "addr:full":"266 Havelock St  Ashburton Canterbury",
    "addr:housenumber":"266",
    "addr:street":"Havelock St",
    "iso:country":"NZ",
    "sg:address":"266 Havelock St ",
    "sg:city":"Ashburton",
    "sg:classifiers":[
        {
            "category":"Sports & Exercise",
            "subcategory":"Playing Field",
            "type":"Entertainment"
        }
    ],
    "sg:phone":"+64 3-308 4477",
    "sg:province":"Canterbury",
    "sg:tags":[
        "operator",
        "totalisator",
        "leisure"
    ],
    "wof:name":"TAB",
    "wof:placetype":"venue"
},
  "geometry": {"coordinates":[-77.127831,39.012852],"type":"Point"}
}