{
  "type": "Feature",
  "properties": {
    "addr:full":"Ocean View Pde New  Plymouth Taranaki",
    "addr:street":"View",
    "iso:country":"NZ",
    "sg:address":"Ocean View Pde New ",
    "sg:city":"Plymouth",
    "sg:classifiers":[
        {
            "category":"Farming",
            "subcategory":"Fish & Marine Products",
            "type":"Manufacturing & Wholesale Goods"
        }
    ],
    "sg:phone":"+64 6-757 4850",
    "sg:province":"Taranaki",
    "sg:tags":[
        "-",
        "boat",
        "transport"
    ],
    "wof:name":"Rainbow Abalone & Pearls",
    "wof:placetype":"venue"
},
  "geometry": {"coordinates":[174.074005,-39.058292],"type":"Point"}
}