{
  "type": "Feature",
  "properties": {
    "iso:country":"NZ",
    "sg:address":"1225 Haupapa St ",
    "sg:city":"Rotorua",
    "sg:classifiers":[
        {
            "category":"Communications",
            "subcategory":"Film & Video Production",
            "type":"Services"
        }
    ],
    "sg:phone":"+64 7-343 6756",
    "sg:province":"Bay of Plenty",
    "sg:tags":[
        "sport",
        "leisure",
        "library",
        "entertainment"
    ],
    "wof:name":"Adult Wild Things",
    "wof:placetype":"venue"
},
  "geometry": {"coordinates":[176.24970999999999,-38.135727],"type":"Point"}
}