{
  "type": "Feature",
  "properties": {
    "iso:country":"NZ",
    "sg:address":"631 Huia Rd Parau ",
    "sg:city":"Auckland",
    "sg:classifiers":[
        {
            "category":"Health Services",
            "subcategory":"Doctor",
            "type":"Services"
        }
    ],
    "sg:phone":"+64 9-817 3450",
    "sg:province":"Auckland",
    "sg:tags":[
        "services",
        "meditation",
        "beauty"
    ],
    "wof:name":"International Buddhist Meditation Temple Of New Zealand",
    "wof:placetype":"venue"
},
  "geometry": {"coordinates":[174.612946,-36.976875],"type":"Point"}
}