{
  "type": "Feature",
  "properties": {
    "addr:full":"Alexandra St Te  Awamutu Waikato",
    "addr:street":"Alexandra St",
    "iso:country":"NZ",
    "sg:address":"Alexandra St Te ",
    "sg:city":"Awamutu",
    "sg:classifiers":[
        {
            "category":"Restaurant",
            "type":"Food & Drink"
        }
    ],
    "sg:phone":"+64 7-871 5373",
    "sg:province":"Waikato",
    "sg:tags":[
        "merchant",
        "fish",
        "sea"
    ],
    "wof:name":"Dolphin Fisheries",
    "wof:placetype":"venue"
},
  "geometry": {"coordinates":[175.325256,-38.00996],"type":"Point"}
}