{
  "type": "Feature",
  "properties": {
    "addr:full":"648 Maunganui Rd Mt  Maunganui Bay of Plenty",
    "addr:housenumber":"648",
    "addr:street":"Maunganui Rd;Maunganui",
    "iso:country":"NZ",
    "sg:address":"648 Maunganui Rd Mt ",
    "sg:city":"Maunganui",
    "sg:orig_category":"Health And Beauty: Specialists: Chiropractors",
    "sg:phone":"+64 7-574 0900",
    "sg:province":"Bay of Plenty",
    "wof:name":"Matier Dr Sean M",
    "wof:placetype":"venue"
},
  "geometry": {"coordinates":[176.19285600000001,-37.650269],"type":"Point"}
}