{
  "type": "Feature",
  "properties": {
    "iso:country":"NZ",
    "sg:address":"10 Bridle Path Rd Heathcote ",
    "sg:city":"Christchurch",
    "sg:classifiers":[
        {
            "category":"Professional",
            "type":"Services"
        }
    ],
    "sg:phone":"+64 3-384 0700",
    "sg:province":"Canterbury",
    "sg:tags":[
        "function",
        "entertainment",
        "leisure",
        "planning",
        "party",
        "sport"
    ],
    "wof:name":"Christchurch Gondola",
    "wof:placetype":"venue"
},
  "geometry": {"coordinates":[172.707184,-43.584625],"type":"Point"}
}