{
  "type": "Feature",
  "properties": {
    "addr:full":"Taharoto Park Taharoto Rd Takapuna  Auckland Auckland",
    "addr:street":"Taharoto Park Taharoto Rd",
    "iso:country":"NZ",
    "sg:address":"Taharoto Park Taharoto Rd Takapuna ",
    "sg:city":"Auckland",
    "sg:classifiers":[
        {
            "category":"Arena",
            "subcategory":"Sports Club",
            "type":"Entertainment"
        }
    ],
    "sg:phone":"+64 9-489 8410",
    "sg:province":"Auckland",
    "sg:tags":[
        "-",
        "leisure",
        "sports"
    ],
    "wof:name":"Takapuna City Assn Football Club Inc",
    "wof:placetype":"venue"
},
  "geometry": {"coordinates":[174.76788300000001,-36.787838],"type":"Point"}
}