{
  "type": "Feature",
  "properties": {
    "addr:full":"1 Smith St Lepperton PO Box 682 New Plymouth  Lepperton",
    "addr:housenumber":"1;po box 682",
    "addr:street":"Smith St",
    "iso:country":"NZ",
    "sg:address":"1 Smith St Lepperton PO Box 682 New Plymouth ",
    "sg:city":"Lepperton",
    "sg:classifiers":[
        {
            "category":"Social Services",
            "subcategory":"Job Training",
            "type":"Services"
        }
    ],
    "sg:phone":"+64 6-752 0635",
    "sg:tags":[
        "education"
    ],
    "wof:name":"Alpha Training & Development Centre",
    "wof:placetype":"venue"
},
  "geometry": {"coordinates":[-116.81971,43.972191],"type":"Point"}
}