{
  "type": "Feature",
  "properties": {
    "iso:country":"NZ",
    "sg:address":"269 Gt South Rd Manurewa ",
    "sg:city":"Auckland",
    "sg:orig_category":"Industrial: Metal: Scrap Metal Dealers",
    "sg:phone":"+64 9-266 7026",
    "sg:province":"Auckland",
    "wof:name":"Scrap Metal Recyclers",
    "wof:placetype":"venue"
},
  "geometry": {"coordinates":[174.90242,-37.028709],"type":"Point"}
}