{
  "type": "Feature",
  "properties": {
    "iso:country":"NZ",
    "sg:address":"75 Lees St ",
    "sg:city":"Invercargill",
    "sg:classifiers":[
        {
            "category":"Social Services",
            "subcategory":"Child Care",
            "type":"Services"
        }
    ],
    "sg:phone":"+64 3-218 6680",
    "sg:province":"Southland",
    "sg:tags":[
        "home",
        "garden",
        "children"
    ],
    "wof:name":"Southland Kindergarten Association",
    "wof:placetype":"venue"
},
  "geometry": {"coordinates":[168.36003099999999,-46.390991],"type":"Point"}
}