{
  "type": "Feature",
  "properties": {
    "iso:country":"NZ",
    "sg:address":"62 Airport Dve Bell Block RD 3 New ",
    "sg:city":"Plymouth",
    "sg:classifiers":[
        {
            "category":"Utilities",
            "type":"Services"
        }
    ],
    "sg:phone":"+64 6-755 0696",
    "sg:province":"Taranaki",
    "sg:tags":[
        "industrial",
        "energy",
        "utilities",
        "coal",
        "wood",
        "coke"
    ],
    "wof:name":"Heartlands Environmental Buildings",
    "wof:placetype":"venue"
},
  "geometry": {"coordinates":[174.074005,-39.058292],"type":"Point"}
}