{
  "type": "Feature",
  "properties": {
    "addr:full":"271 Queen St  Richmond Nelson",
    "addr:housenumber":"271",
    "addr:street":"Queen St",
    "iso:country":"NZ",
    "sg:address":"271 Queen St ",
    "sg:city":"Richmond",
    "sg:classifiers":[
        {
            "category":"Food & Beverages",
            "subcategory":"Liquor & Beverages",
            "type":"Retail Goods"
        }
    ],
    "sg:phone":"+64 3-544 6380",
    "sg:province":"Nelson",
    "sg:tags":[
        "drink",
        "outlet"
    ],
    "wof:name":"The Liquor Shoppe",
    "wof:placetype":"venue"
},
  "geometry": {"coordinates":[-77.36608099999999,37.528542],"type":"Point"}
}