{
  "type": "Feature",
  "properties": {
    "iso:country":"NZ",
    "sg:address":"7-9 Farnham St ",
    "sg:city":"Parnell",
    "sg:orig_category":"Industrial: Services: Platemakers Film/Print",
    "sg:phone":"+64 9-309 9692",
    "sg:province":"Auckland",
    "wof:name":"Focus Group",
    "wof:placetype":"venue"
},
  "geometry": {"coordinates":[-92.004288,41.583519],"type":"Point"}
}