{
  "type": "Feature",
  "properties": {
    "iso:country":"NZ",
    "sg:address":"1066 Great South Rd Otahuhu ",
    "sg:city":"Auckland",
    "sg:orig_category":"Industrial: Electrical/Electronic",
    "sg:phone":"+64 9-276 9050",
    "sg:province":"Auckland",
    "wof:name":"WEG Electric Motors",
    "wof:placetype":"venue"
},
  "geometry": {"coordinates":[174.849197,-36.954819],"type":"Point"}
}