{
  "type": "Feature",
  "properties": {
    "addr:full":"247 Symonds St Auckland Central  Auckland Auckland",
    "addr:housenumber":"247",
    "addr:street":"Symonds St",
    "iso:country":"NZ",
    "sg:address":"247 Symonds St Auckland Central ",
    "sg:city":"Auckland",
    "sg:classifiers":[
        {
            "category":"Personal",
            "subcategory":"Adult",
            "type":"Services"
        }
    ],
    "sg:phone":"+64 9-302 4111",
    "sg:province":"Auckland",
    "sg:tags":[
        "sport",
        "leisure"
    ],
    "wof:name":"Toms Peeps",
    "wof:placetype":"venue"
},
  "geometry": {"coordinates":[174.764771,-36.857189],"type":"Point"}
}