{
  "type": "Feature",
  "properties": {
    "addr:full":"178 Gt South Rd Papakura  Auckland Auckland",
    "addr:housenumber":"178",
    "addr:street":"Gt South Rd",
    "iso:country":"NZ",
    "sg:address":"178 Gt South Rd Papakura ",
    "sg:city":"Auckland",
    "sg:orig_category":"Shopping: Retail Stores: Department Stores",
    "sg:phone":"+64 9-298 6659",
    "sg:province":"Auckland",
    "wof:name":"Two Buck Bargains",
    "wof:placetype":"venue"
},
  "geometry": {"coordinates":[174.94276400000001,-37.063046],"type":"Point"}
}