{
  "type": "Feature",
  "properties": {
    "iso:country":"NZ",
    "sg:address":"178 Gt South Rd Papakura ",
    "sg:city":"Auckland",
    "sg:orig_category":"Shopping: Retail Stores: Department Stores",
    "sg:phone":"+64 9-298 6659",
    "sg:province":"Auckland",
    "wof:name":"Two Buck Bargains",
    "wof:placetype":"venue"
},
  "geometry": {"coordinates":[174.942764,-37.063046],"type":"Point"}
}