{
  "type": "Feature",
  "properties": {
    "addr:full":"Quay Centre Taupo Qy  Wanganui Manawatu-Wanganui",
    "addr:street":"Qy",
    "iso:country":"NZ",
    "sg:address":"Quay Centre Taupo Qy ",
    "sg:city":"Wanganui",
    "sg:orig_category":"Health And Beauty: Products: Pharmacies",
    "sg:phone":"+64 6-345 7551",
    "sg:province":"Manawatu-Wanganui",
    "wof:name":"Hawkins Pharmacy",
    "wof:placetype":"venue"
},
  "geometry": {"coordinates":[175.052841,-39.933369],"type":"Point"}
}