{
  "type": "Feature",
  "properties": {
    "addr:full":"41 Porowini Ave  Whangarei Northland",
    "addr:housenumber":"41",
    "addr:street":"Porowini Ave",
    "iso:country":"NZ",
    "sg:address":"41 Porowini Ave ",
    "sg:city":"Whangarei",
    "sg:classifiers":[
        {
            "category":"Arena",
            "subcategory":"Sports Club",
            "type":"Entertainment"
        }
    ],
    "sg:phone":"+64 9-438 9675",
    "sg:province":"Northland",
    "sg:tags":[
        "-",
        "leisure",
        "sports"
    ],
    "wof:name":"Badminton Assoc Headquarters (Northland)",
    "wof:placetype":"venue"
},
  "geometry": {"coordinates":[174.32122799999999,-35.731758],"type":"Point"}
}