{
  "type": "Feature",
  "properties": {
    "addr:full":"195 Maungatapu Rd  Tauranga Bay of Plenty",
    "addr:housenumber":"195",
    "addr:street":"Maungatapu Rd",
    "iso:country":"NZ",
    "sg:address":"195 Maungatapu Rd ",
    "sg:city":"Tauranga",
    "sg:orig_category":"Home And Garden: Accessories: Hardware",
    "sg:phone":"+64 7-544 0776",
    "sg:province":"Bay of Plenty",
    "wof:name":"Small Pac Distributors Ltd",
    "wof:placetype":"venue"
},
  "geometry": {"coordinates":[176.17524700000001,-37.720585],"type":"Point"}
}