{
  "type": "Feature",
  "properties": {
    "iso:country":"NZ",
    "sg:address":"Waimauku ",
    "sg:city":"Auckland",
    "sg:orig_category":"Transport: Boats And Marine: Boats: Boat Maintenance",
    "sg:phone":"+64 9-411 9931",
    "sg:province":"Auckland",
    "wof:name":"Wouter Ten Broek",
    "wof:placetype":"venue"
},
  "geometry": {"coordinates":[174.49212600000001,-36.76432],"type":"Point"}
}