{
  "type": "Feature",
  "properties": {
    "addr:full":"17 Murdoch St  Dargaville Northland",
    "addr:housenumber":"17",
    "addr:street":"Murdoch St",
    "iso:country":"NZ",
    "sg:address":"17 Murdoch St ",
    "sg:city":"Dargaville",
    "sg:classifiers":[
        {
            "category":"Arts & Performance",
            "subcategory":"Art Gallery",
            "type":"Entertainment"
        }
    ],
    "sg:phone":"+64 9-439 0255",
    "sg:province":"Northland",
    "sg:tags":[
        "arts",
        "sport",
        "leisure"
    ],
    "wof:name":"Big River Art Gallery",
    "wof:placetype":"venue"
},
  "geometry": {"coordinates":[173.8638,-35.951103],"type":"Point"}
}