{
  "type": "Feature",
  "properties": {
    "addr:full":"Merivale  Christchurch Canterbury",
    "iso:country":"NZ",
    "sg:address":"Merivale ",
    "sg:city":"Christchurch",
    "sg:orig_category":"Clothing And Fabric: Clothing: Children'S Wear",
    "sg:phone":"+64 3-341 5991",
    "sg:province":"Canterbury",
    "wof:name":"Wee Things",
    "wof:placetype":"venue"
},
  "geometry": {"coordinates":[172.620758,-43.514442],"type":"Point"}
}