{
  "type": "Feature",
  "properties": {
    "iso:country":"NZ",
    "sg:address":"Centennial Mall Broadway ",
    "sg:city":"Marton",
    "sg:classifiers":[
        {
            "category":"Food & Beverages",
            "subcategory":"Liquor & Beverages",
            "type":"Retail Goods"
        }
    ],
    "sg:phone":"+64 6-327 8025",
    "sg:province":"Manawatu-Wanganui",
    "sg:tags":[
        "drink",
        "outlet"
    ],
    "wof:name":"Max Liquor",
    "wof:placetype":"venue"
},
  "geometry": {"coordinates":[-3.01544,53.799294],"type":"Point"}
}