{
  "type": "Feature",
  "properties": {
    "iso:country":"NZ",
    "sg:address":"2 MacMurray Rd ",
    "sg:city":"Paihia",
    "sg:orig_category":"Shopping: Sports Retailers: Sports Goods: Sporting Goods",
    "sg:phone":"+64 9-402 6236",
    "sg:province":"Northland",
    "wof:name":"Airtorn Kite Boarding",
    "wof:placetype":"venue"
},
  "geometry": {"coordinates":[174.095566,-35.286957],"type":"Point"}
}