{
  "type": "Feature",
  "properties": {
    "addr:full":"725 Tremaine Ave Palmerston  Palmerston North Manawatu-Wanganui",
    "addr:housenumber":"725",
    "addr:street":"Tremaine Ave",
    "iso:country":"NZ",
    "sg:address":"725 Tremaine Ave Palmerston ",
    "sg:city":"Palmerston North",
    "sg:classifiers":[
        {
            "category":"Home & Garden",
            "subcategory":"Building Materials",
            "type":"Retail Goods"
        }
    ],
    "sg:phone":"+64 6-356 7065",
    "sg:province":"Manawatu-Wanganui",
    "sg:tags":[
        "design",
        "fitting",
        "fittings",
        "kitchen"
    ],
    "wof:name":"Scott Panel & Hardware",
    "wof:placetype":"venue"
},
  "geometry": {"coordinates":[175.61525,-40.337097],"type":"Point"}
}