{
  "type": "Feature",
  "properties": {
    "addr:full":"1135 Arawa Street G, 4th Floor, Zen Building, Rotorua RO3201 Manawatu-Wanganui",
    "addr:housenumber":"1135;4th floor",
    "addr:postcode":"ro3201",
    "addr:street":"Arawa Street G",
    "iso:country":"NZ",
    "sg:address":"1135 Arawa Street G, 4th Floor, Zen Building, Rotorua",
    "sg:city":"RO3201",
    "sg:classifiers":[
        {
            "category":"Travel",
            "subcategory":"Travel Agent",
            "type":"Entertainment"
        }
    ],
    "sg:phone":"+64 6473502000",
    "sg:province":"Manawatu-Wanganui",
    "sg:website":"www.white-heron.com",
    "wof:name":"White Heron Travel Services Ltd",
    "wof:placetype":"venue"
},
  "geometry": {"coordinates":[176.24499499999999,-38.1418],"type":"Point"}
}