{
  "type": "Feature",
  "properties": {
    "iso:country":"NZ",
    "sg:address":"9 A Mahunga Dve Mangere ",
    "sg:city":"Auckland",
    "sg:orig_category":"Transport: Transportation: Air Freight",
    "sg:phone":"+64 9-634 3977",
    "sg:province":"Auckland",
    "sg:website":"http://www.yellowpages.co.nz/pages/108086817/dp43544.html",
    "wof:name":"New Zealand Van Lines Ltd",
    "wof:placetype":"venue"
},
  "geometry": {"coordinates":[174.794235,-36.943462],"type":"Point"}
}