{
  "type": "Feature",
  "properties": {
    "addr:full":"705 Tremaine Ave Palmerston  Palmerston North Manawatu-Wanganui",
    "addr:housenumber":"705",
    "addr:street":"Tremaine Ave",
    "iso:country":"NZ",
    "sg:address":"705 Tremaine Ave Palmerston ",
    "sg:city":"Palmerston North",
    "sg:orig_category":"Automotive: Accessories: Towbars",
    "sg:phone":"+64 6-353 6027",
    "sg:province":"Manawatu-Wanganui",
    "wof:name":"Fully Equipped",
    "wof:placetype":"venue"
},
  "geometry": {"coordinates":[175.61360199999999,-40.33783],"type":"Point"}
}