{
  "type": "Feature",
  "properties": {
    "addr:full":"Waihi Tce  Geraldine",
    "addr:street":"Tce",
    "iso:country":"NZ",
    "sg:address":"Waihi Tce ",
    "sg:city":"Geraldine",
    "sg:orig_category":"Automotive: General Services: Service Stations",
    "sg:phone":"+64 3-693 1300",
    "wof:name":"Shell Geraldine",
    "wof:placetype":"venue"
},
  "geometry": {"coordinates":[171.245926,-44.085011],"type":"Point"}
}