{
  "type": "Feature",
  "properties": {
    "iso:country":"NZ",
    "sg:address":"2 Bracken St ",
    "sg:city":"Cambridge",
    "sg:classifiers":[
        {
            "category":"Farming",
            "subcategory":"Fish & Marine Products",
            "type":"Manufacturing & Wholesale Goods"
        }
    ],
    "sg:phone":"+64 7-823 0374",
    "sg:province":"Waikato",
    "sg:tags":[
        "boats",
        "yacht",
        "transport",
        "boat",
        "supply"
    ],
    "wof:name":"Grouse Boat Valet & Bait",
    "wof:placetype":"venue"
},
  "geometry": {"coordinates":[-116.676048,44.572186],"type":"Point"}
}