{
  "type": "Feature",
  "properties": {
    "iso:country":"NZ",
    "sg:address":"52 Hickory Pl ",
    "sg:city":"Christchurch",
    "sg:orig_category":"Industrial: Manufacturing: Tank Manufacturers",
    "sg:phone":"+64 800 861 333",
    "sg:province":"Canterbury",
    "wof:name":"Bailey Tanks Ltd",
    "wof:placetype":"venue"
},
  "geometry": {"coordinates":[-76.537834,37.605659],"type":"Point"}
}