{
  "type": "Feature",
  "properties": {
    "addr:full":"141 Grace St  Invercargill Southland",
    "addr:housenumber":"141",
    "addr:street":"Grace St",
    "iso:country":"NZ",
    "sg:address":"141 Grace St ",
    "sg:city":"Invercargill",
    "sg:orig_category":"Shopping: Retail Stores: Secondhand Dealers",
    "sg:phone":"+64 3-218 3690",
    "sg:province":"Southland",
    "wof:name":"Second Time Round",
    "wof:placetype":"venue"
},
  "geometry": {"coordinates":[168.361099,-46.427155],"type":"Point"}
}