{
  "type": "Feature",
  "properties": {
    "addr:full":"82 Eastern Hutt Rd Wingate Lower  Hutt Wellington",
    "addr:housenumber":"82",
    "addr:street":"Eastern Hutt Rd Wingate",
    "iso:country":"NZ",
    "sg:address":"82 Eastern Hutt Rd Wingate Lower ",
    "sg:city":"Hutt",
    "sg:classifiers":[
        {
            "category":"Retail",
            "subcategory":"Auto Repair",
            "type":"Services"
        }
    ],
    "sg:phone":"+64 4-577 2438",
    "sg:province":"Wellington",
    "sg:tags":[
        "automotive",
        "restoration",
        "servicing",
        "car"
    ],
    "wof:name":"Earl's Body Shop",
    "wof:placetype":"venue"
},
  "geometry": {"coordinates":[174.95452900000001,-41.189522],"type":"Point"}
}