{
  "type": "Feature",
  "properties": {
    "addr:full":"1 Miro St  Taupo Waikato",
    "addr:housenumber":"1",
    "addr:street":"Miro St",
    "iso:country":"NZ",
    "sg:address":"1 Miro St ",
    "sg:city":"Taupo",
    "sg:orig_category":"Industrial: Engineering: Engineers: Engineers - General",
    "sg:phone":"+64 7-378 4158",
    "sg:province":"Waikato",
    "wof:name":"Lake Forest Engineering",
    "wof:placetype":"venue"
},
  "geometry": {"coordinates":[176.10299699999999,-38.691769],"type":"Point"}
}