{
  "type": "Feature",
  "properties": {
    "iso:country":"NZ",
    "sg:address":"23 Patrick St Onehunga ",
    "sg:city":"Auckland",
    "sg:classifiers":[
        {
            "category":"Home & Garden",
            "subcategory":"Furniture",
            "type":"Retail Goods"
        }
    ],
    "sg:phone":"+64 9-636 7621",
    "sg:province":"Auckland",
    "sg:tags":[
        "furniture/furnishings",
        "repair",
        "finishing"
    ],
    "wof:name":"Supreme Finishers",
    "wof:placetype":"venue"
},
  "geometry": {"coordinates":[174.783661,-36.909973],"type":"Point"}
}