{
  "type": "Feature",
  "properties": {
    "iso:country":"NZ",
    "sg:address":"Industrial La ",
    "sg:city":"Queenstown",
    "sg:orig_category":"Transport: Transportation: Courier Services",
    "sg:phone":"+64 3-442 6869",
    "sg:province":"Otago",
    "wof:name":"Fastway Couriers Queenstown",
    "wof:placetype":"venue"
},
  "geometry": {"coordinates":[-76.157791,38.990379],"type":"Point"}
}