{
  "type": "Feature",
  "properties": {
    "iso:country":"NZ",
    "sg:address":"434 Queen St ",
    "sg:city":"Masterton",
    "sg:classifiers":[
        {
            "category":"Bars & Pubs",
            "subcategory":"Wine Bar",
            "type":"Food & Drink"
        }
    ],
    "sg:phone":"+64 6-378 8660",
    "sg:province":"Wellington",
    "sg:tags":[
        "wining",
        "dining",
        "cafe"
    ],
    "wof:name":"A J's Coffee House",
    "wof:placetype":"venue"
},
  "geometry": {"coordinates":[175.64883399999999,-40.957767],"type":"Point"}
}