{
  "type": "Feature",
  "properties": {
    "iso:country":"NZ",
    "sg:address":"188 Cameron Rd ",
    "sg:city":"Tauranga",
    "sg:classifiers":[
        {
            "category":"Communications",
            "subcategory":"Film & Video Production",
            "type":"Services"
        }
    ],
    "sg:phone":"+64 7-578 0806",
    "sg:province":"Bay of Plenty",
    "sg:tags":[
        "sport",
        "leisure",
        "library",
        "entertainment"
    ],
    "sg:website":"http://www.aristocratadult.co.nz",
    "wof:name":"Aristocrat Adult Shop",
    "wof:placetype":"venue"
},
  "geometry": {"coordinates":[176.165863,-37.685787],"type":"Point"}
}