{
  "type": "Feature",
  "properties": {
    "addr:full":"42 Tay St  Invercargill Southland",
    "addr:housenumber":"42",
    "addr:street":"Tay St",
    "iso:country":"NZ",
    "sg:address":"42 Tay St ",
    "sg:city":"Invercargill",
    "sg:orig_category":"Shopping: Retail Stores: Department Stores",
    "sg:phone":"+64 3-211 1140",
    "sg:province":"Southland",
    "wof:name":"Farmers Trading Co Ltd",
    "wof:placetype":"venue"
},
  "geometry": {"coordinates":[168.380325,-46.40926],"type":"Point"}
}