{
  "type": "Feature",
  "properties": {
    "iso:country":"NZ",
    "sg:address":"494 Brighton Rd Westwood ",
    "sg:city":"Dunedin",
    "sg:classifiers":[
        {
            "category":"Shopping",
            "subcategory":"Pets & Pet Supplies",
            "type":"Retail Goods"
        }
    ],
    "sg:phone":"+64 3-481 1330",
    "sg:province":"Otago",
    "sg:tags":[
        "boarding",
        "garden",
        "pets",
        "catteries",
        "home",
        "kennel"
    ],
    "wof:name":"Allandale Park Boarding Kennels & Cattery",
    "wof:placetype":"venue"
},
  "geometry": {"coordinates":[170.381195,-45.931664],"type":"Point"}
}