{
  "type": "Feature",
  "properties": {
    "addr:full":"Rangiuru Te  Puke Bay of Plenty",
    "addr:street":"Rangiuru",
    "iso:country":"NZ",
    "sg:address":"Rangiuru Te ",
    "sg:city":"Puke",
    "sg:classifiers":[
        {
            "category":"Manufacturing",
            "subcategory":"Food",
            "type":"Manufacturing & Wholesale Goods"
        }
    ],
    "sg:phone":"+64 7-573 0034",
    "sg:province":"Bay of Plenty",
    "sg:tags":[
        "processing",
        "drink"
    ],
    "wof:name":"AFFCO NZ Ltd",
    "wof:placetype":"venue"
},
  "geometry": {"coordinates":[176.32008400000001,-37.786819],"type":"Point"}
}