{
  "type": "Feature",
  "properties": {
    "addr:full":"Overseas Terminal Chaffers Marina  Wellington Wellington",
    "iso:country":"NZ",
    "sg:address":"Overseas Terminal Chaffers Marina ",
    "sg:city":"Wellington",
    "sg:orig_category":"Shopping: Sports Retailers: Sports Goods: Canvas Goods",
    "sg:phone":"+64 4-384 8447",
    "sg:province":"Wellington",
    "wof:name":"Linton Sails Ltd",
    "wof:placetype":"venue"
},
  "geometry": {"coordinates":[-85.910454,33.827946],"type":"Point"}
}