{
  "type": "Feature",
  "properties": {
    "iso:country":"NZ",
    "sg:address":"PO Box 4500 Palmerston ",
    "sg:city":"Palmerston North",
    "sg:classifiers":[
        {
            "category":"Health Services",
            "subcategory":"Doctor",
            "type":"Services"
        }
    ],
    "sg:phone":"+64 6-355 4998",
    "sg:province":"Manawatu-Wanganui",
    "sg:tags":[
        "beauty"
    ],
    "sg:website":"http://www.magnoheal.co.nz",
    "wof:name":"Magnoheal NZ",
    "wof:placetype":"venue"
},
  "geometry": {"coordinates":[175.611481,-40.357418],"type":"Point"}
}