{
  "type": "Feature",
  "properties": {
    "addr:full":"Pyes Pa  Tauranga Bay of Plenty",
    "addr:postcode":"pyes",
    "iso:country":"NZ",
    "sg:address":"Pyes Pa ",
    "sg:city":"Tauranga",
    "sg:classifiers":[
        {
            "category":"Home & Garden",
            "subcategory":"Building Materials",
            "type":"Retail Goods"
        }
    ],
    "sg:phone":"+64 7-543 3317",
    "sg:province":"Bay of Plenty",
    "sg:tags":[
        "gate",
        "fitting",
        "outdoor"
    ],
    "wof:name":"Lifestyle Signs & Gates",
    "wof:placetype":"venue"
},
  "geometry": {"coordinates":[176.12835699999999,-37.822392],"type":"Point"}
}