{
  "type": "Feature",
  "properties": {
    "addr:full":"280 Cumberland St  Dunedin Otago",
    "addr:housenumber":"280",
    "addr:street":"Cumberland St",
    "iso:country":"NZ",
    "sg:address":"280 Cumberland St ",
    "sg:city":"Dunedin",
    "sg:classifiers":[
        {
            "category":"Food & Beverages",
            "subcategory":"Candy",
            "type":"Retail Goods"
        }
    ],
    "sg:phone":"+64 3-467 7800",
    "sg:province":"Otago",
    "sg:tags":[
        "confectioner",
        "drink",
        "-"
    ],
    "sg:website":"http://www.Cadbury.co.nz",
    "wof:name":"Cadbury Confectionery Ltd",
    "wof:placetype":"venue"
},
  "geometry": {"coordinates":[-82.742638,28.02434],"type":"Point"}
}