{
  "type": "Feature",
  "properties": {
    "addr:full":"12 SouthPark Pl Penrose  Auckland Auckland",
    "addr:housenumber":"12",
    "addr:street":"Southpark Pl",
    "iso:country":"NZ",
    "sg:address":"12 SouthPark Pl Penrose ",
    "sg:city":"Auckland",
    "sg:orig_category":"Clothing And Fabric: Clothing: Jeans",
    "sg:phone":"+64 9-526 2740",
    "sg:province":"Auckland",
    "wof:name":"Just Jeans",
    "wof:placetype":"venue"
},
  "geometry": {"coordinates":[174.82122799999999,-36.925354],"type":"Point"}
}