{
  "type": "Feature",
  "properties": {
    "iso:country":"NZ",
    "sg:address":"24 Wharf St ",
    "sg:city":"Tauranga",
    "sg:classifiers":[
        {
            "category":"Arts & Performance",
            "subcategory":"Art Gallery",
            "type":"Entertainment"
        }
    ],
    "sg:phone":"+64 7-578 5028",
    "sg:province":"Bay of Plenty",
    "sg:tags":[
        "arts",
        "sport",
        "leisure"
    ],
    "wof:name":"Pyromania",
    "wof:placetype":"venue"
},
  "geometry": {"coordinates":[176.169281,-37.683525],"type":"Point"}
}