{
  "type": "Feature",
  "properties": {
    "iso:country":"NZ",
    "sg:address":"PO Box 10-017 ",
    "sg:city":"Wellington",
    "sg:classifiers":[
        {
            "category":"Organizations",
            "subcategory":"Labor Organization",
            "type":"Services"
        }
    ],
    "sg:phone":"+64 4-916 1205",
    "sg:province":"Wellington",
    "sg:tags":[
        "travel",
        "tourism"
    ],
    "sg:website":"http://www.WellingtonNZ.com",
    "wof:name":"Totally Wellington Tourism",
    "wof:placetype":"venue"
},
  "geometry": {"coordinates":[-87.692841,40.560177],"type":"Point"}
}