{
  "type": "Feature",
  "properties": {
    "iso:country":"NZ",
    "sg:address":"23 Minnie St Eden ",
    "sg:city":"Terrace",
    "sg:classifiers":[
        {
            "category":"Banks & Credit Unions",
            "subcategory":"Investment Brokerage",
            "type":"Services"
        }
    ],
    "sg:phone":"+64 21 944 985",
    "sg:tags":[
        "television",
        "production",
        "broadcasting"
    ],
    "wof:name":"Legge Work Ltd",
    "wof:placetype":"venue"
},
  "geometry": {"coordinates":[174.75462300000001,-36.867321],"type":"Point"}
}