{
  "type": "Feature",
  "properties": {
    "iso:country":"NZ",
    "sg:address":"32 Birkenhead Ave Birkenhead ",
    "sg:city":"Auckland",
    "sg:classifiers":[
        {
            "category":"Bars & Pubs",
            "subcategory":"Lounge",
            "type":"Food & Drink"
        }
    ],
    "sg:phone":"+64 9-418 0188",
    "sg:province":"Auckland",
    "sg:tags":[
        "baker",
        "-"
    ],
    "wof:name":"The Phnon Phen Bakery",
    "wof:placetype":"venue"
},
  "geometry": {"coordinates":[174.72560100000001,-36.810749],"type":"Point"}
}