{
  "type": "Feature",
  "properties": {
    "iso:country":"NZ",
    "sg:address":"Founders Park 87 Atawhai Dve ",
    "sg:city":"Nelson",
    "sg:classifiers":[
        {
            "category":"Brewery",
            "type":"Food & Drink"
        }
    ],
    "sg:phone":"+64 3-548 4638",
    "sg:province":"Nelson",
    "sg:tags":[
        "brewer"
    ],
    "wof:name":"Founders Brewery & Cafe",
    "wof:placetype":"venue"
},
  "geometry": {"coordinates":[-87.814133,41.74321],"type":"Point"}
}