{
  "type": "Feature",
  "properties": {
    "addr:full":"PO Box 9024 Greerton  Tauranga Bay of Plenty",
    "addr:housenumber":"po",
    "addr:street":"Box 9024",
    "iso:country":"NZ",
    "sg:address":"PO Box 9024 Greerton ",
    "sg:city":"Tauranga",
    "sg:classifiers":[
        {
            "category":"Utilities",
            "subcategory":"Water",
            "type":"Services"
        }
    ],
    "sg:phone":"+64 7-543 3411",
    "sg:province":"Bay of Plenty",
    "sg:tags":[
        "storage"
    ],
    "wof:name":"Bay Reservoirs",
    "wof:placetype":"venue"
},
  "geometry": {"coordinates":[176.12973,-37.729122],"type":"Point"}
}