{
  "type": "Feature",
  "properties": {
    "addr:full":"Ihumatao Rd Mangere  Auckland Auckland",
    "addr:street":"Ihumatao Rd",
    "iso:country":"NZ",
    "sg:address":"Ihumatao Rd Mangere ",
    "sg:city":"Auckland",
    "sg:classifiers":[
        {
            "category":"Manufacturing",
            "subcategory":"Glass & Minerals",
            "type":"Manufacturing & Wholesale Goods"
        }
    ],
    "sg:phone":"+64 9-275 7966",
    "sg:province":"Auckland",
    "sg:tags":[
        "raw",
        "industrial",
        "quarry",
        "materials"
    ],
    "wof:name":"Ihumatao Quarries Ltd",
    "wof:placetype":"venue"
},
  "geometry": {"coordinates":[174.75836200000001,-36.992409],"type":"Point"}
}