{
  "type": "Feature",
  "properties": {
    "iso:country":"NZ",
    "sg:address":"646 Te Ngae Rd ",
    "sg:city":"Rotorua",
    "sg:classifiers":[
        {
            "category":"Restaurant",
            "type":"Food & Drink"
        }
    ],
    "sg:phone":"+64 7-345 4526",
    "sg:province":"Bay of Plenty",
    "sg:tags":[
        "merchant",
        "fish",
        "sea"
    ],
    "wof:name":"Oyster World",
    "wof:placetype":"venue"
},
  "geometry": {"coordinates":[176.258224,-38.145161],"type":"Point"}
}