{
  "type": "Feature",
  "properties": {
    "addr:full":"Mirrielees Road, Sulphur Point  Tauranga Bay of Plenty",
    "addr:street":"Mirrielees Road",
    "iso:country":"NZ",
    "sg:address":"Mirrielees Road, Sulphur Point ",
    "sg:city":"Tauranga",
    "sg:classifiers":[
        {
            "category":"Shopping",
            "subcategory":"Discount & Variety Stores",
            "type":"Retail Goods"
        }
    ],
    "sg:phone":"+64 7-571 0043",
    "sg:province":"Bay of Plenty",
    "sg:tags":[
        "storage",
        "cool"
    ],
    "wof:name":"P&O Cold Logistics (NZ) Ltd",
    "wof:placetype":"venue"
},
  "geometry": {"coordinates":[176.169556,-37.669209],"type":"Point"}
}