{
  "type": "Feature",
  "properties": {
    "iso:country":"NZ",
    "sg:address":"83 Devonport Rd ",
    "sg:city":"Tauranga",
    "sg:orig_category":"Shopping: Accessories: Sunglasses",
    "sg:phone":"+64 7-571 8909",
    "sg:province":"Auckland",
    "wof:name":"Sunglass Store The",
    "wof:placetype":"venue"
},
  "geometry": {"coordinates":[176.16922,-37.686138],"type":"Point"}
}