{
  "type": "Feature",
  "properties": {
    "addr:full":"Awamate Rd RD3  Wairoa",
    "addr:street":"Awamate Rd Rd3",
    "iso:country":"NZ",
    "sg:address":"Awamate Rd RD3 ",
    "sg:city":"Wairoa",
    "sg:classifiers":[
        {
            "category":"Wholesale",
            "subcategory":"Meat",
            "type":"Manufacturing & Wholesale Goods"
        }
    ],
    "sg:phone":"+64 6-838 8553",
    "sg:tags":[
        "food",
        "drink",
        "meats",
        "slaughtering"
    ],
    "wof:name":"Venex Ltd",
    "wof:placetype":"venue"
},
  "geometry": {"coordinates":[177.42704800000001,-39.038643],"type":"Point"}
}