{
  "type": "Feature",
  "properties": {
    "addr:full":"2/24 Honan Pl Avondale  Auckland Auckland",
    "addr:housenumber":"2 / 24",
    "addr:street":"Honan Pl",
    "iso:country":"NZ",
    "sg:address":"2/24 Honan Pl Avondale ",
    "sg:city":"Auckland",
    "sg:orig_category":"Industrial: Engineering: Engineers: Engineers - General",
    "sg:phone":"+64 9-817 4565",
    "sg:province":"Auckland",
    "wof:name":"Briarz Beauty Solutions",
    "wof:placetype":"venue"
},
  "geometry": {"coordinates":[174.690933,-36.8932],"type":"Point"}
}