{
  "type": "Feature",
  "properties": {
    "iso:country":"NZ",
    "sg:address":"12 Pembroke St Palmerston North PO Box ",
    "sg:city":"5257",
    "sg:orig_category":"Transport: Land: Taxis",
    "sg:phone":"+64 6-355 5059",
    "wof:name":"Taxis Gold & Black Ltd",
    "wof:placetype":"venue"
},
  "geometry": {"coordinates":[175.611481,-40.357422],"type":"Point"}
}