{
  "type": "Feature",
  "properties": {
    "iso:country":"NZ",
    "sg:address":"Christchurch ",
    "sg:city":"Christchurch",
    "sg:classifiers":[
        {
            "category":"Personal",
            "subcategory":"Beauty Salon",
            "type":"Services"
        }
    ],
    "sg:phone":"+64 21 444 057",
    "sg:province":"Canterbury",
    "sg:tags":[
        "artist",
        "health",
        "make-up"
    ],
    "wof:name":"Allsopp Tracey",
    "wof:placetype":"venue"
},
  "geometry": {"coordinates":[-1.77656,50.73407],"type":"Point"}
}