{
  "type": "Feature",
  "properties": {
    "addr:full":"3 Andrews Ave Lower  Hutt Wellington",
    "addr:housenumber":"3",
    "addr:street":"Andrews Ave",
    "iso:country":"NZ",
    "sg:address":"3 Andrews Ave Lower ",
    "sg:city":"Hutt",
    "sg:classifiers":[
        {
            "category":"Health Services",
            "subcategory":"Optometrist",
            "type":"Services"
        }
    ],
    "sg:phone":"+64 4-566 3940",
    "sg:province":"Wellington",
    "sg:tags":[
        "optical",
        "optician",
        "beauty"
    ],
    "wof:name":"Tubman Shannon OPTOMETRIST",
    "wof:placetype":"venue"
},
  "geometry": {"coordinates":[174.901489,-41.209946],"type":"Point"}
}