{
  "type": "Feature",
  "properties": {
    "iso:country":"NZ",
    "sg:address":"496 East Coast Rd Windsor Prk Mairangi Bay ",
    "sg:city":"Auckland",
    "sg:classifiers":[
        {
            "category":"Community Center",
            "subcategory":"Senior",
            "type":"Public Place"
        }
    ],
    "sg:phone":"+64 9-478 6352",
    "sg:province":"Auckland",
    "sg:tags":[
        "arrangements",
        "room",
        "reception",
        "wedding"
    ],
    "wof:name":"East Coast Bays Rugby Club Bar & Grill",
    "wof:placetype":"venue"
},
  "geometry": {"coordinates":[174.741089,-36.741703],"type":"Point"}
}