{
  "type": "Feature",
  "properties": {
    "addr:full":"2/65 Ellice Rd Glenfield  Auckland Auckland",
    "addr:housenumber":"2 / 65",
    "addr:street":"Ellice Rd",
    "iso:country":"NZ",
    "sg:address":"2/65 Ellice Rd Glenfield ",
    "sg:city":"Auckland",
    "sg:orig_category":"Industrial: Parts: Bolts And Nuts",
    "sg:phone":"+64 9-444 1894",
    "sg:province":"Auckland",
    "wof:name":"EDL Fasteners Ltd",
    "wof:placetype":"venue"
},
  "geometry": {"coordinates":[174.728622,-36.784813],"type":"Point"}
}