{
  "type": "Feature",
  "properties": {
    "iso:country":"NZ",
    "sg:address":"9/41 View Rd Glenfield ",
    "sg:city":"Auckland",
    "sg:classifiers":[
        {
            "category":"Shopping",
            "type":"Retail Goods"
        }
    ],
    "sg:phone":"+64 9-444 1431",
    "sg:province":"Auckland",
    "sg:website":"http://www.yellowpages.co.nz/for/adams/dp11680.html",
    "wof:name":"Adams Engineering 1996 Ltd",
    "wof:placetype":"venue"
},
  "geometry": {"coordinates":[174.734436,-36.771477],"type":"Point"}
}