{
  "type": "Feature",
  "properties": {
    "addr:full":"Shop G 16 277 Broadway Newmarket  Auckland Manawatu-Wanganui",
    "addr:housenumber":"16 277",
    "addr:street":"Shop G;Broadway",
    "iso:country":"NZ",
    "sg:address":"Shop G 16 277 Broadway Newmarket ",
    "sg:city":"Auckland",
    "sg:orig_category":"Transport: Distribution - General: Distributors",
    "sg:phone":"+64 9-522 7656",
    "sg:province":"Manawatu-Wanganui",
    "wof:name":"Polo Ralph Lauren",
    "wof:placetype":"venue"
},
  "geometry": {"coordinates":[174.77375799999999,-36.867878],"type":"Point"}
}