{
  "type": "Feature",
  "properties": {
    "iso:country":"NZ",
    "sg:address":"3 Glenburn Rd Nawton ",
    "sg:city":"Hamilton",
    "sg:classifiers":[
        {
            "category":"Health Services",
            "subcategory":"Clinic",
            "type":"Services"
        }
    ],
    "sg:phone":"+64 7-846 5656",
    "sg:province":"Waikato",
    "sg:tags":[
        "trainer",
        "personal",
        "beauty",
        "fitness"
    ],
    "wof:name":"Angela Watson",
    "wof:placetype":"venue"
},
  "geometry": {"coordinates":[175.230316,-37.779934],"type":"Point"}
}