{
  "type": "Feature",
  "properties": {
    "iso:country":"NZ",
    "sg:address":"20 Sylvia Park Rd Penrose ",
    "sg:city":"Auckland",
    "sg:classifiers":[
        {
            "category":"Manufacturing",
            "subcategory":"Tools & Machinery",
            "type":"Manufacturing & Wholesale Goods"
        }
    ],
    "sg:phone":"+64 9-573 1051",
    "sg:province":"Auckland",
    "sg:tags":[
        "equipment",
        "industrial",
        "hydraulic"
    ],
    "wof:name":"Hydraulic Cartridge Valves Ltd",
    "wof:placetype":"venue"
},
  "geometry": {"coordinates":[174.83595299999999,-36.923798],"type":"Point"}
}