{
  "type": "Feature",
  "properties": {
    "addr:full":"21-27 Udy St Petone Lower  Hutt Wellington",
    "addr:housenumber":"21-27",
    "addr:street":"Udy St",
    "iso:country":"NZ",
    "sg:address":"21-27 Udy St Petone Lower ",
    "sg:city":"Hutt",
    "sg:orig_category":"Industrial: Packaging: Paper And Cardboard",
    "sg:phone":"+64 4-568 3774",
    "sg:province":"Wellington",
    "wof:name":"CPI Papers",
    "wof:placetype":"venue"
},
  "geometry": {"coordinates":[174.88215600000001,-41.220833],"type":"Point"}
}