{
  "type": "Feature",
  "properties": {
    "iso:country":"NZ",
    "sg:address":"49 Cameron Rd Waituna West ",
    "sg:city":"Waiuku",
    "sg:classifiers":[
        {
            "category":"Farming",
            "subcategory":"Farm",
            "type":"Manufacturing & Wholesale Goods"
        }
    ],
    "sg:phone":"+64 9-235 8527",
    "sg:tags":[
        "-",
        "ostrich"
    ],
    "wof:name":"Overland Ostrich Products",
    "wof:placetype":"venue"
},
  "geometry": {"coordinates":[174.745132,-37.233814],"type":"Point"}
}