{
  "type": "Feature",
  "properties": {
    "iso:country":"NZ",
    "sg:address":"47 Birmingham Dve Middleton ",
    "sg:city":"Christchurch",
    "sg:classifiers":[
        {
            "category":"Restaurant",
            "type":"Food & Drink"
        }
    ],
    "sg:phone":"+64 3-339 3058",
    "sg:province":"Canterbury",
    "sg:tags":[
        "fishing",
        "sea"
    ],
    "wof:name":"Takaroa Industries Ltd",
    "wof:placetype":"venue"
},
  "geometry": {"coordinates":[172.584579,-43.543751],"type":"Point"}
}