{
  "type": "Feature",
  "properties": {
    "addr:full":"81 The Square Palmerston  Palmerston North Wellington",
    "addr:housenumber":"81",
    "addr:street":"The Square",
    "iso:country":"NZ",
    "sg:address":"81 The Square Palmerston ",
    "sg:city":"Palmerston North",
    "sg:classifiers":[
        {
            "category":"Health Services",
            "subcategory":"Clinic",
            "type":"Services"
        }
    ],
    "sg:phone":"+64 6-354 4155",
    "sg:province":"Wellington",
    "sg:tags":[
        "services",
        "therapy",
        "natural",
        "beauty"
    ],
    "wof:name":"Health 2000 Manawatu",
    "wof:placetype":"venue"
},
  "geometry": {"coordinates":[175.611481,-40.357418],"type":"Point"}
}