{
  "type": "Feature",
  "properties": {
    "iso:country":"NZ",
    "sg:address":"59 Guinness St ",
    "sg:city":"Greymouth",
    "sg:classifiers":[
        {
            "category":"Manufacturing",
            "subcategory":"Tools & Machinery",
            "type":"Manufacturing & Wholesale Goods"
        }
    ],
    "sg:phone":"+64 3-768 6546",
    "sg:province":"West Coast",
    "sg:tags":[
        "equipment",
        "industrial",
        "hydraulic"
    ],
    "wof:name":"Westland Hydraulics Ltd",
    "wof:placetype":"venue"
},
  "geometry": {"coordinates":[171.20765700000001,-42.449722],"type":"Point"}
}