{
  "type": "Feature",
  "properties": {
    "addr:full":"204 Stafford St  Timaru Canterbury",
    "addr:housenumber":"204",
    "addr:street":"Stafford St",
    "iso:country":"NZ",
    "sg:address":"204 Stafford St ",
    "sg:city":"Timaru",
    "sg:orig_category":"Clothing And Fabric: Clothing: Women'S Fashions",
    "sg:phone":"+64 3-684 4204",
    "sg:province":"Canterbury",
    "wof:name":"Miss Timaru Fashion",
    "wof:placetype":"venue"
},
  "geometry": {"coordinates":[171.25309799999999,-44.396076],"type":"Point"}
}