{
  "type": "Feature",
  "properties": {
    "addr:full":"58 Wickham St Bromley  Christchurch Canterbury",
    "addr:housenumber":"58",
    "addr:street":"Wickham St;Christchurch",
    "iso:country":"NZ",
    "sg:address":"58 Wickham St Bromley ",
    "sg:city":"Christchurch",
    "sg:classifiers":[
        {
            "category":"Manufacturing",
            "subcategory":"Glass & Minerals",
            "type":"Manufacturing & Wholesale Goods"
        }
    ],
    "sg:phone":"+64 3-384 4959",
    "sg:province":"Canterbury",
    "sg:tags":[
        "chemical",
        "fibre",
        "industrial",
        "compounds"
    ],
    "wof:name":"Glass Repros Fibreglass",
    "wof:placetype":"venue"
},
  "geometry": {"coordinates":[172.696945,-43.536835],"type":"Point"}
}