{
  "type": "Feature",
  "properties": {
    "iso:country":"NZ",
    "sg:address":"1/13 Chilman St New ",
    "sg:city":"Plymouth",
    "sg:classifiers":[
        {
            "category":"Personal",
            "subcategory":"Tanning Parlor",
            "type":"Services"
        }
    ],
    "sg:phone":"+64 6-758 1888",
    "sg:province":"Taranaki",
    "sg:tags":[
        "sun",
        "health",
        "beauty"
    ],
    "wof:name":"Chique Skin Therapy Clinic",
    "wof:placetype":"venue"
},
  "geometry": {"coordinates":[-116.819725,43.97221],"type":"Point"}
}