{
  "type": "Feature",
  "properties": {
    "iso:country":"NZ",
    "sg:address":"Barnes Kirk Building Cnr Eastbourne & Market Sts",
    "sg:city":"Hastings",
    "sg:classifiers":[
        {
            "category":"Banks & Credit Unions",
            "subcategory":"Investment Brokerage",
            "type":"Services"
        }
    ],
    "sg:phone":"+64 6-878 9015",
    "sg:province":"Wellington",
    "sg:tags":[
        "personal",
        "-",
        "finance"
    ],
    "wof:name":"AMP Hawkes Bay Financial Solutions Ltd",
    "wof:placetype":"venue"
},
  "geometry": {"coordinates":[-98.081558,46.684471],"type":"Point"}
}