{
  "type": "Feature",
  "properties": {
    "addr:full":"182 Ormond Rd Gisborne  Gisborne Gisborne",
    "addr:housenumber":"182",
    "addr:street":"Ormond Rd",
    "iso:country":"NZ",
    "sg:address":"182 Ormond Rd Gisborne ",
    "sg:city":"Gisborne",
    "sg:orig_category":"Health And Beauty: Specialists: Midwives",
    "sg:phone":"+64 6-868 8528",
    "sg:province":"Gisborne",
    "wof:name":"Choice Independent Midwifery Clinic",
    "wof:placetype":"venue"
},
  "geometry": {"coordinates":[178.016785,-38.663258],"type":"Point"}
}