{
  "type": "Feature",
  "properties": {
    "iso:country":"NZ",
    "sg:address":"21 Honeystone St Helensburgh ",
    "sg:city":"Dunedin",
    "sg:classifiers":[
        {
            "category":"Home & Garden",
            "subcategory":"Building Materials",
            "type":"Retail Goods"
        }
    ],
    "sg:phone":"+64 3-476 2284",
    "sg:province":"Otago",
    "sg:tags":[
        "brick",
        "outdoor",
        "paving"
    ],
    "wof:name":"Smarts Landscaping",
    "wof:placetype":"venue"
},
  "geometry": {"coordinates":[170.477554,-45.850674],"type":"Point"}
}