{
  "type": "Feature",
  "properties": {
    "addr:full":"22 Lewis St Gladstone  Invercargill Southland",
    "addr:housenumber":"22",
    "addr:street":"Lewis St",
    "iso:country":"NZ",
    "sg:address":"22 Lewis St Gladstone ",
    "sg:city":"Invercargill",
    "sg:classifiers":[
        {
            "category":"Social Services",
            "subcategory":"Child Care",
            "type":"Services"
        }
    ],
    "sg:phone":"+64 3-214 9303",
    "sg:province":"Southland",
    "sg:tags":[
        "home",
        "garden",
        "children"
    ],
    "wof:name":"Gladstone Pre School",
    "wof:placetype":"venue"
},
  "geometry": {"coordinates":[168.34878499999999,-46.393166],"type":"Point"}
}