{
  "type": "Feature",
  "properties": {
    "addr:full":"27 Heu Heu St  Taupo Waikato",
    "addr:housenumber":"27",
    "addr:street":"Heu Heu St",
    "iso:country":"NZ",
    "sg:address":"27 Heu Heu St ",
    "sg:city":"Taupo",
    "sg:orig_category":"Shopping: Retail Stores: Books",
    "sg:phone":"+64 7-378 5838",
    "sg:province":"Waikato",
    "wof:name":"Paper Plus",
    "wof:placetype":"venue"
},
  "geometry": {"coordinates":[176.07074,-38.687946],"type":"Point"}
}