{
  "type": "Feature",
  "properties": {
    "iso:country":"NZ",
    "sg:address":"16 Martin St ",
    "sg:city":"Timaru",
    "sg:orig_category":"Farming: Supplies: Farm Buildings",
    "sg:phone":"+64 3-688 2166",
    "sg:province":"Canterbury",
    "wof:name":"GoldPine",
    "wof:placetype":"venue"
},
  "geometry": {"coordinates":[171.233261,-44.350838],"type":"Point"}
}