{
  "type": "Feature",
  "properties": {
    "addr:full":"12 The Centre Waipu  Whangarei Northland",
    "addr:housenumber":"12",
    "addr:street":"The Centre",
    "iso:country":"NZ",
    "sg:address":"12 The Centre Waipu ",
    "sg:city":"Whangarei",
    "sg:classifiers":[
        {
            "category":"Bars & Pubs",
            "subcategory":"Lounge",
            "type":"Food & Drink"
        }
    ],
    "sg:phone":"+64 9-432 0852",
    "sg:province":"Northland",
    "sg:tags":[
        "baker",
        "-"
    ],
    "wof:name":"Waipu Bakery",
    "wof:placetype":"venue"
},
  "geometry": {"coordinates":[174.44288599999999,-35.986801],"type":"Point"}
}