{
  "type": "Feature",
  "properties": {
    "addr:full":"118 D Wattle Pl  Whangamata",
    "addr:housenumber":"118 d",
    "addr:street":"Wattle Pl",
    "iso:country":"NZ",
    "sg:address":"118 D Wattle Pl ",
    "sg:city":"Whangamata",
    "sg:classifiers":[
        {
            "category":"Manufacturing",
            "subcategory":"Textiles",
            "type":"Manufacturing & Wholesale Goods"
        }
    ],
    "sg:phone":"+64 7-865 6368",
    "sg:tags":[
        "clothing",
        "fabric",
        "manufacturer"
    ],
    "wof:name":"S M P Clothing",
    "wof:placetype":"venue"
},
  "geometry": {"coordinates":[175.86526499999999,-37.204063],"type":"Point"}
}