{
  "type": "Feature",
  "properties": {
    "iso:country":"NZ",
    "sg:address":"62 Rosewill Valley Rd R D 4 ",
    "sg:city":"Timaru",
    "sg:orig_category":"Farming: Agriculture: Agricultural Contractors",
    "sg:phone":"+64 3-688 2470",
    "sg:province":"Canterbury",
    "wof:name":"Hamish George Direct Drilling Contractor",
    "wof:placetype":"venue"
},
  "geometry": {"coordinates":[171.237411,-44.395428],"type":"Point"}
}