{
  "type": "Feature",
  "properties": {
    "iso:country":"NZ",
    "sg:address":"Maple Ct Puckey Ave ",
    "sg:city":"Kaitaia",
    "sg:classifiers":[
        {
            "category":"Personal",
            "subcategory":"Beauty Salon",
            "type":"Services"
        }
    ],
    "sg:phone":"+64 9-408 0580",
    "sg:province":"Northland",
    "sg:tags":[
        "therapy",
        "health"
    ],
    "wof:name":"Suzie's Aesthetics",
    "wof:placetype":"venue"
},
  "geometry": {"coordinates":[173.259445,-35.114212],"type":"Point"}
}