{
  "type": "Feature",
  "properties": {
    "addr:full":"130 Broadway  Matamata Manawatu-Wanganui",
    "addr:housenumber":"130",
    "addr:street":"Broadway",
    "iso:country":"NZ",
    "sg:address":"130 Broadway ",
    "sg:city":"Matamata",
    "sg:orig_category":"Shopping: Gifts",
    "sg:phone":"+64 7-888 6262",
    "sg:province":"Manawatu-Wanganui",
    "wof:name":"Cafe on Broadway",
    "wof:placetype":"venue"
},
  "geometry": {"coordinates":[175.77778599999999,-37.81144],"type":"Point"}
}