{
  "type": "Feature",
  "properties": {
    "iso:country":"NZ",
    "sg:address":"15 Gordon Rd ",
    "sg:city":"Wanaka",
    "sg:orig_category":"Transport: Boats And Marine: Boats: Boat Maintenance",
    "sg:phone":"+64 3-443 6404",
    "sg:province":"Otago",
    "wof:name":"Torque Marine Ltd",
    "wof:placetype":"venue"
},
  "geometry": {"coordinates":[169.14604199999999,-44.704315],"type":"Point"}
}