{
  "type": "Feature",
  "properties": {
    "iso:country":"NZ",
    "sg:address":"7 Ngatai Rd ",
    "sg:city":"Tauranga",
    "sg:classifiers":[
        {
            "category":"Social Services",
            "subcategory":"Child Care",
            "type":"Services"
        }
    ],
    "sg:phone":"+64 7-576 1740",
    "sg:province":"Bay of Plenty",
    "sg:tags":[
        "home",
        "garden",
        "children"
    ],
    "wof:name":"Dove Care and Education Centre 2002 Ltd",
    "wof:placetype":"venue"
},
  "geometry": {"coordinates":[176.160782,-37.669586],"type":"Point"}
}