{
  "type": "Feature",
  "properties": {
    "addr:full":"MacDonald Rd Matawhero  Gisborne Gisborne",
    "addr:street":"Macdonald Rd",
    "iso:country":"NZ",
    "sg:address":"MacDonald Rd Matawhero ",
    "sg:city":"Gisborne",
    "sg:orig_category":"Home And Garden: Gardening: Products: Fertilisers",
    "sg:phone":"+64 6-868 6059",
    "sg:province":"Gisborne",
    "wof:name":"Ravensdown Fertiliser Co-op Ltd",
    "wof:placetype":"venue"
},
  "geometry": {"coordinates":[177.94927999999999,-38.659481],"type":"Point"}
}