{
  "type": "Feature",
  "properties": {
    "addr:full":"521 A Mt Albert Rd Three Kings  Auckland Auckland",
    "addr:housenumber":"521",
    "addr:street":"A Mt Albert Rd",
    "iso:country":"NZ",
    "sg:address":"521 A Mt Albert Rd Three Kings ",
    "sg:city":"Auckland",
    "sg:orig_category":"Home And Garden: Gardening: Products",
    "sg:phone":"+64 9-625 7121",
    "sg:province":"Auckland",
    "sg:website":"http://www.masportsales.co.nz",
    "wof:name":"Bob Coldham Mowers",
    "wof:placetype":"venue"
},
  "geometry": {"coordinates":[174.756958,-36.909416],"type":"Point"}
}