{
  "type": "Feature",
  "properties": {
    "addr:full":"Tauranga  Tauranga Bay of Plenty",
    "iso:country":"NZ",
    "sg:address":"Tauranga ",
    "sg:city":"Tauranga",
    "sg:classifiers":[
        {
            "category":"Sports & Exercise",
            "subcategory":"Tennis Court",
            "type":"Entertainment"
        }
    ],
    "sg:phone":"+64 7-571 0771",
    "sg:province":"Bay of Plenty",
    "sg:tags":[
        "escort",
        "agency",
        "adult",
        "leisure"
    ],
    "wof:name":"Executive Services",
    "wof:placetype":"venue"
},
  "geometry": {"coordinates":[176.166473,-37.686142],"type":"Point"}
}