{
  "type": "Feature",
  "properties": {
    "addr:full":"North Shore Mail Cen  Auckland Auckland",
    "iso:country":"NZ",
    "sg:address":"North Shore Mail Cen ",
    "sg:city":"Auckland",
    "sg:classifiers":[
        {
            "category":"Home & Garden",
            "subcategory":"Building Materials",
            "type":"Retail Goods"
        }
    ],
    "sg:phone":"+64 9-415 2254",
    "sg:province":"Auckland",
    "sg:tags":[
        "related"
    ],
    "sg:website":"http://www.yellowpages.co.nz/for/draintech/dp47863.html",
    "wof:name":"Draintech Ltd",
    "wof:placetype":"venue"
},
  "geometry": {"coordinates":[174.92965699999999,-36.917198],"type":"Point"}
}