{
  "type": "Feature",
  "properties": {
    "iso:country":"NZ",
    "sg:address":"67 Main St ",
    "sg:city":"Tuatapere",
    "sg:classifiers":[
        {
            "category":"Bus Charters",
            "type":"Transportation"
        }
    ],
    "sg:phone":"+64 3-226 6715",
    "sg:tags":[
        "services",
        "travel",
        "tourism"
    ],
    "wof:name":"Brazier Motors 1988 Ltd",
    "wof:placetype":"venue"
},
  "geometry": {"coordinates":[167.69038399999999,-46.13147],"type":"Point"}
}