{
  "type": "Feature",
  "properties": {
    "addr:full":"21 Chancery La  Christchurch Canterbury",
    "addr:housenumber":"21",
    "addr:street":"Chancery La Christchurch",
    "iso:country":"NZ",
    "sg:address":"21 Chancery La ",
    "sg:city":"Christchurch",
    "sg:classifiers":[
        {
            "category":"Health Services",
            "subcategory":"Optometrist",
            "type":"Services"
        }
    ],
    "sg:phone":"+64 3-366 3467",
    "sg:province":"Canterbury",
    "sg:tags":[
        "optical",
        "beauty"
    ],
    "wof:name":"Maher Robert H Optician",
    "wof:placetype":"venue"
},
  "geometry": {"coordinates":[-76.537834,37.605659],"type":"Point"}
}