{
  "type": "Feature",
  "properties": {
    "addr:full":"Komiti Rd Tinopai  Maungaturoto",
    "addr:street":"Komiti Rd",
    "iso:country":"NZ",
    "sg:address":"Komiti Rd Tinopai ",
    "sg:city":"Maungaturoto",
    "sg:classifiers":[
        {
            "category":"Personal",
            "type":"Services"
        }
    ],
    "sg:phone":"+64 9-431 6388",
    "sg:tags":[
        "celebrant",
        "arrangements",
        "marriage",
        "wedding"
    ],
    "wof:name":"Macdonald Raewyn",
    "wof:placetype":"venue"
},
  "geometry": {"coordinates":[174.24790999999999,-36.250851],"type":"Point"}
}