{
  "type": "Feature",
  "properties": {
    "addr:full":"55 Harley St  Masterton Wellington",
    "addr:housenumber":"55",
    "addr:street":"Harley St",
    "iso:country":"NZ",
    "sg:address":"55 Harley St ",
    "sg:city":"Masterton",
    "sg:classifiers":[
        {
            "category":"Building & Trades",
            "subcategory":"Plumbing",
            "type":"Services"
        }
    ],
    "sg:phone":"+64 6-378 9503",
    "sg:province":"Wellington",
    "sg:tags":[
        "home",
        "plumber",
        "garden",
        "related"
    ],
    "wof:name":"Alan S McEwen",
    "wof:placetype":"venue"
},
  "geometry": {"coordinates":[175.638687,-40.962902],"type":"Point"}
}