{
  "type": "Feature",
  "properties": {
    "addr:full":"PO Box 25615 St  Heliers",
    "addr:housenumber":"po box 25615",
    "iso:country":"NZ",
    "sg:address":"PO Box 25615 St ",
    "sg:city":"Heliers",
    "sg:orig_category":"Farming: Forestry: Forestry Consultants",
    "sg:phone":"+64 800 761 176",
    "wof:name":"Sovereign Forestry Ltd",
    "wof:placetype":"venue"
},
  "geometry": {"coordinates":[174.862976,-36.856163],"type":"Point"}
}