{
  "type": "Feature",
  "properties": {
    "iso:country":"NZ",
    "sg:address":"5 Devon St ",
    "sg:city":"Picton",
    "sg:orig_category":"Transport: Boats And Marine: Boats: Boat Dealers",
    "sg:phone":"+64 3-573 7940",
    "sg:province":"Marlborough",
    "sg:website":"http://www.marineplus.co.nz",
    "wof:name":"Marine Plus Marlborough",
    "wof:placetype":"venue"
},
  "geometry": {"coordinates":[174.00376900000001,-41.29649],"type":"Point"}
}