{
  "type": "Feature",
  "properties": {
    "iso:country":"NZ",
    "sg:address":"127 Target Rd Glenfield ",
    "sg:city":"Auckland",
    "sg:classifiers":[
        {
            "category":"Bars & Pubs",
            "subcategory":"Sports Bar",
            "type":"Food & Drink"
        }
    ],
    "sg:phone":"+64 9-443 7111",
    "sg:province":"Auckland",
    "sg:tags":[
        "shop",
        "adult",
        "leisure"
    ],
    "wof:name":"Video Expo",
    "wof:placetype":"venue"
},
  "geometry": {"coordinates":[174.728622,-36.784813],"type":"Point"}
}