{
  "type": "Feature",
  "properties": {
    "iso:country":"NZ",
    "sg:address":"9 Papawai Pl Palmerston ",
    "sg:city":"Palmerston North",
    "sg:classifiers":[
        {
            "category":"Personal",
            "type":"Services"
        }
    ],
    "sg:phone":"+64 6-358 1415",
    "sg:province":"Manawatu-Wanganui",
    "sg:tags":[
        "celebrant",
        "arrangements",
        "marriage",
        "wedding"
    ],
    "wof:name":"Goodwin Suzanne",
    "wof:placetype":"venue"
},
  "geometry": {"coordinates":[175.61726400000001,-40.32909],"type":"Point"}
}