{
  "type": "Feature",
  "properties": {
    "addr:full":"Ahuroa Rd Te  Kuiti",
    "addr:street":"Ahuroa Rd",
    "iso:country":"NZ",
    "sg:address":"Ahuroa Rd Te ",
    "sg:city":"Kuiti",
    "sg:classifiers":[
        {
            "category":"Food & Beverages",
            "subcategory":"Meat & Fish",
            "type":"Retail Goods"
        }
    ],
    "sg:phone":"+64 7-878 6045",
    "sg:tags":[
        "drink"
    ],
    "wof:name":"Te Kuiti Meat Processors Ltd",
    "wof:placetype":"venue"
},
  "geometry": {"coordinates":[175.16665599999999,-38.333019],"type":"Point"}
}