{
  "type": "Feature",
  "properties": {
    "iso:country":"NZ",
    "sg:address":"156 Bealey Ave ",
    "sg:city":"Christchurch",
    "sg:classifiers":[
        {
            "category":"Health Services",
            "subcategory":"Hospital",
            "type":"Services"
        }
    ],
    "sg:phone":"+64 3-366 0620",
    "sg:province":"Canterbury",
    "sg:tags":[
        "beauty",
        "fitness"
    ],
    "sg:website":"http://www.sports-med.co.nz",
    "wof:name":"Sports Med",
    "wof:placetype":"venue"
},
  "geometry": {"coordinates":[172.63765000000001,-43.521107],"type":"Point"}
}