{
  "type": "Feature",
  "properties": {
    "addr:full":"Ponatahi Rd  Martinborough",
    "addr:street":"Ponatahi Rd",
    "iso:country":"NZ",
    "sg:address":"Ponatahi Rd ",
    "sg:city":"Martinborough",
    "sg:classifiers":[
        {
            "category":"Travel",
            "subcategory":"Hotels & Motels",
            "type":"Entertainment"
        }
    ],
    "sg:phone":"+64 6-306 9202",
    "sg:tags":[
        "lodge",
        "tourism",
        "accommodation"
    ],
    "sg:website":"http://margrainvineyard.co.nz",
    "wof:name":"Margrain Vineyards",
    "wof:placetype":"venue"
},
  "geometry": {"coordinates":[175.51000999999999,-41.181767],"type":"Point"}
}