{
  "type": "Feature",
  "properties": {
    "iso:country":"NZ",
    "sg:address":"607 Hamurana Rd Hamurana ",
    "sg:city":"Rotorua",
    "sg:classifiers":[
        {
            "category":"Health Services",
            "subcategory":"Clinic",
            "type":"Services"
        }
    ],
    "sg:phone":"+64 7-332 2911",
    "sg:province":"Bay of Plenty",
    "sg:tags":[
        "services",
        "therapy",
        "natural",
        "beauty"
    ],
    "wof:name":"Rainbow Health",
    "wof:placetype":"venue"
},
  "geometry": {"coordinates":[176.239059,-38.036686],"type":"Point"}
}