{
  "type": "Feature",
  "properties": {
    "addr:full":"22-24 Bay Park Pl Beach Haven  Auckland Auckland",
    "addr:housenumber":"22-24",
    "addr:street":"Bay Park Pl",
    "iso:country":"NZ",
    "sg:address":"22-24 Bay Park Pl Beach Haven ",
    "sg:city":"Auckland",
    "sg:orig_category":"Industrial: Products: Filters And Filtration",
    "sg:phone":"+64 9-483 7149",
    "sg:province":"Auckland",
    "wof:name":"Filtercorp International Ltd",
    "wof:placetype":"venue"
},
  "geometry": {"coordinates":[174.68959000000001,-36.790905],"type":"Point"}
}