{
  "type": "Feature",
  "properties": {
    "addr:full":"316 Te Moana Rd  Waikanae",
    "addr:housenumber":"316",
    "addr:street":"Te Moana Rd",
    "iso:country":"NZ",
    "sg:address":"316 Te Moana Rd ",
    "sg:city":"Waikanae",
    "sg:orig_category":"Transport: Land: Shuttle Services",
    "sg:phone":"+64 272 412 151",
    "wof:name":"Kapiti Shuttles (2002)",
    "wof:placetype":"venue"
},
  "geometry": {"coordinates":[175.04463200000001,-40.877647],"type":"Point"}
}