{
  "type": "Feature",
  "properties": {
    "iso:country":"NZ",
    "sg:address":"Kaiwaka-Mangawhai Rd RD1 ",
    "sg:city":"Kaiwaka",
    "sg:classifiers":[
        {
            "category":"Bus Charters",
            "type":"Transportation"
        }
    ],
    "sg:phone":"+64 800 361 715",
    "sg:tags":[
        "services",
        "travel",
        "tourism"
    ],
    "wof:name":"Inside Touring of New Zealand",
    "wof:placetype":"venue"
},
  "geometry": {"coordinates":[174.437485,-36.163948],"type":"Point"}
}