{
  "type": "Feature",
  "properties": {
    "addr:full":"20 Conical Hill Rd Hanmer  Springs",
    "addr:housenumber":"20",
    "addr:street":"Conical Hill Rd",
    "iso:country":"NZ",
    "sg:address":"20 Conical Hill Rd Hanmer ",
    "sg:city":"Springs",
    "sg:classifiers":[
        {
            "category":"Landmark",
            "subcategory":"Tourist Information",
            "type":"Public Place"
        }
    ],
    "sg:phone":"+64 3-315 7233",
    "sg:tags":[
        "services",
        "travel",
        "tourism"
    ],
    "wof:name":"Hanmer Springs Adventure Centre",
    "wof:placetype":"venue"
},
  "geometry": {"coordinates":[172.829498,-42.52071],"type":"Point"}
}