{
  "type": "Feature",
  "properties": {
    "iso:country":"NZ",
    "sg:address":"214 Waltham Rd Waltham ",
    "sg:city":"Christchurch",
    "sg:classifiers":[
        {
            "category":"Manufacturing",
            "subcategory":"Motor Vehicles & Parts",
            "type":"Manufacturing & Wholesale Goods"
        }
    ],
    "sg:phone":"+64 3-366 9514",
    "sg:province":"Canterbury",
    "sg:tags":[
        "box",
        "industrial",
        "parts",
        "-",
        "gear"
    ],
    "wof:name":"Brooks John Ltd",
    "wof:placetype":"venue"
},
  "geometry": {"coordinates":[172.647079,-43.544533],"type":"Point"}
}