{
  "type": "Feature",
  "properties": {
    "iso:country":"NZ",
    "sg:address":"332 State Highway 2 Te ",
    "sg:city":"Puke",
    "sg:classifiers":[
        {
            "category":"Health Services",
            "subcategory":"Clinic",
            "type":"Services"
        }
    ],
    "sg:phone":"+64 7-573 5422",
    "sg:province":"Bay of Plenty",
    "sg:tags":[
        "medical",
        "beauty"
    ],
    "wof:name":"Waitangi Medical Centre",
    "wof:placetype":"venue"
},
  "geometry": {"coordinates":[176.284439,-37.717075],"type":"Point"}
}