{
  "type": "Feature",
  "properties": {
    "addr:full":"Titirangi  Auckland Auckland",
    "iso:country":"NZ",
    "sg:address":"Titirangi ",
    "sg:city":"Auckland",
    "sg:orig_category":"Health And Beauty: Mental: Psychotherapy",
    "sg:phone":"+64 9-360 0035",
    "sg:province":"Auckland",
    "wof:name":"Davies Rod",
    "wof:placetype":"venue"
},
  "geometry": {"coordinates":[174.655869,-36.93795],"type":"Point"}
}