{
  "type": "Feature",
  "properties": {
    "iso:country":"NZ",
    "sg:address":"27 North Rd ",
    "sg:city":"Invercargill",
    "sg:orig_category":"Industrial: Abrasives: Water Blasting",
    "sg:phone":"+64 3-215 9064",
    "sg:province":"Southland",
    "wof:name":"George Wilson Sales",
    "wof:placetype":"venue"
},
  "geometry": {"coordinates":[168.347076,-46.388657],"type":"Point"}
}