{
  "type": "Feature",
  "properties": {
    "iso:country":"NZ",
    "sg:address":"12 Don St",
    "sg:city":"Invercargill",
    "sg:classifiers":[
        {
            "category":"Banks & Credit Unions",
            "subcategory":"Bank",
            "type":"Services"
        }
    ],
    "sg:phone":"+64 2183113",
    "sg:province":"Southland",
    "wof:name":"Bank of New Zealand",
    "wof:placetype":"venue"
},
  "geometry": {"coordinates":[168.34814499999999,-46.410629],"type":"Point"}
}