{
  "type": "Feature",
  "properties": {
    "iso:country":"NZ",
    "sg:address":"301 Gloucester St Taradale ",
    "sg:city":"Napier",
    "sg:classifiers":[
        {
            "category":"Home & Garden",
            "subcategory":"Garden Supply",
            "type":"Retail Goods"
        }
    ],
    "sg:phone":"+64 6-844 8893",
    "sg:province":"Hawke's Bay",
    "sg:tags":[
        "aquarium",
        "pets"
    ],
    "wof:name":"Taradale Pet Centre",
    "wof:placetype":"venue"
},
  "geometry": {"coordinates":[176.848129,-39.536358],"type":"Point"}
}