{
  "type": "Feature",
  "properties": {
    "addr:full":"33 Glengarry Cre Glengarry  Invercargill Southland",
    "addr:housenumber":"33;cre",
    "addr:street":"Glengarry",
    "iso:country":"NZ",
    "sg:address":"33 Glengarry Cre Glengarry ",
    "sg:city":"Invercargill",
    "sg:orig_category":"Shopping: Retail Stores: Secondhand Dealers",
    "sg:phone":"+64 3-217 2730",
    "sg:province":"Southland",
    "wof:name":"Bargin Barn - Habitat For Humanity",
    "wof:placetype":"venue"
},
  "geometry": {"coordinates":[168.385178,-46.400578],"type":"Point"}
}