{
  "type": "Feature",
  "properties": {
    "iso:country":"NZ",
    "sg:address":"12 West St Frankton ",
    "sg:city":"Hamilton",
    "sg:classifiers":[
        {
            "category":"Home & Garden",
            "subcategory":"Furniture",
            "type":"Retail Goods"
        }
    ],
    "sg:phone":"+64 7-847 7740",
    "sg:province":"Waikato",
    "sg:tags":[
        "furniture/furnishings",
        "repair",
        "finishing"
    ],
    "wof:name":"Meredith Furniture Finishings",
    "wof:placetype":"venue"
},
  "geometry": {"coordinates":[175.257721,-37.787994],"type":"Point"}
}