{
  "type": "Feature",
  "properties": {
    "addr:full":"10 Titoki St Parnell  Auckland Auckland",
    "addr:housenumber":"10",
    "addr:street":"Titoki St",
    "iso:country":"NZ",
    "sg:address":"10 Titoki St Parnell ",
    "sg:city":"Auckland",
    "sg:classifiers":[
        {
            "category":"Education",
            "subcategory":"University",
            "type":"Public Place"
        }
    ],
    "sg:phone":"+64 9-307 6507",
    "sg:province":"Auckland",
    "sg:tags":[
        "training",
        "instruction",
        "language"
    ],
    "wof:name":"Aspect International Language Academies",
    "wof:placetype":"venue"
},
  "geometry": {"coordinates":[174.779312,-36.862556],"type":"Point"}
}