{
  "type": "Feature",
  "properties": {
    "iso:country":"NZ",
    "sg:address":"1 Curry St ",
    "sg:city":"Blenheim",
    "sg:classifiers":[
        {
            "category":"Professional",
            "subcategory":"Art Services",
            "type":"Services"
        }
    ],
    "sg:phone":"+64 3-578 2668",
    "sg:province":"Marlborough",
    "sg:tags":[
        "personal",
        "photographer",
        "services",
        "garden",
        "home"
    ],
    "wof:name":"Leandra Robinson Photography",
    "wof:placetype":"venue"
},
  "geometry": {"coordinates":[-74.459564,42.468643],"type":"Point"}
}