{
  "type": "Feature",
  "properties": {
    "iso:country":"NZ",
    "sg:address":"567 Kamo Rd Kamo ",
    "sg:city":"Whangarei",
    "sg:classifiers":[
        {
            "category":"Travel",
            "subcategory":"Hotels & Motels",
            "type":"Entertainment"
        }
    ],
    "sg:phone":"+64 9-435 5430",
    "sg:province":"Northland",
    "sg:tags":[
        "tavern",
        "tourism",
        "accommodation"
    ],
    "wof:name":"Kamo Hotel",
    "wof:placetype":"venue"
},
  "geometry": {"coordinates":[174.300262,-35.682449],"type":"Point"}
}