{
  "type": "Feature",
  "properties": {
    "iso:country":"NZ",
    "sg:address":"Argyll Lane 58 Queen St ",
    "sg:city":"Warkworth",
    "sg:orig_category":"Shopping: Retail Stores: Cds, Cassettes And Records",
    "sg:phone":"+64 9-425 7387",
    "sg:province":"Auckland",
    "wof:name":"Warkworth Cycle & Music Centre",
    "wof:placetype":"venue"
},
  "geometry": {"coordinates":[174.665115,-36.401466],"type":"Point"}
}