{
  "type": "Feature",
  "properties": {
    "addr:full":"1378 Cameron Rd Greerton Greerton  Tauranga Bay of Plenty",
    "addr:housenumber":"1378",
    "addr:street":"Cameron Rd",
    "iso:country":"NZ",
    "sg:address":"1378 Cameron Rd Greerton Greerton ",
    "sg:city":"Tauranga",
    "sg:orig_category":"Shopping: Sports Retailers: Sports Goods: Canvas Goods",
    "sg:phone":"+64 7-541 3322",
    "sg:province":"Bay of Plenty",
    "wof:name":"CanvasWorx Ltd",
    "wof:placetype":"venue"
},
  "geometry": {"coordinates":[176.131439,-37.727734],"type":"Point"}
}