{
  "type": "Feature",
  "properties": {
    "addr:full":"Town Centre  Turangi Southland",
    "iso:country":"NZ",
    "sg:address":"Town Centre ",
    "sg:city":"Turangi",
    "sg:classifiers":[
        {
            "category":"Sports & Exercise",
            "subcategory":"Sports Center",
            "type":"Entertainment"
        }
    ],
    "sg:phone":"+64 7-386 8021",
    "sg:province":"Southland",
    "sg:tags":[
        "sporting",
        "sports",
        "-",
        "leisure",
        "facility"
    ],
    "wof:name":"Turtle Swimming Pool",
    "wof:placetype":"venue"
},
  "geometry": {"coordinates":[175.803955,-38.988941],"type":"Point"}
}