{
  "type": "Feature",
  "properties": {
    "addr:full":"17 Ingram St Papakura  Auckland Auckland",
    "addr:housenumber":"17",
    "addr:street":"Ingram St",
    "iso:country":"NZ",
    "sg:address":"17 Ingram St Papakura ",
    "sg:city":"Auckland",
    "sg:orig_category":"Home And Garden: Furniture/Furnishings: Cabinetmakers",
    "sg:phone":"+64 9-298 0088",
    "sg:province":"Auckland",
    "wof:name":"Alexander Home Improvements Ltd",
    "wof:placetype":"venue"
},
  "geometry": {"coordinates":[174.944199,-37.059109],"type":"Point"}
}