{
  "type": "Feature",
  "properties": {
    "iso:country":"NZ",
    "sg:address":"127 Spa Rd ",
    "sg:city":"Taupo",
    "sg:classifiers":[
        {
            "category":"Health Services",
            "subcategory":"Dentist",
            "type":"Services"
        }
    ],
    "sg:phone":"+64 7-378 9069",
    "sg:province":"Waikato",
    "sg:tags":[
        "dental",
        "beauty"
    ],
    "wof:name":"Casswell Chris Dental Surgeon",
    "wof:placetype":"venue"
},
  "geometry": {"coordinates":[176.077866,-38.68277],"type":"Point"}
}