{
  "type": "Feature",
  "properties": {
    "iso:country":"NZ",
    "sg:address":"Taupo Qy ",
    "sg:city":"Wanganui",
    "sg:orig_category":"Transport: Transportation: Transport Operators",
    "sg:phone":"+64 6-343 5207",
    "sg:province":"Manawatu-Wanganui",
    "wof:name":"Tranz Rail",
    "wof:placetype":"venue"
},
  "geometry": {"coordinates":[175.04199199999999,-39.94492],"type":"Point"}
}