{
  "type": "Feature",
  "properties": {
    "iso:country":"NZ",
    "sg:address":"Level 12 Majestic Centre 100 Willis St ",
    "sg:city":"Wellington",
    "sg:orig_category":"Industrial: Parts: Pipes, Tubes And Cabling: Cables",
    "sg:phone":"+64 4-499 2729",
    "sg:province":"Wellington",
    "wof:name":"Logical",
    "wof:placetype":"venue"
},
  "geometry": {"coordinates":[-80.236366,26.6626],"type":"Point"}
}