{
  "type": "Feature",
  "properties": {
    "iso:country":"NZ",
    "sg:address":"4th Floor 151 Worcester St ",
    "sg:city":"Christchurch",
    "sg:classifiers":[
        {
            "category":"Banks & Credit Unions",
            "subcategory":"Financial Services",
            "type":"Services"
        }
    ],
    "sg:phone":"+64 3-365 3763",
    "sg:province":"Canterbury",
    "sg:tags":[
        "personal",
        "loan",
        "-",
        "finance",
        "mortgage"
    ],
    "sg:website":"http://www.yellowpages.co.nz/for/crombielockwood/dp10099.html",
    "wof:name":"Crombie Lockwood Insurance Brokers",
    "wof:placetype":"venue"
},
  "geometry": {"coordinates":[-76.537834,37.605659],"type":"Point"}
}