{
  "type": "Feature",
  "properties": {
    "addr:full":"10 Hinau St Woburn Lower  Hutt Wellington",
    "addr:housenumber":"10",
    "addr:street":"Hinau St",
    "iso:country":"NZ",
    "sg:address":"10 Hinau St Woburn Lower ",
    "sg:city":"Hutt",
    "sg:classifiers":[
        {
            "category":"Banks & Credit Unions",
            "subcategory":"Investment Brokerage",
            "type":"Services"
        }
    ],
    "sg:phone":"+64 800 348 027",
    "sg:province":"Wellington",
    "sg:tags":[
        "chemical",
        "industrial",
        "-",
        "compounds"
    ],
    "wof:name":"Amtrade New Zealand Limited",
    "wof:placetype":"venue"
},
  "geometry": {"coordinates":[174.91154499999999,-41.216217],"type":"Point"}
}