{
  "type": "Feature",
  "properties": {
    "addr:full":"13 King St Te  Puke Bay of Plenty",
    "addr:housenumber":"13",
    "addr:street":"King St",
    "iso:country":"NZ",
    "sg:address":"13 King St Te ",
    "sg:city":"Puke",
    "sg:orig_category":"Farming: Services",
    "sg:phone":"+64 7-573 8512",
    "sg:province":"Bay of Plenty",
    "sg:website":"http://www.electrodip.co.nz",
    "wof:name":"Electroquip",
    "wof:placetype":"venue"
},
  "geometry": {"coordinates":[176.33090200000001,-37.785164],"type":"Point"}
}