{
  "type": "Feature",
  "properties": {
    "iso:country":"NZ",
    "sg:address":"7-9 Nelson St Auckland Central ",
    "sg:city":"Auckland",
    "sg:classifiers":[
        {
            "category":"Autos & Motor Vehicles",
            "subcategory":"Auto Supplies",
            "type":"Retail Goods"
        }
    ],
    "sg:phone":"+64 9-379 3240",
    "sg:province":"Auckland",
    "sg:tags":[
        "equipment",
        "garage",
        "part",
        "supplies",
        "automotive"
    ],
    "sg:website":"http://www.tradetools.co.nz",
    "wof:name":"Trade Tools Ltd",
    "wof:placetype":"venue"
},
  "geometry": {"coordinates":[174.760574,-36.846203],"type":"Point"}
}