{
  "type": "Feature",
  "properties": {
    "addr:full":"7/376 Riccarton Rd Upper Riccarton  Christchurch Canterbury",
    "addr:housenumber":"7 / 376",
    "addr:street":"Riccarton Rd",
    "iso:country":"NZ",
    "sg:address":"7/376 Riccarton Rd Upper Riccarton ",
    "sg:city":"Christchurch",
    "sg:classifiers":[
        {
            "category":"Bars & Pubs",
            "subcategory":"Lounge",
            "type":"Food & Drink"
        }
    ],
    "sg:phone":"+64 3-341 0936",
    "sg:province":"Canterbury",
    "sg:tags":[
        "-",
        "asian"
    ],
    "wof:name":"Penny's Groceries",
    "wof:placetype":"venue"
},
  "geometry": {"coordinates":[172.573273,-43.531708],"type":"Point"}
}