{
  "type": "Feature",
  "properties": {
    "iso:country":"NZ",
    "sg:address":"75 B Halswater Dve Churton Park ",
    "sg:city":"Wellington",
    "sg:classifiers":[
        {
            "category":"Retail",
            "subcategory":"Driving School",
            "type":"Services"
        }
    ],
    "sg:phone":"+64 4-478 0797",
    "sg:province":"Wellington",
    "sg:tags":[
        "training",
        "education",
        "driver"
    ],
    "wof:name":"Able Driving School",
    "wof:placetype":"venue"
},
  "geometry": {"coordinates":[174.767151,-41.28054],"type":"Point"}
}