{
  "type": "Feature",
  "properties": {
    "iso:country":"NZ",
    "sg:address":"PO Box 202 ",
    "sg:city":"Napier",
    "sg:classifiers":[
        {
            "category":"Education",
            "subcategory":"Special Training",
            "type":"Public Place"
        }
    ],
    "sg:phone":"+64 6-835 7712",
    "sg:province":"Hawke's Bay",
    "sg:tags":[
        "therapist",
        "speech",
        "language"
    ],
    "wof:name":"Bevin Maxine",
    "wof:placetype":"venue"
},
  "geometry": {"coordinates":[-80.588562,38.790821],"type":"Point"}
}