{
  "type": "Feature",
  "properties": {
    "iso:country":"NZ",
    "sg:address":"PO Box 1256 ",
    "sg:city":"Invercargill",
    "sg:orig_category":"Farming: Horticulture: Grain And Seed",
    "sg:phone":"+64 3-214 3136",
    "sg:province":"Southland",
    "wof:name":"RTR Grain & Seeds",
    "wof:placetype":"venue"
},
  "geometry": {"coordinates":[168.352173,-46.411854],"type":"Point"}
}