{
  "type": "Feature",
  "properties": {
    "iso:country":"NZ",
    "sg:address":"Bookings 1 Kent Tce Mt Victoria ",
    "sg:city":"Wellington",
    "sg:orig_category":"Sports And Leisure: Arts: Theatres",
    "sg:phone":"+64 4-802 4175",
    "sg:province":"Wellington",
    "wof:name":"Bats Theatre",
    "wof:placetype":"venue"
},
  "geometry": {"coordinates":[174.78154000000001,-41.298347],"type":"Point"}
}