{
  "type": "Feature",
  "properties": {
    "iso:country":"NZ",
    "sg:address":"239-241 Queen St ",
    "sg:city":"Masterton",
    "sg:classifiers":[
        {
            "category":"Professional",
            "subcategory":"Art Services",
            "type":"Services"
        }
    ],
    "sg:phone":"+64 6-377 3920",
    "sg:province":"Wellington",
    "sg:tags":[
        "picture",
        "arts",
        "sport",
        "framing",
        "leisure"
    ],
    "wof:name":"Nikolaison's Photo Centre Ltd",
    "wof:placetype":"venue"
},
  "geometry": {"coordinates":[175.658691,-40.951843],"type":"Point"}
}