{
  "type": "Feature",
  "properties": {
    "iso:country":"NZ",
    "sg:address":"156 Tuam St ",
    "sg:city":"Christchurch",
    "sg:orig_category":"Transport",
    "sg:phone":"+64 3-366 0929",
    "sg:province":"Canterbury",
    "sg:website":"http://www.yellowpages.co.nz/for/mcdonaldsrentacar/dp15640.html",
    "wof:name":"McDonald Rent-A-Car",
    "wof:placetype":"venue"
},
  "geometry": {"coordinates":[-76.537834,37.605659],"type":"Point"}
}