{
  "type": "Feature",
  "properties": {
    "iso:country":"NZ",
    "sg:address":"1 Clive Sq West ",
    "sg:city":"Napier",
    "sg:classifiers":[
        {
            "category":"Shopping",
            "subcategory":"Bicycles & Sporting Goods",
            "type":"Retail Goods"
        }
    ],
    "sg:phone":"+64 6-835 9528",
    "sg:province":"Hawke's Bay",
    "sg:tags":[
        "cycle",
        "sport",
        "sale",
        "retailers",
        "cycles"
    ],
    "wof:name":"Cycle & Kart Centre",
    "wof:placetype":"venue"
},
  "geometry": {"coordinates":[-80.588562,38.790821],"type":"Point"}
}