{
  "type": "Feature",
  "properties": {
    "iso:country":"NZ",
    "sg:address":"29 Robins Rd ",
    "sg:city":"Queenstown",
    "sg:classifiers":[
        {
            "category":"Education",
            "subcategory":"University",
            "type":"Public Place"
        }
    ],
    "sg:phone":"+64 3-442 6625",
    "sg:province":"Otago",
    "sg:tags":[
        "training",
        "instruction",
        "language"
    ],
    "wof:name":"Language Schools New Zealand Queenstown",
    "wof:placetype":"venue"
},
  "geometry": {"coordinates":[-76.157791,38.990379],"type":"Point"}
}