{
  "type": "Feature",
  "properties": {
    "addr:full":"501 Parnell Rd Parnell  Auckland Auckland",
    "addr:housenumber":"501",
    "addr:street":"Parnell Rd",
    "iso:country":"NZ",
    "sg:address":"501 Parnell Rd Parnell ",
    "sg:city":"Auckland",
    "sg:classifiers":[
        {
            "category":"Sports & Exercise",
            "subcategory":"Golf",
            "type":"Entertainment"
        }
    ],
    "sg:phone":"+64 9-359 9923",
    "sg:province":"Auckland",
    "sg:tags":[
        "club",
        "equipment",
        "leisure",
        "sports"
    ],
    "wof:name":"ACTIVE LEISURE Ltd",
    "wof:placetype":"venue"
},
  "geometry": {"coordinates":[174.781937,-36.861668],"type":"Point"}
}