{
  "type": "Feature",
  "properties": {
    "iso:country":"NZ",
    "sg:address":"Cnr Queen & Warren Sts ",
    "sg:city":"Hastings",
    "sg:classifiers":[
        {
            "category":"Banks & Credit Unions",
            "subcategory":"Investment Brokerage",
            "type":"Services"
        }
    ],
    "sg:phone":"+64 6-878 5656",
    "sg:province":"Hawke's Bay",
    "sg:tags":[
        "personal",
        "-",
        "finance"
    ],
    "wof:name":"Money Managers Ltd",
    "wof:placetype":"venue"
},
  "geometry": {"coordinates":[-98.392372,40.585651],"type":"Point"}
}