{
  "type": "Feature",
  "properties": {
    "iso:country":"NZ",
    "sg:address":"Corner 14th Avenue & Devonport Road ",
    "sg:city":"Tauranga",
    "sg:classifiers":[
        {
            "category":"Sports & Exercise",
            "subcategory":"Tennis Court",
            "type":"Entertainment"
        }
    ],
    "sg:phone":"+64 7-928 8000",
    "sg:province":"Waikato",
    "sg:tags":[
        "medicine",
        "specialists",
        "health",
        "beauty"
    ],
    "wof:name":"CentralMed Medical Centre",
    "wof:placetype":"venue"
},
  "geometry": {"coordinates":[176.14476,-37.703152],"type":"Point"}
}