{
  "type": "Feature",
  "properties": {
    "iso:country":"NZ",
    "sg:address":"148 Jackson St Petone Lower ",
    "sg:city":"Hutt",
    "sg:classifiers":[
        {
            "category":"Home & Garden",
            "subcategory":"Building Materials",
            "type":"Retail Goods"
        }
    ],
    "sg:phone":"+64 4-568 7619",
    "sg:province":"Wellington",
    "sg:tags":[
        "door",
        "fitting",
        "fittings"
    ],
    "wof:name":"Handles Knockers & Knobs",
    "wof:placetype":"venue"
},
  "geometry": {"coordinates":[174.87460300000001,-41.22427],"type":"Point"}
}