{
  "type": "Feature",
  "properties": {
    "iso:country":"NZ",
    "sg:address":"179 Crawford Rd R D 1 Te Puna ",
    "sg:city":"Tauranga",
    "sg:orig_category":"Home And Garden: Furniture/Furnishings: Cabinetmakers",
    "sg:phone":"+64 7-552 5358",
    "sg:province":"Bay of Plenty",
    "wof:name":"Swiss Cabinet Maker",
    "wof:placetype":"venue"
},
  "geometry": {"coordinates":[176.073334,-37.692341],"type":"Point"}
}