{
  "type": "Feature",
  "properties": {
    "iso:country":"NZ",
    "sg:address":"114 Riddiford St Newtown ",
    "sg:city":"Wellington",
    "sg:classifiers":[
        {
            "category":"Organizations",
            "subcategory":"Community Association",
            "type":"Services"
        }
    ],
    "sg:phone":"+64 4-380 0556",
    "sg:province":"Wellington",
    "sg:tags":[
        "funeral",
        "arrangements",
        "monumental",
        "mason"
    ],
    "wof:name":"Glover Memorials Ltd",
    "wof:placetype":"venue"
},
  "geometry": {"coordinates":[174.77916,-41.311981],"type":"Point"}
}