{
  "type": "Feature",
  "properties": {
    "addr:full":"27 Norman Spencer Dve Manukau City  Auckland Auckland",
    "addr:housenumber":"27;dve",
    "addr:street":"Norman Spencer",
    "iso:country":"NZ",
    "sg:address":"27 Norman Spencer Dve Manukau City ",
    "sg:city":"Auckland",
    "sg:classifiers":[
        {
            "category":"Home & Garden",
            "subcategory":"Furniture",
            "type":"Retail Goods"
        }
    ],
    "sg:phone":"+64 9-277 5441",
    "sg:province":"Auckland",
    "sg:tags":[
        "furniture/furnishings",
        "furnishing"
    ],
    "wof:name":"Furniture Court (NZ) Ltd",
    "wof:placetype":"venue"
},
  "geometry": {"coordinates":[174.88145399999999,-36.98967],"type":"Point"}
}