{
  "type": "Feature",
  "properties": {
    "addr:full":"80 Alexandra  Cre",
    "addr:housenumber":"80",
    "addr:street":"Alexandra Cre",
    "iso:country":"NZ",
    "sg:address":"80 Alexandra ",
    "sg:city":"Cre",
    "sg:orig_category":"Industrial: Manufacturing: Tank Manufacturers",
    "sg:phone":"+64 800 302 530",
    "wof:name":"Skellerup Rotomould",
    "wof:placetype":"venue"
},
  "geometry": {"coordinates":[-87.63273599999999,41.444504],"type":"Point"}
}