{
  "type": "Feature",
  "properties": {
    "iso:country":"NZ",
    "sg:address":"31 Main Rd ",
    "sg:city":"Tirau",
    "sg:classifiers":[
        {
            "category":"Shopping",
            "subcategory":"Crafts & Fabrics",
            "type":"Retail Goods"
        }
    ],
    "sg:phone":"+64 7-883 1076",
    "sg:tags":[
        "pottery",
        "home",
        "accessories",
        "garden",
        "supply"
    ],
    "wof:name":"That Lovely Pot Shop",
    "wof:placetype":"venue"
},
  "geometry": {"coordinates":[175.75701900000001,-37.977913],"type":"Point"}
}