{
  "type": "Feature",
  "properties": {
    "iso:country":"NZ",
    "sg:address":"27 Ellis St ",
    "sg:city":"Hamilton",
    "sg:classifiers":[
        {
            "category":"Utilities",
            "subcategory":"Electric",
            "type":"Services"
        }
    ],
    "sg:phone":"+64 800 800 360",
    "sg:province":"Waikato",
    "sg:tags":[
        "energy",
        "industrial"
    ],
    "sg:website":"http://www.yellowpages.co.nz/for/wymers/dp24034.html",
    "wof:name":"Isuzu Truck Parts Richard Wymer Ltd",
    "wof:placetype":"venue"
},
  "geometry": {"coordinates":[-87.988968,34.142426],"type":"Point"}
}