{
  "type": "Feature",
  "properties": {
    "iso:country":"NZ",
    "sg:address":"PO Box 76304 Manukau City ",
    "sg:city":"Porirua",
    "sg:orig_category":"Clothing And Fabric: Clothing: Clothing - Specialty",
    "sg:phone":"+64 4-237 9713",
    "sg:province":"Auckland",
    "wof:name":"Carmont Fashions Ltd",
    "wof:placetype":"venue"
},
  "geometry": {"coordinates":[174.881439,-36.98967],"type":"Point"}
}