{
  "type": "Feature",
  "properties": {
    "addr:full":"15 Ballance St Kihikihi Te  Awamutu Waikato",
    "addr:housenumber":"15",
    "addr:street":"Ballance St Kihikihi",
    "iso:country":"NZ",
    "sg:address":"15 Ballance St Kihikihi Te ",
    "sg:city":"Awamutu",
    "sg:orig_category":"Home And Garden: General: Handyman'S Services",
    "sg:phone":"+64 7-871 7762",
    "sg:province":"Waikato",
    "wof:name":"Property Maintenance Services (Waipa)",
    "wof:placetype":"venue"
},
  "geometry": {"coordinates":[175.34368900000001,-38.040134],"type":"Point"}
}