{
  "type": "Feature",
  "properties": {
    "iso:country":"NZ",
    "sg:address":"2 Roberts Line Palmerston ",
    "sg:city":"Palmerston North",
    "sg:orig_category":"Home And Garden: Building Related: Blocklaying",
    "sg:phone":"+64 6-358 2292",
    "sg:province":"Manawatu-Wanganui",
    "wof:name":"McCosh G N",
    "wof:placetype":"venue"
},
  "geometry": {"coordinates":[175.656799,-40.336926],"type":"Point"}
}