{
  "type": "Feature",
  "properties": {
    "iso:country":"NZ",
    "sg:address":"Apirana Ave Regent ",
    "sg:city":"Whangarei",
    "sg:classifiers":[
        {
            "category":"Banks & Credit Unions",
            "subcategory":"Investment Brokerage",
            "type":"Services"
        }
    ],
    "sg:phone":"+64 9-438 2644",
    "sg:province":"Northland",
    "sg:tags":[
        "director",
        "funeral",
        "arrangements"
    ],
    "sg:website":"http://www.funeral-link.co.nz",
    "wof:name":"Newberrys Funeral Home",
    "wof:placetype":"venue"
},
  "geometry": {"coordinates":[174.320618,-35.718224],"type":"Point"}
}