{
  "type": "Feature",
  "properties": {
    "addr:full":"153-157 Thorndon Qy Thorndon  Wellington Wellington",
    "addr:housenumber":"153-157",
    "addr:street":"Thorndon Qy",
    "iso:country":"NZ",
    "sg:address":"153-157 Thorndon Qy Thorndon ",
    "sg:city":"Wellington",
    "sg:classifiers":[
        {
            "category":"Communications",
            "subcategory":"Film & Video Production",
            "type":"Services"
        }
    ],
    "sg:phone":"+64 4-472 2654",
    "sg:province":"Wellington",
    "sg:tags":[
        "broadcasting",
        "studio",
        "producer"
    ],
    "wof:name":"Sauce",
    "wof:placetype":"venue"
},
  "geometry": {"coordinates":[174.776016,-41.274925],"type":"Point"}
}