{
  "type": "Feature",
  "properties": {
    "addr:full":"110 Pope St Plimmerton  Wellington Wellington",
    "addr:housenumber":"110",
    "addr:street":"Pope St",
    "iso:country":"NZ",
    "sg:address":"110 Pope St Plimmerton ",
    "sg:city":"Wellington",
    "sg:classifiers":[
        {
            "category":"Wholesale",
            "subcategory":"Machinery & Supplies",
            "type":"Manufacturing & Wholesale Goods"
        }
    ],
    "sg:phone":"+64 274 425 666",
    "sg:province":"Wellington",
    "sg:tags":[
        "equipment",
        "crane",
        "industrial",
        "hoist",
        "lifting"
    ],
    "wof:name":"Warren Dean Cartage",
    "wof:placetype":"venue"
},
  "geometry": {"coordinates":[174.86428799999999,-41.079514],"type":"Point"}
}