{
  "type": "Feature",
  "properties": {
    "iso:country":"NZ",
    "sg:address":"52 Bothams Bend Rd Spring Creek R D 3 ",
    "sg:city":"Blenheim",
    "sg:classifiers":[
        {
            "category":"Home & Garden",
            "subcategory":"Carpets & Floor Coverings",
            "type":"Retail Goods"
        }
    ],
    "sg:phone":"+64 3-577 6611",
    "sg:province":"Marlborough",
    "sg:tags":[
        "cleaning",
        "furniture"
    ],
    "wof:name":"Chem-Dry Marlborough",
    "wof:placetype":"venue"
},
  "geometry": {"coordinates":[-74.459564,42.468643],"type":"Point"}
}