{
  "type": "Feature",
  "properties": {
    "iso:country":"NZ",
    "sg:address":"189 Commerce St ",
    "sg:city":"Hamilton",
    "sg:orig_category":"Home And Garden: Accessories: Hardware",
    "sg:phone":"+64 7-847 6473",
    "sg:province":"Waikato",
    "wof:name":"Frankton Hammer Hardware",
    "wof:placetype":"venue"
},
  "geometry": {"coordinates":[-84.580231,39.407902],"type":"Point"}
}