{
  "type": "Feature",
  "properties": {
    "addr:full":"Goddards Rd  Tasman",
    "addr:street":"Goddards Rd",
    "iso:country":"NZ",
    "sg:address":"Goddards Rd ",
    "sg:city":"Tasman",
    "sg:classifiers":[
        {
            "category":"Building & Trades",
            "subcategory":"Plumbing",
            "type":"Services"
        }
    ],
    "sg:phone":"+64 3-526 6800",
    "sg:tags":[
        "home",
        "plumber",
        "garden",
        "related"
    ],
    "wof:name":"Rob Visser Plumber",
    "wof:placetype":"venue"
},
  "geometry": {"coordinates":[173.32431,-41.224808],"type":"Point"}
}