{
  "type": "Feature",
  "properties": {
    "addr:full":"127 Denbigh St  Feilding Manawatu-Wanganui",
    "addr:housenumber":"127",
    "addr:street":"Denbigh St",
    "iso:country":"NZ",
    "sg:address":"127 Denbigh St ",
    "sg:city":"Feilding",
    "sg:orig_category":"Home And Garden: Furniture/Furnishings: Blinds",
    "sg:phone":"+64 6-323 3900",
    "sg:province":"Manawatu-Wanganui",
    "wof:name":"Shademaster Window Fashions",
    "wof:placetype":"venue"
},
  "geometry": {"coordinates":[175.565674,-40.217216],"type":"Point"}
}