{
  "type": "Feature",
  "properties": {
    "iso:country":"NZ",
    "sg:address":"2 James St ",
    "sg:city":"Whangarei",
    "sg:classifiers":[
        {
            "category":"Shopping",
            "subcategory":"Gifts & Souvenirs",
            "type":"Retail Goods"
        }
    ],
    "sg:phone":"+64 9-438 2236",
    "sg:province":"Northland",
    "sg:tags":[
        "shop",
        "gifts",
        "supplier"
    ],
    "wof:name":"Focus",
    "wof:placetype":"venue"
},
  "geometry": {"coordinates":[174.321106,-35.72559],"type":"Point"}
}