{
  "type": "Feature",
  "properties": {
    "iso:country":"NZ",
    "sg:address":"8 Sheffield St ",
    "sg:city":"Paraparaumu",
    "sg:classifiers":[
        {
            "category":"Sports & Exercise",
            "subcategory":"Swimming Pool",
            "type":"Entertainment"
        }
    ],
    "sg:phone":"+64 4-298 4917",
    "sg:province":"Wellington",
    "sg:tags":[
        "home",
        "outdoor",
        "garden",
        "spa"
    ],
    "wof:name":"Pacific Pools 1987 Ltd",
    "wof:placetype":"venue"
},
  "geometry": {"coordinates":[175.000397,-40.905952],"type":"Point"}
}