{
  "type": "Feature",
  "properties": {
    "addr:full":"43 Nith St  Invercargill Southland",
    "addr:housenumber":"43",
    "addr:street":"Nith St",
    "iso:country":"NZ",
    "sg:address":"43 Nith St ",
    "sg:city":"Invercargill",
    "sg:orig_category":"Transport: Transportation: Furniture Removal/Packers",
    "sg:phone":"+64 3-218 8237",
    "sg:province":"Southland",
    "wof:name":"Purdue Bros Ltd",
    "wof:placetype":"venue"
},
  "geometry": {"coordinates":[168.35041799999999,-46.415962],"type":"Point"}
}