{
  "type": "Feature",
  "properties": {
    "addr:full":"115 Victoria Ave  Wanganui Manawatu-Wanganui",
    "addr:housenumber":"115",
    "addr:street":"Victoria Ave",
    "iso:country":"NZ",
    "sg:address":"115 Victoria Ave ",
    "sg:city":"Wanganui",
    "sg:orig_category":"Shopping: Retail Stores: Books: Bookshops",
    "sg:phone":"+64 6-345 8747",
    "sg:province":"Manawatu-Wanganui",
    "wof:name":"Whitcoulls",
    "wof:placetype":"venue"
},
  "geometry": {"coordinates":[175.050995,-39.932457],"type":"Point"}
}