{
  "type": "Feature",
  "properties": {
    "addr:full":"PO Box 22 376  Otahuhu Auckland",
    "addr:housenumber":"po box 22 376",
    "iso:country":"NZ",
    "sg:address":"PO Box 22 376 ",
    "sg:city":"Otahuhu",
    "sg:classifiers":[
        {
            "category":"Wholesale",
            "subcategory":"Machinery & Supplies",
            "type":"Manufacturing & Wholesale Goods"
        }
    ],
    "sg:phone":"+64 272 300 909",
    "sg:province":"Auckland",
    "sg:tags":[
        "equipment",
        "industrial"
    ],
    "sg:website":"http://www.yellowpages.co.nz/for/discountcranes/dp31525.html",
    "wof:name":"Discount Crane Hire Ltd",
    "wof:placetype":"venue"
},
  "geometry": {"coordinates":[174.85611,-36.940605],"type":"Point"}
}