{
  "type": "Feature",
  "properties": {
    "iso:country":"NZ",
    "sg:address":"3 Russell Rd Manurewa ",
    "sg:city":"Auckland",
    "sg:classifiers":[
        {
            "category":"Social Services",
            "subcategory":"Child Care",
            "type":"Services"
        }
    ],
    "sg:phone":"+64 9-266 3233",
    "sg:province":"Auckland",
    "sg:tags":[
        "home",
        "garden",
        "children"
    ],
    "wof:name":"Te Whanau Tuhonotia Trust",
    "wof:placetype":"venue"
},
  "geometry": {"coordinates":[174.89312699999999,-37.024914],"type":"Point"}
}