{
  "type": "Feature",
  "properties": {
    "iso:country":"NZ",
    "sg:address":"83 The Strand ",
    "sg:city":"Whakatane",
    "sg:classifiers":[
        {
            "category":"Shopping",
            "subcategory":"Pharmacy",
            "type":"Retail Goods"
        }
    ],
    "sg:phone":"+64 7-308 0399",
    "sg:province":"Auckland",
    "sg:tags":[
        "product",
        "health"
    ],
    "wof:name":"Nature Zone Health Shop",
    "wof:placetype":"venue"
},
  "geometry": {"coordinates":[176.99807699999999,-37.950554],"type":"Point"}
}