{
  "type": "Feature",
  "properties": {
    "addr:full":"19 Queen St  Waimate",
    "addr:housenumber":"19",
    "addr:street":"Queen St",
    "iso:country":"NZ",
    "sg:address":"19 Queen St ",
    "sg:city":"Waimate",
    "sg:orig_category":"Automotive: General Services: Service Stations",
    "sg:phone":"+64 3-689 7303",
    "wof:name":"Sadlers Service Station",
    "wof:placetype":"venue"
},
  "geometry": {"coordinates":[171.04478499999999,-44.735359],"type":"Point"}
}