{
  "type": "Feature",
  "properties": {
    "iso:country":"NZ",
    "sg:address":"14 A Parity Pl Glenfield ",
    "sg:city":"Auckland",
    "sg:classifiers":[
        {
            "category":"Shopping",
            "subcategory":"Gifts & Souvenirs",
            "type":"Retail Goods"
        }
    ],
    "sg:phone":"+64 9-443 6396",
    "sg:province":"Auckland",
    "sg:tags":[
        "travel",
        "tourism"
    ],
    "sg:website":"http://www.yellowpages.co.nz/for/badges/dp16240.html",
    "wof:name":"Distinctive Badges",
    "wof:placetype":"venue"
},
  "geometry": {"coordinates":[174.728622,-36.784813],"type":"Point"}
}