{
  "type": "Feature",
  "properties": {
    "addr:full":"Main Rd Te  Karaka",
    "addr:street":"Main Rd",
    "iso:country":"NZ",
    "sg:address":"Main Rd Te ",
    "sg:city":"Karaka",
    "sg:orig_category":"Education And Training: General: Schools",
    "sg:phone":"+64 6-862 3750",
    "wof:name":"Waikohu College",
    "wof:placetype":"venue"
},
  "geometry": {"coordinates":[177.867355,-38.469765],"type":"Point"}
}