{
  "type": "Feature",
  "properties": {
    "iso:country":"NZ",
    "sg:address":"cnr Don & Deveron Sts ",
    "sg:city":"Invercargill",
    "sg:classifiers":[
        {
            "category":"Parking",
            "subcategory":"Garage",
            "type":"Transportation"
        }
    ],
    "sg:phone":"+64 3-218 7364",
    "sg:province":"Southland",
    "sg:tags":[
        "hire",
        "container",
        "transport",
        "lease"
    ],
    "wof:name":"D W Stokes Shipping & Travel Ltd",
    "wof:placetype":"venue"
},
  "geometry": {"coordinates":[168.352173,-46.41185],"type":"Point"}
}