{
  "type": "Feature",
  "properties": {
    "iso:country":"NZ",
    "sg:address":"PO Box 6042 Glenview ",
    "sg:city":"Hamilton",
    "sg:classifiers":[
        {
            "category":"Building & Trades",
            "subcategory":"Pest Control",
            "type":"Services"
        }
    ],
    "sg:phone":"+64 7-839 4505",
    "sg:province":"Waikato",
    "sg:tags":[
        "home",
        "garden"
    ],
    "wof:name":"Enviropro Pest Management",
    "wof:placetype":"venue"
},
  "geometry": {"coordinates":[175.282593,-37.821182],"type":"Point"}
}