{
  "type": "Feature",
  "properties": {
    "addr:full":"5 Grants Rd  Timaru Canterbury",
    "addr:housenumber":"5",
    "addr:street":"Grants Rd",
    "iso:country":"NZ",
    "sg:address":"5 Grants Rd ",
    "sg:city":"Timaru",
    "sg:classifiers":[
        {
            "category":"Autos & Motor Vehicles",
            "subcategory":"Automobile Sales",
            "type":"Retail Goods"
        }
    ],
    "sg:phone":"+64 3-688 8202",
    "sg:province":"Canterbury",
    "sg:tags":[
        "car",
        "-used",
        "leasing",
        "truck",
        "automotive"
    ],
    "wof:name":"Guinans Motors Ltd",
    "wof:placetype":"venue"
},
  "geometry": {"coordinates":[171.24070699999999,-44.373882],"type":"Point"}
}