{
  "type": "Feature",
  "properties": {
    "addr:full":"Main Rd S Tolaga  Bay",
    "addr:street":"Main Rd S Tolaga Bay",
    "iso:country":"NZ",
    "sg:address":"Main Rd S Tolaga ",
    "sg:city":"Bay",
    "sg:orig_category":"Industrial: Engineering: Engineers: Engineers - General",
    "sg:phone":"+64 6-862 6769",
    "wof:name":"Beard Engineering Tolaga Bay Ltd",
    "wof:placetype":"venue"
},
  "geometry": {"coordinates":[178.29631000000001,-38.37804],"type":"Point"}
}