{
  "type": "Feature",
  "properties": {
    "addr:full":"Rapaura Rd  Blenheim Marlborough",
    "addr:street":"Rapaura Rd",
    "iso:country":"NZ",
    "sg:address":"Rapaura Rd ",
    "sg:city":"Blenheim",
    "sg:orig_category":"Storage: Storage",
    "sg:phone":"+64 3-572 8005",
    "sg:province":"Marlborough",
    "wof:name":"Wairau Storage",
    "wof:placetype":"venue"
},
  "geometry": {"coordinates":[173.949387,-41.458393],"type":"Point"}
}