{
  "type": "Feature",
  "properties": {
    "addr:full":"76 Main Rd Kumeu  Auckland Auckland",
    "addr:housenumber":"76",
    "addr:street":"Main Rd",
    "iso:country":"NZ",
    "sg:address":"76 Main Rd Kumeu ",
    "sg:city":"Auckland",
    "sg:classifiers":[
        {
            "category":"Health Services",
            "subcategory":"Health Practitioner",
            "type":"Services"
        }
    ],
    "sg:phone":"+64 9-412 8722",
    "sg:province":"Auckland",
    "sg:tags":[
        "specialist",
        "medical",
        "beauty",
        "specialists"
    ],
    "wof:name":"Country Medical Clinic",
    "wof:placetype":"venue"
},
  "geometry": {"coordinates":[174.56019599999999,-36.777271],"type":"Point"}
}