{
  "type": "Feature",
  "properties": {
    "addr:full":"14 Arohia Pl Snells Beach  Warkworth Auckland",
    "addr:housenumber":"14",
    "addr:street":"Arohia Pl",
    "iso:country":"NZ",
    "sg:address":"14 Arohia Pl Snells Beach ",
    "sg:city":"Warkworth",
    "sg:orig_category":"Transport: Boats And Marine: Products",
    "sg:phone":"+64 9-425 5858",
    "sg:province":"Auckland",
    "wof:name":"Paktronics Systems Ltd",
    "wof:placetype":"venue"
},
  "geometry": {"coordinates":[174.727585,-36.41523],"type":"Point"}
}