{
  "type": "Feature",
  "properties": {
    "iso:country":"NZ",
    "sg:address":"402 George St Dunedin North ",
    "sg:city":"Dunedin",
    "sg:classifiers":[
        {
            "category":"Farming",
            "subcategory":"Fish & Marine Products",
            "type":"Manufacturing & Wholesale Goods"
        }
    ],
    "sg:phone":"+64 3-477 0635",
    "sg:province":"Otago",
    "sg:tags":[
        "health",
        "beauty"
    ],
    "wof:name":"Knox Unichem Pharmacy",
    "wof:placetype":"venue"
},
  "geometry": {"coordinates":[170.507416,-45.867741],"type":"Point"}
}