{
  "type": "Feature",
  "properties": {
    "iso:country":"NZ",
    "sg:address":"65 Carr Rd Mt Roskill ",
    "sg:city":"Auckland",
    "sg:classifiers":[
        {
            "category":"Home & Garden",
            "subcategory":"Building Materials",
            "type":"Retail Goods"
        }
    ],
    "sg:phone":"+64 9-624 1180",
    "sg:province":"Auckland",
    "sg:tags":[
        "shower",
        "fittings",
        "screen",
        "door"
    ],
    "wof:name":"Euroglass Systems Ltd",
    "wof:placetype":"venue"
},
  "geometry": {"coordinates":[174.742767,-36.905895],"type":"Point"}
}