{
  "type": "Feature",
  "properties": {
    "iso:country":"NZ",
    "sg:address":"Thames Valley ",
    "sg:city":"Thames",
    "sg:orig_category":"Automotive: Parts And Supplies: Tyres",
    "sg:phone":"+64 800 466 393",
    "sg:province":"Waikato",
    "sg:website":"http://www.goodyear.co.nz",
    "wof:name":"Goodyear Authorised Dealers",
    "wof:placetype":"venue"
},
  "geometry": {"coordinates":[-72.112679,41.394623],"type":"Point"}
}