{
  "type": "Feature",
  "properties": {
    "iso:country":"NZ",
    "sg:address":"390 Devon St East New ",
    "sg:city":"Plymouth",
    "sg:classifiers":[
        {
            "category":"Personal",
            "type":"Services"
        }
    ],
    "sg:phone":"+64 6-759 9099",
    "sg:province":"Taranaki",
    "sg:tags":[
        "arrangements",
        "wedding"
    ],
    "sg:website":"http://www.devonhotel.co.nz",
    "wof:name":"The Devon Hotel & Conference Centre",
    "wof:placetype":"venue"
},
  "geometry": {"coordinates":[-116.819725,43.97221],"type":"Point"}
}