{
  "type": "Feature",
  "properties": {
    "addr:full":"26 Moore St  Cambridge Waikato",
    "addr:housenumber":"26",
    "addr:street":"Moore St",
    "iso:country":"NZ",
    "sg:address":"26 Moore St ",
    "sg:city":"Cambridge",
    "sg:classifiers":[
        {
            "category":"Shopping",
            "subcategory":"Pets & Pet Supplies",
            "type":"Retail Goods"
        }
    ],
    "sg:phone":"+64 7-823 4288",
    "sg:province":"Waikato",
    "sg:tags":[
        "home",
        "grooming",
        "garden",
        "pets"
    ],
    "wof:name":"Cambridge K9 Groomers",
    "wof:placetype":"venue"
},
  "geometry": {"coordinates":[-71.093857,42.365589],"type":"Point"}
}