{
  "type": "Feature",
  "properties": {
    "addr:full":"11 Mangahao Rd  Pahiatua",
    "addr:housenumber":"11",
    "addr:street":"Mangahao Rd",
    "iso:country":"NZ",
    "sg:address":"11 Mangahao Rd ",
    "sg:city":"Pahiatua",
    "sg:classifiers":[
        {
            "category":"Banks & Credit Unions",
            "subcategory":"Investment Brokerage",
            "type":"Services"
        }
    ],
    "sg:phone":"+64 6-376 7476",
    "sg:tags":[
        "personal",
        "accountant",
        "chartered",
        "-",
        "finance"
    ],
    "wof:name":"Shinnick Fouhy Limited",
    "wof:placetype":"venue"
},
  "geometry": {"coordinates":[175.83514400000001,-40.450596],"type":"Point"}
}