{
  "type": "Feature",
  "properties": {
    "addr:full":"47 Commerce St  Whangarei Northland",
    "addr:housenumber":"47",
    "addr:street":"Commerce St",
    "iso:country":"NZ",
    "sg:address":"47 Commerce St ",
    "sg:city":"Whangarei",
    "sg:classifiers":[
        {
            "category":"Home & Garden",
            "subcategory":"Building Materials",
            "type":"Retail Goods"
        }
    ],
    "sg:phone":"+64 9-438 8946",
    "sg:province":"Northland",
    "sg:tags":[
        "door",
        "fitting",
        "fittings"
    ],
    "wof:name":"Doors Northland Ltd",
    "wof:placetype":"venue"
},
  "geometry": {"coordinates":[174.32556199999999,-35.730915],"type":"Point"}
}