{
  "type": "Feature",
  "properties": {
    "addr:full":"41 School Rd Riwaka  Motueka Tasman",
    "addr:housenumber":"41",
    "addr:street":"School Rd",
    "iso:country":"NZ",
    "sg:address":"41 School Rd Riwaka ",
    "sg:city":"Motueka",
    "sg:classifiers":[
        {
            "category":"Health Services",
            "subcategory":"Hospital",
            "type":"Services"
        }
    ],
    "sg:phone":"+64 800 111 025",
    "sg:province":"Tasman",
    "sg:tags":[
        "medical",
        "beauty",
        "ambulance"
    ],
    "wof:name":"Motueka Regional Ambulance",
    "wof:placetype":"venue"
},
  "geometry": {"coordinates":[173.013443,-41.108101],"type":"Point"}
}