{
  "type": "Feature",
  "properties": {
    "addr:full":"745 Gt South Rd Otahuhu  Auckland Auckland",
    "addr:housenumber":"745",
    "addr:street":"Gt South Rd",
    "iso:country":"NZ",
    "sg:address":"745 Gt South Rd Otahuhu ",
    "sg:city":"Auckland",
    "sg:classifiers":[
        {
            "category":"Retail",
            "subcategory":"Storage",
            "type":"Services"
        }
    ],
    "sg:phone":"+64 9-276 0925",
    "sg:province":"Auckland",
    "sg:website":"http://www.yellowpages.co.nz/pages/201185031/dp39983.html",
    "wof:name":"Commercial Office Equipment Ltd",
    "wof:placetype":"venue"
},
  "geometry": {"coordinates":[174.85611,-36.940605],"type":"Point"}
}