{
  "type": "Feature",
  "properties": {
    "addr:full":"107 Riri St  Rotorua Bay of Plenty",
    "addr:housenumber":"107",
    "addr:street":"Riri St",
    "iso:country":"NZ",
    "sg:address":"107 Riri St ",
    "sg:city":"Rotorua",
    "sg:orig_category":"Automotive: Parts And Supplies: Automotive Dismantlers",
    "sg:phone":"+64 7-348 9049",
    "sg:province":"Bay of Plenty",
    "wof:name":"A 1 Used Parts",
    "wof:placetype":"venue"
},
  "geometry": {"coordinates":[176.22726399999999,-38.133522],"type":"Point"}
}