{
  "type": "Feature",
  "properties": {
    "iso:country":"NZ",
    "sg:address":"Olson St Egmont ",
    "sg:city":"Village",
    "sg:classifiers":[
        {
            "category":"Professional",
            "subcategory":"Art Services",
            "type":"Services"
        }
    ],
    "sg:phone":"+64 6-752 2788",
    "sg:tags":[
        "picture",
        "arts",
        "sport",
        "framing",
        "leisure"
    ],
    "wof:name":"Frameworks",
    "wof:placetype":"venue"
},
  "geometry": {"coordinates":[174.145157,-39.148235],"type":"Point"}
}