{
  "type": "Feature",
  "properties": {
    "addr:full":"260 Dee St PO Box 1005  Invercargill Southland",
    "addr:housenumber":"260",
    "addr:postcode":"box 1005",
    "addr:street":"Dee St Po",
    "iso:country":"NZ",
    "sg:address":"260 Dee St PO Box 1005 ",
    "sg:city":"Invercargill",
    "sg:orig_category":"Industrial: Parts: Bearings",
    "sg:phone":"+64 3-218 7174",
    "sg:province":"Southland",
    "sg:website":"http://www.yellowpages.co.nz/for/jjltd/dp23164.html",
    "wof:name":"J J Ltd",
    "wof:placetype":"venue"
},
  "geometry": {"coordinates":[168.35217299999999,-46.411854],"type":"Point"}
}