{
  "type": "Feature",
  "properties": {
    "addr:full":"E2/119 Meadowland Dve Howick  Auckland Auckland",
    "addr:housenumber":"119",
    "addr:street":"Meadowland Dve",
    "iso:country":"NZ",
    "sg:address":"E2/119 Meadowland Dve Howick ",
    "sg:city":"Auckland",
    "sg:classifiers":[
        {
            "category":"Education",
            "subcategory":"Music School",
            "type":"Public Place"
        }
    ],
    "sg:phone":"+64 9-537 1613",
    "sg:province":"Auckland",
    "sg:tags":[
        "sport",
        "teacher",
        "leisure"
    ],
    "wof:name":"Amateur Music Ltd",
    "wof:placetype":"venue"
},
  "geometry": {"coordinates":[174.76205400000001,-36.882732],"type":"Point"}
}