{
  "type": "Feature",
  "properties": {
    "addr:full":"cnr Rathbone & Robert Sts  Whangarei Northland",
    "addr:housenumber":"whangarei",
    "addr:street":"Cnr Rathbone & Robert Sts",
    "iso:country":"NZ",
    "sg:address":"cnr Rathbone & Robert Sts ",
    "sg:city":"Whangarei",
    "sg:classifiers":[
        {
            "category":"Travel",
            "subcategory":"Travel Agent",
            "type":"Entertainment"
        }
    ],
    "sg:phone":"+64 9-438 2333",
    "sg:province":"Northland",
    "sg:tags":[
        "tourism",
        "broker"
    ],
    "wof:name":"Stephen Gillingham House Of Travel",
    "wof:placetype":"venue"
},
  "geometry": {"coordinates":[174.320526,-35.725399],"type":"Point"}
}