{
  "type": "Feature",
  "properties": {
    "addr:full":"62 Kaiwharawhara Rd Kaiwharawhara  Wellington Wellington",
    "addr:housenumber":"62",
    "addr:street":"Kaiwharawhara Rd",
    "iso:country":"NZ",
    "sg:address":"62 Kaiwharawhara Rd Kaiwharawhara ",
    "sg:city":"Wellington",
    "sg:orig_category":"Shopping: Sports Retailers: Sports Goods: Canvas Goods",
    "sg:phone":"+64 4-472 2110",
    "sg:province":"Wellington",
    "wof:name":"Capital Canvas Company Ltd",
    "wof:placetype":"venue"
},
  "geometry": {"coordinates":[174.78511,-41.257629],"type":"Point"}
}