{
  "type": "Feature",
  "properties": {
    "iso:country":"NZ",
    "sg:address":"503 Port Rd ",
    "sg:city":"Whangamata",
    "sg:orig_category":"Health And Beauty: Products: Pharmacies",
    "sg:phone":"+64 7-865 9398",
    "wof:name":"Schicker's Unichem Pharmacy Ltd",
    "wof:placetype":"venue"
},
  "geometry": {"coordinates":[175.877808,-37.200172],"type":"Point"}
}