{
  "type": "Feature",
  "properties": {
    "addr:full":"Downtown Shopping Centre Broadway Ave Palmerston  Palmerston North Manawatu-Wanganui",
    "addr:street":"Broadway Ave",
    "iso:country":"NZ",
    "sg:address":"Downtown Shopping Centre Broadway Ave Palmerston ",
    "sg:city":"Palmerston North",
    "sg:orig_category":"Shopping: Accessories: Jewellers And Watchmakers",
    "sg:phone":"+64 6-358 3670",
    "sg:province":"Manawatu-Wanganui",
    "wof:name":"Downtown Souvenirs",
    "wof:placetype":"venue"
},
  "geometry": {"coordinates":[-118.25245700000001,34.039051],"type":"Point"}
}