{
  "type": "Feature",
  "properties": {
    "iso:country":"NZ",
    "sg:address":"20 Ribble St ",
    "sg:city":"Oamaru",
    "sg:classifiers":[
        {
            "category":"Wholesale",
            "subcategory":"Hardware",
            "type":"Manufacturing & Wholesale Goods"
        }
    ],
    "sg:phone":"+64 3-434 6913",
    "sg:province":"Otago",
    "sg:tags":[
        "gardening",
        "garden",
        "chainsaw",
        "products",
        "brush",
        "home",
        "cutter"
    ],
    "wof:name":"Oamaru Motor Cycles",
    "wof:placetype":"venue"
},
  "geometry": {"coordinates":[170.973984,-45.095943],"type":"Point"}
}