{
  "type": "Feature",
  "properties": {
    "addr:full":"cnr Maunganui & Girven Rds Mt  Maunganui Bay of Plenty",
    "addr:street":"Cnr Maunganui & Girven Rds;Maunganui Bay",
    "iso:country":"NZ",
    "sg:address":"cnr Maunganui & Girven Rds Mt ",
    "sg:city":"Maunganui",
    "sg:classifiers":[
        {
            "category":"Shopping Center",
            "type":"Public Place"
        }
    ],
    "sg:phone":"+64 7-575 9349",
    "sg:province":"Bay of Plenty",
    "sg:tags":[
        "mall",
        "retail",
        "stores"
    ],
    "wof:name":"Bayfair Shopping Centre",
    "wof:placetype":"venue"
},
  "geometry": {"coordinates":[176.18627900000001,-37.641048],"type":"Point"}
}