{
  "type": "Feature",
  "properties": {
    "addr:full":"61-63 Rugby St  Wellington Wellington",
    "addr:housenumber":"61-63",
    "addr:street":"Rugby St",
    "iso:country":"NZ",
    "sg:address":"61-63 Rugby St ",
    "sg:city":"Wellington",
    "sg:classifiers":[
        {
            "category":"Professional",
            "type":"Services"
        }
    ],
    "sg:phone":"+64 4-385 8476",
    "sg:province":"Wellington",
    "sg:tags":[
        "services",
        "car",
        "valet",
        "automotive"
    ],
    "wof:name":"Bruce Condren's Car Grooming",
    "wof:placetype":"venue"
},
  "geometry": {"coordinates":[174.77862500000001,-41.300865],"type":"Point"}
}