{
  "type": "Feature",
  "properties": {
    "addr:full":"7 Old Renwick Rd  Blenheim Marlborough",
    "addr:housenumber":"7",
    "addr:street":"Old Renwick Rd",
    "iso:country":"NZ",
    "sg:address":"7 Old Renwick Rd ",
    "sg:city":"Blenheim",
    "sg:classifiers":[
        {
            "category":"Social Services",
            "subcategory":"Child Care",
            "type":"Services"
        }
    ],
    "sg:phone":"+64 3-578 8680",
    "sg:province":"Marlborough",
    "sg:tags":[
        "home",
        "garden",
        "children"
    ],
    "wof:name":"Wairau Preschool",
    "wof:placetype":"venue"
},
  "geometry": {"coordinates":[173.95262099999999,-41.498352],"type":"Point"}
}