{
  "type": "Feature",
  "properties": {
    "iso:country":"NZ",
    "sg:address":"56 Livingstone St ",
    "sg:city":"Hokitika",
    "sg:classifiers":[
        {
            "category":"Ice Cream",
            "type":"Food & Drink"
        }
    ],
    "sg:phone":"+64 3-756 9800",
    "sg:province":"West Coast",
    "sg:tags":[
        "dairy",
        "product",
        "-"
    ],
    "wof:name":"Westland Milk Products",
    "wof:placetype":"venue"
},
  "geometry": {"coordinates":[170.97996499999999,-42.72057],"type":"Point"}
}