{
  "type": "Feature",
  "properties": {
    "iso:country":"NZ",
    "sg:address":"57 St Lukes Rd Mt Albert ",
    "sg:city":"Auckland",
    "sg:classifiers":[
        {
            "category":"Professional",
            "type":"Services"
        }
    ],
    "sg:phone":"+64 9-846 5329",
    "sg:province":"Auckland",
    "sg:tags":[
        "services",
        "car",
        "valet",
        "automotive"
    ],
    "wof:name":"Washworld Services (Auckland) Ltd",
    "wof:placetype":"venue"
},
  "geometry": {"coordinates":[174.731277,-36.882317],"type":"Point"}
}