{
  "type": "Feature",
  "properties": {
    "iso:country":"NZ",
    "sg:address":"Onerahi Shopping Centre Onerahi ",
    "sg:city":"Whangarei",
    "sg:orig_category":"Shopping: Retail Stores: Books",
    "sg:phone":"+64 9-436 5037",
    "sg:province":"Northland",
    "wof:name":"Onerahi Bookshop & Lotto OBL",
    "wof:placetype":"venue"
},
  "geometry": {"coordinates":[174.36286899999999,-35.765949],"type":"Point"}
}