{
  "type": "Feature",
  "properties": {
    "addr:full":"40 Ward St Wallaceville Upper  Hutt Wellington",
    "addr:housenumber":"40",
    "addr:street":"Ward St",
    "iso:country":"NZ",
    "sg:address":"40 Ward St Wallaceville Upper ",
    "sg:city":"Hutt",
    "sg:orig_category":"Industrial: Energy And Utilities: Gas",
    "sg:phone":"+64 4-528 2580",
    "sg:province":"Wellington",
    "wof:name":"Bristol Motors",
    "wof:placetype":"venue"
},
  "geometry": {"coordinates":[175.05566400000001,-41.129284],"type":"Point"}
}