{
  "type": "Feature",
  "properties": {
    "addr:full":"PO Box 45-153 Te Atatu Peninsula  Auckland Auckland",
    "addr:housenumber":"po box 45-153",
    "iso:country":"NZ",
    "sg:address":"PO Box 45-153 Te Atatu Peninsula ",
    "sg:city":"Auckland",
    "sg:orig_category":"Industrial: Parts: Pipes, Tubes And Cabling: Cables",
    "sg:phone":"+64 9-834 4764",
    "sg:province":"Auckland",
    "wof:name":"Network Cabling Solutions",
    "wof:placetype":"venue"
},
  "geometry": {"coordinates":[174.65112300000001,-36.841228],"type":"Point"}
}