{
  "type": "Feature",
  "properties": {
    "iso:country":"NZ",
    "sg:address":"PO Box 45-153 Te Atatu Peninsula ",
    "sg:city":"Auckland",
    "sg:orig_category":"Industrial: Parts: Pipes, Tubes And Cabling: Cables",
    "sg:phone":"+64 9-834 4764",
    "sg:province":"Auckland",
    "wof:name":"Network Cabling Solutions",
    "wof:placetype":"venue"
},
  "geometry": {"coordinates":[174.651123,-36.841228],"type":"Point"}
}