{
  "type": "Feature",
  "properties": {
    "addr:full":"High Point Shopping Centre Mokoia Rd Birkenhead  Auckland Auckland",
    "addr:street":"Mokoia Rd",
    "iso:country":"NZ",
    "sg:address":"High Point Shopping Centre Mokoia Rd Birkenhead ",
    "sg:city":"Auckland",
    "sg:orig_category":"Home And Garden: Accessories: Decorations",
    "sg:phone":"+64 9-419 7278",
    "sg:province":"Auckland",
    "wof:name":"Party on Party Shop",
    "wof:placetype":"venue"
},
  "geometry": {"coordinates":[174.734467,-36.818214],"type":"Point"}
}