{
  "type": "Feature",
  "properties": {
    "addr:full":"43 A Church St Devonport  Auckland Auckland",
    "addr:housenumber":"43 a",
    "addr:street":"Church St",
    "iso:country":"NZ",
    "sg:address":"43 A Church St Devonport ",
    "sg:city":"Auckland",
    "sg:orig_category":"Transport: Boats And Marine: Shipping: Shipping Companies",
    "sg:phone":"+64 9-445 3000",
    "sg:province":"Auckland",
    "wof:name":"Gilfoyle Shipping Services Ltd",
    "wof:placetype":"venue"
},
  "geometry": {"coordinates":[174.801636,-36.826771],"type":"Point"}
}