{
  "type": "Feature",
  "properties": {
    "addr:full":"84 Commercial St  Takaka",
    "addr:housenumber":"84",
    "addr:street":"Commercial St",
    "iso:country":"NZ",
    "sg:address":"84 Commercial St ",
    "sg:city":"Takaka",
    "sg:classifiers":[
        {
            "category":"Social Services",
            "subcategory":"Job Training",
            "type":"Services"
        }
    ],
    "sg:phone":"+64 3-525 8099",
    "sg:tags":[
        "education"
    ],
    "wof:name":"Golden Bay Work Centre Trust",
    "wof:placetype":"venue"
},
  "geometry": {"coordinates":[172.80714399999999,-40.85276],"type":"Point"}
}