{
  "type": "Feature",
  "properties": {
    "iso:country":"NZ",
    "sg:address":"Main Rd ",
    "sg:city":"Havelock",
    "sg:classifiers":[
        {
            "category":"Fast Food",
            "type":"Food & Drink"
        }
    ],
    "sg:phone":"+64 3-574 2944",
    "sg:tags":[
        "wining",
        "dining",
        "takeaway"
    ],
    "wof:name":"Havelock Gold N Store",
    "wof:placetype":"venue"
},
  "geometry": {"coordinates":[-94.702415,42.835812],"type":"Point"}
}