{
  "type": "Feature",
  "properties": {
    "iso:country":"NZ",
    "sg:address":"Main Rd Grovetown ",
    "sg:city":"Blenheim",
    "sg:classifiers":[
        {
            "category":"Professional",
            "type":"Services"
        }
    ],
    "sg:phone":"+64 3-578 5525",
    "sg:province":"Marlborough",
    "sg:tags":[
        "function",
        "entertainment",
        "leisure",
        "planning",
        "party",
        "sport"
    ],
    "wof:name":"Grovetown Hotel",
    "wof:placetype":"venue"
},
  "geometry": {"coordinates":[173.962524,-41.481834],"type":"Point"}
}