{
  "type": "Feature",
  "properties": {
    "iso:country":"NZ",
    "sg:address":"50 David Cre Karori ",
    "sg:city":"Wellington",
    "sg:orig_category":"Transport: Air: Airport Services",
    "sg:phone":"+64 4-476 2233",
    "sg:province":"Wellington",
    "wof:name":"Capital Jet Services Ltd",
    "wof:placetype":"venue"
},
  "geometry": {"coordinates":[174.73803699999999,-41.279667],"type":"Point"}
}