{
  "type": "Feature",
  "properties": {
    "iso:country":"NZ",
    "sg:address":"117 Elizabeth St Kew ",
    "sg:city":"Invercargill",
    "sg:classifiers":[
        {
            "category":"Health Services",
            "subcategory":"Dentist",
            "type":"Services"
        }
    ],
    "sg:phone":"+64 3-218 6962",
    "sg:province":"Southland",
    "sg:tags":[
        "dental",
        "clinic",
        "beauty"
    ],
    "wof:name":"Kew School Dental Clinic",
    "wof:placetype":"venue"
},
  "geometry": {"coordinates":[168.35818499999999,-46.434261],"type":"Point"}
}