{
  "type": "Feature",
  "properties": {
    "iso:country":"NZ",
    "sg:address":"87 Taylor Tce Tawa ",
    "sg:city":"Porirua",
    "sg:classifiers":[
        {
            "category":"Professional",
            "type":"Services"
        }
    ],
    "sg:phone":"+64 4-232 8231",
    "sg:province":"Wellington",
    "sg:tags":[
        "home",
        "cleaning",
        "help",
        "garden"
    ],
    "wof:name":"Heavenly Helpers",
    "wof:placetype":"venue"
},
  "geometry": {"coordinates":[174.824203,-41.17149],"type":"Point"}
}