{
  "type": "Feature",
  "properties": {
    "addr:full":"Youth Hostel 3 Simpson La Lake  Tekapo",
    "addr:housenumber":"3",
    "addr:street":"Simpson La Lake",
    "iso:country":"NZ",
    "sg:address":"Youth Hostel 3 Simpson La Lake ",
    "sg:city":"Tekapo",
    "sg:orig_category":"Travel And Tourism: Accommodation: Backpackers",
    "sg:phone":"+64 3-680 6857",
    "wof:name":"YHA Hostels",
    "wof:placetype":"venue"
},
  "geometry": {"coordinates":[170.48287999999999,-44.00576],"type":"Point"}
}