{
  "type": "Feature",
  "properties": {
    "iso:country":"NZ",
    "sg:address":"159 Victoria Ave ",
    "sg:city":"Wanganui",
    "sg:classifiers":[
        {
            "category":"Bars & Pubs",
            "subcategory":"Wine Bar",
            "type":"Food & Drink"
        }
    ],
    "sg:phone":"+64 6-345 2046",
    "sg:province":"Manawatu-Wanganui",
    "sg:tags":[
        "wining",
        "dining",
        "cafe"
    ],
    "wof:name":"T JAYZ",
    "wof:placetype":"venue"
},
  "geometry": {"coordinates":[175.049149,-39.931351],"type":"Point"}
}