{
  "type": "Feature",
  "properties": {
    "addr:full":"20 Eric Paton Way Mt Wellington  Auckland Auckland",
    "addr:housenumber":"20",
    "addr:street":"Eric Paton Way",
    "iso:country":"NZ",
    "sg:address":"20 Eric Paton Way Mt Wellington ",
    "sg:city":"Auckland",
    "sg:classifiers":[
        {
            "category":"Banks & Credit Unions",
            "subcategory":"Investment Brokerage",
            "type":"Services"
        }
    ],
    "sg:phone":"+64 9-570 5145",
    "sg:province":"Auckland",
    "sg:tags":[
        "chemical",
        "industrial",
        "-",
        "compounds"
    ],
    "wof:name":"Quality Transport Equipment NZ Ltd",
    "wof:placetype":"venue"
},
  "geometry": {"coordinates":[174.83029199999999,-36.909569],"type":"Point"}
}