{
  "type": "Feature",
  "properties": {
    "addr:full":"Ground Floor, 192 Willis St  Wellington Wellington",
    "addr:housenumber":"192",
    "addr:street":"Ground Floor;Willis St",
    "iso:country":"NZ",
    "sg:address":"Ground Floor, 192 Willis St ",
    "sg:city":"Wellington",
    "sg:classifiers":[
        {
            "category":"Communications",
            "subcategory":"Film & Video Production",
            "type":"Services"
        }
    ],
    "sg:phone":"+64 4-381 3987",
    "sg:province":"Wellington",
    "sg:tags":[
        "sport",
        "leisure",
        "library",
        "entertainment"
    ],
    "wof:name":"The Source Wellington Videos Ltd",
    "wof:placetype":"venue"
},
  "geometry": {"coordinates":[-119.27385700000001,38.661472],"type":"Point"}
}