{
  "type": "Feature",
  "properties": {
    "iso:country":"NZ",
    "sg:address":"5 G Miro Pl Albany ",
    "sg:city":"Auckland",
    "sg:classifiers":[
        {
            "category":"Home & Garden",
            "subcategory":"Building Materials",
            "type":"Retail Goods"
        }
    ],
    "sg:phone":"+64 9-414 7330",
    "sg:province":"Auckland",
    "sg:tags":[
        "fittings",
        "staircase",
        "handrail"
    ],
    "wof:name":"Sellwood Products",
    "wof:placetype":"venue"
},
  "geometry": {"coordinates":[174.71781899999999,-36.738342],"type":"Point"}
}