{
  "type": "Feature",
  "properties": {
    "iso:country":"NZ",
    "sg:address":"Westfield Shoppingtown ",
    "sg:city":"Auckland",
    "sg:orig_category":"Shopping: Retail Stores: Stationery",
    "sg:phone":"+64 9-441 7084",
    "sg:province":"Auckland",
    "wof:name":"Paper Plus",
    "wof:placetype":"venue"
},
  "geometry": {"coordinates":[174.630798,-36.818272],"type":"Point"}
}