{
  "type": "Feature",
  "properties": {
    "iso:country":"NZ",
    "sg:address":"12 Portage Rd New Lynn ",
    "sg:city":"Auckland",
    "sg:classifiers":[
        {
            "category":"Manufacturing",
            "subcategory":"Metals",
            "type":"Manufacturing & Wholesale Goods"
        }
    ],
    "sg:phone":"+64 9-827 3358",
    "sg:province":"Auckland",
    "sg:tags":[
        "-",
        "engineering",
        "industrial",
        "sheet",
        "engineer"
    ],
    "wof:name":"Fagan & Hannay Sheetmetals Ltd",
    "wof:placetype":"venue"
},
  "geometry": {"coordinates":[174.690079,-36.904873],"type":"Point"}
}