{
  "type": "Feature",
  "properties": {
    "addr:full":"cnr Clyde & Ilam Rds 291 Clyde Rd Fendalton  Christchurch Canterbury",
    "addr:housenumber":"291",
    "addr:street":"Cnr Clyde;Rds;Clyde Rd",
    "iso:country":"NZ",
    "sg:address":"cnr Clyde & Ilam Rds 291 Clyde Rd Fendalton ",
    "sg:city":"Christchurch",
    "sg:classifiers":[
        {
            "category":"Health Services",
            "subcategory":"Dentist",
            "type":"Services"
        }
    ],
    "sg:phone":"+64 3-351 2477",
    "sg:province":"Canterbury",
    "sg:tags":[
        "dental",
        "beauty"
    ],
    "wof:name":"Canham John",
    "wof:placetype":"venue"
},
  "geometry": {"coordinates":[172.596756,-43.516548],"type":"Point"}
}