{
  "type": "Feature",
  "properties": {
    "iso:country":"NZ",
    "sg:address":"82 Meeanee Qy Westshore ",
    "sg:city":"Napier",
    "sg:classifiers":[
        {
            "category":"Restaurant",
            "type":"Food & Drink"
        }
    ],
    "sg:phone":"+64 6-835 9707",
    "sg:province":"Hawke's Bay",
    "sg:tags":[
        "merchant",
        "fish",
        "sea"
    ],
    "wof:name":"Quay Fish & Chips Takeaways",
    "wof:placetype":"venue"
},
  "geometry": {"coordinates":[176.888443,-39.481701],"type":"Point"}
}