{
  "type": "Feature",
  "properties": {
    "addr:full":"25 James St  Balclutha",
    "addr:housenumber":"25",
    "addr:street":"James St",
    "iso:country":"NZ",
    "sg:address":"25 James St ",
    "sg:city":"Balclutha",
    "sg:classifiers":[
        {
            "category":"Communications",
            "subcategory":"Film & Video Production",
            "type":"Services"
        }
    ],
    "sg:phone":"+64 3-418 2409",
    "sg:tags":[
        "sport",
        "leisure",
        "library",
        "entertainment"
    ],
    "wof:name":"Willetts Radio & TV Ltd",
    "wof:placetype":"venue"
},
  "geometry": {"coordinates":[169.74105800000001,-46.238518],"type":"Point"}
}