{
  "type": "Feature",
  "properties": {
    "addr:full":"Dee St Physio & Rehab Centre Dee St Mt Maunganui Tauranga Bay of Plenty",
    "addr:street":"Dee St;Dee St",
    "iso:country":"NZ",
    "sg:address":"Dee St Physio & Rehab Centre Dee St Mt Maunganui",
    "sg:city":"Tauranga",
    "sg:classifiers":[
        {
            "category":"Health Services",
            "subcategory":"Health Practitioner",
            "type":"Services"
        }
    ],
    "sg:phone":"+64 7-576 1516",
    "sg:province":"Bay of Plenty",
    "sg:tags":[
        "services",
        "beauty",
        "acupuncturists"
    ],
    "wof:name":"Konrad Dubbeldam",
    "wof:placetype":"venue"
},
  "geometry": {"coordinates":[176.18627900000001,-37.641048],"type":"Point"}
}