{
  "type": "Feature",
  "properties": {
    "addr:full":"8 St George St Papatoetoe  Auckland Auckland",
    "addr:housenumber":"8",
    "addr:street":"St George St",
    "iso:country":"NZ",
    "sg:address":"8 St George St Papatoetoe ",
    "sg:city":"Auckland",
    "sg:orig_category":"Shopping: Retail Stores: General Stores",
    "sg:phone":"+64 9-277 6226",
    "sg:province":"Auckland",
    "wof:name":"Uday Sons (NZ) Limited",
    "wof:placetype":"venue"
},
  "geometry": {"coordinates":[174.851562,-36.979603],"type":"Point"}
}