{
  "type": "Feature",
  "properties": {
    "addr:full":"8/124 Ocean View Rd Oneroa  Auckland Auckland",
    "addr:housenumber":"8 / 124",
    "addr:street":"Ocean View Rd",
    "iso:country":"NZ",
    "sg:address":"8/124 Ocean View Rd Oneroa ",
    "sg:city":"Auckland",
    "sg:classifiers":[
        {
            "category":"Shopping",
            "subcategory":"Gifts & Souvenirs",
            "type":"Retail Goods"
        }
    ],
    "sg:phone":"+64 9-372 7094",
    "sg:province":"Auckland",
    "sg:tags":[
        "shop",
        "gifts",
        "supplier"
    ],
    "wof:name":"Waiheke Arts & Crafts",
    "wof:placetype":"venue"
},
  "geometry": {"coordinates":[174.732178,-36.843193],"type":"Point"}
}