{
  "type": "Feature",
  "properties": {
    "iso:country":"NZ",
    "sg:address":"78 C Riccarton Rd Riccarton ",
    "sg:city":"Christchurch",
    "sg:classifiers":[
        {
            "category":"Recreation",
            "subcategory":"Gun Range",
            "type":"Entertainment"
        }
    ],
    "sg:phone":"+64 3-348 0656",
    "sg:province":"Canterbury",
    "sg:tags":[
        "sports",
        "sport",
        "-",
        "leisure",
        "gunsmith"
    ],
    "wof:name":"Shooters Supplies Ltd",
    "wof:placetype":"venue"
},
  "geometry": {"coordinates":[172.603256,-43.529366],"type":"Point"}
}