{
  "type": "Feature",
  "properties": {
    "addr:full":"Herbert St  Greymouth West Coast",
    "addr:street":"Herbert St",
    "iso:country":"NZ",
    "sg:address":"Herbert St ",
    "sg:city":"Greymouth",
    "sg:orig_category":"Transport: Transportation: Transport Operators",
    "sg:phone":"+64 3-768 4058",
    "sg:province":"West Coast",
    "wof:name":"Trans-West Freighters",
    "wof:placetype":"venue"
},
  "geometry": {"coordinates":[171.20735199999999,-42.449245],"type":"Point"}
}