{
  "type": "Feature",
  "properties": {
    "iso:country":"NZ",
    "sg:address":"292 Flaxmere Ave Flaxmere ",
    "sg:city":"Hastings",
    "sg:orig_category":"Transport: Air: Air Charter Services",
    "sg:phone":"+64 252770364",
    "sg:province":"Hawke's Bay",
    "wof:name":"Silver Wing Charters",
    "wof:placetype":"venue"
},
  "geometry": {"coordinates":[176.7742,-39.615788],"type":"Point"}
}