{
  "type": "Feature",
  "properties": {
    "iso:country":"NZ",
    "sg:address":"Paisley Pl/Gabador Pl, Mt Wgtn ",
    "sg:city":"Auckland",
    "sg:classifiers":[
        {
            "category":"Shopping",
            "subcategory":"Discount & Variety Stores",
            "type":"Retail Goods"
        }
    ],
    "sg:phone":"+64 9-571 1270",
    "sg:province":"Auckland",
    "sg:tags":[
        "storage",
        "cool"
    ],
    "wof:name":"P&O Cold Logistics (NZ) Ltd",
    "wof:placetype":"venue"
},
  "geometry": {"coordinates":[-119.10457599999999,36.597755],"type":"Point"}
}