{
  "type": "Feature",
  "properties": {
    "addr:full":"137 Quay St Auckland Central  Auckland Auckland",
    "addr:housenumber":"137",
    "addr:street":"Quay St",
    "iso:country":"NZ",
    "sg:address":"137 Quay St Auckland Central ",
    "sg:city":"Auckland",
    "sg:classifiers":[
        {
            "category":"Travel",
            "subcategory":"Hotels & Motels",
            "type":"Entertainment"
        }
    ],
    "sg:phone":"+64 9-309 9304",
    "sg:province":"Auckland",
    "sg:tags":[
        "duty",
        "shop",
        "tourism",
        "free"
    ],
    "wof:name":"Louis Vuitton New Zealand Ltd",
    "wof:placetype":"venue"
},
  "geometry": {"coordinates":[174.76561000000001,-36.842777],"type":"Point"}
}