{
  "type": "Feature",
  "properties": {
    "iso:country":"NZ",
    "sg:address":"69 A South Rd New ",
    "sg:city":"Plymouth",
    "sg:classifiers":[
        {
            "category":"Home & Garden",
            "subcategory":"Home Furnishings",
            "type":"Retail Goods"
        }
    ],
    "sg:phone":"+64 252249071",
    "sg:province":"Taranaki",
    "sg:tags":[
        "furniture/furnishings",
        "bedding",
        "bed"
    ],
    "wof:name":"MrB Waterbed Specialist",
    "wof:placetype":"venue"
},
  "geometry": {"coordinates":[-70.544678,41.900955],"type":"Point"}
}