{
  "type": "Feature",
  "properties": {
    "addr:full":"57 Ninth Ave  Tauranga Bay of Plenty",
    "addr:housenumber":"57",
    "addr:street":"Ninth Ave",
    "iso:country":"NZ",
    "sg:address":"57 Ninth Ave ",
    "sg:city":"Tauranga",
    "sg:classifiers":[
        {
            "category":"Shopping",
            "subcategory":"Crafts & Fabrics",
            "type":"Retail Goods"
        }
    ],
    "sg:phone":"+64 7-577 9397",
    "sg:province":"Bay of Plenty",
    "sg:tags":[
        "arts",
        "sport",
        "art",
        "leisure",
        "supply"
    ],
    "wof:name":"Prestige Framing & Gallery",
    "wof:placetype":"venue"
},
  "geometry": {"coordinates":[176.16068999999999,-37.694885],"type":"Point"}
}