{
  "type": "Feature",
  "properties": {
    "iso:country":"NZ",
    "sg:address":"4 Bougainville St ",
    "sg:city":"Whangarei",
    "sg:classifiers":[
        {
            "category":"Home & Garden",
            "subcategory":"Building Materials",
            "type":"Retail Goods"
        }
    ],
    "sg:phone":"+64 9-430 3660",
    "sg:province":"Northland",
    "sg:tags":[
        "fittings",
        "staircase",
        "handrail"
    ],
    "sg:website":"http://www.engineeringservices.co.nz/",
    "wof:name":"Engineering Services (Nth 1988) Ltd",
    "wof:placetype":"venue"
},
  "geometry": {"coordinates":[174.335693,-35.741997],"type":"Point"}
}