{
  "type": "Feature",
  "properties": {
    "addr:full":"20B Huia Rd  Otahuhu Auckland",
    "addr:housenumber":"20b",
    "addr:street":"Huia Rd",
    "iso:country":"NZ",
    "sg:address":"20B Huia Rd ",
    "sg:city":"Otahuhu",
    "sg:orig_category":"Industrial: Metal: Services: Chromium Platers",
    "sg:phone":"+64 9-276 4796",
    "sg:province":"Auckland",
    "wof:name":"Otahuhu Hard Chrome Ltd",
    "wof:placetype":"venue"
},
  "geometry": {"coordinates":[174.838303,-36.941109],"type":"Point"}
}