{
  "type": "Feature",
  "properties": {
    "iso:country":"NZ",
    "sg:address":"11 Biak St ",
    "sg:city":"Rotorua",
    "sg:orig_category":"Farming: Forestry: Forestry Consultants",
    "sg:phone":"+64 7-349 2795",
    "sg:province":"Bay of Plenty",
    "wof:name":"Pumicelands Rural Fire Authority",
    "wof:placetype":"venue"
},
  "geometry": {"coordinates":[176.236145,-38.133045],"type":"Point"}
}