{
  "type": "Feature",
  "properties": {
    "addr:full":"6 Hanworth Ave Hornby  Christchurch Canterbury",
    "addr:housenumber":"6",
    "addr:street":"Hanworth Ave",
    "iso:country":"NZ",
    "sg:address":"6 Hanworth Ave Hornby ",
    "sg:city":"Christchurch",
    "sg:orig_category":"Farming: Machinery: Farm Machinery",
    "sg:phone":"+64 3-349 2129",
    "sg:province":"Canterbury",
    "wof:name":"Nairn Harvesters Ltd",
    "wof:placetype":"venue"
},
  "geometry": {"coordinates":[172.540955,-43.54269],"type":"Point"}
}