{
  "type": "Feature",
  "properties": {
    "addr:full":"4 Kingsford Smith Pl Mangere  Auckland Auckland",
    "addr:housenumber":"4",
    "addr:street":"Kingsford Smith Pl",
    "iso:country":"NZ",
    "sg:address":"4 Kingsford Smith Pl Mangere ",
    "sg:city":"Auckland",
    "sg:classifiers":[
        {
            "category":"Banks & Credit Unions",
            "subcategory":"Investment Brokerage",
            "type":"Services"
        }
    ],
    "sg:phone":"+64 9-275 0745",
    "sg:province":"Auckland",
    "sg:tags":[
        "chemical",
        "industrial",
        "-",
        "compounds"
    ],
    "wof:name":"International Sales & Marketing (NZ) Ltd",
    "wof:placetype":"venue"
},
  "geometry": {"coordinates":[174.78190599999999,-36.979652],"type":"Point"}
}