{
  "type": "Feature",
  "properties": {
    "addr:full":"722 Mt Eden Rd Mt Eden  Auckland Auckland",
    "addr:housenumber":"722",
    "addr:street":"Mt Eden Rd",
    "iso:country":"NZ",
    "sg:address":"722 Mt Eden Rd Mt Eden ",
    "sg:city":"Auckland",
    "sg:orig_category":"Industrial: Engineering: Engineers: Civil Engineering Contractors",
    "sg:phone":"+64 9-623 3595",
    "sg:province":"Auckland",
    "wof:name":"CC (NZ) Ltd",
    "wof:placetype":"venue"
},
  "geometry": {"coordinates":[174.75860599999999,-36.894669],"type":"Point"}
}