{
  "type": "Feature",
  "properties": {
    "addr:full":"33 Water St  Whangarei Northland",
    "addr:housenumber":"33",
    "addr:street":"Water St",
    "iso:country":"NZ",
    "sg:address":"33 Water St ",
    "sg:city":"Whangarei",
    "sg:orig_category":"Automotive: General Services: Service Stations",
    "sg:phone":"+64 9-438 1975",
    "sg:province":"Northland",
    "wof:name":"Shell Water Street",
    "wof:placetype":"venue"
},
  "geometry": {"coordinates":[174.318161,-35.726131],"type":"Point"}
}