{
  "type": "Feature",
  "properties": {
    "iso:country":"NZ",
    "sg:address":"11 Estuary Way ",
    "sg:city":"Tauranga",
    "sg:classifiers":[
        {
            "category":"Shopping",
            "subcategory":"Beauty & Cosmetics",
            "type":"Retail Goods"
        }
    ],
    "sg:phone":"+64 7-577 9119",
    "sg:province":"Bay of Plenty",
    "sg:tags":[
        "health",
        "perfumery"
    ],
    "wof:name":"Baccarat Aromatique Ltd",
    "wof:placetype":"venue"
},
  "geometry": {"coordinates":[176.150436,-37.713703],"type":"Point"}
}