{
  "type": "Feature",
  "properties": {
    "addr:full":"5/38 Eaglehurst Rd Ellerslie  Auckland Auckland",
    "addr:housenumber":"5 / 38",
    "addr:street":"Eaglehurst Rd",
    "iso:country":"NZ",
    "sg:address":"5/38 Eaglehurst Rd Ellerslie ",
    "sg:city":"Auckland",
    "sg:classifiers":[
        {
            "category":"Recreation",
            "type":"Entertainment"
        }
    ],
    "sg:phone":"+64 9-525 0200",
    "sg:province":"Auckland",
    "sg:tags":[
        "sport",
        "leisure"
    ],
    "wof:name":"TimeOut Leisure Ltd",
    "wof:placetype":"venue"
},
  "geometry": {"coordinates":[174.81800799999999,-36.902248],"type":"Point"}
}