{
  "type": "Feature",
  "properties": {
    "iso:country":"NZ",
    "sg:address":"cnr Bryce & Barton Sts ",
    "sg:city":"Hamilton",
    "sg:classifiers":[
        {
            "category":"Travel",
            "subcategory":"Travel Agent",
            "type":"Entertainment"
        }
    ],
    "sg:phone":"+64 7-838 1100",
    "sg:province":"Waikato",
    "sg:tags":[
        "tourism",
        "broker"
    ],
    "wof:name":"United Travel On Bryce & Barton",
    "wof:placetype":"venue"
},
  "geometry": {"coordinates":[-74.45687100000001,43.66745],"type":"Point"}
}