{
  "type": "Feature",
  "properties": {
    "iso:country":"NZ",
    "sg:address":"3 Alfred St ",
    "sg:city":"Rangiora",
    "sg:orig_category":"Clothing And Fabric: Clothing: Women'S Fashions",
    "sg:phone":"+64 3-313 8500",
    "sg:province":"Canterbury",
    "wof:name":"Corina's House Of Fashion",
    "wof:placetype":"venue"
},
  "geometry": {"coordinates":[172.59608499999999,-43.303905],"type":"Point"}
}