{
  "type": "Feature",
  "properties": {
    "iso:country":"NZ",
    "sg:address":"Pipitea Mews 56 Pipitea St Thorndon ",
    "sg:city":"Wellington",
    "sg:classifiers":[
        {
            "category":"Insurance",
            "subcategory":"Health Insurance",
            "type":"Services"
        }
    ],
    "sg:phone":"+64 4-499 4345",
    "sg:province":"Wellington",
    "sg:tags":[
        "specialist",
        "beauty"
    ],
    "wof:name":"Bishop Richard C MNZAS (CCC), Msc (Soton)",
    "wof:placetype":"venue"
},
  "geometry": {"coordinates":[174.776016,-41.274925],"type":"Point"}
}