{
  "type": "Feature",
  "properties": {
    "iso:country":"NZ",
    "sg:address":"27 Bernera St ",
    "sg:city":"Karitane",
    "sg:orig_category":"Industrial: Services: Specialist Services: Laboratories",
    "sg:phone":"+64 25397874",
    "wof:name":"N D Testing Services Ltd",
    "wof:placetype":"venue"
},
  "geometry": {"coordinates":[170.65606700000001,-45.640873],"type":"Point"}
}