{
  "type": "Feature",
  "properties": {
    "iso:country":"NZ",
    "sg:address":"61 B Barry's Point Rd Takapuna ",
    "sg:city":"Auckland",
    "sg:classifiers":[
        {
            "category":"Personal",
            "subcategory":"Adult",
            "type":"Services"
        }
    ],
    "sg:phone":"+64 9-486 4231",
    "sg:province":"Auckland",
    "sg:tags":[
        "sport",
        "leisure"
    ],
    "sg:website":"http://www.yellowpages.co.nz/for/cityescorts/dp40345.html",
    "wof:name":"Centrefold",
    "wof:placetype":"venue"
},
  "geometry": {"coordinates":[174.76788300000001,-36.787842],"type":"Point"}
}