{
  "type": "Feature",
  "properties": {
    "iso:country":"NZ",
    "sg:address":"12 Merton Ave Glenfield ",
    "sg:city":"Auckland",
    "sg:orig_category":"Home And Garden: Children: Child Related: Children'S Entertainment",
    "sg:phone":"+64 9-444 0811",
    "sg:province":"Auckland",
    "wof:name":"Toadstool Kids Parties",
    "wof:placetype":"venue"
},
  "geometry": {"coordinates":[174.729904,-36.771435],"type":"Point"}
}