{
  "type": "Feature",
  "properties": {
    "addr:full":"Lochmara Bay Marlborough Sounds  Picton Marlborough",
    "iso:country":"NZ",
    "sg:address":"Lochmara Bay Marlborough Sounds ",
    "sg:city":"Picton",
    "sg:classifiers":[
        {
            "category":"Travel",
            "subcategory":"Hotels & Motels",
            "type":"Entertainment"
        }
    ],
    "sg:phone":"+64 3-573 4554",
    "sg:province":"Marlborough",
    "sg:tags":[
        "holiday",
        "tourism",
        "accommodation"
    ],
    "sg:website":"http://www.lochmaralodge.co.nz",
    "wof:name":"Lochmara Lodge",
    "wof:placetype":"venue"
},
  "geometry": {"coordinates":[174.00427199999999,-41.294788],"type":"Point"}
}