{
  "type": "Feature",
  "properties": {
    "iso:country":"NZ",
    "sg:address":"Kaiapoi Village Arcade ",
    "sg:city":"Kaiapoi",
    "sg:classifiers":[
        {
            "category":"Travel",
            "subcategory":"Travel Agent",
            "type":"Entertainment"
        }
    ],
    "sg:phone":"+64 3-327 9247",
    "sg:tags":[
        "tourism",
        "broker"
    ],
    "wof:name":"Holiday Shoppe",
    "wof:placetype":"venue"
},
  "geometry": {"coordinates":[172.65931699999999,-43.366875],"type":"Point"}
}