{
  "type": "Feature",
  "properties": {
    "iso:country":"NZ",
    "sg:address":"191 Victoria Ave ",
    "sg:city":"Wanganui",
    "sg:orig_category":"Shopping: Retail Stores: Secondhand Dealers",
    "sg:phone":"+64 6-348 9119",
    "sg:province":"Manawatu-Wanganui",
    "wof:name":"Cash Converters",
    "wof:placetype":"venue"
},
  "geometry": {"coordinates":[175.04809599999999,-39.930733],"type":"Point"}
}