{
  "type": "Feature",
  "properties": {
    "iso:country":"NZ",
    "sg:address":"PO Box 54226 Bucklands Beach ",
    "sg:city":"Auckland",
    "sg:orig_category":"Transport: Boats And Marine: Boats: Boat Maintenance",
    "sg:phone":"+64 9-576 0304",
    "sg:province":"Auckland",
    "wof:name":"Jeremy Anderson BoatBuilding",
    "wof:placetype":"venue"
},
  "geometry": {"coordinates":[174.90318300000001,-36.858368],"type":"Point"}
}