{
  "type": "Feature",
  "properties": {
    "iso:country":"NZ",
    "sg:address":"75 Yarrow St ",
    "sg:city":"Invercargill",
    "sg:classifiers":[
        {
            "category":"Manufacturing",
            "subcategory":"Motor Vehicles & Parts",
            "type":"Manufacturing & Wholesale Goods"
        }
    ],
    "sg:phone":"+64 3-218 2462",
    "sg:province":"Southland",
    "sg:tags":[
        "air conditioning",
        "automotive",
        "supplies"
    ],
    "wof:name":"Dominion Electric Co Ltd",
    "wof:placetype":"venue"
},
  "geometry": {"coordinates":[168.352448,-46.408783],"type":"Point"}
}