{
  "type": "Feature",
  "properties": {
    "iso:country":"NZ",
    "sg:address":"165 Moffat Rd ",
    "sg:city":"Tauranga",
    "sg:orig_category":"Home And Garden: Gardening: Services: Landscape Design",
    "sg:phone":"+64 7-576 4777",
    "sg:province":"Bay of Plenty",
    "wof:name":"Decor Greenworld Garden Centre",
    "wof:placetype":"venue"
},
  "geometry": {"coordinates":[176.11273199999999,-37.699532],"type":"Point"}
}