{
  "type": "Feature",
  "properties": {
    "iso:country":"NZ",
    "sg:address":"Level 1 McCaw Lewis Building, Riverbank Business Centre, 312 Victoria St ",
    "sg:city":"Hamilton",
    "sg:classifiers":[
        {
            "category":"Banks & Credit Unions",
            "subcategory":"Financial Services",
            "type":"Services"
        }
    ],
    "sg:phone":"+64 7-839 2960",
    "sg:province":"Waikato",
    "sg:tags":[
        "personal",
        "loan",
        "-",
        "finance",
        "mortgage"
    ],
    "wof:name":"Oliver Financial Services",
    "wof:placetype":"venue"
},
  "geometry": {"coordinates":[142.025467,-37.734207],"type":"Point"}
}