{
  "type": "Feature",
  "properties": {
    "addr:full":"PO Box 42169  Orakei Auckland",
    "addr:housenumber":"po box",
    "addr:postcode":"42169",
    "iso:country":"NZ",
    "sg:address":"PO Box 42169 ",
    "sg:city":"Orakei",
    "sg:classifiers":[
        {
            "category":"Home & Garden",
            "subcategory":"Household Appliances",
            "type":"Retail Goods"
        }
    ],
    "sg:phone":"+64 25761544",
    "sg:province":"Auckland",
    "sg:tags":[
        "box",
        "accessories",
        "letter"
    ],
    "wof:name":"Living Letterboxes Ltd",
    "wof:placetype":"venue"
},
  "geometry": {"coordinates":[174.81826799999999,-36.856617],"type":"Point"}
}