{
  "type": "Feature",
  "properties": {
    "addr:full":"Level 14 Forsyth Barr Frater Williams Tower 55-65 Shortland, St Auckland Central  Auckland Auckland",
    "addr:housenumber":"14;55-65",
    "addr:street":"Forsyth Barr Frater Williams;Shortland St",
    "iso:country":"NZ",
    "sg:address":"Level 14 Forsyth Barr Frater Williams Tower 55-65 Shortland, St Auckland Central ",
    "sg:city":"Auckland",
    "sg:classifiers":[
        {
            "category":"Banks & Credit Unions",
            "subcategory":"Investment Brokerage",
            "type":"Services"
        }
    ],
    "sg:phone":"+64 9-303 2485",
    "sg:province":"Auckland",
    "sg:tags":[
        "personal",
        "accountant",
        "chartered",
        "-",
        "finance"
    ],
    "sg:website":"http://www.horwath.co.nz/akl/",
    "wof:name":"Horwath Porter Wigglesworth Limited",
    "wof:placetype":"venue"
},
  "geometry": {"coordinates":[174.76454200000001,-36.848358],"type":"Point"}
}