{
  "type": "Feature",
  "properties": {
    "iso:country":"NZ",
    "sg:address":"www.meangreen.co.nz PO Box 1555 Shortland Street ",
    "sg:city":"Auckland",
    "sg:classifiers":[
        {
            "category":"Shopping",
            "type":"Retail Goods"
        }
    ],
    "sg:phone":"+64 9-520 6117",
    "sg:province":"Canterbury",
    "sg:tags":[
        "chemical",
        "industrial",
        "cleaning",
        "maintenance"
    ],
    "wof:name":"Mean Green",
    "wof:placetype":"venue"
},
  "geometry": {"coordinates":[-119.10457599999999,36.597755],"type":"Point"}
}