{
  "type": "Feature",
  "properties": {
    "addr:full":"7 Willow Pl  Whangarei Northland",
    "addr:housenumber":"7",
    "addr:street":"Willow Pl",
    "iso:country":"NZ",
    "sg:address":"7 Willow Pl ",
    "sg:city":"Whangarei",
    "sg:classifiers":[
        {
            "category":"Building & Trades",
            "subcategory":"Plumbing",
            "type":"Services"
        }
    ],
    "sg:phone":"+64 9-430 0053",
    "sg:province":"Northland",
    "sg:tags":[
        "home",
        "plumber",
        "garden",
        "related"
    ],
    "wof:name":"Graham Wright",
    "wof:placetype":"venue"
},
  "geometry": {"coordinates":[174.29679899999999,-35.735287],"type":"Point"}
}