{
  "type": "Feature",
  "properties": {
    "addr:full":"49 a Shakespeare St  Cambridge Waikato",
    "addr:housenumber":"49 a",
    "addr:street":"Shakespeare St",
    "iso:country":"NZ",
    "sg:address":"49 a Shakespeare St ",
    "sg:city":"Cambridge",
    "sg:classifiers":[
        {
            "category":"Home & Garden",
            "subcategory":"Garden Supply",
            "type":"Retail Goods"
        }
    ],
    "sg:phone":"+64 7-823 1320",
    "sg:province":"Waikato",
    "sg:tags":[
        "fencing",
        "outdoor",
        "contractor"
    ],
    "wof:name":"Outdoor Structures",
    "wof:placetype":"venue"
},
  "geometry": {"coordinates":[-116.67604799999999,44.572186],"type":"Point"}
}