{
  "type": "Feature",
  "properties": {
    "iso:country":"NZ",
    "sg:address":"Shop 4 1 Turon Cre Totara Park Upper ",
    "sg:city":"Hutt",
    "sg:classifiers":[
        {
            "category":"Bars & Pubs",
            "type":"Food & Drink"
        }
    ],
    "sg:phone":"+64 4-526 7002",
    "sg:province":"Bay of Plenty",
    "sg:tags":[
        "wining",
        "dining",
        "brasserie"
    ],
    "wof:name":"Nevada Cafe and Bar",
    "wof:placetype":"venue"
},
  "geometry": {"coordinates":[175.08410599999999,-41.108181],"type":"Point"}
}