{
  "type": "Feature",
  "properties": {
    "addr:full":"132 Hinemoa St Birkenhead  Auckland Auckland",
    "addr:housenumber":"132",
    "addr:street":"Hinemoa St",
    "iso:country":"NZ",
    "sg:address":"132 Hinemoa St Birkenhead ",
    "sg:city":"Auckland",
    "sg:orig_category":"Shopping: Hobbies And Games: Handcrafts",
    "sg:phone":"+64 9-480 5401",
    "sg:province":"Auckland",
    "wof:name":"Patchwork Barn",
    "wof:placetype":"venue"
},
  "geometry": {"coordinates":[174.73123200000001,-36.815849],"type":"Point"}
}