{
  "type": "Feature",
  "properties": {
    "addr:full":"Unit 9 46 Stanley St Parnell Auckland Mail Centre  Auckland Auckland",
    "addr:housenumber":"unit;46",
    "addr:street":"Stanley St",
    "iso:country":"NZ",
    "sg:address":"Unit 9 46 Stanley St Parnell Auckland Mail Centre ",
    "sg:city":"Auckland",
    "sg:orig_category":"Industrial: Products: Laboratory Supplies",
    "sg:phone":"+64 9-377 6819",
    "sg:province":"Auckland",
    "wof:name":"Vital Diagnostics",
    "wof:placetype":"venue"
},
  "geometry": {"coordinates":[174.77534499999999,-36.851032],"type":"Point"}
}