{
  "type": "Feature",
  "properties": {
    "iso:country":"NZ",
    "sg:address":"5/197 Montgomerie Rd Mangere ",
    "sg:city":"Auckland",
    "sg:orig_category":"Transport: Transportation: Freight",
    "sg:phone":"+64 9-275 6655",
    "sg:province":"Auckland",
    "wof:name":"A Hartrodt (NZ) Ltd",
    "wof:placetype":"venue"
},
  "geometry": {"coordinates":[174.775375,-36.972507],"type":"Point"}
}