{
  "type": "Feature",
  "properties": {
    "iso:country":"NZ",
    "sg:address":"560 SH 1 RD 4 ",
    "sg:city":"Cambridge",
    "sg:orig_category":"Home And Garden: Gardening: Services: Landscape Design",
    "sg:phone":"+64 7-823 2521",
    "sg:province":"Auckland",
    "wof:name":"Leaf Landscapers",
    "wof:placetype":"venue"
},
  "geometry": {"coordinates":[-93.529121,41.89719],"type":"Point"}
}