{
  "type": "Feature",
  "properties": {
    "iso:country":"NZ",
    "sg:address":"7 Talbot St ",
    "sg:city":"Geraldine",
    "sg:classifiers":[
        {
            "category":"Home & Garden",
            "subcategory":"Home Furnishings",
            "type":"Retail Goods"
        }
    ],
    "sg:phone":"+64 3-693 9548",
    "sg:tags":[
        "furniture/furnishings",
        "upholstery",
        "supply"
    ],
    "wof:name":"Stitch 'n' Time",
    "wof:placetype":"venue"
},
  "geometry": {"coordinates":[-86.008263,34.360641],"type":"Point"}
}