{
  "type": "Feature",
  "properties": {
    "iso:country":"NZ",
    "sg:address":"Molloys Rd Te Marua Upper ",
    "sg:city":"Hutt",
    "sg:orig_category":"Education And Training: General: Schools",
    "sg:phone":"+64 4-526 9909",
    "sg:province":"Wellington",
    "wof:name":"Plateau School",
    "wof:placetype":"venue"
},
  "geometry": {"coordinates":[175.13200399999999,-41.09333],"type":"Point"}
}