{
  "type": "Feature",
  "properties": {
    "addr:full":"987 Cameron Rd Gate Pa  Tauranga Bay of Plenty",
    "addr:housenumber":"987",
    "addr:street":"Cameron Rd",
    "iso:country":"NZ",
    "sg:address":"987 Cameron Rd Gate Pa ",
    "sg:city":"Tauranga",
    "sg:classifiers":[
        {
            "category":"Professional",
            "subcategory":"Art Services",
            "type":"Services"
        }
    ],
    "sg:phone":"+64 7-578 6688",
    "sg:province":"Bay of Plenty",
    "sg:tags":[
        "picture",
        "arts",
        "sport",
        "framing",
        "leisure"
    ],
    "wof:name":"Paramount Picture Framers",
    "wof:placetype":"venue"
},
  "geometry": {"coordinates":[176.14137299999999,-37.713997],"type":"Point"}
}