{
  "type": "Feature",
  "properties": {
    "iso:country":"NZ",
    "sg:address":"PO Box 284 ",
    "sg:city":"Hokitika",
    "sg:classifiers":[
        {
            "category":"Ice Cream",
            "type":"Food & Drink"
        }
    ],
    "sg:phone":"+64 3-755 6913",
    "sg:province":"West Coast",
    "sg:tags":[
        "dairy",
        "product",
        "-"
    ],
    "wof:name":"Wall's Milk Delivery Service",
    "wof:placetype":"venue"
},
  "geometry": {"coordinates":[170.97221400000001,-42.719032],"type":"Point"}
}