{
  "type": "Feature",
  "properties": {
    "iso:country":"NZ",
    "sg:address":"Moresby Ave ",
    "sg:city":"Waihi",
    "sg:classifiers":[
        {
            "category":"Sports & Exercise",
            "subcategory":"Sports Center",
            "type":"Entertainment"
        }
    ],
    "sg:phone":"+64 7-863 8499",
    "sg:tags":[
        "health",
        "beauty",
        "fitness"
    ],
    "wof:name":"Feel Great Health & Fitness Club",
    "wof:placetype":"venue"
},
  "geometry": {"coordinates":[175.83963,-37.390518],"type":"Point"}
}