{
  "type": "Feature",
  "properties": {
    "addr:full":"Udy St  Greytown",
    "addr:street":"Udy St",
    "iso:country":"NZ",
    "sg:address":"Udy St ",
    "sg:city":"Greytown",
    "sg:classifiers":[
        {
            "category":"Coffee & Tea",
            "type":"Food & Drink"
        }
    ],
    "sg:phone":"+64 6-304 9699",
    "sg:tags":[
        "vegetable",
        "fruit",
        "veges"
    ],
    "wof:name":"Pinehaven Orchards",
    "wof:placetype":"venue"
},
  "geometry": {"coordinates":[175.45620700000001,-41.070866],"type":"Point"}
}