{
  "type": "Feature",
  "properties": {
    "iso:country":"NZ",
    "sg:address":"197 Evans St ",
    "sg:city":"Timaru",
    "sg:orig_category":"Home And Garden: Gardening: Services: Landscaping",
    "sg:phone":"+64 3-688 3794",
    "sg:province":"Canterbury",
    "wof:name":"Landscape Centre The",
    "wof:placetype":"venue"
},
  "geometry": {"coordinates":[171.23826600000001,-44.38195],"type":"Point"}
}