{
  "type": "Feature",
  "properties": {
    "iso:country":"NZ",
    "sg:address":"9 Maidstone St Grey Lynn ",
    "sg:city":"Auckland",
    "sg:classifiers":[
        {
            "category":"Home & Garden",
            "subcategory":"Garden Supply",
            "type":"Retail Goods"
        }
    ],
    "sg:phone":"+64 9-360 4820",
    "sg:province":"Auckland",
    "sg:tags":[
        "cleaning"
    ],
    "sg:website":"http://www.yellowpages.co.nz/for/manchester/dp22783.html",
    "wof:name":"Manchester Property Care Ltd",
    "wof:placetype":"venue"
},
  "geometry": {"coordinates":[174.751129,-36.859879],"type":"Point"}
}