{
  "type": "Feature",
  "properties": {
    "addr:full":"951 Devon Rd Bell Block New  Plymouth Taranaki",
    "addr:housenumber":"951",
    "addr:street":"Devon Rd",
    "iso:country":"NZ",
    "sg:address":"951 Devon Rd Bell Block New ",
    "sg:city":"Plymouth",
    "sg:classifiers":[
        {
            "category":"Coffee & Tea",
            "type":"Food & Drink"
        }
    ],
    "sg:phone":"+64 6-755 0687",
    "sg:province":"Taranaki",
    "sg:tags":[
        "vegetable",
        "fruit",
        "veges"
    ],
    "wof:name":"Bell Block Fruit n Vege",
    "wof:placetype":"venue"
},
  "geometry": {"coordinates":[174.14419599999999,-39.035797],"type":"Point"}
}