{
  "type": "Feature",
  "properties": {
    "addr:full":"Airlie St The Glen  Nelson Manawatu-Wanganui",
    "addr:street":"Airlie St The Glen",
    "iso:country":"NZ",
    "sg:address":"Airlie St The Glen ",
    "sg:city":"Nelson",
    "sg:classifiers":[
        {
            "category":"Home & Garden",
            "subcategory":"Building Materials",
            "type":"Retail Goods"
        }
    ],
    "sg:phone":"+64 3-545 0424",
    "sg:province":"Manawatu-Wanganui",
    "sg:tags":[
        "builder",
        "related"
    ],
    "wof:name":"Herizon Builders",
    "wof:placetype":"venue"
},
  "geometry": {"coordinates":[173.29289199999999,-41.269615],"type":"Point"}
}