{
  "type": "Feature",
  "properties": {
    "addr:full":"Mount Aspiring Rd  Wanaka Otago",
    "addr:street":"Aspiring Rd",
    "iso:country":"NZ",
    "sg:address":"Mount Aspiring Rd ",
    "sg:city":"Wanaka",
    "sg:classifiers":[
        {
            "category":"Winery",
            "type":"Food & Drink"
        }
    ],
    "sg:phone":"+64 3-443 8084",
    "sg:province":"Otago",
    "sg:tags":[
        "wining",
        "vineyard",
        "dining"
    ],
    "wof:name":"Rippon Vineyard",
    "wof:placetype":"venue"
},
  "geometry": {"coordinates":[169.12069700000001,-44.700367],"type":"Point"}
}