{
  "type": "Feature",
  "properties": {
    "iso:country":"NZ",
    "sg:address":"307 C Hibiscus Coast Hwy Orewa Hibiscus ",
    "sg:city":"Hibiscus Coast",
    "sg:classifiers":[
        {
            "category":"Health Services",
            "subcategory":"Health Practitioner",
            "type":"Services"
        }
    ],
    "sg:phone":"+64 9-426 9188",
    "sg:province":"Auckland",
    "sg:tags":[
        "services",
        "beauty",
        "acupuncturists"
    ],
    "wof:name":"Orewa Acupuncture & Chinese Medicine Clinic",
    "wof:placetype":"venue"
},
  "geometry": {"coordinates":[174.69012499999999,-36.582741],"type":"Point"}
}