{
  "type": "Feature",
  "properties": {
    "addr:full":"73 Bryndwr Rd Fendalton  Christchurch Canterbury",
    "addr:housenumber":"73",
    "addr:street":"Bryndwr Rd",
    "iso:country":"NZ",
    "sg:address":"73 Bryndwr Rd Fendalton ",
    "sg:city":"Christchurch",
    "sg:classifiers":[
        {
            "category":"Social Services",
            "subcategory":"Retirement Home",
            "type":"Services"
        }
    ],
    "sg:phone":"+64 3-351 5979",
    "sg:province":"Canterbury",
    "sg:tags":[
        "elderly",
        "convalescent",
        "garden",
        "rest",
        "care"
    ],
    "wof:name":"Fendalton Retirement Village",
    "wof:placetype":"venue"
},
  "geometry": {"coordinates":[172.594955,-43.511139],"type":"Point"}
}