{
  "type": "Feature",
  "properties": {
    "iso:country":"NZ",
    "sg:address":"3 Rata St ",
    "sg:city":"Feilding",
    "sg:orig_category":"Food And Drink: Catering: Caterers",
    "sg:phone":"+64 6-323 1104",
    "sg:province":"Manawatu-Wanganui",
    "sg:website":"http://www.yellowpages.co.nz/for/harvestpantry/dp37163.html",
    "wof:name":"The Harvest Pantry",
    "wof:placetype":"venue"
},
  "geometry": {"coordinates":[175.55461099999999,-40.232494],"type":"Point"}
}