{
  "type": "Feature",
  "properties": {
    "iso:country":"NZ",
    "sg:address":"www.brandmagic.co.nz ",
    "sg:city":"Auckland",
    "sg:classifiers":[
        {
            "category":"Education",
            "subcategory":"Vocational School",
            "type":"Public Place"
        }
    ],
    "sg:phone":"+64 9-374 4340",
    "sg:province":"Auckland",
    "sg:tags":[
        "training",
        "agency",
        "model"
    ],
    "wof:name":"Brand Magic",
    "wof:placetype":"venue"
},
  "geometry": {"coordinates":[-119.10457599999999,36.597755],"type":"Point"}
}