{
  "type": "Feature",
  "properties": {
    "addr:full":"7 MacArthur St  Levin Manawatu-Wanganui",
    "addr:housenumber":"7",
    "addr:street":"Macarthur St",
    "iso:country":"NZ",
    "sg:address":"7 MacArthur St ",
    "sg:city":"Levin",
    "sg:classifiers":[
        {
            "category":"Banks & Credit Unions",
            "subcategory":"Atm",
            "type":"Services"
        }
    ],
    "sg:phone":"+64 25983655",
    "sg:province":"Manawatu-Wanganui",
    "sg:tags":[
        "home",
        "rental",
        "garden"
    ],
    "wof:name":"Te Awe Awe Air Conditioning",
    "wof:placetype":"venue"
},
  "geometry": {"coordinates":[175.296494,-40.615608],"type":"Point"}
}