{
  "type": "Feature",
  "properties": {
    "addr:full":"Main Rd, Coatesville Riverhead Hwy Coatesville  Auckland Auckland",
    "addr:street":"Main Rd;Riverhead Hwy",
    "iso:country":"NZ",
    "sg:address":"Main Rd, Coatesville Riverhead Hwy Coatesville ",
    "sg:city":"Auckland",
    "sg:orig_category":"Shopping: Retail Stores: Antiques",
    "sg:phone":"+64 9-414 2541",
    "sg:province":"Auckland",
    "wof:name":"The Shed",
    "wof:placetype":"venue"
},
  "geometry": {"coordinates":[174.629257,-36.90831],"type":"Point"}
}