{
  "type": "Feature",
  "properties": {
    "addr:full":"Queensgate Mall Lower  Hutt Wellington",
    "addr:street":"Queensgate",
    "iso:country":"NZ",
    "sg:address":"Queensgate Mall Lower ",
    "sg:city":"Hutt",
    "sg:classifiers":[
        {
            "category":"Manufacturing",
            "subcategory":"Textiles",
            "type":"Manufacturing & Wholesale Goods"
        }
    ],
    "sg:phone":"+64 4-569 2452",
    "sg:province":"Wellington",
    "sg:tags":[
        "surf",
        "street",
        "clothing",
        "fabric",
        "wear"
    ],
    "wof:name":"Amazon",
    "wof:placetype":"venue"
},
  "geometry": {"coordinates":[174.904526,-41.208431],"type":"Point"}
}