{
  "type": "Feature",
  "properties": {
    "addr:full":"102 Wadestown Rd  Wellington Wellington",
    "addr:housenumber":"102",
    "addr:street":"Wadestown Rd",
    "iso:country":"NZ",
    "sg:address":"102 Wadestown Rd ",
    "sg:city":"Wellington",
    "sg:classifiers":[
        {
            "category":"Fast Food",
            "type":"Food & Drink"
        }
    ],
    "sg:phone":"+64 4-499 1463",
    "sg:province":"Wellington",
    "sg:tags":[
        "wining",
        "dining",
        "takeaway"
    ],
    "wof:name":"Burger Wisconsin",
    "wof:placetype":"venue"
},
  "geometry": {"coordinates":[174.77430699999999,-41.261803],"type":"Point"}
}