{
  "type": "Feature",
  "properties": {
    "addr:full":"1D Antares Pl Albany  Auckland Auckland",
    "addr:housenumber":"1d",
    "addr:street":"Antares Pl",
    "iso:country":"NZ",
    "sg:address":"1D Antares Pl Albany ",
    "sg:city":"Auckland",
    "sg:classifiers":[
        {
            "category":"Health Services",
            "subcategory":"Doctor",
            "type":"Services"
        }
    ],
    "sg:phone":"+64 9-479 8802",
    "sg:province":"Auckland",
    "sg:tags":[
        "specialists",
        "surgery",
        "cosmetic",
        "beauty"
    ],
    "wof:name":"Lifespan Health",
    "wof:placetype":"venue"
},
  "geometry": {"coordinates":[174.709686,-36.720142],"type":"Point"}
}