{
  "type": "Feature",
  "properties": {
    "addr:full":"110 Jack Lachlan Dve Beachlands  Auckland Auckland",
    "addr:housenumber":"110",
    "addr:street":"Jack;Dve",
    "iso:country":"NZ",
    "sg:address":"110 Jack Lachlan Dve Beachlands ",
    "sg:city":"Auckland",
    "sg:orig_category":"Sports And Leisure: Sports: Golf: Golf Courses",
    "sg:phone":"+64 9-536 5895",
    "sg:province":"Auckland",
    "wof:name":"Formosa Auckland Country Club",
    "wof:placetype":"venue"
},
  "geometry": {"coordinates":[174.99380500000001,-36.890327],"type":"Point"}
}