{
  "type": "Feature",
  "properties": {
    "addr:full":"National Park  Taumarunui",
    "iso:country":"NZ",
    "sg:address":"National Park ",
    "sg:city":"Taumarunui",
    "sg:classifiers":[
        {
            "category":"Banks & Credit Unions",
            "subcategory":"Financial Services",
            "type":"Services"
        }
    ],
    "sg:phone":"+64 7-892 2736",
    "sg:tags":[
        "lender",
        "money",
        "-",
        "finance",
        "personal"
    ],
    "wof:name":"Easy Loans",
    "wof:placetype":"venue"
},
  "geometry": {"coordinates":[175.25524899999999,-38.880814],"type":"Point"}
}