{
  "type": "Feature",
  "properties": {
    "addr:full":"8 Tower Hill Manly Hibiscus  Hibiscus Coast Auckland",
    "addr:housenumber":"8",
    "addr:street":"Tower",
    "iso:country":"NZ",
    "sg:address":"8 Tower Hill Manly Hibiscus ",
    "sg:city":"Hibiscus Coast",
    "sg:classifiers":[
        {
            "category":"Shopping",
            "subcategory":"Pets & Pet Supplies",
            "type":"Retail Goods"
        }
    ],
    "sg:phone":"+64 9-424 7277",
    "sg:province":"Auckland",
    "sg:tags":[
        "boarding",
        "garden",
        "pets",
        "catteries",
        "home",
        "kennel"
    ],
    "wof:name":"Whangaparaoa Cattery",
    "wof:placetype":"venue"
},
  "geometry": {"coordinates":[174.70623800000001,-36.636581],"type":"Point"}
}