{
  "type": "Feature",
  "properties": {
    "iso:country":"NZ",
    "sg:address":"124 Riccarton Rd ",
    "sg:city":"Christchurch",
    "sg:classifiers":[
        {
            "category":"Shopping",
            "subcategory":"Bicycles & Sporting Goods",
            "type":"Retail Goods"
        }
    ],
    "sg:phone":"+64 3-343 4634",
    "sg:province":"Canterbury",
    "sg:tags":[
        "equipment",
        "sport",
        "tramping",
        "leisure",
        "camping"
    ],
    "wof:name":"Kathmandu Ltd",
    "wof:placetype":"venue"
},
  "geometry": {"coordinates":[172.598618,-43.529823],"type":"Point"}
}