{
  "type": "Feature",
  "properties": {
    "iso:country":"NZ",
    "sg:address":"6/35 High St Auckland Central ",
    "sg:city":"Auckland",
    "sg:classifiers":[
        {
            "category":"Communications",
            "subcategory":"Film & Video Production",
            "type":"Services"
        }
    ],
    "sg:phone":"+64 9-309 8388",
    "sg:province":"Auckland",
    "sg:tags":[
        "broadcasting",
        "studio",
        "producer"
    ],
    "wof:name":"Footprint Films Ltd",
    "wof:placetype":"venue"
},
  "geometry": {"coordinates":[174.766388,-36.847958],"type":"Point"}
}