{
  "type": "Feature",
  "properties": {
    "iso:country":"NZ",
    "sg:address":"Caveland Rd Gladstone R D 4 Masterton ",
    "sg:city":"Gladstone",
    "sg:classifiers":[
        {
            "category":"Food & Beverages",
            "subcategory":"Cheese",
            "type":"Retail Goods"
        }
    ],
    "sg:phone":"+64 6-372 7730",
    "sg:tags":[
        "merchant",
        "drink",
        "-"
    ],
    "wof:name":"Saratoga Dairy Goats",
    "wof:placetype":"venue"
},
  "geometry": {"coordinates":[175.657333,-41.076488],"type":"Point"}
}