{
  "type": "Feature",
  "properties": {
    "iso:country":"NZ",
    "sg:address":"19 East St Papakura ",
    "sg:city":"Auckland",
    "sg:classifiers":[
        {
            "category":"Home & Garden",
            "subcategory":"Furniture",
            "type":"Retail Goods"
        }
    ],
    "sg:phone":"+64 9-298 4049",
    "sg:province":"Auckland",
    "sg:tags":[
        "furniture/furnishings",
        "repair",
        "finishing"
    ],
    "wof:name":"Campbell C&A Furniture Finishers",
    "wof:placetype":"venue"
},
  "geometry": {"coordinates":[174.940109,-37.062138],"type":"Point"}
}