{
  "type": "Feature",
  "properties": {
    "iso:country":"NZ",
    "sg:address":"112 Avonside Dve Linwood ",
    "sg:city":"Christchurch",
    "sg:classifiers":[
        {
            "category":"Education",
            "subcategory":"University",
            "type":"Public Place"
        }
    ],
    "sg:phone":"+64 3-389 1164",
    "sg:province":"Canterbury",
    "sg:tags":[
        "training",
        "college"
    ],
    "wof:name":"Avon College",
    "wof:placetype":"venue"
},
  "geometry": {"coordinates":[172.657715,-43.525581],"type":"Point"}
}