{
  "type": "Feature",
  "properties": {
    "addr:full":"85 King St  Temuka",
    "addr:housenumber":"85",
    "addr:street":"King St",
    "iso:country":"NZ",
    "sg:address":"85 King St ",
    "sg:city":"Temuka",
    "sg:orig_category":"Farming: Horticulture: Horticultural Supplies",
    "sg:phone":"+64 3-615 8761",
    "wof:name":"Eddys Hammer Hardware",
    "wof:placetype":"venue"
},
  "geometry": {"coordinates":[171.27615399999999,-44.238956],"type":"Point"}
}