{
  "type": "Feature",
  "properties": {
    "addr:full":"215 Centre St Heidelberg  Invercargill Southland",
    "addr:housenumber":"215",
    "addr:street":"Centre St",
    "iso:country":"NZ",
    "sg:address":"215 Centre St Heidelberg ",
    "sg:city":"Invercargill",
    "sg:classifiers":[
        {
            "category":"Building & Trades",
            "subcategory":"Landscaping Services",
            "type":"Services"
        }
    ],
    "sg:phone":"+64 3-216 8099",
    "sg:province":"Southland",
    "sg:tags":[
        "personal",
        "home",
        "garden"
    ],
    "sg:website":"http://www.yellowpages.co.nz/for/calvaryhospital/dp22687.html",
    "wof:name":"Calvary Hospital",
    "wof:placetype":"venue"
},
  "geometry": {"coordinates":[168.384232,-46.422733],"type":"Point"}
}