{
  "type": "Feature",
  "properties": {
    "addr:full":"Level 5 104 The Terrace  Wellington Waikato",
    "addr:housenumber":"level 5 104",
    "addr:street":"The Terrace",
    "iso:country":"NZ",
    "sg:address":"Level 5 104 The Terrace ",
    "sg:city":"Wellington",
    "sg:classifiers":[
        {
            "category":"Banks & Credit Unions",
            "subcategory":"Investment Brokerage",
            "type":"Services"
        }
    ],
    "sg:province":"Waikato",
    "sg:tags":[
        "personal",
        "accountant",
        "chartered",
        "-",
        "finance"
    ],
    "wof:name":"Munro Benge.BKR",
    "wof:placetype":"venue"
},
  "geometry": {"coordinates":[-100.19828800000001,34.795418],"type":"Point"}
}