{
  "type": "Feature",
  "properties": {
    "addr:full":"cnr Dublin & St Hill Sts  Wanganui Manawatu-Wanganui",
    "addr:street":"Cnr;Hill",
    "iso:country":"NZ",
    "sg:address":"cnr Dublin & St Hill Sts ",
    "sg:city":"Wanganui",
    "sg:classifiers":[
        {
            "category":"Autos & Motor Vehicles",
            "subcategory":"Automobile Sales",
            "type":"Retail Goods"
        }
    ],
    "sg:phone":"+64 6-349 1122",
    "sg:province":"Manawatu-Wanganui",
    "sg:tags":[
        "car",
        "-used",
        "leasing",
        "truck",
        "automotive"
    ],
    "wof:name":"Watkins Honda & Nissan",
    "wof:placetype":"venue"
},
  "geometry": {"coordinates":[-83.13314099999999,40.104912],"type":"Point"}
}