{
  "type": "Feature",
  "properties": {
    "addr:full":"Bakehouse La Hibiscus  Hibiscus Coast Auckland",
    "addr:street":"La Hibiscus",
    "iso:country":"NZ",
    "sg:address":"Bakehouse La Hibiscus ",
    "sg:city":"Hibiscus Coast",
    "sg:orig_category":"Industrial: Electrical/Electronic: Electronic Components",
    "sg:phone":"+64 9-426 2007",
    "sg:province":"Auckland",
    "wof:name":"Dick Smith Electronics",
    "wof:placetype":"venue"
},
  "geometry": {"coordinates":[174.70623800000001,-36.636581],"type":"Point"}
}