{
  "type": "Feature",
  "properties": {
    "iso:country":"NZ",
    "sg:address":"55 Mahana Rd Te Rapa ",
    "sg:city":"Hamilton",
    "sg:orig_category":"Industrial: Coatings",
    "sg:phone":"+64 7-957 7680",
    "sg:province":"Waikato",
    "wof:name":"Stafford Hardware Ltd",
    "wof:placetype":"venue"
},
  "geometry": {"coordinates":[175.249908,-37.76038],"type":"Point"}
}