{
  "type": "Feature",
  "properties": {
    "iso:country":"NZ",
    "sg:address":"111 Thames St ",
    "sg:city":"Oamaru",
    "sg:classifiers":[
        {
            "category":"Shopping",
            "subcategory":"Gifts & Souvenirs",
            "type":"Retail Goods"
        }
    ],
    "sg:phone":"+64 3-434 1002",
    "sg:province":"Otago",
    "sg:tags":[
        "travel",
        "tourism"
    ],
    "wof:name":"Mementos Gifts & Souvenirs",
    "wof:placetype":"venue"
},
  "geometry": {"coordinates":[170.97056599999999,-45.098988],"type":"Point"}
}