{
  "type": "Feature",
  "properties": {
    "iso:country":"NZ",
    "sg:address":"252-258 Onehunga Mal Onehunga ",
    "sg:city":"Auckland",
    "sg:orig_category":"Industrial: Electrical/Electronic: Electronic Components",
    "sg:phone":"+64 9-634 6767",
    "sg:province":"Auckland",
    "wof:name":"Dick Smith Electronics",
    "wof:placetype":"venue"
},
  "geometry": {"coordinates":[174.785339,-36.922909],"type":"Point"}
}