{
  "type": "Feature",
  "properties": {
    "addr:full":"149 Te Puna Rd RD6 Te Puna  Tauranga Bay of Plenty",
    "addr:housenumber":"149",
    "addr:street":"Te Puna Rd Rd6",
    "iso:country":"NZ",
    "sg:address":"149 Te Puna Rd RD6 Te Puna ",
    "sg:city":"Tauranga",
    "sg:classifiers":[
        {
            "category":"Food Court",
            "type":"Food & Drink"
        }
    ],
    "sg:phone":"+64 7-552 4030",
    "sg:province":"Bay of Plenty",
    "sg:tags":[
        "egg",
        "product",
        "-"
    ],
    "wof:name":"Braemar Poultry Farm",
    "wof:placetype":"venue"
},
  "geometry": {"coordinates":[176.07333399999999,-37.692341],"type":"Point"}
}