{
  "type": "Feature",
  "properties": {
    "addr:full":"Rangiora St  Wanganui Manawatu-Wanganui",
    "addr:street":"St",
    "iso:country":"NZ",
    "sg:address":"Rangiora St ",
    "sg:city":"Wanganui",
    "sg:classifiers":[
        {
            "category":"Fast Food",
            "type":"Food & Drink"
        }
    ],
    "sg:phone":"+64 6-344 5699",
    "sg:province":"Manawatu-Wanganui",
    "sg:tags":[
        "wining",
        "dining",
        "takeaway"
    ],
    "wof:name":"Castlecliff Camp Store & Takeaways",
    "wof:placetype":"venue"
},
  "geometry": {"coordinates":[174.982697,-39.93581],"type":"Point"}
}