{
  "type": "Feature",
  "properties": {
    "iso:country":"NZ",
    "sg:address":"582 Remuera Rd ",
    "sg:city":"Remuera",
    "sg:classifiers":[
        {
            "category":"Banks & Credit Unions",
            "subcategory":"Investment Brokerage",
            "type":"Services"
        }
    ],
    "sg:phone":"+64 9-520 3119",
    "sg:province":"Auckland",
    "sg:tags":[
        "director",
        "funeral",
        "arrangements"
    ],
    "wof:name":"Sibuns Funeral Directors & Advisors",
    "wof:placetype":"venue"
},
  "geometry": {"coordinates":[174.78916899999999,-36.877647],"type":"Point"}
}