{
  "type": "Feature",
  "properties": {
    "iso:country":"NZ",
    "sg:address":"33 Parker St Hornby ",
    "sg:city":"Christchurch",
    "sg:orig_category":"Industrial: Abrasives: Water Blasting",
    "sg:phone":"+64 3-349 9165",
    "sg:province":"Canterbury",
    "wof:name":"Salton Sales & Service",
    "wof:placetype":"venue"
},
  "geometry": {"coordinates":[172.53633099999999,-43.534431],"type":"Point"}
}