{
  "type": "Feature",
  "properties": {
    "addr:full":"Coatesville R/head Hwy Riverhead  Auckland Auckland",
    "addr:street":"Hwy",
    "iso:country":"NZ",
    "sg:address":"Coatesville R/head Hwy Riverhead ",
    "sg:city":"Auckland",
    "sg:orig_category":"Transport: Boats And Marine: Boats: Boat Maintenance",
    "sg:phone":"+64 9-412 2925",
    "sg:province":"Auckland",
    "wof:name":"Blue Diamond Boat Builders",
    "wof:placetype":"venue"
},
  "geometry": {"coordinates":[174.59385700000001,-36.760101],"type":"Point"}
}