{
  "type": "Feature",
  "properties": {
    "addr:full":"232 Great South Rd Remuera  Auckland Auckland",
    "addr:housenumber":"232",
    "addr:street":"Great South Rd",
    "iso:country":"NZ",
    "sg:address":"232 Great South Rd Remuera ",
    "sg:city":"Auckland",
    "sg:orig_category":"Health And Beauty: Specialists: Audiologists",
    "sg:phone":"+64 9-524 5736",
    "sg:province":"Auckland",
    "wof:name":"Applied Hearing Ltd",
    "wof:placetype":"venue"
},
  "geometry": {"coordinates":[174.80886799999999,-36.869381],"type":"Point"}
}