{
  "type": "Feature",
  "properties": {
    "iso:country":"NZ",
    "sg:address":"Phone / Fax 128 Victoria Ave ",
    "sg:city":"Wanganui",
    "sg:classifiers":[
        {
            "category":"Manufacturing",
            "subcategory":"Rubber & Plastics",
            "type":"Manufacturing & Wholesale Goods"
        }
    ],
    "sg:phone":"+64 6-345 8662",
    "sg:province":"Manawatu-Wanganui",
    "sg:tags":[
        "industrial",
        "goods"
    ],
    "wof:name":"Plastic Box",
    "wof:placetype":"venue"
},
  "geometry": {"coordinates":[175.052841,-39.933369],"type":"Point"}
}