{
  "type": "Feature",
  "properties": {
    "iso:country":"NZ",
    "sg:address":"367 Heads Rd ",
    "sg:city":"Wanganui",
    "sg:classifiers":[
        {
            "category":"Manufacturing",
            "subcategory":"Tools & Machinery",
            "type":"Manufacturing & Wholesale Goods"
        }
    ],
    "sg:phone":"+64 6-344 5068",
    "sg:province":"Manawatu-Wanganui",
    "sg:tags":[
        "equipment",
        "industrial",
        "hydraulic"
    ],
    "wof:name":"Hydraulink Fluid Connectors",
    "wof:placetype":"venue"
},
  "geometry": {"coordinates":[175.01272599999999,-39.9487],"type":"Point"}
}