{
  "type": "Feature",
  "properties": {
    "addr:full":"G44/7 Queen St Auckland City  Auckland Auckland",
    "addr:housenumber":"7",
    "addr:street":"Queen St",
    "iso:country":"NZ",
    "sg:address":"G44/7 Queen St Auckland City ",
    "sg:city":"Auckland",
    "sg:orig_category":"Clothing And Fabric: Clothing: Menswear",
    "sg:phone":"+64 9-309 6112",
    "sg:province":"Auckland",
    "wof:name":"Crew Headquarters",
    "wof:placetype":"venue"
},
  "geometry": {"coordinates":[174.78450000000001,-37.006058],"type":"Point"}
}