{
  "type": "Feature",
  "properties": {
    "addr:full":"Shop 5 Edwin Arcade Victoria St  Dargaville Northland",
    "addr:housenumber":"shop 5;arcade",
    "addr:street":"Edwin;Victoria St",
    "iso:country":"NZ",
    "sg:address":"Shop 5 Edwin Arcade Victoria St ",
    "sg:city":"Dargaville",
    "sg:classifiers":[
        {
            "category":"Personal",
            "subcategory":"Beauty Salon",
            "type":"Services"
        }
    ],
    "sg:phone":"+64 9-439 5354",
    "sg:province":"Northland",
    "sg:tags":[
        "therapy",
        "health"
    ],
    "wof:name":"Verge Beauty Therapy",
    "wof:placetype":"venue"
},
  "geometry": {"coordinates":[173.86938499999999,-35.935867],"type":"Point"}
}