{
  "type": "Feature",
  "properties": {
    "addr:full":"33 Scott St  Blenheim Marlborough",
    "addr:housenumber":"33",
    "addr:street":"Scott St",
    "iso:country":"NZ",
    "sg:address":"33 Scott St ",
    "sg:city":"Blenheim",
    "sg:classifiers":[
        {
            "category":"Recreation",
            "subcategory":"Gun Range",
            "type":"Entertainment"
        }
    ],
    "sg:phone":"+64 3-578 8130",
    "sg:province":"Marlborough",
    "sg:tags":[
        "sports",
        "sport",
        "-",
        "leisure",
        "gunsmith"
    ],
    "wof:name":"Lock Stock'N'Barrel",
    "wof:placetype":"venue"
},
  "geometry": {"coordinates":[-74.459564,42.468643],"type":"Point"}
}