{
  "type": "Feature",
  "properties": {
    "addr:full":"66 Churchill Rd Murrays Bay  Auckland Auckland",
    "addr:housenumber":"66",
    "addr:street":"Churchill Rd",
    "iso:country":"NZ",
    "sg:address":"66 Churchill Rd Murrays Bay ",
    "sg:city":"Auckland",
    "sg:classifiers":[
        {
            "category":"Building & Trades",
            "subcategory":"Plumbing",
            "type":"Services"
        }
    ],
    "sg:phone":"+64 9-479 4619",
    "sg:province":"Auckland",
    "sg:tags":[
        "home",
        "plumber",
        "garden",
        "related"
    ],
    "wof:name":"Gladding B D",
    "wof:placetype":"venue"
},
  "geometry": {"coordinates":[174.75376900000001,-36.728226],"type":"Point"}
}