{
  "type": "Feature",
  "properties": {
    "iso:country":"NZ",
    "sg:address":"469 Main St Palmerston ",
    "sg:city":"Palmerston North",
    "sg:classifiers":[
        {
            "category":"Sports & Exercise",
            "subcategory":"Sports Center",
            "type":"Entertainment"
        }
    ],
    "sg:phone":"+64 6-355 5932",
    "sg:province":"Manawatu-Wanganui",
    "sg:tags":[
        "game",
        "-",
        "leisure",
        "interactive"
    ],
    "wof:name":"Central Park Interactive",
    "wof:placetype":"venue"
},
  "geometry": {"coordinates":[175.61329699999999,-40.355034],"type":"Point"}
}