{
  "type": "Feature",
  "properties": {
    "addr:full":"Cnr Marine Pde & Delhi St  Wairoa",
    "addr:housenumber":"cnr;pde",
    "addr:street":"Marine;St",
    "iso:country":"NZ",
    "sg:address":"Cnr Marine Pde & Delhi St ",
    "sg:city":"Wairoa",
    "sg:classifiers":[
        {
            "category":"Bus Charters",
            "type":"Transportation"
        }
    ],
    "sg:phone":"+64 6-838 6049",
    "sg:tags":[
        "services",
        "travel",
        "tourism"
    ],
    "wof:name":"W & W Buses",
    "wof:placetype":"venue"
},
  "geometry": {"coordinates":[177.427032,-39.038639],"type":"Point"}
}