{
  "type": "Feature",
  "properties": {
    "iso:country":"NZ",
    "sg:address":"243 Strafford St, Timaru",
    "sg:city":"8601",
    "sg:classifiers":[
        {
            "category":"Banks & Credit Unions",
            "subcategory":"Bank",
            "type":"Services"
        }
    ],
    "sg:phone":"+64 5683179",
    "wof:name":"Trust Bank South Canterbury Ltd",
    "wof:placetype":"venue"
},
  "geometry": {"coordinates":[171.21783400000001,-44.395889],"type":"Point"}
}