{
  "type": "Feature",
  "properties": {
    "iso:country":"NZ",
    "sg:address":"PO Box 31205 Lower ",
    "sg:city":"Hutt",
    "sg:classifiers":[
        {
            "category":"Manufacturing",
            "subcategory":"Tools & Machinery",
            "type":"Manufacturing & Wholesale Goods"
        }
    ],
    "sg:phone":"+64 4-566 8180",
    "sg:province":"Wellington",
    "sg:tags":[
        "equipment",
        "industrial",
        "label"
    ],
    "wof:name":"RapidAllmark Labels",
    "wof:placetype":"venue"
},
  "geometry": {"coordinates":[174.90838600000001,-41.206631],"type":"Point"}
}