{
  "type": "Feature",
  "properties": {
    "addr:full":"225 Gt South Rd Otahuhu  Auckland Auckland",
    "addr:housenumber":"225",
    "addr:street":"Gt South Rd",
    "iso:country":"NZ",
    "sg:address":"225 Gt South Rd Otahuhu ",
    "sg:city":"Auckland",
    "sg:classifiers":[
        {
            "category":"Autos & Motor Vehicles",
            "subcategory":"Auto Supplies",
            "type":"Retail Goods"
        }
    ],
    "sg:phone":"+64 9-276 5032",
    "sg:province":"Auckland",
    "sg:tags":[
        "car",
        "supplies",
        "part",
        "automotive",
        "paint"
    ],
    "wof:name":"Colourworks Paint Supplies Ltd",
    "wof:placetype":"venue"
},
  "geometry": {"coordinates":[174.84017900000001,-36.940746],"type":"Point"}
}