{
  "type": "Feature",
  "properties": {
    "addr:full":"PO Box 38 326 Howick  Auckland Auckland",
    "addr:housenumber":"po box 38 326",
    "iso:country":"NZ",
    "sg:address":"PO Box 38 326 Howick ",
    "sg:city":"Auckland",
    "sg:classifiers":[
        {
            "category":"Coffee & Tea",
            "type":"Food & Drink"
        }
    ],
    "sg:phone":"+64 9-296 6955",
    "sg:province":"Auckland",
    "sg:tags":[
        "vegetable",
        "fruit",
        "veges"
    ],
    "wof:name":"Bosley Farms Ltd",
    "wof:placetype":"venue"
},
  "geometry": {"coordinates":[174.77041600000001,-36.884109],"type":"Point"}
}