{
  "type": "Feature",
  "properties": {
    "addr:full":"127 d Pilkington Rd Panmure  Auckland Auckland",
    "addr:housenumber":"127 d",
    "addr:street":"Pilkington Rd",
    "iso:country":"NZ",
    "sg:address":"127 d Pilkington Rd Panmure ",
    "sg:city":"Auckland",
    "sg:classifiers":[
        {
            "category":"Home & Garden",
            "subcategory":"Garden Supply",
            "type":"Retail Goods"
        }
    ],
    "sg:phone":"+64 9-570 1003",
    "sg:province":"Auckland",
    "sg:tags":[
        "gardening"
    ],
    "sg:website":"http://www.outdoorfurniture.co.nz",
    "wof:name":"Australasian Furniture Ltd",
    "wof:placetype":"venue"
},
  "geometry": {"coordinates":[174.85749799999999,-36.90181],"type":"Point"}
}