{
  "type": "Feature",
  "properties": {
    "addr:full":"59-63 Maurice Rd Penrose  Auckland Auckland",
    "addr:housenumber":"59-63",
    "addr:street":"Maurice Rd",
    "iso:country":"NZ",
    "sg:address":"59-63 Maurice Rd Penrose ",
    "sg:city":"Auckland",
    "sg:orig_category":"Industrial: Services: Material/Fluids Handling",
    "sg:phone":"+64 9-636 4167",
    "sg:province":"Auckland",
    "wof:name":"Anderton Holdings Limited",
    "wof:placetype":"venue"
},
  "geometry": {"coordinates":[174.809845,-36.919716],"type":"Point"}
}