{
  "type": "Feature",
  "properties": {
    "addr:full":"4A/710 Great South Rd  Manukau",
    "addr:housenumber":"4a / 710",
    "addr:street":"Great South Rd",
    "iso:country":"NZ",
    "sg:address":"4A/710 Great South Rd ",
    "sg:city":"Manukau",
    "sg:classifiers":[
        {
            "category":"Personal",
            "subcategory":"Tanning Parlor",
            "type":"Services"
        }
    ],
    "sg:phone":"+64 800 787 378",
    "sg:tags":[
        "sun",
        "health",
        "beauty"
    ],
    "wof:name":"Supertan Sunbeds Ltd",
    "wof:placetype":"venue"
},
  "geometry": {"coordinates":[174.88452100000001,-36.991287],"type":"Point"}
}