{
  "type": "Feature",
  "properties": {
    "iso:country":"NZ",
    "sg:address":"20 Shand St Green Island ",
    "sg:city":"Dunedin",
    "sg:classifiers":[
        {
            "category":"Health Services",
            "subcategory":"Clinic",
            "type":"Services"
        }
    ],
    "sg:phone":"+64 3-488 2222",
    "sg:province":"Otago",
    "sg:tags":[
        "medical",
        "beauty"
    ],
    "wof:name":"Green Island Family Health Care",
    "wof:placetype":"venue"
},
  "geometry": {"coordinates":[170.43012999999999,-45.902733],"type":"Point"}
}