{
  "type": "Feature",
  "properties": {
    "iso:country":"NZ",
    "sg:address":"54 Moray Pl ",
    "sg:city":"Dunedin",
    "sg:orig_category":"Automotive: General Services: Car Parking",
    "sg:phone":"+64 3-477 6099",
    "sg:province":"Otago",
    "wof:name":"Wilson Parking NZ Ltd",
    "wof:placetype":"venue"
},
  "geometry": {"coordinates":[-82.784721,28.013355],"type":"Point"}
}