{
  "type": "Feature",
  "properties": {
    "iso:country":"NZ",
    "sg:address":"47 Marguerita St ",
    "sg:city":"Rotorua",
    "sg:classifiers":[
        {
            "category":"Professional",
            "subcategory":"Detective & Security Services",
            "type":"Services"
        }
    ],
    "sg:phone":"+64 7-348 4876",
    "sg:province":"Bay of Plenty",
    "sg:tags":[
        "services",
        "automotive",
        "warrant",
        "fitness"
    ],
    "wof:name":"Vehicle Testing New Zealand Limited",
    "wof:placetype":"venue"
},
  "geometry": {"coordinates":[176.26033,-38.150791],"type":"Point"}
}