{
  "type": "Feature",
  "properties": {
    "addr:full":"31 Heu Heu St  Taupo Waikato",
    "addr:housenumber":"31",
    "addr:street":"Heu Heu St",
    "iso:country":"NZ",
    "sg:address":"31 Heu Heu St ",
    "sg:city":"Taupo",
    "sg:classifiers":[
        {
            "category":"Arts & Performance",
            "subcategory":"Art Gallery",
            "type":"Entertainment"
        }
    ],
    "sg:phone":"+64 7-377 6022",
    "sg:province":"Waikato",
    "sg:tags":[
        "arts",
        "sport",
        "leisure"
    ],
    "wof:name":"M C F Antiques and Interiors",
    "wof:placetype":"venue"
},
  "geometry": {"coordinates":[176.07086200000001,-38.688042],"type":"Point"}
}