{
  "type": "Feature",
  "properties": {
    "iso:country":"NZ",
    "sg:address":"92 Main Rd ",
    "sg:city":"Tapawera",
    "sg:orig_category":"Shopping: Retail Stores: Supermarkets",
    "sg:phone":"+64 3-522 4010",
    "wof:name":"Tapawera Four Square Discount Store",
    "wof:placetype":"venue"
},
  "geometry": {"coordinates":[172.823273,-41.386723],"type":"Point"}
}