{
  "type": "Feature",
  "properties": {
    "addr:full":"66 White St  Rotorua Bay of Plenty",
    "addr:housenumber":"66",
    "addr:street":"White St",
    "iso:country":"NZ",
    "sg:address":"66 White St ",
    "sg:city":"Rotorua",
    "sg:classifiers":[
        {
            "category":"Farming",
            "subcategory":"Fish & Marine Products",
            "type":"Manufacturing & Wholesale Goods"
        }
    ],
    "sg:phone":"+64 7-348 9335",
    "sg:province":"Bay of Plenty",
    "sg:tags":[
        "boats",
        "yacht",
        "transport",
        "boat",
        "supply"
    ],
    "wof:name":"Design Furniture Upholstery Specialists",
    "wof:placetype":"venue"
},
  "geometry": {"coordinates":[176.26170300000001,-38.151485],"type":"Point"}
}