{
  "type": "Feature",
  "properties": {
    "addr:full":"193 Parnell Rd Parnell  Auckland Auckland",
    "addr:housenumber":"193",
    "addr:street":"Parnell Rd",
    "iso:country":"NZ",
    "sg:address":"193 Parnell Rd Parnell ",
    "sg:city":"Auckland",
    "sg:classifiers":[
        {
            "category":"Sports & Exercise",
            "subcategory":"Playing Field",
            "type":"Entertainment"
        }
    ],
    "sg:phone":"+64 9-379 5178",
    "sg:province":"Auckland",
    "sg:tags":[
        "operator",
        "totalisator",
        "leisure"
    ],
    "wof:name":"TAB",
    "wof:placetype":"venue"
},
  "geometry": {"coordinates":[174.779999,-36.854912],"type":"Point"}
}