{
  "type": "Feature",
  "properties": {
    "addr:full":"13/15 Morningside Rd  Whangarei Northland",
    "addr:housenumber":"13 / 15",
    "addr:street":"Morningside Rd",
    "iso:country":"NZ",
    "sg:address":"13/15 Morningside Rd ",
    "sg:city":"Whangarei",
    "sg:classifiers":[
        {
            "category":"Manufacturing",
            "subcategory":"Textiles",
            "type":"Manufacturing & Wholesale Goods"
        }
    ],
    "sg:phone":"+64 9-438 2037",
    "sg:province":"Northland",
    "sg:tags":[
        "clothing",
        "fabric",
        "manufacturer"
    ],
    "wof:name":"Glenside Clothing Ltd",
    "wof:placetype":"venue"
},
  "geometry": {"coordinates":[174.31887800000001,-35.732185],"type":"Point"}
}