{
  "type": "Feature",
  "properties": {
    "addr:full":"Larcombs Rd  Rolleston",
    "addr:street":"Larcombs Rd",
    "iso:country":"NZ",
    "sg:address":"Larcombs Rd ",
    "sg:city":"Rolleston",
    "sg:classifiers":[
        {
            "category":"Food & Beverages",
            "subcategory":"Liquor & Beverages",
            "type":"Retail Goods"
        }
    ],
    "sg:phone":"+64 3-347 8909",
    "sg:tags":[
        "drink",
        "maker",
        "wine"
    ],
    "wof:name":"Larcomb Vineyard",
    "wof:placetype":"venue"
},
  "geometry": {"coordinates":[172.42941300000001,-43.581833],"type":"Point"}
}