{
  "type": "Feature",
  "properties": {
    "iso:country":"NZ",
    "sg:address":"Hudsons Rd Greenpark ",
    "sg:city":"Christchurch",
    "sg:orig_category":"Farming: Forestry: Logging Services",
    "sg:phone":"+64 252243301",
    "sg:province":"Canterbury",
    "wof:name":"David Murphy",
    "wof:placetype":"venue"
},
  "geometry": {"coordinates":[172.49084500000001,-43.67963],"type":"Point"}
}