{
  "type": "Feature",
  "properties": {
    "iso:country":"NZ",
    "sg:address":"8 Elizabeth St ",
    "sg:city":"Waikanae",
    "sg:classifiers":[
        {
            "category":"Recreation",
            "type":"Entertainment"
        }
    ],
    "sg:phone":"+64 4-293 5915",
    "sg:tags":[
        "sport",
        "leisure"
    ],
    "wof:name":"Waikanae Club Inc",
    "wof:placetype":"venue"
},
  "geometry": {"coordinates":[175.06604,-40.878025],"type":"Point"}
}