{
  "type": "Feature",
  "properties": {
    "addr:full":"305 A Mansfield St Newtown  Wellington Wellington",
    "addr:housenumber":"305 a",
    "addr:street":"Mansfield St",
    "iso:country":"NZ",
    "sg:address":"305 A Mansfield St Newtown ",
    "sg:city":"Wellington",
    "sg:orig_category":"Home And Garden: Furniture/Furnishings: Cabinetmakers",
    "sg:phone":"+64 4-389 5838",
    "sg:province":"Wellington",
    "wof:name":"Bryan Seal Cabinetmakers",
    "wof:placetype":"venue"
},
  "geometry": {"coordinates":[174.78154000000001,-41.318615],"type":"Point"}
}