{
  "type": "Feature",
  "properties": {
    "addr:full":"228 Antigua St  Christchurch Canterbury",
    "addr:housenumber":"228",
    "addr:street":"Antigua St",
    "iso:country":"NZ",
    "sg:address":"228 Antigua St ",
    "sg:city":"Christchurch",
    "sg:classifiers":[
        {
            "category":"Bars & Pubs",
            "subcategory":"Lounge",
            "type":"Food & Drink"
        }
    ],
    "sg:phone":"+64 3-365 3654",
    "sg:province":"Canterbury",
    "sg:tags":[
        "-",
        "asian"
    ],
    "wof:name":"Japanese Food Supplies ENSO",
    "wof:placetype":"venue"
},
  "geometry": {"coordinates":[-76.537834,37.605659],"type":"Point"}
}