{
  "type": "Feature",
  "properties": {
    "iso:country":"NZ",
    "sg:address":"361 Gt North Rd Henderson ",
    "sg:city":"Auckland",
    "sg:orig_category":"Shopping: Engravers",
    "sg:phone":"+64 9-838 9271",
    "sg:province":"Auckland",
    "wof:name":"Dr Shoe Henderson",
    "wof:placetype":"venue"
},
  "geometry": {"coordinates":[174.633026,-36.879642],"type":"Point"}
}