{
  "type": "Feature",
  "properties": {
    "iso:country":"NZ",
    "sg:address":"69 The Concourse Henderson ",
    "sg:city":"Auckland",
    "sg:classifiers":[
        {
            "category":"Retail",
            "subcategory":"Storage",
            "type":"Services"
        }
    ],
    "sg:phone":"+64 9-838 2670",
    "sg:province":"Auckland",
    "sg:website":"http://www.yellowpages.co.nz/for/europacific/dp9519.html",
    "wof:name":"Euro Pacific International Movers",
    "wof:placetype":"venue"
},
  "geometry": {"coordinates":[174.63295,-36.877289],"type":"Point"}
}