{
  "type": "Feature",
  "properties": {
    "iso:country":"NZ",
    "sg:address":"77 Remuera Rd Remuera ",
    "sg:city":"Auckland",
    "sg:classifiers":[
        {
            "category":"Health Services",
            "subcategory":"Health Practitioner",
            "type":"Services"
        }
    ],
    "sg:phone":"+64 9-524 2133",
    "sg:province":"Auckland",
    "sg:tags":[
        "services",
        "beauty",
        "acupuncturists"
    ],
    "wof:name":"Wong Doo Health Clinic",
    "wof:placetype":"venue"
},
  "geometry": {"coordinates":[174.78005999999999,-36.872185],"type":"Point"}
}