{
  "type": "Feature",
  "properties": {
    "addr:full":"21 Coleridge St Waltham  Christchurch Canterbury",
    "addr:housenumber":"21",
    "addr:street":"Coleridge St",
    "iso:country":"NZ",
    "sg:address":"21 Coleridge St Waltham ",
    "sg:city":"Christchurch",
    "sg:classifiers":[
        {
            "category":"Manufacturing",
            "subcategory":"Rubber & Plastics",
            "type":"Manufacturing & Wholesale Goods"
        }
    ],
    "sg:phone":"+64 3-379 3018",
    "sg:province":"Canterbury",
    "sg:tags":[
        "product",
        "industrial",
        "goods"
    ],
    "wof:name":"Rex Rubbercraft Ltd",
    "wof:placetype":"venue"
},
  "geometry": {"coordinates":[172.64987199999999,-43.547878],"type":"Point"}
}