{
  "type": "Feature",
  "properties": {
    "addr:full":"281 Fraser St  Tauranga Bay of Plenty",
    "addr:housenumber":"281",
    "addr:street":"Fraser St",
    "iso:country":"NZ",
    "sg:address":"281 Fraser St ",
    "sg:city":"Tauranga",
    "sg:orig_category":"Shopping: Accessories: Embroidery And Monograms",
    "sg:phone":"+64 7-578 1751",
    "sg:province":"Bay of Plenty",
    "wof:name":"LogoTech Embroidery & Screenprinting",
    "wof:placetype":"venue"
},
  "geometry": {"coordinates":[176.15014600000001,-37.71521],"type":"Point"}
}