{
  "type": "Feature",
  "properties": {
    "iso:country":"NZ",
    "sg:address":"28 Bledisloe St ",
    "sg:city":"Kurow",
    "sg:orig_category":"Food And Drink: Meats: Butchers",
    "sg:phone":"+64 3-436 0715",
    "wof:name":"Gerry Dyson's Butchery Kurow",
    "wof:placetype":"venue"
},
  "geometry": {"coordinates":[170.471725,-44.736259],"type":"Point"}
}