{
  "type": "Feature",
  "properties": {
    "iso:country":"NZ",
    "sg:address":"Cnr Inland Rd & Mt Lyford Forest Drive ",
    "sg:city":"Waiau",
    "sg:classifiers":[
        {
            "category":"Recreation",
            "type":"Entertainment"
        }
    ],
    "sg:phone":"+64 3-366 8155",
    "sg:province":"Canterbury",
    "sg:tags":[
        "trek",
        "travel",
        "horse",
        "tour",
        "tourism",
        "sightseeing"
    ],
    "wof:name":"Mt Lyford Horse Treks",
    "wof:placetype":"venue"
},
  "geometry": {"coordinates":[-157.962997,21.39381],"type":"Point"}
}