{
  "type": "Feature",
  "properties": {
    "addr:full":"Upper Wairau Rd R D 4 New Plymouth  Oakura",
    "addr:housenumber":"4",
    "addr:street":"Upper Wairau Rd R D",
    "iso:country":"NZ",
    "sg:address":"Upper Wairau Rd R D 4 New Plymouth ",
    "sg:city":"Oakura",
    "sg:classifiers":[
        {
            "category":"Personal",
            "type":"Services"
        }
    ],
    "sg:phone":"+64 6-752 7620",
    "sg:tags":[
        "services",
        "home",
        "garden",
        "counselling"
    ],
    "wof:name":"Manna Healing Centre",
    "wof:placetype":"venue"
},
  "geometry": {"coordinates":[173.95230100000001,-39.115391],"type":"Point"}
}