{
  "type": "Feature",
  "properties": {
    "iso:country":"NZ",
    "sg:address":"268 Church St Onehunga ",
    "sg:city":"Auckland",
    "sg:orig_category":"Industrial: Engineering: Engineers - Precision",
    "sg:phone":"+64 9-634 0160",
    "sg:province":"Auckland",
    "wof:name":"Hunkin Engineering Ltd",
    "wof:placetype":"venue"
},
  "geometry": {"coordinates":[174.79212999999999,-36.922318],"type":"Point"}
}