{
  "type": "Feature",
  "properties": {
    "iso:country":"NZ",
    "sg:address":"6 Barnard St ",
    "sg:city":"Timaru",
    "sg:classifiers":[
        {
            "category":"Home & Garden",
            "subcategory":"Building Materials",
            "type":"Retail Goods"
        }
    ],
    "sg:phone":"+64 3-684 2181",
    "sg:province":"Canterbury",
    "sg:tags":[
        "design",
        "fitting",
        "fittings",
        "kitchen"
    ],
    "wof:name":"Mainly Kitchens",
    "wof:placetype":"venue"
},
  "geometry": {"coordinates":[171.254501,-44.400002],"type":"Point"}
}