{
  "type": "Feature",
  "properties": {
    "addr:full":"Unit J, 119 Captain Springs Rd Onehunga  Auckland Auckland",
    "addr:housenumber":"119",
    "addr:street":"Captain Springs Rd",
    "iso:country":"NZ",
    "sg:address":"Unit J, 119 Captain Springs Rd Onehunga ",
    "sg:city":"Auckland",
    "sg:classifiers":[
        {
            "category":"Retail",
            "subcategory":"Auto Repair",
            "type":"Services"
        }
    ],
    "sg:phone":"+64 9-636 6468",
    "sg:province":"Auckland",
    "sg:tags":[
        "automotive",
        "servicing"
    ],
    "sg:website":"http://www.bossmotorbodies.co.nz/",
    "wof:name":"Boss Motorbodies Ltd",
    "wof:placetype":"venue"
},
  "geometry": {"coordinates":[174.783661,-36.909973],"type":"Point"}
}