{
  "type": "Feature",
  "properties": {
    "iso:country":"NZ",
    "sg:address":"52 Marywil Cre Takapuna ",
    "sg:city":"Auckland",
    "sg:orig_category":"Automotive: Accessories: Car Security Systems",
    "sg:phone":"+64 9-443 4713",
    "sg:province":"Auckland",
    "wof:name":"A1 Security",
    "wof:placetype":"venue"
},
  "geometry": {"coordinates":[174.76788300000001,-36.787838],"type":"Point"}
}