{
  "type": "Feature",
  "properties": {
    "iso:country":"NZ",
    "sg:address":"Auckland ",
    "sg:city":"Wide",
    "sg:classifiers":[
        {
            "category":"Social Services",
            "subcategory":"Retirement Home",
            "type":"Services"
        }
    ],
    "sg:phone":"+64 21 968 913",
    "sg:tags":[
        "sharpening",
        "garden"
    ],
    "wof:name":"Lion Mobile Sharpening",
    "wof:placetype":"venue"
},
  "geometry": {"coordinates":[-80.858093,38.472992],"type":"Point"}
}