{
  "type": "Feature",
  "properties": {
    "addr:full":"12 Woodruffe Ave Henderson  Auckland Auckland",
    "addr:housenumber":"12",
    "addr:street":"Woodruffe Ave",
    "iso:country":"NZ",
    "sg:address":"12 Woodruffe Ave Henderson ",
    "sg:city":"Auckland",
    "sg:classifiers":[
        {
            "category":"Farming",
            "subcategory":"Fish & Marine Products",
            "type":"Manufacturing & Wholesale Goods"
        }
    ],
    "sg:phone":"+64 9-836 4829",
    "sg:province":"Auckland",
    "sg:tags":[
        "boats",
        "yacht",
        "transport",
        "boat",
        "supply"
    ],
    "wof:name":"Osman & Son Ltd",
    "wof:placetype":"venue"
},
  "geometry": {"coordinates":[174.62970000000001,-36.887131],"type":"Point"}
}