{
  "type": "Feature",
  "properties": {
    "iso:country":"NZ",
    "sg:address":"56 Rostrevor St ",
    "sg:city":"Hamilton",
    "sg:orig_category":"Clothing And Fabric: Fabric: Drapers",
    "sg:phone":"+64 7-834 2366",
    "sg:province":"Waikato",
    "wof:name":"Fabric & Curtain Barn",
    "wof:placetype":"venue"
},
  "geometry": {"coordinates":[-87.988968,34.142426],"type":"Point"}
}