{
  "type": "Feature",
  "properties": {
    "iso:country":"NZ",
    "sg:address":"47-49 Atkinson Ave Otahuhu ",
    "sg:city":"Auckland",
    "sg:classifiers":[
        {
            "category":"Professional",
            "type":"Services"
        }
    ],
    "sg:phone":"+64 9-276 2012",
    "sg:province":"Auckland",
    "sg:tags":[
        "food",
        "drink",
        "catering"
    ],
    "wof:name":"Cowell's Pavlovas",
    "wof:placetype":"venue"
},
  "geometry": {"coordinates":[174.84303283689999,-36.9392585754],"type":"Point"}
}