{
  "type": "Feature",
  "properties": {
    "iso:country":"NZ",
    "sg:address":"281 Palmerston Rd ",
    "sg:city":"Gisborne",
    "sg:classifiers":[
        {
            "category":"Retail",
            "subcategory":"Auto Repair",
            "type":"Services"
        }
    ],
    "sg:phone":"+64 6-867 9342",
    "sg:province":"Gisborne",
    "sg:tags":[
        "muffler",
        "exhaust",
        "servicing",
        "automotive"
    ],
    "wof:name":"Pit Stop",
    "wof:placetype":"venue"
},
  "geometry": {"coordinates":[178.023529,-38.662273],"type":"Point"}
}