{
  "type": "Feature",
  "properties": {
    "addr:full":"1/94 Austin St Onekawa  Napier Hawke's Bay",
    "addr:housenumber":"1 / 94",
    "addr:street":"Austin St",
    "iso:country":"NZ",
    "sg:address":"1/94 Austin St Onekawa ",
    "sg:city":"Napier",
    "sg:classifiers":[
        {
            "category":"Manufacturing",
            "subcategory":"Rubber & Plastics",
            "type":"Manufacturing & Wholesale Goods"
        }
    ],
    "sg:phone":"+64 6-843 3251",
    "sg:province":"Hawke's Bay",
    "sg:tags":[
        "repair",
        "industrial",
        "-",
        "goods"
    ],
    "wof:name":"Trimline (Hawkes Bay) Ltd",
    "wof:placetype":"venue"
},
  "geometry": {"coordinates":[176.87777700000001,-39.498192],"type":"Point"}
}