{
  "type": "Feature",
  "properties": {
    "addr:full":"42 Egmont Rd New  Plymouth Taranaki",
    "addr:housenumber":"42",
    "addr:street":"Egmont Rd",
    "iso:country":"NZ",
    "sg:address":"42 Egmont Rd New ",
    "sg:city":"Plymouth",
    "sg:orig_category":"Automotive: General Services: Car Transporters",
    "sg:phone":"+64 6-755 9011",
    "sg:province":"Taranaki",
    "wof:name":"New Plymouth Towing (2000) Ltd",
    "wof:placetype":"venue"
},
  "geometry": {"coordinates":[174.12617499999999,-39.046421],"type":"Point"}
}