{
  "type": "Feature",
  "properties": {
    "iso:country":"NZ",
    "sg:address":"Levin ",
    "sg:city":"Abattoir",
    "sg:orig_category":"Food And Drink: Meats: Butchers",
    "sg:phone":"+64 800 884 009",
    "wof:name":"Levin Abbatoir",
    "wof:placetype":"venue"
},
  "geometry": {"coordinates":[175.285324,-40.625278],"type":"Point"}
}