{
  "type": "Feature",
  "properties": {
    "addr:full":"PO Box 722  Hawera Taranaki",
    "addr:housenumber":"po",
    "addr:postcode":"722",
    "addr:street":"Box",
    "iso:country":"NZ",
    "sg:address":"PO Box 722 ",
    "sg:city":"Hawera",
    "sg:orig_category":"Transport: Land: Taxis",
    "sg:phone":"+64 6-278 8888",
    "sg:province":"Taranaki",
    "wof:name":"Hawera Taxis Ltd",
    "wof:placetype":"venue"
},
  "geometry": {"coordinates":[174.27131700000001,-39.57584],"type":"Point"}
}