{
  "type": "Feature",
  "properties": {
    "iso:country":"NZ",
    "sg:address":"PO Box 722 ",
    "sg:city":"Hawera",
    "sg:orig_category":"Transport: Land: Taxis",
    "sg:phone":"+64 6-278 8888",
    "sg:province":"Taranaki",
    "wof:name":"Hawera Taxis Ltd",
    "wof:placetype":"venue"
},
  "geometry": {"coordinates":[174.271317,-39.57584],"type":"Point"}
}