{
  "type": "Feature",
  "properties": {
    "addr:full":"284 St Hill St  Wanganui Manawatu-Wanganui",
    "addr:housenumber":"284",
    "addr:street":"St Hill St",
    "iso:country":"NZ",
    "sg:address":"284 St Hill St ",
    "sg:city":"Wanganui",
    "sg:classifiers":[
        {
            "category":"Banks & Credit Unions",
            "subcategory":"Investment Brokerage",
            "type":"Services"
        }
    ],
    "sg:phone":"+64 6-348 0062",
    "sg:province":"Manawatu-Wanganui",
    "sg:tags":[
        "personal",
        "accountant",
        "chartered",
        "-",
        "finance"
    ],
    "wof:name":"Peach Cornwall Limited",
    "wof:placetype":"venue"
},
  "geometry": {"coordinates":[175.04373200000001,-39.929218],"type":"Point"}
}