{
  "type": "Feature",
  "properties": {
    "iso:country":"NZ",
    "sg:address":"164-188 Beaumont St Auckland PO Box ",
    "sg:city":"1709",
    "sg:classifiers":[
        {
            "category":"Utilities",
            "subcategory":"Fuel Oil & Lpg",
            "type":"Services"
        }
    ],
    "sg:phone":"+64 9-302 4700",
    "sg:tags":[
        "petrol",
        "energy",
        "industrial",
        "utilities"
    ],
    "wof:name":"Mobil Oil New Zealand Limited",
    "wof:placetype":"venue"
},
  "geometry": {"coordinates":[7.141216,46.796478],"type":"Point"}
}