{
  "type": "Feature",
  "properties": {
    "addr:full":"cnr Grey & Rangitane Sts Palmerston  Palmerston North Manawatu-Wanganui",
    "addr:street":"Cnr;Sts",
    "iso:country":"NZ",
    "sg:address":"cnr Grey & Rangitane Sts Palmerston ",
    "sg:city":"Palmerston North",
    "sg:orig_category":"Health And Beauty: Dental: Dentists",
    "sg:phone":"+64 6-356 9020",
    "sg:province":"Manawatu-Wanganui",
    "wof:name":"Cosmetic Dental Care Ltd",
    "wof:placetype":"venue"
},
  "geometry": {"coordinates":[175.611481,-40.357422],"type":"Point"}
}