{
  "type": "Feature",
  "properties": {
    "iso:country":"NZ",
    "sg:address":"105 Palmerston St ",
    "sg:city":"Riverton",
    "sg:orig_category":"Automotive: General Services: Service Stations",
    "sg:phone":"+64 3-234 8564",
    "wof:name":"Riverton Service Station (1995) Ltd",
    "wof:placetype":"venue"
},
  "geometry": {"coordinates":[-73.025848,41.957958],"type":"Point"}
}