{
  "type": "Feature",
  "properties": {
    "iso:country":"NZ",
    "sg:address":"38 Johnston St ",
    "sg:city":"Gore",
    "sg:classifiers":[
        {
            "category":"Retail",
            "subcategory":"Driving School",
            "type":"Services"
        }
    ],
    "sg:phone":"+64 25433858",
    "sg:province":"Southland",
    "sg:tags":[
        "training",
        "education",
        "driver"
    ],
    "wof:name":"Command Driving School",
    "wof:placetype":"venue"
},
  "geometry": {"coordinates":[-95.116547,35.530331],"type":"Point"}
}