{
  "type": "Feature",
  "properties": {
    "addr:full":"PO Box 6245  Rotorua Bay of Plenty",
    "addr:housenumber":"po",
    "addr:postcode":"6245",
    "addr:street":"Box",
    "iso:country":"NZ",
    "sg:address":"PO Box 6245 ",
    "sg:city":"Rotorua",
    "sg:classifiers":[
        {
            "category":"Home & Garden",
            "subcategory":"Carpets & Floor Coverings",
            "type":"Retail Goods"
        }
    ],
    "sg:phone":"+64 7-347 9823",
    "sg:province":"Bay of Plenty",
    "sg:tags":[
        "cleaning",
        "furniture"
    ],
    "wof:name":"Total Carpet Services",
    "wof:placetype":"venue"
},
  "geometry": {"coordinates":[176.24499499999999,-38.1418],"type":"Point"}
}