{
  "type": "Feature",
  "properties": {
    "addr:full":"1/80 Flanshaw Rd Te Atatu South  Auckland Auckland",
    "addr:housenumber":"1 / 80",
    "addr:street":"Flanshaw Rd",
    "iso:country":"NZ",
    "sg:address":"1/80 Flanshaw Rd Te Atatu South ",
    "sg:city":"Auckland",
    "sg:orig_category":"Shopping: Retail Stores: Florist Accessories",
    "sg:phone":"+64 9-834 2655",
    "sg:province":"Auckland",
    "wof:name":"Peninsula Agencies",
    "wof:placetype":"venue"
},
  "geometry": {"coordinates":[174.64218099999999,-36.856274],"type":"Point"}
}