{
  "type": "Feature",
  "properties": {
    "iso:country":"NZ",
    "sg:address":"Browning St ",
    "sg:city":"Napier",
    "sg:classifiers":[
        {
            "category":"Ice Cream",
            "type":"Food & Drink"
        }
    ],
    "sg:phone":"+64 6-835 7800",
    "sg:province":"Hawke's Bay",
    "sg:website":"http://www.friars.co.nz/hosts/countyhotel.html",
    "wof:name":"County Hotel The",
    "wof:placetype":"venue"
},
  "geometry": {"coordinates":[-80.588562,38.790821],"type":"Point"}
}