{
  "type": "Feature",
  "properties": {
    "iso:country":"NZ",
    "sg:address":"PO Box 47-691 Ponsonby",
    "sg:city":"Auckland",
    "sg:classifiers":[
        {
            "category":"Health Services",
            "subcategory":"Optometrist",
            "type":"Services"
        }
    ],
    "sg:phone":"+64 800 847 478",
    "sg:province":"Auckland",
    "sg:tags":[
        "optical",
        "optician",
        "beauty"
    ],
    "wof:name":"Visique",
    "wof:placetype":"venue"
},
  "geometry": {"coordinates":[174.742416,-36.85326],"type":"Point"}
}