{
  "type": "Feature",
  "properties": {
    "iso:country":"NZ",
    "sg:address":"46 Brown St Ponsonby ",
    "sg:city":"Auckland",
    "sg:classifiers":[
        {
            "category":"Education",
            "subcategory":"Special Training",
            "type":"Public Place"
        }
    ],
    "sg:phone":"+64 9-378 0411",
    "sg:province":"Auckland",
    "sg:website":"http://www.acetraining.co.nz",
    "wof:name":"ACE Training Ltd",
    "wof:placetype":"venue"
},
  "geometry": {"coordinates":[174.74310299999999,-36.856426],"type":"Point"}
}