{
  "type": "Feature",
  "properties": {
    "iso:country":"NZ",
    "sg:address":"109 Park Ave ",
    "sg:city":"Whangamata",
    "sg:orig_category":"Industrial: Parts: Valves",
    "sg:phone":"+64 7-865 9015",
    "wof:name":"The Skimmer Valve Company 2001 Ltd",
    "wof:placetype":"venue"
},
  "geometry": {"coordinates":[175.86741599999999,-37.220547],"type":"Point"}
}