{
  "type": "Feature",
  "properties": {
    "addr:full":"67 North Rd Gardens  Dunedin Otago",
    "addr:housenumber":"67",
    "addr:street":"North Rd",
    "iso:country":"NZ",
    "sg:address":"67 North Rd Gardens ",
    "sg:city":"Dunedin",
    "sg:orig_category":"Health And Beauty: Mental: Psychotherapy",
    "sg:phone":"+64 3-473 6102",
    "sg:province":"Otago",
    "wof:name":"Bond Anne",
    "wof:placetype":"venue"
},
  "geometry": {"coordinates":[-82.79143500000001,28.003851],"type":"Point"}
}