{
  "type": "Feature",
  "properties": {
    "iso:country":"NZ",
    "sg:address":"Te Kowhai Rd ",
    "sg:city":"Hamilton",
    "sg:classifiers":[
        {
            "category":"Food & Beverages",
            "subcategory":"Groceries & Convenience Stores",
            "type":"Retail Goods"
        }
    ],
    "sg:phone":"+64 7-849 5005",
    "sg:province":"Waikato",
    "sg:tags":[
        "foodstuff",
        "drink",
        "-"
    ],
    "wof:name":"Todays Food",
    "wof:placetype":"venue"
},
  "geometry": {"coordinates":[175.196136,-37.741592],"type":"Point"}
}