{
  "type": "Feature",
  "properties": {
    "addr:full":"43 Cleveland St Brooklyn  Wellington Wellington",
    "addr:housenumber":"43",
    "addr:street":"Cleveland St",
    "iso:country":"NZ",
    "sg:address":"43 Cleveland St Brooklyn ",
    "sg:city":"Wellington",
    "sg:classifiers":[
        {
            "category":"Sports & Exercise",
            "subcategory":"Tennis Court",
            "type":"Entertainment"
        }
    ],
    "sg:phone":"+64 4-385 0724",
    "sg:province":"Wellington",
    "sg:tags":[
        "arts",
        "art",
        "leisure"
    ],
    "wof:name":"Beca Fine Arts Ltd",
    "wof:placetype":"venue"
},
  "geometry": {"coordinates":[174.76448099999999,-41.30521],"type":"Point"}
}