{
  "type": "Feature",
  "properties": {
    "iso:country":"NZ",
    "sg:address":"192 Reeces Rd R D 3 Amberley ",
    "sg:city":"Omihi",
    "sg:classifiers":[
        {
            "category":"Food & Beverages",
            "subcategory":"Liquor & Beverages",
            "type":"Retail Goods"
        }
    ],
    "sg:phone":"+64 3-314 5901",
    "sg:tags":[
        "drink",
        "maker",
        "wine"
    ],
    "wof:name":"Daniel Schuster Wines Ltd",
    "wof:placetype":"venue"
},
  "geometry": {"coordinates":[-84.431168,39.198769],"type":"Point"}
}