{
  "type": "Feature",
  "properties": {
    "addr:full":"26 Williamson Ave Grey Lynn  Auckland Auckland",
    "addr:housenumber":"26",
    "addr:street":"Williamson Ave",
    "iso:country":"NZ",
    "sg:address":"26 Williamson Ave Grey Lynn ",
    "sg:city":"Auckland",
    "sg:orig_category":"Shopping: Accessories: Hats And Caps",
    "sg:phone":"+64 9-361 0206",
    "sg:province":"Auckland",
    "wof:name":"George Graham Ltd",
    "wof:placetype":"venue"
},
  "geometry": {"coordinates":[174.747513,-36.859108],"type":"Point"}
}