{
  "type": "Feature",
  "properties": {
    "addr:full":"15 Paremata Cre Paremata  Wellington Wellington",
    "addr:housenumber":"15",
    "iso:country":"NZ",
    "sg:address":"15 Paremata Cre Paremata ",
    "sg:city":"Wellington",
    "sg:orig_category":"Farming: Services: Veterinarians",
    "sg:phone":"+64 4-233 8059",
    "sg:province":"Wellington",
    "wof:name":"Paremata Veterinary Hospital",
    "wof:placetype":"venue"
},
  "geometry": {"coordinates":[174.86679100000001,-41.107944],"type":"Point"}
}