{
  "type": "Feature",
  "properties": {
    "addr:full":"12 Sheffield Pl Onekawa  Napier Hawke's Bay",
    "addr:housenumber":"12",
    "addr:street":"Sheffield Pl",
    "iso:country":"NZ",
    "sg:address":"12 Sheffield Pl Onekawa ",
    "sg:city":"Napier",
    "sg:classifiers":[
        {
            "category":"Manufacturing",
            "subcategory":"Textiles",
            "type":"Manufacturing & Wholesale Goods"
        }
    ],
    "sg:phone":"+64 6-843 4513",
    "sg:province":"Hawke's Bay",
    "sg:tags":[
        "clothing",
        "fabric",
        "manufacturer"
    ],
    "wof:name":"Moray Manufacturing Co",
    "wof:placetype":"venue"
},
  "geometry": {"coordinates":[176.879501,-39.50214],"type":"Point"}
}