{
  "type": "Feature",
  "properties": {
    "iso:country":"NZ",
    "sg:address":"107 Karamu Rd Nth ",
    "sg:city":"Hastings",
    "sg:orig_category":"Sports And Leisure: Sports: Equestrian: Saddlers",
    "sg:phone":"+64 6-878 7830",
    "sg:province":"Hawke's Bay",
    "wof:name":"Forbes & Co",
    "wof:placetype":"venue"
},
  "geometry": {"coordinates":[176.879517,-39.669403],"type":"Point"}
}