{
  "type": "Feature",
  "properties": {
    "addr:full":"4/14 Euclid Ave Te Rapa  Hamilton Waikato",
    "addr:housenumber":"4 / 14",
    "addr:street":"Euclid Ave",
    "iso:country":"NZ",
    "sg:address":"4/14 Euclid Ave Te Rapa ",
    "sg:city":"Hamilton",
    "sg:classifiers":[
        {
            "category":"Home & Garden",
            "subcategory":"Building Materials",
            "type":"Retail Goods"
        }
    ],
    "sg:phone":"+64 7-849 2440",
    "sg:province":"Waikato",
    "sg:tags":[
        "door",
        "fitting",
        "fittings"
    ],
    "wof:name":"Stirling & Stratford",
    "wof:placetype":"venue"
},
  "geometry": {"coordinates":[175.249481,-37.75885],"type":"Point"}
}