{
  "type": "Feature",
  "properties": {
    "iso:country":"NZ",
    "sg:address":"PO Box 97-588 South Auckl Mail ",
    "sg:city":"Cen",
    "sg:classifiers":[
        {
            "category":"Shopping",
            "subcategory":"Pharmacy",
            "type":"Retail Goods"
        }
    ],
    "sg:phone":"+64 800 667 784",
    "sg:tags":[
        "product",
        "health"
    ],
    "wof:name":"Apex Health & Nutrition Ltd",
    "wof:placetype":"venue"
},
  "geometry": {"coordinates":[-101.291153,19.911659],"type":"Point"}
}