{
  "type": "Feature",
  "properties": {
    "iso:country":"NZ",
    "sg:address":"4 Oxford St Tawa ",
    "sg:city":"Wellington",
    "sg:orig_category":"Industrial: Services: Specialist Services: Scanning",
    "sg:phone":"+64 4-232 9396",
    "sg:province":"Wellington",
    "wof:name":"NZ Micrographic Services Ltd",
    "wof:placetype":"venue"
},
  "geometry": {"coordinates":[174.825333,-41.173279],"type":"Point"}
}