{
  "type": "Feature",
  "properties": {
    "addr:full":"18 Kimberley St Casebrook  Christchurch Canterbury",
    "addr:housenumber":"18",
    "addr:street":"Kimberley St",
    "iso:country":"NZ",
    "sg:address":"18 Kimberley St Casebrook ",
    "sg:city":"Christchurch",
    "sg:orig_category":"Home And Garden: Gardening: Products: Garden Ornaments",
    "sg:phone":"+64 25513323",
    "sg:province":"Canterbury",
    "wof:name":"Classic Bronze",
    "wof:placetype":"venue"
},
  "geometry": {"coordinates":[172.59646599999999,-43.480957],"type":"Point"}
}