{
  "type": "Feature",
  "properties": {
    "iso:country":"NZ",
    "sg:address":"711 Tremaine Ave Palmerston ",
    "sg:city":"Palmerston North",
    "sg:classifiers":[
        {
            "category":"Home & Garden",
            "subcategory":"Building Materials",
            "type":"Retail Goods"
        }
    ],
    "sg:phone":"+64 6-355 4479",
    "sg:province":"Manawatu-Wanganui",
    "sg:tags":[
        "related"
    ],
    "sg:website":"http://www.chilltech.co.nz",
    "wof:name":"Chilltech",
    "wof:placetype":"venue"
},
  "geometry": {"coordinates":[175.613937,-40.337681],"type":"Point"}
}