{
  "type": "Feature",
  "properties": {
    "addr:full":"153 Hurndal St  Maungaturoto",
    "addr:housenumber":"153",
    "addr:street":"Hurndal St",
    "iso:country":"NZ",
    "sg:address":"153 Hurndal St ",
    "sg:city":"Maungaturoto",
    "sg:classifiers":[
        {
            "category":"Bus Charters",
            "type":"Transportation"
        }
    ],
    "sg:phone":"+64 9-431 8059",
    "sg:tags":[
        "services",
        "travel",
        "tourism"
    ],
    "wof:name":"Brooks Motors",
    "wof:placetype":"venue"
},
  "geometry": {"coordinates":[174.358597,-36.109028],"type":"Point"}
}