{
  "type": "Feature",
  "properties": {
    "addr:full":"217 High St  Motueka Tasman",
    "addr:housenumber":"217",
    "addr:street":"High St",
    "iso:country":"NZ",
    "sg:address":"217 High St ",
    "sg:city":"Motueka",
    "sg:classifiers":[
        {
            "category":"Health Services",
            "subcategory":"Optometrist",
            "type":"Services"
        }
    ],
    "sg:phone":"+64 3-528 8724",
    "sg:province":"Tasman",
    "sg:tags":[
        "optical",
        "optician",
        "beauty"
    ],
    "wof:name":"Matthews Optometrists",
    "wof:placetype":"venue"
},
  "geometry": {"coordinates":[173.01026899999999,-41.126648],"type":"Point"}
}