{
  "type": "Feature",
  "properties": {
    "iso:country":"NZ",
    "sg:address":"Air NZ Building Cnr Milford & Kitchener Rds Milford",
    "sg:city":"Auckland",
    "sg:orig_category":"Transport: Boats And Marine: Shipping",
    "sg:phone":"+64 9-486 5725",
    "sg:province":"Auckland",
    "wof:name":"Yacht Chandlers NZ Ltd",
    "wof:placetype":"venue"
},
  "geometry": {"coordinates":[174.764999,-36.771809],"type":"Point"}
}