{
  "type": "Feature",
  "properties": {
    "addr:full":"120 Birch Ave Judea  Tauranga Bay of Plenty",
    "addr:housenumber":"120",
    "addr:street":"Birch Ave",
    "iso:country":"NZ",
    "sg:address":"120 Birch Ave Judea ",
    "sg:city":"Tauranga",
    "sg:classifiers":[
        {
            "category":"Home & Garden",
            "subcategory":"Building Materials",
            "type":"Retail Goods"
        }
    ],
    "sg:phone":"+64 7-578 9425",
    "sg:province":"Bay of Plenty",
    "sg:tags":[
        "door",
        "fitting",
        "fittings"
    ],
    "wof:name":"Supreme Lock & Hardware",
    "wof:placetype":"venue"
},
  "geometry": {"coordinates":[176.14175399999999,-37.699928],"type":"Point"}
}