{
  "type": "Feature",
  "properties": {
    "iso:country":"NZ",
    "sg:address":"1158 Hinemoa St ",
    "sg:city":"Rotorua",
    "sg:classifiers":[
        {
            "category":"Ice Cream",
            "type":"Food & Drink"
        }
    ],
    "sg:phone":"+64 7-349 1504",
    "sg:province":"Bay of Plenty",
    "sg:tags":[
        "-"
    ],
    "wof:name":"Taste Of Paradise",
    "wof:placetype":"venue"
},
  "geometry": {"coordinates":[176.25198399999999,-38.137997],"type":"Point"}
}