{
  "type": "Feature",
  "properties": {
    "iso:country":"NZ",
    "sg:address":"PO Box 194 ",
    "sg:city":"Queenstown",
    "sg:orig_category":"Sports And Leisure: Sports: Aerial",
    "sg:phone":"+64 3-442 3148",
    "sg:province":"Otago",
    "wof:name":"Wakatipu Aero Club",
    "wof:placetype":"venue"
},
  "geometry": {"coordinates":[168.663254,-45.031445],"type":"Point"}
}