{
  "type": "Feature",
  "properties": {
    "iso:country":"NZ",
    "sg:address":"59 Victoria Ave ",
    "sg:city":"Wanganui",
    "sg:orig_category":"Clothing And Fabric: Clothing: Women'S Fashions",
    "sg:phone":"+64 6-347 2956",
    "sg:province":"Manawatu-Wanganui",
    "wof:name":"Jean Jones Wanganui",
    "wof:placetype":"venue"
},
  "geometry": {"coordinates":[175.053253,-39.933784],"type":"Point"}
}