{
  "type": "Feature",
  "properties": {
    "addr:full":"PO Box 26-031 Newlands  Wellington Wellington",
    "addr:housenumber":"po box 26-031",
    "addr:street":"Newlands",
    "iso:country":"NZ",
    "sg:address":"PO Box 26-031 Newlands ",
    "sg:city":"Wellington",
    "sg:classifiers":[
        {
            "category":"Retail",
            "subcategory":"Auto Repair",
            "type":"Services"
        }
    ],
    "sg:phone":"+64 25452102",
    "sg:province":"Wellington",
    "sg:tags":[
        "engine",
        "automotive",
        "servicing"
    ],
    "wof:name":"Car Tune Specialists",
    "wof:placetype":"venue"
},
  "geometry": {"coordinates":[174.76715100000001,-41.28054],"type":"Point"}
}