{
  "type": "Feature",
  "properties": {
    "iso:country":"NZ",
    "sg:address":"Otaika Valley Road R D 10 ",
    "sg:city":"Whangarei",
    "sg:classifiers":[
        {
            "category":"Shopping",
            "subcategory":"Bicycles & Sporting Goods",
            "type":"Retail Goods"
        }
    ],
    "sg:phone":"+64 800 304 382",
    "sg:province":"Wellington",
    "sg:tags":[
        "sport",
        "fishing",
        "hunting",
        "retailers"
    ],
    "wof:name":"P.T. Products",
    "wof:placetype":"venue"
},
  "geometry": {"coordinates":[174.320526,-35.725399],"type":"Point"}
}