{
  "type": "Feature",
  "properties": {
    "addr:full":"Town Ctr  Turangi",
    "addr:street":"Town Ctr",
    "iso:country":"NZ",
    "sg:address":"Town Ctr ",
    "sg:city":"Turangi",
    "sg:orig_category":"Shopping: Accessories: Lingerie - Retail",
    "sg:phone":"+64 7-386 7681",
    "wof:name":"Buttons 'N' Bows",
    "wof:placetype":"venue"
},
  "geometry": {"coordinates":[175.803955,-38.988941],"type":"Point"}
}