{
  "type": "Feature",
  "properties": {
    "addr:full":"PO Box 38-246 Wellington Mail Cntr Lower  Hutt Wellington",
    "addr:housenumber":"po box 38-246",
    "addr:street":"Cntr",
    "iso:country":"NZ",
    "sg:address":"PO Box 38-246 Wellington Mail Cntr Lower ",
    "sg:city":"Hutt",
    "sg:classifiers":[
        {
            "category":"Home & Garden",
            "subcategory":"Building Materials",
            "type":"Retail Goods"
        }
    ],
    "sg:phone":"+64 4-576 0644",
    "sg:province":"Wellington",
    "sg:tags":[
        "door",
        "fitting",
        "fittings"
    ],
    "wof:name":"Boston Wardrobe Systems",
    "wof:placetype":"venue"
},
  "geometry": {"coordinates":[174.904526,-41.208431],"type":"Point"}
}