{
  "type": "Feature",
  "properties": {
    "iso:country":"NZ",
    "sg:address":"www.photoandvideo.co.nz ",
    "sg:city":"Auckland",
    "sg:classifiers":[
        {
            "category":"Building & Trades",
            "subcategory":"Landscaping Services",
            "type":"Services"
        }
    ],
    "sg:phone":"+64 274 772 412",
    "sg:province":"Auckland",
    "sg:tags":[
        "personal",
        "home",
        "garden"
    ],
    "sg:website":"http://www.photoandvideo.co.nz",
    "wof:name":"Weddings Photo & Video",
    "wof:placetype":"venue"
},
  "geometry": {"coordinates":[-119.104576,36.597755],"type":"Point"}
}