{
  "type": "Feature",
  "properties": {
    "iso:country":"NZ",
    "sg:address":"155 Oteramika Rd ",
    "sg:city":"Invercargill",
    "sg:classifiers":[
        {
            "category":"Brewery",
            "type":"Food & Drink"
        }
    ],
    "sg:phone":"+64 25932056",
    "sg:province":"Southland",
    "sg:tags":[
        "brewer"
    ],
    "wof:name":"Invercargill Brewery",
    "wof:placetype":"venue"
},
  "geometry": {"coordinates":[168.413162,-46.414345],"type":"Point"}
}