{
  "type": "Feature",
  "properties": {
    "iso:country":"NZ",
    "sg:address":"1000 Great South Rd Penrose ",
    "sg:city":"Auckland",
    "sg:classifiers":[
        {
            "category":"Autos & Motor Vehicles",
            "subcategory":"Automobile Sales",
            "type":"Retail Goods"
        }
    ],
    "sg:phone":"+64 9-579 6830",
    "sg:province":"Auckland",
    "sg:tags":[
        "bus",
        "leasing",
        "truck",
        "automotive"
    ],
    "wof:name":"Auckland Truck Sales Limited",
    "wof:placetype":"venue"
},
  "geometry": {"coordinates":[174.830231,-36.923183],"type":"Point"}
}