{
  "type": "Feature",
  "properties": {
    "iso:country":"NZ",
    "sg:address":"13 Windsor Pl Mairangi Bay ",
    "sg:city":"Auckland",
    "sg:classifiers":[
        {
            "category":"Marine",
            "type":"Transportation"
        }
    ],
    "sg:phone":"+64 9-478 6742",
    "sg:province":"Auckland",
    "sg:tags":[
        "boats",
        "builder",
        "yacht",
        "transport",
        "boat"
    ],
    "wof:name":"Blumhardt Boatbuilders",
    "wof:placetype":"venue"
},
  "geometry": {"coordinates":[174.74816899999999,-36.738461],"type":"Point"}
}