{
  "type": "Feature",
  "properties": {
    "iso:country":"NZ",
    "sg:address":"Level 7, Baycorp House cnr Hopetoun & Hereford, Sts Newton ",
    "sg:city":"Auckland",
    "sg:orig_category":"Shopping: Retail Stores: Cds, Cassettes And Records",
    "sg:phone":"+64 9-377 1699",
    "sg:province":"Auckland",
    "wof:name":"Warner Music New Zealand Ltd",
    "wof:placetype":"venue"
},
  "geometry": {"coordinates":[174.754807,-36.860142],"type":"Point"}
}