{
  "type": "Feature",
  "properties": {
    "addr:full":"2//133 Glenmore Rd Pakuranga  Auckland Auckland",
    "addr:housenumber":"2 / / 133",
    "addr:street":"Glenmore Rd",
    "iso:country":"NZ",
    "sg:address":"2//133 Glenmore Rd Pakuranga ",
    "sg:city":"Auckland",
    "sg:orig_category":"Home And Garden: Gardening: Services: Landscaping",
    "sg:phone":"+64 25789253",
    "sg:province":"Auckland",
    "wof:name":"Mike Fife Landscape Construction",
    "wof:placetype":"venue"
},
  "geometry": {"coordinates":[174.88815299999999,-36.897114],"type":"Point"}
}