{
  "type": "Feature",
  "properties": {
    "addr:full":"140 Vipond Rd Whangaparaoa Hibiscus  Hibiscus Coast Auckland",
    "addr:housenumber":"140",
    "addr:street":"Vipond Rd",
    "iso:country":"NZ",
    "sg:address":"140 Vipond Rd Whangaparaoa Hibiscus ",
    "sg:city":"Hibiscus Coast",
    "sg:orig_category":"Transport: Boats And Marine: Products",
    "sg:phone":"+64 9-428 3419",
    "sg:province":"Auckland",
    "wof:name":"Propulse Propellers",
    "wof:placetype":"venue"
},
  "geometry": {"coordinates":[174.74916099999999,-36.634239],"type":"Point"}
}