{
  "type": "Feature",
  "properties": {
    "addr:full":"37 West Plains Rd Waikiwi  Invercargill Southland",
    "addr:housenumber":"37",
    "addr:street":"West Plains Rd",
    "iso:country":"NZ",
    "sg:address":"37 West Plains Rd Waikiwi ",
    "sg:city":"Invercargill",
    "sg:classifiers":[
        {
            "category":"Sports & Exercise",
            "subcategory":"Tennis Court",
            "type":"Entertainment"
        }
    ],
    "sg:phone":"+64 3-215 6698",
    "sg:province":"Southland",
    "sg:tags":[
        "hire",
        "-",
        "leisure"
    ],
    "wof:name":"Taff Hewton Sound Systems",
    "wof:placetype":"venue"
},
  "geometry": {"coordinates":[168.35140999999999,-46.378384],"type":"Point"}
}