{
  "type": "Feature",
  "properties": {
    "addr:full":"28 Hodgson Rd Pakowhai  Hastings Hawke's Bay",
    "addr:housenumber":"28",
    "addr:street":"Hodgson Rd",
    "iso:country":"NZ",
    "sg:address":"28 Hodgson Rd Pakowhai ",
    "sg:city":"Hastings",
    "sg:classifiers":[
        {
            "category":"Shopping",
            "subcategory":"Pets & Pet Supplies",
            "type":"Retail Goods"
        }
    ],
    "sg:phone":"+64 6-876 5655",
    "sg:province":"Hawke's Bay",
    "sg:tags":[
        "boarding",
        "garden",
        "pets",
        "catteries",
        "home",
        "kennel"
    ],
    "wof:name":"Pakowhai Cat Resort",
    "wof:placetype":"venue"
},
  "geometry": {"coordinates":[176.868652,-39.59193],"type":"Point"}
}