{
  "type": "Feature",
  "properties": {
    "addr:full":"90 Mays Rd Te Papapa  Auckland Auckland",
    "addr:housenumber":"90",
    "addr:street":"Mays Rd",
    "iso:country":"NZ",
    "sg:address":"90 Mays Rd Te Papapa ",
    "sg:city":"Auckland",
    "sg:classifiers":[
        {
            "category":"Shopping",
            "subcategory":"Pharmacy",
            "type":"Retail Goods"
        }
    ],
    "sg:phone":"+64 9-634 1036",
    "sg:province":"Auckland",
    "sg:tags":[
        "products",
        "medical",
        "health",
        "beauty",
        "supply"
    ],
    "wof:name":"New Zealand Medical & Scientific Ltd",
    "wof:placetype":"venue"
},
  "geometry": {"coordinates":[174.80140700000001,-36.918404],"type":"Point"}
}