{
  "type": "Feature",
  "properties": {
    "addr:full":"41 Barton St Woolston  Christchurch Canterbury",
    "addr:housenumber":"41",
    "addr:street":"Barton St",
    "iso:country":"NZ",
    "sg:address":"41 Barton St Woolston ",
    "sg:city":"Christchurch",
    "sg:orig_category":"Industrial: Metal: Products: Tubular Steel Products",
    "sg:phone":"+64 3-384 2184",
    "sg:province":"Canterbury",
    "wof:name":"Alastair Young Ltd",
    "wof:placetype":"venue"
},
  "geometry": {"coordinates":[172.68330399999999,-43.554855],"type":"Point"}
}