{
  "type": "Feature",
  "properties": {
    "addr:full":"46 West St Palmerston  Palmerston North Manawatu-Wanganui",
    "addr:housenumber":"46",
    "addr:street":"West St Palmerston",
    "iso:country":"NZ",
    "sg:address":"46 West St Palmerston ",
    "sg:city":"Palmerston North",
    "sg:classifiers":[
        {
            "category":"Building & Trades",
            "subcategory":"Cleaning & Sanitation",
            "type":"Services"
        }
    ],
    "sg:phone":"+64 6-356 3873",
    "sg:province":"Manawatu-Wanganui",
    "sg:tags":[
        "equipment",
        "industrial",
        "maintenance"
    ],
    "wof:name":"Doonan's Cleaning Rag Service",
    "wof:placetype":"venue"
},
  "geometry": {"coordinates":[175.60058599999999,-40.364155],"type":"Point"}
}