{
  "type": "Feature",
  "properties": {
    "iso:country":"NZ",
    "sg:address":"10 Brigade Rd Mangere ",
    "sg:city":"Auckland",
    "sg:classifiers":[
        {
            "category":"Manufacturing",
            "subcategory":"Furniture",
            "type":"Manufacturing & Wholesale Goods"
        }
    ],
    "sg:phone":"+64 9-275 2454",
    "sg:province":"Auckland",
    "sg:tags":[
        "furniture/furnishings",
        "home",
        "garden",
        "manufacturer"
    ],
    "wof:name":"Room Service Ltd",
    "wof:placetype":"venue"
},
  "geometry": {"coordinates":[174.781509,-36.974697],"type":"Point"}
}