{
  "type": "Feature",
  "properties": {
    "addr:full":"37 Golf Rd Tahunanui  Nelson Nelson",
    "addr:housenumber":"37",
    "addr:street":"Golf Rd",
    "iso:country":"NZ",
    "sg:address":"37 Golf Rd Tahunanui ",
    "sg:city":"Nelson",
    "sg:classifiers":[
        {
            "category":"Education",
            "subcategory":"Dance Studio",
            "type":"Public Place"
        }
    ],
    "sg:phone":"+64 3-546 4645",
    "sg:province":"Nelson",
    "sg:tags":[
        "school",
        "dancing",
        "-",
        "leisure",
        "sports",
        "sport"
    ],
    "wof:name":"J D Dancers",
    "wof:placetype":"venue"
},
  "geometry": {"coordinates":[173.24087499999999,-41.285362],"type":"Point"}
}