{
  "type": "Feature",
  "properties": {
    "iso:country":"NZ",
    "sg:address":"17 George St ",
    "sg:city":"Dunedin",
    "sg:classifiers":[
        {
            "category":"Structure",
            "subcategory":"Shopping Mall",
            "type":"Public Place"
        }
    ],
    "sg:phone":"+64 800 864 686",
    "sg:province":"Otago",
    "sg:tags":[
        "mail",
        "order"
    ],
    "sg:website":"http://www.dunedin-direct.co.nz/scottishshop",
    "wof:name":"Scottish Shop The",
    "wof:placetype":"venue"
},
  "geometry": {"coordinates":[-82.784721,28.013355],"type":"Point"}
}