{
  "type": "Feature",
  "properties": {
    "addr:full":"Tuhoe St  Whakatane Bay of Plenty",
    "addr:street":"St",
    "iso:country":"NZ",
    "sg:address":"Tuhoe St ",
    "sg:city":"Whakatane",
    "sg:orig_category":"Sports And Leisure: General: Clubs",
    "sg:phone":"+64 7-308 5183",
    "sg:province":"Bay of Plenty",
    "wof:name":"Whakatane Womens Bowling Club",
    "wof:placetype":"venue"
},
  "geometry": {"coordinates":[176.98419200000001,-37.965305],"type":"Point"}
}