{
  "type": "Feature",
  "properties": {
    "iso:country":"NZ",
    "sg:address":"110 B Ocean View Rd Oneroa ",
    "sg:city":"Auckland",
    "sg:classifiers":[
        {
            "category":"Bars & Pubs",
            "subcategory":"Wine Bar",
            "type":"Food & Drink"
        }
    ],
    "sg:phone":"+64 9-372 5559",
    "sg:province":"Auckland",
    "sg:tags":[
        "shop"
    ],
    "wof:name":"Crown Cellars",
    "wof:placetype":"venue"
},
  "geometry": {"coordinates":[174.732178,-36.843193],"type":"Point"}
}