{
  "type": "Feature",
  "properties": {
    "iso:country":"NZ",
    "sg:address":"PO Box 8565 Havelock North ",
    "sg:city":"Okawa",
    "sg:classifiers":[
        {
            "category":"Shopping",
            "subcategory":"Stationery & Office Supplies",
            "type":"Retail Goods"
        }
    ],
    "sg:phone":"+64 6-874 3731",
    "sg:tags":[
        "supplies",
        "educational",
        "material",
        "education",
        "training"
    ],
    "wof:name":"Blackboard Jungle Ltd",
    "wof:placetype":"venue"
},
  "geometry": {"coordinates":[176.87951699999999,-39.669399],"type":"Point"}
}