{
  "type": "Feature",
  "properties": {
    "iso:country":"NZ",
    "sg:address":"512 Queen St West ",
    "sg:city":"Hastings",
    "sg:orig_category":"Home And Garden: Gardening: Products: Lawnmowers",
    "sg:phone":"+64 6-878 2579",
    "sg:province":"Hawke's Bay",
    "wof:name":"Victa Sales & Service",
    "wof:placetype":"venue"
},
  "geometry": {"coordinates":[176.83900499999999,-39.636429],"type":"Point"}
}