{
  "type": "Feature",
  "properties": {
    "iso:country":"NZ",
    "sg:address":"Hunters Plaza 217 Great South Rd Papatoetoe ",
    "sg:city":"Auckland",
    "sg:orig_category":"Transport: Transportation: Postal Services",
    "sg:phone":"+64 9-277 7285",
    "sg:province":"Auckland",
    "wof:name":"Books & More: New Zealand Post",
    "wof:placetype":"venue"
},
  "geometry": {"coordinates":[174.867157,-36.971188],"type":"Point"}
}