{
  "type": "Feature",
  "properties": {
    "iso:country":"NZ",
    "sg:address":"10/35 Riccarton Rd Riccarton ",
    "sg:city":"Christchurch",
    "sg:orig_category":"Health And Beauty: Mental: Psychology",
    "sg:phone":"+64 3-348 5595",
    "sg:province":"Canterbury",
    "wof:name":"Clarke Graeme",
    "wof:placetype":"venue"
},
  "geometry": {"coordinates":[172.608322,-43.529232],"type":"Point"}
}