{
  "type": "Feature",
  "properties": {
    "iso:country":"NZ",
    "sg:address":"776 Birch Hill Rd Glentui ",
    "sg:city":"Loburn",
    "sg:classifiers":[
        {
            "category":"Home & Garden",
            "subcategory":"Garden Supply",
            "type":"Retail Goods"
        }
    ],
    "sg:phone":"+64 3-312 8672",
    "sg:tags":[
        "products",
        "nursery",
        "gardening"
    ],
    "wof:name":"Triple S Nursery",
    "wof:placetype":"venue"
},
  "geometry": {"coordinates":[172.53991699220001,-43.2526817322],"type":"Point"}
}