{
  "type": "Feature",
  "properties": {
    "addr:full":"74 Bentley Ave Glenfield  Auckland Auckland",
    "addr:housenumber":"74",
    "addr:street":"Bentley Ave",
    "iso:country":"NZ",
    "sg:address":"74 Bentley Ave Glenfield ",
    "sg:city":"Auckland",
    "sg:classifiers":[
        {
            "category":"Retail",
            "subcategory":"Repair Shop",
            "type":"Services"
        }
    ],
    "sg:phone":"+64 9-444 0228",
    "sg:province":"Auckland",
    "sg:tags":[
        "clothing",
        "fabric",
        "cleaning"
    ],
    "wof:name":"Clothing Alterations Threds",
    "wof:placetype":"venue"
},
  "geometry": {"coordinates":[174.723648,-36.781315],"type":"Point"}
}