{
  "type": "Feature",
  "properties": {
    "iso:country":"NZ",
    "sg:address":"16 McColl St Newmarket ",
    "sg:city":"Auckland",
    "sg:classifiers":[
        {
            "category":"Autos & Motor Vehicles",
            "subcategory":"Auto Supplies",
            "type":"Retail Goods"
        }
    ],
    "sg:phone":"+64 9-524 8028",
    "sg:province":"Auckland",
    "sg:tags":[
        "radiator",
        "car",
        "-",
        "part",
        "automotive",
        "supplies"
    ],
    "wof:name":"Vercoe Radiators Ltd",
    "wof:placetype":"venue"
},
  "geometry": {"coordinates":[174.7733,-36.867325],"type":"Point"}
}