{
  "type": "Feature",
  "properties": {
    "iso:country":"NZ",
    "sg:address":"31 Cameron St ",
    "sg:city":"Whangarei",
    "sg:classifiers":[
        {
            "category":"Shopping",
            "subcategory":"Clothing, Apparel, & Fashions",
            "type":"Retail Goods"
        }
    ],
    "sg:phone":"+64 9-438 8742",
    "sg:province":"Northland",
    "sg:tags":[
        "-",
        "hire",
        "clothing",
        "fabric"
    ],
    "wof:name":"Hugh Wright Ltd",
    "wof:placetype":"venue"
},
  "geometry": {"coordinates":[174.320862,-35.725769],"type":"Point"}
}