{
  "type": "Feature",
  "properties": {
    "addr:full":"Shop 6 Okara Shopping Ctr  Whangarei Northland",
    "addr:housenumber":"shop 6",
    "addr:street":"Shopping",
    "iso:country":"NZ",
    "sg:address":"Shop 6 Okara Shopping Ctr ",
    "sg:city":"Whangarei",
    "sg:classifiers":[
        {
            "category":"Personal",
            "subcategory":"Beauty Salon",
            "type":"Services"
        }
    ],
    "sg:phone":"+64 9-438 5500",
    "sg:province":"Northland",
    "sg:tags":[
        "therapy",
        "health"
    ],
    "wof:name":"Jagged Edge",
    "wof:placetype":"venue"
},
  "geometry": {"coordinates":[174.320526,-35.725399],"type":"Point"}
}