{
  "type": "Feature",
  "properties": {
    "iso:country":"NZ",
    "sg:address":"40 Riverside Dve ",
    "sg:city":"Whangarei",
    "sg:orig_category":"Transport: Boats And Marine: Products: Outboard Motors",
    "sg:phone":"+64 9-430 0975",
    "sg:province":"Nelson",
    "wof:name":"Anchorage Marine Team Ltd",
    "wof:placetype":"venue"
},
  "geometry": {"coordinates":[174.320526,-35.725399],"type":"Point"}
}