{
  "type": "Feature",
  "properties": {
    "addr:full":"27 College St  Wellington Wellington",
    "addr:housenumber":"27",
    "addr:street":"College St",
    "iso:country":"NZ",
    "sg:address":"27 College St ",
    "sg:city":"Wellington",
    "sg:classifiers":[
        {
            "category":"Bars & Pubs",
            "subcategory":"Wine Bar",
            "type":"Food & Drink"
        }
    ],
    "sg:phone":"+64 4-385 9748",
    "sg:province":"Wellington",
    "sg:tags":[
        "wining",
        "dining",
        "cafe"
    ],
    "sg:website":"http://www.laffare.co.nz",
    "wof:name":"Caffe L'Affare",
    "wof:placetype":"venue"
},
  "geometry": {"coordinates":[-93.98419199999999,39.131489],"type":"Point"}
}