{
  "type": "Feature",
  "properties": {
    "iso:country":"NZ",
    "sg:address":"Devonport ",
    "sg:city":"Auckland",
    "sg:classifiers":[
        {
            "category":"Manufacturing",
            "subcategory":"Tools & Machinery",
            "type":"Manufacturing & Wholesale Goods"
        }
    ],
    "sg:phone":"+64 800 445 286",
    "sg:province":"Auckland",
    "sg:tags":[
        "equipment",
        "industrial",
        "label"
    ],
    "wof:name":"Personalised School Products",
    "wof:placetype":"venue"
},
  "geometry": {"coordinates":[174.79956100000001,-36.824425],"type":"Point"}
}