{
  "type": "Feature",
  "properties": {
    "addr:full":"25 Sealy Pl Torbay  Auckland Auckland",
    "addr:housenumber":"25",
    "addr:street":"Sealy Pl",
    "iso:country":"NZ",
    "sg:address":"25 Sealy Pl Torbay ",
    "sg:city":"Auckland",
    "sg:classifiers":[
        {
            "category":"Home & Garden",
            "subcategory":"Carpets & Floor Coverings",
            "type":"Retail Goods"
        }
    ],
    "sg:phone":"+64 800 731 173",
    "sg:province":"Auckland",
    "sg:tags":[
        "protection",
        "fabric"
    ],
    "wof:name":"Soil Guard Fabric Protector",
    "wof:placetype":"venue"
},
  "geometry": {"coordinates":[174.74766500000001,-36.699665],"type":"Point"}
}