{
  "type": "Feature",
  "properties": {
    "iso:country":"NZ",
    "sg:address":"Levels Store Rd Levels ",
    "sg:city":"Timaru",
    "sg:classifiers":[
        {
            "category":"Food Court",
            "type":"Food & Drink"
        }
    ],
    "sg:phone":"+64 3-688 2216",
    "sg:province":"Canterbury",
    "sg:tags":[
        "egg",
        "product",
        "-"
    ],
    "wof:name":"Dickson Wholesale Products",
    "wof:placetype":"venue"
},
  "geometry": {"coordinates":[171.194794,-44.324783],"type":"Point"}
}