{
  "type": "Feature",
  "properties": {
    "iso:country":"NZ",
    "sg:address":"213 Jervois Rd Herne Bay ",
    "sg:city":"Auckland",
    "sg:classifiers":[
        {
            "category":"Travel",
            "subcategory":"Hotels & Motels",
            "type":"Entertainment"
        }
    ],
    "sg:phone":"+64 9-376 2139",
    "sg:province":"Auckland",
    "sg:tags":[
        "lodge",
        "tourism",
        "accommodation"
    ],
    "sg:website":"http://www.seabreeze.co.nz",
    "wof:name":"Seabreeze Boutique Motel",
    "wof:placetype":"venue"
},
  "geometry": {"coordinates":[174.730164,-36.848145],"type":"Point"}
}