{
  "type": "Feature",
  "properties": {
    "iso:country":"NZ",
    "sg:address":"Hilton Hwy Washdyke ",
    "sg:city":"Timaru",
    "sg:orig_category":"Transport: Transportation: Transport Operators",
    "sg:phone":"+64 3-688 2699",
    "sg:province":"Canterbury",
    "wof:name":"Tregenza G E Ltd",
    "wof:placetype":"venue"
},
  "geometry": {"coordinates":[171.23747299999999,-44.350239],"type":"Point"}
}