{
  "type": "Feature",
  "properties": {
    "iso:country":"NZ",
    "sg:address":"18 Vernon St Papakura ",
    "sg:city":"Auckland",
    "sg:orig_category":"Sports And Leisure: Sports: Golf",
    "sg:phone":"+64 9-298 2345",
    "sg:province":"Auckland",
    "sg:website":"http://www.ezgo.co.nz",
    "wof:name":"Golf Imports Ltd",
    "wof:placetype":"venue"
},
  "geometry": {"coordinates":[174.944168,-37.060669],"type":"Point"}
}