{
  "type": "Feature",
  "properties": {
    "addr:full":"530 Swanson Rd Swanson  Auckland Auckland",
    "addr:housenumber":"530",
    "addr:street":"Swanson Rd",
    "iso:country":"NZ",
    "sg:address":"530 Swanson Rd Swanson ",
    "sg:city":"Auckland",
    "sg:orig_category":"Home And Garden: Gardening: Products: Outdoor Furniture",
    "sg:phone":"+64 9-833 9053",
    "sg:province":"Auckland",
    "sg:website":"http://www.yellowpages.co.nz/for/hwl/dp41384.html",
    "wof:name":"Homestead Woodworkers Ltd",
    "wof:placetype":"venue"
},
  "geometry": {"coordinates":[174.591599,-36.863445],"type":"Point"}
}