{
  "type": "Feature",
  "properties": {
    "addr:full":"105 Wordsworth St Sydenham  Christchurch Canterbury",
    "addr:housenumber":"105",
    "addr:street":"Wordsworth St",
    "iso:country":"NZ",
    "sg:address":"105 Wordsworth St Sydenham ",
    "sg:city":"Christchurch",
    "sg:orig_category":"Industrial: Packaging: Bags",
    "sg:phone":"+64 3-366 7568",
    "sg:province":"Canterbury",
    "wof:name":"Flexoplas Packaging Ltd",
    "wof:placetype":"venue"
},
  "geometry": {"coordinates":[172.63940400000001,-43.544594],"type":"Point"}
}