{
  "type": "Feature",
  "properties": {
    "addr:full":"103 Greenwood St Frankton  Hamilton Waikato",
    "addr:housenumber":"103",
    "addr:street":"Greenwood St",
    "iso:country":"NZ",
    "sg:address":"103 Greenwood St Frankton ",
    "sg:city":"Hamilton",
    "sg:classifiers":[
        {
            "category":"Manufacturing",
            "subcategory":"Textiles",
            "type":"Manufacturing & Wholesale Goods"
        }
    ],
    "sg:phone":"+64 7-847 9537",
    "sg:province":"Waikato",
    "sg:tags":[
        "clothing",
        "fabric",
        "manufacturer"
    ],
    "wof:name":"Pragma Fashion Ltd & Factory Shop",
    "wof:placetype":"venue"
},
  "geometry": {"coordinates":[175.26365699999999,-37.786728],"type":"Point"}
}