{
  "type": "Feature",
  "properties": {
    "iso:country":"NZ",
    "sg:address":"PO Box 106258 Auckland Central ",
    "sg:city":"Auckland",
    "sg:classifiers":[
        {
            "category":"Juice Bar",
            "subcategory":"None",
            "type":"Food & Drink"
        }
    ],
    "sg:phone":"+64 9-358 5765",
    "sg:province":"Auckland",
    "sg:tags":[
        "fruit",
        "processor",
        "veges"
    ],
    "wof:name":"Charlie's Trading Company",
    "wof:placetype":"venue"
},
  "geometry": {"coordinates":[174.76454200000001,-36.848358],"type":"Point"}
}