{
  "type": "Feature",
  "properties": {
    "addr:full":"7/139 Cascades Rd Pakuranga  Auckland Auckland",
    "addr:housenumber":"7 / 139",
    "addr:street":"Cascades Rd",
    "iso:country":"NZ",
    "sg:address":"7/139 Cascades Rd Pakuranga ",
    "sg:city":"Auckland",
    "sg:classifiers":[
        {
            "category":"Retail",
            "subcategory":"Auto Repair",
            "type":"Services"
        }
    ],
    "sg:phone":"+64 9-576 7883",
    "sg:province":"Auckland",
    "sg:tags":[
        "wheel",
        "automotive",
        "servicing",
        "alignment"
    ],
    "wof:name":"Cascades Wheel Alignment Services",
    "wof:placetype":"venue"
},
  "geometry": {"coordinates":[174.90231299999999,-36.913418],"type":"Point"}
}