{
  "type": "Feature",
  "properties": {
    "addr:full":"88 Commercial Rd  Helensville Auckland",
    "addr:housenumber":"88",
    "addr:street":"Commercial Rd",
    "iso:country":"NZ",
    "sg:address":"88 Commercial Rd ",
    "sg:city":"Helensville",
    "sg:classifiers":[
        {
            "category":"Brewery",
            "type":"Food & Drink"
        }
    ],
    "sg:phone":"+64 9-420 7984",
    "sg:province":"Auckland",
    "sg:tags":[
        "brewer"
    ],
    "wof:name":"Burkes Wholesale Liquor Centre",
    "wof:placetype":"venue"
},
  "geometry": {"coordinates":[174.450684,-36.675571],"type":"Point"}
}