{
  "type": "Feature",
  "properties": {
    "addr:full":"40 Gillies Ave Epsom  Auckland Auckland",
    "addr:housenumber":"40",
    "addr:street":"Gillies Ave",
    "iso:country":"NZ",
    "sg:address":"40 Gillies Ave Epsom ",
    "sg:city":"Auckland",
    "sg:classifiers":[
        {
            "category":"Sports & Exercise",
            "subcategory":"Skate Park",
            "type":"Entertainment"
        }
    ],
    "sg:phone":"+64 9-524 5729",
    "sg:province":"Auckland",
    "sg:tags":[
        "arts",
        "museum",
        "leisure",
        "gallery"
    ],
    "wof:name":"Highwic",
    "wof:placetype":"venue"
},
  "geometry": {"coordinates":[174.77424600000001,-36.872288],"type":"Point"}
}