{
  "type": "Feature",
  "properties": {
    "addr:full":"82 Caledonian Rd St Albans  Christchurch Canterbury",
    "addr:housenumber":"82",
    "addr:street":"Caledonian Rd",
    "iso:country":"NZ",
    "sg:address":"82 Caledonian Rd St Albans ",
    "sg:city":"Christchurch",
    "sg:classifiers":[
        {
            "category":"Travel",
            "subcategory":"Bed & Breakfast",
            "type":"Entertainment"
        }
    ],
    "sg:phone":"+64 3-365 3985",
    "sg:province":"Canterbury",
    "sg:tags":[
        "tourism",
        "accommodation"
    ],
    "wof:name":"Barrich Homestay",
    "wof:placetype":"venue"
},
  "geometry": {"coordinates":[172.63587999999999,-43.516705],"type":"Point"}
}