{
  "type": "Feature",
  "properties": {
    "addr:full":"1016 Omahu Rd  Hastings Hawke's Bay",
    "addr:housenumber":"1016",
    "addr:street":"Omahu Rd",
    "iso:country":"NZ",
    "sg:address":"1016 Omahu Rd ",
    "sg:city":"Hastings",
    "sg:classifiers":[
        {
            "category":"Retail",
            "subcategory":"Auto Repair",
            "type":"Services"
        }
    ],
    "sg:phone":"+64 6-879 5044",
    "sg:province":"Hawke's Bay",
    "sg:tags":[
        "clutch",
        "brake",
        "servicing",
        "automotive"
    ],
    "wof:name":"Universal Auto Works",
    "wof:placetype":"venue"
},
  "geometry": {"coordinates":[-81.508163,29.711214],"type":"Point"}
}