{
  "type": "Feature",
  "properties": {
    "addr:full":"9/21 Poland Rd Glenfield  Auckland Auckland",
    "addr:housenumber":"9 / 21",
    "addr:street":"Poland Rd",
    "iso:country":"NZ",
    "sg:address":"9/21 Poland Rd Glenfield ",
    "sg:city":"Auckland",
    "sg:classifiers":[
        {
            "category":"Shopping",
            "subcategory":"Pharmacy",
            "type":"Retail Goods"
        }
    ],
    "sg:phone":"+64 9-443 7000",
    "sg:province":"Auckland",
    "sg:tags":[
        "products",
        "medical",
        "health",
        "beauty",
        "supply"
    ],
    "wof:name":"Michev Medical Supplies Ltd",
    "wof:placetype":"venue"
},
  "geometry": {"coordinates":[174.740692,-36.776588],"type":"Point"}
}