{
  "type": "Feature",
  "properties": {
    "addr:full":"ASB Building Cnr Williams and Selwyn Rds  Paihia Northland",
    "addr:street":"Cnr",
    "iso:country":"NZ",
    "sg:address":"ASB Building Cnr Williams and Selwyn Rds ",
    "sg:city":"Paihia",
    "sg:classifiers":[
        {
            "category":"Travel",
            "subcategory":"Travel Agent",
            "type":"Entertainment"
        }
    ],
    "sg:phone":"+64 9-402 7811",
    "sg:province":"Northland",
    "sg:tags":[
        "tourism",
        "broker"
    ],
    "wof:name":"Paihia Holiday Shoppe",
    "wof:placetype":"venue"
},
  "geometry": {"coordinates":[174.09106399999999,-35.283691],"type":"Point"}
}