{
  "type": "Feature",
  "properties": {
    "iso:country":"NZ",
    "sg:address":"PO Box 272-1152 Papakura ",
    "sg:city":"Auckland",
    "sg:orig_category":"Industrial: Equipment And Machinery: Trolleys",
    "sg:phone":"+64 9-292 8915",
    "sg:province":"Auckland",
    "wof:name":"European Castor Sales Ltd",
    "wof:placetype":"venue"
},
  "geometry": {"coordinates":[174.959457,-37.059521],"type":"Point"}
}