{
  "type": "Feature",
  "properties": {
    "iso:country":"NZ",
    "sg:address":"56 Cathedral Sq ",
    "sg:city":"Christchurch",
    "sg:orig_category":"Travel And Tourism: Accommodation: Backpackers",
    "sg:phone":"+64 3-982 2225",
    "sg:province":"Canterbury",
    "sg:website":"http://www.startimes.co.nz",
    "wof:name":"Star Times Accommodation & Backpackers",
    "wof:placetype":"venue"
},
  "geometry": {"coordinates":[-76.537834,37.605659],"type":"Point"}
}