{
  "type": "Feature",
  "properties": {
    "iso:country":"NZ",
    "sg:address":"Unit 10 673 Great North Rd Grey Lynn ",
    "sg:city":"Auckland",
    "sg:classifiers":[
        {
            "category":"Manufacturing",
            "subcategory":"Furniture",
            "type":"Manufacturing & Wholesale Goods"
        }
    ],
    "sg:phone":"+64 9-361 2699",
    "sg:province":"Auckland",
    "sg:tags":[
        "furniture/furnishings",
        "home",
        "garden",
        "manufacturer"
    ],
    "wof:name":"Luhrmann Upholstery",
    "wof:placetype":"venue"
},
  "geometry": {"coordinates":[174.73344399999999,-36.864235],"type":"Point"}
}