{
  "type": "Feature",
  "properties": {
    "addr:full":"301 George St  Dunedin Otago",
    "addr:housenumber":"301",
    "addr:street":"George St",
    "iso:country":"NZ",
    "sg:address":"301 George St ",
    "sg:city":"Dunedin",
    "sg:classifiers":[
        {
            "category":"Shopping",
            "subcategory":"Clothing, Apparel, & Fashions",
            "type":"Retail Goods"
        }
    ],
    "sg:phone":"+64 3-477 3066",
    "sg:province":"Otago",
    "sg:tags":[
        "-",
        "hire",
        "clothing",
        "fabric"
    ],
    "wof:name":"Bob Shepherd Suit Hire",
    "wof:placetype":"venue"
},
  "geometry": {"coordinates":[170.50602699999999,-45.869705],"type":"Point"}
}