{
  "type": "Feature",
  "properties": {
    "iso:country":"NZ",
    "sg:address":"301 George St ",
    "sg:city":"Dunedin",
    "sg:classifiers":[
        {
            "category":"Shopping",
            "subcategory":"Clothing, Apparel, & Fashions",
            "type":"Retail Goods"
        }
    ],
    "sg:phone":"+64 3-477 3066",
    "sg:province":"Otago",
    "sg:tags":[
        "-",
        "hire",
        "clothing",
        "fabric"
    ],
    "wof:name":"Bob Shepherd Suit Hire",
    "wof:placetype":"venue"
},
  "geometry": {"coordinates":[170.506027,-45.869705],"type":"Point"}
}