{
  "type": "Feature",
  "properties": {
    "iso:country":"NZ",
    "sg:address":"14 Ameku Rd ",
    "sg:city":"Raetihi",
    "sg:classifiers":[
        {
            "category":"Travel",
            "subcategory":"Hotels & Motels",
            "type":"Entertainment"
        }
    ],
    "sg:phone":"+64 6-385 4511",
    "sg:tags":[
        "lodge",
        "tourism",
        "accommodation"
    ],
    "wof:name":"Country Classic Lodge",
    "wof:placetype":"venue"
},
  "geometry": {"coordinates":[175.267502,-39.424107],"type":"Point"}
}