{
  "type": "Feature",
  "properties": {
    "iso:country":"NZ",
    "sg:address":"169 London St ",
    "sg:city":"Hamilton",
    "sg:classifiers":[
        {
            "category":"Professional",
            "type":"Services"
        }
    ],
    "sg:phone":"+64 7-839 1859",
    "sg:province":"Waikato",
    "sg:tags":[
        "home",
        "cleaning",
        "help",
        "garden"
    ],
    "wof:name":"Access Homehealth",
    "wof:placetype":"venue"
},
  "geometry": {"coordinates":[-84.57756,39.395996],"type":"Point"}
}