{
  "type": "Feature",
  "properties": {
    "iso:country":"NZ",
    "sg:address":"51 Domain Rd ",
    "sg:city":"Whakatane",
    "sg:orig_category":"Health And Beauty: Specialists: Midwives",
    "sg:phone":"+64 7-308 6515",
    "sg:province":"Bay of Plenty",
    "wof:name":"Carlin G",
    "wof:placetype":"venue"
},
  "geometry": {"coordinates":[176.987808,-37.95853],"type":"Point"}
}