{
  "type": "Feature",
  "properties": {
    "iso:country":"NZ",
    "sg:address":"7 Johns La Pakuranga ",
    "sg:city":"Auckland",
    "sg:orig_category":"Farming: Services: Veterinarians",
    "sg:phone":"+64 9-576 4108",
    "sg:province":"Auckland",
    "wof:name":"Pakuranga Veterinary Clinic & Cattery",
    "wof:placetype":"venue"
},
  "geometry": {"coordinates":[174.884308,-36.909271],"type":"Point"}
}