{
  "type": "Feature",
  "properties": {
    "addr:full":"44 Browne St Parkside  Timaru Canterbury",
    "addr:housenumber":"44",
    "addr:street":"Browne St",
    "iso:country":"NZ",
    "sg:address":"44 Browne St Parkside ",
    "sg:city":"Timaru",
    "sg:orig_category":"Sports And Leisure: General: Clubs",
    "sg:phone":"+64 3-688 1935",
    "sg:province":"Canterbury",
    "wof:name":"Timaru Cosmopolitan Club Inc (Members)",
    "wof:placetype":"venue"
},
  "geometry": {"coordinates":[171.25060999999999,-44.40279],"type":"Point"}
}