{
  "type": "Feature",
  "properties": {
    "addr:full":"Old Waipu Rd  Mangawhai",
    "addr:street":"Waipu Rd",
    "iso:country":"NZ",
    "sg:address":"Old Waipu Rd ",
    "sg:city":"Mangawhai",
    "sg:classifiers":[
        {
            "category":"Food & Beverages",
            "subcategory":"Candy",
            "type":"Retail Goods"
        }
    ],
    "sg:phone":"+64 9-431 5500",
    "sg:tags":[
        "confectioner",
        "drink",
        "-"
    ],
    "wof:name":"Bennetts Of Mangawhai Ltd",
    "wof:placetype":"venue"
},
  "geometry": {"coordinates":[174.55349699999999,-36.112072],"type":"Point"}
}