{
  "type": "Feature",
  "properties": {
    "iso:country":"NZ",
    "sg:address":"PO Box 591 ",
    "sg:city":"Rangiora",
    "sg:orig_category":"Shopping: Hobbies And Games: Aromatherapy",
    "sg:phone":"+64 3-313 8032",
    "sg:province":"Canterbury",
    "wof:name":"Essential Oils of New Zealand Ltd",
    "wof:placetype":"venue"
},
  "geometry": {"coordinates":[172.59030200000001,-43.302963],"type":"Point"}
}