{
  "type": "Feature",
  "properties": {
    "addr:full":"West Coast, Westport, Greymouth  Christchurch Canterbury",
    "iso:country":"NZ",
    "sg:address":"West Coast, Westport, Greymouth ",
    "sg:city":"Christchurch",
    "sg:orig_category":"Health And Beauty: Medical: Hospitals",
    "sg:phone":"+64 3-366 1876",
    "sg:province":"Canterbury",
    "sg:website":"http://www.southerncross.co.nz",
    "wof:name":"Southern Cross Healthcare",
    "wof:placetype":"venue"
},
  "geometry": {"coordinates":[172.63729900000001,-43.531311],"type":"Point"}
}