{
  "type": "Feature",
  "properties": {
    "iso:country":"NZ",
    "sg:address":"55 B Portage Rd ",
    "sg:city":"Auckland",
    "sg:classifiers":[
        {
            "category":"Manufacturing",
            "subcategory":"Tools & Machinery",
            "type":"Manufacturing & Wholesale Goods"
        }
    ],
    "sg:phone":"+64 9-827 6567",
    "sg:province":"Auckland",
    "sg:tags":[
        "equipment",
        "hot",
        "industrial",
        "stamping"
    ],
    "wof:name":"Techspan",
    "wof:placetype":"venue"
},
  "geometry": {"coordinates":[-119.10457599999999,36.597755],"type":"Point"}
}