{
  "type": "Feature",
  "properties": {
    "iso:country":"NZ",
    "sg:address":"6 Broadway Papakura ",
    "sg:city":"Auckland",
    "sg:classifiers":[
        {
            "category":"Shopping",
            "subcategory":"Crafts & Fabrics",
            "type":"Retail Goods"
        }
    ],
    "sg:phone":"+64 9-298 5278",
    "sg:province":"Manawatu-Wanganui",
    "sg:tags":[
        "clothing"
    ],
    "wof:name":"Top Togs & Knitting",
    "wof:placetype":"venue"
},
  "geometry": {"coordinates":[174.942261,-37.062168],"type":"Point"}
}