{
  "type": "Feature",
  "properties": {
    "addr:full":"120-122 Fitzherbert Ave Palmerston  Palmerston North Manawatu-Wanganui",
    "addr:postcode":"120-122",
    "addr:street":"Fitzherbert Ave",
    "iso:country":"NZ",
    "sg:address":"120-122 Fitzherbert Ave Palmerston ",
    "sg:city":"Palmerston North",
    "sg:classifiers":[
        {
            "category":"Travel",
            "subcategory":"Hotels & Motels",
            "type":"Entertainment"
        }
    ],
    "sg:phone":"+64 6-356 5388",
    "sg:province":"Manawatu-Wanganui",
    "sg:tags":[
        "holiday",
        "tourism",
        "accommodation"
    ],
    "sg:website":"http://www.rosecitymotel.co.nz",
    "wof:name":"Rose City Motel",
    "wof:placetype":"venue"
},
  "geometry": {"coordinates":[175.614273,-40.360512],"type":"Point"}
}