{
  "type": "Feature",
  "properties": {
    "iso:country":"NZ",
    "sg:address":"Albert Mall ",
    "sg:city":"Greymouth",
    "sg:classifiers":[
        {
            "category":"Health Services",
            "subcategory":"Dentist",
            "type":"Services"
        }
    ],
    "sg:phone":"+64 3-768 6243",
    "sg:province":"West Coast",
    "sg:tags":[
        "dental",
        "beauty"
    ],
    "wof:name":"Margetts Dr Guy BSc BDS",
    "wof:placetype":"venue"
},
  "geometry": {"coordinates":[171.209656,-42.448853],"type":"Point"}
}