{
  "type": "Feature",
  "properties": {
    "addr:full":"140 Devon St East New  Plymouth Taranaki",
    "addr:housenumber":"140",
    "addr:street":"Devon St",
    "iso:country":"NZ",
    "sg:address":"140 Devon St East New ",
    "sg:city":"Plymouth",
    "sg:classifiers":[
        {
            "category":"Shopping",
            "subcategory":"Clothing, Apparel, & Fashions",
            "type":"Retail Goods"
        }
    ],
    "sg:phone":"+64 6-757 2727",
    "sg:province":"Taranaki",
    "sg:tags":[
        "-",
        "hire",
        "clothing",
        "fabric"
    ],
    "wof:name":"Disguise Costumes",
    "wof:placetype":"venue"
},
  "geometry": {"coordinates":[174.07844499999999,-39.056606],"type":"Point"}
}