{
  "type": "Feature",
  "properties": {
    "addr:full":"Rn118 State Highway 3  Whangaehu",
    "addr:street":"State Highway 3 Whangaehu",
    "iso:country":"NZ",
    "sg:address":"Rn118 State Highway 3 ",
    "sg:city":"Whangaehu",
    "sg:classifiers":[
        {
            "category":"Bars & Pubs",
            "subcategory":"Lounge",
            "type":"Food & Drink"
        }
    ],
    "sg:phone":"+64 25574451",
    "sg:tags":[
        "-"
    ],
    "wof:name":"Jim's Organiks",
    "wof:placetype":"venue"
},
  "geometry": {"coordinates":[175.80543499999999,-40.897579],"type":"Point"}
}