{
  "type": "Feature",
  "properties": {
    "addr:full":"82 a Hillside Rd Glenfield  Auckland Auckland",
    "addr:housenumber":"82 a",
    "addr:street":"Hillside Rd",
    "iso:country":"NZ",
    "sg:address":"82 a Hillside Rd Glenfield ",
    "sg:city":"Auckland",
    "sg:classifiers":[
        {
            "category":"Home & Garden",
            "subcategory":"Building Materials",
            "type":"Retail Goods"
        }
    ],
    "sg:phone":"+64 9-444 9985",
    "sg:province":"Auckland",
    "sg:tags":[
        "fittings",
        "door",
        "garage"
    ],
    "wof:name":"Castle Doors Ltd",
    "wof:placetype":"venue"
},
  "geometry": {"coordinates":[174.73468,-36.777519],"type":"Point"}
}