{
  "type": "Feature",
  "properties": {
    "addr:full":"8 Wise St Riccarton  Christchurch Canterbury",
    "addr:housenumber":"8",
    "addr:street":"Wise St;Christchurch",
    "iso:country":"NZ",
    "sg:address":"8 Wise St Riccarton ",
    "sg:city":"Christchurch",
    "sg:orig_category":"Automotive: General Services: Vehicle Certification",
    "sg:phone":"+64 3-338 9566",
    "sg:province":"Canterbury",
    "wof:name":"Hesson Neil Repair Certification Ltd",
    "wof:placetype":"venue"
},
  "geometry": {"coordinates":[172.597351,-43.532143],"type":"Point"}
}