{
  "type": "Feature",
  "properties": {
    "iso:country":"NZ",
    "sg:address":"Weavers Crossing Rotowaro Rd ",
    "sg:city":"Huntly",
    "sg:orig_category":"Home And Garden: Gardening: Products: Outdoor Furniture",
    "sg:phone":"+64 7-828 0690",
    "wof:name":"Solid Energy Waikato",
    "wof:placetype":"venue"
},
  "geometry": {"coordinates":[175.16101074220001,-37.5565032959],"type":"Point"}
}