{
  "type": "Feature",
  "properties": {
    "iso:country":"NZ",
    "sg:address":"Cornwall St Lower ",
    "sg:city":"Hutt",
    "sg:orig_category":"Home And Garden: Furniture/Furnishings: Curtains",
    "sg:phone":"+64 4-569 8136",
    "sg:province":"Wellington",
    "wof:name":"Guthrie Bowron",
    "wof:placetype":"venue"
},
  "geometry": {"coordinates":[174.908997,-41.210922],"type":"Point"}
}