{
  "type": "Feature",
  "properties": {
    "addr:full":"PO Box 57-056 Mana  Wellington Wellington",
    "addr:housenumber":"po box",
    "addr:postcode":"57-056",
    "iso:country":"NZ",
    "sg:address":"PO Box 57-056 Mana ",
    "sg:city":"Wellington",
    "sg:orig_category":"Home And Garden: Gardening: Services: Tree Services",
    "sg:phone":"+64 4-233 9395",
    "sg:province":"Wellington",
    "wof:name":"Tree Fella's NZ Ltd",
    "wof:placetype":"venue"
},
  "geometry": {"coordinates":[174.76715100000001,-41.28054],"type":"Point"}
}