{
  "type": "Feature",
  "properties": {
    "addr:full":"172 Ruru Rd Bromley PO Box 19936  Christchurch Canterbury",
    "addr:housenumber":"172;po box",
    "addr:postcode":"19936",
    "addr:street":"Ruru Rd",
    "iso:country":"NZ",
    "sg:address":"172 Ruru Rd Bromley PO Box 19936 ",
    "sg:city":"Christchurch",
    "sg:classifiers":[
        {
            "category":"Internet Cafe",
            "subcategory":"None",
            "type":"Food & Drink"
        }
    ],
    "sg:phone":"+64 3-982 3008",
    "sg:province":"Canterbury",
    "sg:tags":[
        "fish",
        "processing",
        "processor"
    ],
    "wof:name":"Pacific Canneries Ltd",
    "wof:placetype":"venue"
},
  "geometry": {"coordinates":[172.637314,-43.531315],"type":"Point"}
}