{
  "type": "Feature",
  "properties": {
    "iso:country":"NZ",
    "sg:address":"59 St John St ",
    "sg:city":"Tauranga",
    "sg:orig_category":"Farming: Horticulture: Horticultural Supplies",
    "sg:phone":"+64 7-578 0442",
    "sg:province":"Bay of Plenty",
    "wof:name":"General Packaging",
    "wof:placetype":"venue"
},
  "geometry": {"coordinates":[176.158554,-37.697025],"type":"Point"}
}