{
  "type": "Feature",
  "properties": {
    "addr:full":"59 St John St  Tauranga Bay of Plenty",
    "addr:housenumber":"59",
    "addr:street":"St John St",
    "iso:country":"NZ",
    "sg:address":"59 St John St ",
    "sg:city":"Tauranga",
    "sg:orig_category":"Farming: Horticulture: Horticultural Supplies",
    "sg:phone":"+64 7-578 0442",
    "sg:province":"Bay of Plenty",
    "wof:name":"General Packaging",
    "wof:placetype":"venue"
},
  "geometry": {"coordinates":[176.15855400000001,-37.697025],"type":"Point"}
}