{
  "type": "Feature",
  "properties": {
    "iso:country":"NZ",
    "sg:address":"96 Nandina La ",
    "sg:city":"Pukekohe",
    "sg:classifiers":[
        {
            "category":"Home & Garden",
            "subcategory":"Home Furnishings",
            "type":"Retail Goods"
        }
    ],
    "sg:phone":"+64 9-238 1884",
    "sg:province":"Auckland",
    "sg:tags":[
        "furniture/furnishings",
        "upholstery",
        "supply"
    ],
    "wof:name":"Horne Upholstery",
    "wof:placetype":"venue"
},
  "geometry": {"coordinates":[174.913666,-37.235378],"type":"Point"}
}