{
  "type": "Feature",
  "properties": {
    "addr:full":"3 Hallys La  Cambridge Waikato",
    "addr:housenumber":"3",
    "addr:street":"Hallys La Cambridge",
    "iso:country":"NZ",
    "sg:address":"3 Hallys La ",
    "sg:city":"Cambridge",
    "sg:classifiers":[
        {
            "category":"Banks & Credit Unions",
            "subcategory":"Investment Brokerage",
            "type":"Services"
        }
    ],
    "sg:phone":"+64 7-827 6037",
    "sg:province":"Waikato",
    "sg:tags":[
        "director",
        "funeral",
        "arrangements"
    ],
    "wof:name":"Grinter Funeral Services Ltd",
    "wof:placetype":"venue"
},
  "geometry": {"coordinates":[-116.67604799999999,44.572186],"type":"Point"}
}