{
  "type": "Feature",
  "properties": {
    "iso:country":"NZ",
    "sg:address":"174 Bank St ",
    "sg:city":"Whangarei",
    "sg:classifiers":[
        {
            "category":"Social Services",
            "subcategory":"Retirement Home",
            "type":"Services"
        }
    ],
    "sg:phone":"+64 9-438 2668",
    "sg:province":"Northland",
    "sg:tags":[
        "personal",
        "services",
        "garden",
        "elderly",
        "care"
    ],
    "wof:name":"Potter Aged Care Center",
    "wof:placetype":"venue"
},
  "geometry": {"coordinates":[174.322113,-35.717865],"type":"Point"}
}