{
  "type": "Feature",
  "properties": {
    "iso:country":"NZ",
    "sg:address":"67 Malden St Palmerston ",
    "sg:city":"Palmerston North",
    "sg:classifiers":[
        {
            "category":"Manufacturing",
            "subcategory":"Rubber & Plastics",
            "type":"Manufacturing & Wholesale Goods"
        }
    ],
    "sg:phone":"+64 6-358 2004",
    "sg:province":"Manawatu-Wanganui",
    "sg:tags":[
        "industrial",
        "goods"
    ],
    "wof:name":"Iplex Pipelines NZ Ltd",
    "wof:placetype":"venue"
},
  "geometry": {"coordinates":[175.624313,-40.33078],"type":"Point"}
}