{
  "type": "Feature",
  "properties": {
    "addr:full":"16/318 Beach Haven Rd Beach Haven  Auckland Auckland",
    "addr:housenumber":"16 / 318",
    "addr:street":"Beach Haven Rd",
    "iso:country":"NZ",
    "sg:address":"16/318 Beach Haven Rd Beach Haven ",
    "sg:city":"Auckland",
    "sg:classifiers":[
        {
            "category":"Farming",
            "subcategory":"Fish & Marine Products",
            "type":"Manufacturing & Wholesale Goods"
        }
    ],
    "sg:phone":"+64 9-483 8400",
    "sg:province":"Auckland",
    "sg:tags":[
        "-",
        "boat",
        "transport"
    ],
    "wof:name":"Pinzon Marine Engineering Ltd",
    "wof:placetype":"venue"
},
  "geometry": {"coordinates":[174.69761700000001,-36.788528],"type":"Point"}
}