{
  "type": "Feature",
  "properties": {
    "iso:country":"NZ",
    "sg:address":"80 Carbine Rd Mt Wellington ",
    "sg:city":"Auckland",
    "sg:classifiers":[
        {
            "category":"Manufacturing",
            "subcategory":"Motor Vehicles & Parts",
            "type":"Manufacturing & Wholesale Goods"
        }
    ],
    "sg:phone":"+64 9-573 5720",
    "sg:province":"Auckland",
    "sg:tags":[
        "box",
        "industrial",
        "parts",
        "-",
        "gear"
    ],
    "sg:website":"http://www.machine.co.nz",
    "wof:name":"MacDonald Machinery Ltd",
    "wof:placetype":"venue"
},
  "geometry": {"coordinates":[174.847702,-36.919136],"type":"Point"}
}