{
  "type": "Feature",
  "properties": {
    "addr:full":"18 St Georges Rd Avondale  Auckland Auckland",
    "addr:housenumber":"18",
    "addr:street":"St Georges Rd",
    "iso:country":"NZ",
    "sg:address":"18 St Georges Rd Avondale ",
    "sg:city":"Auckland",
    "sg:classifiers":[
        {
            "category":"Arena",
            "subcategory":"Sports Club",
            "type":"Entertainment"
        }
    ],
    "sg:phone":"+64 9-828 2627",
    "sg:province":"Auckland",
    "sg:tags":[
        "martial art",
        "-",
        "leisure",
        "sports"
    ],
    "wof:name":"Strike Force Martial Arts & Fitness Academy",
    "wof:placetype":"venue"
},
  "geometry": {"coordinates":[174.69712799999999,-36.899334],"type":"Point"}
}