{
  "type": "Feature",
  "properties": {
    "addr:full":"Onekawa  Napier Hawke's Bay",
    "iso:country":"NZ",
    "sg:address":"Onekawa ",
    "sg:city":"Napier",
    "sg:classifiers":[
        {
            "category":"Autos & Motor Vehicles",
            "subcategory":"Motorcycle Sales",
            "type":"Retail Goods"
        }
    ],
    "sg:phone":"+64 6-843 1340",
    "sg:province":"Hawke's Bay",
    "sg:tags":[
        "automotive",
        "scooter",
        "leasing"
    ],
    "wof:name":"Torque Motorcycles",
    "wof:placetype":"venue"
},
  "geometry": {"coordinates":[176.89598100000001,-39.504456],"type":"Point"}
}