{
  "type": "Feature",
  "properties": {
    "addr:full":"Riccarton Mall SHOP 26 Riccarton Rd  Christchurch Canterbury",
    "addr:housenumber":"26",
    "addr:street":"Riccarton Rd",
    "iso:country":"NZ",
    "sg:address":"Riccarton Mall SHOP 26 Riccarton Rd ",
    "sg:city":"Christchurch",
    "sg:orig_category":"Shopping: Retail Stores: Cds, Cassettes And Records",
    "sg:phone":"+64 3-348 8414",
    "sg:province":"Canterbury",
    "wof:name":"Sounds",
    "wof:placetype":"venue"
},
  "geometry": {"coordinates":[172.637314,-43.531315],"type":"Point"}
}