{
  "type": "Feature",
  "properties": {
    "iso:country":"NZ",
    "sg:address":"212 Kitchener Rd Milford ",
    "sg:city":"Auckland",
    "sg:classifiers":[
        {
            "category":"Insurance",
            "subcategory":"Health Insurance",
            "type":"Services"
        }
    ],
    "sg:phone":"+64 9-486 3663",
    "sg:province":"Auckland",
    "sg:tags":[
        "beauty",
        "supply"
    ],
    "wof:name":"CiCi Nails & Beauty",
    "wof:placetype":"venue"
},
  "geometry": {"coordinates":[174.764343,-36.772499],"type":"Point"}
}