{
  "type": "Feature",
  "properties": {
    "addr:full":"Rosella Rd Opua  Paihia Northland",
    "addr:street":"Rosella Rd",
    "iso:country":"NZ",
    "sg:address":"Rosella Rd Opua ",
    "sg:city":"Paihia",
    "sg:classifiers":[
        {
            "category":"Shopping",
            "subcategory":"Pets & Pet Supplies",
            "type":"Retail Goods"
        }
    ],
    "sg:phone":"+64 9-402 8570",
    "sg:province":"Northland",
    "sg:tags":[
        "boarding",
        "garden",
        "pets",
        "catteries",
        "home",
        "kennel"
    ],
    "wof:name":"Bay Of Islands Boarding Cattery",
    "wof:placetype":"venue"
},
  "geometry": {"coordinates":[174.10630800000001,-35.311543],"type":"Point"}
}