{
  "type": "Feature",
  "properties": {
    "addr:full":"Mahara Pl  Waikanae",
    "addr:street":"Mahara Pl",
    "iso:country":"NZ",
    "sg:address":"Mahara Pl ",
    "sg:city":"Waikanae",
    "sg:orig_category":"Shopping: Retail Stores: Florists",
    "sg:phone":"+64 4-293 6629",
    "wof:name":"Kapiti Coast Florists",
    "wof:placetype":"venue"
},
  "geometry": {"coordinates":[175.064728,-40.877113],"type":"Point"}
}