{
  "type": "Feature",
  "properties": {
    "iso:country":"NZ",
    "sg:address":"31 Charlcott St Russley ",
    "sg:city":"Christchurch",
    "sg:classifiers":[
        {
            "category":"Arena",
            "subcategory":"Sports Club",
            "type":"Entertainment"
        }
    ],
    "sg:phone":"+64 3-359 5440",
    "sg:province":"Canterbury",
    "sg:tags":[
        "leisure"
    ],
    "sg:website":"http://www.yellowpages.co.nz/for/chappie/dp27243.html",
    "wof:name":"Chappie Chapman's Fly Fishing School",
    "wof:placetype":"venue"
},
  "geometry": {"coordinates":[172.54385400000001,-43.52],"type":"Point"}
}