{
  "type": "Feature",
  "properties": {
    "iso:country":"NZ",
    "sg:address":"17 Sherson St ",
    "sg:city":"Tauranga",
    "sg:classifiers":[
        {
            "category":"Manufacturing",
            "subcategory":"Motor Vehicles & Parts",
            "type":"Manufacturing & Wholesale Goods"
        }
    ],
    "sg:phone":"+64 7-571 0100",
    "sg:province":"Bay of Plenty",
    "sg:tags":[
        "body",
        "repair",
        "builder",
        "servicing",
        "automotive"
    ],
    "wof:name":"Kiwi Bus Builders Ltd",
    "wof:placetype":"venue"
},
  "geometry": {"coordinates":[176.12780799999999,-37.724911],"type":"Point"}
}