{
  "type": "Feature",
  "properties": {
    "iso:country":"NZ",
    "sg:address":"Roger Marshall Waipukurau ",
    "sg:city":"Waipukurau",
    "sg:orig_category":"Home And Garden: Gardening: Services: Lawnmowing Services",
    "sg:phone":"+64 6-858 7353",
    "wof:name":"Mr Mow - Central Hawkes Bay",
    "wof:placetype":"venue"
},
  "geometry": {"coordinates":[176.55128500000001,-39.994652],"type":"Point"}
}