{
  "type": "Feature",
  "properties": {
    "addr:full":"1/241 Moore St Howick  Auckland Auckland",
    "addr:housenumber":"1 / 241",
    "addr:street":"Moore St",
    "iso:country":"NZ",
    "sg:address":"1/241 Moore St Howick ",
    "sg:city":"Auckland",
    "sg:orig_category":"Transport: Boats And Marine: Products",
    "sg:phone":"+64 9-534 6947",
    "sg:province":"Auckland",
    "wof:name":"Howick Marine Motors & Accessories Ltd",
    "wof:placetype":"venue"
},
  "geometry": {"coordinates":[174.92600999999999,-36.904758],"type":"Point"}
}