{
  "type": "Feature",
  "properties": {
    "iso:country":"NZ",
    "sg:address":"80 Kaniere Rd ",
    "sg:city":"Hokitika",
    "sg:classifiers":[
        {
            "category":"Home & Garden",
            "subcategory":"Furniture",
            "type":"Retail Goods"
        }
    ],
    "sg:phone":"+64 3-755 8675",
    "sg:province":"West Coast",
    "sg:tags":[
        "furniture/furnishings",
        "furnishing"
    ],
    "wof:name":"Mitchell John Cabinetmaker",
    "wof:placetype":"venue"
},
  "geometry": {"coordinates":[170.986069,-42.725914],"type":"Point"}
}