{
  "type": "Feature",
  "properties": {
    "addr:full":"cnr Taylor Rd & State Highway 1 Springs Flat  Whangarei Northland",
    "addr:street":"Cnr Taylor Rd & State Highway 1 Springs Flat",
    "iso:country":"NZ",
    "sg:address":"cnr Taylor Rd & State Highway 1 Springs Flat ",
    "sg:city":"Whangarei",
    "sg:orig_category":"Farming: Services: Veterinarians",
    "sg:phone":"+64 9-435 1100",
    "sg:province":"Northland",
    "wof:name":"Kauri Veterinary Hospital",
    "wof:placetype":"venue"
},
  "geometry": {"coordinates":[174.29750100000001,-35.66713],"type":"Point"}
}