{
  "type": "Feature",
  "properties": {
    "addr:full":"67 a Brunner St  Bishopdale Canterbury",
    "addr:housenumber":"67",
    "addr:street":"A Brunner St Bishopdale",
    "iso:country":"NZ",
    "sg:address":"67 a Brunner St ",
    "sg:city":"Bishopdale",
    "sg:orig_category":"Home And Garden: Furniture/Furnishings: Curtains",
    "sg:phone":"+64 252205836",
    "sg:province":"Canterbury",
    "wof:name":"Gordon Mora",
    "wof:placetype":"venue"
},
  "geometry": {"coordinates":[172.58607499999999,-43.487144],"type":"Point"}
}