{
  "type": "Feature",
  "properties": {
    "addr:full":"739 Massey Rd Mangere  Auckland Auckland",
    "addr:housenumber":"739",
    "addr:street":"Massey Rd",
    "iso:country":"NZ",
    "sg:address":"739 Massey Rd Mangere ",
    "sg:city":"Auckland",
    "sg:classifiers":[
        {
            "category":"Autos & Motor Vehicles",
            "subcategory":"Automobile Sales",
            "type":"Retail Goods"
        }
    ],
    "sg:phone":"+64 9-256 0555",
    "sg:province":"Auckland",
    "sg:tags":[
        "automotive"
    ],
    "sg:website":"http://www.yellowpages.co.nz/for/aokrentalcars/dp40403.html",
    "wof:name":"AO'K Airport Discount Rentals Ltd",
    "wof:placetype":"venue"
},
  "geometry": {"coordinates":[174.81716900000001,-36.973118],"type":"Point"}
}