{
  "type": "Feature",
  "properties": {
    "iso:country":"NZ",
    "sg:address":"34 Wordsworth St Cambridge ",
    "sg:city":"Hamilton",
    "sg:classifiers":[
        {
            "category":"Sports & Exercise",
            "subcategory":"Swimming Pool",
            "type":"Entertainment"
        }
    ],
    "sg:phone":"+64 7-823 2977",
    "sg:province":"Waikato",
    "sg:tags":[
        "home",
        "outdoor",
        "garden",
        "spa"
    ],
    "wof:name":"Professional Pools Ltd",
    "wof:placetype":"venue"
},
  "geometry": {"coordinates":[175.47524999999999,-37.901901],"type":"Point"}
}