{
  "type": "Feature",
  "properties": {
    "addr:full":"834 Tremaine Ave Palmerston  Palmerston North Manawatu-Wanganui",
    "addr:housenumber":"834",
    "addr:street":"Tremaine Ave",
    "iso:country":"NZ",
    "sg:address":"834 Tremaine Ave Palmerston ",
    "sg:city":"Palmerston North",
    "sg:classifiers":[
        {
            "category":"Farming",
            "subcategory":"Fish & Marine Products",
            "type":"Manufacturing & Wholesale Goods"
        }
    ],
    "sg:phone":"+64 6-357 8039",
    "sg:province":"Manawatu-Wanganui",
    "sg:tags":[
        "boats",
        "yacht",
        "transport",
        "boat",
        "supply"
    ],
    "wof:name":"Gull Superior Oars & Paddles",
    "wof:placetype":"venue"
},
  "geometry": {"coordinates":[175.62167400000001,-40.334507],"type":"Point"}
}