{
  "type": "Feature",
  "properties": {
    "iso:country":"NZ",
    "sg:address":"Oxford St ",
    "sg:city":"Masterton",
    "sg:orig_category":"Health And Beauty: Medical: Hospitals",
    "sg:phone":"+64 6-377 3339",
    "sg:province":"Wellington",
    "wof:name":"Lansdowne Court Hospital Rest Home & Retirement Village",
    "wof:placetype":"venue"
},
  "geometry": {"coordinates":[175.66529800000001,-40.942036],"type":"Point"}
}