{
  "type": "Feature",
  "properties": {
    "addr:full":"Unit/9 Tait Pl Albany  Auckland Auckland",
    "addr:housenumber":"/ 9",
    "addr:street":"Tait Pl",
    "iso:country":"NZ",
    "sg:address":"Unit/9 Tait Pl Albany ",
    "sg:city":"Auckland",
    "sg:classifiers":[
        {
            "category":"Arena",
            "subcategory":"Sports Club",
            "type":"Entertainment"
        }
    ],
    "sg:phone":"+64 9-415 9460",
    "sg:province":"Auckland",
    "sg:tags":[
        "martial art",
        "-",
        "leisure",
        "sports"
    ],
    "wof:name":"Lee Gar Fitness Centre",
    "wof:placetype":"venue"
},
  "geometry": {"coordinates":[174.71762100000001,-36.742306],"type":"Point"}
}