{
  "type": "Feature",
  "properties": {
    "addr:full":"42 Hamilton St  Hokitika West Coast",
    "addr:housenumber":"42",
    "addr:street":"Hamilton St",
    "iso:country":"NZ",
    "sg:address":"42 Hamilton St ",
    "sg:city":"Hokitika",
    "sg:orig_category":"Sports And Leisure: General: Clubs",
    "sg:phone":"+64 3-755 8342",
    "sg:province":"West Coast",
    "wof:name":"Hokitika Chartered Club",
    "wof:placetype":"venue"
},
  "geometry": {"coordinates":[170.96220400000001,-42.718845],"type":"Point"}
}