{
  "type": "Feature",
  "properties": {
    "addr:full":"207 A Queen St  Richmond Nelson",
    "addr:housenumber":"207 a",
    "addr:street":"Queen St",
    "iso:country":"NZ",
    "sg:address":"207 A Queen St ",
    "sg:city":"Richmond",
    "sg:orig_category":"Farming: Forestry: Logging Services",
    "sg:phone":"+64 800 502 299",
    "sg:province":"Nelson",
    "wof:name":"Forestworks NZ Ltd",
    "wof:placetype":"venue"
},
  "geometry": {"coordinates":[-122.34271200000001,37.937809],"type":"Point"}
}