{
  "type": "Feature",
  "properties": {
    "addr:full":"Lvl 2 32 Lorne St Auckland Central  Auckland Auckland",
    "addr:housenumber":"lvl 2 32",
    "addr:street":"Lorne St",
    "iso:country":"NZ",
    "sg:address":"Lvl 2 32 Lorne St Auckland Central ",
    "sg:city":"Auckland",
    "sg:classifiers":[
        {
            "category":"Arts & Performance",
            "subcategory":"Art Gallery",
            "type":"Entertainment"
        }
    ],
    "sg:phone":"+64 9-379 4170",
    "sg:province":"Auckland",
    "sg:tags":[
        "arts",
        "sport",
        "leisure"
    ],
    "wof:name":"ASA Gallery",
    "wof:placetype":"venue"
},
  "geometry": {"coordinates":[174.765717,-36.850494],"type":"Point"}
}