{
  "type": "Feature",
  "properties": {
    "addr:full":"175 Great North Rd Ponsonby  Auckland Auckland",
    "addr:housenumber":"175",
    "addr:street":"Great North Rd",
    "iso:country":"NZ",
    "sg:address":"175 Great North Rd Ponsonby ",
    "sg:city":"Auckland",
    "sg:classifiers":[
        {
            "category":"Sports & Exercise",
            "subcategory":"Ski Resort",
            "type":"Entertainment"
        }
    ],
    "sg:phone":"+64 9-303 2148",
    "sg:province":"Auckland",
    "sg:tags":[
        "hobbies",
        "photographic",
        "leisure",
        "developing"
    ],
    "sg:website":"http://www.photowarehouse.co.nz",
    "wof:name":"Photo Warehouse",
    "wof:placetype":"venue"
},
  "geometry": {"coordinates":[174.74241599999999,-36.85326],"type":"Point"}
}