{
  "type": "Feature",
  "properties": {
    "iso:country":"NZ",
    "sg:address":"231-233 Great South Rd Drury ",
    "sg:city":"Auckland",
    "sg:classifiers":[
        {
            "category":"Food & Beverages",
            "subcategory":"Bakery",
            "type":"Retail Goods"
        }
    ],
    "sg:phone":"+64 9-294 6432",
    "sg:province":"Auckland",
    "sg:tags":[
        "shop",
        "cake",
        "drink",
        "-"
    ],
    "wof:name":"Tran Bakery",
    "wof:placetype":"venue"
},
  "geometry": {"coordinates":[174.95159899999999,-37.102818],"type":"Point"}
}