{
  "type": "Feature",
  "properties": {
    "iso:country":"NZ",
    "sg:address":"3-5 Auburn St Takapuna ",
    "sg:city":"Auckland",
    "sg:classifiers":[
        {
            "category":"Health Services",
            "subcategory":"Doctor",
            "type":"Services"
        }
    ],
    "sg:phone":"+64 9-489 1053",
    "sg:province":"Auckland",
    "sg:tags":[
        "beauty"
    ],
    "wof:name":"A.C.E Massage",
    "wof:placetype":"venue"
},
  "geometry": {"coordinates":[174.76924099999999,-36.789211],"type":"Point"}
}