{
  "type": "Feature",
  "properties": {
    "addr:full":"2 High St  Greymouth West Coast",
    "addr:housenumber":"2",
    "addr:street":"High St",
    "iso:country":"NZ",
    "sg:address":"2 High St ",
    "sg:city":"Greymouth",
    "sg:orig_category":"Farming: Supplies: Veterinary Supplies",
    "sg:phone":"+64 3-768 0370",
    "sg:province":"West Coast",
    "wof:name":"Grey Vet Centre",
    "wof:placetype":"venue"
},
  "geometry": {"coordinates":[171.20574999999999,-42.457539],"type":"Point"}
}