{
  "type": "Feature",
  "properties": {
    "addr:full":"30 Sunset Rd  Rotorua Bay of Plenty",
    "addr:housenumber":"30",
    "addr:street":"Sunset Rd",
    "iso:country":"NZ",
    "sg:address":"30 Sunset Rd ",
    "sg:city":"Rotorua",
    "sg:orig_category":"Sports And Leisure: Sports: Skiing",
    "sg:phone":"+64 7-343 6661",
    "sg:province":"Bay of Plenty",
    "wof:name":"Ski Time",
    "wof:placetype":"venue"
},
  "geometry": {"coordinates":[176.23202499999999,-38.134529],"type":"Point"}
}