{
  "type": "Feature",
  "properties": {
    "iso:country":"NZ",
    "sg:address":"PO Box 154 ",
    "sg:city":"Omarama",
    "sg:orig_category":"Farming: Agriculture: Agricultural Contractors",
    "sg:phone":"+64 25335523",
    "wof:name":"David O'Neill Contracting Ltd",
    "wof:placetype":"venue"
},
  "geometry": {"coordinates":[169.968933,-44.491158],"type":"Point"}
}