{
  "type": "Feature",
  "properties": {
    "iso:country":"NZ",
    "sg:address":"189-191 Marua Rd Ellerslie ",
    "sg:city":"Auckland",
    "sg:orig_category":"Home And Garden: Outdoor: Stonemasons",
    "sg:phone":"+64 9-526 4580",
    "sg:province":"Auckland",
    "wof:name":"SCE Stone & Design",
    "wof:placetype":"venue"
},
  "geometry": {"coordinates":[174.825424,-36.892048],"type":"Point"}
}