{
  "type": "Feature",
  "properties": {
    "iso:country":"NZ",
    "sg:address":"PO Box 7490 Sydenham ",
    "sg:city":"Christchurch",
    "sg:classifiers":[
        {
            "category":"Home & Garden",
            "subcategory":"Building Materials",
            "type":"Retail Goods"
        }
    ],
    "sg:phone":"+64 3-365 5900",
    "sg:province":"Canterbury",
    "sg:tags":[
        "door",
        "fitting",
        "fittings"
    ],
    "wof:name":"DoorTech",
    "wof:placetype":"venue"
},
  "geometry": {"coordinates":[172.63748200000001,-43.547424],"type":"Point"}
}