{
  "type": "Feature",
  "properties": {
    "iso:country":"NZ",
    "sg:address":"47 b Kildare St ",
    "sg:city":"Belfast",
    "sg:classifiers":[
        {
            "category":"Manufacturing",
            "subcategory":"Textiles",
            "type":"Manufacturing & Wholesale Goods"
        }
    ],
    "sg:phone":"+64 3-323 8282",
    "sg:province":"Canterbury",
    "sg:tags":[
        "clothing",
        "fabric",
        "manufacturer"
    ],
    "wof:name":"Advert Apparel Ltd",
    "wof:placetype":"venue"
},
  "geometry": {"coordinates":[-69.007973,44.425869],"type":"Point"}
}