{
  "type": "Feature",
  "properties": {
    "addr:full":"41 Buchanans Rd Sockburn  Christchurch Canterbury",
    "addr:housenumber":"41",
    "addr:street":"Buchanans Rd",
    "iso:country":"NZ",
    "sg:address":"41 Buchanans Rd Sockburn ",
    "sg:city":"Christchurch",
    "sg:classifiers":[
        {
            "category":"Sports & Exercise",
            "subcategory":"Tennis Court",
            "type":"Entertainment"
        }
    ],
    "sg:phone":"+64 3-342 8822",
    "sg:province":"Canterbury",
    "sg:tags":[
        "-",
        "leisure",
        "sports"
    ],
    "wof:name":"The Pot Hole People Ltd",
    "wof:placetype":"venue"
},
  "geometry": {"coordinates":[172.541031,-43.534218],"type":"Point"}
}