{
  "type": "Feature",
  "properties": {
    "addr:full":"Gorge Rd Ballance  Pahiatua",
    "addr:street":"Gorge Rd",
    "iso:country":"NZ",
    "sg:address":"Gorge Rd Ballance ",
    "sg:city":"Pahiatua",
    "sg:classifiers":[
        {
            "category":"Bars & Pubs",
            "subcategory":"Wine Bar",
            "type":"Food & Drink"
        }
    ],
    "sg:phone":"+64 6-376 8004",
    "sg:tags":[
        "wining",
        "dining",
        "cafe"
    ],
    "wof:name":"Beyond The Bridge Cafe",
    "wof:placetype":"venue"
},
  "geometry": {"coordinates":[175.816925,-40.343952],"type":"Point"}
}