{
  "type": "Feature",
  "properties": {
    "addr:full":"24 Koromiko St  Tauranga Bay of Plenty",
    "addr:housenumber":"24",
    "addr:street":"Koromiko St",
    "iso:country":"NZ",
    "sg:address":"24 Koromiko St ",
    "sg:city":"Tauranga",
    "sg:classifiers":[
        {
            "category":"Manufacturing",
            "subcategory":"Motor Vehicles & Parts",
            "type":"Manufacturing & Wholesale Goods"
        }
    ],
    "sg:phone":"+64 7-578 5626",
    "sg:province":"Bay of Plenty",
    "sg:tags":[
        "air conditioning",
        "automotive",
        "supplies"
    ],
    "wof:name":"Smac Electrical & Auto Air",
    "wof:placetype":"venue"
},
  "geometry": {"coordinates":[176.15141299999999,-37.699413],"type":"Point"}
}