{
  "type": "Feature",
  "properties": {
    "iso:country":"NZ",
    "sg:address":"PO Box 33198 Petone Lower ",
    "sg:city":"Hutt",
    "sg:orig_category":"Industrial: Packaging: Paper Products",
    "sg:phone":"+64 4-586 3737",
    "sg:province":"Wellington",
    "wof:name":"Wipertec",
    "wof:placetype":"venue"
},
  "geometry": {"coordinates":[174.87507600000001,-41.221291],"type":"Point"}
}