{
  "type": "Feature",
  "properties": {
    "addr:full":"cnr The Esplanade & Sydney St Petone Lower  Hutt Auckland",
    "addr:street":"Cnr The;Sydney St",
    "iso:country":"NZ",
    "sg:address":"cnr The Esplanade & Sydney St Petone Lower ",
    "sg:city":"Hutt",
    "sg:orig_category":"Shopping: Accessories: Embroidery And Monograms",
    "sg:phone":"+64 4-568 4869",
    "sg:province":"Auckland",
    "wof:name":"Muzzy Shirts",
    "wof:placetype":"venue"
},
  "geometry": {"coordinates":[174.87507600000001,-41.221291],"type":"Point"}
}