{
  "type": "Feature",
  "properties": {
    "addr:full":"129 Main Highway Ellerslie  Auckland Auckland",
    "addr:housenumber":"129",
    "addr:street":"Main Highway",
    "iso:country":"NZ",
    "sg:address":"129 Main Highway Ellerslie ",
    "sg:city":"Auckland",
    "sg:classifiers":[
        {
            "category":"Shopping",
            "subcategory":"Stationery & Office Supplies",
            "type":"Retail Goods"
        }
    ],
    "sg:phone":"+64 9-526 1984",
    "sg:province":"Auckland",
    "sg:tags":[
        "supplies",
        "educational",
        "material",
        "education",
        "training"
    ],
    "wof:name":"Stemax Ltd",
    "wof:placetype":"venue"
},
  "geometry": {"coordinates":[174.81028699999999,-36.898376],"type":"Point"}
}