{
  "type": "Feature",
  "properties": {
    "addr:full":"Shop 4, Maddison Apartments Building Cnr Queen &, Rangitikei Sts Palmerston  Palmerston North Manawatu-Wanganui",
    "addr:housenumber":"shop 4",
    "addr:street":"Cnr Queen & Rangitikei Sts",
    "iso:country":"NZ",
    "sg:address":"Shop 4, Maddison Apartments Building Cnr Queen &, Rangitikei Sts Palmerston ",
    "sg:city":"Palmerston North",
    "sg:orig_category":"Shopping: Gifts: Gift Baskets",
    "sg:phone":"+64 6-355 5532",
    "sg:province":"Manawatu-Wanganui",
    "sg:website":"http://www.gkoccasions.co.nz",
    "wof:name":"GK Occasions Ltd",
    "wof:placetype":"venue"
},
  "geometry": {"coordinates":[175.611481,-40.357422],"type":"Point"}
}