{
  "type": "Feature",
  "properties": {
    "iso:country":"NZ",
    "sg:address":"1190 Cameron Rd Gate Pa ",
    "sg:city":"Tauranga",
    "sg:classifiers":[
        {
            "category":"Retail",
            "subcategory":"Auto Repair",
            "type":"Services"
        }
    ],
    "sg:phone":"+64 7-578 8105",
    "sg:province":"Bay of Plenty",
    "sg:tags":[
        "automotive",
        "panel",
        "servicing",
        "beater"
    ],
    "wof:name":"Smith & Boyle Ltd",
    "wof:placetype":"venue"
},
  "geometry": {"coordinates":[176.136765,-37.720139],"type":"Point"}
}