{
  "type": "Feature",
  "properties": {
    "iso:country":"NZ",
    "sg:address":"31 Newtown St Bromley ",
    "sg:city":"Christchurch",
    "sg:orig_category":"Storage: Storage",
    "sg:phone":"+64 3-384 2820",
    "sg:province":"Canterbury",
    "wof:name":"Graeme Welsh Storage",
    "wof:placetype":"venue"
},
  "geometry": {"coordinates":[172.69821200000001,-43.540184],"type":"Point"}
}