{
  "type": "Feature",
  "properties": {
    "addr:full":"24 Bennett Gro Newlands  Wellington Wellington",
    "addr:housenumber":"24",
    "addr:street":"Bennett Gro Newlands",
    "iso:country":"NZ",
    "sg:address":"24 Bennett Gro Newlands ",
    "sg:city":"Wellington",
    "sg:orig_category":"Industrial: Parts: Pipes, Tubes And Cabling: Cables",
    "sg:phone":"+64 4-478 6121",
    "sg:province":"Wellington",
    "wof:name":"Home.Com Ltd",
    "wof:placetype":"venue"
},
  "geometry": {"coordinates":[174.83592200000001,-41.228142],"type":"Point"}
}