{
  "type": "Feature",
  "properties": {
    "iso:country":"NZ",
    "sg:address":"42 Woodlands ",
    "sg:city":"Pl",
    "sg:classifiers":[
        {
            "category":"Retail",
            "subcategory":"Laundry & Dry Cleaning",
            "type":"Services"
        }
    ],
    "sg:phone":"+64 3-366 9962",
    "sg:tags":[
        "repair",
        "clothing",
        "fabric",
        "cleaner"
    ],
    "wof:name":"Murray Hartland Drycleaning Agent",
    "wof:placetype":"venue"
},
  "geometry": {"coordinates":[-84.384666,39.267826],"type":"Point"}
}