{
  "type": "Feature",
  "properties": {
    "iso:country":"NZ",
    "sg:address":"R D 2 ",
    "sg:city":"Wyndham",
    "sg:orig_category":"Farming: Agriculture: Agricultural Contractors",
    "sg:phone":"+64 3-206 4124",
    "wof:name":"Johnston Silage",
    "wof:placetype":"venue"
},
  "geometry": {"coordinates":[-77.613281,37.698261],"type":"Point"}
}