{
  "type": "Feature",
  "properties": {
    "iso:country":"NZ",
    "sg:address":"Main Rd Havelock R D ",
    "sg:city":"7154",
    "sg:orig_category":"Education And Training: General: Schools",
    "sg:phone":"+64 3-574 2106",
    "wof:name":"Havelock School",
    "wof:placetype":"venue"
},
  "geometry": {"coordinates":[173.766586,-41.27599],"type":"Point"}
}