{
  "type": "Feature",
  "properties": {
    "iso:country":"NZ",
    "sg:address":"O'Connor Rd Appleby ",
    "sg:city":"Richmond",
    "sg:classifiers":[
        {
            "category":"Home & Garden",
            "subcategory":"Building Materials",
            "type":"Retail Goods"
        }
    ],
    "sg:phone":"+64 3-544 2443",
    "sg:province":"Nelson",
    "sg:tags":[
        "builder",
        "related"
    ],
    "wof:name":"Perriam Neil R",
    "wof:placetype":"venue"
},
  "geometry": {"coordinates":[173.13368199999999,-41.32053],"type":"Point"}
}