{
  "type": "Feature",
  "properties": {
    "iso:country":"NZ",
    "sg:address":"202 A Commerce St Frankton ",
    "sg:city":"Hamilton",
    "sg:orig_category":"Shopping: Retail Stores: Books: Books - Secondhand",
    "sg:phone":"+64 7-847 5628",
    "sg:province":"Waikato",
    "wof:name":"Bullocks Book Exchange",
    "wof:placetype":"venue"
},
  "geometry": {"coordinates":[175.264191,-37.788342],"type":"Point"}
}