{
  "type": "Feature",
  "properties": {
    "addr:full":"50 College Hill Ponsonby  Auckland Auckland",
    "addr:housenumber":"50",
    "addr:street":"College Hill",
    "iso:country":"NZ",
    "sg:address":"50 College Hill Ponsonby ",
    "sg:city":"Auckland",
    "sg:classifiers":[
        {
            "category":"Retail",
            "subcategory":"Repair Shop",
            "type":"Services"
        }
    ],
    "sg:phone":"+64 9-360 8119",
    "sg:province":"Auckland",
    "sg:tags":[
        "clothing",
        "fabric",
        "cleaning"
    ],
    "wof:name":"Quick Stitch Clothing Alteration",
    "wof:placetype":"venue"
},
  "geometry": {"coordinates":[174.74241599999999,-36.85326],"type":"Point"}
}