{
  "type": "Feature",
  "properties": {
    "addr:full":"Lambton Sq 180 Lambton Quay  Wellington Wellington",
    "addr:housenumber":"180",
    "addr:street":"Lambton Sq",
    "iso:country":"NZ",
    "sg:address":"Lambton Sq 180 Lambton Quay ",
    "sg:city":"Wellington",
    "sg:classifiers":[
        {
            "category":"Shopping",
            "subcategory":"Photographic Equipment",
            "type":"Retail Goods"
        }
    ],
    "sg:phone":"+64 4-473 0167",
    "sg:province":"Wellington",
    "sg:tags":[
        "sport",
        "leisure",
        "hobbies"
    ],
    "wof:name":"Colin Kirk Photographics",
    "wof:placetype":"venue"
},
  "geometry": {"coordinates":[174.76715100000001,-41.28054],"type":"Point"}
}