{
  "type": "Feature",
  "properties": {
    "addr:full":"22 Whittaker Rd  Warkworth Auckland",
    "addr:housenumber":"22",
    "addr:street":"Whittaker Rd",
    "iso:country":"NZ",
    "sg:address":"22 Whittaker Rd ",
    "sg:city":"Warkworth",
    "sg:orig_category":"Automotive: Accessories",
    "sg:phone":"+64 9-425 9101",
    "sg:province":"Auckland",
    "wof:name":"AutoShop Rodney",
    "wof:placetype":"venue"
},
  "geometry": {"coordinates":[174.662262,-36.401024],"type":"Point"}
}