{
  "type": "Feature",
  "properties": {
    "addr:full":"Awahuri Rd  Feilding Manawatu-Wanganui",
    "addr:street":"Awahuri Rd",
    "iso:country":"NZ",
    "sg:address":"Awahuri Rd ",
    "sg:city":"Feilding",
    "sg:orig_category":"Home And Garden: Gardening: Products: Hydroponics Supplies",
    "sg:phone":"+64 6-323 9423",
    "sg:province":"Manawatu-Wanganui",
    "wof:name":"Manawatu Hydroponics",
    "wof:placetype":"venue"
},
  "geometry": {"coordinates":[175.55169699999999,-40.235958],"type":"Point"}
}