{
  "type": "Feature",
  "properties": {
    "iso:country":"NZ",
    "sg:address":"PO Box 24164 Royal ",
    "sg:city":"Oak",
    "sg:orig_category":"Automotive: Parts And Supplies: Taximeters",
    "sg:phone":"+64 9-636 5443",
    "wof:name":"Taximeter Services Ltd",
    "wof:placetype":"venue"
},
  "geometry": {"coordinates":[-76.187569,38.719971],"type":"Point"}
}