{
  "type": "Feature",
  "properties": {
    "addr:full":"8 Railway Rd  Rotorua Bay of Plenty",
    "addr:housenumber":"8",
    "addr:street":"Railway Rd",
    "iso:country":"NZ",
    "sg:address":"8 Railway Rd ",
    "sg:city":"Rotorua",
    "sg:orig_category":"Storage: Storage",
    "sg:phone":"+64 7-349 6500",
    "sg:province":"Bay of Plenty",
    "wof:name":"Lake Storage",
    "wof:placetype":"venue"
},
  "geometry": {"coordinates":[176.235229,-38.125523],"type":"Point"}
}