{
  "type": "Feature",
  "properties": {
    "iso:country":"NZ",
    "sg:address":"PO Box 33202 Petone Lower ",
    "sg:city":"Hutt",
    "sg:classifiers":[
        {
            "category":"Manufacturing",
            "subcategory":"Glass & Minerals",
            "type":"Manufacturing & Wholesale Goods"
        }
    ],
    "sg:phone":"+64 4-565 3102",
    "sg:province":"Wellington",
    "sg:tags":[
        "asbestos",
        "raw",
        "industrial",
        "materials"
    ],
    "wof:name":"Bricon Asbestos Removal",
    "wof:placetype":"venue"
},
  "geometry": {"coordinates":[174.875076,-41.221291],"type":"Point"}
}