{
  "type": "Feature",
  "properties": {
    "addr:full":"15 Morley Rd Tomoana  Hastings Hawke's Bay",
    "addr:housenumber":"15",
    "addr:street":"Morley Rd",
    "iso:country":"NZ",
    "sg:address":"15 Morley Rd Tomoana ",
    "sg:city":"Hastings",
    "sg:classifiers":[
        {
            "category":"Shopping",
            "subcategory":"Crafts & Fabrics",
            "type":"Retail Goods"
        }
    ],
    "sg:phone":"+64 6-870 6000",
    "sg:province":"Hawke's Bay",
    "sg:tags":[
        "pottery",
        "home",
        "accessories",
        "garden",
        "supply"
    ],
    "wof:name":"Bay Potters Supplies",
    "wof:placetype":"venue"
},
  "geometry": {"coordinates":[176.85401899999999,-39.612751],"type":"Point"}
}