{
  "type": "Feature",
  "properties": {
    "iso:country":"NZ",
    "sg:address":"57 Parkside Rd Gracefield Lower ",
    "sg:city":"Hutt",
    "sg:classifiers":[
        {
            "category":"Home & Garden",
            "subcategory":"Home Furnishings",
            "type":"Retail Goods"
        }
    ],
    "sg:phone":"+64 4-586 4178",
    "sg:province":"Wellington",
    "sg:tags":[
        "furniture/furnishings",
        "-",
        "secondhand",
        "furniture"
    ],
    "sg:website":"http://www.yellowpages.co.nz/for/petonefurnituretraders/dp44023.html",
    "wof:name":"PFT Office Furniture",
    "wof:placetype":"venue"
},
  "geometry": {"coordinates":[174.912811,-41.235054],"type":"Point"}
}