{
  "type": "Feature",
  "properties": {
    "addr:full":"Unit 7 A/43A Linwood Ave Mt Albert  Auckland Canterbury",
    "addr:housenumber":"unit 7 a / 43a",
    "addr:street":"Linwood Ave",
    "iso:country":"NZ",
    "sg:address":"Unit 7 A/43A Linwood Ave Mt Albert ",
    "sg:city":"Auckland",
    "sg:classifiers":[
        {
            "category":"Coffee & Tea",
            "type":"Food & Drink"
        }
    ],
    "sg:phone":"+64 9-849 8080",
    "sg:province":"Canterbury",
    "sg:tags":[
        "vegetable",
        "fruit",
        "veges"
    ],
    "wof:name":"Lettuce Deliver",
    "wof:placetype":"venue"
},
  "geometry": {"coordinates":[174.714798,-36.88784],"type":"Point"}
}