{
  "type": "Feature",
  "properties": {
    "addr:full":"Taonui St Palmerston  Palmerston North Manawatu-Wanganui",
    "addr:street":"St Palmerston",
    "iso:country":"NZ",
    "sg:address":"Taonui St Palmerston ",
    "sg:city":"Palmerston North",
    "sg:classifiers":[
        {
            "category":"Professional",
            "subcategory":"Detective & Security Services",
            "type":"Services"
        }
    ],
    "sg:phone":"+64 6-952 4353",
    "sg:province":"Manawatu-Wanganui",
    "sg:tags":[
        "services",
        "automotive",
        "warrant",
        "fitness"
    ],
    "wof:name":"Central City WOF Testing Station",
    "wof:placetype":"venue"
},
  "geometry": {"coordinates":[175.60635400000001,-40.352898],"type":"Point"}
}