{
  "type": "Feature",
  "properties": {
    "iso:country":"NZ",
    "sg:address":"315 Brighton Rd Waldronville ",
    "sg:city":"Dunedin",
    "sg:classifiers":[
        {
            "category":"Building & Trades",
            "subcategory":"Construction",
            "type":"Services"
        }
    ],
    "sg:phone":"+64 3-488 2428",
    "sg:province":"Otago",
    "sg:tags":[
        "home",
        "garden",
        "related",
        "plasterer"
    ],
    "wof:name":"Plastering Solid",
    "wof:placetype":"venue"
},
  "geometry": {"coordinates":[170.406021,-45.921776],"type":"Point"}
}