{
  "type": "Feature",
  "properties": {
    "addr:full":"488 Tuam St Linwood  Christchurch Canterbury",
    "addr:housenumber":"488",
    "addr:street":"Tuam St",
    "iso:country":"NZ",
    "sg:address":"488 Tuam St Linwood ",
    "sg:city":"Christchurch",
    "sg:orig_category":"Industrial: Services: Gear Cutters",
    "sg:phone":"+64 3-389 5681",
    "sg:province":"Canterbury",
    "wof:name":"Mike Jones Gears",
    "wof:placetype":"venue"
},
  "geometry": {"coordinates":[172.66213999999999,-43.53146],"type":"Point"}
}