{
  "type": "Feature",
  "properties": {
    "iso:country":"NZ",
    "sg:address":"Leith Pl ",
    "sg:city":"Tokoroa",
    "sg:orig_category":"Clothing And Fabric: Clothing: Menswear",
    "sg:phone":"+64 7-886 8488",
    "wof:name":"Tokoroa Mens & Boys Wear",
    "wof:placetype":"venue"
},
  "geometry": {"coordinates":[175.87291,-38.218281],"type":"Point"}
}