{
  "type": "Feature",
  "properties": {
    "iso:country":"NZ",
    "sg:address":"Jelliepark Aqualand 295 Ilam Rd Ilam ",
    "sg:city":"Christchurch",
    "sg:classifiers":[
        {
            "category":"Personal",
            "subcategory":"Tanning Parlor",
            "type":"Services"
        }
    ],
    "sg:phone":"+64 3-351 8774",
    "sg:province":"Canterbury",
    "sg:tags":[
        "sun",
        "health",
        "beauty"
    ],
    "wof:name":"Tantastic Sunbeds",
    "wof:placetype":"venue"
},
  "geometry": {"coordinates":[172.575638,-43.519951],"type":"Point"}
}