{
  "type": "Feature",
  "properties": {
    "iso:country":"NZ",
    "sg:address":"43 Caledonia St ",
    "sg:city":"Hawera",
    "sg:orig_category":"Sports And Leisure: General: Clubs",
    "sg:phone":"+64 6-278 4015",
    "sg:province":"Taranaki",
    "wof:name":"South Taranaki Club",
    "wof:placetype":"venue"
},
  "geometry": {"coordinates":[174.28566,-39.590576],"type":"Point"}
}