{
  "type": "Feature",
  "properties": {
    "addr:full":"Karamea Rd  Mangonui",
    "addr:street":"Karamea Rd",
    "iso:country":"NZ",
    "sg:address":"Karamea Rd ",
    "sg:city":"Mangonui",
    "sg:orig_category":"Storage: Storage",
    "sg:phone":"+64 800 468 000",
    "wof:name":"Doubtless Bay Mini Storage",
    "wof:placetype":"venue"
},
  "geometry": {"coordinates":[173.53259299999999,-34.995663],"type":"Point"}
}