{
  "type": "Feature",
  "properties": {
    "addr:full":"173 Tainui St  Greymouth West Coast",
    "addr:housenumber":"173",
    "addr:street":"Tainui St",
    "iso:country":"NZ",
    "sg:address":"173 Tainui St ",
    "sg:city":"Greymouth",
    "sg:classifiers":[
        {
            "category":"Bars & Pubs",
            "subcategory":"Lounge",
            "type":"Food & Drink"
        }
    ],
    "sg:phone":"+64 3-768 9165",
    "sg:province":"West Coast",
    "sg:tags":[
        "baker",
        "-"
    ],
    "wof:name":"Phil's Bakery",
    "wof:placetype":"venue"
},
  "geometry": {"coordinates":[171.207382,-42.455738],"type":"Point"}
}