{
  "type": "Feature",
  "properties": {
    "iso:country":"NZ",
    "sg:address":"208 Tremaine Ave Palmerston ",
    "sg:city":"Palmerston North",
    "sg:classifiers":[
        {
            "category":"Home & Garden",
            "subcategory":"Furniture",
            "type":"Retail Goods"
        }
    ],
    "sg:phone":"+64 6-357 5684",
    "sg:province":"Manawatu-Wanganui",
    "sg:tags":[
        "furniture/furnishings",
        "repair",
        "finishing"
    ],
    "wof:name":"John Jacques & Co Ltd",
    "wof:placetype":"venue"
},
  "geometry": {"coordinates":[175.579926,-40.353191],"type":"Point"}
}