{
  "type": "Feature",
  "properties": {
    "iso:country":"NZ",
    "sg:address":"40 Heu Heu St ",
    "sg:city":"Taupo",
    "sg:classifiers":[
        {
            "category":"Travel",
            "subcategory":"Travel Agent",
            "type":"Entertainment"
        }
    ],
    "sg:phone":"+64 7-378 9709",
    "sg:province":"Waikato",
    "sg:tags":[
        "tourism",
        "broker"
    ],
    "wof:name":"United Travel Taupo",
    "wof:placetype":"venue"
},
  "geometry": {"coordinates":[176.07144199999999,-38.687958],"type":"Point"}
}