{
  "type": "Feature",
  "properties": {
    "iso:country":"NZ",
    "sg:address":"Golf Links Rd ",
    "sg:city":"Whakatane",
    "sg:orig_category":"Sports And Leisure: Sports: Golf",
    "sg:phone":"+64 7-308 8117",
    "sg:province":"Bay of Plenty",
    "wof:name":"Whakatane Golf Club",
    "wof:placetype":"venue"
},
  "geometry": {"coordinates":[176.942307,-37.923798],"type":"Point"}
}