{
  "type": "Feature",
  "properties": {
    "iso:country":"NZ",
    "sg:address":"3B/300 Queen St Auckland Central ",
    "sg:city":"Auckland",
    "sg:classifiers":[
        {
            "category":"Landmark",
            "subcategory":"Tourist Information",
            "type":"Public Place"
        }
    ],
    "sg:phone":"+64 9-309 4320",
    "sg:province":"Auckland",
    "sg:tags":[
        "services",
        "travel",
        "tourism"
    ],
    "wof:name":"Kochoo Tours Ltd",
    "wof:placetype":"venue"
},
  "geometry": {"coordinates":[174.76452599999999,-36.851219],"type":"Point"}
}