{
  "type": "Feature",
  "properties": {
    "addr:full":"44 Huanui St  Porirua Wellington",
    "addr:housenumber":"44",
    "addr:street":"Huanui St",
    "iso:country":"NZ",
    "sg:address":"44 Huanui St ",
    "sg:city":"Porirua",
    "sg:classifiers":[
        {
            "category":"Arena",
            "subcategory":"Sports Club",
            "type":"Entertainment"
        }
    ],
    "sg:phone":"+64 4-237 5254",
    "sg:province":"Wellington",
    "sg:tags":[
        "martial art",
        "-",
        "leisure",
        "sports"
    ],
    "wof:name":"Shaolin Kempo",
    "wof:placetype":"venue"
},
  "geometry": {"coordinates":[174.85223400000001,-41.138294],"type":"Point"}
}