{
  "type": "Feature",
  "properties": {
    "iso:country":"NZ",
    "sg:address":"102 Old Taupo Rd ",
    "sg:city":"Rotorua",
    "sg:classifiers":[
        {
            "category":"Communications",
            "subcategory":"Film & Video Production",
            "type":"Services"
        }
    ],
    "sg:phone":"+64 7-349 2777",
    "sg:province":"Bay of Plenty",
    "sg:tags":[
        "sport",
        "leisure",
        "library",
        "entertainment"
    ],
    "wof:name":"Video Ezy",
    "wof:placetype":"venue"
},
  "geometry": {"coordinates":[176.238663,-38.147594],"type":"Point"}
}