{
  "type": "Feature",
  "properties": {
    "addr:full":"Ruataniwha St  Waipukurau",
    "addr:street":"Ruataniwha St",
    "iso:country":"NZ",
    "sg:address":"Ruataniwha St ",
    "sg:city":"Waipukurau",
    "sg:orig_category":"Health And Beauty: Beauty: Hairdressers",
    "sg:phone":"+64 6-858 7044",
    "wof:name":"The Barber Shop",
    "wof:placetype":"venue"
},
  "geometry": {"coordinates":[176.55548099999999,-39.995388],"type":"Point"}
}