{
  "type": "Feature",
  "properties": {
    "iso:country":"NZ",
    "sg:address":"99 Victoria Ave ",
    "sg:city":"Wanganui",
    "sg:orig_category":"Shopping: Accessories: Jewellers And Watchmakers",
    "sg:phone":"+64 6-348 8451",
    "sg:province":"Manawatu-Wanganui",
    "wof:name":"Michael Hill Jeweller",
    "wof:placetype":"venue"
},
  "geometry": {"coordinates":[175.051941,-39.933014],"type":"Point"}
}