{
  "type": "Feature",
  "properties": {
    "iso:country":"NZ",
    "sg:address":"Sheraton Mall Cnr Karangahape Rd & Symonds St Auckland, City ",
    "sg:city":"Auckland",
    "sg:classifiers":[
        {
            "category":"Shopping",
            "subcategory":"Bridal",
            "type":"Retail Goods"
        }
    ],
    "sg:phone":"+64 9-379 8819",
    "sg:province":"Auckland",
    "sg:tags":[
        "arrangements",
        "wear",
        "wedding"
    ],
    "wof:name":"La-vie Bridal",
    "wof:placetype":"venue"
},
  "geometry": {"coordinates":[-119.104584,36.59774],"type":"Point"}
}