{
  "type": "Feature",
  "properties": {
    "iso:country":"NZ",
    "sg:address":"57 Carr Rd Mt Roskill ",
    "sg:city":"Auckland",
    "sg:orig_category":"Industrial: Electrical/Electronic: Electric Elements",
    "sg:phone":"+64 9-625 4292",
    "sg:province":"Auckland",
    "wof:name":"Hislop & Barley Electrical Ltd",
    "wof:placetype":"venue"
},
  "geometry": {"coordinates":[174.742767,-36.905895],"type":"Point"}
}