{
  "type": "Feature",
  "properties": {
    "iso:country":"NZ",
    "sg:address":"157 Oxford St ",
    "sg:city":"Levin",
    "sg:orig_category":"Health And Beauty: Products: Home Healthcare Equipment",
    "sg:phone":"+64 6-367 8272",
    "sg:province":"Manawatu-Wanganui",
    "wof:name":"Trikes & Homecare",
    "wof:placetype":"venue"
},
  "geometry": {"coordinates":[-89.084503,37.193748],"type":"Point"}
}