{
  "type": "Feature",
  "properties": {
    "addr:full":"366 Church St Palmerston  Palmerston North Manawatu-Wanganui",
    "addr:housenumber":"366",
    "addr:street":"Church St",
    "iso:country":"NZ",
    "sg:address":"366 Church St Palmerston ",
    "sg:city":"Palmerston North",
    "sg:orig_category":"Shopping: Gifts: Gift Baskets",
    "sg:phone":"+64 6-354 8071",
    "sg:province":"Manawatu-Wanganui",
    "wof:name":"Streets Ahead (P.N) Ltd",
    "wof:placetype":"venue"
},
  "geometry": {"coordinates":[175.614182,-40.356441],"type":"Point"}
}