{
  "type": "Feature",
  "properties": {
    "addr:full":"154 Fitzherbert Ave Palmerston  Palmerston North Manawatu-Wanganui",
    "addr:housenumber":"154",
    "addr:street":"Fitzherbert Ave",
    "iso:country":"NZ",
    "sg:address":"154 Fitzherbert Ave Palmerston ",
    "sg:city":"Palmerston North",
    "sg:orig_category":"Shopping: Retail Stores: Books: Books - Secondhand",
    "sg:phone":"+64 6-353 0358",
    "sg:province":"Manawatu-Wanganui",
    "sg:website":"http://www.textbook.co.nz",
    "wof:name":"VOL 1 Bookshop - Volume 1",
    "wof:placetype":"venue"
},
  "geometry": {"coordinates":[175.61586,-40.362587],"type":"Point"}
}