{
  "type": "Feature",
  "properties": {
    "addr:full":"305 Cameron Rd  Tauranga Bay of Plenty",
    "addr:housenumber":"305",
    "addr:street":"Cameron Rd",
    "iso:country":"NZ",
    "sg:address":"305 Cameron Rd ",
    "sg:city":"Tauranga",
    "sg:orig_category":"Home And Garden: Furniture/Furnishings: Blinds",
    "sg:phone":"+64 7-578 5909",
    "sg:province":"Bay of Plenty",
    "wof:name":"Weathermaster",
    "wof:placetype":"venue"
},
  "geometry": {"coordinates":[176.164658,-37.689583],"type":"Point"}
}