{
  "type": "Feature",
  "properties": {
    "addr:full":"3 Fairview Rd Papatoetoe  Auckland Auckland",
    "addr:housenumber":"3",
    "addr:street":"Fairview Rd",
    "iso:country":"NZ",
    "sg:address":"3 Fairview Rd Papatoetoe ",
    "sg:city":"Auckland",
    "sg:orig_category":"Health And Beauty: Medical: Hospitals",
    "sg:phone":"+64 9-278 5370",
    "sg:province":"Auckland",
    "wof:name":"Papatoetoe Private Hospital",
    "wof:placetype":"venue"
},
  "geometry": {"coordinates":[174.85621599999999,-36.983116],"type":"Point"}
}