{
  "type": "Feature",
  "properties": {
    "addr:full":"126 Fisher Ave Beckenham  Christchurch Canterbury",
    "addr:housenumber":"126",
    "addr:street":"Fisher Ave",
    "iso:country":"NZ",
    "sg:address":"126 Fisher Ave Beckenham ",
    "sg:city":"Christchurch",
    "sg:classifiers":[
        {
            "category":"Education",
            "subcategory":"Special Training",
            "type":"Public Place"
        }
    ],
    "sg:phone":"+64 3-332 4617",
    "sg:province":"Canterbury",
    "sg:tags":[
        "school",
        "swimming"
    ],
    "wof:name":"Bumble Bees Swim School",
    "wof:placetype":"venue"
},
  "geometry": {"coordinates":[172.64524800000001,-43.560062],"type":"Point"}
}