{
  "type": "Feature",
  "properties": {
    "addr:full":"4/9 Haig St  Hamilton Waikato",
    "addr:housenumber":"4 / 9",
    "addr:street":"Haig St",
    "iso:country":"NZ",
    "sg:address":"4/9 Haig St ",
    "sg:city":"Hamilton",
    "sg:classifiers":[
        {
            "category":"Shopping",
            "subcategory":"Clothing, Apparel, & Fashions",
            "type":"Retail Goods"
        }
    ],
    "sg:phone":"+64 800 205 255",
    "sg:province":"Waikato",
    "sg:tags":[
        "clothing",
        "fabric"
    ],
    "sg:website":"http://www.yellowpages.co.nz/pages/216101792/dp10940.html",
    "wof:name":"Trio Marketing",
    "wof:placetype":"venue"
},
  "geometry": {"coordinates":[175.26312300000001,-37.7859],"type":"Point"}
}