{
  "type": "Feature",
  "properties": {
    "addr:full":"10 March Pl Christchurch  Belfast Canterbury",
    "addr:housenumber":"10",
    "addr:street":"March Pl",
    "iso:country":"NZ",
    "sg:address":"10 March Pl Christchurch ",
    "sg:city":"Belfast",
    "sg:orig_category":"Industrial: Packaging",
    "sg:phone":"+64 3-323 6540",
    "sg:province":"Canterbury",
    "wof:name":"Long Plastics Ltd",
    "wof:placetype":"venue"
},
  "geometry": {"coordinates":[172.632904,-43.451603],"type":"Point"}
}