{
  "type": "Feature",
  "properties": {
    "addr:full":"5/75B Ellice Rd Glenfield  Auckland Auckland",
    "addr:housenumber":"5 / 75b",
    "addr:street":"Ellice Rd",
    "iso:country":"NZ",
    "sg:address":"5/75B Ellice Rd Glenfield ",
    "sg:city":"Auckland",
    "sg:classifiers":[
        {
            "category":"Retail",
            "subcategory":"Auto Repair",
            "type":"Services"
        }
    ],
    "sg:phone":"+64 9-444 2314",
    "sg:province":"Auckland",
    "sg:tags":[
        "engine",
        "automotive",
        "diesel",
        "servicing"
    ],
    "wof:name":"North Shore Diesels Ltd",
    "wof:placetype":"venue"
},
  "geometry": {"coordinates":[174.728622,-36.784813],"type":"Point"}
}