{
  "type": "Feature",
  "properties": {
    "addr:full":"unit/29 Keeling Rd Henderson  Auckland Auckland",
    "addr:housenumber":"/ 29",
    "addr:street":"Keeling Rd",
    "iso:country":"NZ",
    "sg:address":"unit/29 Keeling Rd Henderson ",
    "sg:city":"Auckland",
    "sg:classifiers":[
        {
            "category":"Bars & Pubs",
            "type":"Food & Drink"
        }
    ],
    "sg:phone":"+64 9-837 8998",
    "sg:province":"Auckland",
    "sg:tags":[
        "-",
        "pie",
        "manufacturer"
    ],
    "wof:name":"Goldies Pies & Pasteries",
    "wof:placetype":"venue"
},
  "geometry": {"coordinates":[174.62480199999999,-36.885494],"type":"Point"}
}