{
  "type": "Feature",
  "properties": {
    "iso:country":"NZ",
    "sg:address":"13 Laings Rd Lower Hutt ",
    "sg:city":"Wellington",
    "sg:orig_category":"Clothing And Fabric: Fabric: Drapers",
    "sg:phone":"+64 4-939 4425",
    "sg:province":"Wellington",
    "wof:name":"Priya - House of Silks",
    "wof:placetype":"venue"
},
  "geometry": {"coordinates":[174.901581,-41.210674],"type":"Point"}
}