{
  "type": "Feature",
  "properties": {
    "iso:country":"NZ",
    "sg:address":"9//254 Lincoln Rd Henderson ",
    "sg:city":"Auckland",
    "sg:orig_category":"Shopping: Retail Stores: Books: Bookshops",
    "sg:phone":"+64 9-836 2500",
    "sg:province":"Auckland",
    "wof:name":"Edu Book Shop",
    "wof:placetype":"venue"
},
  "geometry": {"coordinates":[174.628235,-36.870419],"type":"Point"}
}