{
  "type": "Feature",
  "properties": {
    "iso:country":"NZ",
    "sg:address":"28 Canning Cre Mangere ",
    "sg:city":"Auckland",
    "sg:classifiers":[
        {
            "category":"Retail",
            "subcategory":"Funeral Services",
            "type":"Services"
        }
    ],
    "sg:phone":"+64 9-275 3307",
    "sg:province":"Auckland",
    "sg:tags":[
        "arrangements",
        "arrangement"
    ],
    "wof:name":"Ligaliga Funeral Services",
    "wof:placetype":"venue"
},
  "geometry": {"coordinates":[174.804428,-36.971325],"type":"Point"}
}