{
  "type": "Feature",
  "properties": {
    "addr:full":"143 Station Rd Otahuhu  Auckland Auckland",
    "addr:housenumber":"143",
    "addr:street":"Station Rd",
    "iso:country":"NZ",
    "sg:address":"143 Station Rd Otahuhu ",
    "sg:city":"Auckland",
    "sg:classifiers":[
        {
            "category":"Retail",
            "subcategory":"Auto Repair",
            "type":"Services"
        }
    ],
    "sg:phone":"+64 9-276 6152",
    "sg:province":"Auckland",
    "sg:tags":[
        "automotive",
        "absorber",
        "shock",
        "servicing"
    ],
    "wof:name":"Otahuhu Wheel Alignment Specialists 1998 Ltd",
    "wof:placetype":"venue"
},
  "geometry": {"coordinates":[174.83457899999999,-36.945702],"type":"Point"}
}