{
  "type": "Feature",
  "properties": {
    "addr:full":"3 Monahan Road Mt Wellington  Auckland Auckland",
    "addr:housenumber":"3",
    "addr:street":"Monahan Road",
    "iso:country":"NZ",
    "sg:address":"3 Monahan Road Mt Wellington ",
    "sg:city":"Auckland",
    "sg:orig_category":"Farming: Horticulture: Flowers",
    "sg:phone":"+64 9-573 1123",
    "sg:province":"Auckland",
    "wof:name":"Flowers.com",
    "wof:placetype":"venue"
},
  "geometry": {"coordinates":[174.84292600000001,-36.922997],"type":"Point"}
}