{
  "type": "Feature",
  "properties": {
    "addr:full":"109 Devonport Rd  Tauranga Auckland",
    "addr:housenumber":"109",
    "addr:street":"Devonport Rd",
    "iso:country":"NZ",
    "sg:address":"109 Devonport Rd ",
    "sg:city":"Tauranga",
    "sg:orig_category":"Travel And Tourism: Accommodation: Backpackers",
    "sg:phone":"+64 7-579 5638",
    "sg:province":"Auckland",
    "wof:name":"Loft 109",
    "wof:placetype":"venue"
},
  "geometry": {"coordinates":[176.16902200000001,-37.687134],"type":"Point"}
}