{
  "type": "Feature",
  "properties": {
    "addr:full":"4128 Great North Rd Kelston  Auckland Auckland",
    "addr:housenumber":"4128",
    "addr:street":"Great North Rd",
    "iso:country":"NZ",
    "sg:address":"4128 Great North Rd Kelston ",
    "sg:city":"Auckland",
    "sg:orig_category":"Automotive: Sales And Leasing: Trailers",
    "sg:phone":"+64 9-813 5600",
    "sg:province":"Auckland",
    "wof:name":"Total Hire",
    "wof:placetype":"venue"
},
  "geometry": {"coordinates":[174.66392500000001,-36.908218],"type":"Point"}
}