{
  "type": "Feature",
  "properties": {
    "addr:full":"158 Homewood Rd  Waipawa",
    "addr:housenumber":"158",
    "addr:street":"Homewood Rd",
    "iso:country":"NZ",
    "sg:address":"158 Homewood Rd ",
    "sg:city":"Waipawa",
    "sg:classifiers":[
        {
            "category":"Personal",
            "type":"Services"
        }
    ],
    "sg:phone":"+64 6-857 8362",
    "sg:tags":[
        "celebrant",
        "arrangements",
        "marriage",
        "wedding"
    ],
    "wof:name":"Pickett W D B",
    "wof:placetype":"venue"
},
  "geometry": {"coordinates":[176.639252,-39.933445],"type":"Point"}
}