{
  "type": "Feature",
  "properties": {
    "iso:country":"NZ",
    "sg:address":"PO Box 12002 Maori ",
    "sg:city":"Hill",
    "sg:classifiers":[
        {
            "category":"Landmark",
            "subcategory":"Tourist Information",
            "type":"Public Place"
        }
    ],
    "sg:phone":"+64 21 622 195",
    "sg:tags":[
        "travel",
        "tourism",
        "tour",
        "sightseeing"
    ],
    "wof:name":"Country Tours",
    "wof:placetype":"venue"
},
  "geometry": {"coordinates":[170.502701,-45.859348],"type":"Point"}
}