{
  "type": "Feature",
  "properties": {
    "addr:full":"64 Mersey St  Gore Southland",
    "addr:housenumber":"64",
    "addr:street":"Mersey St",
    "iso:country":"NZ",
    "sg:address":"64 Mersey St ",
    "sg:city":"Gore",
    "sg:classifiers":[
        {
            "category":"Home & Garden",
            "subcategory":"Home Furnishings",
            "type":"Retail Goods"
        }
    ],
    "sg:phone":"+64 3-208 6014",
    "sg:province":"Southland",
    "sg:tags":[
        "furniture/furnishings",
        "upholstery",
        "supply"
    ],
    "wof:name":"J P Upholstery",
    "wof:placetype":"venue"
},
  "geometry": {"coordinates":[-95.116547,35.530331],"type":"Point"}
}