{
  "type": "Feature",
  "properties": {
    "addr:full":"Petone  Wellington Wellington",
    "iso:country":"NZ",
    "sg:address":"Petone ",
    "sg:city":"Wellington",
    "sg:classifiers":[
        {
            "category":"Sports & Exercise",
            "subcategory":"Race Track",
            "type":"Entertainment"
        }
    ],
    "sg:phone":"+64 4-939 0552",
    "sg:province":"Wellington",
    "sg:tags":[
        "-",
        "motor",
        "leisure",
        "sports"
    ],
    "wof:name":"Racetech",
    "wof:placetype":"venue"
},
  "geometry": {"coordinates":[174.87507600000001,-41.221294],"type":"Point"}
}