{
  "type": "Feature",
  "properties": {
    "addr:full":"6th Floor Westpac Trust Building  Tauranga Bay of Plenty",
    "addr:housenumber":"6th floor",
    "addr:street":"Tauranga Bay",
    "iso:country":"NZ",
    "sg:address":"6th Floor Westpac Trust Building ",
    "sg:city":"Tauranga",
    "sg:classifiers":[
        {
            "category":"Insurance",
            "subcategory":"Health Insurance",
            "type":"Services"
        }
    ],
    "sg:phone":"+64 7-574 5940",
    "sg:province":"Bay of Plenty",
    "sg:tags":[
        "specialist",
        "beauty"
    ],
    "sg:website":"http://www.yellowpages.co.nz/for/skincentre/dp24283.html",
    "wof:name":"Skincentre",
    "wof:placetype":"venue"
},
  "geometry": {"coordinates":[176.14475999999999,-37.703152],"type":"Point"}
}