{
  "type": "Feature",
  "properties": {
    "iso:country":"NZ",
    "sg:address":"17 Clifton Rd ",
    "sg:city":"Hamilton",
    "sg:classifiers":[
        {
            "category":"Banks & Credit Unions",
            "subcategory":"Investment Brokerage",
            "type":"Services"
        }
    ],
    "sg:phone":"+64 7-838 3848",
    "sg:province":"Waikato",
    "sg:tags":[
        "personal",
        "accountant",
        "chartered",
        "-",
        "finance"
    ],
    "wof:name":"Mackrell Murcott",
    "wof:placetype":"venue"
},
  "geometry": {"coordinates":[-74.688683,40.23177],"type":"Point"}
}