{
  "type": "Feature",
  "properties": {
    "addr:full":"17 Turuturu Rd  Hawera Taranaki",
    "addr:housenumber":"17",
    "addr:street":"Turuturu Rd",
    "iso:country":"NZ",
    "sg:address":"17 Turuturu Rd ",
    "sg:city":"Hawera",
    "sg:classifiers":[
        {
            "category":"Bus Charters",
            "type":"Transportation"
        }
    ],
    "sg:phone":"+64 6-278 5858",
    "sg:province":"Taranaki",
    "sg:tags":[
        "services",
        "travel",
        "tourism"
    ],
    "wof:name":"Weir Bros",
    "wof:placetype":"venue"
},
  "geometry": {"coordinates":[174.27281199999999,-39.578003],"type":"Point"}
}