{
  "type": "Feature",
  "properties": {
    "addr:full":"18 Bath St  Christchurch Canterbury",
    "addr:housenumber":"18",
    "addr:street":"Bath St",
    "iso:country":"NZ",
    "sg:address":"18 Bath St ",
    "sg:city":"Christchurch",
    "sg:classifiers":[
        {
            "category":"Banks & Credit Unions",
            "subcategory":"Financial Services",
            "type":"Services"
        }
    ],
    "sg:phone":"+64 3-366 6172",
    "sg:province":"Canterbury",
    "sg:tags":[
        "services",
        "die",
        "industrial",
        "maker",
        "sinker"
    ],
    "wof:name":"Burgess A F",
    "wof:placetype":"venue"
},
  "geometry": {"coordinates":[-76.537834,37.605659],"type":"Point"}
}