{
  "type": "Feature",
  "properties": {
    "addr:full":"Okahu Rd  Kaitaia Northland",
    "addr:street":"Okahu Rd",
    "iso:country":"NZ",
    "sg:address":"Okahu Rd ",
    "sg:city":"Kaitaia",
    "sg:classifiers":[
        {
            "category":"Winery",
            "type":"Food & Drink"
        }
    ],
    "sg:phone":"+64 9-408 2066",
    "sg:province":"Northland",
    "sg:tags":[
        "wining",
        "vineyard",
        "dining"
    ],
    "wof:name":"Okahu Estate Vineyard & Winery",
    "wof:placetype":"venue"
},
  "geometry": {"coordinates":[173.24954199999999,-35.144962],"type":"Point"}
}