{
  "type": "Feature",
  "properties": {
    "addr:full":"PO Box 50-184  Porirua Wellington",
    "addr:housenumber":"po box",
    "addr:postcode":"50-184",
    "iso:country":"NZ",
    "sg:address":"PO Box 50-184 ",
    "sg:city":"Porirua",
    "sg:classifiers":[
        {
            "category":"Building & Trades",
            "subcategory":"Cleaning & Sanitation",
            "type":"Services"
        }
    ],
    "sg:phone":"+64 800 180 184",
    "sg:province":"Wellington",
    "sg:tags":[
        "equipment",
        "industrial",
        "maintenance"
    ],
    "wof:name":"Kelly Enterprises Ltd",
    "wof:placetype":"venue"
},
  "geometry": {"coordinates":[174.85223400000001,-41.138294],"type":"Point"}
}