{
  "type": "Feature",
  "properties": {
    "addr:full":"11 Mountjoy Pl Onehunga  Auckland Auckland",
    "addr:housenumber":"11",
    "addr:street":"Mountjoy Pl",
    "iso:country":"NZ",
    "sg:address":"11 Mountjoy Pl Onehunga ",
    "sg:city":"Auckland",
    "sg:classifiers":[
        {
            "category":"Professional",
            "subcategory":"Art Services",
            "type":"Services"
        }
    ],
    "sg:phone":"+64 9-622 1252",
    "sg:province":"Auckland",
    "sg:tags":[
        "picture",
        "arts",
        "sport",
        "framing",
        "leisure"
    ],
    "wof:name":"Graphics 80",
    "wof:placetype":"venue"
},
  "geometry": {"coordinates":[174.783661,-36.909973],"type":"Point"}
}