{
  "type": "Feature",
  "properties": {
    "iso:country":"NZ",
    "sg:address":"PO Box 6794 Wellesley Street ",
    "sg:city":"Auckland",
    "sg:classifiers":[
        {
            "category":"Food Court",
            "type":"Food & Drink"
        }
    ],
    "sg:phone":"+64 9-579 0883",
    "sg:province":"Manawatu-Wanganui",
    "sg:tags":[
        "packer",
        "processing",
        "processor"
    ],
    "wof:name":"Chef's Choice",
    "wof:placetype":"venue"
},
  "geometry": {"coordinates":[-119.10457599999999,36.597755],"type":"Point"}
}