{
  "type": "Feature",
  "properties": {
    "addr:full":"P.O Box 58 493  Greenmount Auckland",
    "addr:housenumber":"58 493",
    "addr:street":"P.O Box",
    "iso:country":"NZ",
    "sg:address":"P.O Box 58 493 ",
    "sg:city":"Greenmount",
    "sg:classifiers":[
        {
            "category":"Manufacturing",
            "subcategory":"Chemicals & Compounds",
            "type":"Manufacturing & Wholesale Goods"
        }
    ],
    "sg:phone":"+64 9-476 6922",
    "sg:province":"Auckland",
    "sg:tags":[
        "industrial"
    ],
    "wof:name":"Loctite",
    "wof:placetype":"venue"
},
  "geometry": {"coordinates":[-77.271118,39.767288],"type":"Point"}
}