{
  "type": "Feature",
  "properties": {
    "iso:country":"NZ",
    "sg:address":"33 Mandeville St Riccarton ",
    "sg:city":"Christchurch",
    "sg:classifiers":[
        {
            "category":"Home & Garden",
            "subcategory":"Hardware",
            "type":"Retail Goods"
        }
    ],
    "sg:phone":"+64 3-343 5644",
    "sg:province":"Canterbury",
    "sg:tags":[
        "window",
        "fittings"
    ],
    "sg:website":"http://www.energydoctor.co.nz",
    "wof:name":"The Energy Doctor (S.I)",
    "wof:placetype":"venue"
},
  "geometry": {"coordinates":[172.606689,-43.534828],"type":"Point"}
}