{
  "type": "Feature",
  "properties": {
    "addr:full":"186 The Strand  Whakatane Auckland",
    "addr:housenumber":"186",
    "addr:street":"The Strand",
    "iso:country":"NZ",
    "sg:address":"186 The Strand ",
    "sg:city":"Whakatane",
    "sg:classifiers":[
        {
            "category":"Education",
            "subcategory":"Special Training",
            "type":"Public Place"
        }
    ],
    "sg:phone":"+64 7-307 0714",
    "sg:province":"Auckland",
    "sg:tags":[
        "charter",
        "shopping",
        "dive",
        "tuition",
        "water",
        "sports",
        "retailers",
        "sport"
    ],
    "wof:name":"Sportsworld",
    "wof:placetype":"venue"
},
  "geometry": {"coordinates":[176.995193,-37.951645],"type":"Point"}
}