{
  "type": "Feature",
  "properties": {
    "iso:country":"NZ",
    "sg:address":"Moreton Rd ",
    "sg:city":"Carterton",
    "sg:classifiers":[
        {
            "category":"Food & Beverages",
            "subcategory":"Meat & Fish",
            "type":"Retail Goods"
        }
    ],
    "sg:phone":"+64 800 506 701",
    "sg:tags":[
        "drink"
    ],
    "sg:website":"http://www.premierebacon.co.nz",
    "wof:name":"Premiere Bacon Company Ltd",
    "wof:placetype":"venue"
},
  "geometry": {"coordinates":[-82.190933,36.941956],"type":"Point"}
}