{
  "type": "Feature",
  "properties": {
    "iso:country":"NZ",
    "sg:address":"429 Te Ngae Rd ",
    "sg:city":"Rotorua",
    "sg:orig_category":"Health And Beauty: Medical: Hospitals",
    "sg:phone":"+64 7-349 7150",
    "sg:province":"Bay of Plenty",
    "wof:name":"Redwood Lodge Home & Hospital",
    "wof:placetype":"venue"
},
  "geometry": {"coordinates":[176.25914,-38.14566],"type":"Point"}
}