{
  "type": "Feature",
  "properties": {
    "addr:full":"89 Maunganui Rd Mt  Maunganui Bay of Plenty",
    "addr:housenumber":"89",
    "addr:street":"Maunganui Rd;Maunganui",
    "iso:country":"NZ",
    "sg:address":"89 Maunganui Rd Mt ",
    "sg:city":"Maunganui",
    "sg:classifiers":[
        {
            "category":"Shopping",
            "subcategory":"Gifts & Souvenirs",
            "type":"Retail Goods"
        }
    ],
    "sg:phone":"+64 7-575 8899",
    "sg:province":"Bay of Plenty",
    "sg:tags":[
        "shop",
        "gifts",
        "supplier"
    ],
    "wof:name":"Options",
    "wof:placetype":"venue"
},
  "geometry": {"coordinates":[176.18270899999999,-37.636211],"type":"Point"}
}