{
  "type": "Feature",
  "properties": {
    "iso:country":"NZ",
    "sg:address":"10 Robinson St ",
    "sg:city":"Cambridge",
    "sg:orig_category":"Industrial: Coatings",
    "sg:phone":"+64 7-827 7289",
    "sg:province":"Waikato",
    "wof:name":"Home Textures",
    "wof:placetype":"venue"
},
  "geometry": {"coordinates":[-71.12578600000001,42.383793],"type":"Point"}
}