{
  "type": "Feature",
  "properties": {
    "addr:full":"214 Te Awa Ave  Napier Hawke's Bay",
    "addr:housenumber":"214",
    "addr:street":"Te Awa Ave",
    "iso:country":"NZ",
    "sg:address":"214 Te Awa Ave ",
    "sg:city":"Napier",
    "sg:classifiers":[
        {
            "category":"Shopping",
            "subcategory":"Crafts & Fabrics",
            "type":"Retail Goods"
        }
    ],
    "sg:phone":"+64 6-835 8737",
    "sg:province":"Hawke's Bay",
    "sg:tags":[
        "arts",
        "sport",
        "art",
        "leisure",
        "supply"
    ],
    "wof:name":"Crackpots Mosaics",
    "wof:placetype":"venue"
},
  "geometry": {"coordinates":[176.917328,-39.530647],"type":"Point"}
}