{
  "type": "Feature",
  "properties": {
    "addr:full":"5th floor, Dingwall Building 87 Queen St Auckland Central Auckland Auckland",
    "addr:housenumber":"5th floor dingwall building 87",
    "addr:street":"Queen St",
    "iso:country":"NZ",
    "sg:address":"5th floor, Dingwall Building 87 Queen St Auckland Central",
    "sg:city":"Auckland",
    "sg:classifiers":[
        {
            "category":"Shopping",
            "subcategory":"Beauty & Cosmetics",
            "type":"Retail Goods"
        }
    ],
    "sg:phone":"+64 9-373 4621",
    "sg:province":"Auckland",
    "sg:tags":[
        "medical",
        "health"
    ],
    "wof:name":"Auckland Metro Doctors & Travelcare",
    "wof:placetype":"venue"
},
  "geometry": {"coordinates":[174.76454200000001,-36.848358],"type":"Point"}
}