{
  "type": "Feature",
  "properties": {
    "iso:country":"NZ",
    "sg:address":"11 Manchester St ",
    "sg:city":"Paraparaumu",
    "sg:classifiers":[
        {
            "category":"Home & Garden",
            "subcategory":"Hardware",
            "type":"Retail Goods"
        }
    ],
    "sg:phone":"+64 4-298 7091",
    "sg:province":"Wellington",
    "sg:tags":[
        "window",
        "fitting"
    ],
    "wof:name":"Nu Look Windows & Doors",
    "wof:placetype":"venue"
},
  "geometry": {"coordinates":[175.001892,-40.905037],"type":"Point"}
}