{
  "type": "Feature",
  "properties": {
    "iso:country":"NZ",
    "sg:address":"PO Box 51184 ",
    "sg:city":"Tawa",
    "sg:classifiers":[
        {
            "category":"Insurance",
            "subcategory":"Health Insurance",
            "type":"Services"
        }
    ],
    "sg:phone":"+64 4-920 5667",
    "sg:province":"Wellington",
    "sg:tags":[
        "pregnancy",
        "specialists",
        "beauty"
    ],
    "wof:name":"The House of Grace Trust Inc. - A Home for Pregnant Teens",
    "wof:placetype":"venue"
},
  "geometry": {"coordinates":[-100.303078,19.11949],"type":"Point"}
}