{
  "type": "Feature",
  "properties": {
    "iso:country":"NZ",
    "sg:address":"424 Scotts Rd Linton R D ",
    "sg:city":"4",
    "sg:orig_category":"Farming: Machinery: Milking Machinery",
    "sg:phone":"+64 6-325 8811",
    "wof:name":"Professional Maintenance Services",
    "wof:placetype":"venue"
},
  "geometry": {"coordinates":[-87.167717,39.03495],"type":"Point"}
}