{
  "type": "Feature",
  "properties": {
    "addr:full":"98 Churchill Dve Crofton Downs  Wellington Wellington",
    "addr:housenumber":"98",
    "addr:street":"Churchill Dve",
    "iso:country":"NZ",
    "sg:address":"98 Churchill Dve Crofton Downs ",
    "sg:city":"Wellington",
    "sg:classifiers":[
        {
            "category":"Health Services",
            "subcategory":"Dentist",
            "type":"Services"
        }
    ],
    "sg:phone":"+64 4-479 4495",
    "sg:province":"Wellington",
    "sg:tags":[
        "dental",
        "oral",
        "surgeon",
        "beauty"
    ],
    "wof:name":"Adams Donald B",
    "wof:placetype":"venue"
},
  "geometry": {"coordinates":[174.76715100000001,-41.28054],"type":"Point"}
}