{
  "type": "Feature",
  "properties": {
    "addr:full":"402 Princes St  Dunedin Otago",
    "addr:housenumber":"402",
    "addr:street":"Princes St",
    "iso:country":"NZ",
    "sg:address":"402 Princes St ",
    "sg:city":"Dunedin",
    "sg:classifiers":[
        {
            "category":"Building & Trades",
            "subcategory":"Construction",
            "type":"Services"
        }
    ],
    "sg:phone":"+64 3-477 9384",
    "sg:province":"Otago",
    "sg:tags":[
        "home",
        "garden",
        "related",
        "plasterer"
    ],
    "wof:name":"James Wren & Co Ltd",
    "wof:placetype":"venue"
},
  "geometry": {"coordinates":[170.500046,-45.880112],"type":"Point"}
}