{
  "type": "Feature",
  "properties": {
    "addr:full":"6 Karamea Rd  Mangonui",
    "addr:housenumber":"6",
    "addr:street":"Karamea Rd",
    "iso:country":"NZ",
    "sg:address":"6 Karamea Rd ",
    "sg:city":"Mangonui",
    "sg:classifiers":[
        {
            "category":"Landmark",
            "subcategory":"Tourist Information",
            "type":"Public Place"
        }
    ],
    "sg:phone":"+64 9-406 0460",
    "sg:tags":[
        "travel",
        "tourism",
        "tour",
        "sightseeing"
    ],
    "wof:name":"Paradise Connexion Bus Tours",
    "wof:placetype":"venue"
},
  "geometry": {"coordinates":[173.53259299999999,-34.995663],"type":"Point"}
}