{
  "type": "Feature",
  "properties": {
    "addr:full":"Depot cnr Elizabeth & Comber Sts  Matamata Waikato",
    "addr:street":"Cnr Elizabeth & Comber Sts",
    "iso:country":"NZ",
    "sg:address":"Depot cnr Elizabeth & Comber Sts ",
    "sg:city":"Matamata",
    "sg:orig_category":"Industrial: Parts: Pipes, Tubes And Cabling: Cables",
    "sg:phone":"+64 7-888 5724",
    "sg:province":"Waikato",
    "wof:name":"Don Griffiths Ltd",
    "wof:placetype":"venue"
},
  "geometry": {"coordinates":[175.77354399999999,-37.81176],"type":"Point"}
}