{
  "type": "Feature",
  "properties": {
    "addr:full":"16 Lipton Pl Onekawa  Napier Hawke's Bay",
    "addr:housenumber":"16",
    "addr:street":"Lipton Pl",
    "iso:country":"NZ",
    "sg:address":"16 Lipton Pl Onekawa ",
    "sg:city":"Napier",
    "sg:orig_category":"Automotive: General Services: Rental Vehicles",
    "sg:phone":"+64 6-843 6846",
    "sg:province":"Hawke's Bay",
    "wof:name":"Auto Rental Vehicles",
    "wof:placetype":"venue"
},
  "geometry": {"coordinates":[176.87809799999999,-39.501209],"type":"Point"}
}