{
  "type": "Feature",
  "properties": {
    "addr:full":"204 Devon St West New  Plymouth Taranaki",
    "addr:housenumber":"204",
    "addr:street":"Devon St",
    "iso:country":"NZ",
    "sg:address":"204 Devon St West New ",
    "sg:city":"Plymouth",
    "sg:classifiers":[
        {
            "category":"Retail",
            "subcategory":"Laundry & Dry Cleaning",
            "type":"Services"
        }
    ],
    "sg:phone":"+64 6-758 3430",
    "sg:province":"Taranaki",
    "sg:tags":[
        "repair",
        "clothing",
        "fabric",
        "cleaner"
    ],
    "wof:name":"Taylors Sanitone Drycleaners",
    "wof:placetype":"venue"
},
  "geometry": {"coordinates":[174.06680299999999,-39.059834],"type":"Point"}
}