{
  "type": "Feature",
  "properties": {
    "iso:country":"NZ",
    "sg:address":"204 Devon St West New ",
    "sg:city":"Plymouth",
    "sg:classifiers":[
        {
            "category":"Retail",
            "subcategory":"Laundry & Dry Cleaning",
            "type":"Services"
        }
    ],
    "sg:phone":"+64 6-758 3430",
    "sg:province":"Taranaki",
    "sg:tags":[
        "repair",
        "clothing",
        "fabric",
        "cleaner"
    ],
    "wof:name":"Taylors Sanitone Drycleaners",
    "wof:placetype":"venue"
},
  "geometry": {"coordinates":[174.066803,-39.059834],"type":"Point"}
}