{
  "type": "Feature",
  "properties": {
    "addr:full":"17 Keith St Palmerston  Palmerston North Manawatu-Wanganui",
    "addr:housenumber":"17",
    "addr:street":"Keith St Palmerston",
    "iso:country":"NZ",
    "sg:address":"17 Keith St Palmerston ",
    "sg:city":"Palmerston North",
    "sg:orig_category":"Industrial: Engineering: Engineers - Mechanical",
    "sg:phone":"+64 6-355 2754",
    "sg:province":"Manawatu-Wanganui",
    "wof:name":"Baty Les Engineering",
    "wof:placetype":"venue"
},
  "geometry": {"coordinates":[175.63713100000001,-40.332489],"type":"Point"}
}