{
  "type": "Feature",
  "properties": {
    "addr:full":"Salisbury Ave Post Bag 1 Mt  Maunganui Bay of Plenty",
    "addr:housenumber":"1",
    "addr:street":"Salisbury;Bag;Mt Maunganui",
    "iso:country":"NZ",
    "sg:address":"Salisbury Ave Post Bag 1 Mt ",
    "sg:city":"Maunganui",
    "sg:orig_category":"Transport: Boats And Marine: Shipping",
    "sg:phone":"+64 7-575 1899",
    "sg:province":"Bay of Plenty",
    "sg:website":"http://www.port-tauranga.co.nz",
    "wof:name":"Port Of Tauranga Limited",
    "wof:placetype":"venue"
},
  "geometry": {"coordinates":[176.18627900000001,-37.641048],"type":"Point"}
}