{
  "type": "Feature",
  "properties": {
    "iso:country":"NZ",
    "sg:address":"1 Dee St ",
    "sg:city":"Oamaru",
    "sg:classifiers":[
        {
            "category":"Retail",
            "subcategory":"Auto Repair",
            "type":"Services"
        }
    ],
    "sg:phone":"+64 3-434 8777",
    "sg:province":"Otago",
    "sg:tags":[
        "muffler",
        "exhaust",
        "servicing",
        "automotive"
    ],
    "wof:name":"Oamaru Exhausts",
    "wof:placetype":"venue"
},
  "geometry": {"coordinates":[170.971985,-45.094559],"type":"Point"}
}