{
  "type": "Feature",
  "properties": {
    "addr:full":"Te  Anau Southland",
    "iso:country":"NZ",
    "sg:address":"Te ",
    "sg:city":"Anau",
    "sg:classifiers":[
        {
            "category":"Bus Charters",
            "type":"Transportation"
        }
    ],
    "sg:phone":"+64 800 277 483",
    "sg:province":"Southland",
    "sg:tags":[
        "services",
        "travel",
        "tourism"
    ],
    "wof:name":"Spitfire Shuttle (Te Anau)",
    "wof:placetype":"venue"
},
  "geometry": {"coordinates":[167.71940599999999,-45.416828],"type":"Point"}
}