{
  "type": "Feature",
  "properties": {
    "iso:country":"NZ",
    "sg:address":"65 Bridge St ",
    "sg:city":"Tokoroa",
    "sg:orig_category":"Clothing And Fabric: Clothing: Women'S Fashions",
    "sg:phone":"+64 7-886 0268",
    "wof:name":"Anventagous Boutique",
    "wof:placetype":"venue"
},
  "geometry": {"coordinates":[175.86958300000001,-38.218643],"type":"Point"}
}