{
  "type": "Feature",
  "properties": {
    "iso:country":"NZ",
    "sg:address":"11 Links Rd Titirangi ",
    "sg:city":"Auckland",
    "sg:orig_category":"Sports And Leisure: Sports: Golf: Golf Courses",
    "sg:phone":"+64 9-827 5749",
    "sg:province":"Auckland",
    "wof:name":"Titirangi Golf Club Inc",
    "wof:placetype":"venue"
},
  "geometry": {"coordinates":[174.662796,-36.926861],"type":"Point"}
}