{
  "type": "Feature",
  "properties": {
    "addr:full":"154 E Harris Rd East Tamaki  Auckland Auckland",
    "addr:housenumber":"154",
    "addr:street":"E Harris Rd",
    "iso:country":"NZ",
    "sg:address":"154 E Harris Rd East Tamaki ",
    "sg:city":"Auckland",
    "sg:orig_category":"Industrial: Refrigeration And Services: Coolstore Builders",
    "sg:phone":"+64 9-274 4447",
    "sg:province":"Auckland",
    "sg:website":"http://www.thermo.co.nz",
    "wof:name":"Thermo Tech Auckland Ltd",
    "wof:placetype":"venue"
},
  "geometry": {"coordinates":[174.897278,-36.928825],"type":"Point"}
}