{
  "type": "Feature",
  "properties": {
    "iso:country":"NZ",
    "sg:address":"PO Box 6034 Palmerston ",
    "sg:city":"Palmerston North",
    "sg:orig_category":"Transport: Transportation: Courier Services",
    "sg:phone":"+64 6-358 6196",
    "sg:province":"Manawatu-Wanganui",
    "wof:name":"Citisprint Couriers Ltd",
    "wof:placetype":"venue"
},
  "geometry": {"coordinates":[175.611481,-40.357418],"type":"Point"}
}