{
  "type": "Feature",
  "properties": {
    "iso:country":"NZ",
    "sg:address":"726 Richardson Rd Mt Roskill ",
    "sg:city":"Auckland",
    "sg:classifiers":[
        {
            "category":"Home & Garden",
            "subcategory":"Home Furnishings",
            "type":"Retail Goods"
        }
    ],
    "sg:phone":"+64 9-625 5475",
    "sg:province":"Auckland",
    "sg:tags":[
        "furniture/furnishings",
        "upholstery",
        "supply"
    ],
    "wof:name":"Royal Furniture & Upholstery",
    "wof:placetype":"venue"
},
  "geometry": {"coordinates":[174.74276699999999,-36.905895],"type":"Point"}
}