{
  "type": "Feature",
  "properties": {
    "iso:country":"NZ",
    "sg:address":"29 Shakespeare St Te ",
    "sg:city":"Aroha",
    "sg:orig_category":"Industrial: Electrical/Electronic",
    "sg:phone":"+64 7-884 9352",
    "wof:name":"Winton Heath TV & Appliances",
    "wof:placetype":"venue"
},
  "geometry": {"coordinates":[175.70463599999999,-37.535137],"type":"Point"}
}