{
  "type": "Feature",
  "properties": {
    "addr:full":"32 Kepa Rd Ruakaka  Whangarei Northland",
    "addr:housenumber":"32",
    "addr:street":"Kepa Rd",
    "iso:country":"NZ",
    "sg:address":"32 Kepa Rd Ruakaka ",
    "sg:city":"Whangarei",
    "sg:classifiers":[
        {
            "category":"Home & Garden",
            "subcategory":"Building Materials",
            "type":"Retail Goods"
        }
    ],
    "sg:phone":"+64 9-432 8650",
    "sg:province":"Northland",
    "sg:tags":[
        "builder",
        "related"
    ],
    "wof:name":"Tristar Engineering Ltd",
    "wof:placetype":"venue"
},
  "geometry": {"coordinates":[174.46250900000001,-35.874886],"type":"Point"}
}