{
  "type": "Feature",
  "properties": {
    "addr:full":"227 Waltham Rd Waltham  Christchurch Canterbury",
    "addr:housenumber":"227",
    "addr:street":"Waltham Rd",
    "iso:country":"NZ",
    "sg:address":"227 Waltham Rd Waltham ",
    "sg:city":"Christchurch",
    "sg:classifiers":[
        {
            "category":"Banks & Credit Unions",
            "subcategory":"Investment Brokerage",
            "type":"Services"
        }
    ],
    "sg:phone":"+64 3-365 6868",
    "sg:province":"Canterbury",
    "sg:tags":[
        "services",
        "industrial",
        "refrigeration",
        "servicing"
    ],
    "sg:website":"http://www.commercialrefrigeration.co.nz",
    "wof:name":"Commercial Refrigeration & Wholesale",
    "wof:placetype":"venue"
},
  "geometry": {"coordinates":[172.64987199999999,-43.547878],"type":"Point"}
}