{
  "type": "Feature",
  "properties": {
    "iso:country":"NZ",
    "sg:address":"Upper Plain Rd RD8 ",
    "sg:city":"Masterton",
    "sg:classifiers":[
        {
            "category":"Travel",
            "subcategory":"Bed & Breakfast",
            "type":"Entertainment"
        }
    ],
    "sg:phone":"+64 6-378 6654",
    "sg:province":"Wellington",
    "sg:tags":[
        "tourism",
        "accommodation"
    ],
    "wof:name":"Springfield Lodge",
    "wof:placetype":"venue"
},
  "geometry": {"coordinates":[175.657333,-40.94931],"type":"Point"}
}