{
  "type": "Feature",
  "properties": {
    "addr:full":"30 Delhi Cre Khandallah  Wellington Wellington",
    "addr:housenumber":"30",
    "addr:street":"Delhi;Wellington",
    "iso:country":"NZ",
    "sg:address":"30 Delhi Cre Khandallah ",
    "sg:city":"Wellington",
    "sg:classifiers":[
        {
            "category":"Retail",
            "subcategory":"Laundry & Dry Cleaning",
            "type":"Services"
        }
    ],
    "sg:phone":"+64 4-479 5517",
    "sg:province":"Wellington",
    "sg:tags":[
        "product",
        "wool",
        "clothing",
        "fabric"
    ],
    "wof:name":"NZ Wool Exports Ltd",
    "wof:placetype":"venue"
},
  "geometry": {"coordinates":[174.796494,-41.246201],"type":"Point"}
}