{
  "type": "Feature",
  "properties": {
    "addr:full":"13 Maidstone St Ponsonby  Auckland Auckland",
    "addr:housenumber":"13",
    "addr:street":"Maidstone St",
    "iso:country":"NZ",
    "sg:address":"13 Maidstone St Ponsonby ",
    "sg:city":"Auckland",
    "sg:classifiers":[
        {
            "category":"Health Services",
            "subcategory":"Clinic",
            "type":"Services"
        }
    ],
    "sg:phone":"+64 9-303 5112",
    "sg:province":"Auckland",
    "sg:tags":[
        "medical",
        "beauty"
    ],
    "sg:website":"http://www.yellowpages.co.nz/pages/227142874/dp45624.html",
    "wof:name":"Ric Church - Counsellor",
    "wof:placetype":"venue"
},
  "geometry": {"coordinates":[174.74241599999999,-36.85326],"type":"Point"}
}