{
  "type": "Feature",
  "properties": {
    "addr:full":"45 North Rd  Kaitaia Northland",
    "addr:housenumber":"45",
    "addr:street":"North Rd",
    "iso:country":"NZ",
    "sg:address":"45 North Rd ",
    "sg:city":"Kaitaia",
    "sg:classifiers":[
        {
            "category":"Health Services",
            "subcategory":"Dentist",
            "type":"Services"
        }
    ],
    "sg:phone":"+64 9-408 0125",
    "sg:province":"Northland",
    "sg:tags":[
        "dental",
        "clinic",
        "beauty"
    ],
    "wof:name":"Kaitaia Intermediate School Dental Clinic",
    "wof:placetype":"venue"
},
  "geometry": {"coordinates":[173.25973500000001,-35.100063],"type":"Point"}
}