{
  "type": "Feature",
  "properties": {
    "iso:country":"NZ",
    "sg:address":"16 Kahu St Otahuhu ",
    "sg:city":"Auckland",
    "sg:orig_category":"Transport: Transportation: Courier Services",
    "sg:phone":"+64 9-259 1515",
    "sg:province":"Auckland",
    "wof:name":"Advance Freight & Couriers Ltd",
    "wof:placetype":"venue"
},
  "geometry": {"coordinates":[174.85611,-36.940605],"type":"Point"}
}