{
  "type": "Feature",
  "properties": {
    "iso:country":"NZ",
    "sg:address":"Hokianga Rd ",
    "sg:city":"Dargaville",
    "sg:orig_category":"Health And Beauty: Specialists: Osteopaths",
    "sg:phone":"+64 9-439 8158",
    "sg:province":"Northland",
    "wof:name":"Paul Gray Osteopath",
    "wof:placetype":"venue"
},
  "geometry": {"coordinates":[173.86338799999999,-35.937065],"type":"Point"}
}