{
  "type": "Feature",
  "properties": {
    "addr:full":"Maple St  Tapanui",
    "addr:street":"Maple St",
    "iso:country":"NZ",
    "sg:address":"Maple St ",
    "sg:city":"Tapanui",
    "sg:orig_category":"Sports And Leisure: General: Clubs",
    "sg:phone":"+64 3-204 8474",
    "wof:name":"West Otago Town & Country Club",
    "wof:placetype":"venue"
},
  "geometry": {"coordinates":[169.26147499999999,-45.943905],"type":"Point"}
}