{
  "type": "Feature",
  "properties": {
    "iso:country":"NZ",
    "sg:address":"10 Matthews Ave ",
    "sg:city":"Kaitaia",
    "sg:classifiers":[
        {
            "category":"Health Services",
            "subcategory":"Dentist",
            "type":"Services"
        }
    ],
    "sg:phone":"+64 9-408 1255",
    "sg:province":"Northland",
    "sg:tags":[
        "dental",
        "beauty"
    ],
    "wof:name":"D J Legg",
    "wof:placetype":"venue"
},
  "geometry": {"coordinates":[173.264938,-35.112343],"type":"Point"}
}