{
  "type": "Feature",
  "properties": {
    "iso:country":"NZ",
    "sg:address":"Janice Young ",
    "sg:city":"Pakuranga",
    "sg:classifiers":[
        {
            "category":"Personal",
            "subcategory":"Beauty Salon",
            "type":"Services"
        }
    ],
    "sg:phone":"+64 9-576 7833",
    "sg:province":"Auckland",
    "sg:tags":[
        "artist",
        "health",
        "make-up"
    ],
    "wof:name":"B. Beautiful",
    "wof:placetype":"venue"
},
  "geometry": {"coordinates":[174.879044,-36.91584],"type":"Point"}
}