{
  "type": "Feature",
  "properties": {
    "addr:full":"P.O. Box 34  Omarama",
    "addr:housenumber":"p.o. box 34",
    "iso:country":"NZ",
    "sg:address":"P.O. Box 34 ",
    "sg:city":"Omarama",
    "sg:classifiers":[
        {
            "category":"Travel",
            "subcategory":"Hotels & Motels",
            "type":"Entertainment"
        }
    ],
    "sg:phone":"+64 3-438 9875",
    "sg:tags":[
        "holiday",
        "tourism",
        "accommodation"
    ],
    "wof:name":"Omarama Top 10 Holiday Park",
    "wof:placetype":"venue"
},
  "geometry": {"coordinates":[169.96893299999999,-44.491158],"type":"Point"}
}