{
  "type": "Feature",
  "properties": {
    "addr:full":"Palmerston St  Westport West Coast",
    "addr:street":"Palmerston St",
    "iso:country":"NZ",
    "sg:address":"Palmerston St ",
    "sg:city":"Westport",
    "sg:classifiers":[
        {
            "category":"Recreation",
            "type":"Entertainment"
        }
    ],
    "sg:phone":"+64 3-789 8872",
    "sg:province":"West Coast",
    "sg:tags":[
        "sport",
        "leisure"
    ],
    "wof:name":"Returned Services Assn & Club",
    "wof:placetype":"venue"
},
  "geometry": {"coordinates":[-123.78488900000001,39.639027],"type":"Point"}
}