{
  "type": "Feature",
  "properties": {
    "addr:full":"127 Wordsworth St Sydenham  Christchurch Canterbury",
    "addr:housenumber":"127",
    "addr:street":"Wordsworth St",
    "iso:country":"NZ",
    "sg:address":"127 Wordsworth St Sydenham ",
    "sg:city":"Christchurch",
    "sg:classifiers":[
        {
            "category":"Retail",
            "subcategory":"Auto Repair",
            "type":"Services"
        }
    ],
    "sg:phone":"+64 3-365 3498",
    "sg:province":"Canterbury",
    "sg:tags":[
        "automotive",
        "servicing"
    ],
    "sg:website":"http://www.turbotechnology.co.nz",
    "wof:name":"Turbo Technology",
    "wof:placetype":"venue"
},
  "geometry": {"coordinates":[172.64059399999999,-43.54459],"type":"Point"}
}