{
  "type": "Feature",
  "properties": {
    "iso:country":"NZ",
    "sg:address":"14 McFarlane Pl Springlands ",
    "sg:city":"Blenheim",
    "sg:classifiers":[
        {
            "category":"Personal",
            "type":"Services"
        }
    ],
    "sg:phone":"+64 3-578 0825",
    "sg:province":"Marlborough",
    "sg:tags":[
        "celebrant",
        "arrangements",
        "marriage",
        "wedding"
    ],
    "wof:name":"Simpson Doug",
    "wof:placetype":"venue"
},
  "geometry": {"coordinates":[173.942459,-41.503448],"type":"Point"}
}