{
  "type": "Feature",
  "properties": {
    "addr:full":"105 C Wheturangi Rd Greenlane  Auckland Auckland",
    "addr:housenumber":"105 c",
    "addr:street":"Wheturangi Rd",
    "iso:country":"NZ",
    "sg:address":"105 C Wheturangi Rd Greenlane ",
    "sg:city":"Auckland",
    "sg:orig_category":"Health And Beauty: Medical: Hospitals",
    "sg:phone":"+64 9-524 8622",
    "sg:province":"Auckland",
    "wof:name":"Manor Medical Hospital",
    "wof:placetype":"venue"
},
  "geometry": {"coordinates":[174.78713999999999,-36.889694],"type":"Point"}
}