{
  "type": "Feature",
  "properties": {
    "addr:full":"9/2A Commerce St Auckland Central  Auckland Auckland",
    "addr:housenumber":"9 / 2a",
    "addr:street":"Commerce St",
    "iso:country":"NZ",
    "sg:address":"9/2A Commerce St Auckland Central ",
    "sg:city":"Auckland",
    "sg:classifiers":[
        {
            "category":"Deli",
            "type":"Food & Drink"
        }
    ],
    "sg:phone":"+64 9-379 7726",
    "sg:province":"Auckland",
    "sg:tags":[
        "delicatessen",
        "-"
    ],
    "wof:name":"Peppercorn Deli",
    "wof:placetype":"venue"
},
  "geometry": {"coordinates":[174.768036,-36.845173],"type":"Point"}
}