{
  "type": "Feature",
  "properties": {
    "iso:country":"NZ",
    "sg:address":"Sophia St ",
    "sg:city":"Timaru",
    "sg:classifiers":[
        {
            "category":"Bars & Pubs",
            "subcategory":"Lounge",
            "type":"Food & Drink"
        }
    ],
    "sg:phone":"+64 3-684 3670",
    "sg:province":"Canterbury",
    "sg:tags":[
        "baker",
        "-"
    ],
    "wof:name":"Bread Basket The",
    "wof:placetype":"venue"
},
  "geometry": {"coordinates":[171.25,-44.394825],"type":"Point"}
}