{
  "type": "Feature",
  "properties": {
    "iso:country":"NZ",
    "sg:address":"272 Stafford St ",
    "sg:city":"Timaru",
    "sg:orig_category":"Shopping: Retail Stores: Cds, Cassettes And Records",
    "sg:phone":"+64 3-688 6491",
    "sg:province":"Canterbury",
    "wof:name":"Chapters & Verses Booksellers & Music",
    "wof:placetype":"venue"
},
  "geometry": {"coordinates":[171.251404,-44.394588],"type":"Point"}
}