{
  "type": "Feature",
  "properties": {
    "addr:full":"2 Greenstone Way Ohauiti  Tauranga Bay of Plenty",
    "addr:housenumber":"2",
    "addr:street":"Greenstone Way",
    "iso:country":"NZ",
    "sg:address":"2 Greenstone Way Ohauiti ",
    "sg:city":"Tauranga",
    "sg:classifiers":[
        {
            "category":"Utilities",
            "subcategory":"Refuse",
            "type":"Services"
        }
    ],
    "sg:phone":"+64 7-544 4215",
    "sg:province":"Bay of Plenty",
    "sg:tags":[
        "bin",
        "hire",
        "garden",
        "cleaning",
        "rubbish",
        "home"
    ],
    "wof:name":"Bin Boys",
    "wof:placetype":"venue"
},
  "geometry": {"coordinates":[176.15631099999999,-37.737389],"type":"Point"}
}