{
  "type": "Feature",
  "properties": {
    "addr:full":"Alfredton Rd R D 3  Eketahuna",
    "addr:housenumber":"3",
    "addr:street":"Alfredton Rd R D",
    "iso:country":"NZ",
    "sg:address":"Alfredton Rd R D 3 ",
    "sg:city":"Eketahuna",
    "sg:classifiers":[
        {
            "category":"Home & Garden",
            "subcategory":"Building Materials",
            "type":"Retail Goods"
        }
    ],
    "sg:phone":"+64 6-375 8034",
    "sg:tags":[
        "builder",
        "related"
    ],
    "wof:name":"Warren Walker",
    "wof:placetype":"venue"
},
  "geometry": {"coordinates":[175.70159899999999,-40.651649],"type":"Point"}
}