{
  "type": "Feature",
  "properties": {
    "addr:full":"Commercial St  Takaka",
    "addr:street":"Commercial St",
    "iso:country":"NZ",
    "sg:address":"Commercial St ",
    "sg:city":"Takaka",
    "sg:orig_category":"Shopping: Retail Stores: Books: Libraries",
    "sg:phone":"+64 3-525 9538",
    "wof:name":"Takaka Memorial Library",
    "wof:placetype":"venue"
},
  "geometry": {"coordinates":[172.80714399999999,-40.85276],"type":"Point"}
}