{
  "type": "Feature",
  "properties": {
    "addr:full":"Havelock  Palmerston North Manawatu-Wanganui",
    "iso:country":"NZ",
    "sg:address":"Havelock ",
    "sg:city":"Palmerston North",
    "sg:orig_category":"Farming: Agriculture: Agricultural Contractors",
    "sg:phone":"+64 25433913",
    "sg:province":"Manawatu-Wanganui",
    "wof:name":"Silage HB Ltd",
    "wof:placetype":"venue"
},
  "geometry": {"coordinates":[176.87951699999999,-39.669399],"type":"Point"}
}