{
  "type": "Feature",
  "properties": {
    "addr:full":"Unit 1/7 Newton Pl  Hamilton Auckland",
    "addr:housenumber":"unit 1 / 7",
    "addr:street":"Newton Pl",
    "iso:country":"NZ",
    "sg:address":"Unit 1/7 Newton Pl ",
    "sg:city":"Hamilton",
    "sg:classifiers":[
        {
            "category":"Building & Trades",
            "subcategory":"Electrical",
            "type":"Services"
        }
    ],
    "sg:phone":"+64 7-847 7900",
    "sg:province":"Auckland",
    "sg:tags":[
        "industrial",
        "refrigeration"
    ],
    "wof:name":"Doug Robinson Appliances Ltd",
    "wof:placetype":"venue"
},
  "geometry": {"coordinates":[-74.76312299999999,40.212112],"type":"Point"}
}