{
  "type": "Feature",
  "properties": {
    "addr:full":"109 Mount Aspiring Rd  Wanaka Otago",
    "addr:housenumber":"109",
    "addr:street":"Mount Aspiring Rd",
    "iso:country":"NZ",
    "sg:address":"109 Mount Aspiring Rd ",
    "sg:city":"Wanaka",
    "sg:classifiers":[
        {
            "category":"Restaurant",
            "type":"Food & Drink"
        }
    ],
    "sg:phone":"+64 800 688 688",
    "sg:province":"Otago",
    "sg:tags":[
        "wining",
        "dining"
    ],
    "sg:website":"http://www.wanakanz.com",
    "wof:name":"Wanaka Motor Inn",
    "wof:placetype":"venue"
},
  "geometry": {"coordinates":[169.13845800000001,-44.693981],"type":"Point"}
}