{
  "type": "Feature",
  "properties": {
    "iso:country":"NZ",
    "sg:address":"109 Mount Aspiring Rd ",
    "sg:city":"Wanaka",
    "sg:classifiers":[
        {
            "category":"Restaurant",
            "type":"Food & Drink"
        }
    ],
    "sg:phone":"+64 800 688 688",
    "sg:province":"Otago",
    "sg:tags":[
        "wining",
        "dining"
    ],
    "sg:website":"http://www.wanakanz.com",
    "wof:name":"Wanaka Motor Inn",
    "wof:placetype":"venue"
},
  "geometry": {"coordinates":[169.138458,-44.693981],"type":"Point"}
}