{
  "type": "Feature",
  "properties": {
    "iso:country":"NZ",
    "sg:address":"Ashworth St ",
    "sg:city":"Tokoroa",
    "sg:classifiers":[
        {
            "category":"Bars & Pubs",
            "subcategory":"Lounge",
            "type":"Food & Drink"
        }
    ],
    "sg:phone":"+64 7-886 4627",
    "sg:tags":[
        "baker",
        "-"
    ],
    "wof:name":"The Bakehouse",
    "wof:placetype":"venue"
},
  "geometry": {"coordinates":[175.872467,-38.215569],"type":"Point"}
}