{
  "type": "Feature",
  "properties": {
    "addr:full":"78 Kuratawhiti St  Greytown",
    "addr:housenumber":"78",
    "addr:street":"Kuratawhiti St",
    "iso:country":"NZ",
    "sg:address":"78 Kuratawhiti St ",
    "sg:city":"Greytown",
    "sg:classifiers":[
        {
            "category":"Travel",
            "subcategory":"Bed & Breakfast",
            "type":"Entertainment"
        }
    ],
    "sg:phone":"+64 6-304 8588",
    "sg:tags":[
        "tourism",
        "accommodation"
    ],
    "wof:name":"Ambers Homestay",
    "wof:placetype":"venue"
},
  "geometry": {"coordinates":[175.46092200000001,-41.077442],"type":"Point"}
}