{
  "type": "Feature",
  "properties": {
    "iso:country":"NZ",
    "sg:address":"56 Manuka St ",
    "sg:city":"Taupo",
    "sg:orig_category":"Transport: Transportation: Courier Services",
    "sg:phone":"+64 7-378 8280",
    "sg:province":"Waikato",
    "wof:name":"Midland Freighters Limited",
    "wof:placetype":"venue"
},
  "geometry": {"coordinates":[176.106461,-38.688614],"type":"Point"}
}