{
  "type": "Feature",
  "properties": {
    "addr:full":"188 Songer St Stoke  Nelson Nelson",
    "addr:housenumber":"188",
    "addr:street":"Songer St",
    "iso:country":"NZ",
    "sg:address":"188 Songer St Stoke ",
    "sg:city":"Nelson",
    "sg:classifiers":[
        {
            "category":"Social Services",
            "subcategory":"Retirement Home",
            "type":"Services"
        }
    ],
    "sg:phone":"+64 3-547 9703",
    "sg:province":"Nelson",
    "sg:tags":[
        "elderly",
        "convalescent",
        "garden",
        "rest",
        "care"
    ],
    "wof:name":"Omaio Village",
    "wof:placetype":"venue"
},
  "geometry": {"coordinates":[173.23129299999999,-41.312386],"type":"Point"}
}