{
  "type": "Feature",
  "properties": {
    "iso:country":"NZ",
    "sg:address":"Main Rd ",
    "sg:city":"Katikati",
    "sg:orig_category":"Clothing And Fabric: Clothing: Women'S Fashions",
    "sg:phone":"+64 7-549 0168",
    "wof:name":"Harts Fashions",
    "wof:placetype":"venue"
},
  "geometry": {"coordinates":[175.918076,-37.551952],"type":"Point"}
}