{
  "type": "Feature",
  "properties": {
    "addr:full":"177 Chester St East  Christchurch Canterbury",
    "addr:housenumber":"177",
    "addr:street":"Chester St",
    "iso:country":"NZ",
    "sg:address":"177 Chester St East ",
    "sg:city":"Christchurch",
    "sg:classifiers":[
        {
            "category":"Sports & Exercise",
            "subcategory":"Sports Center",
            "type":"Entertainment"
        }
    ],
    "sg:phone":"+64 3-366 0144",
    "sg:province":"Canterbury",
    "sg:tags":[
        "sporting",
        "sports",
        "-",
        "leisure",
        "facility"
    ],
    "wof:name":"Crichton Cobbers Youth Club Inc",
    "wof:placetype":"venue"
},
  "geometry": {"coordinates":[-76.537834,37.605659],"type":"Point"}
}