{
  "type": "Feature",
  "properties": {
    "addr:full":"Jipcho Rd Sockburn PO Box 8295  Christchurch Canterbury",
    "addr:housenumber":"po box",
    "addr:postcode":"8295",
    "addr:street":"Jipcho Rd",
    "iso:country":"NZ",
    "sg:address":"Jipcho Rd Sockburn PO Box 8295 ",
    "sg:city":"Christchurch",
    "sg:classifiers":[
        {
            "category":"Education",
            "subcategory":"Special Training",
            "type":"Public Place"
        }
    ],
    "sg:phone":"+64 3-343 3454",
    "sg:province":"Canterbury",
    "sg:tags":[
        "testing",
        "driver",
        "licencing",
        "/"
    ],
    "wof:name":"Vehicle Testing NZ Ltd",
    "wof:placetype":"venue"
},
  "geometry": {"coordinates":[172.637314,-43.531315],"type":"Point"}
}