{
  "type": "Feature",
  "properties": {
    "iso:country":"NZ",
    "sg:address":"56 Broadway ",
    "sg:city":"Kaikohe",
    "sg:orig_category":"Farming: Machinery: Tractors",
    "sg:phone":"+64 9-405 2269",
    "sg:province":"Manawatu-Wanganui",
    "wof:name":"Dave Boyt Machinery Services Ltd",
    "wof:placetype":"venue"
},
  "geometry": {"coordinates":[173.801071,-35.407009],"type":"Point"}
}