{
  "type": "Feature",
  "properties": {
    "addr:full":"Braeside Ave  Tokoroa Otago",
    "addr:street":"Braeside Ave",
    "iso:country":"NZ",
    "sg:address":"Braeside Ave ",
    "sg:city":"Tokoroa",
    "sg:classifiers":[
        {
            "category":"Health Services",
            "subcategory":"Nursing And Care Facility",
            "type":"Services"
        }
    ],
    "sg:phone":"+64 7-886 6339",
    "sg:province":"Otago",
    "sg:tags":[
        "services",
        "rehabilitation",
        "beauty",
        "social"
    ],
    "wof:name":"Oasis House",
    "wof:placetype":"venue"
},
  "geometry": {"coordinates":[175.8759,-38.227699],"type":"Point"}
}