{
  "type": "Feature",
  "properties": {
    "iso:country":"NZ",
    "sg:address":"Roscommon Rd Weymouth ",
    "sg:city":"Auckland",
    "sg:classifiers":[
        {
            "category":"Shopping Center",
            "type":"Public Place"
        }
    ],
    "sg:phone":"+64 9-267 5736",
    "sg:province":"Auckland",
    "sg:tags":[
        "mall",
        "retail",
        "stores"
    ],
    "wof:name":"Clendon Shopping Centre",
    "wof:placetype":"venue"
},
  "geometry": {"coordinates":[174.863724,-37.04583],"type":"Point"}
}