{
  "type": "Feature",
  "properties": {
    "addr:full":"PO Box 21614 Henderson  Auckland Auckland",
    "addr:housenumber":"po box 21614",
    "iso:country":"NZ",
    "sg:address":"PO Box 21614 Henderson ",
    "sg:city":"Auckland",
    "sg:classifiers":[
        {
            "category":"Shopping",
            "subcategory":"Stationery & Office Supplies",
            "type":"Retail Goods"
        }
    ],
    "sg:phone":"+64 9-828 7742",
    "sg:province":"Auckland",
    "sg:tags":[
        "supplies",
        "educational",
        "material",
        "education",
        "training"
    ],
    "wof:name":"Butterflies - Resources for Young Learners",
    "wof:placetype":"venue"
},
  "geometry": {"coordinates":[174.63294999999999,-36.877289],"type":"Point"}
}