{
  "type": "Feature",
  "properties": {
    "addr:full":"16a Bell St  Wanganui Manawatu-Wanganui",
    "addr:housenumber":"16a",
    "addr:street":"Bell St",
    "iso:country":"NZ",
    "sg:address":"16a Bell St ",
    "sg:city":"Wanganui",
    "sg:orig_category":"Farming: Forestry: Forestry Consultants",
    "sg:phone":"+64 6-349 0468",
    "sg:province":"Manawatu-Wanganui",
    "wof:name":"Rayonier New Zealand Ltd",
    "wof:placetype":"venue"
},
  "geometry": {"coordinates":[175.054596,-39.930241],"type":"Point"}
}