{
  "type": "Feature",
  "properties": {
    "addr:full":"1186 Sandspit Rd  Warkworth Auckland",
    "addr:housenumber":"1186",
    "addr:street":"Sandspit Rd",
    "iso:country":"NZ",
    "sg:address":"1186 Sandspit Rd ",
    "sg:city":"Warkworth",
    "sg:classifiers":[
        {
            "category":"Shopping",
            "subcategory":"Crafts & Fabrics",
            "type":"Retail Goods"
        }
    ],
    "sg:phone":"+64 9-425 9441",
    "sg:province":"Auckland",
    "sg:tags":[
        "sport",
        "art",
        "leisure",
        "hobbies"
    ],
    "wof:name":"Kiwi Artz",
    "wof:placetype":"venue"
},
  "geometry": {"coordinates":[174.66511499999999,-36.401466],"type":"Point"}
}