{
  "type": "Feature",
  "properties": {
    "iso:country":"NZ",
    "sg:address":"Seaview Roundabout Lower ",
    "sg:city":"Hutt",
    "sg:orig_category":"Industrial: Instruments",
    "sg:phone":"+64 4-568 7938",
    "sg:province":"Wellington",
    "wof:name":"Shardlow Auto Electrical Ltd",
    "wof:placetype":"venue"
},
  "geometry": {"coordinates":[174.899567,-41.246059],"type":"Point"}
}