{
  "type": "Feature",
  "properties": {
    "addr:full":"6-10 Vivian St  Wellington Wellington",
    "addr:housenumber":"6-10",
    "addr:street":"Vivian St",
    "iso:country":"NZ",
    "sg:address":"6-10 Vivian St ",
    "sg:city":"Wellington",
    "sg:classifiers":[
        {
            "category":"Home & Garden",
            "subcategory":"Building Materials",
            "type":"Retail Goods"
        }
    ],
    "sg:phone":"+64 4-385 9485",
    "sg:province":"Wellington",
    "sg:tags":[
        "door",
        "fitting",
        "fittings"
    ],
    "wof:name":"G A Lang & Co",
    "wof:placetype":"venue"
},
  "geometry": {"coordinates":[174.781509,-41.296795],"type":"Point"}
}