{
  "type": "Feature",
  "properties": {
    "addr:full":"36 Curries Rd PO Box 19646  Christchurch Canterbury",
    "addr:housenumber":"36;box 19646",
    "addr:street":"Curries Rd;Christchurch",
    "iso:country":"NZ",
    "sg:address":"36 Curries Rd PO Box 19646 ",
    "sg:city":"Christchurch",
    "sg:orig_category":"Industrial: Instruments",
    "sg:phone":"+64 800 662 274",
    "sg:province":"Canterbury",
    "wof:name":"Marconi Commerce Systems (NZ) Ltd",
    "wof:placetype":"venue"
},
  "geometry": {"coordinates":[-76.537834,37.605659],"type":"Point"}
}