{
  "type": "Feature",
  "properties": {
    "addr:full":"3 Edward St Richmond  Nelson Nelson",
    "addr:housenumber":"3",
    "addr:street":"Edward St",
    "iso:country":"NZ",
    "sg:address":"3 Edward St Richmond ",
    "sg:city":"Nelson",
    "sg:classifiers":[
        {
            "category":"Retail",
            "subcategory":"Driving School",
            "type":"Services"
        }
    ],
    "sg:phone":"+64 3-544 9090",
    "sg:province":"Nelson",
    "sg:tags":[
        "training",
        "education",
        "driver"
    ],
    "wof:name":"Drive Alive",
    "wof:placetype":"venue"
},
  "geometry": {"coordinates":[-121.765488,39.553471],"type":"Point"}
}