{
  "type": "Feature",
  "properties": {
    "iso:country":"NZ",
    "sg:address":"P O Box 84001 Westgate ",
    "sg:city":"Auckland",
    "sg:classifiers":[
        {
            "category":"Shopping Center",
            "type":"Public Place"
        }
    ],
    "sg:phone":"+64 9-831 0200",
    "sg:province":"Otago",
    "sg:tags":[
        "mall",
        "retail",
        "stores"
    ],
    "wof:name":"Westgate Shopping Centre Management Office",
    "wof:placetype":"venue"
},
  "geometry": {"coordinates":[-119.104584,36.59774],"type":"Point"}
}