{
  "type": "Feature",
  "properties": {
    "iso:country":"NZ",
    "sg:address":"20 Maisey Pl ",
    "sg:city":"Rotorua",
    "sg:classifiers":[
        {
            "category":"Manufacturing",
            "subcategory":"Glass & Minerals",
            "type":"Manufacturing & Wholesale Goods"
        }
    ],
    "sg:phone":"+64 7-347 8520",
    "sg:province":"Bay of Plenty",
    "sg:tags":[
        "asbestos",
        "raw",
        "industrial",
        "materials"
    ],
    "sg:website":"http://www.yellowpages.co.nz/for/insulation/dp739.html",
    "wof:name":"Best Insulation Co Ltd",
    "wof:placetype":"venue"
},
  "geometry": {"coordinates":[176.227066,-38.120762],"type":"Point"}
}