{
  "type": "Feature",
  "properties": {
    "iso:country":"NZ",
    "sg:address":"43 The Boulevard ",
    "sg:city":"Hamilton",
    "sg:classifiers":[
        {
            "category":"Home & Garden",
            "subcategory":"Building Materials",
            "type":"Retail Goods"
        }
    ],
    "sg:phone":"+64 7-849 2845",
    "sg:province":"Auckland",
    "sg:tags":[
        "fittings",
        "staircase",
        "handrail"
    ],
    "wof:name":"Truline Stairways Ltd",
    "wof:placetype":"venue"
},
  "geometry": {"coordinates":[-70.88813,42.624191],"type":"Point"}
}