{
  "type": "Feature",
  "properties": {
    "iso:country":"NZ",
    "sg:address":"2nd Floor 27 Gillies Ave Newmarket ",
    "sg:city":"Auckland",
    "sg:classifiers":[
        {
            "category":"Landmark",
            "subcategory":"Tourist Information",
            "type":"Public Place"
        }
    ],
    "sg:phone":"+64 9-520 5295",
    "sg:province":"Auckland",
    "sg:tags":[
        "services",
        "travel",
        "tourism"
    ],
    "wof:name":"Women's Health Action",
    "wof:placetype":"venue"
},
  "geometry": {"coordinates":[174.77441400000001,-36.871193],"type":"Point"}
}