{
  "type": "Feature",
  "properties": {
    "iso:country":"NZ",
    "sg:address":"57 Firth St Drury ",
    "sg:city":"Auckland",
    "sg:classifiers":[
        {
            "category":"Fast Food",
            "type":"Food & Drink"
        }
    ],
    "sg:phone":"+64 9-294 8024",
    "sg:province":"Auckland",
    "sg:tags":[
        "seafood",
        "sea"
    ],
    "wof:name":"Sea Products (1998) Ltd",
    "wof:placetype":"venue"
},
  "geometry": {"coordinates":[174.947754,-37.101425],"type":"Point"}
}