{
  "type": "Feature",
  "properties": {
    "addr:full":"104 Glenpark Ave Maryhill  Dunedin Otago",
    "addr:housenumber":"104",
    "addr:street":"Glenpark Ave",
    "iso:country":"NZ",
    "sg:address":"104 Glenpark Ave Maryhill ",
    "sg:city":"Dunedin",
    "sg:classifiers":[
        {
            "category":"Arena",
            "subcategory":"Sports Club",
            "type":"Entertainment"
        }
    ],
    "sg:phone":"+64 3-453 0449",
    "sg:province":"Otago",
    "sg:tags":[
        "goods",
        "shopping",
        "sporting",
        "equipment",
        "retailers",
        "hire-"
    ],
    "wof:name":"Lomacs Hire Service",
    "wof:placetype":"venue"
},
  "geometry": {"coordinates":[170.502701,-45.859348],"type":"Point"}
}