{
  "type": "Feature",
  "properties": {
    "addr:full":"Cnr Fenton & Hinemoa Sts Rotorua Bay of Plenty",
    "addr:street":"Cnr",
    "iso:country":"NZ",
    "sg:address":"Cnr Fenton & Hinemoa Sts",
    "sg:city":"Rotorua",
    "sg:classifiers":[
        {
            "category":"Banks & Credit Unions",
            "subcategory":"Bank",
            "type":"Services"
        }
    ],
    "sg:phone":"+64 7381074",
    "sg:province":"Bay of Plenty",
    "wof:name":"Bank of New Zealand",
    "wof:placetype":"venue"
},
  "geometry": {"coordinates":[175.88891599999999,-40.60202],"type":"Point"}
}