{
  "type": "Feature",
  "properties": {
    "iso:country":"NZ",
    "sg:address":"14 Herschell St ",
    "sg:city":"Napier",
    "sg:orig_category":"Travel And Tourism: Accommodation: Backpackers",
    "sg:phone":"+64 6-833 7990",
    "sg:province":"Hawke's Bay",
    "wof:name":"Archie's Bunker",
    "wof:placetype":"venue"
},
  "geometry": {"coordinates":[-80.588562,38.790821],"type":"Point"}
}