{
  "type": "Feature",
  "properties": {
    "addr:full":"Braziers Building 23 Amohia St  Paraparaumu Wellington",
    "addr:housenumber":"23",
    "addr:street":"Amohia St",
    "iso:country":"NZ",
    "sg:address":"Braziers Building 23 Amohia St ",
    "sg:city":"Paraparaumu",
    "sg:orig_category":"Clothing And Fabric: Clothing: Tailors",
    "sg:phone":"+64 4-902 9991",
    "sg:province":"Wellington",
    "wof:name":"Executive Alteration Tailors",
    "wof:placetype":"venue"
},
  "geometry": {"coordinates":[175.00799599999999,-40.910465],"type":"Point"}
}