{
  "type": "Feature",
  "properties": {
    "iso:country":"NZ",
    "sg:address":"PO Box 40253 Upper ",
    "sg:city":"Hutt",
    "sg:orig_category":"Industrial: Abrasives: Water Blasting",
    "sg:phone":"+64 4-526 3202",
    "sg:province":"Wellington",
    "wof:name":"Certified Commercial Cleaners Ltd",
    "wof:placetype":"venue"
},
  "geometry": {"coordinates":[175.07037399999999,-41.124439],"type":"Point"}
}