{
  "type": "Feature",
  "properties": {
    "iso:country":"NZ",
    "sg:address":"Level 6, 186-190 Willis St ",
    "sg:city":"Wellington",
    "sg:classifiers":[
        {
            "category":"Shopping",
            "subcategory":"Beauty & Cosmetics",
            "type":"Retail Goods"
        }
    ],
    "sg:phone":"+64 4-801 7642",
    "sg:province":"Wellington",
    "sg:tags":[
        "health",
        "perfumery"
    ],
    "wof:name":"Face to Face",
    "wof:placetype":"venue"
},
  "geometry": {"coordinates":[-100.206306,34.858204],"type":"Point"}
}