{
  "type": "Feature",
  "properties": {
    "iso:country":"NZ",
    "sg:address":"State Hwy 1 Oakleigh ",
    "sg:city":"Whangarei",
    "sg:classifiers":[
        {
            "category":"Home & Garden",
            "subcategory":"Garden Supply",
            "type":"Retail Goods"
        }
    ],
    "sg:phone":"+64 9-432 2542",
    "sg:province":"Northland",
    "sg:tags":[
        "products",
        "nursery",
        "gardening"
    ],
    "wof:name":"Oakleigh Nurseries Palms & Cycads",
    "wof:placetype":"venue"
},
  "geometry": {"coordinates":[174.320526,-35.725399],"type":"Point"}
}