{
  "type": "Feature",
  "properties": {
    "addr:full":"PO Box 251  Picton Marlborough",
    "addr:housenumber":"po",
    "addr:street":"Box 251",
    "iso:country":"NZ",
    "sg:address":"PO Box 251 ",
    "sg:city":"Picton",
    "sg:classifiers":[
        {
            "category":"Professional",
            "subcategory":"Art Services",
            "type":"Services"
        }
    ],
    "sg:phone":"+64 25331575",
    "sg:province":"Marlborough",
    "sg:tags":[
        "personal",
        "photographer",
        "services",
        "garden",
        "home"
    ],
    "wof:name":"Paul Palmer Photographer",
    "wof:placetype":"venue"
},
  "geometry": {"coordinates":[174.00427199999999,-41.294796],"type":"Point"}
}