{
  "type": "Feature",
  "properties": {
    "iso:country":"NZ",
    "sg:address":"156 B Rockinghorse Rd Southshore ",
    "sg:city":"Christchurch",
    "sg:classifiers":[
        {
            "category":"Education",
            "subcategory":"Special Training",
            "type":"Public Place"
        }
    ],
    "sg:phone":"+64 3-388 7216",
    "sg:province":"Canterbury",
    "sg:tags":[
        "school",
        "swimming"
    ],
    "wof:name":"Dalton D H & M",
    "wof:placetype":"venue"
},
  "geometry": {"coordinates":[172.748383,-43.552235],"type":"Point"}
}