{
  "type": "Feature",
  "properties": {
    "addr:full":"15 Pitt St  Wanganui Manawatu-Wanganui",
    "addr:housenumber":"15",
    "addr:street":"Pitt St",
    "iso:country":"NZ",
    "sg:address":"15 Pitt St ",
    "sg:city":"Wanganui",
    "sg:orig_category":"Health And Beauty: Specialists: Osteopaths",
    "sg:phone":"+64 6-345 9394",
    "sg:province":"Manawatu-Wanganui",
    "wof:name":"Brooke Nigel & Amanda",
    "wof:placetype":"venue"
},
  "geometry": {"coordinates":[175.04994199999999,-39.922173],"type":"Point"}
}