{
  "type": "Feature",
  "properties": {
    "iso:country":"NZ",
    "sg:address":"Level 1 59-73 Adelaide Rd ",
    "sg:city":"Wellington",
    "sg:classifiers":[
        {
            "category":"Arena",
            "subcategory":"Sports Club",
            "type":"Entertainment"
        }
    ],
    "sg:phone":"+64 4-939 3616",
    "sg:province":"Wellington",
    "sg:tags":[
        "arts",
        "writer",
        "leisure",
        "author"
    ],
    "wof:name":"WriteUp",
    "wof:placetype":"venue"
},
  "geometry": {"coordinates":[-85.914917,33.839149],"type":"Point"}
}