{
  "type": "Feature",
  "properties": {
    "iso:country":"NZ",
    "sg:address":"62 Marine Pde ",
    "sg:city":"Wairoa",
    "sg:classifiers":[
        {
            "category":"Retail",
            "subcategory":"Funeral Services",
            "type":"Services"
        }
    ],
    "sg:phone":"+64 6-838 7606",
    "sg:tags":[
        "arrangements",
        "arrangement"
    ],
    "wof:name":"Pickering A S Funeral Director",
    "wof:placetype":"venue"
},
  "geometry": {"coordinates":[177.433502,-39.034782],"type":"Point"}
}