{
  "type": "Feature",
  "properties": {
    "addr:full":"12 Richards Ave Papanui  Christchurch Canterbury",
    "addr:housenumber":"12",
    "addr:street":"Richards Ave",
    "iso:country":"NZ",
    "sg:address":"12 Richards Ave Papanui ",
    "sg:city":"Christchurch",
    "sg:orig_category":"Home And Garden: Gardening: Services: Garden Maintenance",
    "sg:phone":"+64 25454520",
    "sg:province":"Canterbury",
    "wof:name":"Mr Garden",
    "wof:placetype":"venue"
},
  "geometry": {"coordinates":[172.59581,-43.493832],"type":"Point"}
}