{
  "type": "Feature",
  "properties": {
    "addr:full":"101 B Gordon Rd Mosgiel  Dunedin Otago",
    "addr:housenumber":"101 b",
    "addr:street":"Gordon Rd",
    "iso:country":"NZ",
    "sg:address":"101 B Gordon Rd Mosgiel ",
    "sg:city":"Dunedin",
    "sg:orig_category":"Food And Drink: Catering: Caterers",
    "sg:phone":"+64 3-489 7752",
    "sg:province":"Otago",
    "wof:name":"Monte Carlo Milk Bar",
    "wof:placetype":"venue"
},
  "geometry": {"coordinates":[170.34968599999999,-45.877125],"type":"Point"}
}