{
  "type": "Feature",
  "properties": {
    "addr:full":"239 State Highway 2 Clive  Hastings Hawke's Bay",
    "addr:housenumber":"239",
    "addr:street":"State Highway 2",
    "iso:country":"NZ",
    "sg:address":"239 State Highway 2 Clive ",
    "sg:city":"Hastings",
    "sg:classifiers":[
        {
            "category":"Personal",
            "type":"Services"
        }
    ],
    "sg:phone":"+64 6-870 1004",
    "sg:province":"Hawke's Bay",
    "sg:tags":[
        "services",
        "home",
        "garden",
        "counselling"
    ],
    "wof:name":"Kara Duncan-Hewitt",
    "wof:placetype":"venue"
},
  "geometry": {"coordinates":[-78.71354700000001,40.663212],"type":"Point"}
}