{
  "type": "Feature",
  "properties": {
    "addr:full":"1306 Amohia St  Rotorua Bay of Plenty",
    "addr:housenumber":"1306",
    "addr:street":"Amohia St",
    "iso:country":"NZ",
    "sg:address":"1306 Amohia St ",
    "sg:city":"Rotorua",
    "sg:classifiers":[
        {
            "category":"Sports & Exercise",
            "subcategory":"Playing Field",
            "type":"Entertainment"
        }
    ],
    "sg:phone":"+64 7-347 0379",
    "sg:province":"Bay of Plenty",
    "sg:tags":[
        "hobby",
        "hobbies",
        "leisure",
        "supply"
    ],
    "wof:name":"Kevin's Hobby Supplies",
    "wof:placetype":"venue"
},
  "geometry": {"coordinates":[176.24903900000001,-38.139507],"type":"Point"}
}