{
  "type": "Feature",
  "properties": {
    "addr:full":"55 Kerwyn Ave East Tamaki  Auckland Auckland",
    "addr:housenumber":"55",
    "addr:street":"Kerwyn Ave",
    "iso:country":"NZ",
    "sg:address":"55 Kerwyn Ave East Tamaki ",
    "sg:city":"Auckland",
    "sg:orig_category":"Industrial: Equipment And Machinery: Crushers",
    "sg:phone":"+64 9-274 3811",
    "sg:province":"Auckland",
    "wof:name":"Process Machinery Ltd",
    "wof:placetype":"venue"
},
  "geometry": {"coordinates":[174.88201900000001,-36.945732],"type":"Point"}
}