{
  "type": "Feature",
  "properties": {
    "iso:country":"NZ",
    "sg:address":"11 Edinburgh St K'rd Auckland City ",
    "sg:city":"Auckland",
    "sg:classifiers":[
        {
            "category":"Banks & Credit Unions",
            "subcategory":"Investment Brokerage",
            "type":"Services"
        }
    ],
    "sg:phone":"+64 9-358 5353",
    "sg:province":"Auckland",
    "sg:tags":[
        "television",
        "production",
        "broadcasting"
    ],
    "wof:name":"TVZOO creative",
    "wof:placetype":"venue"
},
  "geometry": {"coordinates":[174.77041600000001,-36.884109],"type":"Point"}
}