{
  "type": "Feature",
  "properties": {
    "addr:full":"4356 Highway 26 Waihou Township Te  Aroha Waikato",
    "addr:housenumber":"4356",
    "addr:street":"Highway 26 Waihou Township Te Aroha",
    "iso:country":"NZ",
    "sg:address":"4356 Highway 26 Waihou Township Te ",
    "sg:city":"Aroha",
    "sg:orig_category":"Home And Garden: Gardening: Products: Aquatic Gardens",
    "sg:phone":"+64 7-884 7033",
    "sg:province":"Waikato",
    "wof:name":"Amazonia",
    "wof:placetype":"venue"
},
  "geometry": {"coordinates":[175.674713,-37.57375],"type":"Point"}
}