{
  "type": "Feature",
  "properties": {
    "addr:full":"228 Wilks Rd Dairy Flat Hibiscus  Hibiscus Coast Auckland",
    "addr:housenumber":"228;hibiscus",
    "addr:street":"Wilks Rd;Hibiscus",
    "iso:country":"NZ",
    "sg:address":"228 Wilks Rd Dairy Flat Hibiscus ",
    "sg:city":"Hibiscus Coast",
    "sg:classifiers":[
        {
            "category":"Wholesale",
            "subcategory":"Meat",
            "type":"Manufacturing & Wholesale Goods"
        }
    ],
    "sg:phone":"+64 9-427 8497",
    "sg:province":"Auckland",
    "sg:tags":[
        "food",
        "drink",
        "meats",
        "slaughtering"
    ],
    "wof:name":"Country Meat Processors Ltd",
    "wof:placetype":"venue"
},
  "geometry": {"coordinates":[174.664368,-36.651516],"type":"Point"}
}