{
  "type": "Feature",
  "properties": {
    "iso:country":"NZ",
    "sg:address":"26 Days Rd ",
    "sg:city":"Lyttelton",
    "sg:classifiers":[
        {
            "category":"Coffee & Tea",
            "type":"Food & Drink"
        }
    ],
    "sg:phone":"+64 21 750 555",
    "sg:tags":[
        "merchant"
    ],
    "wof:name":"E.s.p Espresso Service Person",
    "wof:placetype":"venue"
},
  "geometry": {"coordinates":[172.723373,-43.597443],"type":"Point"}
}