{
  "type": "Feature",
  "properties": {
    "addr:full":"10 D Seaview Rd New  Plymouth Taranaki",
    "addr:housenumber":"10 d",
    "addr:street":"Seaview Rd",
    "iso:country":"NZ",
    "sg:address":"10 D Seaview Rd New ",
    "sg:city":"Plymouth",
    "sg:orig_category":"Automotive: General Services: Engine Importers/Dealers",
    "sg:phone":"+64 6-751 1455",
    "sg:province":"Taranaki",
    "wof:name":"Eagle Automotive Ltd",
    "wof:placetype":"venue"
},
  "geometry": {"coordinates":[-116.81972500000001,43.97221],"type":"Point"}
}