{
  "type": "Feature",
  "properties": {
    "iso:country":"NZ",
    "sg:address":"18 Turnbull St ",
    "sg:city":"Timaru",
    "sg:classifiers":[
        {
            "category":"Manufacturing",
            "subcategory":"Metals",
            "type":"Manufacturing & Wholesale Goods"
        }
    ],
    "sg:phone":"+64 3-688 6364",
    "sg:province":"Canterbury",
    "sg:tags":[
        "-",
        "engineering",
        "industrial",
        "sheet",
        "engineer"
    ],
    "wof:name":"Southgate A F & Sons",
    "wof:placetype":"venue"
},
  "geometry": {"coordinates":[171.25706500000001,-44.399345],"type":"Point"}
}