{
  "type": "Feature",
  "properties": {
    "addr:full":"PO Box 633  Taupo Waikato",
    "addr:housenumber":"po;633",
    "addr:street":"Box",
    "iso:country":"NZ",
    "sg:address":"PO Box 633 ",
    "sg:city":"Taupo",
    "sg:classifiers":[
        {
            "category":"Building & Trades",
            "subcategory":"Pest Control",
            "type":"Services"
        }
    ],
    "sg:phone":"+64 7-378 8225",
    "sg:province":"Waikato",
    "sg:tags":[
        "home",
        "garden"
    ],
    "wof:name":"Jae Pest Control Services",
    "wof:placetype":"venue"
},
  "geometry": {"coordinates":[176.084351,-38.689285],"type":"Point"}
}