{
  "type": "Feature",
  "properties": {
    "iso:country":"NZ",
    "sg:address":"913 St Aubyn St East ",
    "sg:city":"Hastings",
    "sg:classifiers":[
        {
            "category":"Ice Cream",
            "type":"Food & Drink"
        }
    ],
    "sg:phone":"+64 6-876 8105",
    "sg:province":"Hawke's Bay",
    "sg:website":"http://www.vidal.co.nz",
    "wof:name":"Vidal Estate Restaurant & Wine Shop",
    "wof:placetype":"venue"
},
  "geometry": {"coordinates":[-81.508163,29.711214],"type":"Point"}
}