{
  "type": "Feature",
  "properties": {
    "iso:country":"NZ",
    "sg:address":"170 Queen St ",
    "sg:city":"Masterton",
    "sg:orig_category":"Shopping: Retail Stores: Florists",
    "sg:phone":"+64 6-377 0487",
    "sg:province":"Wellington",
    "wof:name":"La Fleure Floriste",
    "wof:placetype":"venue"
},
  "geometry": {"coordinates":[175.66030900000001,-40.950481],"type":"Point"}
}