{
  "type": "Feature",
  "properties": {
    "iso:country":"NZ",
    "sg:address":"30 Karaka St Newton ",
    "sg:city":"Auckland",
    "sg:classifiers":[
        {
            "category":"Sports & Exercise",
            "subcategory":"Tennis Court",
            "type":"Entertainment"
        }
    ],
    "sg:phone":"+64 9-309 4922",
    "sg:province":"Auckland",
    "sg:tags":[
        "hobby",
        "leisure"
    ],
    "wof:name":"Labtec Photographic Processing Ltd",
    "wof:placetype":"venue"
},
  "geometry": {"coordinates":[174.758698,-36.861858],"type":"Point"}
}