{
  "type": "Feature",
  "properties": {
    "iso:country":"NZ",
    "sg:address":"226 Wainui Rd Silverdale Hibiscus ",
    "sg:city":"Hibiscus Coast",
    "sg:orig_category":"Home And Garden: Children",
    "sg:phone":"+64 9-426 7140",
    "sg:province":"Auckland",
    "sg:website":"http://www.danishhouse.co.nz",
    "wof:name":"DANISH HOUSE",
    "wof:placetype":"venue"
},
  "geometry": {"coordinates":[174.664856,-36.607853],"type":"Point"}
}