{
  "type": "Feature",
  "properties": {
    "addr:full":"73 C Greenmount Dve East Tamaki  Auckland Auckland",
    "addr:housenumber":"73 c",
    "addr:street":"Greenmount Dve",
    "iso:country":"NZ",
    "sg:address":"73 C Greenmount Dve East Tamaki ",
    "sg:city":"Auckland",
    "sg:orig_category":"Transport: Boats And Marine: Products: Marine Engines",
    "sg:phone":"+64 9-274 4305",
    "sg:province":"Auckland",
    "wof:name":"Volpower NZ Ltd",
    "wof:placetype":"venue"
},
  "geometry": {"coordinates":[174.901917,-36.929539],"type":"Point"}
}