{
  "type": "Feature",
  "properties": {
    "iso:country":"NZ",
    "sg:address":"Level 13, AXA Centre 80 The Terrace ",
    "sg:city":"Wellington",
    "sg:classifiers":[
        {
            "category":"Banks & Credit Unions",
            "subcategory":"Financial Services",
            "type":"Services"
        }
    ],
    "sg:phone":"+64 4-385 2162",
    "sg:province":"Waikato",
    "sg:tags":[
        "personal",
        "-",
        "finance",
        "software"
    ],
    "wof:name":"Grant Thornton",
    "wof:placetype":"venue"
},
  "geometry": {"coordinates":[-100.223625,34.851154],"type":"Point"}
}