{
  "type": "Feature",
  "properties": {
    "iso:country":"NZ",
    "sg:address":"9 Veronica St New Lynn ",
    "sg:city":"Auckland",
    "sg:classifiers":[
        {
            "category":"Education",
            "subcategory":"Dance Studio",
            "type":"Public Place"
        }
    ],
    "sg:phone":"+64 9-817 3313",
    "sg:province":"Auckland",
    "sg:tags":[
        "school",
        "dancing",
        "-",
        "leisure",
        "sports",
        "sport"
    ],
    "wof:name":"Tops Dance Studio",
    "wof:placetype":"venue"
},
  "geometry": {"coordinates":[174.68826300000001,-36.9076],"type":"Point"}
}