{
  "type": "Feature",
  "properties": {
    "addr:full":"19 Cooneys Dve  Tauranga Bay of Plenty",
    "addr:housenumber":"19",
    "addr:street":"Cooneys Dve Tauranga",
    "iso:country":"NZ",
    "sg:address":"19 Cooneys Dve ",
    "sg:city":"Tauranga",
    "sg:orig_category":"Automotive: Parts And Supplies: Windscreens",
    "sg:phone":"+64 800 158 821",
    "sg:province":"Bay of Plenty",
    "wof:name":"Resin Weld",
    "wof:placetype":"venue"
},
  "geometry": {"coordinates":[176.144745,-37.703156],"type":"Point"}
}