{
  "type": "Feature",
  "properties": {
    "iso:country":"NZ",
    "sg:address":"50 Sommerville Rd Howick ",
    "sg:city":"Auckland",
    "sg:classifiers":[
        {
            "category":"Shopping",
            "subcategory":"Bridal",
            "type":"Retail Goods"
        }
    ],
    "sg:phone":"+64 9-537 3793",
    "sg:province":"Auckland",
    "sg:tags":[
        "arrangements",
        "wear",
        "wedding"
    ],
    "wof:name":"Bridal Elegance",
    "wof:placetype":"venue"
},
  "geometry": {"coordinates":[174.916946,-36.894379],"type":"Point"}
}