{
  "type": "Feature",
  "properties": {
    "addr:full":"43 Tui Rd Papatoetoe  Auckland Auckland",
    "addr:housenumber":"43",
    "addr:street":"Tui Rd",
    "iso:country":"NZ",
    "sg:address":"43 Tui Rd Papatoetoe ",
    "sg:city":"Auckland",
    "sg:classifiers":[
        {
            "category":"Health Services",
            "subcategory":"Dentist",
            "type":"Services"
        }
    ],
    "sg:phone":"+64 9-278 5819",
    "sg:province":"Auckland",
    "sg:tags":[
        "dental",
        "beauty"
    ],
    "wof:name":"Papatoetoe K J M Pegler",
    "wof:placetype":"venue"
},
  "geometry": {"coordinates":[174.866165,-36.973],"type":"Point"}
}