{
  "type": "Feature",
  "properties": {
    "iso:country":"NZ",
    "sg:address":"15 Herekino St ",
    "sg:city":"Whangarei",
    "sg:orig_category":"Home And Garden: Furniture/Furnishings",
    "sg:phone":"+64 9-430 0030",
    "sg:province":"Northland",
    "sg:website":"http://www.yellowpages.co.nz/for/rowanindustries/dp33763.html",
    "wof:name":"Rowan Industries",
    "wof:placetype":"venue"
},
  "geometry": {"coordinates":[174.328247,-35.728104],"type":"Point"}
}