{
  "type": "Feature",
  "properties": {
    "addr:full":"27 Water St  Whangarei Northland",
    "addr:housenumber":"27",
    "addr:street":"Water St",
    "iso:country":"NZ",
    "sg:address":"27 Water St ",
    "sg:city":"Whangarei",
    "sg:classifiers":[
        {
            "category":"Bars & Pubs",
            "subcategory":"Lounge",
            "type":"Food & Drink"
        }
    ],
    "sg:phone":"+64 9-438 7631",
    "sg:province":"Northland",
    "sg:tags":[
        "baker",
        "-"
    ],
    "wof:name":"Water Street Bakery",
    "wof:placetype":"venue"
},
  "geometry": {"coordinates":[174.31826799999999,-35.726116],"type":"Point"}
}