{
  "type": "Feature",
  "properties": {
    "addr:full":"1 Howe St Newton  Auckland Auckland",
    "addr:housenumber":"1",
    "addr:street":"Howe St",
    "iso:country":"NZ",
    "sg:address":"1 Howe St Newton ",
    "sg:city":"Auckland",
    "sg:classifiers":[
        {
            "category":"Shopping",
            "subcategory":"Clothing, Apparel, & Fashions",
            "type":"Retail Goods"
        }
    ],
    "sg:phone":"+64 9-366 3003",
    "sg:province":"Auckland",
    "sg:tags":[
        "-",
        "hire",
        "clothing",
        "fabric"
    ],
    "wof:name":"Costume Magic",
    "wof:placetype":"venue"
},
  "geometry": {"coordinates":[174.755066,-36.858349],"type":"Point"}
}