{
  "type": "Feature",
  "properties": {
    "addr:full":"Main Rd Eskdale  Napier Hawke's Bay",
    "addr:street":"Main Rd",
    "iso:country":"NZ",
    "sg:address":"Main Rd Eskdale ",
    "sg:city":"Napier",
    "sg:classifiers":[
        {
            "category":"Shopping",
            "subcategory":"Pets & Pet Supplies",
            "type":"Retail Goods"
        }
    ],
    "sg:phone":"+64 6-836 6081",
    "sg:province":"Hawke's Bay",
    "sg:tags":[
        "boarding",
        "garden",
        "pets",
        "catteries",
        "home",
        "kennel"
    ],
    "wof:name":"Whitebay Kennels",
    "wof:placetype":"venue"
},
  "geometry": {"coordinates":[176.878174,-39.393673],"type":"Point"}
}