{
  "type": "Feature",
  "properties": {
    "iso:country":"NZ",
    "sg:address":"64 Johnsonville Rd Johnsonville ",
    "sg:city":"Wellington",
    "sg:classifiers":[
        {
            "category":"Food & Beverages",
            "subcategory":"Bakery",
            "type":"Retail Goods"
        }
    ],
    "sg:phone":"+64 4-478 3291",
    "sg:province":"Wellington",
    "sg:tags":[
        "shop",
        "cake",
        "drink",
        "-"
    ],
    "wof:name":"Nada Bakery",
    "wof:placetype":"venue"
},
  "geometry": {"coordinates":[174.807144,-41.22377],"type":"Point"}
}