{
  "type": "Feature",
  "properties": {
    "addr:full":"70 Princes St PO Box 13-472 Onehunga  Auckland Auckland",
    "addr:housenumber":"70;box",
    "addr:postcode":"13-472",
    "addr:street":"Princes St Po",
    "iso:country":"NZ",
    "sg:address":"70 Princes St PO Box 13-472 Onehunga ",
    "sg:city":"Auckland",
    "sg:classifiers":[
        {
            "category":"Social Services",
            "subcategory":"Retirement Home",
            "type":"Services"
        }
    ],
    "sg:phone":"+64 9-634 5322",
    "sg:province":"Auckland",
    "sg:tags":[
        "equipment",
        "industrial",
        "machinery",
        "lifting"
    ],
    "wof:name":"Konecranes",
    "wof:placetype":"venue"
},
  "geometry": {"coordinates":[174.77041600000001,-36.884109],"type":"Point"}
}