{
  "type": "Feature",
  "properties": {
    "addr:full":"139 Ohaupo Road  Hamilton Waikato",
    "addr:housenumber":"139",
    "addr:street":"Ohaupo Road",
    "iso:country":"NZ",
    "sg:address":"139 Ohaupo Road ",
    "sg:city":"Hamilton",
    "sg:classifiers":[
        {
            "category":"Bars & Pubs",
            "subcategory":"Wine Bar",
            "type":"Food & Drink"
        }
    ],
    "sg:phone":"+64 7-843 0350",
    "sg:province":"Waikato",
    "sg:tags":[
        "shop"
    ],
    "wof:name":"Bacchus Liquor Centre",
    "wof:placetype":"venue"
},
  "geometry": {"coordinates":[175.28195199999999,-37.818741],"type":"Point"}
}