{
  "type": "Feature",
  "properties": {
    "iso:country":"NZ",
    "sg:address":"14 Elmslie Pl ",
    "sg:city":"Rotorua",
    "sg:classifiers":[
        {
            "category":"Professional",
            "subcategory":"Art Services",
            "type":"Services"
        }
    ],
    "sg:phone":"+64 7-345 4647",
    "sg:province":"Bay of Plenty",
    "sg:tags":[
        "personal",
        "photographer",
        "services",
        "garden",
        "home"
    ],
    "wof:name":"Craig Robertson Photography",
    "wof:placetype":"venue"
},
  "geometry": {"coordinates":[176.295456,-38.1395],"type":"Point"}
}