{
  "type": "Feature",
  "properties": {
    "iso:country":"NZ",
    "sg:address":"32 Devonport Rd ",
    "sg:city":"Tauranga",
    "sg:classifiers":[
        {
            "category":"Restaurant",
            "type":"Food & Drink"
        }
    ],
    "sg:phone":"+64 7-578 6033",
    "sg:province":"Auckland",
    "sg:tags":[
        "brewing",
        "supply"
    ],
    "wof:name":"Brewers Den",
    "wof:placetype":"venue"
},
  "geometry": {"coordinates":[176.16983,-37.685139],"type":"Point"}
}