{
  "type": "Feature",
  "properties": {
    "iso:country":"NZ",
    "sg:address":"5-7 George St Te ",
    "sg:city":"Awamutu",
    "sg:orig_category":"Shopping: Retail Stores: Department Stores",
    "sg:phone":"+64 7-870 2579",
    "sg:province":"Waikato",
    "wof:name":"The Warehouse Ltd",
    "wof:placetype":"venue"
},
  "geometry": {"coordinates":[175.327255,-38.009495],"type":"Point"}
}