{
  "type": "Feature",
  "properties": {
    "addr:full":"5-7 George St Te  Awamutu Waikato",
    "addr:housenumber":"5-7",
    "addr:street":"George St",
    "iso:country":"NZ",
    "sg:address":"5-7 George St Te ",
    "sg:city":"Awamutu",
    "sg:orig_category":"Shopping: Retail Stores: Department Stores",
    "sg:phone":"+64 7-870 2579",
    "sg:province":"Waikato",
    "wof:name":"The Warehouse Ltd",
    "wof:placetype":"venue"
},
  "geometry": {"coordinates":[175.32725500000001,-38.009495],"type":"Point"}
}