{
  "type": "Feature",
  "properties": {
    "addr:full":"91 Ostend Rd Ostend  Auckland Auckland",
    "addr:housenumber":"91",
    "addr:street":"Ostend Rd",
    "iso:country":"NZ",
    "sg:address":"91 Ostend Rd Ostend ",
    "sg:city":"Auckland",
    "sg:orig_category":"Sports And Leisure: Sports: Equestrian: Riding Schools",
    "sg:phone":"+64 9-372 8104",
    "sg:province":"Auckland",
    "wof:name":"Shepherds Point Riding Centre - Waiheke Island",
    "wof:placetype":"venue"
},
  "geometry": {"coordinates":[175.05690000000001,-36.7999],"type":"Point"}
}