{
  "type": "Feature",
  "properties": {
    "iso:country":"NZ",
    "sg:address":"653 c Manakau Rd Epsom ",
    "sg:city":"Auckland",
    "sg:orig_category":"Clothing And Fabric: Clothing: Kilts",
    "sg:phone":"+64 9-624 4611",
    "sg:province":"Wellington",
    "wof:name":"Lewis Turrell's House of Scotland Ltd",
    "wof:placetype":"venue"
},
  "geometry": {"coordinates":[174.77356,-36.876179],"type":"Point"}
}