{
  "type": "Feature",
  "properties": {
    "iso:country":"NZ",
    "sg:address":"All Enquiries ",
    "sg:city":"Wanganui",
    "sg:orig_category":"Shopping: Accessories: Lingerie - Retail",
    "sg:phone":"+64 6-344 4904",
    "sg:province":"Manawatu-Wanganui",
    "wof:name":"Inner Sanctum",
    "wof:placetype":"venue"
},
  "geometry": {"coordinates":[175.052841,-39.933369],"type":"Point"}
}