{
  "type": "Feature",
  "properties": {
    "iso:country":"NZ",
    "sg:address":"46 Riverbank Rd ",
    "sg:city":"Otaki",
    "sg:orig_category":"Home And Garden: Gardening: Products: Outdoor Furniture",
    "sg:phone":"+64 6-364 0016",
    "wof:name":"Otaki Timber",
    "wof:placetype":"venue"
},
  "geometry": {"coordinates":[175.140091,-40.763649],"type":"Point"}
}