{
  "type": "Feature",
  "properties": {
    "addr:full":"46 Riverbank Rd  Otaki",
    "addr:housenumber":"46",
    "addr:street":"Riverbank Rd",
    "iso:country":"NZ",
    "sg:address":"46 Riverbank Rd ",
    "sg:city":"Otaki",
    "sg:orig_category":"Home And Garden: Gardening: Products: Outdoor Furniture",
    "sg:phone":"+64 6-364 0016",
    "wof:name":"Otaki Timber",
    "wof:placetype":"venue"
},
  "geometry": {"coordinates":[175.14009100000001,-40.763649],"type":"Point"}
}