{
  "type": "Feature",
  "properties": {
    "addr:full":"Green Ghyll Pine Valley Rd Silverdale Hibiscus  Hibiscus Coast Auckland",
    "addr:street":"Pine Valley Rd",
    "iso:country":"NZ",
    "sg:address":"Green Ghyll Pine Valley Rd Silverdale Hibiscus ",
    "sg:city":"Hibiscus Coast",
    "sg:orig_category":"Sports And Leisure: Sports: Equestrian: Riding Schools",
    "sg:phone":"+64 9-426 2396",
    "sg:province":"Auckland",
    "wof:name":"Green Ghyll Riding Centre",
    "wof:placetype":"venue"
},
  "geometry": {"coordinates":[174.67579699999999,-36.6208],"type":"Point"}
}