{
  "type": "Feature",
  "properties": {
    "addr:full":"Wyllies Crossing Mosgiel R D 1  Dunedin Otago",
    "addr:housenumber":"1",
    "addr:street":"Wyllies Crossing;R D",
    "iso:country":"NZ",
    "sg:address":"Wyllies Crossing Mosgiel R D 1 ",
    "sg:city":"Dunedin",
    "sg:orig_category":"Farming: Services: Hedge Cutting Contractors",
    "sg:phone":"+64 274 786 448",
    "sg:province":"Otago",
    "wof:name":"Hedgecutting Services",
    "wof:placetype":"venue"
},
  "geometry": {"coordinates":[170.50384500000001,-45.8745],"type":"Point"}
}