{
  "type": "Feature",
  "properties": {
    "iso:country":"NZ",
    "sg:address":"2/144 Central Park Dve Henderson ",
    "sg:city":"Auckland",
    "sg:orig_category":"Transport: Boats And Marine: Products",
    "sg:phone":"+64 9-836 0065",
    "sg:province":"Auckland",
    "wof:name":"Aero Trading Ltd",
    "wof:placetype":"venue"
},
  "geometry": {"coordinates":[174.630402,-36.887714],"type":"Point"}
}