{
  "type": "Feature",
  "properties": {
    "addr:full":"Jim Speirs La  Otaki",
    "iso:country":"NZ",
    "sg:address":"Jim Speirs La ",
    "sg:city":"Otaki",
    "sg:classifiers":[
        {
            "category":"Arena",
            "subcategory":"Sports Club",
            "type":"Entertainment"
        }
    ],
    "sg:phone":"+64 6-364 0274",
    "sg:tags":[
        "-",
        "leisure",
        "sports"
    ],
    "wof:name":"Rahui Football & Sports Club Inc",
    "wof:placetype":"venue"
},
  "geometry": {"coordinates":[175.14691199999999,-40.756664],"type":"Point"}
}