{
  "type": "Feature",
  "properties": {
    "iso:country":"NZ",
    "sg:address":"4 a Expo Pl Bromley ",
    "sg:city":"Christchurch",
    "sg:orig_category":"Farming: Horticulture: Soil Testing",
    "sg:phone":"+64 3-384 8900",
    "sg:province":"Canterbury",
    "wof:name":"Streat Instruments Ltd",
    "wof:placetype":"venue"
},
  "geometry": {"coordinates":[172.694366,-43.540726],"type":"Point"}
}