{
  "type": "Feature",
  "properties": {
    "iso:country":"NZ",
    "sg:address":"133 Gordon Rd Mosgiel ",
    "sg:city":"Dunedin",
    "sg:classifiers":[
        {
            "category":"Home & Garden",
            "subcategory":"Kitchen Supply",
            "type":"Retail Goods"
        }
    ],
    "sg:phone":"+64 3-489 7724",
    "sg:province":"Otago",
    "sg:tags":[
        "shop",
        "pet",
        "pets"
    ],
    "wof:name":"Mosgiel Garden Pet Shop",
    "wof:placetype":"venue"
},
  "geometry": {"coordinates":[170.348129,-45.874454],"type":"Point"}
}