{
  "type": "Feature",
  "properties": {
    "iso:country":"NZ",
    "sg:address":"Main Rd ",
    "sg:city":"Patutahi",
    "sg:classifiers":[
        {
            "category":"Bus Charters",
            "type":"Transportation"
        }
    ],
    "sg:phone":"+64 6-862 7732",
    "sg:tags":[
        "services",
        "travel",
        "tourism"
    ],
    "wof:name":"Hindmarsh Bus Charter",
    "wof:placetype":"venue"
},
  "geometry": {"coordinates":[177.888702,-38.624489],"type":"Point"}
}