{
  "type": "Feature",
  "properties": {
    "iso:country":"NZ",
    "sg:address":"8 McEntee Pl Papakura ",
    "sg:city":"Auckland",
    "sg:orig_category":"Home And Garden: Gardening: Services: Lawnmowing Services",
    "sg:phone":"+64 9-298 5649",
    "sg:province":"Auckland",
    "wof:name":"Renown Homes Ltd",
    "wof:placetype":"venue"
},
  "geometry": {"coordinates":[174.962402,-37.064316],"type":"Point"}
}