{
  "type": "Feature",
  "properties": {
    "addr:full":"Pourerere Rd  Waipawa",
    "addr:street":"Pourerere Rd",
    "iso:country":"NZ",
    "sg:address":"Pourerere Rd ",
    "sg:city":"Waipawa",
    "sg:classifiers":[
        {
            "category":"Coffee & Tea",
            "type":"Food & Drink"
        }
    ],
    "sg:phone":"+64 6-857 7047",
    "sg:tags":[
        "vegetable",
        "fruit",
        "veges"
    ],
    "wof:name":"Waipawa Orchard",
    "wof:placetype":"venue"
},
  "geometry": {"coordinates":[176.605728,-39.943638],"type":"Point"}
}