{
  "type": "Feature",
  "properties": {
    "addr:full":"Aotea  Quay",
    "addr:street":"Aotea Quay",
    "iso:country":"NZ",
    "sg:address":"Aotea ",
    "sg:city":"Quay",
    "sg:orig_category":"Transport: Transportation: Freight",
    "sg:phone":"+64 800872695465",
    "wof:name":"Tranz Rail Limited",
    "wof:placetype":"venue"
},
  "geometry": {"coordinates":[174.81939700000001,-38.00983],"type":"Point"}
}