{
  "type": "Feature",
  "properties": {
    "addr:full":"25 Orbell St Highfield  Timaru Canterbury",
    "addr:housenumber":"25",
    "addr:street":"Orbell St",
    "iso:country":"NZ",
    "sg:address":"25 Orbell St Highfield ",
    "sg:city":"Timaru",
    "sg:classifiers":[
        {
            "category":"Wholesale",
            "subcategory":"Hardware",
            "type":"Manufacturing & Wholesale Goods"
        }
    ],
    "sg:phone":"+64 3-686 6275",
    "sg:province":"Canterbury",
    "sg:tags":[
        "gardening",
        "garden",
        "chainsaw",
        "products",
        "brush",
        "home",
        "cutter"
    ],
    "wof:name":"South Canterbury Small Engine Services Ltd",
    "wof:placetype":"venue"
},
  "geometry": {"coordinates":[171.22036700000001,-44.385921],"type":"Point"}
}