{
  "type": "Feature",
  "properties": {
    "iso:country":"NZ",
    "sg:address":"145 Seven Mile Rd ",
    "sg:city":"Runanga",
    "sg:classifiers":[
        {
            "category":"Social Services",
            "subcategory":"Job Training",
            "type":"Services"
        }
    ],
    "sg:phone":"+64 3-762 7828",
    "sg:tags":[
        "education"
    ],
    "wof:name":"Mines Rescue Station",
    "wof:placetype":"venue"
},
  "geometry": {"coordinates":[171.24887100000001,-42.38903],"type":"Point"}
}