{
  "type": "Feature",
  "properties": {
    "iso:country":"NZ",
    "sg:address":"P O Box 13-628 Johnsonville ",
    "sg:city":"Wellington",
    "sg:classifiers":[
        {
            "category":"Personal",
            "subcategory":"Skin Care",
            "type":"Services"
        }
    ],
    "sg:phone":"+64 4-973 1567",
    "sg:province":"Wellington",
    "sg:tags":[
        "introduction",
        "services",
        "garden",
        "home"
    ],
    "wof:name":"Balfoort A",
    "wof:placetype":"venue"
},
  "geometry": {"coordinates":[174.801788,-41.222324],"type":"Point"}
}