{
  "type": "Feature",
  "properties": {
    "addr:full":"19 Canada St  Morrinsville Waikato",
    "addr:housenumber":"19",
    "addr:street":"Canada St",
    "iso:country":"NZ",
    "sg:address":"19 Canada St ",
    "sg:city":"Morrinsville",
    "sg:classifiers":[
        {
            "category":"Retail",
            "subcategory":"Auto Repair",
            "type":"Services"
        }
    ],
    "sg:phone":"+64 7-889 5091",
    "sg:province":"Waikato",
    "sg:tags":[
        "automotive",
        "electric",
        "servicing"
    ],
    "wof:name":"Belfor Auto 1",
    "wof:placetype":"venue"
},
  "geometry": {"coordinates":[175.53207399999999,-37.658783],"type":"Point"}
}