{
  "type": "Feature",
  "properties": {
    "iso:country":"NZ",
    "sg:address":"Cnr Matai & Gt South Rds Greenlane ",
    "sg:city":"Auckland",
    "sg:classifiers":[
        {
            "category":"Banks & Credit Unions",
            "subcategory":"Investment Brokerage",
            "type":"Services"
        }
    ],
    "sg:phone":"+64 9-525 8808",
    "sg:province":"Auckland",
    "sg:tags":[
        "automotive",
        "leasing",
        "sale"
    ],
    "sg:website":"http://www.eurodrive.renault.com",
    "wof:name":"Renault Eurodrive",
    "wof:placetype":"venue"
},
  "geometry": {"coordinates":[174.79191599999999,-36.89296],"type":"Point"}
}