{
  "type": "Feature",
  "properties": {
    "addr:full":"3rd Floor 52 Symonds St Auckland Central PO Box 796 Auckland Auckland",
    "addr:housenumber":"3rd floor 52;796",
    "addr:postcode":"po box",
    "addr:street":"Symonds St",
    "iso:country":"NZ",
    "sg:address":"3rd Floor 52 Symonds St Auckland Central PO Box 796",
    "sg:city":"Auckland",
    "sg:orig_category":"Transport: Boats And Marine: Shipping",
    "sg:phone":"+64 9-356 2333",
    "sg:province":"Auckland",
    "wof:name":"Pacific Forum Line (NZ) Ltd",
    "wof:placetype":"venue"
},
  "geometry": {"coordinates":[174.77041600000001,-36.884109],"type":"Point"}
}