{
  "type": "Feature",
  "properties": {
    "addr:full":"455 New North Rd Kingsland  Auckland Auckland",
    "addr:housenumber":"455",
    "addr:street":"New North Rd",
    "iso:country":"NZ",
    "sg:address":"455 New North Rd Kingsland ",
    "sg:city":"Auckland",
    "sg:orig_category":"Automotive: General Services: Service Stations",
    "sg:phone":"+64 9-849 2700",
    "sg:province":"Auckland",
    "wof:name":"BP Oil",
    "wof:placetype":"venue"
},
  "geometry": {"coordinates":[174.74551399999999,-36.871677],"type":"Point"}
}