{
  "type": "Feature",
  "properties": {
    "iso:country":"NZ",
    "sg:address":"115 Phillip Rd Takanini ",
    "sg:city":"Auckland",
    "sg:orig_category":"Home And Garden: Gardening: Services: Tree Services",
    "sg:phone":"+64 21 364 969",
    "sg:province":"Auckland",
    "wof:name":"Able Earthmoving Ltd",
    "wof:placetype":"venue"
},
  "geometry": {"coordinates":[174.9545288086,-37.0215301514],"type":"Point"}
}