{
  "type": "Feature",
  "properties": {
    "iso:country":"NZ",
    "sg:address":"official web site Unit 9/81 Hillside Rd Glenfield ",
    "sg:city":"Auckland",
    "sg:orig_category":"Shopping: Retail Stores: Stationery",
    "sg:phone":"+64 800 633 423",
    "sg:province":"Auckland",
    "sg:website":"http://www.officeproductsdepot.co.nz",
    "wof:name":"Office Products Depot",
    "wof:placetype":"venue"
},
  "geometry": {"coordinates":[174.728622,-36.784813],"type":"Point"}
}