{
  "type": "Feature",
  "properties": {
    "addr:full":"3 Old Wairoa Rd Papakura  Auckland Auckland",
    "addr:housenumber":"3",
    "addr:street":"Old Wairoa Rd",
    "iso:country":"NZ",
    "sg:address":"3 Old Wairoa Rd Papakura ",
    "sg:city":"Auckland",
    "sg:classifiers":[
        {
            "category":"Retail",
            "subcategory":"Auto Repair",
            "type":"Services"
        }
    ],
    "sg:phone":"+64 9-299 6083",
    "sg:province":"Auckland",
    "sg:tags":[
        "wheel",
        "automotive",
        "servicing",
        "alignment"
    ],
    "wof:name":"Papakura Alignment Centre",
    "wof:placetype":"venue"
},
  "geometry": {"coordinates":[174.94146699999999,-37.057327],"type":"Point"}
}