{
  "type": "Feature",
  "properties": {
    "addr:full":"McGowan St  Runanga",
    "addr:street":"Mcgowan St",
    "iso:country":"NZ",
    "sg:address":"McGowan St ",
    "sg:city":"Runanga",
    "sg:classifiers":[
        {
            "category":"Banks & Credit Unions",
            "subcategory":"Investment Brokerage",
            "type":"Services"
        }
    ],
    "sg:phone":"+64 3-762 7873",
    "sg:tags":[
        "educational",
        "education",
        "training"
    ],
    "wof:name":"Runanga School",
    "wof:placetype":"venue"
},
  "geometry": {"coordinates":[171.251373,-42.402603],"type":"Point"}
}