{
  "type": "Feature",
  "properties": {
    "iso:country":"NZ",
    "sg:address":"614 Remuera Rd Remuera ",
    "sg:city":"Auckland",
    "sg:classifiers":[
        {
            "category":"Health Services",
            "subcategory":"Dentist",
            "type":"Services"
        }
    ],
    "sg:phone":"+64 9-524 4528",
    "sg:province":"Auckland",
    "sg:tags":[
        "dental",
        "beauty"
    ],
    "wof:name":"McCabe Dr John BDS (Otago)",
    "wof:placetype":"venue"
},
  "geometry": {"coordinates":[174.808044,-36.882359],"type":"Point"}
}