{
  "type": "Feature",
  "properties": {
    "iso:country":"NZ",
    "sg:address":"Hokonui Dve ",
    "sg:city":"Gore",
    "sg:classifiers":[
        {
            "category":"Utilities",
            "type":"Services"
        }
    ],
    "sg:phone":"+64 3-203 9056",
    "sg:province":"Southland",
    "sg:tags":[
        "industrial",
        "energy",
        "utilities",
        "coal",
        "wood",
        "coke"
    ],
    "wof:name":"Fulton Hogan Southland",
    "wof:placetype":"venue"
},
  "geometry": {"coordinates":[168.48820499999999,-46.132141],"type":"Point"}
}