{
  "type": "Feature",
  "properties": {
    "iso:country":"NZ",
    "sg:address":"18 Raumati Rd Raumati Beach ",
    "sg:city":"Paraparaumu",
    "sg:orig_category":"Health And Beauty: Products: Pharmacies",
    "sg:phone":"+64 4-299 5206",
    "sg:province":"Wellington",
    "wof:name":"Raumati Pharmacy Ltd",
    "wof:placetype":"venue"
},
  "geometry": {"coordinates":[174.98185699999999,-40.919086],"type":"Point"}
}