{
  "type": "Feature",
  "properties": {
    "addr:full":"71 Parkhurst Rd Parakai R D 1  Helensville Auckland",
    "addr:housenumber":"71;1",
    "addr:street":"Parkhurst Rd;R D",
    "iso:country":"NZ",
    "sg:address":"71 Parkhurst Rd Parakai R D 1 ",
    "sg:city":"Helensville",
    "sg:orig_category":"Automotive: Accessories: Motor Accessories",
    "sg:phone":"+64 9-420 7127",
    "sg:province":"Auckland",
    "wof:name":"Thrifty Auto Supplies Ltd",
    "wof:placetype":"venue"
},
  "geometry": {"coordinates":[174.45178200000001,-36.683239],"type":"Point"}
}