{
  "type": "Feature",
  "properties": {
    "addr:full":"385 Neilson St Onehunga  Auckland Auckland",
    "addr:housenumber":"385",
    "addr:street":"Neilson St",
    "iso:country":"NZ",
    "sg:address":"385 Neilson St Onehunga ",
    "sg:city":"Auckland",
    "sg:classifiers":[
        {
            "category":"Wholesale",
            "subcategory":"Machinery & Supplies",
            "type":"Manufacturing & Wholesale Goods"
        }
    ],
    "sg:phone":"+64 9-636 0982",
    "sg:province":"Auckland",
    "sg:tags":[
        "equipment",
        "crane",
        "industrial",
        "hoist",
        "lifting"
    ],
    "sg:website":"http://www.richmondcastors.co.nz",
    "wof:name":"Richmond's Handling & Storage",
    "wof:placetype":"venue"
},
  "geometry": {"coordinates":[174.792496,-36.926411],"type":"Point"}
}