{
  "type": "Feature",
  "properties": {
    "addr:full":"22 c Parkway Dve Mairangi Bay  Auckland Wellington",
    "addr:housenumber":"22",
    "addr:street":"C Parkway Dve",
    "iso:country":"NZ",
    "sg:address":"22 c Parkway Dve Mairangi Bay ",
    "sg:city":"Auckland",
    "sg:classifiers":[
        {
            "category":"Professional",
            "type":"Services"
        }
    ],
    "sg:phone":"+64 9-478 2392",
    "sg:province":"Wellington",
    "sg:tags":[
        "services",
        "car",
        "valet",
        "automotive"
    ],
    "wof:name":"Shiners 2002 Ltd",
    "wof:placetype":"venue"
},
  "geometry": {"coordinates":[174.77041600000001,-36.884109],"type":"Point"}
}