{
  "type": "Feature",
  "properties": {
    "addr:full":"15 Helston Rd Johnsonville  Wellington Wellington",
    "addr:housenumber":"15",
    "addr:street":"Helston Rd",
    "iso:country":"NZ",
    "sg:address":"15 Helston Rd Johnsonville ",
    "sg:city":"Wellington",
    "sg:orig_category":"Health And Beauty: Specialists: Chiropractors",
    "sg:phone":"+64 4-478 6194",
    "sg:province":"Wellington",
    "wof:name":"Johnsonville Chiropractic Clinic",
    "wof:placetype":"venue"
},
  "geometry": {"coordinates":[174.809448,-41.221279],"type":"Point"}
}