{
  "type": "Feature",
  "properties": {
    "iso:country":"NZ",
    "sg:address":"97 Austin St Onekawa ",
    "sg:city":"Napier",
    "sg:classifiers":[
        {
            "category":"Retail",
            "subcategory":"Auto Repair",
            "type":"Services"
        }
    ],
    "sg:phone":"+64 6-843 2748",
    "sg:province":"Hawke's Bay",
    "sg:tags":[
        "automotive",
        "electric",
        "servicing"
    ],
    "wof:name":"BPD Automotive Electrical Ltd",
    "wof:placetype":"venue"
},
  "geometry": {"coordinates":[176.877945,-39.496834],"type":"Point"}
}