{
  "type": "Feature",
  "properties": {
    "iso:country":"NZ",
    "sg:address":"Mill Rd ",
    "sg:city":"Whakatane",
    "sg:orig_category":"Industrial: Packaging: Pallet Manufacturers",
    "sg:phone":"+64 7-307 9038",
    "sg:province":"Bay of Plenty",
    "wof:name":"Whakatane Pallets Ltd",
    "wof:placetype":"venue"
},
  "geometry": {"coordinates":[176.96234100000001,-37.953869],"type":"Point"}
}