{
  "type": "Feature",
  "properties": {
    "iso:country":"NZ",
    "sg:address":"399 New North Rd Kingsland ",
    "sg:city":"Auckland",
    "sg:classifiers":[
        {
            "category":"Sports & Exercise",
            "subcategory":"Winter Sports",
            "type":"Entertainment"
        }
    ],
    "sg:phone":"+64 9-846 1076",
    "sg:province":"Auckland",
    "sg:tags":[
        "hire",
        "camping",
        "-",
        "leisure",
        "equipment",
        "tramping"
    ],
    "wof:name":"Tent Town Ltd",
    "wof:placetype":"venue"
},
  "geometry": {"coordinates":[174.747925,-36.870705],"type":"Point"}
}