{
  "type": "Feature",
  "properties": {
    "iso:country":"NZ",
    "sg:address":"37 McAlister St ",
    "sg:city":"Whakatane",
    "sg:classifiers":[
        {
            "category":"Farming",
            "subcategory":"Fish & Marine Products",
            "type":"Manufacturing & Wholesale Goods"
        }
    ],
    "sg:phone":"+64 7-308 6330",
    "sg:province":"Bay of Plenty",
    "sg:tags":[
        "boats",
        "yacht",
        "transport",
        "boat",
        "supply"
    ],
    "wof:name":"Auto & Marine Upholstery",
    "wof:placetype":"venue"
},
  "geometry": {"coordinates":[176.991119,-37.952396],"type":"Point"}
}