{
  "type": "Feature",
  "properties": {
    "addr:full":"700 Cashmere Rd Cashmere  Christchurch Canterbury",
    "addr:housenumber":"700",
    "addr:street":"Cashmere Rd",
    "iso:country":"NZ",
    "sg:address":"700 Cashmere Rd Cashmere ",
    "sg:city":"Christchurch",
    "sg:orig_category":"Automotive: General Services: Electric Vehicles",
    "sg:phone":"+64 3-322 8494",
    "sg:province":"Canterbury",
    "wof:name":"Pandect Electric Vehicles Ltd",
    "wof:placetype":"venue"
},
  "geometry": {"coordinates":[172.63026400000001,-43.567249],"type":"Point"}
}