{
  "type": "Feature",
  "properties": {
    "iso:country":"NZ",
    "sg:address":"Central Wellington ",
    "sg:city":"Wellington",
    "sg:classifiers":[
        {
            "category":"Banks & Credit Unions",
            "subcategory":"Financial Services",
            "type":"Services"
        }
    ],
    "sg:phone":"+64 4-499 0550",
    "sg:province":"Wellington",
    "sg:tags":[
        "lender",
        "money",
        "-",
        "finance",
        "personal"
    ],
    "wof:name":"Easy Loans",
    "wof:placetype":"venue"
},
  "geometry": {"coordinates":[174.778046,-41.280739],"type":"Point"}
}