{
  "type": "Feature",
  "properties": {
    "iso:country":"NZ",
    "sg:address":"25 Highland Dve ",
    "sg:city":"Hamilton",
    "sg:orig_category":"Shopping: Retail Stores: Cds, Cassettes And Records",
    "sg:phone":"+64 7-849 6833",
    "sg:province":"Waikato",
    "wof:name":"CD Repair Services",
    "wof:placetype":"venue"
},
  "geometry": {"coordinates":[-91.35011299999999,40.399193],"type":"Point"}
}