{
  "type": "Feature",
  "properties": {
    "iso:country":"NZ",
    "sg:address":"112 Ronaldsay St ",
    "sg:city":"Palmerston",
    "sg:orig_category":"Farming: Machinery: Farm Machinery",
    "sg:phone":"+64 3-465 1115",
    "wof:name":"Warrens Garage Ltd",
    "wof:placetype":"venue"
},
  "geometry": {"coordinates":[170.712402,-45.486641],"type":"Point"}
}