{
  "type": "Feature",
  "properties": {
    "addr:full":"3rd Floor GRE Bldg Garden Pl  Hamilton Waikato",
    "addr:housenumber":"3rd floor gre bldg",
    "addr:street":"Garden Pl",
    "iso:country":"NZ",
    "sg:address":"3rd Floor GRE Bldg Garden Pl ",
    "sg:city":"Hamilton",
    "sg:orig_category":"Health And Beauty: Dental: Dentists",
    "sg:phone":"+64 7-839 5862",
    "sg:province":"Waikato",
    "wof:name":"Southall J R",
    "wof:placetype":"venue"
},
  "geometry": {"coordinates":[175.276993,-37.783215],"type":"Point"}
}