{
  "type": "Feature",
  "properties": {
    "addr:full":"1260 Eruera St  Rotorua Bay of Plenty",
    "addr:housenumber":"1260",
    "addr:street":"Eruera St",
    "iso:country":"NZ",
    "sg:address":"1260 Eruera St ",
    "sg:city":"Rotorua",
    "sg:classifiers":[
        {
            "category":"Shopping",
            "subcategory":"Crafts & Fabrics",
            "type":"Retail Goods"
        }
    ],
    "sg:phone":"+64 7-348 7205",
    "sg:province":"Bay of Plenty",
    "sg:tags":[
        "clothing"
    ],
    "wof:name":"Cut Price Fabrics",
    "wof:placetype":"venue"
},
  "geometry": {"coordinates":[176.24839800000001,-38.13903],"type":"Point"}
}