{
  "type": "Feature",
  "properties": {
    "iso:country":"NZ",
    "sg:address":"PO Box 999 ",
    "sg:city":"Wanganui",
    "sg:classifiers":[
        {
            "category":"Recreation",
            "subcategory":"Gun Range",
            "type":"Entertainment"
        }
    ],
    "sg:phone":"+64 6-344 6741",
    "sg:province":"Manawatu-Wanganui",
    "sg:tags":[
        "sports",
        "sport",
        "-",
        "leisure",
        "gunsmith"
    ],
    "wof:name":"Belmont Ammunition",
    "wof:placetype":"venue"
},
  "geometry": {"coordinates":[175.052841,-39.933369],"type":"Point"}
}