{
  "type": "Feature",
  "properties": {
    "iso:country":"NZ",
    "sg:address":"52 Worcester Bvd ",
    "sg:city":"Christchurch",
    "sg:orig_category":"Health And Beauty: Dental: Dentists",
    "sg:phone":"+64 3-379 6766",
    "sg:province":"Canterbury",
    "wof:name":"Richmond Christopher J",
    "wof:placetype":"venue"
},
  "geometry": {"coordinates":[172.63133199999999,-43.531136],"type":"Point"}
}