{
  "type": "Feature",
  "properties": {
    "iso:country":"NZ",
    "sg:address":"PO Box 35346 Browns Bay ",
    "sg:city":"Auckland",
    "sg:classifiers":[
        {
            "category":"Education",
            "subcategory":"Special Training",
            "type":"Public Place"
        }
    ],
    "sg:phone":"+64 9-377 9147",
    "sg:province":"Auckland",
    "sg:tags":[
        "aid",
        "medical",
        "health",
        "beauty",
        "first"
    ],
    "wof:name":"Emcare Ltd",
    "wof:placetype":"venue"
},
  "geometry": {"coordinates":[174.744324,-36.714409],"type":"Point"}
}