{
  "type": "Feature",
  "properties": {
    "iso:country":"NZ",
    "sg:address":"211 Kiripaka Rd Tikipunga ",
    "sg:city":"Whangarei",
    "sg:classifiers":[
        {
            "category":"Education",
            "subcategory":"University",
            "type":"Public Place"
        }
    ],
    "sg:phone":"+64 9-437 3541",
    "sg:province":"Northland",
    "sg:tags":[
        "training",
        "adult"
    ],
    "wof:name":"Community Education Tikipunga",
    "wof:placetype":"venue"
},
  "geometry": {"coordinates":[174.329285,-35.684635],"type":"Point"}
}