{
  "type": "Feature",
  "properties": {
    "iso:country":"NZ",
    "sg:address":"133 Park Rd Miramar ",
    "sg:city":"Wellington",
    "sg:classifiers":[
        {
            "category":"Farming",
            "subcategory":"Farm",
            "type":"Manufacturing & Wholesale Goods"
        }
    ],
    "sg:phone":"+64 4-388 9944",
    "sg:province":"Wellington",
    "sg:website":"http://www.heartlands.co.nz",
    "wof:name":"Heartlands",
    "wof:placetype":"venue"
},
  "geometry": {"coordinates":[174.821289,-41.309135],"type":"Point"}
}