{
  "type": "Feature",
  "properties": {
    "addr:full":"Cnr Sala St & Te Ngae Rd  Rotorua Bay of Plenty",
    "addr:street":"Cnr Sala St & Te Ngae Rd",
    "iso:country":"NZ",
    "sg:address":"Cnr Sala St & Te Ngae Rd ",
    "sg:city":"Rotorua",
    "sg:orig_category":"Sports And Leisure: Sports: Golf",
    "sg:phone":"+64 7-348 3531",
    "sg:province":"Bay of Plenty",
    "wof:name":"Shortgolf",
    "wof:placetype":"venue"
},
  "geometry": {"coordinates":[176.24499499999999,-38.1418],"type":"Point"}
}