{
  "type": "Feature",
  "properties": {
    "iso:country":"NZ",
    "sg:address":"54 Chappel St ",
    "sg:city":"Tauranga",
    "sg:classifiers":[
        {
            "category":"Sports & Exercise",
            "subcategory":"Tennis Court",
            "type":"Entertainment"
        }
    ],
    "sg:phone":"+64 7-578 1940",
    "sg:province":"Bay of Plenty",
    "sg:tags":[
        "hire",
        "-",
        "leisure"
    ],
    "wof:name":"Direct Office Furniture",
    "wof:placetype":"venue"
},
  "geometry": {"coordinates":[176.16593900000001,-37.675655],"type":"Point"}
}