{
  "type": "Feature",
  "properties": {
    "iso:country":"NZ",
    "sg:address":"PO Box 19 Lyttelton ",
    "sg:city":"Christchurch",
    "sg:classifiers":[
        {
            "category":"Utilities",
            "subcategory":"Refuse",
            "type":"Services"
        }
    ],
    "sg:phone":"+64 3-364 8990",
    "sg:province":"Canterbury",
    "sg:tags":[
        "bin",
        "hire",
        "garden",
        "cleaning",
        "rubbish",
        "home"
    ],
    "wof:name":"Summit Bin Hire",
    "wof:placetype":"venue"
},
  "geometry": {"coordinates":[172.722839,-43.599499],"type":"Point"}
}