{
  "type": "Feature",
  "properties": {
    "iso:country":"NZ",
    "sg:address":"40 Moir St ",
    "sg:city":"Mangawhai",
    "sg:classifiers":[
        {
            "category":"Bars & Pubs",
            "type":"Food & Drink"
        }
    ],
    "sg:phone":"+64 9-431 4848",
    "sg:tags":[
        "wining",
        "dining",
        "brasserie"
    ],
    "wof:name":"Smashed Pipi Bar",
    "wof:placetype":"venue"
},
  "geometry": {"coordinates":[174.575714,-36.125828],"type":"Point"}
}