{
  "type": "Feature",
  "properties": {
    "addr:full":"34 Hurlstone Dve New  Plymouth Taranaki",
    "addr:housenumber":"34",
    "addr:street":"Hurlstone Dve",
    "iso:country":"NZ",
    "sg:address":"34 Hurlstone Dve New ",
    "sg:city":"Plymouth",
    "sg:classifiers":[
        {
            "category":"Banks & Credit Unions",
            "subcategory":"Investment Brokerage",
            "type":"Services"
        }
    ],
    "sg:phone":"+64 6-757 5197",
    "sg:province":"Taranaki",
    "sg:tags":[
        "industrial",
        "cleaning",
        "maintenance"
    ],
    "sg:website":"http://www.abequipment.co.nz",
    "wof:name":"AB Equipment Ltd",
    "wof:placetype":"venue"
},
  "geometry": {"coordinates":[-116.81972500000001,43.97221],"type":"Point"}
}