{
  "type": "Feature",
  "properties": {
    "iso:country":"NZ",
    "sg:address":"34 Barry's Point Rd ",
    "sg:city":"Takapuna",
    "sg:classifiers":[
        {
            "category":"Sports & Exercise",
            "subcategory":"Sports Center",
            "type":"Entertainment"
        }
    ],
    "sg:phone":"+64 800 752 963",
    "sg:province":"Auckland",
    "sg:tags":[
        "game",
        "-",
        "leisure",
        "interactive"
    ],
    "wof:name":"Central Park Interactive",
    "wof:placetype":"venue"
},
  "geometry": {"coordinates":[174.767883,-36.787842],"type":"Point"}
}