{
  "type": "Feature",
  "properties": {
    "iso:country":"NZ",
    "sg:address":"147 The Parade Island Bay ",
    "sg:city":"Wellington",
    "sg:classifiers":[
        {
            "category":"Shopping",
            "subcategory":"Crafts & Fabrics",
            "type":"Retail Goods"
        }
    ],
    "sg:phone":"+64 4-383 5757",
    "sg:province":"Auckland",
    "sg:tags":[
        "sport",
        "art",
        "leisure",
        "hobbies"
    ],
    "wof:name":"Koru",
    "wof:placetype":"venue"
},
  "geometry": {"coordinates":[174.774307,-41.336449],"type":"Point"}
}