{
  "type": "Feature",
  "properties": {
    "iso:country":"NZ",
    "sg:address":"28 Church St ",
    "sg:city":"Waipawa",
    "sg:classifiers":[
        {
            "category":"Professional",
            "subcategory":"Art Services",
            "type":"Services"
        }
    ],
    "sg:phone":"+64 6-857 7881",
    "sg:tags":[
        "picture",
        "arts",
        "sport",
        "framing",
        "leisure"
    ],
    "wof:name":"Abbotsford Art & Picture Framing",
    "wof:placetype":"venue"
},
  "geometry": {"coordinates":[176.586273,-39.941162],"type":"Point"}
}