{
  "type": "Feature",
  "properties": {
    "addr:full":"Waikanae Health Centre 83 Winanra Ave  Waikanae",
    "addr:housenumber":"83",
    "addr:street":"Winanra Ave",
    "iso:country":"NZ",
    "sg:address":"Waikanae Health Centre 83 Winanra Ave ",
    "sg:city":"Waikanae",
    "sg:orig_category":"Health And Beauty: Specialists: Podiatrists",
    "sg:phone":"+64 274 846 229",
    "wof:name":"Sander Timothy Podiatrist",
    "wof:placetype":"venue"
},
  "geometry": {"coordinates":[175.06102000000001,-40.873184],"type":"Point"}
}