{
  "type": "Feature",
  "properties": {
    "addr:full":"81 Ikitara Rd  Wanganui Manawatu-Wanganui",
    "addr:housenumber":"81",
    "addr:street":"Ikitara Rd",
    "iso:country":"NZ",
    "sg:address":"81 Ikitara Rd ",
    "sg:city":"Wanganui",
    "sg:orig_category":"Health And Beauty: Beauty: Hairdressers",
    "sg:phone":"+64 6-343 1113",
    "sg:province":"Manawatu-Wanganui",
    "wof:name":"Jenny's Hair Boutique",
    "wof:placetype":"venue"
},
  "geometry": {"coordinates":[175.065369,-39.923904],"type":"Point"}
}