{
  "type": "Feature",
  "properties": {
    "addr:full":"105 Duncan St  Wanganui Manawatu-Wanganui",
    "addr:housenumber":"105",
    "addr:street":"Duncan St",
    "iso:country":"NZ",
    "sg:address":"105 Duncan St ",
    "sg:city":"Wanganui",
    "sg:classifiers":[
        {
            "category":"Retail",
            "subcategory":"Storage",
            "type":"Services"
        }
    ],
    "sg:phone":"+64 6-343 9223",
    "sg:province":"Manawatu-Wanganui",
    "wof:name":"Mac's Refrigeration & Air Conditioning",
    "wof:placetype":"venue"
},
  "geometry": {"coordinates":[175.06199599999999,-39.917103],"type":"Point"}
}