{
  "type": "Feature",
  "properties": {
    "addr:full":"65 St Micheals Ave Point Chevalier  Auckland Auckland",
    "addr:housenumber":"65",
    "addr:street":"St Micheals Ave",
    "iso:country":"NZ",
    "sg:address":"65 St Micheals Ave Point Chevalier ",
    "sg:city":"Auckland",
    "sg:classifiers":[
        {
            "category":"Organizations",
            "subcategory":"Religious Organization",
            "type":"Services"
        }
    ],
    "sg:phone":"+64 9-849 4604",
    "sg:province":"Auckland",
    "sg:tags":[
        "arrangements",
        "tent",
        "marquee",
        "wedding"
    ],
    "wof:name":"Fabric Shelter Systems",
    "wof:placetype":"venue"
},
  "geometry": {"coordinates":[174.698868,-36.863319],"type":"Point"}
}