{
  "type": "Feature",
  "properties": {
    "addr:full":"89 Fitzherbert Ave Palmerston  Palmerston North Manawatu-Wanganui",
    "addr:housenumber":"89",
    "addr:street":"Fitzherbert Ave",
    "iso:country":"NZ",
    "sg:address":"89 Fitzherbert Ave Palmerston ",
    "sg:city":"Palmerston North",
    "sg:classifiers":[
        {
            "category":"Fast Food",
            "type":"Food & Drink"
        }
    ],
    "sg:phone":"+64 6-358 0280",
    "sg:province":"Manawatu-Wanganui",
    "sg:tags":[
        "wining",
        "dining",
        "takeaway"
    ],
    "sg:website":"http://www.bkk.co.nz",
    "wof:name":"Bangkok Thai Restaurant",
    "wof:placetype":"venue"
},
  "geometry": {"coordinates":[175.61350999999999,-40.358978],"type":"Point"}
}