{
  "type": "Feature",
  "properties": {
    "iso:country":"NZ",
    "sg:address":"58-60 Queen St Auckland City ",
    "sg:city":"Auckland",
    "sg:classifiers":[
        {
            "category":"Travel",
            "subcategory":"Hotels & Motels",
            "type":"Entertainment"
        }
    ],
    "sg:phone":"+64 9-309 9979",
    "sg:province":"Auckland",
    "sg:tags":[
        "tourism",
        "-",
        "rental",
        "accommodation"
    ],
    "wof:name":"Mercure Hotel Windsor House",
    "wof:placetype":"venue"
},
  "geometry": {"coordinates":[174.766571,-36.845409],"type":"Point"}
}