{
  "type": "Feature",
  "properties": {
    "addr:full":"Gisborne Hastings  Napier Hawke's Bay",
    "addr:street":"Gisborne",
    "iso:country":"NZ",
    "sg:address":"Gisborne Hastings ",
    "sg:city":"Napier",
    "sg:orig_category":"Home And Garden: General: Handyman'S Services",
    "sg:phone":"+64 800 616 188",
    "sg:province":"Hawke's Bay",
    "sg:website":"http://www.yellowpages.co.nz/for/readyhire/dp39023.html",
    "wof:name":"Ready Hire",
    "wof:placetype":"venue"
},
  "geometry": {"coordinates":[177.836197,-38.252838],"type":"Point"}
}