{
  "type": "Feature",
  "properties": {
    "addr:full":"39 Spring St  Tauranga Bay of Plenty",
    "addr:housenumber":"39",
    "addr:street":"Spring St",
    "iso:country":"NZ",
    "sg:address":"39 Spring St ",
    "sg:city":"Tauranga",
    "sg:classifiers":[
        {
            "category":"Banks & Credit Unions",
            "subcategory":"Financial Services",
            "type":"Services"
        }
    ],
    "sg:phone":"+64 7-578 7039",
    "sg:province":"Bay of Plenty",
    "sg:tags":[
        "personal",
        "superannuation",
        "-",
        "finance"
    ],
    "wof:name":"Tower Financial Advisory Services",
    "wof:placetype":"venue"
},
  "geometry": {"coordinates":[176.16871599999999,-37.684261],"type":"Point"}
}