{
  "type": "Feature",
  "properties": {
    "addr:full":"5 B Raiha St Elsdon  Porirua Wellington",
    "addr:housenumber":"5 b",
    "addr:street":"Raiha St",
    "iso:country":"NZ",
    "sg:address":"5 B Raiha St Elsdon ",
    "sg:city":"Porirua",
    "sg:orig_category":"Shopping: Gifts",
    "sg:phone":"+64 4-237 8044",
    "sg:province":"Wellington",
    "wof:name":"Folio Graphics Ltd",
    "wof:placetype":"venue"
},
  "geometry": {"coordinates":[174.83105499999999,-41.135094],"type":"Point"}
}