{
  "type": "Feature",
  "properties": {
    "iso:country":"NZ",
    "sg:address":"Leet St ",
    "sg:city":"Invercargill",
    "sg:classifiers":[
        {
            "category":"Sports & Exercise",
            "subcategory":"Sports Center",
            "type":"Entertainment"
        }
    ],
    "sg:phone":"+64 3-214 4944",
    "sg:province":"Southland",
    "sg:tags":[
        "indoor",
        "-",
        "leisure",
        "sports"
    ],
    "wof:name":"Super Bowl",
    "wof:placetype":"venue"
},
  "geometry": {"coordinates":[168.355316,-46.407497],"type":"Point"}
}