{
  "type": "Feature",
  "properties": {
    "addr:full":"241 A Linwood Ave Linwood  Christchurch Canterbury",
    "addr:housenumber":"241 a",
    "addr:street":"Linwood Ave",
    "iso:country":"NZ",
    "sg:address":"241 A Linwood Ave Linwood ",
    "sg:city":"Christchurch",
    "sg:classifiers":[
        {
            "category":"Building & Trades",
            "subcategory":"Construction",
            "type":"Services"
        }
    ],
    "sg:phone":"+64 3-389 7742",
    "sg:province":"Canterbury",
    "sg:tags":[
        "home",
        "hire",
        "garden"
    ],
    "wof:name":"LO TV RENTALS",
    "wof:placetype":"venue"
},
  "geometry": {"coordinates":[172.67308,-43.533371],"type":"Point"}
}