{
  "type": "Feature",
  "properties": {
    "iso:country":"NZ",
    "sg:address":"47 Kahotea Pl Motuoapa ",
    "sg:city":"Turangi",
    "sg:orig_category":"Health And Beauty: Specialists: Midwives",
    "sg:phone":"+64 7-386 6082",
    "wof:name":"Wilberforce Cassandra",
    "wof:placetype":"venue"
},
  "geometry": {"coordinates":[175.803955,-38.988941],"type":"Point"}
}