{
  "type": "Feature",
  "properties": {
    "iso:country":"NZ",
    "sg:address":"40 Corbett Rd Bell Block New ",
    "sg:city":"Plymouth",
    "sg:classifiers":[
        {
            "category":"Professional",
            "subcategory":"Engineering",
            "type":"Services"
        }
    ],
    "sg:phone":"+64 6-755 1113",
    "sg:province":"Taranaki",
    "sg:tags":[
        "industrial"
    ],
    "sg:website":"http://www.yellowpages.co.nz/for/nzfasteners/dp28427.html",
    "wof:name":"NZF Stainless",
    "wof:placetype":"venue"
},
  "geometry": {"coordinates":[174.142746,-39.032024],"type":"Point"}
}