{
  "type": "Feature",
  "properties": {
    "iso:country":"NZ",
    "sg:address":"704 Buller St ",
    "sg:city":"Hastings",
    "sg:classifiers":[
        {
            "category":"Personal",
            "subcategory":"Massage",
            "type":"Services"
        }
    ],
    "sg:phone":"+64 6-878 6993",
    "sg:province":"Hawke's Bay",
    "sg:tags":[
        "services",
        "health",
        "-",
        "beauty",
        "fitness"
    ],
    "wof:name":"Helena's Beauty & Slimming",
    "wof:placetype":"venue"
},
  "geometry": {"coordinates":[-81.508163,29.711214],"type":"Point"}
}