{
  "type": "Feature",
  "properties": {
    "iso:country":"NZ",
    "sg:address":"Ruru St Waikiwi ",
    "sg:city":"Invercargill",
    "sg:orig_category":"Education And Training: General: Schools",
    "sg:phone":"+64 3-215 9379",
    "sg:province":"Southland",
    "wof:name":"Ruru School",
    "wof:placetype":"venue"
},
  "geometry": {"coordinates":[168.34738200000001,-46.376484],"type":"Point"}
}