{
  "type": "Feature",
  "properties": {
    "iso:country":"NZ",
    "sg:address":"84 Sturrocks Rd Redwood ",
    "sg:city":"Christchurch",
    "sg:orig_category":"Shopping: Accessories: Hats And Caps",
    "sg:phone":"+64 3-352 3587",
    "sg:province":"Canterbury",
    "wof:name":"Susan Rodgers Millinery",
    "wof:placetype":"venue"
},
  "geometry": {"coordinates":[172.625534,-43.467388],"type":"Point"}
}