{
  "type": "Feature",
  "properties": {
    "addr:full":"5 Arthurs Point Rd  Queenstown Otago",
    "addr:housenumber":"5",
    "addr:street":"Arthurs Point Rd",
    "iso:country":"NZ",
    "sg:address":"5 Arthurs Point Rd ",
    "sg:city":"Queenstown",
    "sg:classifiers":[
        {
            "category":"Professional",
            "subcategory":"Art Services",
            "type":"Services"
        }
    ],
    "sg:phone":"+64 3-442 6116",
    "sg:province":"Otago",
    "sg:tags":[
        "picture",
        "arts",
        "sport",
        "framing",
        "leisure"
    ],
    "wof:name":"Shotover Picture Framing",
    "wof:placetype":"venue"
},
  "geometry": {"coordinates":[168.67250100000001,-44.9879],"type":"Point"}
}