{
  "type": "Feature",
  "properties": {
    "addr:full":"158 Walnut Ave  Ashburton Canterbury",
    "addr:housenumber":"158",
    "addr:street":"Walnut Ave",
    "iso:country":"NZ",
    "sg:address":"158 Walnut Ave ",
    "sg:city":"Ashburton",
    "sg:classifiers":[
        {
            "category":"Bars & Pubs",
            "subcategory":"Lounge",
            "type":"Food & Drink"
        }
    ],
    "sg:phone":"+64 3-308 3826",
    "sg:province":"Canterbury",
    "sg:tags":[
        "baker",
        "-"
    ],
    "sg:website":"http://www.derlenbakery.co.nz",
    "wof:name":"Derlen Bakery Ltd",
    "wof:placetype":"venue"
},
  "geometry": {"coordinates":[-77.127831,39.012852],"type":"Point"}
}