{
  "type": "Feature",
  "properties": {
    "addr:full":"1206 High St Taita Lower  Hutt Wellington",
    "addr:housenumber":"1206",
    "addr:street":"High St",
    "iso:country":"NZ",
    "sg:address":"1206 High St Taita Lower ",
    "sg:city":"Hutt",
    "sg:orig_category":"Food And Drink: Meats: Butchers",
    "sg:phone":"+64 4-567 7341",
    "sg:province":"Wellington",
    "wof:name":"Reeds Butchery Co Ltd",
    "wof:placetype":"venue"
},
  "geometry": {"coordinates":[174.96090699999999,-41.179817],"type":"Point"}
}