{
  "type": "Feature",
  "properties": {
    "addr:full":"50 Childers Rd  Gisborne Gisborne",
    "addr:housenumber":"50",
    "addr:street":"Childers Rd",
    "iso:country":"NZ",
    "sg:address":"50 Childers Rd ",
    "sg:city":"Gisborne",
    "sg:orig_category":"Farming: Forestry",
    "sg:phone":"+64 6-863 2447",
    "sg:province":"Gisborne",
    "wof:name":"Logic Forest Solutions Ltd",
    "wof:placetype":"venue"
},
  "geometry": {"coordinates":[178.02581799999999,-38.668377],"type":"Point"}
}