{
  "type": "Feature",
  "properties": {
    "iso:country":"NZ",
    "sg:address":"495 b Nelson Rd ",
    "sg:city":"Gisborne",
    "sg:classifiers":[
        {
            "category":"Home & Garden",
            "subcategory":"Garden Supply",
            "type":"Retail Goods"
        }
    ],
    "sg:phone":"+64 6-867 7238",
    "sg:province":"Gisborne",
    "sg:tags":[
        "products",
        "nursery",
        "gardening"
    ],
    "wof:name":"Nursery Land",
    "wof:placetype":"venue"
},
  "geometry": {"coordinates":[177.987671,-38.644753],"type":"Point"}
}