{
  "type": "Feature",
  "properties": {
    "addr:full":"3/60 Lynden Ave Northcote  Auckland Auckland",
    "addr:housenumber":"3 / 60",
    "addr:street":"Lynden Ave",
    "iso:country":"NZ",
    "sg:address":"3/60 Lynden Ave Northcote ",
    "sg:city":"Auckland",
    "sg:classifiers":[
        {
            "category":"Shopping",
            "subcategory":"Bridal",
            "type":"Retail Goods"
        }
    ],
    "sg:phone":"+64 9-480 7174",
    "sg:province":"Auckland",
    "sg:tags":[
        "arrangements",
        "wear",
        "wedding"
    ],
    "wof:name":"Faye Marmont Fashions",
    "wof:placetype":"venue"
},
  "geometry": {"coordinates":[174.73237599999999,-36.791122],"type":"Point"}
}