{
  "type": "Feature",
  "properties": {
    "iso:country":"NZ",
    "sg:address":"193 Riddiford St Newtown ",
    "sg:city":"Wellington",
    "sg:classifiers":[
        {
            "category":"Food & Beverages",
            "subcategory":"Groceries & Convenience Stores",
            "type":"Retail Goods"
        }
    ],
    "sg:phone":"+64 4-389 2296",
    "sg:province":"Wellington",
    "sg:tags":[
        "foodstuff",
        "drink",
        "-"
    ],
    "wof:name":"Eastern Food Distributors Ltd",
    "wof:placetype":"venue"
},
  "geometry": {"coordinates":[174.780273,-41.314533],"type":"Point"}
}