{
  "type": "Feature",
  "properties": {
    "addr:full":"Hazelwood St Flaxmere  Hastings Hawke's Bay",
    "addr:street":"Hazelwood St",
    "iso:country":"NZ",
    "sg:address":"Hazelwood St Flaxmere ",
    "sg:city":"Hastings",
    "sg:orig_category":"Industrial: Abrasives: Abrasive Blasting",
    "sg:phone":"+64 6-879 9787",
    "sg:province":"Hawke's Bay",
    "wof:name":"Barley Sandblasting Ltd",
    "wof:placetype":"venue"
},
  "geometry": {"coordinates":[176.79631000000001,-39.614914],"type":"Point"}
}