{
  "type": "Feature",
  "properties": {
    "iso:country":"NZ",
    "sg:address":"8-10 King St Upper Hutt ",
    "sg:city":"Wellington",
    "sg:classifiers":[
        {
            "category":"Professional",
            "subcategory":"Detective & Security Services",
            "type":"Services"
        }
    ],
    "sg:phone":"+64 4-527 3762",
    "sg:province":"Wellington",
    "sg:tags":[
        "services",
        "automotive",
        "warrant",
        "fitness"
    ],
    "wof:name":"Stevens Motors",
    "wof:placetype":"venue"
},
  "geometry": {"coordinates":[174.90838600000001,-41.206631],"type":"Point"}
}