{
  "type": "Feature",
  "properties": {
    "iso:country":"NZ",
    "sg:address":"16 a Jellicoe Ave Stoke ",
    "sg:city":"Nelson",
    "sg:classifiers":[
        {
            "category":"Home & Garden",
            "subcategory":"Carpets & Floor Coverings",
            "type":"Retail Goods"
        }
    ],
    "sg:phone":"+64 3-547 1153",
    "sg:province":"Nelson",
    "sg:tags":[
        "cleaning",
        "furniture"
    ],
    "wof:name":"Top To Toe Cleaning Service",
    "wof:placetype":"venue"
},
  "geometry": {"coordinates":[173.23419189449999,-41.3128585815],"type":"Point"}
}