{
  "type": "Feature",
  "properties": {
    "iso:country":"NZ",
    "sg:address":"144 Thames St Wst ",
    "sg:city":"Morrinsville",
    "sg:classifiers":[
        {
            "category":"Retail",
            "subcategory":"Auto Repair",
            "type":"Services"
        }
    ],
    "sg:phone":"+64 7-889 7308",
    "sg:province":"Waikato",
    "sg:tags":[
        "automotive",
        "electric",
        "servicing"
    ],
    "wof:name":"Morrinsville Auto Electrical",
    "wof:placetype":"venue"
},
  "geometry": {"coordinates":[175.52577199999999,-37.658939],"type":"Point"}
}