{
  "type": "Feature",
  "properties": {
    "addr:full":"51 Barrys Point Rd Takapuna  Auckland Auckland",
    "addr:housenumber":"51",
    "addr:street":"Barrys Point Rd",
    "iso:country":"NZ",
    "sg:address":"51 Barrys Point Rd Takapuna ",
    "sg:city":"Auckland",
    "sg:orig_category":"Transport: Boats And Marine: Boats: Boat Dealers",
    "sg:phone":"+64 9-486 2422",
    "sg:province":"Auckland",
    "wof:name":"Takapuna Sailing Centre",
    "wof:placetype":"venue"
},
  "geometry": {"coordinates":[174.76487700000001,-36.792583],"type":"Point"}
}