{
  "type": "Feature",
  "properties": {
    "addr:full":"46 Paterson Ave West  Pukekohe Auckland",
    "addr:housenumber":"46",
    "addr:street":"Paterson Ave West",
    "iso:country":"NZ",
    "sg:address":"46 Paterson Ave West ",
    "sg:city":"Pukekohe",
    "sg:classifiers":[
        {
            "category":"Professional",
            "subcategory":"Art Services",
            "type":"Services"
        }
    ],
    "sg:phone":"+64 9-238 6491",
    "sg:province":"Auckland",
    "sg:tags":[
        "personal",
        "photographer",
        "services",
        "garden",
        "home"
    ],
    "wof:name":"Thorpe Studio",
    "wof:placetype":"venue"
},
  "geometry": {"coordinates":[174.890411,-37.205128],"type":"Point"}
}