{
  "type": "Feature",
  "properties": {
    "addr:full":"Main Rd Awakino  Mokau",
    "addr:street":"Main Rd",
    "iso:country":"NZ",
    "sg:address":"Main Rd Awakino ",
    "sg:city":"Mokau",
    "sg:orig_category":"Automotive: General Services: Service Stations",
    "sg:phone":"+64 6-752 9885",
    "wof:name":"Junction Service Station",
    "wof:placetype":"venue"
},
  "geometry": {"coordinates":[174.627914,-38.65432],"type":"Point"}
}