{
  "type": "Feature",
  "properties": {
    "addr:full":"109 Fitzherbert Ave Palmerston  Palmerston North Manawatu-Wanganui",
    "addr:housenumber":"109",
    "addr:street":"Fitzherbert Ave",
    "iso:country":"NZ",
    "sg:address":"109 Fitzherbert Ave Palmerston ",
    "sg:city":"Palmerston North",
    "sg:orig_category":"Home And Garden: General",
    "sg:phone":"+64 6-356 8688",
    "sg:province":"Manawatu-Wanganui",
    "sg:website":"http://www.harcourts.co.nz",
    "wof:name":"Harcourts Real Estate",
    "wof:placetype":"venue"
},
  "geometry": {"coordinates":[175.614182,-40.359859],"type":"Point"}
}