{
  "type": "Feature",
  "properties": {
    "addr:full":"66 Scruttons Rd Heathcote  Christchurch Canterbury",
    "addr:housenumber":"66",
    "addr:street":"Scruttons Rd",
    "iso:country":"NZ",
    "sg:address":"66 Scruttons Rd Heathcote ",
    "sg:city":"Christchurch",
    "sg:orig_category":"Industrial: Services: Gasfitters",
    "sg:phone":"+64 3-384 8780",
    "sg:province":"Canterbury",
    "wof:name":"Gas, Plumbing & Oil Installation Services",
    "wof:placetype":"venue"
},
  "geometry": {"coordinates":[172.693985,-43.568279],"type":"Point"}
}