{
  "type": "Feature",
  "properties": {
    "iso:country":"NZ",
    "sg:address":"Cnr Reads Quay & Pitt St ",
    "sg:city":"Gisborne",
    "sg:classifiers":[
        {
            "category":"Travel",
            "subcategory":"Hotels & Motels",
            "type":"Entertainment"
        }
    ],
    "sg:phone":"+64 6-867 8847",
    "sg:province":"Gisborne",
    "sg:tags":[
        "lodge",
        "tourism",
        "accommodation"
    ],
    "wof:name":"Pacific Harbour Motor Inn",
    "wof:placetype":"venue"
},
  "geometry": {"coordinates":[177.836197,-38.252838],"type":"Point"}
}