{
  "type": "Feature",
  "properties": {
    "iso:country":"NZ",
    "sg:address":"1 Stafford St ",
    "sg:city":"Timaru",
    "sg:classifiers":[
        {
            "category":"Food Court",
            "type":"Food & Drink"
        }
    ],
    "sg:phone":"+64 3-684 3145",
    "sg:province":"Canterbury",
    "sg:tags":[
        "packer",
        "processing",
        "processor"
    ],
    "wof:name":"Milling Co Timaru",
    "wof:placetype":"venue"
},
  "geometry": {"coordinates":[171.25657699999999,-44.402382],"type":"Point"}
}