{
  "type": "Feature",
  "properties": {
    "addr:full":"35 Victoria St  Wellington Wellington",
    "addr:housenumber":"35",
    "addr:street":"Victoria St",
    "iso:country":"NZ",
    "sg:address":"35 Victoria St ",
    "sg:city":"Wellington",
    "sg:classifiers":[
        {
            "category":"Health Services",
            "subcategory":"Hospital",
            "type":"Services"
        }
    ],
    "sg:phone":"+64 4-499 1992",
    "sg:province":"Wellington",
    "sg:tags":[
        "medical",
        "beauty"
    ],
    "wof:name":"Family Planning Association (FPA)",
    "wof:placetype":"venue"
},
  "geometry": {"coordinates":[-3.231961,50.979923],"type":"Point"}
}