{
  "type": "Feature",
  "properties": {
    "addr:full":"52-56 Aorangi St  Feilding Manawatu-Wanganui",
    "addr:housenumber":"52-56",
    "addr:street":"Aorangi St",
    "iso:country":"NZ",
    "sg:address":"52-56 Aorangi St ",
    "sg:city":"Feilding",
    "sg:orig_category":"Farming: Horticulture: Grain And Seed",
    "sg:phone":"+64 6-323 3361",
    "sg:province":"Manawatu-Wanganui",
    "wof:name":"Manawatu Grain & Seed Limited",
    "wof:placetype":"venue"
},
  "geometry": {"coordinates":[175.54719499999999,-40.224236],"type":"Point"}
}