{
  "type": "Feature",
  "properties": {
    "addr:full":"88a Evans St  Timaru Canterbury",
    "addr:housenumber":"88a",
    "addr:street":"Evans St",
    "iso:country":"NZ",
    "sg:address":"88a Evans St ",
    "sg:city":"Timaru",
    "sg:classifiers":[
        {
            "category":"Fast Food",
            "type":"Food & Drink"
        }
    ],
    "sg:phone":"+64 800 864 646",
    "sg:province":"Canterbury",
    "sg:tags":[
        "wining",
        "dining",
        "takeaway"
    ],
    "wof:name":"Pizza To-Go-Go",
    "wof:placetype":"venue"
},
  "geometry": {"coordinates":[171.241119,-44.373558],"type":"Point"}
}