{
  "type": "Feature",
  "properties": {
    "addr:full":"21 Hewletts Rd Mt  Maunganui Bay of Plenty",
    "addr:housenumber":"21",
    "addr:street":"Hewletts Rd;Maunganui",
    "iso:country":"NZ",
    "sg:address":"21 Hewletts Rd Mt ",
    "sg:city":"Maunganui",
    "sg:orig_category":"Home And Garden: Gardening: Products: Garden Ornaments",
    "sg:phone":"+64 7-572 1151",
    "sg:province":"Bay of Plenty",
    "wof:name":"Rockz & Stonz Ltd",
    "wof:placetype":"venue"
},
  "geometry": {"coordinates":[176.18627900000001,-37.641048],"type":"Point"}
}