{
  "type": "Feature",
  "properties": {
    "iso:country":"NZ",
    "sg:address":"Auckland International",
    "sg:city":"Auckland",
    "sg:classifiers":[
        {
            "category":"Banks & Credit Unions",
            "subcategory":"Bank",
            "type":"Services"
        }
    ],
    "sg:phone":"+64 9-275 9259",
    "sg:province":"Auckland",
    "wof:name":"Bank of New Zealand",
    "wof:placetype":"venue"
},
  "geometry": {"coordinates":[174.782104,-37.008541],"type":"Point"}
}