{
  "type": "Feature",
  "properties": {
    "addr:full":"25 Centennial Hwy Ngauranga  Wellington Wellington",
    "addr:housenumber":"25",
    "addr:street":"Centennial Hwy",
    "iso:country":"NZ",
    "sg:address":"25 Centennial Hwy Ngauranga ",
    "sg:city":"Wellington",
    "sg:classifiers":[
        {
            "category":"Home & Garden",
            "subcategory":"Building Materials",
            "type":"Retail Goods"
        }
    ],
    "sg:phone":"+64 4-916 9000",
    "sg:province":"Wellington",
    "sg:tags":[
        "electrician",
        "related"
    ],
    "sg:website":"http://www.indeserve.co.nz/",
    "wof:name":"IndeServe Limited",
    "wof:placetype":"venue"
},
  "geometry": {"coordinates":[174.81222500000001,-41.242535],"type":"Point"}
}