{
  "type": "Feature",
  "properties": {
    "addr:full":"238 Centaurus Rd St Martins  Christchurch Canterbury",
    "addr:housenumber":"238",
    "addr:street":"Centaurus Rd",
    "iso:country":"NZ",
    "sg:address":"238 Centaurus Rd St Martins ",
    "sg:city":"Christchurch",
    "sg:classifiers":[
        {
            "category":"Retail",
            "subcategory":"Auto Repair",
            "type":"Services"
        }
    ],
    "sg:phone":"+64 3-332 6138",
    "sg:province":"Canterbury",
    "sg:tags":[
        "automotive",
        "servicing"
    ],
    "sg:website":"http://www.yellowpages.co.nz/for/stmartinsgarage/dp55623.html",
    "wof:name":"St Martins Garage Ltd",
    "wof:placetype":"venue"
},
  "geometry": {"coordinates":[172.65237400000001,-43.555965],"type":"Point"}
}