{
  "type": "Feature",
  "properties": {
    "addr:full":"29 Crowther St Avondale  Auckland Auckland",
    "addr:housenumber":"29",
    "addr:street":"Crowther St",
    "iso:country":"NZ",
    "sg:address":"29 Crowther St Avondale ",
    "sg:city":"Auckland",
    "sg:classifiers":[
        {
            "category":"Shopping",
            "subcategory":"Pets & Pet Supplies",
            "type":"Retail Goods"
        }
    ],
    "sg:phone":"+64 9-828 3410",
    "sg:province":"Auckland",
    "sg:tags":[
        "boarding",
        "garden",
        "pets",
        "catteries",
        "home",
        "kennel"
    ],
    "wof:name":"Avondale Pussy Cat Lodge",
    "wof:placetype":"venue"
},
  "geometry": {"coordinates":[174.693634,-36.912167],"type":"Point"}
}