{
  "type": "Feature",
  "properties": {
    "addr:full":"363 Gt North Rd Henderson  Auckland Auckland",
    "addr:housenumber":"363",
    "addr:street":"Gt North Rd",
    "iso:country":"NZ",
    "sg:address":"363 Gt North Rd Henderson ",
    "sg:city":"Auckland",
    "sg:classifiers":[
        {
            "category":"Recreation",
            "type":"Entertainment"
        }
    ],
    "sg:phone":"+64 9-838 9782",
    "sg:province":"Auckland",
    "sg:tags":[
        "sport",
        "tramping",
        "leisure",
        "camping"
    ],
    "wof:name":"Henderson Camping Centre",
    "wof:placetype":"venue"
},
  "geometry": {"coordinates":[174.632904,-36.879646],"type":"Point"}
}