{
  "type": "Feature",
  "properties": {
    "addr:full":"1/87 Clyde Rd Browns Bay  Auckland Auckland",
    "addr:housenumber":"1 / 87",
    "addr:street":"Clyde Rd",
    "iso:country":"NZ",
    "sg:address":"1/87 Clyde Rd Browns Bay ",
    "sg:city":"Auckland",
    "sg:classifiers":[
        {
            "category":"Internet Cafe",
            "subcategory":"None",
            "type":"Food & Drink"
        }
    ],
    "sg:phone":"+64 9-479 4229",
    "sg:province":"Auckland",
    "sg:tags":[
        "wining",
        "dining"
    ],
    "wof:name":"The Icon Internet Cafe",
    "wof:placetype":"venue"
},
  "geometry": {"coordinates":[174.74847399999999,-36.714287],"type":"Point"}
}