{
  "type": "Feature",
  "properties": {
    "iso:country":"NZ",
    "sg:address":"Fitzgerald La ",
    "sg:city":"Hawera",
    "sg:classifiers":[
        {
            "category":"Travel",
            "subcategory":"Bed & Breakfast",
            "type":"Entertainment"
        }
    ],
    "sg:phone":"+64 6-278 5195",
    "sg:province":"Taranaki",
    "sg:tags":[
        "tourism"
    ],
    "sg:website":"http://www.yellowpages.co.nz/for/mahonyhire/dp31583.html",
    "wof:name":"Mahony Hire Ltd",
    "wof:placetype":"venue"
},
  "geometry": {"coordinates":[174.27011100000001,-39.566235],"type":"Point"}
}