{
  "type": "Feature",
  "properties": {
    "addr:full":"C//741-743 Te Atatu Rd Te Atatu Peninsula  Auckland Auckland",
    "addr:housenumber":"741-743",
    "addr:street":"C / /;Te Atatu Rd",
    "iso:country":"NZ",
    "sg:address":"C//741-743 Te Atatu Rd Te Atatu Peninsula ",
    "sg:city":"Auckland",
    "sg:orig_category":"Industrial: Packaging: Bags",
    "sg:phone":"+64 9-834 1343",
    "sg:province":"Auckland",
    "wof:name":"Polymark Packaging Ltd",
    "wof:placetype":"venue"
},
  "geometry": {"coordinates":[174.65112300000001,-36.841228],"type":"Point"}
}