{
  "type": "Feature",
  "properties": {
    "addr:full":"564 Coatesville Rd Riverhead  Auckland Auckland",
    "addr:housenumber":"564",
    "addr:street":"Coatesville Rd",
    "iso:country":"NZ",
    "sg:address":"564 Coatesville Rd Riverhead ",
    "sg:city":"Auckland",
    "sg:orig_category":"Sports And Leisure: Sports: Equestrian: Riding Schools",
    "sg:phone":"+64 9-415 8480",
    "sg:province":"Auckland",
    "wof:name":"Maree Green Equestrian",
    "wof:placetype":"venue"
},
  "geometry": {"coordinates":[174.59385700000001,-36.760101],"type":"Point"}
}