{
  "type": "Feature",
  "properties": {
    "iso:country":"NZ",
    "sg:address":"16 Philson Tce Browns Bay ",
    "sg:city":"Auckland",
    "sg:orig_category":"Transport: Boats And Marine: Services",
    "sg:phone":"+64 9-478 3286",
    "sg:province":"Auckland",
    "wof:name":"Maddick Marine Surveys Ltd",
    "wof:placetype":"venue"
},
  "geometry": {"coordinates":[174.74411000000001,-36.720451],"type":"Point"}
}