{
  "type": "Feature",
  "properties": {
    "iso:country":"NZ",
    "sg:address":"Galloway St Hamilton East ",
    "sg:city":"Hamilton",
    "sg:classifiers":[
        {
            "category":"Personal",
            "subcategory":"Massage",
            "type":"Services"
        }
    ],
    "sg:phone":"+64 7-856 0055",
    "sg:province":"Waikato",
    "sg:tags":[
        "services",
        "health",
        "-",
        "beauty",
        "fitness"
    ],
    "wof:name":"Tinas Nurture House",
    "wof:placetype":"venue"
},
  "geometry": {"coordinates":[175.30229199999999,-37.79401],"type":"Point"}
}