{
  "type": "Feature",
  "properties": {
    "addr:full":"79 Eugenia Rse Manukau City  Auckland Auckland",
    "addr:housenumber":"79",
    "addr:street":"Eugenia Rse",
    "iso:country":"NZ",
    "sg:address":"79 Eugenia Rse Manukau City ",
    "sg:city":"Auckland",
    "sg:classifiers":[
        {
            "category":"Manufacturing",
            "subcategory":"Tools & Machinery",
            "type":"Manufacturing & Wholesale Goods"
        }
    ],
    "sg:phone":"+64 9-266 0709",
    "sg:province":"Auckland",
    "sg:tags":[
        "equipment",
        "industrial",
        "hydraulic"
    ],
    "wof:name":"Swivel Consultants (NZ) Ltd",
    "wof:placetype":"venue"
},
  "geometry": {"coordinates":[174.88145399999999,-36.98967],"type":"Point"}
}