{
  "type": "Feature",
  "properties": {
    "iso:country":"NZ",
    "sg:address":"52-54 Kimbolton Rd ",
    "sg:city":"Feilding",
    "sg:classifiers":[
        {
            "category":"Home & Garden",
            "subcategory":"Garden Supply",
            "type":"Retail Goods"
        }
    ],
    "sg:phone":"+64 6-323 4484",
    "sg:province":"Manawatu-Wanganui",
    "sg:tags":[
        "trainer",
        "breeder",
        "/",
        "pets",
        "animal"
    ],
    "wof:name":"South Devon Cattle Society of NZ",
    "wof:placetype":"venue"
},
  "geometry": {"coordinates":[175.565201,-40.22578],"type":"Point"}
}