{
  "type": "Feature",
  "properties": {
    "iso:country":"NZ",
    "sg:address":"Cnr Mathews Ave & Empire St ",
    "sg:city":"Kaitaia",
    "sg:classifiers":[
        {
            "category":"Wholesale",
            "subcategory":"Hardware",
            "type":"Manufacturing & Wholesale Goods"
        }
    ],
    "sg:phone":"+64 9-408 0777",
    "sg:province":"Northland",
    "sg:tags":[
        "gardening",
        "garden",
        "chainsaw",
        "products",
        "brush",
        "home",
        "cutter"
    ],
    "wof:name":"Far North Chainsaws & Mowers",
    "wof:placetype":"venue"
},
  "geometry": {"coordinates":[173.259445,-35.114208],"type":"Point"}
}