{
  "type": "Feature",
  "properties": {
    "addr:full":"64 Birchwood Rd  Ohai",
    "addr:housenumber":"64",
    "addr:street":"Birchwood Rd",
    "iso:country":"NZ",
    "sg:address":"64 Birchwood Rd ",
    "sg:city":"Ohai",
    "sg:classifiers":[
        {
            "category":"Retail",
            "subcategory":"Laundry & Dry Cleaning",
            "type":"Services"
        }
    ],
    "sg:phone":"+64 3-225 4244",
    "sg:tags":[
        "product",
        "wool",
        "clothing",
        "fabric"
    ],
    "wof:name":"McKitterick David Woolbuyer",
    "wof:placetype":"venue"
},
  "geometry": {"coordinates":[167.954193,-45.933693],"type":"Point"}
}