{
  "type": "Feature",
  "properties": {
    "addr:full":"Rust Ave  Whangarei Northland",
    "addr:street":"Rust Ave",
    "iso:country":"NZ",
    "sg:address":"Rust Ave ",
    "sg:city":"Whangarei",
    "sg:classifiers":[
        {
            "category":"Banks & Credit Unions",
            "subcategory":"Investment Brokerage",
            "type":"Services"
        }
    ],
    "sg:phone":"+64 9-430 0471",
    "sg:province":"Northland",
    "sg:tags":[
        "personal",
        "accountant",
        "chartered",
        "-",
        "finance"
    ],
    "wof:name":"Petherick Kennedy",
    "wof:placetype":"venue"
},
  "geometry": {"coordinates":[174.31698600000001,-35.722858],"type":"Point"}
}