{
  "type": "Feature",
  "properties": {
    "iso:country":"NZ",
    "sg:address":"14 A Atanga Ave Epsom ",
    "sg:city":"Auckland",
    "sg:classifiers":[
        {
            "category":"Professional",
            "subcategory":"Art Services",
            "type":"Services"
        }
    ],
    "sg:phone":"+64 9-638 9201",
    "sg:province":"Auckland",
    "sg:tags":[
        "hire",
        "sport",
        "leisure",
        "arts",
        "consultancy"
    ],
    "wof:name":"Artscape Limited",
    "wof:placetype":"venue"
},
  "geometry": {"coordinates":[174.77356,-36.876179],"type":"Point"}
}