{
  "type": "Feature",
  "properties": {
    "addr:full":"Unit 5 & 6 11 Hurley Rd PO Box 1593 Paraparaumu, Beach  Paraparaumu Wellington",
    "addr:housenumber":"unit 5 &;11;box 1593",
    "addr:street":"6;Hurley Rd;Beach Paraparaumu",
    "iso:country":"NZ",
    "sg:address":"Unit 5 & 6 11 Hurley Rd PO Box 1593 Paraparaumu, Beach ",
    "sg:city":"Paraparaumu",
    "sg:classifiers":[
        {
            "category":"Building & Trades",
            "subcategory":"Plumbing",
            "type":"Services"
        }
    ],
    "sg:phone":"+64 4-902 8800",
    "sg:province":"Wellington",
    "sg:tags":[
        "home",
        "plumber",
        "garden",
        "related"
    ],
    "wof:name":"Klee Plumbers Ltd",
    "wof:placetype":"venue"
},
  "geometry": {"coordinates":[175.00799599999999,-40.910461],"type":"Point"}
}