{
  "type": "Feature",
  "properties": {
    "addr:full":"Awapuni Racecourse Palmerston  Palmerston North Manawatu-Wanganui",
    "addr:street":"Racecourse",
    "iso:country":"NZ",
    "sg:address":"Awapuni Racecourse Palmerston ",
    "sg:city":"Palmerston North",
    "sg:orig_category":"Sports And Leisure: General: Clubs",
    "sg:phone":"+64 6-356 4940",
    "sg:province":"Manawatu-Wanganui",
    "wof:name":"Awapuni Racing Centre",
    "wof:placetype":"venue"
},
  "geometry": {"coordinates":[175.584656,-40.37672],"type":"Point"}
}