{
  "type": "Feature",
  "properties": {
    "iso:country":"NZ",
    "sg:address":"528 Sandringham Rd Sandringham ",
    "sg:city":"Auckland",
    "sg:classifiers":[
        {
            "category":"Bars & Pubs",
            "subcategory":"Lounge",
            "type":"Food & Drink"
        }
    ],
    "sg:phone":"+64 9-815 2307",
    "sg:province":"Auckland",
    "sg:tags":[
        "-",
        "asian"
    ],
    "wof:name":"Khyber Food & Spices(Jairaj NZ Ltd)",
    "wof:placetype":"venue"
},
  "geometry": {"coordinates":[174.73661799999999,-36.891369],"type":"Point"}
}