{
  "type": "Feature",
  "properties": {
    "addr:full":"cnr Regan & Juliet Sts  Stratford",
    "addr:street":"Cnr Regan & Juliet Sts",
    "iso:country":"NZ",
    "sg:address":"cnr Regan & Juliet Sts ",
    "sg:city":"Stratford",
    "sg:orig_category":"Automotive: General Services: Rental Vehicles",
    "sg:phone":"+64 6-765 7754",
    "wof:name":"Rent-a-Dent Quality Rental Vehicles",
    "wof:placetype":"venue"
},
  "geometry": {"coordinates":[-119.824966,36.189419],"type":"Point"}
}