{
  "type": "Feature",
  "properties": {
    "addr:full":"247 Stanley Rd  Whakatane Bay of Plenty",
    "addr:housenumber":"247",
    "addr:street":"Stanley Rd",
    "iso:country":"NZ",
    "sg:address":"247 Stanley Rd ",
    "sg:city":"Whakatane",
    "sg:classifiers":[
        {
            "category":"Retail",
            "subcategory":"Laundry & Dry Cleaning",
            "type":"Services"
        }
    ],
    "sg:phone":"+64 7-312 5083",
    "sg:province":"Bay of Plenty",
    "sg:tags":[
        "product",
        "wool",
        "clothing",
        "fabric"
    ],
    "wof:name":"Eastern Bay Wools",
    "wof:placetype":"venue"
},
  "geometry": {"coordinates":[176.98419200000001,-37.965305],"type":"Point"}
}