{
  "type": "Feature",
  "properties": {
    "iso:country":"NZ",
    "sg:address":"2/71 Gt South Rd Papakura ",
    "sg:city":"Auckland",
    "sg:classifiers":[
        {
            "category":"Autos & Motor Vehicles",
            "subcategory":"Auto Supplies",
            "type":"Retail Goods"
        }
    ],
    "sg:phone":"+64 9-298 8188",
    "sg:province":"Auckland",
    "sg:tags":[
        "car",
        "supplies",
        "part",
        "automotive",
        "paint"
    ],
    "wof:name":"Shanes Car Colours Ltd",
    "wof:placetype":"venue"
},
  "geometry": {"coordinates":[174.93988,-37.058464],"type":"Point"}
}