{
  "type": "Feature",
  "properties": {
    "iso:country":"NZ",
    "sg:address":"112 Johnsonville Rd Johnsonville ",
    "sg:city":"Wellington",
    "sg:classifiers":[
        {
            "category":"Retail",
            "subcategory":"Laundry & Dry Cleaning",
            "type":"Services"
        }
    ],
    "sg:phone":"+64 4-478 9494",
    "sg:province":"Wellington",
    "sg:tags":[
        "repair",
        "clothing",
        "fabric"
    ],
    "wof:name":"Johnsonville Laundrette",
    "wof:placetype":"venue"
},
  "geometry": {"coordinates":[174.807068,-41.225006],"type":"Point"}
}