{
  "type": "Feature",
  "properties": {
    "iso:country":"NZ",
    "sg:address":"114 High St ",
    "sg:city":"Hawera",
    "sg:orig_category":"Food And Drink: Meats: Butchers",
    "sg:phone":"+64 6-278 6566",
    "sg:province":"Taranaki",
    "wof:name":"Berg's Butchery",
    "wof:placetype":"venue"
},
  "geometry": {"coordinates":[174.282898,-39.588985],"type":"Point"}
}