{
  "type": "Feature",
  "properties": {
    "iso:country":"NZ",
    "sg:address":"Chartwell Sq ",
    "sg:city":"Hamilton",
    "sg:orig_category":"Health And Beauty: Beauty: Hairdressers",
    "sg:phone":"+64 7-854 8392",
    "sg:province":"Waikato",
    "wof:name":"Rodney Wayne Hairdressing",
    "wof:placetype":"venue"
},
  "geometry": {"coordinates":[175.27124000000001,-37.763653],"type":"Point"}
}