{
  "type": "Feature",
  "properties": {
    "addr:full":"95 Coronation Rd Mangere Bridge  Auckland Auckland",
    "addr:housenumber":"95",
    "addr:street":"Coronation Rd",
    "iso:country":"NZ",
    "sg:address":"95 Coronation Rd Mangere Bridge ",
    "sg:city":"Auckland",
    "sg:classifiers":[
        {
            "category":"Shopping",
            "subcategory":"Pets & Pet Supplies",
            "type":"Retail Goods"
        }
    ],
    "sg:phone":"+64 9-636 6732",
    "sg:province":"Auckland",
    "sg:tags":[
        "home",
        "grooming",
        "garden",
        "pets"
    ],
    "wof:name":"Auckland Animal Grooming Centre & Paws-A-While Pet Supplies",
    "wof:placetype":"venue"
},
  "geometry": {"coordinates":[174.789627,-36.947872],"type":"Point"}
}