{
  "type": "Feature",
  "properties": {
    "addr:full":"PO Box 58027  Whitby Wellington",
    "addr:housenumber":"po box",
    "addr:postcode":"58027",
    "iso:country":"NZ",
    "sg:address":"PO Box 58027 ",
    "sg:city":"Whitby",
    "sg:classifiers":[
        {
            "category":"Organizations",
            "subcategory":"Labor Organization",
            "type":"Services"
        }
    ],
    "sg:phone":"+64 800 113 901",
    "sg:province":"Wellington",
    "sg:tags":[
        "control",
        "specialist",
        "industrial",
        "equipment",
        "machinery",
        "ultra-violet"
    ],
    "wof:name":"Glasshield 2000 - The Ultimate U.V. Protection",
    "wof:placetype":"venue"
},
  "geometry": {"coordinates":[-81.191002,37.663349],"type":"Point"}
}