{
  "type": "Feature",
  "properties": {
    "addr:full":"Kokohuia Rd Opononi  Kaikohe",
    "addr:street":"Kokohuia Rd",
    "iso:country":"NZ",
    "sg:address":"Kokohuia Rd Opononi ",
    "sg:city":"Kaikohe",
    "sg:classifiers":[
        {
            "category":"Recreation",
            "type":"Entertainment"
        }
    ],
    "sg:phone":"+64 9-405 8872",
    "sg:tags":[
        "shopping",
        "hunting",
        "fishing",
        "retailers",
        "sport",
        "trip"
    ],
    "wof:name":"Hokianga Express Charters",
    "wof:placetype":"venue"
},
  "geometry": {"coordinates":[173.39033499999999,-35.506851],"type":"Point"}
}