{
  "type": "Feature",
  "properties": {
    "addr:full":"1 Greys Ave Auckland City  Auckland Auckland",
    "addr:housenumber":"1",
    "addr:street":"Greys Ave",
    "iso:country":"NZ",
    "sg:address":"1 Greys Ave Auckland City ",
    "sg:city":"Auckland",
    "sg:classifiers":[
        {
            "category":"Sports & Exercise",
            "subcategory":"Climbing Gym",
            "type":"Entertainment"
        }
    ],
    "sg:phone":"+64 9-379 2020",
    "sg:province":"Auckland",
    "sg:tags":[
        "-",
        "leisure",
        "sports"
    ],
    "sg:website":"http://www.akcity.govt.nz",
    "wof:name":"Auckland City Council",
    "wof:placetype":"venue"
},
  "geometry": {"coordinates":[174.76226800000001,-36.853123],"type":"Point"}
}