{
  "type": "Feature",
  "properties": {
    "addr:full":"New Zealand wide Te Awamutu  Hamilton Waikato",
    "addr:street":"Wide Te",
    "iso:country":"NZ",
    "sg:address":"New Zealand wide Te Awamutu ",
    "sg:city":"Hamilton",
    "sg:classifiers":[
        {
            "category":"Shopping",
            "subcategory":"Musical Instruments",
            "type":"Retail Goods"
        }
    ],
    "sg:phone":"+64 800 665 555",
    "sg:province":"Waikato",
    "sg:tags":[
        "sport",
        "music",
        "leisure"
    ],
    "sg:website":"http://www.appliancesdirect.co.nz",
    "wof:name":"Appliances Direct",
    "wof:placetype":"venue"
},
  "geometry": {"coordinates":[175.319244,-38.00964],"type":"Point"}
}