{
  "type": "Feature",
  "properties": {
    "addr:full":"96 Marsden Rd  Paihia Northland",
    "addr:housenumber":"96",
    "addr:street":"Marsden Rd",
    "iso:country":"NZ",
    "sg:address":"96 Marsden Rd ",
    "sg:city":"Paihia",
    "sg:classifiers":[
        {
            "category":"Sports & Exercise",
            "subcategory":"Sports Center",
            "type":"Entertainment"
        }
    ],
    "sg:phone":"+64 9-402 7722",
    "sg:province":"Northland",
    "sg:tags":[
        "sporting",
        "sports",
        "-",
        "leisure",
        "facility"
    ],
    "wof:name":"Paihia Gym",
    "wof:placetype":"venue"
},
  "geometry": {"coordinates":[174.085556,-35.278419],"type":"Point"}
}