{
  "type": "Feature",
  "properties": {
    "iso:country":"NZ",
    "sg:address":"272 Parnell Rd ",
    "sg:city":"Auckland",
    "sg:classifiers":[
        {
            "category":"Arts & Performance",
            "subcategory":"Art Gallery",
            "type":"Entertainment"
        }
    ],
    "sg:phone":"+64 9-379 4010",
    "sg:province":"Auckland",
    "sg:tags":[
        "arts",
        "sport",
        "leisure"
    ],
    "sg:website":"http://www.internationalartcentre.co.nz",
    "wof:name":"International Art Centre",
    "wof:placetype":"venue"
},
  "geometry": {"coordinates":[174.781052,-36.85619],"type":"Point"}
}