{
  "type": "Feature",
  "properties": {
    "iso:country":"NZ",
    "sg:address":"54 Carbine Rd Mt Wellington ",
    "sg:city":"Auckland",
    "sg:orig_category":"Industrial: Chemicals And Compounds: Pharmaceuticals",
    "sg:phone":"+64 9-570 1080",
    "sg:province":"Auckland",
    "wof:name":"Zuellig Pharma Limited",
    "wof:placetype":"venue"
},
  "geometry": {"coordinates":[174.846298,-36.914108],"type":"Point"}
}