{
  "type": "Feature",
  "properties": {
    "addr:full":"11 Channel View Rd Campbells Bay  Auckland Auckland",
    "addr:housenumber":"11",
    "addr:street":"Channel View Rd",
    "iso:country":"NZ",
    "sg:address":"11 Channel View Rd Campbells Bay ",
    "sg:city":"Auckland",
    "sg:classifiers":[
        {
            "category":"Arena",
            "subcategory":"Sports Club",
            "type":"Entertainment"
        }
    ],
    "sg:phone":"+64 9-479 5681",
    "sg:province":"Auckland",
    "sg:tags":[
        "arts",
        "writer",
        "leisure",
        "author"
    ],
    "wof:name":"Richards Literary Agency",
    "wof:placetype":"venue"
},
  "geometry": {"coordinates":[174.75659200000001,-36.745159],"type":"Point"}
}