{
  "type": "Feature",
  "properties": {
    "iso:country":"NZ",
    "sg:address":"Erua Ski Lodge State Highway 4 National Park ",
    "sg:city":"Taumarunui",
    "sg:classifiers":[
        {
            "category":"Travel",
            "subcategory":"Travel Agent",
            "type":"Entertainment"
        }
    ],
    "sg:phone":"+64 7-892 2894",
    "sg:tags":[
        "tourism",
        "-",
        "accommodation",
        "booking"
    ],
    "wof:name":"National Park District Accommodation Bureau",
    "wof:placetype":"venue"
},
  "geometry": {"coordinates":[175.255249,-38.880814],"type":"Point"}
}