{
  "type": "Feature",
  "properties": {
    "addr:full":"885 Mt Albert Rd Mt Albert  Auckland Auckland",
    "addr:housenumber":"885",
    "addr:street":"Mt Albert Rd",
    "iso:country":"NZ",
    "sg:address":"885 Mt Albert Rd Mt Albert ",
    "sg:city":"Auckland",
    "sg:orig_category":"Shopping: Retail Stores: Books: Books - Secondhand",
    "sg:phone":"+64 9-846 5208",
    "sg:province":"Auckland",
    "wof:name":"China Book Centre",
    "wof:placetype":"venue"
},
  "geometry": {"coordinates":[174.714798,-36.88784],"type":"Point"}
}