{
  "type": "Feature",
  "properties": {
    "addr:full":"32 B Honan Pl Avondale  Auckland Auckland",
    "addr:housenumber":"32 b",
    "addr:street":"Honan Pl",
    "iso:country":"NZ",
    "sg:address":"32 B Honan Pl Avondale ",
    "sg:city":"Auckland",
    "sg:orig_category":"Industrial: Abrasives: Abrasive Blasting",
    "sg:phone":"+64 9-828 0720",
    "sg:province":"Auckland",
    "wof:name":"Avondale Blasting & Coatings Ltd",
    "wof:placetype":"venue"
},
  "geometry": {"coordinates":[174.690933,-36.8932],"type":"Point"}
}