{
  "type": "Feature",
  "properties": {
    "iso:country":"NZ",
    "sg:address":"317 Pakuranga Rd Pakuranga ",
    "sg:city":"Auckland",
    "sg:orig_category":"Health And Beauty: Specialists: Chiropractors",
    "sg:phone":"+64 9-576 5169",
    "sg:province":"Auckland",
    "wof:name":"Pakuranga Chiropractic Clinic",
    "wof:placetype":"venue"
},
  "geometry": {"coordinates":[174.889725,-36.906124],"type":"Point"}
}