{
  "type": "Feature",
  "properties": {
    "addr:full":"Lagoon Rd  Picton Marlborough",
    "addr:street":"Lagoon Rd",
    "iso:country":"NZ",
    "sg:address":"Lagoon Rd ",
    "sg:city":"Picton",
    "sg:orig_category":"Transport: Boats And Marine: Transport",
    "sg:phone":"+64 3-573 8880",
    "sg:province":"Marlborough",
    "wof:name":"O'Donnell Park Barging Ltd",
    "wof:placetype":"venue"
},
  "geometry": {"coordinates":[174.000732,-41.28915],"type":"Point"}
}