{
  "type": "Feature",
  "properties": {
    "addr:full":"320 Mt Albert Rd Mt Roskill  Auckland Auckland",
    "addr:housenumber":"320",
    "addr:street":"Mt Albert Rd",
    "iso:country":"NZ",
    "sg:address":"320 Mt Albert Rd Mt Roskill ",
    "sg:city":"Auckland",
    "sg:classifiers":[
        {
            "category":"Health Services",
            "subcategory":"Health Practitioner",
            "type":"Services"
        }
    ],
    "sg:phone":"+64 9-629 1575",
    "sg:province":"Auckland",
    "sg:tags":[
        "services",
        "beauty",
        "acupuncturists"
    ],
    "wof:name":"Lifewell Chinese Medical Centre",
    "wof:placetype":"venue"
},
  "geometry": {"coordinates":[174.74041700000001,-36.903542],"type":"Point"}
}