{
  "type": "Feature",
  "properties": {
    "addr:full":"Franz Josef Franz Josef  Glacier",
    "iso:country":"NZ",
    "sg:address":"Franz Josef Franz Josef ",
    "sg:city":"Glacier",
    "sg:classifiers":[
        {
            "category":"Landmark",
            "subcategory":"Tourist Information",
            "type":"Public Place"
        }
    ],
    "sg:phone":"+64 3-752 0047",
    "sg:tags":[
        "travel",
        "tourism",
        "tour",
        "sightseeing"
    ],
    "sg:website":"http://www.nzguides.com",
    "wof:name":"Guiding Company At Franz Josef Glacier Ltd",
    "wof:placetype":"venue"
},
  "geometry": {"coordinates":[-121.956535,48.891335],"type":"Point"}
}