{
  "type": "Feature",
  "properties": {
    "addr:full":"PO Box 260005 Howick East  Auckland Auckland",
    "addr:housenumber":"po",
    "addr:postcode":"260005;east",
    "addr:street":"Box",
    "iso:country":"NZ",
    "sg:address":"PO Box 260005 Howick East ",
    "sg:city":"Auckland",
    "sg:classifiers":[
        {
            "category":"Banks & Credit Unions",
            "subcategory":"Investment Brokerage",
            "type":"Services"
        }
    ],
    "sg:phone":"+64 9-533 7999",
    "sg:province":"Auckland",
    "sg:tags":[
        "chemical",
        "industrial",
        "-",
        "compounds"
    ],
    "wof:name":"BTB Chemicals Ltd",
    "wof:placetype":"venue"
},
  "geometry": {"coordinates":[174.916946,-36.894379],"type":"Point"}
}