{
  "type": "Feature",
  "properties": {
    "iso:country":"NZ",
    "sg:address":"773 Hamurana Rd RD 2 Ngongotaha ",
    "sg:city":"Rotorua",
    "sg:orig_category":"Sports And Leisure: Sports: Golf",
    "sg:phone":"+64 7-332 3866",
    "sg:province":"Bay of Plenty",
    "wof:name":"Hamurana Gardens & Golf Resort",
    "wof:placetype":"venue"
},
  "geometry": {"coordinates":[176.215317,-38.079964],"type":"Point"}
}