{
  "type": "Feature",
  "properties": {
    "addr:full":"Shop 21 159 Gorge Rd  Queenstown Otago",
    "addr:housenumber":"21 159",
    "addr:street":"Gorge Rd",
    "iso:country":"NZ",
    "sg:address":"Shop 21 159 Gorge Rd ",
    "sg:city":"Queenstown",
    "sg:orig_category":"Shopping: Retail Stores: Florists",
    "sg:phone":"+64 3-442 4450",
    "sg:province":"Otago",
    "wof:name":"Renaissance Florist",
    "wof:placetype":"venue"
},
  "geometry": {"coordinates":[-76.157791,38.990379],"type":"Point"}
}