{
  "type": "Feature",
  "properties": {
    "addr:full":"16 Ranfurly St Trentham Upper  Hutt Wellington",
    "addr:housenumber":"16",
    "addr:street":"Ranfurly St",
    "iso:country":"NZ",
    "sg:address":"16 Ranfurly St Trentham Upper ",
    "sg:city":"Hutt",
    "sg:classifiers":[
        {
            "category":"Shopping",
            "subcategory":"Computers & Home Electronics",
            "type":"Retail Goods"
        }
    ],
    "sg:phone":"+64 4-528 6408",
    "sg:province":"Wellington",
    "sg:tags":[
        "recording",
        "equipment",
        "sport",
        "music",
        "leisure"
    ],
    "wof:name":"Sims Sound Service",
    "wof:placetype":"venue"
},
  "geometry": {"coordinates":[175.04045099999999,-41.134567],"type":"Point"}
}