{
  "type": "Feature",
  "properties": {
    "iso:country":"NZ",
    "sg:address":"104 Mt Eden Rd Mt Eden ",
    "sg:city":"Auckland",
    "sg:orig_category":"Shopping: Retail Stores: Stationery",
    "sg:phone":"+64 9-980 4500",
    "sg:province":"Auckland",
    "wof:name":"Data Group",
    "wof:placetype":"venue"
},
  "geometry": {"coordinates":[174.761688,-36.871292],"type":"Point"}
}