{
  "type": "Feature",
  "properties": {
    "addr:full":"104 Mt Eden Rd Mt Eden  Auckland Auckland",
    "addr:housenumber":"104",
    "addr:street":"Mt Eden Rd",
    "iso:country":"NZ",
    "sg:address":"104 Mt Eden Rd Mt Eden ",
    "sg:city":"Auckland",
    "sg:orig_category":"Shopping: Retail Stores: Stationery",
    "sg:phone":"+64 9-980 4500",
    "sg:province":"Auckland",
    "wof:name":"Data Group",
    "wof:placetype":"venue"
},
  "geometry": {"coordinates":[174.76168799999999,-36.871292],"type":"Point"}
}