{
  "type": "Feature",
  "properties": {
    "addr:full":"217 Kennedy Rd Ph/Fax  Napier Hawke's Bay",
    "addr:housenumber":"217",
    "addr:street":"Kennedy Rd Ph / Fax",
    "iso:country":"NZ",
    "sg:address":"217 Kennedy Rd Ph/Fax ",
    "sg:city":"Napier",
    "sg:classifiers":[
        {
            "category":"Shopping",
            "subcategory":"Pets & Pet Supplies",
            "type":"Retail Goods"
        }
    ],
    "sg:phone":"+64 6-843 4640",
    "sg:province":"Hawke's Bay",
    "sg:tags":[
        "boarding",
        "garden",
        "pets",
        "catteries",
        "home",
        "kennel"
    ],
    "wof:name":"Grandma's Paradise Cat Motel",
    "wof:placetype":"venue"
},
  "geometry": {"coordinates":[-80.588562,38.790821],"type":"Point"}
}