{
  "type": "Feature",
  "properties": {
    "iso:country":"NZ",
    "sg:address":"23 Buckingham St ",
    "sg:city":"Arrowtown",
    "sg:orig_category":"Clothing And Fabric: Clothing: Clothing - Specialty",
    "sg:phone":"+64 3-442 1205",
    "sg:province":"Otago",
    "wof:name":"Golden Fleece",
    "wof:placetype":"venue"
},
  "geometry": {"coordinates":[168.831512,-44.938316],"type":"Point"}
}