{
  "type": "Feature",
  "properties": {
    "iso:country":"NZ",
    "sg:address":"Central Park Building 2 666 Gt South Rd Ellerslie PO, Box 2116 ",
    "sg:city":"Auckland",
    "sg:orig_category":"Farming: Horticulture",
    "sg:phone":"+64 9-525 0420",
    "sg:province":"Auckland",
    "wof:name":"Fruitfed Supplies",
    "wof:placetype":"venue"
},
  "geometry": {"coordinates":[174.770416,-36.884109],"type":"Point"}
}