{
  "type": "Feature",
  "properties": {
    "addr:full":"Central Park Building 2 666 Gt South Rd Ellerslie PO, Box 2116  Auckland Auckland",
    "addr:housenumber":"666;po box",
    "addr:postcode":"2116",
    "addr:street":"Gt South Rd",
    "iso:country":"NZ",
    "sg:address":"Central Park Building 2 666 Gt South Rd Ellerslie PO, Box 2116 ",
    "sg:city":"Auckland",
    "sg:orig_category":"Farming: Horticulture",
    "sg:phone":"+64 9-525 0420",
    "sg:province":"Auckland",
    "wof:name":"Fruitfed Supplies",
    "wof:placetype":"venue"
},
  "geometry": {"coordinates":[174.77041600000001,-36.884109],"type":"Point"}
}