{
  "type": "Feature",
  "properties": {
    "addr:full":"15 Daly St Lower Hutt  Wellington Wellington",
    "addr:housenumber":"15",
    "addr:street":"Daly St",
    "iso:country":"NZ",
    "sg:address":"15 Daly St Lower Hutt ",
    "sg:city":"Wellington",
    "sg:classifiers":[
        {
            "category":"Banks & Credit Unions",
            "subcategory":"Financial Services",
            "type":"Services"
        }
    ],
    "sg:phone":"+64 4-939 3274",
    "sg:province":"Wellington",
    "sg:tags":[
        "personal",
        "-",
        "finance",
        "software"
    ],
    "sg:website":"http://www.easitech.co.nz",
    "wof:name":"EasiTech (NZ) Limited",
    "wof:placetype":"venue"
},
  "geometry": {"coordinates":[174.90214499999999,-41.208145],"type":"Point"}
}