{
  "type": "Feature",
  "properties": {
    "addr:full":"695 Childers Rd  Gisborne Gisborne",
    "addr:housenumber":"695",
    "addr:street":"Childers Rd",
    "iso:country":"NZ",
    "sg:address":"695 Childers Rd ",
    "sg:city":"Gisborne",
    "sg:orig_category":"Food And Drink: Meats: Butchers",
    "sg:phone":"+64 6-868 8054",
    "sg:province":"Gisborne",
    "wof:name":"Elgin Butchery",
    "wof:placetype":"venue"
},
  "geometry": {"coordinates":[177.99648999999999,-38.65707],"type":"Point"}
}