{
  "type": "Feature",
  "properties": {
    "addr:full":"29 River Rd  Ngaruawahia",
    "addr:housenumber":"29",
    "addr:street":"River Rd",
    "iso:country":"NZ",
    "sg:address":"29 River Rd ",
    "sg:city":"Ngaruawahia",
    "sg:classifiers":[
        {
            "category":"Health Services",
            "subcategory":"Health Practitioner",
            "type":"Services"
        }
    ],
    "sg:phone":"+64 7-824 5129",
    "sg:tags":[
        "consultant",
        "medical",
        "beauty"
    ],
    "wof:name":"Nga Miro Health Centre",
    "wof:placetype":"venue"
},
  "geometry": {"coordinates":[175.150589,-37.660255],"type":"Point"}
}