{
  "type": "Feature",
  "properties": {
    "addr:full":"14 Barberry St Judea  Tauranga Bay of Plenty",
    "addr:housenumber":"14",
    "addr:street":"Barberry St",
    "iso:country":"NZ",
    "sg:address":"14 Barberry St Judea ",
    "sg:city":"Tauranga",
    "sg:classifiers":[
        {
            "category":"Food Court",
            "type":"Food & Drink"
        }
    ],
    "sg:phone":"+64 7-578 5124",
    "sg:province":"Bay of Plenty",
    "sg:tags":[
        "packer",
        "processing",
        "processor"
    ],
    "wof:name":"Mr Chips",
    "wof:placetype":"venue"
},
  "geometry": {"coordinates":[176.14726300000001,-37.699108],"type":"Point"}
}