{
  "type": "Feature",
  "properties": {
    "iso:country":"NZ",
    "sg:address":"Horse Range Rd ",
    "sg:city":"Palmerston",
    "sg:orig_category":"Home And Garden: Gardening: Services: Landscaping",
    "sg:phone":"+64 25967760",
    "wof:name":"Southern Continous Curbing",
    "wof:placetype":"venue"
},
  "geometry": {"coordinates":[170.760345,-45.424091],"type":"Point"}
}