{
  "type": "Feature",
  "properties": {
    "addr:full":"Whangapoua Forest Coromandel  Whitianga",
    "addr:street":"Whangapoua Forest",
    "iso:country":"NZ",
    "sg:address":"Whangapoua Forest Coromandel ",
    "sg:city":"Whitianga",
    "sg:orig_category":"Farming: Forestry",
    "sg:phone":"+64 7-866 5710",
    "wof:name":"Ernslaw One Ltd",
    "wof:placetype":"venue"
},
  "geometry": {"coordinates":[175.61251799999999,-36.712212],"type":"Point"}
}