{
  "type": "Feature",
  "properties": {
    "iso:country":"NZ",
    "sg:address":"190-194 Federal St ",
    "sg:city":"Auckland",
    "sg:classifiers":[
        {
            "category":"Sports & Exercise",
            "subcategory":"Sports Center",
            "type":"Entertainment"
        }
    ],
    "sg:phone":"+64 9-303 4855",
    "sg:province":"Auckland",
    "sg:tags":[
        "health",
        "beauty",
        "fitness"
    ],
    "wof:name":"The Atrium Club Inc",
    "wof:placetype":"venue"
},
  "geometry": {"coordinates":[-119.10457599999999,36.597755],"type":"Point"}
}