{
  "type": "Feature",
  "properties": {
    "iso:country":"NZ",
    "sg:address":"PO Box 24 ",
    "sg:city":"Manapouri",
    "sg:classifiers":[
        {
            "category":"Travel",
            "subcategory":"Travel Agent",
            "type":"Entertainment"
        }
    ],
    "sg:phone":"+64 3-249 6626",
    "sg:province":"Wellington",
    "sg:tags":[
        "tour",
        "tourism",
        "sightseeing"
    ],
    "sg:website":"http://www.fiordlandadventure.co.nz",
    "wof:name":"Adventure Kayak & Cruise",
    "wof:placetype":"venue"
},
  "geometry": {"coordinates":[167.611237,-45.567215],"type":"Point"}
}