{
  "type": "Feature",
  "properties": {
    "iso:country":"NZ",
    "sg:address":"2 Madden St Auckland City ",
    "sg:city":"Auckland",
    "sg:classifiers":[
        {
            "category":"Restaurant",
            "type":"Food & Drink"
        }
    ],
    "sg:phone":"+64 9-302 4183",
    "sg:province":"Auckland",
    "sg:tags":[
        "fruit",
        "veges"
    ],
    "wof:name":"Fresh Harvest Produce",
    "wof:placetype":"venue"
},
  "geometry": {"coordinates":[174.78450000000001,-37.006058],"type":"Point"}
}