{
  "type": "Feature",
  "properties": {
    "addr:full":"Mawhitiwhiti Rd Normanby  Hawera Taranaki",
    "addr:street":"Mawhitiwhiti Rd",
    "iso:country":"NZ",
    "sg:address":"Mawhitiwhiti Rd Normanby ",
    "sg:city":"Hawera",
    "sg:orig_category":"Food And Drink: Meats: Butchers",
    "sg:phone":"+64 6-272 8106",
    "sg:province":"Taranaki",
    "wof:name":"Normanby Butchery",
    "wof:placetype":"venue"
},
  "geometry": {"coordinates":[174.27032500000001,-39.535904],"type":"Point"}
}