{
  "type": "Feature",
  "properties": {
    "addr:full":"36 G MacDonald St Mt  Maunganui Bay of Plenty",
    "addr:housenumber":"36",
    "addr:street":"G Macdonald St;Maunganui Bay",
    "iso:country":"NZ",
    "sg:address":"36 G MacDonald St Mt ",
    "sg:city":"Maunganui",
    "sg:classifiers":[
        {
            "category":"Marine",
            "type":"Transportation"
        }
    ],
    "sg:phone":"+64 7-575 9555",
    "sg:province":"Bay of Plenty",
    "sg:tags":[
        "boats",
        "builder",
        "yacht",
        "transport",
        "boat"
    ],
    "wof:name":"McEwan Engineering",
    "wof:placetype":"venue"
},
  "geometry": {"coordinates":[176.18627900000001,-37.641048],"type":"Point"}
}