{
  "type": "Feature",
  "properties": {
    "addr:full":"52 East Coast Rd Milford  Auckland Auckland",
    "addr:housenumber":"52",
    "addr:street":"East Coast Rd",
    "iso:country":"NZ",
    "sg:address":"52 East Coast Rd Milford ",
    "sg:city":"Auckland",
    "sg:classifiers":[
        {
            "category":"Sports & Exercise",
            "subcategory":"Tennis Court",
            "type":"Entertainment"
        }
    ],
    "sg:phone":"+64 9-410 9415",
    "sg:province":"Auckland",
    "sg:tags":[
        "bait",
        "hunting",
        "fishing",
        "retailers",
        "tackle",
        "shopping"
    ],
    "wof:name":"Hunts Sports Store",
    "wof:placetype":"venue"
},
  "geometry": {"coordinates":[174.75869800000001,-36.768578],"type":"Point"}
}