{
  "type": "Feature",
  "properties": {
    "addr:full":"23 Murphy Rd Wainui Beach  Gisborne Gisborne",
    "addr:housenumber":"23",
    "addr:street":"Murphy Rd",
    "iso:country":"NZ",
    "sg:address":"23 Murphy Rd Wainui Beach ",
    "sg:city":"Gisborne",
    "sg:classifiers":[
        {
            "category":"Home & Garden",
            "subcategory":"Building Materials",
            "type":"Retail Goods"
        }
    ],
    "sg:phone":"+64 6-868 1202",
    "sg:province":"Gisborne",
    "sg:tags":[
        "builder",
        "related"
    ],
    "wof:name":"John Fitzgerald",
    "wof:placetype":"venue"
},
  "geometry": {"coordinates":[178.07023599999999,-38.691601],"type":"Point"}
}