{
  "type": "Feature",
  "properties": {
    "iso:country":"NZ",
    "sg:address":"PO Box 104103 ",
    "sg:city":"Lincoln",
    "sg:classifiers":[
        {
            "category":"Shopping",
            "subcategory":"Beauty & Cosmetics",
            "type":"Retail Goods"
        }
    ],
    "sg:phone":"+64 800 180 190",
    "sg:tags":[
        "supply",
        "health",
        "hairdressing"
    ],
    "wof:name":"Total Beauty Supplies",
    "wof:placetype":"venue"
},
  "geometry": {"coordinates":[-86.11953,33.603867],"type":"Point"}
}