{
  "type": "Feature",
  "properties": {
    "addr:full":"cnr Devon & Mt Edgecumbe Sts New  Plymouth Taranaki",
    "addr:housenumber":"cnr",
    "addr:street":"Devon & Mt Edgecumbe Sts",
    "iso:country":"NZ",
    "sg:address":"cnr Devon & Mt Edgecumbe Sts New ",
    "sg:city":"Plymouth",
    "sg:classifiers":[
        {
            "category":"Food & Beverages",
            "subcategory":"Liquor & Beverages",
            "type":"Retail Goods"
        }
    ],
    "sg:phone":"+64 6-759 6151",
    "sg:province":"Taranaki",
    "sg:tags":[
        "drink",
        "outlet"
    ],
    "sg:website":"http://www.lk.co.nz",
    "wof:name":"Liquor King",
    "wof:placetype":"venue"
},
  "geometry": {"coordinates":[-116.81971,43.972191],"type":"Point"}
}