{
  "type": "Feature",
  "properties": {
    "iso:country":"NZ",
    "sg:address":"Omaka Aerodrome ",
    "sg:city":"Blenheim",
    "sg:classifiers":[
        {
            "category":"Organizations",
            "subcategory":"Labor Organization",
            "type":"Services"
        }
    ],
    "sg:phone":"+64 3-578 9684",
    "sg:province":"Marlborough",
    "sg:tags":[
        "services",
        "helicopter",
        "travel",
        "tourism"
    ],
    "wof:name":"Marlborough Helicopters Ltd",
    "wof:placetype":"venue"
},
  "geometry": {"coordinates":[173.92285200000001,-41.54018],"type":"Point"}
}