{
  "type": "Feature",
  "properties": {
    "addr:full":"56 Harbour Rd Brooklands  Christchurch Canterbury",
    "addr:housenumber":"56",
    "addr:street":"Harbour Rd",
    "iso:country":"NZ",
    "sg:address":"56 Harbour Rd Brooklands ",
    "sg:city":"Christchurch",
    "sg:classifiers":[
        {
            "category":"Health Services",
            "subcategory":"Dentist",
            "type":"Services"
        }
    ],
    "sg:phone":"+64 3-329 8555",
    "sg:province":"Canterbury",
    "sg:tags":[
        "dental",
        "beauty"
    ],
    "wof:name":"Brooklands Dental Laboratory",
    "wof:placetype":"venue"
},
  "geometry": {"coordinates":[172.69712799999999,-43.399475],"type":"Point"}
}