{
  "type": "Feature",
  "properties": {
    "addr:full":"117 Ocean Beach Rd  Tairua",
    "addr:housenumber":"117",
    "addr:street":"Ocean Beach Rd",
    "iso:country":"NZ",
    "sg:address":"117 Ocean Beach Rd ",
    "sg:city":"Tairua",
    "sg:orig_category":"Home And Garden: Gardening: Services: Landscaping",
    "sg:phone":"+64 7-864 7377",
    "wof:name":"Lou's Landscaping",
    "wof:placetype":"venue"
},
  "geometry": {"coordinates":[175.85076900000001,-36.990147],"type":"Point"}
}