{
  "type": "Feature",
  "properties": {
    "addr:full":"Auckland Central  Auckland Auckland",
    "iso:country":"NZ",
    "sg:address":"Auckland Central ",
    "sg:city":"Auckland",
    "sg:orig_category":"Automotive: Parts And Supplies: Windscreens",
    "sg:phone":"+64 800 373 344",
    "sg:province":"Auckland",
    "wof:name":"Chip Away",
    "wof:placetype":"venue"
},
  "geometry": {"coordinates":[174.76454200000001,-36.848358],"type":"Point"}
}