{
  "type": "Feature",
  "properties": {
    "iso:country":"NZ",
    "sg:address":"403 Te Rapa Rd ",
    "sg:city":"Hamilton",
    "sg:classifiers":[
        {
            "category":"Social Services",
            "subcategory":"Retirement Home",
            "type":"Services"
        }
    ],
    "sg:phone":"+64 7-849 3949",
    "sg:province":"Waikato",
    "sg:tags":[
        "automotive"
    ],
    "sg:website":"http://www.yellowpages.co.nz/pages/102754201/dp23424.html",
    "wof:name":"Cross Country Rentals Ltd",
    "wof:placetype":"venue"
},
  "geometry": {"coordinates":[175.252151,-37.764278],"type":"Point"}
}