{
  "type": "Feature",
  "properties": {
    "iso:country":"NZ",
    "sg:address":"9 Whangaparaoa Town Cen Whangaparaoa Hibiscus ",
    "sg:city":"Hibiscus Coast",
    "sg:classifiers":[
        {
            "category":"Fast Food",
            "type":"Food & Drink"
        }
    ],
    "sg:phone":"+64 9-424 7384",
    "sg:province":"Auckland",
    "sg:tags":[
        "wining",
        "dining",
        "takeaway"
    ],
    "wof:name":"Peninsula Chinese Takeaways",
    "wof:placetype":"venue"
},
  "geometry": {"coordinates":[174.74916099999999,-36.634239],"type":"Point"}
}