{
  "type": "Feature",
  "properties": {
    "addr:full":"128 West St  Feilding Manawatu-Wanganui",
    "addr:housenumber":"128",
    "addr:street":"West St",
    "iso:country":"NZ",
    "sg:address":"128 West St ",
    "sg:city":"Feilding",
    "sg:classifiers":[
        {
            "category":"Personal",
            "subcategory":"Hair Removal",
            "type":"Services"
        }
    ],
    "sg:phone":"+64 6-323 1900",
    "sg:province":"Manawatu-Wanganui",
    "sg:tags":[
        "health",
        "beauty"
    ],
    "wof:name":"Feilding's House of Beauty",
    "wof:placetype":"venue"
},
  "geometry": {"coordinates":[175.55766299999999,-40.216702],"type":"Point"}
}