{
  "type": "Feature",
  "properties": {
    "addr:full":"506 Takapau Ormondville Rd  Takapau",
    "addr:housenumber":"506",
    "addr:street":"Takapau Ormondville Rd",
    "iso:country":"NZ",
    "sg:address":"506 Takapau Ormondville Rd ",
    "sg:city":"Takapau",
    "sg:orig_category":"Sports And Leisure: Sports: Equestrian: Stud Farms",
    "sg:phone":"+64 6-855 8944",
    "wof:name":"J K Holsteiner Stud",
    "wof:placetype":"venue"
},
  "geometry": {"coordinates":[176.34664900000001,-40.032661],"type":"Point"}
}