{
  "type": "Feature",
  "properties": {
    "addr:full":"29 Stronsa St  Palmerston",
    "addr:housenumber":"29",
    "addr:street":"Stronsa St",
    "iso:country":"NZ",
    "sg:address":"29 Stronsa St ",
    "sg:city":"Palmerston",
    "sg:orig_category":"Sports And Leisure: Sports: Equestrian",
    "sg:phone":"+64 3-465 1291",
    "wof:name":"Palmerston Veterinary Clinic",
    "wof:placetype":"venue"
},
  "geometry": {"coordinates":[170.71319600000001,-45.48402],"type":"Point"}
}