{
  "type": "Feature",
  "properties": {
    "iso:country":"NZ",
    "sg:address":"12 Silverdale St Silverdale ",
    "sg:city":"Auckland",
    "sg:orig_category":"Shopping: Discount",
    "sg:phone":"+64 9-426 7844",
    "sg:province":"Auckland",
    "wof:name":"Swanndri/Legends Male Fashion",
    "wof:placetype":"venue"
},
  "geometry": {"coordinates":[174.67666600000001,-36.618233],"type":"Point"}
}