{
  "type": "Feature",
  "properties": {
    "addr:full":"cnr Mt Eden & Mt Albert Rds  Auckland Auckland",
    "addr:street":"Cnr Mt",
    "iso:country":"NZ",
    "sg:address":"cnr Mt Eden & Mt Albert Rds ",
    "sg:city":"Auckland",
    "sg:classifiers":[
        {
            "category":"Education",
            "subcategory":"Special Training",
            "type":"Public Place"
        }
    ],
    "sg:phone":"+64 9-624 1456",
    "sg:province":"Auckland",
    "sg:tags":[
        "school",
        "swimming"
    ],
    "wof:name":"Ross Millar Swim School",
    "wof:placetype":"venue"
},
  "geometry": {"coordinates":[174.7621,-36.882469],"type":"Point"}
}