{
  "type": "Feature",
  "properties": {
    "addr:full":"57 Rugby St  Wellington Wellington",
    "addr:housenumber":"57",
    "addr:street":"Rugby St",
    "iso:country":"NZ",
    "sg:address":"57 Rugby St ",
    "sg:city":"Wellington",
    "sg:classifiers":[
        {
            "category":"Education",
            "subcategory":"Special Training",
            "type":"Public Place"
        }
    ],
    "sg:phone":"+64 4-385 8533",
    "sg:province":"Wellington",
    "sg:tags":[
        "charter",
        "shopping",
        "dive",
        "tuition",
        "water",
        "sports",
        "retailers",
        "sport"
    ],
    "wof:name":"Divers World (1999) Ltd",
    "wof:placetype":"venue"
},
  "geometry": {"coordinates":[-85.910454,33.827946],"type":"Point"}
}