{
  "type": "Feature",
  "properties": {
    "iso:country":"NZ",
    "sg:address":"PO Box 35020 Browns Bay ",
    "sg:city":"Auckland",
    "sg:orig_category":"Shopping: Dispensing: Vending Machines",
    "sg:phone":"+64 9-478 5385",
    "sg:province":"Auckland",
    "wof:name":"The Vending Company Ltd",
    "wof:placetype":"venue"
},
  "geometry": {"coordinates":[174.74432400000001,-36.714409],"type":"Point"}
}