{
  "type": "Feature",
  "properties": {
    "iso:country":"NZ",
    "sg:address":"105 O' Shannessey St Papakura ",
    "sg:city":"Auckland",
    "sg:orig_category":"Clothing And Fabric: Clothing: Clothing - Specialty",
    "sg:phone":"+64 9-299 5500",
    "sg:province":"Auckland",
    "wof:name":"Famory Clothing Ltd",
    "wof:placetype":"venue"
},
  "geometry": {"coordinates":[174.943924,-37.065418],"type":"Point"}
}