{
  "type": "Feature",
  "properties": {
    "iso:country":"NZ",
    "sg:address":"C/-Green Door 93 Havelock Rd Havelock North ",
    "sg:city":"Hastings",
    "sg:orig_category":"Shopping: Retail Stores: Florist Accessories",
    "sg:phone":"+64 6-877 1920",
    "sg:province":"Hawke's Bay",
    "wof:name":"Stems",
    "wof:placetype":"venue"
},
  "geometry": {"coordinates":[176.879517,-39.669403],"type":"Point"}
}