{
  "type": "Feature",
  "properties": {
    "iso:country":"NZ",
    "sg:address":"169 Main St ",
    "sg:city":"Greytown",
    "sg:orig_category":"Sports And Leisure: Sports: Equestrian: Saddlers",
    "sg:phone":"+64 6-304 9896",
    "wof:name":"Maverick Saddlery",
    "wof:placetype":"venue"
},
  "geometry": {"coordinates":[-83.94277200000001,41.370808],"type":"Point"}
}