{
  "type": "Feature",
  "properties": {
    "iso:country":"NZ",
    "sg:address":"259 Thames St ",
    "sg:city":"Oamaru",
    "sg:classifiers":[
        {
            "category":"Professional",
            "subcategory":"Detective & Security Services",
            "type":"Services"
        }
    ],
    "sg:phone":"+64 3-434 5354",
    "sg:province":"Otago",
    "sg:tags":[
        "services",
        "automotive",
        "warrant",
        "fitness"
    ],
    "wof:name":"Young's Tyre & Auto Centre",
    "wof:placetype":"venue"
},
  "geometry": {"coordinates":[170.972824,-45.094498],"type":"Point"}
}