{
  "type": "Feature",
  "properties": {
    "iso:country":"NZ",
    "sg:address":"41 Roger ",
    "sg:city":"St",
    "sg:classifiers":[
        {
            "category":"Manufacturing",
            "subcategory":"Tools & Machinery",
            "type":"Manufacturing & Wholesale Goods"
        }
    ],
    "sg:phone":"+64 800 111 333",
    "sg:tags":[
        "equipment",
        "industrial",
        "welding"
    ],
    "wof:name":"BOC",
    "wof:placetype":"venue"
},
  "geometry": {"coordinates":[170.366638,-43.587711],"type":"Point"}
}