{
  "type": "Feature",
  "properties": {
    "addr:full":"PO Box 60  Methven",
    "addr:housenumber":"po box 60",
    "addr:street":"Methven",
    "iso:country":"NZ",
    "sg:address":"PO Box 60 ",
    "sg:city":"Methven",
    "sg:classifiers":[
        {
            "category":"Travel",
            "subcategory":"Travel Agent",
            "type":"Entertainment"
        }
    ],
    "sg:phone":"+64 274 508 283",
    "sg:tags":[
        "tour",
        "tourism",
        "adventure",
        "sightseeing"
    ],
    "wof:name":"Black Diamond Safaris",
    "wof:placetype":"venue"
},
  "geometry": {"coordinates":[171.644272,-43.631443],"type":"Point"}
}