{
  "type": "Feature",
  "properties": {
    "iso:country":"NZ",
    "sg:address":"PO Box 11 ",
    "sg:city":"Mokau",
    "sg:classifiers":[
        {
            "category":"Sports & Exercise",
            "subcategory":"Skate Park",
            "type":"Entertainment"
        }
    ],
    "sg:phone":"+64 6-752 9072",
    "sg:tags":[
        "arts",
        "museum",
        "leisure",
        "gallery"
    ],
    "wof:name":"Tainui Historical Society Museum",
    "wof:placetype":"venue"
},
  "geometry": {"coordinates":[174.618195,-38.69796],"type":"Point"}
}