{
  "type": "Feature",
  "properties": {
    "addr:full":"36 Dalton Gro Stokes Valley Lower  Hutt Wellington",
    "addr:housenumber":"36",
    "addr:street":"Dalton Gro Stokes Valley",
    "iso:country":"NZ",
    "sg:address":"36 Dalton Gro Stokes Valley Lower ",
    "sg:city":"Hutt",
    "sg:classifiers":[
        {
            "category":"Autos & Motor Vehicles",
            "subcategory":"Motorcycle Sales",
            "type":"Retail Goods"
        }
    ],
    "sg:phone":"+64 4-563 5054",
    "sg:province":"Wellington",
    "sg:tags":[
        "automotive",
        "scooter",
        "leasing"
    ],
    "wof:name":"Motorcycle Maintenance Ltd",
    "wof:placetype":"venue"
},
  "geometry": {"coordinates":[174.98187300000001,-41.17495],"type":"Point"}
}