{
  "type": "Feature",
  "properties": {
    "addr:full":"36 Cryers Rd East Tamaki  Auckland Auckland",
    "addr:housenumber":"36",
    "addr:street":"Cryers Rd",
    "iso:country":"NZ",
    "sg:address":"36 Cryers Rd East Tamaki ",
    "sg:city":"Auckland",
    "sg:classifiers":[
        {
            "category":"Manufacturing",
            "subcategory":"Rubber & Plastics",
            "type":"Manufacturing & Wholesale Goods"
        }
    ],
    "sg:phone":"+64 9-273 5666",
    "sg:province":"Auckland",
    "sg:tags":[
        "industrial",
        "goods"
    ],
    "wof:name":"Galloway International Ltd",
    "wof:placetype":"venue"
},
  "geometry": {"coordinates":[174.887024,-36.933609],"type":"Point"}
}