{
  "type": "Feature",
  "properties": {
    "addr:full":"186 Fitzherbert Ave Palmerston  Palmerston North Manawatu-Wanganui",
    "addr:housenumber":"186",
    "addr:street":"Fitzherbert Ave",
    "iso:country":"NZ",
    "sg:address":"186 Fitzherbert Ave Palmerston ",
    "sg:city":"Palmerston North",
    "sg:classifiers":[
        {
            "category":"Travel",
            "subcategory":"Bed & Breakfast",
            "type":"Entertainment"
        }
    ],
    "sg:phone":"+64 6-355 3653",
    "sg:province":"Manawatu-Wanganui",
    "sg:tags":[
        "tourism",
        "accommodation"
    ],
    "wof:name":"Contact House Bed & Breakfast",
    "wof:placetype":"venue"
},
  "geometry": {"coordinates":[175.617233,-40.364307],"type":"Point"}
}