{
  "type": "Feature",
  "properties": {
    "addr:full":"PO Box 51-311 Tawa  Porirua Wellington",
    "addr:housenumber":"po box",
    "addr:postcode":"51-311",
    "iso:country":"NZ",
    "sg:address":"PO Box 51-311 Tawa ",
    "sg:city":"Porirua",
    "sg:classifiers":[
        {
            "category":"Home & Garden",
            "subcategory":"Garden Supply",
            "type":"Retail Goods"
        }
    ],
    "sg:phone":"+64 4-238 4158",
    "sg:province":"Wellington",
    "sg:tags":[
        "cleaning"
    ],
    "wof:name":"Custodian Services Ltd",
    "wof:placetype":"venue"
},
  "geometry": {"coordinates":[174.82420300000001,-41.17149],"type":"Point"}
}