{
  "type": "Feature",
  "properties": {
    "iso:country":"NZ",
    "sg:address":"Main Rd Paparoa ",
    "sg:city":"Maungaturoto",
    "sg:orig_category":"Automotive: General Services: Service Stations",
    "sg:phone":"+64 9-431 7332",
    "wof:name":"Paparoa Service Station",
    "wof:placetype":"venue"
},
  "geometry": {"coordinates":[175.386429,-37.238689],"type":"Point"}
}