{
  "type": "Feature",
  "properties": {
    "addr:full":"Pakuranga  Auckland Auckland",
    "iso:country":"NZ",
    "sg:address":"Pakuranga ",
    "sg:city":"Auckland",
    "sg:orig_category":"Shopping: Gifts: Gift Baskets",
    "sg:phone":"+64 9-537 4782",
    "sg:province":"Auckland",
    "wof:name":"Christmas Collection",
    "wof:placetype":"venue"
},
  "geometry": {"coordinates":[174.87904399999999,-36.91584],"type":"Point"}
}