{
  "type": "Feature",
  "properties": {
    "addr:full":"3 Wharawhara Rd  Katikati",
    "addr:housenumber":"3",
    "addr:street":"Wharawhara Rd",
    "iso:country":"NZ",
    "sg:address":"3 Wharawhara Rd ",
    "sg:city":"Katikati",
    "sg:classifiers":[
        {
            "category":"Sports & Exercise",
            "subcategory":"Skate Park",
            "type":"Entertainment"
        }
    ],
    "sg:phone":"+64 7-549 0651",
    "sg:tags":[
        "arts",
        "museum",
        "leisure",
        "gallery"
    ],
    "wof:name":"Katikati Heritage Museum",
    "wof:placetype":"venue"
},
  "geometry": {"coordinates":[175.88055399999999,-37.57151],"type":"Point"}
}