{
  "type": "Feature",
  "properties": {
    "addr:full":"Rocky Hundreds Rd Fairlie R D 2  Timaru Canterbury",
    "addr:housenumber":"2",
    "addr:street":"Hundreds Rd;R D",
    "iso:country":"NZ",
    "sg:address":"Rocky Hundreds Rd Fairlie R D 2 ",
    "sg:city":"Timaru",
    "sg:classifiers":[
        {
            "category":"Farming",
            "subcategory":"Farm & Veterinary Services",
            "type":"Manufacturing & Wholesale Goods"
        }
    ],
    "sg:phone":"+64 3-688 0280",
    "sg:province":"Canterbury",
    "sg:tags":[
        "supplies",
        "supply"
    ],
    "wof:name":"Bell-Booth Ltd",
    "wof:placetype":"venue"
},
  "geometry": {"coordinates":[171.23741100000001,-44.395428],"type":"Point"}
}