{
  "type": "Feature",
  "properties": {
    "addr:full":"UNT/10 Magdala  Pl",
    "addr:housenumber":"/ 10",
    "addr:street":"Pl",
    "iso:country":"NZ",
    "sg:address":"UNT/10 Magdala ",
    "sg:city":"Pl",
    "sg:orig_category":"Industrial: Packaging",
    "wof:name":"Elldex Packaging (SI) Ltd",
    "wof:placetype":"venue"
},
  "geometry": {"coordinates":[170.36663799999999,-43.587711],"type":"Point"}
}