{
  "type": "Feature",
  "properties": {
    "iso:country":"NZ",
    "sg:address":"UNT/10 Magdala ",
    "sg:city":"Pl",
    "sg:orig_category":"Industrial: Packaging",
    "wof:name":"Elldex Packaging (SI) Ltd",
    "wof:placetype":"venue"
},
  "geometry": {"coordinates":[170.366638,-43.587711],"type":"Point"}
}