{
  "type": "Feature",
  "properties": {
    "addr:full":"87 Pinfold Rd Aokautere Palmerston  Palmerston North Manawatu-Wanganui",
    "addr:housenumber":"87",
    "addr:street":"Pinfold Rd;Palmerston",
    "iso:country":"NZ",
    "sg:address":"87 Pinfold Rd Aokautere Palmerston ",
    "sg:city":"Palmerston North",
    "sg:classifiers":[
        {
            "category":"Food & Beverages",
            "subcategory":"Meat & Fish",
            "type":"Retail Goods"
        }
    ],
    "sg:phone":"+64 6-354 0047",
    "sg:province":"Manawatu-Wanganui",
    "sg:tags":[
        "drink"
    ],
    "wof:name":"Country Meats",
    "wof:placetype":"venue"
},
  "geometry": {"coordinates":[175.650711,-40.359756],"type":"Point"}
}