{
  "type": "Feature",
  "properties": {
    "addr:full":"121 Creans Rd R D 2  Waihi",
    "addr:housenumber":"121;2",
    "addr:street":"Creans Rd R D",
    "iso:country":"NZ",
    "sg:address":"121 Creans Rd R D 2 ",
    "sg:city":"Waihi",
    "sg:orig_category":"Health And Beauty: Specialists: Midwives",
    "sg:phone":"+64 7-863 6488",
    "wof:name":"Burton, Jan ( Midwife)",
    "wof:placetype":"venue"
},
  "geometry": {"coordinates":[175.83845500000001,-37.388897],"type":"Point"}
}