{
  "type": "Feature",
  "properties": {
    "iso:country":"NZ",
    "sg:address":"Tay St ",
    "sg:city":"Invercargill",
    "sg:classifiers":[
        {
            "category":"Health Services",
            "subcategory":"Dentist",
            "type":"Services"
        }
    ],
    "sg:phone":"+64 3-217 2702",
    "sg:province":"Southland",
    "sg:tags":[
        "dental",
        "clinic",
        "beauty"
    ],
    "wof:name":"Ascot Community Dental Clinic",
    "wof:placetype":"venue"
},
  "geometry": {"coordinates":[168.412155,-46.575806],"type":"Point"}
}