{
  "type": "Feature",
  "properties": {
    "iso:country":"NZ",
    "sg:address":"14 Dublin St ",
    "sg:city":"Wanganui",
    "sg:orig_category":"Automotive: General Services: Service Stations",
    "sg:phone":"+64 6-347 9586",
    "sg:province":"Manawatu-Wanganui",
    "wof:name":"Shell Dublin Street",
    "wof:placetype":"venue"
},
  "geometry": {"coordinates":[-6.24946,53.294788],"type":"Point"}
}