{
  "type": "Feature",
  "properties": {
    "iso:country":"NZ",
    "sg:address":"78 Queen St ",
    "sg:city":"Masterton",
    "sg:classifiers":[
        {
            "category":"Bars & Pubs",
            "subcategory":"Wine Bar",
            "type":"Food & Drink"
        }
    ],
    "sg:phone":"+64 6-370 1431",
    "sg:province":"Wellington",
    "sg:tags":[
        "wining",
        "dining",
        "cafe"
    ],
    "wof:name":"Russian Jack Cafe",
    "wof:placetype":"venue"
},
  "geometry": {"coordinates":[175.662415,-40.949135],"type":"Point"}
}