{
  "type": "Feature",
  "properties": {
    "iso:country":"NZ",
    "sg:address":"Shop 4 1 Aylesbury St Pakuranga ",
    "sg:city":"Auckland",
    "sg:classifiers":[
        {
            "category":"Bars & Pubs",
            "subcategory":"Lounge",
            "type":"Food & Drink"
        }
    ],
    "sg:phone":"+64 9-576 8202",
    "sg:province":"Auckland",
    "sg:tags":[
        "-"
    ],
    "wof:name":"Angkor Bakery",
    "wof:placetype":"venue"
},
  "geometry": {"coordinates":[174.870575,-36.913422],"type":"Point"}
}