{
  "type": "Feature",
  "properties": {
    "addr:full":"8 Durham St East Auckland City  Auckland Auckland",
    "addr:housenumber":"8",
    "addr:street":"Durham St",
    "iso:country":"NZ",
    "sg:address":"8 Durham St East Auckland City ",
    "sg:city":"Auckland",
    "sg:classifiers":[
        {
            "category":"Health Services",
            "subcategory":"Podiatrist",
            "type":"Services"
        }
    ],
    "sg:phone":"+64 9-379 7421",
    "sg:province":"Auckland",
    "sg:tags":[
        "wig",
        "hairpiece",
        "beauty"
    ],
    "wof:name":"Headfirst Mens Hairpieces",
    "wof:placetype":"venue"
},
  "geometry": {"coordinates":[174.765961,-36.848225],"type":"Point"}
}