{
  "type": "Feature",
  "properties": {
    "addr:full":"Millflat Rd R D 3 Albany  Auckland Auckland",
    "addr:housenumber":"3",
    "addr:street":"Millflat Rd R D",
    "iso:country":"NZ",
    "sg:address":"Millflat Rd R D 3 Albany ",
    "sg:city":"Auckland",
    "sg:classifiers":[
        {
            "category":"Manufacturing",
            "subcategory":"Food",
            "type":"Manufacturing & Wholesale Goods"
        }
    ],
    "sg:phone":"+64 9-412 8953",
    "sg:province":"Auckland",
    "sg:tags":[
        "drink",
        "-",
        "manufacturer"
    ],
    "wof:name":"Shaws Berry Farm Jams",
    "wof:placetype":"venue"
},
  "geometry": {"coordinates":[174.77041600000001,-36.884109],"type":"Point"}
}