{
  "type": "Feature",
  "properties": {
    "iso:country":"NZ",
    "sg:address":"25 Watts Rd Sockburn ",
    "sg:city":"Christchurch",
    "sg:classifiers":[
        {
            "category":"Home & Garden",
            "subcategory":"Furniture",
            "type":"Retail Goods"
        }
    ],
    "sg:phone":"+64 3-343 9872",
    "sg:province":"Canterbury",
    "sg:tags":[
        "furniture/furnishings",
        "furnishing"
    ],
    "wof:name":"A & A Furniture",
    "wof:placetype":"venue"
},
  "geometry": {"coordinates":[172.561768,-43.538006],"type":"Point"}
}