{
  "type": "Feature",
  "properties": {
    "addr:full":"586 Cameron Rd  Tauranga Bay of Plenty",
    "addr:housenumber":"586",
    "addr:street":"Cameron Rd",
    "iso:country":"NZ",
    "sg:address":"586 Cameron Rd ",
    "sg:city":"Tauranga",
    "sg:classifiers":[
        {
            "category":"Professional",
            "subcategory":"Art Services",
            "type":"Services"
        }
    ],
    "sg:phone":"+64 7-578 2550",
    "sg:province":"Bay of Plenty",
    "sg:tags":[
        "picture",
        "arts",
        "sport",
        "framing",
        "leisure"
    ],
    "wof:name":"The Framing Shop Ltd",
    "wof:placetype":"venue"
},
  "geometry": {"coordinates":[176.15846300000001,-37.699463],"type":"Point"}
}