{
  "type": "Feature",
  "properties": {
    "iso:country":"NZ",
    "sg:address":"189 Queen St Auckland Central ",
    "sg:city":"Auckland",
    "sg:classifiers":[
        {
            "category":"Shopping",
            "subcategory":"Beauty & Cosmetics",
            "type":"Retail Goods"
        }
    ],
    "sg:phone":"+64 9-303 3318",
    "sg:province":"Auckland",
    "sg:tags":[
        "health",
        "perfumery"
    ],
    "wof:name":"Lush (New Zealand) Ltd",
    "wof:placetype":"venue"
},
  "geometry": {"coordinates":[174.76535000000001,-36.848392],"type":"Point"}
}