{
  "type": "Feature",
  "properties": {
    "addr:full":"62 Hospital Rd Te  Kuiti",
    "addr:housenumber":"62",
    "addr:street":"Hospital Rd",
    "iso:country":"NZ",
    "sg:address":"62 Hospital Rd Te ",
    "sg:city":"Kuiti",
    "sg:classifiers":[
        {
            "category":"Farming",
            "subcategory":"Farm & Veterinary Services",
            "type":"Manufacturing & Wholesale Goods"
        }
    ],
    "sg:phone":"+64 7-878 7913",
    "sg:tags":[
        "supplies",
        "supply"
    ],
    "wof:name":"Stocktech Waipa",
    "wof:placetype":"venue"
},
  "geometry": {"coordinates":[175.15730300000001,-38.329704],"type":"Point"}
}