{
  "type": "Feature",
  "properties": {
    "iso:country":"NZ",
    "sg:address":"9 Guinness St ",
    "sg:city":"Greymouth",
    "sg:classifiers":[
        {
            "category":"Professional",
            "subcategory":"Art Services",
            "type":"Services"
        }
    ],
    "sg:phone":"+64 3-768 4887",
    "sg:province":"West Coast",
    "sg:tags":[
        "picture",
        "arts",
        "sport",
        "framing",
        "leisure"
    ],
    "wof:name":"Gallery 9",
    "wof:placetype":"venue"
},
  "geometry": {"coordinates":[171.21051,-42.44976],"type":"Point"}
}