{
  "type": "Feature",
  "properties": {
    "iso:country":"NZ",
    "sg:address":"Lambton Square Shopping Centre 180 Lambton Qy ",
    "sg:city":"Wellington",
    "sg:classifiers":[
        {
            "category":"Health Services",
            "subcategory":"Optometrist",
            "type":"Services"
        }
    ],
    "sg:phone":"+64 4-499 0293",
    "sg:province":"Wellington",
    "sg:tags":[
        "optical",
        "optician",
        "beauty"
    ],
    "wof:name":"Geraldine Booth Optical",
    "wof:placetype":"venue"
},
  "geometry": {"coordinates":[174.767151,-41.28054],"type":"Point"}
}