{
  "type": "Feature",
  "properties": {
    "iso:country":"NZ",
    "sg:address":"45 Boston Rd Newmarket ",
    "sg:city":"Auckland",
    "sg:classifiers":[
        {
            "category":"Retail",
            "subcategory":"Auto Repair",
            "type":"Services"
        }
    ],
    "sg:phone":"+64 9-373 2568",
    "sg:province":"Auckland",
    "sg:tags":[
        "automotive",
        "panel",
        "servicing",
        "beater"
    ],
    "wof:name":"Auto Pro Panel And Paint Limited",
    "wof:placetype":"venue"
},
  "geometry": {"coordinates":[174.767685,-36.865978],"type":"Point"}
}