{
  "type": "Feature",
  "properties": {
    "iso:country":"NZ",
    "sg:address":"Wellington Hospital Grounds, 39 Riddiford St Newtown",
    "sg:city":"Wellington",
    "sg:orig_category":"Travel And Tourism: Accommodation: Hostels",
    "sg:phone":"+64 4-385 5362",
    "sg:province":"Wellington",
    "wof:name":"Riddiford Street Hostel",
    "wof:placetype":"venue"
},
  "geometry": {"coordinates":[174.779022,-41.314163],"type":"Point"}
}