{
  "type": "Feature",
  "properties": {
    "iso:country":"NZ",
    "sg:address":"Gladstone Rd ",
    "sg:city":"Gladstone",
    "sg:classifiers":[
        {
            "category":"Wholesale",
            "subcategory":"Meat",
            "type":"Manufacturing & Wholesale Goods"
        }
    ],
    "sg:phone":"+64 6-372 7882",
    "sg:tags":[
        "food",
        "drink",
        "meats",
        "slaughtering"
    ],
    "wof:name":"Kintyre Abattoir",
    "wof:placetype":"venue"
},
  "geometry": {"coordinates":[-103.973007,36.297733],"type":"Point"}
}