{
  "type": "Feature",
  "properties": {
    "iso:country":"NZ",
    "sg:address":"Graingers Rd R D 1 ",
    "sg:city":"Outram",
    "sg:classifiers":[
        {
            "category":"Shopping",
            "subcategory":"Pets & Pet Supplies",
            "type":"Retail Goods"
        }
    ],
    "sg:phone":"+64 3-486 1621",
    "sg:tags":[
        "boarding",
        "garden",
        "pets",
        "catteries",
        "home",
        "kennel"
    ],
    "wof:name":"Paradise Pets",
    "wof:placetype":"venue"
},
  "geometry": {"coordinates":[170.231293,-45.858738],"type":"Point"}
}