{
  "type": "Feature",
  "properties": {
    "iso:country":"NZ",
    "sg:address":"35 A Murphys Rd Springlands ",
    "sg:city":"Blenheim",
    "sg:orig_category":"Transport: Transportation: Courier Services",
    "sg:phone":"+64 3-578 0048",
    "sg:province":"Marlborough",
    "wof:name":"Nichols Freight",
    "wof:placetype":"venue"
},
  "geometry": {"coordinates":[173.93215900000001,-41.505253],"type":"Point"}
}