{
  "type": "Feature",
  "properties": {
    "addr:full":"27 Dunlop Rd Onekawa  Napier Hawke's Bay",
    "addr:housenumber":"27",
    "addr:street":"Dunlop Rd",
    "iso:country":"NZ",
    "sg:address":"27 Dunlop Rd Onekawa ",
    "sg:city":"Napier",
    "sg:classifiers":[
        {
            "category":"Restaurant",
            "type":"Food & Drink"
        }
    ],
    "sg:phone":"+64 6-843 5115",
    "sg:province":"Hawke's Bay",
    "sg:tags":[
        "merchant",
        "fish",
        "sea"
    ],
    "wof:name":"Star Fish Supply Ltd",
    "wof:placetype":"venue"
},
  "geometry": {"coordinates":[176.88561999999999,-39.502403],"type":"Point"}
}