{
  "type": "Feature",
  "properties": {
    "iso:country":"NZ",
    "sg:address":"Levin Agent 43 Power St ",
    "sg:city":"Levin",
    "sg:orig_category":"Shopping: Retail Stores: Dolls",
    "sg:phone":"+64 6-367 9376",
    "sg:province":"Manawatu-Wanganui",
    "wof:name":"Doll Hospital",
    "wof:placetype":"venue"
},
  "geometry": {"coordinates":[175.285324,-40.625278],"type":"Point"}
}