{
  "type": "Feature",
  "properties": {
    "addr:full":"Private Bag 3010 Ph/Fax  Hamilton Waikato",
    "addr:postcode":"3010",
    "addr:street":"Private Bag;Ph / Fax",
    "iso:country":"NZ",
    "sg:address":"Private Bag 3010 Ph/Fax ",
    "sg:city":"Hamilton",
    "sg:classifiers":[
        {
            "category":"Sports & Exercise",
            "subcategory":"Sports Center",
            "type":"Entertainment"
        }
    ],
    "sg:phone":"+64 7-856 2132",
    "sg:province":"Waikato",
    "sg:tags":[
        "health",
        "beauty",
        "fitness"
    ],
    "wof:name":"Hamilton Gardens Pavilion",
    "wof:placetype":"venue"
},
  "geometry": {"coordinates":[120.6194,16.3764],"type":"Point"}
}