{
  "type": "Feature",
  "properties": {
    "addr:full":"cnr Dent & Carruth Sts  Whangarei Northland",
    "addr:housenumber":"cnr;sts",
    "addr:street":"Dent & Carruth",
    "iso:country":"NZ",
    "sg:address":"cnr Dent & Carruth Sts ",
    "sg:city":"Whangarei",
    "sg:orig_category":"Automotive: Accessories: Car Audio Systems",
    "sg:phone":"+64 9-430 4470",
    "sg:province":"Northland",
    "sg:website":"http://www.pacificmotorgroup.co.nz",
    "wof:name":"Pacific Motor Group",
    "wof:placetype":"venue"
},
  "geometry": {"coordinates":[174.320526,-35.725399],"type":"Point"}
}