{
  "type": "Feature",
  "properties": {
    "iso:country":"NZ",
    "sg:address":"140 Anzac Pde ",
    "sg:city":"Wanganui",
    "sg:classifiers":[
        {
            "category":"Travel",
            "subcategory":"Hotels & Motels",
            "type":"Entertainment"
        }
    ],
    "sg:phone":"+64 800 800 225",
    "sg:province":"Manawatu-Wanganui",
    "sg:tags":[
        "holiday",
        "tourism",
        "accommodation"
    ],
    "sg:website":"http://www.acacia-park.co.nz",
    "wof:name":"Acacia Park Motel",
    "wof:placetype":"venue"
},
  "geometry": {"coordinates":[175.06053199999999,-39.930664],"type":"Point"}
}