{
  "type": "Feature",
  "properties": {
    "iso:country":"NZ",
    "sg:address":"215 Heretaunga St West ",
    "sg:city":"Hastings",
    "sg:orig_category":"Food And Drink: Catering: Caterers",
    "sg:phone":"+64 6-878 8466",
    "sg:province":"Hawke's Bay",
    "wof:name":"The Maine Food & Coffee House",
    "wof:placetype":"venue"
},
  "geometry": {"coordinates":[-81.508163,29.711214],"type":"Point"}
}