{
  "type": "Feature",
  "properties": {
    "addr:full":"527 State Highway 2 R D 2  Hastings Hawke's Bay",
    "addr:housenumber":"527;2",
    "addr:street":"State Highway 2 R D",
    "iso:country":"NZ",
    "sg:address":"527 State Highway 2 R D 2 ",
    "sg:city":"Hastings",
    "sg:classifiers":[
        {
            "category":"Home & Garden",
            "subcategory":"Garden Supply",
            "type":"Retail Goods"
        }
    ],
    "sg:phone":"+64 6-870 1070",
    "sg:province":"Hawke's Bay",
    "sg:tags":[
        "products",
        "nursery",
        "gardening"
    ],
    "wof:name":"Paradise Palms",
    "wof:placetype":"venue"
},
  "geometry": {"coordinates":[-97.967888,46.677605],"type":"Point"}
}