{
  "type": "Feature",
  "properties": {
    "addr:full":"4 Mason St  Dunedin Otago",
    "addr:housenumber":"4",
    "addr:street":"Mason St",
    "iso:country":"NZ",
    "sg:address":"4 Mason St ",
    "sg:city":"Dunedin",
    "sg:classifiers":[
        {
            "category":"Building & Trades",
            "subcategory":"Construction",
            "type":"Services"
        }
    ],
    "sg:phone":"+64 3-477 0011",
    "sg:province":"Otago",
    "sg:tags":[
        "home",
        "garden",
        "related",
        "plasterer"
    ],
    "wof:name":"Able Scaffolding Ltd",
    "wof:placetype":"venue"
},
  "geometry": {"coordinates":[-82.784721,28.013355],"type":"Point"}
}