{
  "type": "Feature",
  "properties": {
    "addr:full":"4 Port Rd  Whangarei Northland",
    "addr:housenumber":"4",
    "addr:street":"Port Rd",
    "iso:country":"NZ",
    "sg:address":"4 Port Rd ",
    "sg:city":"Whangarei",
    "sg:orig_category":"Industrial: Engineering: Engineers: Engineers - Consulting",
    "sg:phone":"+64 9-438 3345",
    "sg:province":"Northland",
    "wof:name":"Northern - Civil Consulting Engineers Ltd",
    "wof:placetype":"venue"
},
  "geometry": {"coordinates":[174.32710299999999,-35.72982],"type":"Point"}
}