{
  "type": "Feature",
  "properties": {
    "addr:full":"100 Durham St  Christchurch Canterbury",
    "addr:housenumber":"100",
    "addr:street":"Durham St",
    "iso:country":"NZ",
    "sg:address":"100 Durham St ",
    "sg:city":"Christchurch",
    "sg:classifiers":[
        {
            "category":"Shopping",
            "subcategory":"Clothing, Apparel, & Fashions",
            "type":"Retail Goods"
        }
    ],
    "sg:phone":"+64 3-365 4741",
    "sg:province":"Canterbury",
    "sg:tags":[
        "clothing",
        "fabric"
    ],
    "sg:website":"http://www.yellowpages.co.nz/for/sgm/dp37303.html",
    "wof:name":"Badger Solutions Ltd",
    "wof:placetype":"venue"
},
  "geometry": {"coordinates":[172.633804,-43.541695],"type":"Point"}
}