{
  "type": "Feature",
  "properties": {
    "iso:country":"NZ",
    "sg:address":"33 A Box Hill Khandallah ",
    "sg:city":"Wellington",
    "sg:classifiers":[
        {
            "category":"Personal",
            "subcategory":"Hair Removal",
            "type":"Services"
        }
    ],
    "sg:phone":"+64 4-479 3757",
    "sg:province":"Wellington",
    "sg:tags":[
        "health",
        "beauty"
    ],
    "wof:name":"Jill Learmonth",
    "wof:placetype":"venue"
},
  "geometry": {"coordinates":[174.791412,-41.244102],"type":"Point"}
}