{
  "type": "Feature",
  "properties": {
    "addr:full":"Unit 6 954 Ferry Rd  Christchurch Canterbury",
    "addr:housenumber":"unit 6 954",
    "addr:street":"Ferry Rd",
    "iso:country":"NZ",
    "sg:address":"Unit 6 954 Ferry Rd ",
    "sg:city":"Christchurch",
    "sg:classifiers":[
        {
            "category":"Home & Garden",
            "subcategory":"Home Furnishings",
            "type":"Retail Goods"
        }
    ],
    "sg:phone":"+64 3-384 2488",
    "sg:province":"Canterbury",
    "sg:tags":[
        "accessory"
    ],
    "sg:website":"http://www.yellowpages.co.nz/for/birchfieldsglass/dp45364.html",
    "wof:name":"Birchfield's Glass & Glazing",
    "wof:placetype":"venue"
},
  "geometry": {"coordinates":[-76.537834,37.605659],"type":"Point"}
}