{
  "type": "Feature",
  "properties": {
    "iso:country":"NZ",
    "sg:address":"12 Irwell St ",
    "sg:city":"Gore",
    "sg:orig_category":"Health And Beauty: Specialists: Chiropractors",
    "sg:phone":"+64 3-208 9520",
    "sg:province":"Southland",
    "wof:name":"Gore Chiropractic Clinic",
    "wof:placetype":"venue"
},
  "geometry": {"coordinates":[-95.116547,35.530331],"type":"Point"}
}