{
  "type": "Feature",
  "properties": {
    "iso:country":"NZ",
    "sg:address":"100 Gore St ",
    "sg:city":"Bluff",
    "sg:classifiers":[
        {
            "category":"Education",
            "subcategory":"Special Training",
            "type":"Public Place"
        }
    ],
    "sg:phone":"+64 3-212 7757",
    "sg:tags":[
        "charter",
        "shopping",
        "dive",
        "tuition",
        "water",
        "sports",
        "retailers",
        "sport"
    ],
    "wof:name":"Southern Aqua Adventures",
    "wof:placetype":"venue"
},
  "geometry": {"coordinates":[-109.546745,37.286579],"type":"Point"}
}