{
  "type": "Feature",
  "properties": {
    "addr:full":"162 Te Aute Rd Havelock North  Hastings Hawke's Bay",
    "addr:housenumber":"162",
    "addr:street":"Te Aute Rd",
    "iso:country":"NZ",
    "sg:address":"162 Te Aute Rd Havelock North ",
    "sg:city":"Hastings",
    "sg:orig_category":"Home And Garden: Gardening: Services: Landscape Consultants",
    "sg:phone":"+64 6-877 1188",
    "sg:province":"Hawke's Bay",
    "wof:name":"Macphail Jamie Landscape Designer",
    "wof:placetype":"venue"
},
  "geometry": {"coordinates":[176.862076,-39.676376],"type":"Point"}
}