{
  "type": "Feature",
  "properties": {
    "iso:country":"NZ",
    "sg:address":"9 Alexandra Rd RD1 Te ",
    "sg:city":"Aroha",
    "sg:classifiers":[
        {
            "category":"Bars & Pubs",
            "subcategory":"Lounge",
            "type":"Food & Drink"
        }
    ],
    "sg:phone":"+64 7-884 4550",
    "sg:tags":[
        "-"
    ],
    "wof:name":"Swiss Sausage Ltd",
    "wof:placetype":"venue"
},
  "geometry": {"coordinates":[175.707718,-37.534805],"type":"Point"}
}