{
  "type": "Feature",
  "properties": {
    "addr:full":"55 Aviation Ave Mt  Maunganui Bay of Plenty",
    "addr:housenumber":"55",
    "addr:street":"Aviation Ave;Maunganui Bay",
    "iso:country":"NZ",
    "sg:address":"55 Aviation Ave Mt ",
    "sg:city":"Maunganui",
    "sg:classifiers":[
        {
            "category":"Home & Garden",
            "subcategory":"Building Materials",
            "type":"Retail Goods"
        }
    ],
    "sg:phone":"+64 7-572 1557",
    "sg:province":"Bay of Plenty",
    "sg:tags":[
        "brick",
        "outdoor",
        "paving"
    ],
    "wof:name":"Paving Worx",
    "wof:placetype":"venue"
},
  "geometry": {"coordinates":[176.18627900000001,-37.641048],"type":"Point"}
}