{
  "type": "Feature",
  "properties": {
    "addr:full":"102 Victoria St  Christchurch Canterbury",
    "addr:housenumber":"102",
    "addr:street":"Victoria St",
    "iso:country":"NZ",
    "sg:address":"102 Victoria St ",
    "sg:city":"Christchurch",
    "sg:classifiers":[
        {
            "category":"Communications",
            "subcategory":"Radio Station",
            "type":"Services"
        }
    ],
    "sg:phone":"+64 3-377 1999",
    "sg:province":"Canterbury",
    "sg:tags":[
        "broadcasting"
    ],
    "wof:name":"More FM Christchurch Ltd",
    "wof:placetype":"venue"
},
  "geometry": {"coordinates":[-76.537834,37.605659],"type":"Point"}
}