{
  "type": "Feature",
  "properties": {
    "iso:country":"NZ",
    "sg:address":"102 Leonard Rd ",
    "sg:city":"Penrose",
    "sg:classifiers":[
        {
            "category":"Home & Garden",
            "subcategory":"Building Materials",
            "type":"Retail Goods"
        }
    ],
    "sg:phone":"+64 9-580 1220",
    "sg:province":"Auckland",
    "sg:tags":[
        "brick",
        "outdoor",
        "paving"
    ],
    "wof:name":"Slatecrete Paving Ltd",
    "wof:placetype":"venue"
},
  "geometry": {"coordinates":[-105.02407100000001,38.431049],"type":"Point"}
}