{
  "type": "Feature",
  "properties": {
    "addr:full":"PO Box 2752  Christchurch Canterbury",
    "addr:housenumber":"po",
    "addr:postcode":"2752",
    "addr:street":"Box",
    "iso:country":"NZ",
    "sg:address":"PO Box 2752 ",
    "sg:city":"Christchurch",
    "sg:classifiers":[
        {
            "category":"Shopping",
            "subcategory":"Pets & Pet Supplies",
            "type":"Retail Goods"
        }
    ],
    "sg:phone":"+64 3-379 3797",
    "sg:province":"Canterbury",
    "sg:tags":[
        "home",
        "garden"
    ],
    "wof:name":"Kendon Dr Evan BVSc",
    "wof:placetype":"venue"
},
  "geometry": {"coordinates":[172.637314,-43.531315],"type":"Point"}
}