{
  "type": "Feature",
  "properties": {
    "iso:country":"NZ",
    "sg:address":"450 George St ",
    "sg:city":"Dunedin",
    "sg:classifiers":[
        {
            "category":"Personal",
            "subcategory":"Tanning Parlor",
            "type":"Services"
        }
    ],
    "sg:phone":"+64 3-477 2303",
    "sg:province":"Otago",
    "sg:tags":[
        "sun",
        "health",
        "beauty"
    ],
    "wof:name":"Hairhunters Hiz & Herz Salon",
    "wof:placetype":"venue"
},
  "geometry": {"coordinates":[170.507812,-45.867043],"type":"Point"}
}