{
  "type": "Feature",
  "properties": {
    "addr:full":"81 Victoria St  Dargaville Northland",
    "addr:housenumber":"81",
    "addr:street":"Victoria St",
    "iso:country":"NZ",
    "sg:address":"81 Victoria St ",
    "sg:city":"Dargaville",
    "sg:classifiers":[
        {
            "category":"Food & Beverages",
            "subcategory":"Liquor & Beverages",
            "type":"Retail Goods"
        }
    ],
    "sg:phone":"+64 9-439 8786",
    "sg:province":"Northland",
    "sg:tags":[
        "drink",
        "outlet"
    ],
    "wof:name":"Empire Liquor Centre Wines And Spirits",
    "wof:placetype":"venue"
},
  "geometry": {"coordinates":[173.882553,-35.934937],"type":"Point"}
}