{
  "type": "Feature",
  "properties": {
    "iso:country":"NZ",
    "sg:address":"15 Kakariki Gro ",
    "sg:city":"Waikanae",
    "sg:orig_category":"Health And Beauty: Specialists: Osteopaths",
    "sg:phone":"+64 4-293 2237",
    "wof:name":"Elaine Youngs Osteopath",
    "wof:placetype":"venue"
},
  "geometry": {"coordinates":[175.073898,-40.877113],"type":"Point"}
}