{
  "type": "Feature",
  "properties": {
    "addr:full":"15 Kakariki Gro  Waikanae",
    "addr:housenumber":"15",
    "addr:street":"Kakariki Gro",
    "iso:country":"NZ",
    "sg:address":"15 Kakariki Gro ",
    "sg:city":"Waikanae",
    "sg:orig_category":"Health And Beauty: Specialists: Osteopaths",
    "sg:phone":"+64 4-293 2237",
    "wof:name":"Elaine Youngs Osteopath",
    "wof:placetype":"venue"
},
  "geometry": {"coordinates":[175.07389800000001,-40.877113],"type":"Point"}
}