{
  "type": "Feature",
  "properties": {
    "addr:full":"PO Box 36481 Northcote  Auckland Auckland",
    "addr:housenumber":"po box 36481",
    "iso:country":"NZ",
    "sg:address":"PO Box 36481 Northcote ",
    "sg:city":"Auckland",
    "sg:classifiers":[
        {
            "category":"Shopping",
            "subcategory":"Stationery & Office Supplies",
            "type":"Retail Goods"
        }
    ],
    "sg:phone":"+64 9-480 0771",
    "sg:province":"Auckland",
    "sg:tags":[
        "supplies",
        "educational",
        "material",
        "education",
        "training"
    ],
    "wof:name":"Flashbacks Ltd",
    "wof:placetype":"venue"
},
  "geometry": {"coordinates":[174.747849,-36.801125],"type":"Point"}
}