{
  "type": "Feature",
  "properties": {
    "addr:full":"Mastermall 202 Queen St  Masterton Wellington",
    "addr:housenumber":"202",
    "addr:street":"Queen St",
    "iso:country":"NZ",
    "sg:address":"Mastermall 202 Queen St ",
    "sg:city":"Masterton",
    "sg:orig_category":"Home And Garden: Accessories: Hardware",
    "sg:phone":"+64 6-377 0213",
    "sg:province":"Wellington",
    "wof:name":"Masterton Tool Shed Ltd",
    "wof:placetype":"venue"
},
  "geometry": {"coordinates":[175.65733299999999,-40.94931],"type":"Point"}
}