{
  "type": "Feature",
  "properties": {
    "iso:country":"NZ",
    "sg:address":"89 Rata St Naenae Lower ",
    "sg:city":"Hutt",
    "sg:orig_category":"Industrial: Engineering: Engineers - Precision",
    "sg:phone":"+64 4-567 8411",
    "sg:province":"Wellington",
    "wof:name":"Voisey W J Ltd",
    "wof:placetype":"venue"
},
  "geometry": {"coordinates":[174.959625,-41.20002],"type":"Point"}
}