{
  "type": "Feature",
  "properties": {
    "addr:full":"Westpac Plaza Moana Ave Orewa Hibiscus  Hibiscus Coast Auckland",
    "addr:street":"Moana Ave",
    "iso:country":"NZ",
    "sg:address":"Westpac Plaza Moana Ave Orewa Hibiscus ",
    "sg:city":"Hibiscus Coast",
    "sg:classifiers":[
        {
            "category":"Home & Garden",
            "subcategory":"Kitchen Supply",
            "type":"Retail Goods"
        }
    ],
    "sg:phone":"+64 9-426 4935",
    "sg:province":"Auckland",
    "sg:tags":[
        "shop",
        "pet",
        "pets"
    ],
    "wof:name":"Tails & Scales",
    "wof:placetype":"venue"
},
  "geometry": {"coordinates":[174.69012499999999,-36.582741],"type":"Point"}
}