{
  "type": "Feature",
  "properties": {
    "addr:full":"Unit 4 131 Park Rd Miramar  Wellington Wellington",
    "addr:housenumber":"unit 4 131",
    "addr:street":"Park Rd",
    "iso:country":"NZ",
    "sg:address":"Unit 4 131 Park Rd Miramar ",
    "sg:city":"Wellington",
    "sg:classifiers":[
        {
            "category":"Professional",
            "subcategory":"Art Services",
            "type":"Services"
        }
    ],
    "sg:phone":"+64 4-388 5931",
    "sg:province":"Wellington",
    "sg:tags":[
        "equipment",
        "arts",
        "sport",
        "film",
        "leisure"
    ],
    "wof:name":"Robotechnology",
    "wof:placetype":"venue"
},
  "geometry": {"coordinates":[174.82119800000001,-41.309319],"type":"Point"}
}