{
  "type": "Feature",
  "properties": {
    "addr:full":"104 Campbell St Karori  Wellington Wellington",
    "addr:housenumber":"104",
    "addr:street":"Campbell St",
    "iso:country":"NZ",
    "sg:address":"104 Campbell St Karori ",
    "sg:city":"Wellington",
    "sg:classifiers":[
        {
            "category":"Recreation",
            "subcategory":"Gun Range",
            "type":"Entertainment"
        }
    ],
    "sg:phone":"+64 4-476 8460",
    "sg:province":"Wellington",
    "sg:tags":[
        "sports",
        "sport",
        "-",
        "leisure",
        "gunsmith"
    ],
    "wof:name":"Collings D W & Bradey Ltd",
    "wof:placetype":"venue"
},
  "geometry": {"coordinates":[174.74231,-41.291294],"type":"Point"}
}