{
  "type": "Feature",
  "properties": {
    "addr:full":"211 A Parnell Rd Parnell  Auckland Auckland",
    "addr:housenumber":"211 a",
    "addr:street":"Parnell Rd",
    "iso:country":"NZ",
    "sg:address":"211 A Parnell Rd Parnell ",
    "sg:city":"Auckland",
    "sg:classifiers":[
        {
            "category":"Insurance",
            "subcategory":"Health Insurance",
            "type":"Services"
        }
    ],
    "sg:phone":"+64 9-373 4665",
    "sg:province":"Auckland",
    "sg:tags":[
        "beauty",
        "supply"
    ],
    "wof:name":"Filing Cabinet",
    "wof:placetype":"venue"
},
  "geometry": {"coordinates":[174.78027299999999,-36.855328],"type":"Point"}
}