{
  "type": "Feature",
  "properties": {
    "iso:country":"NZ",
    "sg:address":"Line Rd ",
    "sg:city":"Methven",
    "sg:orig_category":"Transport: Transportation: Transport Operators",
    "sg:phone":"+64 3-302 8616",
    "wof:name":"Wareing Philip Ltd",
    "wof:placetype":"venue"
},
  "geometry": {"coordinates":[171.658401,-43.642918],"type":"Point"}
}