{
  "type": "Feature",
  "properties": {
    "addr:full":"C/- 439 South Rd Caversham  Dunedin Otago",
    "addr:housenumber":"439",
    "addr:street":"C /;South Rd",
    "iso:country":"NZ",
    "sg:address":"C/- 439 South Rd Caversham ",
    "sg:city":"Dunedin",
    "sg:classifiers":[
        {
            "category":"Education",
            "subcategory":"Dance Studio",
            "type":"Public Place"
        }
    ],
    "sg:phone":"+64 3-487 9158",
    "sg:province":"Otago",
    "sg:tags":[
        "school",
        "dancing",
        "-",
        "leisure",
        "sports",
        "sport"
    ],
    "wof:name":"Martha Still School of Dance",
    "wof:placetype":"venue"
},
  "geometry": {"coordinates":[170.47966,-45.896809],"type":"Point"}
}