{
  "type": "Feature",
  "properties": {
    "iso:country":"NZ",
    "sg:address":"594 Rosebank Rd Avondale ",
    "sg:city":"Auckland",
    "sg:orig_category":"Industrial: Parts: Chains - Transmission",
    "sg:phone":"+64 9-828 5018",
    "sg:province":"Auckland",
    "sg:website":"http://www.renold.com.au",
    "wof:name":"Renold New Zealand",
    "wof:placetype":"venue"
},
  "geometry": {"coordinates":[174.685684,-36.888668],"type":"Point"}
}