{
  "type": "Feature",
  "properties": {
    "addr:full":"Hood Aerodrome  Masterton Wellington",
    "iso:country":"NZ",
    "sg:address":"Hood Aerodrome ",
    "sg:city":"Masterton",
    "sg:classifiers":[
        {
            "category":"Sports & Exercise",
            "subcategory":"Ski Slope",
            "type":"Entertainment"
        }
    ],
    "sg:phone":"+64 800 867 593",
    "sg:province":"Wellington",
    "sg:tags":[
        "skydiving",
        "parachuting",
        "aerial",
        "leisure",
        "sports"
    ],
    "wof:name":"Skydive Wairarapa",
    "wof:placetype":"venue"
},
  "geometry": {"coordinates":[175.62898300000001,-40.9762],"type":"Point"}
}