{
  "type": "Feature",
  "properties": {
    "iso:country":"NZ",
    "sg:address":"8 Arthur Brown Pl Mt Wellington ",
    "sg:city":"Auckland",
    "sg:orig_category":"Industrial: Products: Laboratory Supplies",
    "sg:phone":"+64 9-573 0770",
    "sg:province":"Auckland",
    "wof:name":"Biotek",
    "wof:placetype":"venue"
},
  "geometry": {"coordinates":[174.844925,-36.91618],"type":"Point"}
}