{
  "type": "Feature",
  "properties": {
    "iso:country":"NZ",
    "sg:address":"Schultz Rd Belgrove ",
    "sg:city":"Wakefield",
    "sg:classifiers":[
        {
            "category":"Utilities",
            "type":"Services"
        }
    ],
    "sg:phone":"+64 3-541 8845",
    "sg:tags":[
        "industrial",
        "energy",
        "utilities",
        "coal",
        "wood",
        "coke"
    ],
    "wof:name":"Belgrove Firewood",
    "wof:placetype":"venue"
},
  "geometry": {"coordinates":[172.94899,-41.459869],"type":"Point"}
}