{
  "type": "Feature",
  "properties": {
    "iso:country":"NZ",
    "sg:address":"93 Dominion Rd Mt Eden ",
    "sg:city":"Auckland",
    "sg:orig_category":"Shopping: Sports Retailers: Sports Goods: Sporting Goods",
    "sg:phone":"+64 9-630 6645",
    "sg:province":"Auckland",
    "wof:name":"James Gilbert (New Zealand) Ltd",
    "wof:placetype":"venue"
},
  "geometry": {"coordinates":[174.75238,-36.871555],"type":"Point"}
}