{
  "type": "Feature",
  "properties": {
    "addr:full":"162 Queen St Auckland Central  Auckland Auckland",
    "addr:housenumber":"162",
    "addr:street":"Queen St",
    "iso:country":"NZ",
    "sg:address":"162 Queen St Auckland Central ",
    "sg:city":"Auckland",
    "sg:classifiers":[
        {
            "category":"Shopping",
            "subcategory":"Photographic Equipment",
            "type":"Retail Goods"
        }
    ],
    "sg:phone":"+64 9-303 1879",
    "sg:province":"Auckland",
    "sg:tags":[
        "sport",
        "leisure",
        "hobbies"
    ],
    "sg:website":"http://www.camera-camera.com",
    "wof:name":"Camera & Camera",
    "wof:placetype":"venue"
},
  "geometry": {"coordinates":[174.76573200000001,-36.84798],"type":"Point"}
}