{
  "type": "Feature",
  "properties": {
    "addr:full":"Tennyson St  Wanganui Manawatu-Wanganui",
    "addr:street":"Tennyson St",
    "iso:country":"NZ",
    "sg:address":"Tennyson St ",
    "sg:city":"Wanganui",
    "sg:orig_category":"Sports And Leisure: General: Clubs",
    "sg:phone":"+64 6-344 4449",
    "sg:province":"Manawatu-Wanganui",
    "wof:name":"Castlecliff Club Inc",
    "wof:placetype":"venue"
},
  "geometry": {"coordinates":[174.99281300000001,-39.941895],"type":"Point"}
}