{
  "type": "Feature",
  "properties": {
    "addr:full":"State Highway 32 Tihoi  Taupo Waikato",
    "addr:street":"State Highway 32 Tihoi",
    "iso:country":"NZ",
    "sg:address":"State Highway 32 Tihoi ",
    "sg:city":"Taupo",
    "sg:orig_category":"Automotive: General Services: Service Stations",
    "sg:phone":"+64 7-372 8366",
    "sg:province":"Waikato",
    "wof:name":"Tihoi Trading Post",
    "wof:placetype":"venue"
},
  "geometry": {"coordinates":[176.08433500000001,-38.689281],"type":"Point"}
}