{
  "type": "Feature",
  "properties": {
    "iso:country":"NZ",
    "sg:address":"Cnr Vienna & Buffon St ",
    "sg:city":"Waltham",
    "sg:classifiers":[
        {
            "category":"Recreation",
            "type":"Entertainment"
        }
    ],
    "sg:phone":"+64 25325416",
    "sg:tags":[
        "sport",
        "tramping",
        "leisure",
        "camping"
    ],
    "wof:name":"Hire Cool Refrigeration",
    "wof:placetype":"venue"
},
  "geometry": {"coordinates":[-71.235321,42.376438],"type":"Point"}
}