{
  "type": "Feature",
  "properties": {
    "addr:full":"Springs Rd Lincoln R D 4  Christchurch Canterbury",
    "addr:housenumber":"4",
    "addr:street":"Springs Rd;R D",
    "iso:country":"NZ",
    "sg:address":"Springs Rd Lincoln R D 4 ",
    "sg:city":"Christchurch",
    "sg:classifiers":[
        {
            "category":"Utilities",
            "subcategory":"Sewage",
            "type":"Services"
        }
    ],
    "sg:phone":"+64 3-349 8871",
    "sg:province":"Canterbury",
    "sg:tags":[
        "home",
        "tank",
        "garden",
        "septic"
    ],
    "wof:name":"Murray Robson",
    "wof:placetype":"venue"
},
  "geometry": {"coordinates":[172.637314,-43.531315],"type":"Point"}
}