{
  "type": "Feature",
  "properties": {
    "iso:country":"NZ",
    "sg:address":"Tautoro Rd ",
    "sg:city":"Kaitaia",
    "sg:classifiers":[
        {
            "category":"Building & Trades",
            "subcategory":"Plumbing",
            "type":"Services"
        }
    ],
    "sg:phone":"+64 9-409 5352",
    "sg:province":"Northland",
    "sg:tags":[
        "home",
        "plumber",
        "garden",
        "related"
    ],
    "wof:name":"Peita Boys Contractors",
    "wof:placetype":"venue"
},
  "geometry": {"coordinates":[173.259445,-35.114212],"type":"Point"}
}