{
  "type": "Feature",
  "properties": {
    "addr:full":"PO Box 893  Wellington Wellington",
    "addr:housenumber":"po;893",
    "addr:street":"Box",
    "iso:country":"NZ",
    "sg:address":"PO Box 893 ",
    "sg:city":"Wellington",
    "sg:classifiers":[
        {
            "category":"Sports & Exercise",
            "subcategory":"Skate Park",
            "type":"Entertainment"
        }
    ],
    "sg:phone":"+64 4-472 8904",
    "sg:province":"Wellington",
    "sg:tags":[
        "arts",
        "museum",
        "leisure",
        "gallery"
    ],
    "wof:name":"Museum of Wellington City & Sea",
    "wof:placetype":"venue"
},
  "geometry": {"coordinates":[-85.910454,33.827946],"type":"Point"}
}