{
  "type": "Feature",
  "properties": {
    "addr:full":"1 Admiralty Place Waikawa Bay  Picton Marlborough",
    "addr:housenumber":"1",
    "addr:street":"Admiralty Place Waikawa Bay",
    "iso:country":"NZ",
    "sg:address":"1 Admiralty Place Waikawa Bay ",
    "sg:city":"Picton",
    "sg:classifiers":[
        {
            "category":"Building & Trades",
            "subcategory":"Plumbing",
            "type":"Services"
        }
    ],
    "sg:phone":"+64 25480785",
    "sg:province":"Marlborough",
    "sg:tags":[
        "home",
        "plumber",
        "garden",
        "related"
    ],
    "wof:name":"Chris Ford Plumbing Ltd",
    "wof:placetype":"venue"
},
  "geometry": {"coordinates":[174.00427199999999,-41.294788],"type":"Point"}
}