{
  "type": "Feature",
  "properties": {
    "iso:country":"NZ",
    "sg:address":"6 Rangipoia Pl ",
    "sg:city":"Turangi",
    "sg:classifiers":[
        {
            "category":"Personal",
            "type":"Services"
        }
    ],
    "sg:phone":"+64 7-386 0723",
    "sg:tags":[
        "celebrant",
        "arrangements",
        "marriage",
        "wedding"
    ],
    "wof:name":"Green Janeve",
    "wof:placetype":"venue"
},
  "geometry": {"coordinates":[175.812729,-38.982136],"type":"Point"}
}