{
  "type": "Feature",
  "properties": {
    "addr:full":"6 Rangipoia Pl  Turangi",
    "addr:housenumber":"6",
    "addr:street":"Rangipoia Pl",
    "iso:country":"NZ",
    "sg:address":"6 Rangipoia Pl ",
    "sg:city":"Turangi",
    "sg:classifiers":[
        {
            "category":"Personal",
            "type":"Services"
        }
    ],
    "sg:phone":"+64 7-386 0723",
    "sg:tags":[
        "celebrant",
        "arrangements",
        "marriage",
        "wedding"
    ],
    "wof:name":"Green Janeve",
    "wof:placetype":"venue"
},
  "geometry": {"coordinates":[175.81272899999999,-38.982136],"type":"Point"}
}