{
  "type": "Feature",
  "properties": {
    "addr:full":"75 High St  Waimate",
    "addr:housenumber":"75",
    "addr:street":"High St",
    "iso:country":"NZ",
    "sg:address":"75 High St ",
    "sg:city":"Waimate",
    "sg:orig_category":"Transport: Transportation: Transport Operators",
    "sg:phone":"+64 3-689 8992",
    "wof:name":"Interfreight Carriers",
    "wof:placetype":"venue"
},
  "geometry": {"coordinates":[171.04991100000001,-44.733742],"type":"Point"}
}