{
  "type": "Feature",
  "properties": {
    "addr:full":"Information Centre Willow St  Tauranga Bay of Plenty",
    "addr:street":"Willow St",
    "iso:country":"NZ",
    "sg:address":"Information Centre Willow St ",
    "sg:city":"Tauranga",
    "sg:classifiers":[
        {
            "category":"Bus Charters",
            "type":"Transportation"
        }
    ],
    "sg:phone":"+64 7-578 8103",
    "sg:province":"Bay of Plenty",
    "sg:tags":[
        "services",
        "travel",
        "tourism"
    ],
    "wof:name":"InterCity Coachlines",
    "wof:placetype":"venue"
},
  "geometry": {"coordinates":[176.144745,-37.703156],"type":"Point"}
}