{
  "type": "Feature",
  "properties": {
    "addr:full":"23 Landing Rd  Whakatane Bay of Plenty",
    "addr:housenumber":"23",
    "addr:street":"Landing Rd",
    "iso:country":"NZ",
    "sg:address":"23 Landing Rd ",
    "sg:city":"Whakatane",
    "sg:orig_category":"Farming: Services: Veterinarians",
    "sg:phone":"+64 7-308 7479",
    "sg:province":"Bay of Plenty",
    "wof:name":"Veterinary Health Centre Whakatane",
    "wof:placetype":"venue"
},
  "geometry": {"coordinates":[176.97972100000001,-37.95863],"type":"Point"}
}