{
  "type": "Feature",
  "properties": {
    "iso:country":"NZ",
    "sg:address":"67 Customs St East Auckland Central ",
    "sg:city":"Auckland",
    "sg:orig_category":"Transport: Transportation: Freight",
    "sg:phone":"+64 9-377 3590",
    "sg:province":"Auckland",
    "wof:name":"Freight Services Limited",
    "wof:placetype":"venue"
},
  "geometry": {"coordinates":[174.768753,-36.845303],"type":"Point"}
}