{
  "type": "Feature",
  "properties": {
    "addr:full":"116 Totora Rd Miramar  Wellington Wellington",
    "addr:housenumber":"116",
    "addr:street":"Totora Rd",
    "iso:country":"NZ",
    "sg:address":"116 Totora Rd Miramar ",
    "sg:city":"Wellington",
    "sg:orig_category":"Health And Beauty: Diet: Dietitians",
    "sg:phone":"+64 4-388 8838",
    "sg:province":"Wellington",
    "wof:name":"Andrew Harris",
    "wof:placetype":"venue"
},
  "geometry": {"coordinates":[174.82782,-41.305393],"type":"Point"}
}