{
  "type": "Feature",
  "properties": {
    "addr:full":"4 York St  Picton Marlborough",
    "addr:housenumber":"4",
    "addr:street":"York St",
    "iso:country":"NZ",
    "sg:address":"4 York St ",
    "sg:city":"Picton",
    "sg:classifiers":[
        {
            "category":"Farming",
            "subcategory":"Fish & Marine Products",
            "type":"Manufacturing & Wholesale Goods"
        }
    ],
    "sg:phone":"+64 3-573 8087",
    "sg:province":"Marlborough",
    "sg:tags":[
        "-",
        "boat",
        "transport"
    ],
    "wof:name":"Jules Engineering",
    "wof:placetype":"venue"
},
  "geometry": {"coordinates":[174.00195299999999,-41.293465],"type":"Point"}
}