{
  "type": "Feature",
  "properties": {
    "iso:country":"NZ",
    "sg:address":"Cnr Taonui & Maire Sts Palmerston ",
    "sg:city":"Palmerston North",
    "sg:classifiers":[
        {
            "category":"Home & Garden",
            "subcategory":"Furniture",
            "type":"Retail Goods"
        }
    ],
    "sg:phone":"+64 6-358 6800",
    "sg:province":"Manawatu-Wanganui",
    "sg:tags":[
        "furniture/furnishings",
        "designer"
    ],
    "wof:name":"Turnbull Lounge Suites",
    "wof:placetype":"venue"
},
  "geometry": {"coordinates":[175.60560599999999,-40.261379],"type":"Point"}
}