{
  "type": "Feature",
  "properties": {
    "addr:full":"Level one 1109 Tutanekai St  Rotorua Bay of Plenty",
    "addr:housenumber":"1109",
    "addr:street":"Tutanekai St",
    "iso:country":"NZ",
    "sg:address":"Level one 1109 Tutanekai St ",
    "sg:city":"Rotorua",
    "sg:classifiers":[
        {
            "category":"Retail",
            "subcategory":"Driving School",
            "type":"Services"
        }
    ],
    "sg:phone":"+64 7-349 0739",
    "sg:province":"Bay of Plenty",
    "sg:tags":[
        "health",
        "beauty"
    ],
    "wof:name":"Imagez Beauty College",
    "wof:placetype":"venue"
},
  "geometry": {"coordinates":[176.24499499999999,-38.1418],"type":"Point"}
}