{
  "type": "Feature",
  "properties": {
    "addr:full":"3 Lindsay-Calcium Rd Isla Bank  Thornbury",
    "addr:housenumber":"3",
    "addr:street":"Lindsay-Calcium Rd",
    "iso:country":"NZ",
    "sg:address":"3 Lindsay-Calcium Rd Isla Bank ",
    "sg:city":"Thornbury",
    "sg:classifiers":[
        {
            "category":"Health Services",
            "subcategory":"Dentist",
            "type":"Services"
        }
    ],
    "sg:phone":"+64 3-224 6173",
    "sg:tags":[
        "dental",
        "clinic",
        "beauty"
    ],
    "wof:name":"Isla Bank School Dental Clinic",
    "wof:placetype":"venue"
},
  "geometry": {"coordinates":[168.12661700000001,-46.199162],"type":"Point"}
}