{
  "type": "Feature",
  "properties": {
    "iso:country":"NZ",
    "sg:address":"16 Miro St ",
    "sg:city":"Inglewood",
    "sg:classifiers":[
        {
            "category":"Personal",
            "type":"Services"
        }
    ],
    "sg:phone":"+64 6-756 7494",
    "sg:tags":[
        "celebrant",
        "arrangements",
        "marriage",
        "wedding"
    ],
    "wof:name":"Jeanette Morrison",
    "wof:placetype":"venue"
},
  "geometry": {"coordinates":[-118.356224,33.961781],"type":"Point"}
}