{
  "type": "Feature",
  "properties": {
    "addr:full":"43 Bank St  Timaru Canterbury",
    "addr:housenumber":"43",
    "addr:street":"Bank St",
    "iso:country":"NZ",
    "sg:address":"43 Bank St ",
    "sg:city":"Timaru",
    "sg:orig_category":"Shopping: Accessories: Accessories - Clothing",
    "sg:phone":"+64 3-688 6956",
    "sg:province":"Canterbury",
    "wof:name":"Alpsocks",
    "wof:placetype":"venue"
},
  "geometry": {"coordinates":[171.25027499999999,-44.397015],"type":"Point"}
}