{
  "type": "Feature",
  "properties": {
    "addr:full":"277 Dyers Rd Bromley  Christchurch Canterbury",
    "addr:housenumber":"277",
    "addr:street":"Dyers Rd;Christchurch",
    "iso:country":"NZ",
    "sg:address":"277 Dyers Rd Bromley ",
    "sg:city":"Christchurch",
    "sg:orig_category":"Non-Classified Establishments",
    "sg:phone":"+64 3-384 6536",
    "sg:province":"Canterbury",
    "wof:name":"Avondale Karting World",
    "wof:placetype":"venue"
},
  "geometry": {"coordinates":[172.70408599999999,-43.537415],"type":"Point"}
}