{
  "type": "Feature",
  "properties": {
    "iso:country":"NZ",
    "sg:address":"7 Upland St Brookfield ",
    "sg:city":"Tauranga",
    "sg:orig_category":"Industrial: Services: Gasfitters",
    "sg:phone":"+64 7-576 6112",
    "sg:province":"Bay of Plenty",
    "wof:name":"V I P Gas & Plumbing Services",
    "wof:placetype":"venue"
},
  "geometry": {"coordinates":[176.128723,-37.686409],"type":"Point"}
}