{
  "type": "Feature",
  "properties": {
    "iso:country":"NZ",
    "sg:address":"76 Clyde St ",
    "sg:city":"Balclutha",
    "sg:classifiers":[
        {
            "category":"Autos & Motor Vehicles",
            "subcategory":"Motorcycle Sales",
            "type":"Retail Goods"
        }
    ],
    "sg:phone":"+64 3-418 0626",
    "sg:tags":[
        "automotive",
        "scooter",
        "leasing"
    ],
    "wof:name":"Hasler Honda",
    "wof:placetype":"venue"
},
  "geometry": {"coordinates":[169.73457300000001,-46.239868],"type":"Point"}
}