{
  "type": "Feature",
  "properties": {
    "addr:full":"Brighton Plz New Brighton  Christchurch Canterbury",
    "addr:street":"Brighton Plz",
    "iso:country":"NZ",
    "sg:address":"Brighton Plz New Brighton ",
    "sg:city":"Christchurch",
    "sg:orig_category":"Industrial: Equipment And Machinery: Specialist Equipment: Machinery: Sewing Machines",
    "sg:phone":"+64 3-388 2200",
    "sg:province":"Canterbury",
    "wof:name":"Sewing World",
    "wof:placetype":"venue"
},
  "geometry": {"coordinates":[172.73010300000001,-43.507099],"type":"Point"}
}