{
  "type": "Feature",
  "properties": {
    "iso:country":"NZ",
    "sg:address":"136 Cuba St ",
    "sg:city":"Wellington",
    "sg:classifiers":[
        {
            "category":"Organizations",
            "subcategory":"Labor Organization",
            "type":"Services"
        }
    ],
    "sg:phone":"+64 4-385 7324",
    "sg:province":"Wellington",
    "sg:tags":[
        "cake",
        "arrangements",
        "wedding"
    ],
    "wof:name":"Dorothy Patisserie, Chocolaterie, Coffee House (Est 1930)",
    "wof:placetype":"venue"
},
  "geometry": {"coordinates":[-85.910454,33.827946],"type":"Point"}
}