{
  "type": "Feature",
  "properties": {
    "iso:country":"NZ",
    "sg:address":"State Highway 3 Kihikihi Te ",
    "sg:city":"Awamutu",
    "sg:orig_category":"Automotive: General Services: Service Stations",
    "sg:phone":"+64 7-871 1764",
    "sg:province":"Waikato",
    "wof:name":"Te Kawa Service Station",
    "wof:placetype":"venue"
},
  "geometry": {"coordinates":[175.345718,-38.045269],"type":"Point"}
}