{
  "type": "Feature",
  "properties": {
    "iso:country":"NZ",
    "sg:address":"PO Box 96075 Balmoral ",
    "sg:city":"Auckland",
    "sg:orig_category":"Health And Beauty: Beauty: Manicurists",
    "sg:phone":"+64 9-620 4536",
    "sg:province":"Auckland",
    "wof:name":"Focus On You",
    "wof:placetype":"venue"
},
  "geometry": {"coordinates":[174.748215,-36.884689],"type":"Point"}
}