{
  "type": "Feature",
  "properties": {
    "addr:full":"236 Houghton Bay Rd Houghton  Bay",
    "addr:housenumber":"236",
    "addr:street":"Houghton Bay Rd",
    "iso:country":"NZ",
    "sg:address":"236 Houghton Bay Rd Houghton ",
    "sg:city":"Bay",
    "sg:classifiers":[
        {
            "category":"Bars & Pubs",
            "type":"Food & Drink"
        }
    ],
    "sg:phone":"+64 4-387 9541",
    "wof:name":"Wind Gardens",
    "wof:placetype":"venue"
},
  "geometry": {"coordinates":[174.785416,-41.340321],"type":"Point"}
}