{
  "type": "Feature",
  "properties": {
    "addr:full":"18 Turner St Auckland Central  Auckland Auckland",
    "addr:housenumber":"18",
    "addr:street":"Turner St",
    "iso:country":"NZ",
    "sg:address":"18 Turner St Auckland Central ",
    "sg:city":"Auckland",
    "sg:classifiers":[
        {
            "category":"Home & Garden",
            "subcategory":"Garden Supply",
            "type":"Retail Goods"
        }
    ],
    "sg:phone":"+64 9-309 9300",
    "sg:province":"Auckland",
    "sg:tags":[
        "pet",
        "pets",
        "minding"
    ],
    "wof:name":"Homesit NZ Ltd",
    "wof:placetype":"venue"
},
  "geometry": {"coordinates":[174.76454200000001,-36.848358],"type":"Point"}
}