{
  "type": "Feature",
  "properties": {
    "addr:full":"746 Whangaparaoa Rd Whangaparaoa Hibiscus  Hibiscus Coast Auckland",
    "addr:housenumber":"746",
    "addr:street":"Whangaparaoa Rd",
    "iso:country":"NZ",
    "sg:address":"746 Whangaparaoa Rd Whangaparaoa Hibiscus ",
    "sg:city":"Hibiscus Coast",
    "sg:orig_category":"Health And Beauty: Specialists: Physiotherapists",
    "sg:phone":"+64 9-424 0503",
    "sg:province":"Auckland",
    "wof:name":"Burnett Helena NZPT",
    "wof:placetype":"venue"
},
  "geometry": {"coordinates":[174.751251,-36.637787],"type":"Point"}
}