{
  "type": "Feature",
  "properties": {
    "addr:full":"455 B Mt Eden Rd Mt Eden  Auckland Auckland",
    "addr:housenumber":"455",
    "addr:street":"B Mt Eden Rd",
    "iso:country":"NZ",
    "sg:address":"455 B Mt Eden Rd Mt Eden ",
    "sg:city":"Auckland",
    "sg:classifiers":[
        {
            "category":"Deli",
            "type":"Food & Drink"
        }
    ],
    "sg:phone":"+64 9-630 6793",
    "sg:province":"Auckland",
    "sg:tags":[
        "delicatessen",
        "-"
    ],
    "wof:name":"Essential Deli",
    "wof:placetype":"venue"
},
  "geometry": {"coordinates":[174.76156599999999,-36.883232],"type":"Point"}
}