{
  "type": "Feature",
  "properties": {
    "iso:country":"NZ",
    "sg:address":"79 Broadway Ave Palmerston ",
    "sg:city":"Palmerston North",
    "sg:classifiers":[
        {
            "category":"Recreation",
            "type":"Entertainment"
        }
    ],
    "sg:phone":"+64 6-357 8181",
    "sg:province":"Manawatu-Wanganui",
    "sg:tags":[
        "sport",
        "tramping",
        "leisure",
        "camping"
    ],
    "wof:name":"Doyles Outdoors",
    "wof:placetype":"venue"
},
  "geometry": {"coordinates":[175.613571,-40.353619],"type":"Point"}
}