{
  "type": "Feature",
  "properties": {
    "iso:country":"NZ",
    "sg:address":"18 Peach Rd R D 1 Taupiri ",
    "sg:city":"Hamilton",
    "sg:orig_category":"Transport: Transportation: Transport Operators",
    "sg:phone":"+64 7-824 3507",
    "sg:province":"Waikato",
    "wof:name":"Woodlands Transport Ltd",
    "wof:placetype":"venue"
},
  "geometry": {"coordinates":[175.276993,-37.783215],"type":"Point"}
}