{
  "type": "Feature",
  "properties": {
    "addr:full":"100 Highbury Ave Palmerston  Palmerston North Manawatu-Wanganui",
    "addr:housenumber":"100",
    "addr:street":"Highbury Ave",
    "iso:country":"NZ",
    "sg:address":"100 Highbury Ave Palmerston ",
    "sg:city":"Palmerston North",
    "sg:classifiers":[
        {
            "category":"Manufacturing",
            "subcategory":"Food",
            "type":"Manufacturing & Wholesale Goods"
        }
    ],
    "sg:phone":"+64 6-355 1155",
    "sg:province":"Manawatu-Wanganui",
    "sg:tags":[
        "drink",
        "-",
        "manufacturer"
    ],
    "wof:name":"National Foods International Fine Foods Limited",
    "wof:placetype":"venue"
},
  "geometry": {"coordinates":[175.58680699999999,-40.359554],"type":"Point"}
}