{
  "type": "Feature",
  "properties": {
    "iso:country":"NZ",
    "sg:address":"115 A Diana Dve ",
    "sg:city":"Glenfield",
    "sg:classifiers":[
        {
            "category":"Organizations",
            "subcategory":"Religious Organization",
            "type":"Services"
        }
    ],
    "sg:phone":"+64 9-444 1787",
    "sg:province":"Auckland",
    "sg:tags":[
        "arrangements",
        "tent",
        "marquee",
        "wedding"
    ],
    "wof:name":"Castles Marquee & Party Hire",
    "wof:placetype":"venue"
},
  "geometry": {"coordinates":[-75.404037,43.709122],"type":"Point"}
}