{
  "type": "Feature",
  "properties": {
    "addr:full":"Belinda Bunn  A.T.T.S.N.Z.",
    "iso:country":"NZ",
    "sg:address":"Belinda Bunn ",
    "sg:city":"A.T.T.S.N.Z.",
    "sg:classifiers":[
        {
            "category":"Health Services",
            "subcategory":"Medical Lab",
            "type":"Services"
        }
    ],
    "sg:phone":"+64 3-328 8968",
    "sg:tags":[
        "services",
        "technique",
        "beauty",
        "alexander"
    ],
    "wof:name":"Alexander Technique Works",
    "wof:placetype":"venue"
},
  "geometry": {"coordinates":[-96.107658,30.914276],"type":"Point"}
}