{
  "type": "Feature",
  "properties": {
    "addr:full":"Ground Floor 163 The Terrace  Wellington Waikato",
    "addr:housenumber":"163",
    "addr:street":"Ground Floor;The Terrace",
    "iso:country":"NZ",
    "sg:address":"Ground Floor 163 The Terrace ",
    "sg:city":"Wellington",
    "sg:classifiers":[
        {
            "category":"Travel",
            "subcategory":"Hotels & Motels",
            "type":"Entertainment"
        }
    ],
    "sg:phone":"+64 4-499 2938",
    "sg:province":"Waikato",
    "sg:tags":[
        "tavern",
        "tourism",
        "accommodation"
    ],
    "sg:website":"http://www.yellowpages.co.nz/for/primeproperty/dp30890.html",
    "wof:name":"Prime Property Executive Apartments",
    "wof:placetype":"venue"
},
  "geometry": {"coordinates":[174.76713599999999,-41.28054],"type":"Point"}
}