{
  "type": "Feature",
  "properties": {
    "addr:full":"10 Endeavour St  Gisborne Gisborne",
    "addr:housenumber":"10",
    "addr:street":"Endeavour St",
    "iso:country":"NZ",
    "sg:address":"10 Endeavour St ",
    "sg:city":"Gisborne",
    "sg:classifiers":[
        {
            "category":"Manufacturing",
            "subcategory":"Tools & Machinery",
            "type":"Manufacturing & Wholesale Goods"
        }
    ],
    "sg:phone":"+64 6-867 7117",
    "sg:province":"Gisborne",
    "sg:tags":[
        "specialist",
        "energy",
        "industrial",
        "solar",
        "equipment"
    ],
    "wof:name":"Allen T P & Co Ltd",
    "wof:placetype":"venue"
},
  "geometry": {"coordinates":[178.00166300000001,-38.661491],"type":"Point"}
}