{
  "type": "Feature",
  "properties": {
    "iso:country":"NZ",
    "sg:address":"Kohimarama Rd Kohimarama ",
    "sg:city":"Auckland",
    "sg:orig_category":"Education And Training: General: Schools",
    "sg:phone":"+64 9-521 9610",
    "sg:province":"Auckland",
    "wof:name":"Selwyn College",
    "wof:placetype":"venue"
},
  "geometry": {"coordinates":[174.843994,-36.865051],"type":"Point"}
}