{
  "type": "Feature",
  "properties": {
    "addr:full":"Commerce St  Kaitaia Northland",
    "addr:street":"Commerce St",
    "iso:country":"NZ",
    "sg:address":"Commerce St ",
    "sg:city":"Kaitaia",
    "sg:orig_category":"Shopping: Retail Stores: Supermarkets",
    "sg:phone":"+64 9-408 6222",
    "sg:province":"Northland",
    "wof:name":"Pak N Save Food Warehouses",
    "wof:placetype":"venue"
},
  "geometry": {"coordinates":[173.26226800000001,-35.112064],"type":"Point"}
}