{
  "type": "Feature",
  "properties": {
    "iso:country":"NZ",
    "sg:address":"60 Mana Esp Mana ",
    "sg:city":"Wellington",
    "sg:orig_category":"Health And Beauty: Specialists: Osteopaths",
    "sg:phone":"+64 4-233 9800",
    "sg:province":"Wellington",
    "wof:name":"Maurice Tuckwell",
    "wof:placetype":"venue"
},
  "geometry": {"coordinates":[174.86975100000001,-41.097809],"type":"Point"}
}