{
  "type": "Feature",
  "properties": {
    "iso:country":"NZ",
    "sg:address":"Moutere Rd ",
    "sg:city":"Levin",
    "sg:orig_category":"Sports And Leisure: Sports: Golf: Golf Courses",
    "sg:phone":"+64 6-368 6189",
    "sg:province":"Manawatu-Wanganui",
    "wof:name":"Levin Championship Links",
    "wof:placetype":"venue"
},
  "geometry": {"coordinates":[175.285324,-40.625278],"type":"Point"}
}