{
  "type": "Feature",
  "properties": {
    "iso:country":"NZ",
    "sg:address":"167-171 Parnell Rd Parnell ",
    "sg:city":"Auckland",
    "sg:classifiers":[
        {
            "category":"Restaurant",
            "type":"Food & Drink"
        }
    ],
    "sg:phone":"+64 9-309 0807",
    "sg:province":"Auckland",
    "sg:tags":[
        "wining",
        "dining",
        "pizza"
    ],
    "wof:name":"La Porchetta Pizza Restaurant",
    "wof:placetype":"venue"
},
  "geometry": {"coordinates":[174.77964782710001,-36.8542861938],"type":"Point"}
}