{
  "type": "Feature",
  "properties": {
    "addr:full":"1/166-170 Lansford Cre Avondale  Auckland Auckland",
    "addr:housenumber":"1 / 166-170;cre",
    "iso:country":"NZ",
    "sg:address":"1/166-170 Lansford Cre Avondale ",
    "sg:city":"Auckland",
    "sg:orig_category":"Industrial: Electrical/Electronic: Electronic Components",
    "sg:phone":"+64 9-828 5730",
    "sg:province":"Auckland",
    "wof:name":"Electronics Hobby Shop",
    "wof:placetype":"venue"
},
  "geometry": {"coordinates":[174.69963100000001,-36.906803],"type":"Point"}
}