{
  "type": "Feature",
  "properties": {
    "addr:full":"Capital On The Quay Complex Lambton Qy  Wellington Wellington",
    "iso:country":"NZ",
    "sg:address":"Capital On The Quay Complex Lambton Qy ",
    "sg:city":"Wellington",
    "sg:orig_category":"Clothing And Fabric: Clothing: Women'S Fashions",
    "sg:phone":"+64 4-499 4322",
    "sg:province":"Wellington",
    "wof:name":"Staxs",
    "wof:placetype":"venue"
},
  "geometry": {"coordinates":[174.82162500000001,-41.325909],"type":"Point"}
}