{
  "type": "Feature",
  "properties": {
    "iso:country":"NZ",
    "sg:address":"297 Blenheim Rd Middleton ",
    "sg:city":"Christchurch",
    "sg:orig_category":"Industrial: Manufacturing",
    "sg:phone":"+64 3-343 3799",
    "sg:province":"Canterbury",
    "wof:name":"Drinnan Tank Services",
    "wof:placetype":"venue"
},
  "geometry": {"coordinates":[172.580246,-43.542606],"type":"Point"}
}