{
  "type": "Feature",
  "properties": {
    "iso:country":"NZ",
    "sg:address":"29 Courtenay Pl ",
    "sg:city":"Wellington",
    "sg:classifiers":[
        {
            "category":"Retail",
            "subcategory":"Laundry & Dry Cleaning",
            "type":"Services"
        }
    ],
    "sg:phone":"+64 4-384 6668",
    "sg:province":"Wellington",
    "sg:tags":[
        "repair",
        "clothing",
        "fabric"
    ],
    "wof:name":"Mall Dry Cleaners Ltd",
    "wof:placetype":"venue"
},
  "geometry": {"coordinates":[-83.545181,37.882641],"type":"Point"}
}