{
  "type": "Feature",
  "properties": {
    "addr:full":"132 Regan St  Stratford",
    "addr:housenumber":"132",
    "addr:street":"Regan St",
    "iso:country":"NZ",
    "sg:address":"132 Regan St ",
    "sg:city":"Stratford",
    "sg:orig_category":"Home And Garden: Gardening: Products: Lawnmowers",
    "sg:phone":"+64 6-765 7807",
    "wof:name":"Standard Machinery & Hire",
    "wof:placetype":"venue"
},
  "geometry": {"coordinates":[-119.824966,36.189419],"type":"Point"}
}