{
  "type": "Feature",
  "properties": {
    "addr:full":"37 Te Ngae Rd  Rotorua Bay of Plenty",
    "addr:housenumber":"37",
    "addr:street":"Te Ngae Rd",
    "iso:country":"NZ",
    "sg:address":"37 Te Ngae Rd ",
    "sg:city":"Rotorua",
    "sg:orig_category":"Automotive: Parts And Supplies: Windscreens",
    "sg:phone":"+64 7-350 2131",
    "sg:province":"Bay of Plenty",
    "wof:name":"Impact Glass & Windscreens",
    "wof:placetype":"venue"
},
  "geometry": {"coordinates":[176.25727800000001,-38.144497],"type":"Point"}
}