{
  "type": "Feature",
  "properties": {
    "iso:country":"NZ",
    "sg:address":"Cnr Devon & Waitara Rd ",
    "sg:city":"Waitara",
    "sg:classifiers":[
        {
            "category":"Coffee & Tea",
            "type":"Food & Drink"
        }
    ],
    "sg:phone":"+64 6-754 6298",
    "sg:tags":[
        "vegetable",
        "fruit",
        "veges"
    ],
    "wof:name":"Rua Kiwi Gardens",
    "wof:placetype":"venue"
},
  "geometry": {"coordinates":[174.237305,-39.00127],"type":"Point"}
}