{
  "type": "Feature",
  "properties": {
    "iso:country":"NZ",
    "sg:address":"472 Cranford St Redwood ",
    "sg:city":"Christchurch",
    "sg:classifiers":[
        {
            "category":"Recreation",
            "type":"Entertainment"
        }
    ],
    "sg:phone":"+64 3-352 4476",
    "sg:province":"Canterbury",
    "sg:tags":[
        "sport",
        "leisure"
    ],
    "wof:name":"Chipmunks",
    "wof:placetype":"venue"
},
  "geometry": {"coordinates":[172.62553399999999,-43.467388],"type":"Point"}
}