{
  "type": "Feature",
  "properties": {
    "iso:country":"NZ",
    "sg:address":"21 Fitzherbert St Petone ",
    "sg:city":"Wellington",
    "sg:classifiers":[
        {
            "category":"Retail",
            "subcategory":"Auto Repair",
            "type":"Services"
        }
    ],
    "sg:phone":"+64 4-939 9896",
    "sg:province":"Wellington",
    "sg:tags":[
        "transmission",
        "automotive",
        "servicing"
    ],
    "wof:name":"Dynatrans Automatic Transmissions",
    "wof:placetype":"venue"
},
  "geometry": {"coordinates":[174.873749,-41.226021],"type":"Point"}
}