{
  "type": "Feature",
  "properties": {
    "addr:full":"59 Awapuni Rd  Gisborne Manawatu-Wanganui",
    "addr:housenumber":"59",
    "addr:street":"Awapuni Rd",
    "iso:country":"NZ",
    "sg:address":"59 Awapuni Rd ",
    "sg:city":"Gisborne",
    "sg:orig_category":"Transport: Boats And Marine: Services",
    "sg:phone":"+64 6-869 0170",
    "sg:province":"Manawatu-Wanganui",
    "wof:name":"McCannics",
    "wof:placetype":"venue"
},
  "geometry": {"coordinates":[177.998932,-38.669556],"type":"Point"}
}