{
  "type": "Feature",
  "properties": {
    "addr:full":"South Rd Omata New  Plymouth Taranaki",
    "addr:street":"South Rd",
    "iso:country":"NZ",
    "sg:address":"South Rd Omata New ",
    "sg:city":"Plymouth",
    "sg:classifiers":[
        {
            "category":"Manufacturing",
            "subcategory":"Food",
            "type":"Manufacturing & Wholesale Goods"
        }
    ],
    "sg:phone":"+64 6-751 2359",
    "sg:province":"Taranaki",
    "sg:tags":[
        "processing",
        "drink"
    ],
    "wof:name":"Omata Meat Processors",
    "wof:placetype":"venue"
},
  "geometry": {"coordinates":[174.011673,-39.10186],"type":"Point"}
}