{
  "type": "Feature",
  "properties": {
    "addr:full":"161 Rutene Rd  Gisborne Gisborne",
    "addr:housenumber":"161",
    "addr:street":"Rutene Rd",
    "iso:country":"NZ",
    "sg:address":"161 Rutene Rd ",
    "sg:city":"Gisborne",
    "sg:orig_category":"Shopping: Retail Stores: Florist Accessories",
    "sg:phone":"+64 6-867 8400",
    "sg:province":"Gisborne",
    "wof:name":"Passion Posies",
    "wof:placetype":"venue"
},
  "geometry": {"coordinates":[178.038971,-38.670242],"type":"Point"}
}