{
  "type": "Feature",
  "properties": {
    "addr:full":"3/142 Maces Rd Bromley  Christchurch Canterbury",
    "addr:housenumber":"3 / 142",
    "addr:street":"Maces Rd;Christchurch",
    "iso:country":"NZ",
    "sg:address":"3/142 Maces Rd Bromley ",
    "sg:city":"Christchurch",
    "sg:orig_category":"Industrial: Metal: Stainless Steel",
    "sg:phone":"+64 3-384 2234",
    "sg:province":"Canterbury",
    "wof:name":"Bob Moore Sheet Metal Ltd",
    "wof:placetype":"venue"
},
  "geometry": {"coordinates":[172.69349700000001,-43.537289],"type":"Point"}
}