{
  "type": "Feature",
  "properties": {
    "addr:full":"2/595 Glenfield Rd Glenfield  Auckland Auckland",
    "addr:housenumber":"2 / 595",
    "addr:street":"Glenfield Rd",
    "iso:country":"NZ",
    "sg:address":"2/595 Glenfield Rd Glenfield ",
    "sg:city":"Auckland",
    "sg:classifiers":[
        {
            "category":"Shopping",
            "subcategory":"Computers & Home Electronics",
            "type":"Retail Goods"
        }
    ],
    "sg:phone":"+64 9-441 4355",
    "sg:province":"Auckland",
    "sg:tags":[
        "recording",
        "equipment",
        "sport",
        "music",
        "leisure"
    ],
    "wof:name":"On Stage Productions",
    "wof:placetype":"venue"
},
  "geometry": {"coordinates":[174.721924,-36.76973],"type":"Point"}
}