{
  "type": "Feature",
  "properties": {
    "iso:country":"NZ",
    "sg:address":"47 a Waimumu Rd Massey ",
    "sg:city":"Auckland",
    "sg:classifiers":[
        {
            "category":"Organizations",
            "subcategory":"Labor Organization",
            "type":"Services"
        }
    ],
    "sg:phone":"+64 9-832 2225",
    "sg:province":"Auckland",
    "sg:tags":[
        "services",
        "charter",
        "tourism",
        "travel",
        "boat"
    ],
    "wof:name":"Awesome Boat Charters",
    "wof:placetype":"venue"
},
  "geometry": {"coordinates":[174.62274199999999,-36.846375],"type":"Point"}
}