{
  "type": "Feature",
  "properties": {
    "iso:country":"NZ",
    "sg:address":"83 Firth St ",
    "sg:city":"Matamata",
    "sg:classifiers":[
        {
            "category":"Health Services",
            "subcategory":"Health Practitioner",
            "type":"Services"
        }
    ],
    "sg:phone":"+64 7-888 8271",
    "sg:province":"Waikato",
    "sg:tags":[
        "consultant",
        "medical",
        "beauty"
    ],
    "wof:name":"Braeburn House",
    "wof:placetype":"venue"
},
  "geometry": {"coordinates":[175.769897,-37.825302],"type":"Point"}
}