{
  "type": "Feature",
  "properties": {
    "addr:full":"83 Firth St  Matamata Waikato",
    "addr:housenumber":"83",
    "addr:street":"Firth St",
    "iso:country":"NZ",
    "sg:address":"83 Firth St ",
    "sg:city":"Matamata",
    "sg:classifiers":[
        {
            "category":"Health Services",
            "subcategory":"Health Practitioner",
            "type":"Services"
        }
    ],
    "sg:phone":"+64 7-888 8271",
    "sg:province":"Waikato",
    "sg:tags":[
        "consultant",
        "medical",
        "beauty"
    ],
    "wof:name":"Braeburn House",
    "wof:placetype":"venue"
},
  "geometry": {"coordinates":[175.76989699999999,-37.825302],"type":"Point"}
}