{
  "type": "Feature",
  "properties": {
    "addr:full":"Norfolk Rd R D 8  Inglewood",
    "addr:housenumber":"8",
    "addr:street":"Norfolk Rd R D",
    "iso:country":"NZ",
    "sg:address":"Norfolk Rd R D 8 ",
    "sg:city":"Inglewood",
    "sg:orig_category":"Education And Training: General: Schools",
    "sg:phone":"+64 6-756 8306",
    "wof:name":"Norfolk School",
    "wof:placetype":"venue"
},
  "geometry": {"coordinates":[174.20588699999999,-39.156784],"type":"Point"}
}