{
  "type": "Feature",
  "properties": {
    "iso:country":"NZ",
    "sg:address":"7 Brigade Rd Auckland Airport ",
    "sg:city":"Auckland",
    "sg:classifiers":[
        {
            "category":"Social Services",
            "subcategory":"Retirement Home",
            "type":"Services"
        }
    ],
    "sg:phone":"+64 9-275 8229",
    "sg:province":"Auckland",
    "sg:tags":[
        "automotive"
    ],
    "sg:website":"http://www.rental-car.co.nz",
    "wof:name":"U-Save Rental Cars",
    "wof:placetype":"venue"
},
  "geometry": {"coordinates":[174.7845,-37.006058],"type":"Point"}
}