{
  "type": "Feature",
  "properties": {
    "addr:full":"67 High St  Hawera Taranaki",
    "addr:housenumber":"67",
    "addr:street":"High St",
    "iso:country":"NZ",
    "sg:address":"67 High St ",
    "sg:city":"Hawera",
    "sg:classifiers":[
        {
            "category":"Banks & Credit Unions",
            "subcategory":"Investment Brokerage",
            "type":"Services"
        }
    ],
    "sg:phone":"+64 6-278 5058",
    "sg:province":"Taranaki",
    "sg:tags":[
        "personal",
        "accountant",
        "chartered",
        "-",
        "finance"
    ],
    "wof:name":"Harris & Taylor Ltd",
    "wof:placetype":"venue"
},
  "geometry": {"coordinates":[174.28410299999999,-39.589558],"type":"Point"}
}