{
  "type": "Feature",
  "properties": {
    "addr:full":"Level 1 32 -34 Bay Rd Kilbirnie  Wellington Wellington",
    "addr:housenumber":"level;-34",
    "addr:street":"1 32;Bay Rd",
    "iso:country":"NZ",
    "sg:address":"Level 1 32 -34 Bay Rd Kilbirnie ",
    "sg:city":"Wellington",
    "sg:classifiers":[
        {
            "category":"Shopping",
            "subcategory":"Stationery & Office Supplies",
            "type":"Retail Goods"
        }
    ],
    "sg:phone":"+64 4-387 2220",
    "sg:province":"Wellington",
    "sg:tags":[
        "supplies",
        "educational",
        "material",
        "education",
        "training"
    ],
    "wof:name":"Modern Teaching Aids New Zealand Ltd",
    "wof:placetype":"venue"
},
  "geometry": {"coordinates":[174.79458600000001,-41.318638],"type":"Point"}
}