{
  "type": "Feature",
  "properties": {
    "iso:country":"NZ",
    "sg:address":"Main Road ",
    "sg:city":"Whataroa",
    "sg:classifiers":[
        {
            "category":"Home & Garden",
            "subcategory":"Building Materials",
            "type":"Retail Goods"
        }
    ],
    "sg:phone":"+64 3-753 4249",
    "sg:province":"Otago",
    "sg:tags":[
        "wooden",
        "product",
        "accessories"
    ],
    "wof:name":"Kotuku Gallery",
    "wof:placetype":"venue"
},
  "geometry": {"coordinates":[170.359085,-43.261608],"type":"Point"}
}