{
  "type": "Feature",
  "properties": {
    "addr:full":"68 A Morrin Rd Mt Wellington  Auckland Auckland",
    "addr:housenumber":"68",
    "addr:street":"A Morrin Rd",
    "iso:country":"NZ",
    "sg:address":"68 A Morrin Rd Mt Wellington ",
    "sg:city":"Auckland",
    "sg:classifiers":[
        {
            "category":"Wholesale",
            "subcategory":"Meat",
            "type":"Manufacturing & Wholesale Goods"
        }
    ],
    "sg:phone":"+64 9-570 1138",
    "sg:province":"Auckland",
    "sg:tags":[
        "food",
        "distributor",
        "drink",
        "meats"
    ],
    "wof:name":"McMasters Farms",
    "wof:placetype":"venue"
},
  "geometry": {"coordinates":[174.84965500000001,-36.888733],"type":"Point"}
}