{
  "type": "Feature",
  "properties": {
    "iso:country":"NZ",
    "sg:address":"37 Paice Ave Mt ",
    "sg:city":"Eden",
    "sg:classifiers":[
        {
            "category":"Retail",
            "subcategory":"Auto Repair",
            "type":"Services"
        }
    ],
    "sg:phone":"+64 25981658",
    "sg:tags":[
        "mobile",
        "automotive",
        "servicing",
        "mechanic"
    ],
    "wof:name":"Automotive Injection Services",
    "wof:placetype":"venue"
},
  "geometry": {"coordinates":[-109.894737,32.961712],"type":"Point"}
}