{
  "type": "Feature",
  "properties": {
    "addr:full":"Esplanade  Omokoroa Gisborne",
    "addr:street":"Esplanade Omokoroa",
    "iso:country":"NZ",
    "sg:address":"Esplanade ",
    "sg:city":"Omokoroa",
    "sg:orig_category":"Transport: Boats And Marine: Transport",
    "sg:phone":"+64 25927251",
    "sg:province":"Gisborne",
    "wof:name":"Matakana Ferry 2000 Ltd",
    "wof:placetype":"venue"
},
  "geometry": {"coordinates":[176.04667699999999,-37.632431],"type":"Point"}
}