{
  "type": "Feature",
  "properties": {
    "addr:full":"C/o The Warehouse 70-100 Levin St  Invercargill Southland",
    "addr:housenumber":"/ o",
    "addr:postcode":"70-100",
    "addr:street":"C;The;Levin St",
    "iso:country":"NZ",
    "sg:address":"C/o The Warehouse 70-100 Levin St ",
    "sg:city":"Invercargill",
    "sg:classifiers":[
        {
            "category":"Professional",
            "subcategory":"Art Services",
            "type":"Services"
        }
    ],
    "sg:phone":"+64 3-214 3099",
    "sg:province":"Southland",
    "sg:tags":[
        "personal",
        "photographer",
        "services",
        "garden",
        "home"
    ],
    "wof:name":"Pixi Foto",
    "wof:placetype":"venue"
},
  "geometry": {"coordinates":[168.35217299999999,-46.411854],"type":"Point"}
}