{
  "type": "Feature",
  "properties": {
    "iso:country":"NZ",
    "sg:address":"463 Brookby Rd Whitford ",
    "sg:city":"Auckland",
    "sg:orig_category":"Home And Garden: Furniture/Furnishings: Cabinetmakers",
    "sg:phone":"+64 9-530 8997",
    "sg:province":"Auckland",
    "wof:name":"Kitchen Creation Design & Manufacture",
    "wof:placetype":"venue"
},
  "geometry": {"coordinates":[174.97789,-36.997169],"type":"Point"}
}