{
  "type": "Feature",
  "properties": {
    "iso:country":"NZ",
    "sg:address":"7 Glenmore Dve ",
    "sg:city":"Warkworth",
    "sg:classifiers":[
        {
            "category":"Home & Garden",
            "subcategory":"Hardware",
            "type":"Retail Goods"
        }
    ],
    "sg:phone":"+64 800 274 100",
    "sg:province":"Auckland",
    "sg:tags":[
        "window",
        "fitting"
    ],
    "wof:name":"Satellite Blinds",
    "wof:placetype":"venue"
},
  "geometry": {"coordinates":[174.654404,-36.407612],"type":"Point"}
}