{
  "type": "Feature",
  "properties": {
    "addr:full":"33 Orchard Rd Christchurch Airport  Christchurch Canterbury",
    "addr:housenumber":"33",
    "addr:street":"Orchard Rd",
    "iso:country":"NZ",
    "sg:address":"33 Orchard Rd Christchurch Airport ",
    "sg:city":"Christchurch",
    "sg:classifiers":[
        {
            "category":"Autos & Motor Vehicles",
            "subcategory":"Automobile Sales",
            "type":"Retail Goods"
        }
    ],
    "sg:phone":"+64 3-358 6920",
    "sg:province":"Canterbury",
    "sg:tags":[
        "home",
        "caravan",
        "leasing",
        "automotive"
    ],
    "wof:name":"Hertz Campervans",
    "wof:placetype":"venue"
},
  "geometry": {"coordinates":[172.546616,-43.487843],"type":"Point"}
}