{
  "type": "Feature",
  "properties": {
    "addr:full":"6/30 Upper Queen St Auckland Central  Auckland Auckland",
    "addr:housenumber":"6 / 30",
    "addr:street":"Upper Queen St",
    "iso:country":"NZ",
    "sg:address":"6/30 Upper Queen St Auckland Central ",
    "sg:city":"Auckland",
    "sg:classifiers":[
        {
            "category":"Shopping",
            "subcategory":"Crafts & Fabrics",
            "type":"Retail Goods"
        }
    ],
    "sg:phone":"+64 9-309 2909",
    "sg:province":"Auckland",
    "sg:tags":[
        "leather",
        "clothing",
        "suede"
    ],
    "wof:name":"AK Leather Fashions (Victoria Leather)",
    "wof:placetype":"venue"
},
  "geometry": {"coordinates":[174.89967300000001,-37.217171],"type":"Point"}
}