{
  "type": "Feature",
  "properties": {
    "addr:full":"442 Suffolk Rd Stoke  Nelson Nelson",
    "addr:housenumber":"442",
    "addr:street":"Suffolk Rd",
    "iso:country":"NZ",
    "sg:address":"442 Suffolk Rd Stoke ",
    "sg:city":"Nelson",
    "sg:classifiers":[
        {
            "category":"Building & Trades",
            "subcategory":"Pest Control",
            "type":"Services"
        }
    ],
    "sg:phone":"+64 3-547 4764",
    "sg:province":"Nelson",
    "sg:tags":[
        "home",
        "garden"
    ],
    "wof:name":"Bugz-Out",
    "wof:placetype":"venue"
},
  "geometry": {"coordinates":[173.22233600000001,-41.327644],"type":"Point"}
}