{
  "type": "Feature",
  "properties": {
    "addr:full":"45 a Treffers Rd Sockburn  Christchurch Canterbury",
    "addr:housenumber":"45",
    "addr:street":"A Treffers Rd",
    "iso:country":"NZ",
    "sg:address":"45 a Treffers Rd Sockburn ",
    "sg:city":"Christchurch",
    "sg:classifiers":[
        {
            "category":"Home & Garden",
            "subcategory":"Kitchen Supply",
            "type":"Retail Goods"
        }
    ],
    "sg:phone":"+64 800 464 932",
    "sg:province":"Canterbury",
    "sg:tags":[
        "motel",
        "industrial",
        "products",
        "hotel"
    ],
    "sg:website":"http://www.miweb.co.nz",
    "wof:name":"Miweb",
    "wof:placetype":"venue"
},
  "geometry": {"coordinates":[172.55043000000001,-43.534966],"type":"Point"}
}