{
  "type": "Feature",
  "properties": {
    "addr:full":"3 Church St  Mosgiel",
    "addr:housenumber":"3",
    "addr:street":"Church St",
    "iso:country":"NZ",
    "sg:address":"3 Church St ",
    "sg:city":"Mosgiel",
    "sg:classifiers":[
        {
            "category":"Arena",
            "subcategory":"Sports Club",
            "type":"Entertainment"
        }
    ],
    "sg:phone":"+64 3-476 4951",
    "sg:tags":[
        "martial art",
        "-",
        "leisure",
        "sports"
    ],
    "wof:name":"Mosgiel Okinawa Goju Ryu Karate Do- Jundokan New Zealand",
    "wof:placetype":"venue"
},
  "geometry": {"coordinates":[170.349411,-45.873924],"type":"Point"}
}