{
  "type": "Feature",
  "properties": {
    "addr:full":"Whitford Roundabout 1 Whitford Wharf Rd Whitford  Auckland Auckland",
    "addr:housenumber":"1",
    "addr:street":"Whitford Roundabout;Wharf Rd",
    "iso:country":"NZ",
    "sg:address":"Whitford Roundabout 1 Whitford Wharf Rd Whitford ",
    "sg:city":"Auckland",
    "sg:classifiers":[
        {
            "category":"Recreation",
            "type":"Entertainment"
        }
    ],
    "sg:phone":"+64 9-530 8437",
    "sg:province":"Auckland",
    "sg:tags":[
        "sport",
        "leisure"
    ],
    "sg:website":"http://www.generalstorerestaurant.co.nz",
    "wof:name":"General Store Restaurant",
    "wof:placetype":"venue"
},
  "geometry": {"coordinates":[174.96301299999999,-36.944344],"type":"Point"}
}