{
  "type": "Feature",
  "properties": {
    "addr:full":"24 Ryan Pl Manukau City  Auckland Auckland",
    "addr:housenumber":"24",
    "addr:street":"Ryan Pl",
    "iso:country":"NZ",
    "sg:address":"24 Ryan Pl Manukau City ",
    "sg:city":"Auckland",
    "sg:classifiers":[
        {
            "category":"Manufacturing",
            "subcategory":"Tools & Machinery",
            "type":"Manufacturing & Wholesale Goods"
        }
    ],
    "sg:phone":"+64 9-262 3643",
    "sg:province":"Auckland",
    "sg:tags":[
        "equipment",
        "industrial",
        "label"
    ],
    "wof:name":"Dy-Mark NZ Ltd",
    "wof:placetype":"venue"
},
  "geometry": {"coordinates":[174.875732,-36.986599],"type":"Point"}
}