{
  "type": "Feature",
  "properties": {
    "iso:country":"NZ",
    "sg:address":"Bell St ",
    "sg:city":"Wanganui",
    "sg:classifiers":[
        {
            "category":"Home & Garden",
            "subcategory":"Carpets & Floor Coverings",
            "type":"Retail Goods"
        }
    ],
    "sg:phone":"+64 6-345 3805",
    "sg:province":"Manawatu-Wanganui",
    "sg:tags":[
        "cleaning",
        "furniture"
    ],
    "wof:name":"Fabricare/Floorcare",
    "wof:placetype":"venue"
},
  "geometry": {"coordinates":[175.06944300000001,-39.930176],"type":"Point"}
}