{
  "type": "Feature",
  "properties": {
    "iso:country":"NZ",
    "sg:address":"Cape Barrier Rd Tryphena R D 1 Great Barrier ",
    "sg:city":"Island",
    "sg:orig_category":"Travel And Tourism: Accommodation: Hostels",
    "sg:phone":"+64 9-429 0109",
    "sg:province":"Auckland",
    "wof:name":"Stray Possum Lodge",
    "wof:placetype":"venue"
},
  "geometry": {"coordinates":[175.428665,-36.199791],"type":"Point"}
}