{
  "type": "Feature",
  "properties": {
    "iso:country":"NZ",
    "sg:address":"137 Frederick St ",
    "sg:city":"Hastings",
    "sg:classifiers":[
        {
            "category":"Manufacturing",
            "subcategory":"Metals",
            "type":"Manufacturing & Wholesale Goods"
        }
    ],
    "sg:phone":"+64 6-876 7748",
    "sg:province":"Hawke's Bay",
    "sg:tags":[
        "-",
        "engineering",
        "industrial",
        "sheet",
        "engineer"
    ],
    "wof:name":"Garry Kirk Ltd",
    "wof:placetype":"venue"
},
  "geometry": {"coordinates":[-81.44255800000001,29.6283],"type":"Point"}
}