{
  "type": "Feature",
  "properties": {
    "addr:full":"36 A James Laurie St Henderson  Auckland Auckland",
    "addr:housenumber":"36",
    "addr:street":"A James Laurie St",
    "iso:country":"NZ",
    "sg:address":"36 A James Laurie St Henderson ",
    "sg:city":"Auckland",
    "sg:classifiers":[
        {
            "category":"Shopping",
            "subcategory":"Pharmacy",
            "type":"Retail Goods"
        }
    ],
    "sg:phone":"+64 9-837 0112",
    "sg:province":"Auckland",
    "sg:tags":[
        "products",
        "medical",
        "health",
        "beauty",
        "supply"
    ],
    "wof:name":"Complete First Aid Supplies Ltd",
    "wof:placetype":"venue"
},
  "geometry": {"coordinates":[174.64120500000001,-36.887577],"type":"Point"}
}