{
  "type": "Feature",
  "properties": {
    "iso:country":"NZ",
    "sg:address":"Gd SH28 Coastlands Pde ",
    "sg:city":"Paraparaumu",
    "sg:classifiers":[
        {
            "category":"Personal",
            "subcategory":"Shoe Repair & Shine",
            "type":"Services"
        }
    ],
    "sg:phone":"+64 4-298 8008",
    "sg:province":"Wellington",
    "sg:tags":[
        "foot",
        "clothing",
        "fabric",
        "wear"
    ],
    "wof:name":"Minit Solutions",
    "wof:placetype":"venue"
},
  "geometry": {"coordinates":[175.007996,-40.910465],"type":"Point"}
}