{
  "type": "Feature",
  "properties": {
    "iso:country":"NZ",
    "sg:address":"49 George St Newmarket ",
    "sg:city":"Auckland",
    "sg:orig_category":"Farming: Supplies: Veterinary Supplies",
    "sg:phone":"+64 9-309 0600",
    "sg:province":"Auckland",
    "wof:name":"Intervet Ltd",
    "wof:placetype":"venue"
},
  "geometry": {"coordinates":[174.779144,-36.863861],"type":"Point"}
}