{
  "type": "Feature",
  "properties": {
    "iso:country":"NZ",
    "sg:address":"Pukeware Depot Pukeoware Rd Waiuku ",
    "sg:city":"Pukekohe",
    "sg:classifiers":[
        {
            "category":"Recreation",
            "type":"Entertainment"
        }
    ],
    "sg:phone":"+64 9-235 8595",
    "sg:province":"Auckland",
    "sg:tags":[
        "sport",
        "leisure"
    ],
    "sg:website":"http://www.railfan.org.nz/",
    "wof:name":"Glenbrook Vintage Railway",
    "wof:placetype":"venue"
},
  "geometry": {"coordinates":[174.76724200000001,-37.248112],"type":"Point"}
}