{
  "type": "Feature",
  "properties": {
    "addr:full":"366 Church St Palmerston  Palmerston North Manawatu-Wanganui",
    "addr:housenumber":"366",
    "addr:street":"Church St",
    "iso:country":"NZ",
    "sg:address":"366 Church St Palmerston ",
    "sg:city":"Palmerston North",
    "sg:classifiers":[
        {
            "category":"Deli",
            "type":"Food & Drink"
        }
    ],
    "sg:phone":"+64 6-355 1199",
    "sg:province":"Manawatu-Wanganui",
    "sg:tags":[
        "delicatessen",
        "-"
    ],
    "wof:name":"The Gourmet's Pantry",
    "wof:placetype":"venue"
},
  "geometry": {"coordinates":[175.614182,-40.356441],"type":"Point"}
}