{
  "type": "Feature",
  "properties": {
    "iso:country":"NZ",
    "sg:address":"197 Great North Rd Grey Lynn ",
    "sg:city":"Auckland",
    "sg:classifiers":[
        {
            "category":"Personal",
            "subcategory":"Adult",
            "type":"Services"
        }
    ],
    "sg:phone":"+64 9-360 6986",
    "sg:province":"Auckland",
    "sg:tags":[
        "sport",
        "parlour",
        "massage",
        "leisure"
    ],
    "wof:name":"Essential Club For Men",
    "wof:placetype":"venue"
},
  "geometry": {"coordinates":[174.74771100000001,-36.863686],"type":"Point"}
}