{
  "type": "Feature",
  "properties": {
    "iso:country":"NZ",
    "sg:address":"Scotland St Roxburgh ",
    "sg:city":"Alexandra",
    "sg:classifiers":[
        {
            "category":"Landmark",
            "subcategory":"Tourist Information",
            "type":"Public Place"
        }
    ],
    "sg:phone":"+64 3-446 8920",
    "sg:province":"Otago",
    "sg:tags":[
        "services",
        "travel",
        "tourism"
    ],
    "wof:name":"Roxburgh Visitor Information Centre",
    "wof:placetype":"venue"
},
  "geometry": {"coordinates":[169.314621,-45.557201],"type":"Point"}
}