{
  "type": "Feature",
  "properties": {
    "iso:country":"NZ",
    "sg:address":"73 Airport Ave ",
    "sg:city":"Invercargill",
    "sg:orig_category":"Automotive: General Services: Rental Vehicles",
    "sg:phone":"+64 3-218 7019",
    "sg:province":"Southland",
    "wof:name":"Avis Rent-A-Car Ltd",
    "wof:placetype":"venue"
},
  "geometry": {"coordinates":[168.325958,-46.415474],"type":"Point"}
}