{
  "type": "Feature",
  "properties": {
    "addr:full":"95 a Collingwood St  Hamilton Waikato",
    "addr:housenumber":"95",
    "addr:street":"A Collingwood St",
    "iso:country":"NZ",
    "sg:address":"95 a Collingwood St ",
    "sg:city":"Hamilton",
    "sg:classifiers":[
        {
            "category":"Shopping",
            "subcategory":"Gifts & Souvenirs",
            "type":"Retail Goods"
        }
    ],
    "sg:phone":"+64 7-838 3404",
    "sg:province":"Waikato",
    "sg:tags":[
        "trophy",
        "award"
    ],
    "wof:name":"Trophyworld New Zealand LTD",
    "wof:placetype":"venue"
},
  "geometry": {"coordinates":[-87.988968,34.142426],"type":"Point"}
}