{
  "type": "Feature",
  "properties": {
    "iso:country":"NZ",
    "sg:address":"7 Heatherlea St ",
    "sg:city":"Gisborne",
    "sg:orig_category":"Shopping: Retail Stores: Stationery",
    "sg:phone":"+64 6-867 5370",
    "sg:province":"Gisborne",
    "wof:name":"SmartArt Designers",
    "wof:placetype":"venue"
},
  "geometry": {"coordinates":[178.05275,-38.663971],"type":"Point"}
}