{
  "type": "Feature",
  "properties": {
    "addr:full":"16 Lyndhurst Rd Te Atatu South  Auckland Auckland",
    "addr:housenumber":"16",
    "addr:street":"Lyndhurst Rd",
    "iso:country":"NZ",
    "sg:address":"16 Lyndhurst Rd Te Atatu South ",
    "sg:city":"Auckland",
    "sg:orig_category":"Home And Garden: Accessories: Silverplaters",
    "sg:phone":"+64 9-834 5337",
    "sg:province":"Auckland",
    "wof:name":"Precious Metal Services 1990 Ltd",
    "wof:placetype":"venue"
},
  "geometry": {"coordinates":[174.64977999999999,-36.865822],"type":"Point"}
}