{
  "type": "Feature",
  "properties": {
    "iso:country":"NZ",
    "sg:address":"297 Blenheim Rd Upper Riccarton ",
    "sg:city":"Christchurch",
    "sg:orig_category":"Industrial: Metal: Stainless Steel",
    "sg:phone":"+64 3-348 5322",
    "sg:province":"Canterbury",
    "wof:name":"Drinnan Engineering",
    "wof:placetype":"venue"
},
  "geometry": {"coordinates":[172.582535,-43.538776],"type":"Point"}
}