{
  "type": "Feature",
  "properties": {
    "addr:full":"PO Box 15-243 New Lynn  Auckland Auckland",
    "addr:housenumber":"po box",
    "addr:street":"15-243",
    "iso:country":"NZ",
    "sg:address":"PO Box 15-243 New Lynn ",
    "sg:city":"Auckland",
    "sg:classifiers":[
        {
            "category":"Banks & Credit Unions",
            "subcategory":"Investment Brokerage",
            "type":"Services"
        }
    ],
    "sg:phone":"+64 9-827 3017",
    "sg:province":"Auckland",
    "sg:tags":[
        "funeral",
        "arrangements",
        "headstone"
    ],
    "wof:name":"Trethewey Stone Industries Ltd",
    "wof:placetype":"venue"
},
  "geometry": {"coordinates":[174.68308999999999,-36.920143],"type":"Point"}
}