{
  "type": "Feature",
  "properties": {
    "addr:full":"Pukete Industrial Estate Maui St  Hamilton Waikato",
    "addr:street":"Maui St",
    "iso:country":"NZ",
    "sg:address":"Pukete Industrial Estate Maui St ",
    "sg:city":"Hamilton",
    "sg:orig_category":"Transport: Consultancy: Transport - Engineering",
    "sg:phone":"+64 7-849 4839",
    "sg:province":"Waikato",
    "sg:website":"http://www.yellowpages.co.nz/pages/102745788/dp39503.html",
    "wof:name":"TRT-Tidd Ross Todd Ltd",
    "wof:placetype":"venue"
},
  "geometry": {"coordinates":[175.276993,-37.783215],"type":"Point"}
}