{
  "type": "Feature",
  "properties": {
    "addr:full":"40 Niven St Onekawa  Napier Hawke's Bay",
    "addr:housenumber":"40",
    "addr:street":"Niven St",
    "iso:country":"NZ",
    "sg:address":"40 Niven St Onekawa ",
    "sg:city":"Napier",
    "sg:orig_category":"Industrial: Engineering: Engineers: Engineers - General",
    "sg:phone":"+64 6-843 3860",
    "sg:province":"Hawke's Bay",
    "wof:name":"Derrys Engineering",
    "wof:placetype":"venue"
},
  "geometry": {"coordinates":[176.87886,-39.506382],"type":"Point"}
}