{
  "type": "Feature",
  "properties": {
    "iso:country":"NZ",
    "sg:address":"23-25 Fremlin Pl ",
    "sg:city":"Avondale",
    "sg:orig_category":"Industrial: Manufacturing: Tank Manufacturers",
    "sg:phone":"+64 800 861 333",
    "sg:province":"Auckland",
    "wof:name":"Bailey Tanks Ltd",
    "wof:placetype":"venue"
},
  "geometry": {"coordinates":[-112.349663,33.440498],"type":"Point"}
}