{
  "type": "Feature",
  "properties": {
    "addr:full":"632 Port Rd  Whangamata",
    "addr:housenumber":"632",
    "addr:street":"Port Rd",
    "iso:country":"NZ",
    "sg:address":"632 Port Rd ",
    "sg:city":"Whangamata",
    "sg:orig_category":"Shopping: Retail Stores: Department Stores",
    "sg:phone":"+64 7-865 9666",
    "wof:name":"Sunny's Of Whangamata",
    "wof:placetype":"venue"
},
  "geometry": {"coordinates":[175.87780799999999,-37.200172],"type":"Point"}
}