{
  "type": "Feature",
  "properties": {
    "addr:full":"B1/50 Keeling Rd Henderson  Auckland Auckland",
    "addr:housenumber":"50",
    "addr:street":"Keeling Rd",
    "iso:country":"NZ",
    "sg:address":"B1/50 Keeling Rd Henderson ",
    "sg:city":"Auckland",
    "sg:orig_category":"Industrial: Equipment And Machinery: Boilers",
    "sg:phone":"+64 9-835 2100",
    "sg:province":"Auckland",
    "wof:name":"Alaskon Aira Limited",
    "wof:placetype":"venue"
},
  "geometry": {"coordinates":[174.63294999999999,-36.877289],"type":"Point"}
}