{
  "type": "Feature",
  "properties": {
    "addr:full":"Central Pde Mt  Maunganui Bay of Plenty",
    "addr:street":"Mt Maunganui",
    "iso:country":"NZ",
    "sg:address":"Central Pde Mt ",
    "sg:city":"Maunganui",
    "sg:classifiers":[
        {
            "category":"Retail",
            "subcategory":"Laundry & Dry Cleaning",
            "type":"Services"
        }
    ],
    "sg:phone":"+64 7-575 4567",
    "sg:province":"Bay of Plenty",
    "sg:tags":[
        "repair",
        "clothing",
        "fabric"
    ],
    "wof:name":"Mt Maunganui Dry Cleaners & Laundry",
    "wof:placetype":"venue"
},
  "geometry": {"coordinates":[176.18627900000001,-37.641048],"type":"Point"}
}