{
  "type": "Feature",
  "properties": {
    "iso:country":"NZ",
    "sg:address":"11 Tralee Pl ",
    "sg:city":"Hamilton",
    "sg:classifiers":[
        {
            "category":"Professional",
            "subcategory":"Art Services",
            "type":"Services"
        }
    ],
    "sg:phone":"+64 274 849 852",
    "sg:province":"Waikato",
    "sg:tags":[
        "personal",
        "photographer",
        "services",
        "garden",
        "home"
    ],
    "sg:website":"http://www.mainlyweddingsphotography.co.nz/",
    "wof:name":"Mainly Weddings & Portraits Photography",
    "wof:placetype":"venue"
},
  "geometry": {"coordinates":[-87.988968,34.142426],"type":"Point"}
}