{
  "type": "Feature",
  "properties": {
    "addr:full":"30 Glover Rd  Ngauranga",
    "addr:housenumber":"30",
    "addr:street":"Glover Rd",
    "iso:country":"NZ",
    "sg:address":"30 Glover Rd ",
    "sg:city":"Ngauranga",
    "sg:classifiers":[
        {
            "category":"Banks & Credit Unions",
            "subcategory":"Investment Brokerage",
            "type":"Services"
        }
    ],
    "sg:phone":"+64 800 223 826",
    "sg:tags":[
        "industrial",
        "cleaning",
        "maintenance"
    ],
    "wof:name":"Advance International Cleaning Systems (NZ) Ltd",
    "wof:placetype":"venue"
},
  "geometry": {"coordinates":[174.81420900000001,-41.238293],"type":"Point"}
}