{
  "type": "Feature",
  "properties": {
    "addr:full":"24 Queen St Upper  Hutt Wellington",
    "addr:housenumber":"24",
    "addr:street":"Queen St",
    "iso:country":"NZ",
    "sg:address":"24 Queen St Upper ",
    "sg:city":"Hutt",
    "sg:classifiers":[
        {
            "category":"Shopping",
            "subcategory":"Clothing, Apparel, & Fashions",
            "type":"Retail Goods"
        }
    ],
    "sg:phone":"+64 4-528 4653",
    "sg:province":"Wellington",
    "sg:tags":[
        "-",
        "hire",
        "clothing",
        "fabric"
    ],
    "wof:name":"Anything Goes Costume Hire",
    "wof:placetype":"venue"
},
  "geometry": {"coordinates":[175.07002299999999,-41.123444],"type":"Point"}
}