{
  "type": "Feature",
  "properties": {
    "addr:full":"Crane Rd RD1 Kamo  Whangarei Northland",
    "addr:housenumber":"kamo",
    "addr:postcode":"rd1",
    "addr:street":"Crane Rd",
    "iso:country":"NZ",
    "sg:address":"Crane Rd RD1 Kamo ",
    "sg:city":"Whangarei",
    "sg:orig_category":"Home And Garden: Furniture/Furnishings: Curtains",
    "sg:phone":"+64 9-430 0293",
    "sg:province":"Northland",
    "wof:name":"Quality Curtains",
    "wof:placetype":"venue"
},
  "geometry": {"coordinates":[174.30708300000001,-35.683804],"type":"Point"}
}