{
  "type": "Feature",
  "properties": {
    "addr:full":"Cnr Manukau & Ranfurly Rd Epsom  Auckland Auckland",
    "addr:street":"Cnr;Rd",
    "iso:country":"NZ",
    "sg:address":"Cnr Manukau & Ranfurly Rd Epsom ",
    "sg:city":"Auckland",
    "sg:orig_category":"Clothing And Fabric: Clothing: Tailors",
    "sg:phone":"+64 9-630 0951",
    "sg:province":"Auckland",
    "wof:name":"Sabe-Vinny The Tailor",
    "wof:placetype":"venue"
},
  "geometry": {"coordinates":[174.77018699999999,-36.888802],"type":"Point"}
}