{
  "type": "Feature",
  "properties": {
    "addr:full":"39 Church St  Masterton Wellington",
    "addr:housenumber":"39",
    "addr:street":"Church St",
    "iso:country":"NZ",
    "sg:address":"39 Church St ",
    "sg:city":"Masterton",
    "sg:classifiers":[
        {
            "category":"Social Services",
            "subcategory":"Retirement Home",
            "type":"Services"
        }
    ],
    "sg:phone":"+64 6-377 3362",
    "sg:province":"Wellington",
    "sg:tags":[
        "personal",
        "services",
        "garden",
        "elderly",
        "care"
    ],
    "wof:name":"Abbeyfield House For Elderly People",
    "wof:placetype":"venue"
},
  "geometry": {"coordinates":[175.664322,-40.95192],"type":"Point"}
}