{
  "type": "Feature",
  "properties": {
    "addr:full":"260 Papakura-Clevedon Rd Clevedon R D 2 Papakura  Auckland Auckland",
    "addr:housenumber":"260;2",
    "addr:street":"Papakura-Clevedon Rd;R D",
    "iso:country":"NZ",
    "sg:address":"260 Papakura-Clevedon Rd Clevedon R D 2 Papakura ",
    "sg:city":"Auckland",
    "sg:orig_category":"Industrial: Packaging: Paper Products",
    "sg:phone":"+64 9-292 9163",
    "sg:province":"Auckland",
    "wof:name":"Pack 'N' Wrap",
    "wof:placetype":"venue"
},
  "geometry": {"coordinates":[174.95945699999999,-37.059521],"type":"Point"}
}