{
  "type": "Feature",
  "properties": {
    "addr:full":"28 C Parkway Dve Mairangi Bay  Auckland Wellington",
    "addr:housenumber":"28",
    "addr:street":"C Parkway Dve",
    "iso:country":"NZ",
    "sg:address":"28 C Parkway Dve Mairangi Bay ",
    "sg:city":"Auckland",
    "sg:orig_category":"Farming: Farms - General: Poultry",
    "sg:phone":"+64 9-478 8614",
    "sg:province":"Wellington",
    "wof:name":"Cuisine Supreme Limited",
    "wof:placetype":"venue"
},
  "geometry": {"coordinates":[174.77041600000001,-36.884109],"type":"Point"}
}