{
  "type": "Feature",
  "properties": {
    "addr:full":"1304 Tutanekai St  Rotorua Bay of Plenty",
    "addr:housenumber":"1304",
    "addr:street":"Tutanekai St",
    "iso:country":"NZ",
    "sg:address":"1304 Tutanekai St ",
    "sg:city":"Rotorua",
    "sg:orig_category":"Shopping: Retail Stores: Stationery",
    "sg:phone":"+64 7-346 2674",
    "sg:province":"Bay of Plenty",
    "wof:name":"Tutanekai Paper Plus",
    "wof:placetype":"venue"
},
  "geometry": {"coordinates":[176.25174000000001,-38.139469],"type":"Point"}
}