{
  "type": "Feature",
  "properties": {
    "iso:country":"NZ",
    "sg:address":"PO Box 240 ",
    "sg:city":"Invercargill",
    "sg:classifiers":[
        {
            "category":"Social Services",
            "subcategory":"Job Training",
            "type":"Services"
        }
    ],
    "sg:phone":"+64 3-218 8532",
    "sg:province":"Southland",
    "sg:tags":[
        "education"
    ],
    "wof:name":"Southern Group Training Trust",
    "wof:placetype":"venue"
},
  "geometry": {"coordinates":[168.35217299999999,-46.411854],"type":"Point"}
}