{
  "type": "Feature",
  "properties": {
    "addr:full":"43 King St Palmerston  Palmerston North Manawatu-Wanganui",
    "addr:housenumber":"43",
    "addr:street":"King St Palmerston",
    "iso:country":"NZ",
    "sg:address":"43 King St Palmerston ",
    "sg:city":"Palmerston North",
    "sg:classifiers":[
        {
            "category":"Shopping",
            "subcategory":"Bridal",
            "type":"Retail Goods"
        }
    ],
    "sg:phone":"+64 6-357 7090",
    "sg:province":"Manawatu-Wanganui",
    "sg:tags":[
        "arrangements",
        "wear",
        "wedding"
    ],
    "wof:name":"Simpson Suit & Bridal Formal Wear",
    "wof:placetype":"venue"
},
  "geometry": {"coordinates":[175.61093099999999,-40.353752],"type":"Point"}
}