{
  "type": "Feature",
  "properties": {
    "addr:full":"850 Wairakei Rd Harewood  Christchurch Canterbury",
    "addr:housenumber":"850",
    "addr:street":"Wairakei Rd",
    "iso:country":"NZ",
    "sg:address":"850 Wairakei Rd Harewood ",
    "sg:city":"Christchurch",
    "sg:orig_category":"Transport: Air",
    "sg:phone":"+64 3-357 0084",
    "sg:province":"Canterbury",
    "wof:name":"JMI Aerospace Ltd",
    "wof:placetype":"venue"
},
  "geometry": {"coordinates":[172.553955,-43.48634],"type":"Point"}
}