{
  "type": "Feature",
  "properties": {
    "iso:country":"NZ",
    "sg:address":"Henderson Howick Glenfield Manukau Newmarket Pakuranga, Royal Oak St Lukes Takapuna Whangaparaoa New",
    "sg:city":"Auckland",
    "sg:classifiers":[
        {
            "category":"Health Services",
            "subcategory":"Optometrist",
            "type":"Services"
        }
    ],
    "sg:phone":"+64 9-358 5595",
    "sg:province":"Auckland",
    "sg:tags":[
        "optical",
        "optician",
        "beauty"
    ],
    "sg:website":"http://www.opsm.com",
    "wof:name":"OPSM Limited",
    "wof:placetype":"venue"
},
  "geometry": {"coordinates":[174.767883,-36.787842],"type":"Point"}
}