{
  "type": "Feature",
  "properties": {
    "iso:country":"NZ",
    "sg:address":"Arcadia Building Worley Pl ",
    "sg:city":"Hamilton",
    "sg:classifiers":[
        {
            "category":"Social Services",
            "subcategory":"Job Training",
            "type":"Services"
        }
    ],
    "sg:phone":"+64 7-839 0806",
    "sg:province":"Waikato",
    "sg:tags":[
        "education"
    ],
    "sg:website":"http://www.ema.co.nz",
    "wof:name":"Employers & Manufacturers Association (Northern) Inc",
    "wof:placetype":"venue"
},
  "geometry": {"coordinates":[-87.988968,34.142426],"type":"Point"}
}