{
  "type": "Feature",
  "properties": {
    "addr:full":"8 Riddiford St Newtown  Wellington Wellington",
    "addr:housenumber":"8",
    "addr:street":"Riddiford St",
    "iso:country":"NZ",
    "sg:address":"8 Riddiford St Newtown ",
    "sg:city":"Wellington",
    "sg:orig_category":"Shopping: Retail Stores: Antiques",
    "sg:phone":"+64 4-389 6689",
    "sg:province":"Wellington",
    "wof:name":"Hobsons",
    "wof:placetype":"venue"
},
  "geometry": {"coordinates":[174.77795399999999,-41.308018],"type":"Point"}
}