{
  "type": "Feature",
  "properties": {
    "iso:country":"NZ",
    "sg:address":"24 Waterview Rd Devonport ",
    "sg:city":"Auckland",
    "sg:classifiers":[
        {
            "category":"Shopping",
            "subcategory":"Stationery & Office Supplies",
            "type":"Retail Goods"
        }
    ],
    "sg:phone":"+64 9-445 3094",
    "sg:province":"Auckland",
    "sg:tags":[
        "supplies",
        "educational",
        "material",
        "education",
        "training"
    ],
    "wof:name":"Leyden Publications",
    "wof:placetype":"venue"
},
  "geometry": {"coordinates":[174.79956100000001,-36.824425],"type":"Point"}
}