{
  "type": "Feature",
  "properties": {
    "iso:country":"NZ",
    "sg:address":"PO Box 40835 Upper Hutt ",
    "sg:city":"Wellington",
    "sg:classifiers":[
        {
            "category":"Sports & Exercise",
            "subcategory":"Ice Rink",
            "type":"Entertainment"
        }
    ],
    "sg:phone":"+64 4-939 0507",
    "sg:province":"Wellington",
    "sg:tags":[
        "skating",
        "-",
        "leisure",
        "sports"
    ],
    "wof:name":"Upper Hutt Roller Skating Club",
    "wof:placetype":"venue"
},
  "geometry": {"coordinates":[175.07037399999999,-41.124439],"type":"Point"}
}