{
  "type": "Feature",
  "properties": {
    "addr:full":"81 Orbell St Sydenham  Christchurch Canterbury",
    "addr:housenumber":"81",
    "addr:street":"Orbell St",
    "iso:country":"NZ",
    "sg:address":"81 Orbell St Sydenham ",
    "sg:city":"Christchurch",
    "sg:orig_category":"Industrial: Electrical/Electronic: Electric Motors",
    "sg:phone":"+64 3-379 3770",
    "sg:province":"Canterbury",
    "wof:name":"Electrical Repairs Ltd",
    "wof:placetype":"venue"
},
  "geometry": {"coordinates":[172.63192699999999,-43.543343],"type":"Point"}
}