{
  "type": "Feature",
  "properties": {
    "iso:country":"NZ",
    "sg:address":"Works Rd Pukeuri Junction ",
    "sg:city":"Oamaru",
    "sg:classifiers":[
        {
            "category":"Shopping",
            "subcategory":"Crafts & Fabrics",
            "type":"Retail Goods"
        }
    ],
    "sg:phone":"+64 3-433 1850",
    "sg:province":"Otago",
    "sg:tags":[
        "leather",
        "clothing",
        "suede"
    ],
    "wof:name":"Waitaki Leathers",
    "wof:placetype":"venue"
},
  "geometry": {"coordinates":[171.02972399999999,-45.03511],"type":"Point"}
}