{
  "type": "Feature",
  "properties": {
    "iso:country":"NZ",
    "sg:address":"51 High St Kakanui ",
    "sg:city":"Maheno",
    "sg:orig_category":"Shopping: Retail Stores: Supermarkets",
    "sg:phone":"+64 3-439 5759",
    "wof:name":"Kakanui Store",
    "wof:placetype":"venue"
},
  "geometry": {"coordinates":[170.899246,-45.181141],"type":"Point"}
}