{
  "type": "Feature",
  "properties": {
    "addr:full":"548 Main St Palmerston  Palmerston North Manawatu-Wanganui",
    "addr:housenumber":"548",
    "addr:street":"Main St",
    "iso:country":"NZ",
    "sg:address":"548 Main St Palmerston ",
    "sg:city":"Palmerston North",
    "sg:classifiers":[
        {
            "category":"Home & Garden",
            "subcategory":"Furniture",
            "type":"Retail Goods"
        }
    ],
    "sg:phone":"+64 6-357 6200",
    "sg:province":"Manawatu-Wanganui",
    "sg:tags":[
        "furniture/furnishings",
        "repair",
        "finishing"
    ],
    "wof:name":"Lombard Stripping & Polishing",
    "wof:placetype":"venue"
},
  "geometry": {"coordinates":[175.61552399999999,-40.354359],"type":"Point"}
}