{
  "type": "Feature",
  "properties": {
    "iso:country":"NZ",
    "sg:address":"736 Great South Rd Manukau ",
    "sg:city":"Auckland",
    "sg:classifiers":[
        {
            "category":"Bars & Pubs",
            "type":"Food & Drink"
        }
    ],
    "sg:phone":"+64 9-263 9007",
    "sg:province":"Auckland",
    "sg:tags":[
        "wining",
        "dining",
        "brasserie"
    ],
    "wof:name":"Silo Casino Bar And Bistro",
    "wof:placetype":"venue"
},
  "geometry": {"coordinates":[-119.104576,36.597755],"type":"Point"}
}