{
  "type": "Feature",
  "properties": {
    "iso:country":"NZ",
    "sg:address":"73 Duke St ",
    "sg:city":"Hamilton",
    "sg:classifiers":[
        {
            "category":"Building & Trades",
            "subcategory":"Construction",
            "type":"Services"
        }
    ],
    "sg:phone":"+64 7-846 7900",
    "sg:province":"Waikato",
    "sg:tags":[
        "specialist",
        "industrial",
        "equipment",
        "cooling",
        "machinery",
        "tower"
    ],
    "wof:name":"Invensys",
    "wof:placetype":"venue"
},
  "geometry": {"coordinates":[-84.847351,32.758301],"type":"Point"}
}