{
  "type": "Feature",
  "properties": {
    "addr:full":"12 The Cresent  Invercargill Southland",
    "addr:housenumber":"12",
    "addr:street":"The Cresent",
    "iso:country":"NZ",
    "sg:address":"12 The Cresent ",
    "sg:city":"Invercargill",
    "sg:classifiers":[
        {
            "category":"Restaurant",
            "type":"Food & Drink"
        }
    ],
    "sg:phone":"+64 3-214 6189",
    "sg:province":"Southland",
    "sg:tags":[
        "wining",
        "dining"
    ],
    "wof:name":"The Crescent Restaurant & Bar",
    "wof:placetype":"venue"
},
  "geometry": {"coordinates":[168.35217299999999,-46.411854],"type":"Point"}
}