{
  "type": "Feature",
  "properties": {
    "iso:country":"NZ",
    "sg:address":"31 Johnsonville Rd Johnsonville ",
    "sg:city":"Wellington",
    "sg:orig_category":"Health And Beauty: Beauty: Manicurists",
    "sg:phone":"+64 4-972 2428",
    "sg:province":"Wellington",
    "wof:name":"All Nail Secrets",
    "wof:placetype":"venue"
},
  "geometry": {"coordinates":[174.80746500000001,-41.223156],"type":"Point"}
}