{
  "type": "Feature",
  "properties": {
    "addr:full":"366 Princes St  Dunedin Otago",
    "addr:housenumber":"366",
    "addr:street":"Princes St",
    "iso:country":"NZ",
    "sg:address":"366 Princes St ",
    "sg:city":"Dunedin",
    "sg:classifiers":[
        {
            "category":"Personal",
            "subcategory":"Tattoo Parlor",
            "type":"Services"
        }
    ],
    "sg:phone":"+64 3-477 5887",
    "sg:province":"Otago",
    "sg:tags":[
        "services",
        "home",
        "tattooists",
        "garden"
    ],
    "wof:name":"Dig A Tattoo",
    "wof:placetype":"venue"
},
  "geometry": {"coordinates":[170.50027499999999,-45.87973],"type":"Point"}
}