{
  "type": "Feature",
  "properties": {
    "addr:full":"42 B Porana Rd Glenfield  Auckland Auckland",
    "addr:housenumber":"42",
    "addr:street":"B Porana Rd",
    "iso:country":"NZ",
    "sg:address":"42 B Porana Rd Glenfield ",
    "sg:city":"Auckland",
    "sg:classifiers":[
        {
            "category":"Sports & Exercise",
            "subcategory":"Sports Center",
            "type":"Entertainment"
        }
    ],
    "sg:phone":"+64 9-444 5308",
    "sg:province":"Auckland",
    "sg:tags":[
        "art",
        "leisure"
    ],
    "sg:website":"http://www.marinetrimmers.co.nz",
    "wof:name":"All Awnings",
    "wof:placetype":"venue"
},
  "geometry": {"coordinates":[174.728622,-36.784813],"type":"Point"}
}