{
  "type": "Feature",
  "properties": {
    "iso:country":"NZ",
    "sg:address":"748 Waitakere Rd Kumeu ",
    "sg:city":"Auckland",
    "sg:classifiers":[
        {
            "category":"Winery",
            "type":"Food & Drink"
        }
    ],
    "sg:phone":"+64 9-412 7256",
    "sg:province":"Auckland",
    "sg:tags":[
        "wining",
        "vineyard",
        "dining"
    ],
    "wof:name":"Harrier Rise Vineyard",
    "wof:placetype":"venue"
},
  "geometry": {"coordinates":[174.553329,-36.795135],"type":"Point"}
}