{
  "type": "Feature",
  "properties": {
    "addr:full":"30 North Rd North East Valley  Dunedin Otago",
    "addr:housenumber":"30",
    "addr:street":"North Rd",
    "iso:country":"NZ",
    "sg:address":"30 North Rd North East Valley ",
    "sg:city":"Dunedin",
    "sg:orig_category":"Farming: Farms - General: Poultry",
    "sg:phone":"+64 3-473 1748",
    "sg:province":"Otago",
    "wof:name":"Dunedin Poultry Processors Ltd",
    "wof:placetype":"venue"
},
  "geometry": {"coordinates":[170.519867,-45.85453],"type":"Point"}
}