{
  "type": "Feature",
  "properties": {
    "addr:full":"Alexandra Rd R D 1 Te Aroha  Morrinsville Waikato",
    "addr:housenumber":"1",
    "addr:street":"Alexandra Rd R D",
    "iso:country":"NZ",
    "sg:address":"Alexandra Rd R D 1 Te Aroha ",
    "sg:city":"Morrinsville",
    "sg:classifiers":[
        {
            "category":"Personal",
            "type":"Services"
        }
    ],
    "sg:phone":"+64 7-884 6603",
    "sg:province":"Waikato",
    "sg:tags":[
        "celebrant",
        "arrangements",
        "marriage",
        "wedding"
    ],
    "wof:name":"Singh Harbail JP",
    "wof:placetype":"venue"
},
  "geometry": {"coordinates":[175.528717,-37.65411],"type":"Point"}
}