{
  "type": "Feature",
  "properties": {
    "iso:country":"NZ",
    "sg:address":"31-33 Great South Road ",
    "sg:city":"Auckland",
    "sg:orig_category":"Industrial: Products: Window Control Gear",
    "sg:phone":"+64 9-573 5444",
    "sg:province":"Wellington",
    "wof:name":"Aluminium Solutions",
    "wof:placetype":"venue"
},
  "geometry": {"coordinates":[-119.10457599999999,36.597755],"type":"Point"}
}