{
  "type": "Feature",
  "properties": {
    "addr:full":"PO Box 205  Hamilton Waikato",
    "addr:housenumber":"po;205",
    "addr:street":"Box",
    "iso:country":"NZ",
    "sg:address":"PO Box 205 ",
    "sg:city":"Hamilton",
    "sg:classifiers":[
        {
            "category":"Farming",
            "subcategory":"Farm & Veterinary Services",
            "type":"Manufacturing & Wholesale Goods"
        }
    ],
    "sg:phone":"+64 7-854 6751",
    "sg:province":"Waikato",
    "sg:tags":[
        "supplies",
        "supply"
    ],
    "wof:name":"Cooper Industries Ltd",
    "wof:placetype":"venue"
},
  "geometry": {"coordinates":[-74.71270800000001,40.222748],"type":"Point"}
}