{
  "type": "Feature",
  "properties": {
    "iso:country":"NZ",
    "sg:address":"27 Mackay St ",
    "sg:city":"Greymouth",
    "sg:classifiers":[
        {
            "category":"Building & Trades",
            "subcategory":"Landscaping Services",
            "type":"Services"
        }
    ],
    "sg:phone":"+64 3-768 6499",
    "sg:province":"West Coast",
    "sg:tags":[
        "personal",
        "home",
        "garden"
    ],
    "sg:website":"http://www.stewartnimmo.co.nz",
    "wof:name":"Stewart Nimmo Photography",
    "wof:placetype":"venue"
},
  "geometry": {"coordinates":[171.20851099999999,-42.448624],"type":"Point"}
}