{
  "type": "Feature",
  "properties": {
    "iso:country":"NZ",
    "sg:address":"13 Grant St Havelock North ",
    "sg:city":"Hastings",
    "sg:classifiers":[
        {
            "category":"Building & Trades",
            "subcategory":"Construction",
            "type":"Services"
        }
    ],
    "sg:phone":"+64 800 206 2879",
    "sg:province":"Hawke's Bay",
    "sg:tags":[
        "home",
        "garden",
        "related",
        "plasterer"
    ],
    "wof:name":"East Coast Suspended Ceilings",
    "wof:placetype":"venue"
},
  "geometry": {"coordinates":[176.871445,-39.677635],"type":"Point"}
}