{
  "type": "Feature",
  "properties": {
    "addr:full":"861 A Dominion Rd Mt Roskill  Auckland Auckland",
    "addr:housenumber":"861 a",
    "addr:street":"Dominion Rd",
    "iso:country":"NZ",
    "sg:address":"861 A Dominion Rd Mt Roskill ",
    "sg:city":"Auckland",
    "sg:classifiers":[
        {
            "category":"Sports & Exercise",
            "subcategory":"Climbing Gym",
            "type":"Entertainment"
        }
    ],
    "sg:phone":"+64 9-620 6973",
    "sg:province":"Auckland",
    "sg:tags":[
        "-",
        "leisure",
        "sports"
    ],
    "wof:name":"The Dance Studio",
    "wof:placetype":"venue"
},
  "geometry": {"coordinates":[174.74169900000001,-36.904678],"type":"Point"}
}