{
  "type": "Feature",
  "properties": {
    "addr:full":"18 Union St New Brighton  Christchurch Canterbury",
    "addr:housenumber":"18",
    "addr:street":"Union St",
    "iso:country":"NZ",
    "sg:address":"18 Union St New Brighton ",
    "sg:city":"Christchurch",
    "sg:classifiers":[
        {
            "category":"Health Services",
            "subcategory":"Medical Lab",
            "type":"Services"
        }
    ],
    "sg:phone":"+64 3-382 4093",
    "sg:province":"Canterbury",
    "sg:tags":[
        "laboratory",
        "beauty",
        "specialists"
    ],
    "wof:name":"Medlab South Ltd",
    "wof:placetype":"venue"
},
  "geometry": {"coordinates":[172.72735599999999,-43.508648],"type":"Point"}
}