{
  "type": "Feature",
  "properties": {
    "addr:full":"6 c Forests Rd Stoke  Nelson Nelson",
    "addr:housenumber":"6 c",
    "addr:street":"Forests Rd",
    "iso:country":"NZ",
    "sg:address":"6 c Forests Rd Stoke ",
    "sg:city":"Nelson",
    "sg:classifiers":[
        {
            "category":"Food & Beverages",
            "subcategory":"Groceries & Convenience Stores",
            "type":"Retail Goods"
        }
    ],
    "sg:phone":"+64 3-547 4696",
    "sg:province":"Nelson",
    "sg:tags":[
        "foodstuff",
        "drink",
        "-"
    ],
    "wof:name":"Natural Choice Distributors Ltd",
    "wof:placetype":"venue"
},
  "geometry": {"coordinates":[173.23419200000001,-41.312859],"type":"Point"}
}