{
  "type": "Feature",
  "properties": {
    "iso:country":"NZ",
    "sg:address":"11 The Mall ",
    "sg:city":"Queenstown",
    "sg:orig_category":"Sports And Leisure: Arts: Theatres",
    "sg:phone":"+64 3-442 9990",
    "sg:province":"Otago",
    "wof:name":"Embassy Cinemas",
    "wof:placetype":"venue"
},
  "geometry": {"coordinates":[-76.157791,38.990379],"type":"Point"}
}