{
  "type": "Feature",
  "properties": {
    "iso:country":"NZ",
    "sg:address":"138 Percival St ",
    "sg:city":"Rangiora",
    "sg:classifiers":[
        {
            "category":"Recreation",
            "type":"Entertainment"
        }
    ],
    "sg:phone":"+64 800 426 6846",
    "sg:province":"Canterbury",
    "sg:tags":[
        "sport",
        "leisure"
    ],
    "sg:website":"http://www.yellowpages.co.nz/pages/112630509/dp49343.html",
    "wof:name":"Continental",
    "wof:placetype":"venue"
},
  "geometry": {"coordinates":[172.593796,-43.304653],"type":"Point"}
}