{
  "type": "Feature",
  "properties": {
    "iso:country":"NZ",
    "sg:address":"7 E Mandeville St Riccarton ",
    "sg:city":"Christchurch",
    "sg:classifiers":[
        {
            "category":"Home & Garden",
            "subcategory":"Building Materials",
            "type":"Retail Goods"
        }
    ],
    "sg:phone":"+64 3-343 4005",
    "sg:province":"Canterbury",
    "sg:tags":[
        "design",
        "fitting",
        "fittings",
        "kitchen"
    ],
    "sg:website":"http://www.kitchenexpress.co.nz",
    "wof:name":"Kitchen Express",
    "wof:placetype":"venue"
},
  "geometry": {"coordinates":[172.606842,-43.536022],"type":"Point"}
}