{
  "type": "Feature",
  "properties": {
    "iso:country":"NZ",
    "sg:address":"132 Broadway Ave Palmerston ",
    "sg:city":"Palmerston North",
    "sg:classifiers":[
        {
            "category":"Food & Beverages",
            "subcategory":"Bakery",
            "type":"Retail Goods"
        }
    ],
    "sg:phone":"+64 6-357 2927",
    "sg:province":"Manawatu-Wanganui",
    "sg:tags":[
        "shop",
        "cake",
        "drink",
        "-"
    ],
    "sg:website":"http://www.yellowpages.co.nz/for/fairytalecakes/dp58363.html",
    "wof:name":"Fairytale Cakes",
    "wof:placetype":"venue"
},
  "geometry": {"coordinates":[175.614395,-40.353512],"type":"Point"}
}