{
  "type": "Feature",
  "properties": {
    "iso:country":"NZ",
    "sg:address":"29 Ritchie St ",
    "sg:city":"Timaru",
    "sg:classifiers":[
        {
            "category":"Social Services",
            "subcategory":"Job Training",
            "type":"Services"
        }
    ],
    "sg:phone":"+64 3-684 8663",
    "sg:province":"Canterbury",
    "sg:tags":[
        "education"
    ],
    "wof:name":"Timaru Fishing School",
    "wof:placetype":"venue"
},
  "geometry": {"coordinates":[171.257431,-44.394176],"type":"Point"}
}