{
  "type": "Feature",
  "properties": {
    "iso:country":"NZ",
    "sg:address":"PO Box 14337 Kilbirnie ",
    "sg:city":"Wellington",
    "sg:orig_category":"Industrial: Services: Gasfitters",
    "sg:phone":"+64 4-478 4437",
    "sg:province":"Wellington",
    "wof:name":"Go With The Flow Ltd",
    "wof:placetype":"venue"
},
  "geometry": {"coordinates":[174.794678,-41.318909],"type":"Point"}
}