{
  "type": "Feature",
  "properties": {
    "addr:full":"Unit 6 122 Railside Ave Henderson  Auckland Auckland",
    "addr:housenumber":"unit 6",
    "addr:postcode":"122",
    "addr:street":"Railside Ave",
    "iso:country":"NZ",
    "sg:address":"Unit 6 122 Railside Ave Henderson ",
    "sg:city":"Auckland",
    "sg:classifiers":[
        {
            "category":"Manufacturing",
            "subcategory":"Motor Vehicles & Parts",
            "type":"Manufacturing & Wholesale Goods"
        }
    ],
    "sg:phone":"+64 9-838 9297",
    "sg:province":"Auckland",
    "sg:tags":[
        "body",
        "repair",
        "builder",
        "servicing",
        "automotive"
    ],
    "wof:name":"Waitakere Motorbodies Ltd",
    "wof:placetype":"venue"
},
  "geometry": {"coordinates":[174.63179,-36.888165],"type":"Point"}
}