{
  "type": "Feature",
  "properties": {
    "iso:country":"NZ",
    "sg:address":"Glen Eden ",
    "sg:city":"Auckland",
    "sg:classifiers":[
        {
            "category":"Autos & Motor Vehicles",
            "subcategory":"Automobile Sales",
            "type":"Retail Goods"
        }
    ],
    "sg:phone":"+64 9-818 5175",
    "sg:province":"Auckland",
    "sg:tags":[
        "home",
        "caravan",
        "leasing",
        "automotive"
    ],
    "wof:name":"Henderson Caravans",
    "wof:placetype":"venue"
},
  "geometry": {"coordinates":[174.644623,-36.913029],"type":"Point"}
}