{
  "type": "Feature",
  "properties": {
    "addr:full":"Glenfield  Auckland Auckland",
    "iso:country":"NZ",
    "sg:address":"Glenfield ",
    "sg:city":"Auckland",
    "sg:classifiers":[
        {
            "category":"Travel",
            "subcategory":"Travel Agent",
            "type":"Entertainment"
        }
    ],
    "sg:phone":"+64 9-478 2843",
    "sg:province":"Auckland",
    "sg:tags":[
        "tourism",
        "-",
        "accommodation",
        "booking"
    ],
    "wof:name":"Calbo Holdings Ltd",
    "wof:placetype":"venue"
},
  "geometry": {"coordinates":[174.72280900000001,-36.77676],"type":"Point"}
}