{
  "type": "Feature",
  "properties": {
    "iso:country":"NZ",
    "sg:address":"89 Broadway ",
    "sg:city":"Kaikohe",
    "sg:classifiers":[
        {
            "category":"Sports & Exercise",
            "subcategory":"Ski Resort",
            "type":"Entertainment"
        }
    ],
    "sg:phone":"+64 9-401 1886",
    "sg:province":"Manawatu-Wanganui",
    "sg:tags":[
        "hobbies",
        "photographic",
        "leisure",
        "developing"
    ],
    "wof:name":"Kodak Express",
    "wof:placetype":"venue"
},
  "geometry": {"coordinates":[173.801071,-35.407009],"type":"Point"}
}