{
  "type": "Feature",
  "properties": {
    "addr:full":"PO Box 164  Ohakune",
    "addr:housenumber":"po",
    "addr:street":"Box 164",
    "iso:country":"NZ",
    "sg:address":"PO Box 164 ",
    "sg:city":"Ohakune",
    "sg:classifiers":[
        {
            "category":"Social Services",
            "subcategory":"Job Training",
            "type":"Services"
        }
    ],
    "sg:phone":"+64 6-385 9095",
    "sg:tags":[
        "education"
    ],
    "wof:name":"Vertical Horizonz",
    "wof:placetype":"venue"
},
  "geometry": {"coordinates":[175.403839,-39.412289],"type":"Point"}
}