{
  "type": "Feature",
  "properties": {
    "iso:country":"NZ",
    "sg:address":"105 Victoria Ave Ph/Fax ",
    "sg:city":"Wanganui",
    "sg:orig_category":"Shopping: Retail Stores: Secondhand Dealers",
    "sg:phone":"+64 6-347 2000",
    "sg:province":"Manawatu-Wanganui",
    "wof:name":"Antique Affaire",
    "wof:placetype":"venue"
},
  "geometry": {"coordinates":[175.051331,-39.932655],"type":"Point"}
}