{
  "type": "Feature",
  "properties": {
    "iso:country":"NZ",
    "sg:address":"8 Roberta Dve Spreydon ",
    "sg:city":"Christchurch",
    "sg:classifiers":[
        {
            "category":"Banks & Credit Unions",
            "subcategory":"Investment Brokerage",
            "type":"Services"
        }
    ],
    "sg:phone":"+64 21 1031 395",
    "sg:province":"Canterbury",
    "sg:tags":[
        "services",
        "industrial",
        "refrigeration",
        "servicing"
    ],
    "wof:name":"Moore Refrigeration",
    "wof:placetype":"venue"
},
  "geometry": {"coordinates":[172.616211,-43.553249],"type":"Point"}
}