{
  "type": "Feature",
  "properties": {
    "addr:full":"8 Cypress St Judea  Tauranga Bay of Plenty",
    "addr:housenumber":"8",
    "addr:street":"Cypress St",
    "iso:country":"NZ",
    "sg:address":"8 Cypress St Judea ",
    "sg:city":"Tauranga",
    "sg:classifiers":[
        {
            "category":"Home & Garden",
            "subcategory":"Building Materials",
            "type":"Retail Goods"
        }
    ],
    "sg:phone":"+64 7-578 1414",
    "sg:province":"Bay of Plenty",
    "sg:tags":[
        "fittings",
        "staircase",
        "handrail"
    ],
    "wof:name":"Beetham's Top Flyte Stairs",
    "wof:placetype":"venue"
},
  "geometry": {"coordinates":[176.141434,-37.69899],"type":"Point"}
}