{
  "type": "Feature",
  "properties": {
    "addr:full":"Pauanui Shopping Centre Pauanui  Tairua",
    "iso:country":"NZ",
    "sg:address":"Pauanui Shopping Centre Pauanui ",
    "sg:city":"Tairua",
    "sg:classifiers":[
        {
            "category":"Landmark",
            "subcategory":"Tourist Information",
            "type":"Public Place"
        }
    ],
    "sg:phone":"+64 7-864 7101",
    "sg:tags":[
        "services",
        "travel",
        "tourism"
    ],
    "wof:name":"Pauanui Information Centre",
    "wof:placetype":"venue"
},
  "geometry": {"coordinates":[175.846405,-37.00642],"type":"Point"}
}