{
  "type": "Feature",
  "properties": {
    "iso:country":"NZ",
    "sg:address":"28 B Kent St Marchwiel ",
    "sg:city":"Timaru",
    "sg:classifiers":[
        {
            "category":"Education",
            "subcategory":"Dance Studio",
            "type":"Public Place"
        }
    ],
    "sg:phone":"+64 3-684 7797",
    "sg:province":"Canterbury",
    "sg:tags":[
        "school",
        "dancing",
        "-",
        "leisure",
        "sports",
        "sport"
    ],
    "wof:name":"Blackham Kaye",
    "wof:placetype":"venue"
},
  "geometry": {"coordinates":[171.22726399999999,-44.382481],"type":"Point"}
}