{
  "type": "Feature",
  "properties": {
    "addr:full":"47 Torquay St Abbotsford  Dunedin Auckland",
    "addr:housenumber":"47",
    "addr:street":"Torquay St",
    "iso:country":"NZ",
    "sg:address":"47 Torquay St Abbotsford ",
    "sg:city":"Dunedin",
    "sg:orig_category":"Transport: Land: Shuttle Services",
    "sg:phone":"+64 274 394 323",
    "sg:province":"Auckland",
    "wof:name":"O'Brien Shuttles",
    "wof:placetype":"venue"
},
  "geometry": {"coordinates":[170.42584199999999,-45.894348],"type":"Point"}
}