{
  "type": "Feature",
  "properties": {
    "addr:full":"409 Main South Rd Hornby  Christchurch Canterbury",
    "addr:housenumber":"409",
    "addr:street":"Main South Rd",
    "iso:country":"NZ",
    "sg:address":"409 Main South Rd Hornby ",
    "sg:city":"Christchurch",
    "sg:orig_category":"Shopping: Discount",
    "sg:phone":"+64 3-349 4980",
    "sg:province":"Canterbury",
    "wof:name":"Dress-Smart Factory Outlet Centre",
    "wof:placetype":"venue"
},
  "geometry": {"coordinates":[172.52439899999999,-43.543655],"type":"Point"}
}