{
  "type": "Feature",
  "properties": {
    "addr:full":"278 B King Edward St South Dunedin  Dunedin Otago",
    "addr:housenumber":"278 b",
    "addr:street":"King Edward St",
    "iso:country":"NZ",
    "sg:address":"278 B King Edward St South Dunedin ",
    "sg:city":"Dunedin",
    "sg:classifiers":[
        {
            "category":"Retail",
            "subcategory":"Laundry & Dry Cleaning",
            "type":"Services"
        }
    ],
    "sg:phone":"+64 3-455 2119",
    "sg:province":"Otago",
    "sg:tags":[
        "repair",
        "clothing",
        "fabric"
    ],
    "wof:name":"South Laundry",
    "wof:placetype":"venue"
},
  "geometry": {"coordinates":[170.50096099999999,-45.896103],"type":"Point"}
}