{
  "type": "Feature",
  "properties": {
    "addr:full":"55 Picton St Howick  Auckland Auckland",
    "addr:housenumber":"55",
    "addr:street":"Picton St",
    "iso:country":"NZ",
    "sg:address":"55 Picton St Howick ",
    "sg:city":"Auckland",
    "sg:classifiers":[
        {
            "category":"Health Services",
            "subcategory":"Optometrist",
            "type":"Services"
        }
    ],
    "sg:phone":"+64 9-535 6577",
    "sg:province":"Auckland",
    "sg:tags":[
        "optical",
        "beauty"
    ],
    "wof:name":"Thompson Optometrists",
    "wof:placetype":"venue"
},
  "geometry": {"coordinates":[174.916946,-36.894379],"type":"Point"}
}