{
  "type": "Feature",
  "properties": {
    "addr:full":"Ruataniwha St  Waipukurau",
    "addr:street":"Ruataniwha St",
    "iso:country":"NZ",
    "sg:address":"Ruataniwha St ",
    "sg:city":"Waipukurau",
    "sg:classifiers":[
        {
            "category":"Health Services",
            "subcategory":"Clinic",
            "type":"Services"
        }
    ],
    "sg:phone":"+64 6-858 8908",
    "sg:tags":[
        "services",
        "therapy",
        "natural",
        "beauty"
    ],
    "wof:name":"Food for Thought Health Centre",
    "wof:placetype":"venue"
},
  "geometry": {"coordinates":[176.55548099999999,-39.995388],"type":"Point"}
}