{
  "type": "Feature",
  "properties": {
    "addr:full":"398 East Coast Rd Mairangi Bay  Auckland Auckland",
    "addr:housenumber":"398",
    "addr:street":"East Coast Rd",
    "iso:country":"NZ",
    "sg:address":"398 East Coast Rd Mairangi Bay ",
    "sg:city":"Auckland",
    "sg:classifiers":[
        {
            "category":"Shopping",
            "subcategory":"Pets & Pet Supplies",
            "type":"Retail Goods"
        }
    ],
    "sg:phone":"+64 9-479 6034",
    "sg:province":"Auckland",
    "sg:tags":[
        "home",
        "garden"
    ],
    "wof:name":"North Harbour Veterinary Hospital",
    "wof:placetype":"venue"
},
  "geometry": {"coordinates":[174.742401,-36.747284],"type":"Point"}
}