{
  "type": "Feature",
  "properties": {
    "addr:full":"260 Featherston St Palmerston  Palmerston North Manawatu-Wanganui",
    "addr:housenumber":"260",
    "addr:street":"Featherston St Palmerston",
    "iso:country":"NZ",
    "sg:address":"260 Featherston St Palmerston ",
    "sg:city":"Palmerston North",
    "sg:orig_category":"Food And Drink: Catering: Caterers",
    "sg:phone":"+64 6-357 8096",
    "sg:province":"Manawatu-Wanganui",
    "wof:name":"Bakers Bakery",
    "wof:placetype":"venue"
},
  "geometry": {"coordinates":[175.608002,-40.34927],"type":"Point"}
}