{
  "type": "Feature",
  "properties": {
    "iso:country":"NZ",
    "sg:address":"Awakino Rd ",
    "sg:city":"Dargaville",
    "sg:classifiers":[
        {
            "category":"Health Services",
            "subcategory":"Health Practitioner",
            "type":"Services"
        }
    ],
    "sg:phone":"+64 9-439 1690",
    "sg:province":"Northland",
    "sg:tags":[
        "consultant",
        "medical",
        "beauty"
    ],
    "wof:name":"Te Ha O' Te Oranga O Ngatiwhatua",
    "wof:placetype":"venue"
},
  "geometry": {"coordinates":[173.86891199999999,-35.914841],"type":"Point"}
}