{
  "type": "Feature",
  "properties": {
    "addr:full":"Auckland Viaduct 95 Customs St West Auckland Central Auckland Auckland",
    "addr:housenumber":"95",
    "addr:street":"Auckland Viaduct;Customs St",
    "iso:country":"NZ",
    "sg:address":"Auckland Viaduct 95 Customs St West Auckland Central",
    "sg:city":"Auckland",
    "sg:classifiers":[
        {
            "category":"Shopping",
            "subcategory":"Crafts & Fabrics",
            "type":"Retail Goods"
        }
    ],
    "sg:phone":"+64 9-358 3835",
    "sg:province":"Auckland",
    "sg:tags":[
        "pottery",
        "home",
        "accessories",
        "garden",
        "supply"
    ],
    "wof:name":"The Garden Party Shops",
    "wof:placetype":"venue"
},
  "geometry": {"coordinates":[-119.10457599999999,36.597755],"type":"Point"}
}