{
  "type": "Feature",
  "properties": {
    "iso:country":"NZ",
    "sg:address":"Cnr Tutanekai & Haupapa St ",
    "sg:city":"Rotorua",
    "sg:orig_category":"Shopping: Sports Retailers: Sports Goods: Sportswear",
    "sg:phone":"+64 7-349 2610",
    "sg:province":"Bay of Plenty",
    "wof:name":"N-Zone Design Ltd",
    "wof:placetype":"venue"
},
  "geometry": {"coordinates":[-70.604202,-26.329201],"type":"Point"}
}