{
  "type": "Feature",
  "properties": {
    "addr:full":"45 Weld St  Feilding Manawatu-Wanganui",
    "addr:housenumber":"45",
    "addr:street":"Weld St",
    "iso:country":"NZ",
    "sg:address":"45 Weld St ",
    "sg:city":"Feilding",
    "sg:classifiers":[
        {
            "category":"Sports & Exercise",
            "subcategory":"Tennis Court",
            "type":"Entertainment"
        }
    ],
    "sg:phone":"+64 6-323 6068",
    "sg:province":"Manawatu-Wanganui",
    "sg:tags":[
        "hire",
        "-",
        "leisure"
    ],
    "wof:name":"Faulding's Electrical & Sound Service Ltd",
    "wof:placetype":"venue"
},
  "geometry": {"coordinates":[175.568207,-40.223621],"type":"Point"}
}