{
  "type": "Feature",
  "properties": {
    "addr:full":"43 Russell St Palmerston  Palmerston North Manawatu-Wanganui",
    "addr:housenumber":"43",
    "addr:street":"Russell St Palmerston",
    "iso:country":"NZ",
    "sg:address":"43 Russell St Palmerston ",
    "sg:city":"Palmerston North",
    "sg:classifiers":[
        {
            "category":"Education",
            "subcategory":"Special Training",
            "type":"Public Place"
        }
    ],
    "sg:phone":"+64 6-357 1444",
    "sg:province":"Manawatu-Wanganui",
    "sg:tags":[
        "drama",
        "speech",
        "-",
        "teacher",
        "language"
    ],
    "wof:name":"Switzer Paul & Gail",
    "wof:placetype":"venue"
},
  "geometry": {"coordinates":[175.61381499999999,-40.341156],"type":"Point"}
}