{
  "type": "Feature",
  "properties": {
    "addr:full":"7 Brook St Bexley  Christchurch Canterbury",
    "addr:housenumber":"7",
    "addr:street":"Brook St",
    "iso:country":"NZ",
    "sg:address":"7 Brook St Bexley ",
    "sg:city":"Christchurch",
    "sg:classifiers":[
        {
            "category":"Manufacturing",
            "subcategory":"Tools & Machinery",
            "type":"Manufacturing & Wholesale Goods"
        }
    ],
    "sg:phone":"+64 3-388 1909",
    "sg:province":"Canterbury",
    "sg:tags":[
        "equipment",
        "industrial",
        "label"
    ],
    "wof:name":"Flash Screenprint",
    "wof:placetype":"venue"
},
  "geometry": {"coordinates":[172.719086,-43.513832],"type":"Point"}
}