{
  "type": "Feature",
  "properties": {
    "addr:full":"244 Gloucester St Taradale  Napier Hawke's Bay",
    "addr:housenumber":"244",
    "addr:street":"Gloucester St",
    "iso:country":"NZ",
    "sg:address":"244 Gloucester St Taradale ",
    "sg:city":"Napier",
    "sg:classifiers":[
        {
            "category":"Communications",
            "subcategory":"Film & Video Production",
            "type":"Services"
        }
    ],
    "sg:phone":"+64 6-844 1547",
    "sg:province":"Hawke's Bay",
    "sg:tags":[
        "sport",
        "leisure",
        "library",
        "entertainment"
    ],
    "wof:name":"United Video Taradale",
    "wof:placetype":"venue"
},
  "geometry": {"coordinates":[176.848862,-39.535034],"type":"Point"}
}