{
  "type": "Feature",
  "properties": {
    "addr:full":"Matakawau Awhitu  Pukekohe Auckland",
    "iso:country":"NZ",
    "sg:address":"Matakawau Awhitu ",
    "sg:city":"Pukekohe",
    "sg:orig_category":"Education And Training: General: Schools",
    "sg:phone":"+64 9-235 1005",
    "sg:province":"Auckland",
    "wof:name":"Awhitu School",
    "wof:placetype":"venue"
},
  "geometry": {"coordinates":[174.62571700000001,-37.102638],"type":"Point"}
}