{
  "type": "Feature",
  "properties": {
    "addr:full":"8 Daldy St Auckland Central  Auckland Auckland",
    "addr:housenumber":"8",
    "addr:street":"Daldy St",
    "iso:country":"NZ",
    "sg:address":"8 Daldy St Auckland Central ",
    "sg:city":"Auckland",
    "sg:orig_category":"Transport: Boats And Marine: Boats: Boat Design",
    "sg:phone":"+64 9-357 0606",
    "sg:province":"Auckland",
    "wof:name":"Bakewell-White Yacht Design Ltd",
    "wof:placetype":"venue"
},
  "geometry": {"coordinates":[174.75415000000001,-36.844711],"type":"Point"}
}