{
  "type": "Feature",
  "properties": {
    "iso:country":"NZ",
    "sg:address":"157 Maces Rd Bromley ",
    "sg:city":"Christchurch",
    "sg:classifiers":[
        {
            "category":"Wholesale",
            "subcategory":"Auto Parts",
            "type":"Manufacturing & Wholesale Goods"
        }
    ],
    "sg:phone":"+64 3-389 9969",
    "sg:province":"Canterbury",
    "sg:tags":[
        "automotive",
        "supply"
    ],
    "sg:website":"http://www.eurospare.co.nz",
    "wof:name":"Ansell Eurospares",
    "wof:placetype":"venue"
},
  "geometry": {"coordinates":[172.69380200000001,-43.535976],"type":"Point"}
}