{
  "type": "Feature",
  "properties": {
    "addr:full":"9 Nixon St Grey Lynn  Auckland Auckland",
    "addr:housenumber":"9",
    "addr:street":"Nixon St",
    "iso:country":"NZ",
    "sg:address":"9 Nixon St Grey Lynn ",
    "sg:city":"Auckland",
    "sg:orig_category":"Shopping: Accessories",
    "sg:phone":"+64 9-378 7653",
    "sg:province":"Auckland",
    "sg:website":"http://www.yellowpages.co.nz/pages/200474595/dp32923.html",
    "wof:name":"Theo Meyer",
    "wof:placetype":"venue"
},
  "geometry": {"coordinates":[174.73474100000001,-36.861408],"type":"Point"}
}