{
  "type": "Feature",
  "properties": {
    "iso:country":"NZ",
    "sg:address":"20 Broad St Woolston ",
    "sg:city":"Christchurch",
    "sg:orig_category":"Industrial: Parts: Pipes, Tubes And Cabling: Pipes",
    "sg:phone":"+64 3-384 3040",
    "sg:province":"Canterbury",
    "wof:name":"Dawn Group Ltd",
    "wof:placetype":"venue"
},
  "geometry": {"coordinates":[172.68521100000001,-43.559216],"type":"Point"}
}