{
  "type": "Feature",
  "properties": {
    "iso:country":"NZ",
    "sg:address":"PO Box 51091 Tawa ",
    "sg:city":"Porirua",
    "sg:classifiers":[
        {
            "category":"Education",
            "subcategory":"Dance Studio",
            "type":"Public Place"
        }
    ],
    "sg:phone":"+64 4-237 5662",
    "sg:province":"Wellington",
    "sg:tags":[
        "school",
        "dancing",
        "-",
        "leisure",
        "sports",
        "sport"
    ],
    "wof:name":"Suzanne Denton Dance Academy",
    "wof:placetype":"venue"
},
  "geometry": {"coordinates":[174.82420300000001,-41.17149],"type":"Point"}
}