{
  "type": "Feature",
  "properties": {
    "iso:country":"NZ",
    "sg:address":"51-59 Preston Rd ",
    "sg:city":"Greymouth",
    "sg:classifiers":[
        {
            "category":"Retail",
            "subcategory":"Auto Repair",
            "type":"Services"
        }
    ],
    "sg:phone":"+64 3-768 0614",
    "sg:province":"West Coast",
    "sg:tags":[
        "breakdown",
        "automotive",
        "towing",
        "servicing"
    ],
    "wof:name":"John Pfeifer Panelbeating",
    "wof:placetype":"venue"
},
  "geometry": {"coordinates":[171.19712799999999,-42.453003],"type":"Point"}
}