{
  "type": "Feature",
  "properties": {
    "iso:country":"NZ",
    "sg:address":"141 Aikmans Rd Merivale ",
    "sg:city":"Christchurch",
    "sg:classifiers":[
        {
            "category":"Insurance",
            "subcategory":"Health Insurance",
            "type":"Services"
        }
    ],
    "sg:phone":"+64 3-355 8639",
    "sg:province":"Canterbury",
    "sg:tags":[
        "beauty",
        "supply"
    ],
    "wof:name":"PG Nail Design",
    "wof:placetype":"venue"
},
  "geometry": {"coordinates":[172.620834,-43.51173],"type":"Point"}
}