{
  "type": "Feature",
  "properties": {
    "iso:country":"NZ",
    "sg:address":"106 Lower Dent St ",
    "sg:city":"Whangarei",
    "sg:classifiers":[
        {
            "category":"Food & Beverages",
            "subcategory":"Liquor & Beverages",
            "type":"Retail Goods"
        }
    ],
    "sg:phone":"+64 800 436 7923",
    "sg:province":"Northland",
    "sg:tags":[
        "distributor",
        "drink"
    ],
    "wof:name":"Northland Hospitality",
    "wof:placetype":"venue"
},
  "geometry": {"coordinates":[174.326874,-35.726246],"type":"Point"}
}