{
  "type": "Feature",
  "properties": {
    "iso:country":"NZ",
    "sg:address":"Whgri Town Basin ",
    "sg:city":"Whangarei",
    "sg:classifiers":[
        {
            "category":"Internet Cafe",
            "subcategory":"None",
            "type":"Food & Drink"
        }
    ],
    "sg:phone":"+64 9-430 7477",
    "sg:province":"Northland",
    "sg:tags":[
        "wining",
        "dining"
    ],
    "wof:name":"Cable Action Communications",
    "wof:placetype":"venue"
},
  "geometry": {"coordinates":[174.504944,-35.815502],"type":"Point"}
}