{
  "type": "Feature",
  "properties": {
    "addr:full":"55 Grove Rd Addington  Christchurch Canterbury",
    "addr:housenumber":"55",
    "addr:street":"Grove Rd",
    "iso:country":"NZ",
    "sg:address":"55 Grove Rd Addington ",
    "sg:city":"Christchurch",
    "sg:classifiers":[
        {
            "category":"Autos & Motor Vehicles",
            "subcategory":"Automobile Sales",
            "type":"Retail Goods"
        }
    ],
    "sg:phone":"+64 3-339 0042",
    "sg:province":"Canterbury",
    "sg:tags":[
        "car",
        "management",
        "leasing",
        "fleet",
        "automotive"
    ],
    "sg:website":"http://www.leasedirect.co.nz",
    "wof:name":"Lease Direct",
    "wof:placetype":"venue"
},
  "geometry": {"coordinates":[172.61784399999999,-43.541355],"type":"Point"}
}