{
  "type": "Feature",
  "properties": {
    "addr:full":"518 a Main Rd Stoke  Nelson Nelson",
    "addr:housenumber":"518",
    "addr:street":"A Main Rd",
    "iso:country":"NZ",
    "sg:address":"518 a Main Rd Stoke ",
    "sg:city":"Nelson",
    "sg:orig_category":"Shopping: Retail Stores: Florist Accessories",
    "sg:phone":"+64 3-547 7688",
    "sg:province":"Nelson",
    "wof:name":"Angels' Flowers",
    "wof:placetype":"venue"
},
  "geometry": {"coordinates":[173.23407,-41.312851],"type":"Point"}
}