{
  "type": "Feature",
  "properties": {
    "iso:country":"NZ",
    "sg:address":"61 Rathgar Rd Henderson ",
    "sg:city":"Auckland",
    "sg:classifiers":[
        {
            "category":"Home & Garden",
            "subcategory":"Carpets & Floor Coverings",
            "type":"Retail Goods"
        }
    ],
    "sg:phone":"+64 9-836 3474",
    "sg:province":"Auckland",
    "sg:tags":[
        "cleaning",
        "furniture"
    ],
    "wof:name":"True Clean Carpet Services",
    "wof:placetype":"venue"
},
  "geometry": {"coordinates":[174.62072800000001,-36.870792],"type":"Point"}
}