{
  "type": "Feature",
  "properties": {
    "addr:full":"Main St  Manaia Wellington",
    "addr:street":"Main St",
    "iso:country":"NZ",
    "sg:address":"Main St ",
    "sg:city":"Manaia",
    "sg:orig_category":"Shopping: Retail Stores: Supermarkets",
    "sg:phone":"+64 6-274 8406",
    "sg:province":"Wellington",
    "wof:name":"Manaia Four Square",
    "wof:placetype":"venue"
},
  "geometry": {"coordinates":[174.12503100000001,-39.550308],"type":"Point"}
}