{
  "type": "Feature",
  "properties": {
    "addr:full":"PO Box 21-496 Henderson  Auckland Auckland",
    "addr:housenumber":"po box 21-496",
    "iso:country":"NZ",
    "sg:address":"PO Box 21-496 Henderson ",
    "sg:city":"Auckland",
    "sg:classifiers":[
        {
            "category":"Utilities",
            "subcategory":"Refuse",
            "type":"Services"
        }
    ],
    "sg:phone":"+64 9-378 0803",
    "sg:province":"Auckland",
    "sg:tags":[
        "bin",
        "hire",
        "garden",
        "cleaning",
        "rubbish",
        "home"
    ],
    "wof:name":"Auckland Contracting Services",
    "wof:placetype":"venue"
},
  "geometry": {"coordinates":[174.77041600000001,-36.884109],"type":"Point"}
}