{
  "type": "Feature",
  "properties": {
    "addr:full":"3 Blomfield Spa Takapuna  Auckland Auckland",
    "addr:housenumber":"3",
    "iso:country":"NZ",
    "sg:address":"3 Blomfield Spa Takapuna ",
    "sg:city":"Auckland",
    "sg:classifiers":[
        {
            "category":"Health Services",
            "subcategory":"Health Practitioner",
            "type":"Services"
        }
    ],
    "sg:phone":"+64 9-489 5151",
    "sg:province":"Auckland",
    "sg:tags":[
        "services",
        "beauty",
        "acupuncturists"
    ],
    "wof:name":"Acupuncture & Massage Clinic Takapuna",
    "wof:placetype":"venue"
},
  "geometry": {"coordinates":[174.773956,-36.790436],"type":"Point"}
}