{
  "type": "Feature",
  "properties": {
    "iso:country":"NZ",
    "sg:address":"Works Rd Longburn Palmerston ",
    "sg:city":"Palmerston North",
    "sg:orig_category":"Industrial: Manufacturing",
    "sg:phone":"+64 6-354 2749",
    "sg:province":"Manawatu-Wanganui",
    "wof:name":"Page Tanks",
    "wof:placetype":"venue"
},
  "geometry": {"coordinates":[175.54229699999999,-40.388725],"type":"Point"}
}