{
  "type": "Feature",
  "properties": {
    "iso:country":"NZ",
    "sg:address":"233 Anglesea St ",
    "sg:city":"Hamilton",
    "sg:orig_category":"Clothing And Fabric: Clothing: Clothing - Specialty",
    "sg:phone":"+64 7-834 9997",
    "sg:province":"Waikato",
    "wof:name":"Rangeen Collections Ltd",
    "wof:placetype":"venue"
},
  "geometry": {"coordinates":[-87.988968,34.142426],"type":"Point"}
}