{
  "type": "Feature",
  "properties": {
    "iso:country":"NZ",
    "sg:address":"481 Heads Rd ",
    "sg:city":"Wanganui",
    "sg:classifiers":[
        {
            "category":"Wholesale",
            "subcategory":"Auto Parts",
            "type":"Manufacturing & Wholesale Goods"
        }
    ],
    "sg:phone":"+64 6-344 4295",
    "sg:province":"Manawatu-Wanganui",
    "sg:tags":[
        "automotive",
        "supplies"
    ],
    "wof:name":"Wanganui Four x Four Centre",
    "wof:placetype":"venue"
},
  "geometry": {"coordinates":[174.997696,-39.943844],"type":"Point"}
}