{
  "type": "Feature",
  "properties": {
    "addr:full":"Waterfront Rd  Oamaru Otago",
    "addr:street":"Waterfront Rd",
    "iso:country":"NZ",
    "sg:address":"Waterfront Rd ",
    "sg:city":"Oamaru",
    "sg:classifiers":[
        {
            "category":"Utilities",
            "subcategory":"Fuel Oil & Lpg",
            "type":"Services"
        }
    ],
    "sg:phone":"+64 3-433 1022",
    "sg:province":"Otago",
    "sg:tags":[
        "petrol",
        "energy",
        "industrial",
        "utilities"
    ],
    "wof:name":"McKeown And Graham Ltd",
    "wof:placetype":"venue"
},
  "geometry": {"coordinates":[170.970932,-45.107555],"type":"Point"}
}