{
  "type": "Feature",
  "properties": {
    "addr:full":"Wellington, Porirua, Upper Hutt, Lower  Hutt Wellington",
    "iso:country":"NZ",
    "sg:address":"Wellington, Porirua, Upper Hutt, Lower ",
    "sg:city":"Hutt",
    "sg:classifiers":[
        {
            "category":"Autos & Motor Vehicles",
            "subcategory":"Automobile Sales",
            "type":"Retail Goods"
        }
    ],
    "sg:province":"Wellington",
    "sg:tags":[
        "automotive"
    ],
    "sg:website":"http://www.yellowpages.co.nz/pages/206118938/dp59975.html",
    "wof:name":"PartsWorld",
    "wof:placetype":"venue"
},
  "geometry": {"coordinates":[174.90838600000001,-41.206631],"type":"Point"}
}