{
  "type": "Feature",
  "properties": {
    "addr:full":"59 Awapuni Rd  Gisborne Manawatu-Wanganui",
    "addr:housenumber":"59",
    "addr:street":"Awapuni Rd",
    "iso:country":"NZ",
    "sg:address":"59 Awapuni Rd ",
    "sg:city":"Gisborne",
    "sg:orig_category":"Industrial: Services: Specialist Services: Laboratories",
    "sg:phone":"+64 6-863 0434",
    "sg:province":"Manawatu-Wanganui",
    "wof:name":"Hydro Technologies Ltd",
    "wof:placetype":"venue"
},
  "geometry": {"coordinates":[177.998932,-38.669556],"type":"Point"}
}