{
  "type": "Feature",
  "properties": {
    "iso:country":"NZ",
    "sg:address":"Level 7, 203-209 Willis St ",
    "sg:city":"Wellington",
    "sg:classifiers":[
        {
            "category":"Health Services",
            "subcategory":"Hospital",
            "type":"Services"
        }
    ],
    "sg:phone":"+64 4-384 4349",
    "sg:province":"Wellington",
    "sg:tags":[
        "medical",
        "beauty"
    ],
    "wof:name":"Family Planning Association (FPA)",
    "wof:placetype":"venue"
},
  "geometry": {"coordinates":[-104.999298,40.70546],"type":"Point"}
}