{
  "type": "Feature",
  "properties": {
    "addr:full":"cnr Cameron Rd & Sixteenth Ave  Tauranga Bay of Plenty",
    "addr:street":"Cnr Cameron Rd & Sixteenth Ave",
    "iso:country":"NZ",
    "sg:address":"cnr Cameron Rd & Sixteenth Ave ",
    "sg:city":"Tauranga",
    "sg:classifiers":[
        {
            "category":"Retail",
            "subcategory":"Laundry & Dry Cleaning",
            "type":"Services"
        }
    ],
    "sg:phone":"+64 7-578 7219",
    "sg:province":"Bay of Plenty",
    "sg:tags":[
        "repair",
        "clothing",
        "fabric",
        "cleaner"
    ],
    "wof:name":"Tauranga Dry Cleaners",
    "wof:placetype":"venue"
},
  "geometry": {"coordinates":[176.14475999999999,-37.703152],"type":"Point"}
}