{
  "type": "Feature",
  "properties": {
    "addr:full":"139 Randwick Rd Moera  Wellington Wellington",
    "addr:housenumber":"139",
    "addr:street":"Randwick Rd",
    "iso:country":"NZ",
    "sg:address":"139 Randwick Rd Moera ",
    "sg:city":"Wellington",
    "sg:classifiers":[
        {
            "category":"Sports & Exercise",
            "subcategory":"Tennis Court",
            "type":"Entertainment"
        }
    ],
    "sg:phone":"+64 4-939 7900",
    "sg:province":"Wellington",
    "sg:tags":[
        "escort",
        "agency",
        "adult",
        "leisure"
    ],
    "wof:name":"Body & Soul",
    "wof:placetype":"venue"
},
  "geometry": {"coordinates":[174.90562399999999,-41.22625],"type":"Point"}
}