{
  "type": "Feature",
  "properties": {
    "addr:full":"644 Colombo St  Christchurch Canterbury",
    "addr:housenumber":"644",
    "addr:street":"Colombo St",
    "iso:country":"NZ",
    "sg:address":"644 Colombo St ",
    "sg:city":"Christchurch",
    "sg:classifiers":[
        {
            "category":"Shopping",
            "subcategory":"Crafts & Fabrics",
            "type":"Retail Goods"
        }
    ],
    "sg:phone":"+64 3-366 1095",
    "sg:province":"Canterbury",
    "sg:tags":[
        "clothing"
    ],
    "sg:website":"http://www.lorenzo.co.nz",
    "wof:name":"Lorenzo Uomo",
    "wof:placetype":"venue"
},
  "geometry": {"coordinates":[172.63677999999999,-43.534756],"type":"Point"}
}