{
  "type": "Feature",
  "properties": {
    "addr:full":"15 Morningside Dve Morningside  Auckland Auckland",
    "addr:housenumber":"15",
    "addr:street":"Morningside Dve",
    "iso:country":"NZ",
    "sg:address":"15 Morningside Dve Morningside ",
    "sg:city":"Auckland",
    "sg:classifiers":[
        {
            "category":"Professional",
            "subcategory":"Art Services",
            "type":"Services"
        }
    ],
    "sg:phone":"+64 9-845 5616",
    "sg:province":"Auckland",
    "sg:tags":[
        "theatrical",
        "arts",
        "sport",
        "leisure"
    ],
    "sg:website":"http://www.lightsup.co.nz",
    "wof:name":"Lighting Supply Co Ltd",
    "wof:placetype":"venue"
},
  "geometry": {"coordinates":[174.732697,-36.878799],"type":"Point"}
}