{
  "type": "Feature",
  "properties": {
    "iso:country":"NZ",
    "sg:address":"PO Box 109430 Newmarket ",
    "sg:city":"Auckland",
    "sg:orig_category":"Clothing And Fabric: Fabric: Textiles",
    "sg:phone":"+64 9-309 4451",
    "sg:province":"Auckland",
    "wof:name":"one2one design Limited",
    "wof:placetype":"venue"
},
  "geometry": {"coordinates":[174.773758,-36.867878],"type":"Point"}
}