{
  "type": "Feature",
  "properties": {
    "iso:country":"NZ",
    "sg:address":"316 State Hwy 16 Huapai ",
    "sg:city":"Auckland",
    "sg:classifiers":[
        {
            "category":"Restaurant",
            "type":"Food & Drink"
        }
    ],
    "sg:phone":"+64 9-412 8644",
    "sg:province":"Auckland",
    "sg:tags":[
        "wining",
        "dining",
        "pizza"
    ],
    "wof:name":"Daddio's TAKE-N-BAKE",
    "wof:placetype":"venue"
},
  "geometry": {"coordinates":[174.77041600000001,-36.884109],"type":"Point"}
}