{
  "type": "Feature",
  "properties": {
    "iso:country":"NZ",
    "sg:address":"3/9 Allens Rd East Tamaki ",
    "sg:city":"Auckland",
    "sg:classifiers":[
        {
            "category":"Food & Beverages",
            "subcategory":"Meat & Fish",
            "type":"Retail Goods"
        }
    ],
    "sg:phone":"+64 9-274 2370",
    "sg:province":"Auckland",
    "sg:tags":[
        "drink"
    ],
    "wof:name":"IBEX Industries Limited",
    "wof:placetype":"venue"
},
  "geometry": {"coordinates":[174.89198300000001,-36.942917],"type":"Point"}
}