{
  "type": "Feature",
  "properties": {
    "iso:country":"NZ",
    "sg:address":"Unit B 5 Tarndale Gro Albany ",
    "sg:city":"Auckland",
    "sg:classifiers":[
        {
            "category":"Farming",
            "subcategory":"Fish & Marine Products",
            "type":"Manufacturing & Wholesale Goods"
        }
    ],
    "sg:phone":"+64 9-414 4430",
    "sg:province":"Auckland",
    "sg:tags":[
        "boats",
        "yacht",
        "transport",
        "boat",
        "supply"
    ],
    "wof:name":"Marine Specialties Ltd",
    "wof:placetype":"venue"
},
  "geometry": {"coordinates":[174.78736900000001,-36.825169],"type":"Point"}
}