{
  "type": "Feature",
  "properties": {
    "iso:country":"NZ",
    "sg:address":"32 Northumberland St ",
    "sg:city":"Tapanui",
    "sg:orig_category":"Food And Drink: Meats: Butchers",
    "sg:phone":"+64 3-204 8287",
    "wof:name":"Tapanui Butchery",
    "wof:placetype":"venue"
},
  "geometry": {"coordinates":[169.265137,-45.943466],"type":"Point"}
}