{
  "type": "Feature",
  "properties": {
    "addr:full":"Bonshaw Prk  Taupo Waikato",
    "iso:country":"NZ",
    "sg:address":"Bonshaw Prk ",
    "sg:city":"Taupo",
    "sg:orig_category":"Transport",
    "sg:phone":"+64 7-378 5609",
    "sg:province":"Waikato",
    "sg:website":"http://www.yellowpages.co.nz/for/taylorplanthire/dp27264.html",
    "wof:name":"Taylor Plant Hire Ltd",
    "wof:placetype":"venue"
},
  "geometry": {"coordinates":[176.08433500000001,-38.689281],"type":"Point"}
}