{
  "type": "Feature",
  "properties": {
    "addr:full":"22 Curley Rd Silverdale Hibiscus  Hibiscus Coast Auckland",
    "addr:housenumber":"22",
    "addr:street":"Curley Rd",
    "iso:country":"NZ",
    "sg:address":"22 Curley Rd Silverdale Hibiscus ",
    "sg:city":"Hibiscus Coast",
    "sg:classifiers":[
        {
            "category":"Retail",
            "subcategory":"Auto Repair",
            "type":"Services"
        }
    ],
    "sg:phone":"+64 9-426 5613",
    "sg:province":"Auckland",
    "sg:tags":[
        "automotive",
        "panel",
        "servicing",
        "beater"
    ],
    "wof:name":"Emerson Panelbeating (2002) Ltd",
    "wof:placetype":"venue"
},
  "geometry": {"coordinates":[174.67579699999999,-36.6208],"type":"Point"}
}