{
  "type": "Feature",
  "properties": {
    "addr:full":"681 Kaikorai Valley Rd Burnside  Dunedin Otago",
    "addr:housenumber":"681",
    "addr:street":"Kaikorai Valley Rd",
    "iso:country":"NZ",
    "sg:address":"681 Kaikorai Valley Rd Burnside ",
    "sg:city":"Dunedin",
    "sg:orig_category":"Automotive: Sales And Leasing: Trailers",
    "sg:phone":"+64 3-488 1360",
    "sg:province":"Otago",
    "wof:name":"Otago Trailers",
    "wof:placetype":"venue"
},
  "geometry": {"coordinates":[170.459518,-45.894634],"type":"Point"}
}