{
  "type": "Feature",
  "properties": {
    "iso:country":"NZ",
    "sg:address":"180 Tasman St Mt Cook ",
    "sg:city":"Wellington",
    "sg:classifiers":[
        {
            "category":"Health Services",
            "subcategory":"Health Practitioner",
            "type":"Services"
        }
    ],
    "sg:phone":"+64 4-384 8232",
    "sg:province":"Wellington",
    "sg:tags":[
        "services",
        "beauty",
        "acupuncturists"
    ],
    "wof:name":"Chinese Medicine & Herbal Clinic (1964)",
    "wof:placetype":"venue"
},
  "geometry": {"coordinates":[174.77610799999999,-41.306656],"type":"Point"}
}