{
  "type": "Feature",
  "properties": {
    "iso:country":"NZ",
    "sg:address":"Orders ",
    "sg:city":"Napier",
    "sg:orig_category":"Shopping: Retail Stores: Florist Accessories",
    "sg:phone":"+64 800 909 090",
    "sg:province":"Hawke's Bay",
    "wof:name":"Teleflora Orders",
    "wof:placetype":"venue"
},
  "geometry": {"coordinates":[-80.588562,38.790821],"type":"Point"}
}