{
  "type": "Feature",
  "properties": {
    "addr:full":"Federated Farmers Buliding 169 London St  Hamilton Waikato",
    "addr:housenumber":"169",
    "addr:street":"London St",
    "iso:country":"NZ",
    "sg:address":"Federated Farmers Buliding 169 London St ",
    "sg:city":"Hamilton",
    "sg:classifiers":[
        {
            "category":"Personal",
            "type":"Services"
        }
    ],
    "sg:phone":"+64 7-834 0220",
    "sg:province":"Waikato",
    "sg:tags":[
        "services",
        "home",
        "garden",
        "counselling"
    ],
    "sg:website":"http://www.nzac.org.nz",
    "wof:name":"NZ Association of Counsellors Inc",
    "wof:placetype":"venue"
},
  "geometry": {"coordinates":[175.276993,-37.783215],"type":"Point"}
}