{
  "type": "Feature",
  "properties": {
    "iso:country":"NZ",
    "sg:address":"T & G Building 15 Wellesley St W Auckland Central",
    "sg:city":"Auckland",
    "sg:classifiers":[
        {
            "category":"Manufacturing",
            "subcategory":"Textiles",
            "type":"Manufacturing & Wholesale Goods"
        }
    ],
    "sg:phone":"+64 9-309 9530",
    "sg:province":"Auckland",
    "sg:tags":[
        "clothing",
        "fabric",
        "manufacturer"
    ],
    "wof:name":"The Cutting Room",
    "wof:placetype":"venue"
},
  "geometry": {"coordinates":[174.764542,-36.848358],"type":"Point"}
}