{
  "type": "Feature",
  "properties": {
    "iso:country":"NZ",
    "sg:address":"318-324 Lambton Quay",
    "sg:city":"Wellington",
    "sg:classifiers":[
        {
            "category":"Banks & Credit Unions",
            "subcategory":"Bank",
            "type":"Services"
        }
    ],
    "sg:phone":"+64 4-498 1000",
    "sg:province":"Wellington",
    "wof:name":"Westpac Banking Co.",
    "wof:placetype":"venue"
},
  "geometry": {"coordinates":[174.77548200000001,-41.285027],"type":"Point"}
}