{
  "type": "Feature",
  "properties": {
    "iso:country":"NZ",
    "sg:address":"16 Portage Rd New Lynn ",
    "sg:city":"Auckland",
    "sg:orig_category":"Home And Garden: Furniture/Furnishings: Cabinetmakers",
    "sg:phone":"+64 9-827 0202",
    "sg:province":"Auckland",
    "sg:website":"http://www.yellowpages.co.nz/for/essexcabinetmakers/dp14780.html",
    "wof:name":"Comshape Technology Ltd",
    "wof:placetype":"venue"
},
  "geometry": {"coordinates":[174.690369,-36.905273],"type":"Point"}
}