{
  "type": "Feature",
  "properties": {
    "iso:country":"NZ",
    "sg:address":"8 Castle St ",
    "sg:city":"Eltham",
    "sg:orig_category":"Industrial: Metal: Stainless Steel",
    "sg:phone":"+64 6-764 8022",
    "wof:name":"Taranaki Stainless Ltd",
    "wof:placetype":"venue"
},
  "geometry": {"coordinates":[-76.82550000000001,37.524654],"type":"Point"}
}