{
  "type": "Feature",
  "properties": {
    "addr:full":"42 Connett Rd West Bell Block New  Plymouth Taranaki",
    "addr:housenumber":"42",
    "addr:street":"Connett Rd West",
    "iso:country":"NZ",
    "sg:address":"42 Connett Rd West Bell Block New ",
    "sg:city":"Plymouth",
    "sg:orig_category":"Industrial: Consultancy",
    "sg:phone":"+64 6-755 3077",
    "sg:province":"Taranaki",
    "wof:name":"NGC",
    "wof:placetype":"venue"
},
  "geometry": {"coordinates":[174.14274599999999,-39.032024],"type":"Point"}
}