{
  "type": "Feature",
  "properties": {
    "iso:country":"NZ",
    "sg:address":"D72 Building 72 Dominion Rd Mt Eden ",
    "sg:city":"Auckland",
    "sg:classifiers":[
        {
            "category":"Banks & Credit Unions",
            "subcategory":"Investment Brokerage",
            "type":"Services"
        }
    ],
    "sg:phone":"+64 9-623 8251",
    "sg:province":"Auckland",
    "sg:tags":[
        "television",
        "production",
        "broadcasting"
    ],
    "wof:name":"Satellite Media Group",
    "wof:placetype":"venue"
},
  "geometry": {"coordinates":[174.752777,-36.870937],"type":"Point"}
}