{
  "type": "Feature",
  "properties": {
    "addr:full":"309 Blenheim Rd Upper Riccarton  Christchurch Canterbury",
    "addr:housenumber":"309",
    "addr:street":"Blenheim Rd",
    "iso:country":"NZ",
    "sg:address":"309 Blenheim Rd Upper Riccarton ",
    "sg:city":"Christchurch",
    "sg:orig_category":"Industrial: Metal: Stainless Steel",
    "sg:phone":"+64 3-348 6023",
    "sg:province":"Canterbury",
    "wof:name":"Coombes Sheetmetal & Fabrication Ltd",
    "wof:placetype":"venue"
},
  "geometry": {"coordinates":[172.58171100000001,-43.538834],"type":"Point"}
}