{
  "type": "Feature",
  "properties": {
    "iso:country":"NZ",
    "sg:address":"Heaton St ",
    "sg:city":"Timaru",
    "sg:orig_category":"Storage: Storage",
    "sg:phone":"+64 3-684 3817",
    "sg:province":"Canterbury",
    "wof:name":"Heaton Street Lockups",
    "wof:placetype":"venue"
},
  "geometry": {"coordinates":[171.225845,-44.39608],"type":"Point"}
}