{
  "type": "Feature",
  "properties": {
    "addr:full":"36 A Hillside Rd Glenfield  Auckland Auckland",
    "addr:housenumber":"36 a",
    "addr:street":"Hillside Rd",
    "iso:country":"NZ",
    "sg:address":"36 A Hillside Rd Glenfield ",
    "sg:city":"Auckland",
    "sg:orig_category":"Industrial: Equipment And Machinery: Specialist Equipment: Machinery: Textile Machinery",
    "sg:phone":"+64 9-443 1100",
    "sg:province":"Auckland",
    "wof:name":"Marinco Textiles (NZ) Ltd",
    "wof:placetype":"venue"
},
  "geometry": {"coordinates":[174.73760999999999,-36.775337],"type":"Point"}
}