{
  "type": "Feature",
  "properties": {
    "iso:country":"NZ",
    "sg:address":"PO Box 38341 Te Puni Mail Centre Upper ",
    "sg:city":"Hutt",
    "sg:orig_category":"Industrial: Products: Filters And Filtration",
    "sg:phone":"+64 4-527 7088",
    "sg:province":"Wellington",
    "wof:name":"Filters Direct Wellington Ltd",
    "wof:placetype":"venue"
},
  "geometry": {"coordinates":[175.069031,-41.12458],"type":"Point"}
}