{
  "type": "Feature",
  "properties": {
    "iso:country":"NZ",
    "sg:address":"Kaipaki Rd R D 1 Ohaupo ",
    "sg:city":"Hamilton",
    "sg:orig_category":"Education And Training: General: Schools",
    "sg:phone":"+64 7-823 6653",
    "sg:province":"Waikato",
    "wof:name":"Kaipaki School",
    "wof:placetype":"venue"
},
  "geometry": {"coordinates":[175.305878,-37.9193],"type":"Point"}
}