{
  "type": "Feature",
  "properties": {
    "addr:full":"5 St Leonards Rd  Culverden",
    "addr:housenumber":"5",
    "addr:street":"St Leonards Rd",
    "iso:country":"NZ",
    "sg:address":"5 St Leonards Rd ",
    "sg:city":"Culverden",
    "sg:orig_category":"Farming: Services: Irrigation",
    "sg:phone":"+64 3-315 8303",
    "wof:name":"Balmoral Concrete",
    "wof:placetype":"venue"
},
  "geometry": {"coordinates":[172.98185699999999,-42.810043],"type":"Point"}
}