{
  "type": "Feature",
  "properties": {
    "addr:full":"33 Depot St  Rotorua Bay of Plenty",
    "addr:housenumber":"33",
    "addr:street":"Depot St",
    "iso:country":"NZ",
    "sg:address":"33 Depot St ",
    "sg:city":"Rotorua",
    "sg:orig_category":"Industrial: Engineering: Engineers: Engineers Supplies",
    "sg:phone":"+64 7-347 9848",
    "sg:province":"Bay of Plenty",
    "wof:name":"Total Trade Supplies Ltd",
    "wof:placetype":"venue"
},
  "geometry": {"coordinates":[176.23689300000001,-38.133942],"type":"Point"}
}