{
  "type": "Feature",
  "properties": {
    "iso:country":"NZ",
    "sg:address":"Cameron Rd Greerton ",
    "sg:city":"Tauranga",
    "sg:classifiers":[
        {
            "category":"Retail",
            "subcategory":"Laundry & Dry Cleaning",
            "type":"Services"
        }
    ],
    "sg:phone":"+64 7-578 6701",
    "sg:province":"Bay of Plenty",
    "sg:tags":[
        "repair",
        "clothing",
        "fabric",
        "cleaner"
    ],
    "wof:name":"West End Drycleaners",
    "wof:placetype":"venue"
},
  "geometry": {"coordinates":[176.135574,-37.722015],"type":"Point"}
}