{
  "type": "Feature",
  "properties": {
    "iso:country":"NZ",
    "sg:address":"15 Dunlop Rd ",
    "sg:city":"Napier",
    "sg:orig_category":"Transport: Transportation: Courier Services",
    "sg:phone":"+64 6-843 9493",
    "sg:province":"Hawke's Bay",
    "wof:name":"Post Haste Couriers",
    "wof:placetype":"venue"
},
  "geometry": {"coordinates":[-80.588562,38.790821],"type":"Point"}
}