{
  "type": "Feature",
  "properties": {
    "iso:country":"NZ",
    "sg:address":"Unit 2 14 Airborne Rd ",
    "sg:city":"Albany",
    "sg:orig_category":"Industrial: Products: Magnets",
    "sg:phone":"+64 800 766 737",
    "sg:province":"Auckland",
    "wof:name":"Body Magnetix Magnetic Underlays",
    "wof:placetype":"venue"
},
  "geometry": {"coordinates":[-71.215576,43.939495],"type":"Point"}
}