{
  "type": "Feature",
  "properties": {
    "addr:full":"Hokitika Airport  Hokitika West Coast",
    "iso:country":"NZ",
    "sg:address":"Hokitika Airport ",
    "sg:city":"Hokitika",
    "sg:orig_category":"Transport: Air",
    "sg:phone":"+64 3-755 8118",
    "sg:province":"West Coast",
    "sg:website":"http://www.yellowpages.co.nz/for/wildernesswings/dp25244.html",
    "wof:name":"Wilderness Wings Ltd",
    "wof:placetype":"venue"
},
  "geometry": {"coordinates":[170.989136,-42.7141],"type":"Point"}
}