{
  "type": "Feature",
  "properties": {
    "addr:full":"Wellington/Wairarapa  Carterton",
    "iso:country":"NZ",
    "sg:address":"Wellington/Wairarapa ",
    "sg:city":"Carterton",
    "sg:classifiers":[
        {
            "category":"Banks & Credit Unions",
            "subcategory":"Financial Services",
            "type":"Services"
        }
    ],
    "sg:phone":"+64 6-379 6693",
    "sg:tags":[
        "personal",
        "loan",
        "-",
        "finance",
        "mortgage"
    ],
    "wof:name":"Umbrella Financial Services",
    "wof:placetype":"venue"
},
  "geometry": {"coordinates":[175.523819,-41.02393],"type":"Point"}
}