{
  "type": "Feature",
  "properties": {
    "addr:full":"PO Box 51776  Pakuranga Auckland",
    "addr:housenumber":"po box",
    "addr:postcode":"51776",
    "iso:country":"NZ",
    "sg:address":"PO Box 51776 ",
    "sg:city":"Pakuranga",
    "sg:classifiers":[
        {
            "category":"Home & Garden",
            "subcategory":"Building Materials",
            "type":"Retail Goods"
        }
    ],
    "sg:phone":"+64 9-534 8860",
    "sg:province":"Auckland",
    "sg:tags":[
        "brick",
        "outdoor",
        "paving"
    ],
    "wof:name":"Abrahams Paving Ltd",
    "wof:placetype":"venue"
},
  "geometry": {"coordinates":[174.892807,-36.901218],"type":"Point"}
}