{
  "type": "Feature",
  "properties": {
    "iso:country":"NZ",
    "sg:address":"69 Carnavon St ",
    "sg:city":"Gisborne",
    "sg:classifiers":[
        {
            "category":"Retail",
            "subcategory":"Auto Repair",
            "type":"Services"
        }
    ],
    "sg:phone":"+64 6-868 1938",
    "sg:province":"Gisborne",
    "sg:tags":[
        "automotive",
        "servicing"
    ],
    "wof:name":"AA Auto Service",
    "wof:placetype":"venue"
},
  "geometry": {"coordinates":[178.019608,-38.66069],"type":"Point"}
}