{
  "type": "Feature",
  "properties": {
    "addr:full":"Motupiko  Tapawera",
    "iso:country":"NZ",
    "sg:address":"Motupiko ",
    "sg:city":"Tapawera",
    "sg:classifiers":[
        {
            "category":"Personal",
            "subcategory":"Massage",
            "type":"Services"
        }
    ],
    "sg:phone":"+64 3-522 4260",
    "sg:tags":[
        "services",
        "health",
        "-",
        "beauty",
        "fitness"
    ],
    "wof:name":"Sheila Kennard",
    "wof:placetype":"venue"
},
  "geometry": {"coordinates":[172.81926000000001,-41.453129],"type":"Point"}
}