{
  "type": "Feature",
  "properties": {
    "iso:country":"NZ",
    "sg:address":"1 Kent Lodge Ave Avonhead ",
    "sg:city":"Christchurch",
    "sg:orig_category":"Clothing And Fabric: Clothing: Dressmakers",
    "sg:phone":"+64 3-342 4442",
    "sg:province":"Canterbury",
    "wof:name":"Teresa Morrison Dressmaking & Alterations",
    "wof:placetype":"venue"
},
  "geometry": {"coordinates":[172.54844700000001,-43.523808],"type":"Point"}
}