{
  "type": "Feature",
  "properties": {
    "addr:full":"Green Bay 56d Godley Rd Auckland Auckland",
    "addr:housenumber":"56d",
    "addr:street":"Green Bay;Godley Rd",
    "iso:country":"NZ",
    "sg:address":"Green Bay 56d Godley Rd",
    "sg:city":"Auckland",
    "sg:classifiers":[
        {
            "category":"Banks & Credit Unions",
            "subcategory":"Bank",
            "type":"Services"
        }
    ],
    "sg:phone":"+64 9873235",
    "sg:province":"Auckland",
    "wof:name":"ASB Bank",
    "wof:placetype":"venue"
},
  "geometry": {"coordinates":[174.77041600000001,-36.884109],"type":"Point"}
}