{
  "type": "Feature",
  "properties": {
    "iso:country":"NZ",
    "sg:address":"92-96 Main Rd PO Box 51-031 ",
    "sg:city":"Tawa",
    "sg:orig_category":"Industrial: Engineering: Engineers - Steam",
    "sg:phone":"+64 800 772 182",
    "sg:province":"Wellington",
    "wof:name":"Aquaheat Industries Ltd",
    "wof:placetype":"venue"
},
  "geometry": {"coordinates":[-84.027679,40.237774],"type":"Point"}
}