{
  "type": "Feature",
  "properties": {
    "addr:full":"23 Queen St  Masterton Wellington",
    "addr:housenumber":"23",
    "addr:street":"Queen St",
    "iso:country":"NZ",
    "sg:address":"23 Queen St ",
    "sg:city":"Masterton",
    "sg:classifiers":[
        {
            "category":"Sports & Exercise",
            "subcategory":"Ski Resort",
            "type":"Entertainment"
        }
    ],
    "sg:phone":"+64 6-377 4697",
    "sg:province":"Wellington",
    "sg:tags":[
        "hobbies",
        "photographic",
        "leisure",
        "developing"
    ],
    "wof:name":"Wairarapa Camera Services Ltd",
    "wof:placetype":"venue"
},
  "geometry": {"coordinates":[175.664062,-40.948479],"type":"Point"}
}