{
  "type": "Feature",
  "properties": {
    "iso:country":"NZ",
    "sg:address":"619 Main St Palmerston ",
    "sg:city":"Palmerston North",
    "sg:classifiers":[
        {
            "category":"Communications",
            "subcategory":"Radio Station",
            "type":"Services"
        }
    ],
    "sg:phone":"+64 6-350 3550",
    "sg:province":"Manawatu-Wanganui",
    "sg:tags":[
        "broadcasting"
    ],
    "wof:name":"Radio Network Central Limited",
    "wof:placetype":"venue"
},
  "geometry": {"coordinates":[175.615463,-40.354267],"type":"Point"}
}