{
  "type": "Feature",
  "properties": {
    "addr:full":"Farndon Rd RD 2 Hastings  Napier Hawke's Bay",
    "addr:street":"Farndon Rd Rd 2",
    "iso:country":"NZ",
    "sg:address":"Farndon Rd RD 2 Hastings ",
    "sg:city":"Napier",
    "sg:classifiers":[
        {
            "category":"Social Services",
            "subcategory":"Job Training",
            "type":"Services"
        }
    ],
    "sg:phone":"+64 6-870 0934",
    "sg:province":"Hawke's Bay",
    "sg:tags":[
        "education"
    ],
    "wof:name":"Hawkes Bay Security Officers Training Ctr",
    "wof:placetype":"venue"
},
  "geometry": {"coordinates":[-80.588562,38.790821],"type":"Point"}
}