{
  "type": "Feature",
  "properties": {
    "addr:full":"65 Hillside Rd Glenfield  Auckland Auckland",
    "addr:housenumber":"65",
    "addr:street":"Hillside Rd",
    "iso:country":"NZ",
    "sg:address":"65 Hillside Rd Glenfield ",
    "sg:city":"Auckland",
    "sg:classifiers":[
        {
            "category":"Bars & Pubs",
            "type":"Food & Drink"
        }
    ],
    "sg:phone":"+64 9-441 6474",
    "sg:province":"Auckland",
    "sg:website":"http://www.deliimports.co.nz",
    "wof:name":"Southpoint Imports Ltd",
    "wof:placetype":"venue"
},
  "geometry": {"coordinates":[174.73551900000001,-36.776112],"type":"Point"}
}