{
  "type": "Feature",
  "properties": {
    "iso:country":"NZ",
    "sg:address":"65 Hillside Rd Glenfield ",
    "sg:city":"Auckland",
    "sg:classifiers":[
        {
            "category":"Bars & Pubs",
            "type":"Food & Drink"
        }
    ],
    "sg:phone":"+64 9-441 6474",
    "sg:province":"Auckland",
    "sg:website":"http://www.deliimports.co.nz",
    "wof:name":"Southpoint Imports Ltd",
    "wof:placetype":"venue"
},
  "geometry": {"coordinates":[174.735519,-36.776112],"type":"Point"}
}