{
  "type": "Feature",
  "properties": {
    "addr:full":"775 b Cameron Rd  Tauranga Bay of Plenty",
    "addr:housenumber":"775 b",
    "addr:street":"Cameron Rd",
    "iso:country":"NZ",
    "sg:address":"775 b Cameron Rd ",
    "sg:city":"Tauranga",
    "sg:classifiers":[
        {
            "category":"Arena",
            "subcategory":"Sports Club",
            "type":"Entertainment"
        }
    ],
    "sg:phone":"+64 7-571 6772",
    "sg:province":"Bay of Plenty",
    "sg:tags":[
        "-",
        "leisure",
        "sports"
    ],
    "wof:name":"Coastal Sports Club Inc",
    "wof:placetype":"venue"
},
  "geometry": {"coordinates":[176.15202300000001,-37.705589],"type":"Point"}
}