{
  "type": "Feature",
  "properties": {
    "addr:full":"794 Pironga Rd R D 6 Te  Awamutu Waikato",
    "addr:housenumber":"794;6",
    "addr:street":"Pironga Rd R D",
    "iso:country":"NZ",
    "sg:address":"794 Pironga Rd R D 6 Te ",
    "sg:city":"Awamutu",
    "sg:orig_category":"Home And Garden: Gardening: Products: Fertilisers",
    "sg:phone":"+64 7-871 9080",
    "sg:province":"Waikato",
    "wof:name":"Gro Worm Vermiculture",
    "wof:placetype":"venue"
},
  "geometry": {"coordinates":[175.319244,-38.009647],"type":"Point"}
}