{
  "type": "Feature",
  "properties": {
    "addr:full":"159 A Scenic Dve Titirangi  Auckland Auckland",
    "addr:housenumber":"159 a",
    "addr:street":"Dve",
    "iso:country":"NZ",
    "sg:address":"159 A Scenic Dve Titirangi ",
    "sg:city":"Auckland",
    "sg:classifiers":[
        {
            "category":"Home & Garden",
            "subcategory":"Garden Supply",
            "type":"Retail Goods"
        }
    ],
    "sg:phone":"+64 9-817 3498",
    "sg:province":"Auckland",
    "sg:tags":[
        "products",
        "nursery",
        "gardening"
    ],
    "wof:name":"Gordons Native Plant Nurseries",
    "wof:placetype":"venue"
},
  "geometry": {"coordinates":[174.66279599999999,-36.926861],"type":"Point"}
}