{
  "type": "Feature",
  "properties": {
    "iso:country":"NZ",
    "sg:address":"429 Wellington Rd ",
    "sg:city":"Marton",
    "sg:classifiers":[
        {
            "category":"Fast Food",
            "type":"Food & Drink"
        }
    ],
    "sg:phone":"+64 6-327 6627",
    "sg:tags":[
        "wining",
        "dining",
        "takeaway"
    ],
    "wof:name":"Pats Takeaways",
    "wof:placetype":"venue"
},
  "geometry": {"coordinates":[-3.01544,53.799294],"type":"Point"}
}