{
  "type": "Feature",
  "properties": {
    "iso:country":"NZ",
    "sg:address":"Tram Valley Rd Swanson ",
    "sg:city":"Auckland",
    "sg:classifiers":[
        {
            "category":"Coffee & Tea",
            "type":"Food & Drink"
        }
    ],
    "sg:phone":"+64 9-833 4195",
    "sg:province":"Auckland",
    "sg:tags":[
        "merchant"
    ],
    "wof:name":"Executive Vending",
    "wof:placetype":"venue"
},
  "geometry": {"coordinates":[174.569931,-36.87051],"type":"Point"}
}