{
  "type": "Feature",
  "properties": {
    "iso:country":"NZ",
    "sg:address":"223 Middleton Rd Corstorphine ",
    "sg:city":"Dunedin",
    "sg:classifiers":[
        {
            "category":"Fast Food",
            "type":"Food & Drink"
        }
    ],
    "sg:phone":"+64 3-487 6432",
    "sg:province":"Otago",
    "sg:tags":[
        "wining",
        "dining",
        "takeaway"
    ],
    "wof:name":"Cookies Takeaways",
    "wof:placetype":"venue"
},
  "geometry": {"coordinates":[170.471649,-45.909092],"type":"Point"}
}