{
  "type": "Feature",
  "properties": {
    "addr:full":"Maunu Rd  Whangarei Northland",
    "addr:street":"Maunu Rd",
    "iso:country":"NZ",
    "sg:address":"Maunu Rd ",
    "sg:city":"Whangarei",
    "sg:classifiers":[
        {
            "category":"Manufacturing",
            "subcategory":"Glass & Minerals",
            "type":"Manufacturing & Wholesale Goods"
        }
    ],
    "sg:phone":"+64 9-438 1501",
    "sg:province":"Northland",
    "sg:tags":[
        "raw",
        "industrial",
        "quarry",
        "materials"
    ],
    "wof:name":"Brocks Western Hills Quarry",
    "wof:placetype":"venue"
},
  "geometry": {"coordinates":[174.279449,-35.73909],"type":"Point"}
}