{
  "type": "Feature",
  "properties": {
    "addr:full":"Te Atatu Peninsula  Auckland Auckland",
    "iso:country":"NZ",
    "sg:address":"Te Atatu Peninsula ",
    "sg:city":"Auckland",
    "sg:orig_category":"Sports And Leisure: Entertainment: Musicians",
    "sg:phone":"+64 9-834 4909",
    "sg:province":"Auckland",
    "wof:name":"Pianist - Mark",
    "wof:placetype":"venue"
},
  "geometry": {"coordinates":[174.65112300000001,-36.841228],"type":"Point"}
}