{
  "type": "Feature",
  "properties": {
    "addr:full":"345 Great North Rd Henderson  Auckland Auckland",
    "addr:housenumber":"345",
    "addr:street":"Great North Rd",
    "iso:country":"NZ",
    "sg:address":"345 Great North Rd Henderson ",
    "sg:city":"Auckland",
    "sg:orig_category":"Shopping: Retail Stores: Secondhand Dealers",
    "sg:phone":"+64 9-838 3969",
    "sg:province":"Auckland",
    "wof:name":"Smilies Second Hand Shop",
    "wof:placetype":"venue"
},
  "geometry": {"coordinates":[174.63385,-36.879547],"type":"Point"}
}