{
  "type": "Feature",
  "properties": {
    "iso:country":"NZ",
    "sg:address":"3/3 Hugh Brown Dve New Lynn ",
    "sg:city":"Auckland",
    "sg:classifiers":[
        {
            "category":"Personal",
            "subcategory":"Beauty Salon",
            "type":"Services"
        }
    ],
    "sg:phone":"+64 9-629 3327",
    "sg:province":"Auckland",
    "sg:tags":[
        "yoga",
        "health",
        "fitness"
    ],
    "wof:name":"Yoga Workshop Auckland",
    "wof:placetype":"venue"
},
  "geometry": {"coordinates":[174.68222,-36.907242],"type":"Point"}
}