{
  "type": "Feature",
  "properties": {
    "iso:country":"NZ",
    "sg:address":"30 Tamamutu St ",
    "sg:city":"Taupo",
    "sg:classifiers":[
        {
            "category":"Manufacturing",
            "subcategory":"Rubber & Plastics",
            "type":"Manufacturing & Wholesale Goods"
        }
    ],
    "sg:phone":"+64 7-376 8461",
    "sg:province":"Waikato",
    "sg:tags":[
        "industrial",
        "goods"
    ],
    "wof:name":"Plastic Box",
    "wof:placetype":"venue"
},
  "geometry": {"coordinates":[176.07164,-38.68586],"type":"Point"}
}