{
  "type": "Feature",
  "properties": {
    "addr:full":"8 Aranui Rd  Mapua Auckland",
    "addr:housenumber":"8",
    "addr:street":"Aranui Rd",
    "iso:country":"NZ",
    "sg:address":"8 Aranui Rd ",
    "sg:city":"Mapua",
    "sg:classifiers":[
        {
            "category":"Home & Garden",
            "subcategory":"Garden Supply",
            "type":"Retail Goods"
        }
    ],
    "sg:phone":"+64 3-540 3557",
    "sg:province":"Auckland",
    "sg:tags":[
        "aquarium",
        "pets"
    ],
    "wof:name":"Touch The Sea Aquarium & Gift Shop",
    "wof:placetype":"venue"
},
  "geometry": {"coordinates":[173.101089,-41.256508],"type":"Point"}
}