{
  "type": "Feature",
  "properties": {
    "iso:country":"NZ",
    "sg:address":"118 Raumanga Valley Rd ",
    "sg:city":"Whangarei",
    "sg:orig_category":"Shopping: Retail Stores: Florists",
    "sg:phone":"+64 9-438 8568",
    "sg:province":"Northland",
    "wof:name":"Marlene Florist",
    "wof:placetype":"venue"
},
  "geometry": {"coordinates":[174.299744,-35.740196],"type":"Point"}
}