{
  "type": "Feature",
  "properties": {
    "addr:full":"347 North Rd North East Valley  Dunedin Otago",
    "addr:housenumber":"347",
    "addr:street":"North Rd",
    "iso:country":"NZ",
    "sg:address":"347 North Rd North East Valley ",
    "sg:city":"Dunedin",
    "sg:orig_category":"Shopping: Gifts",
    "sg:phone":"+64 3-473 0124",
    "sg:province":"Otago",
    "wof:name":"CKI Ltd",
    "wof:placetype":"venue"
},
  "geometry": {"coordinates":[170.53540000000001,-45.846703],"type":"Point"}
}