{
  "type": "Feature",
  "properties": {
    "iso:country":"NZ",
    "sg:address":"12 Puhinui Rd Manukau City ",
    "sg:city":"Auckland",
    "sg:classifiers":[
        {
            "category":"Education",
            "subcategory":"Special Training",
            "type":"Public Place"
        }
    ],
    "sg:phone":"+64 9-277 6888",
    "sg:province":"Auckland",
    "sg:tags":[
        "charter",
        "shopping",
        "dive",
        "tuition",
        "water",
        "sports",
        "retailers",
        "sport"
    ],
    "wof:name":"Adventure Education",
    "wof:placetype":"venue"
},
  "geometry": {"coordinates":[174.876419,-36.982121],"type":"Point"}
}