{
  "type": "Feature",
  "properties": {
    "addr:full":"115 Carnarvon St  Gisborne Gisborne",
    "addr:housenumber":"115",
    "addr:street":"Carnarvon St",
    "iso:country":"NZ",
    "sg:address":"115 Carnarvon St ",
    "sg:city":"Gisborne",
    "sg:classifiers":[
        {
            "category":"Building & Trades",
            "subcategory":"Cleaning & Sanitation",
            "type":"Services"
        }
    ],
    "sg:phone":"+64 6-867 2898",
    "sg:province":"Gisborne",
    "sg:tags":[
        "equipment",
        "industrial",
        "maintenance"
    ],
    "wof:name":"CleanCare Supplies",
    "wof:placetype":"venue"
},
  "geometry": {"coordinates":[178.01812699999999,-38.66193],"type":"Point"}
}