{
  "type": "Feature",
  "properties": {
    "iso:country":"NZ",
    "sg:address":"Tait Dve Greenmeadows ",
    "sg:city":"Napier",
    "sg:classifiers":[
        {
            "category":"Education",
            "subcategory":"Music School",
            "type":"Public Place"
        }
    ],
    "sg:phone":"+64 6-845 2464",
    "sg:province":"Hawke's Bay",
    "sg:tags":[
        "sport",
        "teacher",
        "leisure"
    ],
    "wof:name":"Technics Music Academy",
    "wof:placetype":"venue"
},
  "geometry": {"coordinates":[176.856247,-39.520939],"type":"Point"}
}