{
  "type": "Feature",
  "properties": {
    "iso:country":"NZ",
    "sg:address":"44 Florance Ave ",
    "sg:city":"Russell",
    "sg:classifiers":[
        {
            "category":"Home & Garden",
            "subcategory":"Carpets & Floor Coverings",
            "type":"Retail Goods"
        }
    ],
    "sg:phone":"+64 9-403 8525",
    "sg:tags":[
        "cleaning",
        "furniture"
    ],
    "wof:name":"Murray Williams Carpet Cleaning",
    "wof:placetype":"venue"
},
  "geometry": {"coordinates":[-91.508163,35.362637],"type":"Point"}
}