{
  "type": "Feature",
  "properties": {
    "iso:country":"NZ",
    "sg:address":"87 Te Mata Rd Havelock North ",
    "sg:city":"Hastings",
    "sg:classifiers":[
        {
            "category":"Farming",
            "subcategory":"Fish & Marine Products",
            "type":"Manufacturing & Wholesale Goods"
        }
    ],
    "sg:phone":"+64 6-877 8193",
    "sg:province":"Hawke's Bay",
    "sg:tags":[
        "health",
        "beauty"
    ],
    "sg:website":"http://www.ps.org.nz/eastcoast",
    "wof:name":"Presbyterian Support (East Coast)",
    "wof:placetype":"venue"
},
  "geometry": {"coordinates":[176.887756,-39.666054],"type":"Point"}
}