{
  "type": "Feature",
  "properties": {
    "iso:country":"NZ",
    "sg:address":"87 Stanmore Rd Linwood ",
    "sg:city":"Christchurch",
    "sg:classifiers":[
        {
            "category":"Shopping",
            "subcategory":"Thrift Store",
            "type":"Retail Goods"
        }
    ],
    "sg:phone":"+64 3-389 5501",
    "sg:province":"Canterbury",
    "sg:tags":[
        "-",
        "clothing",
        "secondhand",
        "fabric"
    ],
    "wof:name":"Miss Fitz",
    "wof:placetype":"venue"
},
  "geometry": {"coordinates":[172.65692100000001,-43.53104],"type":"Point"}
}