{
  "type": "Feature",
  "properties": {
    "iso:country":"NZ",
    "sg:address":"1 Buchanan Rd Hikurangi ",
    "sg:city":"Whangarei",
    "sg:classifiers":[
        {
            "category":"Arts & Performance",
            "subcategory":"Music",
            "type":"Entertainment"
        }
    ],
    "sg:phone":"+64 9-433 7207",
    "sg:province":"Northland",
    "sg:tags":[
        "mobile",
        "sport",
        "-",
        "leisure",
        "disco"
    ],
    "wof:name":"N.Trance Mobile Disco",
    "wof:placetype":"venue"
},
  "geometry": {"coordinates":[174.28599500000001,-35.596409],"type":"Point"}
}