{
  "type": "Feature",
  "properties": {
    "iso:country":"NZ",
    "sg:address":"23 Southbrook Rd ",
    "sg:city":"Rangiora",
    "sg:orig_category":"Farming: Supplies",
    "sg:phone":"+64 3-313 6221",
    "sg:province":"Canterbury",
    "wof:name":"Weston Animal Nutrition",
    "wof:placetype":"venue"
},
  "geometry": {"coordinates":[172.598038,-43.323063],"type":"Point"}
}