{
  "type": "Feature",
  "properties": {
    "addr:full":"Hinemoa St  Rotorua Bay of Plenty",
    "addr:street":"Hinemoa St",
    "iso:country":"NZ",
    "sg:address":"Hinemoa St ",
    "sg:city":"Rotorua",
    "sg:classifiers":[
        {
            "category":"Travel",
            "subcategory":"Travel Agent",
            "type":"Entertainment"
        }
    ],
    "sg:phone":"+64 7-348 1328",
    "sg:province":"Bay of Plenty",
    "sg:tags":[
        "tour",
        "tourism",
        "sightseeing"
    ],
    "sg:website":"http://www.polynesianspa.co.nz",
    "wof:name":"Polynesian Spa",
    "wof:placetype":"venue"
},
  "geometry": {"coordinates":[176.25628699999999,-38.137856],"type":"Point"}
}