{
  "type": "Feature",
  "properties": {
    "iso:country":"NZ",
    "sg:address":"2 George St Tuakau ",
    "sg:city":"Pukekohe",
    "sg:orig_category":"Shopping: Retail Stores: Supermarkets",
    "sg:phone":"+64 9-236 8128",
    "sg:province":"Auckland",
    "wof:name":"Tuakau Discount Supermarket",
    "wof:placetype":"venue"
},
  "geometry": {"coordinates":[174.947006,-37.257229],"type":"Point"}
}