{
  "type": "Feature",
  "properties": {
    "addr:full":"19 Wellesley St Auckland Central  Auckland Auckland",
    "addr:housenumber":"19",
    "addr:street":"Wellesley St",
    "iso:country":"NZ",
    "sg:address":"19 Wellesley St Auckland Central ",
    "sg:city":"Auckland",
    "sg:classifiers":[
        {
            "category":"Retail",
            "subcategory":"Laundry & Dry Cleaning",
            "type":"Services"
        }
    ],
    "sg:phone":"+64 9-379 5470",
    "sg:province":"Auckland",
    "sg:tags":[
        "repair",
        "clothing",
        "fabric"
    ],
    "wof:name":"Vogue Drycleaning",
    "wof:placetype":"venue"
},
  "geometry": {"coordinates":[174.763397,-36.850422],"type":"Point"}
}