{
  "type": "Feature",
  "properties": {
    "addr:full":"Blueskin Bay  Dunedin Otago",
    "addr:street":"Blueskin",
    "iso:country":"NZ",
    "sg:address":"Blueskin Bay ",
    "sg:city":"Dunedin",
    "sg:classifiers":[
        {
            "category":"Social Services",
            "subcategory":"Retirement Home",
            "type":"Services"
        }
    ],
    "sg:phone":"+64 3-482 2842",
    "sg:province":"Otago",
    "sg:tags":[
        "elderly",
        "convalescent",
        "garden",
        "rest",
        "care"
    ],
    "wof:name":"Ashwood Valley Home",
    "wof:placetype":"venue"
},
  "geometry": {"coordinates":[170.53454600000001,-45.894531],"type":"Point"}
}