{
  "type": "Feature",
  "properties": {
    "iso:country":"NZ",
    "sg:address":"264 Neilson St Onehunga ",
    "sg:city":"Auckland",
    "sg:classifiers":[
        {
            "category":"Wholesale",
            "subcategory":"Electrical",
            "type":"Manufacturing & Wholesale Goods"
        }
    ],
    "sg:phone":"+64 9-636 9891",
    "sg:province":"Auckland",
    "sg:tags":[
        "wire",
        "electrical/electronic",
        "industrial",
        "electric",
        "cable"
    ],
    "wof:name":"Associated Insulation Materials Ltd",
    "wof:placetype":"venue"
},
  "geometry": {"coordinates":[174.79257200000001,-36.9263],"type":"Point"}
}