{
  "type": "Feature",
  "properties": {
    "addr:full":"Cambridge St  Putaruru",
    "addr:street":"Cambridge St",
    "iso:country":"NZ",
    "sg:address":"Cambridge St ",
    "sg:city":"Putaruru",
    "sg:classifiers":[
        {
            "category":"Health Services",
            "subcategory":"Dentist",
            "type":"Services"
        }
    ],
    "sg:phone":"+64 7-883 8713",
    "sg:tags":[
        "dental",
        "clinic",
        "beauty"
    ],
    "wof:name":"Cambridge Street School Dental Clinic",
    "wof:placetype":"venue"
},
  "geometry": {"coordinates":[175.781845,-38.04953],"type":"Point"}
}