{
  "type": "Feature",
  "properties": {
    "iso:country":"NZ",
    "sg:address":"2 Church St ",
    "sg:city":"Masterton",
    "sg:classifiers":[
        {
            "category":"Banks & Credit Unions",
            "subcategory":"Investment Brokerage",
            "type":"Services"
        }
    ],
    "sg:phone":"+64 6-378 2694",
    "sg:province":"Wellington",
    "sg:tags":[
        "personal",
        "accountant",
        "chartered",
        "-",
        "finance"
    ],
    "wof:name":"Sexton John C",
    "wof:placetype":"venue"
},
  "geometry": {"coordinates":[175.661743,-40.949989],"type":"Point"}
}