{
  "type": "Feature",
  "properties": {
    "addr:full":"120 Bank St  Whangarei Northland",
    "addr:housenumber":"120",
    "addr:street":"Bank St",
    "iso:country":"NZ",
    "sg:address":"120 Bank St ",
    "sg:city":"Whangarei",
    "sg:classifiers":[
        {
            "category":"Banks & Credit Unions",
            "subcategory":"Financial Services",
            "type":"Services"
        }
    ],
    "sg:phone":"+64 9-438 9499",
    "sg:province":"Northland",
    "sg:tags":[
        "personal",
        "superannuation",
        "-",
        "finance"
    ],
    "wof:name":"Tower Financial Advisory Services",
    "wof:placetype":"venue"
},
  "geometry": {"coordinates":[174.32089199999999,-35.720989],"type":"Point"}
}