{
  "type": "Feature",
  "properties": {
    "iso:country":"NZ",
    "sg:address":"29 Broadway Papakura ",
    "sg:city":"Auckland",
    "sg:orig_category":"Shopping: Sports Retailers: Cycles",
    "sg:phone":"+64 9-298 7772",
    "sg:province":"Manawatu-Wanganui",
    "wof:name":"Broadway Cycles & Mowers",
    "wof:placetype":"venue"
},
  "geometry": {"coordinates":[174.944214,-37.06287],"type":"Point"}
}