{
  "type": "Feature",
  "properties": {
    "addr:full":"1st Floor 32 Lorne St Auckland Central  Auckland Auckland",
    "addr:housenumber":"32",
    "addr:street":"Lorne St",
    "iso:country":"NZ",
    "sg:address":"1st Floor 32 Lorne St Auckland Central ",
    "sg:city":"Auckland",
    "sg:classifiers":[
        {
            "category":"Arts & Performance",
            "subcategory":"Art Gallery",
            "type":"Entertainment"
        }
    ],
    "sg:phone":"+64 9-379 0588",
    "sg:province":"Auckland",
    "sg:tags":[
        "arts",
        "sport",
        "leisure"
    ],
    "wof:name":"Oedipus Rex Gallery",
    "wof:placetype":"venue"
},
  "geometry": {"coordinates":[174.765717,-36.850494],"type":"Point"}
}