{
  "type": "Feature",
  "properties": {
    "iso:country":"NZ",
    "sg:address":"51 Kenepuru Dve ",
    "sg:city":"Porirua",
    "sg:classifiers":[
        {
            "category":"Manufacturing",
            "subcategory":"Motor Vehicles & Parts",
            "type":"Manufacturing & Wholesale Goods"
        }
    ],
    "sg:phone":"+64 4-237 8279",
    "sg:province":"Wellington",
    "sg:tags":[
        "automotive",
        "steering",
        "supplies",
        "suspension"
    ],
    "wof:name":"The Shock Shop",
    "wof:placetype":"venue"
},
  "geometry": {"coordinates":[174.852234,-41.138294],"type":"Point"}
}