{
  "type": "Feature",
  "properties": {
    "addr:full":"205 Gracefield Rd Seaview Lower  Hutt Wellington",
    "addr:housenumber":"205",
    "addr:street":"Gracefield Rd",
    "iso:country":"NZ",
    "sg:address":"205 Gracefield Rd Seaview Lower ",
    "sg:city":"Hutt",
    "sg:orig_category":"Industrial: Energy And Utilities: Gas",
    "sg:phone":"+64 4-568 6142",
    "sg:province":"Wellington",
    "wof:name":"Air Liquide",
    "wof:placetype":"venue"
},
  "geometry": {"coordinates":[174.89956699999999,-41.246059],"type":"Point"}
}