{
  "type": "Feature",
  "properties": {
    "iso:country":"NZ",
    "sg:address":"420 Dee St ",
    "sg:city":"Invercargill",
    "sg:orig_category":"Shopping: Sports Retailers: Cycles",
    "sg:phone":"+64 3-218 8822",
    "sg:province":"Southland",
    "wof:name":"Gladstone Cycles",
    "wof:placetype":"venue"
},
  "geometry": {"coordinates":[168.346985,-46.39502],"type":"Point"}
}