{
  "type": "Feature",
  "properties": {
    "iso:country":"NZ",
    "sg:address":"Ph/Fax 22 a Perclo Pl ",
    "sg:city":"Hamilton",
    "sg:classifiers":[
        {
            "category":"Manufacturing",
            "subcategory":"Rubber & Plastics",
            "type":"Manufacturing & Wholesale Goods"
        }
    ],
    "sg:phone":"+64 7-850 5038",
    "sg:province":"Waikato",
    "sg:tags":[
        "industrial",
        "goods"
    ],
    "wof:name":"Plasenz Ltd",
    "wof:placetype":"venue"
},
  "geometry": {"coordinates":[-98.103645,31.700565],"type":"Point"}
}