{
  "type": "Feature",
  "properties": {
    "iso:country":"NZ",
    "sg:address":"634 Ferry Rd Woolston ",
    "sg:city":"Christchurch",
    "sg:classifiers":[
        {
            "category":"Sports & Exercise",
            "subcategory":"Race Track",
            "type":"Entertainment"
        }
    ],
    "sg:phone":"+64 3-384 4315",
    "sg:province":"Canterbury",
    "sg:tags":[
        "-",
        "leisure",
        "sports",
        "billiard",
        "table",
        "pool"
    ],
    "wof:name":"Woolley T D Ltd",
    "wof:placetype":"venue"
},
  "geometry": {"coordinates":[172.68362400000001,-43.549835],"type":"Point"}
}