{
  "type": "Feature",
  "properties": {
    "iso:country":"NZ",
    "sg:address":"6 Mt Eden Rd Eden Terrace ",
    "sg:city":"Auckland",
    "sg:orig_category":"Clothing And Fabric: Fabric: Textiles",
    "sg:phone":"+64 9-306 1580",
    "sg:province":"Auckland",
    "wof:name":"Unique Fabrics Ltd",
    "wof:placetype":"venue"
},
  "geometry": {"coordinates":[174.757095,-36.867268],"type":"Point"}
}