{
  "type": "Feature",
  "properties": {
    "addr:full":"6 Mt Eden Rd Eden Terrace  Auckland Auckland",
    "addr:housenumber":"6",
    "addr:street":"Mt Eden Rd Eden Terrace",
    "iso:country":"NZ",
    "sg:address":"6 Mt Eden Rd Eden Terrace ",
    "sg:city":"Auckland",
    "sg:orig_category":"Clothing And Fabric: Fabric: Textiles",
    "sg:phone":"+64 9-306 1580",
    "sg:province":"Auckland",
    "wof:name":"Unique Fabrics Ltd",
    "wof:placetype":"venue"
},
  "geometry": {"coordinates":[174.75709499999999,-36.867268],"type":"Point"}
}