{
  "type": "Feature",
  "properties": {
    "iso:country":"NZ",
    "sg:address":"Kindergarten House 74 Vivian St New ",
    "sg:city":"Plymouth",
    "sg:orig_category":"Home And Garden: Children",
    "sg:phone":"+64 6-759 7036",
    "sg:province":"Taranaki",
    "wof:name":"Kindergarten Association North Taranaki",
    "wof:placetype":"venue"
},
  "geometry": {"coordinates":[-116.819725,43.97221],"type":"Point"}
}