{
  "type": "Feature",
  "properties": {
    "iso:country":"NZ",
    "sg:address":"Empire St ",
    "sg:city":"Cambridge",
    "sg:orig_category":"Automotive: Parts And Supplies: Tyres",
    "sg:phone":"+64 7-827 5002",
    "sg:province":"Waikato",
    "wof:name":"Beaurepaires For Tyres",
    "wof:placetype":"venue"
},
  "geometry": {"coordinates":[-116.67604799999999,44.572186],"type":"Point"}
}