{
  "type": "Feature",
  "properties": {
    "iso:country":"NZ",
    "sg:address":"211 Papanui Rd Merivale ",
    "sg:city":"Christchurch",
    "sg:orig_category":"Shopping: Hobbies And Games: Handcrafts",
    "sg:phone":"+64 3-355 7026",
    "sg:province":"Canterbury",
    "wof:name":"Broomfields",
    "wof:placetype":"venue"
},
  "geometry": {"coordinates":[172.62149,-43.511818],"type":"Point"}
}