{
  "type": "Feature",
  "properties": {
    "iso:country":"NZ",
    "sg:address":"Shop 30 Centre City New ",
    "sg:city":"Plymouth",
    "sg:orig_category":"Clothing And Fabric: Clothing: Women'S Fashions",
    "sg:phone":"+64 6-759 4241",
    "sg:province":"Taranaki",
    "wof:name":"Zest",
    "wof:placetype":"venue"
},
  "geometry": {"coordinates":[-116.80023199999999,43.882797],"type":"Point"}
}