{
  "type": "Feature",
  "properties": {
    "iso:country":"NZ",
    "sg:address":"1173 Paerata Rd ",
    "sg:city":"Pukekohe",
    "sg:classifiers":[
        {
            "category":"Professional",
            "type":"Services"
        }
    ],
    "sg:phone":"+64 800 929 743",
    "sg:province":"Auckland",
    "sg:tags":[
        "food",
        "drink",
        "catering"
    ],
    "wof:name":"Quality Caterers Ltd",
    "wof:placetype":"venue"
},
  "geometry": {"coordinates":[174.930252,-37.195728],"type":"Point"}
}