{
  "type": "Feature",
  "properties": {
    "addr:full":"Manukau City Shopping Centre  Auckland Auckland",
    "iso:country":"NZ",
    "sg:address":"Manukau City Shopping Centre ",
    "sg:city":"Auckland",
    "sg:classifiers":[
        {
            "category":"Health Services",
            "subcategory":"Dentist",
            "type":"Services"
        }
    ],
    "sg:phone":"+64 9-262 1890",
    "sg:province":"Auckland",
    "sg:tags":[
        "dental",
        "beauty"
    ],
    "wof:name":"Geddes Dental Group",
    "wof:placetype":"venue"
},
  "geometry": {"coordinates":[174.88145399999999,-36.98967],"type":"Point"}
}