{
  "type": "Feature",
  "properties": {
    "addr:full":"77 Broadway  Matamata Manawatu-Wanganui",
    "addr:housenumber":"77",
    "addr:street":"Broadway",
    "iso:country":"NZ",
    "sg:address":"77 Broadway ",
    "sg:city":"Matamata",
    "sg:orig_category":"Shopping: Accessories: Jewellers And Watchmakers",
    "sg:phone":"+64 7-888 8879",
    "sg:province":"Manawatu-Wanganui",
    "wof:name":"Williams Jewellery",
    "wof:placetype":"venue"
},
  "geometry": {"coordinates":[175.77778599999999,-37.81144],"type":"Point"}
}