{
  "type": "Feature",
  "properties": {
    "iso:country":"NZ",
    "sg:address":"7 Oak St ",
    "sg:city":"Masterton",
    "sg:orig_category":"Farming: Agriculture: Agricultural Contractors",
    "sg:phone":"+64 6-377 5132",
    "sg:province":"Wellington",
    "wof:name":"Candy Contracts",
    "wof:placetype":"venue"
},
  "geometry": {"coordinates":[175.636642,-40.940205],"type":"Point"}
}