{
  "type": "Feature",
  "properties": {
    "addr:full":"131 Hanmer Springs Rd Hanmer  Springs",
    "addr:housenumber":"131",
    "addr:street":"Hanmer Springs Rd",
    "iso:country":"NZ",
    "sg:address":"131 Hanmer Springs Rd Hanmer ",
    "sg:city":"Springs",
    "sg:orig_category":"Sports And Leisure: Sports: Skiing",
    "sg:phone":"+64 800 888 308",
    "wof:name":"Hanmer Heliski & Heliboard",
    "wof:placetype":"venue"
},
  "geometry": {"coordinates":[172.811035,-42.544456],"type":"Point"}
}