{
  "type": "Feature",
  "properties": {
    "iso:country":"NZ",
    "sg:address":"25 b Herekino St ",
    "sg:city":"Whangarei",
    "sg:classifiers":[
        {
            "category":"Autos & Motor Vehicles",
            "subcategory":"Automobile Sales",
            "type":"Retail Goods"
        }
    ],
    "sg:phone":"+64 9-438 3037",
    "sg:province":"Northland",
    "sg:tags":[
        "home",
        "caravan",
        "leasing",
        "automotive"
    ],
    "wof:name":"Kitchen Trendz 2000 Limited",
    "wof:placetype":"venue"
},
  "geometry": {"coordinates":[174.328766,-35.728172],"type":"Point"}
}