{
  "type": "Feature",
  "properties": {
    "addr:full":"132 A Marua Rd Ellerslie  Auckland Auckland",
    "addr:housenumber":"132",
    "addr:street":"A Marua Rd",
    "iso:country":"NZ",
    "sg:address":"132 A Marua Rd Ellerslie ",
    "sg:city":"Auckland",
    "sg:classifiers":[
        {
            "category":"Food & Beverages",
            "subcategory":"Meat & Fish",
            "type":"Retail Goods"
        }
    ],
    "sg:phone":"+64 9-525 8030",
    "sg:province":"Auckland",
    "sg:tags":[
        "drink"
    ],
    "wof:name":"Columbit (New Zealand) Ltd",
    "wof:placetype":"venue"
},
  "geometry": {"coordinates":[174.825424,-36.892048],"type":"Point"}
}