{
  "type": "Feature",
  "properties": {
    "iso:country":"NZ",
    "sg:address":"4 Rymer Pl Mangere Bridge ",
    "sg:city":"Auckland",
    "sg:orig_category":"Industrial: Packaging: Packaging - General",
    "sg:phone":"+64 9-634 6615",
    "sg:province":"Auckland",
    "wof:name":"Carton Brokers Ltd",
    "wof:placetype":"venue"
},
  "geometry": {"coordinates":[174.79669200000001,-36.947651],"type":"Point"}
}