{
  "type": "Feature",
  "properties": {
    "iso:country":"NZ",
    "sg:address":"359 Church Rd Taradale ",
    "sg:city":"Napier",
    "sg:classifiers":[
        {
            "category":"Shopping",
            "subcategory":"Crafts & Fabrics",
            "type":"Retail Goods"
        }
    ],
    "sg:phone":"+64 6-844 5727",
    "sg:province":"Hawke's Bay",
    "sg:tags":[
        "pottery",
        "home",
        "accessories",
        "garden",
        "supply"
    ],
    "wof:name":"Penny Madden Pottery",
    "wof:placetype":"venue"
},
  "geometry": {"coordinates":[176.84700000000001,-39.522659],"type":"Point"}
}