{
  "type": "Feature",
  "properties": {
    "addr:full":"53 Arawa St Matata  Whakatane Bay of Plenty",
    "addr:housenumber":"53",
    "addr:street":"Arawa St;Whakatane",
    "iso:country":"NZ",
    "sg:address":"53 Arawa St Matata ",
    "sg:city":"Whakatane",
    "sg:classifiers":[
        {
            "category":"Manufacturing",
            "subcategory":"Glass & Minerals",
            "type":"Manufacturing & Wholesale Goods"
        }
    ],
    "sg:phone":"+64 7-322 2057",
    "sg:province":"Bay of Plenty",
    "sg:tags":[
        "industrial",
        "raw",
        "material"
    ],
    "wof:name":"Paterson J W & Sons Ltd",
    "wof:placetype":"venue"
},
  "geometry": {"coordinates":[176.984207,-37.965302],"type":"Point"}
}