{
  "type": "Feature",
  "properties": {
    "addr:full":"139 Ridgway St  Wanganui Manawatu-Wanganui",
    "addr:housenumber":"139",
    "addr:street":"Ridgway St",
    "iso:country":"NZ",
    "sg:address":"139 Ridgway St ",
    "sg:city":"Wanganui",
    "sg:orig_category":"Industrial: Metal: Scrap Metal Dealers",
    "sg:phone":"+64 6-347 8516",
    "sg:province":"Manawatu-Wanganui",
    "wof:name":"Scrap Metal Wanganui Ltd",
    "wof:placetype":"venue"
},
  "geometry": {"coordinates":[175.0504,-39.937683],"type":"Point"}
}