{
  "type": "Feature",
  "properties": {
    "addr:full":"2/18 Bower Ave North New Brighton  Christchurch Canterbury",
    "addr:housenumber":"2 / 18",
    "addr:street":"Bower Ave North",
    "iso:country":"NZ",
    "sg:address":"2/18 Bower Ave North New Brighton ",
    "sg:city":"Christchurch",
    "sg:classifiers":[
        {
            "category":"Communications",
            "subcategory":"Television Station",
            "type":"Services"
        }
    ],
    "sg:phone":"+64 3-382 1502",
    "sg:province":"Canterbury",
    "sg:tags":[
        "equipment",
        "broadcasting"
    ],
    "wof:name":"Blyth Radio Systems Ltd",
    "wof:placetype":"venue"
},
  "geometry": {"coordinates":[172.709869,-43.503239],"type":"Point"}
}