{
  "type": "Feature",
  "properties": {
    "addr:full":"Cooper St Havelock North  Hastings Hawke's Bay",
    "addr:street":"Cooper St",
    "iso:country":"NZ",
    "sg:address":"Cooper St Havelock North ",
    "sg:city":"Hastings",
    "sg:orig_category":"Industrial: Metal: Products: Aluminium Products",
    "sg:phone":"+64 6-877 7270",
    "sg:province":"Hawke's Bay",
    "wof:name":"Rylock Sivewright Aluminium Ltd",
    "wof:placetype":"venue"
},
  "geometry": {"coordinates":[176.87657200000001,-39.667595],"type":"Point"}
}