{
  "type": "Feature",
  "properties": {
    "addr:full":"45 Normanby Rd Mt Eden  Auckland Auckland",
    "addr:housenumber":"45",
    "addr:street":"Normanby Rd",
    "iso:country":"NZ",
    "sg:address":"45 Normanby Rd Mt Eden ",
    "sg:city":"Auckland",
    "sg:classifiers":[
        {
            "category":"Arena",
            "subcategory":"Sports Club",
            "type":"Entertainment"
        }
    ],
    "sg:phone":"+64 9-630 9260",
    "sg:province":"Auckland",
    "sg:tags":[
        "-",
        "leisure",
        "sports"
    ],
    "wof:name":"College Sport",
    "wof:placetype":"venue"
},
  "geometry": {"coordinates":[174.76438899999999,-36.868565],"type":"Point"}
}