{
  "type": "Feature",
  "properties": {
    "iso:country":"NZ",
    "sg:address":"385 Palmerston Rd ",
    "sg:city":"Gisborne",
    "sg:classifiers":[
        {
            "category":"Home & Garden",
            "subcategory":"Building Materials",
            "type":"Retail Goods"
        }
    ],
    "sg:phone":"+64 6-867 4809",
    "sg:province":"Gisborne",
    "sg:tags":[
        "fittings",
        "door",
        "garage"
    ],
    "wof:name":"Emms Garage Doors",
    "wof:placetype":"venue"
},
  "geometry": {"coordinates":[178.019547,-38.65934],"type":"Point"}
}