{
  "type": "Feature",
  "properties": {
    "iso:country":"NZ",
    "sg:address":"232 Taniwha St Glen Innes ",
    "sg:city":"Auckland",
    "sg:orig_category":"Health And Beauty: Specialists: Midwives",
    "sg:phone":"+64 9-521 2172",
    "sg:province":"Auckland",
    "wof:name":"Eastern Suburbs Midwives Pregnancy Care",
    "wof:placetype":"venue"
},
  "geometry": {"coordinates":[174.85588100000001,-36.877857],"type":"Point"}
}