{
  "type": "Feature",
  "properties": {
    "addr:full":"Kauri Rd Awhitu  Pukekohe Auckland",
    "addr:street":"Kauri Rd",
    "iso:country":"NZ",
    "sg:address":"Kauri Rd Awhitu ",
    "sg:city":"Pukekohe",
    "sg:orig_category":"Farming: Horticulture: Flowers",
    "sg:phone":"+64 9-235 1254",
    "sg:province":"Auckland",
    "wof:name":"Floratech Nurseries",
    "wof:placetype":"venue"
},
  "geometry": {"coordinates":[174.885941,-37.196117],"type":"Point"}
}