{
  "type": "Feature",
  "properties": {
    "iso:country":"NZ",
    "sg:address":"PO Box 48182 Silverstream Upper ",
    "sg:city":"Hutt",
    "sg:orig_category":"Home And Garden: Gardening: Services: Tree Services",
    "sg:phone":"+64 4-528 3778",
    "sg:province":"Wellington",
    "wof:name":"Treescape Limited",
    "wof:placetype":"venue"
},
  "geometry": {"coordinates":[175.011475,-41.147579],"type":"Point"}
}