{
  "type": "Feature",
  "properties": {
    "addr:full":"5th floor Tower Bldg cnr Railway & Lyndon Rds  Hastings Hawke's Bay",
    "addr:housenumber":"5th floor tower bldg",
    "addr:street":"Cnr Railway & Lyndon Rds",
    "iso:country":"NZ",
    "sg:address":"5th floor Tower Bldg cnr Railway & Lyndon Rds ",
    "sg:city":"Hastings",
    "sg:orig_category":"Farming: Agriculture: Agricultural Consultants",
    "sg:phone":"+64 6-878 6656",
    "sg:province":"Hawke's Bay",
    "wof:name":"Agriculture New Zealand",
    "wof:placetype":"venue"
},
  "geometry": {"coordinates":[-98.39237199999999,40.585651],"type":"Point"}
}