{
  "type": "Feature",
  "properties": {
    "iso:country":"NZ",
    "sg:address":"34 Main Rd ",
    "sg:city":"Tirau",
    "sg:classifiers":[
        {
            "category":"Home & Garden",
            "subcategory":"Kitchen Supply",
            "type":"Retail Goods"
        }
    ],
    "sg:phone":"+64 7-883 1061",
    "sg:tags":[
        "shop",
        "pet",
        "pets"
    ],
    "wof:name":"Tropical Blues Aquariums",
    "wof:placetype":"venue"
},
  "geometry": {"coordinates":[175.757019,-37.977913],"type":"Point"}
}