{
  "type": "Feature",
  "properties": {
    "iso:country":"NZ",
    "sg:address":"51 Burnham St Seatoun ",
    "sg:city":"Wellington",
    "sg:orig_category":"Shopping: Gifts: Gift Baskets",
    "sg:phone":"+64 4-388 5403",
    "sg:province":"Wellington",
    "wof:name":"Prezence (Corporate Gifts)",
    "wof:placetype":"venue"
},
  "geometry": {"coordinates":[174.835464,-41.326241],"type":"Point"}
}