{
  "type": "Feature",
  "properties": {
    "addr:full":"500 Thames Hwy  Oamaru Otago",
    "addr:housenumber":"500",
    "addr:street":"Thames Hwy",
    "iso:country":"NZ",
    "sg:address":"500 Thames Hwy ",
    "sg:city":"Oamaru",
    "sg:classifiers":[
        {
            "category":"Restaurant",
            "type":"Food & Drink"
        }
    ],
    "sg:phone":"+64 3-437 0017",
    "sg:province":"Otago",
    "sg:tags":[
        "wining",
        "dining",
        "pizza"
    ],
    "wof:name":"Galleon Pizza's",
    "wof:placetype":"venue"
},
  "geometry": {"coordinates":[170.99299600000001,-45.068893],"type":"Point"}
}