{
  "type": "Feature",
  "properties": {
    "addr:full":"11 Clark Rd Kamo  Whangarei Northland",
    "addr:housenumber":"11",
    "addr:street":"Clark Rd",
    "iso:country":"NZ",
    "sg:address":"11 Clark Rd Kamo ",
    "sg:city":"Whangarei",
    "sg:classifiers":[
        {
            "category":"Retail",
            "subcategory":"Auto Repair",
            "type":"Services"
        }
    ],
    "sg:phone":"+64 9-435 3092",
    "sg:province":"Northland",
    "sg:tags":[
        "muffler",
        "exhaust",
        "servicing",
        "automotive"
    ],
    "wof:name":"Kamo Muffler Centre",
    "wof:placetype":"venue"
},
  "geometry": {"coordinates":[174.29972799999999,-35.684101],"type":"Point"}
}