{
  "type": "Feature",
  "properties": {
    "addr:full":"cnr Royal Tce & Winston Pl  Alexandra Otago",
    "addr:street":"Cnr Royal Tce & Winston Pl",
    "iso:country":"NZ",
    "sg:address":"cnr Royal Tce & Winston Pl ",
    "sg:city":"Alexandra",
    "sg:orig_category":"Shopping: Retail Stores: Supermarkets",
    "sg:phone":"+64 3-448 8779",
    "sg:province":"Otago",
    "wof:name":"Terrace Store",
    "wof:placetype":"venue"
},
  "geometry": {"coordinates":[169.389984,-45.251148],"type":"Point"}
}