{
  "type": "Feature",
  "properties": {
    "iso:country":"NZ",
    "sg:address":"Cheeseman Rd ",
    "sg:city":"Gisborne",
    "sg:classifiers":[
        {
            "category":"Social Services",
            "subcategory":"Retirement Home",
            "type":"Services"
        }
    ],
    "sg:phone":"+64 6-867 7697",
    "sg:province":"Gisborne",
    "sg:tags":[
        "elderly",
        "convalescent",
        "garden",
        "rest",
        "care"
    ],
    "wof:name":"Leighton House",
    "wof:placetype":"venue"
},
  "geometry": {"coordinates":[178.03414900000001,-38.664989],"type":"Point"}
}