{
  "type": "Feature",
  "properties": {
    "iso:country":"NZ",
    "sg:address":"Cnr of Cuba & Dixon Sts ",
    "sg:city":"Wellington",
    "sg:orig_category":"Clothing And Fabric: Clothing: Jeans",
    "sg:phone":"+64 4-385 6590",
    "sg:province":"Wellington",
    "wof:name":"Area51",
    "wof:placetype":"venue"
},
  "geometry": {"coordinates":[146.22790499999999,-20.081173],"type":"Point"}
}