{
  "type": "Feature",
  "properties": {
    "addr:full":"85 Gt South Rd Papakura  Auckland Auckland",
    "addr:housenumber":"85",
    "addr:street":"Gt South Rd",
    "iso:country":"NZ",
    "sg:address":"85 Gt South Rd Papakura ",
    "sg:city":"Auckland",
    "sg:classifiers":[
        {
            "category":"Shopping",
            "subcategory":"Beauty & Cosmetics",
            "type":"Retail Goods"
        }
    ],
    "sg:phone":"+64 800 434 935",
    "sg:province":"Auckland",
    "sg:tags":[
        "medical",
        "health"
    ],
    "wof:name":"The Dental Company",
    "wof:placetype":"venue"
},
  "geometry": {"coordinates":[174.94026199999999,-37.059456],"type":"Point"}
}