{
  "type": "Feature",
  "properties": {
    "addr:full":"701 Gloucester St Linwood  Christchurch Canterbury",
    "addr:housenumber":"701",
    "addr:street":"Gloucester St",
    "iso:country":"NZ",
    "sg:address":"701 Gloucester St Linwood ",
    "sg:city":"Christchurch",
    "sg:classifiers":[
        {
            "category":"Home & Garden",
            "subcategory":"Home Furnishings",
            "type":"Retail Goods"
        }
    ],
    "sg:phone":"+64 3-381 2261",
    "sg:province":"Canterbury",
    "sg:tags":[
        "furniture/furnishings",
        "upholstery",
        "supply"
    ],
    "wof:name":"Dallington Market Upholstery Services",
    "wof:placetype":"venue"
},
  "geometry": {"coordinates":[172.67259200000001,-43.525696],"type":"Point"}
}