{
  "type": "Feature",
  "properties": {
    "addr:full":"1/91 High St  Bulls",
    "addr:housenumber":"1 / 91",
    "addr:street":"High St",
    "iso:country":"NZ",
    "sg:address":"1/91 High St ",
    "sg:city":"Bulls",
    "sg:orig_category":"Home And Garden: Windows And Fittings: Leadlights",
    "sg:phone":"+64 6-322 1014",
    "wof:name":"Our Glass",
    "wof:placetype":"venue"
},
  "geometry": {"coordinates":[175.38789399999999,-40.17234],"type":"Point"}
}