{
  "type": "Feature",
  "properties": {
    "iso:country":"NZ",
    "sg:address":"860 a Devon Rd Bell Block New ",
    "sg:city":"Plymouth",
    "sg:classifiers":[
        {
            "category":"Manufacturing",
            "subcategory":"Glass & Minerals",
            "type":"Manufacturing & Wholesale Goods"
        }
    ],
    "sg:phone":"+64 6-755 2194",
    "sg:province":"Taranaki",
    "sg:tags":[
        "chemical",
        "fibre",
        "industrial",
        "compounds"
    ],
    "wof:name":"Fibresport",
    "wof:placetype":"venue"
},
  "geometry": {"coordinates":[174.15020799999999,-39.034698],"type":"Point"}
}