{
  "type": "Feature",
  "properties": {
    "addr:full":"145 North Rd  Invercargill Southland",
    "addr:housenumber":"145",
    "addr:street":"North Rd",
    "iso:country":"NZ",
    "sg:address":"145 North Rd ",
    "sg:city":"Invercargill",
    "sg:classifiers":[
        {
            "category":"Manufacturing",
            "subcategory":"Tools & Machinery",
            "type":"Manufacturing & Wholesale Goods"
        }
    ],
    "sg:phone":"+64 3-215 8104",
    "sg:province":"Southland",
    "sg:tags":[
        "equipment",
        "industrial",
        "hydraulic"
    ],
    "wof:name":"Pirtek Southland Ltd",
    "wof:placetype":"venue"
},
  "geometry": {"coordinates":[168.34704600000001,-46.383205],"type":"Point"}
}