{
  "type": "Feature",
  "properties": {
    "iso:country":"NZ",
    "sg:address":"1 Hubbard St Te ",
    "sg:city":"Aroha",
    "sg:classifiers":[
        {
            "category":"Professional",
            "subcategory":"Engineering",
            "type":"Services"
        }
    ],
    "sg:phone":"+64 7-884 8232",
    "sg:tags":[
        "industrial"
    ],
    "sg:website":"http://www.yellowpages.co.nz/for/cullensengineering/dp30623.html",
    "wof:name":"Cullen Engineering Co Ltd",
    "wof:placetype":"venue"
},
  "geometry": {"coordinates":[175.706467,-37.539906],"type":"Point"}
}