{
  "type": "Feature",
  "properties": {
    "addr:full":"79-81 Gaunt St, Westhaven  Auckland Auckland",
    "addr:housenumber":"79-81",
    "addr:street":"Gaunt St",
    "iso:country":"NZ",
    "sg:address":"79-81 Gaunt St, Westhaven ",
    "sg:city":"Auckland",
    "sg:classifiers":[
        {
            "category":"Farming",
            "subcategory":"Fish & Marine Products",
            "type":"Manufacturing & Wholesale Goods"
        }
    ],
    "sg:phone":"+64 9-309 9111",
    "sg:province":"Auckland",
    "sg:tags":[
        "boats",
        "yacht",
        "transport",
        "boat",
        "supply"
    ],
    "sg:website":"http://www.safetyatsea.co.nz/",
    "wof:name":"Safety At Sea (Australasia) Ltd",
    "wof:placetype":"venue"
},
  "geometry": {"coordinates":[174.630798,-36.818272],"type":"Point"}
}