{
  "type": "Feature",
  "properties": {
    "addr:full":"18 Horomatangi St  Taupo Waikato",
    "addr:housenumber":"18",
    "addr:street":"Horomatangi St",
    "iso:country":"NZ",
    "sg:address":"18 Horomatangi St ",
    "sg:city":"Taupo",
    "sg:orig_category":"Shopping: Retail Stores: Antiques",
    "sg:phone":"+64 7-378 2288",
    "sg:province":"Waikato",
    "wof:name":"Art Collector",
    "wof:placetype":"venue"
},
  "geometry": {"coordinates":[176.07074,-38.686691],"type":"Point"}
}