{
  "type": "Feature",
  "properties": {
    "iso:country":"NZ",
    "sg:address":"Pukeko Rd R D 7 ",
    "sg:city":"Tarata",
    "sg:classifiers":[
        {
            "category":"Organizations",
            "subcategory":"Labor Organization",
            "type":"Services"
        }
    ],
    "sg:phone":"+64 252315525",
    "sg:tags":[
        "services",
        "helicopter",
        "travel",
        "tourism"
    ],
    "wof:name":"Eggers Matt & Helen",
    "wof:placetype":"venue"
},
  "geometry": {"coordinates":[174.365128,-39.152321],"type":"Point"}
}