{
  "type": "Feature",
  "properties": {
    "iso:country":"NZ",
    "sg:address":"Atrium on Elliott 21 Elliott St Auckland Central ",
    "sg:city":"Auckland",
    "sg:classifiers":[
        {
            "category":"Bars & Pubs",
            "subcategory":"Wine Bar",
            "type":"Food & Drink"
        }
    ],
    "sg:phone":"+64 9-379 3688",
    "sg:province":"Auckland",
    "sg:tags":[
        "wining",
        "dining",
        "cafe"
    ],
    "wof:name":"Cafe BBS'S",
    "wof:placetype":"venue"
},
  "geometry": {"coordinates":[174.764542,-36.848358],"type":"Point"}
}