{
  "type": "Feature",
  "properties": {
    "addr:full":"247 Remuera Rd Remuera  Auckland Auckland",
    "addr:housenumber":"247",
    "addr:street":"Remuera Rd",
    "iso:country":"NZ",
    "sg:address":"247 Remuera Rd Remuera ",
    "sg:city":"Auckland",
    "sg:classifiers":[
        {
            "category":"Health Services",
            "subcategory":"Health Practitioner",
            "type":"Services"
        }
    ],
    "sg:phone":"+64 9-520 4760",
    "sg:province":"Auckland",
    "sg:tags":[
        "specialist",
        "medical",
        "beauty",
        "specialists"
    ],
    "wof:name":"Quin Dr Paul",
    "wof:placetype":"venue"
},
  "geometry": {"coordinates":[174.79156499999999,-36.879539],"type":"Point"}
}