{
  "type": "Feature",
  "properties": {
    "iso:country":"NZ",
    "sg:address":"10 Andrews Ave Lower ",
    "sg:city":"Hutt",
    "sg:classifiers":[
        {
            "category":"Landmark",
            "subcategory":"Tourist Information",
            "type":"Public Place"
        }
    ],
    "sg:phone":"+64 4-560 4715",
    "sg:province":"Wellington",
    "sg:tags":[
        "services",
        "travel",
        "tourism"
    ],
    "wof:name":"Hutt City Information & Visitors Centre",
    "wof:placetype":"venue"
},
  "geometry": {"coordinates":[174.90141299999999,-41.20948],"type":"Point"}
}