{
  "type": "Feature",
  "properties": {
    "iso:country":"NZ",
    "sg:address":"304 Broadway Ave Palmerston ",
    "sg:city":"Palmerston North",
    "sg:classifiers":[
        {
            "category":"Health Services",
            "subcategory":"Clinic",
            "type":"Services"
        }
    ],
    "sg:phone":"+64 6-356 3310",
    "sg:province":"Manawatu-Wanganui",
    "sg:tags":[
        "medical",
        "beauty"
    ],
    "wof:name":"Central Orthotics Limited",
    "wof:placetype":"venue"
},
  "geometry": {"coordinates":[175.624741,-40.348862],"type":"Point"}
}