{
  "type": "Feature",
  "properties": {
    "iso:country":"NZ",
    "sg:address":"1237 Ada St ",
    "sg:city":"Hastings",
    "sg:classifiers":[
        {
            "category":"Retail",
            "subcategory":"Auto Repair",
            "type":"Services"
        }
    ],
    "sg:phone":"+64 6-876 0780",
    "sg:province":"Hawke's Bay",
    "sg:tags":[
        "automotive",
        "electric",
        "servicing"
    ],
    "wof:name":"Windsor Auto Electrical",
    "wof:placetype":"venue"
},
  "geometry": {"coordinates":[-81.508163,29.711214],"type":"Point"}
}