{
  "type": "Feature",
  "properties": {
    "iso:country":"NZ",
    "sg:address":"181 Victoria St ",
    "sg:city":"Wellington",
    "sg:classifiers":[
        {
            "category":"Social Services",
            "subcategory":"Child Care",
            "type":"Services"
        }
    ],
    "sg:phone":"+64 4-385 4599",
    "sg:province":"Wellington",
    "sg:tags":[
        "baby",
        "home",
        "product",
        "garden",
        "children"
    ],
    "wof:name":"Baby Factory",
    "wof:placetype":"venue"
},
  "geometry": {"coordinates":[-3.230097,50.981392],"type":"Point"}
}