{
  "type": "Feature",
  "properties": {
    "iso:country":"NZ",
    "sg:address":"75 Commerce St ",
    "sg:city":"Whakatane",
    "sg:classifiers":[
        {
            "category":"Retail",
            "subcategory":"Auto Repair",
            "type":"Services"
        }
    ],
    "sg:phone":"+64 7-308 8601",
    "sg:province":"Bay of Plenty",
    "sg:tags":[
        "muffler",
        "exhaust",
        "servicing",
        "automotive"
    ],
    "wof:name":"Coastline Mufflers",
    "wof:placetype":"venue"
},
  "geometry": {"coordinates":[176.995544,-37.955063],"type":"Point"}
}