{
  "type": "Feature",
  "properties": {
    "iso:country":"NZ",
    "sg:address":"935 High St Lower Hutt ",
    "sg:city":"Wellington",
    "sg:orig_category":"Shopping: Retail Stores: Secondhand Dealers",
    "sg:phone":"+64 4-939 0059",
    "sg:province":"Wellington",
    "wof:name":"Baby Go Round",
    "wof:placetype":"venue"
},
  "geometry": {"coordinates":[174.912567,-41.204727],"type":"Point"}
}