{
  "type": "Feature",
  "properties": {
    "iso:country":"NZ",
    "sg:address":"Vickery St Te Rapa ",
    "sg:city":"Hamilton",
    "sg:orig_category":"Farming: Supplies: Veterinary Supplies",
    "sg:phone":"+64 800 509 876",
    "sg:province":"Waikato",
    "wof:name":"Instrument Supplies",
    "wof:placetype":"venue"
},
  "geometry": {"coordinates":[175.244019,-37.752434],"type":"Point"}
}