{
  "type": "Feature",
  "properties": {
    "iso:country":"NZ",
    "sg:address":"PO Box 40426 Glenfield ",
    "sg:city":"Auckland",
    "sg:orig_category":"Home And Garden: General: Handyman'S Services",
    "sg:phone":"+64 9-418 1970",
    "sg:province":"Auckland",
    "wof:name":"Bluestone Productions Ltd",
    "wof:placetype":"venue"
},
  "geometry": {"coordinates":[174.728622,-36.784813],"type":"Point"}
}