{
  "type": "Feature",
  "properties": {
    "iso:country":"NZ",
    "sg:address":"86 Fergusson St ",
    "sg:city":"Feilding",
    "sg:orig_category":"Shopping: Hobbies And Games: Collectables",
    "sg:phone":"+64 6-323 8585",
    "sg:province":"Manawatu-Wanganui",
    "wof:name":"Keith Smith & Son",
    "wof:placetype":"venue"
},
  "geometry": {"coordinates":[175.56658899999999,-40.226826],"type":"Point"}
}