{
  "type": "Feature",
  "properties": {
    "addr:full":"80 Johnsonville Rd Wellington Wellington",
    "addr:housenumber":"80",
    "addr:street":"Johnsonville Rd",
    "iso:country":"NZ",
    "sg:address":"80 Johnsonville Rd",
    "sg:city":"Wellington",
    "sg:classifiers":[
        {
            "category":"Banks & Credit Unions",
            "subcategory":"Bank",
            "type":"Services"
        }
    ],
    "sg:phone":"+64 4780916",
    "sg:province":"Wellington",
    "wof:name":"Countrywide Banking Corporation Ltd",
    "wof:placetype":"venue"
},
  "geometry": {"coordinates":[174.80715900000001,-41.224079],"type":"Point"}
}