{
  "type": "Feature",
  "properties": {
    "iso:country":"NZ",
    "sg:address":"17 Aberfeldy Ave Highland Park ",
    "sg:city":"Auckland",
    "sg:orig_category":"Health And Beauty: Diet: Dietitians",
    "sg:phone":"+64 9-537 3208",
    "sg:province":"Auckland",
    "wof:name":"Alda Lee",
    "wof:placetype":"venue"
},
  "geometry": {"coordinates":[174.908829,-36.900127],"type":"Point"}
}