{
  "type": "Feature",
  "properties": {
    "addr:full":"71 Kowhai Dve  Renwick Marlborough",
    "addr:housenumber":"71",
    "addr:street":"Kowhai Dve Renwick",
    "iso:country":"NZ",
    "sg:address":"71 Kowhai Dve ",
    "sg:city":"Renwick",
    "sg:orig_category":"Farming: Forestry",
    "sg:phone":"+64 25339961",
    "sg:province":"Marlborough",
    "wof:name":"Jones Barry Forestry Contracting Ltd",
    "wof:placetype":"venue"
},
  "geometry": {"coordinates":[-93.980659,42.827869],"type":"Point"}
}