{
  "type": "Feature",
  "properties": {
    "iso:country":"NZ",
    "sg:address":"Level 6 Compaq House 86-96 Victoria St PO Box 2833",
    "sg:city":"Wellington",
    "sg:classifiers":[
        {
            "category":"Wholesale",
            "subcategory":"Meat",
            "type":"Manufacturing & Wholesale Goods"
        }
    ],
    "sg:phone":"+64 4-917 8300",
    "sg:province":"Wellington",
    "sg:tags":[
        "food",
        "distributor",
        "drink",
        "meats"
    ],
    "wof:name":"ANZCO Foods Ltd",
    "wof:placetype":"venue"
},
  "geometry": {"coordinates":[-2.511816,52.699959],"type":"Point"}
}