{
  "type": "Feature",
  "properties": {
    "addr:full":"125 Commerce St  Hamilton Waikato",
    "addr:housenumber":"125",
    "addr:street":"Commerce St",
    "iso:country":"NZ",
    "sg:address":"125 Commerce St ",
    "sg:city":"Hamilton",
    "sg:classifiers":[
        {
            "category":"Fast Food",
            "type":"Food & Drink"
        }
    ],
    "sg:phone":"+64 7-846 2223",
    "sg:province":"Waikato",
    "sg:tags":[
        "wining",
        "dining",
        "takeaway"
    ],
    "wof:name":"Lath Lay's",
    "wof:placetype":"venue"
},
  "geometry": {"coordinates":[-84.580231,39.407902],"type":"Point"}
}