{
  "type": "Feature",
  "properties": {
    "iso:country":"NZ",
    "sg:address":"361 Mangorei Rd New ",
    "sg:city":"Plymouth",
    "sg:classifiers":[
        {
            "category":"Social Services",
            "subcategory":"Retirement Home",
            "type":"Services"
        }
    ],
    "sg:phone":"+64 6-758 0666",
    "sg:province":"Taranaki",
    "sg:tags":[
        "care",
        "garden",
        "elderly",
        "village"
    ],
    "wof:name":"Riverview Lodge - Rest Home & Hospital",
    "wof:placetype":"venue"
},
  "geometry": {"coordinates":[174.107941,-39.079201],"type":"Point"}
}