{
  "type": "Feature",
  "properties": {
    "addr:full":"16 Bell Bird Rse Murrays Bay  Auckland Auckland",
    "addr:housenumber":"16",
    "addr:street":"Bell Bird",
    "iso:country":"NZ",
    "sg:address":"16 Bell Bird Rse Murrays Bay ",
    "sg:city":"Auckland",
    "sg:classifiers":[
        {
            "category":"Wholesale",
            "subcategory":"Meat",
            "type":"Manufacturing & Wholesale Goods"
        }
    ],
    "sg:phone":"+64 9-478 5311",
    "sg:province":"Auckland",
    "sg:tags":[
        "food",
        "drink",
        "meats",
        "slaughtering"
    ],
    "wof:name":"Taylor Preston Ltd",
    "wof:placetype":"venue"
},
  "geometry": {"coordinates":[174.74444600000001,-36.731228],"type":"Point"}
}