{
  "type": "Feature",
  "properties": {
    "addr:full":"169-171 Ngaumutawa Rd  Masterton Wellington",
    "addr:housenumber":"169-171",
    "addr:street":"Ngaumutawa Rd",
    "iso:country":"NZ",
    "sg:address":"169-171 Ngaumutawa Rd ",
    "sg:city":"Masterton",
    "sg:orig_category":"Home And Garden: Accessories: Hardware",
    "sg:phone":"+64 6-377 4955",
    "sg:province":"Wellington",
    "wof:name":"Mitre 10",
    "wof:placetype":"venue"
},
  "geometry": {"coordinates":[175.634613,-40.948341],"type":"Point"}
}