{
  "type": "Feature",
  "properties": {
    "iso:country":"NZ",
    "sg:address":"cnr New Brighton Rd & Cresswell Ave Burwood ",
    "sg:city":"Christchurch",
    "sg:orig_category":"Automotive: General Services: Service Stations",
    "sg:phone":"+64 3-385 1399",
    "sg:province":"Canterbury",
    "wof:name":"Cresswell Motors Ltd CHALLENGE",
    "wof:placetype":"venue"
},
  "geometry": {"coordinates":[172.682007,-43.49456],"type":"Point"}
}