{
  "type": "Feature",
  "properties": {
    "iso:country":"NZ",
    "sg:address":"Brookfield Shopping Centre Otumoetai Rd ",
    "sg:city":"Tauranga",
    "sg:classifiers":[
        {
            "category":"Communications",
            "subcategory":"Film & Video Production",
            "type":"Services"
        }
    ],
    "sg:phone":"+64 7-576 5436",
    "sg:province":"Bay of Plenty",
    "sg:tags":[
        "sport",
        "leisure",
        "library",
        "entertainment"
    ],
    "wof:name":"Video Ezy",
    "wof:placetype":"venue"
},
  "geometry": {"coordinates":[176.144745,-37.703156],"type":"Point"}
}