{
  "type": "Feature",
  "properties": {
    "addr:full":"Queen St  Pahiatua",
    "addr:street":"Queen St",
    "iso:country":"NZ",
    "sg:address":"Queen St ",
    "sg:city":"Pahiatua",
    "sg:classifiers":[
        {
            "category":"Manufacturing",
            "subcategory":"Textiles",
            "type":"Manufacturing & Wholesale Goods"
        }
    ],
    "sg:phone":"+64 6-376 8456",
    "sg:tags":[
        "clothing",
        "fabric",
        "manufacturer"
    ],
    "wof:name":"Betacraft NZ Ltd",
    "wof:placetype":"venue"
},
  "geometry": {"coordinates":[175.838348,-40.458954],"type":"Point"}
}