{
  "type": "Feature",
  "properties": {
    "addr:full":"E/119 Capt. Springs Rd  Onehunga Auckland",
    "addr:housenumber":"119",
    "addr:street":"E /;Capt. Springs Rd",
    "iso:country":"NZ",
    "sg:address":"E/119 Capt. Springs Rd ",
    "sg:city":"Onehunga",
    "sg:classifiers":[
        {
            "category":"Bars & Pubs",
            "subcategory":"Lounge",
            "type":"Food & Drink"
        }
    ],
    "sg:phone":"+64 800 100 004",
    "sg:province":"Auckland",
    "sg:tags":[
        "-"
    ],
    "sg:website":"http://www.lollies.co.nz",
    "wof:name":"Fundraising Buy Confectionery Ltd/Confectionery Holdings Ltd",
    "wof:placetype":"venue"
},
  "geometry": {"coordinates":[174.783661,-36.909973],"type":"Point"}
}