{
  "type": "Feature",
  "properties": {
    "iso:country":"NZ",
    "sg:address":"PO Box 300 761 Albany ",
    "sg:city":"Auckland",
    "sg:orig_category":"Industrial: Equipment And Machinery: Generators",
    "sg:phone":"+64 9-415 3669",
    "sg:province":"Auckland",
    "wof:name":"Benmac Equipment",
    "wof:placetype":"venue"
},
  "geometry": {"coordinates":[174.770416,-36.884109],"type":"Point"}
}