{
  "type": "Feature",
  "properties": {
    "addr:full":"PO Box 300 761 Albany  Auckland Auckland",
    "addr:housenumber":"po;761",
    "addr:street":"Box 300",
    "iso:country":"NZ",
    "sg:address":"PO Box 300 761 Albany ",
    "sg:city":"Auckland",
    "sg:orig_category":"Industrial: Equipment And Machinery: Generators",
    "sg:phone":"+64 9-415 3669",
    "sg:province":"Auckland",
    "wof:name":"Benmac Equipment",
    "wof:placetype":"venue"
},
  "geometry": {"coordinates":[174.77041600000001,-36.884109],"type":"Point"}
}