{
  "type": "Feature",
  "properties": {
    "iso:country":"NZ",
    "sg:address":"21 Cordyline Pl North New Brighton ",
    "sg:city":"Christchurch",
    "sg:orig_category":"Home And Garden: Children: Nannies",
    "sg:phone":"+64 3-382 3093",
    "sg:province":"Canterbury",
    "wof:name":"Annies Nannies",
    "wof:placetype":"venue"
},
  "geometry": {"coordinates":[172.71757500000001,-43.497295],"type":"Point"}
}