{
  "type": "Feature",
  "properties": {
    "iso:country":"NZ",
    "sg:address":"Logan Plaza Main St Upper ",
    "sg:city":"Hutt",
    "sg:classifiers":[
        {
            "category":"Shopping",
            "subcategory":"Pharmacy",
            "type":"Retail Goods"
        }
    ],
    "sg:phone":"+64 4-528 3363",
    "sg:province":"Wellington",
    "sg:tags":[
        "product",
        "health"
    ],
    "wof:name":"Culpeper House",
    "wof:placetype":"venue"
},
  "geometry": {"coordinates":[175.069031,-41.12458],"type":"Point"}
}