{
  "type": "Feature",
  "properties": {
    "iso:country":"NZ",
    "sg:address":"129 High St Lower ",
    "sg:city":"Hutt",
    "sg:classifiers":[
        {
            "category":"Building & Trades",
            "subcategory":"Construction",
            "type":"Services"
        }
    ],
    "sg:phone":"+64 4-566 4119",
    "sg:province":"Wellington",
    "sg:tags":[
        "home",
        "hire",
        "garden"
    ],
    "wof:name":"DTR (Dominion TV Rentals)",
    "wof:placetype":"venue"
},
  "geometry": {"coordinates":[174.901428,-41.210041],"type":"Point"}
}