{
  "type": "Feature",
  "properties": {
    "iso:country":"NZ",
    "sg:address":"Tarewa Rd ",
    "sg:city":"Whangarei",
    "sg:orig_category":"Farming: Supplies: Farm Buildings",
    "sg:phone":"+64 9-438 4020",
    "sg:province":"Northland",
    "wof:name":"Tri Steel",
    "wof:placetype":"venue"
},
  "geometry": {"coordinates":[174.28276099999999,-35.689789],"type":"Point"}
}