{
  "type": "Feature",
  "properties": {
    "iso:country":"NZ",
    "sg:address":"101 Edgecumbe Rd ",
    "sg:city":"Tauranga",
    "sg:classifiers":[
        {
            "category":"Social Services",
            "subcategory":"Retirement Home",
            "type":"Services"
        }
    ],
    "sg:phone":"+64 7-571 0052",
    "sg:province":"Bay of Plenty",
    "sg:tags":[
        "care",
        "garden",
        "elderly",
        "village"
    ],
    "wof:name":"Accadia On The Avenue's",
    "wof:placetype":"venue"
},
  "geometry": {"coordinates":[176.156418,-37.697578],"type":"Point"}
}