{
  "type": "Feature",
  "properties": {
    "iso:country":"NZ",
    "sg:address":"Unit L 44-46 Constellation Dve Mairangi Bay ",
    "sg:city":"Auckland",
    "sg:orig_category":"Industrial: Electrical/Electronic",
    "sg:phone":"+64 9-476 8330",
    "sg:province":"Auckland",
    "sg:website":"http://www.avd.co.nz",
    "wof:name":"Audio Video Designs Ltd",
    "wof:placetype":"venue"
},
  "geometry": {"coordinates":[174.770416,-36.884109],"type":"Point"}
}