{
  "type": "Feature",
  "properties": {
    "addr:full":"Hokianga Rd  Dargaville Northland",
    "addr:street":"Hokianga Rd",
    "iso:country":"NZ",
    "sg:address":"Hokianga Rd ",
    "sg:city":"Dargaville",
    "sg:classifiers":[
        {
            "category":"Health Services",
            "subcategory":"Hospital",
            "type":"Services"
        }
    ],
    "sg:phone":"+64 9-439 7618",
    "sg:province":"Northland",
    "sg:tags":[
        "medical",
        "beauty"
    ],
    "wof:name":"Plunket Society",
    "wof:placetype":"venue"
},
  "geometry": {"coordinates":[173.86338799999999,-35.937065],"type":"Point"}
}