{
  "type": "Feature",
  "properties": {
    "iso:country":"NZ",
    "sg:address":"16 Akepiro St Mt Eden ",
    "sg:city":"Auckland",
    "sg:classifiers":[
        {
            "category":"Arts & Performance",
            "subcategory":"Music",
            "type":"Entertainment"
        }
    ],
    "sg:phone":"+64 9-627 9876",
    "sg:province":"Auckland",
    "sg:tags":[
        "mobile",
        "sport",
        "-",
        "leisure",
        "disco"
    ],
    "wof:name":"DISCOTECH DJ Ltd",
    "wof:placetype":"venue"
},
  "geometry": {"coordinates":[174.751968,-36.869934],"type":"Point"}
}