{
  "type": "Feature",
  "properties": {
    "iso:country":"NZ",
    "sg:address":"1081 State Highway 1 Te Horo ",
    "sg:city":"Otaki",
    "sg:classifiers":[
        {
            "category":"Restaurant",
            "type":"Food & Drink"
        }
    ],
    "sg:phone":"+64 6-364 3665",
    "sg:tags":[
        "wining",
        "dining"
    ],
    "wof:name":"The Winemakers Daughter",
    "wof:placetype":"venue"
},
  "geometry": {"coordinates":[175.12133800000001,-40.802349],"type":"Point"}
}