{
  "type": "Feature",
  "properties": {
    "addr:full":"35 Weld St  Hokitika West Coast",
    "addr:housenumber":"35",
    "addr:street":"Weld St",
    "iso:country":"NZ",
    "sg:address":"35 Weld St ",
    "sg:city":"Hokitika",
    "sg:classifiers":[
        {
            "category":"Restaurant",
            "type":"Food & Drink"
        }
    ],
    "sg:phone":"+64 3-755 8128",
    "sg:province":"West Coast",
    "sg:tags":[
        "wining",
        "dining"
    ],
    "wof:name":"Millies Place Licensed Restaurant",
    "wof:placetype":"venue"
},
  "geometry": {"coordinates":[170.96464499999999,-42.718636],"type":"Point"}
}