{
  "type": "Feature",
  "properties": {
    "addr:full":"26 Domain St Palmerston  Palmerston North Manawatu-Wanganui",
    "addr:housenumber":"26",
    "addr:street":"Domain St Palmerston",
    "iso:country":"NZ",
    "sg:address":"26 Domain St Palmerston ",
    "sg:city":"Palmerston North",
    "sg:classifiers":[
        {
            "category":"Retail",
            "subcategory":"Auto Repair",
            "type":"Services"
        }
    ],
    "sg:phone":"+64 6-355 5070",
    "sg:province":"Manawatu-Wanganui",
    "sg:tags":[
        "engine",
        "automotive",
        "servicing"
    ],
    "wof:name":"The Head Shop",
    "wof:placetype":"venue"
},
  "geometry": {"coordinates":[175.60462999999999,-40.358505],"type":"Point"}
}