{
  "type": "Feature",
  "properties": {
    "iso:country":"NZ",
    "sg:address":"5 Nandina Ave East Tamaki ",
    "sg:city":"Auckland",
    "sg:classifiers":[
        {
            "category":"Sports & Exercise",
            "subcategory":"Sports Center",
            "type":"Entertainment"
        }
    ],
    "sg:phone":"+64 9-274 4511",
    "sg:province":"Auckland",
    "sg:tags":[
        "health",
        "beauty",
        "fitness"
    ],
    "wof:name":"Clive Green Health Centres",
    "wof:placetype":"venue"
},
  "geometry": {"coordinates":[174.900757,-36.930031],"type":"Point"}
}