{
  "type": "Feature",
  "properties": {
    "addr:full":"200 Victoria St West  Auckland Auckland",
    "addr:housenumber":"200",
    "addr:street":"Victoria St",
    "iso:country":"NZ",
    "sg:address":"200 Victoria St West ",
    "sg:city":"Auckland",
    "sg:orig_category":"Shopping: Discount: Factory Shops",
    "sg:phone":"+64 9-377 7560",
    "sg:province":"Auckland",
    "wof:name":"Kathmandu Ltd",
    "wof:placetype":"venue"
},
  "geometry": {"coordinates":[-1.721739,54.631775],"type":"Point"}
}