{
  "type": "Feature",
  "properties": {
    "iso:country":"NZ",
    "sg:address":"Arthurs Point ",
    "sg:city":"Queenstown",
    "sg:classifiers":[
        {
            "category":"Recreation",
            "type":"Entertainment"
        }
    ],
    "sg:phone":"+64 3-442 7486",
    "sg:province":"Otago",
    "sg:tags":[
        "trek",
        "travel",
        "horse",
        "tour",
        "tourism",
        "sightseeing"
    ],
    "wof:name":"Shotover Stables",
    "wof:placetype":"venue"
},
  "geometry": {"coordinates":[168.670334,-44.991478],"type":"Point"}
}