{
  "type": "Feature",
  "properties": {
    "iso:country":"NZ",
    "sg:address":"Mangarara Rd R D 2 Otane ",
    "sg:city":"Waipukurau",
    "sg:orig_category":"Farming: Machinery: Farm Machinery",
    "sg:phone":"+64 6-858 4937",
    "wof:name":"Hart Machinery",
    "wof:placetype":"venue"
},
  "geometry": {"coordinates":[176.5513,-39.994656],"type":"Point"}
}