{
  "type": "Feature",
  "properties": {
    "addr:full":"129 Marsden Rd  Greymouth West Coast",
    "addr:housenumber":"129",
    "addr:street":"Marsden Rd",
    "iso:country":"NZ",
    "sg:address":"129 Marsden Rd ",
    "sg:city":"Greymouth",
    "sg:classifiers":[
        {
            "category":"Home & Garden",
            "subcategory":"Building Materials",
            "type":"Retail Goods"
        }
    ],
    "sg:phone":"+64 3-768 6719",
    "sg:province":"West Coast",
    "sg:tags":[
        "bricklaying",
        "related"
    ],
    "wof:name":"Packham Masonry Ltd",
    "wof:placetype":"venue"
},
  "geometry": {"coordinates":[171.20872499999999,-42.469402],"type":"Point"}
}