{
  "type": "Feature",
  "properties": {
    "addr:full":"71 Bank St  Whangarei Northland",
    "addr:housenumber":"71",
    "addr:street":"Bank St",
    "iso:country":"NZ",
    "sg:address":"71 Bank St ",
    "sg:city":"Whangarei",
    "sg:classifiers":[
        {
            "category":"Banks & Credit Unions",
            "subcategory":"Investment Brokerage",
            "type":"Services"
        }
    ],
    "sg:phone":"+64 9-438 2511",
    "sg:province":"Northland",
    "sg:tags":[
        "educational",
        "education",
        "training"
    ],
    "wof:name":"Adult Learning Assistance",
    "wof:placetype":"venue"
},
  "geometry": {"coordinates":[174.31961100000001,-35.723778],"type":"Point"}
}