{
  "type": "Feature",
  "properties": {
    "addr:full":"375 Tweed St  Invercargill Southland",
    "addr:housenumber":"375",
    "addr:street":"Tweed St",
    "iso:country":"NZ",
    "sg:address":"375 Tweed St ",
    "sg:city":"Invercargill",
    "sg:classifiers":[
        {
            "category":"Personal",
            "type":"Services"
        }
    ],
    "sg:phone":"+64 3-216 6077",
    "sg:province":"Southland",
    "sg:tags":[
        "arrangements",
        "wedding"
    ],
    "sg:website":"http://southland.bizdirectorynz.com/companies/html/whiteheron.htm",
    "wof:name":"White Heron Caterers",
    "wof:placetype":"venue"
},
  "geometry": {"coordinates":[168.36908,-46.418095],"type":"Point"}
}