{
  "type": "Feature",
  "properties": {
    "addr:full":"37 Robert St Ellerslie  Auckland Auckland",
    "addr:housenumber":"37",
    "addr:street":"Robert St",
    "iso:country":"NZ",
    "sg:address":"37 Robert St Ellerslie ",
    "sg:city":"Auckland",
    "sg:orig_category":"Health And Beauty: Specialists: Osteopaths",
    "sg:phone":"+64 9-525 7766",
    "sg:province":"Auckland",
    "wof:name":"Burnett Christopher",
    "wof:placetype":"venue"
},
  "geometry": {"coordinates":[174.80943300000001,-36.894035],"type":"Point"}
}