{
  "type": "Feature",
  "properties": {
    "addr:full":"PO Box 556  Picton Marlborough",
    "addr:housenumber":"po",
    "addr:street":"Box 556",
    "iso:country":"NZ",
    "sg:address":"PO Box 556 ",
    "sg:city":"Picton",
    "sg:classifiers":[
        {
            "category":"Building & Trades",
            "subcategory":"Plumbing",
            "type":"Services"
        }
    ],
    "sg:phone":"+64 25345242",
    "sg:province":"Marlborough",
    "sg:tags":[
        "home",
        "plumber",
        "garden",
        "related"
    ],
    "wof:name":"Clough Shayne Plumbing Ltd",
    "wof:placetype":"venue"
},
  "geometry": {"coordinates":[174.00427199999999,-41.294796],"type":"Point"}
}