{
  "type": "Feature",
  "properties": {
    "iso:country":"NZ",
    "sg:address":"Newmarket & GreyLynn ",
    "sg:city":"Auckland",
    "sg:classifiers":[
        {
            "category":"Personal",
            "type":"Services"
        }
    ],
    "sg:phone":"+64 9-520 0363",
    "sg:province":"Auckland",
    "sg:tags":[
        "health",
        "beauty",
        "diet"
    ],
    "wof:name":"Brenda Tallentire NZR Dietitian",
    "wof:placetype":"venue"
},
  "geometry": {"coordinates":[174.734741,-36.861408],"type":"Point"}
}