{
  "type": "Feature",
  "properties": {
    "addr:full":"277 B Neilson St Onehunga  Auckland Auckland",
    "addr:housenumber":"277 b",
    "addr:street":"Neilson St",
    "iso:country":"NZ",
    "sg:address":"277 B Neilson St Onehunga ",
    "sg:city":"Auckland",
    "sg:orig_category":"Automotive: Parts And Supplies: Panel Beaters' Supplies",
    "sg:phone":"+64 9-634 2460",
    "sg:province":"Auckland",
    "wof:name":"Auto & Industrial Supplies Ltd",
    "wof:placetype":"venue"
},
  "geometry": {"coordinates":[174.792496,-36.926411],"type":"Point"}
}