{
  "type": "Feature",
  "properties": {
    "iso:country":"NZ",
    "sg:address":"100 Molyneux Ave ",
    "sg:city":"Cromwell",
    "sg:orig_category":"Transport: Land: Taxis",
    "sg:phone":"+64 3-445 1445",
    "wof:name":"Lake Dunstan/Cromwell Taxis",
    "wof:placetype":"venue"
},
  "geometry": {"coordinates":[-72.651642,41.598629],"type":"Point"}
}