{
  "type": "Feature",
  "properties": {
    "addr:full":"Domain Ave  Temuka",
    "addr:street":"Domain Ave",
    "iso:country":"NZ",
    "sg:address":"Domain Ave ",
    "sg:city":"Temuka",
    "sg:orig_category":"Industrial: Packaging: Sacks And Bags",
    "sg:phone":"+64 3-615 9060",
    "wof:name":"Wool & Bag",
    "wof:placetype":"venue"
},
  "geometry": {"coordinates":[171.28222700000001,-44.246677],"type":"Point"}
}