{
  "type": "Feature",
  "properties": {
    "iso:country":"NZ",
    "sg:address":"Verbena Rd Birkdale ",
    "sg:city":"Auckland",
    "sg:classifiers":[
        {
            "category":"Coffee & Tea",
            "type":"Food & Drink"
        }
    ],
    "sg:phone":"+64 9-482 0207",
    "sg:province":"Auckland",
    "sg:tags":[
        "merchant"
    ],
    "wof:name":"Coffee Design",
    "wof:placetype":"venue"
},
  "geometry": {"coordinates":[174.709259,-36.794453],"type":"Point"}
}