{
  "type": "Feature",
  "properties": {
    "iso:country":"NZ",
    "sg:address":"52 Cameron St ",
    "sg:city":"Whangarei",
    "sg:classifiers":[
        {
            "category":"Sports & Exercise",
            "subcategory":"Ski Resort",
            "type":"Entertainment"
        }
    ],
    "sg:phone":"+64 9-438 3082",
    "sg:province":"Northland",
    "sg:tags":[
        "hobbies",
        "photographic",
        "leisure",
        "developing"
    ],
    "wof:name":"Shirley's Photo Centre",
    "wof:placetype":"venue"
},
  "geometry": {"coordinates":[174.321335,-35.725811],"type":"Point"}
}