{
  "type": "Feature",
  "properties": {
    "addr:full":"7 Seaward Rd  Edendale",
    "addr:housenumber":"7",
    "addr:street":"Seaward Rd",
    "iso:country":"NZ",
    "sg:address":"7 Seaward Rd ",
    "sg:city":"Edendale",
    "sg:orig_category":"Food And Drink: Meats: Butchers",
    "sg:phone":"+64 3-206 6827",
    "wof:name":"Edendale Butchery 2000 Ltd",
    "wof:placetype":"venue"
},
  "geometry": {"coordinates":[-118.258545,34.090382],"type":"Point"}
}