{
  "type": "Feature",
  "properties": {
    "addr:full":"PO Box 376  Wanganui Manawatu-Wanganui",
    "addr:housenumber":"po",
    "addr:street":"Box 376",
    "iso:country":"NZ",
    "sg:address":"PO Box 376 ",
    "sg:city":"Wanganui",
    "sg:classifiers":[
        {
            "category":"Sports & Exercise",
            "subcategory":"Sports Center",
            "type":"Entertainment"
        }
    ],
    "sg:phone":"+64 6-348 1440",
    "sg:province":"Manawatu-Wanganui",
    "sg:tags":[
        "sporting",
        "sports",
        "-",
        "leisure",
        "facility"
    ],
    "wof:name":"Cooks Gardens Trust Board Westpac Trust Stadium & Velodrome",
    "wof:placetype":"venue"
},
  "geometry": {"coordinates":[175.052841,-39.933369],"type":"Point"}
}