{
  "type": "Feature",
  "properties": {
    "iso:country":"NZ",
    "sg:address":"Level 4 Westfield Tower 45 Knights Road Lower Hutt, Lower ",
    "sg:city":"Hutt",
    "sg:classifiers":[
        {
            "category":"Banks & Credit Unions",
            "subcategory":"Financial Services",
            "type":"Services"
        }
    ],
    "sg:phone":"+64 4-566 6816",
    "sg:province":"Auckland",
    "sg:tags":[
        "personal",
        "retirement",
        "planning",
        "-",
        "finance"
    ],
    "sg:website":"http://www.forbar.co.nz",
    "wof:name":"Forsyth Barr Ltd",
    "wof:placetype":"venue"
},
  "geometry": {"coordinates":[174.90452575680001,-41.2084312439],"type":"Point"}
}