{
  "type": "Feature",
  "properties": {
    "iso:country":"NZ",
    "sg:address":"11 James St ",
    "sg:city":"Whangarei",
    "sg:classifiers":[
        {
            "category":"Travel",
            "subcategory":"Hotels & Motels",
            "type":"Entertainment"
        }
    ],
    "sg:phone":"+64 9-438 1332",
    "sg:province":"Northland",
    "sg:tags":[
        "tourism",
        "accommodation"
    ],
    "sg:website":"http://www.ljhooker.co.nz/whangarei",
    "wof:name":"Hooker L.J.",
    "wof:placetype":"venue"
},
  "geometry": {"coordinates":[174.32115200000001,-35.725159],"type":"Point"}
}