{
  "type": "Feature",
  "properties": {
    "addr:full":"7 Geange St Upper  Hutt Wellington",
    "addr:housenumber":"7",
    "addr:street":"Geange St",
    "iso:country":"NZ",
    "sg:address":"7 Geange St Upper ",
    "sg:city":"Hutt",
    "sg:classifiers":[
        {
            "category":"Farming",
            "subcategory":"Fish & Marine Products",
            "type":"Manufacturing & Wholesale Goods"
        }
    ],
    "sg:phone":"+64 4-529 8453",
    "sg:province":"Wellington",
    "sg:tags":[
        "equipment",
        "medical",
        "health",
        "products",
        "beauty"
    ],
    "wof:name":"Biomedical Services NZ Ltd",
    "wof:placetype":"venue"
},
  "geometry": {"coordinates":[175.07124300000001,-41.124878],"type":"Point"}
}