{
  "type": "Feature",
  "properties": {
    "addr:full":"87-93 Dixon St  Masterton Wellington",
    "addr:housenumber":"87-93",
    "addr:street":"Dixon St",
    "iso:country":"NZ",
    "sg:address":"87-93 Dixon St ",
    "sg:city":"Masterton",
    "sg:orig_category":"Automotive: General Services: Service Stations",
    "sg:phone":"+64 6-377 5169",
    "sg:province":"Wellington",
    "wof:name":"BP Oil",
    "wof:placetype":"venue"
},
  "geometry": {"coordinates":[175.65927099999999,-40.952911],"type":"Point"}
}