{
  "type": "Feature",
  "properties": {
    "iso:country":"NZ",
    "sg:address":"Onerahi Shopping Centre ",
    "sg:city":"Whangarei",
    "sg:orig_category":"Health And Beauty: Products: Pharmacies",
    "sg:phone":"+64 9-436 0567",
    "sg:province":"Northland",
    "wof:name":"Onerahi Unichem Pharmacy",
    "wof:placetype":"venue"
},
  "geometry": {"coordinates":[174.362869,-35.765949],"type":"Point"}
}