{
  "type": "Feature",
  "properties": {
    "addr:full":"18 Bridge St Edgecumbe  Whakatane Bay of Plenty",
    "addr:housenumber":"18",
    "addr:street":"Bridge St;Whakatane",
    "iso:country":"NZ",
    "sg:address":"18 Bridge St Edgecumbe ",
    "sg:city":"Whakatane",
    "sg:classifiers":[
        {
            "category":"Personal",
            "subcategory":"Massage",
            "type":"Services"
        }
    ],
    "sg:phone":"+64 7-304 8386",
    "sg:province":"Bay of Plenty",
    "sg:tags":[
        "services",
        "health",
        "-",
        "beauty",
        "fitness"
    ],
    "wof:name":"Glo's Remedial Massage",
    "wof:placetype":"venue"
},
  "geometry": {"coordinates":[176.98001099999999,-37.969036],"type":"Point"}
}