{
  "type": "Feature",
  "properties": {
    "iso:country":"NZ",
    "sg:address":"1 Nixon St Grey Lynn ",
    "sg:city":"Auckland",
    "sg:classifiers":[
        {
            "category":"Autos & Motor Vehicles",
            "subcategory":"Automobile Sales",
            "type":"Retail Goods"
        }
    ],
    "sg:phone":"+64 9-360 2911",
    "sg:province":"Auckland",
    "sg:tags":[
        "car",
        "importer",
        "leasing",
        "automotive"
    ],
    "wof:name":"British Vehicle Importers Ltd",
    "wof:placetype":"venue"
},
  "geometry": {"coordinates":[174.73474100000001,-36.861408],"type":"Point"}
}