{
  "type": "Feature",
  "properties": {
    "iso:country":"NZ",
    "sg:address":"37 Mellons Bay Rd Howick ",
    "sg:city":"Auckland",
    "sg:orig_category":"Shopping: Hobbies And Games: Telescopes",
    "sg:phone":"+64 800 333 308",
    "sg:province":"Auckland",
    "wof:name":"Optical Instruments",
    "wof:placetype":"venue"
},
  "geometry": {"coordinates":[174.916946,-36.894379],"type":"Point"}
}