{
  "type": "Feature",
  "properties": {
    "addr:full":"Mountfield Rd Waipu  Whangarei Northland",
    "addr:street":"Mountfield Rd",
    "iso:country":"NZ",
    "sg:address":"Mountfield Rd Waipu ",
    "sg:city":"Whangarei",
    "sg:classifiers":[
        {
            "category":"Manufacturing",
            "subcategory":"Glass & Minerals",
            "type":"Manufacturing & Wholesale Goods"
        }
    ],
    "sg:phone":"+64 9-432 0606",
    "sg:province":"Northland",
    "sg:tags":[
        "raw",
        "industrial",
        "quarry",
        "materials"
    ],
    "wof:name":"Mountfield Quarry",
    "wof:placetype":"venue"
},
  "geometry": {"coordinates":[174.442566,-35.931755],"type":"Point"}
}