{
  "type": "Feature",
  "properties": {
    "iso:country":"NZ",
    "sg:address":"23 Bristol Pl ",
    "sg:city":"Hamilton",
    "sg:orig_category":"Home And Garden: Furniture/Furnishings: Cabinetmakers",
    "sg:phone":"+64 7-849 6636",
    "sg:province":"Waikato",
    "wof:name":"Branchin Out",
    "wof:placetype":"venue"
},
  "geometry": {"coordinates":[-84.603607,39.418964],"type":"Point"}
}