{
  "type": "Feature",
  "properties": {
    "iso:country":"NZ",
    "sg:address":"Weld St ",
    "sg:city":"Hokitika",
    "sg:classifiers":[
        {
            "category":"Shopping",
            "subcategory":"Crafts & Fabrics",
            "type":"Retail Goods"
        }
    ],
    "sg:phone":"+64 3-755 8139",
    "sg:province":"West Coast",
    "sg:tags":[
        "foot",
        "clothing",
        "retailer",
        "footwear",
        "wear"
    ],
    "wof:name":"Oliver's Shoe Store",
    "wof:placetype":"venue"
},
  "geometry": {"coordinates":[170.96464499999999,-42.718636],"type":"Point"}
}