{
  "type": "Feature",
  "properties": {
    "addr:full":"Albert St  Cambridge Waikato",
    "addr:street":"Albert St",
    "iso:country":"NZ",
    "sg:address":"Albert St ",
    "sg:city":"Cambridge",
    "sg:orig_category":"Farming: Machinery: Tractors",
    "sg:phone":"+64 7-827 7159",
    "sg:province":"Waikato",
    "wof:name":"Ross Todd Motors",
    "wof:placetype":"venue"
},
  "geometry": {"coordinates":[-71.130371,42.39677],"type":"Point"}
}