{
  "type": "Feature",
  "properties": {
    "addr:full":"Suite 2 154-156 Remuera Rd Newmarket  Auckland Auckland",
    "addr:housenumber":"suite 2",
    "addr:postcode":"154-156",
    "addr:street":"Remuera Rd",
    "iso:country":"NZ",
    "sg:address":"Suite 2 154-156 Remuera Rd Newmarket ",
    "sg:city":"Auckland",
    "sg:orig_category":"Home And Garden",
    "sg:phone":"+64 9-522 7350",
    "sg:province":"Auckland",
    "sg:website":"http://www.yellowpages.co.nz/for/fieldingdave/dp22642.html",
    "wof:name":"Fielding Dave Financial Services",
    "wof:placetype":"venue"
},
  "geometry": {"coordinates":[174.77870200000001,-36.870819],"type":"Point"}
}