{
  "type": "Feature",
  "properties": {
    "iso:country":"NZ",
    "sg:address":"12 Beaumont St Auckland Central ",
    "sg:city":"Auckland",
    "sg:classifiers":[
        {
            "category":"Retail",
            "subcategory":"Auto Repair",
            "type":"Services"
        }
    ],
    "sg:phone":"+64 9-358 3577",
    "sg:province":"Auckland",
    "sg:tags":[
        "automotive",
        "panel",
        "servicing",
        "beater"
    ],
    "wof:name":"Bodyworks Panelbeaters Ltd",
    "wof:placetype":"venue"
},
  "geometry": {"coordinates":[174.753052,-36.844482],"type":"Point"}
}