{
  "type": "Feature",
  "properties": {
    "addr:full":"cnr Bryant Rd & Norris Ave  Hamilton Waikato",
    "addr:street":"Cnr Bryant Rd & Norris Ave",
    "iso:country":"NZ",
    "sg:address":"cnr Bryant Rd & Norris Ave ",
    "sg:city":"Hamilton",
    "sg:classifiers":[
        {
            "category":"Home & Garden",
            "subcategory":"Furniture",
            "type":"Retail Goods"
        }
    ],
    "sg:phone":"+64 7-849 1239",
    "sg:province":"Waikato",
    "sg:tags":[
        "fitting"
    ],
    "sg:website":"http://www.yellowpages.co.nz/for/plycodoors/dp22948.html",
    "wof:name":"Door Styles",
    "wof:placetype":"venue"
},
  "geometry": {"coordinates":[175.276993,-37.783211],"type":"Point"}
}