{
  "type": "Feature",
  "properties": {
    "iso:country":"NZ",
    "sg:address":"134 Gorge Rd ",
    "sg:city":"Queenstown",
    "sg:classifiers":[
        {
            "category":"Shopping",
            "subcategory":"Crafts & Fabrics",
            "type":"Retail Goods"
        }
    ],
    "sg:phone":"+64 3-442 7216",
    "sg:province":"Otago",
    "sg:tags":[
        "clothing"
    ],
    "sg:website":"http://www.ajhackett.com",
    "wof:name":"AJ Gear",
    "wof:placetype":"venue"
},
  "geometry": {"coordinates":[168.662277,-45.020836],"type":"Point"}
}