{
  "type": "Feature",
  "properties": {
    "iso:country":"NZ",
    "sg:address":"2 Goodbehere St Feilding ",
    "sg:city":"Rangiwahia",
    "sg:orig_category":"Health And Beauty: Mental: Psychotherapy",
    "sg:phone":"+64 6-328 2777",
    "wof:name":"Dalhanna Consulting",
    "wof:placetype":"venue"
},
  "geometry": {"coordinates":[175.900558,-39.89875],"type":"Point"}
}