{
  "type": "Feature",
  "properties": {
    "iso:country":"NZ",
    "sg:address":"PO Box 12-564 Penrose ",
    "sg:city":"Auckland",
    "sg:classifiers":[
        {
            "category":"Banks & Credit Unions",
            "subcategory":"Financial Services",
            "type":"Services"
        }
    ],
    "sg:phone":"+64 9-579 1026",
    "sg:province":"Auckland",
    "sg:tags":[
        "finance"
    ],
    "sg:website":"http://www.cua.co.nz",
    "wof:name":"Credit Union Auckland",
    "wof:placetype":"venue"
},
  "geometry": {"coordinates":[174.770416,-36.884109],"type":"Point"}
}