{
  "type": "Feature",
  "properties": {
    "iso:country":"NZ",
    "sg:address":"183 Old Renwick Rd ",
    "sg:city":"Blenheim",
    "sg:classifiers":[
        {
            "category":"Coffee & Tea",
            "type":"Food & Drink"
        }
    ],
    "sg:phone":"+64 3-578 7022",
    "sg:province":"Marlborough",
    "sg:tags":[
        "vegetable",
        "fruit",
        "veges"
    ],
    "wof:name":"Jones Berryfruits & Asian Foods",
    "wof:placetype":"venue"
},
  "geometry": {"coordinates":[173.924988,-41.49963],"type":"Point"}
}