{
  "type": "Feature",
  "properties": {
    "iso:country":"NZ",
    "sg:address":"PO Box 64 ",
    "sg:city":"Balfour",
    "sg:orig_category":"Farming: Agriculture",
    "sg:phone":"+64 3-201 6494",
    "wof:name":"McKenzie Spraying Co",
    "wof:placetype":"venue"
},
  "geometry": {"coordinates":[-100.534088,47.9492],"type":"Point"}
}