{
  "type": "Feature",
  "properties": {
    "addr:full":"PO Box 78209 Grey Lynn  Auckland Auckland",
    "addr:housenumber":"po box 78209",
    "iso:country":"NZ",
    "sg:address":"PO Box 78209 Grey Lynn ",
    "sg:city":"Auckland",
    "sg:classifiers":[
        {
            "category":"Professional",
            "subcategory":"Management & Consulting",
            "type":"Services"
        }
    ],
    "sg:phone":"+64 9-360 0257",
    "sg:province":"Auckland",
    "sg:tags":[
        "consultant",
        "training",
        "education"
    ],
    "wof:name":"Teuila Consultancy",
    "wof:placetype":"venue"
},
  "geometry": {"coordinates":[174.73474100000001,-36.861408],"type":"Point"}
}