{
  "type": "Feature",
  "properties": {
    "addr:full":"Cnr Park & Grafton Rds Grafton  Auckland Auckland",
    "addr:street":"Cnr Park & Grafton Rds",
    "iso:country":"NZ",
    "sg:address":"Cnr Park & Grafton Rds Grafton ",
    "sg:city":"Auckland",
    "sg:orig_category":"Travel And Tourism: Accommodation: Hostels",
    "sg:phone":"+64 9-377 1345",
    "sg:province":"Auckland",
    "wof:name":"Huia Residence",
    "wof:placetype":"venue"
},
  "geometry": {"coordinates":[174.76547199999999,-36.862888],"type":"Point"}
}