{
  "type": "Feature",
  "properties": {
    "addr:full":"BT Client Service Line 23-29 Albert St Auckland PO, Box 6088 Wellesley  Street",
    "addr:housenumber":"23-29;po box 6088",
    "addr:street":"Albert St;Wellesley Street",
    "iso:country":"NZ",
    "sg:address":"BT Client Service Line 23-29 Albert St Auckland PO, Box 6088 Wellesley ",
    "sg:city":"Street",
    "sg:classifiers":[
        {
            "category":"Banks & Credit Unions",
            "subcategory":"Investment Brokerage",
            "type":"Services"
        }
    ],
    "sg:phone":"+64 800 800 661",
    "sg:tags":[
        "personal",
        "-",
        "finance"
    ],
    "sg:website":"http://www.btonline.co.nz",
    "wof:name":"BT Funds Management",
    "wof:placetype":"venue"
},
  "geometry": {"coordinates":[-119.104584,36.59774],"type":"Point"}
}