{
  "type": "Feature",
  "properties": {
    "addr:full":"14 Garden Pl  Hamilton Waikato",
    "addr:housenumber":"14",
    "addr:street":"Garden Pl",
    "iso:country":"NZ",
    "sg:address":"14 Garden Pl ",
    "sg:city":"Hamilton",
    "sg:classifiers":[
        {
            "category":"Coffee & Tea",
            "type":"Food & Drink"
        }
    ],
    "sg:phone":"+64 7-839 3055",
    "sg:province":"Waikato",
    "sg:tags":[
        "merchant"
    ],
    "wof:name":"Urge",
    "wof:placetype":"venue"
},
  "geometry": {"coordinates":[-74.702591,40.198151],"type":"Point"}
}