{
  "type": "Feature",
  "properties": {
    "addr:full":"20 Robson St  Normanby",
    "addr:housenumber":"20",
    "addr:street":"Robson St",
    "iso:country":"NZ",
    "sg:address":"20 Robson St ",
    "sg:city":"Normanby",
    "sg:classifiers":[
        {
            "category":"Building & Trades",
            "subcategory":"Construction",
            "type":"Services"
        }
    ],
    "sg:phone":"+64 274 458 708",
    "sg:tags":[
        "home",
        "garden",
        "related",
        "plasterer"
    ],
    "wof:name":"Abels Plastering and Contracting",
    "wof:placetype":"venue"
},
  "geometry": {"coordinates":[174.27179000000001,-39.544128],"type":"Point"}
}