{
  "type": "Feature",
  "properties": {
    "iso:country":"NZ",
    "sg:address":"39G Victoria St ",
    "sg:city":"Cambridge",
    "sg:orig_category":"Shopping: Retail Stores: Antiques",
    "sg:phone":"+64 7-823 0905",
    "sg:province":"Waikato",
    "wof:name":"Red, White & Blue Collectables",
    "wof:placetype":"venue"
},
  "geometry": {"coordinates":[-81.470535,40.034199],"type":"Point"}
}