{
  "type": "Feature",
  "properties": {
    "iso:country":"NZ",
    "sg:address":"75 Cambridge Tce ",
    "sg:city":"Christchurch",
    "sg:classifiers":[
        {
            "category":"Health Services",
            "subcategory":"Dentist",
            "type":"Services"
        }
    ],
    "sg:phone":"+64 3-366 1948",
    "sg:province":"Canterbury",
    "sg:tags":[
        "dental",
        "beauty"
    ],
    "sg:website":"http://www.smileco.co.nz",
    "wof:name":"The Smile Company Dental Care",
    "wof:placetype":"venue"
},
  "geometry": {"coordinates":[172.63176,-43.533772],"type":"Point"}
}