{
  "type": "Feature",
  "properties": {
    "addr:full":"252 The Strand  Whakatane Auckland",
    "addr:housenumber":"252",
    "addr:street":"The Strand",
    "iso:country":"NZ",
    "sg:address":"252 The Strand ",
    "sg:city":"Whakatane",
    "sg:orig_category":"Health And Beauty: Specialists: Podiatrists",
    "sg:phone":"+64 7-308 8267",
    "sg:province":"Auckland",
    "wof:name":"Whakatane Foot Clinic",
    "wof:placetype":"venue"
},
  "geometry": {"coordinates":[176.992828,-37.95237],"type":"Point"}
}