{
  "type": "Feature",
  "properties": {
    "iso:country":"NZ",
    "sg:address":"915 Tremaine Ave Palmerston ",
    "sg:city":"Palmerston North",
    "sg:orig_category":"Farming: Services: Irrigation",
    "sg:phone":"+64 6-356 1521",
    "sg:province":"Manawatu-Wanganui",
    "wof:name":"Water Dynamics",
    "wof:placetype":"venue"
},
  "geometry": {"coordinates":[175.626953,-40.331848],"type":"Point"}
}