{
  "type": "Feature",
  "properties": {
    "addr:full":"3 Devon Lane Alison Court Fleet St Devonport  Auckland Auckland",
    "addr:housenumber":"3",
    "addr:street":"Devon Lane Alison Court Fleet St",
    "iso:country":"NZ",
    "sg:address":"3 Devon Lane Alison Court Fleet St Devonport ",
    "sg:city":"Auckland",
    "sg:classifiers":[
        {
            "category":"Banks & Credit Unions",
            "subcategory":"Investment Brokerage",
            "type":"Services"
        }
    ],
    "sg:phone":"+64 9-445 2094",
    "sg:province":"Auckland",
    "sg:tags":[
        "personal",
        "accountant",
        "chartered",
        "-",
        "finance"
    ],
    "wof:name":"Handisides M K",
    "wof:placetype":"venue"
},
  "geometry": {"coordinates":[174.79714999999999,-36.8297],"type":"Point"}
}