{
  "type": "Feature",
  "properties": {
    "iso:country":"NZ",
    "sg:address":"25-27 Wigan St Te Aro ",
    "sg:city":"Wellington",
    "sg:classifiers":[
        {
            "category":"Manufacturing",
            "subcategory":"Rubber & Plastics",
            "type":"Manufacturing & Wholesale Goods"
        }
    ],
    "sg:phone":"+64 4-384 6647",
    "sg:province":"Wellington",
    "sg:tags":[
        "welder",
        "industrial",
        "-",
        "goods"
    ],
    "sg:website":"http://www.yellowpages.co.nz/for/mayfairauto/dp13280.html",
    "wof:name":"Mayfair Collision Repairs",
    "wof:placetype":"venue"
},
  "geometry": {"coordinates":[174.77516199999999,-41.29615],"type":"Point"}
}