{
  "type": "Feature",
  "properties": {
    "iso:country":"NZ",
    "sg:address":"368 Gladstone Rd ",
    "sg:city":"Gisborne",
    "sg:classifiers":[
        {
            "category":"Autos & Motor Vehicles",
            "subcategory":"Motorcycle Sales",
            "type":"Retail Goods"
        }
    ],
    "sg:phone":"+64 6-868 9109",
    "sg:province":"Gisborne",
    "sg:tags":[
        "automotive",
        "scooter",
        "leasing"
    ],
    "wof:name":"Gisborne Honda Motorcycles",
    "wof:placetype":"venue"
},
  "geometry": {"coordinates":[178.01828,-38.66098],"type":"Point"}
}