{
  "type": "Feature",
  "properties": {
    "iso:country":"NZ",
    "sg:address":"Inside Unitec Carrington Rd Mt Albert ",
    "sg:city":"Auckland",
    "sg:classifiers":[
        {
            "category":"Sports & Exercise",
            "subcategory":"Sports Center",
            "type":"Entertainment"
        }
    ],
    "sg:phone":"+64 9-815 8602",
    "sg:province":"Auckland",
    "sg:tags":[
        "sporting",
        "sports",
        "-",
        "leisure",
        "facility"
    ],
    "wof:name":"National Squash Centre",
    "wof:placetype":"venue"
},
  "geometry": {"coordinates":[174.71479797360001,-36.887840271],"type":"Point"}
}