{
  "type": "Feature",
  "properties": {
    "addr:full":"Pohara  Takaka",
    "iso:country":"NZ",
    "sg:address":"Pohara ",
    "sg:city":"Takaka",
    "sg:classifiers":[
        {
            "category":"Travel",
            "subcategory":"Travel Agent",
            "type":"Entertainment"
        }
    ],
    "sg:phone":"+64 3-525 9095",
    "sg:tags":[
        "tour",
        "tourism",
        "adventure",
        "sightseeing"
    ],
    "wof:name":"Golden Bay Kayaks",
    "wof:placetype":"venue"
},
  "geometry": {"coordinates":[172.880875,-40.833981],"type":"Point"}
}