{
  "type": "Feature",
  "properties": {
    "addr:full":"20 Mayville Ave New Lynn  Auckland Auckland",
    "addr:housenumber":"20",
    "addr:street":"Mayville Ave",
    "iso:country":"NZ",
    "sg:address":"20 Mayville Ave New Lynn ",
    "sg:city":"Auckland",
    "sg:classifiers":[
        {
            "category":"Banks & Credit Unions",
            "subcategory":"Investment Brokerage",
            "type":"Services"
        }
    ],
    "sg:phone":"+64 9-827 4748",
    "sg:province":"Auckland",
    "sg:tags":[
        "educational",
        "education",
        "training"
    ],
    "wof:name":"Oaklynn Special School",
    "wof:placetype":"venue"
},
  "geometry": {"coordinates":[174.682312,-36.918411],"type":"Point"}
}