{
  "type": "Feature",
  "properties": {
    "iso:country":"NZ",
    "sg:address":"463 Jackson St Petone ",
    "sg:city":"Wellington",
    "sg:classifiers":[
        {
            "category":"Manufacturing",
            "subcategory":"Rubber & Plastics",
            "type":"Manufacturing & Wholesale Goods"
        }
    ],
    "sg:phone":"+64 4-939 6276",
    "sg:province":"Wellington",
    "sg:tags":[
        "industrial"
    ],
    "wof:name":"Marnick Plastics 1980 Ltd",
    "wof:placetype":"venue"
},
  "geometry": {"coordinates":[174.89631700000001,-41.230549],"type":"Point"}
}