{
  "type": "Feature",
  "properties": {
    "iso:country":"NZ",
    "sg:address":"59 Clarence St ",
    "sg:city":"Hamilton",
    "sg:classifiers":[
        {
            "category":"Shopping",
            "subcategory":"Clothing, Apparel, & Fashions",
            "type":"Retail Goods"
        }
    ],
    "sg:phone":"+64 7-839 3082",
    "sg:province":"Waikato",
    "sg:tags":[
        "-",
        "hire",
        "clothing",
        "fabric"
    ],
    "wof:name":"Hamilton Operatic Society Inc",
    "wof:placetype":"venue"
},
  "geometry": {"coordinates":[175.282501,-37.794598],"type":"Point"}
}