{
  "type": "Feature",
  "properties": {
    "addr:full":"400 Tuam St  Christchurch Canterbury",
    "addr:housenumber":"400",
    "addr:street":"Tuam St",
    "iso:country":"NZ",
    "sg:address":"400 Tuam St ",
    "sg:city":"Christchurch",
    "sg:classifiers":[
        {
            "category":"Professional",
            "type":"Services"
        }
    ],
    "sg:phone":"+64 3-374 6461",
    "sg:province":"Canterbury",
    "sg:tags":[
        "services",
        "car",
        "valet",
        "automotive"
    ],
    "wof:name":"B & K Groomers",
    "wof:placetype":"venue"
},
  "geometry": {"coordinates":[172.652298,-43.535603],"type":"Point"}
}