{
  "type": "Feature",
  "properties": {
    "iso:country":"NZ",
    "sg:address":"52 Antrim Cre Wainuiomata Lower ",
    "sg:city":"Hutt",
    "sg:classifiers":[
        {
            "category":"Home & Garden",
            "subcategory":"Garden Supply",
            "type":"Retail Goods"
        }
    ],
    "sg:phone":"+64 4-564 9014",
    "sg:province":"Wellington",
    "sg:tags":[
        "trainer",
        "breeder",
        "/",
        "pets",
        "animal"
    ],
    "wof:name":"Canine Solutions",
    "wof:placetype":"venue"
},
  "geometry": {"coordinates":[174.950836,-41.261421],"type":"Point"}
}