{
  "type": "Feature",
  "properties": {
    "iso:country":"NZ",
    "sg:address":"84 Falsgrave St ",
    "sg:city":"Christchurch",
    "sg:orig_category":"Industrial: Abrasives: Abrasive Blasting",
    "sg:phone":"+64 3-379 5017",
    "sg:province":"Canterbury",
    "wof:name":"Iron Crafts 2002",
    "wof:placetype":"venue"
},
  "geometry": {"coordinates":[-76.537834,37.605659],"type":"Point"}
}