{
  "type": "Feature",
  "properties": {
    "iso:country":"NZ",
    "sg:address":"242/7 Henderson Sq Henderson ",
    "sg:city":"Auckland",
    "sg:classifiers":[
        {
            "category":"Shopping",
            "subcategory":"Crafts & Fabrics",
            "type":"Retail Goods"
        }
    ],
    "sg:phone":"+64 9-836 2897",
    "sg:province":"Auckland",
    "sg:tags":[
        "foot",
        "clothing",
        "retailer",
        "footwear",
        "wear"
    ],
    "wof:name":"Overland Footwear",
    "wof:placetype":"venue"
},
  "geometry": {"coordinates":[174.63295,-36.877289],"type":"Point"}
}