{
  "type": "Feature",
  "properties": {
    "addr:full":"OTATARA  Invercargill Southland",
    "iso:country":"NZ",
    "sg:address":"OTATARA ",
    "sg:city":"Invercargill",
    "sg:orig_category":"Health And Beauty: Specialists: Midwives",
    "sg:phone":"+64 3-213 0892",
    "sg:province":"Southland",
    "wof:name":"Bernadette Archer",
    "wof:placetype":"venue"
},
  "geometry": {"coordinates":[168.284683,-46.434555],"type":"Point"}
}