{
  "type": "Feature",
  "properties": {
    "iso:country":"NZ",
    "sg:address":"62 Jervois Rd ",
    "sg:city":"Auckland",
    "sg:classifiers":[
        {
            "category":"Retail",
            "subcategory":"Laundry & Dry Cleaning",
            "type":"Services"
        }
    ],
    "sg:phone":"+64 9-376 3297",
    "sg:province":"Auckland",
    "sg:tags":[
        "repair",
        "clothing",
        "fabric",
        "cleaner"
    ],
    "wof:name":"New Zealand Drycleaners",
    "wof:placetype":"venue"
},
  "geometry": {"coordinates":[174.730164,-36.848415],"type":"Point"}
}