{
  "type": "Feature",
  "properties": {
    "addr:full":"190 Hereford St  Christchurch Canterbury",
    "addr:housenumber":"190",
    "addr:street":"Hereford St",
    "iso:country":"NZ",
    "sg:address":"190 Hereford St ",
    "sg:city":"Christchurch",
    "sg:classifiers":[
        {
            "category":"Personal",
            "type":"Services"
        }
    ],
    "sg:phone":"+64 3-366 6944",
    "sg:province":"Canterbury",
    "sg:tags":[
        "services",
        "home",
        "garden",
        "counselling"
    ],
    "wof:name":"Child Helpline",
    "wof:placetype":"venue"
},
  "geometry": {"coordinates":[172.640488,-43.532162],"type":"Point"}
}