{
  "type": "Feature",
  "properties": {
    "addr:full":"241 Stanley Rd  Gisborne Gisborne",
    "addr:housenumber":"241",
    "addr:street":"Stanley Rd",
    "iso:country":"NZ",
    "sg:address":"241 Stanley Rd ",
    "sg:city":"Gisborne",
    "sg:classifiers":[
        {
            "category":"Food & Beverages",
            "subcategory":"Groceries & Convenience Stores",
            "type":"Retail Goods"
        }
    ],
    "sg:phone":"+64 21 2151 608",
    "sg:province":"Gisborne",
    "sg:tags":[
        "foodstuff",
        "drink",
        "-"
    ],
    "wof:name":"Barber Distributors",
    "wof:placetype":"venue"
},
  "geometry": {"coordinates":[178.00401299999999,-38.668133],"type":"Point"}
}