{
  "type": "Feature",
  "properties": {
    "iso:country":"NZ",
    "sg:address":"Rivington Farm Main Rd R D 1 Wakapuaka ",
    "sg:city":"Nelson",
    "sg:classifiers":[
        {
            "category":"Sports & Exercise",
            "subcategory":"Tennis Court",
            "type":"Entertainment"
        }
    ],
    "sg:phone":"+64 3-545 1045",
    "sg:province":"Nelson",
    "sg:tags":[
        "hobby",
        "leisure"
    ],
    "wof:name":"Rivington Wares Quilts & Crafts",
    "wof:placetype":"venue"
},
  "geometry": {"coordinates":[173.28396599999999,-41.27227],"type":"Point"}
}