{
  "type": "Feature",
  "properties": {
    "iso:country":"NZ",
    "sg:address":"84 Leet St ",
    "sg:city":"Invercargill",
    "sg:classifiers":[
        {
            "category":"Autos & Motor Vehicles",
            "subcategory":"Motorcycle Sales",
            "type":"Retail Goods"
        }
    ],
    "sg:phone":"+64 3-218 9584",
    "sg:province":"Southland",
    "sg:tags":[
        "automotive",
        "scooter",
        "leasing"
    ],
    "wof:name":"Rogers Yamaha",
    "wof:placetype":"venue"
},
  "geometry": {"coordinates":[168.352127,-46.407303],"type":"Point"}
}