{
  "type": "Feature",
  "properties": {
    "iso:country":"NZ",
    "sg:address":"PO Box 11 ",
    "sg:city":"Bluff",
    "sg:classifiers":[
        {
            "category":"Social Services",
            "subcategory":"Job Training",
            "type":"Services"
        }
    ],
    "sg:phone":"+64 3-212 7437",
    "sg:tags":[
        "education"
    ],
    "wof:name":"Bluff Marine Centre Ltd",
    "wof:placetype":"venue"
},
  "geometry": {"coordinates":[-84.959877,31.521713],"type":"Point"}
}