{
  "type": "Feature",
  "properties": {
    "addr:full":"14 The Centre Waipu  Whangarei Northland",
    "addr:housenumber":"14",
    "addr:street":"The Centre",
    "iso:country":"NZ",
    "sg:address":"14 The Centre Waipu ",
    "sg:city":"Whangarei",
    "sg:orig_category":"Shopping: Retail Stores: Stationery",
    "sg:phone":"+64 9-432 0900",
    "sg:province":"Northland",
    "wof:name":"Waipu Stationery & Lotto",
    "wof:placetype":"venue"
},
  "geometry": {"coordinates":[174.44288599999999,-35.986801],"type":"Point"}
}