{
  "type": "Feature",
  "properties": {
    "iso:country":"NZ",
    "sg:address":"2 Rabone St Henderson ",
    "sg:city":"Auckland",
    "sg:classifiers":[
        {
            "category":"Home & Garden",
            "subcategory":"Hardware",
            "type":"Retail Goods"
        }
    ],
    "sg:phone":"+64 9-836 0788",
    "sg:province":"Auckland",
    "sg:tags":[
        "track",
        "furniture/furnishings",
        "rod",
        "curtain"
    ],
    "wof:name":"Selecon-Reid",
    "wof:placetype":"venue"
},
  "geometry": {"coordinates":[174.630508,-36.886684],"type":"Point"}
}