{
  "type": "Feature",
  "properties": {
    "addr:full":"9 Nursery La  Seddon",
    "addr:housenumber":"9",
    "addr:street":"Nursery La Seddon",
    "iso:country":"NZ",
    "sg:address":"9 Nursery La ",
    "sg:city":"Seddon",
    "sg:classifiers":[
        {
            "category":"Bars & Pubs",
            "subcategory":"Lounge",
            "type":"Food & Drink"
        }
    ],
    "sg:phone":"+64 25432914",
    "sg:tags":[
        "baker",
        "-"
    ],
    "wof:name":"Flaxmill Bakery",
    "wof:placetype":"venue"
},
  "geometry": {"coordinates":[-86.229118,33.59137],"type":"Point"}
}