{
  "type": "Feature",
  "properties": {
    "iso:country":"NZ",
    "sg:address":"Rimu St Kerepehi ",
    "sg:city":"Ngatea",
    "sg:orig_category":"Home And Garden: Gardening: Products: Fertilisers",
    "sg:phone":"+64 7-867 6623",
    "wof:name":"Kerepehi Transport",
    "wof:placetype":"venue"
},
  "geometry": {"coordinates":[175.54451,-37.300175],"type":"Point"}
}