{
  "type": "Feature",
  "properties": {
    "addr:full":"304 Apirana Ave Glen Innes  Auckland Auckland",
    "addr:housenumber":"304",
    "addr:street":"Apirana Ave",
    "iso:country":"NZ",
    "sg:address":"304 Apirana Ave Glen Innes ",
    "sg:city":"Auckland",
    "sg:orig_category":"Automotive: General Services: Service Stations",
    "sg:phone":"+64 9-570 1513",
    "sg:province":"Auckland",
    "wof:name":"Mobil Glen Innes",
    "wof:placetype":"venue"
},
  "geometry": {"coordinates":[174.85269199999999,-36.87183],"type":"Point"}
}