{
  "type": "Feature",
  "properties": {
    "addr:full":"6 Miro St Upper  Hutt Wellington",
    "addr:housenumber":"6",
    "addr:street":"Miro St",
    "iso:country":"NZ",
    "sg:address":"6 Miro St Upper ",
    "sg:city":"Hutt",
    "sg:classifiers":[
        {
            "category":"Professional",
            "subcategory":"Detective & Security Services",
            "type":"Services"
        }
    ],
    "sg:phone":"+64 4-528 5873",
    "sg:province":"Wellington",
    "sg:tags":[
        "services",
        "automotive",
        "warrant",
        "fitness"
    ],
    "wof:name":"Miro Auto Services (1998) Ltd",
    "wof:placetype":"venue"
},
  "geometry": {"coordinates":[175.069031,-41.12458],"type":"Point"}
}