{
  "type": "Feature",
  "properties": {
    "addr:full":"15 Green St Tahunanui  Nelson Nelson",
    "addr:housenumber":"15",
    "addr:street":"Green St",
    "iso:country":"NZ",
    "sg:address":"15 Green St Tahunanui ",
    "sg:city":"Nelson",
    "sg:orig_category":"Storage: Storage",
    "sg:phone":"+64 3-546 4159",
    "sg:province":"Nelson",
    "wof:name":"Nelson Mini Storage",
    "wof:placetype":"venue"
},
  "geometry": {"coordinates":[173.24543800000001,-41.288876],"type":"Point"}
}