{
  "type": "Feature",
  "properties": {
    "addr:full":"Railway Settlement S.H. 12  Maungaturoto",
    "addr:street":"Railway Settlement S.H. 12 Maungaturoto",
    "iso:country":"NZ",
    "sg:address":"Railway Settlement S.H. 12 ",
    "sg:city":"Maungaturoto",
    "sg:orig_category":"Farming: Machinery: Farm Machinery",
    "sg:phone":"+64 9-431 1020",
    "wof:name":"Transpread Company Ltd",
    "wof:placetype":"venue"
},
  "geometry": {"coordinates":[174.353973,-36.110321],"type":"Point"}
}