{
  "type": "Feature",
  "properties": {
    "addr:full":"73 McDonnell Rd  Arrowtown Otago",
    "addr:housenumber":"73",
    "addr:street":"Mcdonnell Rd",
    "iso:country":"NZ",
    "sg:address":"73 McDonnell Rd ",
    "sg:city":"Arrowtown",
    "sg:orig_category":"Home And Garden: Outdoor: Stonemasons",
    "sg:phone":"+64 3-442 0128",
    "sg:province":"Otago",
    "wof:name":"Glen Dennison Stone Mason",
    "wof:placetype":"venue"
},
  "geometry": {"coordinates":[168.83209199999999,-44.946819],"type":"Point"}
}