{
  "type": "Feature",
  "properties": {
    "iso:country":"NZ",
    "sg:address":"917 Devon Rd Bell Block New ",
    "sg:city":"Plymouth",
    "sg:classifiers":[
        {
            "category":"Social Services",
            "subcategory":"Retirement Home",
            "type":"Services"
        }
    ],
    "sg:phone":"+64 6-755 0558",
    "sg:province":"Taranaki",
    "sg:tags":[
        "care",
        "garden",
        "elderly",
        "village"
    ],
    "wof:name":"Maida Vale Retirement Village",
    "wof:placetype":"venue"
},
  "geometry": {"coordinates":[174.141205,-39.035595],"type":"Point"}
}