{
  "type": "Feature",
  "properties": {
    "addr:full":"137 Victoria St  Christchurch Canterbury",
    "addr:housenumber":"137",
    "addr:street":"Victoria St",
    "iso:country":"NZ",
    "sg:address":"137 Victoria St ",
    "sg:city":"Christchurch",
    "sg:classifiers":[
        {
            "category":"Social Services",
            "subcategory":"Job Training",
            "type":"Services"
        }
    ],
    "sg:phone":"+64 3-365 9335",
    "sg:province":"Canterbury",
    "sg:tags":[
        "education"
    ],
    "wof:name":"George Francis & Associates",
    "wof:placetype":"venue"
},
  "geometry": {"coordinates":[-76.537834,37.605659],"type":"Point"}
}