{
  "type": "Feature",
  "properties": {
    "iso:country":"NZ",
    "sg:address":"274 Gloucester St Taradale ",
    "sg:city":"Napier",
    "sg:classifiers":[
        {
            "category":"Bars & Pubs",
            "subcategory":"Lounge",
            "type":"Food & Drink"
        }
    ],
    "sg:phone":"+64 6-845 2388",
    "sg:province":"Hawke's Bay",
    "sg:tags":[
        "baker",
        "-"
    ],
    "wof:name":"New Century Bakery",
    "wof:placetype":"venue"
},
  "geometry": {"coordinates":[176.84863300000001,-39.535816],"type":"Point"}
}