{
  "type": "Feature",
  "properties": {
    "iso:country":"NZ",
    "sg:address":"11 Opawa Rd Opawa ",
    "sg:city":"Christchurch",
    "sg:orig_category":"Automotive: General Services: Service Stations",
    "sg:phone":"+64 3-379 5549",
    "sg:province":"Canterbury",
    "wof:name":"Opawa Garage Ltd",
    "wof:placetype":"venue"
},
  "geometry": {"coordinates":[172.65934799999999,-43.550301],"type":"Point"}
}