{
  "type": "Feature",
  "properties": {
    "addr:full":"Big Top Assid Corban Recreation Centre Alderman Dve, Henderson  Auckland Auckland",
    "addr:street":"Dve",
    "iso:country":"NZ",
    "sg:address":"Big Top Assid Corban Recreation Centre Alderman Dve, Henderson ",
    "sg:city":"Auckland",
    "sg:classifiers":[
        {
            "category":"Education",
            "subcategory":"Music School",
            "type":"Public Place"
        }
    ],
    "sg:phone":"+64 9-838 7294",
    "sg:province":"Auckland",
    "sg:tags":[
        "sport",
        "teacher",
        "leisure"
    ],
    "wof:name":"Music Education Centre",
    "wof:placetype":"venue"
},
  "geometry": {"coordinates":[174.80403100000001,-36.970119],"type":"Point"}
}