{
  "type": "Feature",
  "properties": {
    "addr:full":"cnr Gaunt & Beaumont St Westhaven  Auckland Auckland",
    "addr:street":"Cnr Gaunt & Beaumont St",
    "iso:country":"NZ",
    "sg:address":"cnr Gaunt & Beaumont St Westhaven ",
    "sg:city":"Auckland",
    "sg:orig_category":"Industrial: Engineering: Engineers: Engineers Supplies",
    "sg:phone":"+64 9-377 7517",
    "sg:province":"Auckland",
    "wof:name":"Teleflex Morse (NZ) Ltd",
    "wof:placetype":"venue"
},
  "geometry": {"coordinates":[174.754456,-36.841389],"type":"Point"}
}