{
  "type": "Feature",
  "properties": {
    "addr:full":"76 Virginia Rd  Wanganui Manawatu-Wanganui",
    "addr:housenumber":"76",
    "addr:street":"Virginia Rd",
    "iso:country":"NZ",
    "sg:address":"76 Virginia Rd ",
    "sg:city":"Wanganui",
    "sg:classifiers":[
        {
            "category":"Manufacturing",
            "subcategory":"Tools & Machinery",
            "type":"Manufacturing & Wholesale Goods"
        }
    ],
    "sg:phone":"+64 6-345 5738",
    "sg:province":"Manawatu-Wanganui",
    "sg:tags":[
        "equipment",
        "industrial",
        "label"
    ],
    "wof:name":"Imprint Systems Ltd",
    "wof:placetype":"venue"
},
  "geometry": {"coordinates":[175.027008,-39.908798],"type":"Point"}
}