{
  "type": "Feature",
  "properties": {
    "addr:full":"Bridge St  Tokoroa",
    "addr:street":"Bridge St",
    "iso:country":"NZ",
    "sg:address":"Bridge St ",
    "sg:city":"Tokoroa",
    "sg:classifiers":[
        {
            "category":"Shopping",
            "subcategory":"Crafts & Fabrics",
            "type":"Retail Goods"
        }
    ],
    "sg:phone":"+64 7-886 6530",
    "sg:tags":[
        "foot",
        "clothing",
        "retailer",
        "footwear",
        "wear"
    ],
    "wof:name":"Hannahs Shoe Shop",
    "wof:placetype":"venue"
},
  "geometry": {"coordinates":[175.86496,-38.219837],"type":"Point"}
}