{
  "type": "Feature",
  "properties": {
    "iso:country":"NZ",
    "sg:address":"Dixon St ",
    "sg:city":"Masterton",
    "sg:orig_category":"Automotive: General Services: Service Stations",
    "sg:phone":"+64 6-377 5169",
    "sg:province":"Wellington",
    "sg:website":"http://www.waggs.co.nz",
    "wof:name":"Waggs Of Masterton",
    "wof:placetype":"venue"
},
  "geometry": {"coordinates":[175.662857,-40.950459],"type":"Point"}
}