{
  "type": "Feature",
  "properties": {
    "iso:country":"NZ",
    "sg:address":"10 Victory Rd Laingholm ",
    "sg:city":"Auckland",
    "sg:orig_category":"Health And Beauty: Mental: Psychology",
    "sg:phone":"+64 9-817 5947",
    "sg:province":"Auckland",
    "wof:name":"Dieter Dvorak",
    "wof:placetype":"venue"
},
  "geometry": {"coordinates":[174.624619,-36.958302],"type":"Point"}
}