{
  "type": "Feature",
  "properties": {
    "addr:full":"28 Dungarvon St  Wanaka Otago",
    "addr:housenumber":"28",
    "addr:street":"Dungarvon St",
    "iso:country":"NZ",
    "sg:address":"28 Dungarvon St ",
    "sg:city":"Wanaka",
    "sg:orig_category":"Health And Beauty: Specialists: Chiropractors",
    "sg:phone":"+64 3-443 1226",
    "sg:province":"Otago",
    "wof:name":"Jongsma Dr David M",
    "wof:placetype":"venue"
},
  "geometry": {"coordinates":[169.13519299999999,-44.698063],"type":"Point"}
}