{
  "type": "Feature",
  "properties": {
    "addr:full":"105 Hokonui Dve  Gore Southland",
    "addr:housenumber":"105",
    "addr:street":"Hokonui Dve",
    "iso:country":"NZ",
    "sg:address":"105 Hokonui Dve ",
    "sg:city":"Gore",
    "sg:orig_category":"Farming: Machinery: Farm Machinery",
    "sg:phone":"+64 3-208 9099",
    "sg:province":"Southland",
    "wof:name":"Dan Cosgrove Ltd",
    "wof:placetype":"venue"
},
  "geometry": {"coordinates":[168.93743900000001,-46.100636],"type":"Point"}
}