{
  "type": "Feature",
  "properties": {
    "iso:country":"NZ",
    "sg:address":"Reliable Way Mt Wellington ",
    "sg:city":"Auckland",
    "sg:orig_category":"Industrial: Manufacturing",
    "sg:phone":"+64 9-579 6187",
    "sg:province":"Auckland",
    "sg:website":"http://www.fultonhogan.co.nz",
    "wof:name":"Fulton Hogan Ltd",
    "wof:placetype":"venue"
},
  "geometry": {"coordinates":[174.825546,-36.903805],"type":"Point"}
}