{
  "type": "Feature",
  "properties": {
    "iso:country":"NZ",
    "sg:address":"2/43 Aitken Ave Mission Bay ",
    "sg:city":"Auckland",
    "sg:orig_category":"Farming: Services: Irrigation",
    "sg:phone":"+64 9-521 6362",
    "sg:province":"Auckland",
    "wof:name":"AquaSpray",
    "wof:placetype":"venue"
},
  "geometry": {"coordinates":[174.82870500000001,-36.851555],"type":"Point"}
}