{
  "type": "Feature",
  "properties": {
    "addr:full":"1066 Colombo St St Albans  Christchurch Canterbury",
    "addr:housenumber":"1066",
    "addr:street":"Colombo St",
    "iso:country":"NZ",
    "sg:address":"1066 Colombo St St Albans ",
    "sg:city":"Christchurch",
    "sg:classifiers":[
        {
            "category":"Communications",
            "subcategory":"Film & Video Production",
            "type":"Services"
        }
    ],
    "sg:phone":"+64 3-365 6260",
    "sg:province":"Canterbury",
    "sg:tags":[
        "sport",
        "leisure",
        "library",
        "entertainment"
    ],
    "wof:name":"Civic Video",
    "wof:placetype":"venue"
},
  "geometry": {"coordinates":[172.63618500000001,-43.511974],"type":"Point"}
}