{
  "type": "Feature",
  "properties": {
    "iso:country":"NZ",
    "sg:address":"129 Brightside Rd Stanmore Bay Hibiscus ",
    "sg:city":"Hibiscus Coast",
    "sg:classifiers":[
        {
            "category":"Personal",
            "subcategory":"Day Spa",
            "type":"Services"
        }
    ],
    "sg:phone":"+64 9-424 5303",
    "sg:province":"Auckland",
    "sg:tags":[
        "specialist",
        "satellite",
        "industrial",
        "machinery",
        "equipment"
    ],
    "wof:name":"Satellite System Services",
    "wof:placetype":"venue"
},
  "geometry": {"coordinates":[174.737823,-36.626949],"type":"Point"}
}