{
  "type": "Feature",
  "properties": {
    "iso:country":"NZ",
    "sg:address":"1062 Colombo St St Albans ",
    "sg:city":"Christchurch",
    "sg:classifiers":[
        {
            "category":"Home & Garden",
            "subcategory":"Building Materials",
            "type":"Retail Goods"
        }
    ],
    "sg:phone":"+64 3-366 4044",
    "sg:province":"Canterbury",
    "sg:tags":[
        "door",
        "fitting",
        "fittings"
    ],
    "wof:name":"Hardie & Thomson Limited",
    "wof:placetype":"venue"
},
  "geometry": {"coordinates":[172.636765,-43.513714],"type":"Point"}
}