{
  "type": "Feature",
  "properties": {
    "iso:country":"NZ",
    "sg:address":"1 Redruth St ",
    "sg:city":"Timaru",
    "sg:classifiers":[
        {
            "category":"Retail",
            "subcategory":"Auto Repair",
            "type":"Services"
        }
    ],
    "sg:phone":"+64 3-684 8282",
    "sg:province":"Canterbury",
    "sg:tags":[
        "automotive",
        "panel",
        "servicing",
        "beater"
    ],
    "wof:name":"Autobody Shop",
    "wof:placetype":"venue"
},
  "geometry": {"coordinates":[171.248871,-44.41853],"type":"Point"}
}