{
  "type": "Feature",
  "properties": {
    "addr:full":"249 Papanui Rd  Christchurch Canterbury",
    "addr:housenumber":"249",
    "addr:street":"Papanui Rd",
    "iso:country":"NZ",
    "sg:address":"249 Papanui Rd ",
    "sg:city":"Christchurch",
    "sg:classifiers":[
        {
            "category":"Shopping Center",
            "type":"Public Place"
        }
    ],
    "sg:phone":"+64 3-355 6397",
    "sg:province":"Canterbury",
    "sg:tags":[
        "health",
        "surgery",
        "optical",
        "eye",
        "beauty"
    ],
    "wof:name":"Tarr Dr Kenneth H",
    "wof:placetype":"venue"
},
  "geometry": {"coordinates":[172.61964399999999,-43.510021],"type":"Point"}
}