{
  "type": "Feature",
  "properties": {
    "iso:country":"NZ",
    "sg:address":"45-51 Fremlin Pl PO Box 19206 Avondale ",
    "sg:city":"Auckland",
    "sg:orig_category":"Industrial: Engineering: Engineers: Civil Engineering Contractors",
    "sg:phone":"+64 9-828 4182",
    "sg:province":"Auckland",
    "wof:name":"Vuksich & Borich Ltd",
    "wof:placetype":"venue"
},
  "geometry": {"coordinates":[174.690933,-36.8932],"type":"Point"}
}