{
  "type": "Feature",
  "properties": {
    "addr:full":"6 A King St  Timaru Canterbury",
    "addr:housenumber":"6 a",
    "addr:street":"King St",
    "iso:country":"NZ",
    "sg:address":"6 A King St ",
    "sg:city":"Timaru",
    "sg:orig_category":"Transport: Transportation: Courier Services",
    "sg:phone":"+64 3-684 6902",
    "sg:province":"Canterbury",
    "wof:name":"Fastway Couriers Timaru",
    "wof:placetype":"venue"
},
  "geometry": {"coordinates":[171.25465399999999,-44.404472],"type":"Point"}
}