{
  "type": "Feature",
  "properties": {
    "addr:full":"15 Maisey Pl  Rotorua Bay of Plenty",
    "addr:housenumber":"15",
    "addr:street":"Maisey Pl",
    "iso:country":"NZ",
    "sg:address":"15 Maisey Pl ",
    "sg:city":"Rotorua",
    "sg:orig_category":"Automotive: Parts And Supplies: Automotive Dismantlers",
    "sg:phone":"+64 7-347 7308",
    "sg:province":"Bay of Plenty",
    "wof:name":"Maisey Place Auto Wreckers",
    "wof:placetype":"venue"
},
  "geometry": {"coordinates":[176.226608,-38.120399],"type":"Point"}
}