{
  "type": "Feature",
  "properties": {
    "iso:country":"NZ",
    "sg:address":"6 Barberry St Judea ",
    "sg:city":"Tauranga",
    "sg:classifiers":[
        {
            "category":"Banks & Credit Unions",
            "subcategory":"Investment Brokerage",
            "type":"Services"
        }
    ],
    "sg:phone":"+64 7-578 5257",
    "sg:province":"Bay of Plenty",
    "sg:tags":[
        "services",
        "industrial",
        "refrigeration",
        "servicing"
    ],
    "wof:name":"Guy Refrigeration Ltd",
    "wof:placetype":"venue"
},
  "geometry": {"coordinates":[176.147537,-37.699375],"type":"Point"}
}