{
  "type": "Feature",
  "properties": {
    "iso:country":"NZ",
    "sg:address":"Thames St Palmerston ",
    "sg:city":"Palmerston North",
    "sg:classifiers":[
        {
            "category":"Sports & Exercise",
            "subcategory":"Sports Center",
            "type":"Entertainment"
        }
    ],
    "sg:phone":"+64 6-354 3856",
    "sg:province":"Manawatu-Wanganui",
    "sg:tags":[
        "sporting",
        "sports",
        "-",
        "leisure",
        "facility"
    ],
    "wof:name":"Freyberg Community Pool",
    "wof:placetype":"venue"
},
  "geometry": {"coordinates":[175.626038,-40.332993],"type":"Point"}
}