{
  "type": "Feature",
  "properties": {
    "iso:country":"NZ",
    "sg:address":"8 Whitby Cre ",
    "sg:city":"Hastings",
    "sg:classifiers":[
        {
            "category":"Home & Garden",
            "subcategory":"Garden Supply",
            "type":"Retail Goods"
        }
    ],
    "sg:phone":"+64 800 879 988",
    "sg:province":"Wellington",
    "sg:tags":[
        "cleaning"
    ],
    "wof:name":"Able Home Services",
    "wof:placetype":"venue"
},
  "geometry": {"coordinates":[-81.508163,29.711214],"type":"Point"}
}