{
  "type": "Feature",
  "properties": {
    "addr:full":"399 New North Rd Kingsland  Auckland Auckland",
    "addr:housenumber":"399",
    "addr:street":"New North Rd",
    "iso:country":"NZ",
    "sg:address":"399 New North Rd Kingsland ",
    "sg:city":"Auckland",
    "sg:classifiers":[
        {
            "category":"Autos & Motor Vehicles",
            "subcategory":"Automobile Sales",
            "type":"Retail Goods"
        }
    ],
    "sg:phone":"+64 9-846 1076",
    "sg:province":"Auckland",
    "sg:tags":[
        "home",
        "caravan",
        "leasing",
        "automotive"
    ],
    "wof:name":"Tent Town Ltd",
    "wof:placetype":"venue"
},
  "geometry": {"coordinates":[174.74792500000001,-36.870705],"type":"Point"}
}