{
  "type": "Feature",
  "properties": {
    "addr:full":"200 Maunu Rd  Whangarei Northland",
    "addr:housenumber":"200",
    "addr:street":"Maunu Rd",
    "iso:country":"NZ",
    "sg:address":"200 Maunu Rd ",
    "sg:city":"Whangarei",
    "sg:classifiers":[
        {
            "category":"Social Services",
            "subcategory":"Retirement Home",
            "type":"Services"
        }
    ],
    "sg:phone":"+64 9-438 4941",
    "sg:province":"Northland",
    "sg:tags":[
        "elderly",
        "convalescent",
        "garden",
        "rest",
        "care"
    ],
    "wof:name":"The Lady Jessica Residential Home",
    "wof:placetype":"venue"
},
  "geometry": {"coordinates":[174.312073,-35.730747],"type":"Point"}
}