{
  "type": "Feature",
  "properties": {
    "addr:full":"792 Manukau Rd Royal Oak  Auckland Auckland",
    "addr:housenumber":"792",
    "addr:street":"Manukau Rd",
    "iso:country":"NZ",
    "sg:address":"792 Manukau Rd Royal Oak ",
    "sg:city":"Auckland",
    "sg:classifiers":[
        {
            "category":"Farming",
            "subcategory":"Fish & Marine Products",
            "type":"Manufacturing & Wholesale Goods"
        }
    ],
    "sg:phone":"+64 9-625 7488",
    "sg:province":"Auckland",
    "sg:tags":[
        "health",
        "beauty"
    ],
    "sg:website":"http://www.chemistdirect.co.nz",
    "wof:name":"Walls And Roche Royal Oak Pharmacy Ltd",
    "wof:placetype":"venue"
},
  "geometry": {"coordinates":[174.77623,-36.91153],"type":"Point"}
}