{
  "type": "Feature",
  "properties": {
    "iso:country":"NZ",
    "sg:address":"752 Kaikorai Valley Rd ",
    "sg:city":"Dunedin",
    "sg:orig_category":"Industrial: Products: Galvanizing",
    "sg:phone":"+64 3-488 2035",
    "sg:province":"Otago",
    "wof:name":"Henderson Sandblasting Ltd",
    "wof:placetype":"venue"
},
  "geometry": {"coordinates":[170.47035199999999,-45.879337],"type":"Point"}
}