{
  "type": "Feature",
  "properties": {
    "addr:full":"PO Box 3400 Richmond  Wakefield Nelson",
    "addr:housenumber":"po",
    "addr:street":"Box 3400",
    "iso:country":"NZ",
    "sg:address":"PO Box 3400 Richmond ",
    "sg:city":"Wakefield",
    "sg:classifiers":[
        {
            "category":"Shopping",
            "subcategory":"Pharmacy",
            "type":"Retail Goods"
        }
    ],
    "sg:phone":"+64 3-541 8422",
    "sg:province":"Nelson",
    "sg:tags":[
        "product",
        "health"
    ],
    "wof:name":"Superfood Spirulina",
    "wof:placetype":"venue"
},
  "geometry": {"coordinates":[173.18867499999999,-41.33989],"type":"Point"}
}