{
  "type": "Feature",
  "properties": {
    "addr:full":"15 Sabulite Rd Glen Eden  Auckland Auckland",
    "addr:housenumber":"15",
    "addr:street":"Sabulite Rd",
    "iso:country":"NZ",
    "sg:address":"15 Sabulite Rd Glen Eden ",
    "sg:city":"Auckland",
    "sg:classifiers":[
        {
            "category":"Arena",
            "subcategory":"Sports Club",
            "type":"Entertainment"
        }
    ],
    "sg:phone":"+64 9-818 6078",
    "sg:province":"Auckland",
    "sg:tags":[
        "-",
        "leisure",
        "sports"
    ],
    "wof:name":"Waitakere Boxing Club",
    "wof:placetype":"venue"
},
  "geometry": {"coordinates":[174.658783,-36.898239],"type":"Point"}
}