{
  "type": "Feature",
  "properties": {
    "addr:full":"147 Ward St  Invercargill Southland",
    "addr:housenumber":"147",
    "addr:street":"Ward St",
    "iso:country":"NZ",
    "sg:address":"147 Ward St ",
    "sg:city":"Invercargill",
    "sg:orig_category":"Home And Garden: Gardening: Services: Lawnmowing Services",
    "sg:phone":"+64 272 244 242",
    "sg:province":"Southland",
    "wof:name":"Spruce Up Lawn Mowing & Property Maintenance",
    "wof:placetype":"venue"
},
  "geometry": {"coordinates":[168.38069200000001,-46.391685],"type":"Point"}
}