{
  "type": "Feature",
  "properties": {
    "addr:full":"Cnr Katere & Devon Rds New  Plymouth Taranaki",
    "addr:street":"Cnr Katere & Devon",
    "iso:country":"NZ",
    "sg:address":"Cnr Katere & Devon Rds New ",
    "sg:city":"Plymouth",
    "sg:classifiers":[
        {
            "category":"Sports & Exercise",
            "subcategory":"Swimming Pool",
            "type":"Entertainment"
        }
    ],
    "sg:phone":"+64 6-758 4400",
    "sg:province":"Taranaki",
    "sg:tags":[
        "home",
        "outdoor",
        "garden",
        "spa"
    ],
    "wof:name":"The Pool & Paving Co.",
    "wof:placetype":"venue"
},
  "geometry": {"coordinates":[-116.81971,43.972191],"type":"Point"}
}