{
  "type": "Feature",
  "properties": {
    "addr:full":"1394 Main South Rd Weedons R D 5 Christchurch  Rolleston",
    "addr:housenumber":"1394;5",
    "addr:street":"Main South Rd;R D",
    "iso:country":"NZ",
    "sg:address":"1394 Main South Rd Weedons R D 5 Christchurch ",
    "sg:city":"Rolleston",
    "sg:orig_category":"Farming: Horticulture",
    "sg:phone":"+64 3-347 9415",
    "wof:name":"South-Hort",
    "wof:placetype":"venue"
},
  "geometry": {"coordinates":[172.375046,-43.593182],"type":"Point"}
}