{
  "type": "Feature",
  "properties": {
    "addr:full":"116 Marsden Ave Mt Eden  Auckland Auckland",
    "addr:housenumber":"116",
    "addr:street":"Marsden Ave",
    "iso:country":"NZ",
    "sg:address":"116 Marsden Ave Mt Eden ",
    "sg:city":"Auckland",
    "sg:orig_category":"Health And Beauty: Specialists: Midwives",
    "sg:phone":"+64 9-629 2019",
    "sg:province":"Auckland",
    "wof:name":"Midwives Collective",
    "wof:placetype":"venue"
},
  "geometry": {"coordinates":[174.74757399999999,-36.892181],"type":"Point"}
}