{
  "type": "Feature",
  "properties": {
    "addr:full":"145 Wai-iti Rd Highfield  Timaru Canterbury",
    "addr:housenumber":"145",
    "addr:street":"Wai-Iti Rd",
    "iso:country":"NZ",
    "sg:address":"145 Wai-iti Rd Highfield ",
    "sg:city":"Timaru",
    "sg:classifiers":[
        {
            "category":"Bars & Pubs",
            "subcategory":"Wine Bar",
            "type":"Food & Drink"
        }
    ],
    "sg:phone":"+64 3-684 5146",
    "sg:province":"Canterbury",
    "sg:tags":[
        "wining",
        "dining",
        "cafe"
    ],
    "wof:name":"Cafe Chatters",
    "wof:placetype":"venue"
},
  "geometry": {"coordinates":[171.22616600000001,-44.39027],"type":"Point"}
}