{
  "type": "Feature",
  "properties": {
    "addr:full":"18 Normanby Rd Mt Eden  Auckland Auckland",
    "addr:housenumber":"18",
    "addr:street":"Normanby Rd",
    "iso:country":"NZ",
    "sg:address":"18 Normanby Rd Mt Eden ",
    "sg:city":"Auckland",
    "sg:classifiers":[
        {
            "category":"Health Services",
            "subcategory":"Hospital",
            "type":"Services"
        }
    ],
    "sg:phone":"+64 9-623 3383",
    "sg:province":"Auckland",
    "sg:tags":[
        "beauty",
        "fitness"
    ],
    "wof:name":"BodyTech Fitness & Spa",
    "wof:placetype":"venue"
},
  "geometry": {"coordinates":[174.76409899999999,-36.869717],"type":"Point"}
}