{
  "type": "Feature",
  "properties": {
    "addr:full":"318 Ruakura Rd  Hamilton Waikato",
    "addr:housenumber":"318",
    "addr:street":"Ruakura Rd",
    "iso:country":"NZ",
    "sg:address":"318 Ruakura Rd ",
    "sg:city":"Hamilton",
    "sg:classifiers":[
        {
            "category":"Home & Garden",
            "subcategory":"Home Furnishings",
            "type":"Retail Goods"
        }
    ],
    "sg:phone":"+64 7-856 1882",
    "sg:province":"Waikato",
    "sg:tags":[
        "furniture/furnishings",
        "upholstery",
        "supply"
    ],
    "sg:website":"http://www.furnrefabs.co.nz",
    "wof:name":"Furniture Refabricators",
    "wof:placetype":"venue"
},
  "geometry": {"coordinates":[175.30458100000001,-37.781193],"type":"Point"}
}