{
  "type": "Feature",
  "properties": {
    "addr:full":"Fox  Glacier",
    "iso:country":"NZ",
    "sg:address":"Fox ",
    "sg:city":"Glacier",
    "sg:classifiers":[
        {
            "category":"Travel",
            "subcategory":"Travel Agent",
            "type":"Entertainment"
        }
    ],
    "sg:phone":"+64 3-751 0080",
    "sg:tags":[
        "tour",
        "tourism",
        "adventure",
        "sightseeing"
    ],
    "wof:name":"Skydive N.Z.",
    "wof:placetype":"venue"
},
  "geometry": {"coordinates":[170.015411,-43.464077],"type":"Point"}
}