{
  "type": "Feature",
  "properties": {
    "addr:full":"32 Sylvania Cre Lynfield  Auckland Auckland",
    "addr:housenumber":"32;lynfield",
    "addr:street":"Sylvania Cre",
    "iso:country":"NZ",
    "sg:address":"32 Sylvania Cre Lynfield ",
    "sg:city":"Auckland",
    "sg:classifiers":[
        {
            "category":"Home & Garden",
            "subcategory":"Building Materials",
            "type":"Retail Goods"
        }
    ],
    "sg:phone":"+64 9-298 8101",
    "sg:province":"Auckland",
    "sg:tags":[
        "builder",
        "related"
    ],
    "sg:website":"http://www.yellowpages.co.nz/pages/201419976/dp52283.html",
    "wof:name":"Durabuilt Homes Ltd",
    "wof:placetype":"venue"
},
  "geometry": {"coordinates":[174.72195400000001,-36.934738],"type":"Point"}
}