{
  "type": "Feature",
  "properties": {
    "iso:country":"NZ",
    "sg:address":"34 Mains Ave Kensington ",
    "sg:city":"Whangarei",
    "sg:classifiers":[
        {
            "category":"Retail",
            "subcategory":"Laundry & Dry Cleaning",
            "type":"Services"
        }
    ],
    "sg:phone":"+64 9-437 2914",
    "sg:province":"Northland",
    "sg:tags":[
        "repair",
        "clothing",
        "fabric"
    ],
    "wof:name":"Whangarei Sewing Services",
    "wof:placetype":"venue"
},
  "geometry": {"coordinates":[174.32015999999999,-35.708782],"type":"Point"}
}