{
  "type": "Feature",
  "properties": {
    "addr:full":"cnr Cashel & Madras Sts  Christchurch Canterbury",
    "addr:street":"Cnr Cashel &",
    "iso:country":"NZ",
    "sg:address":"cnr Cashel & Madras Sts ",
    "sg:city":"Christchurch",
    "sg:classifiers":[
        {
            "category":"Wholesale",
            "subcategory":"Auto Parts",
            "type":"Manufacturing & Wholesale Goods"
        }
    ],
    "sg:phone":"+64 3-379 5500",
    "sg:province":"Canterbury",
    "sg:tags":[
        "automotive",
        "supply"
    ],
    "sg:website":"http://www.blackwells.co.nz",
    "wof:name":"Blackwell Motor Group",
    "wof:placetype":"venue"
},
  "geometry": {"coordinates":[-76.537834,37.605659],"type":"Point"}
}