{
  "type": "Feature",
  "properties": {
    "addr:full":"246 b Otipua Rd Highfield  Timaru Canterbury",
    "addr:housenumber":"246 b",
    "addr:street":"Otipua Rd",
    "iso:country":"NZ",
    "sg:address":"246 b Otipua Rd Highfield ",
    "sg:city":"Timaru",
    "sg:orig_category":"Health And Beauty: Specialists: Physiotherapists",
    "sg:phone":"+64 3-684 6230",
    "sg:province":"Canterbury",
    "wof:name":"Jenkins Brett Physiotherapy",
    "wof:placetype":"venue"
},
  "geometry": {"coordinates":[171.22204600000001,-44.39209],"type":"Point"}
}