{
  "type": "Feature",
  "properties": {
    "iso:country":"NZ",
    "sg:address":"287 Dee St Avenal ",
    "sg:city":"Invercargill",
    "sg:orig_category":"Transport: Boats And Marine: Products",
    "sg:phone":"+64 3-218 3495",
    "sg:province":"Southland",
    "wof:name":"BHM Electronics Ltd",
    "wof:placetype":"venue"
},
  "geometry": {"coordinates":[168.347534,-46.401073],"type":"Point"}
}