{
  "type": "Feature",
  "properties": {
    "addr:full":"59B Broadway  Reefton Manawatu-Wanganui",
    "addr:housenumber":"59b",
    "addr:street":"Broadway",
    "iso:country":"NZ",
    "sg:address":"59B Broadway ",
    "sg:city":"Reefton",
    "sg:orig_category":"Health And Beauty: Beauty: Hairdressers",
    "sg:phone":"+64 3-732 8587",
    "sg:province":"Manawatu-Wanganui",
    "wof:name":"Salon Broadway",
    "wof:placetype":"venue"
},
  "geometry": {"coordinates":[171.86291499999999,-42.119503],"type":"Point"}
}