{
  "type": "Feature",
  "properties": {
    "iso:country":"NZ",
    "sg:address":"59B Broadway ",
    "sg:city":"Reefton",
    "sg:orig_category":"Health And Beauty: Beauty: Hairdressers",
    "sg:phone":"+64 3-732 8587",
    "sg:province":"Manawatu-Wanganui",
    "wof:name":"Salon Broadway",
    "wof:placetype":"venue"
},
  "geometry": {"coordinates":[171.862915,-42.119503],"type":"Point"}
}