{
  "type": "Feature",
  "properties": {
    "addr:full":"188 Palmerston Rd  Gisborne Gisborne",
    "addr:housenumber":"188",
    "addr:street":"Palmerston Rd",
    "iso:country":"NZ",
    "sg:address":"188 Palmerston Rd ",
    "sg:city":"Gisborne",
    "sg:orig_category":"Automotive: Accessories: Car Audio Systems",
    "sg:phone":"+64 6-868 6405",
    "sg:province":"Gisborne",
    "wof:name":"Eastland Hi Fi Limited",
    "wof:placetype":"venue"
},
  "geometry": {"coordinates":[178.02578700000001,-38.664295],"type":"Point"}
}