{
  "type": "Feature",
  "properties": {
    "iso:country":"NZ",
    "sg:address":"188 Palmerston Rd ",
    "sg:city":"Gisborne",
    "sg:orig_category":"Automotive: Accessories: Car Audio Systems",
    "sg:phone":"+64 6-868 6405",
    "sg:province":"Gisborne",
    "wof:name":"Eastland Hi Fi Limited",
    "wof:placetype":"venue"
},
  "geometry": {"coordinates":[178.025787,-38.664295],"type":"Point"}
}