{
  "type": "Feature",
  "properties": {
    "addr:full":"383 New North Rd Kingsland  Auckland Auckland",
    "addr:housenumber":"383",
    "addr:street":"New North Rd",
    "iso:country":"NZ",
    "sg:address":"383 New North Rd Kingsland ",
    "sg:city":"Auckland",
    "sg:orig_category":"Transport: Boats And Marine: Products: Marine Electronics",
    "sg:phone":"+64 9-845 5347",
    "sg:province":"Auckland",
    "wof:name":"Advance Trident Ltd",
    "wof:placetype":"venue"
},
  "geometry": {"coordinates":[174.748276,-36.870274],"type":"Point"}
}