{
  "type": "Feature",
  "properties": {
    "addr:full":"Barrys Point Rd Takapuna  Auckland Auckland",
    "addr:street":"Barrys Point Rd",
    "iso:country":"NZ",
    "sg:address":"Barrys Point Rd Takapuna ",
    "sg:city":"Auckland",
    "sg:orig_category":"Shopping: Sports Retailers: Cycles",
    "sg:phone":"+64 9-486 0277",
    "sg:province":"Auckland",
    "wof:name":"Bikes Direct",
    "wof:placetype":"venue"
},
  "geometry": {"coordinates":[174.76527400000001,-36.794643],"type":"Point"}
}