{
  "type": "Feature",
  "properties": {
    "addr:full":"224 Park Rd Palmerston  Palmerston North Manawatu-Wanganui",
    "addr:housenumber":"224",
    "addr:street":"Park Rd",
    "iso:country":"NZ",
    "sg:address":"224 Park Rd Palmerston ",
    "sg:city":"Palmerston North",
    "sg:classifiers":[
        {
            "category":"Social Services",
            "subcategory":"Child Care",
            "type":"Services"
        }
    ],
    "sg:phone":"+64 6-354 9994",
    "sg:province":"Manawatu-Wanganui",
    "sg:tags":[
        "home",
        "garden",
        "children"
    ],
    "wof:name":"Gregory's Childcare & Education Centre Ltd",
    "wof:placetype":"venue"
},
  "geometry": {"coordinates":[175.621185,-40.363735],"type":"Point"}
}