{
  "type": "Feature",
  "properties": {
    "iso:country":"NZ",
    "sg:address":"371 Remuera Rd Remuera ",
    "sg:city":"Auckland",
    "sg:classifiers":[
        {
            "category":"Food & Beverages",
            "subcategory":"Bakery",
            "type":"Retail Goods"
        }
    ],
    "sg:phone":"+64 9-520 2900",
    "sg:province":"Auckland",
    "sg:tags":[
        "shop",
        "cake",
        "drink",
        "-"
    ],
    "wof:name":"Rembrandt's Patisserie/Chocolaterie",
    "wof:placetype":"venue"
},
  "geometry": {"coordinates":[174.789169,-36.877647],"type":"Point"}
}