{
  "type": "Feature",
  "properties": {
    "addr:full":"PO Box 239  Motueka Tasman",
    "addr:housenumber":"po",
    "addr:street":"Box 239",
    "iso:country":"NZ",
    "sg:address":"PO Box 239 ",
    "sg:city":"Motueka",
    "sg:classifiers":[
        {
            "category":"Utilities",
            "subcategory":"Sewage",
            "type":"Services"
        }
    ],
    "sg:phone":"+64 800 725 326",
    "sg:province":"Tasman",
    "sg:tags":[
        "home",
        "tank",
        "garden",
        "septic"
    ],
    "wof:name":"Sepclean",
    "wof:placetype":"venue"
},
  "geometry": {"coordinates":[173.013443,-41.108101],"type":"Point"}
}