{
  "type": "Feature",
  "properties": {
    "addr:full":"PO Box 34654 Birkenhead  Auckland Auckland",
    "addr:housenumber":"po box",
    "addr:postcode":"34654",
    "iso:country":"NZ",
    "sg:address":"PO Box 34654 Birkenhead ",
    "sg:city":"Auckland",
    "sg:classifiers":[
        {
            "category":"Home & Garden",
            "subcategory":"Garden Supply",
            "type":"Retail Goods"
        }
    ],
    "sg:phone":"+64 9-480 9680",
    "sg:province":"Auckland",
    "sg:tags":[
        "outdoor"
    ],
    "sg:website":"http://www.yellowpages.co.nz/for/gardenwall-co/dp14147.html",
    "wof:name":"Garden Wall Co",
    "wof:placetype":"venue"
},
  "geometry": {"coordinates":[174.734467,-36.818214],"type":"Point"}
}