{
  "type": "Feature",
  "properties": {
    "iso:country":"NZ",
    "sg:address":"Kitchener St ",
    "sg:city":"Martinborough",
    "sg:classifiers":[
        {
            "category":"Winery",
            "type":"Food & Drink"
        }
    ],
    "sg:phone":"+64 6-306 9832",
    "sg:tags":[
        "wining",
        "vineyard",
        "dining"
    ],
    "wof:name":"Nga Waka Vineyard",
    "wof:placetype":"venue"
},
  "geometry": {"coordinates":[175.456345,-41.21529],"type":"Point"}
}