{
  "type": "Feature",
  "properties": {
    "addr:full":"Golf View Rd  Kerikeri Northland",
    "addr:street":"Golf View Rd",
    "iso:country":"NZ",
    "sg:address":"Golf View Rd ",
    "sg:city":"Kerikeri",
    "sg:orig_category":"Sports And Leisure: Sports: Golf",
    "sg:phone":"+64 9-407 8837",
    "sg:province":"Northland",
    "wof:name":"Kerikeri Golf Club",
    "wof:placetype":"venue"
},
  "geometry": {"coordinates":[173.94487000000001,-35.222607],"type":"Point"}
}