{
  "type": "Feature",
  "properties": {
    "addr:full":"108 E Columbo St  Hamilton Waikato",
    "addr:housenumber":"108",
    "addr:street":"E Columbo St",
    "iso:country":"NZ",
    "sg:address":"108 E Columbo St ",
    "sg:city":"Hamilton",
    "sg:classifiers":[
        {
            "category":"Shopping",
            "subcategory":"Stationery & Office Supplies",
            "type":"Retail Goods"
        }
    ],
    "sg:phone":"+64 7-847 4608",
    "sg:province":"Waikato",
    "sg:tags":[
        "supplies",
        "educational",
        "material",
        "education",
        "training"
    ],
    "wof:name":"El'Finesse Products",
    "wof:placetype":"venue"
},
  "geometry": {"coordinates":[-74.739639,40.217033],"type":"Point"}
}