{
  "type": "Feature",
  "properties": {
    "iso:country":"NZ",
    "sg:address":"54 Pandora Rd ",
    "sg:city":"Napier",
    "sg:orig_category":"Automotive: General Services: Service Stations",
    "sg:phone":"+64 6-835 7529",
    "sg:province":"Hawke's Bay",
    "wof:name":"BP Pandora",
    "wof:placetype":"venue"
},
  "geometry": {"coordinates":[176.890228,-39.485424],"type":"Point"}
}