{
  "type": "Feature",
  "properties": {
    "iso:country":"NZ",
    "sg:address":"44 Heu Heu St ",
    "sg:city":"Taupo",
    "sg:orig_category":"Shopping: Sports Retailers: Sports Goods: Sporting Goods",
    "sg:phone":"+64 7-378 8311",
    "sg:province":"Waikato",
    "wof:name":"Hikoi Taupo",
    "wof:placetype":"venue"
},
  "geometry": {"coordinates":[176.07167100000001,-38.687939],"type":"Point"}
}