{
  "type": "Feature",
  "properties": {
    "iso:country":"NZ",
    "sg:address":"14 Laings Rd Lower Hutt ",
    "sg:city":"Wellington",
    "sg:orig_category":"Health And Beauty: Specialists: Osteopaths",
    "sg:phone":"+64 4-570 0202",
    "sg:province":"Wellington",
    "wof:name":"NZ Register of Osteopaths",
    "wof:placetype":"venue"
},
  "geometry": {"coordinates":[174.901276,-41.210838],"type":"Point"}
}