{
  "type": "Feature",
  "properties": {
    "iso:country":"NZ",
    "sg:address":"1 Dundas St ",
    "sg:city":"Whitianga",
    "sg:orig_category":"Transport: Boats And Marine: Boats: Boat Maintenance",
    "sg:phone":"+64 25971444",
    "wof:name":"H & M Pascoe Boat Builders",
    "wof:placetype":"venue"
},
  "geometry": {"coordinates":[175.70379600000001,-36.83868],"type":"Point"}
}