{
  "type": "Feature",
  "properties": {
    "addr:full":"34 Greenmount Dve East Tamaki  Auckland Auckland",
    "addr:housenumber":"34",
    "addr:street":"Greenmount Dve",
    "iso:country":"NZ",
    "sg:address":"34 Greenmount Dve East Tamaki ",
    "sg:city":"Auckland",
    "sg:classifiers":[
        {
            "category":"Food & Beverages",
            "subcategory":"Candy",
            "type":"Retail Goods"
        }
    ],
    "sg:phone":"+64 9-271 1294",
    "sg:province":"Auckland",
    "sg:tags":[
        "confectioner",
        "drink",
        "-"
    ],
    "wof:name":"Bergens International Snack Foods",
    "wof:placetype":"venue"
},
  "geometry": {"coordinates":[174.90136699999999,-36.933708],"type":"Point"}
}