{
  "type": "Feature",
  "properties": {
    "iso:country":"NZ",
    "sg:address":"181 A Dee St ",
    "sg:city":"Invercargill",
    "sg:classifiers":[
        {
            "category":"Personal",
            "subcategory":"Beauty Salon",
            "type":"Services"
        }
    ],
    "sg:phone":"+64 3-215 6160",
    "sg:province":"Southland",
    "sg:tags":[
        "yoga",
        "health",
        "fitness"
    ],
    "wof:name":"Yoga Centre (Southland)",
    "wof:placetype":"venue"
},
  "geometry": {"coordinates":[168.347321,-46.392628],"type":"Point"}
}