{
  "type": "Feature",
  "properties": {
    "addr:full":"480 Matakana Rd Matakana  Warkworth Auckland",
    "addr:housenumber":"480",
    "addr:street":"Matakana Rd",
    "iso:country":"NZ",
    "sg:address":"480 Matakana Rd Matakana ",
    "sg:city":"Warkworth",
    "sg:classifiers":[
        {
            "category":"Winery",
            "type":"Food & Drink"
        }
    ],
    "sg:phone":"+64 9-422 9601",
    "sg:province":"Auckland",
    "sg:tags":[
        "wining",
        "vineyard",
        "dining"
    ],
    "wof:name":"Ascension Vineyard",
    "wof:placetype":"venue"
},
  "geometry": {"coordinates":[174.689987,-36.369572],"type":"Point"}
}