{
  "type": "Feature",
  "properties": {
    "addr:full":"59 c Cavendish Dve Manukau  Auckland Auckland",
    "addr:housenumber":"59 c",
    "addr:street":"Dve",
    "iso:country":"NZ",
    "sg:address":"59 c Cavendish Dve Manukau ",
    "sg:city":"Auckland",
    "sg:classifiers":[
        {
            "category":"Banks & Credit Unions",
            "subcategory":"Financial Services",
            "type":"Services"
        }
    ],
    "sg:phone":"+64 9-263 8518",
    "sg:province":"Auckland",
    "sg:tags":[
        "lender",
        "money",
        "-",
        "finance",
        "personal"
    ],
    "wof:name":"South Pacific Loans",
    "wof:placetype":"venue"
},
  "geometry": {"coordinates":[-119.10457599999999,36.597755],"type":"Point"}
}