{
  "type": "Feature",
  "properties": {
    "iso:country":"NZ",
    "sg:address":"21 Heu Heu St ",
    "sg:city":"Taupo",
    "sg:classifiers":[
        {
            "category":"Shopping",
            "subcategory":"Photographic Equipment",
            "type":"Retail Goods"
        }
    ],
    "sg:phone":"+64 7-378 3888",
    "sg:province":"Waikato",
    "sg:tags":[
        "sport",
        "leisure",
        "hobbies"
    ],
    "wof:name":"Camera House",
    "wof:placetype":"venue"
},
  "geometry": {"coordinates":[176.070374,-38.687935],"type":"Point"}
}