{
  "type": "Feature",
  "properties": {
    "iso:country":"NZ",
    "sg:address":"16 a Cortina Pl Pakuranga ",
    "sg:city":"Auckland",
    "sg:classifiers":[
        {
            "category":"Health Services",
            "subcategory":"Clinic",
            "type":"Services"
        }
    ],
    "sg:phone":"+64 9-577 2029",
    "sg:province":"Auckland",
    "sg:tags":[
        "optical",
        "beauty",
        "supply"
    ],
    "wof:name":"Stoco",
    "wof:placetype":"venue"
},
  "geometry": {"coordinates":[174.87280273440001,-36.9151115417],"type":"Point"}
}