{
  "type": "Feature",
  "properties": {
    "addr:full":"419 Thames Highway  Oamaru Otago",
    "addr:housenumber":"419",
    "addr:street":"Thames Highway",
    "iso:country":"NZ",
    "sg:address":"419 Thames Highway ",
    "sg:city":"Oamaru",
    "sg:classifiers":[
        {
            "category":"Autos & Motor Vehicles",
            "subcategory":"Motorcycle Sales",
            "type":"Retail Goods"
        }
    ],
    "sg:phone":"+64 3-437 0559",
    "sg:province":"Otago",
    "sg:tags":[
        "automotive",
        "scooter",
        "leasing"
    ],
    "wof:name":"Colin Clyne Motorcycles Oamaru",
    "wof:placetype":"venue"
},
  "geometry": {"coordinates":[170.98291,-45.080322],"type":"Point"}
}