{
  "type": "Feature",
  "properties": {
    "addr:full":"254 Kimbolton Rd  Feilding Manawatu-Wanganui",
    "addr:housenumber":"254",
    "addr:street":"Kimbolton Rd",
    "iso:country":"NZ",
    "sg:address":"254 Kimbolton Rd ",
    "sg:city":"Feilding",
    "sg:classifiers":[
        {
            "category":"Social Services",
            "subcategory":"Child Care",
            "type":"Services"
        }
    ],
    "sg:phone":"+64 6-323 6100",
    "sg:province":"Manawatu-Wanganui",
    "sg:tags":[
        "home",
        "garden",
        "children"
    ],
    "wof:name":"Feilding Play Centre",
    "wof:placetype":"venue"
},
  "geometry": {"coordinates":[175.54719499999999,-40.224236],"type":"Point"}
}