{
  "type": "Feature",
  "properties": {
    "addr:full":"78 A Marellen Dve Red Beach Hibiscus  Hibiscus Coast Auckland",
    "addr:housenumber":"78",
    "addr:street":"A Marellen",
    "iso:country":"NZ",
    "sg:address":"78 A Marellen Dve Red Beach Hibiscus ",
    "sg:city":"Hibiscus Coast",
    "sg:orig_category":"Home And Garden: Children",
    "sg:phone":"+64 9-426 3451",
    "sg:province":"Auckland",
    "wof:name":"Aranatui Pre School & Childcare Centre",
    "wof:placetype":"venue"
},
  "geometry": {"coordinates":[174.70347599999999,-36.602089],"type":"Point"}
}