{
  "type": "Feature",
  "properties": {
    "addr:full":"23 The Esplanade Raumati South  Wellington Auckland",
    "addr:housenumber":"23",
    "addr:street":"The Esplanade",
    "iso:country":"NZ",
    "sg:address":"23 The Esplanade Raumati South ",
    "sg:city":"Wellington",
    "sg:classifiers":[
        {
            "category":"Education",
            "subcategory":"Special Training",
            "type":"Public Place"
        }
    ],
    "sg:phone":"+64 4-904 9944",
    "sg:province":"Auckland",
    "sg:tags":[
        "building",
        "programme",
        "team"
    ],
    "wof:name":"Renegade Productions",
    "wof:placetype":"venue"
},
  "geometry": {"coordinates":[174.97456399999999,-40.938503],"type":"Point"}
}