{
  "type": "Feature",
  "properties": {
    "addr:full":"27 Glen Rd Mornington  Dunedin Otago",
    "addr:housenumber":"27",
    "addr:street":"Glen Rd",
    "iso:country":"NZ",
    "sg:address":"27 Glen Rd Mornington ",
    "sg:city":"Dunedin",
    "sg:orig_category":"Home And Garden: Gardening: Services: Tree Services",
    "sg:phone":"+64 3-453 1239",
    "sg:province":"Otago",
    "wof:name":"David Baird Tree Advocate",
    "wof:placetype":"venue"
},
  "geometry": {"coordinates":[170.48277300000001,-45.885586],"type":"Point"}
}