{
  "type": "Feature",
  "properties": {
    "addr:full":"1 Lincoln Ave Tawa  Wellington Wellington",
    "addr:housenumber":"1",
    "addr:street":"Lincoln Ave",
    "iso:country":"NZ",
    "sg:address":"1 Lincoln Ave Tawa ",
    "sg:city":"Wellington",
    "sg:orig_category":"Industrial: Electrical/Electronic",
    "sg:phone":"+64 4-232 3233",
    "sg:province":"Wellington",
    "sg:website":"http://www.nichecom.co.nz",
    "wof:name":"Nichecom",
    "wof:placetype":"venue"
},
  "geometry": {"coordinates":[174.82466099999999,-41.168571],"type":"Point"}
}