{
  "type": "Feature",
  "properties": {
    "addr:full":"654 Swanson Rd Swanson  Auckland Auckland",
    "addr:housenumber":"654",
    "addr:street":"Swanson Rd",
    "iso:country":"NZ",
    "sg:address":"654 Swanson Rd Swanson ",
    "sg:city":"Auckland",
    "sg:orig_category":"Automotive: General Services: Service Stations",
    "sg:phone":"+64 9-832 0597",
    "sg:province":"Auckland",
    "wof:name":"BP Oil",
    "wof:placetype":"venue"
},
  "geometry": {"coordinates":[174.585724,-36.865608],"type":"Point"}
}