{
  "type": "Feature",
  "properties": {
    "addr:full":"8 Gipps St Karori  Wellington Wellington",
    "addr:housenumber":"8",
    "addr:street":"Gipps St",
    "iso:country":"NZ",
    "sg:address":"8 Gipps St Karori ",
    "sg:city":"Wellington",
    "sg:orig_category":"Food And Drink: Meats: Butchers",
    "sg:phone":"+64 4-476 9584",
    "sg:province":"Wellington",
    "wof:name":"Gipps Street Butchery",
    "wof:placetype":"venue"
},
  "geometry": {"coordinates":[174.746521,-41.287395],"type":"Point"}
}