{
  "type": "Feature",
  "properties": {
    "iso:country":"NZ",
    "sg:address":"15 Belvue Cre Witherlea ",
    "sg:city":"Blenheim",
    "sg:classifiers":[
        {
            "category":"Shopping",
            "subcategory":"Crafts & Fabrics",
            "type":"Retail Goods"
        }
    ],
    "sg:phone":"+64 3-577 8674",
    "sg:province":"Marlborough",
    "sg:tags":[
        "clothing",
        "maternity",
        "wear"
    ],
    "wof:name":"Ben-Lee Maternity",
    "wof:placetype":"venue"
},
  "geometry": {"coordinates":[173.96023600000001,-41.535198],"type":"Point"}
}