{
  "type": "Feature",
  "properties": {
    "addr:full":"PO Box 715  Tauranga Bay of Plenty",
    "addr:housenumber":"po;715",
    "addr:street":"Box",
    "iso:country":"NZ",
    "sg:address":"PO Box 715 ",
    "sg:city":"Tauranga",
    "sg:classifiers":[
        {
            "category":"Health Services",
            "subcategory":"Dentist",
            "type":"Services"
        }
    ],
    "sg:phone":"+64 7-571 0559",
    "sg:province":"Bay of Plenty",
    "sg:tags":[
        "dental",
        "beauty"
    ],
    "wof:name":"Biodent NZ Ltd",
    "wof:placetype":"venue"
},
  "geometry": {"coordinates":[176.144745,-37.703156],"type":"Point"}
}