{
  "type": "Feature",
  "properties": {
    "iso:country":"NZ",
    "sg:address":"113 Peria Rd ",
    "sg:city":"Matamata",
    "sg:orig_category":"Shopping: Gifts",
    "sg:phone":"+64 7-888 9434",
    "sg:province":"Waikato",
    "sg:website":"http://www.countrykitchenware.co.nz",
    "wof:name":"Fern Hill Heritage Ltd",
    "wof:placetype":"venue"
},
  "geometry": {"coordinates":[175.761932,-37.805096],"type":"Point"}
}