{
  "type": "Feature",
  "properties": {
    "addr:full":"Unit E 665 Great South Rd Penrose  Auckland Auckland",
    "addr:housenumber":"665",
    "addr:street":"Great South Rd",
    "iso:country":"NZ",
    "sg:address":"Unit E 665 Great South Rd Penrose ",
    "sg:city":"Auckland",
    "sg:classifiers":[
        {
            "category":"Personal",
            "type":"Services"
        }
    ],
    "sg:phone":"+64 9-525 1995",
    "sg:province":"Auckland",
    "sg:tags":[
        "diet",
        "reduction",
        "health",
        "beauty",
        "weight"
    ],
    "wof:name":"The Looking Good Centre",
    "wof:placetype":"venue"
},
  "geometry": {"coordinates":[174.81016500000001,-36.911617],"type":"Point"}
}