{
  "type": "Feature",
  "properties": {
    "iso:country":"NZ",
    "sg:address":"401 Ferry Rd ",
    "sg:city":"Woolston",
    "sg:orig_category":"Transport: Boats And Marine: Boats: Boat Dealers",
    "sg:phone":"+64 800 700 600",
    "sg:province":"Canterbury",
    "wof:name":"Powerboat Centre Ltd",
    "wof:placetype":"venue"
},
  "geometry": {"coordinates":[-75.68988,38.298489],"type":"Point"}
}