{
  "type": "Feature",
  "properties": {
    "iso:country":"NZ",
    "sg:address":"Papakura ",
    "sg:city":"Auckland",
    "sg:classifiers":[
        {
            "category":"Banks & Credit Unions",
            "subcategory":"Investment Brokerage",
            "type":"Services"
        }
    ],
    "sg:phone":"+64 9-298 1600",
    "sg:province":"Auckland",
    "sg:tags":[
        "director",
        "funeral",
        "arrangements"
    ],
    "wof:name":"Bennetts Ross",
    "wof:placetype":"venue"
},
  "geometry": {"coordinates":[174.943924,-37.065418],"type":"Point"}
}