{
  "type": "Feature",
  "properties": {
    "iso:country":"NZ",
    "sg:address":"123 Main St ",
    "sg:city":"Pahiatua",
    "sg:orig_category":"Health And Beauty: Products: Pharmacies",
    "sg:phone":"+64 6-376 8446",
    "wof:name":"Bollards Pharmacy",
    "wof:placetype":"venue"
},
  "geometry": {"coordinates":[175.83583100000001,-40.458637],"type":"Point"}
}