{
  "type": "Feature",
  "properties": {
    "addr:full":"19 A Raxworthy St Avonhead  Christchurch Canterbury",
    "addr:housenumber":"19",
    "addr:street":"A Raxworthy St",
    "iso:country":"NZ",
    "sg:address":"19 A Raxworthy St Avonhead ",
    "sg:city":"Christchurch",
    "sg:orig_category":"Farming: Services: Irrigation",
    "sg:phone":"+64 3-357 2405",
    "sg:province":"Canterbury",
    "wof:name":"Ward Irrigation & Turf",
    "wof:placetype":"venue"
},
  "geometry": {"coordinates":[172.555984,-43.513943],"type":"Point"}
}