{
  "type": "Feature",
  "properties": {
    "addr:full":"Northland  Whangarei Northland",
    "iso:country":"NZ",
    "sg:address":"Northland ",
    "sg:city":"Whangarei",
    "sg:orig_category":"Farming: Machinery: Tractors",
    "sg:phone":"+64 800 872 272",
    "sg:province":"Northland",
    "wof:name":"Discount Tractor Parts",
    "wof:placetype":"venue"
},
  "geometry": {"coordinates":[174.320526,-35.725399],"type":"Point"}
}