{
  "type": "Feature",
  "properties": {
    "iso:country":"NZ",
    "sg:address":"54 Clyde St ",
    "sg:city":"Balclutha",
    "sg:classifiers":[
        {
            "category":"Shopping",
            "subcategory":"Shoes",
            "type":"Retail Goods"
        }
    ],
    "sg:phone":"+64 3-418 0019",
    "sg:tags":[
        "foot",
        "clothing",
        "fabric",
        "wear"
    ],
    "wof:name":"Entity",
    "wof:placetype":"venue"
},
  "geometry": {"coordinates":[169.734573,-46.239868],"type":"Point"}
}