{
  "type": "Feature",
  "properties": {
    "iso:country":"NZ",
    "sg:address":"18 Norman Spencer Dve Papatoetoe ",
    "sg:city":"Auckland",
    "sg:orig_category":"Industrial: Packaging: Bags",
    "sg:phone":"+64 9-278 1320",
    "sg:province":"Auckland",
    "wof:name":"Presslok-Sarich Packaging",
    "wof:placetype":"venue"
},
  "geometry": {"coordinates":[174.867157,-36.971188],"type":"Point"}
}