{
  "type": "Feature",
  "properties": {
    "addr:full":"18 Norman Spencer Dve Papatoetoe  Auckland Auckland",
    "addr:housenumber":"18;dve",
    "addr:street":"Norman Spencer",
    "iso:country":"NZ",
    "sg:address":"18 Norman Spencer Dve Papatoetoe ",
    "sg:city":"Auckland",
    "sg:orig_category":"Industrial: Packaging: Bags",
    "sg:phone":"+64 9-278 1320",
    "sg:province":"Auckland",
    "wof:name":"Presslok-Sarich Packaging",
    "wof:placetype":"venue"
},
  "geometry": {"coordinates":[174.86715699999999,-36.971188],"type":"Point"}
}