{
  "type": "Feature",
  "properties": {
    "addr:full":"190 West Coast Rd Glen Eden  Auckland Auckland",
    "addr:housenumber":"190",
    "addr:street":"West Coast Rd",
    "iso:country":"NZ",
    "sg:address":"190 West Coast Rd Glen Eden ",
    "sg:city":"Auckland",
    "sg:orig_category":"Health And Beauty: Dental: Dentists",
    "sg:phone":"+64 9-818 8855",
    "sg:province":"Auckland",
    "wof:name":"Nelson Deanna",
    "wof:placetype":"venue"
},
  "geometry": {"coordinates":[174.652908,-36.910648],"type":"Point"}
}