{
  "type": "Feature",
  "properties": {
    "addr:full":"17 Redruth St Redruth  Timaru Canterbury",
    "addr:housenumber":"17",
    "addr:street":"Redruth St",
    "iso:country":"NZ",
    "sg:address":"17 Redruth St Redruth ",
    "sg:city":"Timaru",
    "sg:classifiers":[
        {
            "category":"Utilities",
            "subcategory":"Refuse",
            "type":"Services"
        }
    ],
    "sg:phone":"+64 3-688 4664",
    "sg:province":"Canterbury",
    "sg:tags":[
        "bin",
        "hire",
        "garden",
        "cleaning",
        "rubbish",
        "home"
    ],
    "wof:name":"Timaru Bins",
    "wof:placetype":"venue"
},
  "geometry": {"coordinates":[171.24977100000001,-44.418133],"type":"Point"}
}