{
  "type": "Feature",
  "properties": {
    "addr:full":"157 Princess St  Hawera Taranaki",
    "addr:housenumber":"157",
    "addr:street":"Princess St",
    "iso:country":"NZ",
    "sg:address":"157 Princess St ",
    "sg:city":"Hawera",
    "sg:classifiers":[
        {
            "category":"Building & Trades",
            "subcategory":"Electrical",
            "type":"Services"
        }
    ],
    "sg:phone":"+64 6-278 1480",
    "sg:province":"Taranaki",
    "sg:tags":[
        "industrial",
        "refrigeration"
    ],
    "wof:name":"York New Zealand Ltd",
    "wof:placetype":"venue"
},
  "geometry": {"coordinates":[174.28417999999999,-39.58783],"type":"Point"}
}