{
  "type": "Feature",
  "properties": {
    "iso:country":"NZ",
    "sg:address":"State Highway 25 ",
    "sg:city":"Whitianga",
    "sg:orig_category":"Shopping: Sports Retailers: Sports Goods: Canvas Goods",
    "sg:phone":"+64 7-866 4972",
    "wof:name":"Mercury Bay Canvas & Upholstery",
    "wof:placetype":"venue"
},
  "geometry": {"coordinates":[175.722702,-36.790661],"type":"Point"}
}