{
  "type": "Feature",
  "properties": {
    "addr:full":"Makareao Lime Works  Dunback",
    "iso:country":"NZ",
    "sg:address":"Makareao Lime Works ",
    "sg:city":"Dunback",
    "sg:classifiers":[
        {
            "category":"Manufacturing",
            "subcategory":"Glass & Minerals",
            "type":"Manufacturing & Wholesale Goods"
        }
    ],
    "sg:phone":"+64 3-465 0854",
    "sg:tags":[
        "industrial",
        "raw",
        "material"
    ],
    "wof:name":"Taylors Lime",
    "wof:placetype":"venue"
},
  "geometry": {"coordinates":[170.66978499999999,-45.376221],"type":"Point"}
}