{
  "type": "Feature",
  "properties": {
    "addr:full":"1 Alma Rd  Wanganui Manawatu-Wanganui",
    "addr:housenumber":"1",
    "addr:street":"Alma Rd",
    "iso:country":"NZ",
    "sg:address":"1 Alma Rd ",
    "sg:city":"Wanganui",
    "sg:orig_category":"Shopping: Retail Stores: Secondhand Dealers",
    "sg:phone":"+64 6-345 5983",
    "sg:province":"Manawatu-Wanganui",
    "wof:name":"Knicknacs",
    "wof:placetype":"venue"
},
  "geometry": {"coordinates":[175.03533899999999,-39.938709],"type":"Point"}
}