{
  "type": "Feature",
  "properties": {
    "addr:full":"8 A Provincial La  Nelson Nelson",
    "addr:housenumber":"8 a",
    "addr:street":"Provincial La Nelson",
    "iso:country":"NZ",
    "sg:address":"8 A Provincial La ",
    "sg:city":"Nelson",
    "sg:classifiers":[
        {
            "category":"Health Services",
            "subcategory":"Health Practitioner",
            "type":"Services"
        }
    ],
    "sg:phone":"+64 3-546 9829",
    "sg:province":"Nelson",
    "sg:tags":[
        "consultant",
        "medical",
        "beauty"
    ],
    "wof:name":"Child Development (Nelson)",
    "wof:placetype":"venue"
},
  "geometry": {"coordinates":[173.28866600000001,-41.27216],"type":"Point"}
}