{
  "type": "Feature",
  "properties": {
    "iso:country":"NZ",
    "sg:address":"Te Rahu Rd Te ",
    "sg:city":"Awamutu",
    "sg:classifiers":[
        {
            "category":"Coffee & Tea",
            "type":"Food & Drink"
        }
    ],
    "sg:phone":"+64 7-871 5805",
    "sg:province":"Waikato",
    "sg:tags":[
        "vegetable",
        "fruit",
        "veges"
    ],
    "wof:name":"Te Awamutu Berryfruit Exporters Ltd",
    "wof:placetype":"venue"
},
  "geometry": {"coordinates":[175.34338399999999,-37.998062],"type":"Point"}
}