{
  "type": "Feature",
  "properties": {
    "addr:full":"Hastings St  Napier Hawke's Bay",
    "addr:street":"Hastings St",
    "iso:country":"NZ",
    "sg:address":"Hastings St ",
    "sg:city":"Napier",
    "sg:orig_category":"Shopping: Retail Stores: Department Stores",
    "sg:phone":"+64 6-835 3044",
    "sg:province":"Hawke's Bay",
    "wof:name":"Briscoes Homeware",
    "wof:placetype":"venue"
},
  "geometry": {"coordinates":[-80.588562,38.790821],"type":"Point"}
}