{
  "type": "Feature",
  "properties": {
    "addr:full":"Level 3 Textile Centre Kenwyn St, Parnell  Auckland Auckland",
    "addr:housenumber":"level 3 textile centre",
    "addr:street":"St",
    "iso:country":"NZ",
    "sg:address":"Level 3 Textile Centre Kenwyn St, Parnell ",
    "sg:city":"Auckland",
    "sg:orig_category":"Clothing And Fabric: Fabric: Textiles",
    "sg:phone":"+64 9-379 2080",
    "sg:province":"Auckland",
    "wof:name":"Beyer Textiles Limited",
    "wof:placetype":"venue"
},
  "geometry": {"coordinates":[174.78608700000001,-36.85479],"type":"Point"}
}