{
  "type": "Feature",
  "properties": {
    "iso:country":"NZ",
    "sg:address":"109 Fergusson St ",
    "sg:city":"Feilding",
    "sg:orig_category":"Shopping: Retail Stores: Florists",
    "sg:phone":"+64 6-323 5510",
    "sg:province":"Manawatu-Wanganui",
    "wof:name":"Flower Box",
    "wof:placetype":"venue"
},
  "geometry": {"coordinates":[175.56684899999999,-40.226387],"type":"Point"}
}