{
  "type": "Feature",
  "properties": {
    "addr:full":"16 a Fyffe St Witherlea  Blenheim Marlborough",
    "addr:housenumber":"16",
    "addr:street":"A Fyffe St",
    "iso:country":"NZ",
    "sg:address":"16 a Fyffe St Witherlea ",
    "sg:city":"Blenheim",
    "sg:orig_category":"Farming: Services: Farm Consultants",
    "sg:phone":"+64 3-577 9100",
    "sg:province":"Marlborough",
    "wof:name":"Agricultural Consulting Services",
    "wof:placetype":"venue"
},
  "geometry": {"coordinates":[173.959778,-41.540253],"type":"Point"}
}