{
  "type": "Feature",
  "properties": {
    "addr:full":"616 Te Rapa Rd  Hamilton Waikato",
    "addr:housenumber":"616",
    "addr:street":"Te Rapa Rd",
    "iso:country":"NZ",
    "sg:address":"616 Te Rapa Rd ",
    "sg:city":"Hamilton",
    "sg:orig_category":"Home And Garden: Furniture/Furnishings: Chairmakers",
    "sg:phone":"+64 7-849 2059",
    "sg:province":"Waikato",
    "wof:name":"New Zealand Seating Ltd",
    "wof:placetype":"venue"
},
  "geometry": {"coordinates":[175.245239,-37.756718],"type":"Point"}
}