{
  "type": "Feature",
  "properties": {
    "addr:full":"14 A Main St  Blenheim Marlborough",
    "addr:housenumber":"14",
    "addr:street":"A Main St",
    "iso:country":"NZ",
    "sg:address":"14 A Main St ",
    "sg:city":"Blenheim",
    "sg:classifiers":[
        {
            "category":"Retail",
            "subcategory":"Auto Repair",
            "type":"Services"
        }
    ],
    "sg:phone":"+64 3-578 7853",
    "sg:province":"Marlborough",
    "sg:tags":[
        "engine",
        "automotive",
        "servicing"
    ],
    "wof:name":"Martin Motors",
    "wof:placetype":"venue"
},
  "geometry": {"coordinates":[-74.459564,42.468643],"type":"Point"}
}