{
  "type": "Feature",
  "properties": {
    "addr:full":"225-227 Cuba St Palmerston  Palmerston North Manawatu-Wanganui",
    "addr:housenumber":"225-227",
    "addr:street":"Cuba St Palmerston",
    "iso:country":"NZ",
    "sg:address":"225-227 Cuba St Palmerston ",
    "sg:city":"Palmerston North",
    "sg:orig_category":"Shopping: Retail Stores: Batteries",
    "sg:phone":"+64 6-357 0579",
    "sg:province":"Manawatu-Wanganui",
    "wof:name":"Collins Auto Parts",
    "wof:placetype":"venue"
},
  "geometry": {"coordinates":[175.607697,-40.35537],"type":"Point"}
}