{
  "type": "Feature",
  "properties": {
    "addr:full":"955 Cameron Rd  Tauranga Bay of Plenty",
    "addr:housenumber":"955",
    "addr:street":"Cameron Rd",
    "iso:country":"NZ",
    "sg:address":"955 Cameron Rd ",
    "sg:city":"Tauranga",
    "sg:orig_category":"Health And Beauty: Beauty: Hairdressers",
    "sg:phone":"+64 7-577 6044",
    "sg:province":"Bay of Plenty",
    "wof:name":"Clipz",
    "wof:placetype":"venue"
},
  "geometry": {"coordinates":[176.14219700000001,-37.713367],"type":"Point"}
}