{
  "type": "Feature",
  "properties": {
    "addr:full":"1 Bath St  Dunedin Otago",
    "addr:housenumber":"1",
    "addr:street":"Bath St",
    "iso:country":"NZ",
    "sg:address":"1 Bath St ",
    "sg:city":"Dunedin",
    "sg:classifiers":[
        {
            "category":"Bars & Pubs",
            "type":"Food & Drink"
        }
    ],
    "sg:phone":"+64 3-477 6750",
    "sg:province":"Otago",
    "sg:tags":[
        "wining",
        "dining",
        "brasserie"
    ],
    "wof:name":"Bath St",
    "wof:placetype":"venue"
},
  "geometry": {"coordinates":[-82.784721,28.013355],"type":"Point"}
}