{
  "type": "Feature",
  "properties": {
    "addr:full":"63 Springfield Rd  Christchurch Canterbury",
    "addr:housenumber":"63",
    "addr:street":"Springfield Rd",
    "iso:country":"NZ",
    "sg:address":"63 Springfield Rd ",
    "sg:city":"Christchurch",
    "sg:orig_category":"Health And Beauty: Mental: Psychology",
    "sg:phone":"+64 3-366 8946",
    "sg:province":"Canterbury",
    "wof:name":"De Freitas John",
    "wof:placetype":"venue"
},
  "geometry": {"coordinates":[172.632462,-43.517593],"type":"Point"}
}