{
  "type": "Feature",
  "properties": {
    "iso:country":"NZ",
    "sg:address":"Hamilton International Airport ",
    "sg:city":"Hamilton",
    "sg:classifiers":[
        {
            "category":"Travel",
            "subcategory":"Hotels & Motels",
            "type":"Entertainment"
        }
    ],
    "sg:phone":"+64 7-843 3246",
    "sg:province":"Waikato",
    "sg:tags":[
        "duty",
        "shop",
        "tourism",
        "free"
    ],
    "wof:name":"Duty Free Stores Hamilton",
    "wof:placetype":"venue"
},
  "geometry": {"coordinates":[-87.988968,34.142426],"type":"Point"}
}