{
  "type": "Feature",
  "properties": {
    "iso:country":"NZ",
    "sg:address":"1 Argyle Tce ",
    "sg:city":"Milford",
    "sg:orig_category":"Health And Beauty: Specialists: Chiropractors",
    "sg:phone":"+64 9-410 8142",
    "sg:province":"Auckland",
    "wof:name":"Stewart Dr Glenn;",
    "wof:placetype":"venue"
},
  "geometry": {"coordinates":[-73.063499,41.210743],"type":"Point"}
}