{
  "type": "Feature",
  "properties": {
    "addr:full":"10 Hartham Place Porirua  Wellington Wellington",
    "addr:housenumber":"10",
    "addr:street":"Hartham Place",
    "iso:country":"NZ",
    "sg:address":"10 Hartham Place Porirua ",
    "sg:city":"Wellington",
    "sg:classifiers":[
        {
            "category":"Retail",
            "subcategory":"Repair Shop",
            "type":"Services"
        }
    ],
    "sg:phone":"+64 4-238 2212",
    "sg:province":"Wellington",
    "sg:tags":[
        "clothing",
        "fabric",
        "cleaning"
    ],
    "wof:name":"Billis Shoetique & Boutique",
    "wof:placetype":"venue"
},
  "geometry": {"coordinates":[174.84137000000001,-41.137268],"type":"Point"}
}