{
  "type": "Feature",
  "properties": {
    "iso:country":"NZ",
    "sg:address":"4/26 Sheffield St Te Rapa ",
    "sg:city":"Hamilton",
    "sg:orig_category":"Industrial: Metal: Scrap Metal Dealers",
    "sg:phone":"+64 7-849 9010",
    "sg:province":"Waikato",
    "wof:name":"Tanks & Machinery Traders (NZ) Ltd",
    "wof:placetype":"venue"
},
  "geometry": {"coordinates":[175.243637,-37.758762],"type":"Point"}
}