{
  "type": "Feature",
  "properties": {
    "iso:country":"NZ",
    "sg:address":"35 Scanlan St Grey Lynn ",
    "sg:city":"Auckland",
    "sg:classifiers":[
        {
            "category":"Travel",
            "subcategory":"Travel Agent",
            "type":"Entertainment"
        }
    ],
    "sg:phone":"+64 9-376 2533",
    "sg:province":"Auckland",
    "sg:tags":[
        "tourism",
        "broker"
    ],
    "wof:name":"Fiji Visitors Bureau",
    "wof:placetype":"venue"
},
  "geometry": {"coordinates":[174.746994,-36.860069],"type":"Point"}
}