{
  "type": "Feature",
  "properties": {
    "addr:full":"New Haven Way Off Discovery Dve Whitby  Porirua Wellington",
    "addr:street":"New Haven Way Off Discovery",
    "iso:country":"NZ",
    "sg:address":"New Haven Way Off Discovery Dve Whitby ",
    "sg:city":"Porirua",
    "sg:classifiers":[
        {
            "category":"Social Services",
            "subcategory":"Retirement Home",
            "type":"Services"
        }
    ],
    "sg:phone":"+64 4-234 6627",
    "sg:province":"Wellington",
    "sg:tags":[
        "care",
        "garden",
        "elderly",
        "village"
    ],
    "wof:name":"Whitby Village Estate",
    "wof:placetype":"venue"
},
  "geometry": {"coordinates":[174.88900799999999,-41.111599],"type":"Point"}
}