{
  "type": "Feature",
  "properties": {
    "addr:full":"32 James Line RD 10 Palmerston  Palmerston North Manawatu-Wanganui",
    "addr:housenumber":"32;10;palmerston",
    "addr:street":"James Line Rd;Palmerston",
    "iso:country":"NZ",
    "sg:address":"32 James Line RD 10 Palmerston ",
    "sg:city":"Palmerston North",
    "sg:classifiers":[
        {
            "category":"Autos & Motor Vehicles",
            "subcategory":"Automobile Sales",
            "type":"Retail Goods"
        }
    ],
    "sg:phone":"+64 6-355 5864",
    "sg:province":"Manawatu-Wanganui",
    "sg:tags":[
        "home",
        "caravan",
        "leasing",
        "automotive"
    ],
    "wof:name":"Caravan Clinic",
    "wof:placetype":"venue"
},
  "geometry": {"coordinates":[175.611481,-40.357418],"type":"Point"}
}