{
  "type": "Feature",
  "properties": {
    "iso:country":"NZ",
    "sg:address":"424 Featherston St Palmerston ",
    "sg:city":"Palmerston North",
    "sg:orig_category":"Shopping: Retail Stores: Florist Accessories",
    "sg:phone":"+64 6-357 3320",
    "sg:province":"Manawatu-Wanganui",
    "wof:name":"Flower Shop",
    "wof:placetype":"venue"
},
  "geometry": {"coordinates":[175.61972,-40.344006],"type":"Point"}
}