{
  "type": "Feature",
  "properties": {
    "addr:full":"114 Main Highway Ellerslie  Auckland Auckland",
    "addr:housenumber":"114",
    "addr:street":"Main Highway",
    "iso:country":"NZ",
    "sg:address":"114 Main Highway Ellerslie ",
    "sg:city":"Auckland",
    "sg:classifiers":[
        {
            "category":"Professional",
            "subcategory":"Art Services",
            "type":"Services"
        }
    ],
    "sg:phone":"+64 9-526 4856",
    "sg:province":"Auckland",
    "sg:tags":[
        "picture",
        "arts",
        "sport",
        "framing",
        "leisure"
    ],
    "sg:website":"http://framebyframe.co.nz",
    "wof:name":"Frame By Frame",
    "wof:placetype":"venue"
},
  "geometry": {"coordinates":[174.80883800000001,-36.897575],"type":"Point"}
}