{
  "type": "Feature",
  "properties": {
    "iso:country":"NZ",
    "sg:address":"PO Box 35216 Browns Bay ",
    "sg:city":"Auckland",
    "sg:orig_category":"Shopping: Sports Retailers: Water Sports: Diving Equipment",
    "sg:phone":"+64 9-415 0229",
    "sg:province":"Auckland",
    "wof:name":"Pinnacle Sports Ltd",
    "wof:placetype":"venue"
},
  "geometry": {"coordinates":[174.744324,-36.714409],"type":"Point"}
}