{
  "type": "Feature",
  "properties": {
    "addr:full":"Main Rd Waikanae  Paraparaumu Wellington",
    "addr:street":"Main Rd",
    "iso:country":"NZ",
    "sg:address":"Main Rd Waikanae ",
    "sg:city":"Paraparaumu",
    "sg:classifiers":[
        {
            "category":"Food & Beverages",
            "subcategory":"Bakery",
            "type":"Retail Goods"
        }
    ],
    "sg:phone":"+64 9026888",
    "sg:province":"Wellington",
    "sg:tags":[
        "shop",
        "cake",
        "drink",
        "-"
    ],
    "wof:name":"Collins Pastrycooks Ltd",
    "wof:placetype":"venue"
},
  "geometry": {"coordinates":[175.06466699999999,-40.878239],"type":"Point"}
}