{
  "type": "Feature",
  "properties": {
    "addr:full":"528 Pollen St  Thames Waikato",
    "addr:housenumber":"528",
    "addr:street":"Pollen St",
    "iso:country":"NZ",
    "sg:address":"528 Pollen St ",
    "sg:city":"Thames",
    "sg:orig_category":"Home And Garden: Furniture/Furnishings: Curtains",
    "sg:phone":"+64 7-867 9205",
    "sg:province":"Waikato",
    "wof:name":"Fabric Express",
    "wof:placetype":"venue"
},
  "geometry": {"coordinates":[120.35865,23.960051],"type":"Point"}
}