{
  "type": "Feature",
  "properties": {
    "addr:full":"491 Cameron Rd  Tauranga Bay of Plenty",
    "addr:housenumber":"491",
    "addr:street":"Cameron Rd",
    "iso:country":"NZ",
    "sg:address":"491 Cameron Rd ",
    "sg:city":"Tauranga",
    "sg:classifiers":[
        {
            "category":"Restaurant",
            "type":"Food & Drink"
        }
    ],
    "sg:phone":"+64 7-578 5446",
    "sg:province":"Bay of Plenty",
    "sg:tags":[
        "wining",
        "dining",
        "pizza"
    ],
    "wof:name":"Pizza Haven",
    "wof:placetype":"venue"
},
  "geometry": {"coordinates":[176.15991199999999,-37.696995],"type":"Point"}
}