{
  "type": "Feature",
  "properties": {
    "iso:country":"NZ",
    "sg:address":"5 Anderley Ave Omokoroa ",
    "sg:city":"Tauranga",
    "sg:classifiers":[
        {
            "category":"Social Services",
            "subcategory":"Retirement Home",
            "type":"Services"
        }
    ],
    "sg:phone":"+64 7-548 1100",
    "sg:province":"Bay of Plenty",
    "sg:tags":[
        "care",
        "garden",
        "elderly",
        "village"
    ],
    "wof:name":"Omokoroa Country Estate",
    "wof:placetype":"venue"
},
  "geometry": {"coordinates":[176.14475999999999,-37.703152],"type":"Point"}
}