{
  "type": "Feature",
  "properties": {
    "addr:full":"30 Greenpark Rd Penrose  Auckland Auckland",
    "addr:housenumber":"30",
    "addr:street":"Greenpark Rd",
    "iso:country":"NZ",
    "sg:address":"30 Greenpark Rd Penrose ",
    "sg:city":"Auckland",
    "sg:orig_category":"Food And Drink: Catering: Caterers",
    "sg:phone":"+64 9-525 5785",
    "sg:province":"Auckland",
    "wof:name":"Corporate Function Services",
    "wof:placetype":"venue"
},
  "geometry": {"coordinates":[174.80779999999999,-36.906345],"type":"Point"}
}