{
  "type": "Feature",
  "properties": {
    "iso:country":"NZ",
    "sg:address":"306 Stafford St ",
    "sg:city":"Timaru",
    "sg:classifiers":[
        {
            "category":"Bars & Pubs",
            "type":"Food & Drink"
        }
    ],
    "sg:phone":"+64 3-684 3302",
    "sg:province":"Canterbury",
    "sg:tags":[
        "wining",
        "dining",
        "brasserie"
    ],
    "wof:name":"Zebz Cafe & Bar",
    "wof:placetype":"venue"
},
  "geometry": {"coordinates":[171.250778,-44.394012],"type":"Point"}
}