{
  "type": "Feature",
  "properties": {
    "addr:full":"Awanui  Kaitaia Northland",
    "iso:country":"NZ",
    "sg:address":"Awanui ",
    "sg:city":"Kaitaia",
    "sg:classifiers":[
        {
            "category":"Shopping",
            "subcategory":"Pets & Pet Supplies",
            "type":"Retail Goods"
        }
    ],
    "sg:phone":"+64 9-406 7070",
    "sg:province":"Northland",
    "sg:tags":[
        "boarding",
        "garden",
        "pets",
        "catteries",
        "home",
        "kennel"
    ],
    "wof:name":"Awanui Ani-Motel",
    "wof:placetype":"venue"
},
  "geometry": {"coordinates":[173.25520299999999,-35.05006],"type":"Point"}
}