{
  "type": "Feature",
  "properties": {
    "addr:full":"140 Chapel St  Masterton Wellington",
    "addr:housenumber":"140",
    "addr:street":"Chapel St",
    "iso:country":"NZ",
    "sg:address":"140 Chapel St ",
    "sg:city":"Masterton",
    "sg:classifiers":[
        {
            "category":"Social Services",
            "subcategory":"Retirement Home",
            "type":"Services"
        }
    ],
    "sg:phone":"+64 6-378 2577",
    "sg:province":"Wellington",
    "sg:tags":[
        "care",
        "garden",
        "elderly",
        "village"
    ],
    "wof:name":"Metlifecare",
    "wof:placetype":"venue"
},
  "geometry": {"coordinates":[175.65010100000001,-40.95562],"type":"Point"}
}