{
  "type": "Feature",
  "properties": {
    "addr:full":"179 Featherston St  Wellington Wellington",
    "addr:housenumber":"179",
    "addr:street":"Featherston St",
    "iso:country":"NZ",
    "sg:address":"179 Featherston St ",
    "sg:city":"Wellington",
    "sg:classifiers":[
        {
            "category":"Retail",
            "subcategory":"Laundry & Dry Cleaning",
            "type":"Services"
        }
    ],
    "sg:phone":"+64 4-472 8174",
    "sg:province":"Wellington",
    "sg:tags":[
        "repair",
        "clothing",
        "fabric",
        "cleaner"
    ],
    "wof:name":"Taylors Drycleaners",
    "wof:placetype":"venue"
},
  "geometry": {"coordinates":[174.77629099999999,-41.284847],"type":"Point"}
}