{
  "type": "Feature",
  "properties": {
    "iso:country":"NZ",
    "sg:address":"89 B Main Rd Redcliffs ",
    "sg:city":"Christchurch",
    "sg:classifiers":[
        {
            "category":"Shopping",
            "subcategory":"Crafts & Fabrics",
            "type":"Retail Goods"
        }
    ],
    "sg:phone":"+64 3-384 4783",
    "sg:province":"Canterbury",
    "sg:tags":[
        "pottery",
        "home",
        "accessories",
        "garden",
        "supply"
    ],
    "wof:name":"Mainly Pots",
    "wof:placetype":"venue"
},
  "geometry": {"coordinates":[172.738953,-43.561771],"type":"Point"}
}