{
  "type": "Feature",
  "properties": {
    "addr:full":"30 Stevens St Waltham  Christchurch Canterbury",
    "addr:housenumber":"30",
    "addr:street":"Stevens St",
    "iso:country":"NZ",
    "sg:address":"30 Stevens St Waltham ",
    "sg:city":"Christchurch",
    "sg:classifiers":[
        {
            "category":"Professional",
            "type":"Services"
        }
    ],
    "sg:phone":"+64 3-379 7089",
    "sg:province":"Canterbury",
    "sg:tags":[
        "function",
        "entertainment",
        "leisure",
        "planning",
        "party",
        "sport"
    ],
    "sg:website":"http://www.jadestadium.co.nz",
    "wof:name":"Jade Stadium Christchurch",
    "wof:placetype":"venue"
},
  "geometry": {"coordinates":[172.65339700000001,-43.541164],"type":"Point"}
}