{
  "type": "Feature",
  "properties": {
    "addr:full":"5 Mins from Town 525 Ngongotaha Rd  Rotorua Bay of Plenty",
    "addr:housenumber":"5;525",
    "addr:street":"Ngongotaha Rd",
    "iso:country":"NZ",
    "sg:address":"5 Mins from Town 525 Ngongotaha Rd ",
    "sg:city":"Rotorua",
    "sg:classifiers":[
        {
            "category":"Recreation",
            "type":"Entertainment"
        }
    ],
    "sg:phone":"+64 7-348 8400",
    "sg:province":"Bay of Plenty",
    "sg:tags":[
        "sport",
        "leisure"
    ],
    "sg:website":"http://www.mountainaction.co.nz",
    "wof:name":"Mountain Action",
    "wof:placetype":"venue"
},
  "geometry": {"coordinates":[176.24499499999999,-38.1418],"type":"Point"}
}