{
  "type": "Feature",
  "properties": {
    "addr:full":"15 Fisher Cre Mt Wellington  Auckland Auckland",
    "addr:housenumber":"15",
    "addr:street":"Fisher Cre",
    "iso:country":"NZ",
    "sg:address":"15 Fisher Cre Mt Wellington ",
    "sg:city":"Auckland",
    "sg:orig_category":"Industrial: Consultancy: Corrosion Control",
    "sg:phone":"+64 9-573 0262",
    "sg:province":"Auckland",
    "wof:name":"Mount Wellington Metalisation",
    "wof:placetype":"venue"
},
  "geometry": {"coordinates":[174.854263,-36.921532],"type":"Point"}
}