{
  "type": "Feature",
  "properties": {
    "iso:country":"NZ",
    "sg:address":"Preeces Point Rd ",
    "sg:city":"Coromandel",
    "sg:orig_category":"Shopping: Engravers",
    "sg:phone":"+64 7-866 8946",
    "wof:name":"Express Engravers",
    "wof:placetype":"venue"
},
  "geometry": {"coordinates":[175.503906,-36.775913],"type":"Point"}
}