{
  "type": "Feature",
  "properties": {
    "iso:country":"NZ",
    "sg:address":"24 Parumoana St Porirua ",
    "sg:city":"Wellington",
    "sg:orig_category":"Shopping: Retail Stores: Department Stores",
    "sg:phone":"+64 4-238 9101",
    "sg:province":"Wellington",
    "wof:name":"Briscoes Homeware",
    "wof:placetype":"venue"
},
  "geometry": {"coordinates":[174.83926399999999,-41.131008],"type":"Point"}
}