{
  "type": "Feature",
  "properties": {
    "addr:full":"14-16 Kokako St  Rotorua Bay of Plenty",
    "addr:housenumber":"14-16",
    "addr:street":"Kokako St",
    "iso:country":"NZ",
    "sg:address":"14-16 Kokako St ",
    "sg:city":"Rotorua",
    "sg:classifiers":[
        {
            "category":"Bars & Pubs",
            "type":"Food & Drink"
        }
    ],
    "sg:phone":"+64 7-349 1971",
    "sg:province":"Bay of Plenty",
    "sg:tags":[
        "wining",
        "dining",
        "brasserie"
    ],
    "wof:name":"Mac's Bar",
    "wof:placetype":"venue"
},
  "geometry": {"coordinates":[176.22279399999999,-38.116909],"type":"Point"}
}