{
  "type": "Feature",
  "properties": {
    "addr:full":"Hawthorne Dve, Remarkables Park  Queenstown Otago",
    "iso:country":"NZ",
    "sg:address":"Hawthorne Dve, Remarkables Park ",
    "sg:city":"Queenstown",
    "sg:orig_category":"Shopping: Retail Stores: Department Stores",
    "sg:phone":"+64 3-441 4400",
    "sg:province":"Otago",
    "wof:name":"The Warehouse Ltd",
    "wof:placetype":"venue"
},
  "geometry": {"coordinates":[-76.157791,38.990379],"type":"Point"}
}