{
  "type": "Feature",
  "properties": {
    "iso:country":"NZ",
    "sg:address":"Maungakaramea Rd ",
    "sg:city":"Maungakaramea",
    "sg:orig_category":"Farming: Forestry",
    "sg:phone":"+64 9-432 3750",
    "sg:website":"http://www.yellowpages.co.nz/for/cochranelogging/dp52103.html",
    "wof:name":"Cochrane Logging Ltd",
    "wof:placetype":"venue"
},
  "geometry": {"coordinates":[174.19593800000001,-35.846291],"type":"Point"}
}