{
  "type": "Feature",
  "properties": {
    "addr:full":"263-269 Fraser St  Tauranga Bay of Plenty",
    "addr:housenumber":"263-269",
    "addr:street":"Fraser St",
    "iso:country":"NZ",
    "sg:address":"263-269 Fraser St ",
    "sg:city":"Tauranga",
    "sg:classifiers":[
        {
            "category":"Home & Garden",
            "subcategory":"Home Furnishings",
            "type":"Retail Goods"
        }
    ],
    "sg:phone":"+64 7-571 0249",
    "sg:province":"Bay of Plenty",
    "sg:tags":[
        "furniture/furnishings",
        "bedding",
        "bed"
    ],
    "wof:name":"Bigsave Furniture Ltd",
    "wof:placetype":"venue"
},
  "geometry": {"coordinates":[176.15077199999999,-37.714573],"type":"Point"}
}