{
  "type": "Feature",
  "properties": {
    "iso:country":"NZ",
    "sg:address":"Cook Flat Rd Fox ",
    "sg:city":"Glacier",
    "sg:classifiers":[
        {
            "category":"Banks & Credit Unions",
            "subcategory":"Investment Brokerage",
            "type":"Services"
        }
    ],
    "sg:phone":"+64 3-751 0816",
    "sg:tags":[
        "educational",
        "education",
        "training"
    ],
    "wof:name":"Fox Glacier School",
    "wof:placetype":"venue"
},
  "geometry": {"coordinates":[170.00836200000001,-43.462543],"type":"Point"}
}