{
  "type": "Feature",
  "properties": {
    "addr:full":"215 Crawford St  Dunedin Otago",
    "addr:housenumber":"215",
    "addr:street":"Crawford St",
    "iso:country":"NZ",
    "sg:address":"215 Crawford St ",
    "sg:city":"Dunedin",
    "sg:classifiers":[
        {
            "category":"Retail",
            "subcategory":"Auto Repair",
            "type":"Services"
        }
    ],
    "sg:phone":"+64 3-479 0555",
    "sg:province":"Otago",
    "sg:tags":[
        "automotive",
        "electric",
        "servicing"
    ],
    "wof:name":"Pan Pacific Auto Electronics Ltd",
    "wof:placetype":"venue"
},
  "geometry": {"coordinates":[-82.784721,28.013355],"type":"Point"}
}