{
  "type": "Feature",
  "properties": {
    "iso:country":"NZ",
    "sg:address":"7 Leader St ",
    "sg:city":"Riverton",
    "sg:classifiers":[
        {
            "category":"Health Services",
            "subcategory":"Dentist",
            "type":"Services"
        }
    ],
    "sg:phone":"+64 3-234 8571",
    "sg:tags":[
        "dental",
        "clinic",
        "beauty"
    ],
    "wof:name":"Riverton School Dental Clinic",
    "wof:placetype":"venue"
},
  "geometry": {"coordinates":[-73.025848,41.957958],"type":"Point"}
}