{
  "type": "Feature",
  "properties": {
    "addr:full":"Ward St  Hamilton Waikato",
    "addr:street":"Ward St",
    "iso:country":"NZ",
    "sg:address":"Ward St ",
    "sg:city":"Hamilton",
    "sg:orig_category":"Shopping: Retail Stores: Convenience Stores",
    "sg:phone":"+64 7-834 1545",
    "sg:province":"Waikato",
    "wof:name":"Star Mart",
    "wof:placetype":"venue"
},
  "geometry": {"coordinates":[-114.180809,46.134609],"type":"Point"}
}