{
  "type": "Feature",
  "properties": {
    "addr:full":"370 Glenfield Rd Glenfield  Auckland Auckland",
    "addr:housenumber":"370",
    "addr:street":"Glenfield Rd",
    "iso:country":"NZ",
    "sg:address":"370 Glenfield Rd Glenfield ",
    "sg:city":"Auckland",
    "sg:classifiers":[
        {
            "category":"Shopping",
            "subcategory":"Pharmacy",
            "type":"Retail Goods"
        }
    ],
    "sg:phone":"+64 9-443 6630",
    "sg:province":"Auckland",
    "sg:tags":[
        "products",
        "medical",
        "health",
        "beauty",
        "supply"
    ],
    "wof:name":"Sheffmed NZ Ltd",
    "wof:placetype":"venue"
},
  "geometry": {"coordinates":[174.72071800000001,-36.786121],"type":"Point"}
}