{
  "type": "Feature",
  "properties": {
    "addr:full":"cnr Lake Rd & Somerset St  Hamilton Waikato",
    "addr:street":"Cnr Lake Rd & Somerset St",
    "iso:country":"NZ",
    "sg:address":"cnr Lake Rd & Somerset St ",
    "sg:city":"Hamilton",
    "sg:orig_category":"Shopping: Sports Retailers: Water Sports: Surfboards",
    "sg:phone":"+64 7-846 9007",
    "sg:province":"Waikato",
    "wof:name":"The Fibreglass Shop",
    "wof:placetype":"venue"
},
  "geometry": {"coordinates":[-74.619331,40.50626],"type":"Point"}
}