{
  "type": "Feature",
  "properties": {
    "addr:full":"248 Stanmore Rd Richmond  Christchurch Nelson",
    "addr:housenumber":"248",
    "addr:street":"Stanmore Rd",
    "iso:country":"NZ",
    "sg:address":"248 Stanmore Rd Richmond ",
    "sg:city":"Christchurch",
    "sg:classifiers":[
        {
            "category":"Communications",
            "subcategory":"Film & Video Production",
            "type":"Services"
        }
    ],
    "sg:phone":"+64 3-389 7506",
    "sg:province":"Nelson",
    "sg:tags":[
        "sport",
        "leisure",
        "library",
        "entertainment"
    ],
    "wof:name":"Movie Man Ltd",
    "wof:placetype":"venue"
},
  "geometry": {"coordinates":[172.65669299999999,-43.522678],"type":"Point"}
}