{
  "type": "Feature",
  "properties": {
    "addr:full":"17 Fairfax Ave Penrose  Auckland Auckland",
    "addr:housenumber":"17",
    "addr:street":"Fairfax Ave",
    "iso:country":"NZ",
    "sg:address":"17 Fairfax Ave Penrose ",
    "sg:city":"Auckland",
    "sg:classifiers":[
        {
            "category":"Home & Garden",
            "subcategory":"Building Materials",
            "type":"Retail Goods"
        }
    ],
    "sg:phone":"+64 9-579 0333",
    "sg:province":"Auckland",
    "sg:tags":[
        "door",
        "fitting",
        "fittings"
    ],
    "wof:name":"Door Services Ltd",
    "wof:placetype":"venue"
},
  "geometry": {"coordinates":[174.810394,-36.912186],"type":"Point"}
}