{
  "type": "Feature",
  "properties": {
    "iso:country":"NZ",
    "sg:address":"Cnr Fifteenth Ave & Fraser St ",
    "sg:city":"Tauranga",
    "sg:classifiers":[
        {
            "category":"Home & Garden",
            "subcategory":"Building Materials",
            "type":"Retail Goods"
        }
    ],
    "sg:phone":"+64 7-577 9934",
    "sg:province":"Bay of Plenty",
    "sg:tags":[
        "builder",
        "related"
    ],
    "wof:name":"Golden Homes",
    "wof:placetype":"venue"
},
  "geometry": {"coordinates":[176.14475999999999,-37.703152],"type":"Point"}
}