{
  "type": "Feature",
  "properties": {
    "iso:country":"NZ",
    "sg:address":"CALL FREE Anywhere in New Zealand Palmerston ",
    "sg:city":"Palmerston North",
    "sg:classifiers":[
        {
            "category":"Shopping",
            "subcategory":"Beauty & Cosmetics",
            "type":"Retail Goods"
        }
    ],
    "sg:phone":"+64 800 925 546",
    "sg:province":"Manawatu-Wanganui",
    "sg:tags":[
        "podiatrist",
        "health",
        "products",
        "supply"
    ],
    "wof:name":"Walking New Zealand Magazine",
    "wof:placetype":"venue"
},
  "geometry": {"coordinates":[175.609543,-40.354053],"type":"Point"}
}