{
  "type": "Feature",
  "properties": {
    "addr:full":"37 Maleme St Greerton  Tauranga Bay of Plenty",
    "addr:housenumber":"37",
    "addr:street":"Maleme St",
    "iso:country":"NZ",
    "sg:address":"37 Maleme St Greerton ",
    "sg:city":"Tauranga",
    "sg:orig_category":"Farming: Forestry: Logging Services",
    "sg:phone":"+64 7-541 3866",
    "sg:province":"Bay of Plenty",
    "wof:name":"Timber Posts and Rails",
    "wof:placetype":"venue"
},
  "geometry": {"coordinates":[176.13729900000001,-37.736198],"type":"Point"}
}