{
  "type": "Feature",
  "properties": {
    "addr:full":"22 Lowther St Sockburn  Christchurch Canterbury",
    "addr:housenumber":"22",
    "addr:street":"Lowther St",
    "iso:country":"NZ",
    "sg:address":"22 Lowther St Sockburn ",
    "sg:city":"Christchurch",
    "sg:orig_category":"Shopping: Sports Retailers: Sports Goods: Canvas Goods",
    "sg:phone":"+64 3-348 0380",
    "sg:province":"Canterbury",
    "wof:name":"Tunnelworld New Zealand Ltd",
    "wof:placetype":"venue"
},
  "geometry": {"coordinates":[172.549454,-43.538879],"type":"Point"}
}