{
  "type": "Feature",
  "properties": {
    "addr:full":"31 Woodmancote Rd Khandallah  Wellington Wellington",
    "addr:housenumber":"31",
    "addr:street":"Woodmancote Rd",
    "iso:country":"NZ",
    "sg:address":"31 Woodmancote Rd Khandallah ",
    "sg:city":"Wellington",
    "sg:classifiers":[
        {
            "category":"Education",
            "subcategory":"Music School",
            "type":"Public Place"
        }
    ],
    "sg:phone":"+64 4-479 2542",
    "sg:province":"Wellington",
    "sg:tags":[
        "sport",
        "teacher",
        "leisure"
    ],
    "wof:name":"Loretta Lander",
    "wof:placetype":"venue"
},
  "geometry": {"coordinates":[174.789627,-41.242439],"type":"Point"}
}