{
  "type": "Feature",
  "properties": {
    "addr:full":"889 Main St Palmerston  Palmerston North Manawatu-Wanganui",
    "addr:housenumber":"889",
    "addr:street":"Main St",
    "iso:country":"NZ",
    "sg:address":"889 Main St Palmerston ",
    "sg:city":"Palmerston North",
    "sg:classifiers":[
        {
            "category":"Bars & Pubs",
            "subcategory":"Lounge",
            "type":"Food & Drink"
        }
    ],
    "sg:phone":"+64 6-356 3181",
    "sg:province":"Manawatu-Wanganui",
    "sg:tags":[
        "baker",
        "-"
    ],
    "wof:name":"Mr Macs ME T PI",
    "wof:placetype":"venue"
},
  "geometry": {"coordinates":[175.60633899999999,-40.35825],"type":"Point"}
}