{
  "type": "Feature",
  "properties": {
    "addr:full":"6 Great South Rd Papatoetoe  Auckland Auckland",
    "addr:housenumber":"6",
    "addr:street":"Great South Rd",
    "iso:country":"NZ",
    "sg:address":"6 Great South Rd Papatoetoe ",
    "sg:city":"Auckland",
    "sg:orig_category":"Home And Garden: Furniture/Furnishings: Curtains",
    "sg:phone":"+64 9-278 0193",
    "sg:province":"Auckland",
    "wof:name":"Curtain Supermarket Ltd",
    "wof:placetype":"venue"
},
  "geometry": {"coordinates":[174.85813899999999,-36.9669],"type":"Point"}
}