{
  "type": "Feature",
  "properties": {
    "addr:full":"362 Western Hills Dve  Whangarei Northland",
    "addr:housenumber":"362",
    "addr:street":"Western",
    "iso:country":"NZ",
    "sg:address":"362 Western Hills Dve ",
    "sg:city":"Whangarei",
    "sg:classifiers":[
        {
            "category":"Travel",
            "subcategory":"Hotels & Motels",
            "type":"Entertainment"
        }
    ],
    "sg:phone":"+64 9-430 8634",
    "sg:province":"Northland",
    "sg:tags":[
        "lodge",
        "tourism",
        "accommodation"
    ],
    "sg:website":"http://www.yellowpages.co.nz/pages/223860988/dp17240.html",
    "wof:name":"BK'S Pohutukawa Lodge",
    "wof:placetype":"venue"
},
  "geometry": {"coordinates":[-81.474701,39.417198],"type":"Point"}
}