{
  "type": "Feature",
  "properties": {
    "iso:country":"NZ",
    "sg:address":"PO Box 51 ",
    "sg:city":"Blenheim",
    "sg:classifiers":[
        {
            "category":"Home & Garden",
            "subcategory":"Building Materials",
            "type":"Retail Goods"
        }
    ],
    "sg:phone":"+64 3-577 8606",
    "sg:province":"Marlborough",
    "sg:tags":[
        "builder",
        "related"
    ],
    "wof:name":"Tomlinson Construction Ltd",
    "wof:placetype":"venue"
},
  "geometry": {"coordinates":[-74.459564,42.468643],"type":"Point"}
}