{
  "type": "Feature",
  "properties": {
    "iso:country":"NZ",
    "sg:address":"5/7 Manuka Rd Glenfield ",
    "sg:city":"Auckland",
    "sg:classifiers":[
        {
            "category":"Bars & Pubs",
            "subcategory":"Lounge",
            "type":"Food & Drink"
        }
    ],
    "sg:phone":"+64 9-444 4427",
    "sg:province":"Auckland",
    "sg:tags":[
        "baker",
        "-"
    ],
    "wof:name":"Loafers Bakery",
    "wof:placetype":"venue"
},
  "geometry": {"coordinates":[174.72023,-36.7742],"type":"Point"}
}