{
  "type": "Feature",
  "properties": {
    "iso:country":"NZ",
    "sg:address":"19 Horomatangi St ",
    "sg:city":"Taupo",
    "sg:classifiers":[
        {
            "category":"Shopping",
            "subcategory":"Crafts & Fabrics",
            "type":"Retail Goods"
        }
    ],
    "sg:phone":"+64 7-377 0421",
    "sg:province":"Waikato",
    "sg:tags":[
        "foot",
        "clothing",
        "retailer",
        "footwear",
        "wear"
    ],
    "wof:name":"Chasse",
    "wof:placetype":"venue"
},
  "geometry": {"coordinates":[176.07055700000001,-38.686932],"type":"Point"}
}