{
  "type": "Feature",
  "properties": {
    "iso:country":"NZ",
    "sg:address":"536 Bethels Rd R D 5 Christchurch ",
    "sg:city":"Springston",
    "sg:orig_category":"Transport: Land",
    "sg:phone":"+64 3-329 5197",
    "sg:website":"http://www.southerncarrentals.co.nz",
    "wof:name":"Southern Car Rentals Ltd",
    "wof:placetype":"venue"
},
  "geometry": {"coordinates":[172.423187,-43.642738],"type":"Point"}
}