{
  "type": "Feature",
  "properties": {
    "addr:full":"2 Des Swann Dve Takapuna  Auckland Auckland",
    "addr:housenumber":"2",
    "addr:street":"Des Swann",
    "iso:country":"NZ",
    "sg:address":"2 Des Swann Dve Takapuna ",
    "sg:city":"Auckland",
    "sg:classifiers":[
        {
            "category":"Personal",
            "subcategory":"Tanning Parlor",
            "type":"Services"
        }
    ],
    "sg:phone":"+64 9-486 4691",
    "sg:province":"Auckland",
    "sg:tags":[
        "sun",
        "health",
        "beauty"
    ],
    "wof:name":"Shore Tan",
    "wof:placetype":"venue"
},
  "geometry": {"coordinates":[174.76417499999999,-36.793018],"type":"Point"}
}