{
  "type": "Feature",
  "properties": {
    "iso:country":"NZ",
    "sg:address":"44 McAlistair Street ",
    "sg:city":"Whakatane",
    "sg:orig_category":"Industrial: Equipment And Machinery: Generators",
    "sg:phone":"+64 7-307 0902",
    "sg:province":"Bay of Plenty",
    "wof:name":"Bay Engineers Supplies Ltd",
    "wof:placetype":"venue"
},
  "geometry": {"coordinates":[176.98419200000001,-37.965305],"type":"Point"}
}