{
  "type": "Feature",
  "properties": {
    "addr:full":"31 Maisey Pl  Rotorua Bay of Plenty",
    "addr:housenumber":"31",
    "addr:street":"Maisey Pl",
    "iso:country":"NZ",
    "sg:address":"31 Maisey Pl ",
    "sg:city":"Rotorua",
    "sg:classifiers":[
        {
            "category":"Home & Garden",
            "subcategory":"Furniture",
            "type":"Retail Goods"
        }
    ],
    "sg:phone":"+64 7-349 2744",
    "sg:province":"Bay of Plenty",
    "sg:tags":[
        "furniture/furnishings",
        "repair",
        "finishing"
    ],
    "wof:name":"The Polish Shop",
    "wof:placetype":"venue"
},
  "geometry": {"coordinates":[176.22717299999999,-38.121674],"type":"Point"}
}