{
  "type": "Feature",
  "properties": {
    "addr:full":"639 Tremaine Ave Palmerston  Palmerston North Manawatu-Wanganui",
    "addr:housenumber":"639",
    "addr:street":"Tremaine Ave",
    "iso:country":"NZ",
    "sg:address":"639 Tremaine Ave Palmerston ",
    "sg:city":"Palmerston North",
    "sg:classifiers":[
        {
            "category":"Communications",
            "subcategory":"Television Station",
            "type":"Services"
        }
    ],
    "sg:phone":"+64 6-351 7250",
    "sg:province":"Manawatu-Wanganui",
    "sg:tags":[
        "tv",
        "radio",
        "broadcasting",
        "-"
    ],
    "wof:name":"B.C.L.",
    "wof:placetype":"venue"
},
  "geometry": {"coordinates":[175.607101,-40.340736],"type":"Point"}
}