{
  "type": "Feature",
  "properties": {
    "iso:country":"NZ",
    "sg:address":"43 Veronica St New Lynn ",
    "sg:city":"Auckland",
    "sg:classifiers":[
        {
            "category":"Shopping",
            "type":"Retail Goods"
        }
    ],
    "sg:phone":"+64 9-827 1111",
    "sg:province":"Auckland",
    "sg:tags":[
        "store"
    ],
    "sg:website":"http://www.partyhire.co.nz",
    "wof:name":"Laser Direct Ltd",
    "wof:placetype":"venue"
},
  "geometry": {"coordinates":[174.685043,-36.904442],"type":"Point"}
}