{
  "type": "Feature",
  "properties": {
    "iso:country":"NZ",
    "sg:address":"1892 Gt North Rd Avondale ",
    "sg:city":"Auckland",
    "sg:classifiers":[
        {
            "category":"Shopping",
            "subcategory":"Shoes",
            "type":"Retail Goods"
        }
    ],
    "sg:phone":"+64 9-828 8904",
    "sg:province":"Auckland",
    "sg:tags":[
        "foot",
        "clothing",
        "fabric",
        "wear"
    ],
    "wof:name":"Avondale Shoes",
    "wof:placetype":"venue"
},
  "geometry": {"coordinates":[174.69693,-36.895157],"type":"Point"}
}