{
  "type": "Feature",
  "properties": {
    "addr:full":"22 A Aranui Rd  Mapua Auckland",
    "addr:housenumber":"22 a",
    "addr:street":"Aranui Rd",
    "iso:country":"NZ",
    "sg:address":"22 A Aranui Rd ",
    "sg:city":"Mapua",
    "sg:classifiers":[
        {
            "category":"Home & Garden",
            "subcategory":"Home Furnishings",
            "type":"Retail Goods"
        }
    ],
    "sg:phone":"+64 3-540 3467",
    "sg:province":"Auckland",
    "sg:tags":[
        "furniture/furnishings",
        "upholstery",
        "supply"
    ],
    "wof:name":"Couldn't Be Keener Upholstery",
    "wof:placetype":"venue"
},
  "geometry": {"coordinates":[173.101089,-41.256508],"type":"Point"}
}