{
  "type": "Feature",
  "properties": {
    "addr:full":"PO Box 58-131 Greenmount  Auckland Auckland",
    "addr:housenumber":"po box 58-131",
    "iso:country":"NZ",
    "sg:address":"PO Box 58-131 Greenmount ",
    "sg:city":"Auckland",
    "sg:classifiers":[
        {
            "category":"Home & Garden",
            "subcategory":"Building Materials",
            "type":"Retail Goods"
        }
    ],
    "sg:phone":"+64 9-536 4431",
    "sg:province":"Auckland",
    "sg:tags":[
        "gate",
        "fitting",
        "outdoor"
    ],
    "wof:name":"Premier Electronics Ltd",
    "wof:placetype":"venue"
},
  "geometry": {"coordinates":[174.67128,-36.774693],"type":"Point"}
}