{
  "type": "Feature",
  "properties": {
    "addr:full":"119 Mary Rd  Whangamata",
    "addr:housenumber":"119",
    "addr:street":"Mary Rd",
    "iso:country":"NZ",
    "sg:address":"119 Mary Rd ",
    "sg:city":"Whangamata",
    "sg:classifiers":[
        {
            "category":"Shopping",
            "subcategory":"Pharmacy",
            "type":"Retail Goods"
        }
    ],
    "sg:phone":"+64 7-865 9983",
    "sg:tags":[
        "product",
        "health"
    ],
    "wof:name":"Rawleigh Independent Distributor --- Lillian Taylor",
    "wof:placetype":"venue"
},
  "geometry": {"coordinates":[175.87554900000001,-37.214363],"type":"Point"}
}