{
  "type": "Feature",
  "properties": {
    "iso:country":"NZ",
    "sg:address":"PO Box 149 New ",
    "sg:city":"Plymouth",
    "sg:classifiers":[
        {
            "category":"Banks & Credit Unions",
            "subcategory":"Investment Brokerage",
            "type":"Services"
        }
    ],
    "sg:phone":"+64 6-759 1118",
    "sg:province":"Taranaki",
    "sg:tags":[
        "educational",
        "education",
        "training"
    ],
    "wof:name":"Literacy/ESOL",
    "wof:placetype":"venue"
},
  "geometry": {"coordinates":[-76.771889,35.848404],"type":"Point"}
}