{
  "type": "Feature",
  "properties": {
    "addr:full":"203 g Maxwell Rd Redwoodtown  Blenheim Marlborough",
    "addr:housenumber":"203",
    "addr:street":"G Maxwell Rd",
    "iso:country":"NZ",
    "sg:address":"203 g Maxwell Rd Redwoodtown ",
    "sg:city":"Blenheim",
    "sg:classifiers":[
        {
            "category":"Building & Trades",
            "subcategory":"Cleaning & Sanitation",
            "type":"Services"
        }
    ],
    "sg:phone":"+64 3-578 2368",
    "sg:province":"Marlborough",
    "sg:tags":[
        "equipment",
        "industrial",
        "maintenance"
    ],
    "wof:name":"Diamantel Cleaning Supplies",
    "wof:placetype":"venue"
},
  "geometry": {"coordinates":[173.943039,-41.531902],"type":"Point"}
}