{
  "type": "Feature",
  "properties": {
    "iso:country":"NZ",
    "sg:address":"64 White St ",
    "sg:city":"Rotorua",
    "sg:classifiers":[
        {
            "category":"Retail",
            "subcategory":"Auto Repair",
            "type":"Services"
        }
    ],
    "sg:phone":"+64 7-350 1088",
    "sg:province":"Bay of Plenty",
    "sg:tags":[
        "mobile",
        "automotive",
        "servicing",
        "mechanic"
    ],
    "wof:name":"Engine Care Systems BOP",
    "wof:placetype":"venue"
},
  "geometry": {"coordinates":[176.261765,-38.151417],"type":"Point"}
}