{
  "type": "Feature",
  "properties": {
    "addr:full":"105 White Pine Bush Rd  Whakatane Bay of Plenty",
    "addr:housenumber":"105",
    "addr:street":"White Pine Bush Rd",
    "iso:country":"NZ",
    "sg:address":"105 White Pine Bush Rd ",
    "sg:city":"Whakatane",
    "sg:orig_category":"Home And Garden: Gardening: Services: Landscaping",
    "sg:phone":"+64 252790549",
    "sg:province":"Bay of Plenty",
    "wof:name":"Outdoor Living Services",
    "wof:placetype":"venue"
},
  "geometry": {"coordinates":[176.98419200000001,-37.965305],"type":"Point"}
}