{
  "type": "Feature",
  "properties": {
    "iso:country":"NZ",
    "sg:address":"Kaiti Beach Rd ",
    "sg:city":"Gisborne",
    "sg:classifiers":[
        {
            "category":"Shopping",
            "subcategory":"Discount & Variety Stores",
            "type":"Retail Goods"
        }
    ],
    "sg:phone":"+64 6-867 5457",
    "sg:province":"Gisborne",
    "sg:tags":[
        "storage",
        "cool"
    ],
    "wof:name":"Harbour Cool Ltd",
    "wof:placetype":"venue"
},
  "geometry": {"coordinates":[178.035141,-38.672092],"type":"Point"}
}