{
  "type": "Feature",
  "properties": {
    "iso:country":"NZ",
    "sg:address":"14 Porowini Ave ",
    "sg:city":"Whangarei",
    "sg:classifiers":[
        {
            "category":"Home & Garden",
            "subcategory":"Building Materials",
            "type":"Retail Goods"
        }
    ],
    "sg:phone":"+64 9-438 4023",
    "sg:province":"Northland",
    "sg:tags":[
        "design",
        "fitting",
        "fittings",
        "kitchen"
    ],
    "wof:name":"Richards G C Ltd",
    "wof:placetype":"venue"
},
  "geometry": {"coordinates":[174.31762699999999,-35.730385],"type":"Point"}
}