{
  "type": "Feature",
  "properties": {
    "iso:country":"NZ",
    "sg:address":"1 C Beatrice Tinsley Cre Albany ",
    "sg:city":"Auckland",
    "sg:classifiers":[
        {
            "category":"Banks & Credit Unions",
            "subcategory":"Financial Services",
            "type":"Services"
        }
    ],
    "sg:phone":"+64 9-415 8340",
    "sg:province":"Auckland",
    "sg:tags":[
        "services",
        "die",
        "industrial",
        "maker",
        "sinker"
    ],
    "wof:name":"Fine Formes Limited",
    "wof:placetype":"venue"
},
  "geometry": {"coordinates":[174.704483,-36.752453],"type":"Point"}
}