{
  "type": "Feature",
  "properties": {
    "iso:country":"NZ",
    "sg:address":"Smith Road R D 2 ",
    "sg:city":"Waiuku",
    "sg:orig_category":"Home And Garden: Accessories: Kitchenware",
    "sg:phone":"+64 21 812 966",
    "sg:province":"West Coast",
    "wof:name":"Svord Knives",
    "wof:placetype":"venue"
},
  "geometry": {"coordinates":[174.73268100000001,-37.248444],"type":"Point"}
}