{
  "type": "Feature",
  "properties": {
    "addr:full":"1043 Papamoa Beach Rd  Tauranga Bay of Plenty",
    "addr:housenumber":"1043",
    "addr:street":"Papamoa Beach Rd",
    "iso:country":"NZ",
    "sg:address":"1043 Papamoa Beach Rd ",
    "sg:city":"Tauranga",
    "sg:classifiers":[
        {
            "category":"Personal",
            "subcategory":"Beauty Salon",
            "type":"Services"
        }
    ],
    "sg:phone":"+64 7-542 2762",
    "sg:province":"Bay of Plenty",
    "sg:tags":[
        "therapy",
        "health"
    ],
    "wof:name":"Janesce Skin Care Products",
    "wof:placetype":"venue"
},
  "geometry": {"coordinates":[176.32994099999999,-37.712883],"type":"Point"}
}