{
  "type": "Feature",
  "properties": {
    "iso:country":"NZ",
    "sg:address":"459 Sloane St Te ",
    "sg:city":"Awamutu",
    "sg:orig_category":"Farming: Machinery: Milking Machinery",
    "sg:phone":"+64 7-870 4011",
    "sg:province":"Waikato",
    "wof:name":"Pratt Milking Machines",
    "wof:placetype":"venue"
},
  "geometry": {"coordinates":[175.32489000000001,-38.014511],"type":"Point"}
}