{
  "type": "Feature",
  "properties": {
    "addr:full":"Devonport, North Shore  Auckland Auckland",
    "iso:country":"NZ",
    "sg:address":"Devonport, North Shore ",
    "sg:city":"Auckland",
    "sg:classifiers":[
        {
            "category":"Home & Garden",
            "subcategory":"Furniture",
            "type":"Retail Goods"
        }
    ],
    "sg:phone":"+64 9-445 9845",
    "sg:province":"Auckland",
    "sg:tags":[
        "furniture/furnishings",
        "repair",
        "finishing"
    ],
    "wof:name":"Cane Furniture Specialists",
    "wof:placetype":"venue"
},
  "geometry": {"coordinates":[174.79956100000001,-36.824421],"type":"Point"}
}