{
  "type": "Feature",
  "properties": {
    "addr:full":"113 Carbine Rd Mt Wellington  Auckland Auckland",
    "addr:housenumber":"113",
    "addr:street":"Carbine Rd",
    "iso:country":"NZ",
    "sg:address":"113 Carbine Rd Mt Wellington ",
    "sg:city":"Auckland",
    "sg:classifiers":[
        {
            "category":"Ice Cream",
            "type":"Food & Drink"
        }
    ],
    "sg:phone":"+64 9-573 7200",
    "sg:province":"Auckland",
    "sg:tags":[
        "-"
    ],
    "wof:name":"Tip Top Ice Cream Company Limited",
    "wof:placetype":"venue"
},
  "geometry": {"coordinates":[174.850189,-36.921909],"type":"Point"}
}