{
  "type": "Feature",
  "properties": {
    "iso:country":"NZ",
    "sg:address":"301 Blenheim Rd Sockburn ",
    "sg:city":"Christchurch",
    "sg:orig_category":"Automotive: Accessories: Car Security Systems",
    "sg:phone":"+64 80022725276",
    "sg:province":"Canterbury",
    "wof:name":"Autoguard NZ Ltd",
    "wof:placetype":"venue"
},
  "geometry": {"coordinates":[172.576385,-43.539108],"type":"Point"}
}