{
  "type": "Feature",
  "properties": {
    "addr:full":"39 Devonport Rd  Tauranga Auckland",
    "addr:housenumber":"39",
    "addr:street":"Devonport Rd",
    "iso:country":"NZ",
    "sg:address":"39 Devonport Rd ",
    "sg:city":"Tauranga",
    "sg:orig_category":"Shopping: Retail Stores: Cds, Cassettes And Records",
    "sg:phone":"+64 7-571 0466",
    "sg:province":"Auckland",
    "wof:name":"Tracs Records",
    "wof:placetype":"venue"
},
  "geometry": {"coordinates":[176.16944899999999,-37.68528],"type":"Point"}
}