{
  "type": "Feature",
  "properties": {
    "iso:country":"NZ",
    "sg:address":"232 Whitford Park Rd R D 1 Manurewa ",
    "sg:city":"Auckland",
    "sg:orig_category":"Farming: Horticulture: Horticulturists",
    "sg:phone":"+64 9-530 8846",
    "sg:province":"Auckland",
    "wof:name":"Whitford Nursery",
    "wof:placetype":"venue"
},
  "geometry": {"coordinates":[174.770416,-36.884109],"type":"Point"}
}