{
  "type": "Feature",
  "properties": {
    "iso:country":"NZ",
    "sg:address":"cnr Trafalgar & Halifax Sts ",
    "sg:city":"Nelson",
    "sg:classifiers":[
        {
            "category":"Organizations",
            "subcategory":"Labor Organization",
            "type":"Services"
        }
    ],
    "sg:phone":"+64 3-548 2304",
    "sg:province":"Nelson",
    "sg:tags":[
        "travel",
        "tourism"
    ],
    "sg:website":"http://www.nelsonnz.com",
    "wof:name":"Nelson Visitor Information Centre",
    "wof:placetype":"venue"
},
  "geometry": {"coordinates":[-121.765488,39.553471],"type":"Point"}
}