{
  "type": "Feature",
  "properties": {
    "addr:full":"153 Stafford St  Timaru Canterbury",
    "addr:housenumber":"153",
    "addr:street":"Stafford St",
    "iso:country":"NZ",
    "sg:address":"153 Stafford St ",
    "sg:city":"Timaru",
    "sg:classifiers":[
        {
            "category":"Banks & Credit Unions",
            "subcategory":"Financial Services",
            "type":"Services"
        }
    ],
    "sg:phone":"+64 3-688 9018",
    "sg:province":"Canterbury",
    "sg:tags":[
        "personal",
        "loan",
        "-",
        "finance",
        "mortgage"
    ],
    "wof:name":"Petrie Mayman Clark",
    "wof:placetype":"venue"
},
  "geometry": {"coordinates":[171.25488300000001,-44.39674],"type":"Point"}
}