{
  "type": "Feature",
  "properties": {
    "addr:full":"Level 2, 60 Grafton Rd PO Box 37-757 Parnell  Auckland Auckland",
    "addr:housenumber":"level;60;box 37-757",
    "addr:street":"2;Grafton Rd",
    "iso:country":"NZ",
    "sg:address":"Level 2, 60 Grafton Rd PO Box 37-757 Parnell ",
    "sg:city":"Auckland",
    "sg:classifiers":[
        {
            "category":"Banks & Credit Unions",
            "subcategory":"Financial Services",
            "type":"Services"
        }
    ],
    "sg:phone":"+64 9-303 4190",
    "sg:province":"Auckland",
    "sg:tags":[
        "personal",
        "superannuation",
        "-",
        "finance"
    ],
    "wof:name":"Tower Financial Advisory Services",
    "wof:placetype":"venue"
},
  "geometry": {"coordinates":[174.77041600000001,-36.884109],"type":"Point"}
}