{
  "type": "Feature",
  "properties": {
    "addr:full":"15 Matanaka Dve  Waikouaiti",
    "addr:housenumber":"15",
    "addr:street":"Matanaka Dve Waikouaiti",
    "iso:country":"NZ",
    "sg:address":"15 Matanaka Dve ",
    "sg:city":"Waikouaiti",
    "sg:orig_category":"Farming: Farms - General: Poultry",
    "sg:phone":"+64 3-465 7670",
    "wof:name":"Mainland Poultry Limited",
    "wof:placetype":"venue"
},
  "geometry": {"coordinates":[170.680161,-45.599018],"type":"Point"}
}