{
  "type": "Feature",
  "properties": {
    "addr:full":"286 b Woodland Rd  Katikati",
    "addr:housenumber":"286 b",
    "addr:street":"Woodland Rd",
    "iso:country":"NZ",
    "sg:address":"286 b Woodland Rd ",
    "sg:city":"Katikati",
    "sg:classifiers":[
        {
            "category":"Manufacturing",
            "subcategory":"Motor Vehicles & Parts",
            "type":"Manufacturing & Wholesale Goods"
        }
    ],
    "sg:phone":"+64 7-549 2827",
    "sg:tags":[
        "air conditioning",
        "automotive",
        "supplies"
    ],
    "wof:name":"Katikati Auto Air",
    "wof:placetype":"venue"
},
  "geometry": {"coordinates":[175.92105100000001,-37.555534],"type":"Point"}
}