{
  "type": "Feature",
  "properties": {
    "addr:full":"87 Stanmore Rd Linwood  Christchurch Canterbury",
    "addr:housenumber":"87",
    "addr:street":"Stanmore Rd",
    "iso:country":"NZ",
    "sg:address":"87 Stanmore Rd Linwood ",
    "sg:city":"Christchurch",
    "sg:classifiers":[
        {
            "category":"Shopping",
            "subcategory":"Thrift Store",
            "type":"Retail Goods"
        }
    ],
    "sg:phone":"+64 3-381 6161",
    "sg:province":"Canterbury",
    "sg:tags":[
        "-",
        "clothing",
        "secondhand",
        "fabric"
    ],
    "wof:name":"Monique's Preloved Clothing",
    "wof:placetype":"venue"
},
  "geometry": {"coordinates":[172.65692100000001,-43.53104],"type":"Point"}
}