{
  "type": "Feature",
  "properties": {
    "addr:full":"11 Clemow Dve Mt Wellington  Auckland Auckland",
    "addr:housenumber":"11",
    "addr:street":"Clemow Dve",
    "iso:country":"NZ",
    "sg:address":"11 Clemow Dve Mt Wellington ",
    "sg:city":"Auckland",
    "sg:classifiers":[
        {
            "category":"Coffee & Tea",
            "type":"Food & Drink"
        }
    ],
    "sg:phone":"+64 9-573 5251",
    "sg:province":"Auckland",
    "sg:tags":[
        "vegetable",
        "fruit",
        "veges"
    ],
    "wof:name":"Fresh NZ 2000 Ltd",
    "wof:placetype":"venue"
},
  "geometry": {"coordinates":[174.83029199999999,-36.909569],"type":"Point"}
}