{
  "type": "Feature",
  "properties": {
    "addr:full":"R D 4  Dargaville Northland",
    "addr:housenumber":"4",
    "addr:street":"R D;Northland",
    "iso:country":"NZ",
    "sg:address":"R D 4 ",
    "sg:city":"Dargaville",
    "sg:classifiers":[
        {
            "category":"Organizations",
            "subcategory":"Labor Organization",
            "type":"Services"
        }
    ],
    "sg:phone":"+64 9-439 4535",
    "sg:province":"Northland",
    "sg:tags":[
        "services",
        "helicopter",
        "travel",
        "tourism"
    ],
    "wof:name":"Finlayson Helicopters",
    "wof:placetype":"venue"
},
  "geometry": {"coordinates":[173.86938499999999,-35.935867],"type":"Point"}
}