{
  "type": "Feature",
  "properties": {
    "addr:full":"4-10 Parliament St Lower  Hutt Wellington",
    "addr:housenumber":"4-10",
    "addr:street":"Parliament St",
    "iso:country":"NZ",
    "sg:address":"4-10 Parliament St Lower ",
    "sg:city":"Hutt",
    "sg:orig_category":"Farming: Services: Irrigation",
    "sg:phone":"+64 4-560 4710",
    "sg:province":"Wellington",
    "wof:name":"Mico Pipelines",
    "wof:placetype":"venue"
},
  "geometry": {"coordinates":[174.904526,-41.208431],"type":"Point"}
}