{
  "type": "Feature",
  "properties": {
    "addr:full":"35 A Holmes Rd Manurewa  Auckland Auckland",
    "addr:housenumber":"35 a",
    "addr:street":"Holmes Rd",
    "iso:country":"NZ",
    "sg:address":"35 A Holmes Rd Manurewa ",
    "sg:city":"Auckland",
    "sg:orig_category":"Home And Garden: Furniture/Furnishings: Cabinetmakers",
    "sg:phone":"+64 9-267 0078",
    "sg:province":"Auckland",
    "wof:name":"Cabinet World",
    "wof:placetype":"venue"
},
  "geometry": {"coordinates":[174.90344200000001,-37.036358],"type":"Point"}
}