{
  "type": "Feature",
  "properties": {
    "iso:country":"NZ",
    "sg:address":"22 Korau Rd Greenlane ",
    "sg:city":"Auckland",
    "sg:classifiers":[
        {
            "category":"Shopping",
            "subcategory":"Gifts & Souvenirs",
            "type":"Retail Goods"
        }
    ],
    "sg:phone":"+64 9-529 0099",
    "sg:province":"Auckland",
    "sg:tags":[
        "travel",
        "tourism"
    ],
    "wof:name":"Clarke Maurice Ltd",
    "wof:placetype":"venue"
},
  "geometry": {"coordinates":[174.784317,-36.887833],"type":"Point"}
}