{
  "type": "Feature",
  "properties": {
    "iso:country":"NZ",
    "sg:address":"63 Tay St ",
    "sg:city":"Invercargill",
    "sg:classifiers":[
        {
            "category":"Shopping",
            "subcategory":"Gifts & Souvenirs",
            "type":"Retail Goods"
        }
    ],
    "sg:phone":"+64 3-218 4850",
    "sg:province":"Southland",
    "sg:tags":[
        "shop",
        "gifts",
        "supplier"
    ],
    "wof:name":"The Little Gallery",
    "wof:placetype":"venue"
},
  "geometry": {"coordinates":[168.380325,-46.40926],"type":"Point"}
}