{
  "type": "Feature",
  "properties": {
    "iso:country":"NZ",
    "sg:address":"161 Kahutia St ",
    "sg:city":"Gisborne",
    "sg:classifiers":[
        {
            "category":"Autos & Motor Vehicles",
            "subcategory":"Automobile Sales",
            "type":"Retail Goods"
        }
    ],
    "sg:phone":"+64 6-868 9004",
    "sg:province":"Gisborne",
    "sg:tags":[
        "car",
        "-used",
        "leasing",
        "truck",
        "automotive"
    ],
    "wof:name":"The Royale Car Company",
    "wof:placetype":"venue"
},
  "geometry": {"coordinates":[178.021759,-38.667469],"type":"Point"}
}