{
  "type": "Feature",
  "properties": {
    "iso:country":"NZ",
    "sg:address":"38 Tawa Dve Albany ",
    "sg:city":"Auckland",
    "sg:orig_category":"Transport: Boats And Marine: Products: Marine Electronics",
    "sg:phone":"+64 9-415 8303",
    "sg:province":"Wellington",
    "wof:name":"Raymarine Electronics",
    "wof:placetype":"venue"
},
  "geometry": {"coordinates":[174.709686,-36.720142],"type":"Point"}
}