{
  "type": "Feature",
  "properties": {
    "iso:country":"NZ",
    "sg:address":"81 Kingsley St Sydenham ",
    "sg:city":"Christchurch",
    "sg:classifiers":[
        {
            "category":"Banks & Credit Unions",
            "subcategory":"Investment Brokerage",
            "type":"Services"
        }
    ],
    "sg:phone":"+64 3-365 2723",
    "sg:province":"Canterbury",
    "sg:tags":[
        "chemical",
        "industrial",
        "-",
        "compounds"
    ],
    "wof:name":"COGNIS NZ",
    "wof:placetype":"venue"
},
  "geometry": {"coordinates":[172.64425700000001,-43.543499],"type":"Point"}
}