{
  "type": "Feature",
  "properties": {
    "iso:country":"NZ",
    "sg:address":"1/126 Carruth Rd Papatoetoe ",
    "sg:city":"Auckland",
    "sg:classifiers":[
        {
            "category":"Professional",
            "type":"Services"
        }
    ],
    "sg:phone":"+64 9-278 5141",
    "sg:province":"Auckland",
    "sg:tags":[
        "services",
        "car",
        "valet",
        "automotive"
    ],
    "wof:name":"Precious Metal Car Valet",
    "wof:placetype":"venue"
},
  "geometry": {"coordinates":[174.867859,-36.982769],"type":"Point"}
}