{
  "type": "Feature",
  "properties": {
    "addr:full":"350 George St  Dunedin Otago",
    "addr:housenumber":"350",
    "addr:street":"George St",
    "iso:country":"NZ",
    "sg:address":"350 George St ",
    "sg:city":"Dunedin",
    "sg:orig_category":"Sports And Leisure: Sports: Skiing",
    "sg:phone":"+64 3-477 0567",
    "sg:province":"Otago",
    "wof:name":"Cheapskates",
    "wof:placetype":"venue"
},
  "geometry": {"coordinates":[-82.784721,28.013355],"type":"Point"}
}