{
  "type": "Feature",
  "properties": {
    "iso:country":"NZ",
    "sg:address":"Wai-iti R D 1 ",
    "sg:city":"Wakefield",
    "sg:classifiers":[
        {
            "category":"Utilities",
            "type":"Services"
        }
    ],
    "sg:phone":"+64 3-541 8579",
    "sg:tags":[
        "industrial",
        "energy",
        "utilities",
        "coal",
        "wood",
        "coke"
    ],
    "wof:name":"Wai-iti Wood Supply",
    "wof:placetype":"venue"
},
  "geometry": {"coordinates":[173.00296,-41.370647],"type":"Point"}
}