{
  "type": "Feature",
  "properties": {
    "addr:full":"1 Bremner Ave Mt Roskill  Auckland Auckland",
    "addr:housenumber":"1",
    "addr:street":"Bremner Ave",
    "iso:country":"NZ",
    "sg:address":"1 Bremner Ave Mt Roskill ",
    "sg:city":"Auckland",
    "sg:classifiers":[
        {
            "category":"Banks & Credit Unions",
            "subcategory":"Financial Services",
            "type":"Services"
        }
    ],
    "sg:phone":"+64 9-620 7491",
    "sg:province":"Auckland",
    "sg:tags":[
        "lender",
        "money",
        "-",
        "finance",
        "personal"
    ],
    "wof:name":"Freddies Finance",
    "wof:placetype":"venue"
},
  "geometry": {"coordinates":[174.74835200000001,-36.906998],"type":"Point"}
}