{
  "type": "Feature",
  "properties": {
    "iso:country":"NZ",
    "sg:address":"49 Fitzherbert St Petone ",
    "sg:city":"Wellington",
    "sg:orig_category":"Health And Beauty: Specialists: Podiatrists",
    "sg:phone":"+64 4-939 0272",
    "sg:province":"Wellington",
    "wof:name":"Eastbourne - Valley Podiatry",
    "wof:placetype":"venue"
},
  "geometry": {"coordinates":[174.874908,-41.223991],"type":"Point"}
}