{
  "type": "Feature",
  "properties": {
    "iso:country":"NZ",
    "sg:address":"578 Te Atatu Rd Te Atatu ",
    "sg:city":"Auckland",
    "sg:orig_category":"Shopping: Retail Stores: Secondhand Dealers",
    "sg:phone":"+64 9-834 4633",
    "sg:province":"Auckland",
    "wof:name":"Te Atatu Traders",
    "wof:placetype":"venue"
},
  "geometry": {"coordinates":[174.651337,-36.840034],"type":"Point"}
}