{
  "type": "Feature",
  "properties": {
    "addr:full":"cnr Guyton & Hatrick Sts  Wanganui Manawatu-Wanganui",
    "addr:street":"Cnr Guyton & Hatrick Sts",
    "iso:country":"NZ",
    "sg:address":"cnr Guyton & Hatrick Sts ",
    "sg:city":"Wanganui",
    "sg:orig_category":"Farming: Machinery: Tractors",
    "sg:phone":"+64 6-345 8855",
    "sg:province":"Manawatu-Wanganui",
    "wof:name":"Tracmac",
    "wof:placetype":"venue"
},
  "geometry": {"coordinates":[175.052841,-39.933369],"type":"Point"}
}