{
  "type": "Feature",
  "properties": {
    "addr:full":"85 Birchs Rd  Prebbleton",
    "addr:housenumber":"85",
    "addr:street":"Birchs Rd",
    "iso:country":"NZ",
    "sg:address":"85 Birchs Rd ",
    "sg:city":"Prebbleton",
    "sg:classifiers":[
        {
            "category":"Sports & Exercise",
            "subcategory":"Playing Field",
            "type":"Entertainment"
        }
    ],
    "sg:phone":"+64 25345083",
    "sg:tags":[
        "hobby",
        "hobbies",
        "leisure",
        "supply"
    ],
    "wof:name":"Obsolete Toys NZ",
    "wof:placetype":"venue"
},
  "geometry": {"coordinates":[172.51045199999999,-43.590508],"type":"Point"}
}