{
  "type": "Feature",
  "properties": {
    "addr:full":"157 Hilton Hwy  Timaru Canterbury",
    "addr:housenumber":"157",
    "addr:street":"Hilton Hwy",
    "iso:country":"NZ",
    "sg:address":"157 Hilton Hwy ",
    "sg:city":"Timaru",
    "sg:classifiers":[
        {
            "category":"Manufacturing",
            "subcategory":"Furniture",
            "type":"Manufacturing & Wholesale Goods"
        }
    ],
    "sg:phone":"+64 3-688 2164",
    "sg:province":"Canterbury",
    "sg:tags":[
        "furniture/furnishings",
        "home",
        "garden",
        "manufacturer"
    ],
    "wof:name":"South Pacific Laminates Ltd",
    "wof:placetype":"venue"
},
  "geometry": {"coordinates":[171.23893699999999,-44.357769],"type":"Point"}
}