{
  "type": "Feature",
  "properties": {
    "iso:country":"NZ",
    "sg:address":"cnr Castle & Frederick Sts ",
    "sg:city":"Dunedin",
    "sg:classifiers":[
        {
            "category":"Shopping",
            "subcategory":"Photographic Equipment",
            "type":"Retail Goods"
        }
    ],
    "sg:phone":"+64 3-477 4345",
    "sg:province":"Otago",
    "sg:tags":[
        "sport",
        "leisure",
        "hobbies"
    ],
    "wof:name":"Spectrum Photos Ltd",
    "wof:placetype":"venue"
},
  "geometry": {"coordinates":[-82.784729,28.013371],"type":"Point"}
}