{
  "type": "Feature",
  "properties": {
    "iso:country":"NZ",
    "sg:address":"118 Bamford St Hillsborough ",
    "sg:city":"Christchurch",
    "sg:orig_category":"Industrial: Services: Drum Reconditioners",
    "sg:phone":"+64 274 393 134",
    "sg:province":"Canterbury",
    "wof:name":"Mainland Drums Ltd",
    "wof:placetype":"venue"
},
  "geometry": {"coordinates":[172.68277,-43.559067],"type":"Point"}
}