{
  "type": "Feature",
  "properties": {
    "iso:country":"NZ",
    "sg:address":"191 Thames St ",
    "sg:city":"Oamaru",
    "sg:classifiers":[
        {
            "category":"Bars & Pubs",
            "subcategory":"Wine Bar",
            "type":"Food & Drink"
        }
    ],
    "sg:phone":"+64 3-434 8716",
    "sg:province":"Otago",
    "sg:tags":[
        "wining",
        "dining",
        "cafe"
    ],
    "wof:name":"Lagonda Milk Bar Ltd",
    "wof:placetype":"venue"
},
  "geometry": {"coordinates":[170.97160299999999,-45.096828],"type":"Point"}
}