{
  "type": "Feature",
  "properties": {
    "iso:country":"NZ",
    "sg:address":"65 Stafford St ",
    "sg:city":"Feilding",
    "sg:orig_category":"Health And Beauty: Dental: Dentists",
    "sg:phone":"+64 6-323 6285",
    "sg:province":"Manawatu-Wanganui",
    "wof:name":"Tansley J B BDS",
    "wof:placetype":"venue"
},
  "geometry": {"coordinates":[175.565475,-40.223942],"type":"Point"}
}