{
  "type": "Feature",
  "properties": {
    "iso:country":"NZ",
    "sg:address":"4 Waipuna Rd Mt Wellington ",
    "sg:city":"Auckland",
    "sg:orig_category":"Farming: Horticulture",
    "sg:phone":"+64 9-570 1793",
    "sg:province":"Auckland",
    "wof:name":"Industrial Processors Ltd",
    "wof:placetype":"venue"
},
  "geometry": {"coordinates":[174.8396,-36.908661],"type":"Point"}
}