{
  "type": "Feature",
  "properties": {
    "addr:full":"4 Waipuna Rd Mt Wellington  Auckland Auckland",
    "addr:housenumber":"4",
    "addr:street":"Waipuna Rd",
    "iso:country":"NZ",
    "sg:address":"4 Waipuna Rd Mt Wellington ",
    "sg:city":"Auckland",
    "sg:orig_category":"Farming: Horticulture",
    "sg:phone":"+64 9-570 1793",
    "sg:province":"Auckland",
    "wof:name":"Industrial Processors Ltd",
    "wof:placetype":"venue"
},
  "geometry": {"coordinates":[174.83959999999999,-36.908661],"type":"Point"}
}