{
  "type": "Feature",
  "properties": {
    "addr:full":"70 Centennial Ave  Alexandra Otago",
    "addr:housenumber":"70",
    "addr:street":"Centennial Ave",
    "iso:country":"NZ",
    "sg:address":"70 Centennial Ave ",
    "sg:city":"Alexandra",
    "sg:classifiers":[
        {
            "category":"Restaurant",
            "type":"Food & Drink"
        }
    ],
    "sg:phone":"+64 3-448 9422",
    "sg:province":"Otago",
    "sg:tags":[
        "wining",
        "dining",
        "pizza"
    ],
    "wof:name":"Pisa Pizza Alexandra",
    "wof:placetype":"venue"
},
  "geometry": {"coordinates":[169.382721,-45.246353],"type":"Point"}
}