{
  "type": "Feature",
  "properties": {
    "iso:country":"NZ",
    "sg:address":"Jellicoe St Te ",
    "sg:city":"Puke",
    "sg:classifiers":[
        {
            "category":"Travel",
            "subcategory":"Travel Agent",
            "type":"Entertainment"
        }
    ],
    "sg:phone":"+64 7-574 5774",
    "sg:province":"Bay of Plenty",
    "sg:tags":[
        "tourism",
        "broker"
    ],
    "wof:name":"Harvey World Travel",
    "wof:placetype":"venue"
},
  "geometry": {"coordinates":[176.33049,-37.785503],"type":"Point"}
}