{
  "type": "Feature",
  "properties": {
    "iso:country":"NZ",
    "sg:address":"Gorge Rd ",
    "sg:city":"Queenstown",
    "sg:classifiers":[
        {
            "category":"Retail",
            "subcategory":"Laundry & Dry Cleaning",
            "type":"Services"
        }
    ],
    "sg:phone":"+64 3-442 8621",
    "sg:province":"Otago",
    "sg:tags":[
        "repair",
        "clothing",
        "fabric",
        "cleaner"
    ],
    "wof:name":"Butlers Queenstown Ltd",
    "wof:placetype":"venue"
},
  "geometry": {"coordinates":[-76.157791,38.990379],"type":"Point"}
}