{
  "type": "Feature",
  "properties": {
    "addr:full":"59 Ribbonwood Rd  Geraldine",
    "addr:housenumber":"59",
    "addr:street":"Ribbonwood Rd",
    "iso:country":"NZ",
    "sg:address":"59 Ribbonwood Rd ",
    "sg:city":"Geraldine",
    "sg:orig_category":"Farming: Agriculture",
    "sg:phone":"+64 3-693 7438",
    "wof:name":"Dairy Farm Management Services",
    "wof:placetype":"venue"
},
  "geometry": {"coordinates":[-86.008263,34.360641],"type":"Point"}
}