{
  "type": "Feature",
  "properties": {
    "addr:full":"Cnr Victoria & High St Auckland Central  Auckland Auckland",
    "addr:street":"Cnr Victoria & High St",
    "iso:country":"NZ",
    "sg:address":"Cnr Victoria & High St Auckland Central ",
    "sg:city":"Auckland",
    "sg:orig_category":"Health And Beauty: Specialists: Chiropractors",
    "sg:phone":"+64 9-358 5226",
    "sg:province":"Auckland",
    "wof:name":"Advanced Spine And Joint Clinic",
    "wof:placetype":"venue"
},
  "geometry": {"coordinates":[174.76454200000001,-36.848358],"type":"Point"}
}