{
  "type": "Feature",
  "properties": {
    "addr:full":"71 Jackson St Petone Lower  Hutt Wellington",
    "addr:housenumber":"71",
    "addr:street":"Jackson St",
    "iso:country":"NZ",
    "sg:address":"71 Jackson St Petone Lower ",
    "sg:city":"Hutt",
    "sg:orig_category":"Home And Garden: Gardening: Products: Lawnmowers",
    "sg:phone":"+64 4-568 9111",
    "sg:province":"Wellington",
    "wof:name":"Lawnmower & Machinery",
    "wof:placetype":"venue"
},
  "geometry": {"coordinates":[174.87364199999999,-41.223717],"type":"Point"}
}