{
  "type": "Feature",
  "properties": {
    "iso:country":"NZ",
    "sg:address":"34 Birch St Lower ",
    "sg:city":"Hutt",
    "sg:classifiers":[
        {
            "category":"Home & Garden",
            "subcategory":"Building Materials",
            "type":"Retail Goods"
        }
    ],
    "sg:phone":"+64 4-569 6125",
    "sg:province":"Wellington",
    "sg:tags":[
        "builder",
        "related"
    ],
    "wof:name":"Van Baarle Construction",
    "wof:placetype":"venue"
},
  "geometry": {"coordinates":[174.904526,-41.208431],"type":"Point"}
}