{
  "type": "Feature",
  "properties": {
    "iso:country":"NZ",
    "sg:address":"107 Mana Esplanade Paremata ",
    "sg:city":"Wellington",
    "sg:classifiers":[
        {
            "category":"Health Services",
            "subcategory":"Health Practitioner",
            "type":"Services"
        }
    ],
    "sg:phone":"+64 4-233 0805",
    "sg:province":"Wellington",
    "sg:tags":[
        "specialist",
        "medical",
        "beauty",
        "specialists"
    ],
    "wof:name":"Mana Specialists Centre",
    "wof:placetype":"venue"
},
  "geometry": {"coordinates":[174.869095,-41.106552],"type":"Point"}
}