{
  "type": "Feature",
  "properties": {
    "addr:full":"Matangi Rd Matangi  Hamilton Waikato",
    "addr:street":"Matangi Rd",
    "iso:country":"NZ",
    "sg:address":"Matangi Rd Matangi ",
    "sg:city":"Hamilton",
    "sg:orig_category":"Sports And Leisure: Sports: Equestrian: Saddlers",
    "sg:phone":"+64 7-829 5754",
    "sg:province":"Waikato",
    "wof:name":"Kiwipolo.co.nz",
    "wof:placetype":"venue"
},
  "geometry": {"coordinates":[175.33332799999999,-37.797184],"type":"Point"}
}