{
  "type": "Feature",
  "properties": {
    "addr:full":"35 B The Mall  Queenstown Otago",
    "addr:housenumber":"35 b",
    "addr:street":"The Mall",
    "iso:country":"NZ",
    "sg:address":"35 B The Mall ",
    "sg:city":"Queenstown",
    "sg:orig_category":"Clothing And Fabric: Clothing: Clothing - Specialty",
    "sg:phone":"+64 3-409 0073",
    "sg:province":"Otago",
    "wof:name":"Jay Jays",
    "wof:placetype":"venue"
},
  "geometry": {"coordinates":[168.66325399999999,-45.031445],"type":"Point"}
}