{
  "type": "Feature",
  "properties": {
    "iso:country":"NZ",
    "sg:address":"UNT3/15 Trugood Dve East Tamaki ",
    "sg:city":"Auckland",
    "sg:orig_category":"Shopping: Discount",
    "sg:phone":"+64 9-272 4520",
    "sg:province":"Auckland",
    "wof:name":"Why Knot Ltd",
    "wof:placetype":"venue"
},
  "geometry": {"coordinates":[174.887436,-36.956711],"type":"Point"}
}