{
  "type": "Feature",
  "properties": {
    "addr:full":"B/580 Rosebank Rd Avondale  Auckland Auckland",
    "addr:housenumber":"/ 580",
    "addr:street":"Rosebank Rd",
    "iso:country":"NZ",
    "sg:address":"B/580 Rosebank Rd Avondale ",
    "sg:city":"Auckland",
    "sg:classifiers":[
        {
            "category":"Home & Garden",
            "subcategory":"Household Appliances",
            "type":"Retail Goods"
        }
    ],
    "sg:phone":"+64 9-820 6080",
    "sg:province":"Auckland",
    "sg:tags":[
        "toilet",
        "cleaning",
        "supply"
    ],
    "wof:name":"Unisource Limited",
    "wof:placetype":"venue"
},
  "geometry": {"coordinates":[174.690933,-36.8932],"type":"Point"}
}