{
  "type": "Feature",
  "properties": {
    "addr:full":"PO Box 15866 New Lynn  Auckland Auckland",
    "addr:housenumber":"po box",
    "addr:street":"15866",
    "iso:country":"NZ",
    "sg:address":"PO Box 15866 New Lynn ",
    "sg:city":"Auckland",
    "sg:orig_category":"Home And Garden: Children",
    "sg:phone":"+64 9-489 1024",
    "sg:province":"Auckland",
    "sg:website":"http://www.kiwiaupair.com",
    "wof:name":"Prestige Nannies & Aupairs",
    "wof:placetype":"venue"
},
  "geometry": {"coordinates":[174.68308999999999,-36.920143],"type":"Point"}
}