{
  "type": "Feature",
  "properties": {
    "iso:country":"NZ",
    "sg:address":"40 Rata St ",
    "sg:city":"Inglewood",
    "sg:classifiers":[
        {
            "category":"Wholesale",
            "subcategory":"Meat",
            "type":"Manufacturing & Wholesale Goods"
        }
    ],
    "sg:phone":"+64 6-756 7136",
    "sg:tags":[
        "food",
        "drink",
        "meats",
        "slaughtering"
    ],
    "wof:name":"Moa Butchery",
    "wof:placetype":"venue"
},
  "geometry": {"coordinates":[-118.356224,33.961781],"type":"Point"}
}