{
  "type": "Feature",
  "properties": {
    "iso:country":"NZ",
    "sg:address":"434 The Esplanade Island Bay ",
    "sg:city":"Wellington",
    "sg:classifiers":[
        {
            "category":"Recreation",
            "type":"Entertainment"
        }
    ],
    "sg:phone":"+64 4-971 5070",
    "sg:province":"Auckland",
    "sg:tags":[
        "sport",
        "leisure"
    ],
    "wof:name":"S.M.C. Music",
    "wof:placetype":"venue"
},
  "geometry": {"coordinates":[174.762161,-41.347782],"type":"Point"}
}