{
  "type": "Feature",
  "properties": {
    "iso:country":"NZ",
    "sg:address":"12 Wakefield Ave Sumner ",
    "sg:city":"Christchurch",
    "sg:orig_category":"Food And Drink: Catering: Caterers",
    "sg:phone":"+64 3-326 6501",
    "sg:province":"Canterbury",
    "wof:name":"Forget Me Not Cafe",
    "wof:placetype":"venue"
},
  "geometry": {"coordinates":[172.75889599999999,-43.569042],"type":"Point"}
}