{
  "type": "Feature",
  "properties": {
    "iso:country":"NZ",
    "sg:address":"2 Boundary Rd Mosgiel ",
    "sg:city":"Junction",
    "sg:classifiers":[
        {
            "category":"Home & Garden",
            "subcategory":"Building Materials",
            "type":"Retail Goods"
        }
    ],
    "sg:phone":"+64 252224719",
    "sg:tags":[
        "bricklaying",
        "related"
    ],
    "wof:name":"Riach G W",
    "wof:placetype":"venue"
},
  "geometry": {"coordinates":[170.35755900000001,-45.891991],"type":"Point"}
}