{
  "type": "Feature",
  "properties": {
    "addr:full":"cnr Greenwood & Duke Sts Frankton  Hamilton Waikato",
    "addr:housenumber":"cnr;&;sts",
    "addr:street":"Greenwood",
    "iso:country":"NZ",
    "sg:address":"cnr Greenwood & Duke Sts Frankton ",
    "sg:city":"Hamilton",
    "sg:classifiers":[
        {
            "category":"Manufacturing",
            "subcategory":"Tools & Machinery",
            "type":"Manufacturing & Wholesale Goods"
        }
    ],
    "sg:phone":"+64 7-847 5027",
    "sg:province":"Waikato",
    "sg:tags":[
        "specialist",
        "energy",
        "industrial",
        "solar",
        "equipment"
    ],
    "wof:name":"Environmental Plumbing & Drainage Ltd",
    "wof:placetype":"venue"
},
  "geometry": {"coordinates":[175.264084,-37.79319],"type":"Point"}
}