{
  "type": "Feature",
  "properties": {
    "addr:full":"35 Porowini Ave  Whangarei Northland",
    "addr:housenumber":"35",
    "addr:street":"Porowini Ave",
    "iso:country":"NZ",
    "sg:address":"35 Porowini Ave ",
    "sg:city":"Whangarei",
    "sg:classifiers":[
        {
            "category":"Communications",
            "subcategory":"Radio Station",
            "type":"Services"
        }
    ],
    "sg:phone":"+64 9-438 6115",
    "sg:province":"Northland",
    "sg:tags":[
        "broadcasting"
    ],
    "wof:name":"Radio Ngatihine FM (99.5/96.4)",
    "wof:placetype":"venue"
},
  "geometry": {"coordinates":[174.31970200000001,-35.730972],"type":"Point"}
}