{
  "type": "Feature",
  "properties": {
    "iso:country":"NZ",
    "sg:address":"R D 1 Riverton ",
    "sg:city":"Invercargill",
    "sg:classifiers":[
        {
            "category":"Recreation",
            "type":"Entertainment"
        }
    ],
    "sg:phone":"+64 3-234 8407",
    "sg:province":"Southland",
    "sg:tags":[
        "trek",
        "travel",
        "horse",
        "tour",
        "tourism",
        "sightseeing"
    ],
    "wof:name":"Southern Scenic Horse Treks",
    "wof:placetype":"venue"
},
  "geometry": {"coordinates":[-108.381317,43.02467],"type":"Point"}
}