{
  "type": "Feature",
  "properties": {
    "addr:full":"19 Tuarangi Rd Grey Lynn  Auckland Auckland",
    "addr:housenumber":"19",
    "addr:street":"Tuarangi Rd",
    "iso:country":"NZ",
    "sg:address":"19 Tuarangi Rd Grey Lynn ",
    "sg:city":"Auckland",
    "sg:orig_category":"Industrial: Energy And Utilities: Gas",
    "sg:phone":"+64 9-376 8566",
    "sg:province":"Auckland",
    "wof:name":"Auckland Gasco Ltd",
    "wof:placetype":"venue"
},
  "geometry": {"coordinates":[174.73541299999999,-36.864754],"type":"Point"}
}