{
  "type": "Feature",
  "properties": {
    "addr:full":"12 A Golders St  Taupo Waikato",
    "addr:housenumber":"12",
    "addr:street":"A Golders St",
    "iso:country":"NZ",
    "sg:address":"12 A Golders St ",
    "sg:city":"Taupo",
    "sg:classifiers":[
        {
            "category":"Shopping",
            "subcategory":"Bicycles & Sporting Goods",
            "type":"Retail Goods"
        }
    ],
    "sg:phone":"+64 252729856",
    "sg:province":"Waikato",
    "sg:tags":[
        "sport",
        "fishing",
        "hunting",
        "retailers"
    ],
    "wof:name":"Windsor Charters",
    "wof:placetype":"venue"
},
  "geometry": {"coordinates":[176.09461999999999,-38.715424],"type":"Point"}
}