{
  "type": "Feature",
  "properties": {
    "addr:full":"53 Rata St  Inglewood",
    "addr:housenumber":"53",
    "addr:street":"Rata St",
    "iso:country":"NZ",
    "sg:address":"53 Rata St ",
    "sg:city":"Inglewood",
    "sg:classifiers":[
        {
            "category":"Building & Trades",
            "subcategory":"Plumbing",
            "type":"Services"
        }
    ],
    "sg:phone":"+64 6-756 8290",
    "sg:tags":[
        "home",
        "plumber",
        "garden",
        "related"
    ],
    "wof:name":"A D Charteris & Co",
    "wof:placetype":"venue"
},
  "geometry": {"coordinates":[174.19454999999999,-39.15443],"type":"Point"}
}