{
  "type": "Feature",
  "properties": {
    "iso:country":"NZ",
    "sg:address":"39 B Waterman Pl Woolston ",
    "sg:city":"Christchurch",
    "sg:classifiers":[
        {
            "category":"Manufacturing",
            "subcategory":"Food",
            "type":"Manufacturing & Wholesale Goods"
        }
    ],
    "sg:phone":"+64 3-384 6438",
    "sg:province":"Canterbury",
    "sg:tags":[
        "drink",
        "-",
        "manufacturer"
    ],
    "wof:name":"Sahara Cuisine (NZ) Limited",
    "wof:placetype":"venue"
},
  "geometry": {"coordinates":[172.677719,-43.54937],"type":"Point"}
}