{
  "type": "Feature",
  "properties": {
    "addr:full":"PO Box 33 Matangi  Hamilton Waikato",
    "addr:housenumber":"po box 33",
    "iso:country":"NZ",
    "sg:address":"PO Box 33 Matangi ",
    "sg:city":"Hamilton",
    "sg:orig_category":"Shopping: Gifts: Sheepskins",
    "sg:phone":"+64 7-829 5940",
    "sg:province":"Waikato",
    "wof:name":"Merino Sheepskin Company Ltd",
    "wof:placetype":"venue"
},
  "geometry": {"coordinates":[175.40571600000001,-37.792549],"type":"Point"}
}