{
  "type": "Feature",
  "properties": {
    "iso:country":"NZ",
    "sg:address":"Karapiro RD 4 ",
    "sg:city":"Cambridge",
    "sg:orig_category":"Automotive: Parts And Supplies: Windscreens",
    "sg:phone":"+64 7-827 8403",
    "sg:province":"Waikato",
    "wof:name":"K J's Windscreen Repairs",
    "wof:placetype":"venue"
},
  "geometry": {"coordinates":[175.47131300000001,-37.893063],"type":"Point"}
}