{
  "type": "Feature",
  "properties": {
    "iso:country":"NZ",
    "sg:address":"142 Heretaunga St East ",
    "sg:city":"Hastings",
    "sg:classifiers":[
        {
            "category":"Shopping",
            "subcategory":"Gifts & Souvenirs",
            "type":"Retail Goods"
        }
    ],
    "sg:phone":"+64 6-878 7987",
    "sg:province":"Hawke's Bay",
    "sg:tags":[
        "shop",
        "gifts",
        "supplier"
    ],
    "wof:name":"Iconix",
    "wof:placetype":"venue"
},
  "geometry": {"coordinates":[-81.508163,29.711214],"type":"Point"}
}