{
  "type": "Feature",
  "properties": {
    "addr:full":"4G/22 Te Pai Pl Henderson  Auckland Auckland",
    "addr:housenumber":"4g / 22",
    "addr:street":"Te Pai Pl",
    "iso:country":"NZ",
    "sg:address":"4G/22 Te Pai Pl Henderson ",
    "sg:city":"Auckland",
    "sg:classifiers":[
        {
            "category":"Home & Garden",
            "subcategory":"Furniture",
            "type":"Retail Goods"
        }
    ],
    "sg:phone":"+64 9-835 3511",
    "sg:province":"Auckland",
    "sg:tags":[
        "fitting"
    ],
    "sg:website":"http://www.doors4u.co.nz",
    "wof:name":"Doors 4 U Limited",
    "wof:placetype":"venue"
},
  "geometry": {"coordinates":[174.63294999999999,-36.877289],"type":"Point"}
}