{
  "type": "Feature",
  "properties": {
    "iso:country":"NZ",
    "sg:address":"Esk St ",
    "sg:city":"Invercargill",
    "sg:orig_category":"Home And Garden: Accessories: Hardware",
    "sg:phone":"+64 3-211 0180",
    "sg:province":"Southland",
    "wof:name":"Mitre 10",
    "wof:placetype":"venue"
},
  "geometry": {"coordinates":[168.347488,-46.411854],"type":"Point"}
}