{
  "type": "Feature",
  "properties": {
    "addr:full":"61 Layard St Rosedale  Invercargill Southland",
    "addr:housenumber":"61",
    "addr:street":"Layard St",
    "iso:country":"NZ",
    "sg:address":"61 Layard St Rosedale ",
    "sg:city":"Invercargill",
    "sg:classifiers":[
        {
            "category":"Arts & Performance",
            "subcategory":"Music",
            "type":"Entertainment"
        }
    ],
    "sg:phone":"+64 3-217 8425",
    "sg:province":"Southland",
    "sg:tags":[
        "sport",
        "leisure"
    ],
    "wof:name":"NZ Modern School of Music",
    "wof:placetype":"venue"
},
  "geometry": {"coordinates":[168.365906,-46.391312],"type":"Point"}
}