{
  "type": "Feature",
  "properties": {
    "iso:country":"NZ",
    "sg:address":"26 Tuckers Rd Redwood ",
    "sg:city":"Christchurch",
    "sg:orig_category":"Education And Training: General: Schools",
    "sg:phone":"+64 3-352 9371",
    "sg:province":"Canterbury",
    "wof:name":"Northcote Primary School",
    "wof:placetype":"venue"
},
  "geometry": {"coordinates":[172.625534,-43.467388],"type":"Point"}
}