{
  "type": "Feature",
  "properties": {
    "iso:country":"NZ",
    "sg:address":"2 Vine St ",
    "sg:city":"Whangarei",
    "sg:orig_category":"Shopping: Retail Stores: Antiques",
    "sg:phone":"+64 9-438 6339",
    "sg:province":"Northland",
    "wof:name":"Against The Grain",
    "wof:placetype":"venue"
},
  "geometry": {"coordinates":[174.319412,-35.725925],"type":"Point"}
}