{
  "type": "Feature",
  "properties": {
    "iso:country":"NZ",
    "sg:address":"Manukau City ",
    "sg:city":"Auckland",
    "sg:classifiers":[
        {
            "category":"Communications",
            "subcategory":"Television Station",
            "type":"Services"
        }
    ],
    "sg:phone":"+64 9-263 9885",
    "sg:province":"Auckland",
    "sg:tags":[
        "equipment",
        "broadcasting"
    ],
    "wof:name":"Syntec International Ltd",
    "wof:placetype":"venue"
},
  "geometry": {"coordinates":[174.881439,-36.98967],"type":"Point"}
}