{
  "type": "Feature",
  "properties": {
    "addr:full":"143 a Budge St  Blenheim Marlborough",
    "addr:housenumber":"143",
    "addr:street":"A Budge St",
    "iso:country":"NZ",
    "sg:address":"143 a Budge St ",
    "sg:city":"Blenheim",
    "sg:classifiers":[
        {
            "category":"Professional",
            "subcategory":"Art Services",
            "type":"Services"
        }
    ],
    "sg:phone":"+64 25313245",
    "sg:province":"Marlborough",
    "sg:tags":[
        "personal",
        "photographer",
        "services",
        "garden",
        "home"
    ],
    "wof:name":"Skyworks Photography",
    "wof:placetype":"venue"
},
  "geometry": {"coordinates":[173.973557,-41.504913],"type":"Point"}
}