{
  "type": "Feature",
  "properties": {
    "addr:full":"3 Margaret St Lower  Hutt Wellington",
    "addr:housenumber":"3",
    "addr:street":"Margaret St",
    "iso:country":"NZ",
    "sg:address":"3 Margaret St Lower ",
    "sg:city":"Hutt",
    "sg:orig_category":"Clothing And Fabric: Fabric: Drapers",
    "sg:phone":"+64 4-569 7074",
    "sg:province":"Wellington",
    "wof:name":"Arthur Toye Ltd",
    "wof:placetype":"venue"
},
  "geometry": {"coordinates":[174.903854,-41.20937],"type":"Point"}
}