{
  "type": "Feature",
  "properties": {
    "addr:full":"11 Otupai St  Taupo Waikato",
    "addr:housenumber":"11",
    "addr:street":"Otupai St",
    "iso:country":"NZ",
    "sg:address":"11 Otupai St ",
    "sg:city":"Taupo",
    "sg:classifiers":[
        {
            "category":"Organizations",
            "subcategory":"Labor Organization",
            "type":"Services"
        }
    ],
    "sg:phone":"+64 7-378 8074",
    "sg:province":"Waikato",
    "sg:tags":[
        "services",
        "helicopter",
        "travel",
        "tourism"
    ],
    "wof:name":"Heli Harvest Ltd",
    "wof:placetype":"venue"
},
  "geometry": {"coordinates":[176.08528100000001,-38.714645],"type":"Point"}
}