{
  "type": "Feature",
  "properties": {
    "addr:full":"285 Tinakori Rd Thorndon  Wellington Wellington",
    "addr:housenumber":"285",
    "addr:street":"Tinakori Rd",
    "iso:country":"NZ",
    "sg:address":"285 Tinakori Rd Thorndon ",
    "sg:city":"Wellington",
    "sg:classifiers":[
        {
            "category":"Travel",
            "subcategory":"Hotels & Motels",
            "type":"Entertainment"
        }
    ],
    "sg:phone":"+64 4-472 1320",
    "sg:province":"Wellington",
    "sg:tags":[
        "tourism",
        "accommodation"
    ],
    "sg:website":"http://www.yellowpages.co.nz/for/shepherdsarmshotel/dp30285.html",
    "wof:name":"Shepherds Arms Hotel",
    "wof:placetype":"venue"
},
  "geometry": {"coordinates":[174.77006499999999,-41.278297],"type":"Point"}
}