{
  "type": "Feature",
  "properties": {
    "iso:country":"NZ",
    "sg:address":"PO Box 2199 ",
    "sg:city":"Wellington",
    "sg:classifiers":[
        {
            "category":"Banks & Credit Unions",
            "subcategory":"Investment Brokerage",
            "type":"Services"
        }
    ],
    "sg:phone":"+64 4-801 3185",
    "sg:province":"Wellington",
    "sg:tags":[
        "personal",
        "-",
        "finance"
    ],
    "wof:name":"Invest Wellington Region",
    "wof:placetype":"venue"
},
  "geometry": {"coordinates":[-85.910454,33.827946],"type":"Point"}
}