{
  "type": "Feature",
  "properties": {
    "addr:full":"513 Queen St  Levin Manawatu-Wanganui",
    "addr:housenumber":"513",
    "addr:street":"Queen St",
    "iso:country":"NZ",
    "sg:address":"513 Queen St ",
    "sg:city":"Levin",
    "sg:classifiers":[
        {
            "category":"Shopping",
            "subcategory":"Pharmacy",
            "type":"Retail Goods"
        }
    ],
    "sg:phone":"+64 6-368 4473",
    "sg:province":"Manawatu-Wanganui",
    "sg:tags":[
        "product",
        "health"
    ],
    "wof:name":"Hadlums Health & Nutrition",
    "wof:placetype":"venue"
},
  "geometry": {"coordinates":[175.28717,-40.621952],"type":"Point"}
}