{
  "type": "Feature",
  "properties": {
    "addr:full":"Duncan Rd  Hamilton Waikato",
    "addr:street":"Duncan Rd",
    "iso:country":"NZ",
    "sg:address":"Duncan Rd ",
    "sg:city":"Hamilton",
    "sg:classifiers":[
        {
            "category":"Arena",
            "subcategory":"Sports Club",
            "type":"Entertainment"
        }
    ],
    "sg:phone":"+64 7-849 3490",
    "sg:province":"Waikato",
    "sg:tags":[
        "-",
        "leisure",
        "sports"
    ],
    "wof:name":"Waikato Indoor Bowling Centre Hall",
    "wof:placetype":"venue"
},
  "geometry": {"coordinates":[-74.675301,40.222309],"type":"Point"}
}