{
  "type": "Feature",
  "properties": {
    "iso:country":"NZ",
    "sg:address":"PO Box 65402 Mairangi Bay ",
    "sg:city":"Auckland",
    "sg:classifiers":[
        {
            "category":"Shopping",
            "subcategory":"Gifts & Souvenirs",
            "type":"Retail Goods"
        }
    ],
    "sg:phone":"+64 9-478 3474",
    "sg:province":"Auckland",
    "sg:tags":[
        "postcard",
        "gifts",
        "greeting",
        "card"
    ],
    "wof:name":"Colin J. Kemplen & Assoc. Ltd",
    "wof:placetype":"venue"
},
  "geometry": {"coordinates":[174.748169,-36.738461],"type":"Point"}
}