{
  "type": "Feature",
  "properties": {
    "addr:full":"22 a Ihakara St  Paraparaumu Wellington",
    "addr:housenumber":"22",
    "addr:street":"A Ihakara St",
    "iso:country":"NZ",
    "sg:address":"22 a Ihakara St ",
    "sg:city":"Paraparaumu",
    "sg:classifiers":[
        {
            "category":"Shopping",
            "subcategory":"Crafts & Fabrics",
            "type":"Retail Goods"
        }
    ],
    "sg:phone":"+64 4-298 8059",
    "sg:province":"Wellington",
    "sg:tags":[
        "arts",
        "sport",
        "art",
        "leisure",
        "supply"
    ],
    "wof:name":"School Art Manufacturing",
    "wof:placetype":"venue"
},
  "geometry": {"coordinates":[174.99945099999999,-40.918449],"type":"Point"}
}