{
  "type": "Feature",
  "properties": {
    "iso:country":"NZ",
    "sg:address":"408 Heads Rd ",
    "sg:city":"Wanganui",
    "sg:classifiers":[
        {
            "category":"Building & Trades",
            "subcategory":"Pest Control",
            "type":"Services"
        }
    ],
    "sg:phone":"+64 6-344 5302",
    "sg:province":"Manawatu-Wanganui",
    "sg:tags":[
        "home",
        "garden"
    ],
    "wof:name":"Animal Control Products Ltd",
    "wof:placetype":"venue"
},
  "geometry": {"coordinates":[175.007217,-39.947155],"type":"Point"}
}