{
  "type": "Feature",
  "properties": {
    "addr:full":"353 The Parade Island Bay  Wellington Auckland",
    "addr:housenumber":"353",
    "addr:street":"The Parade",
    "iso:country":"NZ",
    "sg:address":"353 The Parade Island Bay ",
    "sg:city":"Wellington",
    "sg:orig_category":"Shopping: Sports Retailers: Water Sports",
    "sg:phone":"+64 4-383 6778",
    "sg:province":"Auckland",
    "sg:website":"http://www.ibdivers.co.nz",
    "wof:name":"Island Bay Divers",
    "wof:placetype":"venue"
},
  "geometry": {"coordinates":[174.770599,-41.342697],"type":"Point"}
}