{
  "type": "Feature",
  "properties": {
    "iso:country":"NZ",
    "sg:address":"Shop 7, 98-110 Victoria St ",
    "sg:city":"Wellington",
    "sg:classifiers":[
        {
            "category":"Internet Cafe",
            "subcategory":"None",
            "type":"Food & Drink"
        }
    ],
    "sg:phone":"+64 4-472 1144",
    "sg:province":"Wellington",
    "sg:tags":[
        "wining",
        "dining"
    ],
    "wof:name":"I-World",
    "wof:placetype":"venue"
},
  "geometry": {"coordinates":[147.016953,-37.911911],"type":"Point"}
}