{
  "type": "Feature",
  "properties": {
    "iso:country":"NZ",
    "sg:address":"Bowen St Waiuku ",
    "sg:city":"Pukekohe",
    "sg:classifiers":[
        {
            "category":"Shopping",
            "subcategory":"Bicycles & Sporting Goods",
            "type":"Retail Goods"
        }
    ],
    "sg:phone":"+64 9-235 2070",
    "sg:province":"Auckland",
    "sg:tags":[
        "cycle",
        "sport",
        "sale",
        "retailers",
        "cycles"
    ],
    "wof:name":"Sunset Cycles",
    "wof:placetype":"venue"
},
  "geometry": {"coordinates":[174.730301,-37.249146],"type":"Point"}
}