{
  "type": "Feature",
  "properties": {
    "addr:full":"Titirangi  Auckland Auckland",
    "iso:country":"NZ",
    "sg:address":"Titirangi ",
    "sg:city":"Auckland",
    "sg:classifiers":[
        {
            "category":"Personal",
            "subcategory":"Beauty Salon",
            "type":"Services"
        }
    ],
    "sg:phone":"+64 9-817 4820",
    "sg:province":"Auckland",
    "sg:tags":[
        "artist",
        "health",
        "make-up"
    ],
    "wof:name":"Trish Cohen",
    "wof:placetype":"venue"
},
  "geometry": {"coordinates":[174.655869,-36.93795],"type":"Point"}
}