{
  "type": "Feature",
  "properties": {
    "addr:full":"77 Shirley Rd Papatoetoe  Auckland Canterbury",
    "addr:housenumber":"77",
    "addr:street":"Shirley Rd",
    "iso:country":"NZ",
    "sg:address":"77 Shirley Rd Papatoetoe ",
    "sg:city":"Auckland",
    "sg:orig_category":"Industrial: Packaging: Bags",
    "sg:phone":"+64 9-278 1001",
    "sg:province":"Canterbury",
    "wof:name":"Provincial Sacks and Filters",
    "wof:placetype":"venue"
},
  "geometry": {"coordinates":[174.85003699999999,-36.977825],"type":"Point"}
}