{
  "type": "Feature",
  "properties": {
    "iso:country":"NZ",
    "sg:address":"284 Te Matai Rd Palmerston ",
    "sg:city":"Palmerston North",
    "sg:orig_category":"Storage: Storage",
    "sg:phone":"+64 6-358 4927",
    "sg:province":"Manawatu-Wanganui",
    "wof:name":"Te Matai Vehicle Storage",
    "wof:placetype":"venue"
},
  "geometry": {"coordinates":[175.68718000000001,-40.338146],"type":"Point"}
}