{
  "type": "Feature",
  "properties": {
    "iso:country":"NZ",
    "sg:address":"PO Box 1486 Auckland Central ",
    "sg:city":"Auckland",
    "sg:orig_category":"Industrial: Packaging: Packaging Machinery",
    "sg:phone":"+64 9-307 0923",
    "sg:province":"Auckland",
    "wof:name":"Securefresh Pacific Ltd",
    "wof:placetype":"venue"
},
  "geometry": {"coordinates":[174.76454200000001,-36.848358],"type":"Point"}
}