{
  "type": "Feature",
  "properties": {
    "iso:country":"NZ",
    "sg:address":"Pohaninga R D 14 Ashhurst ",
    "sg:city":"Pohangina",
    "sg:orig_category":"Farming: Forestry",
    "sg:phone":"+64 6-329 4802",
    "wof:name":"Max Clearwood J & C Collins",
    "wof:placetype":"venue"
},
  "geometry": {"coordinates":[175.755875,-40.287991],"type":"Point"}
}