{
  "type": "Feature",
  "properties": {
    "addr:full":"68 Park Rd Titirangi  Auckland Auckland",
    "addr:housenumber":"68",
    "addr:street":"Park Rd",
    "iso:country":"NZ",
    "sg:address":"68 Park Rd Titirangi ",
    "sg:city":"Auckland",
    "sg:orig_category":"Industrial: Consultancy: Quality Assurance",
    "sg:phone":"+64 9-817 9101",
    "sg:province":"Auckland",
    "wof:name":"Quality Associates International (NZ) Ltd",
    "wof:placetype":"venue"
},
  "geometry": {"coordinates":[174.66192599999999,-36.939159],"type":"Point"}
}