{
  "type": "Feature",
  "properties": {
    "iso:country":"NZ",
    "sg:address":"99 Hurstmere Rd PO Box 331-263 Takapuna ",
    "sg:city":"Auckland",
    "sg:orig_category":"Industrial: Packaging: Paper And Cardboard",
    "sg:phone":"+64 9-486 1906",
    "sg:province":"Auckland",
    "wof:name":"DaiEi Australasia",
    "wof:placetype":"venue"
},
  "geometry": {"coordinates":[174.767883,-36.787838],"type":"Point"}
}