{
  "type": "Feature",
  "properties": {
    "addr:full":"11 Remuera Rd Newmarket  Auckland Auckland",
    "addr:housenumber":"11",
    "addr:street":"Remuera Rd",
    "iso:country":"NZ",
    "sg:address":"11 Remuera Rd Newmarket ",
    "sg:city":"Auckland",
    "sg:classifiers":[
        {
            "category":"Shopping",
            "subcategory":"Crafts & Fabrics",
            "type":"Retail Goods"
        }
    ],
    "sg:phone":"+64 9-523 0398",
    "sg:province":"Auckland",
    "sg:tags":[
        "clothing",
        "maternity",
        "wear"
    ],
    "wof:name":"Egg Maternity Wear",
    "wof:placetype":"venue"
},
  "geometry": {"coordinates":[174.77775600000001,-36.870201],"type":"Point"}
}