{
  "type": "Feature",
  "properties": {
    "addr:full":"Weza La Kumeu  Auckland Auckland",
    "addr:street":"Weza La Kumeu",
    "iso:country":"NZ",
    "sg:address":"Weza La Kumeu ",
    "sg:city":"Auckland",
    "sg:orig_category":"Farming: Horticulture: Soil Sterilisation",
    "sg:phone":"+64 9-412 6232",
    "sg:province":"Auckland",
    "wof:name":"Aotea Steam Company Ltd",
    "wof:placetype":"venue"
},
  "geometry": {"coordinates":[174.56021100000001,-36.777275],"type":"Point"}
}