{
  "type": "Feature",
  "properties": {
    "addr:full":"31 Waihi Rd  Tauranga Bay of Plenty",
    "addr:housenumber":"31",
    "addr:street":"Waihi Rd",
    "iso:country":"NZ",
    "sg:address":"31 Waihi Rd ",
    "sg:city":"Tauranga",
    "sg:orig_category":"Industrial: Electrical/Electronic: Electric Motors",
    "sg:phone":"+64 7-578 6149",
    "sg:province":"Bay of Plenty",
    "wof:name":"Industrial Rewinds Ltd",
    "wof:placetype":"venue"
},
  "geometry": {"coordinates":[176.15089399999999,-37.697495],"type":"Point"}
}