{
  "type": "Feature",
  "properties": {
    "addr:full":"45 Vigor Brown St  Napier Hawke's Bay",
    "addr:housenumber":"45",
    "addr:street":"Vigor Brown St",
    "iso:country":"NZ",
    "sg:address":"45 Vigor Brown St ",
    "sg:city":"Napier",
    "sg:classifiers":[
        {
            "category":"Health Services",
            "subcategory":"Health Practitioner",
            "type":"Services"
        }
    ],
    "sg:phone":"+64 6-835 7198",
    "sg:province":"Hawke's Bay",
    "sg:tags":[
        "services",
        "beauty",
        "acupuncturists"
    ],
    "wof:name":"Nigel Prior - Acupuncturist",
    "wof:placetype":"venue"
},
  "geometry": {"coordinates":[-80.588562,38.790821],"type":"Point"}
}