{
  "type": "Feature",
  "properties": {
    "addr:full":"257 Stafford St  Timaru Canterbury",
    "addr:housenumber":"257",
    "addr:street":"Stafford St",
    "iso:country":"NZ",
    "sg:address":"257 Stafford St ",
    "sg:city":"Timaru",
    "sg:classifiers":[
        {
            "category":"Travel",
            "subcategory":"Travel Agent",
            "type":"Entertainment"
        }
    ],
    "sg:phone":"+64 3-688 6099",
    "sg:province":"Canterbury",
    "sg:tags":[
        "tourism",
        "broker"
    ],
    "wof:name":"Thomas Cook",
    "wof:placetype":"venue"
},
  "geometry": {"coordinates":[171.25192300000001,-44.394615],"type":"Point"}
}