{
  "type": "Feature",
  "properties": {
    "addr:full":"16/34 Miro Rd Mangere Bridge  Auckland Auckland",
    "addr:housenumber":"16 / 34",
    "addr:street":"Miro Rd",
    "iso:country":"NZ",
    "sg:address":"16/34 Miro Rd Mangere Bridge ",
    "sg:city":"Auckland",
    "sg:classifiers":[
        {
            "category":"Social Services",
            "subcategory":"Job Training",
            "type":"Services"
        }
    ],
    "sg:phone":"+64 9-636 9792",
    "sg:province":"Auckland",
    "sg:tags":[
        "education"
    ],
    "wof:name":"Tamaki Ki Raro Trust",
    "wof:placetype":"venue"
},
  "geometry": {"coordinates":[174.792618,-36.942131],"type":"Point"}
}