{
  "type": "Feature",
  "properties": {
    "iso:country":"NZ",
    "sg:address":"141 Cambridge Tce ",
    "sg:city":"Christchurch",
    "sg:orig_category":"Transport: Boats And Marine: Shipping: Shipping Companies",
    "sg:phone":"+64 3-379 6566",
    "sg:province":"Canterbury",
    "wof:name":"Columbus Line New Zealand Ltd",
    "wof:placetype":"venue"
},
  "geometry": {"coordinates":[-76.537834,37.605659],"type":"Point"}
}