{
  "type": "Feature",
  "properties": {
    "iso:country":"NZ",
    "sg:address":"427 New North Rd Kingsland ",
    "sg:city":"Auckland",
    "sg:orig_category":"Clothing And Fabric: Clothing: Uniforms",
    "sg:phone":"+64 9-846 6310",
    "sg:province":"Auckland",
    "wof:name":"Harrison J Corporate Apparel",
    "wof:placetype":"venue"
},
  "geometry": {"coordinates":[174.746674,-36.871441],"type":"Point"}
}