{
  "type": "Feature",
  "properties": {
    "iso:country":"NZ",
    "sg:address":"72 Hilton Hwy ",
    "sg:city":"Timaru",
    "sg:orig_category":"Farming: Machinery: Farm Machinery",
    "sg:phone":"+64 3-688 2111",
    "sg:province":"Canterbury",
    "wof:name":"Cosgrove Dan Ltd",
    "wof:placetype":"venue"
},
  "geometry": {"coordinates":[171.239288,-44.358669],"type":"Point"}
}