{
  "type": "Feature",
  "properties": {
    "addr:full":"10 Fleet St  Masterton Wellington",
    "addr:housenumber":"10",
    "addr:street":"Fleet St",
    "iso:country":"NZ",
    "sg:address":"10 Fleet St ",
    "sg:city":"Masterton",
    "sg:classifiers":[
        {
            "category":"Social Services",
            "subcategory":"Retirement Home",
            "type":"Services"
        }
    ],
    "sg:phone":"+64 6-377 4900",
    "sg:province":"Wellington",
    "sg:tags":[
        "sharpening",
        "garden"
    ],
    "wof:name":"Wairarapa Saw Service",
    "wof:placetype":"venue"
},
  "geometry": {"coordinates":[175.63284300000001,-40.960678],"type":"Point"}
}