{
  "type": "Feature",
  "properties": {
    "addr:full":"1 Awamutu Gro Gracefield  Wellington Wellington",
    "addr:housenumber":"1",
    "addr:street":"Awamutu Gro",
    "iso:country":"NZ",
    "sg:address":"1 Awamutu Gro Gracefield ",
    "sg:city":"Wellington",
    "sg:orig_category":"Shopping: Hobbies And Games: Aromatherapy",
    "sg:phone":"+64 4-939 0220",
    "sg:province":"Wellington",
    "wof:name":"Christene Carden",
    "wof:placetype":"venue"
},
  "geometry": {"coordinates":[174.91166699999999,-41.238205],"type":"Point"}
}