{
  "type": "Feature",
  "properties": {
    "addr:full":"20 A Rylock Pl Pakuranga  Auckland Auckland",
    "addr:housenumber":"20",
    "addr:street":"A Rylock Pl",
    "iso:country":"NZ",
    "sg:address":"20 A Rylock Pl Pakuranga ",
    "sg:city":"Auckland",
    "sg:classifiers":[
        {
            "category":"Food & Beverages",
            "subcategory":"Candy",
            "type":"Retail Goods"
        }
    ],
    "sg:phone":"+64 9-576 4561",
    "sg:province":"Auckland",
    "sg:tags":[
        "confectioner",
        "drink",
        "-"
    ],
    "wof:name":"Chocolates Are Us Ltd",
    "wof:placetype":"venue"
},
  "geometry": {"coordinates":[174.89987199999999,-36.918491],"type":"Point"}
}