{
  "type": "Feature",
  "properties": {
    "iso:country":"NZ",
    "sg:address":"231 Leith Pl ",
    "sg:city":"Tokoroa",
    "sg:classifiers":[
        {
            "category":"Travel",
            "subcategory":"Travel Agent",
            "type":"Entertainment"
        }
    ],
    "sg:phone":"+64 7-886 6258",
    "sg:tags":[
        "tourism",
        "broker"
    ],
    "sg:website":"http://www.flightsdirect.co.nz",
    "wof:name":"Pacesetter Holiday Shoppe",
    "wof:placetype":"venue"
},
  "geometry": {"coordinates":[175.87292500000001,-38.218658],"type":"Point"}
}