{
  "type": "Feature",
  "properties": {
    "iso:country":"NZ",
    "sg:address":"37 Victoria St ",
    "sg:city":"Cambridge",
    "sg:classifiers":[
        {
            "category":"Communications",
            "subcategory":"Film & Video Production",
            "type":"Services"
        }
    ],
    "sg:phone":"+64 7-827 5428",
    "sg:province":"Waikato",
    "sg:tags":[
        "sport",
        "leisure",
        "library",
        "entertainment"
    ],
    "wof:name":"United Video Cambridge",
    "wof:placetype":"venue"
},
  "geometry": {"coordinates":[175.470474,-37.895702],"type":"Point"}
}