{
  "type": "Feature",
  "properties": {
    "addr:full":"4 Augusta St Redcliffs  Christchurch Canterbury",
    "addr:housenumber":"4",
    "addr:street":"Augusta St",
    "iso:country":"NZ",
    "sg:address":"4 Augusta St Redcliffs ",
    "sg:city":"Christchurch",
    "sg:classifiers":[
        {
            "category":"Social Services",
            "subcategory":"Child Care",
            "type":"Services"
        }
    ],
    "sg:phone":"+64 3-384 1910",
    "sg:province":"Canterbury",
    "sg:tags":[
        "home",
        "garden",
        "children"
    ],
    "wof:name":"Redcliffs-Sumner Community Creche Assoc Inc",
    "wof:placetype":"venue"
},
  "geometry": {"coordinates":[172.73835800000001,-43.562305],"type":"Point"}
}