{
  "type": "Feature",
  "properties": {
    "iso:country":"NZ",
    "sg:address":"10 Dawick St Foxton Beach ",
    "sg:city":"Foxton",
    "sg:classifiers":[
        {
            "category":"Social Services",
            "subcategory":"Retirement Home",
            "type":"Services"
        }
    ],
    "sg:phone":"+64 6-363 8273",
    "sg:tags":[
        "elderly",
        "convalescent",
        "garden",
        "rest",
        "care"
    ],
    "wof:name":"Riverside at Foxton Beach",
    "wof:placetype":"venue"
},
  "geometry": {"coordinates":[175.23104900000001,-40.465851],"type":"Point"}
}