{
  "type": "Feature",
  "properties": {
    "addr:full":"Te Rapa Rd Te Rapa  Hamilton Waikato",
    "addr:street":"Te Rapa Rd",
    "iso:country":"NZ",
    "sg:address":"Te Rapa Rd Te Rapa ",
    "sg:city":"Hamilton",
    "sg:classifiers":[
        {
            "category":"Sports & Exercise",
            "subcategory":"Playing Field",
            "type":"Entertainment"
        }
    ],
    "sg:phone":"+64 7-849 2162",
    "sg:province":"Waikato",
    "sg:tags":[
        "operator",
        "totalisator",
        "leisure"
    ],
    "wof:name":"TAB",
    "wof:placetype":"venue"
},
  "geometry": {"coordinates":[175.24704,-37.75872],"type":"Point"}
}