{
  "type": "Feature",
  "properties": {
    "addr:full":"Wrights Rd Middleton  Christchurch Canterbury",
    "addr:street":"Wrights Rd",
    "iso:country":"NZ",
    "sg:address":"Wrights Rd Middleton ",
    "sg:city":"Christchurch",
    "sg:classifiers":[
        {
            "category":"Autos & Motor Vehicles",
            "subcategory":"Boat Sales",
            "type":"Retail Goods"
        }
    ],
    "sg:phone":"+64 3-338 5525",
    "sg:province":"Canterbury",
    "sg:tags":[
        "car",
        "leasing",
        "market",
        "automotive"
    ],
    "wof:name":"Canterbury Car Fair",
    "wof:placetype":"venue"
},
  "geometry": {"coordinates":[172.59657300000001,-43.541981],"type":"Point"}
}