{
  "type": "Feature",
  "properties": {
    "addr:full":"363 b Ngatai Rd Otumoetai  Tauranga Bay of Plenty",
    "addr:housenumber":"363 b",
    "addr:street":"Ngatai Rd",
    "iso:country":"NZ",
    "sg:address":"363 b Ngatai Rd Otumoetai ",
    "sg:city":"Tauranga",
    "sg:classifiers":[
        {
            "category":"Personal",
            "subcategory":"Massage",
            "type":"Services"
        }
    ],
    "sg:phone":"+64 7-576 1561",
    "sg:province":"Bay of Plenty",
    "sg:tags":[
        "services",
        "health",
        "-",
        "beauty",
        "fitness"
    ],
    "wof:name":"Paula Roper",
    "wof:placetype":"venue"
},
  "geometry": {"coordinates":[176.13519299999999,-37.667923],"type":"Point"}
}