{
  "type": "Feature",
  "properties": {
    "iso:country":"NZ",
    "sg:address":"64 James St ",
    "sg:city":"Whangarei",
    "sg:classifiers":[
        {
            "category":"Autos & Motor Vehicles",
            "subcategory":"Automobile Sales",
            "type":"Retail Goods"
        }
    ],
    "sg:phone":"+64 9-438 2419",
    "sg:province":"Northland",
    "sg:tags":[
        "car",
        "importer",
        "leasing",
        "automotive"
    ],
    "wof:name":"CJ's Auto One",
    "wof:placetype":"venue"
},
  "geometry": {"coordinates":[174.323624,-35.723354],"type":"Point"}
}