{
  "type": "Feature",
  "properties": {
    "iso:country":"NZ",
    "sg:address":"701 Karamu Rd North ",
    "sg:city":"Hastings",
    "sg:orig_category":"Shopping: Retail Stores: Batteries",
    "sg:phone":"+64 6-878 8876",
    "sg:province":"Hawke's Bay",
    "wof:name":"Leo's Tyre Service",
    "wof:placetype":"venue"
},
  "geometry": {"coordinates":[176.85116600000001,-39.638962],"type":"Point"}
}