{
  "type": "Feature",
  "properties": {
    "iso:country":"NZ",
    "sg:address":"31 Hands Rd Addington ",
    "sg:city":"Christchurch",
    "sg:classifiers":[
        {
            "category":"Autos & Motor Vehicles",
            "subcategory":"Automobile Sales",
            "type":"Retail Goods"
        }
    ],
    "sg:phone":"+64 3-351 8065",
    "sg:province":"Canterbury",
    "sg:tags":[
        "car",
        "-used",
        "leasing",
        "truck",
        "automotive"
    ],
    "sg:website":"http://www.interbus.co.nz",
    "wof:name":"Interbus",
    "wof:placetype":"venue"
},
  "geometry": {"coordinates":[172.61795,-43.54319],"type":"Point"}
}