{
  "type": "Feature",
  "properties": {
    "addr:full":"79 Broadway  Matamata Manawatu-Wanganui",
    "addr:housenumber":"79",
    "addr:street":"Broadway",
    "iso:country":"NZ",
    "sg:address":"79 Broadway ",
    "sg:city":"Matamata",
    "sg:classifiers":[
        {
            "category":"Shopping",
            "subcategory":"Shoes",
            "type":"Retail Goods"
        }
    ],
    "sg:phone":"+64 7-888 8824",
    "sg:province":"Manawatu-Wanganui",
    "sg:tags":[
        "foot",
        "clothing",
        "fabric",
        "wear"
    ],
    "wof:name":"Happy Feet Footwear Sales",
    "wof:placetype":"venue"
},
  "geometry": {"coordinates":[175.77778599999999,-37.81144],"type":"Point"}
}