{
  "type": "Feature",
  "properties": {
    "addr:full":"251 Tramway Rd Heidelberg  Invercargill Southland",
    "addr:housenumber":"251",
    "addr:street":"Tramway Rd",
    "iso:country":"NZ",
    "sg:address":"251 Tramway Rd Heidelberg ",
    "sg:city":"Invercargill",
    "sg:orig_category":"Shopping: Retail Stores: Batteries",
    "sg:phone":"+64 3-216 0017",
    "sg:province":"Southland",
    "wof:name":"Koyo Batteries (nz) Ltd",
    "wof:placetype":"venue"
},
  "geometry": {"coordinates":[168.378128,-46.432495],"type":"Point"}
}