{
  "type": "Feature",
  "properties": {
    "iso:country":"NZ",
    "sg:address":"267 Pakuranga Highway Pakuranga ",
    "sg:city":"Auckland",
    "sg:orig_category":"Industrial: Engineering: Engineers: Engineers - Consulting",
    "sg:phone":"+64 9-576 8222",
    "sg:province":"Auckland",
    "wof:name":"Protocold Services Ltd",
    "wof:placetype":"venue"
},
  "geometry": {"coordinates":[174.884399,-36.908421],"type":"Point"}
}