{
  "type": "Feature",
  "properties": {
    "addr:full":"Kairimu St Stokes Valley Lower  Hutt Wellington",
    "addr:street":"St",
    "iso:country":"NZ",
    "sg:address":"Kairimu St Stokes Valley Lower ",
    "sg:city":"Hutt",
    "sg:classifiers":[
        {
            "category":"Health Services",
            "subcategory":"Dentist",
            "type":"Services"
        }
    ],
    "sg:phone":"+64 4-562 9015",
    "sg:province":"Wellington",
    "sg:tags":[
        "dental",
        "beauty"
    ],
    "wof:name":"Stokes Valley School Dental Clinic",
    "wof:placetype":"venue"
},
  "geometry": {"coordinates":[174.986435,-41.181374],"type":"Point"}
}