{
  "type": "Feature",
  "properties": {
    "addr:full":"648 Tremaine Ave Palmerston  Palmerston North Manawatu-Wanganui",
    "addr:housenumber":"648",
    "addr:street":"Tremaine Ave",
    "iso:country":"NZ",
    "sg:address":"648 Tremaine Ave Palmerston ",
    "sg:city":"Palmerston North",
    "sg:orig_category":"Industrial: Metal: Products: Aluminium Products",
    "sg:phone":"+64 6-358 7530",
    "sg:province":"Manawatu-Wanganui",
    "wof:name":"Rylock Windows & Doors",
    "wof:placetype":"venue"
},
  "geometry": {"coordinates":[175.60626199999999,-40.341423],"type":"Point"}
}