{
  "type": "Feature",
  "properties": {
    "iso:country":"NZ",
    "sg:address":"22 Alloy St Sockburn ",
    "sg:city":"Christchurch",
    "sg:classifiers":[
        {
            "category":"Personal",
            "subcategory":"Day Spa",
            "type":"Services"
        }
    ],
    "sg:phone":"+64 3-348 8641",
    "sg:province":"Canterbury",
    "sg:tags":[
        "specialist",
        "satellite",
        "industrial",
        "machinery",
        "equipment"
    ],
    "wof:name":"Teltrac Communications Ltd",
    "wof:placetype":"venue"
},
  "geometry": {"coordinates":[172.553818,-43.540241],"type":"Point"}
}