{
  "type": "Feature",
  "properties": {
    "iso:country":"NZ",
    "sg:address":"PO Box 5459 ",
    "sg:city":"Christchurch",
    "sg:classifiers":[
        {
            "category":"Manufacturing",
            "subcategory":"Tools & Machinery",
            "type":"Manufacturing & Wholesale Goods"
        }
    ],
    "sg:phone":"+64 3-352 5245",
    "sg:province":"Canterbury",
    "sg:tags":[
        "specialist",
        "energy",
        "industrial",
        "solar",
        "equipment"
    ],
    "wof:name":"Solahart Solar Hot Water Heating",
    "wof:placetype":"venue"
},
  "geometry": {"coordinates":[-76.537834,37.605659],"type":"Point"}
}