{
  "type": "Feature",
  "properties": {
    "addr:full":"Unt 14 65 Paul Matthews Rd Albany  Auckland Auckland",
    "addr:housenumber":"14 65",
    "addr:street":"Unt;Paul Matthews Rd",
    "iso:country":"NZ",
    "sg:address":"Unt 14 65 Paul Matthews Rd Albany ",
    "sg:city":"Auckland",
    "sg:orig_category":"Shopping: Retail Stores: Supermarkets",
    "sg:phone":"+64 9-415 1311",
    "sg:province":"Auckland",
    "wof:name":"The Palms Superette",
    "wof:placetype":"venue"
},
  "geometry": {"coordinates":[174.71392800000001,-36.751152],"type":"Point"}
}