{
  "type": "Feature",
  "properties": {
    "addr:full":"8 Otaki St South Dunedin  Dunedin Otago",
    "addr:housenumber":"8",
    "addr:street":"Otaki St",
    "iso:country":"NZ",
    "sg:address":"8 Otaki St South Dunedin ",
    "sg:city":"Dunedin",
    "sg:classifiers":[
        {
            "category":"Retail",
            "subcategory":"Auto Repair",
            "type":"Services"
        }
    ],
    "sg:phone":"+64 3-455 2151",
    "sg:province":"Otago",
    "sg:tags":[
        "automotive",
        "panel",
        "servicing",
        "beater"
    ],
    "wof:name":"Brownlie and Scoles Ltd",
    "wof:placetype":"venue"
},
  "geometry": {"coordinates":[170.504898,-45.888805],"type":"Point"}
}