{
  "type": "Feature",
  "properties": {
    "addr:full":"4 Line Rd  Methven",
    "addr:street":"4 Line Rd",
    "iso:country":"NZ",
    "sg:address":"4 Line Rd ",
    "sg:city":"Methven",
    "sg:orig_category":"Industrial: Products: Window Control Gear",
    "sg:phone":"+64 3-302 8329",
    "wof:name":"Shearmac Aluminium & Joinery Ltd",
    "wof:placetype":"venue"
},
  "geometry": {"coordinates":[171.658401,-43.642918],"type":"Point"}
}