{
  "type": "Feature",
  "properties": {
    "iso:country":"NZ",
    "sg:address":"Royal Oak Mall Shop 23C 691 Manukau Rd Royal Oak ",
    "sg:city":"Auckland",
    "sg:classifiers":[
        {
            "category":"Home & Garden",
            "subcategory":"Kitchen Supply",
            "type":"Retail Goods"
        }
    ],
    "sg:phone":"+64 9-624 2443",
    "sg:province":"Auckland",
    "sg:tags":[
        "shop",
        "pet",
        "pets"
    ],
    "wof:name":"James Pet Centre",
    "wof:placetype":"venue"
},
  "geometry": {"coordinates":[174.77351400000001,-36.910019],"type":"Point"}
}