{
  "type": "Feature",
  "properties": {
    "iso:country":"NZ",
    "sg:address":"280 Queen St Auckland Central ",
    "sg:city":"Auckland",
    "sg:orig_category":"Shopping: Accessories: Jewellers And Watchmakers",
    "sg:phone":"+64 9-358 4683",
    "sg:province":"Auckland",
    "wof:name":"Diamond Shop (The)",
    "wof:placetype":"venue"
},
  "geometry": {"coordinates":[174.764847,-36.850601],"type":"Point"}
}