{
  "type": "Feature",
  "properties": {
    "addr:full":"cnr Hewletts Rd & McDonald St Mt  Maunganui Bay of Plenty",
    "addr:street":"Cnr Hewletts Rd & Mcdonald St;Maunganui",
    "iso:country":"NZ",
    "sg:address":"cnr Hewletts Rd & McDonald St Mt ",
    "sg:city":"Maunganui",
    "sg:orig_category":"Home And Garden: Gardening: Products",
    "sg:phone":"+64 7-575 5797",
    "sg:province":"Bay of Plenty",
    "sg:website":"http://www.gardenstatues.co.nz",
    "wof:name":"Garden Statues & Ornaments",
    "wof:placetype":"venue"
},
  "geometry": {"coordinates":[176.18627900000001,-37.641048],"type":"Point"}
}