{
  "type": "Feature",
  "properties": {
    "iso:country":"NZ",
    "sg:address":"Newmarket ",
    "sg:city":"Auckland",
    "sg:orig_category":"Health And Beauty: Dental: Dentists",
    "sg:phone":"+64 9-529 2089",
    "sg:province":"Auckland",
    "sg:website":"http://www.andreashepperson.com",
    "wof:name":"Andrea Shepperson Cosmetic Dentistry",
    "wof:placetype":"venue"
},
  "geometry": {"coordinates":[174.773758,-36.867878],"type":"Point"}
}