{
  "type": "Feature",
  "properties": {
    "iso:country":"NZ",
    "sg:address":"Tui-Glen Main Rd Nth ",
    "sg:city":"Greytown",
    "sg:classifiers":[
        {
            "category":"Coffee & Tea",
            "type":"Food & Drink"
        }
    ],
    "sg:phone":"+64 6-304 8185",
    "sg:tags":[
        "vegetable",
        "fruit",
        "veges"
    ],
    "wof:name":"Tui Glen Gardens",
    "wof:placetype":"venue"
},
  "geometry": {"coordinates":[175.45356799999999,-41.08231],"type":"Point"}
}