{
  "type": "Feature",
  "properties": {
    "addr:full":"137 Mulgrave St  Ashhurst",
    "addr:housenumber":"137",
    "addr:street":"Mulgrave St",
    "iso:country":"NZ",
    "sg:address":"137 Mulgrave St ",
    "sg:city":"Ashhurst",
    "sg:orig_category":"Shopping: Sports Retailers: Sports Goods: Sporting Goods",
    "sg:phone":"+64 6-326 8667",
    "wof:name":"Quality Kayaks Ltd",
    "wof:placetype":"venue"
},
  "geometry": {"coordinates":[175.747421,-40.295963],"type":"Point"}
}