{
  "type": "Feature",
  "properties": {
    "addr:full":"10 Miami Ave Surfdale  Auckland Auckland",
    "addr:housenumber":"10",
    "addr:street":"Miami Ave",
    "iso:country":"NZ",
    "sg:address":"10 Miami Ave Surfdale ",
    "sg:city":"Auckland",
    "sg:orig_category":"Shopping: Retail Stores: Supermarkets",
    "sg:phone":"+64 9-372 8627",
    "sg:province":"Auckland",
    "wof:name":"Miami Price Cutter",
    "wof:placetype":"venue"
},
  "geometry": {"coordinates":[174.67579699999999,-36.6208],"type":"Point"}
}