{
  "type": "Feature",
  "properties": {
    "iso:country":"NZ",
    "sg:address":"10 Miami Ave Surfdale ",
    "sg:city":"Auckland",
    "sg:orig_category":"Shopping: Retail Stores: Supermarkets",
    "sg:phone":"+64 9-372 8627",
    "sg:province":"Auckland",
    "wof:name":"Miami Price Cutter",
    "wof:placetype":"venue"
},
  "geometry": {"coordinates":[174.675797,-36.6208],"type":"Point"}
}