{
  "type": "Feature",
  "properties": {
    "addr:full":"306 Titirangi Rd Titirangi  Auckland Auckland",
    "addr:housenumber":"306",
    "addr:street":"Titirangi Rd",
    "iso:country":"NZ",
    "sg:address":"306 Titirangi Rd Titirangi ",
    "sg:city":"Auckland",
    "sg:orig_category":"Farming: Supplies: Veterinary Supplies",
    "sg:phone":"+64 9-817 6525",
    "sg:province":"Auckland",
    "wof:name":"Reamor (NZ) Limited",
    "wof:placetype":"venue"
},
  "geometry": {"coordinates":[174.66018700000001,-36.929333],"type":"Point"}
}