{
  "type": "Feature",
  "properties": {
    "iso:country":"NZ",
    "sg:address":"Unit/5 Tenehaun Pl Sockburn PO Box 8580 Riccarton ",
    "sg:city":"Christchurch",
    "sg:classifiers":[
        {
            "category":"Sports & Exercise",
            "subcategory":"Athletic Track",
            "type":"Entertainment"
        }
    ],
    "sg:phone":"+64 3-348 7438",
    "sg:province":"Canterbury",
    "sg:tags":[
        "machine",
        "gaming",
        "leisure"
    ],
    "wof:name":"Aristocrat Technologies NZ Ltd",
    "wof:placetype":"venue"
},
  "geometry": {"coordinates":[172.637314,-43.531315],"type":"Point"}
}