{
  "type": "Feature",
  "properties": {
    "addr:full":"24 Herekino St  Whangarei Northland",
    "addr:housenumber":"24",
    "addr:street":"Herekino St",
    "iso:country":"NZ",
    "sg:address":"24 Herekino St ",
    "sg:city":"Whangarei",
    "sg:classifiers":[
        {
            "category":"Bars & Pubs",
            "type":"Food & Drink"
        }
    ],
    "sg:phone":"+64 9-438 9514",
    "sg:province":"Northland",
    "wof:name":"Wes Airconditioning Ltd",
    "wof:placetype":"venue"
},
  "geometry": {"coordinates":[174.329117,-35.728424],"type":"Point"}
}