{
  "type": "Feature",
  "properties": {
    "addr:full":"181 Thorndon Qy Thorndon  Wellington Wellington",
    "addr:housenumber":"181",
    "addr:street":"Thorndon Qy",
    "iso:country":"NZ",
    "sg:address":"181 Thorndon Qy Thorndon ",
    "sg:city":"Wellington",
    "sg:classifiers":[
        {
            "category":"Manufacturing",
            "subcategory":"Glass & Minerals",
            "type":"Manufacturing & Wholesale Goods"
        }
    ],
    "sg:phone":"+64 4-471 0428",
    "sg:province":"Wellington",
    "sg:tags":[
        "chemical",
        "paint",
        "industrial",
        "manufacturer",
        "compounds"
    ],
    "wof:name":"Taubmans",
    "wof:placetype":"venue"
},
  "geometry": {"coordinates":[174.776016,-41.274925],"type":"Point"}
}