{
  "type": "Feature",
  "properties": {
    "addr:full":"19 Earl Pl Palmerston  Palmerston North Manawatu-Wanganui",
    "addr:housenumber":"19",
    "addr:street":"Earl Pl",
    "iso:country":"NZ",
    "sg:address":"19 Earl Pl Palmerston ",
    "sg:city":"Palmerston North",
    "sg:orig_category":"Automotive: Sales And Leasing: Trailers",
    "sg:phone":"+64 6-357 4425",
    "sg:province":"Manawatu-Wanganui",
    "wof:name":"Manawatu Trailer Hire",
    "wof:placetype":"venue"
},
  "geometry": {"coordinates":[175.64245600000001,-40.366802],"type":"Point"}
}