{
  "type": "Feature",
  "properties": {
    "addr:full":"North Harbour Industrial Estate 4 Beatrice Tinsley, Cre Albany  Auckland Auckland",
    "addr:housenumber":"4",
    "addr:street":"North;Estate",
    "iso:country":"NZ",
    "sg:address":"North Harbour Industrial Estate 4 Beatrice Tinsley, Cre Albany ",
    "sg:city":"Auckland",
    "sg:classifiers":[
        {
            "category":"Shopping",
            "subcategory":"Pharmacy",
            "type":"Retail Goods"
        }
    ],
    "sg:phone":"+64 9-415 8477",
    "sg:province":"Auckland",
    "sg:tags":[
        "product",
        "health"
    ],
    "wof:name":"Efamol NZ Ltd",
    "wof:placetype":"venue"
},
  "geometry": {"coordinates":[174.68403599999999,-36.709885],"type":"Point"}
}