{
  "type": "Feature",
  "properties": {
    "addr:full":"Bright St  Gisborne Gisborne",
    "addr:street":"Bright St",
    "iso:country":"NZ",
    "sg:address":"Bright St ",
    "sg:city":"Gisborne",
    "sg:classifiers":[
        {
            "category":"Restaurant",
            "type":"Food & Drink"
        }
    ],
    "sg:phone":"+64 6-867 7047",
    "sg:province":"Gisborne",
    "sg:tags":[
        "wining",
        "dining"
    ],
    "wof:name":"RSA Restaurant",
    "wof:placetype":"venue"
},
  "geometry": {"coordinates":[178.02310199999999,-38.667126],"type":"Point"}
}