{
  "type": "Feature",
  "properties": {
    "addr:full":"Jim Anderson Otago Agent  Dunedin Otago",
    "iso:country":"NZ",
    "sg:address":"Jim Anderson Otago Agent ",
    "sg:city":"Dunedin",
    "sg:classifiers":[
        {
            "category":"Shopping",
            "subcategory":"Gifts & Souvenirs",
            "type":"Retail Goods"
        }
    ],
    "sg:phone":"+64 3-476 4709",
    "sg:province":"Otago",
    "sg:tags":[
        "postcard",
        "gifts",
        "greeting",
        "card"
    ],
    "wof:name":"Vidron Greeting Cards",
    "wof:placetype":"venue"
},
  "geometry": {"coordinates":[170.50384500000001,-45.8745],"type":"Point"}
}