{
  "type": "Feature",
  "properties": {
    "addr:full":"5 Oroua St Eastbourne Lower  Hutt Wellington",
    "addr:housenumber":"5",
    "addr:street":"Oroua St",
    "iso:country":"NZ",
    "sg:address":"5 Oroua St Eastbourne Lower ",
    "sg:city":"Hutt",
    "sg:classifiers":[
        {
            "category":"Restaurant",
            "type":"Food & Drink"
        }
    ],
    "sg:phone":"+64 4-562 0007",
    "sg:province":"Wellington",
    "sg:tags":[
        "wining",
        "dining",
        "pizza"
    ],
    "wof:name":"Lifeboat+",
    "wof:placetype":"venue"
},
  "geometry": {"coordinates":[174.897369,-41.290215],"type":"Point"}
}