{
  "type": "Feature",
  "properties": {
    "iso:country":"NZ",
    "sg:address":"PO Box 64098 Botany Town Centre ",
    "sg:city":"Auckland",
    "sg:orig_category":"Industrial: Consultancy",
    "sg:phone":"+64 9-537 2699",
    "sg:province":"Southland",
    "wof:name":"Nutravision Consultancy Services Ltd",
    "wof:placetype":"venue"
},
  "geometry": {"coordinates":[-119.10457599999999,36.597755],"type":"Point"}
}