{
  "type": "Feature",
  "properties": {
    "addr:full":"115 Featherston St  Wellington Wellington",
    "addr:housenumber":"115",
    "addr:street":"Featherston St",
    "iso:country":"NZ",
    "sg:address":"115 Featherston St ",
    "sg:city":"Wellington",
    "sg:orig_category":"Shopping: Retail Stores: Books: Bookshops",
    "sg:phone":"+64 4-473 8165",
    "sg:province":"Wellington",
    "wof:name":"Anitas Book Shop",
    "wof:placetype":"venue"
},
  "geometry": {"coordinates":[174.77787799999999,-41.282082],"type":"Point"}
}