{
  "type": "Feature",
  "properties": {
    "iso:country":"NZ",
    "sg:address":"115 Featherston St ",
    "sg:city":"Wellington",
    "sg:orig_category":"Shopping: Retail Stores: Books: Bookshops",
    "sg:phone":"+64 4-473 8165",
    "sg:province":"Wellington",
    "wof:name":"Anitas Book Shop",
    "wof:placetype":"venue"
},
  "geometry": {"coordinates":[174.777878,-41.282082],"type":"Point"}
}