{
  "type": "Feature",
  "properties": {
    "iso:country":"NZ",
    "sg:address":"43 Ponsonby Rd Ponsonby ",
    "sg:city":"Auckland",
    "sg:classifiers":[
        {
            "category":"Bars & Pubs",
            "type":"Food & Drink"
        }
    ],
    "sg:phone":"+64 9-376 6373",
    "sg:province":"Auckland",
    "sg:tags":[
        "wining",
        "dining",
        "brasserie"
    ],
    "wof:name":"St Arnou Brewery & Restaurant",
    "wof:placetype":"venue"
},
  "geometry": {"coordinates":[174.746765,-36.856407],"type":"Point"}
}