{
  "type": "Feature",
  "properties": {
    "iso:country":"NZ",
    "sg:address":"75 Riccarton Rd Riccarton ",
    "sg:city":"Christchurch",
    "sg:orig_category":"Health And Beauty: Beauty: Hairdressers",
    "sg:phone":"+64 3-341 5060",
    "sg:province":"Canterbury",
    "wof:name":"Aritzia Hair Design",
    "wof:placetype":"venue"
},
  "geometry": {"coordinates":[172.60405,-43.529572],"type":"Point"}
}