{
  "type": "Feature",
  "properties": {
    "addr:full":"Crn Burswood & Ti Rakau Dve  Auckland Auckland",
    "iso:country":"NZ",
    "sg:address":"Crn Burswood & Ti Rakau Dve ",
    "sg:city":"Auckland",
    "sg:classifiers":[
        {
            "category":"Food & Beverages",
            "subcategory":"Liquor & Beverages",
            "type":"Retail Goods"
        }
    ],
    "sg:phone":"+64 9-272 3520",
    "sg:province":"Auckland",
    "sg:tags":[
        "drink",
        "outlet"
    ],
    "wof:name":"Burswood Liquor",
    "wof:placetype":"venue"
},
  "geometry": {"coordinates":[174.89608799999999,-36.922749],"type":"Point"}
}