{
  "type": "Feature",
  "properties": {
    "addr:full":"29 Hewlett St  Whangarei Northland",
    "addr:housenumber":"29",
    "addr:street":"Hewlett St",
    "iso:country":"NZ",
    "sg:address":"29 Hewlett St ",
    "sg:city":"Whangarei",
    "sg:classifiers":[
        {
            "category":"Wholesale",
            "subcategory":"Meat",
            "type":"Manufacturing & Wholesale Goods"
        }
    ],
    "sg:phone":"+64 9-438 1688",
    "sg:province":"Northland",
    "sg:tags":[
        "food",
        "distributor",
        "drink",
        "meats"
    ],
    "wof:name":"Exotic Game Meats",
    "wof:placetype":"venue"
},
  "geometry": {"coordinates":[174.344742,-35.741608],"type":"Point"}
}