{
  "type": "Feature",
  "properties": {
    "iso:country":"NZ",
    "sg:address":"The Grange Golf ",
    "sg:city":"Club",
    "sg:orig_category":"Sports And Leisure: Sports: Golf: Golf Professionals",
    "sg:phone":"+64 9-278 6713",
    "wof:name":"Auckland City Golf Course Ltd",
    "wof:placetype":"venue"
},
  "geometry": {"coordinates":[174.85205099999999,-36.979698],"type":"Point"}
}