{
  "type": "Feature",
  "properties": {
    "iso:country":"NZ",
    "sg:address":"41 Ennis Ave Pakuranga ",
    "sg:city":"Auckland",
    "sg:classifiers":[
        {
            "category":"Social Services",
            "subcategory":"Retirement Home",
            "type":"Services"
        }
    ],
    "sg:phone":"+64 9-262 2740",
    "sg:province":"Auckland",
    "sg:tags":[
        "garden",
        "related",
        "equipment",
        "playground",
        "child",
        "children"
    ],
    "wof:name":"Alpha Marketing & Contracting",
    "wof:placetype":"venue"
},
  "geometry": {"coordinates":[174.892624,-36.912659],"type":"Point"}
}