{
  "type": "Feature",
  "properties": {
    "addr:full":"Mt Eden  Auckland Auckland",
    "iso:country":"NZ",
    "sg:address":"Mt Eden ",
    "sg:city":"Auckland",
    "sg:classifiers":[
        {
            "category":"Arts & Performance",
            "subcategory":"Music",
            "type":"Entertainment"
        }
    ],
    "sg:phone":"+64 800 768 636",
    "sg:province":"Auckland",
    "sg:tags":[
        "mobile",
        "sport",
        "-",
        "leisure",
        "disco"
    ],
    "wof:name":"Esoteric Sound & Light",
    "wof:placetype":"venue"
},
  "geometry": {"coordinates":[174.7621,-36.882469],"type":"Point"}
}