{
  "type": "Feature",
  "properties": {
    "addr:full":"309 Featherston St Palmerston  Palmerston North Manawatu-Wanganui",
    "addr:housenumber":"309",
    "addr:street":"Featherston St Palmerston",
    "iso:country":"NZ",
    "sg:address":"309 Featherston St Palmerston ",
    "sg:city":"Palmerston North",
    "sg:classifiers":[
        {
            "category":"Personal",
            "subcategory":"Shoe Repair & Shine",
            "type":"Services"
        }
    ],
    "sg:phone":"+64 6-358 1925",
    "sg:province":"Manawatu-Wanganui",
    "sg:tags":[
        "foot",
        "clothing",
        "fabric",
        "wear"
    ],
    "wof:name":"Cobbler",
    "wof:placetype":"venue"
},
  "geometry": {"coordinates":[175.611816,-40.347244],"type":"Point"}
}