{
  "type": "Feature",
  "properties": {
    "addr:full":"953 New North Rd Mt Albert  Auckland Auckland",
    "addr:housenumber":"953",
    "addr:street":"New North Rd",
    "iso:country":"NZ",
    "sg:address":"953 New North Rd Mt Albert ",
    "sg:city":"Auckland",
    "sg:classifiers":[
        {
            "category":"Shopping",
            "subcategory":"Gifts & Souvenirs",
            "type":"Retail Goods"
        }
    ],
    "sg:phone":"+64 9-845 4828",
    "sg:province":"Auckland",
    "sg:tags":[
        "travel",
        "tourism"
    ],
    "wof:name":"Great Wall NZ Sovereign",
    "wof:placetype":"venue"
},
  "geometry": {"coordinates":[174.711761,-36.887554],"type":"Point"}
}