{
  "type": "Feature",
  "properties": {
    "addr:full":"36 Hastie Ave Mangere  Auckland Auckland",
    "addr:housenumber":"36",
    "addr:street":"Hastie Ave",
    "iso:country":"NZ",
    "sg:address":"36 Hastie Ave Mangere ",
    "sg:city":"Auckland",
    "sg:orig_category":"Industrial: Parts: Bearings",
    "sg:phone":"+64 9-634 7550",
    "sg:province":"Auckland",
    "wof:name":"Saeco Bearings & Transmission",
    "wof:placetype":"venue"
},
  "geometry": {"coordinates":[174.79362499999999,-36.945431],"type":"Point"}
}