{
  "type": "Feature",
  "properties": {
    "addr:full":"140 Hutt Rd Petone Lower  Hutt Wellington",
    "addr:housenumber":"140",
    "addr:street":"Hutt Rd",
    "iso:country":"NZ",
    "sg:address":"140 Hutt Rd Petone Lower ",
    "sg:city":"Hutt",
    "sg:classifiers":[
        {
            "category":"Manufacturing",
            "subcategory":"Motor Vehicles & Parts",
            "type":"Manufacturing & Wholesale Goods"
        }
    ],
    "sg:phone":"+64 4-566 6129",
    "sg:province":"Wellington",
    "sg:tags":[
        "box",
        "industrial",
        "parts",
        "-",
        "gear"
    ],
    "wof:name":"Maud Kirk Machinery Ltd",
    "wof:placetype":"venue"
},
  "geometry": {"coordinates":[174.87670900000001,-41.220558],"type":"Point"}
}