{
  "type": "Feature",
  "properties": {
    "iso:country":"NZ",
    "sg:address":"140 Hutt Rd Petone Lower ",
    "sg:city":"Hutt",
    "sg:classifiers":[
        {
            "category":"Manufacturing",
            "subcategory":"Motor Vehicles & Parts",
            "type":"Manufacturing & Wholesale Goods"
        }
    ],
    "sg:phone":"+64 4-566 6129",
    "sg:province":"Wellington",
    "sg:tags":[
        "box",
        "industrial",
        "parts",
        "-",
        "gear"
    ],
    "wof:name":"Maud Kirk Machinery Ltd",
    "wof:placetype":"venue"
},
  "geometry": {"coordinates":[174.876709,-41.220558],"type":"Point"}
}