{
  "type": "Feature",
  "properties": {
    "iso:country":"NZ",
    "sg:address":"State Highway 10 Waipapa ",
    "sg:city":"Kerikeri",
    "sg:classifiers":[
        {
            "category":"Autos & Motor Vehicles",
            "subcategory":"Automobile Sales",
            "type":"Retail Goods"
        }
    ],
    "sg:phone":"+64 9-407 6912",
    "sg:province":"Northland",
    "sg:tags":[
        "home",
        "caravan",
        "leasing",
        "automotive"
    ],
    "wof:name":"Waipapa Caravan Court",
    "wof:placetype":"venue"
},
  "geometry": {"coordinates":[173.92688000000001,-35.206779],"type":"Point"}
}