{
  "type": "Feature",
  "properties": {
    "addr:full":"Esplanade  Kaikoura Gisborne",
    "iso:country":"NZ",
    "sg:address":"Esplanade ",
    "sg:city":"Kaikoura",
    "sg:orig_category":"Sports And Leisure: Arts: Theatres",
    "sg:phone":"+64 3-319 5859",
    "sg:province":"Gisborne",
    "wof:name":"Mayfair Theatre",
    "wof:placetype":"venue"
},
  "geometry": {"coordinates":[173.684113,-42.404743],"type":"Point"}
}