{
  "type": "Feature",
  "properties": {
    "iso:country":"NZ",
    "sg:address":"60 Cawley St Ellerslie ",
    "sg:city":"Auckland",
    "sg:classifiers":[
        {
            "category":"Shopping",
            "type":"Retail Goods"
        }
    ],
    "sg:phone":"+64 9-525 1390",
    "sg:province":"Auckland",
    "sg:tags":[
        "chemical",
        "industrial",
        "cleaning",
        "maintenance"
    ],
    "wof:name":"Clark Products Ltd",
    "wof:placetype":"venue"
},
  "geometry": {"coordinates":[174.811218,-36.901527],"type":"Point"}
}