{
  "type": "Feature",
  "properties": {
    "addr:full":"11 Patiki Rd, Avondale Auckland Auckland",
    "addr:housenumber":"11",
    "addr:street":"Patiki Rd",
    "iso:country":"NZ",
    "sg:address":"11 Patiki Rd, Avondale",
    "sg:city":"Auckland",
    "sg:classifiers":[
        {
            "category":"Restaurant",
            "type":"Food & Drink"
        }
    ],
    "sg:phone":"+64 9-828 3706",
    "sg:province":"Auckland",
    "sg:tags":[
        "equipment",
        "machinery"
    ],
    "wof:name":"Mixtec Fluid Mixers",
    "wof:placetype":"venue"
},
  "geometry": {"coordinates":[174.690933,-36.8932],"type":"Point"}
}