{
  "type": "Feature",
  "properties": {
    "addr:full":"328 Tay St  Invercargill Southland",
    "addr:housenumber":"328",
    "addr:street":"Tay St",
    "iso:country":"NZ",
    "sg:address":"328 Tay St ",
    "sg:city":"Invercargill",
    "sg:orig_category":"Health And Beauty: Specialists: Chiropractors",
    "sg:phone":"+64 3-217 9995",
    "sg:province":"Southland",
    "wof:name":"City Chiropractic",
    "wof:placetype":"venue"
},
  "geometry": {"coordinates":[168.380325,-46.40926],"type":"Point"}
}