{
  "type": "Feature",
  "properties": {
    "iso:country":"NZ",
    "sg:address":"155 Mary St ",
    "sg:city":"Invercargill",
    "sg:classifiers":[
        {
            "category":"Shopping",
            "subcategory":"Pets & Pet Supplies",
            "type":"Retail Goods"
        }
    ],
    "sg:phone":"+64 3-217 7919",
    "sg:province":"Southland",
    "sg:tags":[
        "boarding",
        "garden",
        "pets",
        "catteries",
        "home",
        "kennel"
    ],
    "wof:name":"A Grooming Room",
    "wof:placetype":"venue"
},
  "geometry": {"coordinates":[168.364349,-46.407166],"type":"Point"}
}