{
  "type": "Feature",
  "properties": {
    "iso:country":"NZ",
    "sg:address":"371 St Asaph St ",
    "sg:city":"Christchurch",
    "sg:orig_category":"Automotive: Servicing And Repair: Car Trimming/Upholstery",
    "sg:phone":"+64 3-366 6530",
    "sg:province":"Canterbury",
    "wof:name":"Gardener Kevin Car Upholstery",
    "wof:placetype":"venue"
},
  "geometry": {"coordinates":[-76.537834,37.605659],"type":"Point"}
}