{
  "type": "Feature",
  "properties": {
    "addr:full":"252 Blackbridge Rd Dairy Flat Hibiscus  Hibiscus Coast Auckland",
    "addr:housenumber":"252;hibiscus",
    "addr:street":"Blackbridge Rd;Hibiscus",
    "iso:country":"NZ",
    "sg:address":"252 Blackbridge Rd Dairy Flat Hibiscus ",
    "sg:city":"Hibiscus Coast",
    "sg:orig_category":"Sports And Leisure: Sports: Equestrian: Riding Schools",
    "sg:phone":"+64 9-427 4947",
    "sg:province":"Auckland",
    "wof:name":"Blackbridge Stables",
    "wof:placetype":"venue"
},
  "geometry": {"coordinates":[174.61431899999999,-36.685219],"type":"Point"}
}