{
  "type": "Feature",
  "properties": {
    "addr:full":"827 Old Coach Rd RD 6 Te  Puke Bay of Plenty",
    "addr:housenumber":"827;6",
    "addr:street":"Old Coach Rd Rd",
    "iso:country":"NZ",
    "sg:address":"827 Old Coach Rd RD 6 Te ",
    "sg:city":"Puke",
    "sg:orig_category":"Farming: Forestry",
    "sg:phone":"+64 7-533 4201",
    "sg:province":"Bay of Plenty",
    "wof:name":"McDowell Paul (Forestry)",
    "wof:placetype":"venue"
},
  "geometry": {"coordinates":[169.60586499999999,-46.042324],"type":"Point"}
}