{
  "type": "Feature",
  "properties": {
    "iso:country":"NZ",
    "sg:address":"Milford Cre Te ",
    "sg:city":"Anau",
    "sg:orig_category":"Home And Garden: Accessories: Hardware",
    "sg:phone":"+64 3-249 7661",
    "sg:province":"Auckland",
    "wof:name":"Te Anau Mitre 10",
    "wof:placetype":"venue"
},
  "geometry": {"coordinates":[-98.182678,40.465752],"type":"Point"}
}