{
  "type": "Feature",
  "properties": {
    "addr:full":"39-45 Porana Rd Glenfield  Auckland Auckland",
    "addr:housenumber":"39-45",
    "addr:street":"Porana Rd",
    "iso:country":"NZ",
    "sg:address":"39-45 Porana Rd Glenfield ",
    "sg:city":"Auckland",
    "sg:classifiers":[
        {
            "category":"Shopping",
            "subcategory":"Crafts & Fabrics",
            "type":"Retail Goods"
        }
    ],
    "sg:phone":"+64 9-444 3772",
    "sg:province":"Auckland",
    "sg:tags":[
        "leather",
        "clothing",
        "suede"
    ],
    "wof:name":"Challenge Leather Supplies Ltd",
    "wof:placetype":"venue"
},
  "geometry": {"coordinates":[174.728622,-36.784813],"type":"Point"}
}