{
  "type": "Feature",
  "properties": {
    "iso:country":"NZ",
    "sg:address":"59 Victoria Rd Devonport ",
    "sg:city":"Auckland",
    "sg:classifiers":[
        {
            "category":"Restaurant",
            "type":"Food & Drink"
        }
    ],
    "sg:phone":"+64 9-445 2232",
    "sg:province":"Auckland",
    "sg:tags":[
        "wining",
        "dining",
        "pizza"
    ],
    "wof:name":"Delissimo Pizzas",
    "wof:placetype":"venue"
},
  "geometry": {"coordinates":[174.79763800000001,-36.830372],"type":"Point"}
}