{
  "type": "Feature",
  "properties": {
    "iso:country":"NZ",
    "sg:address":"209 Broadway Newmarket ",
    "sg:city":"Auckland",
    "sg:orig_category":"Clothing And Fabric: Clothing: Women'S Fashions",
    "sg:phone":"+64 9-522 4042",
    "sg:province":"Manawatu-Wanganui",
    "wof:name":"Sussan Retail (NZ) Pty Ltd",
    "wof:placetype":"venue"
},
  "geometry": {"coordinates":[174.777557,-36.869408],"type":"Point"}
}