{
  "type": "Feature",
  "properties": {
    "addr:full":"Level 1, Equinox House 222 Lambton Qy  Wellington Wellington",
    "addr:housenumber":"level 1 equinox;222",
    "iso:country":"NZ",
    "sg:address":"Level 1, Equinox House 222 Lambton Qy ",
    "sg:city":"Wellington",
    "sg:classifiers":[
        {
            "category":"Shopping",
            "subcategory":"Clothing, Apparel, & Fashions",
            "type":"Retail Goods"
        }
    ],
    "sg:phone":"+64 4-499 1007",
    "sg:province":"Wellington",
    "sg:tags":[
        "-",
        "hire",
        "clothing",
        "fabric"
    ],
    "wof:name":"Wilkin Formal Wear",
    "wof:placetype":"venue"
},
  "geometry": {"coordinates":[174.76715100000001,-41.28054],"type":"Point"}
}