{
  "type": "Feature",
  "properties": {
    "addr:full":"Ngarongo Rd Normanby  Hawera Taranaki",
    "addr:street":"Ngarongo Rd",
    "iso:country":"NZ",
    "sg:address":"Ngarongo Rd Normanby ",
    "sg:city":"Hawera",
    "sg:orig_category":"Industrial: Abrasives: Abrasive Blasting",
    "sg:phone":"+64 6-272 8143",
    "sg:province":"Taranaki",
    "wof:name":"Nickel Engineering",
    "wof:placetype":"venue"
},
  "geometry": {"coordinates":[174.27526900000001,-39.546028],"type":"Point"}
}