{
  "type": "Feature",
  "properties": {
    "iso:country":"NZ",
    "sg:address":"Gibsons Rd ",
    "sg:city":"Makikihi",
    "sg:orig_category":"Farming: Agriculture: Agricultural Contractors",
    "sg:phone":"+64 25327118",
    "wof:name":"Bleeker Agricultural Contractors",
    "wof:placetype":"venue"
},
  "geometry": {"coordinates":[171.064316,-44.623199],"type":"Point"}
}