{
  "type": "Feature",
  "properties": {
    "iso:country":"NZ",
    "sg:address":"19 Moore St Howick ",
    "sg:city":"Auckland",
    "sg:classifiers":[
        {
            "category":"Personal",
            "subcategory":"Shoe Repair & Shine",
            "type":"Services"
        }
    ],
    "sg:phone":"+64 9-534 4858",
    "sg:province":"Auckland",
    "sg:tags":[
        "foot",
        "clothing",
        "fabric",
        "wear"
    ],
    "wof:name":"Howick Heel & Sole Bar",
    "wof:placetype":"venue"
},
  "geometry": {"coordinates":[174.931961,-36.895496],"type":"Point"}
}