{
  "type": "Feature",
  "properties": {
    "iso:country":"NZ",
    "sg:address":"366 Heads Rd ",
    "sg:city":"Wanganui",
    "sg:orig_category":"Industrial: Metal",
    "sg:phone":"+64 6-344 2266",
    "sg:province":"Manawatu-Wanganui",
    "wof:name":"Wanganui Steel Supplies",
    "wof:placetype":"venue"
},
  "geometry": {"coordinates":[175.012238,-39.948212],"type":"Point"}
}