{
  "type": "Feature",
  "properties": {
    "addr:full":"1 A Robert St  Whangarei Northland",
    "addr:housenumber":"1",
    "addr:street":"A Robert St",
    "iso:country":"NZ",
    "sg:address":"1 A Robert St ",
    "sg:city":"Whangarei",
    "sg:classifiers":[
        {
            "category":"Professional",
            "subcategory":"Management & Consulting",
            "type":"Services"
        }
    ],
    "sg:phone":"+64 9-438 1986",
    "sg:province":"Northland",
    "sg:tags":[
        "consultant",
        "training",
        "education"
    ],
    "wof:name":"Family Planning Assn",
    "wof:placetype":"venue"
},
  "geometry": {"coordinates":[174.32064800000001,-35.723446],"type":"Point"}
}