{
  "type": "Feature",
  "properties": {
    "iso:country":"NZ",
    "sg:address":"374 West Coast Rd Glen Eden ",
    "sg:city":"Auckland",
    "sg:classifiers":[
        {
            "category":"Shopping",
            "subcategory":"Pharmacy",
            "type":"Retail Goods"
        }
    ],
    "sg:phone":"+64 9-818 9524",
    "sg:province":"Auckland",
    "sg:tags":[
        "product",
        "health"
    ],
    "wof:name":"East West Organics",
    "wof:placetype":"venue"
},
  "geometry": {"coordinates":[174.638885,-36.90905],"type":"Point"}
}