{
  "type": "Feature",
  "properties": {
    "iso:country":"NZ",
    "sg:address":"96 Gavin St Ellerslie ",
    "sg:city":"Auckland",
    "sg:orig_category":"Industrial: Instruments",
    "sg:phone":"+64 9-526 0066",
    "sg:province":"Auckland",
    "wof:name":"Marconi Commerce Systems (NZ) Limited",
    "wof:placetype":"venue"
},
  "geometry": {"coordinates":[174.817963,-36.903587],"type":"Point"}
}