{
  "type": "Feature",
  "properties": {
    "addr:full":"114 Main Rd Fairfield  Dunedin Otago",
    "addr:housenumber":"114",
    "addr:street":"Main Rd",
    "iso:country":"NZ",
    "sg:address":"114 Main Rd Fairfield ",
    "sg:city":"Dunedin",
    "sg:classifiers":[
        {
            "category":"Home & Garden",
            "subcategory":"Furniture",
            "type":"Retail Goods"
        }
    ],
    "sg:phone":"+64 3-488 4608",
    "sg:province":"Otago",
    "sg:tags":[
        "furniture/furnishings",
        "furnishing"
    ],
    "wof:name":"Butston's Furniture House Ltd",
    "wof:placetype":"venue"
},
  "geometry": {"coordinates":[170.39056400000001,-45.899158],"type":"Point"}
}