{
  "type": "Feature",
  "properties": {
    "addr:full":"2 Green La Sockburn  Christchurch Canterbury",
    "addr:housenumber":"2",
    "addr:street":"Green La Sockburn",
    "iso:country":"NZ",
    "sg:address":"2 Green La Sockburn ",
    "sg:city":"Christchurch",
    "sg:orig_category":"Home And Garden: Gardening: Products: Garden Ornaments",
    "sg:phone":"+64 3-343 1301",
    "sg:province":"Canterbury",
    "wof:name":"Millstream Ornamentals & Water Features",
    "wof:placetype":"venue"
},
  "geometry": {"coordinates":[172.55043000000001,-43.534966],"type":"Point"}
}