{
  "type": "Feature",
  "properties": {
    "addr:full":"214 State Highway 1  Otaki",
    "addr:housenumber":"214",
    "addr:street":"State Highway 1 Otaki",
    "iso:country":"NZ",
    "sg:address":"214 State Highway 1 ",
    "sg:city":"Otaki",
    "sg:orig_category":"Shopping: Accessories: Lingerie - Retail",
    "sg:phone":"+64 6-364 8230",
    "wof:name":"Bendon Outlet - Lingerie & Underwear Shop",
    "wof:placetype":"venue"
},
  "geometry": {"coordinates":[175.156113,-40.762062],"type":"Point"}
}