{
  "type": "Feature",
  "properties": {
    "addr:full":"407 Hillside Rd South  Dunedin Otago",
    "addr:housenumber":"407",
    "addr:street":"Hillside Rd",
    "iso:country":"NZ",
    "sg:address":"407 Hillside Rd South ",
    "sg:city":"Dunedin",
    "sg:classifiers":[
        {
            "category":"Retail",
            "subcategory":"Funeral Services",
            "type":"Services"
        }
    ],
    "sg:phone":"+64 800 858 555",
    "sg:province":"Otago",
    "sg:tags":[
        "arrangements",
        "arrangement"
    ],
    "wof:name":"Gillions And Sons Limited",
    "wof:placetype":"venue"
},
  "geometry": {"coordinates":[170.491196,-45.896355],"type":"Point"}
}