{
  "type": "Feature",
  "properties": {
    "iso:country":"NZ",
    "sg:address":"4 Browne St Parkside ",
    "sg:city":"Timaru",
    "sg:classifiers":[
        {
            "category":"Professional",
            "subcategory":"Art Services",
            "type":"Services"
        }
    ],
    "sg:phone":"+64 3-684 6727",
    "sg:province":"Canterbury",
    "sg:tags":[
        "personal",
        "photographer",
        "services",
        "garden",
        "home"
    ],
    "wof:name":"Trace Davidson",
    "wof:placetype":"venue"
},
  "geometry": {"coordinates":[171.25457800000001,-44.402775],"type":"Point"}
}