{
  "type": "Feature",
  "properties": {
    "iso:country":"NZ",
    "sg:address":"cnr Te Rapa Straight & Bryant Rd Te Rapa ",
    "sg:city":"Hamilton",
    "sg:classifiers":[
        {
            "category":"Health Services",
            "subcategory":"Clinic",
            "type":"Services"
        }
    ],
    "sg:phone":"+64 7-849 4181",
    "sg:province":"Waikato",
    "sg:tags":[
        "medical",
        "beauty"
    ],
    "wof:name":"St Andrews Medical Centre",
    "wof:placetype":"venue"
},
  "geometry": {"coordinates":[175.239365,-37.752701],"type":"Point"}
}