{
  "type": "Feature",
  "properties": {
    "addr:full":"39 Picton St Howick  Auckland Auckland",
    "addr:housenumber":"39",
    "addr:street":"Picton St",
    "iso:country":"NZ",
    "sg:address":"39 Picton St Howick ",
    "sg:city":"Auckland",
    "sg:classifiers":[
        {
            "category":"Bars & Pubs",
            "subcategory":"Wine Bar",
            "type":"Food & Drink"
        }
    ],
    "sg:phone":"+64 9-534 7917",
    "sg:province":"Auckland",
    "sg:tags":[
        "wining",
        "dining",
        "cafe"
    ],
    "wof:name":"Cafe Paris",
    "wof:placetype":"venue"
},
  "geometry": {"coordinates":[174.93078600000001,-36.893551],"type":"Point"}
}