{
  "type": "Feature",
  "properties": {
    "addr:full":"6 Market Rd Remuera  Auckland Auckland",
    "addr:housenumber":"6",
    "addr:street":"Market Rd",
    "iso:country":"NZ",
    "sg:address":"6 Market Rd Remuera ",
    "sg:city":"Auckland",
    "sg:classifiers":[
        {
            "category":"Arena",
            "subcategory":"Sports Club",
            "type":"Entertainment"
        }
    ],
    "sg:phone":"+64 9-520 2335",
    "sg:province":"Auckland",
    "sg:tags":[
        "-",
        "leisure",
        "sports"
    ],
    "wof:name":"Remuera Bowling Club",
    "wof:placetype":"venue"
},
  "geometry": {"coordinates":[174.789444,-36.879959],"type":"Point"}
}