{
  "type": "Feature",
  "properties": {
    "addr:full":"20 A Huia Rd Otahuhu  Auckland Auckland",
    "addr:housenumber":"20",
    "addr:street":"A Huia Rd",
    "iso:country":"NZ",
    "sg:address":"20 A Huia Rd Otahuhu ",
    "sg:city":"Auckland",
    "sg:orig_category":"Shopping: Gifts: Gemstones And Crystals",
    "sg:phone":"+64 9-270 0773",
    "sg:province":"Auckland",
    "wof:name":"Australasian Diamond Tools (Auckland) Ltd",
    "wof:placetype":"venue"
},
  "geometry": {"coordinates":[174.838303,-36.941109],"type":"Point"}
}