{
  "type": "Feature",
  "properties": {
    "iso:country":"NZ",
    "sg:address":"State Highway 1 Horotiu ",
    "sg:city":"Hamilton",
    "sg:classifiers":[
        {
            "category":"Home & Garden",
            "subcategory":"Building Materials",
            "type":"Retail Goods"
        }
    ],
    "sg:phone":"+64 7-829 9688",
    "sg:province":"Waikato",
    "sg:tags":[
        "fittings",
        "staircase",
        "handrail"
    ],
    "wof:name":"Allwood Manufacturing Ltd",
    "wof:placetype":"venue"
},
  "geometry": {"coordinates":[175.189896,-37.700481],"type":"Point"}
}