{
  "type": "Feature",
  "properties": {
    "addr:full":"80 Karangahape Rd Auckland Central  Auckland Auckland",
    "addr:housenumber":"80",
    "addr:street":"Karangahape Rd",
    "iso:country":"NZ",
    "sg:address":"80 Karangahape Rd Auckland Central ",
    "sg:city":"Auckland",
    "sg:classifiers":[
        {
            "category":"Shopping",
            "subcategory":"Clothing, Apparel, & Fashions",
            "type":"Retail Goods"
        }
    ],
    "sg:phone":"+64 9-366 0209",
    "sg:province":"Auckland",
    "sg:tags":[
        "-",
        "hire",
        "clothing",
        "fabric"
    ],
    "wof:name":"The Tux Shop",
    "wof:placetype":"venue"
},
  "geometry": {"coordinates":[174.76454200000001,-36.848358],"type":"Point"}
}