{
  "type": "Feature",
  "properties": {
    "addr:full":"60 Tay St  Invercargill Southland",
    "addr:housenumber":"60",
    "addr:street":"Tay St",
    "iso:country":"NZ",
    "sg:address":"60 Tay St ",
    "sg:city":"Invercargill",
    "sg:classifiers":[
        {
            "category":"Travel",
            "subcategory":"Travel Agent",
            "type":"Entertainment"
        }
    ],
    "sg:phone":"+64 3-214 4119",
    "sg:province":"Southland",
    "sg:tags":[
        "tourism",
        "broker"
    ],
    "wof:name":"Ray Muir Harvey World Travel",
    "wof:placetype":"venue"
},
  "geometry": {"coordinates":[168.380325,-46.40926],"type":"Point"}
}