{
  "type": "Feature",
  "properties": {
    "iso:country":"NZ",
    "sg:address":"Northern Landfill Johnsonville ",
    "sg:city":"Wellington",
    "sg:orig_category":"Industrial: Services: Drillers",
    "sg:phone":"+64 4-478 4311",
    "sg:province":"Wellington",
    "wof:name":"Dodds Eric Drilling & Earthworks",
    "wof:placetype":"venue"
},
  "geometry": {"coordinates":[174.801788,-41.222324],"type":"Point"}
}