{
  "type": "Feature",
  "properties": {
    "addr:full":"Midway Shopping Centre 4 Nikau Cre Mt  Maunganui Bay of Plenty",
    "addr:housenumber":"4",
    "addr:street":"Nikau Cre;Maunganui Bay",
    "iso:country":"NZ",
    "sg:address":"Midway Shopping Centre 4 Nikau Cre Mt ",
    "sg:city":"Maunganui",
    "sg:classifiers":[
        {
            "category":"Personal",
            "subcategory":"Tanning Parlor",
            "type":"Services"
        }
    ],
    "sg:phone":"+64 7-575 3534",
    "sg:province":"Bay of Plenty",
    "sg:tags":[
        "sun",
        "health",
        "beauty"
    ],
    "wof:name":"Mount Hair Design & Sunbed",
    "wof:placetype":"venue"
},
  "geometry": {"coordinates":[176.18627900000001,-37.641048],"type":"Point"}
}