{
  "type": "Feature",
  "properties": {
    "addr:full":"State Highway 1  Ohaeawai",
    "addr:street":"State Highway 1 Ohaeawai",
    "iso:country":"NZ",
    "sg:address":"State Highway 1 ",
    "sg:city":"Ohaeawai",
    "sg:classifiers":[
        {
            "category":"Building & Trades",
            "subcategory":"Cleaning & Sanitation",
            "type":"Services"
        }
    ],
    "sg:phone":"+64 252885129",
    "sg:tags":[
        "equipment",
        "industrial",
        "maintenance"
    ],
    "wof:name":"Megatrend",
    "wof:placetype":"venue"
},
  "geometry": {"coordinates":[173.882034,-35.351921],"type":"Point"}
}