{
  "type": "Feature",
  "properties": {
    "iso:country":"NZ",
    "sg:address":"Weymouth Rd ",
    "sg:city":"Auckland",
    "sg:orig_category":"Shopping: Retail Stores: Department Stores",
    "sg:phone":"+64 9-267 1830",
    "sg:province":"Auckland",
    "wof:name":"The Warehouse Ltd",
    "wof:placetype":"venue"
},
  "geometry": {"coordinates":[174.863724,-37.04583],"type":"Point"}
}