{
  "type": "Feature",
  "properties": {
    "addr:full":"PO Box 40-256 Upper  Hutt Wellington",
    "addr:housenumber":"po box",
    "addr:street":"40-256 Upper",
    "iso:country":"NZ",
    "sg:address":"PO Box 40-256 Upper ",
    "sg:city":"Hutt",
    "sg:orig_category":"Industrial: Instruments: Scales/Weighing Machines",
    "sg:phone":"+64 25408289",
    "sg:province":"Wellington",
    "wof:name":"ProWeigh Scales",
    "wof:placetype":"venue"
},
  "geometry": {"coordinates":[175.069031,-41.12458],"type":"Point"}
}