{
  "type": "Feature",
  "properties": {
    "iso:country":"NZ",
    "sg:address":"53/2 Grey St ",
    "sg:city":"Tauranga",
    "sg:classifiers":[
        {
            "category":"Shopping",
            "subcategory":"Bridal",
            "type":"Retail Goods"
        }
    ],
    "sg:phone":"+64 7-571 5577",
    "sg:province":"Bay of Plenty",
    "sg:tags":[
        "arrangements",
        "wear",
        "wedding"
    ],
    "wof:name":"Looking Good Bridal & Fashions 2000",
    "wof:placetype":"venue"
},
  "geometry": {"coordinates":[176.168594,-37.684456],"type":"Point"}
}