{
  "type": "Feature",
  "properties": {
    "iso:country":"NZ",
    "sg:address":"115 B Keith St Palmerston ",
    "sg:city":"Palmerston North",
    "sg:classifiers":[
        {
            "category":"Manufacturing",
            "subcategory":"Rubber & Plastics",
            "type":"Manufacturing & Wholesale Goods"
        }
    ],
    "sg:phone":"+64 6-356 8886",
    "sg:province":"Manawatu-Wanganui",
    "sg:tags":[
        "industrial",
        "goods"
    ],
    "wof:name":"Budget Plastic Company Limited",
    "wof:placetype":"venue"
},
  "geometry": {"coordinates":[175.641617,-40.338322],"type":"Point"}
}