{
  "type": "Feature",
  "properties": {
    "iso:country":"NZ",
    "sg:address":"Leeston Rugby Club ",
    "sg:city":"Leeston",
    "sg:classifiers":[
        {
            "category":"Sports & Exercise",
            "subcategory":"Sports Center",
            "type":"Entertainment"
        }
    ],
    "sg:phone":"+64 3-324 3431",
    "sg:tags":[
        "sporting",
        "sports",
        "-",
        "leisure",
        "facility"
    ],
    "wof:name":"Squash Canterbury",
    "wof:placetype":"venue"
},
  "geometry": {"coordinates":[172.298477,-43.76025],"type":"Point"}
}