{
  "type": "Feature",
  "properties": {
    "addr:full":"cnr Nelson Hwy & Conders Bend Rd Renwick  Blenheim Marlborough",
    "addr:street":"Cnr Nelson Hwy & Conders Bend Rd",
    "iso:country":"NZ",
    "sg:address":"cnr Nelson Hwy & Conders Bend Rd Renwick ",
    "sg:city":"Blenheim",
    "sg:orig_category":"Industrial: Equipment And Machinery: Furnaces, Kilns And Ovens: Kilns",
    "sg:phone":"+64 3-572 8168",
    "sg:province":"Marlborough",
    "wof:name":"Dashwood Timber Renwick Ltd",
    "wof:placetype":"venue"
},
  "geometry": {"coordinates":[173.828461,-41.510769],"type":"Point"}
}