{
  "type": "Feature",
  "properties": {
    "addr:full":"184 Dominion  Rd",
    "addr:housenumber":"184",
    "addr:street":"Dominion Rd",
    "iso:country":"NZ",
    "sg:address":"184 Dominion ",
    "sg:city":"Rd",
    "sg:classifiers":[
        {
            "category":"Food & Beverages",
            "subcategory":"Bakery",
            "type":"Retail Goods"
        }
    ],
    "sg:phone":"+64 9-623 1506",
    "sg:tags":[
        "shop",
        "cake",
        "drink",
        "-"
    ],
    "wof:name":"Cheesecake Shop The",
    "wof:placetype":"venue"
},
  "geometry": {"coordinates":[170.36663799999999,-43.587711],"type":"Point"}
}