{
  "type": "Feature",
  "properties": {
    "addr:full":"2 Craddock St Lower Hutt  Wellington Wellington",
    "addr:housenumber":"2",
    "addr:street":"Craddock St",
    "iso:country":"NZ",
    "sg:address":"2 Craddock St Lower Hutt ",
    "sg:city":"Wellington",
    "sg:classifiers":[
        {
            "category":"Utilities",
            "subcategory":"Refuse",
            "type":"Services"
        }
    ],
    "sg:phone":"+64 4-939 3030",
    "sg:province":"Wellington",
    "sg:tags":[
        "bin",
        "hire",
        "garden",
        "cleaning",
        "rubbish",
        "home"
    ],
    "wof:name":"AL's Mini Skips",
    "wof:placetype":"venue"
},
  "geometry": {"coordinates":[174.90838600000001,-41.206631],"type":"Point"}
}