{
  "type": "Feature",
  "properties": {
    "addr:full":"2 Hyde St  Katikati",
    "addr:housenumber":"2",
    "addr:street":"Hyde St",
    "iso:country":"NZ",
    "sg:address":"2 Hyde St ",
    "sg:city":"Katikati",
    "sg:classifiers":[
        {
            "category":"Wholesale",
            "subcategory":"Auto Parts",
            "type":"Manufacturing & Wholesale Goods"
        }
    ],
    "sg:phone":"+64 7-549 4211",
    "sg:tags":[
        "automotive",
        "supplies"
    ],
    "wof:name":"Ajay's Ford V8 Parts",
    "wof:placetype":"venue"
},
  "geometry": {"coordinates":[175.91038499999999,-37.549389],"type":"Point"}
}