{
  "type": "Feature",
  "properties": {
    "addr:full":"66d Seaview Rd Paraparaumu  Wellington Wellington",
    "addr:housenumber":"66d",
    "addr:street":"Seaview Rd",
    "iso:country":"NZ",
    "sg:address":"66d Seaview Rd Paraparaumu ",
    "sg:city":"Wellington",
    "sg:classifiers":[
        {
            "category":"Travel",
            "subcategory":"Hotels & Motels",
            "type":"Entertainment"
        }
    ],
    "sg:phone":"+64 800 638 538",
    "sg:province":"Wellington",
    "sg:tags":[
        "tourism",
        "accommodation"
    ],
    "sg:website":"http://www.yellowpages.co.nz/pages/400019772/dp52883.html",
    "wof:name":"Netlets.tv",
    "wof:placetype":"venue"
},
  "geometry": {"coordinates":[174.979614,-40.896301],"type":"Point"}
}