{
  "type": "Feature",
  "properties": {
    "addr:full":"cnr Ferguson & Fitzherbert Sts Palmerston  Palmerston North Manawatu-Wanganui",
    "addr:street":"Cnr Ferguson & Fitzherbert Sts",
    "iso:country":"NZ",
    "sg:address":"cnr Ferguson & Fitzherbert Sts Palmerston ",
    "sg:city":"Palmerston North",
    "sg:classifiers":[
        {
            "category":"Restaurant",
            "type":"Food & Drink"
        }
    ],
    "sg:phone":"+64 6-355 5571",
    "sg:province":"Manawatu-Wanganui",
    "sg:tags":[
        "wining",
        "dining"
    ],
    "wof:name":"Diablo's-Cafe-Restaurant-Bar",
    "wof:placetype":"venue"
},
  "geometry": {"coordinates":[175.62294,-40.380459],"type":"Point"}
}