{
  "type": "Feature",
  "properties": {
    "addr:full":"1/ 62 Seymour Rd Henderson  Auckland Auckland",
    "addr:housenumber":"1 / 62",
    "addr:street":"Seymour Rd",
    "iso:country":"NZ",
    "sg:address":"1/ 62 Seymour Rd Henderson ",
    "sg:city":"Auckland",
    "sg:classifiers":[
        {
            "category":"Manufacturing",
            "subcategory":"Metals",
            "type":"Manufacturing & Wholesale Goods"
        }
    ],
    "sg:phone":"+64 9-818 3482",
    "sg:province":"Auckland",
    "sg:tags":[
        "-",
        "engineering",
        "industrial",
        "sheet",
        "engineer"
    ],
    "wof:name":"Alloy Metalworx Ltd",
    "wof:placetype":"venue"
},
  "geometry": {"coordinates":[174.63294999999999,-36.877289],"type":"Point"}
}