{
  "type": "Feature",
  "properties": {
    "addr:full":"Tihiroa R D 3  Otorohanga",
    "addr:housenumber":"3",
    "addr:street":"R D",
    "iso:country":"NZ",
    "sg:address":"Tihiroa R D 3 ",
    "sg:city":"Otorohanga",
    "sg:orig_category":"Farming: Horticulture: Flowers",
    "sg:phone":"+64 7-873 7400",
    "wof:name":"Otorohanga Carnations",
    "wof:placetype":"venue"
},
  "geometry": {"coordinates":[175.20764199999999,-38.184097],"type":"Point"}
}