{
  "type": "Feature",
  "properties": {
    "iso:country":"NZ",
    "sg:address":"388 Main South Rd ",
    "sg:city":"Paroa",
    "sg:orig_category":"Farming: Forestry: Forestry Equipment",
    "sg:phone":"+64 3-762 6111",
    "wof:name":"Timberlands West Coast Limited",
    "wof:placetype":"venue"
},
  "geometry": {"coordinates":[176.941101,-37.951817],"type":"Point"}
}