{
  "type": "Feature",
  "properties": {
    "addr:full":"1st Floor 107 Mana Esp Mana  Wellington Wellington",
    "addr:housenumber":"107",
    "iso:country":"NZ",
    "sg:address":"1st Floor 107 Mana Esp Mana ",
    "sg:city":"Wellington",
    "sg:classifiers":[
        {
            "category":"Health Services",
            "subcategory":"Clinic",
            "type":"Services"
        }
    ],
    "sg:phone":"+64 4-233 0680",
    "sg:province":"Wellington",
    "sg:tags":[
        "medical",
        "beauty"
    ],
    "wof:name":"Mana Orthopaedics",
    "wof:placetype":"venue"
},
  "geometry": {"coordinates":[174.86862199999999,-41.09314],"type":"Point"}
}