{
  "type": "Feature",
  "properties": {
    "iso:country":"NZ",
    "sg:address":"46 Porowini Ave ",
    "sg:city":"Whangarei",
    "sg:classifiers":[
        {
            "category":"Home & Garden",
            "subcategory":"Garden Supply",
            "type":"Retail Goods"
        }
    ],
    "sg:phone":"+64 9-438 4839",
    "sg:province":"Northland",
    "sg:tags":[
        "outdoor"
    ],
    "sg:website":"http://www.yellowpages.co.nz/for/mcbreenjenkins/dp11340.html",
    "wof:name":"McBreen Jenkins Construction Limited",
    "wof:placetype":"venue"
},
  "geometry": {"coordinates":[174.32167100000001,-35.732307],"type":"Point"}
}