{
  "type": "Feature",
  "properties": {
    "iso:country":"NZ",
    "sg:address":"60 Onslow St ",
    "sg:city":"Kawerau",
    "sg:orig_category":"Home And Garden: Gardening: Services: Garden Maintenance",
    "sg:phone":"+64 25976862",
    "wof:name":"Dean Gardening Service",
    "wof:placetype":"venue"
},
  "geometry": {"coordinates":[176.70047,-38.092461],"type":"Point"}
}