{
  "type": "Feature",
  "properties": {
    "iso:country":"NZ",
    "sg:address":"111 Rockinghorse Rd Southshore ",
    "sg:city":"Christchurch",
    "sg:orig_category":"Home And Garden: Gardening: Services: Garden Maintenance",
    "sg:phone":"+64 3-382 1958",
    "sg:province":"Canterbury",
    "wof:name":"Ace Garden Services",
    "wof:placetype":"venue"
},
  "geometry": {"coordinates":[172.74655200000001,-43.547768],"type":"Point"}
}