{
  "type": "Feature",
  "properties": {
    "addr:full":"11 a Wicklow Rd Devonport  Auckland Auckland",
    "addr:housenumber":"11 a",
    "addr:street":"Wicklow Rd",
    "iso:country":"NZ",
    "sg:address":"11 a Wicklow Rd Devonport ",
    "sg:city":"Auckland",
    "sg:orig_category":"Sports And Leisure: Hobbies: Calligraphy",
    "sg:phone":"+64 9-445 9122",
    "sg:province":"Auckland",
    "wof:name":"Margaret Woollett Calligrapher",
    "wof:placetype":"venue"
},
  "geometry": {"coordinates":[174.79956100000001,-36.824425],"type":"Point"}
}