{
  "type": "Feature",
  "properties": {
    "addr:full":"253 Selwyn St  Timaru Canterbury",
    "addr:housenumber":"253",
    "addr:street":"Selwyn St",
    "iso:country":"NZ",
    "sg:address":"253 Selwyn St ",
    "sg:city":"Timaru",
    "sg:classifiers":[
        {
            "category":"Social Services",
            "subcategory":"Child Care",
            "type":"Services"
        }
    ],
    "sg:phone":"+64 3-684 4469",
    "sg:province":"Canterbury",
    "sg:tags":[
        "home",
        "garden",
        "children"
    ],
    "wof:name":"South Canterbury Free Kindergarten Association",
    "wof:placetype":"venue"
},
  "geometry": {"coordinates":[171.22970599999999,-44.379074],"type":"Point"}
}