{
  "type": "Feature",
  "properties": {
    "addr:full":"23 Wastney Tce Atawhai  Nelson Nelson",
    "addr:housenumber":"23",
    "addr:street":"Wastney Tce Atawhai",
    "iso:country":"NZ",
    "sg:address":"23 Wastney Tce Atawhai ",
    "sg:city":"Nelson",
    "sg:classifiers":[
        {
            "category":"Travel",
            "subcategory":"Hotels & Motels",
            "type":"Entertainment"
        }
    ],
    "sg:phone":"+64 3-545 0869",
    "sg:province":"Nelson",
    "sg:tags":[
        "tourism",
        "-",
        "rental",
        "accommodation"
    ],
    "sg:website":"http://www.harrishillcottages.co.nz",
    "wof:name":"Harris Hill Cottages",
    "wof:placetype":"venue"
},
  "geometry": {"coordinates":[173.316666,-41.237453],"type":"Point"}
}