{
  "type": "Feature",
  "properties": {
    "iso:country":"NZ",
    "sg:address":"398 Main South Rd Hornby ",
    "sg:city":"Christchurch",
    "sg:classifiers":[
        {
            "category":"Manufacturing",
            "subcategory":"Textiles",
            "type":"Manufacturing & Wholesale Goods"
        }
    ],
    "sg:phone":"+64 3-344 1407",
    "sg:province":"Canterbury",
    "sg:tags":[
        "clothing",
        "fabric",
        "manufacturer"
    ],
    "wof:name":"Pagani",
    "wof:placetype":"venue"
},
  "geometry": {"coordinates":[172.526611,-43.543209],"type":"Point"}
}