{
  "type": "Feature",
  "properties": {
    "iso:country":"NZ",
    "sg:address":"cnr George & London Sts ",
    "sg:city":"Dunedin",
    "sg:orig_category":"Home And Garden: General",
    "sg:phone":"+64 3-477 0312",
    "sg:province":"Otago",
    "sg:website":"http://www.the-professionals.co.nz",
    "wof:name":"Fisken & Associates Ltd MREINZ",
    "wof:placetype":"venue"
},
  "geometry": {"coordinates":[-82.784729,28.013371],"type":"Point"}
}