{
  "type": "Feature",
  "properties": {
    "addr:full":"Claudelands Rd  Hamilton Waikato",
    "addr:street":"Claudelands Rd",
    "iso:country":"NZ",
    "sg:address":"Claudelands Rd ",
    "sg:city":"Hamilton",
    "sg:orig_category":"Sports And Leisure: General: Clubs",
    "sg:phone":"+64 7-855 2001",
    "sg:province":"Waikato",
    "wof:name":"Hamilton Cosmopolitan Club Inc",
    "wof:placetype":"venue"
},
  "geometry": {"coordinates":[175.286575,-37.777809],"type":"Point"}
}