{
  "type": "Feature",
  "properties": {
    "iso:country":"NZ",
    "sg:address":"1267 Tutanekai St ",
    "sg:city":"Rotorua",
    "sg:orig_category":"Shopping: Retail Stores: Cds, Cassettes And Records",
    "sg:phone":"+64 7-348 4257",
    "sg:province":"Bay of Plenty",
    "wof:name":"Sounds Music Store",
    "wof:placetype":"venue"
},
  "geometry": {"coordinates":[176.251434,-38.13839],"type":"Point"}
}