{
  "type": "Feature",
  "properties": {
    "addr:full":"61 Thames St  Oamaru Otago",
    "addr:housenumber":"61",
    "addr:street":"Thames St",
    "iso:country":"NZ",
    "sg:address":"61 Thames St ",
    "sg:city":"Oamaru",
    "sg:classifiers":[
        {
            "category":"Travel",
            "subcategory":"Travel Agent",
            "type":"Entertainment"
        }
    ],
    "sg:phone":"+64 3-434 9960",
    "sg:province":"Otago",
    "sg:tags":[
        "tourism",
        "broker"
    ],
    "wof:name":"House Of Travel Oamaru",
    "wof:placetype":"venue"
},
  "geometry": {"coordinates":[170.97009299999999,-45.099911],"type":"Point"}
}