{
  "type": "Feature",
  "properties": {
    "addr:full":"Unit 4/15 Trugood Dve East Tamaki  Auckland Auckland",
    "addr:housenumber":"unit 4 / 15",
    "addr:street":"Dve",
    "iso:country":"NZ",
    "sg:address":"Unit 4/15 Trugood Dve East Tamaki ",
    "sg:city":"Auckland",
    "sg:orig_category":"Shopping: Retail Stores: Batteries",
    "sg:phone":"+64 9-274 1904",
    "sg:province":"Auckland",
    "wof:name":"Battery Doctor - Simpower",
    "wof:placetype":"venue"
},
  "geometry": {"coordinates":[174.891525,-36.928001],"type":"Point"}
}