{
  "type": "Feature",
  "properties": {
    "iso:country":"NZ",
    "sg:address":"63 Main St ",
    "sg:city":"Gore",
    "sg:classifiers":[
        {
            "category":"Sports & Exercise",
            "subcategory":"Ski Resort",
            "type":"Entertainment"
        }
    ],
    "sg:phone":"+64 3-208 0675",
    "sg:province":"Southland",
    "sg:tags":[
        "hobbies",
        "photographic",
        "leisure",
        "developing"
    ],
    "wof:name":"Kodak Express",
    "wof:placetype":"venue"
},
  "geometry": {"coordinates":[-95.117569,35.52932],"type":"Point"}
}