{
  "type": "Feature",
  "properties": {
    "iso:country":"NZ",
    "sg:address":"Goldfields Shopping Centre Mary St ",
    "sg:city":"Thames",
    "sg:orig_category":"Home And Garden: Gardening: Products",
    "sg:phone":"+64 7-867 9026",
    "sg:province":"Auckland",
    "wof:name":"Paki Paki Bike Shop",
    "wof:placetype":"venue"
},
  "geometry": {"coordinates":[151.699219,-28.449089],"type":"Point"}
}