{
  "type": "Feature",
  "properties": {
    "addr:full":"PO Box 319  Cambridge Waikato",
    "addr:housenumber":"po",
    "addr:street":"Box 319",
    "iso:country":"NZ",
    "sg:address":"PO Box 319 ",
    "sg:city":"Cambridge",
    "sg:orig_category":"Industrial: Services: Drillers",
    "sg:phone":"+64 7-827 5200",
    "sg:province":"Waikato",
    "wof:name":"Berry Drilling Co Ltd",
    "wof:placetype":"venue"
},
  "geometry": {"coordinates":[175.47131300000001,-37.893063],"type":"Point"}
}