{
  "type": "Feature",
  "properties": {
    "iso:country":"NZ",
    "sg:address":"53 Third Ave Kingsland ",
    "sg:city":"Auckland",
    "sg:orig_category":"Sports And Leisure: Entertainment: Entertainers",
    "sg:phone":"+64 9-846 6495",
    "sg:province":"Auckland",
    "wof:name":"On The Spot Productions",
    "wof:placetype":"venue"
},
  "geometry": {"coordinates":[174.73954800000001,-36.87059],"type":"Point"}
}