{
  "type": "Feature",
  "properties": {
    "iso:country":"NZ",
    "sg:address":"169 Seaview Rd New ",
    "sg:city":"Plymouth",
    "sg:orig_category":"Transport: Transportation: Furniture Removal/Packers",
    "sg:phone":"+64 6-753 9169",
    "sg:province":"Taranaki",
    "wof:name":"M & M Movers",
    "wof:placetype":"venue"
},
  "geometry": {"coordinates":[-70.536819,41.893913],"type":"Point"}
}