{
  "type": "Feature",
  "properties": {
    "addr:full":"468 High St Lower Hutt  Wellington Wellington",
    "addr:housenumber":"468",
    "addr:street":"High St",
    "iso:country":"NZ",
    "sg:address":"468 High St Lower Hutt ",
    "sg:city":"Wellington",
    "sg:classifiers":[
        {
            "category":"Home & Garden",
            "subcategory":"Hardware",
            "type":"Retail Goods"
        }
    ],
    "sg:phone":"+64 4-586 3535",
    "sg:province":"Wellington",
    "sg:tags":[
        "water",
        "heater",
        "fittings"
    ],
    "wof:name":"Gas Centre The",
    "wof:placetype":"venue"
},
  "geometry": {"coordinates":[174.91137699999999,-41.205437],"type":"Point"}
}