{
  "type": "Feature",
  "properties": {
    "addr:full":"427 Gt South Rd Papatoetoe  Auckland Auckland",
    "addr:housenumber":"427",
    "addr:street":"Gt South Rd",
    "iso:country":"NZ",
    "sg:address":"427 Gt South Rd Papatoetoe ",
    "sg:city":"Auckland",
    "sg:classifiers":[
        {
            "category":"Banks & Credit Unions",
            "subcategory":"Financial Services",
            "type":"Services"
        }
    ],
    "sg:phone":"+64 9-279 3009",
    "sg:province":"Auckland",
    "sg:tags":[
        "personal",
        "loan",
        "-",
        "finance",
        "mortgage"
    ],
    "wof:name":"Monk B J",
    "wof:placetype":"venue"
},
  "geometry": {"coordinates":[174.86700400000001,-36.976124],"type":"Point"}
}