{
  "type": "Feature",
  "properties": {
    "addr:full":"222 a Manukau Rd  Pukekohe Auckland",
    "addr:housenumber":"222 a",
    "addr:street":"Manukau Rd",
    "iso:country":"NZ",
    "sg:address":"222 a Manukau Rd ",
    "sg:city":"Pukekohe",
    "sg:orig_category":"Farming: Supplies: Farm Buildings",
    "sg:phone":"+64 9-238 0696",
    "sg:province":"Auckland",
    "wof:name":"Versatile Buildings",
    "wof:placetype":"venue"
},
  "geometry": {"coordinates":[174.930252,-37.195728],"type":"Point"}
}