{
  "type": "Feature",
  "properties": {
    "addr:full":"Frankton Indust Est PO Box 712  Queenstown Waikato",
    "addr:housenumber":"box 712",
    "addr:street":"Indust",
    "iso:country":"NZ",
    "sg:address":"Frankton Indust Est PO Box 712 ",
    "sg:city":"Queenstown",
    "sg:classifiers":[
        {
            "category":"Home & Garden",
            "subcategory":"Building Materials",
            "type":"Retail Goods"
        }
    ],
    "sg:phone":"+64 3-442 3620",
    "sg:province":"Waikato",
    "sg:tags":[
        "related"
    ],
    "sg:website":"http://www.hotwater.net.nz/queenstown.html",
    "wof:name":"Walker & Barnes Plumbing Ltd",
    "wof:placetype":"venue"
},
  "geometry": {"coordinates":[168.66325399999999,-45.031445],"type":"Point"}
}