{
  "type": "Feature",
  "properties": {
    "addr:full":"Broadway Centre Newmarket  Auckland Manawatu-Wanganui",
    "addr:street":"Broadway",
    "iso:country":"NZ",
    "sg:address":"Broadway Centre Newmarket ",
    "sg:city":"Auckland",
    "sg:classifiers":[
        {
            "category":"Travel",
            "subcategory":"Travel Agent",
            "type":"Entertainment"
        }
    ],
    "sg:phone":"+64 9-520 3972",
    "sg:province":"Manawatu-Wanganui",
    "sg:tags":[
        "good",
        "tourism"
    ],
    "wof:name":"Strandbags",
    "wof:placetype":"venue"
},
  "geometry": {"coordinates":[174.77702300000001,-36.872337],"type":"Point"}
}