{
  "type": "Feature",
  "properties": {
    "iso:country":"NZ",
    "sg:address":"123 Great North Rd ",
    "sg:city":"Wanganui",
    "sg:classifiers":[
        {
            "category":"Personal",
            "type":"Services"
        }
    ],
    "sg:phone":"+64 6-345 1936",
    "sg:province":"Manawatu-Wanganui",
    "sg:tags":[
        "celebrant",
        "arrangements",
        "marriage",
        "wedding"
    ],
    "wof:name":"Spurdle Mrs J A JP",
    "wof:placetype":"venue"
},
  "geometry": {"coordinates":[175.02616900000001,-39.913803],"type":"Point"}
}