{
  "type": "Feature",
  "properties": {
    "iso:country":"NZ",
    "sg:address":"85 Market St ",
    "sg:city":"Blenheim",
    "sg:classifiers":[
        {
            "category":"Shopping",
            "subcategory":"Gifts & Souvenirs",
            "type":"Retail Goods"
        }
    ],
    "sg:phone":"+64 3-578 4776",
    "sg:province":"Marlborough",
    "sg:tags":[
        "shop",
        "gifts",
        "supplier"
    ],
    "wof:name":"Just $2 Store",
    "wof:placetype":"venue"
},
  "geometry": {"coordinates":[-74.459564,42.468643],"type":"Point"}
}