{
  "type": "Feature",
  "properties": {
    "addr:full":"Village Cen Waikanae  Paraparaumu Wellington",
    "iso:country":"NZ",
    "sg:address":"Village Cen Waikanae ",
    "sg:city":"Paraparaumu",
    "sg:classifiers":[
        {
            "category":"Food & Beverages",
            "subcategory":"Bakery",
            "type":"Retail Goods"
        }
    ],
    "sg:phone":"+64 9025009",
    "sg:province":"Wellington",
    "sg:tags":[
        "shop",
        "cake",
        "drink",
        "-"
    ],
    "wof:name":"Tulip Cake & Bread Shop",
    "wof:placetype":"venue"
},
  "geometry": {"coordinates":[175.06100499999999,-40.87318],"type":"Point"}
}