{
  "type": "Feature",
  "properties": {
    "addr:full":"112 Hazeldean Rd Sydenham  Christchurch Canterbury",
    "addr:housenumber":"112",
    "addr:street":"Hazeldean Rd",
    "iso:country":"NZ",
    "sg:address":"112 Hazeldean Rd Sydenham ",
    "sg:city":"Christchurch",
    "sg:orig_category":"Industrial: Metal",
    "sg:phone":"+64 3-365 7136",
    "sg:province":"Canterbury",
    "wof:name":"East Coast Steelwork Ltd",
    "wof:placetype":"venue"
},
  "geometry": {"coordinates":[172.627914,-43.54118],"type":"Point"}
}