{
  "type": "Feature",
  "properties": {
    "iso:country":"NZ",
    "sg:address":"960 Gt South Rd Penrose ",
    "sg:city":"Auckland",
    "sg:orig_category":"Industrial: Services",
    "sg:phone":"+64 9-579 1599",
    "sg:province":"Auckland",
    "sg:website":"http://www.yellowpages.co.nz/for/mpw/dp17342.html",
    "wof:name":"Machine Part Welding Ltd",
    "wof:placetype":"venue"
},
  "geometry": {"coordinates":[174.827393,-36.919865],"type":"Point"}
}