{
  "type": "Feature",
  "properties": {
    "iso:country":"NZ",
    "sg:address":"32 Vogel St Naenae Lower ",
    "sg:city":"Hutt",
    "sg:classifiers":[
        {
            "category":"Professional",
            "subcategory":"Engineering",
            "type":"Services"
        }
    ],
    "sg:phone":"+64 800 737 363",
    "sg:province":"Wellington",
    "sg:tags":[
        "industrial"
    ],
    "sg:website":"http://www.yellowpages.co.nz/pages/108096386/dp42564.html",
    "wof:name":"Resene Paints Ltd",
    "wof:placetype":"venue"
},
  "geometry": {"coordinates":[174.947632,-41.201092],"type":"Point"}
}