{
  "type": "Feature",
  "properties": {
    "addr:full":"10 Woodhouse St Kew  Invercargill Southland",
    "addr:housenumber":"10",
    "addr:street":"Woodhouse St",
    "iso:country":"NZ",
    "sg:address":"10 Woodhouse St Kew ",
    "sg:city":"Invercargill",
    "sg:classifiers":[
        {
            "category":"Recreation",
            "type":"Entertainment"
        }
    ],
    "sg:phone":"+64 3-214 5468",
    "sg:province":"Southland",
    "sg:tags":[
        "sport",
        "leisure"
    ],
    "sg:website":"http://www.users.atrix.co.nz/djservices/",
    "wof:name":"Independent DJ Services",
    "wof:placetype":"venue"
},
  "geometry": {"coordinates":[168.351654,-46.430729],"type":"Point"}
}