{
  "type": "Feature",
  "properties": {
    "addr:full":"18 Morrow St Newmarket  Auckland Auckland",
    "addr:housenumber":"18",
    "addr:street":"Morrow St",
    "iso:country":"NZ",
    "sg:address":"18 Morrow St Newmarket ",
    "sg:city":"Auckland",
    "sg:orig_category":"Health And Beauty: Dental: Dentists",
    "sg:phone":"+64 9-524 8399",
    "sg:province":"Auckland",
    "wof:name":"Neumann P",
    "wof:placetype":"venue"
},
  "geometry": {"coordinates":[174.775925,-36.870098],"type":"Point"}
}