{
  "type": "Feature",
  "properties": {
    "iso:country":"NZ",
    "sg:address":"Redwood ",
    "sg:city":"Christchurch",
    "sg:classifiers":[
        {
            "category":"Shopping",
            "subcategory":"Discount & Variety Stores",
            "type":"Retail Goods"
        }
    ],
    "sg:phone":"+64 3-352 9080",
    "sg:province":"Canterbury",
    "sg:tags":[
        "storage",
        "cool"
    ],
    "wof:name":"Cranford Cool Stores",
    "wof:placetype":"venue"
},
  "geometry": {"coordinates":[172.62553399999999,-43.467388],"type":"Point"}
}