{
  "type": "Feature",
  "properties": {
    "addr:full":"110 Wairau Rd Takapuna  Auckland Auckland",
    "addr:housenumber":"110",
    "addr:street":"Wairau Rd",
    "iso:country":"NZ",
    "sg:address":"110 Wairau Rd Takapuna ",
    "sg:city":"Auckland",
    "sg:classifiers":[
        {
            "category":"Banks & Credit Unions",
            "subcategory":"Financial Services",
            "type":"Services"
        }
    ],
    "sg:phone":"+64 9-489 8414",
    "sg:province":"Auckland",
    "sg:tags":[
        "finance"
    ],
    "sg:website":"http://www.yellowpages.co.nz/pages/202358985/dp42883.html",
    "wof:name":"Loan Plan Group",
    "wof:placetype":"venue"
},
  "geometry": {"coordinates":[174.76788300000001,-36.787838],"type":"Point"}
}