{
  "type": "Feature",
  "properties": {
    "iso:country":"NZ",
    "sg:address":"225 Papanui Rd Merivale ",
    "sg:city":"Christchurch",
    "sg:classifiers":[
        {
            "category":"Shopping",
            "subcategory":"Bridal",
            "type":"Retail Goods"
        }
    ],
    "sg:phone":"+64 3-355 1125",
    "sg:province":"Canterbury",
    "sg:tags":[
        "arrangements",
        "wear",
        "wedding"
    ],
    "wof:name":"Brides Of Merivale",
    "wof:placetype":"venue"
},
  "geometry": {"coordinates":[172.620758,-43.514442],"type":"Point"}
}