{
  "type": "Feature",
  "properties": {
    "addr:full":"37 Totara St Mt Maunganui  Tauranga Auckland",
    "addr:housenumber":"37",
    "addr:street":"Totara St",
    "iso:country":"NZ",
    "sg:address":"37 Totara St Mt Maunganui ",
    "sg:city":"Tauranga",
    "sg:classifiers":[
        {
            "category":"Building & Trades",
            "subcategory":"Cleaning & Sanitation",
            "type":"Services"
        }
    ],
    "sg:phone":"+64 800 223 826",
    "sg:province":"Auckland",
    "sg:tags":[
        "equipment",
        "industrial",
        "maintenance"
    ],
    "wof:name":"Advance International Cleaning Systems (NZ) Ltd",
    "wof:placetype":"venue"
},
  "geometry": {"coordinates":[176.186432,-37.645863],"type":"Point"}
}