{
  "type": "Feature",
  "properties": {
    "iso:country":"NZ",
    "sg:address":"107 Nelson St Petone ",
    "sg:city":"Wellington",
    "sg:orig_category":"Industrial: Equipment And Machinery: Generators",
    "sg:phone":"+64 4-939 8586",
    "sg:province":"Wellington",
    "wof:name":"VM Diesels (NZ) Ltd",
    "wof:placetype":"venue"
},
  "geometry": {"coordinates":[174.878738,-41.220974],"type":"Point"}
}