{
  "type": "Feature",
  "properties": {
    "addr:full":"95 Regent St  Martinborough",
    "addr:housenumber":"95",
    "addr:street":"Regent St",
    "iso:country":"NZ",
    "sg:address":"95 Regent St ",
    "sg:city":"Martinborough",
    "sg:classifiers":[
        {
            "category":"Home & Garden",
            "subcategory":"Building Materials",
            "type":"Retail Goods"
        }
    ],
    "sg:phone":"+64 6-306 9539",
    "sg:tags":[
        "electrician",
        "related"
    ],
    "wof:name":"Bush Ray & Sue",
    "wof:placetype":"venue"
},
  "geometry": {"coordinates":[175.457031,-41.22546],"type":"Point"}
}