{
  "type": "Feature",
  "properties": {
    "iso:country":"NZ",
    "sg:address":"29 Waverley Ave Glenfield ",
    "sg:city":"Auckland",
    "sg:orig_category":"Home And Garden: General: Handyman'S Services",
    "sg:phone":"+64 9-443 3966",
    "sg:province":"Auckland",
    "wof:name":"Jim's Property Maintenance Ltd",
    "wof:placetype":"venue"
},
  "geometry": {"coordinates":[174.71641500000001,-36.782639],"type":"Point"}
}