{
  "type": "Feature",
  "properties": {
    "iso:country":"NZ",
    "sg:address":"955 Ferry Rd Woolston ",
    "sg:city":"Christchurch",
    "sg:classifiers":[
        {
            "category":"Retail",
            "subcategory":"Laundry & Dry Cleaning",
            "type":"Services"
        }
    ],
    "sg:phone":"+64 3-384 5015",
    "sg:province":"Canterbury",
    "sg:tags":[
        "repair",
        "clothing",
        "fabric"
    ],
    "wof:name":"Ferrymead Drycleaners & Launderers",
    "wof:placetype":"venue"
},
  "geometry": {"coordinates":[172.690475,-43.55315],"type":"Point"}
}