{
  "type": "Feature",
  "properties": {
    "addr:full":"84 The Terrace Herald Island  Auckland Waikato",
    "addr:housenumber":"84",
    "addr:street":"The Terrace Herald",
    "iso:country":"NZ",
    "sg:address":"84 The Terrace Herald Island ",
    "sg:city":"Auckland",
    "sg:classifiers":[
        {
            "category":"Travel",
            "subcategory":"Bed & Breakfast",
            "type":"Entertainment"
        }
    ],
    "sg:phone":"+64 9-416 7553",
    "sg:province":"Waikato",
    "sg:tags":[
        "tourism",
        "accommodation"
    ],
    "wof:name":"Pratt L L & B J",
    "wof:placetype":"venue"
},
  "geometry": {"coordinates":[174.65821800000001,-36.777882],"type":"Point"}
}