{
  "type": "Feature",
  "properties": {
    "addr:full":"99 Copeland St Lower  Hutt Wellington",
    "addr:housenumber":"99",
    "addr:street":"Copeland St",
    "iso:country":"NZ",
    "sg:address":"99 Copeland St Lower ",
    "sg:city":"Hutt",
    "sg:classifiers":[
        {
            "category":"Restaurant",
            "type":"Food & Drink"
        }
    ],
    "sg:phone":"+64 4-567 3868",
    "sg:province":"Wellington",
    "sg:tags":[
        "merchant",
        "fish",
        "sea"
    ],
    "wof:name":"Sang Fay Takeaways",
    "wof:placetype":"venue"
},
  "geometry": {"coordinates":[174.904526,-41.208431],"type":"Point"}
}