{
  "type": "Feature",
  "properties": {
    "iso:country":"NZ",
    "sg:address":"27 Cornish St Petone Lower ",
    "sg:city":"Hutt",
    "sg:classifiers":[
        {
            "category":"Manufacturing",
            "subcategory":"Metals",
            "type":"Manufacturing & Wholesale Goods"
        }
    ],
    "sg:phone":"+64 4-568 8034",
    "sg:province":"Wellington",
    "sg:tags":[
        "-",
        "engineering",
        "industrial",
        "sheet",
        "engineer"
    ],
    "wof:name":"Contherm Scientific Ltd",
    "wof:placetype":"venue"
},
  "geometry": {"coordinates":[174.87507600000001,-41.221291],"type":"Point"}
}