{
  "type": "Feature",
  "properties": {
    "iso:country":"NZ",
    "sg:address":"61 Port Rd Seaview Lower ",
    "sg:city":"Hutt",
    "sg:orig_category":"Home And Garden",
    "sg:phone":"+64 4-568 2324",
    "sg:province":"Wellington",
    "sg:website":"http://www.yellowpages.co.nz/pages/108086817/dp43543.html",
    "wof:name":"New Zealand Van Lines Ltd",
    "wof:placetype":"venue"
},
  "geometry": {"coordinates":[174.90142800000001,-41.241081],"type":"Point"}
}