{
  "type": "Feature",
  "properties": {
    "addr:full":"Shop 40 Queens Arcade 15 Customs St E Auckland City Auckland Wellington",
    "addr:housenumber":"40;15",
    "addr:street":"Queens;Customs St E Auckland",
    "iso:country":"NZ",
    "sg:address":"Shop 40 Queens Arcade 15 Customs St E Auckland City",
    "sg:city":"Auckland",
    "sg:classifiers":[
        {
            "category":"Personal",
            "subcategory":"Shoe Repair & Shine",
            "type":"Services"
        }
    ],
    "sg:phone":"+64 9-373 5664",
    "sg:province":"Wellington",
    "sg:tags":[
        "foot",
        "clothing",
        "fabric",
        "wear"
    ],
    "wof:name":"Mistry's Shoe Repairs",
    "wof:placetype":"venue"
},
  "geometry": {"coordinates":[174.78450000000001,-37.006058],"type":"Point"}
}