{
  "type": "Feature",
  "properties": {
    "addr:full":"9 Gunn St Te  Anau Southland",
    "addr:housenumber":"9",
    "addr:street":"Gunn St",
    "iso:country":"NZ",
    "sg:address":"9 Gunn St Te ",
    "sg:city":"Anau",
    "sg:classifiers":[
        {
            "category":"Social Services",
            "subcategory":"Child Care",
            "type":"Services"
        }
    ],
    "sg:phone":"+64 3-249 7585",
    "sg:province":"Southland",
    "sg:tags":[
        "home",
        "garden",
        "children"
    ],
    "wof:name":"Southland Kindergarten Association",
    "wof:placetype":"venue"
},
  "geometry": {"coordinates":[167.717804,-45.410774],"type":"Point"}
}