{
  "type": "Feature",
  "properties": {
    "addr:full":"263 Ara-Kotinga Rd Whitford  Auckland Auckland",
    "addr:housenumber":"263",
    "addr:street":"Ara-Kotinga Rd",
    "iso:country":"NZ",
    "sg:address":"263 Ara-Kotinga Rd Whitford ",
    "sg:city":"Auckland",
    "sg:orig_category":"Sports And Leisure: Sports: Equestrian: Horse Floats",
    "sg:phone":"+64 9-530 9071",
    "sg:province":"Auckland",
    "wof:name":"Gould S F",
    "wof:placetype":"venue"
},
  "geometry": {"coordinates":[174.96301299999999,-36.944344],"type":"Point"}
}