{
  "type": "Feature",
  "properties": {
    "iso:country":"NZ",
    "sg:address":"University of Waikato ",
    "sg:city":"Hamilton",
    "sg:classifiers":[
        {
            "category":"Professional",
            "subcategory":"Art Services",
            "type":"Services"
        }
    ],
    "sg:phone":"+64 7-838 4044",
    "sg:province":"Waikato",
    "sg:tags":[
        "personal",
        "photographer",
        "services",
        "garden",
        "home"
    ],
    "wof:name":"Campus Photography",
    "wof:placetype":"venue"
},
  "geometry": {"coordinates":[175.318558,-37.789661],"type":"Point"}
}