{
  "type": "Feature",
  "properties": {
    "addr:full":"85 Normanby St  Dargaville Northland",
    "addr:housenumber":"85",
    "addr:street":"Normanby St",
    "iso:country":"NZ",
    "sg:address":"85 Normanby St ",
    "sg:city":"Dargaville",
    "sg:classifiers":[
        {
            "category":"Autos & Motor Vehicles",
            "subcategory":"Motorcycle Sales",
            "type":"Retail Goods"
        }
    ],
    "sg:phone":"+64 9-439 7166",
    "sg:province":"Northland",
    "sg:tags":[
        "automotive",
        "scooter",
        "leasing"
    ],
    "wof:name":"AgTech Industries",
    "wof:placetype":"venue"
},
  "geometry": {"coordinates":[173.872986,-35.937576],"type":"Point"}
}