{
  "type": "Feature",
  "properties": {
    "addr:full":"Bollard Rd Tuakau  Pukekohe Auckland",
    "addr:street":"Bollard Rd",
    "iso:country":"NZ",
    "sg:address":"Bollard Rd Tuakau ",
    "sg:city":"Pukekohe",
    "sg:orig_category":"Industrial: Products: Poles",
    "sg:phone":"+64 9-236 8880",
    "sg:province":"Auckland",
    "wof:name":"Tuakau Timber Treatment Ltd",
    "wof:placetype":"venue"
},
  "geometry": {"coordinates":[174.95979299999999,-37.267349],"type":"Point"}
}