{
  "type": "Feature",
  "properties": {
    "iso:country":"NZ",
    "sg:address":"State Highway 99 Lorneville ",
    "sg:city":"Invercargill",
    "sg:classifiers":[
        {
            "category":"Restaurant",
            "type":"Food & Drink"
        }
    ],
    "sg:phone":"+64 3-235 8116",
    "sg:province":"Southland",
    "sg:tags":[
        "wining",
        "dining"
    ],
    "wof:name":"Tin Shed Cafe & Bar",
    "wof:placetype":"venue"
},
  "geometry": {"coordinates":[168.34223900000001,-46.344158],"type":"Point"}
}