{
  "type": "Feature",
  "properties": {
    "iso:country":"NZ",
    "sg:address":"190 Connett Rd Bell Block New ",
    "sg:city":"Plymouth",
    "sg:orig_category":"Automotive: Servicing And Repair: Car Trimming/Upholstery",
    "sg:phone":"+64 6-755 4139",
    "sg:province":"Taranaki",
    "wof:name":"Steve Paul A2Z Contracting",
    "wof:placetype":"venue"
},
  "geometry": {"coordinates":[174.14274599999999,-39.032024],"type":"Point"}
}