{
  "type": "Feature",
  "properties": {
    "addr:full":"60 Parnell Rd Parnell  Auckland Auckland",
    "addr:housenumber":"60",
    "addr:street":"Parnell Rd",
    "iso:country":"NZ",
    "sg:address":"60 Parnell Rd Parnell ",
    "sg:city":"Auckland",
    "sg:classifiers":[
        {
            "category":"Home & Garden",
            "subcategory":"Furniture",
            "type":"Retail Goods"
        }
    ],
    "sg:phone":"+64 9-303 4493",
    "sg:province":"Auckland",
    "sg:tags":[
        "furniture/furnishings",
        "furnishing"
    ],
    "wof:name":"Metadesign Ltd",
    "wof:placetype":"venue"
},
  "geometry": {"coordinates":[174.77836600000001,-36.851963],"type":"Point"}
}