{
  "type": "Feature",
  "properties": {
    "addr:full":"96 Victoria St  Christchurch Canterbury",
    "addr:housenumber":"96",
    "addr:street":"Victoria St",
    "iso:country":"NZ",
    "sg:address":"96 Victoria St ",
    "sg:city":"Christchurch",
    "sg:classifiers":[
        {
            "category":"Shopping",
            "subcategory":"Crafts & Fabrics",
            "type":"Retail Goods"
        }
    ],
    "sg:phone":"+64 3-379 4767",
    "sg:province":"Canterbury",
    "sg:tags":[
        "clothing"
    ],
    "sg:website":"http://www.yellowpages.co.nz/for/thehatshop/dp57183.html",
    "wof:name":"The Hat Shop",
    "wof:placetype":"venue"
},
  "geometry": {"coordinates":[172.630188,-43.523582],"type":"Point"}
}