{
  "type": "Feature",
  "properties": {
    "addr:full":"59 Essex St  Balclutha",
    "addr:housenumber":"59",
    "addr:street":"Essex St",
    "iso:country":"NZ",
    "sg:address":"59 Essex St ",
    "sg:city":"Balclutha",
    "sg:orig_category":"Industrial: Metal: Products: Aluminium Products",
    "sg:phone":"+64 3-418 1390",
    "wof:name":"North End Joinery Company Ltd",
    "wof:placetype":"venue"
},
  "geometry": {"coordinates":[169.75735499999999,-46.229843],"type":"Point"}
}