{
  "type": "Feature",
  "properties": {
    "iso:country":"NZ",
    "sg:address":"Kakanui R D 5-0 Oamaru ",
    "sg:city":"Maheno",
    "sg:classifiers":[
        {
            "category":"Home & Garden",
            "subcategory":"Garden Supply",
            "type":"Retail Goods"
        }
    ],
    "sg:phone":"+64 3-439 5866",
    "sg:tags":[
        "products",
        "nursery",
        "gardening"
    ],
    "wof:name":"Riverview Growers",
    "wof:placetype":"venue"
},
  "geometry": {"coordinates":[170.836319,-45.165764],"type":"Point"}
}