{
  "type": "Feature",
  "properties": {
    "iso:country":"NZ",
    "sg:address":"Auckland, Hibiscus ",
    "sg:city":"Hibiscus Coast",
    "sg:classifiers":[
        {
            "category":"Shopping",
            "subcategory":"Beauty & Cosmetics",
            "type":"Retail Goods"
        }
    ],
    "sg:phone":"+64 800 443 258",
    "sg:province":"Auckland",
    "sg:tags":[
        "medical",
        "health"
    ],
    "sg:website":"http://www.southerncross.co.nz",
    "wof:name":"Southern Cross Healthcare",
    "wof:placetype":"venue"
},
  "geometry": {"coordinates":[174.706238,-36.636581],"type":"Point"}
}