{
  "type": "Feature",
  "properties": {
    "addr:full":"PO Box 25344 St Heliers  Auckland Auckland",
    "addr:housenumber":"po box 25344",
    "iso:country":"NZ",
    "sg:address":"PO Box 25344 St Heliers ",
    "sg:city":"Auckland",
    "sg:classifiers":[
        {
            "category":"Travel",
            "subcategory":"Travel Agent",
            "type":"Entertainment"
        }
    ],
    "sg:phone":"+64 9-521 2001",
    "sg:province":"Auckland",
    "sg:tags":[
        "tourism",
        "-",
        "accommodation",
        "booking"
    ],
    "wof:name":"New Zealand Holiday Homes (1996) Limited",
    "wof:placetype":"venue"
},
  "geometry": {"coordinates":[174.862976,-36.856163],"type":"Point"}
}