{
  "type": "Feature",
  "properties": {
    "iso:country":"NZ",
    "sg:address":"728 A Beach Rd Browns Bay ",
    "sg:city":"Auckland",
    "sg:orig_category":"Shopping: Sports Retailers: Water Sports: Surfboards",
    "sg:phone":"+64 9-478 3728",
    "sg:province":"Auckland",
    "wof:name":"Razor Surf Shop",
    "wof:placetype":"venue"
},
  "geometry": {"coordinates":[174.742783,-36.719028],"type":"Point"}
}