{
  "type": "Feature",
  "properties": {
    "addr:full":"cnr Henui & Devon St East Fitzroy New  Plymouth Taranaki",
    "addr:street":"Cnr Henui & Devon St",
    "iso:country":"NZ",
    "sg:address":"cnr Henui & Devon St East Fitzroy New ",
    "sg:city":"Plymouth",
    "sg:classifiers":[
        {
            "category":"Home & Garden",
            "subcategory":"Home Furnishings",
            "type":"Retail Goods"
        }
    ],
    "sg:phone":"+64 6-758 5713",
    "sg:province":"Taranaki",
    "sg:tags":[
        "furniture/furnishings",
        "bedding",
        "bed"
    ],
    "wof:name":"Bed Rumours",
    "wof:placetype":"venue"
},
  "geometry": {"coordinates":[174.104477,-39.048599],"type":"Point"}
}