{
  "type": "Feature",
  "properties": {
    "iso:country":"NZ",
    "sg:address":"3 Marine Pde Paraparaumu Beach ",
    "sg:city":"Paraparaumu",
    "sg:orig_category":"Travel And Tourism: Accommodation: Backpackers",
    "sg:phone":"+64 4-902 5856",
    "sg:province":"Wellington",
    "wof:name":"Barnacles Seaside Inn",
    "wof:placetype":"venue"
},
  "geometry": {"coordinates":[174.98121599999999,-40.891579],"type":"Point"}
}