{
  "type": "Feature",
  "properties": {
    "addr:full":"13 Ray Small Dve Papakura  Auckland Auckland",
    "addr:housenumber":"13",
    "addr:street":"Ray",
    "iso:country":"NZ",
    "sg:address":"13 Ray Small Dve Papakura ",
    "sg:city":"Auckland",
    "sg:orig_category":"Sports And Leisure: Arts: Theatres",
    "sg:phone":"+64 9-297 7712",
    "sg:province":"Auckland",
    "wof:name":"Hawkins Entertainment & Conference Centre",
    "wof:placetype":"venue"
},
  "geometry": {"coordinates":[174.937408,-37.066299],"type":"Point"}
}