{
  "type": "Feature",
  "properties": {
    "iso:country":"NZ",
    "sg:address":"67 Ottawa Rd Ngaio ",
    "sg:city":"Wellington",
    "sg:classifiers":[
        {
            "category":"Restaurant",
            "type":"Food & Drink"
        }
    ],
    "sg:phone":"+64 4-479 1635",
    "sg:province":"Wellington",
    "sg:tags":[
        "wining",
        "dining"
    ],
    "sg:website":"http://www.thecurryshop.co.nz",
    "wof:name":"The Curry Shop Limited",
    "wof:placetype":"venue"
},
  "geometry": {"coordinates":[174.77444499999999,-41.247948],"type":"Point"}
}