{
  "type": "Feature",
  "properties": {
    "addr:full":"State Highway 1 South  Whangarei Northland",
    "addr:street":"State Highway 1 South",
    "iso:country":"NZ",
    "sg:address":"State Highway 1 South ",
    "sg:city":"Whangarei",
    "sg:classifiers":[
        {
            "category":"Shopping",
            "subcategory":"Pets & Pet Supplies",
            "type":"Retail Goods"
        }
    ],
    "sg:phone":"+64 9-432 2853",
    "sg:province":"Northland",
    "sg:tags":[
        "boarding",
        "garden",
        "pets",
        "catteries",
        "home",
        "kennel"
    ],
    "wof:name":"Animotel",
    "wof:placetype":"venue"
},
  "geometry": {"coordinates":[174.52328499999999,-35.724174],"type":"Point"}
}