{
  "type": "Feature",
  "properties": {
    "addr:full":"12 Avoca St  Kaikoura",
    "addr:housenumber":"12",
    "addr:street":"Avoca St",
    "iso:country":"NZ",
    "sg:address":"12 Avoca St ",
    "sg:city":"Kaikoura",
    "sg:classifiers":[
        {
            "category":"Bars & Pubs",
            "type":"Food & Drink"
        }
    ],
    "sg:phone":"+64 3-319 6666",
    "sg:tags":[
        "wining",
        "dining",
        "brasserie"
    ],
    "wof:name":"Green Dolphin Restaurant & Bar",
    "wof:placetype":"venue"
},
  "geometry": {"coordinates":[173.705322,-42.41626],"type":"Point"}
}