{
  "type": "Feature",
  "properties": {
    "iso:country":"NZ",
    "sg:address":"1 Cecil Rd Epsom ",
    "sg:city":"Auckland",
    "sg:classifiers":[
        {
            "category":"Education",
            "subcategory":"Special Training",
            "type":"Public Place"
        }
    ],
    "sg:phone":"+64 9-630 1945",
    "sg:province":"Auckland",
    "sg:tags":[
        "sale",
        "vocational"
    ],
    "sg:website":"http://www.salescoach.co.nz",
    "wof:name":"Salescoach Ltd",
    "wof:placetype":"venue"
},
  "geometry": {"coordinates":[174.766708,-36.879951],"type":"Point"}
}