{
  "type": "Feature",
  "properties": {
    "iso:country":"NZ",
    "sg:address":"652 Tremaine Ave Palmerston ",
    "sg:city":"Palmerston North",
    "sg:classifiers":[
        {
            "category":"Manufacturing",
            "subcategory":"Metals",
            "type":"Manufacturing & Wholesale Goods"
        }
    ],
    "sg:phone":"+64 6-358 8370",
    "sg:province":"Manawatu-Wanganui",
    "sg:tags":[
        "-",
        "engineering",
        "industrial",
        "sheet",
        "engineer"
    ],
    "wof:name":"Turner Metal Fabrication Ltd",
    "wof:placetype":"venue"
},
  "geometry": {"coordinates":[175.606567,-40.34129],"type":"Point"}
}