{
  "type": "Feature",
  "properties": {
    "addr:full":"75 Tirau St  Putaruru",
    "addr:housenumber":"75",
    "addr:street":"Tirau St",
    "iso:country":"NZ",
    "sg:address":"75 Tirau St ",
    "sg:city":"Putaruru",
    "sg:classifiers":[
        {
            "category":"Landmark",
            "subcategory":"Tourist Information",
            "type":"Public Place"
        }
    ],
    "sg:phone":"+64 7-883 7284",
    "sg:tags":[
        "services",
        "travel",
        "tourism"
    ],
    "wof:name":"Putaruru Information Centre",
    "wof:placetype":"venue"
},
  "geometry": {"coordinates":[175.781937,-38.045063],"type":"Point"}
}