{
  "type": "Feature",
  "properties": {
    "addr:full":"Te Waiiti Pl Morningside  Whangarei Northland",
    "addr:street":"Pl",
    "iso:country":"NZ",
    "sg:address":"Te Waiiti Pl Morningside ",
    "sg:city":"Whangarei",
    "sg:classifiers":[
        {
            "category":"Building & Trades",
            "subcategory":"Pest Control",
            "type":"Services"
        }
    ],
    "sg:phone":"+64 9-438 8261",
    "sg:province":"Northland",
    "sg:tags":[
        "services",
        "automotive",
        "equipment"
    ],
    "wof:name":"Fuelquip",
    "wof:placetype":"venue"
},
  "geometry": {"coordinates":[174.31959499999999,-35.7356],"type":"Point"}
}