{
  "type": "Feature",
  "properties": {
    "iso:country":"NZ",
    "sg:address":"251 Kukutauaki Rd ",
    "sg:city":"Levin",
    "sg:classifiers":[
        {
            "category":"Home & Garden",
            "subcategory":"Garden Supply",
            "type":"Retail Goods"
        }
    ],
    "sg:phone":"+64 6-368 6450",
    "sg:province":"Manawatu-Wanganui",
    "sg:tags":[
        "gardening"
    ],
    "sg:website":"http://www.yellowpages.co.nz/for/kerilea/dp48123.html",
    "wof:name":"Kerilea Horticultural Systems Ltd",
    "wof:placetype":"venue"
},
  "geometry": {"coordinates":[175.285324,-40.625278],"type":"Point"}
}