{
  "type": "Feature",
  "properties": {
    "addr:full":"23 Golders Rd Upper Hutt  Wellington Wellington",
    "addr:housenumber":"23",
    "addr:street":"Golders Rd",
    "iso:country":"NZ",
    "sg:address":"23 Golders Rd Upper Hutt ",
    "sg:city":"Wellington",
    "sg:orig_category":"Home And Garden: Gardening: Services: Landscaping",
    "sg:phone":"+64 4-970 1954",
    "sg:province":"Wellington",
    "wof:name":"Riverside Landscaping Ltd",
    "wof:placetype":"venue"
},
  "geometry": {"coordinates":[174.90838600000001,-41.206631],"type":"Point"}
}