{
  "type": "Feature",
  "properties": {
    "addr:full":"Cnr Great North & Pt Chevalier Rds Point Chevalier Auckland Auckland",
    "addr:street":"Cnr Great;Rds",
    "iso:country":"NZ",
    "sg:address":"Cnr Great North & Pt Chevalier Rds Point Chevalier",
    "sg:city":"Auckland",
    "sg:orig_category":"Shopping: Retail Stores: Books: Libraries",
    "sg:phone":"+64 9-846 6559",
    "sg:province":"Auckland",
    "wof:name":"Pt Chevalier",
    "wof:placetype":"venue"
},
  "geometry": {"coordinates":[174.70526100000001,-36.863762],"type":"Point"}
}