{
  "type": "Feature",
  "properties": {
    "iso:country":"NZ",
    "sg:address":"256 The Strand ",
    "sg:city":"Whakatane",
    "sg:classifiers":[
        {
            "category":"Recreation",
            "type":"Entertainment"
        }
    ],
    "sg:phone":"+64 7-307 0500",
    "sg:province":"Auckland",
    "sg:tags":[
        "sport",
        "tramping",
        "leisure",
        "camping"
    ],
    "wof:name":"Whakatane Great Outdoor Centre",
    "wof:placetype":"venue"
},
  "geometry": {"coordinates":[176.992752,-37.952473],"type":"Point"}
}