{
  "type": "Feature",
  "properties": {
    "addr:full":"Opua Estate Paihia PO Box 18  Paihia Northland",
    "addr:housenumber":"po box 18 paihia",
    "addr:street":"Opua",
    "iso:country":"NZ",
    "sg:address":"Opua Estate Paihia PO Box 18 ",
    "sg:city":"Paihia",
    "sg:orig_category":"Home And Garden: Furniture/Furnishings: Curtains",
    "sg:phone":"+64 9-402 8173",
    "sg:province":"Northland",
    "wof:name":"Morgan Interiors Limited",
    "wof:placetype":"venue"
},
  "geometry": {"coordinates":[174.09106399999999,-35.283699],"type":"Point"}
}