{
  "type": "Feature",
  "properties": {
    "iso:country":"NZ",
    "sg:address":"Corsair La Ardmore Airfield ",
    "sg:city":"Auckland",
    "sg:classifiers":[
        {
            "category":"Airport",
            "type":"Transportation"
        }
    ],
    "sg:phone":"+64 9-299 7401",
    "sg:province":"Auckland",
    "sg:tags":[
        "aircraft",
        "transport",
        "sale",
        "maintenance",
        "air"
    ],
    "wof:name":"Airspray Ltd",
    "wof:placetype":"venue"
},
  "geometry": {"coordinates":[174.969559,-37.033154],"type":"Point"}
}