{
  "type": "Feature",
  "properties": {
    "addr:full":"427 Tremaine Ave Palmerston  Palmerston North Manawatu-Wanganui",
    "addr:housenumber":"427",
    "addr:street":"Tremaine Ave",
    "iso:country":"NZ",
    "sg:address":"427 Tremaine Ave Palmerston ",
    "sg:city":"Palmerston North",
    "sg:orig_category":"Shopping: Retail Stores: Batteries",
    "sg:phone":"+64 6-357 6430",
    "sg:province":"Manawatu-Wanganui",
    "wof:name":"Ultra Mobile Batteries",
    "wof:placetype":"venue"
},
  "geometry": {"coordinates":[175.59037799999999,-40.348263],"type":"Point"}
}