{
  "type": "Feature",
  "properties": {
    "addr:full":"303 Rickit Rd Te  Awamutu Waikato",
    "addr:housenumber":"303",
    "addr:street":"Rickit Rd",
    "iso:country":"NZ",
    "sg:address":"303 Rickit Rd Te ",
    "sg:city":"Awamutu",
    "sg:classifiers":[
        {
            "category":"Professional",
            "type":"Services"
        }
    ],
    "sg:phone":"+64 7-870 3452",
    "sg:province":"Waikato",
    "sg:tags":[
        "services",
        "car",
        "valet",
        "automotive"
    ],
    "wof:name":"Ultra Clean Car Valet",
    "wof:placetype":"venue"
},
  "geometry": {"coordinates":[175.32862900000001,-38.013054],"type":"Point"}
}