{
  "type": "Feature",
  "properties": {
    "iso:country":"NZ",
    "sg:address":"582 Tuhikaramea Rd ",
    "sg:city":"Hamilton",
    "sg:classifiers":[
        {
            "category":"Organizations",
            "subcategory":"Religious Organization",
            "type":"Services"
        }
    ],
    "sg:phone":"+64 7-847 5995",
    "sg:province":"Waikato",
    "sg:tags":[
        "funeral",
        "arrangement"
    ],
    "wof:name":"Meadow View Funeral Services",
    "wof:placetype":"venue"
},
  "geometry": {"coordinates":[175.241302,-37.80571],"type":"Point"}
}