{
  "type": "Feature",
  "properties": {
    "addr:full":"14-22 Aintree Ave, Airport Oaks Mangere  Auckland Auckland",
    "addr:housenumber":"14-22",
    "addr:street":"Aintree Ave",
    "iso:country":"NZ",
    "sg:address":"14-22 Aintree Ave, Airport Oaks Mangere ",
    "sg:city":"Auckland",
    "sg:orig_category":"Home And Garden: Furniture/Furnishings: Cabinetmakers",
    "sg:phone":"+64 9-255 1220",
    "sg:province":"Auckland",
    "wof:name":"Tawa Door Company Ltd",
    "wof:placetype":"venue"
},
  "geometry": {"coordinates":[174.777176,-36.974957],"type":"Point"}
}