{
  "type": "Feature",
  "properties": {
    "iso:country":"NZ",
    "sg:address":"PO Box 31-257 Milford ",
    "sg:city":"Auckland",
    "sg:classifiers":[
        {
            "category":"Travel",
            "subcategory":"Travel Agent",
            "type":"Entertainment"
        }
    ],
    "sg:phone":"+64 9-478 3550",
    "sg:province":"Auckland",
    "sg:tags":[
        "tour",
        "tourism",
        "sightseeing"
    ],
    "sg:website":"http://www.tourmasters.co.nz",
    "wof:name":"Tourmasters South Pacific (NZ) Ltd",
    "wof:placetype":"venue"
},
  "geometry": {"coordinates":[174.764984,-36.771812],"type":"Point"}
}