{
  "type": "Feature",
  "properties": {
    "iso:country":"NZ",
    "sg:address":"PO Box 50 ",
    "sg:city":"Akaroa",
    "sg:classifiers":[
        {
            "category":"Landmark",
            "subcategory":"Tourist Information",
            "type":"Public Place"
        }
    ],
    "sg:phone":"+64 3-304 7612",
    "sg:province":"Canterbury",
    "sg:tags":[
        "travel",
        "tourism",
        "tour",
        "sightseeing"
    ],
    "sg:website":"http://www.bankstrack.co.nz",
    "wof:name":"Banks Peninsula Track The",
    "wof:placetype":"venue"
},
  "geometry": {"coordinates":[172.967453,-43.804749],"type":"Point"}
}