{
  "type": "Feature",
  "properties": {
    "addr:full":"30 Carmen Rd Hornby  Christchurch Canterbury",
    "addr:housenumber":"30",
    "addr:street":"Carmen Rd",
    "iso:country":"NZ",
    "sg:address":"30 Carmen Rd Hornby ",
    "sg:city":"Christchurch",
    "sg:orig_category":"Industrial: Parts: Pipes, Tubes And Cabling: Pipes",
    "sg:phone":"+64 3-349 4399",
    "sg:province":"Canterbury",
    "wof:name":"Humes",
    "wof:placetype":"venue"
},
  "geometry": {"coordinates":[172.526794,-43.541008],"type":"Point"}
}