{
  "type": "Feature",
  "properties": {
    "iso:country":"NZ",
    "sg:address":"75 Vanguard St ",
    "sg:city":"Nelson",
    "sg:classifiers":[
        {
            "category":"Retail",
            "subcategory":"Auto Repair",
            "type":"Services"
        }
    ],
    "sg:phone":"+64 3-548 0650",
    "sg:province":"Nelson",
    "sg:tags":[
        "breakdown",
        "automotive",
        "towing",
        "servicing"
    ],
    "wof:name":"A 2 Z Tow & Salvage",
    "wof:placetype":"venue"
},
  "geometry": {"coordinates":[-121.765488,39.553471],"type":"Point"}
}