{
  "type": "Feature",
  "properties": {
    "addr:full":"223 Annex Rd Upper Riccarton  Christchurch Canterbury",
    "addr:housenumber":"223",
    "addr:street":"Annex Rd",
    "iso:country":"NZ",
    "sg:address":"223 Annex Rd Upper Riccarton ",
    "sg:city":"Christchurch",
    "sg:orig_category":"Industrial: Services: Marking And Coding",
    "sg:phone":"+64 3-338 2042",
    "sg:province":"Canterbury",
    "wof:name":"Button R L & Co Ltd",
    "wof:placetype":"venue"
},
  "geometry": {"coordinates":[172.597351,-43.532143],"type":"Point"}
}