{
  "type": "Feature",
  "properties": {
    "iso:country":"NZ",
    "sg:address":"560 Castle St Dunedin North ",
    "sg:city":"Dunedin",
    "sg:orig_category":"Travel And Tourism: Accommodation: Hostels",
    "sg:phone":"+64 3-477 3326",
    "sg:province":"Otago",
    "wof:name":"Selwyn College",
    "wof:placetype":"venue"
},
  "geometry": {"coordinates":[170.51516699999999,-45.862137],"type":"Point"}
}