{
  "type": "Feature",
  "properties": {
    "addr:full":"302 Lambton Qy  Wellington Wellington",
    "addr:housenumber":"302",
    "addr:street":"Lambton",
    "iso:country":"NZ",
    "sg:address":"302 Lambton Qy ",
    "sg:city":"Wellington",
    "sg:orig_category":"Shopping: Accessories: Sunglasses",
    "sg:phone":"+64 4-471 1258",
    "sg:province":"Wellington",
    "wof:name":"Sunglass Hut International",
    "wof:placetype":"venue"
},
  "geometry": {"coordinates":[174.775284,-41.284649],"type":"Point"}
}