{
  "type": "Feature",
  "properties": {
    "iso:country":"NZ",
    "sg:address":"PO Box 5325 Papanui ",
    "sg:city":"Christchurch",
    "sg:classifiers":[
        {
            "category":"Shopping",
            "subcategory":"Beauty & Cosmetics",
            "type":"Retail Goods"
        }
    ],
    "sg:phone":"+64 3-352 0480",
    "sg:province":"Canterbury",
    "sg:tags":[
        "specialist",
        "health",
        "x-ray",
        "specialists"
    ],
    "wof:name":"Radiographic Supplies Ltd",
    "wof:placetype":"venue"
},
  "geometry": {"coordinates":[172.59986900000001,-43.496452],"type":"Point"}
}