{
  "type": "Feature",
  "properties": {
    "addr:full":"14/ K Echelon Pl East Tamaki  Auckland Auckland",
    "addr:housenumber":"14 / k",
    "addr:street":"Echelon Pl",
    "iso:country":"NZ",
    "sg:address":"14/ K Echelon Pl East Tamaki ",
    "sg:city":"Auckland",
    "sg:orig_category":"Industrial: Parts: Pipes, Tubes And Cabling: Pipes - Plastic",
    "sg:phone":"+64 9-575 9755",
    "sg:province":"Auckland",
    "wof:name":"Pipeline Construction Ltd",
    "wof:placetype":"venue"
},
  "geometry": {"coordinates":[174.88305700000001,-36.936211],"type":"Point"}
}