{
  "type": "Feature",
  "properties": {
    "addr:full":"198 Connett Rd East Bell Block New  Plymouth Taranaki",
    "addr:housenumber":"198",
    "addr:street":"Connett Rd East",
    "iso:country":"NZ",
    "sg:address":"198 Connett Rd East Bell Block New ",
    "sg:city":"Plymouth",
    "sg:classifiers":[
        {
            "category":"Utilities",
            "subcategory":"Fuel Oil & Lpg",
            "type":"Services"
        }
    ],
    "sg:phone":"+64 6-755 2622",
    "sg:province":"Taranaki",
    "sg:tags":[
        "energy",
        "industrial",
        "exploration",
        "utilities"
    ],
    "wof:name":"Reeves Wireline Services (New Zealand) Ltd",
    "wof:placetype":"venue"
},
  "geometry": {"coordinates":[174.14274599999999,-39.032024],"type":"Point"}
}