{
  "type": "Feature",
  "properties": {
    "iso:country":"NZ",
    "sg:address":"22 Cambria St ",
    "sg:city":"Hawera",
    "sg:classifiers":[
        {
            "category":"Retail",
            "subcategory":"Auto Repair",
            "type":"Services"
        }
    ],
    "sg:phone":"+64 6-278 8233",
    "sg:province":"Taranaki",
    "sg:tags":[
        "automotive",
        "panel",
        "servicing",
        "beater"
    ],
    "wof:name":"Andrew Purser Panelbeater",
    "wof:placetype":"venue"
},
  "geometry": {"coordinates":[174.285065,-39.585613],"type":"Point"}
}