{
  "type": "Feature",
  "properties": {
    "iso:country":"NZ",
    "sg:address":"40 Laughton St Washdyke ",
    "sg:city":"Timaru",
    "sg:classifiers":[
        {
            "category":"Utilities",
            "type":"Services"
        }
    ],
    "sg:phone":"+64 3-688 2675",
    "sg:province":"Canterbury",
    "sg:tags":[
        "industrial",
        "energy",
        "utilities",
        "coal",
        "wood",
        "coke"
    ],
    "wof:name":"Central Wood",
    "wof:placetype":"venue"
},
  "geometry": {"coordinates":[171.23434399999999,-44.353512],"type":"Point"}
}