{
  "type": "Feature",
  "properties": {
    "iso:country":"NZ",
    "sg:address":"Frankton Indust Est ",
    "sg:city":"Queenstown",
    "sg:classifiers":[
        {
            "category":"Home & Garden",
            "subcategory":"Building Materials",
            "type":"Retail Goods"
        }
    ],
    "sg:phone":"+64 3-442 3620",
    "sg:province":"Waikato",
    "sg:tags":[
        "related"
    ],
    "sg:website":"http://www.warmfloor.co.nz",
    "wof:name":"Walker & Barnes Plumbing Ltd",
    "wof:placetype":"venue"
},
  "geometry": {"coordinates":[168.73263499999999,-45.020927],"type":"Point"}
}