{
  "type": "Feature",
  "properties": {
    "addr:full":"8 D Piermark Dve Albany  Auckland Auckland",
    "addr:housenumber":"8",
    "addr:street":"D Piermark",
    "iso:country":"NZ",
    "sg:address":"8 D Piermark Dve Albany ",
    "sg:city":"Auckland",
    "sg:orig_category":"Shopping: Retail Stores: Cds, Cassettes And Records",
    "sg:phone":"+64 9-414 4686",
    "sg:province":"Auckland",
    "wof:name":"Just Music Ltd",
    "wof:placetype":"venue"
},
  "geometry": {"coordinates":[174.70323200000001,-36.748043],"type":"Point"}
}