{
  "type": "Feature",
  "properties": {
    "addr:full":"19 Waverley St  Auckland Auckland",
    "addr:housenumber":"19",
    "addr:street":"Waverley St",
    "iso:country":"NZ",
    "sg:address":"19 Waverley St ",
    "sg:city":"Auckland",
    "sg:classifiers":[
        {
            "category":"Shopping",
            "subcategory":"Pharmacy",
            "type":"Retail Goods"
        }
    ],
    "sg:phone":"+64 9-309 3773",
    "sg:province":"Auckland",
    "sg:tags":[
        "products",
        "medical",
        "health",
        "beauty",
        "supply"
    ],
    "wof:name":"Harris A R Co Ltd",
    "wof:placetype":"venue"
},
  "geometry": {"coordinates":[174.71698000000001,-36.782009],"type":"Point"}
}