{
  "type": "Feature",
  "properties": {
    "iso:country":"NZ",
    "sg:address":"Chapel Rd ",
    "sg:city":"Auckland",
    "sg:orig_category":"Clothing And Fabric: Clothing: Menswear",
    "sg:phone":"+64 9-272 9880",
    "sg:province":"Auckland",
    "wof:name":"Farmers Trading Co Ltd",
    "wof:placetype":"venue"
},
  "geometry": {"coordinates":[-119.104576,36.597755],"type":"Point"}
}