{
  "type": "Feature",
  "properties": {
    "iso:country":"NZ",
    "sg:address":"College St ",
    "sg:city":"Motueka",
    "sg:classifiers":[
        {
            "category":"Manufacturing",
            "subcategory":"Furniture",
            "type":"Manufacturing & Wholesale Goods"
        }
    ],
    "sg:phone":"+64 3-528 9200",
    "sg:province":"Tasman",
    "sg:tags":[
        "furniture/furnishings",
        "home",
        "garden",
        "manufacturer"
    ],
    "wof:name":"The Woodwrights",
    "wof:placetype":"venue"
},
  "geometry": {"coordinates":[172.98313899999999,-41.12355],"type":"Point"}
}