{
  "type": "Feature",
  "properties": {
    "addr:full":"1048 Beach Rd Torbay  Auckland Auckland",
    "addr:housenumber":"1048",
    "addr:street":"Beach Rd",
    "iso:country":"NZ",
    "sg:address":"1048 Beach Rd Torbay ",
    "sg:city":"Auckland",
    "sg:classifiers":[
        {
            "category":"Health Services",
            "subcategory":"Health Practitioner",
            "type":"Services"
        }
    ],
    "sg:phone":"+64 9-473 2278",
    "sg:province":"Auckland",
    "sg:tags":[
        "services",
        "beauty",
        "acupuncturists"
    ],
    "wof:name":"Torbay Chinese Acupuncture Centre",
    "wof:placetype":"venue"
},
  "geometry": {"coordinates":[174.75129699999999,-36.695267],"type":"Point"}
}