{
  "type": "Feature",
  "properties": {
    "iso:country":"NZ",
    "sg:address":"61-67 King St ",
    "sg:city":"Temuka",
    "sg:classifiers":[
        {
            "category":"Home & Garden",
            "subcategory":"Kitchen Supply",
            "type":"Retail Goods"
        }
    ],
    "sg:phone":"+64 3-615 7777",
    "sg:tags":[
        "food",
        "equipment",
        "drink",
        "catering"
    ],
    "wof:name":"South Canterbury Catering Equipment",
    "wof:placetype":"venue"
},
  "geometry": {"coordinates":[171.27615399999999,-44.238956],"type":"Point"}
}