{
  "type": "Feature",
  "properties": {
    "addr:full":"335 Main Rd Huapai  Auckland Auckland",
    "addr:housenumber":"335",
    "addr:street":"Main Rd",
    "iso:country":"NZ",
    "sg:address":"335 Main Rd Huapai ",
    "sg:city":"Auckland",
    "sg:classifiers":[
        {
            "category":"Home & Garden",
            "subcategory":"Home Furnishings",
            "type":"Retail Goods"
        }
    ],
    "sg:phone":"+64 9-412 8332",
    "sg:province":"Auckland",
    "sg:tags":[
        "furniture/furnishings",
        "upholstery",
        "supply"
    ],
    "wof:name":"Huapai Upholsterers",
    "wof:placetype":"venue"
},
  "geometry": {"coordinates":[174.536224,-36.76432],"type":"Point"}
}