{
  "type": "Feature",
  "properties": {
    "addr:full":"18 Fantame St Porirua  Wellington Wellington",
    "addr:housenumber":"18",
    "addr:street":"Fantame St",
    "iso:country":"NZ",
    "sg:address":"18 Fantame St Porirua ",
    "sg:city":"Wellington",
    "sg:classifiers":[
        {
            "category":"Health Services",
            "subcategory":"Dentist",
            "type":"Services"
        }
    ],
    "sg:phone":"+64 4-235 7958",
    "sg:province":"Wellington",
    "sg:tags":[
        "dental",
        "clinic",
        "beauty"
    ],
    "wof:name":"Russell School Dental Clinic",
    "wof:placetype":"venue"
},
  "geometry": {"coordinates":[174.85223400000001,-41.138294],"type":"Point"}
}