{
  "type": "Feature",
  "properties": {
    "addr:full":"25 Beaumont Rd  Rotorua Bay of Plenty",
    "addr:housenumber":"25",
    "addr:street":"Beaumont Rd",
    "iso:country":"NZ",
    "sg:address":"25 Beaumont Rd ",
    "sg:city":"Rotorua",
    "sg:classifiers":[
        {
            "category":"Sports & Exercise",
            "subcategory":"Swimming Pool",
            "type":"Entertainment"
        }
    ],
    "sg:phone":"+64 7-357 2087",
    "sg:province":"Bay of Plenty",
    "sg:tags":[
        "home",
        "outdoor",
        "garden",
        "spa"
    ],
    "sg:website":"http://www.yellowpages.co.nz/for/cotterillsecurityfencing/dp39103.html",
    "wof:name":"Cotterill Steve & Sharon",
    "wof:placetype":"venue"
},
  "geometry": {"coordinates":[176.215225,-38.08493],"type":"Point"}
}