{
  "type": "Feature",
  "properties": {
    "iso:country":"NZ",
    "sg:address":"34 John St ",
    "sg:city":"Whangarei",
    "sg:classifiers":[
        {
            "category":"Recreation",
            "type":"Entertainment"
        }
    ],
    "sg:phone":"+64 9-438 8111",
    "sg:province":"Northland",
    "sg:tags":[
        "sport",
        "leisure"
    ],
    "wof:name":"Klose Enkounters",
    "wof:placetype":"venue"
},
  "geometry": {"coordinates":[174.32290599999999,-35.724968],"type":"Point"}
}