{
  "type": "Feature",
  "properties": {
    "iso:country":"NZ",
    "sg:address":"P O Box 800 65 Green Bay ",
    "sg:city":"Auckland",
    "sg:orig_category":"Industrial: Services: Gasfitters",
    "sg:phone":"+64 9-827 3206",
    "sg:province":"Auckland",
    "wof:name":"CitiGas Ltd",
    "wof:placetype":"venue"
},
  "geometry": {"coordinates":[174.770416,-36.884109],"type":"Point"}
}