{
  "type": "Feature",
  "properties": {
    "addr:full":"P O Box 800 65 Green Bay  Auckland Auckland",
    "addr:housenumber":"65",
    "addr:postcode":"800",
    "addr:street":"P O Box",
    "iso:country":"NZ",
    "sg:address":"P O Box 800 65 Green Bay ",
    "sg:city":"Auckland",
    "sg:orig_category":"Industrial: Services: Gasfitters",
    "sg:phone":"+64 9-827 3206",
    "sg:province":"Auckland",
    "wof:name":"CitiGas Ltd",
    "wof:placetype":"venue"
},
  "geometry": {"coordinates":[174.77041600000001,-36.884109],"type":"Point"}
}