{
  "type": "Feature",
  "properties": {
    "addr:full":"37 Vine St  Whangarei Northland",
    "addr:housenumber":"37",
    "addr:street":"Vine St",
    "iso:country":"NZ",
    "sg:address":"37 Vine St ",
    "sg:city":"Whangarei",
    "sg:classifiers":[
        {
            "category":"Bars & Pubs",
            "subcategory":"Nightclub",
            "type":"Food & Drink"
        }
    ],
    "sg:phone":"+64 9-459 7461",
    "sg:province":"Northland",
    "sg:tags":[
        "club",
        "night",
        "sport",
        "leisure",
        "entertainment"
    ],
    "wof:name":"Danger! Danger",
    "wof:placetype":"venue"
},
  "geometry": {"coordinates":[174.32058699999999,-35.726437],"type":"Point"}
}