{
  "type": "Feature",
  "properties": {
    "addr:full":"2 Elizabeth St  Waikanae",
    "addr:housenumber":"2",
    "addr:street":"Elizabeth St",
    "iso:country":"NZ",
    "sg:address":"2 Elizabeth St ",
    "sg:city":"Waikanae",
    "sg:classifiers":[
        {
            "category":"Shopping",
            "subcategory":"Pets & Pet Supplies",
            "type":"Retail Goods"
        }
    ],
    "sg:phone":"+64 4-293 4504",
    "sg:tags":[
        "home",
        "garden"
    ],
    "wof:name":"Waikanae Veterinary Service",
    "wof:placetype":"venue"
},
  "geometry": {"coordinates":[175.065506,-40.87788],"type":"Point"}
}