{
  "type": "Feature",
  "properties": {
    "addr:full":"91 Greenwood St  Hamilton Waikato",
    "addr:housenumber":"91",
    "addr:street":"Greenwood St",
    "iso:country":"NZ",
    "sg:address":"91 Greenwood St ",
    "sg:city":"Hamilton",
    "sg:classifiers":[
        {
            "category":"Marine",
            "type":"Transportation"
        }
    ],
    "sg:phone":"+64 7-847 4784",
    "sg:province":"Waikato",
    "sg:tags":[
        "transport",
        "boat"
    ],
    "sg:website":"http://www.deanfreight.co.nz",
    "wof:name":"Dean Freight International Ltd",
    "wof:placetype":"venue"
},
  "geometry": {"coordinates":[175.25994900000001,-37.790478],"type":"Point"}
}