{
  "type": "Feature",
  "properties": {
    "addr:full":"PO Box 39-108 Wgtn Mail Ctre Lower  Hutt Wellington",
    "addr:housenumber":"po box",
    "addr:street":"39-108 Wgtn Mail Ctre",
    "iso:country":"NZ",
    "sg:address":"PO Box 39-108 Wgtn Mail Ctre Lower ",
    "sg:city":"Hutt",
    "sg:orig_category":"Industrial: Services: Specialist Services: Laboratories",
    "sg:phone":"+64 4-586 6202",
    "sg:province":"Wellington",
    "wof:name":"Oil Inspection Limited",
    "wof:placetype":"venue"
},
  "geometry": {"coordinates":[174.904526,-41.208431],"type":"Point"}
}