{
  "type": "Feature",
  "properties": {
    "addr:full":"Customer Services & Sales 5 Tiri Pl Mt Wellington Auckland Auckland",
    "addr:housenumber":"5",
    "addr:street":"Tiri Pl",
    "iso:country":"NZ",
    "sg:address":"Customer Services & Sales 5 Tiri Pl Mt Wellington",
    "sg:city":"Auckland",
    "sg:classifiers":[
        {
            "category":"Manufacturing",
            "subcategory":"Tools & Machinery",
            "type":"Manufacturing & Wholesale Goods"
        }
    ],
    "sg:phone":"+64 9-270 2160",
    "sg:province":"Auckland",
    "sg:tags":[
        "equipment",
        "industrial",
        "label"
    ],
    "wof:name":"Jenkins Labels Ltd",
    "wof:placetype":"venue"
},
  "geometry": {"coordinates":[174.83871500000001,-36.90852],"type":"Point"}
}