{
  "type": "Feature",
  "properties": {
    "addr:full":"State Hwy 1 Levin RD 20 Ohau  Levin Manawatu-Wanganui",
    "addr:housenumber":"20;levin",
    "addr:street":"State Hwy 1 Levin Rd",
    "iso:country":"NZ",
    "sg:address":"State Hwy 1 Levin RD 20 Ohau ",
    "sg:city":"Levin",
    "sg:classifiers":[
        {
            "category":"Social Services",
            "subcategory":"Job Training",
            "type":"Services"
        }
    ],
    "sg:phone":"+64 6-368 3987",
    "sg:province":"Manawatu-Wanganui",
    "sg:tags":[
        "education"
    ],
    "wof:name":"Patumakuku Incorporated",
    "wof:placetype":"venue"
},
  "geometry": {"coordinates":[175.285324,-40.625278],"type":"Point"}
}