{
  "type": "Feature",
  "properties": {
    "addr:full":"Opua  Paihia Northland",
    "iso:country":"NZ",
    "sg:address":"Opua ",
    "sg:city":"Paihia",
    "sg:orig_category":"Transport: Boats And Marine: Services: Marinas",
    "sg:phone":"+64 9-402 7124",
    "sg:province":"Northland",
    "wof:name":"Opua Marina",
    "wof:placetype":"venue"
},
  "geometry": {"coordinates":[174.09106399999999,-35.283691],"type":"Point"}
}