{
  "type": "Feature",
  "properties": {
    "addr:full":"8 Aintree Ave Mangere  Auckland Auckland",
    "addr:housenumber":"8",
    "addr:street":"Aintree Ave",
    "iso:country":"NZ",
    "sg:address":"8 Aintree Ave Mangere ",
    "sg:city":"Auckland",
    "sg:classifiers":[
        {
            "category":"Autos & Motor Vehicles",
            "subcategory":"Automobile Sales",
            "type":"Retail Goods"
        }
    ],
    "sg:phone":"+64 9-256 9016",
    "sg:province":"Auckland",
    "sg:tags":[
        "car",
        "-used",
        "leasing",
        "truck",
        "automotive"
    ],
    "sg:website":"http://www.yellowpages.co.nz/for/aboutnzrentalcar3/dp58943.html",
    "wof:name":"About New Zealand Rental Cars",
    "wof:placetype":"venue"
},
  "geometry": {"coordinates":[174.82380699999999,-36.96891],"type":"Point"}
}