{
  "type": "Feature",
  "properties": {
    "iso:country":"NZ",
    "sg:address":"Molesworth House 101 Molesworth St Thorndon ",
    "sg:city":"Wellington",
    "sg:classifiers":[
        {
            "category":"Banks & Credit Unions",
            "subcategory":"Investment Brokerage",
            "type":"Services"
        }
    ],
    "sg:phone":"+64 4-498 9660",
    "sg:province":"Wellington",
    "sg:tags":[
        "educational",
        "education",
        "training"
    ],
    "wof:name":"New Zealand Speech Board",
    "wof:placetype":"venue"
},
  "geometry": {"coordinates":[174.776016,-41.274925],"type":"Point"}
}