{
  "type": "Feature",
  "properties": {
    "iso:country":"NZ",
    "sg:address":"28 Huron St ",
    "sg:city":"Gore",
    "sg:classifiers":[
        {
            "category":"Wholesale",
            "subcategory":"Meat",
            "type":"Manufacturing & Wholesale Goods"
        }
    ],
    "sg:phone":"+64 3-208 7714",
    "sg:province":"Southland",
    "sg:tags":[
        "food",
        "drink",
        "meats",
        "slaughtering"
    ],
    "wof:name":"Quality Meats Service Killing Abattoir",
    "wof:placetype":"venue"
},
  "geometry": {"coordinates":[-95.116547,35.530331],"type":"Point"}
}