{
  "type": "Feature",
  "properties": {
    "addr:full":"97 Hautapu St  Taihape",
    "addr:housenumber":"97",
    "addr:street":"Hautapu St",
    "iso:country":"NZ",
    "sg:address":"97 Hautapu St ",
    "sg:city":"Taihape",
    "sg:orig_category":"Automotive: General Services: Automobile Associations",
    "sg:phone":"+64 6-388 0300",
    "wof:name":"A A Automobile Association",
    "wof:placetype":"venue"
},
  "geometry": {"coordinates":[175.79930100000001,-39.678398],"type":"Point"}
}