{
  "type": "Feature",
  "properties": {
    "addr:full":"247 Fraser St  Tauranga Bay of Plenty",
    "addr:housenumber":"247",
    "addr:street":"Fraser St",
    "iso:country":"NZ",
    "sg:address":"247 Fraser St ",
    "sg:city":"Tauranga",
    "sg:orig_category":"Home And Garden: Cleaning: Brushware",
    "sg:phone":"+64 7-578 2501",
    "sg:province":"Bay of Plenty",
    "wof:name":"Bay Direct Distributors",
    "wof:placetype":"venue"
},
  "geometry": {"coordinates":[176.15167199999999,-37.713676],"type":"Point"}
}