{
  "type": "Feature",
  "properties": {
    "addr:full":"19 Fraser St  Temuka",
    "addr:housenumber":"19",
    "addr:street":"Fraser St",
    "iso:country":"NZ",
    "sg:address":"19 Fraser St ",
    "sg:city":"Temuka",
    "sg:classifiers":[
        {
            "category":"Retail",
            "subcategory":"Auto Repair",
            "type":"Services"
        }
    ],
    "sg:phone":"+64 3-615 7364",
    "sg:tags":[
        "automotive",
        "panel",
        "servicing",
        "beater"
    ],
    "wof:name":"Greers Panel Repairs Ltd",
    "wof:placetype":"venue"
},
  "geometry": {"coordinates":[171.27711500000001,-44.247108],"type":"Point"}
}