{
  "type": "Feature",
  "properties": {
    "addr:full":"179 Ingestre St  Wanganui Manawatu-Wanganui",
    "addr:housenumber":"179",
    "addr:street":"Ingestre St",
    "iso:country":"NZ",
    "sg:address":"179 Ingestre St ",
    "sg:city":"Wanganui",
    "sg:classifiers":[
        {
            "category":"Retail",
            "subcategory":"Funeral Services",
            "type":"Services"
        }
    ],
    "sg:phone":"+64 6-345 5522",
    "sg:province":"Manawatu-Wanganui",
    "sg:tags":[
        "arrangements",
        "arrangement"
    ],
    "wof:name":"Alex Hird Ltd",
    "wof:placetype":"venue"
},
  "geometry": {"coordinates":[175.04362499999999,-39.934601],"type":"Point"}
}