{
  "type": "Feature",
  "properties": {
    "addr:full":"15 Victoria Ave  Wanganui Manawatu-Wanganui",
    "addr:housenumber":"15",
    "addr:street":"Victoria Ave",
    "iso:country":"NZ",
    "sg:address":"15 Victoria Ave ",
    "sg:city":"Wanganui",
    "sg:classifiers":[
        {
            "category":"Personal",
            "subcategory":"Beauty Salon",
            "type":"Services"
        }
    ],
    "sg:phone":"+64 6-347 7456",
    "sg:province":"Manawatu-Wanganui",
    "sg:tags":[
        "therapy",
        "health"
    ],
    "wof:name":"Cleopatra's Nails Beauty & Massage",
    "wof:placetype":"venue"
},
  "geometry": {"coordinates":[175.05476400000001,-39.934677],"type":"Point"}
}