{
  "type": "Feature",
  "properties": {
    "iso:country":"NZ",
    "sg:address":"164 Malfroy Rd ",
    "sg:city":"Rotorua",
    "sg:orig_category":"Transport: Transportation: Postal Services",
    "sg:phone":"+64 7-348 9128",
    "sg:province":"Bay of Plenty",
    "wof:name":"Rotorua West Post Shop",
    "wof:placetype":"venue"
},
  "geometry": {"coordinates":[176.237595,-38.144733],"type":"Point"}
}