{
  "type": "Feature",
  "properties": {
    "iso:country":"NZ",
    "sg:address":"Airfield Rd Ardmore Airfield ",
    "sg:city":"Auckland",
    "sg:classifiers":[
        {
            "category":"Organizations",
            "subcategory":"Labor Organization",
            "type":"Services"
        }
    ],
    "sg:phone":"+64 9-299 6200",
    "sg:province":"Auckland",
    "sg:tags":[
        "services",
        "helicopter",
        "travel",
        "tourism"
    ],
    "wof:name":"Helitech Ltd",
    "wof:placetype":"venue"
},
  "geometry": {"coordinates":[174.962662,-37.029064],"type":"Point"}
}