{
  "type": "Feature",
  "properties": {
    "iso:country":"NZ",
    "sg:address":"4 Springswood Gro Springlands ",
    "sg:city":"Blenheim",
    "sg:orig_category":"Industrial: Services: Drillers",
    "sg:phone":"+64 21 343 089",
    "sg:province":"Marlborough",
    "wof:name":"Butt Drilling",
    "wof:placetype":"venue"
},
  "geometry": {"coordinates":[173.93855300000001,-41.508965],"type":"Point"}
}