{
  "type": "Feature",
  "properties": {
    "iso:country":"NZ",
    "sg:address":"Queen St ",
    "sg:city":"Masterton",
    "sg:orig_category":"Clothing And Fabric: Clothing: Women'S Fashions",
    "sg:phone":"+64 6-378 7582",
    "sg:province":"Wellington",
    "wof:name":"Milady 86 Ltd",
    "wof:placetype":"venue"
},
  "geometry": {"coordinates":[175.66812100000001,-40.945805],"type":"Point"}
}