{
  "type": "Feature",
  "properties": {
    "iso:country":"NZ",
    "sg:address":"4 B Cartwright Rd Glen Eden ",
    "sg:city":"Auckland",
    "sg:orig_category":"Industrial: Metal: Services: Metal Polishers",
    "sg:phone":"+64 9-818 3345",
    "sg:province":"Auckland",
    "wof:name":"Restoration Metal Polishing Ltd",
    "wof:placetype":"venue"
},
  "geometry": {"coordinates":[174.65711999999999,-36.901428],"type":"Point"}
}