{
  "type": "Feature",
  "properties": {
    "addr:full":"124 Rimu Rd  Paraparaumu Wellington",
    "addr:housenumber":"124",
    "addr:street":"Rimu Rd",
    "iso:country":"NZ",
    "sg:address":"124 Rimu Rd ",
    "sg:city":"Paraparaumu",
    "sg:classifiers":[
        {
            "category":"Shopping",
            "subcategory":"Crafts & Fabrics",
            "type":"Retail Goods"
        }
    ],
    "sg:phone":"+64 4-902 5212",
    "sg:province":"Wellington",
    "sg:tags":[
        "pottery",
        "home",
        "accessories",
        "garden",
        "supply"
    ],
    "wof:name":"Talisman Manufacturing",
    "wof:placetype":"venue"
},
  "geometry": {"coordinates":[175.00058000000001,-40.918491],"type":"Point"}
}