{
  "type": "Feature",
  "properties": {
    "iso:country":"NZ",
    "sg:address":"Wellington Dixon St ",
    "sg:city":"Masterton",
    "sg:classifiers":[
        {
            "category":"Utilities",
            "subcategory":"Electric",
            "type":"Services"
        }
    ],
    "sg:phone":"+64 6-377 5169",
    "sg:province":"Wellington",
    "sg:tags":[
        "energy",
        "industrial"
    ],
    "sg:website":"http://www.waggs.co.nz",
    "wof:name":"Waggs Of Masterton",
    "wof:placetype":"venue"
},
  "geometry": {"coordinates":[175.65733299999999,-40.94931],"type":"Point"}
}