{
  "type": "Feature",
  "properties": {
    "iso:country":"NZ",
    "sg:address":"72 Wellesley St W Auckland Central ",
    "sg:city":"Auckland",
    "sg:orig_category":"Shopping: Markets",
    "sg:phone":"+64 9-376 2367",
    "sg:province":"Auckland",
    "wof:name":"Mt Wellington Sunday Market",
    "wof:placetype":"venue"
},
  "geometry": {"coordinates":[174.760513,-36.84988],"type":"Point"}
}