{
  "type": "Feature",
  "properties": {
    "addr:full":"18 Deveron Pl Lindenvale  Wellington Wellington",
    "addr:housenumber":"18",
    "addr:street":"Deveron Pl",
    "iso:country":"NZ",
    "sg:address":"18 Deveron Pl Lindenvale ",
    "sg:city":"Wellington",
    "sg:classifiers":[
        {
            "category":"Shopping",
            "subcategory":"Bridal",
            "type":"Retail Goods"
        }
    ],
    "sg:phone":"+64 4-232 7641",
    "sg:province":"Wellington",
    "sg:tags":[
        "arrangements",
        "wear",
        "wedding"
    ],
    "wof:name":"Bi-Glamer",
    "wof:placetype":"venue"
},
  "geometry": {"coordinates":[174.82539399999999,-41.161362],"type":"Point"}
}