{
  "type": "Feature",
  "properties": {
    "iso:country":"NZ",
    "sg:address":"18 Rawson Way Takanini ",
    "sg:city":"Auckland",
    "sg:classifiers":[
        {
            "category":"Retail",
            "subcategory":"Driving School",
            "type":"Services"
        }
    ],
    "sg:phone":"+64 9-268 1274",
    "sg:province":"Auckland",
    "sg:tags":[
        "training",
        "education",
        "driver"
    ],
    "sg:website":"http://www.deca.co.nz",
    "wof:name":"DECA Training",
    "wof:placetype":"venue"
},
  "geometry": {"coordinates":[174.916748,-37.032585],"type":"Point"}
}