{
  "type": "Feature",
  "properties": {
    "addr:full":"273 High St  Masterton Wellington",
    "addr:housenumber":"273",
    "addr:street":"High St",
    "iso:country":"NZ",
    "sg:address":"273 High St ",
    "sg:city":"Masterton",
    "sg:classifiers":[
        {
            "category":"Home & Garden",
            "subcategory":"Building Materials",
            "type":"Retail Goods"
        }
    ],
    "sg:phone":"+64 6-378 7508",
    "sg:province":"Wellington",
    "sg:tags":[
        "builder",
        "related"
    ],
    "wof:name":"Initial Homes Madderom G W",
    "wof:placetype":"venue"
},
  "geometry": {"coordinates":[175.61842300000001,-40.962551],"type":"Point"}
}