{
  "type": "Feature",
  "properties": {
    "addr:full":"92 Broadway  St Manawatu-Wanganui",
    "addr:housenumber":"92",
    "addr:street":"Broadway St",
    "iso:country":"NZ",
    "sg:address":"92 Broadway ",
    "sg:city":"St",
    "sg:orig_category":"Clothing And Fabric: Clothing: Menswear",
    "sg:phone":"+64 7-888 7019",
    "sg:province":"Manawatu-Wanganui",
    "wof:name":"Farmers Trading Co Ltd",
    "wof:placetype":"venue"
},
  "geometry": {"coordinates":[170.36663799999999,-43.587711],"type":"Point"}
}