{
  "type": "Feature",
  "properties": {
    "iso:country":"NZ",
    "sg:address":"56 Cridland St ",
    "sg:city":"Kaiapoi",
    "sg:classifiers":[
        {
            "category":"Home & Garden",
            "subcategory":"Home Furnishings",
            "type":"Retail Goods"
        }
    ],
    "sg:phone":"+64 3-327 5711",
    "sg:tags":[
        "furniture/furnishings",
        "upholstery",
        "supply"
    ],
    "wof:name":"Smiths Upholstery Services",
    "wof:placetype":"venue"
},
  "geometry": {"coordinates":[172.656021,-43.375046],"type":"Point"}
}