{
  "type": "Feature",
  "properties": {
    "addr:full":"548 Don Buck Rd Massey  Auckland Auckland",
    "addr:housenumber":"548",
    "addr:street":"Don Buck Rd",
    "iso:country":"NZ",
    "sg:address":"548 Don Buck Rd Massey ",
    "sg:city":"Auckland",
    "sg:orig_category":"Sports And Leisure: Sports: Equestrian: Riding Schools",
    "sg:phone":"+64 9-833 6586",
    "sg:province":"Auckland",
    "wof:name":"Westgate Riding Academy",
    "wof:placetype":"venue"
},
  "geometry": {"coordinates":[174.60742200000001,-36.82299],"type":"Point"}
}