{
  "type": "Feature",
  "properties": {
    "addr:full":"Omuri R D 7  Wanganui Manawatu-Wanganui",
    "addr:housenumber":"7",
    "addr:street":"R D",
    "iso:country":"NZ",
    "sg:address":"Omuri R D 7 ",
    "sg:city":"Wanganui",
    "sg:classifiers":[
        {
            "category":"Sports & Exercise",
            "subcategory":"Swimming Pool",
            "type":"Entertainment"
        }
    ],
    "sg:phone":"+64 6-342 7809",
    "sg:province":"Manawatu-Wanganui",
    "sg:tags":[
        "home",
        "outdoor",
        "garden",
        "spa"
    ],
    "wof:name":"Lourie Pool Systems",
    "wof:placetype":"venue"
},
  "geometry": {"coordinates":[175.052841,-39.933369],"type":"Point"}
}