{
  "type": "Feature",
  "properties": {
    "addr:full":"Main Rd Tatapouri  Gisborne Gisborne",
    "addr:street":"Main Rd",
    "iso:country":"NZ",
    "sg:address":"Main Rd Tatapouri ",
    "sg:city":"Gisborne",
    "sg:orig_category":"Industrial: Services: Drillers",
    "sg:phone":"+64 6-868 6000",
    "sg:province":"Gisborne",
    "wof:name":"Farm Services",
    "wof:placetype":"venue"
},
  "geometry": {"coordinates":[177.975311,-38.648872],"type":"Point"}
}