{
  "type": "Feature",
  "properties": {
    "addr:full":"305 Akersten St Port Nelson  Nelson Nelson",
    "addr:housenumber":"305",
    "addr:street":"Akersten St",
    "iso:country":"NZ",
    "sg:address":"305 Akersten St Port Nelson ",
    "sg:city":"Nelson",
    "sg:classifiers":[
        {
            "category":"Farming",
            "subcategory":"Fish & Marine Products",
            "type":"Manufacturing & Wholesale Goods"
        }
    ],
    "sg:phone":"+64 3-546 7800",
    "sg:province":"Nelson",
    "sg:tags":[
        "-",
        "boat",
        "transport"
    ],
    "wof:name":"Challenge Marine Ltd",
    "wof:placetype":"venue"
},
  "geometry": {"coordinates":[173.284088,-41.255356],"type":"Point"}
}