{
  "type": "Feature",
  "properties": {
    "addr:full":"168 Dee St  Invercargill Southland",
    "addr:housenumber":"168",
    "addr:street":"Dee St",
    "iso:country":"NZ",
    "sg:address":"168 Dee St ",
    "sg:city":"Invercargill",
    "sg:classifiers":[
        {
            "category":"Manufacturing",
            "subcategory":"Tools & Machinery",
            "type":"Manufacturing & Wholesale Goods"
        }
    ],
    "sg:phone":"+64 3-218 2059",
    "sg:province":"Southland",
    "sg:tags":[
        "machine",
        "equipment",
        "industrial",
        "tools"
    ],
    "wof:name":"Hayes E & Sons Ltd",
    "wof:placetype":"venue"
},
  "geometry": {"coordinates":[168.34732099999999,-46.392628],"type":"Point"}
}