{
  "type": "Feature",
  "properties": {
    "addr:full":"144 Castlewood Rd RD 2  Dunedin Otago",
    "addr:housenumber":"144;2",
    "addr:street":"Castlewood Rd Rd",
    "iso:country":"NZ",
    "sg:address":"144 Castlewood Rd RD 2 ",
    "sg:city":"Dunedin",
    "sg:classifiers":[
        {
            "category":"Home & Garden",
            "subcategory":"Building Materials",
            "type":"Retail Goods"
        }
    ],
    "sg:phone":"+64 3-476 1166",
    "sg:province":"Otago",
    "sg:tags":[
        "door",
        "fitting",
        "fittings"
    ],
    "wof:name":"Coutts Ivan Joinery Ltd",
    "wof:placetype":"venue"
},
  "geometry": {"coordinates":[-82.784721,28.013355],"type":"Point"}
}