{
  "type": "Feature",
  "properties": {
    "addr:full":"Masterton Cosmopolitan Club, Queen St  Masterton Wellington",
    "addr:street":"Queen St",
    "iso:country":"NZ",
    "sg:address":"Masterton Cosmopolitan Club, Queen St ",
    "sg:city":"Masterton",
    "sg:classifiers":[
        {
            "category":"Restaurant",
            "type":"Food & Drink"
        }
    ],
    "sg:phone":"+64 6-377 0150",
    "sg:province":"Wellington",
    "sg:tags":[
        "wining",
        "dining"
    ],
    "wof:name":"Stewart Lounge",
    "wof:placetype":"venue"
},
  "geometry": {"coordinates":[175.66163599999999,-40.956474],"type":"Point"}
}