{
  "type": "Feature",
  "properties": {
    "iso:country":"NZ",
    "sg:address":"44 West End ",
    "sg:city":"Kaikoura",
    "sg:orig_category":"Shopping: Hobbies And Games: Handcrafts",
    "sg:phone":"+64 3-319 6416",
    "sg:province":"Canterbury",
    "wof:name":"Sealside Gallery",
    "wof:placetype":"venue"
},
  "geometry": {"coordinates":[173.679596,-42.399712],"type":"Point"}
}