{
  "type": "Feature",
  "properties": {
    "iso:country":"NZ",
    "sg:address":"8 Robina Pl Snells Beach ",
    "sg:city":"Warkworth",
    "sg:orig_category":"Automotive: Accessories: Motor Accessories",
    "sg:phone":"+64 9-425 5968",
    "sg:province":"Auckland",
    "wof:name":"McKenzie Design Ltd",
    "wof:placetype":"venue"
},
  "geometry": {"coordinates":[174.727402,-36.42046],"type":"Point"}
}