{
  "type": "Feature",
  "properties": {
    "iso:country":"NZ",
    "sg:address":"Floor 1 286 a Stafford St ",
    "sg:city":"Timaru",
    "sg:classifiers":[
        {
            "category":"Education",
            "subcategory":"Dance Studio",
            "type":"Public Place"
        }
    ],
    "sg:phone":"+64 21 1471 809",
    "sg:province":"Canterbury",
    "sg:tags":[
        "school",
        "dancing",
        "-",
        "leisure",
        "sports",
        "sport"
    ],
    "wof:name":"Jazz Feet Studio Of Dance - Sharron Ritchie-Francis",
    "wof:placetype":"venue"
},
  "geometry": {"coordinates":[171.25114400000001,-44.394348],"type":"Point"}
}