{
  "type": "Feature",
  "properties": {
    "iso:country":"NZ",
    "sg:address":"26 Margaret Pl Omokoroa ",
    "sg:city":"Tauranga",
    "sg:classifiers":[
        {
            "category":"Building & Trades",
            "subcategory":"Plumbing",
            "type":"Services"
        }
    ],
    "sg:phone":"+64 7-548 0206",
    "sg:province":"Bay of Plenty",
    "sg:tags":[
        "home",
        "plumber",
        "garden",
        "related"
    ],
    "wof:name":"Omokoroa Plumbing Ltd",
    "wof:placetype":"venue"
},
  "geometry": {"coordinates":[176.14475999999999,-37.703152],"type":"Point"}
}