{
  "type": "Feature",
  "properties": {
    "iso:country":"NZ",
    "sg:address":"26 Alexander St Palmerston ",
    "sg:city":"Palmerston North",
    "sg:classifiers":[
        {
            "category":"Social Services",
            "subcategory":"Child Care",
            "type":"Services"
        }
    ],
    "sg:phone":"+64 6-356 6775",
    "sg:province":"Manawatu-Wanganui",
    "sg:tags":[
        "home",
        "garden",
        "children"
    ],
    "wof:name":"Te Reo Tupua O Awapuni",
    "wof:placetype":"venue"
},
  "geometry": {"coordinates":[175.584961,-40.374153],"type":"Point"}
}