{
  "type": "Feature",
  "properties": {
    "iso:country":"NZ",
    "sg:address":"258 Childers Rd ",
    "sg:city":"Gisborne",
    "sg:classifiers":[
        {
            "category":"Banks & Credit Unions",
            "subcategory":"Financial Services",
            "type":"Services"
        }
    ],
    "sg:phone":"+64 6-867 9572",
    "sg:province":"Gisborne",
    "sg:tags":[
        "personal",
        "loan",
        "-",
        "finance",
        "mortgage"
    ],
    "wof:name":"Mortgage Link Eastland Ltd",
    "wof:placetype":"venue"
},
  "geometry": {"coordinates":[178.020981,-38.664867],"type":"Point"}
}