{
  "type": "Feature",
  "properties": {
    "iso:country":"NZ",
    "sg:address":"PO Box 11-444 ",
    "sg:city":"Wellington",
    "sg:orig_category":"Transport: Boats And Marine: Services",
    "sg:phone":"+64 4-385 3199",
    "sg:province":"Wellington",
    "wof:name":"Flinders Cook Limited",
    "wof:placetype":"venue"
},
  "geometry": {"coordinates":[-105.037888,40.762012],"type":"Point"}
}