{
  "type": "Feature",
  "properties": {
    "iso:country":"NZ",
    "sg:address":"5 Taylor St Green Island ",
    "sg:city":"Dunedin",
    "sg:classifiers":[
        {
            "category":"Manufacturing",
            "subcategory":"Food",
            "type":"Manufacturing & Wholesale Goods"
        }
    ],
    "sg:phone":"+64 3-488 1960",
    "sg:province":"Otago",
    "sg:tags":[
        "processing",
        "drink"
    ],
    "wof:name":"Konig Smokehouse",
    "wof:placetype":"venue"
},
  "geometry": {"coordinates":[170.439133,-45.903397],"type":"Point"}
}