{
  "type": "Feature",
  "properties": {
    "iso:country":"NZ",
    "sg:address":"PO Box 76 ",
    "sg:city":"Kaeo",
    "sg:classifiers":[
        {
            "category":"Bus Charters",
            "type":"Transportation"
        }
    ],
    "sg:phone":"+64 9-405 0478",
    "sg:tags":[
        "services",
        "travel",
        "tourism"
    ],
    "wof:name":"Stewart Buses",
    "wof:placetype":"venue"
},
  "geometry": {"coordinates":[173.774139,-35.098103],"type":"Point"}
}