{
  "type": "Feature",
  "properties": {
    "iso:country":"NZ",
    "sg:address":"2 Spey St ",
    "sg:city":"Invercargill",
    "sg:classifiers":[
        {
            "category":"Bus Charters",
            "type":"Transportation"
        }
    ],
    "sg:phone":"+64 3-218 2419",
    "sg:province":"Southland",
    "sg:tags":[
        "services",
        "travel",
        "tourism"
    ],
    "wof:name":"McDermotts Coaches Ltd",
    "wof:placetype":"venue"
},
  "geometry": {"coordinates":[168.345642,-46.409679],"type":"Point"}
}