{
  "type": "Feature",
  "properties": {
    "iso:country":"NZ",
    "sg:address":"75 Union St ",
    "sg:city":"Hawera",
    "sg:classifiers":[
        {
            "category":"Retail",
            "subcategory":"Auto Repair",
            "type":"Services"
        }
    ],
    "sg:phone":"+64 6-278 4201",
    "sg:province":"Taranaki",
    "sg:tags":[
        "wheel",
        "automotive",
        "servicing",
        "alignment"
    ],
    "wof:name":"Sandilands Wheel Alignment",
    "wof:placetype":"venue"
},
  "geometry": {"coordinates":[174.284637,-39.58456],"type":"Point"}
}