{
  "type": "Feature",
  "properties": {
    "iso:country":"NZ",
    "sg:address":"87 Kitchener Rd Milford ",
    "sg:city":"Auckland",
    "sg:classifiers":[
        {
            "category":"Coffee & Tea",
            "type":"Food & Drink"
        }
    ],
    "sg:phone":"+64 9-488 0818",
    "sg:province":"Auckland",
    "sg:tags":[
        "merchant"
    ],
    "wof:name":"Tea Total",
    "wof:placetype":"venue"
},
  "geometry": {"coordinates":[174.767242,-36.773052],"type":"Point"}
}