{
  "type": "Feature",
  "properties": {
    "iso:country":"NZ",
    "sg:address":"6 Spey St ",
    "sg:city":"Invercargill",
    "sg:orig_category":"Industrial: Engineering: Engineers - Precision",
    "sg:phone":"+64 3-218 7265",
    "sg:province":"Southland",
    "wof:name":"McLeay Precision Engineering Ltd",
    "wof:placetype":"venue"
},
  "geometry": {"coordinates":[168.339722,-46.409492],"type":"Point"}
}