{
  "type": "Feature",
  "properties": {
    "iso:country":"NZ",
    "sg:address":"300 Victoria Ave ",
    "sg:city":"Wanganui",
    "sg:classifiers":[
        {
            "category":"Autos & Motor Vehicles",
            "subcategory":"Automobile Sales",
            "type":"Retail Goods"
        }
    ],
    "sg:phone":"+64 6-348 8850",
    "sg:province":"Manawatu-Wanganui",
    "sg:tags":[
        "leasing",
        "car",
        "-",
        "truck",
        "automotive",
        "new"
    ],
    "wof:name":"Wanganui Toyota",
    "wof:placetype":"venue"
},
  "geometry": {"coordinates":[175.04392999999999,-39.927933],"type":"Point"}
}