{
  "type": "Feature",
  "properties": {
    "iso:country":"NZ",
    "sg:address":"66 Bloomfield Tce Lower ",
    "sg:city":"Hutt",
    "sg:orig_category":"Health And Beauty: Dental: Dentists",
    "sg:phone":"+64 4-566 1119",
    "sg:province":"Wellington",
    "wof:name":"Yee Graeme Dental Care Trust (BDS)",
    "wof:placetype":"venue"
},
  "geometry": {"coordinates":[174.904526,-41.208431],"type":"Point"}
}