{
  "type": "Feature",
  "properties": {
    "addr:full":"15 Vickery St Te Rapa  Hamilton Waikato",
    "addr:housenumber":"15",
    "addr:street":"Vickery St",
    "iso:country":"NZ",
    "sg:address":"15 Vickery St Te Rapa ",
    "sg:city":"Hamilton",
    "sg:classifiers":[
        {
            "category":"Manufacturing",
            "subcategory":"Metals",
            "type":"Manufacturing & Wholesale Goods"
        }
    ],
    "sg:phone":"+64 7-849 2274",
    "sg:province":"Waikato",
    "sg:tags":[
        "-",
        "engineering",
        "industrial",
        "sheet",
        "engineer"
    ],
    "wof:name":"HMF Engineering",
    "wof:placetype":"venue"
},
  "geometry": {"coordinates":[175.247345,-37.755363],"type":"Point"}
}