{
  "type": "Feature",
  "properties": {
    "iso:country":"NZ",
    "sg:address":"7/11 Britannia St Petone ",
    "sg:city":"Wellington",
    "sg:classifiers":[
        {
            "category":"Transit Center",
            "subcategory":"Freight",
            "type":"Transportation"
        }
    ],
    "sg:phone":"+64 4-939 1691",
    "sg:province":"Wellington",
    "sg:tags":[
        "distribution",
        "-",
        "transport"
    ],
    "wof:name":"Homecare Distribution",
    "wof:placetype":"venue"
},
  "geometry": {"coordinates":[174.87951699999999,-41.22448],"type":"Point"}
}