{
  "type": "Feature",
  "properties": {
    "iso:country":"NZ",
    "sg:address":"Albany Highway Albany ",
    "sg:city":"Auckland",
    "sg:classifiers":[
        {
            "category":"Shopping",
            "subcategory":"Pets & Pet Supplies",
            "type":"Retail Goods"
        }
    ],
    "sg:phone":"+64 9-415 8909",
    "sg:province":"Auckland",
    "sg:tags":[
        "home",
        "garden"
    ],
    "wof:name":"Albany Veterinary Hospital & Pet centre",
    "wof:placetype":"venue"
},
  "geometry": {"coordinates":[-85.207489,36.739761],"type":"Point"}
}