{
  "type": "Feature",
  "properties": {
    "iso:country":"NZ",
    "sg:address":"Thames ",
    "sg:city":"Hamilton",
    "sg:classifiers":[
        {
            "category":"Home & Garden",
            "subcategory":"Furniture",
            "type":"Retail Goods"
        }
    ],
    "sg:phone":"+64 800 616 188",
    "sg:province":"Waikato",
    "sg:tags":[
        "fitting"
    ],
    "sg:website":"http://www.yellowpages.co.nz/for/readyhire/dp38646.html",
    "wof:name":"Ready Hire",
    "wof:placetype":"venue"
},
  "geometry": {"coordinates":[175.27699279789999,-37.7832107544],"type":"Point"}
}