{
  "type": "Feature",
  "properties": {
    "iso:country":"NZ",
    "sg:address":"77 Devonport Rd ",
    "sg:city":"Tauranga",
    "sg:classifiers":[
        {
            "category":"Professional",
            "subcategory":"Art Services",
            "type":"Services"
        }
    ],
    "sg:phone":"+64 7-571 1000",
    "sg:province":"Auckland",
    "sg:tags":[
        "picture",
        "arts",
        "sport",
        "framing",
        "leisure"
    ],
    "wof:name":"Devonport Framing Studio",
    "wof:placetype":"venue"
},
  "geometry": {"coordinates":[176.16925,-37.686024],"type":"Point"}
}