{
  "type": "Feature",
  "properties": {
    "iso:country":"NZ",
    "sg:address":"C/- Don McKay Pharmacy 349 Lake Rd (Hauraki Cnr) Takapuna",
    "sg:city":"Auckland",
    "sg:orig_category":"Health And Beauty: Specialists: Podiatrists",
    "sg:phone":"+64 9-489 3026",
    "sg:province":"Auckland",
    "wof:name":"Knight Geoffrey F Podiatrist",
    "wof:placetype":"venue"
},
  "geometry": {"coordinates":[174.767883,-36.787838],"type":"Point"}
}