{
  "type": "Feature",
  "properties": {
    "iso:country":"NZ",
    "sg:address":"9-11 Fairfax Ave Penrose ",
    "sg:city":"Auckland",
    "sg:orig_category":"Automotive: Accessories",
    "sg:phone":"+64 9-580 0477",
    "sg:province":"Auckland",
    "wof:name":"VanExtras",
    "wof:placetype":"venue"
},
  "geometry": {"coordinates":[174.81044,-36.912621],"type":"Point"}
}