{
  "type": "Feature",
  "properties": {
    "iso:country":"NZ",
    "sg:address":"168 Broadway North ",
    "sg:city":"Stratford",
    "sg:orig_category":"Industrial: Products: Window Control Gear",
    "sg:phone":"+64 6-765 5580",
    "sg:province":"Manawatu-Wanganui",
    "wof:name":"Designer Security Doors",
    "wof:placetype":"venue"
},
  "geometry": {"coordinates":[174.30183400000001,-39.317245],"type":"Point"}
}