{
  "type": "Feature",
  "properties": {
    "iso:country":"NZ",
    "sg:address":"375 Parnell Rd Parnell ",
    "sg:city":"Auckland",
    "sg:classifiers":[
        {
            "category":"Food Court",
            "type":"Food & Drink"
        }
    ],
    "sg:phone":"+64 9-309 0444",
    "sg:province":"Auckland",
    "sg:tags":[
        "manufacturer"
    ],
    "wof:name":"Mt Aspiring Water Co Ltd",
    "wof:placetype":"venue"
},
  "geometry": {"coordinates":[174.782242,-36.858284],"type":"Point"}
}