{
  "type": "Feature",
  "properties": {
    "addr:full":"Spring Grove  Wakefield Auckland",
    "addr:street":"Spring Grove",
    "iso:country":"NZ",
    "sg:address":"Spring Grove ",
    "sg:city":"Wakefield",
    "sg:orig_category":"Farming: Forestry: Logging Services",
    "sg:phone":"+64 3-541 8711",
    "sg:province":"Auckland",
    "wof:name":"Carter Holt Harvey Forest Fibre Solutions",
    "wof:placetype":"venue"
},
  "geometry": {"coordinates":[173.082855,-41.390339],"type":"Point"}
}