{
  "type": "Feature",
  "properties": {
    "addr:full":"Taupiri St Te  Kuiti",
    "addr:street":"Taupiri St",
    "iso:country":"NZ",
    "sg:address":"Taupiri St Te ",
    "sg:city":"Kuiti",
    "sg:classifiers":[
        {
            "category":"Food & Beverages",
            "subcategory":"Liquor & Beverages",
            "type":"Retail Goods"
        }
    ],
    "sg:phone":"+64 7-878 8172",
    "sg:tags":[
        "drink",
        "outlet"
    ],
    "wof:name":"Te Kuiti Hotel Wholesale",
    "wof:placetype":"venue"
},
  "geometry": {"coordinates":[175.16229200000001,-38.330608],"type":"Point"}
}