{
  "type": "Feature",
  "properties": {
    "iso:country":"NZ",
    "sg:address":"Portland Rd ",
    "sg:city":"Portland",
    "sg:orig_category":"Sports And Leisure: Entertainment: Entertainers",
    "sg:phone":"+64 25531048",
    "wof:name":"Advance Amusements",
    "wof:placetype":"venue"
},
  "geometry": {"coordinates":[-91.381348,33.212421],"type":"Point"}
}