{
  "type": "Feature",
  "properties": {
    "iso:country":"NZ",
    "sg:address":"496 Bainfield Rd Waikiwi RD 2 ",
    "sg:city":"Invercargill",
    "sg:orig_category":"Home And Garden: Gardening: Services: Tree Services",
    "sg:phone":"+64 274 333 205",
    "sg:province":"Southland",
    "wof:name":"Dowling Mark J",
    "wof:placetype":"venue"
},
  "geometry": {"coordinates":[168.352173,-46.411854],"type":"Point"}
}