{
  "type": "Feature",
  "properties": {
    "iso:country":"NZ",
    "sg:address":"161 Parnell Rd ",
    "sg:city":"Auckland",
    "sg:classifiers":[
        {
            "category":"Professional",
            "type":"Services"
        }
    ],
    "sg:phone":"+64 9-366 1758",
    "sg:province":"Auckland",
    "sg:tags":[
        "function",
        "entertainment",
        "leisure",
        "planning",
        "party",
        "sport"
    ],
    "wof:name":"Seattle Bar",
    "wof:placetype":"venue"
},
  "geometry": {"coordinates":[174.779495,-36.854084],"type":"Point"}
}