{
  "type": "Feature",
  "properties": {
    "iso:country":"NZ",
    "sg:address":"9 Weld St",
    "sg:city":"Hokitika",
    "sg:classifiers":[
        {
            "category":"Banks & Credit Unions",
            "subcategory":"Bank",
            "type":"Services"
        }
    ],
    "sg:phone":"+64 2881213",
    "sg:province":"West Coast",
    "wof:name":"Bank of New Zealand",
    "wof:placetype":"venue"
},
  "geometry": {"coordinates":[170.964645,-42.718636],"type":"Point"}
}