{
  "type": "Feature",
  "properties": {
    "iso:country":"NZ",
    "sg:address":"13 Woodside Rd Matangi ",
    "sg:city":"Hamilton",
    "sg:classifiers":[
        {
            "category":"Shopping",
            "subcategory":"Pharmacy",
            "type":"Retail Goods"
        }
    ],
    "sg:phone":"+64 7-847 1588",
    "sg:province":"Waikato",
    "sg:tags":[
        "products",
        "medical",
        "health",
        "beauty",
        "supply"
    ],
    "wof:name":"Weldon Medical",
    "wof:placetype":"venue"
},
  "geometry": {"coordinates":[175.405716,-37.792549],"type":"Point"}
}