{
  "type": "Feature",
  "properties": {
    "iso:country":"NZ",
    "sg:address":"John St ",
    "sg:city":"Balclutha",
    "sg:classifiers":[
        {
            "category":"Home & Garden",
            "subcategory":"Building Materials",
            "type":"Retail Goods"
        }
    ],
    "sg:phone":"+64 3-418 2762",
    "sg:tags":[
        "electrician",
        "related"
    ],
    "wof:name":"Mosley Ross Electrical",
    "wof:placetype":"venue"
},
  "geometry": {"coordinates":[169.73999,-46.240398],"type":"Point"}
}