{
  "type": "Feature",
  "properties": {
    "addr:full":"Queen St Wellington Wellington",
    "addr:street":"Queen St",
    "iso:country":"NZ",
    "sg:address":"Queen St",
    "sg:city":"Wellington",
    "sg:classifiers":[
        {
            "category":"Banks & Credit Unions",
            "subcategory":"Bank",
            "type":"Services"
        }
    ],
    "sg:phone":"+64 4648617",
    "sg:province":"Wellington",
    "wof:name":"National Bank of NZ Ltd",
    "wof:placetype":"venue"
},
  "geometry": {"coordinates":[-103.86666099999999,49.8862],"type":"Point"}
}