{
  "type": "Feature",
  "properties": {
    "addr:full":"370 Tuam St  Christchurch Canterbury",
    "addr:housenumber":"370",
    "addr:street":"Tuam St",
    "iso:country":"NZ",
    "sg:address":"370 Tuam St ",
    "sg:city":"Christchurch",
    "sg:classifiers":[
        {
            "category":"Retail",
            "subcategory":"Auto Repair",
            "type":"Services"
        }
    ],
    "sg:phone":"+64 3-379 4493",
    "sg:province":"Canterbury",
    "sg:tags":[
        "automotive",
        "absorber",
        "shock",
        "servicing"
    ],
    "wof:name":"Fully Equipped Canterbury",
    "wof:placetype":"venue"
},
  "geometry": {"coordinates":[-76.537834,37.605659],"type":"Point"}
}