{
  "type": "Feature",
  "properties": {
    "addr:full":"Gillies St  Cambridge Waikato",
    "addr:street":"Gillies St",
    "iso:country":"NZ",
    "sg:address":"Gillies St ",
    "sg:city":"Cambridge",
    "sg:orig_category":"Shopping: Retail Stores: Batteries",
    "sg:phone":"+64 7-827 6159",
    "sg:province":"Waikato",
    "wof:name":"Cambridge Auto Electric 1999 Ltd",
    "wof:placetype":"venue"
},
  "geometry": {"coordinates":[-73.469353,43.049637],"type":"Point"}
}