{
  "type": "Feature",
  "properties": {
    "iso:country":"NZ",
    "sg:address":"Swansea St ",
    "sg:city":"Middlemarch",
    "sg:orig_category":"Shopping: Retail Stores: Supermarkets",
    "sg:phone":"+64 3-464 3092",
    "wof:name":"Middlemarch Railhead Store",
    "wof:placetype":"venue"
},
  "geometry": {"coordinates":[-71.192886,41.74947],"type":"Point"}
}