{
  "type": "Feature",
  "properties": {
    "addr:full":"Main Rd  Riwaka",
    "addr:street":"Main Rd",
    "iso:country":"NZ",
    "sg:address":"Main Rd ",
    "sg:city":"Riwaka",
    "sg:classifiers":[
        {
            "category":"Retail",
            "subcategory":"Auto Repair",
            "type":"Services"
        }
    ],
    "sg:phone":"+64 252292051",
    "sg:tags":[
        "mobile",
        "automotive",
        "servicing",
        "mechanic"
    ],
    "wof:name":"Robin's Mobile Mechanic Services",
    "wof:placetype":"venue"
},
  "geometry": {"coordinates":[172.99679599999999,-41.088619],"type":"Point"}
}