{
  "type": "Feature",
  "properties": {
    "addr:full":"B/187 Dee St  Invercargill Southland",
    "addr:housenumber":"/ 187",
    "addr:street":"Dee St",
    "iso:country":"NZ",
    "sg:address":"B/187 Dee St ",
    "sg:city":"Invercargill",
    "sg:orig_category":"Shopping: Retail Stores: Books: Books - Secondhand",
    "sg:phone":"+64 3-214 0620",
    "sg:province":"Southland",
    "wof:name":"Browse Around Book Exchange",
    "wof:placetype":"venue"
},
  "geometry": {"coordinates":[168.35217299999999,-46.411854],"type":"Point"}
}