{
  "type": "Feature",
  "properties": {
    "iso:country":"NZ",
    "sg:address":"53 Victoria St Onehunga ",
    "sg:city":"Auckland",
    "sg:classifiers":[
        {
            "category":"Manufacturing",
            "subcategory":"Glass & Minerals",
            "type":"Manufacturing & Wholesale Goods"
        }
    ],
    "sg:phone":"+64 9-636 7324",
    "sg:province":"Auckland",
    "sg:tags":[
        "raw",
        "industrial",
        "-",
        "materials"
    ],
    "wof:name":"Sand Resources (NZ) Ltd",
    "wof:placetype":"venue"
},
  "geometry": {"coordinates":[174.79260300000001,-36.924904],"type":"Point"}
}