{
  "type": "Feature",
  "properties": {
    "iso:country":"NZ",
    "sg:address":"17 Adelaide Rd Newtown ",
    "sg:city":"Wellington",
    "sg:classifiers":[
        {
            "category":"Shopping",
            "subcategory":"Beauty & Cosmetics",
            "type":"Retail Goods"
        }
    ],
    "sg:phone":"+64 4-384 7537",
    "sg:province":"Wellington",
    "sg:tags":[
        "specialist",
        "health",
        "x-ray",
        "specialists"
    ],
    "wof:name":"Wakefield Express (X-Rays only)",
    "wof:placetype":"venue"
},
  "geometry": {"coordinates":[174.777908,-41.30727],"type":"Point"}
}