{
  "type": "Feature",
  "properties": {
    "addr:full":"cnr Newbury & Bairds Rds Otara  Auckland Auckland",
    "addr:housenumber":"cnr;otara",
    "addr:street":"Newbury & Bairds Rds",
    "iso:country":"NZ",
    "sg:address":"cnr Newbury & Bairds Rds Otara ",
    "sg:city":"Auckland",
    "sg:classifiers":[
        {
            "category":"Banks & Credit Unions",
            "subcategory":"Investment Brokerage",
            "type":"Services"
        }
    ],
    "sg:phone":"+64 9-272 3921",
    "sg:province":"Auckland",
    "sg:tags":[
        "educational",
        "education",
        "training"
    ],
    "wof:name":"Creative Learning Scheme",
    "wof:placetype":"venue"
},
  "geometry": {"coordinates":[174.874664,-36.960999],"type":"Point"}
}