{
  "type": "Feature",
  "properties": {
    "addr:full":"Unit S 86 Bush Rd Albany  Auckland Auckland",
    "addr:housenumber":"86",
    "addr:street":"Bush Rd",
    "iso:country":"NZ",
    "sg:address":"Unit S 86 Bush Rd Albany ",
    "sg:city":"Auckland",
    "sg:classifiers":[
        {
            "category":"Retail",
            "subcategory":"Repair Shop",
            "type":"Services"
        }
    ],
    "sg:phone":"+64 9-415 8998",
    "sg:province":"Auckland",
    "sg:tags":[
        "clothing",
        "fabric",
        "cleaning"
    ],
    "wof:name":"Shore Fit Clothing Alterations",
    "wof:placetype":"venue"
},
  "geometry": {"coordinates":[174.709686,-36.720142],"type":"Point"}
}