{
  "type": "Feature",
  "properties": {
    "addr:full":"Kew Bowl Elles Rd Heidelberg  Invercargill Southland",
    "addr:street":"Elles Rd",
    "iso:country":"NZ",
    "sg:address":"Kew Bowl Elles Rd Heidelberg ",
    "sg:city":"Invercargill",
    "sg:classifiers":[
        {
            "category":"Arena",
            "subcategory":"Sports Club",
            "type":"Entertainment"
        }
    ],
    "sg:phone":"+64 3-216 5112",
    "sg:province":"Southland",
    "sg:tags":[
        "-",
        "leisure",
        "sports"
    ],
    "wof:name":"Cycling Southland",
    "wof:placetype":"venue"
},
  "geometry": {"coordinates":[168.38282799999999,-46.429733],"type":"Point"}
}