{
  "type": "Feature",
  "properties": {
    "iso:country":"NZ",
    "sg:address":"1 Kingdon St Newmarket ",
    "sg:city":"Auckland",
    "sg:orig_category":"Shopping: Retail Stores: Antiques",
    "sg:phone":"+64 9-522 0666",
    "sg:province":"Auckland",
    "wof:name":"Van Westen Antique Studio",
    "wof:placetype":"venue"
},
  "geometry": {"coordinates":[174.776215,-36.86713],"type":"Point"}
}