{
  "type": "Feature",
  "properties": {
    "addr:full":"Auckland Airport  Auckland Auckland",
    "iso:country":"NZ",
    "sg:address":"Auckland Airport ",
    "sg:city":"Auckland",
    "sg:classifiers":[
        {
            "category":"Health Services",
            "subcategory":"Clinic",
            "type":"Services"
        }
    ],
    "sg:phone":"+64 25755759",
    "sg:province":"Auckland",
    "sg:tags":[
        "trainer",
        "personal",
        "beauty",
        "fitness"
    ],
    "wof:name":"Simple Science",
    "wof:placetype":"venue"
},
  "geometry": {"coordinates":[174.782104,-37.008541],"type":"Point"}
}