{
  "type": "Feature",
  "properties": {
    "addr:full":"State Highway 10  Kerikeri Northland",
    "addr:street":"State Highway 10 Kerikeri",
    "iso:country":"NZ",
    "sg:address":"State Highway 10 ",
    "sg:city":"Kerikeri",
    "sg:orig_category":"Travel And Tourism: Accommodation: Backpackers",
    "sg:phone":"+64 9-407 6989",
    "sg:province":"Northland",
    "wof:name":"Kerikeri Farm Hostel",
    "wof:placetype":"venue"
},
  "geometry": {"coordinates":[173.93412799999999,-35.256813],"type":"Point"}
}