{
  "type": "Feature",
  "properties": {
    "iso:country":"NZ",
    "sg:address":"Hamilton, Chartwell ",
    "sg:city":"Hamilton",
    "sg:classifiers":[
        {
            "category":"Health Services",
            "subcategory":"Optometrist",
            "type":"Services"
        }
    ],
    "sg:phone":"+64 7-834 1511",
    "sg:province":"Waikato",
    "sg:tags":[
        "optical",
        "beauty"
    ],
    "sg:website":"http://www.opsm.com",
    "wof:name":"OPSM Limited",
    "wof:placetype":"venue"
},
  "geometry": {"coordinates":[175.27124,-37.763649],"type":"Point"}
}