{
  "type": "Feature",
  "properties": {
    "addr:full":"Innes St West  Gisborne Gisborne",
    "addr:street":"Innes St",
    "iso:country":"NZ",
    "sg:address":"Innes St West ",
    "sg:city":"Gisborne",
    "sg:classifiers":[
        {
            "category":"Bars & Pubs",
            "type":"Food & Drink"
        }
    ],
    "sg:phone":"+64 6-867 9089",
    "sg:province":"Gisborne",
    "wof:name":"GisVin Ltd",
    "wof:placetype":"venue"
},
  "geometry": {"coordinates":[177.997604,-38.663677],"type":"Point"}
}