{
  "type": "Feature",
  "properties": {
    "iso:country":"NZ",
    "sg:address":"505 Mt Wellington Hwy Mt Wellington ",
    "sg:city":"Auckland",
    "sg:classifiers":[
        {
            "category":"Shopping",
            "subcategory":"Pharmacy",
            "type":"Retail Goods"
        }
    ],
    "sg:phone":"+64 9-573 3730",
    "sg:province":"Auckland",
    "sg:tags":[
        "product",
        "health"
    ],
    "sg:website":"http://www.healtheries.co.nz",
    "wof:name":"Healtheries Of New Zealand Ltd",
    "wof:placetype":"venue"
},
  "geometry": {"coordinates":[174.841339,-36.924622],"type":"Point"}
}