{
  "type": "Feature",
  "properties": {
    "addr:full":"52 Fremlin Pl Avondale  Auckland Auckland",
    "addr:housenumber":"52",
    "addr:street":"Fremlin Pl",
    "iso:country":"NZ",
    "sg:address":"52 Fremlin Pl Avondale ",
    "sg:city":"Auckland",
    "sg:classifiers":[
        {
            "category":"Banks & Credit Unions",
            "subcategory":"Investment Brokerage",
            "type":"Services"
        }
    ],
    "sg:phone":"+64 9-828 2587",
    "sg:province":"Auckland",
    "sg:tags":[
        "chemical",
        "industrial",
        "-",
        "compounds"
    ],
    "wof:name":"Baker Petrolite",
    "wof:placetype":"venue"
},
  "geometry": {"coordinates":[174.690933,-36.8932],"type":"Point"}
}