{
  "type": "Feature",
  "properties": {
    "addr:full":"237 Stanley Rd  Gisborne Gisborne",
    "addr:housenumber":"237",
    "addr:street":"Stanley Rd",
    "iso:country":"NZ",
    "sg:address":"237 Stanley Rd ",
    "sg:city":"Gisborne",
    "sg:classifiers":[
        {
            "category":"Sports & Exercise",
            "subcategory":"Swimming Pool",
            "type":"Entertainment"
        }
    ],
    "sg:phone":"+64 6-868 1930",
    "sg:province":"Gisborne",
    "sg:tags":[
        "home",
        "outdoor",
        "garden",
        "spa"
    ],
    "wof:name":"Mayfair Pools",
    "wof:placetype":"venue"
},
  "geometry": {"coordinates":[178.00410500000001,-38.667965],"type":"Point"}
}