{
  "type": "Feature",
  "properties": {
    "iso:country":"NZ",
    "sg:address":"Greenlane ",
    "sg:city":"Auckland",
    "sg:classifiers":[
        {
            "category":"Building & Trades",
            "subcategory":"Pest Control",
            "type":"Services"
        }
    ],
    "sg:phone":"+64 9-525 5529",
    "sg:province":"Auckland",
    "sg:tags":[
        "home",
        "garden"
    ],
    "wof:name":"Flea & Cockroach Co",
    "wof:placetype":"venue"
},
  "geometry": {"coordinates":[174.79191599999999,-36.892967],"type":"Point"}
}