{
  "type": "Feature",
  "properties": {
    "addr:full":"10 Manuka St  Taupo Waikato",
    "addr:housenumber":"10",
    "addr:street":"Manuka St",
    "iso:country":"NZ",
    "sg:address":"10 Manuka St ",
    "sg:city":"Taupo",
    "sg:classifiers":[
        {
            "category":"Wholesale",
            "subcategory":"Machinery & Supplies",
            "type":"Manufacturing & Wholesale Goods"
        }
    ],
    "sg:phone":"+64 7-378 8138",
    "sg:province":"Waikato",
    "sg:tags":[
        "equipment",
        "crane",
        "industrial",
        "hoist",
        "lifting"
    ],
    "wof:name":"McPhee Engineering & Crane Hire",
    "wof:placetype":"venue"
},
  "geometry": {"coordinates":[176.10514800000001,-38.691128],"type":"Point"}
}