{
  "type": "Feature",
  "properties": {
    "iso:country":"NZ",
    "sg:address":"5 Anita Ave Mt Roskill ",
    "sg:city":"Auckland",
    "sg:orig_category":"Sports And Leisure: Sports: Golf",
    "sg:phone":"+64 9-621 0090",
    "sg:province":"Auckland",
    "wof:name":"Maungakiekie Golf Club",
    "wof:placetype":"venue"
},
  "geometry": {"coordinates":[174.74276699999999,-36.905895],"type":"Point"}
}