{
  "type": "Feature",
  "properties": {
    "addr:full":"OROMAHOE State Highway 10  Ohaeawai",
    "addr:street":"State Highway 10 Ohaeawai",
    "iso:country":"NZ",
    "sg:address":"OROMAHOE State Highway 10 ",
    "sg:city":"Ohaeawai",
    "sg:classifiers":[
        {
            "category":"Food & Beverages",
            "subcategory":"Cheese",
            "type":"Retail Goods"
        }
    ],
    "sg:phone":"+64 9-405 9681",
    "sg:tags":[
        "merchant",
        "drink",
        "-"
    ],
    "wof:name":"Mahoe Cheese Factory",
    "wof:placetype":"venue"
},
  "geometry": {"coordinates":[173.96644599999999,-35.309479],"type":"Point"}
}