{
  "type": "Feature",
  "properties": {
    "iso:country":"NZ",
    "sg:address":"1235 Tutanekai St ",
    "sg:city":"Rotorua",
    "sg:classifiers":[
        {
            "category":"Travel",
            "subcategory":"Travel Agent",
            "type":"Entertainment"
        }
    ],
    "sg:phone":"+64 7-347 6227",
    "sg:province":"Bay of Plenty",
    "sg:tags":[
        "tourism",
        "broker"
    ],
    "wof:name":"Holiday Shoppe",
    "wof:placetype":"venue"
},
  "geometry": {"coordinates":[176.251389,-38.137398],"type":"Point"}
}