{
  "type": "Feature",
  "properties": {
    "addr:full":"Christchurch Studio 494 A Colombo St Sydenham  Christchurch Canterbury",
    "addr:housenumber":"494 a",
    "addr:street":"Colombo St",
    "iso:country":"NZ",
    "sg:address":"Christchurch Studio 494 A Colombo St Sydenham ",
    "sg:city":"Christchurch",
    "sg:classifiers":[
        {
            "category":"Personal",
            "subcategory":"Tattoo Parlor",
            "type":"Services"
        }
    ],
    "sg:phone":"+64 3-366 0349",
    "sg:province":"Canterbury",
    "sg:tags":[
        "services",
        "home",
        "tattooists",
        "garden"
    ],
    "wof:name":"Graphic Addiction",
    "wof:placetype":"venue"
},
  "geometry": {"coordinates":[172.63748200000001,-43.547424],"type":"Point"}
}