{
  "type": "Feature",
  "properties": {
    "iso:country":"NZ",
    "sg:address":"Unit/12 Clearwater Cov West Harbour ",
    "sg:city":"Auckland",
    "sg:orig_category":"Transport: Boats And Marine: Boats: Boat Dealers",
    "sg:phone":"+64 9-416 6466",
    "sg:province":"Auckland",
    "wof:name":"Westpark Boating Centre",
    "wof:placetype":"venue"
},
  "geometry": {"coordinates":[174.641098,-36.809982],"type":"Point"}
}