{
  "type": "Feature",
  "properties": {
    "iso:country":"NZ",
    "sg:address":"69 Disraeli St Sydenham ",
    "sg:city":"Christchurch",
    "sg:classifiers":[
        {
            "category":"Home & Garden",
            "subcategory":"Hardware",
            "type":"Retail Goods"
        }
    ],
    "sg:phone":"+64 3-365 8104",
    "sg:province":"Canterbury",
    "sg:tags":[
        "window",
        "fitting"
    ],
    "sg:website":"http://www.glassspecialists.co.nz",
    "wof:name":"Glass Specialists Ltd",
    "wof:placetype":"venue"
},
  "geometry": {"coordinates":[172.62793,-43.54229],"type":"Point"}
}