{
  "type": "Feature",
  "properties": {
    "addr:full":"203 Ellis St Frankton  Hamilton Waikato",
    "addr:housenumber":"203",
    "addr:street":"Ellis St",
    "iso:country":"NZ",
    "sg:address":"203 Ellis St Frankton ",
    "sg:city":"Hamilton",
    "sg:orig_category":"Industrial: Metal: Scrap Metal Dealers",
    "sg:phone":"+64 7-847 7831",
    "sg:province":"Waikato",
    "wof:name":"Cableco Metal Industries Ltd",
    "wof:placetype":"venue"
},
  "geometry": {"coordinates":[175.26260400000001,-37.800072],"type":"Point"}
}