{
  "type": "Feature",
  "properties": {
    "addr:full":"cnr Queen & Jackson Sts  Masterton Wellington",
    "addr:housenumber":"cnr",
    "addr:street":"Queen & Jackson Sts",
    "iso:country":"NZ",
    "sg:address":"cnr Queen & Jackson Sts ",
    "sg:city":"Masterton",
    "sg:orig_category":"Home And Garden: Furniture/Furnishings: Curtains",
    "sg:phone":"+64 6-377 1843",
    "sg:province":"Wellington",
    "wof:name":"Furnishing House Limited",
    "wof:placetype":"venue"
},
  "geometry": {"coordinates":[175.65733299999999,-40.94931],"type":"Point"}
}