{
  "type": "Feature",
  "properties": {
    "iso:country":"NZ",
    "sg:address":"21 Spring St ",
    "sg:city":"Tauranga",
    "sg:orig_category":"Clothing And Fabric: Clothing: Jeans",
    "sg:phone":"+64 7-571 5180",
    "sg:province":"Bay of Plenty",
    "wof:name":"Jeanswest",
    "wof:placetype":"venue"
},
  "geometry": {"coordinates":[176.169296,-37.684219],"type":"Point"}
}