{
  "type": "Feature",
  "properties": {
    "iso:country":"NZ",
    "sg:address":"8C Sylvia Park Rd Mt Wellington ",
    "sg:city":"Auckland",
    "sg:classifiers":[
        {
            "category":"Manufacturing",
            "subcategory":"Tools & Machinery",
            "type":"Manufacturing & Wholesale Goods"
        }
    ],
    "sg:phone":"+64 9-573 7000",
    "sg:province":"Auckland",
    "sg:tags":[
        "equipment",
        "industrial",
        "pneumatic",
        "tools"
    ],
    "sg:website":"http://www.smc.co.nz",
    "wof:name":"SMC Pneumatics (N.Z.) Ltd",
    "wof:placetype":"venue"
},
  "geometry": {"coordinates":[174.83793600000001,-36.922596],"type":"Point"}
}