{
  "type": "Feature",
  "properties": {
    "iso:country":"NZ",
    "sg:address":"29 A Hairini St Maungatapu ",
    "sg:city":"Tauranga",
    "sg:classifiers":[
        {
            "category":"Health Services",
            "subcategory":"Clinic",
            "type":"Services"
        }
    ],
    "sg:phone":"+64 7-544 6234",
    "sg:province":"Bay of Plenty",
    "sg:tags":[
        "medical",
        "beauty"
    ],
    "wof:name":"Hairini Family Health Centre",
    "wof:placetype":"venue"
},
  "geometry": {"coordinates":[176.166702,-37.724499],"type":"Point"}
}