{
  "type": "Feature",
  "properties": {
    "addr:full":"Unit K, 1197- 1205 Great North Rd Point Chevalier  Auckland Auckland",
    "addr:housenumber":"1197 1205",
    "addr:street":"Great North Rd",
    "iso:country":"NZ",
    "sg:address":"Unit K, 1197- 1205 Great North Rd Point Chevalier ",
    "sg:city":"Auckland",
    "sg:classifiers":[
        {
            "category":"Personal",
            "type":"Services"
        }
    ],
    "sg:phone":"+64 9-377 8228",
    "sg:province":"Auckland",
    "sg:tags":[
        "health",
        "beauty",
        "diet"
    ],
    "wof:name":"Total Nutrition",
    "wof:placetype":"venue"
},
  "geometry": {"coordinates":[174.71021999999999,-36.861404],"type":"Point"}
}