{
  "type": "Feature",
  "properties": {
    "addr:full":"Adventist Specialist Centre 188 St Heliers Bay Rd St, Heliers  Auckland Auckland",
    "addr:housenumber":"188",
    "addr:street":"St Heliers Bay Rd St",
    "iso:country":"NZ",
    "sg:address":"Adventist Specialist Centre 188 St Heliers Bay Rd St, Heliers ",
    "sg:city":"Auckland",
    "sg:classifiers":[
        {
            "category":"Health Services",
            "subcategory":"Health Practitioner",
            "type":"Services"
        }
    ],
    "sg:phone":"+64 9-575 2109",
    "sg:province":"Auckland",
    "sg:tags":[
        "specialist",
        "medical",
        "beauty",
        "specialists"
    ],
    "wof:name":"Weeks R H Orthopaedic Surgeon",
    "wof:placetype":"venue"
},
  "geometry": {"coordinates":[174.862976,-36.856163],"type":"Point"}
}