{
  "type": "Feature",
  "properties": {
    "addr:full":"28 Fifth Ave  Hamilton Waikato",
    "addr:housenumber":"28",
    "addr:street":"Fifth Ave",
    "iso:country":"NZ",
    "sg:address":"28 Fifth Ave ",
    "sg:city":"Hamilton",
    "sg:orig_category":"Health And Beauty: Specialists: Chiropractors",
    "sg:phone":"+64 7-855 6123",
    "sg:province":"Waikato",
    "wof:name":"Bryce Dr John & Dr Wendy",
    "wof:placetype":"venue"
},
  "geometry": {"coordinates":[-74.727234,40.244415],"type":"Point"}
}