{
  "type": "Feature",
  "properties": {
    "iso:country":"NZ",
    "sg:address":"1317 Alexandra St Te ",
    "sg:city":"Awamutu",
    "sg:orig_category":"Industrial: Engineering: Engineers - Manufacturing",
    "sg:phone":"+64 7-871 7062",
    "sg:province":"Waikato",
    "sg:website":"http://www.stewcav.com/",
    "wof:name":"Stewart & Cavalier",
    "wof:placetype":"venue"
},
  "geometry": {"coordinates":[175.311722,-38.005676],"type":"Point"}
}