{
  "type": "Feature",
  "properties": {
    "iso:country":"NZ",
    "sg:address":"Auckland Wide ",
    "sg:city":"Auckland",
    "sg:classifiers":[
        {
            "category":"Home & Garden",
            "subcategory":"Household Appliances",
            "type":"Retail Goods"
        }
    ],
    "sg:phone":"+64 9-826 0844",
    "sg:province":"Auckland",
    "sg:tags":[
        "box",
        "accessories",
        "letter"
    ],
    "wof:name":"Talking Letterbox Company",
    "wof:placetype":"venue"
},
  "geometry": {"coordinates":[174.78450000000001,-37.006058],"type":"Point"}
}