{
  "type": "Feature",
  "properties": {
    "iso:country":"NZ",
    "sg:address":"87 Dublin St ",
    "sg:city":"Martinborough",
    "sg:classifiers":[
        {
            "category":"Travel",
            "subcategory":"Bed & Breakfast",
            "type":"Entertainment"
        }
    ],
    "sg:phone":"+64 6-306 9057",
    "sg:tags":[
        "tourism",
        "accommodation"
    ],
    "wof:name":"Swanhouse Bed & Breakfast",
    "wof:placetype":"venue"
},
  "geometry": {"coordinates":[175.458588,-41.223362],"type":"Point"}
}