{
  "type": "Feature",
  "properties": {
    "iso:country":"NZ",
    "sg:address":"Reid House 114 Alexandra St ",
    "sg:city":"Hamilton",
    "sg:orig_category":"Shopping: Hobbies And Games: Handcrafts",
    "sg:phone":"+64 7-838 0117",
    "sg:province":"Waikato",
    "wof:name":"Purple Patch",
    "wof:placetype":"venue"
},
  "geometry": {"coordinates":[-93.879616,39.728603],"type":"Point"}
}