{
  "type": "Feature",
  "properties": {
    "iso:country":"NZ",
    "sg:address":"32-34 View Rd Glenfield ",
    "sg:city":"Auckland",
    "sg:orig_category":"Industrial: Manufacturing: Assembly Work",
    "sg:phone":"+64 9-444 0611",
    "sg:province":"Auckland",
    "wof:name":"Abilities Group",
    "wof:placetype":"venue"
},
  "geometry": {"coordinates":[174.734833,-36.771416],"type":"Point"}
}