{
  "type": "Feature",
  "properties": {
    "addr:full":"cnr Wairau Rd & Diana Dve Glenfield  Auckland Auckland",
    "addr:housenumber":"dve",
    "addr:street":"Cnr Wairau Rd &",
    "iso:country":"NZ",
    "sg:address":"cnr Wairau Rd & Diana Dve Glenfield ",
    "sg:city":"Auckland",
    "sg:classifiers":[
        {
            "category":"Autos & Motor Vehicles",
            "subcategory":"Automobile Sales",
            "type":"Retail Goods"
        }
    ],
    "sg:phone":"+64 9-444 8114",
    "sg:province":"Auckland",
    "sg:tags":[
        "bus",
        "leasing",
        "truck",
        "automotive"
    ],
    "wof:name":"Mercedes-Benz Authorised Dealers",
    "wof:placetype":"venue"
},
  "geometry": {"coordinates":[174.72280900000001,-36.77676],"type":"Point"}
}