{
  "type": "Feature",
  "properties": {
    "iso:country":"NZ",
    "sg:address":"60 Weka St Miramar ",
    "sg:city":"Wellington",
    "sg:orig_category":"Health And Beauty: Medical: Hospitals",
    "sg:phone":"+64 4-388 6780",
    "sg:province":"Wellington",
    "wof:name":"Te Karaka Residence For The Elderly & Hospital",
    "wof:placetype":"venue"
},
  "geometry": {"coordinates":[174.824722,-41.304192],"type":"Point"}
}