{
  "type": "Feature",
  "properties": {
    "addr:full":"65 A Main Rd  Havelock",
    "addr:housenumber":"65",
    "addr:street":"A Main Rd",
    "iso:country":"NZ",
    "sg:address":"65 A Main Rd ",
    "sg:city":"Havelock",
    "sg:classifiers":[
        {
            "category":"Bus Charters",
            "type":"Transportation"
        }
    ],
    "sg:phone":"+64 3-574 2114",
    "sg:tags":[
        "services",
        "travel",
        "tourism"
    ],
    "wof:name":"Havelock Outdoors Centre",
    "wof:placetype":"venue"
},
  "geometry": {"coordinates":[-94.701714,42.834831],"type":"Point"}
}