{
  "type": "Feature",
  "properties": {
    "iso:country":"NZ",
    "sg:address":"166 The ",
    "sg:city":"Square",
    "sg:classifiers":[
        {
            "category":"Airline",
            "type":"Transportation"
        }
    ],
    "sg:phone":"+64 6-350 9750",
    "sg:tags":[
        "services",
        "travel",
        "tourism"
    ],
    "wof:name":"Flight Centre",
    "wof:placetype":"venue"
},
  "geometry": {"coordinates":[-3.05094,51.665981],"type":"Point"}
}