{
  "type": "Feature",
  "properties": {
    "addr:full":"7-10 Waiwera Rd Waiwera Hibiscus  Hibiscus Coast Auckland",
    "addr:housenumber":"7-10",
    "addr:street":"Waiwera Rd",
    "iso:country":"NZ",
    "sg:address":"7-10 Waiwera Rd Waiwera Hibiscus ",
    "sg:city":"Hibiscus Coast",
    "sg:classifiers":[
        {
            "category":"Landmark",
            "subcategory":"Tourist Information",
            "type":"Public Place"
        }
    ],
    "sg:phone":"+64 9-426 5369",
    "sg:province":"Auckland",
    "sg:tags":[
        "travel",
        "tourism",
        "tour",
        "sightseeing"
    ],
    "sg:website":"http://www.waiwera.co.nz",
    "wof:name":"Waiwera Thermal Pools",
    "wof:placetype":"venue"
},
  "geometry": {"coordinates":[174.704849,-36.543785],"type":"Point"}
}