{
  "type": "Feature",
  "properties": {
    "addr:full":"PO Box 41-152 Wellington  South",
    "addr:housenumber":"po box 41-152",
    "iso:country":"NZ",
    "sg:address":"PO Box 41-152 Wellington ",
    "sg:city":"South",
    "sg:classifiers":[
        {
            "category":"Communications",
            "subcategory":"Film & Video Production",
            "type":"Services"
        }
    ],
    "sg:phone":"+64 4-562 8787",
    "sg:tags":[
        "broadcasting",
        "studio",
        "producer"
    ],
    "wof:name":"Little Ed Films Ltd",
    "wof:placetype":"venue"
},
  "geometry": {"coordinates":[174.78179900000001,-41.336624],"type":"Point"}
}