{
  "type": "Feature",
  "properties": {
    "addr:full":"9 Riverton-Otautau Rd  Riverton",
    "addr:housenumber":"9",
    "addr:street":"Riverton-Otautau Rd",
    "iso:country":"NZ",
    "sg:address":"9 Riverton-Otautau Rd ",
    "sg:city":"Riverton",
    "sg:orig_category":"Farming: Agriculture: Agricultural Contractors",
    "sg:phone":"+64 3-234 9078",
    "wof:name":"Shearing Brendon",
    "wof:placetype":"venue"
},
  "geometry": {"coordinates":[-72.98241400000001,41.996204],"type":"Point"}
}