{
  "type": "Feature",
  "properties": {
    "addr:full":"Milson Shopping Cen Palmerston  Palmerston North Manawatu-Wanganui",
    "addr:street":"Palmerston",
    "iso:country":"NZ",
    "sg:address":"Milson Shopping Cen Palmerston ",
    "sg:city":"Palmerston North",
    "sg:classifiers":[
        {
            "category":"Personal",
            "subcategory":"Tanning Parlor",
            "type":"Services"
        }
    ],
    "sg:phone":"+64 6-357 2903",
    "sg:province":"Manawatu-Wanganui",
    "sg:tags":[
        "sun",
        "health",
        "beauty"
    ],
    "wof:name":"Salon Define",
    "wof:placetype":"venue"
},
  "geometry": {"coordinates":[175.609238,-40.32935],"type":"Point"}
}