{
  "type": "Feature",
  "properties": {
    "addr:full":"(Clinic) 299 North Rd PO Box 5009  Invercargill Southland",
    "addr:housenumber":"299;box 5009",
    "addr:street":"North Rd",
    "iso:country":"NZ",
    "sg:address":"(Clinic) 299 North Rd PO Box 5009 ",
    "sg:city":"Invercargill",
    "sg:orig_category":"Farming: Services: Veterinarians",
    "sg:phone":"+64 3-215 9237",
    "sg:province":"Southland",
    "wof:name":"Veterinary Services Invercargill At Waikiwi",
    "wof:placetype":"venue"
},
  "geometry": {"coordinates":[168.35217299999999,-46.411854],"type":"Point"}
}