{
  "type": "Feature",
  "properties": {
    "iso:country":"NZ",
    "sg:address":"Dixon St ",
    "sg:city":"Masterton",
    "sg:classifiers":[
        {
            "category":"Sports & Exercise",
            "subcategory":"Sports Center",
            "type":"Entertainment"
        }
    ],
    "sg:phone":"+64 6-378 7758",
    "sg:province":"Wellington",
    "sg:tags":[
        "sporting",
        "sports",
        "-",
        "leisure",
        "facility"
    ],
    "wof:name":"Masterton Swimming Pools",
    "wof:placetype":"venue"
},
  "geometry": {"coordinates":[175.662857,-40.950459],"type":"Point"}
}