{
  "type": "Feature",
  "properties": {
    "iso:country":"NZ",
    "sg:address":"54 Crown Hill Rd RD 4 ",
    "sg:city":"Paeroa",
    "sg:orig_category":"Farming: Services: Farm Consultants",
    "sg:phone":"+64 7-862 7372",
    "sg:province":"Wellington",
    "wof:name":"Underwood Farm Consultancies",
    "wof:placetype":"venue"
},
  "geometry": {"coordinates":[175.673416,-37.378975],"type":"Point"}
}