{
  "type": "Feature",
  "properties": {
    "iso:country":"NZ",
    "sg:address":"State Highway 10 Waipapa ",
    "sg:city":"Kerikeri",
    "sg:classifiers":[
        {
            "category":"Bars & Pubs",
            "type":"Food & Drink"
        }
    ],
    "sg:phone":"+64 9-407 7886",
    "sg:province":"Northland",
    "wof:name":"Cheers Liquor Centre",
    "wof:placetype":"venue"
},
  "geometry": {"coordinates":[173.92688,-35.206779],"type":"Point"}
}