{
  "type": "Feature",
  "properties": {
    "iso:country":"NZ",
    "sg:address":"619 Ahuroa Rd Puhoi ",
    "sg:city":"Warkworth",
    "sg:classifiers":[
        {
            "category":"Food & Beverages",
            "subcategory":"Cheese",
            "type":"Retail Goods"
        }
    ],
    "sg:phone":"+64 9-422 0670",
    "sg:province":"Auckland",
    "sg:tags":[
        "merchant",
        "drink",
        "-"
    ],
    "wof:name":"The Art Of Cheese Cafe",
    "wof:placetype":"venue"
},
  "geometry": {"coordinates":[174.66511499999999,-36.401459],"type":"Point"}
}