{
  "type": "Feature",
  "properties": {
    "iso:country":"NZ",
    "sg:address":"Tawa Street Industrial Estate ",
    "sg:city":"Hamilton",
    "sg:orig_category":"Industrial: Metal: Services: Steel Processing",
    "sg:phone":"+64 7-843 6358",
    "sg:province":"Manawatu-Wanganui",
    "wof:name":"Fletcher Reinforcing",
    "wof:placetype":"venue"
},
  "geometry": {"coordinates":[-87.988968,34.142426],"type":"Point"}
}