{
  "type": "Feature",
  "properties": {
    "addr:full":"Vogler Dve Wiri  Auckland Auckland",
    "iso:country":"NZ",
    "sg:address":"Vogler Dve Wiri ",
    "sg:city":"Auckland",
    "sg:classifiers":[
        {
            "category":"Autos & Motor Vehicles",
            "subcategory":"Automobile Sales",
            "type":"Retail Goods"
        }
    ],
    "sg:phone":"+64 9-262 2200",
    "sg:province":"Auckland",
    "sg:tags":[
        "bus",
        "leasing",
        "truck",
        "automotive"
    ],
    "wof:name":"Iveco Trucks New Zealand",
    "wof:placetype":"venue"
},
  "geometry": {"coordinates":[174.86731,-37.001328],"type":"Point"}
}