{
  "type": "Feature",
  "properties": {
    "iso:country":"NZ",
    "sg:address":"Unit 6 327 Great South Rd Takanini ",
    "sg:city":"Auckland",
    "sg:orig_category":"Automotive: Accessories: Car Care Products",
    "sg:phone":"+64 9-296 2287",
    "sg:province":"Auckland",
    "wof:name":"Perma-Shine Limited",
    "wof:placetype":"venue"
},
  "geometry": {"coordinates":[174.93042,-37.051975],"type":"Point"}
}