{
  "type": "Feature",
  "properties": {
    "addr:full":"8 Totara Pl Redwoodtown  Blenheim Auckland",
    "addr:housenumber":"8",
    "addr:street":"Totara Pl",
    "iso:country":"NZ",
    "sg:address":"8 Totara Pl Redwoodtown ",
    "sg:city":"Blenheim",
    "sg:classifiers":[
        {
            "category":"Home & Garden",
            "subcategory":"Building Materials",
            "type":"Retail Goods"
        }
    ],
    "sg:phone":"+64 3-578 5187",
    "sg:province":"Auckland",
    "sg:tags":[
        "electrician",
        "related"
    ],
    "wof:name":"Trevor Golding Ltd",
    "wof:placetype":"venue"
},
  "geometry": {"coordinates":[173.963776,-41.53109],"type":"Point"}
}