{
  "type": "Feature",
  "properties": {
    "iso:country":"NZ",
    "sg:address":"Stoke Central Mall Cnr Songer Street & Main Road, Stoke ",
    "sg:city":"Nelson",
    "sg:orig_category":"Shopping: Accessories",
    "sg:phone":"+64 3-547 5154",
    "sg:province":"Nelson",
    "wof:name":"Threads",
    "wof:placetype":"venue"
},
  "geometry": {"coordinates":[173.234207,-41.312859],"type":"Point"}
}