{
  "type": "Feature",
  "properties": {
    "addr:full":"234 Annesbrook Dve Tahunanui  Nelson Nelson",
    "addr:housenumber":"234",
    "addr:street":"Annesbrook Dve",
    "iso:country":"NZ",
    "sg:address":"234 Annesbrook Dve Tahunanui ",
    "sg:city":"Nelson",
    "sg:classifiers":[
        {
            "category":"Autos & Motor Vehicles",
            "subcategory":"Motorcycle Sales",
            "type":"Retail Goods"
        }
    ],
    "sg:phone":"+64 3-546 4991",
    "sg:province":"Nelson",
    "sg:tags":[
        "automotive",
        "scooter",
        "leasing"
    ],
    "wof:name":"AB's Motorcycles Service & Repairs",
    "wof:placetype":"venue"
},
  "geometry": {"coordinates":[173.24464399999999,-41.283855],"type":"Point"}
}