{
  "type": "Feature",
  "properties": {
    "iso:country":"NZ",
    "sg:address":"PO Box 64 ",
    "sg:city":"Blenheim",
    "sg:classifiers":[
        {
            "category":"Juice Bar",
            "subcategory":"None",
            "type":"Food & Drink"
        }
    ],
    "sg:phone":"+64 800 283 366",
    "sg:province":"Marlborough",
    "sg:tags":[
        "processing",
        "drying",
        "freeze"
    ],
    "wof:name":"Cuddon Freeze Dry",
    "wof:placetype":"venue"
},
  "geometry": {"coordinates":[-74.459564,42.468643],"type":"Point"}
}