{
  "type": "Feature",
  "properties": {
    "addr:full":"28-30 Sutton Pl Palmerston  Palmerston North Manawatu-Wanganui",
    "addr:housenumber":"28-30",
    "addr:street":"Sutton Pl",
    "iso:country":"NZ",
    "sg:address":"28-30 Sutton Pl Palmerston ",
    "sg:city":"Palmerston North",
    "sg:classifiers":[
        {
            "category":"Farming",
            "subcategory":"Farm",
            "type":"Manufacturing & Wholesale Goods"
        }
    ],
    "sg:phone":"+64 6-355 5747",
    "sg:province":"Manawatu-Wanganui",
    "sg:website":"http://www.galtech.co.nz",
    "wof:name":"Galtech Models Ltd",
    "wof:placetype":"venue"
},
  "geometry": {"coordinates":[175.646545,-40.340809],"type":"Point"}
}