{
  "type": "Feature",
  "properties": {
    "addr:full":"Cnr Alpha and Empire Sts  Cambridge Waikato",
    "addr:housenumber":"cnr",
    "addr:street":"Alpha And;Sts",
    "iso:country":"NZ",
    "sg:address":"Cnr Alpha and Empire Sts ",
    "sg:city":"Cambridge",
    "sg:orig_category":"Farming: Services: Livestock Related: Livestock Buyers/Brokers",
    "sg:phone":"+64 7-823 3185",
    "sg:province":"Waikato",
    "wof:name":"R J Smith Ltd",
    "wof:placetype":"venue"
},
  "geometry": {"coordinates":[-71.10601,42.36681],"type":"Point"}
}