{
  "type": "Feature",
  "properties": {
    "iso:country":"NZ",
    "sg:address":"1 Dowling St ",
    "sg:city":"Dunedin",
    "sg:classifiers":[
        {
            "category":"Arts & Performance",
            "subcategory":"Art Gallery",
            "type":"Entertainment"
        }
    ],
    "sg:phone":"+64 3-477 2774",
    "sg:province":"Otago",
    "sg:tags":[
        "arts",
        "sport",
        "leisure"
    ],
    "wof:name":"Art Care & Conservation",
    "wof:placetype":"venue"
},
  "geometry": {"coordinates":[-82.784721,28.013355],"type":"Point"}
}