{
  "type": "Feature",
  "properties": {
    "iso:country":"NZ",
    "sg:address":"87 Wairau Rd Glenfield ",
    "sg:city":"Auckland",
    "sg:classifiers":[
        {
            "category":"Bars & Pubs",
            "type":"Food & Drink"
        }
    ],
    "sg:phone":"+64 9-442 0151",
    "sg:province":"Auckland",
    "sg:website":"http://www.lk.co.nz",
    "wof:name":"Liquor King",
    "wof:placetype":"venue"
},
  "geometry": {"coordinates":[174.74397300000001,-36.776436],"type":"Point"}
}