{
  "type": "Feature",
  "properties": {
    "iso:country":"NZ",
    "sg:address":"164 Hereford Street",
    "sg:city":"Christchurch",
    "sg:classifiers":[
        {
            "category":"Banks & Credit Unions",
            "subcategory":"Bank",
            "type":"Services"
        }
    ],
    "sg:phone":"+64 3791940",
    "sg:province":"Canterbury",
    "wof:name":"Lloyds Bank Plc",
    "wof:placetype":"venue"
},
  "geometry": {"coordinates":[-76.537834,37.605659],"type":"Point"}
}