{
  "type": "Feature",
  "properties": {
    "iso:country":"NZ",
    "sg:address":"Buckingham St ",
    "sg:city":"Arrowtown",
    "sg:classifiers":[
        {
            "category":"Shopping",
            "subcategory":"Crafts & Fabrics",
            "type":"Retail Goods"
        }
    ],
    "sg:phone":"+64 3-442 1590",
    "sg:province":"Otago",
    "sg:tags":[
        "pottery",
        "home",
        "accessories",
        "garden",
        "supply"
    ],
    "wof:name":"The Muddy Tree Company",
    "wof:placetype":"venue"
},
  "geometry": {"coordinates":[168.83590699999999,-44.939365],"type":"Point"}
}