{
  "type": "Feature",
  "properties": {
    "addr:full":"237 Kaipaki Rd Ohaupo  Hamilton Waikato",
    "addr:housenumber":"237",
    "addr:street":"Kaipaki Rd",
    "iso:country":"NZ",
    "sg:address":"237 Kaipaki Rd Ohaupo ",
    "sg:city":"Hamilton",
    "sg:classifiers":[
        {
            "category":"Professional",
            "subcategory":"Art Services",
            "type":"Services"
        }
    ],
    "sg:phone":"+64 7-823 6236",
    "sg:province":"Waikato",
    "sg:tags":[
        "personal",
        "photographer",
        "services",
        "garden",
        "home"
    ],
    "wof:name":"Quantum Photography",
    "wof:placetype":"venue"
},
  "geometry": {"coordinates":[175.30587800000001,-37.9193],"type":"Point"}
}