{
  "type": "Feature",
  "properties": {
    "iso:country":"NZ",
    "sg:address":"17 Antares Pl Mairangi Bay ",
    "sg:city":"Auckland",
    "sg:orig_category":"Health And Beauty: Specialists: Physiotherapists",
    "sg:phone":"+64 9-477 2090",
    "sg:province":"Auckland",
    "wof:name":"Abercrombie David",
    "wof:placetype":"venue"
},
  "geometry": {"coordinates":[174.748169,-36.738461],"type":"Point"}
}