{
  "type": "Feature",
  "properties": {
    "addr:full":"63 Angle St Onehunga  Auckland Auckland",
    "addr:housenumber":"63",
    "addr:street":"Angle St",
    "iso:country":"NZ",
    "sg:address":"63 Angle St Onehunga ",
    "sg:city":"Auckland",
    "sg:orig_category":"Industrial: Metal",
    "sg:phone":"+64 9-634 2914",
    "sg:province":"Auckland",
    "sg:website":"http://www.stronghonda.co.nz",
    "wof:name":"Strong For Honda",
    "wof:placetype":"venue"
},
  "geometry": {"coordinates":[174.783661,-36.909973],"type":"Point"}
}