{
  "type": "Feature",
  "properties": {
    "addr:full":"32 A Maich Rd Manurewa  Auckland Auckland",
    "addr:housenumber":"32",
    "addr:street":"A Maich Rd",
    "iso:country":"NZ",
    "sg:address":"32 A Maich Rd Manurewa ",
    "sg:city":"Auckland",
    "sg:classifiers":[
        {
            "category":"Retail",
            "subcategory":"Auto Repair",
            "type":"Services"
        }
    ],
    "sg:phone":"+64 9-267 4981",
    "sg:province":"Auckland",
    "sg:tags":[
        "automotive",
        "panel",
        "servicing",
        "beater"
    ],
    "sg:website":"http://www.manurewapanelbeaters.co.nz",
    "wof:name":"Manurewa Panelbeaters, Radiators & Spraypainters",
    "wof:placetype":"venue"
},
  "geometry": {"coordinates":[174.89215100000001,-37.019554],"type":"Point"}
}