{
  "type": "Feature",
  "properties": {
    "iso:country":"NZ",
    "sg:address":"PO Box 8280 Havelock North ",
    "sg:city":"Hastings",
    "sg:orig_category":"Health And Beauty: Mental: Psychotherapy",
    "sg:phone":"+64 6-877 3014",
    "sg:province":"Hawke's Bay",
    "wof:name":"Bailey Paul Psychotherapist",
    "wof:placetype":"venue"
},
  "geometry": {"coordinates":[176.879517,-39.669403],"type":"Point"}
}