{
  "type": "Feature",
  "properties": {
    "iso:country":"NZ",
    "sg:address":"2 Redan Rd ",
    "sg:city":"Kaitaia",
    "sg:classifiers":[
        {
            "category":"Banks & Credit Unions",
            "subcategory":"Investment Brokerage",
            "type":"Services"
        }
    ],
    "sg:phone":"+64 9-408 9366",
    "sg:province":"Northland",
    "sg:tags":[
        "personal",
        "accountant",
        "chartered",
        "-",
        "finance"
    ],
    "wof:name":"Horwath Francis Aickin Ltd",
    "wof:placetype":"venue"
},
  "geometry": {"coordinates":[173.261932,-35.119404],"type":"Point"}
}