{
  "type": "Feature",
  "properties": {
    "iso:country":"NZ",
    "sg:address":"105 Pakowhai Rd ",
    "sg:city":"Hastings",
    "sg:classifiers":[
        {
            "category":"Bars & Pubs",
            "subcategory":"Wine Bar",
            "type":"Food & Drink"
        }
    ],
    "sg:phone":"+64 6-876 7868",
    "sg:province":"Hawke's Bay",
    "sg:tags":[
        "grocery",
        "-"
    ],
    "wof:name":"Rattrays Wholesale Ltd",
    "wof:placetype":"venue"
},
  "geometry": {"coordinates":[176.831482,-39.629707],"type":"Point"}
}