{
  "type": "Feature",
  "properties": {
    "iso:country":"NZ",
    "sg:address":"Ground Floor 12 Alma St ",
    "sg:city":"Hamilton",
    "sg:classifiers":[
        {
            "category":"Social Services",
            "subcategory":"Job Training",
            "type":"Services"
        }
    ],
    "sg:phone":"+64 7-839 7370",
    "sg:province":"Waikato",
    "sg:tags":[
        "education"
    ],
    "wof:name":"New Zealand Industry Training Organisation",
    "wof:placetype":"venue"
},
  "geometry": {"coordinates":[-84.89637,41.486488],"type":"Point"}
}