{
  "type": "Feature",
  "properties": {
    "iso:country":"NZ",
    "sg:address":"66 George St Palmerston ",
    "sg:city":"Palmerston North",
    "sg:classifiers":[
        {
            "category":"Professional",
            "subcategory":"Art Services",
            "type":"Services"
        }
    ],
    "sg:phone":"+64 6-357 0540",
    "sg:province":"Manawatu-Wanganui",
    "sg:tags":[
        "picture",
        "arts",
        "sport",
        "framing",
        "leisure"
    ],
    "wof:name":"Windfall Gallery & Framers",
    "wof:placetype":"venue"
},
  "geometry": {"coordinates":[175.608734,-40.356686],"type":"Point"}
}