{
  "type": "Feature",
  "properties": {
    "iso:country":"NZ",
    "sg:address":"Chamberlain St ",
    "sg:city":"Motueka",
    "sg:classifiers":[
        {
            "category":"Home & Garden",
            "subcategory":"Garden Supply",
            "type":"Retail Goods"
        }
    ],
    "sg:phone":"+64 3-528 7449",
    "sg:province":"Tasman",
    "sg:tags":[
        "products",
        "nursery",
        "gardening"
    ],
    "wof:name":"Tasman Bay Roses Ltd",
    "wof:placetype":"venue"
},
  "geometry": {"coordinates":[172.978439,-41.138084],"type":"Point"}
}