{
  "type": "Feature",
  "properties": {
    "addr:full":"cnr Paorahape & Ruapehu Sts  Taupo Waikato",
    "addr:street":"Cnr Paorahape & Ruapehu Sts",
    "iso:country":"NZ",
    "sg:address":"cnr Paorahape & Ruapehu Sts ",
    "sg:city":"Taupo",
    "sg:orig_category":"Shopping: Gifts: Sheepskins",
    "sg:phone":"+64 7-378 9513",
    "sg:province":"Waikato",
    "wof:name":"Woolshed (NZ) Ltd",
    "wof:placetype":"venue"
},
  "geometry": {"coordinates":[176.08433500000001,-38.689281],"type":"Point"}
}