{
  "type": "Feature",
  "properties": {
    "iso:country":"NZ",
    "sg:address":"52-64 Victoria St West Auckland Central ",
    "sg:city":"Auckland",
    "sg:classifiers":[
        {
            "category":"Education",
            "subcategory":"University",
            "type":"Public Place"
        }
    ],
    "sg:phone":"+64 9-377 2769",
    "sg:province":"Auckland",
    "sg:tags":[
        "training",
        "instruction",
        "language"
    ],
    "wof:name":"Advance School of Language",
    "wof:placetype":"venue"
},
  "geometry": {"coordinates":[-119.10457599999999,36.597755],"type":"Point"}
}