{
  "type": "Feature",
  "properties": {
    "iso:country":"NZ",
    "sg:address":"23 b Stanley Point Rd Devonport ",
    "sg:city":"Auckland",
    "sg:classifiers":[
        {
            "category":"Personal",
            "type":"Services"
        }
    ],
    "sg:phone":"+64 9-446 6262",
    "sg:province":"Auckland",
    "sg:tags":[
        "diet",
        "reduction",
        "health",
        "beauty",
        "weight"
    ],
    "wof:name":"Sarah Ley Dietitian",
    "wof:placetype":"venue"
},
  "geometry": {"coordinates":[174.799561,-36.824425],"type":"Point"}
}