{
  "type": "Feature",
  "properties": {
    "addr:full":"148 Arthur St Onehunga  Auckland Auckland",
    "addr:housenumber":"148",
    "addr:street":"Arthur St",
    "iso:country":"NZ",
    "sg:address":"148 Arthur St Onehunga ",
    "sg:city":"Auckland",
    "sg:orig_category":"Transport: Transportation: Postal Services",
    "sg:phone":"+64 9-634 0199",
    "sg:province":"Auckland",
    "wof:name":"Books & More: New Zealand Post",
    "wof:placetype":"venue"
},
  "geometry": {"coordinates":[174.78611799999999,-36.920471],"type":"Point"}
}