{
  "type": "Feature",
  "properties": {
    "iso:country":"NZ",
    "sg:address":"885 Dominion Rd Mt Roskill ",
    "sg:city":"Auckland",
    "sg:classifiers":[
        {
            "category":"Shopping",
            "subcategory":"Clothing, Apparel, & Fashions",
            "type":"Retail Goods"
        }
    ],
    "sg:phone":"+64 21 673 133",
    "sg:province":"Auckland",
    "sg:tags":[
        "-",
        "hire",
        "clothing",
        "fabric"
    ],
    "sg:website":"http://www.yellowpages.co.nz/pages/219462216/dp33203.html",
    "wof:name":"Embody",
    "wof:placetype":"venue"
},
  "geometry": {"coordinates":[174.741699,-36.904678],"type":"Point"}
}