{
  "type": "Feature",
  "properties": {
    "addr:full":"415 Colombo St Sydenham  Christchurch Canterbury",
    "addr:housenumber":"415",
    "addr:street":"Colombo St",
    "iso:country":"NZ",
    "sg:address":"415 Colombo St Sydenham ",
    "sg:city":"Christchurch",
    "sg:orig_category":"Food And Drink: Meats: Butchers",
    "sg:phone":"+64 3-377 1113",
    "sg:province":"Canterbury",
    "wof:name":"The Meat King",
    "wof:placetype":"venue"
},
  "geometry": {"coordinates":[172.63651999999999,-43.544544],"type":"Point"}
}