{
  "type": "Feature",
  "properties": {
    "iso:country":"NZ",
    "sg:address":"4/33 Sonngs ",
    "sg:city":"Rd",
    "sg:classifiers":[
        {
            "category":"Home & Garden",
            "subcategory":"Hardware",
            "type":"Retail Goods"
        }
    ],
    "sg:phone":"+64 800 652 020",
    "sg:tags":[
        "window",
        "fitting"
    ],
    "sg:website":"http://www.yellowpages.co.nz/for/krestablinds/dp42903.html",
    "wof:name":"Kresta Blinds & Curtains",
    "wof:placetype":"venue"
},
  "geometry": {"coordinates":[170.366638,-43.587711],"type":"Point"}
}