{
  "type": "Feature",
  "properties": {
    "addr:full":"HWY 1 Loffhagen Dve  Waipara",
    "addr:street":"Hwy 1 Loffhagen Dve Waipara",
    "iso:country":"NZ",
    "sg:address":"HWY 1 Loffhagen Dve ",
    "sg:city":"Waipara",
    "sg:classifiers":[
        {
            "category":"Winery",
            "type":"Food & Drink"
        }
    ],
    "sg:phone":"+64 3-314 6929",
    "sg:tags":[
        "wining",
        "vineyard",
        "dining"
    ],
    "wof:name":"Torlesse Winery",
    "wof:placetype":"venue"
},
  "geometry": {"coordinates":[172.759918,-43.05595],"type":"Point"}
}