{
  "type": "Feature",
  "properties": {
    "addr:full":"Edmund Ave  Kaikoura",
    "addr:street":"Edmund Ave",
    "iso:country":"NZ",
    "sg:address":"Edmund Ave ",
    "sg:city":"Kaikoura",
    "sg:orig_category":"Industrial: Products: Window Control Gear",
    "sg:phone":"+64 3-319 5147",
    "wof:name":"Sigglekows Builders & Joiners",
    "wof:placetype":"venue"
},
  "geometry": {"coordinates":[173.67971800000001,-42.39164],"type":"Point"}
}