{
  "type": "Feature",
  "properties": {
    "iso:country":"NZ",
    "sg:address":"31 Kelvin St ",
    "sg:city":"Invercargill",
    "sg:classifiers":[
        {
            "category":"Shopping",
            "subcategory":"Gifts & Souvenirs",
            "type":"Retail Goods"
        }
    ],
    "sg:phone":"+64 3-218 3437",
    "sg:province":"Southland",
    "sg:tags":[
        "shop",
        "gifts",
        "supplier"
    ],
    "wof:name":"Habitat Gift Shop",
    "wof:placetype":"venue"
},
  "geometry": {"coordinates":[168.350739,-46.411236],"type":"Point"}
}