{
  "type": "Feature",
  "properties": {
    "addr:full":"54 a Pretoria St Lower Hutt  Wellington Wellington",
    "addr:housenumber":"54",
    "addr:street":"A Pretoria St",
    "iso:country":"NZ",
    "sg:address":"54 a Pretoria St Lower Hutt ",
    "sg:city":"Wellington",
    "sg:orig_category":"Shopping: Retail Stores: Books: Bookshops",
    "sg:phone":"+64 4-971 1609",
    "sg:province":"Wellington",
    "wof:name":"Books - New Zealand (Horizon Bookshop Ltd)",
    "wof:placetype":"venue"
},
  "geometry": {"coordinates":[174.915863,-41.20789],"type":"Point"}
}