{
  "type": "Feature",
  "properties": {
    "iso:country":"NZ",
    "sg:address":"37 Joseph St Palmerston ",
    "sg:city":"Palmerston North",
    "sg:orig_category":"Clothing And Fabric: Fabric: Yarn",
    "sg:phone":"+64 6-358 7621",
    "sg:province":"Manawatu-Wanganui",
    "wof:name":"Lana Spinning Co Ltd",
    "wof:placetype":"venue"
},
  "geometry": {"coordinates":[175.60256999999999,-40.362907],"type":"Point"}
}