{
  "type": "Feature",
  "properties": {
    "addr:full":"16 Helston Rd Johnsonville  Wellington Wellington",
    "addr:housenumber":"16",
    "addr:street":"Helston Rd",
    "iso:country":"NZ",
    "sg:address":"16 Helston Rd Johnsonville ",
    "sg:city":"Wellington",
    "sg:classifiers":[
        {
            "category":"Social Services",
            "subcategory":"Retirement Home",
            "type":"Services"
        }
    ],
    "sg:phone":"+64 4-478 9051",
    "sg:province":"Wellington",
    "sg:tags":[
        "elderly",
        "convalescent",
        "garden",
        "rest",
        "care"
    ],
    "wof:name":"Aotea Hospital",
    "wof:placetype":"venue"
},
  "geometry": {"coordinates":[174.81050099999999,-41.221756],"type":"Point"}
}