{
  "type": "Feature",
  "properties": {
    "iso:country":"NZ",
    "sg:address":"29 Marian Dve ",
    "sg:city":"Gisborne",
    "sg:orig_category":"Automotive: General Services: Rental Vehicles",
    "sg:phone":"+64 6-868 7784",
    "sg:province":"Gisborne",
    "wof:name":"Alpha Rentals",
    "wof:placetype":"venue"
},
  "geometry": {"coordinates":[178.024475,-38.66597],"type":"Point"}
}