{
  "type": "Feature",
  "properties": {
    "iso:country":"NZ",
    "sg:address":"75 Broadway Ave Palmerston ",
    "sg:city":"Palmerston North",
    "sg:classifiers":[
        {
            "category":"Bars & Pubs",
            "subcategory":"Lounge",
            "type":"Food & Drink"
        }
    ],
    "sg:phone":"+64 6-356 6131",
    "sg:province":"Manawatu-Wanganui",
    "sg:tags":[
        "-"
    ],
    "wof:name":"Golden Tulip Bakery",
    "wof:placetype":"venue"
},
  "geometry": {"coordinates":[175.613144,-40.353764],"type":"Point"}
}