{
  "type": "Feature",
  "properties": {
    "iso:country":"NZ",
    "sg:address":"Coates St ",
    "sg:city":"Westport",
    "sg:classifiers":[
        {
            "category":"Retail",
            "subcategory":"Auto Repair",
            "type":"Services"
        }
    ],
    "sg:phone":"+64 3-789 7774",
    "sg:province":"West Coast",
    "sg:tags":[
        "automotive",
        "panel",
        "servicing",
        "beater"
    ],
    "wof:name":"Carrington/Robertson Panel & Paint",
    "wof:placetype":"venue"
},
  "geometry": {"coordinates":[-123.784889,39.639027],"type":"Point"}
}