{
  "type": "Feature",
  "properties": {
    "addr:full":"Otago, Dunedin, Queenstown  Dunedin Otago",
    "addr:housenumber":"otago",
    "iso:country":"NZ",
    "sg:address":"Otago, Dunedin, Queenstown ",
    "sg:city":"Dunedin",
    "sg:orig_category":"Health And Beauty: Medical: Hospitals",
    "sg:phone":"+64 3-477 6365",
    "sg:province":"Otago",
    "sg:website":"http://www.southerncross.co.nz",
    "wof:name":"Southern Cross Healthcare",
    "wof:placetype":"venue"
},
  "geometry": {"coordinates":[170.50625600000001,-45.878353],"type":"Point"}
}