{
  "type": "Feature",
  "properties": {
    "iso:country":"NZ",
    "sg:address":"South Town Belt ",
    "sg:city":"Rakaia",
    "sg:orig_category":"Home And Garden: Gardening: Products: Fertilisers",
    "sg:phone":"+64 3-302 7421",
    "sg:province":"West Coast",
    "wof:name":"Ravensdown Fertiliser Co-op Ltd",
    "wof:placetype":"venue"
},
  "geometry": {"coordinates":[172.027237,-43.759884],"type":"Point"}
}