{
  "type": "Feature",
  "properties": {
    "iso:country":"NZ",
    "sg:address":"123 Port Rd Seaview Lower ",
    "sg:city":"Hutt",
    "sg:classifiers":[
        {
            "category":"Parking",
            "subcategory":"Garage",
            "type":"Transportation"
        }
    ],
    "sg:phone":"+64 4-568 5858",
    "sg:province":"Wellington",
    "sg:tags":[
        "hire",
        "container",
        "transport",
        "lease"
    ],
    "wof:name":"Wellington Provedoring Co Ltd",
    "wof:placetype":"venue"
},
  "geometry": {"coordinates":[174.89956699999999,-41.246059],"type":"Point"}
}