{
  "type": "Feature",
  "properties": {
    "iso:country":"NZ",
    "sg:address":"267 A Chadwick Rd Greerton ",
    "sg:city":"Tauranga",
    "sg:classifiers":[
        {
            "category":"Arena",
            "subcategory":"Sports Club",
            "type":"Entertainment"
        }
    ],
    "sg:phone":"+64 7-577 1486",
    "sg:province":"Bay of Plenty",
    "sg:tags":[
        "-",
        "leisure",
        "sports"
    ],
    "wof:name":"Tauranga Archers",
    "wof:placetype":"venue"
},
  "geometry": {"coordinates":[176.131241,-37.725212],"type":"Point"}
}