{
  "type": "Feature",
  "properties": {
    "addr:full":"65 Chelwood St Palmerston  Palmerston North Manawatu-Wanganui",
    "addr:housenumber":"65",
    "addr:street":"Chelwood St Palmerston",
    "iso:country":"NZ",
    "sg:address":"65 Chelwood St Palmerston ",
    "sg:city":"Palmerston North",
    "sg:classifiers":[
        {
            "category":"Bars & Pubs",
            "subcategory":"Lounge",
            "type":"Food & Drink"
        }
    ],
    "sg:phone":"+64 6-358 4375",
    "sg:province":"Manawatu-Wanganui",
    "sg:tags":[
        "baker",
        "-"
    ],
    "wof:name":"Chelwood Pies",
    "wof:placetype":"venue"
},
  "geometry": {"coordinates":[175.59657300000001,-40.357689],"type":"Point"}
}