{
  "type": "Feature",
  "properties": {
    "iso:country":"NZ",
    "sg:address":"Tui House 14 Te Ngae Rd Rotorua ",
    "sg:city":"Rotorua",
    "sg:classifiers":[
        {
            "category":"Communications",
            "subcategory":"Film & Video Production",
            "type":"Services"
        }
    ],
    "sg:phone":"+64 7-347 6774",
    "sg:province":"Bay of Plenty",
    "sg:tags":[
        "broadcasting",
        "studio",
        "producer"
    ],
    "wof:name":"Cardno Television & Maui Productions",
    "wof:placetype":"venue"
},
  "geometry": {"coordinates":[176.247986,-38.139851],"type":"Point"}
}