{
  "type": "Feature",
  "properties": {
    "addr:full":"1149 Victoria Rd Tauwhare  Hamilton Waikato",
    "addr:housenumber":"1149",
    "addr:street":"Victoria Rd",
    "iso:country":"NZ",
    "sg:address":"1149 Victoria Rd Tauwhare ",
    "sg:city":"Hamilton",
    "sg:classifiers":[
        {
            "category":"Sports & Exercise",
            "subcategory":"Skate Park",
            "type":"Entertainment"
        }
    ],
    "sg:phone":"+64 7-824 0867",
    "sg:province":"Waikato",
    "sg:tags":[
        "arts",
        "museum",
        "leisure",
        "gallery"
    ],
    "wof:name":"Tauwhare Military Museum",
    "wof:placetype":"venue"
},
  "geometry": {"coordinates":[175.454803,-37.770351],"type":"Point"}
}