{
  "type": "Feature",
  "properties": {
    "addr:full":"400 St Johns Rd Ellerslie  Auckland Auckland",
    "addr:housenumber":"400",
    "addr:street":"St Johns Rd",
    "iso:country":"NZ",
    "sg:address":"400 St Johns Rd Ellerslie ",
    "sg:city":"Auckland",
    "sg:orig_category":"Industrial: Services: Drillers",
    "sg:phone":"+64 9-521 7122",
    "sg:province":"Auckland",
    "wof:name":"Inline Drilling Contractors",
    "wof:placetype":"venue"
},
  "geometry": {"coordinates":[174.80912799999999,-36.884655],"type":"Point"}
}