{
  "type": "Feature",
  "properties": {
    "iso:country":"NZ",
    "sg:address":"Stedman Rd Mosgiel ",
    "sg:city":"Dunedin",
    "sg:classifiers":[
        {
            "category":"Organizations",
            "subcategory":"Labor Organization",
            "type":"Services"
        }
    ],
    "sg:phone":"+64 3-489 7322",
    "sg:province":"Otago",
    "sg:tags":[
        "services",
        "helicopter",
        "travel",
        "tourism"
    ],
    "wof:name":"Helicopters Otago Ltd",
    "wof:placetype":"venue"
},
  "geometry": {"coordinates":[170.37039200000001,-45.85598],"type":"Point"}
}