{
  "type": "Feature",
  "properties": {
    "addr:full":"108 Wilson St  Hawera Taranaki",
    "addr:housenumber":"108",
    "addr:street":"Wilson St",
    "iso:country":"NZ",
    "sg:address":"108 Wilson St ",
    "sg:city":"Hawera",
    "sg:orig_category":"Industrial: Products: Window Control Gear",
    "sg:phone":"+64 6-278 5199",
    "sg:province":"Taranaki",
    "wof:name":"Arthur Brown Construction Co Ltd",
    "wof:placetype":"venue"
},
  "geometry": {"coordinates":[174.28074599999999,-39.581699],"type":"Point"}
}