{
  "type": "Feature",
  "properties": {
    "addr:full":"11 James St  Whangarei Northland",
    "addr:housenumber":"11",
    "addr:street":"James St",
    "iso:country":"NZ",
    "sg:address":"11 James St ",
    "sg:city":"Whangarei",
    "sg:classifiers":[
        {
            "category":"Personal",
            "subcategory":"Massage",
            "type":"Services"
        }
    ],
    "sg:phone":"+64 9-438 6798",
    "sg:province":"Northland",
    "sg:tags":[
        "services",
        "health",
        "-",
        "beauty",
        "fitness"
    ],
    "wof:name":"James St Remedial Massage Clinic",
    "wof:placetype":"venue"
},
  "geometry": {"coordinates":[174.32115200000001,-35.725159],"type":"Point"}
}