{
  "type": "Feature",
  "properties": {
    "addr:full":"Hautotara R D 2  Martinborough Auckland",
    "addr:housenumber":"2",
    "addr:street":"R D",
    "iso:country":"NZ",
    "sg:address":"Hautotara R D 2 ",
    "sg:city":"Martinborough",
    "sg:orig_category":"Travel And Tourism: Accommodation: Farmstays And Homestays",
    "sg:phone":"+64 6-306 9732",
    "sg:province":"Auckland",
    "wof:name":"Hautotara Homestead",
    "wof:placetype":"venue"
},
  "geometry": {"coordinates":[175.45996099999999,-41.220089],"type":"Point"}
}