{
  "type": "Feature",
  "properties": {
    "addr:full":"R D 2 Otautau  Orawia",
    "addr:housenumber":"2",
    "addr:street":"R D;Orawia",
    "iso:country":"NZ",
    "sg:address":"R D 2 Otautau ",
    "sg:city":"Orawia",
    "sg:classifiers":[
        {
            "category":"Food & Beverages",
            "subcategory":"Fruits & Vegetables",
            "type":"Retail Goods"
        }
    ],
    "sg:phone":"+64 3-225 5355",
    "sg:tags":[
        "product",
        "drink",
        "organic",
        "veges"
    ],
    "wof:name":"Mountain Valley Organic Meats Ltd",
    "wof:placetype":"venue"
},
  "geometry": {"coordinates":[167.793915,-46.05315],"type":"Point"}
}