{
  "type": "Feature",
  "properties": {
    "iso:country":"NZ",
    "sg:address":"23 Tocker St Taita Lower ",
    "sg:city":"Hutt",
    "sg:classifiers":[
        {
            "category":"Brewery",
            "type":"Food & Drink"
        }
    ],
    "sg:phone":"+64 4-577 0111",
    "sg:province":"Wellington",
    "sg:tags":[
        "brewer"
    ],
    "wof:name":"Strongcroft Brewery",
    "wof:placetype":"venue"
},
  "geometry": {"coordinates":[174.96038799999999,-41.178745],"type":"Point"}
}