{
  "type": "Feature",
  "properties": {
    "iso:country":"NZ",
    "sg:address":"Rugby Park Stadium Corner Tweed Street & Elles, Rd ",
    "sg:city":"Invercargill",
    "sg:classifiers":[
        {
            "category":"Arena",
            "subcategory":"Sports Club",
            "type":"Entertainment"
        }
    ],
    "sg:phone":"+64 3-216 4068",
    "sg:province":"Canterbury",
    "sg:tags":[
        "-",
        "leisure",
        "sports"
    ],
    "wof:name":"Netball Southland",
    "wof:placetype":"venue"
},
  "geometry": {"coordinates":[168.35217299999999,-46.41185],"type":"Point"}
}