{
  "type": "Feature",
  "properties": {
    "iso:country":"NZ",
    "sg:address":"84 A Elizabeth Knox Pl Panmure ",
    "sg:city":"Auckland",
    "sg:orig_category":"Clothing And Fabric: Fabric: Textiles",
    "sg:phone":"+64 9-527 2905",
    "sg:province":"Auckland",
    "wof:name":"Tritex Holdings Limited",
    "wof:placetype":"venue"
},
  "geometry": {"coordinates":[174.857498,-36.90181],"type":"Point"}
}