{
  "type": "Feature",
  "properties": {
    "iso:country":"NZ",
    "sg:address":"PO Box 15061 ",
    "sg:city":"Tauranga",
    "sg:classifiers":[
        {
            "category":"Recreation",
            "type":"Entertainment"
        }
    ],
    "sg:phone":"+64 25844062",
    "sg:province":"Bay of Plenty",
    "sg:tags":[
        "sport",
        "leisure"
    ],
    "wof:name":"Bay Jetskiis Hire 2000",
    "wof:placetype":"venue"
},
  "geometry": {"coordinates":[176.144745,-37.703156],"type":"Point"}
}