{
  "type": "Feature",
  "properties": {
    "iso:country":"NZ",
    "sg:address":"47 Quintin Dve Te ",
    "sg:city":"Anau",
    "sg:classifiers":[
        {
            "category":"Travel",
            "subcategory":"Hotels & Motels",
            "type":"Entertainment"
        }
    ],
    "sg:phone":"+64 3-249 7256",
    "sg:province":"Southland",
    "sg:tags":[
        "lodge",
        "tourism",
        "accommodation"
    ],
    "sg:website":"http://www.teanaumotel.co.nz",
    "wof:name":"Anchorage Motel 2001 Ltd",
    "wof:placetype":"venue"
},
  "geometry": {"coordinates":[167.71940599999999,-45.416828],"type":"Point"}
}