{
  "type": "Feature",
  "properties": {
    "addr:full":"5 C Druces Rd Manukau  Auckland Auckland",
    "addr:housenumber":"5 c",
    "addr:street":"Druces Rd",
    "iso:country":"NZ",
    "sg:address":"5 C Druces Rd Manukau ",
    "sg:city":"Auckland",
    "sg:classifiers":[
        {
            "category":"Organizations",
            "subcategory":"Religious Organization",
            "type":"Services"
        }
    ],
    "sg:phone":"+64 9-262 1780",
    "sg:province":"Auckland",
    "sg:tags":[
        "arrangements",
        "tent",
        "marquee",
        "wedding"
    ],
    "sg:website":"http://www.yellowpages.co.nz/for/partyhire/dp20583.html",
    "wof:name":"Manukau Party Hire",
    "wof:placetype":"venue"
},
  "geometry": {"coordinates":[-119.10457599999999,36.597755],"type":"Point"}
}