{
  "type": "Feature",
  "properties": {
    "iso:country":"NZ",
    "sg:address":"2 Factory Rd Mosgiel ",
    "sg:city":"Dunedin",
    "sg:classifiers":[
        {
            "category":"Home & Garden",
            "subcategory":"Kitchen Supply",
            "type":"Retail Goods"
        }
    ],
    "sg:phone":"+64 3-489 3716",
    "sg:province":"Otago",
    "sg:tags":[
        "food",
        "equipment",
        "drink",
        "catering"
    ],
    "wof:name":"Stephen White Electrical",
    "wof:placetype":"venue"
},
  "geometry": {"coordinates":[170.347977,-45.873962],"type":"Point"}
}