{
  "type": "Feature",
  "properties": {
    "addr:full":"605 Settlers Rd  Reporoa",
    "addr:housenumber":"605",
    "addr:street":"Settlers Rd",
    "iso:country":"NZ",
    "sg:address":"605 Settlers Rd ",
    "sg:city":"Reporoa",
    "sg:orig_category":"Farming: Services: Veterinarians",
    "sg:phone":"+64 7-333 8707",
    "wof:name":"Veterinary Centre",
    "wof:placetype":"venue"
},
  "geometry": {"coordinates":[176.34553500000001,-38.424908],"type":"Point"}
}