{
  "type": "Feature",
  "properties": {
    "addr:full":"Mirrielees Rd  Tauranga Bay of Plenty",
    "addr:street":"Mirrielees Rd",
    "iso:country":"NZ",
    "sg:address":"Mirrielees Rd ",
    "sg:city":"Tauranga",
    "sg:orig_category":"Industrial: Metal: Scrap Metal Dealers",
    "sg:phone":"+64 7-578 2543",
    "sg:province":"Bay of Plenty",
    "wof:name":"Corbett Steel Scrap Ltd",
    "wof:placetype":"venue"
},
  "geometry": {"coordinates":[176.169556,-37.669209],"type":"Point"}
}