{
  "type": "Feature",
  "properties": {
    "iso:country":"NZ",
    "sg:address":"33 Falcon St Parnell ",
    "sg:city":"Auckland",
    "sg:orig_category":"Clothing And Fabric: Fabric: Textiles",
    "sg:phone":"+64 9-307 3540",
    "sg:province":"Auckland",
    "wof:name":"Fabriche Textiles Ltd",
    "wof:placetype":"venue"
},
  "geometry": {"coordinates":[174.77963299999999,-36.855179],"type":"Point"}
}