{
  "type": "Feature",
  "properties": {
    "addr:full":"cnr Eleventh Ave & Cameron Ave  Tauranga Bay of Plenty",
    "addr:street":"Cnr Eleventh Ave & Cameron Ave",
    "iso:country":"NZ",
    "sg:address":"cnr Eleventh Ave & Cameron Ave ",
    "sg:city":"Tauranga",
    "sg:orig_category":"Industrial: Equipment And Machinery: Specialist Equipment: Machinery: Sewing Machines",
    "sg:phone":"+64 7-578 5480",
    "sg:province":"Bay of Plenty",
    "wof:name":"Bernina Sewing Centres",
    "wof:placetype":"venue"
},
  "geometry": {"coordinates":[176.14475999999999,-37.703152],"type":"Point"}
}