{
  "type": "Feature",
  "properties": {
    "iso:country":"NZ",
    "sg:address":"20 Eastern Hutt Rd Lower Hutt ",
    "sg:city":"Wellington",
    "sg:classifiers":[
        {
            "category":"Restaurant",
            "type":"Food & Drink"
        }
    ],
    "sg:phone":"+64 4-939 8295",
    "sg:province":"Wellington",
    "sg:tags":[
        "merchant",
        "fish",
        "sea"
    ],
    "wof:name":"Fish Wharf Ltd",
    "wof:placetype":"venue"
},
  "geometry": {"coordinates":[174.908386,-41.206631],"type":"Point"}
}