{
  "type": "Feature",
  "properties": {
    "iso:country":"NZ",
    "sg:address":"98 Commercial St ",
    "sg:city":"Takaka",
    "sg:classifiers":[
        {
            "category":"Bus Charters",
            "type":"Transportation"
        }
    ],
    "sg:phone":"+64 3-525 8352",
    "sg:tags":[
        "services",
        "travel",
        "tourism"
    ],
    "wof:name":"Bickley Motors Ltd",
    "wof:placetype":"venue"
},
  "geometry": {"coordinates":[172.80714399999999,-40.85276],"type":"Point"}
}