{
  "type": "Feature",
  "properties": {
    "iso:country":"NZ",
    "sg:address":"8 Queen St Te ",
    "sg:city":"Kuiti",
    "sg:orig_category":"Transport: Transportation: Carriers",
    "sg:phone":"+64 7-878 7120",
    "wof:name":"Sorensen KR Carriers",
    "wof:placetype":"venue"
},
  "geometry": {"coordinates":[175.164551,-38.344055],"type":"Point"}
}