{
  "type": "Feature",
  "properties": {
    "addr:full":"2 B Lydney Pl  Porirua Wellington",
    "addr:housenumber":"2 b",
    "addr:street":"Lydney Pl",
    "iso:country":"NZ",
    "sg:address":"2 B Lydney Pl ",
    "sg:city":"Porirua",
    "sg:classifiers":[
        {
            "category":"Ice Cream",
            "type":"Food & Drink"
        }
    ],
    "sg:phone":"+64 4-237 7501",
    "sg:province":"Wellington",
    "sg:tags":[
        "frozen",
        "-"
    ],
    "wof:name":"Stone Cold Direct",
    "wof:placetype":"venue"
},
  "geometry": {"coordinates":[174.85223400000001,-41.138294],"type":"Point"}
}