{
  "type": "Feature",
  "properties": {
    "addr:full":"7 Wynyard St Devonport  Auckland Auckland",
    "addr:housenumber":"7",
    "addr:street":"Wynyard St",
    "iso:country":"NZ",
    "sg:address":"7 Wynyard St Devonport ",
    "sg:city":"Auckland",
    "sg:classifiers":[
        {
            "category":"Marine",
            "type":"Transportation"
        }
    ],
    "sg:phone":"+64 9-445 0545",
    "sg:province":"Auckland",
    "sg:tags":[
        "transport",
        "boat"
    ],
    "sg:website":"http://www.marinelink.co.nz/Builders/kjbb.htm",
    "wof:name":"Kevin Johnson Boat Builders Ltd",
    "wof:placetype":"venue"
},
  "geometry": {"coordinates":[174.79583700000001,-36.831505],"type":"Point"}
}