{
  "type": "Feature",
  "properties": {
    "iso:country":"NZ",
    "sg:address":"94 Mulgrave St ",
    "sg:city":"Ashhurst",
    "sg:classifiers":[
        {
            "category":"Shopping",
            "subcategory":"Pets & Pet Supplies",
            "type":"Retail Goods"
        }
    ],
    "sg:phone":"+64 6-326 8553",
    "sg:tags":[
        "boarding",
        "garden",
        "pets",
        "catteries",
        "home",
        "kennel"
    ],
    "wof:name":"Tolly Farm Boarding",
    "wof:placetype":"venue"
},
  "geometry": {"coordinates":[175.75100699999999,-40.294182],"type":"Point"}
}