{
  "type": "Feature",
  "properties": {
    "iso:country":"NZ",
    "sg:address":"cnr Glasgow & London Sts ",
    "sg:city":"Wanganui",
    "sg:classifiers":[
        {
            "category":"Home & Garden",
            "subcategory":"Building Materials",
            "type":"Retail Goods"
        }
    ],
    "sg:phone":"+64 6-345 0638",
    "sg:province":"Manawatu-Wanganui",
    "sg:tags":[
        "electrician",
        "related"
    ],
    "wof:name":"Wanganui Electrical Services Ltd",
    "wof:placetype":"venue"
},
  "geometry": {"coordinates":[175.052841,-39.933369],"type":"Point"}
}