{
  "type": "Feature",
  "properties": {
    "iso:country":"NZ",
    "sg:address":"1388 Dominion Rd Mt Roskill ",
    "sg:city":"Auckland",
    "sg:orig_category":"Sports And Leisure: Sports: Golf: Golf Courses",
    "sg:phone":"+64 9-620 5461",
    "sg:province":"Auckland",
    "wof:name":"Akarana Golf Club Inc",
    "wof:placetype":"venue"
},
  "geometry": {"coordinates":[174.739075,-36.913364],"type":"Point"}
}