{
  "type": "Feature",
  "properties": {
    "iso:country":"NZ",
    "sg:address":"Tau Henare Dve Waitangi ",
    "sg:city":"Paihia",
    "sg:orig_category":"Food And Drink: Catering: Caterers",
    "sg:phone":"+64 9-402 6275",
    "sg:province":"Canterbury",
    "wof:name":"Ate At a Table",
    "wof:placetype":"venue"
},
  "geometry": {"coordinates":[174.091064,-35.283691],"type":"Point"}
}