{
  "type": "Feature",
  "properties": {
    "iso:country":"NZ",
    "sg:address":"Porirua ",
    "sg:city":"Wellington",
    "sg:orig_category":"Health And Beauty: Specialists: Midwives",
    "sg:phone":"+64 4-801 0215",
    "sg:province":"Wellington",
    "wof:name":"Aotea Midwives",
    "wof:placetype":"venue"
},
  "geometry": {"coordinates":[174.84071399999999,-41.138359],"type":"Point"}
}