{
  "type": "Feature",
  "properties": {
    "addr:full":"1 Marsh St  Tauranga Bay of Plenty",
    "addr:housenumber":"1",
    "addr:street":"Marsh St",
    "iso:country":"NZ",
    "sg:address":"1 Marsh St ",
    "sg:city":"Tauranga",
    "sg:orig_category":"Shopping: Retail Stores: Secondhand Dealers",
    "sg:phone":"+64 7-579 0009",
    "sg:province":"Bay of Plenty",
    "wof:name":"Bargain Beds Secondhand & New",
    "wof:placetype":"venue"
},
  "geometry": {"coordinates":[176.168915,-37.675655],"type":"Point"}
}