{
  "type": "Feature",
  "properties": {
    "iso:country":"NZ",
    "sg:address":"Wiri Station Rd Wiri ",
    "sg:city":"Auckland",
    "sg:orig_category":"Home And Garden: Gardening: Products: Bark Products",
    "sg:phone":"+64 9-262 3215",
    "sg:province":"Auckland",
    "sg:website":"http://www.fence-crete.co.nz",
    "wof:name":"Fence Crete Ltd",
    "wof:placetype":"venue"
},
  "geometry": {"coordinates":[174.87446600000001,-36.99876],"type":"Point"}
}