{
  "type": "Feature",
  "properties": {
    "iso:country":"NZ",
    "sg:address":"(off Rangitikei line) 19 Jasper Pl Palmerston ",
    "sg:city":"Palmerston North",
    "sg:orig_category":"Storage: Storage",
    "sg:phone":"+64 6-353 2250",
    "sg:province":"Manawatu-Wanganui",
    "wof:name":"Fort Knox Self Storage",
    "wof:placetype":"venue"
},
  "geometry": {"coordinates":[175.599777,-40.339676],"type":"Point"}
}