{
  "type": "Feature",
  "properties": {
    "iso:country":"NZ",
    "sg:address":"2 Crown Hill ",
    "sg:city":"Paraparaumu",
    "sg:classifiers":[
        {
            "category":"Arena",
            "subcategory":"Sports Club",
            "type":"Entertainment"
        }
    ],
    "sg:phone":"+64 4-902 3633",
    "sg:province":"Wellington",
    "sg:tags":[
        "-",
        "leisure",
        "sports"
    ],
    "wof:name":"Kapiti Petanque Club",
    "wof:placetype":"venue"
},
  "geometry": {"coordinates":[175.00900300000001,-40.898304],"type":"Point"}
}