{
  "type": "Feature",
  "properties": {
    "addr:full":"12 Cordelia Pl Avondale  Auckland Auckland",
    "addr:housenumber":"12",
    "addr:street":"Cordelia Pl",
    "iso:country":"NZ",
    "sg:address":"12 Cordelia Pl Avondale ",
    "sg:city":"Auckland",
    "sg:classifiers":[
        {
            "category":"Social Services",
            "subcategory":"Retirement Home",
            "type":"Services"
        }
    ],
    "sg:phone":"+64 9-626 7468",
    "sg:province":"Auckland",
    "sg:tags":[
        "automotive"
    ],
    "sg:website":"http://www.yellowpages.co.nz/for/abacusrentalcars/dp3199.html",
    "wof:name":"Abacus Rental Cars Ltd",
    "wof:placetype":"venue"
},
  "geometry": {"coordinates":[174.690933,-36.8932],"type":"Point"}
}