{
  "type": "Feature",
  "properties": {
    "addr:full":"6 a Piermark Dve Albany  Auckland Auckland",
    "addr:housenumber":"6",
    "addr:street":"A Piermark",
    "iso:country":"NZ",
    "sg:address":"6 a Piermark Dve Albany ",
    "sg:city":"Auckland",
    "sg:classifiers":[
        {
            "category":"Wholesale",
            "subcategory":"Electrical",
            "type":"Manufacturing & Wholesale Goods"
        }
    ],
    "sg:phone":"+64 9-414 0330",
    "sg:province":"Auckland",
    "sg:tags":[
        "wire",
        "electrical/electronic",
        "industrial",
        "electric",
        "cable"
    ],
    "sg:website":"http://www.yellowpages.co.nz/for/maser/dp16640.html",
    "wof:name":"Maser Wire & Cable Limited",
    "wof:placetype":"venue"
},
  "geometry": {"coordinates":[174.70375100000001,-36.748043],"type":"Point"}
}