{
  "type": "Feature",
  "properties": {
    "addr:full":"R D 3  Takapau",
    "addr:housenumber":"3",
    "addr:street":"R D",
    "iso:country":"NZ",
    "sg:address":"R D 3 ",
    "sg:city":"Takapau",
    "sg:classifiers":[
        {
            "category":"Shopping",
            "subcategory":"Pharmacy",
            "type":"Retail Goods"
        }
    ],
    "sg:phone":"+64 6-855 8404",
    "sg:tags":[
        "product",
        "health"
    ],
    "wof:name":"Gevir Premium Deer Velvet Ltd",
    "wof:placetype":"venue"
},
  "geometry": {"coordinates":[176.34875500000001,-40.025593],"type":"Point"}
}