{
  "type": "Feature",
  "properties": {
    "addr:full":"63 Palmerston St  Westport West Coast",
    "addr:housenumber":"63",
    "addr:street":"Palmerston St",
    "iso:country":"NZ",
    "sg:address":"63 Palmerston St ",
    "sg:city":"Westport",
    "sg:classifiers":[
        {
            "category":"Home & Garden",
            "subcategory":"Garden Supply",
            "type":"Retail Goods"
        }
    ],
    "sg:phone":"+64 274 486 648",
    "sg:province":"West Coast",
    "sg:tags":[
        "trainer",
        "breeder",
        "/",
        "pets",
        "animal"
    ],
    "wof:name":"Cedar Park Alpacas",
    "wof:placetype":"venue"
},
  "geometry": {"coordinates":[-123.78488900000001,39.639027],"type":"Point"}
}