{
  "type": "Feature",
  "properties": {
    "addr:full":"73 Courtenay Pl Wellington Wellington",
    "addr:housenumber":"73",
    "addr:street":"Courtenay Pl",
    "iso:country":"NZ",
    "sg:address":"73 Courtenay Pl",
    "sg:city":"Wellington",
    "sg:classifiers":[
        {
            "category":"Banks & Credit Unions",
            "subcategory":"Bank",
            "type":"Services"
        }
    ],
    "sg:phone":"+64 4847767",
    "sg:province":"Wellington",
    "wof:name":"ANZ Banking Group Ltd",
    "wof:placetype":"venue"
},
  "geometry": {"coordinates":[-83.54471599999999,37.881409],"type":"Point"}
}