{
  "type": "Feature",
  "properties": {
    "addr:full":"Nicholson Rd Khandallah  Wellington Wellington",
    "addr:street":"Nicholson Rd",
    "iso:country":"NZ",
    "sg:address":"Nicholson Rd Khandallah ",
    "sg:city":"Wellington",
    "sg:orig_category":"Education And Training: General: Schools",
    "sg:phone":"+64 4-479 6878",
    "sg:province":"Wellington",
    "wof:name":"St Benedicts",
    "wof:placetype":"venue"
},
  "geometry": {"coordinates":[174.792068,-41.256268],"type":"Point"}
}