{
  "type": "Feature",
  "properties": {
    "iso:country":"NZ",
    "sg:address":"33 Levley La ",
    "sg:city":"Katikati",
    "sg:orig_category":"Farming: Agriculture: Agricultural Consultants",
    "sg:phone":"+64 7-549 1413",
    "wof:name":"Barlow Soil & Crop",
    "wof:placetype":"venue"
},
  "geometry": {"coordinates":[175.924805,-37.541637],"type":"Point"}
}