{
  "type": "Feature",
  "properties": {
    "addr:full":"33 Levley La  Katikati",
    "addr:housenumber":"33",
    "addr:street":"Levley La Katikati",
    "iso:country":"NZ",
    "sg:address":"33 Levley La ",
    "sg:city":"Katikati",
    "sg:orig_category":"Farming: Agriculture: Agricultural Consultants",
    "sg:phone":"+64 7-549 1413",
    "wof:name":"Barlow Soil & Crop",
    "wof:placetype":"venue"
},
  "geometry": {"coordinates":[175.92480499999999,-37.541637],"type":"Point"}
}