{
  "type": "Feature",
  "properties": {
    "iso:country":"NZ",
    "sg:address":"94 Cordelia St Sth ",
    "sg:city":"Stratford",
    "sg:classifiers":[
        {
            "category":"Manufacturing",
            "subcategory":"Glass & Minerals",
            "type":"Manufacturing & Wholesale Goods"
        }
    ],
    "sg:phone":"+64 6-765 6165",
    "sg:tags":[
        "raw",
        "industrial",
        "materials",
        "quarry",
        "equipment"
    ],
    "wof:name":"Stratford Quarry Equipment Ltd (Johnco Spare Parts)",
    "wof:placetype":"venue"
},
  "geometry": {"coordinates":[-119.824966,36.189419],"type":"Point"}
}