{
  "type": "Feature",
  "properties": {
    "iso:country":"NZ",
    "sg:address":"Rewarewa Rd ",
    "sg:city":"Whangarei",
    "sg:classifiers":[
        {
            "category":"Manufacturing",
            "subcategory":"Glass & Minerals",
            "type":"Manufacturing & Wholesale Goods"
        }
    ],
    "sg:phone":"+64 9-438 6984",
    "sg:province":"Northland",
    "sg:tags":[
        "raw",
        "industrial",
        "quarry",
        "materials"
    ],
    "wof:name":"Kamo Scoria",
    "wof:placetype":"venue"
},
  "geometry": {"coordinates":[174.31518600000001,-35.752209],"type":"Point"}
}