{
  "type": "Feature",
  "properties": {
    "addr:full":"756 Kihikihi Rd Te  Awamutu Waikato",
    "addr:housenumber":"756",
    "addr:street":"Kihikihi Rd",
    "iso:country":"NZ",
    "sg:address":"756 Kihikihi Rd Te ",
    "sg:city":"Awamutu",
    "sg:orig_category":"Home And Garden: Outdoor: Stonemasons",
    "sg:phone":"+64 7-871 3602",
    "sg:province":"Waikato",
    "wof:name":"Classic Stone Work",
    "wof:placetype":"venue"
},
  "geometry": {"coordinates":[175.33763099999999,-38.028965],"type":"Point"}
}