{
  "type": "Feature",
  "properties": {
    "addr:full":"96 Hatea Dve Regent  Whangarei Northland",
    "addr:housenumber":"96",
    "addr:street":"Hatea Dve",
    "iso:country":"NZ",
    "sg:address":"96 Hatea Dve Regent ",
    "sg:city":"Whangarei",
    "sg:orig_category":"Shopping: Sports Retailers: Sports Goods: Dance Supplies",
    "sg:phone":"+64 9-437 2906",
    "sg:province":"Northland",
    "wof:name":"Dress for Dance",
    "wof:placetype":"venue"
},
  "geometry": {"coordinates":[174.321777,-35.7183],"type":"Point"}
}