{
  "type": "Feature",
  "properties": {
    "addr:full":"Westgate Shopping Centre Massey  Auckland Otago",
    "addr:street":"Westgate;Centre",
    "iso:country":"NZ",
    "sg:address":"Westgate Shopping Centre Massey ",
    "sg:city":"Auckland",
    "sg:classifiers":[
        {
            "category":"Manufacturing",
            "subcategory":"Rubber & Plastics",
            "type":"Manufacturing & Wholesale Goods"
        }
    ],
    "sg:phone":"+64 9-831 0243",
    "sg:province":"Otago",
    "sg:tags":[
        "industrial",
        "goods"
    ],
    "wof:name":"Plastic Box",
    "wof:placetype":"venue"
},
  "geometry": {"coordinates":[174.63568100000001,-36.828793],"type":"Point"}
}