{
  "type": "Feature",
  "properties": {
    "addr:full":"28 b Greenmount Dve East Tamaki  Auckland Auckland",
    "addr:housenumber":"28 b",
    "addr:street":"Greenmount Dve",
    "iso:country":"NZ",
    "sg:address":"28 b Greenmount Dve East Tamaki ",
    "sg:city":"Auckland",
    "sg:classifiers":[
        {
            "category":"Health Services",
            "subcategory":"Health Practitioner",
            "type":"Services"
        }
    ],
    "sg:phone":"+64 9-274 3299",
    "sg:province":"Auckland",
    "sg:tags":[
        "equipment",
        "beauty",
        "fitness"
    ],
    "wof:name":"Fitness Technology",
    "wof:placetype":"venue"
},
  "geometry": {"coordinates":[174.90103099999999,-36.933941],"type":"Point"}
}