{
  "type": "Feature",
  "properties": {
    "addr:full":"24 Barrys Point Rd Takapuna  Auckland Auckland",
    "addr:housenumber":"24",
    "addr:street":"Barrys Point Rd",
    "iso:country":"NZ",
    "sg:address":"24 Barrys Point Rd Takapuna ",
    "sg:city":"Auckland",
    "sg:classifiers":[
        {
            "category":"Retail",
            "subcategory":"Auto Repair",
            "type":"Services"
        }
    ],
    "sg:phone":"+64 9-489 7010",
    "sg:province":"Auckland",
    "sg:tags":[
        "muffler",
        "exhaust",
        "servicing",
        "automotive"
    ],
    "wof:name":"Takapuna Mufflers Ltd",
    "wof:placetype":"venue"
},
  "geometry": {"coordinates":[174.76518200000001,-36.792297],"type":"Point"}
}