{
  "type": "Feature",
  "properties": {
    "iso:country":"NZ",
    "sg:address":"25 McPhee St ",
    "sg:city":"Dannevirke",
    "sg:classifiers":[
        {
            "category":"Personal",
            "type":"Services"
        }
    ],
    "sg:phone":"+64 6-374 7316",
    "sg:tags":[
        "celebrant",
        "arrangements",
        "marriage",
        "wedding"
    ],
    "wof:name":"Edwards-Sextus Mrs P",
    "wof:placetype":"venue"
},
  "geometry": {"coordinates":[-98.60567500000001,41.329346],"type":"Point"}
}