{
  "type": "Feature",
  "properties": {
    "addr:full":"Main Highway Kumeu  Auckland Auckland",
    "addr:street":"Main Highway",
    "iso:country":"NZ",
    "sg:address":"Main Highway Kumeu ",
    "sg:city":"Auckland",
    "sg:orig_category":"Farming: Machinery: Tractors",
    "sg:phone":"+64 9-412 8965",
    "sg:province":"Auckland",
    "wof:name":"Kumeu Tractors Ltd",
    "wof:placetype":"venue"
},
  "geometry": {"coordinates":[174.80398600000001,-36.896004],"type":"Point"}
}