{
  "type": "Feature",
  "properties": {
    "addr:full":"22 Dorset St PO Box 25103 Victoria Street  Christchurch Otago",
    "addr:housenumber":"22;box",
    "addr:street":"Dorset St Po;25103 Victoria Street",
    "iso:country":"NZ",
    "sg:address":"22 Dorset St PO Box 25103 Victoria Street ",
    "sg:city":"Christchurch",
    "sg:orig_category":"Transport: Consultancy: Engineers - Traffic",
    "sg:phone":"+64 3-366 9871",
    "sg:province":"Otago",
    "wof:name":"Transportation & Traffic Systems Ltd",
    "wof:placetype":"venue"
},
  "geometry": {"coordinates":[-1.776564,50.73407],"type":"Point"}
}