{
  "type": "Feature",
  "properties": {
    "addr:full":"Railway Rd Whakatu  Napier Hawke's Bay",
    "addr:street":"Railway Rd",
    "iso:country":"NZ",
    "sg:address":"Railway Rd Whakatu ",
    "sg:city":"Napier",
    "sg:orig_category":"Industrial: Products: Tallow Merchants",
    "sg:phone":"+64 6-870 0374",
    "sg:province":"Hawke's Bay",
    "wof:name":"Liquistore (HB)",
    "wof:placetype":"venue"
},
  "geometry": {"coordinates":[176.90017700000001,-39.601734],"type":"Point"}
}