{
  "type": "Feature",
  "properties": {
    "iso:country":"NZ",
    "sg:address":"UNT.B/77 Hillside Rd Glenfield ",
    "sg:city":"Auckland",
    "sg:classifiers":[
        {
            "category":"Restaurant",
            "type":"Food & Drink"
        }
    ],
    "sg:phone":"+64 9-444 5121",
    "sg:province":"Auckland",
    "sg:tags":[
        "equipment",
        "machinery"
    ],
    "wof:name":"Interfood NZ (1998) Ltd",
    "wof:placetype":"venue"
},
  "geometry": {"coordinates":[174.728622,-36.784813],"type":"Point"}
}