{
  "type": "Feature",
  "properties": {
    "addr:full":"184 Victoria Ave  Wanganui Manawatu-Wanganui",
    "addr:housenumber":"184",
    "addr:street":"Victoria Ave",
    "iso:country":"NZ",
    "sg:address":"184 Victoria Ave ",
    "sg:city":"Wanganui",
    "sg:orig_category":"Shopping: Sports Retailers: Sports Goods: Sporting Goods",
    "sg:phone":"+64 6-345 5391",
    "sg:province":"Manawatu-Wanganui",
    "wof:name":"Eides Sportsworld",
    "wof:placetype":"venue"
},
  "geometry": {"coordinates":[175.04856899999999,-39.930672],"type":"Point"}
}