{
  "type": "Feature",
  "properties": {
    "iso:country":"NZ",
    "sg:address":"641 Manukau Rd Epsom ",
    "sg:city":"Auckland",
    "sg:classifiers":[
        {
            "category":"Health Services",
            "subcategory":"Clinic",
            "type":"Services"
        }
    ],
    "sg:phone":"+64 9-625 1462",
    "sg:province":"Auckland",
    "sg:tags":[
        "medical",
        "beauty"
    ],
    "wof:name":"Jones Mr Wayne O",
    "wof:placetype":"venue"
},
  "geometry": {"coordinates":[174.773026,-36.8997],"type":"Point"}
}