{
  "type": "Feature",
  "properties": {
    "addr:full":"1262 Dominion Rd Mt Roskill  Auckland Auckland",
    "addr:housenumber":"1262",
    "addr:street":"Dominion Rd",
    "iso:country":"NZ",
    "sg:address":"1262 Dominion Rd Mt Roskill ",
    "sg:city":"Auckland",
    "sg:orig_category":"Clothing And Fabric: Clothing: Menswear",
    "sg:phone":"+64 9-620 9496",
    "sg:province":"Auckland",
    "wof:name":"Roskill Ladies Mens Boys Outfitters",
    "wof:placetype":"venue"
},
  "geometry": {"coordinates":[174.74169900000001,-36.904678],"type":"Point"}
}