{
  "type": "Feature",
  "properties": {
    "iso:country":"NZ",
    "sg:address":"64 Ponsonby Rd Ponsonby ",
    "sg:city":"Auckland",
    "sg:classifiers":[
        {
            "category":"Personal",
            "subcategory":"Tattoo Parlor",
            "type":"Services"
        }
    ],
    "sg:phone":"+64 9-376 7217",
    "sg:province":"Auckland",
    "sg:tags":[
        "services",
        "home",
        "tattooists",
        "garden"
    ],
    "wof:name":"Auckland Tattoo Studio",
    "wof:placetype":"venue"
},
  "geometry": {"coordinates":[174.74676500000001,-36.856407],"type":"Point"}
}