{
  "type": "Feature",
  "properties": {
    "addr:full":"40 Tuwharetoa St  Taupo Waikato",
    "addr:housenumber":"40",
    "addr:street":"Tuwharetoa St",
    "iso:country":"NZ",
    "sg:address":"40 Tuwharetoa St ",
    "sg:city":"Taupo",
    "sg:orig_category":"Shopping: Retail Stores: Books: Books - Secondhand",
    "sg:phone":"+64 7-378 0862",
    "sg:province":"Waikato",
    "wof:name":"Silver Fish Books",
    "wof:placetype":"venue"
},
  "geometry": {"coordinates":[176.07115200000001,-38.688839],"type":"Point"}
}