{
  "type": "Feature",
  "properties": {
    "iso:country":"NZ",
    "sg:address":"563 Dominion Rd Mt Eden ",
    "sg:city":"Auckland",
    "sg:orig_category":"Shopping: Retail Stores: Secondhand Dealers",
    "sg:phone":"+64 9-630 8641",
    "sg:province":"Auckland",
    "wof:name":"IOU Furniture",
    "wof:placetype":"venue"
},
  "geometry": {"coordinates":[174.746918,-36.888103],"type":"Point"}
}