{
  "type": "Feature",
  "properties": {
    "addr:full":"563 Dominion Rd Mt Eden  Auckland Auckland",
    "addr:housenumber":"563",
    "addr:street":"Dominion Rd",
    "iso:country":"NZ",
    "sg:address":"563 Dominion Rd Mt Eden ",
    "sg:city":"Auckland",
    "sg:orig_category":"Shopping: Retail Stores: Secondhand Dealers",
    "sg:phone":"+64 9-630 8641",
    "sg:province":"Auckland",
    "wof:name":"IOU Furniture",
    "wof:placetype":"venue"
},
  "geometry": {"coordinates":[174.74691799999999,-36.888103],"type":"Point"}
}