{
  "type": "Feature",
  "properties": {
    "addr:full":"PO Box 2020 Gonville  Wanganui Manawatu-Wanganui",
    "addr:housenumber":"po",
    "addr:postcode":"2020",
    "addr:street":"Box",
    "iso:country":"NZ",
    "sg:address":"PO Box 2020 Gonville ",
    "sg:city":"Wanganui",
    "sg:classifiers":[
        {
            "category":"Professional",
            "type":"Services"
        }
    ],
    "sg:phone":"+64 6-344 4811",
    "sg:province":"Manawatu-Wanganui",
    "sg:tags":[
        "services",
        "car",
        "valet",
        "automotive"
    ],
    "wof:name":"Car Valet Services",
    "wof:placetype":"venue"
},
  "geometry": {"coordinates":[175.02294900000001,-39.941048],"type":"Point"}
}