{
  "type": "Feature",
  "properties": {
    "addr:full":"11 Darroch St  Belfast Canterbury",
    "addr:housenumber":"11",
    "addr:street":"Darroch St",
    "iso:country":"NZ",
    "sg:address":"11 Darroch St ",
    "sg:city":"Belfast",
    "sg:classifiers":[
        {
            "category":"Manufacturing",
            "subcategory":"Motor Vehicles & Parts",
            "type":"Manufacturing & Wholesale Goods"
        }
    ],
    "sg:phone":"+64 3-323 8068",
    "sg:province":"Canterbury",
    "sg:tags":[
        "battery",
        "automotive",
        "charging",
        "supplies"
    ],
    "wof:name":"Electro Products & Services Ltd",
    "wof:placetype":"venue"
},
  "geometry": {"coordinates":[-69.00797300000001,44.425869],"type":"Point"}
}