{
  "type": "Feature",
  "properties": {
    "addr:full":"PO Box 35165 Lower  Hutt Wellington",
    "addr:housenumber":"po box",
    "addr:postcode":"35165",
    "iso:country":"NZ",
    "sg:address":"PO Box 35165 Lower ",
    "sg:city":"Hutt",
    "sg:orig_category":"Industrial: Services: Abseil - Industrial",
    "sg:phone":"+64 274 475 160",
    "sg:province":"Wellington",
    "wof:name":"Skywash High Rise Maintenance",
    "wof:placetype":"venue"
},
  "geometry": {"coordinates":[174.90838600000001,-41.206631],"type":"Point"}
}