{
  "type": "Feature",
  "properties": {
    "addr:full":"77 Forrester Dve Welcome Bay  Tauranga Bay of Plenty",
    "addr:housenumber":"77;dve",
    "addr:street":"Forrester",
    "iso:country":"NZ",
    "sg:address":"77 Forrester Dve Welcome Bay ",
    "sg:city":"Tauranga",
    "sg:orig_category":"Industrial: Electrical/Electronic: Electronic Equipment",
    "sg:phone":"+64 7-544 1378",
    "sg:province":"Bay of Plenty",
    "wof:name":"B J B Electronics",
    "wof:placetype":"venue"
},
  "geometry": {"coordinates":[176.19676200000001,-37.721306],"type":"Point"}
}