{
  "type": "Feature",
  "properties": {
    "addr:full":"Church St Palmerston  Palmerston North Manawatu-Wanganui",
    "addr:street":"Church St",
    "iso:country":"NZ",
    "sg:address":"Church St Palmerston ",
    "sg:city":"Palmerston North",
    "sg:classifiers":[
        {
            "category":"Personal",
            "subcategory":"Beauty Salon",
            "type":"Services"
        }
    ],
    "sg:phone":"+64 6-357 4527",
    "sg:province":"Manawatu-Wanganui",
    "sg:tags":[
        "new age",
        "health",
        "services",
        "professional"
    ],
    "wof:name":"Astrological Advice Centre The",
    "wof:placetype":"venue"
},
  "geometry": {"coordinates":[175.599197,-40.363003],"type":"Point"}
}