{
  "type": "Feature",
  "properties": {
    "addr:full":"34 Cartwright Rd Glen Eden  Auckland Auckland",
    "addr:housenumber":"34",
    "addr:street":"Cartwright Rd",
    "iso:country":"NZ",
    "sg:address":"34 Cartwright Rd Glen Eden ",
    "sg:city":"Auckland",
    "sg:orig_category":"Industrial: Metal: Services: Steel Processing",
    "sg:phone":"+64 9-818 7606",
    "sg:province":"Auckland",
    "wof:name":"Pengelly Engineers Ltd",
    "wof:placetype":"venue"
},
  "geometry": {"coordinates":[174.65991199999999,-36.903244],"type":"Point"}
}