{
  "type": "Feature",
  "properties": {
    "addr:full":"27 Buckingham St  Arrowtown Otago",
    "addr:housenumber":"27",
    "addr:street":"Buckingham St",
    "iso:country":"NZ",
    "sg:address":"27 Buckingham St ",
    "sg:city":"Arrowtown",
    "sg:classifiers":[
        {
            "category":"Travel",
            "subcategory":"Hotels & Motels",
            "type":"Entertainment"
        }
    ],
    "sg:phone":"+64 3-442 1745",
    "sg:province":"Otago",
    "sg:tags":[
        "tavern",
        "tourism",
        "accommodation"
    ],
    "wof:name":"New Orleans Hotel",
    "wof:placetype":"venue"
},
  "geometry": {"coordinates":[168.83175700000001,-44.938343],"type":"Point"}
}