{
  "type": "Feature",
  "properties": {
    "iso:country":"NZ",
    "sg:address":"120 High St ",
    "sg:city":"Southbridge",
    "sg:orig_category":"Industrial: Services: Drillers",
    "sg:phone":"+64 3-324 2571",
    "wof:name":"McMillan Laboratory Services",
    "wof:placetype":"venue"
},
  "geometry": {"coordinates":[-72.045273,42.077225],"type":"Point"}
}