{
  "type": "Feature",
  "properties": {
    "iso:country":"NZ",
    "sg:address":"250 Lake Rd Takapuna ",
    "sg:city":"Auckland",
    "sg:orig_category":"Health And Beauty: Mental: Psychotherapy",
    "sg:phone":"+64 9-489 1932",
    "sg:province":"Auckland",
    "wof:name":"Burgham-Page Maxine",
    "wof:placetype":"venue"
},
  "geometry": {"coordinates":[174.775864,-36.793648],"type":"Point"}
}