{
  "type": "Feature",
  "properties": {
    "iso:country":"NZ",
    "sg:address":"914 Clevedon-Kawakawa Bay Rd Clevedon ",
    "sg:city":"Auckland",
    "sg:classifiers":[
        {
            "category":"Fast Food",
            "type":"Food & Drink"
        }
    ],
    "sg:phone":"+64 9-292 8017",
    "sg:province":"Auckland",
    "sg:tags":[
        "seafood",
        "sea"
    ],
    "wof:name":"Clevedon Coast Oysters",
    "wof:placetype":"venue"
},
  "geometry": {"coordinates":[175.101303,-36.951958],"type":"Point"}
}