{
  "type": "Feature",
  "properties": {
    "addr:full":"20 Brighton Mall New Brighton  Christchurch Canterbury",
    "addr:housenumber":"20",
    "addr:street":"Brighton Mall",
    "iso:country":"NZ",
    "sg:address":"20 Brighton Mall New Brighton ",
    "sg:city":"Christchurch",
    "sg:classifiers":[
        {
            "category":"Personal",
            "subcategory":"Tattoo Parlor",
            "type":"Services"
        }
    ],
    "sg:phone":"+64 3-382 3023",
    "sg:province":"Canterbury",
    "sg:tags":[
        "services",
        "home",
        "tattooists",
        "garden"
    ],
    "wof:name":"Pegasus Tattoos",
    "wof:placetype":"venue"
},
  "geometry": {"coordinates":[172.73019400000001,-43.506935],"type":"Point"}
}