{
  "type": "Feature",
  "properties": {
    "iso:country":"NZ",
    "sg:address":"1 Southbrook Rd ",
    "sg:city":"Rangiora",
    "sg:orig_category":"Farming: Supplies: Farm Buildings",
    "sg:phone":"+64 3-313 8339",
    "sg:province":"Canterbury",
    "wof:name":"McAlpines Ltd - Building Division",
    "wof:placetype":"venue"
},
  "geometry": {"coordinates":[172.598602,-43.325329],"type":"Point"}
}