{
  "type": "Feature",
  "properties": {
    "iso:country":"NZ",
    "sg:address":"3/103 Lansford Cre Avondale ",
    "sg:city":"Auckland",
    "sg:classifiers":[
        {
            "category":"Shopping",
            "subcategory":"Gifts & Souvenirs",
            "type":"Retail Goods"
        }
    ],
    "sg:phone":"+64 9-828 5660",
    "sg:province":"Auckland",
    "sg:tags":[
        "postcard",
        "gifts",
        "greeting",
        "card"
    ],
    "wof:name":"Frames/Prints & More",
    "wof:placetype":"venue"
},
  "geometry": {"coordinates":[174.696991,-36.89856],"type":"Point"}
}