{
  "type": "Feature",
  "properties": {
    "addr:full":"Refreshment Pl Upper Hutt  Wellington Wellington",
    "addr:street":"Refreshment Pl",
    "iso:country":"NZ",
    "sg:address":"Refreshment Pl Upper Hutt ",
    "sg:city":"Wellington",
    "sg:orig_category":"Industrial: Packaging: Paper Products",
    "sg:phone":"+64 800 806 006",
    "sg:province":"Wellington",
    "wof:name":"Unibag Packaging Limited",
    "wof:placetype":"venue"
},
  "geometry": {"coordinates":[174.90838600000001,-41.206631],"type":"Point"}
}