{
  "type": "Feature",
  "properties": {
    "addr:full":"Judy Rynn  Napier Hawke's Bay",
    "iso:country":"NZ",
    "sg:address":"Judy Rynn ",
    "sg:city":"Napier",
    "sg:classifiers":[
        {
            "category":"Health Services",
            "subcategory":"Chiropractor",
            "type":"Services"
        }
    ],
    "sg:phone":"+64 6-843 6110",
    "sg:province":"Hawke's Bay",
    "sg:tags":[
        "specialists",
        "occupational",
        "therapist",
        "beauty"
    ],
    "wof:name":"Occupational Therapist",
    "wof:placetype":"venue"
},
  "geometry": {"coordinates":[-80.588562,38.790821],"type":"Point"}
}