{
  "type": "Feature",
  "properties": {
    "addr:full":"12 Lorne St South Dunedin  Dunedin Otago",
    "addr:housenumber":"12",
    "addr:street":"Lorne St",
    "iso:country":"NZ",
    "sg:address":"12 Lorne St South Dunedin ",
    "sg:city":"Dunedin",
    "sg:classifiers":[
        {
            "category":"Manufacturing",
            "subcategory":"Motor Vehicles & Parts",
            "type":"Manufacturing & Wholesale Goods"
        }
    ],
    "sg:phone":"+64 3-455 4686",
    "sg:province":"Otago",
    "sg:tags":[
        "body",
        "repair",
        "builder",
        "servicing",
        "automotive"
    ],
    "wof:name":"McCormick Motor Bodies",
    "wof:placetype":"venue"
},
  "geometry": {"coordinates":[170.50625600000001,-45.878353],"type":"Point"}
}