{
  "type": "Feature",
  "properties": {
    "iso:country":"NZ",
    "sg:address":"Cobham Rd ",
    "sg:city":"Kerikeri",
    "sg:classifiers":[
        {
            "category":"Home & Garden",
            "subcategory":"Kitchen Supply",
            "type":"Retail Goods"
        }
    ],
    "sg:phone":"+64 9-407 8754",
    "sg:province":"Northland",
    "sg:tags":[
        "shop",
        "pet",
        "pets"
    ],
    "wof:name":"Kerikeri Pet Shop",
    "wof:placetype":"venue"
},
  "geometry": {"coordinates":[173.949738,-35.228264],"type":"Point"}
}