{
  "type": "Feature",
  "properties": {
    "addr:full":"38 C Bouverie St Petone Lower  Hutt Wellington",
    "addr:housenumber":"38 c",
    "addr:street":"Bouverie St",
    "iso:country":"NZ",
    "sg:address":"38 C Bouverie St Petone Lower ",
    "sg:city":"Hutt",
    "sg:orig_category":"Automotive: General Services: Vehicle Certification",
    "sg:phone":"+64 4-568 4446",
    "sg:province":"Wellington",
    "wof:name":"Motosafe Services NZ Ltd",
    "wof:placetype":"venue"
},
  "geometry": {"coordinates":[174.88365200000001,-41.219704],"type":"Point"}
}