{
  "type": "Feature",
  "properties": {
    "iso:country":"NZ",
    "sg:address":"7 Cortina Pl Pakuranga ",
    "sg:city":"Auckland",
    "sg:orig_category":"Shopping: Retail Stores: Batteries",
    "sg:phone":"+64 9-576 7777",
    "sg:province":"Auckland",
    "wof:name":"Pakuranga Tyre & Battery Service",
    "wof:placetype":"venue"
},
  "geometry": {"coordinates":[174.872086,-36.914909],"type":"Point"}
}