{
  "type": "Feature",
  "properties": {
    "addr:full":"22 Clearview Dve Palmerston  Palmerston North Manawatu-Wanganui",
    "addr:housenumber":"22",
    "addr:street":"Clearview Dve",
    "iso:country":"NZ",
    "sg:address":"22 Clearview Dve Palmerston ",
    "sg:city":"Palmerston North",
    "sg:classifiers":[
        {
            "category":"Education",
            "subcategory":"Music School",
            "type":"Public Place"
        }
    ],
    "sg:phone":"+64 6-357 2528",
    "sg:province":"Manawatu-Wanganui",
    "sg:tags":[
        "sport",
        "teacher",
        "leisure"
    ],
    "wof:name":"Institute of Registered Music Teachers",
    "wof:placetype":"venue"
},
  "geometry": {"coordinates":[175.611481,-40.357418],"type":"Point"}
}