{
  "type": "Feature",
  "properties": {
    "addr:full":"53 Woolfield Rd Papatoetoe  Auckland Auckland",
    "addr:housenumber":"53",
    "addr:street":"Woolfield Rd",
    "iso:country":"NZ",
    "sg:address":"53 Woolfield Rd Papatoetoe ",
    "sg:city":"Auckland",
    "sg:orig_category":"Industrial: Engineering: Engineers - Electrical",
    "sg:province":"Auckland",
    "wof:name":"Cee Industries",
    "wof:placetype":"venue"
},
  "geometry": {"coordinates":[174.85047900000001,-36.970428],"type":"Point"}
}