{
  "type": "Feature",
  "properties": {
    "addr:full":"30 Stonedon Dve East Tamaki  Auckland Auckland",
    "addr:housenumber":"30",
    "addr:street":"Stonedon Dve",
    "iso:country":"NZ",
    "sg:address":"30 Stonedon Dve East Tamaki ",
    "sg:city":"Auckland",
    "sg:orig_category":"Farming: Supplies: Veterinary Supplies",
    "sg:phone":"+64 9-273 3814",
    "sg:province":"Auckland",
    "wof:name":"Virbac Laboratories (NZ) Ltd",
    "wof:placetype":"venue"
},
  "geometry": {"coordinates":[174.883926,-36.93235],"type":"Point"}
}