{
  "type": "Feature",
  "properties": {
    "iso:country":"NZ",
    "sg:address":"1021 Totara St ",
    "sg:city":"Hastings",
    "sg:classifiers":[
        {
            "category":"Building & Trades",
            "subcategory":"Plumbing",
            "type":"Services"
        }
    ],
    "sg:phone":"+64 6-876 5432",
    "sg:province":"Auckland",
    "sg:tags":[
        "home",
        "plumber",
        "garden",
        "related"
    ],
    "wof:name":"Greg Jaques Plumbing & Drainage Ltd",
    "wof:placetype":"venue"
},
  "geometry": {"coordinates":[-81.508163,29.711214],"type":"Point"}
}