{
  "type": "Feature",
  "properties": {
    "iso:country":"NZ",
    "sg:address":"13 Dundee St ",
    "sg:city":"Invercargill",
    "sg:orig_category":"Home And Garden: Gardening: Services: Tree Services",
    "sg:phone":"+64 252434077",
    "sg:province":"Southland",
    "wof:name":"Straight Edge",
    "wof:placetype":"venue"
},
  "geometry": {"coordinates":[168.37666300000001,-46.430126],"type":"Point"}
}