{
  "type": "Feature",
  "properties": {
    "iso:country":"NZ",
    "sg:address":"Ridgeway St",
    "sg:city":"Wanganui",
    "sg:classifiers":[
        {
            "category":"Banks & Credit Unions",
            "subcategory":"Bank",
            "type":"Services"
        }
    ],
    "sg:phone":"+64 6-475 8349",
    "sg:province":"Manawatu-Wanganui",
    "wof:name":"Post Office Savings Bank",
    "wof:placetype":"venue"
},
  "geometry": {"coordinates":[175.053406,-39.934429],"type":"Point"}
}