{
  "type": "Feature",
  "properties": {
    "addr:full":"7 Union St  Hawera Taranaki",
    "addr:housenumber":"7",
    "addr:street":"Union St",
    "iso:country":"NZ",
    "sg:address":"7 Union St ",
    "sg:city":"Hawera",
    "sg:classifiers":[
        {
            "category":"Personal",
            "subcategory":"Adult",
            "type":"Services"
        }
    ],
    "sg:phone":"+64 6-278 7040",
    "sg:province":"Taranaki",
    "sg:tags":[
        "sport",
        "parlour",
        "massage",
        "leisure"
    ],
    "sg:website":"http://www.yellowpages.co.nz/for/thegspot/dp46003.html",
    "wof:name":"The G Spot",
    "wof:placetype":"venue"
},
  "geometry": {"coordinates":[174.281845,-39.588448],"type":"Point"}
}