{
  "type": "Feature",
  "properties": {
    "addr:full":"Summer St Ponsonby  Auckland Auckland",
    "addr:street":"Summer St",
    "iso:country":"NZ",
    "sg:address":"Summer St Ponsonby ",
    "sg:city":"Auckland",
    "sg:classifiers":[
        {
            "category":"Insurance",
            "subcategory":"Health Insurance",
            "type":"Services"
        }
    ],
    "sg:phone":"+64 9-360 7119",
    "sg:province":"Auckland",
    "sg:tags":[
        "mental",
        "beauty"
    ],
    "wof:name":"Harding Su",
    "wof:placetype":"venue"
},
  "geometry": {"coordinates":[174.74134799999999,-36.852154],"type":"Point"}
}