{
  "type": "Feature",
  "properties": {
    "iso:country":"NZ",
    "sg:address":"127 Wrights Rd Riccarton ",
    "sg:city":"Christchurch",
    "sg:orig_category":"Farming: Supplies: Farm Buildings",
    "sg:phone":"+64 3-338 0013",
    "sg:province":"Canterbury",
    "wof:name":"Calder Stewart Industries Ltd",
    "wof:placetype":"venue"
},
  "geometry": {"coordinates":[172.597351,-43.532143],"type":"Point"}
}