{
  "type": "Feature",
  "properties": {
    "addr:full":"PO Box 13-105 Onehunga  Auckland Auckland",
    "addr:housenumber":"po box",
    "addr:postcode":"13-105",
    "iso:country":"NZ",
    "sg:address":"PO Box 13-105 Onehunga ",
    "sg:city":"Auckland",
    "sg:classifiers":[
        {
            "category":"Manufacturing",
            "subcategory":"Tools & Machinery",
            "type":"Manufacturing & Wholesale Goods"
        }
    ],
    "sg:phone":"+64 9-622 2166",
    "sg:province":"Auckland",
    "sg:tags":[
        "equipment",
        "industrial",
        "label"
    ],
    "wof:name":"Avery Dennison New Zealand",
    "wof:placetype":"venue"
},
  "geometry": {"coordinates":[174.783661,-36.909973],"type":"Point"}
}