{
  "type": "Feature",
  "properties": {
    "iso:country":"NZ",
    "sg:address":"R D 6 Waimea Gore ",
    "sg:city":"Riversdale",
    "sg:classifiers":[
        {
            "category":"Home & Garden",
            "subcategory":"Home Furnishings",
            "type":"Retail Goods"
        }
    ],
    "sg:phone":"+64 3-202 5449",
    "sg:tags":[
        "furniture/furnishings",
        "upholstery",
        "supply"
    ],
    "wof:name":"Clearwater Sue-Upholstery",
    "wof:placetype":"venue"
},
  "geometry": {"coordinates":[168.93743900000001,-46.100632],"type":"Point"}
}