{
  "type": "Feature",
  "properties": {
    "iso:country":"NZ",
    "sg:address":"18 Olive Rd Penrose ",
    "sg:city":"Auckland",
    "sg:classifiers":[
        {
            "category":"Home & Garden",
            "subcategory":"Hardware",
            "type":"Retail Goods"
        }
    ],
    "sg:phone":"+64 9-571 3153",
    "sg:province":"Auckland",
    "sg:tags":[
        "window",
        "fitting"
    ],
    "wof:name":"Ven Lu Ree Blind Services Ltd",
    "wof:placetype":"venue"
},
  "geometry": {"coordinates":[174.81199599999999,-36.911453],"type":"Point"}
}