{
  "type": "Feature",
  "properties": {
    "iso:country":"NZ",
    "sg:address":"2/25A Drake St Howick ",
    "sg:city":"Auckland",
    "sg:classifiers":[
        {
            "category":"Personal",
            "subcategory":"Day Spa",
            "type":"Services"
        }
    ],
    "sg:phone":"+64 9-535 2304",
    "sg:province":"Auckland",
    "sg:tags":[
        "specialist",
        "satellite",
        "industrial",
        "machinery",
        "equipment"
    ],
    "wof:name":"Babylon Communications",
    "wof:placetype":"venue"
},
  "geometry": {"coordinates":[174.93284600000001,-36.900379],"type":"Point"}
}