{
  "type": "Feature",
  "properties": {
    "iso:country":"NZ",
    "sg:address":"West Coast & ",
    "sg:city":"Buller",
    "sg:classifiers":[
        {
            "category":"Health Services",
            "subcategory":"Health Practitioner",
            "type":"Services"
        }
    ],
    "sg:phone":"+64 800 243 834",
    "sg:tags":[
        "equipment",
        "beauty",
        "fitness"
    ],
    "sg:website":"http://www.elitefitness.co.nz",
    "wof:name":"Elite Fitness Equipment Ltd",
    "wof:placetype":"venue"
},
  "geometry": {"coordinates":[-123.295303,40.191238],"type":"Point"}
}