{
  "type": "Feature",
  "properties": {
    "iso:country":"NZ",
    "sg:address":"246 Gloucester St Taradale ",
    "sg:city":"Napier",
    "sg:classifiers":[
        {
            "category":"Food & Beverages",
            "subcategory":"Bakery",
            "type":"Retail Goods"
        }
    ],
    "sg:phone":"+64 6-844 6090",
    "sg:province":"Hawke's Bay",
    "sg:tags":[
        "shop",
        "cake",
        "drink",
        "-"
    ],
    "wof:name":"A Taste of Europe Patisserie",
    "wof:placetype":"venue"
},
  "geometry": {"coordinates":[176.848846,-39.535088],"type":"Point"}
}