{
  "type": "Feature",
  "properties": {
    "addr:full":"35 The Centre  Waipu Northland",
    "addr:housenumber":"35;waipu",
    "addr:street":"The Centre",
    "iso:country":"NZ",
    "sg:address":"35 The Centre ",
    "sg:city":"Waipu",
    "sg:orig_category":"Home And Garden: Accessories: Hardware",
    "sg:phone":"+64 9-432 0294",
    "sg:province":"Northland",
    "wof:name":"Hammer Hardware",
    "wof:placetype":"venue"
},
  "geometry": {"coordinates":[174.44134500000001,-35.983387],"type":"Point"}
}