{
  "type": "Feature",
  "properties": {
    "addr:full":"SHP 15 Northlands Shopping Centre 55 Main North Rd, Papanui  Christchurch Canterbury",
    "addr:housenumber":"15;55",
    "addr:street":"Shp;Shopping;Main North Rd",
    "iso:country":"NZ",
    "sg:address":"SHP 15 Northlands Shopping Centre 55 Main North Rd, Papanui ",
    "sg:city":"Christchurch",
    "sg:classifiers":[
        {
            "category":"Shopping",
            "subcategory":"Crafts & Fabrics",
            "type":"Retail Goods"
        }
    ],
    "sg:phone":"+64 3-352 5896",
    "sg:province":"Canterbury",
    "sg:tags":[
        "foot",
        "clothing",
        "retailer",
        "footwear",
        "wear"
    ],
    "wof:name":"Barefoot Originals Ltd",
    "wof:placetype":"venue"
},
  "geometry": {"coordinates":[172.59986900000001,-43.496452],"type":"Point"}
}