{
  "type": "Feature",
  "properties": {
    "iso:country":"NZ",
    "sg:address":"8 Moreton Dve Manly Hibiscus ",
    "sg:city":"Hibiscus Coast",
    "sg:orig_category":"Shopping: Accessories: Jewellers And Watchmakers",
    "sg:phone":"+64 9-424 7440",
    "sg:province":"Auckland",
    "wof:name":"Continental Jewellers & Distributers",
    "wof:placetype":"venue"
},
  "geometry": {"coordinates":[-93.20133199999999,43.284019],"type":"Point"}
}