{
  "type": "Feature",
  "properties": {
    "iso:country":"NZ",
    "sg:address":"Porirua ",
    "sg:city":"Wellington",
    "sg:classifiers":[
        {
            "category":"Health Services",
            "subcategory":"Doctor",
            "type":"Services"
        }
    ],
    "sg:phone":"+64 4-239 9421",
    "sg:province":"Wellington",
    "sg:tags":[
        "services",
        "reflexology",
        "beauty"
    ],
    "wof:name":"Feet First School of Reflexology",
    "wof:placetype":"venue"
},
  "geometry": {"coordinates":[174.840714,-41.138359],"type":"Point"}
}