{
  "type": "Feature",
  "properties": {
    "addr:full":"47 Hereford St  Christchurch Canterbury",
    "addr:housenumber":"47",
    "addr:street":"Hereford St",
    "iso:country":"NZ",
    "sg:address":"47 Hereford St ",
    "sg:city":"Christchurch",
    "sg:orig_category":"Industrial: Engineering: Engineers",
    "sg:phone":"+64 3-379 7260",
    "sg:province":"Canterbury",
    "wof:name":"Falloon & Wilson",
    "wof:placetype":"venue"
},
  "geometry": {"coordinates":[-76.537834,37.605659],"type":"Point"}
}