{
  "type": "Feature",
  "properties": {
    "iso:country":"NZ",
    "sg:address":"Serlby Pl ",
    "sg:city":"Porirua",
    "sg:classifiers":[
        {
            "category":"Home & Garden",
            "subcategory":"Kitchen Supply",
            "type":"Retail Goods"
        }
    ],
    "sg:phone":"+64 4-237 4710",
    "sg:province":"Wellington",
    "sg:tags":[
        "shop",
        "pet",
        "pets"
    ],
    "wof:name":"Aquarium & Pet Supplies",
    "wof:placetype":"venue"
},
  "geometry": {"coordinates":[174.85223400000001,-41.138294],"type":"Point"}
}