{
  "type": "Feature",
  "properties": {
    "addr:full":"122 Liverpool St  Wanganui Manawatu-Wanganui",
    "addr:housenumber":"122",
    "addr:street":"Liverpool St",
    "iso:country":"NZ",
    "sg:address":"122 Liverpool St ",
    "sg:city":"Wanganui",
    "sg:orig_category":"Food And Drink: Catering: Caterers",
    "sg:phone":"+64 6-345 8309",
    "sg:province":"Manawatu-Wanganui",
    "wof:name":"Collegiate Hotel & Motor Inn",
    "wof:placetype":"venue"
},
  "geometry": {"coordinates":[175.04028299999999,-39.927677],"type":"Point"}
}