{
  "type": "Feature",
  "properties": {
    "iso:country":"NZ",
    "sg:address":"66 Shelley Beach Road Herne Bay ",
    "sg:city":"Auckland",
    "sg:classifiers":[
        {
            "category":"Communications",
            "subcategory":"Television Station",
            "type":"Services"
        }
    ],
    "sg:phone":"+64 9-361 1206",
    "sg:province":"Auckland",
    "sg:tags":[
        "broadcasting"
    ],
    "wof:name":"Fat Limited",
    "wof:placetype":"venue"
},
  "geometry": {"coordinates":[174.742767,-36.841343],"type":"Point"}
}