{
  "type": "Feature",
  "properties": {
    "iso:country":"NZ",
    "sg:address":"3 Portsmouth Rd Miramar ",
    "sg:city":"Wellington",
    "sg:orig_category":"Industrial: Engineering: Engineers - Manufacturing",
    "sg:phone":"+64 4-388 1755",
    "sg:province":"Wellington",
    "wof:name":"Perry Engineering Limited",
    "wof:placetype":"venue"
},
  "geometry": {"coordinates":[174.813431,-41.315678],"type":"Point"}
}