{
  "type": "Feature",
  "properties": {
    "iso:country":"NZ",
    "sg:address":"99 Carbine Rd Mt ",
    "sg:city":"Wellington",
    "sg:classifiers":[
        {
            "category":"Manufacturing",
            "subcategory":"Tools & Machinery",
            "type":"Manufacturing & Wholesale Goods"
        }
    ],
    "sg:phone":"+64 800 909 192",
    "sg:province":"Wellington",
    "sg:tags":[
        "specialist",
        "industrial",
        "bar",
        "coding",
        "equipment"
    ],
    "wof:name":"William Brandt Technology",
    "wof:placetype":"venue"
},
  "geometry": {"coordinates":[174.848602,-36.920387],"type":"Point"}
}