{
  "type": "Feature",
  "properties": {
    "addr:full":"8 Union St  Hawera Taranaki",
    "addr:housenumber":"8",
    "addr:street":"Union St",
    "iso:country":"NZ",
    "sg:address":"8 Union St ",
    "sg:city":"Hawera",
    "sg:classifiers":[
        {
            "category":"Bars & Pubs",
            "subcategory":"Wine Bar",
            "type":"Food & Drink"
        }
    ],
    "sg:phone":"+64 6-278 5122",
    "sg:province":"Taranaki",
    "sg:tags":[
        "wining",
        "dining",
        "cafe"
    ],
    "wof:name":"Chatter-Nook",
    "wof:placetype":"venue"
},
  "geometry": {"coordinates":[174.28213500000001,-39.588634],"type":"Point"}
}