{
  "type": "Feature",
  "properties": {
    "addr:full":"cnr Old Wharf Rd & Huffam St  Motueka Tasman",
    "addr:street":"Cnr Old Wharf Rd & Huffam St",
    "iso:country":"NZ",
    "sg:address":"cnr Old Wharf Rd & Huffam St ",
    "sg:city":"Motueka",
    "sg:orig_category":"Industrial: Services: Drillers",
    "sg:phone":"+64 3-528 8432",
    "sg:province":"Tasman",
    "wof:name":"CW Drilling & Investigation Ltd",
    "wof:placetype":"venue"
},
  "geometry": {"coordinates":[173.013443,-41.108101],"type":"Point"}
}