{
  "type": "Feature",
  "properties": {
    "iso:country":"NZ",
    "sg:address":"10 Weston Ave Mt Albert ",
    "sg:city":"Auckland",
    "sg:orig_category":"Home And Garden: Gardening: Services: Landscape Design",
    "sg:phone":"+64 9-846 1083",
    "sg:province":"Auckland",
    "wof:name":"Norma de Langen Garden Design",
    "wof:placetype":"venue"
},
  "geometry": {"coordinates":[174.71423300000001,-36.891544],"type":"Point"}
}