{
  "type": "Feature",
  "properties": {
    "iso:country":"NZ",
    "sg:address":"1378 Cameron Rd ",
    "sg:city":"Tauranga",
    "sg:classifiers":[
        {
            "category":"Recreation",
            "type":"Entertainment"
        }
    ],
    "sg:phone":"+64 7-541 0369",
    "sg:province":"Bay of Plenty",
    "sg:tags":[
        "sport",
        "tramping",
        "leisure",
        "camping"
    ],
    "wof:name":"Great Outdoors Centre",
    "wof:placetype":"venue"
},
  "geometry": {"coordinates":[176.131439,-37.727734],"type":"Point"}
}