{
  "type": "Feature",
  "properties": {
    "addr:full":"513 a Sandringham Rd Sandringham  Auckland Auckland",
    "addr:housenumber":"513 a",
    "addr:street":"Sandringham Rd",
    "iso:country":"NZ",
    "sg:address":"513 a Sandringham Rd Sandringham ",
    "sg:city":"Auckland",
    "sg:orig_category":"Shopping: Retail Stores: Supermarkets",
    "sg:phone":"+64 9-846 7316",
    "sg:province":"Auckland",
    "wof:name":"One Stop Grocer",
    "wof:placetype":"venue"
},
  "geometry": {"coordinates":[174.73634300000001,-36.891182],"type":"Point"}
}