{
  "type": "Feature",
  "properties": {
    "addr:full":"PO Box 781 Tauranga  Tauranga Bay of Plenty",
    "addr:housenumber":"po",
    "addr:postcode":"781",
    "addr:street":"Box",
    "iso:country":"NZ",
    "sg:address":"PO Box 781 Tauranga ",
    "sg:city":"Tauranga",
    "sg:classifiers":[
        {
            "category":"Sports & Exercise",
            "subcategory":"Swimming Pool",
            "type":"Entertainment"
        }
    ],
    "sg:phone":"+64 800 765 243",
    "sg:province":"Bay of Plenty",
    "sg:tags":[
        "home",
        "outdoor",
        "garden",
        "spa"
    ],
    "wof:name":"Solaheat New Zealand",
    "wof:placetype":"venue"
},
  "geometry": {"coordinates":[176.166473,-37.686142],"type":"Point"}
}