{
  "type": "Feature",
  "properties": {
    "iso:country":"NZ",
    "sg:address":"Leedstown Rd R D 1 ",
    "sg:city":"Marton",
    "sg:classifiers":[
        {
            "category":"Travel",
            "subcategory":"Hotels & Motels",
            "type":"Entertainment"
        }
    ],
    "sg:phone":"+64 6-327 7820",
    "sg:tags":[
        "tourism",
        "accommodation"
    ],
    "sg:website":"http://www.yellowpages.co.nz/for/mcestate/dp33403.html",
    "wof:name":"Maungaraupi",
    "wof:placetype":"venue"
},
  "geometry": {"coordinates":[-3.01544,53.799294],"type":"Point"}
}