{
  "type": "Feature",
  "properties": {
    "addr:full":"14 Abbot Ave  Waipawa",
    "addr:housenumber":"14",
    "addr:street":"Abbot Ave",
    "iso:country":"NZ",
    "sg:address":"14 Abbot Ave ",
    "sg:city":"Waipawa",
    "sg:classifiers":[
        {
            "category":"Social Services",
            "subcategory":"Job Training",
            "type":"Services"
        }
    ],
    "sg:phone":"+64 6-857 8934",
    "sg:tags":[
        "education"
    ],
    "wof:name":"Fire & Rescue NZ",
    "wof:placetype":"venue"
},
  "geometry": {"coordinates":[176.587997,-39.938644],"type":"Point"}
}