{
  "type": "Feature",
  "properties": {
    "addr:full":"100 Manchester St  Feilding Manawatu-Wanganui",
    "addr:housenumber":"100",
    "addr:street":"Manchester St",
    "iso:country":"NZ",
    "sg:address":"100 Manchester St ",
    "sg:city":"Feilding",
    "sg:orig_category":"Sports And Leisure: Entertainment: Entertainers",
    "sg:phone":"+64 6-323 3814",
    "sg:province":"Manawatu-Wanganui",
    "wof:name":"Tectonic Shift",
    "wof:placetype":"venue"
},
  "geometry": {"coordinates":[175.56341599999999,-40.225163],"type":"Point"}
}