{
  "type": "Feature",
  "properties": {
    "addr:full":"194 Rolleston St  Hokitika West Coast",
    "addr:housenumber":"194",
    "addr:street":"Rolleston St",
    "iso:country":"NZ",
    "sg:address":"194 Rolleston St ",
    "sg:city":"Hokitika",
    "sg:classifiers":[
        {
            "category":"Building & Trades",
            "subcategory":"Plumbing",
            "type":"Services"
        }
    ],
    "sg:phone":"+64 3-755 6312",
    "sg:province":"West Coast",
    "sg:tags":[
        "home",
        "plumber",
        "garden",
        "related"
    ],
    "wof:name":"Keenan Mark",
    "wof:placetype":"venue"
},
  "geometry": {"coordinates":[170.975098,-42.71801],"type":"Point"}
}