{
  "type": "Feature",
  "properties": {
    "iso:country":"NZ",
    "sg:address":"Trafalgar Sq ",
    "sg:city":"Wanganui",
    "sg:classifiers":[
        {
            "category":"Home & Garden",
            "subcategory":"Furniture",
            "type":"Retail Goods"
        }
    ],
    "sg:phone":"+64 6-347 7876",
    "sg:province":"Manawatu-Wanganui",
    "sg:tags":[
        "furniture/furnishings",
        "furnishing"
    ],
    "wof:name":"Country Heirlooms",
    "wof:placetype":"venue"
},
  "geometry": {"coordinates":[175.052841,-39.933369],"type":"Point"}
}