{
  "type": "Feature",
  "properties": {
    "iso:country":"NZ",
    "sg:address":"92 Kent St ",
    "sg:city":"Hamilton",
    "sg:classifiers":[
        {
            "category":"Retail",
            "subcategory":"Laundry & Dry Cleaning",
            "type":"Services"
        }
    ],
    "sg:phone":"+64 7-847 7181",
    "sg:province":"Waikato",
    "sg:tags":[
        "repair",
        "clothing",
        "fabric",
        "cleaner"
    ],
    "wof:name":"Waikato Dry Cleaners",
    "wof:placetype":"venue"
},
  "geometry": {"coordinates":[175.263092,-37.786751],"type":"Point"}
}