{
  "type": "Feature",
  "properties": {
    "addr:full":"St Lukes Rd Mt Albert  Auckland Auckland",
    "addr:street":"St Lukes Rd",
    "iso:country":"NZ",
    "sg:address":"St Lukes Rd Mt Albert ",
    "sg:city":"Auckland",
    "sg:orig_category":"Shopping: Accessories: Jewellers And Watchmakers",
    "sg:phone":"+64 9-846 4366",
    "sg:province":"Auckland",
    "wof:name":"Kleins Jewellery",
    "wof:placetype":"venue"
},
  "geometry": {"coordinates":[174.730423,-36.88097],"type":"Point"}
}