{
  "type": "Feature",
  "properties": {
    "iso:country":"NZ",
    "sg:address":"23 Coronation Rd Mangere Bridge ",
    "sg:city":"Auckland",
    "sg:classifiers":[
        {
            "category":"Fast Food",
            "type":"Food & Drink"
        }
    ],
    "sg:phone":"+64 9-636 9171",
    "sg:province":"Auckland",
    "sg:tags":[
        "wining",
        "dining",
        "takeaway"
    ],
    "wof:name":"Neptune Seafoods",
    "wof:placetype":"venue"
},
  "geometry": {"coordinates":[174.78724700000001,-36.941685],"type":"Point"}
}