{
  "type": "Feature",
  "properties": {
    "addr:full":"Darfield, Ashburton, Kaikoura, Cheviot, Culverden, , Waiau, Hanmer Springs Chatham Islands  Christchurch Canterbury",
    "addr:street":"Darfield",
    "iso:country":"NZ",
    "sg:address":"Darfield, Ashburton, Kaikoura, Cheviot, Culverden, , Waiau, Hanmer Springs Chatham Islands ",
    "sg:city":"Christchurch",
    "sg:classifiers":[
        {
            "category":"Education",
            "subcategory":"Special Training",
            "type":"Public Place"
        }
    ],
    "sg:phone":"+64 800 627 739",
    "sg:province":"Canterbury",
    "sg:website":"http://www.yellowpages.co.nz/for/masseyuniversity/dp55906.html",
    "wof:name":"Massey University",
    "wof:placetype":"venue"
},
  "geometry": {"coordinates":[172.850357,-42.774429],"type":"Point"}
}