{
  "type": "Feature",
  "properties": {
    "iso:country":"NZ",
    "sg:address":"35 Crawford St ",
    "sg:city":"Dunedin",
    "sg:classifiers":[
        {
            "category":"Health Services",
            "subcategory":"Podiatrist",
            "type":"Services"
        }
    ],
    "sg:phone":"+64 508 373 737",
    "sg:province":"Otago",
    "sg:tags":[
        "wig",
        "hairpiece",
        "beauty"
    ],
    "sg:website":"http://www.freedomwigs.co.nz",
    "wof:name":"Barrington Studios",
    "wof:placetype":"venue"
},
  "geometry": {"coordinates":[-82.784721,28.013355],"type":"Point"}
}