{
  "type": "Feature",
  "properties": {
    "addr:full":"97 Derby St  Gisborne Gisborne",
    "addr:housenumber":"97",
    "addr:street":"Derby St",
    "iso:country":"NZ",
    "sg:address":"97 Derby St ",
    "sg:city":"Gisborne",
    "sg:orig_category":"Health And Beauty: Beauty: Hairdressers",
    "sg:phone":"+64 6-868 8935",
    "sg:province":"Gisborne",
    "wof:name":"The Little Hair Shop",
    "wof:placetype":"venue"
},
  "geometry": {"coordinates":[178.02247600000001,-38.664124],"type":"Point"}
}