{
  "type": "Feature",
  "properties": {
    "iso:country":"NZ",
    "sg:address":"28 Marino St Rangataua ",
    "sg:city":"Ohakune",
    "sg:classifiers":[
        {
            "category":"Retail",
            "subcategory":"Auto Repair",
            "type":"Services"
        }
    ],
    "sg:phone":"+64 6-385 8215",
    "sg:tags":[
        "automotive",
        "panel",
        "servicing",
        "beater"
    ],
    "wof:name":"Fred's Panel Shop",
    "wof:placetype":"venue"
},
  "geometry": {"coordinates":[175.403839,-39.412289],"type":"Point"}
}