{
  "type": "Feature",
  "properties": {
    "iso:country":"NZ",
    "sg:address":"176 Spey St ",
    "sg:city":"Invercargill",
    "sg:orig_category":"Farming: Forestry: Forestry Consultants",
    "sg:phone":"+64 3-214 1793",
    "sg:province":"Southland",
    "wof:name":"Rayonier New Zealand Ltd",
    "wof:placetype":"venue"
},
  "geometry": {"coordinates":[168.35446200000001,-46.409485],"type":"Point"}
}