{
  "type": "Feature",
  "properties": {
    "iso:country":"NZ",
    "sg:address":"351 A King Edward St South Dunedin ",
    "sg:city":"Dunedin",
    "sg:orig_category":"Health And Beauty: Products: Pharmacies",
    "sg:phone":"+64 3-455 1680",
    "sg:province":"Otago",
    "wof:name":"McNaughton's Pharmacy",
    "wof:placetype":"venue"
},
  "geometry": {"coordinates":[170.501831,-45.897594],"type":"Point"}
}