{
  "type": "Feature",
  "properties": {
    "iso:country":"NZ",
    "sg:address":"11 Veronica St New Lynn ",
    "sg:city":"Auckland",
    "sg:orig_category":"Automotive: Accessories: Motor Accessories",
    "sg:phone":"+64 9-827 8686",
    "sg:province":"Auckland",
    "wof:name":"Mag & Turbo Warehouse West Auckland",
    "wof:placetype":"venue"
},
  "geometry": {"coordinates":[174.688141,-36.907532],"type":"Point"}
}