{
  "type": "Feature",
  "properties": {
    "addr:full":"58 Stonedon Dve East Tamaki  Auckland Auckland",
    "addr:housenumber":"58",
    "addr:street":"Stonedon Dve",
    "iso:country":"NZ",
    "sg:address":"58 Stonedon Dve East Tamaki ",
    "sg:city":"Auckland",
    "sg:orig_category":"Clothing And Fabric: Clothing: Children'S Wear",
    "sg:phone":"+64 9-273 9421",
    "sg:province":"Auckland",
    "wof:name":"Telstar Manufacturing Ltd",
    "wof:placetype":"venue"
},
  "geometry": {"coordinates":[174.88471999999999,-36.929764],"type":"Point"}
}