{
  "type": "Feature",
  "properties": {
    "iso:country":"NZ",
    "sg:address":"34 Harris St ",
    "sg:city":"Waitara",
    "sg:orig_category":"Farming: Forestry",
    "sg:phone":"+64 6-754 7607",
    "wof:name":"Fred's Forestry Services",
    "wof:placetype":"venue"
},
  "geometry": {"coordinates":[174.23996,-38.99152],"type":"Point"}
}