{
  "type": "Feature",
  "properties": {
    "addr:full":"176 Papanui Rd  Christchurch Canterbury",
    "addr:housenumber":"176",
    "addr:street":"Papanui Rd",
    "iso:country":"NZ",
    "sg:address":"176 Papanui Rd ",
    "sg:city":"Christchurch",
    "sg:classifiers":[
        {
            "category":"Shopping",
            "subcategory":"Musical Instruments",
            "type":"Retail Goods"
        }
    ],
    "sg:phone":"+64 3-355 0297",
    "sg:province":"Canterbury",
    "sg:tags":[
        "sport",
        "music",
        "leisure"
    ],
    "wof:name":"Grahams Music",
    "wof:placetype":"venue"
},
  "geometry": {"coordinates":[172.62249800000001,-43.513004],"type":"Point"}
}