{
  "type": "Feature",
  "properties": {
    "addr:full":"25 Neil Park Dve East Tamaki  Auckland Auckland",
    "addr:housenumber":"25",
    "addr:street":"Neil Park Dve",
    "iso:country":"NZ",
    "sg:address":"25 Neil Park Dve East Tamaki ",
    "sg:city":"Auckland",
    "sg:orig_category":"Transport: Transportation: Transport Operators",
    "sg:phone":"+64 9-273 2334",
    "sg:province":"Auckland",
    "wof:name":"Alderson Bulk Haulage Limited",
    "wof:placetype":"venue"
},
  "geometry": {"coordinates":[174.88743600000001,-36.956711],"type":"Point"}
}