{
  "type": "Feature",
  "properties": {
    "addr:full":"Shop 28 Hunters Plaza 217 Gt South Rd Papatoetoe  Auckland Auckland",
    "addr:housenumber":"28;217",
    "addr:street":"Hunters;Gt South Rd",
    "iso:country":"NZ",
    "sg:address":"Shop 28 Hunters Plaza 217 Gt South Rd Papatoetoe ",
    "sg:city":"Auckland",
    "sg:orig_category":"Transport: Distribution - General: Distributors",
    "sg:phone":"+64 9-279 9388",
    "sg:province":"Auckland",
    "wof:name":"First Mart Limited",
    "wof:placetype":"venue"
},
  "geometry": {"coordinates":[174.86715699999999,-36.971188],"type":"Point"}
}