{
  "type": "Feature",
  "properties": {
    "addr:full":"Dixon Rd R D 2  Hamilton Waikato",
    "addr:housenumber":"2",
    "addr:street":"Dixon Rd R D",
    "iso:country":"NZ",
    "sg:address":"Dixon Rd R D 2 ",
    "sg:city":"Hamilton",
    "sg:orig_category":"Clothing And Fabric: Clothing: Kilts",
    "sg:phone":"+64 7-843 4121",
    "sg:province":"Waikato",
    "sg:website":"http://www.kilts.co.nz",
    "wof:name":"Mitchell Kilt Hire",
    "wof:placetype":"venue"
},
  "geometry": {"coordinates":[-87.970589,34.039825],"type":"Point"}
}