{
  "type": "Feature",
  "properties": {
    "iso:country":"NZ",
    "sg:address":"Te Awamutu Te ",
    "sg:city":"Awamutu",
    "sg:orig_category":"Shopping: Retail Stores: Books: Libraries",
    "sg:phone":"+64 7-871 4887",
    "sg:province":"Waikato",
    "wof:name":"Te Awamutu Community Toy Library",
    "wof:placetype":"venue"
},
  "geometry": {"coordinates":[175.334442,-38.010918],"type":"Point"}
}