{
  "type": "Feature",
  "properties": {
    "addr:full":"133 Clyde St  Invercargill Southland",
    "addr:housenumber":"133",
    "addr:street":"Clyde St",
    "iso:country":"NZ",
    "sg:address":"133 Clyde St ",
    "sg:city":"Invercargill",
    "sg:classifiers":[
        {
            "category":"Autos & Motor Vehicles",
            "subcategory":"Automobile Sales",
            "type":"Retail Goods"
        }
    ],
    "sg:phone":"+64 3-214 2474",
    "sg:province":"Southland",
    "sg:tags":[
        "car",
        "-used",
        "leasing",
        "truck",
        "automotive"
    ],
    "wof:name":"Stan's Auto's",
    "wof:placetype":"venue"
},
  "geometry": {"coordinates":[168.34754899999999,-46.421104],"type":"Point"}
}