{
  "type": "Feature",
  "properties": {
    "iso:country":"NZ",
    "sg:address":"811 Gladstone Rd ",
    "sg:city":"Gisborne",
    "sg:classifiers":[
        {
            "category":"Travel",
            "subcategory":"Hotels & Motels",
            "type":"Entertainment"
        }
    ],
    "sg:phone":"+64 6-863 1515",
    "sg:province":"Gisborne",
    "sg:tags":[
        "tourism",
        "accommodation"
    ],
    "sg:website":"http://www.yellowpages.co.nz/pages/215244474/dp20300.html",
    "wof:name":"Champers Motor Lodge",
    "wof:placetype":"venue"
},
  "geometry": {"coordinates":[177.989883,-38.649986],"type":"Point"}
}