{
  "type": "Feature",
  "properties": {
    "iso:country":"NZ",
    "sg:address":"107 Queen St ",
    "sg:city":"Waimate",
    "sg:classifiers":[
        {
            "category":"Shopping",
            "subcategory":"Bicycles & Sporting Goods",
            "type":"Retail Goods"
        }
    ],
    "sg:phone":"+64 3-689 7950",
    "sg:tags":[
        "cycle",
        "sport",
        "sale",
        "retailers",
        "cycles"
    ],
    "wof:name":"Waimate Outdoors Ltd",
    "wof:placetype":"venue"
},
  "geometry": {"coordinates":[171.04478499999999,-44.735359],"type":"Point"}
}