{
  "type": "Feature",
  "properties": {
    "iso:country":"NZ",
    "sg:address":"cnr Ulster & Liverpool Sts ",
    "sg:city":"Hamilton",
    "sg:classifiers":[
        {
            "category":"Recreation",
            "type":"Entertainment"
        }
    ],
    "sg:phone":"+64 7-838 0575",
    "sg:province":"Waikato",
    "sg:tags":[
        "sport",
        "tramping",
        "leisure",
        "camping"
    ],
    "wof:name":"Pack n' Pedal",
    "wof:placetype":"venue"
},
  "geometry": {"coordinates":[-2.968696,53.422607],"type":"Point"}
}