{
  "type": "Feature",
  "properties": {
    "addr:full":"95 Clevely Lin R D 8  Bunnythorpe",
    "addr:housenumber":"95;8",
    "addr:street":"Clevely Lin R D",
    "iso:country":"NZ",
    "sg:address":"95 Clevely Lin R D 8 ",
    "sg:city":"Bunnythorpe",
    "sg:classifiers":[
        {
            "category":"Shopping",
            "subcategory":"Pets & Pet Supplies",
            "type":"Retail Goods"
        }
    ],
    "sg:phone":"+64 6-329 2637",
    "sg:tags":[
        "home",
        "grooming",
        "garden",
        "pets"
    ],
    "wof:name":"Tailwaggers Mobile Dog Wash",
    "wof:placetype":"venue"
},
  "geometry": {"coordinates":[175.629761,-40.282139],"type":"Point"}
}