{
  "type": "Feature",
  "properties": {
    "addr:full":"82 Clayton Rd  Rotorua Bay of Plenty",
    "addr:housenumber":"82",
    "addr:street":"Clayton Rd",
    "iso:country":"NZ",
    "sg:address":"82 Clayton Rd ",
    "sg:city":"Rotorua",
    "sg:classifiers":[
        {
            "category":"Home & Garden",
            "subcategory":"Kitchen Supply",
            "type":"Retail Goods"
        }
    ],
    "sg:phone":"+64 7-348 0328",
    "sg:province":"Bay of Plenty",
    "sg:tags":[
        "shop",
        "pet",
        "pets"
    ],
    "wof:name":"Wonderworld Aquarium & Pet Centre",
    "wof:placetype":"venue"
},
  "geometry": {"coordinates":[176.22631799999999,-38.126362],"type":"Point"}
}