{
  "type": "Feature",
  "properties": {
    "addr:full":"Coughlan Rd  Waipukurau",
    "addr:street":"Coughlan Rd",
    "iso:country":"NZ",
    "sg:address":"Coughlan Rd ",
    "sg:city":"Waipukurau",
    "sg:orig_category":"Automotive: Parts And Supplies: Windscreens",
    "sg:phone":"+64 6-858 7275",
    "wof:name":"Barry Dean Glass",
    "wof:placetype":"venue"
},
  "geometry": {"coordinates":[176.546539,-39.99239],"type":"Point"}
}