{
  "type": "Feature",
  "properties": {
    "iso:country":"NZ",
    "sg:address":"cnr Wairau Rd & 1 View Rd Glenfield North Shore",
    "sg:city":"Auckland",
    "sg:classifiers":[
        {
            "category":"Shopping",
            "subcategory":"Pharmacy",
            "type":"Retail Goods"
        }
    ],
    "sg:phone":"+64 800 432 584",
    "sg:province":"Auckland",
    "sg:tags":[
        "product",
        "health"
    ],
    "sg:website":"http://www.Healthy.co.nz",
    "wof:name":"Ideal Health",
    "wof:placetype":"venue"
},
  "geometry": {"coordinates":[174.732666,-36.77565],"type":"Point"}
}