{
  "type": "Feature",
  "properties": {
    "addr:full":"50 Mooray Ave Bishopdale  Christchurch Canterbury",
    "addr:housenumber":"50",
    "addr:street":"Mooray Ave Bishopdale Christchurch",
    "iso:country":"NZ",
    "sg:address":"50 Mooray Ave Bishopdale ",
    "sg:city":"Christchurch",
    "sg:orig_category":"Sports And Leisure: Sports: Aerial",
    "sg:phone":"+64 508 727 245",
    "sg:province":"Canterbury",
    "wof:name":"Paragliding New Zealand",
    "wof:placetype":"venue"
},
  "geometry": {"coordinates":[172.58308400000001,-43.49728],"type":"Point"}
}