{
  "type": "Feature",
  "properties": {
    "addr:full":"30 Thames St  Oamaru Otago",
    "addr:housenumber":"30",
    "addr:street":"Thames St",
    "iso:country":"NZ",
    "sg:address":"30 Thames St ",
    "sg:city":"Oamaru",
    "sg:classifiers":[
        {
            "category":"Bars & Pubs",
            "subcategory":"Wine Bar",
            "type":"Food & Drink"
        }
    ],
    "sg:phone":"+64 3-434 1165",
    "sg:province":"Otago",
    "sg:tags":[
        "wining",
        "dining",
        "cafe"
    ],
    "wof:name":"Emma's Cafe",
    "wof:placetype":"venue"
},
  "geometry": {"coordinates":[170.96923799999999,-45.10046],"type":"Point"}
}