{
  "type": "Feature",
  "properties": {
    "addr:full":"118 Spa Rd  Taupo Waikato",
    "addr:housenumber":"118",
    "addr:street":"Spa Rd",
    "iso:country":"NZ",
    "sg:address":"118 Spa Rd ",
    "sg:city":"Taupo",
    "sg:classifiers":[
        {
            "category":"Retail",
            "subcategory":"Auto Repair",
            "type":"Services"
        }
    ],
    "sg:phone":"+64 7-378 8350",
    "sg:province":"Waikato",
    "sg:tags":[
        "muffler",
        "exhaust",
        "servicing",
        "automotive"
    ],
    "wof:name":"Taupo Radiators & Exhausts",
    "wof:placetype":"venue"
},
  "geometry": {"coordinates":[176.076447,-38.682922],"type":"Point"}
}