{
  "type": "Feature",
  "properties": {
    "iso:country":"NZ",
    "sg:address":"R D 15 ",
    "sg:city":"Oamaru",
    "sg:orig_category":"Farming: Agriculture: Agricultural Contractors",
    "sg:phone":"+64 25420404",
    "sg:province":"Otago",
    "wof:name":"Boztrac Agri Contractors",
    "wof:placetype":"venue"
},
  "geometry": {"coordinates":[170.969025,-45.097145],"type":"Point"}
}