{
  "type": "Feature",
  "properties": {
    "addr:full":"218 Greta Rd Greta Valley  Amberley Canterbury",
    "addr:housenumber":"218",
    "addr:street":"Greta Rd",
    "iso:country":"NZ",
    "sg:address":"218 Greta Rd Greta Valley ",
    "sg:city":"Amberley",
    "sg:orig_category":"Transport: Transportation: Transport Operators",
    "sg:phone":"+64 3-314 8329",
    "sg:province":"Canterbury",
    "wof:name":"Deerbrooke Cartage Ltd",
    "wof:placetype":"venue"
},
  "geometry": {"coordinates":[172.727341,-43.155392],"type":"Point"}
}