{
  "type": "Feature",
  "properties": {
    "addr:full":"Golf Rd Heretaunga Upper  Hutt Wellington",
    "addr:street":"Golf Rd",
    "iso:country":"NZ",
    "sg:address":"Golf Rd Heretaunga Upper ",
    "sg:city":"Hutt",
    "sg:classifiers":[
        {
            "category":"Arena",
            "subcategory":"Sports Club",
            "type":"Entertainment"
        }
    ],
    "sg:phone":"+64 4-528 4590",
    "sg:province":"Wellington",
    "sg:tags":[
        "coaching",
        "-",
        "leisure",
        "sports"
    ],
    "wof:name":"Wellington Golf Club",
    "wof:placetype":"venue"
},
  "geometry": {"coordinates":[175.02166700000001,-41.141186],"type":"Point"}
}