{
  "type": "Feature",
  "properties": {
    "iso:country":"NZ",
    "sg:address":"45 A Argyle St Herne ",
    "sg:city":"Bay",
    "sg:classifiers":[
        {
            "category":"Social Services",
            "subcategory":"Child Care",
            "type":"Services"
        }
    ],
    "sg:phone":"+64 800 222 966",
    "sg:tags":[
        "baby",
        "home",
        "product",
        "garden",
        "children"
    ],
    "wof:name":"Baby-On-The-Move",
    "wof:placetype":"venue"
},
  "geometry": {"coordinates":[1.1251,51.371216],"type":"Point"}
}