{
  "type": "Feature",
  "properties": {
    "addr:full":"132 Hutt Rd Petone Lower  Hutt Wellington",
    "addr:housenumber":"132",
    "addr:street":"Hutt Rd",
    "iso:country":"NZ",
    "sg:address":"132 Hutt Rd Petone Lower ",
    "sg:city":"Hutt",
    "sg:orig_category":"Industrial: Parts",
    "sg:phone":"+64 4-569 5118",
    "sg:province":"Wellington",
    "wof:name":"Precision Bearings & Transmission",
    "wof:placetype":"venue"
},
  "geometry": {"coordinates":[174.87608299999999,-41.220917],"type":"Point"}
}