{
  "type": "Feature",
  "properties": {
    "addr:full":"PO Box 1696  Taupo Waikato",
    "addr:housenumber":"po;1696",
    "addr:street":"Box",
    "iso:country":"NZ",
    "sg:address":"PO Box 1696 ",
    "sg:city":"Taupo",
    "sg:orig_category":"Home And Garden: Gardening: Services: Lawnmowing Services",
    "sg:phone":"+64 7-377 1191",
    "sg:province":"Waikato",
    "wof:name":"A1 Lawn & Property Services",
    "wof:placetype":"venue"
},
  "geometry": {"coordinates":[176.084351,-38.689285],"type":"Point"}
}