{
  "type": "Feature",
  "properties": {
    "iso:country":"NZ",
    "sg:address":"22 Westwood St Bellevue ",
    "sg:city":"Tauranga",
    "sg:orig_category":"Home And Garden: Gardening: Services: Landscaping",
    "sg:phone":"+64 274 996 288",
    "sg:province":"Bay of Plenty",
    "wof:name":"Garden Care",
    "wof:placetype":"venue"
},
  "geometry": {"coordinates":[176.12359599999999,-37.681923],"type":"Point"}
}