{
  "type": "Feature",
  "properties": {
    "addr:full":"3 Hill St Onehunga  Auckland Auckland",
    "addr:housenumber":"3",
    "addr:street":"Hill St",
    "iso:country":"NZ",
    "sg:address":"3 Hill St Onehunga ",
    "sg:city":"Auckland",
    "sg:orig_category":"Industrial: Electrical/Electronic: Electrical Switchgear",
    "sg:phone":"+64 9-634 1895",
    "sg:province":"Auckland",
    "wof:name":"VA TECH Reyrolle Pacific Ltd",
    "wof:placetype":"venue"
},
  "geometry": {"coordinates":[174.78143299999999,-36.926395],"type":"Point"}
}