{
  "type": "Feature",
  "properties": {
    "iso:country":"NZ",
    "sg:address":"32 Ben Nevis Pl Howick ",
    "sg:city":"Auckland",
    "sg:classifiers":[
        {
            "category":"Manufacturing",
            "subcategory":"Tools & Machinery",
            "type":"Manufacturing & Wholesale Goods"
        }
    ],
    "sg:phone":"+64 9-534 5268",
    "sg:province":"Auckland",
    "sg:tags":[
        "equipment",
        "industrial",
        "oven",
        "kiln",
        "furnaces"
    ],
    "wof:name":"Aaron Appliance Repair Co Ltd",
    "wof:placetype":"venue"
},
  "geometry": {"coordinates":[174.916946,-36.894379],"type":"Point"}
}