{
  "type": "Feature",
  "properties": {
    "iso:country":"NZ",
    "sg:address":"Level One 13 Devon St East New ",
    "sg:city":"Plymouth",
    "sg:classifiers":[
        {
            "category":"Bars & Pubs",
            "type":"Food & Drink"
        }
    ],
    "sg:phone":"+64 6-759 6919",
    "sg:province":"Taranaki",
    "sg:tags":[
        "wining",
        "dining",
        "brasserie"
    ],
    "wof:name":"Mad Tom's Bar",
    "wof:placetype":"venue"
},
  "geometry": {"coordinates":[-86.266968,41.464134],"type":"Point"}
}