{
  "type": "Feature",
  "properties": {
    "iso:country":"NZ",
    "sg:address":"1 Ra Ora Dve East Tamaki ",
    "sg:city":"Auckland",
    "sg:orig_category":"Farming: Supplies: Veterinary Supplies",
    "sg:phone":"+64 9-273 4080",
    "sg:province":"Auckland",
    "wof:name":"National Veterinary Supplies Ltd",
    "wof:placetype":"venue"
},
  "geometry": {"coordinates":[174.882217,-36.937916],"type":"Point"}
}