{
  "type": "Feature",
  "properties": {
    "addr:full":"122 Henderson Valley Rd Henderson  Auckland Auckland",
    "addr:housenumber":"122",
    "addr:street":"Henderson Valley Rd",
    "iso:country":"NZ",
    "sg:address":"122 Henderson Valley Rd Henderson ",
    "sg:city":"Auckland",
    "sg:classifiers":[
        {
            "category":"Shopping",
            "subcategory":"Crafts & Fabrics",
            "type":"Retail Goods"
        }
    ],
    "sg:phone":"+64 9-836 0854",
    "sg:province":"Auckland",
    "sg:tags":[
        "sewing",
        "clothing",
        "supply"
    ],
    "wof:name":"Dawn Murray Bears",
    "wof:placetype":"venue"
},
  "geometry": {"coordinates":[174.62368799999999,-36.891106],"type":"Point"}
}