{
  "type": "Feature",
  "properties": {
    "addr:full":"Campion Rd  Gisborne Gisborne",
    "addr:street":"Campion Rd",
    "iso:country":"NZ",
    "sg:address":"Campion Rd ",
    "sg:city":"Gisborne",
    "sg:orig_category":"Education And Training: General: Schools",
    "sg:phone":"+64 6-867 9309",
    "sg:province":"Gisborne",
    "wof:name":"Campion College",
    "wof:placetype":"venue"
},
  "geometry": {"coordinates":[177.98996,-38.64521],"type":"Point"}
}