{
  "type": "Feature",
  "properties": {
    "addr:full":"12 Beacon Ave Campbells Bay  Auckland Auckland",
    "addr:housenumber":"12",
    "addr:street":"Beacon Ave",
    "iso:country":"NZ",
    "sg:address":"12 Beacon Ave Campbells Bay ",
    "sg:city":"Auckland",
    "sg:classifiers":[
        {
            "category":"Coffee & Tea",
            "type":"Food & Drink"
        }
    ],
    "sg:phone":"+64 9-479 3660",
    "sg:province":"Auckland",
    "sg:tags":[
        "vegetable",
        "fruit",
        "veges"
    ],
    "wof:name":"Auckland Fruit & Produce Supplies",
    "wof:placetype":"venue"
},
  "geometry": {"coordinates":[174.75470000000001,-36.74461],"type":"Point"}
}