{
  "type": "Feature",
  "properties": {
    "iso:country":"NZ",
    "sg:address":"78 Bannister St ",
    "sg:city":"Masterton",
    "sg:classifiers":[
        {
            "category":"Professional",
            "subcategory":"Art Services",
            "type":"Services"
        }
    ],
    "sg:phone":"+64 6-377 0631",
    "sg:province":"Wellington",
    "sg:tags":[
        "personal",
        "photographer",
        "services",
        "garden",
        "home"
    ],
    "wof:name":"Kannex Photography",
    "wof:placetype":"venue"
},
  "geometry": {"coordinates":[175.664963,-40.954647],"type":"Point"}
}