{
  "type": "Feature",
  "properties": {
    "addr:full":"12 Victoria St Petone Lower  Hutt Wellington",
    "addr:housenumber":"12",
    "addr:street":"Victoria St",
    "iso:country":"NZ",
    "sg:address":"12 Victoria St Petone Lower ",
    "sg:city":"Hutt",
    "sg:classifiers":[
        {
            "category":"Manufacturing",
            "subcategory":"Rubber & Plastics",
            "type":"Manufacturing & Wholesale Goods"
        }
    ],
    "sg:phone":"+64 4-568 3745",
    "sg:province":"Wellington",
    "sg:tags":[
        "industrial",
        "goods"
    ],
    "wof:name":"Rubber Bits",
    "wof:placetype":"venue"
},
  "geometry": {"coordinates":[174.87300099999999,-41.226318],"type":"Point"}
}