{
  "type": "Feature",
  "properties": {
    "iso:country":"NZ",
    "sg:address":"159 Rimu Rd ",
    "sg:city":"Paraparaumu",
    "sg:classifiers":[
        {
            "category":"Communications",
            "subcategory":"Television Station",
            "type":"Services"
        }
    ],
    "sg:phone":"+64 4-297 2266",
    "sg:province":"Wellington",
    "sg:tags":[
        "broadcasting"
    ],
    "wof:name":"Radio 2XX",
    "wof:placetype":"venue"
},
  "geometry": {"coordinates":[175.001495,-40.917355],"type":"Point"}
}