{
  "type": "Feature",
  "properties": {
    "addr:full":"155 Thames St  Oamaru Otago",
    "addr:housenumber":"155",
    "addr:street":"Thames St",
    "iso:country":"NZ",
    "sg:address":"155 Thames St ",
    "sg:city":"Oamaru",
    "sg:classifiers":[
        {
            "category":"Bars & Pubs",
            "subcategory":"Nightclub",
            "type":"Food & Drink"
        }
    ],
    "sg:phone":"+64 3-434 5858",
    "sg:province":"Otago",
    "sg:tags":[
        "club",
        "night",
        "sport",
        "leisure",
        "entertainment"
    ],
    "wof:name":"The Globe Entertainment Bar & Night Club",
    "wof:placetype":"venue"
},
  "geometry": {"coordinates":[170.971329,-45.097366],"type":"Point"}
}