{
  "type": "Feature",
  "properties": {
    "addr:full":"693 Tremaine Ave Palmerston  Palmerston North Manawatu-Wanganui",
    "addr:housenumber":"693",
    "addr:street":"Tremaine Ave",
    "iso:country":"NZ",
    "sg:address":"693 Tremaine Ave Palmerston ",
    "sg:city":"Palmerston North",
    "sg:classifiers":[
        {
            "category":"Wholesale",
            "subcategory":"Auto Parts",
            "type":"Manufacturing & Wholesale Goods"
        }
    ],
    "sg:phone":"+64 6-359 0100",
    "sg:province":"Manawatu-Wanganui",
    "sg:tags":[
        "automotive",
        "supplies"
    ],
    "wof:name":"AutoKraft",
    "wof:placetype":"venue"
},
  "geometry": {"coordinates":[175.61293000000001,-40.338127],"type":"Point"}
}