{
  "type": "Feature",
  "properties": {
    "addr:full":"15 Kopiko Rd Titirangi  Auckland Auckland",
    "addr:housenumber":"15",
    "addr:street":"Kopiko Rd",
    "iso:country":"NZ",
    "sg:address":"15 Kopiko Rd Titirangi ",
    "sg:city":"Auckland",
    "sg:classifiers":[
        {
            "category":"Home & Garden",
            "subcategory":"Building Materials",
            "type":"Retail Goods"
        }
    ],
    "sg:phone":"+64 9-817 8908",
    "sg:province":"Auckland",
    "sg:tags":[
        "fittings",
        "door",
        "garage"
    ],
    "wof:name":"Alltypes Garage Door Repairs",
    "wof:placetype":"venue"
},
  "geometry": {"coordinates":[174.65042099999999,-36.933598],"type":"Point"}
}