{
  "type": "Feature",
  "properties": {
    "iso:country":"NZ",
    "sg:address":"28 MacMaster St ",
    "sg:city":"Invercargill",
    "sg:classifiers":[
        {
            "category":"Professional",
            "subcategory":"Art Services",
            "type":"Services"
        }
    ],
    "sg:phone":"+64 3-217 2444",
    "sg:province":"Southland",
    "sg:tags":[
        "personal",
        "photographer",
        "services",
        "garden",
        "home"
    ],
    "wof:name":"George Bell",
    "wof:placetype":"venue"
},
  "geometry": {"coordinates":[168.362701,-46.411537],"type":"Point"}
}