{
  "type": "Feature",
  "properties": {
    "addr:full":"RD 1  Martinborough",
    "addr:street":"Rd 1",
    "iso:country":"NZ",
    "sg:address":"RD 1 ",
    "sg:city":"Martinborough",
    "sg:orig_category":"Farming: Horticulture: Horticultural Supplies",
    "sg:phone":"+64 6-306 9400",
    "wof:name":"Southdowns Topsoil",
    "wof:placetype":"venue"
},
  "geometry": {"coordinates":[175.45996099999999,-41.220089],"type":"Point"}
}