{
  "type": "Feature",
  "properties": {
    "iso:country":"NZ",
    "sg:address":"130 Hutt Rd Lower Hutt ",
    "sg:city":"Wellington",
    "sg:classifiers":[
        {
            "category":"Home & Garden",
            "subcategory":"Hardware",
            "type":"Retail Goods"
        }
    ],
    "sg:phone":"+64 4-939 0313",
    "sg:province":"Wellington",
    "sg:tags":[
        "water",
        "heater",
        "fittings"
    ],
    "wof:name":"Negawatt Resources Ltd",
    "wof:placetype":"venue"
},
  "geometry": {"coordinates":[174.90838600000001,-41.206631],"type":"Point"}
}