{
  "type": "Feature",
  "properties": {
    "addr:full":"10/39 Mills St Boulcott Lower  Hutt Wellington",
    "addr:housenumber":"10 / 39",
    "addr:street":"Mills St",
    "iso:country":"NZ",
    "sg:address":"10/39 Mills St Boulcott Lower ",
    "sg:city":"Hutt",
    "sg:classifiers":[
        {
            "category":"Personal",
            "subcategory":"Massage",
            "type":"Services"
        }
    ],
    "sg:phone":"+64 4-569 5577",
    "sg:province":"Wellington",
    "sg:tags":[
        "services",
        "health",
        "-",
        "beauty",
        "fitness"
    ],
    "wof:name":"Bryant Sharron Reg TMA",
    "wof:placetype":"venue"
},
  "geometry": {"coordinates":[174.91339099999999,-41.201916],"type":"Point"}
}