{
  "type": "Feature",
  "properties": {
    "addr:full":"PO Box 20035 Bishopdale  Christchurch Canterbury",
    "addr:housenumber":"po box",
    "addr:postcode":"20035 bishopdale",
    "addr:street":"Christchurch",
    "iso:country":"NZ",
    "sg:address":"PO Box 20035 Bishopdale ",
    "sg:city":"Christchurch",
    "sg:orig_category":"Industrial: Products: Laboratory Supplies",
    "sg:phone":"+64 3-358 7410",
    "sg:province":"Canterbury",
    "wof:name":"Global Science & Technology Ltd",
    "wof:placetype":"venue"
},
  "geometry": {"coordinates":[172.58607499999999,-43.487144],"type":"Point"}
}