{
  "type": "Feature",
  "properties": {
    "iso:country":"NZ",
    "sg:address":"Merivale ",
    "sg:city":"Tauranga",
    "sg:orig_category":"Shopping: Sports Retailers: Sports Goods: Canvas Goods",
    "sg:phone":"+64 7-578 3516",
    "sg:province":"Canterbury",
    "wof:name":"Coastal Canvas",
    "wof:placetype":"venue"
},
  "geometry": {"coordinates":[176.14475999999999,-37.703152],"type":"Point"}
}