{
  "type": "Feature",
  "properties": {
    "iso:country":"NZ",
    "sg:address":"North City Plaza ",
    "sg:city":"Porirua",
    "sg:classifiers":[
        {
            "category":"Arts & Performance",
            "subcategory":"Music",
            "type":"Entertainment"
        }
    ],
    "sg:phone":"+64 4-237 8908",
    "sg:province":"Wellington",
    "sg:tags":[
        "sport",
        "leisure"
    ],
    "wof:name":"Sounds",
    "wof:placetype":"venue"
},
  "geometry": {"coordinates":[174.840103,-41.13702],"type":"Point"}
}