{
  "type": "Feature",
  "properties": {
    "iso:country":"NZ",
    "sg:address":"45 Grey St ",
    "sg:city":"Tauranga",
    "sg:orig_category":"Health And Beauty: Specialists: Osteopaths",
    "sg:phone":"+64 7-579 4500",
    "sg:province":"Bay of Plenty",
    "wof:name":"Physique Care",
    "wof:placetype":"venue"
},
  "geometry": {"coordinates":[176.168198,-37.68539],"type":"Point"}
}