{
  "type": "Feature",
  "properties": {
    "addr:full":"State Highway 14  Dargaville Northland",
    "addr:street":"State Highway 14 Dargaville",
    "iso:country":"NZ",
    "sg:address":"State Highway 14 ",
    "sg:city":"Dargaville",
    "sg:orig_category":"Farming: Machinery: Farm Machinery",
    "sg:phone":"+64 9-439 1089",
    "sg:province":"Northland",
    "wof:name":"Dargaville Honda",
    "wof:placetype":"venue"
},
  "geometry": {"coordinates":[173.910507,-35.869175],"type":"Point"}
}