{
  "type": "Feature",
  "properties": {
    "iso:country":"NZ",
    "sg:address":"The Room Hairdressing Cnr Forest Lake Road & Ulster, Street ",
    "sg:city":"Hamilton",
    "sg:classifiers":[
        {
            "category":"Health Services",
            "subcategory":"Clinic",
            "type":"Services"
        }
    ],
    "sg:phone":"+64 7-850 1013",
    "sg:province":"Waikato",
    "sg:tags":[
        "services",
        "therapy",
        "natural",
        "beauty"
    ],
    "wof:name":"Body Mind & Spirit",
    "wof:placetype":"venue"
},
  "geometry": {"coordinates":[175.276993,-37.783211],"type":"Point"}
}