{
  "type": "Feature",
  "properties": {
    "iso:country":"NZ",
    "sg:address":"135 Harris Rd East Tamaki ",
    "sg:city":"Auckland",
    "sg:orig_category":"Automotive: Parts And Supplies: Tyres",
    "sg:phone":"+64 9-274 3003",
    "sg:province":"Auckland",
    "wof:name":"Harris Road Tyrepower Ltd",
    "wof:placetype":"venue"
},
  "geometry": {"coordinates":[174.896912,-36.931458],"type":"Point"}
}