{
  "type": "Feature",
  "properties": {
    "addr:full":"2 Des Swann Dve Takapuna  Auckland Auckland",
    "addr:housenumber":"2",
    "addr:street":"Des Swann",
    "iso:country":"NZ",
    "sg:address":"2 Des Swann Dve Takapuna ",
    "sg:city":"Auckland",
    "sg:orig_category":"Transport: Transportation: Freight",
    "sg:phone":"+64 9-486 7737",
    "sg:province":"Auckland",
    "wof:name":"Access Freight International",
    "wof:placetype":"venue"
},
  "geometry": {"coordinates":[174.76417499999999,-36.793018],"type":"Point"}
}