{
  "type": "Feature",
  "properties": {
    "iso:country":"NZ",
    "sg:address":"359 Lincoln Rd Addington ",
    "sg:city":"Christchurch",
    "sg:classifiers":[
        {
            "category":"Sports & Exercise",
            "subcategory":"Sports Center",
            "type":"Entertainment"
        }
    ],
    "sg:phone":"+64 3-338 3309",
    "sg:province":"Canterbury",
    "sg:tags":[
        "indoor",
        "-",
        "leisure",
        "sports"
    ],
    "wof:name":"BALLSPORTS",
    "wof:placetype":"venue"
},
  "geometry": {"coordinates":[172.615005,-43.541496],"type":"Point"}
}