{
  "type": "Feature",
  "properties": {
    "iso:country":"NZ",
    "sg:address":"10 Bowmont St ",
    "sg:city":"Invercargill",
    "sg:orig_category":"Industrial: Electrical/Electronic: Electric Motors",
    "sg:phone":"+64 3-218 6947",
    "sg:province":"Southland",
    "wof:name":"Wallace Murray Electrical",
    "wof:placetype":"venue"
},
  "geometry": {"coordinates":[168.348297,-46.421116],"type":"Point"}
}