{
  "type": "Feature",
  "properties": {
    "iso:country":"NZ",
    "sg:address":"Central Park 666 Gt South Rd Ellerslie ",
    "sg:city":"Auckland",
    "sg:classifiers":[
        {
            "category":"Professional",
            "type":"Services"
        }
    ],
    "sg:phone":"+64 9-525 1881",
    "sg:province":"Auckland",
    "sg:tags":[
        "function",
        "entertainment",
        "leisure",
        "planning",
        "party",
        "sport"
    ],
    "wof:name":"Six Sixty Six Brasserie",
    "wof:placetype":"venue"
},
  "geometry": {"coordinates":[174.80912799999999,-36.884655],"type":"Point"}
}