{
  "type": "Feature",
  "properties": {
    "addr:full":"Havelock St  Opunake",
    "addr:street":"Havelock St",
    "iso:country":"NZ",
    "sg:address":"Havelock St ",
    "sg:city":"Opunake",
    "sg:classifiers":[
        {
            "category":"Shopping",
            "subcategory":"Beauty & Cosmetics",
            "type":"Retail Goods"
        }
    ],
    "sg:phone":"+64 6-761 8777",
    "sg:tags":[
        "medical",
        "health"
    ],
    "wof:name":"Opunake Health Centre",
    "wof:placetype":"venue"
},
  "geometry": {"coordinates":[173.85910000000001,-39.452728],"type":"Point"}
}