{
  "type": "Feature",
  "properties": {
    "addr:full":"125 Bank St  Whangarei Northland",
    "addr:housenumber":"125",
    "addr:street":"Bank St",
    "iso:country":"NZ",
    "sg:address":"125 Bank St ",
    "sg:city":"Whangarei",
    "sg:classifiers":[
        {
            "category":"Personal",
            "subcategory":"Tanning Parlor",
            "type":"Services"
        }
    ],
    "sg:phone":"+64 9-438 8863",
    "sg:province":"Northland",
    "sg:tags":[
        "sun",
        "health",
        "beauty"
    ],
    "wof:name":"World Of Fitness",
    "wof:placetype":"venue"
},
  "geometry": {"coordinates":[174.32063299999999,-35.720772],"type":"Point"}
}