{
  "type": "Feature",
  "properties": {
    "addr:full":"125 Kapiro Rd  Kerikeri Northland",
    "addr:housenumber":"125",
    "addr:street":"Kapiro Rd",
    "iso:country":"NZ",
    "sg:address":"125 Kapiro Rd ",
    "sg:city":"Kerikeri",
    "sg:orig_category":"Farming: Supplies: Stock Foods",
    "sg:phone":"+64 800 278 214",
    "sg:province":"Northland",
    "wof:name":"Nutritional Services",
    "wof:placetype":"venue"
},
  "geometry": {"coordinates":[173.962875,-35.195705],"type":"Point"}
}