{
  "type": "Feature",
  "properties": {
    "iso:country":"NZ",
    "sg:address":"Shed 1 Queens Wharf PO Box 1550 ",
    "sg:city":"Wellington",
    "sg:classifiers":[
        {
            "category":"Travel",
            "subcategory":"Travel Agent",
            "type":"Entertainment"
        }
    ],
    "sg:phone":"+64 4-472 1550",
    "sg:province":"Wellington",
    "sg:tags":[
        "tour",
        "tourism",
        "sightseeing"
    ],
    "sg:website":"http://www.helipro.co.nz",
    "wof:name":"Helipro",
    "wof:placetype":"venue"
},
  "geometry": {"coordinates":[-100.207474,34.863777],"type":"Point"}
}