{
  "type": "Feature",
  "properties": {
    "addr:full":"68 Don St  Invercargill Southland",
    "addr:housenumber":"68",
    "addr:street":"Don St",
    "iso:country":"NZ",
    "sg:address":"68 Don St ",
    "sg:city":"Invercargill",
    "sg:classifiers":[
        {
            "category":"Health Services",
            "subcategory":"Health Practitioner",
            "type":"Services"
        }
    ],
    "sg:phone":"+64 3-214 4978",
    "sg:province":"Southland",
    "sg:tags":[
        "consultant",
        "medical",
        "beauty"
    ],
    "wof:name":"Family Planning Centre",
    "wof:placetype":"venue"
},
  "geometry": {"coordinates":[168.35189800000001,-46.410629],"type":"Point"}
}