{
  "type": "Feature",
  "properties": {
    "iso:country":"NZ",
    "sg:address":"Austin Rd Maunu ",
    "sg:city":"Whangarei",
    "sg:orig_category":"Farming: Services: Irrigation",
    "sg:phone":"+64 9-438 8140",
    "sg:province":"Northland",
    "wof:name":"Water Specs Irrigation",
    "wof:placetype":"venue"
},
  "geometry": {"coordinates":[174.279449,-35.73909],"type":"Point"}
}