{
  "type": "Feature",
  "properties": {
    "addr:full":"152 Raleigh St  Waitara",
    "addr:housenumber":"152",
    "addr:street":"Raleigh St",
    "iso:country":"NZ",
    "sg:address":"152 Raleigh St ",
    "sg:city":"Waitara",
    "sg:classifiers":[
        {
            "category":"Food & Beverages",
            "subcategory":"Dairy",
            "type":"Retail Goods"
        }
    ],
    "sg:phone":"+64 6-754 7680",
    "sg:tags":[
        "-",
        "drink",
        "vendor",
        "milk"
    ],
    "wof:name":"D & P Crow Distributors",
    "wof:placetype":"venue"
},
  "geometry": {"coordinates":[174.22036700000001,-39.009335],"type":"Point"}
}