{
  "type": "Feature",
  "properties": {
    "addr:full":"Royal View Rd Te Atatu South  Auckland Auckland",
    "addr:street":"Royal View Rd",
    "iso:country":"NZ",
    "sg:address":"Royal View Rd Te Atatu South ",
    "sg:city":"Auckland",
    "sg:classifiers":[
        {
            "category":"Shopping",
            "subcategory":"Clothing, Apparel, & Fashions",
            "type":"Retail Goods"
        }
    ],
    "sg:phone":"+64 9-834 2525",
    "sg:province":"Auckland",
    "sg:tags":[
        "-",
        "hire",
        "clothing",
        "fabric"
    ],
    "wof:name":"Santa Claus Suit Hire Co Ltd",
    "wof:placetype":"venue"
},
  "geometry": {"coordinates":[174.64849899999999,-36.85751],"type":"Point"}
}