{
  "type": "Feature",
  "properties": {
    "addr:full":"170 Leet St  Invercargill Southland",
    "addr:housenumber":"170",
    "addr:street":"Leet St",
    "iso:country":"NZ",
    "sg:address":"170 Leet St ",
    "sg:city":"Invercargill",
    "sg:classifiers":[
        {
            "category":"Health Services",
            "subcategory":"Dentist",
            "type":"Services"
        }
    ],
    "sg:phone":"+64 3-218 9635",
    "sg:province":"Southland",
    "sg:tags":[
        "dental",
        "beauty"
    ],
    "wof:name":"Southern Orthodontic Products (NZ) Ltd",
    "wof:placetype":"venue"
},
  "geometry": {"coordinates":[168.35823099999999,-46.407303],"type":"Point"}
}