{
  "type": "Feature",
  "properties": {
    "iso:country":"NZ",
    "sg:address":"PO Box 2084 ",
    "sg:city":"Dunedin",
    "sg:classifiers":[
        {
            "category":"Building & Trades",
            "subcategory":"Construction",
            "type":"Services"
        }
    ],
    "sg:phone":"+64 25892822",
    "sg:province":"Otago",
    "sg:tags":[
        "home",
        "garden",
        "related",
        "plasterer"
    ],
    "wof:name":"Greg Scott Plasterers & Tilers Ltd",
    "wof:placetype":"venue"
},
  "geometry": {"coordinates":[-82.784721,28.013355],"type":"Point"}
}