{
  "type": "Feature",
  "properties": {
    "iso:country":"NZ",
    "sg:address":"16 Brind Rd ",
    "sg:city":"Russell",
    "sg:classifiers":[
        {
            "category":"Recreation",
            "type":"Entertainment"
        }
    ],
    "sg:phone":"+64 9-403 7123",
    "sg:tags":[
        "shopping",
        "hunting",
        "fishing",
        "retailers",
        "sport",
        "trip"
    ],
    "wof:name":"Island Water Taxi",
    "wof:placetype":"venue"
},
  "geometry": {"coordinates":[-91.508163,35.362637],"type":"Point"}
}