{
  "type": "Feature",
  "properties": {
    "addr:full":"S H 10 Rd Waipapa  Kerikeri Northland",
    "addr:housenumber":"10 rd;kerikeri",
    "addr:street":"S H",
    "iso:country":"NZ",
    "sg:address":"S H 10 Rd Waipapa ",
    "sg:city":"Kerikeri",
    "sg:classifiers":[
        {
            "category":"Autos & Motor Vehicles",
            "subcategory":"Motorcycle Sales",
            "type":"Retail Goods"
        }
    ],
    "sg:phone":"+64 9-407 7736",
    "sg:province":"Northland",
    "sg:tags":[
        "automotive",
        "scooter",
        "leasing"
    ],
    "wof:name":"Kerikeri Motorcycles",
    "wof:placetype":"venue"
},
  "geometry": {"coordinates":[173.92688000000001,-35.206779],"type":"Point"}
}