{
  "type": "Feature",
  "properties": {
    "iso:country":"NZ",
    "sg:address":"Rahuikiri Rd Pakiri R D 2 Wellsford ",
    "sg:city":"Warkworth",
    "sg:classifiers":[
        {
            "category":"Recreation",
            "type":"Entertainment"
        }
    ],
    "sg:phone":"+64 9-422 6275",
    "sg:province":"Auckland",
    "sg:tags":[
        "trek",
        "travel",
        "horse",
        "tour",
        "tourism",
        "sightseeing"
    ],
    "sg:website":"http://www.horseride-nz.co.nz",
    "wof:name":"Pakiri Beach Horse Rides & Overnight Safaris",
    "wof:placetype":"venue"
},
  "geometry": {"coordinates":[174.66511499999999,-36.401459],"type":"Point"}
}