{
  "type": "Feature",
  "properties": {
    "addr:full":"15 Elizabeth St  Warkworth Auckland",
    "addr:housenumber":"15",
    "addr:street":"Elizabeth St",
    "iso:country":"NZ",
    "sg:address":"15 Elizabeth St ",
    "sg:city":"Warkworth",
    "sg:classifiers":[
        {
            "category":"Shopping",
            "subcategory":"Pharmacy",
            "type":"Retail Goods"
        }
    ],
    "sg:phone":"+64 9-425 8142",
    "sg:province":"Auckland",
    "sg:tags":[
        "product",
        "health"
    ],
    "wof:name":"Warkworth Health Food Shop",
    "wof:placetype":"venue"
},
  "geometry": {"coordinates":[174.66217,-36.397621],"type":"Point"}
}