{
  "type": "Feature",
  "properties": {
    "addr:full":"265 Queen St Auckland Central  Auckland Auckland",
    "addr:housenumber":"265",
    "addr:street":"Queen St",
    "iso:country":"NZ",
    "sg:address":"265 Queen St Auckland Central ",
    "sg:city":"Auckland",
    "sg:classifiers":[
        {
            "category":"Personal",
            "subcategory":"Hair Removal",
            "type":"Services"
        }
    ],
    "sg:phone":"+64 9-309 2004",
    "sg:province":"Auckland",
    "sg:tags":[
        "specialist",
        "health",
        "scalp",
        "beauty",
        "specialists"
    ],
    "wof:name":"Hair Care Market",
    "wof:placetype":"venue"
},
  "geometry": {"coordinates":[174.76445000000001,-36.850697],"type":"Point"}
}