{
  "type": "Feature",
  "properties": {
    "addr:full":"5 Edgeware Rd Palmerston  Palmerston North Canterbury",
    "addr:housenumber":"5",
    "addr:street":"Edgeware Rd",
    "iso:country":"NZ",
    "sg:address":"5 Edgeware Rd Palmerston ",
    "sg:city":"Palmerston North",
    "sg:classifiers":[
        {
            "category":"Retail",
            "subcategory":"Auto Repair",
            "type":"Services"
        }
    ],
    "sg:phone":"+64 6-356 7191",
    "sg:province":"Canterbury",
    "sg:tags":[
        "automotive",
        "panel",
        "servicing",
        "beater"
    ],
    "wof:name":"Advanced Panelbeaters",
    "wof:placetype":"venue"
},
  "geometry": {"coordinates":[175.60510300000001,-40.347523],"type":"Point"}
}