{
  "type": "Feature",
  "properties": {
    "addr:full":"Level 3 146 Manchester St  Christchurch Canterbury",
    "addr:housenumber":"level 3 146",
    "addr:street":"Manchester St",
    "iso:country":"NZ",
    "sg:address":"Level 3 146 Manchester St ",
    "sg:city":"Christchurch",
    "sg:classifiers":[
        {
            "category":"Health Services",
            "subcategory":"Hospital",
            "type":"Services"
        }
    ],
    "sg:phone":"+64 3-377 6789",
    "sg:province":"Canterbury",
    "sg:tags":[
        "beauty",
        "fitness"
    ],
    "wof:name":"Christchurch Sports-Therapeutic Massage Clinic",
    "wof:placetype":"venue"
},
  "geometry": {"coordinates":[-76.537834,37.605659],"type":"Point"}
}