{
  "type": "Feature",
  "properties": {
    "iso:country":"NZ",
    "sg:address":"R D 1 Paretai ",
    "sg:city":"Balclutha",
    "sg:orig_category":"Home And Garden: Gardening: Products: Garden Supplies",
    "sg:phone":"+64 3-412 8725",
    "wof:name":"Woco Nurseries",
    "wof:placetype":"venue"
},
  "geometry": {"coordinates":[169.746796,-46.234798],"type":"Point"}
}