{
  "type": "Feature",
  "properties": {
    "addr:full":"22 Kipling Ave Epsom  Auckland Auckland",
    "addr:housenumber":"22",
    "addr:street":"Kipling Ave",
    "iso:country":"NZ",
    "sg:address":"22 Kipling Ave Epsom ",
    "sg:city":"Auckland",
    "sg:classifiers":[
        {
            "category":"Travel",
            "subcategory":"Bed & Breakfast",
            "type":"Entertainment"
        }
    ],
    "sg:phone":"+64 9-638 8020",
    "sg:province":"Auckland",
    "sg:tags":[
        "house",
        "tourism",
        "guest",
        "accommodation"
    ],
    "wof:name":"Epsom Private Hotel",
    "wof:placetype":"venue"
},
  "geometry": {"coordinates":[174.77333100000001,-36.879654],"type":"Point"}
}