{
  "type": "Feature",
  "properties": {
    "addr:full":"30 Elizabeth St Moera  Wellington Wellington",
    "addr:housenumber":"30",
    "addr:street":"Elizabeth St",
    "iso:country":"NZ",
    "sg:address":"30 Elizabeth St Moera ",
    "sg:city":"Wellington",
    "sg:classifiers":[
        {
            "category":"Home & Garden",
            "subcategory":"Household Appliances",
            "type":"Retail Goods"
        }
    ],
    "sg:phone":"+64 4-920 5626",
    "sg:province":"Wellington",
    "sg:tags":[
        "box",
        "accessories",
        "letter"
    ],
    "wof:name":"Letter Boxes-Security",
    "wof:placetype":"venue"
},
  "geometry": {"coordinates":[174.90737899999999,-41.230171],"type":"Point"}
}