{
  "type": "Feature",
  "properties": {
    "iso:country":"NZ",
    "sg:address":"1006 Te Rapa Rd ",
    "sg:city":"Hamilton",
    "sg:classifiers":[
        {
            "category":"Retail",
            "subcategory":"Auto Repair",
            "type":"Services"
        }
    ],
    "sg:phone":"+64 7-849 3481",
    "sg:province":"Waikato",
    "sg:tags":[
        "automotive",
        "electric",
        "servicing"
    ],
    "wof:name":"David R Irving Motors",
    "wof:placetype":"venue"
},
  "geometry": {"coordinates":[175.237213,-37.750191],"type":"Point"}
}