{
  "type": "Feature",
  "properties": {
    "addr:full":"PO Box 487  Cambridge Waikato",
    "addr:housenumber":"po",
    "addr:street":"Box 487",
    "iso:country":"NZ",
    "sg:address":"PO Box 487 ",
    "sg:city":"Cambridge",
    "sg:classifiers":[
        {
            "category":"Health Services",
            "subcategory":"Health Practitioner",
            "type":"Services"
        }
    ],
    "sg:phone":"+64 7-823 4607",
    "sg:province":"Waikato",
    "sg:tags":[
        "specialist",
        "medical",
        "beauty",
        "specialists"
    ],
    "wof:name":"Gold Standard Locums",
    "wof:placetype":"venue"
},
  "geometry": {"coordinates":[-116.67604799999999,44.572186],"type":"Point"}
}