{
  "type": "Feature",
  "properties": {
    "addr:full":"Cnr Austin St & Ford Rd Onekawa  Napier Hawke's Bay",
    "addr:street":"Cnr Austin St & Ford Rd",
    "iso:country":"NZ",
    "sg:address":"Cnr Austin St & Ford Rd Onekawa ",
    "sg:city":"Napier",
    "sg:orig_category":"Automotive: Parts And Supplies: Windscreens",
    "sg:phone":"+64 6-843 6481",
    "sg:province":"Hawke's Bay",
    "wof:name":"Napier Glass",
    "wof:placetype":"venue"
},
  "geometry": {"coordinates":[176.89598100000001,-39.504452],"type":"Point"}
}