{
  "type": "Feature",
  "properties": {
    "iso:country":"NZ",
    "sg:address":"106 The Square Palmerston ",
    "sg:city":"Palmerston North",
    "sg:classifiers":[
        {
            "category":"Recreation",
            "type":"Entertainment"
        }
    ],
    "sg:phone":"+64 6-354 0438",
    "sg:province":"Wellington",
    "sg:tags":[
        "sport",
        "leisure"
    ],
    "wof:name":"Time Zone",
    "wof:placetype":"venue"
},
  "geometry": {"coordinates":[175.611481,-40.357418],"type":"Point"}
}