{
  "type": "Feature",
  "properties": {
    "addr:full":"22 b College Rd  Timaru Canterbury",
    "addr:housenumber":"22 b",
    "addr:street":"College Rd",
    "iso:country":"NZ",
    "sg:address":"22 b College Rd ",
    "sg:city":"Timaru",
    "sg:classifiers":[
        {
            "category":"Social Services",
            "subcategory":"Child Care",
            "type":"Services"
        }
    ],
    "sg:phone":"+64 3-684 5470",
    "sg:province":"Canterbury",
    "sg:tags":[
        "home",
        "garden",
        "children"
    ],
    "wof:name":"South Canterbury Free Kindergarten Association",
    "wof:placetype":"venue"
},
  "geometry": {"coordinates":[171.24273700000001,-44.408146],"type":"Point"}
}