{
  "type": "Feature",
  "properties": {
    "addr:full":"34 Kelvin St  Invercargill Southland",
    "addr:housenumber":"34",
    "addr:street":"Kelvin St",
    "iso:country":"NZ",
    "sg:address":"34 Kelvin St ",
    "sg:city":"Invercargill",
    "sg:classifiers":[
        {
            "category":"Personal",
            "subcategory":"Beauty Salon",
            "type":"Services"
        }
    ],
    "sg:phone":"+64 3-214 1262",
    "sg:province":"Southland",
    "sg:tags":[
        "therapy",
        "health"
    ],
    "wof:name":"Beauty & Beyond",
    "wof:placetype":"venue"
},
  "geometry": {"coordinates":[168.35047900000001,-46.411121],"type":"Point"}
}