{
  "type": "Feature",
  "properties": {
    "addr:full":"3 Dunvegan Pl  Hamilton Waikato",
    "addr:housenumber":"3",
    "addr:street":"Dunvegan Pl",
    "iso:country":"NZ",
    "sg:address":"3 Dunvegan Pl ",
    "sg:city":"Hamilton",
    "sg:classifiers":[
        {
            "category":"Shopping",
            "subcategory":"Clothing, Apparel, & Fashions",
            "type":"Retail Goods"
        }
    ],
    "sg:phone":"+64 7-847 4272",
    "sg:province":"Waikato",
    "sg:tags":[
        "clothing",
        "fabric"
    ],
    "wof:name":"Ken Weeks Scottish Imports",
    "wof:placetype":"venue"
},
  "geometry": {"coordinates":[175.234894,-37.793839],"type":"Point"}
}