{
  "type": "Feature",
  "properties": {
    "addr:full":"304 Burwood Rd Burwood  Christchurch Canterbury",
    "addr:housenumber":"304",
    "addr:street":"Burwood Rd",
    "iso:country":"NZ",
    "sg:address":"304 Burwood Rd Burwood ",
    "sg:city":"Christchurch",
    "sg:classifiers":[
        {
            "category":"Social Services",
            "subcategory":"Retirement Home",
            "type":"Services"
        }
    ],
    "sg:phone":"+64 3-383 1481",
    "sg:province":"Canterbury",
    "sg:tags":[
        "personal",
        "services",
        "garden",
        "elderly",
        "care"
    ],
    "wof:name":"Burwood Day Care Centre For The Elderly Inc.",
    "wof:placetype":"venue"
},
  "geometry": {"coordinates":[172.68130500000001,-43.480976],"type":"Point"}
}