{
  "type": "Feature",
  "properties": {
    "iso:country":"NZ",
    "sg:address":"246 Buckley Rd Southgate ",
    "sg:city":"Wellington",
    "sg:orig_category":"Home And Garden: Children: Child Related: Children'S Entertainment",
    "sg:phone":"+64 4-934 1113",
    "sg:province":"Auckland",
    "wof:name":"Captain Fearless Fickletummy",
    "wof:placetype":"venue"
},
  "geometry": {"coordinates":[174.77844200000001,-41.34412],"type":"Point"}
}