{
  "type": "Feature",
  "properties": {
    "iso:country":"NZ",
    "sg:address":"7-10 Waiwera Rd Waiwera Hibiscus ",
    "sg:city":"Hibiscus Coast",
    "sg:classifiers":[
        {
            "category":"Sports & Exercise",
            "subcategory":"Ice Rink",
            "type":"Entertainment"
        }
    ],
    "sg:phone":"+64 9-426 5369",
    "sg:province":"Auckland",
    "sg:tags":[
        "thermal",
        "pool",
        "leisure"
    ],
    "sg:website":"http://www.waiwera.co.nz",
    "wof:name":"Waiwera Thermal Pools",
    "wof:placetype":"venue"
},
  "geometry": {"coordinates":[174.704849,-36.543785],"type":"Point"}
}