{
  "type": "Feature",
  "properties": {
    "addr:full":"4105 Gt North Rd Glen Eden  Auckland Auckland",
    "addr:housenumber":"4105",
    "addr:street":"Gt North Rd",
    "iso:country":"NZ",
    "sg:address":"4105 Gt North Rd Glen Eden ",
    "sg:city":"Auckland",
    "sg:classifiers":[
        {
            "category":"Banks & Credit Unions",
            "subcategory":"Investment Brokerage",
            "type":"Services"
        }
    ],
    "sg:phone":"+64 9-818 5261",
    "sg:province":"Auckland",
    "sg:tags":[
        "funeral",
        "arrangements",
        "headstone"
    ],
    "sg:website":"http://www.yellowpages.co.nz/for/thompsonmemorials/dp49833.html",
    "wof:name":"Thompson Memorials",
    "wof:placetype":"venue"
},
  "geometry": {"coordinates":[174.65744000000001,-36.903271],"type":"Point"}
}