{
  "type": "Feature",
  "properties": {
    "addr:full":"Takapu Rd Grenada North  Wellington Wellington",
    "addr:street":"Takapu Rd",
    "iso:country":"NZ",
    "sg:address":"Takapu Rd Grenada North ",
    "sg:city":"Wellington",
    "sg:classifiers":[
        {
            "category":"Coffee & Tea",
            "type":"Food & Drink"
        }
    ],
    "sg:phone":"+64 4-232 3575",
    "sg:province":"Wellington",
    "sg:tags":[
        "vegetable",
        "fruit",
        "veges"
    ],
    "wof:name":"Fresh Produce Supplies Wgtn Ltd",
    "wof:placetype":"venue"
},
  "geometry": {"coordinates":[174.83708200000001,-41.179653],"type":"Point"}
}