{
  "type": "Feature",
  "properties": {
    "iso:country":"NZ",
    "sg:address":"345 Fergusson St Palmerston ",
    "sg:city":"Palmerston North",
    "sg:orig_category":"Automotive: Parts And Supplies: Tyres",
    "sg:phone":"+64 6-357 1972",
    "sg:province":"Manawatu-Wanganui",
    "wof:name":"Budget Tyres",
    "wof:placetype":"venue"
},
  "geometry": {"coordinates":[175.612991,-40.359531],"type":"Point"}
}