{
  "type": "Feature",
  "properties": {
    "addr:full":"107 Magdala Pl Hillmorton  Christchurch Canterbury",
    "addr:housenumber":"107",
    "addr:street":"Magdala Pl",
    "iso:country":"NZ",
    "sg:address":"107 Magdala Pl Hillmorton ",
    "sg:city":"Christchurch",
    "sg:classifiers":[
        {
            "category":"Food & Beverages",
            "subcategory":"Groceries & Convenience Stores",
            "type":"Retail Goods"
        }
    ],
    "sg:phone":"+64 3-339 6223",
    "sg:province":"Canterbury",
    "sg:tags":[
        "foodstuff",
        "drink",
        "-"
    ],
    "wof:name":"Marsanta Foods Ltd",
    "wof:placetype":"venue"
},
  "geometry": {"coordinates":[172.58696,-43.55862],"type":"Point"}
}