{
  "type": "Feature",
  "properties": {
    "addr:full":"2/56 Ellice Rd Glenfield  Auckland Auckland",
    "addr:housenumber":"2 / 56",
    "addr:street":"Ellice Rd",
    "iso:country":"NZ",
    "sg:address":"2/56 Ellice Rd Glenfield ",
    "sg:city":"Auckland",
    "sg:classifiers":[
        {
            "category":"Utilities",
            "subcategory":"Water",
            "type":"Services"
        }
    ],
    "sg:phone":"+64 9-444 2350",
    "sg:province":"Auckland",
    "sg:tags":[
        "energy",
        "industrial",
        "utilities",
        "meter"
    ],
    "wof:name":"Arthur D Riley & Co Ltd",
    "wof:placetype":"venue"
},
  "geometry": {"coordinates":[174.728622,-36.784813],"type":"Point"}
}