{
  "type": "Feature",
  "properties": {
    "addr:full":"60 Gill St New  Plymouth Taranaki",
    "addr:housenumber":"60",
    "addr:street":"Gill St",
    "iso:country":"NZ",
    "sg:address":"60 Gill St New ",
    "sg:city":"Plymouth",
    "sg:orig_category":"Shopping: Retail Stores: Batteries",
    "sg:phone":"+64 6-758 6100",
    "sg:province":"Taranaki",
    "wof:name":"Ron Peck Corson Tyres",
    "wof:placetype":"venue"
},
  "geometry": {"coordinates":[-116.81972500000001,43.97221],"type":"Point"}
}