{
  "type": "Feature",
  "properties": {
    "addr:full":"37 Beacon Hill Rd Strathmore  Wellington Wellington",
    "addr:housenumber":"37",
    "addr:street":"Beacon Hill Rd",
    "iso:country":"NZ",
    "sg:address":"37 Beacon Hill Rd Strathmore ",
    "sg:city":"Wellington",
    "sg:classifiers":[
        {
            "category":"Education",
            "subcategory":"Special Training",
            "type":"Public Place"
        }
    ],
    "sg:phone":"+64 4-939 0599",
    "sg:province":"Wellington",
    "sg:tags":[
        "tutor",
        "coach",
        "teacher"
    ],
    "wof:name":"The Schoolhouse",
    "wof:placetype":"venue"
},
  "geometry": {"coordinates":[174.82783499999999,-41.325287],"type":"Point"}
}