{
  "type": "Feature",
  "properties": {
    "iso:country":"NZ",
    "sg:address":"9-13 Sims Rd Penrose ",
    "sg:city":"Auckland",
    "sg:classifiers":[
        {
            "category":"Building & Trades",
            "subcategory":"Cleaning & Sanitation",
            "type":"Services"
        }
    ],
    "sg:phone":"+64 9-580 2099",
    "sg:province":"Auckland",
    "sg:tags":[
        "equipment",
        "industrial",
        "maintenance"
    ],
    "wof:name":"Loadlift Equipment Ltd",
    "wof:placetype":"venue"
},
  "geometry": {"coordinates":[174.82463100000001,-36.915665],"type":"Point"}
}