{
  "type": "Feature",
  "properties": {
    "iso:country":"NZ",
    "sg:address":"42 Papanui Rd St Albans ",
    "sg:city":"Christchurch",
    "sg:classifiers":[
        {
            "category":"Restaurant",
            "type":"Food & Drink"
        }
    ],
    "sg:phone":"+64 3-355 5633",
    "sg:province":"Canterbury",
    "sg:tags":[
        "wining",
        "dining"
    ],
    "sg:website":"http://www.PavilionsHotel.co.nz",
    "wof:name":"Pavilions Hotel Christchurch",
    "wof:placetype":"venue"
},
  "geometry": {"coordinates":[172.636185,-43.511974],"type":"Point"}
}