{
  "type": "Feature",
  "properties": {
    "addr:full":"7 Rata St New Lynn  Auckland Auckland",
    "addr:housenumber":"7",
    "addr:street":"Rata St",
    "iso:country":"NZ",
    "sg:address":"7 Rata St New Lynn ",
    "sg:city":"Auckland",
    "sg:classifiers":[
        {
            "category":"Banks & Credit Unions",
            "subcategory":"Financial Services",
            "type":"Services"
        }
    ],
    "sg:phone":"+64 9-629 0840",
    "sg:province":"Auckland",
    "sg:tags":[
        "personal",
        "-",
        "finance",
        "software"
    ],
    "sg:website":"http://www.sybiz.co.nz",
    "wof:name":"Sybiz New Zealand Ltd",
    "wof:placetype":"venue"
},
  "geometry": {"coordinates":[174.678009,-36.908173],"type":"Point"}
}