{
  "type": "Feature",
  "properties": {
    "iso:country":"NZ",
    "sg:address":"Unit 1B/492 Moorhouse Ave ",
    "sg:city":"Christchurch",
    "sg:classifiers":[
        {
            "category":"Retail",
            "subcategory":"Laundry & Dry Cleaning",
            "type":"Services"
        }
    ],
    "sg:phone":"+64 3-366 9991",
    "sg:province":"Canterbury",
    "sg:tags":[
        "product",
        "wool",
        "clothing",
        "fabric"
    ],
    "wof:name":"Lempriere N.Z. Limited",
    "wof:placetype":"venue"
},
  "geometry": {"coordinates":[-76.537834,37.605659],"type":"Point"}
}