{
  "type": "Feature",
  "properties": {
    "addr:full":"126 Wakanui Rd  Ashburton Canterbury",
    "addr:housenumber":"126",
    "addr:street":"Wakanui Rd",
    "iso:country":"NZ",
    "sg:address":"126 Wakanui Rd ",
    "sg:city":"Ashburton",
    "sg:classifiers":[
        {
            "category":"Banks & Credit Unions",
            "subcategory":"Financial Services",
            "type":"Services"
        }
    ],
    "sg:phone":"+64 3-307 8866",
    "sg:province":"Canterbury",
    "sg:tags":[
        "personal",
        "loan",
        "-",
        "finance",
        "mortgage"
    ],
    "wof:name":"Ashburton Mortgage Solutions",
    "wof:placetype":"venue"
},
  "geometry": {"coordinates":[171.76686100000001,-43.909218],"type":"Point"}
}