{
  "type": "Feature",
  "properties": {
    "addr:full":"86 Pitt St Auckland Central  Auckland Auckland",
    "addr:housenumber":"86",
    "addr:street":"Pitt St",
    "iso:country":"NZ",
    "sg:address":"86 Pitt St Auckland Central ",
    "sg:city":"Auckland",
    "sg:classifiers":[
        {
            "category":"Retail",
            "subcategory":"Repair Shop",
            "type":"Services"
        }
    ],
    "sg:phone":"+64 9-379 0029",
    "sg:province":"Auckland",
    "sg:tags":[
        "clothing",
        "fabric",
        "cleaning"
    ],
    "wof:name":"Alteration Station",
    "wof:placetype":"venue"
},
  "geometry": {"coordinates":[174.75912500000001,-36.85762],"type":"Point"}
}