{
  "type": "Feature",
  "properties": {
    "addr:full":"Main Rd  Katikati",
    "addr:street":"Main Rd",
    "iso:country":"NZ",
    "sg:address":"Main Rd ",
    "sg:city":"Katikati",
    "sg:orig_category":"Clothing And Fabric: Clothing: Menswear",
    "sg:phone":"+64 7-549 1606",
    "wof:name":"Mainstreet Menswear",
    "wof:placetype":"venue"
},
  "geometry": {"coordinates":[175.91807600000001,-37.551952],"type":"Point"}
}