{
  "type": "Feature",
  "properties": {
    "addr:full":"1/3 Brights Rd Waiuku  Auckland Auckland",
    "addr:housenumber":"1 / 3",
    "addr:street":"Brights Rd",
    "iso:country":"NZ",
    "sg:address":"1/3 Brights Rd Waiuku ",
    "sg:city":"Auckland",
    "sg:classifiers":[
        {
            "category":"Recreation",
            "subcategory":"Gun Range",
            "type":"Entertainment"
        }
    ],
    "sg:phone":"+64 9-534 7517",
    "sg:province":"Auckland",
    "sg:tags":[
        "sports",
        "sport",
        "-",
        "leisure",
        "gunsmith"
    ],
    "wof:name":"Howick Gun Shop",
    "wof:placetype":"venue"
},
  "geometry": {"coordinates":[174.73478700000001,-37.247608],"type":"Point"}
}