{
  "type": "Feature",
  "properties": {
    "addr:full":"PO Box 36401 Northcote  Auckland Auckland",
    "addr:housenumber":"po box",
    "addr:postcode":"36401",
    "iso:country":"NZ",
    "sg:address":"PO Box 36401 Northcote ",
    "sg:city":"Auckland",
    "sg:classifiers":[
        {
            "category":"Utilities",
            "subcategory":"Natural Gas",
            "type":"Services"
        }
    ],
    "sg:phone":"+64 9-410 8518",
    "sg:province":"Auckland",
    "sg:tags":[
        "detection",
        "specialist",
        "industrial",
        "machinery",
        "equipment"
    ],
    "wof:name":"Almaza Marketing Ltd",
    "wof:placetype":"venue"
},
  "geometry": {"coordinates":[174.747849,-36.801125],"type":"Point"}
}