{
  "type": "Feature",
  "properties": {
    "iso:country":"NZ",
    "sg:address":"Cnr Slater Street & Shirley Rd Shirley ",
    "sg:city":"Christchurch",
    "sg:orig_category":"Sports And Leisure: General: Halls",
    "sg:phone":"+64 3-385 1417",
    "sg:province":"Canterbury",
    "wof:name":"Shirley Community Centre",
    "wof:placetype":"venue"
},
  "geometry": {"coordinates":[172.66160600000001,-43.502869],"type":"Point"}
}