{
  "type": "Feature",
  "properties": {
    "addr:full":"Howick Village Shopping Centre  Auckland Auckland",
    "iso:country":"NZ",
    "sg:address":"Howick Village Shopping Centre ",
    "sg:city":"Auckland",
    "sg:orig_category":"Home And Garden: Accessories: Linen",
    "sg:phone":"+64 9-534 7794",
    "sg:province":"Auckland",
    "wof:name":"Bedroom Affair",
    "wof:placetype":"venue"
},
  "geometry": {"coordinates":[174.926514,-36.89994],"type":"Point"}
}