{
  "type": "Feature",
  "properties": {
    "addr:full":"Ayr St  Ohakune",
    "addr:street":"Ayr St",
    "iso:country":"NZ",
    "sg:address":"Ayr St ",
    "sg:city":"Ohakune",
    "sg:orig_category":"Sports And Leisure: Sports: Skiing",
    "sg:phone":"+64 6-385 8433",
    "wof:name":"Downtown Ski & Sport Ltd",
    "wof:placetype":"venue"
},
  "geometry": {"coordinates":[175.40126000000001,-39.417915],"type":"Point"}
}