{
  "type": "Feature",
  "properties": {
    "iso:country":"NZ",
    "sg:address":"148 Karori Rd Karori ",
    "sg:city":"Wellington",
    "sg:classifiers":[
        {
            "category":"Arena",
            "subcategory":"Sports Club",
            "type":"Entertainment"
        }
    ],
    "sg:phone":"+64 4-476 6680",
    "sg:province":"Wellington",
    "sg:tags":[
        "martial art",
        "-",
        "leisure",
        "sports"
    ],
    "wof:name":"Tai Chi Moving Meditation",
    "wof:placetype":"venue"
},
  "geometry": {"coordinates":[174.745667,-41.282238],"type":"Point"}
}