{
  "type": "Feature",
  "properties": {
    "addr:full":"23 Douglas St Waikiwi  Invercargill Southland",
    "addr:housenumber":"23",
    "addr:street":"Douglas St",
    "iso:country":"NZ",
    "sg:address":"23 Douglas St Waikiwi ",
    "sg:city":"Invercargill",
    "sg:classifiers":[
        {
            "category":"Retail",
            "subcategory":"Auto Repair",
            "type":"Services"
        }
    ],
    "sg:phone":"+64 3-215 9556",
    "sg:province":"Southland",
    "sg:tags":[
        "automotive",
        "panel",
        "servicing",
        "beater"
    ],
    "wof:name":"Chris Allan Panel Repairs",
    "wof:placetype":"venue"
},
  "geometry": {"coordinates":[168.34738200000001,-46.387737],"type":"Point"}
}