{
  "type": "Feature",
  "properties": {
    "addr:full":"PO Box 412 Paihia  Paihia Northland",
    "addr:housenumber":"po;paihia",
    "addr:street":"Box 412 Paihia",
    "iso:country":"NZ",
    "sg:address":"PO Box 412 Paihia ",
    "sg:city":"Paihia",
    "sg:orig_category":"Sports And Leisure: Sports: Aerial",
    "sg:phone":"+64 9-402 6744",
    "sg:province":"Northland",
    "wof:name":"Bay of Islands Skydive Centre",
    "wof:placetype":"venue"
},
  "geometry": {"coordinates":[174.09106399999999,-35.283691],"type":"Point"}
}