{
  "type": "Feature",
  "properties": {
    "addr:full":"PO Box 30674 Lower  Hutt Wellington",
    "addr:housenumber":"po box",
    "addr:postcode":"30674",
    "iso:country":"NZ",
    "sg:address":"PO Box 30674 Lower ",
    "sg:city":"Hutt",
    "sg:orig_category":"Home And Garden: Gardening: Services: Tree Services",
    "sg:phone":"+64 4-566 2800",
    "sg:province":"Wellington",
    "wof:name":"Tree Care Management Ltd",
    "wof:placetype":"venue"
},
  "geometry": {"coordinates":[174.90838600000001,-41.206631],"type":"Point"}
}