{
  "type": "Feature",
  "properties": {
    "iso:country":"NZ",
    "sg:address":"3 Shirley Rd Shirley ",
    "sg:city":"Christchurch",
    "sg:classifiers":[
        {
            "category":"Banks & Credit Unions",
            "subcategory":"Financial Services",
            "type":"Services"
        }
    ],
    "sg:phone":"+64 3-385 4854",
    "sg:province":"Canterbury",
    "sg:tags":[
        "lender",
        "money",
        "-",
        "finance",
        "personal"
    ],
    "wof:name":"Crester Credit Co",
    "wof:placetype":"venue"
},
  "geometry": {"coordinates":[172.661621,-43.502872],"type":"Point"}
}