{
  "type": "Feature",
  "properties": {
    "addr:full":"127 Hobson St Auckland Central  Auckland Auckland",
    "addr:housenumber":"127",
    "addr:street":"Hobson St",
    "iso:country":"NZ",
    "sg:address":"127 Hobson St Auckland Central ",
    "sg:city":"Auckland",
    "sg:classifiers":[
        {
            "category":"Manufacturing",
            "subcategory":"Food",
            "type":"Manufacturing & Wholesale Goods"
        }
    ],
    "sg:phone":"+64 9-379 9679",
    "sg:province":"Auckland",
    "sg:tags":[
        "drink",
        "-",
        "manufacturer"
    ],
    "wof:name":"Unisoy Ltd",
    "wof:placetype":"venue"
},
  "geometry": {"coordinates":[174.760437,-36.850384],"type":"Point"}
}