{
  "type": "Feature",
  "properties": {
    "addr:full":"266 Church St Onehunga  Auckland Auckland",
    "addr:housenumber":"266",
    "addr:street":"Church St",
    "iso:country":"NZ",
    "sg:address":"266 Church St Onehunga ",
    "sg:city":"Auckland",
    "sg:orig_category":"Industrial: Engineering: Engineers: Engineers - Heating",
    "sg:phone":"+64 9-634 1610",
    "sg:province":"Auckland",
    "sg:website":"http://www.combustioncontrol.com",
    "wof:name":"Combustion Control Ltd",
    "wof:placetype":"venue"
},
  "geometry": {"coordinates":[174.79212999999999,-36.922318],"type":"Point"}
}