{
  "type": "Feature",
  "properties": {
    "addr:full":"321 Maunganui Rd Mt  Maunganui Bay of Plenty",
    "addr:housenumber":"321",
    "addr:street":"Maunganui Rd;Maunganui",
    "iso:country":"NZ",
    "sg:address":"321 Maunganui Rd Mt ",
    "sg:city":"Maunganui",
    "sg:classifiers":[
        {
            "category":"Bars & Pubs",
            "subcategory":"Lounge",
            "type":"Food & Drink"
        }
    ],
    "sg:phone":"+64 7-575 9249",
    "sg:province":"Bay of Plenty",
    "sg:tags":[
        "baker",
        "-"
    ],
    "wof:name":"Ma Bakers Hot Bread Shop",
    "wof:placetype":"venue"
},
  "geometry": {"coordinates":[176.186768,-37.64275],"type":"Point"}
}