{
  "type": "Feature",
  "properties": {
    "iso:country":"NZ",
    "sg:address":"201 Eskdale Rd Birkenhead ",
    "sg:city":"Auckland",
    "sg:classifiers":[
        {
            "category":"Shopping",
            "subcategory":"Pets & Pet Supplies",
            "type":"Retail Goods"
        }
    ],
    "sg:phone":"+64 9-418 2352",
    "sg:province":"Auckland",
    "sg:tags":[
        "home",
        "garden"
    ],
    "wof:name":"Biosuppliers Live Insects",
    "wof:placetype":"venue"
},
  "geometry": {"coordinates":[174.734467,-36.818214],"type":"Point"}
}