{
  "type": "Feature",
  "properties": {
    "iso:country":"NZ",
    "sg:address":"Shop 6, Rotorua Central Mall (By The Warehouse) 1170, Amohau St ",
    "sg:city":"Rotorua",
    "sg:classifiers":[
        {
            "category":"Internet Cafe",
            "subcategory":"None",
            "type":"Food & Drink"
        }
    ],
    "sg:phone":"+64 7-348 4454",
    "sg:province":"Bay of Plenty",
    "sg:tags":[
        "wining",
        "dining"
    ],
    "wof:name":"Pl@net 4 Cyber C@fe",
    "wof:placetype":"venue"
},
  "geometry": {"coordinates":[176.24499499999999,-38.1418],"type":"Point"}
}