{
  "type": "Feature",
  "properties": {
    "addr:full":"cnr Norfolk & Ordsal Sts  Gore Southland",
    "addr:street":"Cnr;Sts",
    "iso:country":"NZ",
    "sg:address":"cnr Norfolk & Ordsal Sts ",
    "sg:city":"Gore",
    "sg:classifiers":[
        {
            "category":"Shopping",
            "subcategory":"Bicycles & Sporting Goods",
            "type":"Retail Goods"
        }
    ],
    "sg:phone":"+64 3-208 6653",
    "sg:province":"Southland",
    "sg:tags":[
        "cycle",
        "sport",
        "sale",
        "retailers",
        "cycles"
    ],
    "wof:name":"Murray Kawasaki",
    "wof:placetype":"venue"
},
  "geometry": {"coordinates":[-95.116547,35.530331],"type":"Point"}
}