{
  "type": "Feature",
  "properties": {
    "iso:country":"NZ",
    "sg:address":"1107 Karamu Rd Nth ",
    "sg:city":"Hastings",
    "sg:classifiers":[
        {
            "category":"Travel",
            "subcategory":"Hotels & Motels",
            "type":"Entertainment"
        }
    ],
    "sg:phone":"+64 6-876 5453",
    "sg:province":"Hawke's Bay",
    "sg:tags":[
        "holiday",
        "tourism",
        "accommodation"
    ],
    "wof:name":"Valdez Motor Lodge",
    "wof:placetype":"venue"
},
  "geometry": {"coordinates":[176.879517,-39.669403],"type":"Point"}
}