{
  "type": "Feature",
  "properties": {
    "addr:full":"91 St Georges Bay Rd Parnell  Auckland Auckland",
    "addr:housenumber":"91",
    "addr:street":"St Georges Bay Rd",
    "iso:country":"NZ",
    "sg:address":"91 St Georges Bay Rd Parnell ",
    "sg:city":"Auckland",
    "sg:classifiers":[
        {
            "category":"Restaurant",
            "type":"Food & Drink"
        }
    ],
    "sg:phone":"+64 9-303 9660",
    "sg:province":"Auckland",
    "sg:tags":[
        "wining",
        "dining"
    ],
    "sg:website":"http://www.cibo.co.nz",
    "wof:name":"Cibo Parnell",
    "wof:placetype":"venue"
},
  "geometry": {"coordinates":[174.78608700000001,-36.85479],"type":"Point"}
}