{
  "type": "Feature",
  "properties": {
    "iso:country":"NZ",
    "sg:address":"7/87 Albert St Auckland Central ",
    "sg:city":"Auckland",
    "sg:orig_category":"Industrial: Engineering: Engineers: Engineers - Consulting",
    "sg:phone":"+64 9-373 5880",
    "sg:province":"Auckland",
    "wof:name":"Peter Swan Ltd",
    "wof:placetype":"venue"
},
  "geometry": {"coordinates":[174.763504,-36.848206],"type":"Point"}
}