{
  "type": "Feature",
  "properties": {
    "iso:country":"NZ",
    "sg:address":"Capital E Civic Square ",
    "sg:city":"Wellington",
    "sg:orig_category":"Shopping: Retail Stores: Toys",
    "sg:phone":"+64 4-801 6987",
    "sg:province":"Wellington",
    "wof:name":"Hocus Pocus Toys",
    "wof:placetype":"venue"
},
  "geometry": {"coordinates":[174.777985,-41.289089],"type":"Point"}
}