{
  "type": "Feature",
  "properties": {
    "addr:full":"60 Sentinel Rd Herne Bay  Auckland Auckland",
    "addr:housenumber":"60",
    "addr:street":"Sentinel Rd",
    "iso:country":"NZ",
    "sg:address":"60 Sentinel Rd Herne Bay ",
    "sg:city":"Auckland",
    "sg:classifiers":[
        {
            "category":"Communications",
            "subcategory":"Film & Video Production",
            "type":"Services"
        }
    ],
    "sg:phone":"+64 9-360 1542",
    "sg:province":"Auckland",
    "sg:tags":[
        "broadcasting",
        "studio",
        "producer"
    ],
    "wof:name":"Flying Fish NZ Ltd",
    "wof:placetype":"venue"
},
  "geometry": {"coordinates":[174.73460399999999,-36.841457],"type":"Point"}
}