{
  "type": "Feature",
  "properties": {
    "iso:country":"NZ",
    "sg:address":"51 A Beacon Hill Rd Seatoun ",
    "sg:city":"Wellington",
    "sg:orig_category":"Home And Garden: Children: Child Related: Children'S Entertainment",
    "sg:phone":"+64 4-388 6795",
    "sg:province":"Wellington",
    "wof:name":"Merrykids (Kids Party Capsules Ltd)",
    "wof:placetype":"venue"
},
  "geometry": {"coordinates":[174.827942,-41.32375],"type":"Point"}
}