{
  "type": "Feature",
  "properties": {
    "iso:country":"NZ",
    "sg:address":"20-24 Pascoe St Tahunanui ",
    "sg:city":"Nelson",
    "sg:classifiers":[
        {
            "category":"Professional",
            "subcategory":"Detective & Security Services",
            "type":"Services"
        }
    ],
    "sg:phone":"+64 3-548 5297",
    "sg:province":"Nelson",
    "sg:tags":[
        "services",
        "automotive",
        "warrant",
        "fitness"
    ],
    "wof:name":"Vehicle Testing NZ Ltd",
    "wof:placetype":"venue"
},
  "geometry": {"coordinates":[173.24464399999999,-41.283855],"type":"Point"}
}