{
  "type": "Feature",
  "properties": {
    "addr:full":"141-145 Main St Upper  Hutt Wellington",
    "addr:housenumber":"141-145",
    "addr:street":"Main St",
    "iso:country":"NZ",
    "sg:address":"141-145 Main St Upper ",
    "sg:city":"Hutt",
    "sg:classifiers":[
        {
            "category":"Home & Garden",
            "subcategory":"Home Furnishings",
            "type":"Retail Goods"
        }
    ],
    "sg:phone":"+64 4-528 2129",
    "sg:province":"Wellington",
    "sg:tags":[
        "furniture/furnishings",
        "bedding",
        "bed"
    ],
    "sg:website":"http://www.hazelwoods.co.nz",
    "wof:name":"Hazelwoods",
    "wof:placetype":"venue"
},
  "geometry": {"coordinates":[175.07148699999999,-41.124191],"type":"Point"}
}