{
  "type": "Feature",
  "properties": {
    "addr:full":"Main Rd Makaraka  Gisborne Gisborne",
    "addr:street":"Main Rd",
    "iso:country":"NZ",
    "sg:address":"Main Rd Makaraka ",
    "sg:city":"Gisborne",
    "sg:classifiers":[
        {
            "category":"Utilities",
            "type":"Services"
        }
    ],
    "sg:phone":"+64 6-867 7135",
    "sg:province":"Gisborne",
    "sg:tags":[
        "industrial",
        "energy",
        "utilities",
        "coal",
        "wood",
        "coke"
    ],
    "wof:name":"Larsen Sawmilling Ltd",
    "wof:placetype":"venue"
},
  "geometry": {"coordinates":[177.975311,-38.648872],"type":"Point"}
}