{
  "type": "Feature",
  "properties": {
    "iso:country":"NZ",
    "sg:address":"60 Atkinson Ave Otahuhu ",
    "sg:city":"Auckland",
    "sg:classifiers":[
        {
            "category":"Retail",
            "subcategory":"Laundry & Dry Cleaning",
            "type":"Services"
        }
    ],
    "sg:phone":"+64 9-270 2093",
    "sg:province":"Auckland",
    "sg:tags":[
        "repair",
        "clothing",
        "fabric"
    ],
    "wof:name":"Ceda Dry Cleaners Ltd",
    "wof:placetype":"venue"
},
  "geometry": {"coordinates":[174.844666,-36.943306],"type":"Point"}
}