{
  "type": "Feature",
  "properties": {
    "addr:full":"284 Apirana Ave Glen Innes  Auckland Auckland",
    "addr:housenumber":"284",
    "addr:street":"Apirana Ave",
    "iso:country":"NZ",
    "sg:address":"284 Apirana Ave Glen Innes ",
    "sg:city":"Auckland",
    "sg:classifiers":[
        {
            "category":"Bars & Pubs",
            "subcategory":"Lounge",
            "type":"Food & Drink"
        }
    ],
    "sg:phone":"+64 9-528 3380",
    "sg:province":"Auckland",
    "sg:tags":[
        "-",
        "asian"
    ],
    "wof:name":"Lim Supermarket Centre",
    "wof:placetype":"venue"
},
  "geometry": {"coordinates":[174.85269199999999,-36.87183],"type":"Point"}
}