{
  "type": "Feature",
  "properties": {
    "addr:full":"176 Eastern Hutt Rd Taita Lower  Hutt Wellington",
    "addr:housenumber":"176",
    "addr:street":"Eastern Hutt Rd",
    "iso:country":"NZ",
    "sg:address":"176 Eastern Hutt Rd Taita Lower ",
    "sg:city":"Hutt",
    "sg:orig_category":"Farming: Services: Veterinarians",
    "sg:phone":"+64 4-567 4051",
    "sg:province":"Wellington",
    "wof:name":"Petvet Lower Hutt",
    "wof:placetype":"venue"
},
  "geometry": {"coordinates":[174.96603400000001,-41.175961],"type":"Point"}
}