{
  "type": "Feature",
  "properties": {
    "addr:full":"Crn Anson Ave & Fairfield Rd  Hamilton Waikato",
    "addr:housenumber":"crn",
    "addr:street":"Anson Ave & Fairfield Rd",
    "iso:country":"NZ",
    "sg:address":"Crn Anson Ave & Fairfield Rd ",
    "sg:city":"Hamilton",
    "sg:classifiers":[
        {
            "category":"Wholesale",
            "subcategory":"Medical Equipment & Supplies",
            "type":"Manufacturing & Wholesale Goods"
        }
    ],
    "sg:phone":"+64 7-855 7013",
    "sg:province":"Waikato",
    "sg:tags":[
        "health",
        "disability",
        "products",
        "beauty",
        "aid"
    ],
    "wof:name":"Conductive Education Early Intervention Unit",
    "wof:placetype":"venue"
},
  "geometry": {"coordinates":[175.281937,-37.765808],"type":"Point"}
}