{
  "type": "Feature",
  "properties": {
    "addr:full":"246c Hobson St Auckland Central  Auckland Auckland",
    "addr:housenumber":"246c",
    "addr:street":"Hobson St",
    "iso:country":"NZ",
    "sg:address":"246c Hobson St Auckland Central ",
    "sg:city":"Auckland",
    "sg:classifiers":[
        {
            "category":"Bars & Pubs",
            "subcategory":"Nightclub",
            "type":"Food & Drink"
        }
    ],
    "sg:phone":"+64 9-366 6162",
    "sg:province":"Auckland",
    "sg:tags":[
        "club",
        "night",
        "sport",
        "leisure",
        "entertainment"
    ],
    "wof:name":"CKK",
    "wof:placetype":"venue"
},
  "geometry": {"coordinates":[174.75848400000001,-36.854019],"type":"Point"}
}