{
  "type": "Feature",
  "properties": {
    "iso:country":"NZ",
    "sg:address":"Clarendon Tower cnr Worcester Blvd & Oxford Tce",
    "sg:city":"Christchurch",
    "sg:classifiers":[
        {
            "category":"Banks & Credit Unions",
            "subcategory":"Investment Brokerage",
            "type":"Services"
        }
    ],
    "sg:phone":"+64 3-379 2430",
    "sg:province":"Canterbury",
    "sg:tags":[
        "personal",
        "-",
        "finance"
    ],
    "wof:name":"Duncan Cotterill",
    "wof:placetype":"venue"
},
  "geometry": {"coordinates":[-71.864693,42.117592],"type":"Point"}
}