{
  "type": "Feature",
  "properties": {
    "addr:full":"676 Mt Wellington Highway Mt Wellington  Auckland Auckland",
    "addr:housenumber":"676",
    "addr:street":"Mt Wellington Highway",
    "iso:country":"NZ",
    "sg:address":"676 Mt Wellington Highway Mt Wellington ",
    "sg:city":"Auckland",
    "sg:classifiers":[
        {
            "category":"Restaurant",
            "type":"Food & Drink"
        }
    ],
    "sg:phone":"+64 9-270 2900",
    "sg:province":"Auckland",
    "sg:tags":[
        "wining",
        "dining"
    ],
    "sg:website":"http://www.yellowpages.co.nz/pages/211330120/dp50423.html",
    "wof:name":"Best Western Mount Richmond Lodge & Conference Centre",
    "wof:placetype":"venue"
},
  "geometry": {"coordinates":[174.84205600000001,-36.934902],"type":"Point"}
}