{
  "type": "Feature",
  "properties": {
    "addr:full":"680 B Queen Street, Levin to  Wellington Otago",
    "addr:housenumber":"680 b",
    "addr:street":"Queen Street;To",
    "iso:country":"NZ",
    "sg:address":"680 B Queen Street, Levin to ",
    "sg:city":"Wellington",
    "sg:orig_category":"Shopping: Gifts",
    "sg:phone":"+64 800 111 995",
    "sg:province":"Otago",
    "wof:name":"Choice Gift Baskets",
    "wof:placetype":"venue"
},
  "geometry": {"coordinates":[-85.910454,33.827946],"type":"Point"}
}