{
  "type": "Feature",
  "properties": {
    "addr:full":"40 Rockridge Ave Penrose  Auckland Auckland",
    "addr:housenumber":"40",
    "addr:street":"Rockridge Ave",
    "iso:country":"NZ",
    "sg:address":"40 Rockridge Ave Penrose ",
    "sg:city":"Auckland",
    "sg:classifiers":[
        {
            "category":"Food & Beverages",
            "subcategory":"Liquor & Beverages",
            "type":"Retail Goods"
        }
    ],
    "sg:phone":"+64 9-526 4870",
    "sg:province":"Auckland",
    "sg:tags":[
        "distributor",
        "drink"
    ],
    "wof:name":"Hancocks Wine & Spirit Merchants",
    "wof:placetype":"venue"
},
  "geometry": {"coordinates":[174.81253100000001,-36.915024],"type":"Point"}
}