{
  "type": "Feature",
  "properties": {
    "addr:full":"5 Jervois St  Dunedin Otago",
    "addr:housenumber":"5",
    "addr:street":"Jervois St",
    "iso:country":"NZ",
    "sg:address":"5 Jervois St ",
    "sg:city":"Dunedin",
    "sg:orig_category":"Automotive: Parts And Supplies: Turbochargers",
    "sg:phone":"+64 3-477 3148",
    "sg:province":"Otago",
    "wof:name":"Turbo Shop",
    "wof:placetype":"venue"
},
  "geometry": {"coordinates":[-82.784721,28.013355],"type":"Point"}
}