{
  "type": "Feature",
  "properties": {
    "addr:full":"36 Liverton Rd Belmont Lower  Hutt Wellington",
    "addr:housenumber":"36",
    "addr:street":"Liverton Rd Belmont",
    "iso:country":"NZ",
    "sg:address":"36 Liverton Rd Belmont Lower ",
    "sg:city":"Hutt",
    "sg:orig_category":"Shopping: Hobbies And Games: Handcrafts",
    "sg:phone":"+64 4-565 3808",
    "sg:province":"Wellington",
    "wof:name":"Automatic Gate Opening Systems",
    "wof:placetype":"venue"
},
  "geometry": {"coordinates":[174.92378199999999,-41.18861],"type":"Point"}
}