{
  "type": "Feature",
  "properties": {
    "addr:full":"PO Box 27118 Mt Roskill  Auckland Auckland",
    "addr:housenumber":"po box 27118",
    "iso:country":"NZ",
    "sg:address":"PO Box 27118 Mt Roskill ",
    "sg:city":"Auckland",
    "sg:classifiers":[
        {
            "category":"Arena",
            "subcategory":"Sports Club",
            "type":"Entertainment"
        }
    ],
    "sg:phone":"+64 9-834 9225",
    "sg:province":"Auckland",
    "sg:tags":[
        "-",
        "leisure",
        "sports"
    ],
    "wof:name":"New Zealand American Football Association New Zealand's Governing Body",
    "wof:placetype":"venue"
},
  "geometry": {"coordinates":[174.74276699999999,-36.905895],"type":"Point"}
}