{
  "type": "Feature",
  "properties": {
    "addr:full":"See Our Ad under 'Contractors General' Palmerston  Palmerston North Manawatu-Wanganui",
    "addr:street":"Palmerston",
    "iso:country":"NZ",
    "sg:address":"See Our Ad under 'Contractors General' Palmerston ",
    "sg:city":"Palmerston North",
    "sg:classifiers":[
        {
            "category":"Home & Garden",
            "subcategory":"Garden Supply",
            "type":"Retail Goods"
        }
    ],
    "sg:phone":"+64 6-368 5425",
    "sg:province":"Manawatu-Wanganui",
    "sg:tags":[
        "fencing",
        "outdoor",
        "contractor"
    ],
    "wof:name":"Heatherlea Contractors",
    "wof:placetype":"venue"
},
  "geometry": {"coordinates":[175.611481,-40.357422],"type":"Point"}
}