{
  "type": "Feature",
  "properties": {
    "addr:full":"169A Great South Rd Manurewa  Auckland Auckland",
    "addr:housenumber":"169a",
    "addr:street":"Great South Rd",
    "iso:country":"NZ",
    "sg:address":"169A Great South Rd Manurewa ",
    "sg:city":"Auckland",
    "sg:classifiers":[
        {
            "category":"Travel",
            "subcategory":"Hotels & Motels",
            "type":"Entertainment"
        }
    ],
    "sg:phone":"+64 9-268 2000",
    "sg:province":"Auckland",
    "sg:tags":[
        "tourism",
        "-",
        "rental",
        "accommodation"
    ],
    "wof:name":"The Rent Shop Ltd",
    "wof:placetype":"venue"
},
  "geometry": {"coordinates":[174.89527899999999,-37.020752],"type":"Point"}
}