{
  "type": "Feature",
  "properties": {
    "iso:country":"NZ",
    "sg:address":"PO Box 38412 Wellington Mail ",
    "sg:city":"Cntr",
    "sg:classifiers":[
        {
            "category":"Manufacturing",
            "subcategory":"Tools & Machinery",
            "type":"Manufacturing & Wholesale Goods"
        }
    ],
    "sg:phone":"+64 800 425 223",
    "sg:tags":[
        "equipment",
        "industrial",
        "label"
    ],
    "wof:name":"Label & Litho Limited",
    "wof:placetype":"venue"
},
  "geometry": {"coordinates":[-80.270012,26.643909],"type":"Point"}
}