{
  "type": "Feature",
  "properties": {
    "iso:country":"NZ",
    "sg:address":"7 A Euclid St New ",
    "sg:city":"Plymouth",
    "sg:classifiers":[
        {
            "category":"Home & Garden",
            "subcategory":"Building Materials",
            "type":"Retail Goods"
        }
    ],
    "sg:phone":"+64 6-753 3822",
    "sg:province":"Taranaki",
    "sg:tags":[
        "design",
        "fitting",
        "fittings",
        "kitchen"
    ],
    "wof:name":"Rhys Powell Joinery",
    "wof:placetype":"venue"
},
  "geometry": {"coordinates":[-70.70890799999999,41.907364],"type":"Point"}
}