{
  "type": "Feature",
  "properties": {
    "iso:country":"NZ",
    "sg:address":"10 Boundary Rd ",
    "sg:city":"Hamilton",
    "sg:classifiers":[
        {
            "category":"Banks & Credit Unions",
            "subcategory":"Financial Services",
            "type":"Services"
        }
    ],
    "sg:phone":"+64 800 446 796",
    "sg:province":"Waikato",
    "sg:tags":[
        "personal",
        "loan",
        "-",
        "finance",
        "mortgage"
    ],
    "sg:website":"http://www.in-sync.co.nz",
    "wof:name":"In-Sync Trustees Ltd",
    "wof:placetype":"venue"
},
  "geometry": {"coordinates":[-77.71453099999999,39.982712],"type":"Point"}
}