{
  "type": "Feature",
  "properties": {
    "addr:full":"11 Akiraho St Mt Eden  Auckland Auckland",
    "addr:housenumber":"11",
    "addr:street":"Akiraho St",
    "iso:country":"NZ",
    "sg:address":"11 Akiraho St Mt Eden ",
    "sg:city":"Auckland",
    "sg:classifiers":[
        {
            "category":"Shopping",
            "subcategory":"Crafts & Fabrics",
            "type":"Retail Goods"
        }
    ],
    "sg:phone":"+64 9-638 6820",
    "sg:province":"Auckland",
    "sg:tags":[
        "leather",
        "clothing",
        "suede"
    ],
    "wof:name":"Taurus Leather Company",
    "wof:placetype":"venue"
},
  "geometry": {"coordinates":[174.75857500000001,-36.868507],"type":"Point"}
}