{
  "type": "Feature",
  "properties": {
    "iso:country":"NZ",
    "sg:address":"21 a Brownston St ",
    "sg:city":"Wanaka",
    "sg:classifiers":[
        {
            "category":"Banks & Credit Unions",
            "subcategory":"Investment Brokerage",
            "type":"Services"
        }
    ],
    "sg:phone":"+64 3-443 4405",
    "sg:province":"Otago",
    "sg:tags":[
        "personal",
        "accountant",
        "chartered",
        "-",
        "finance"
    ],
    "wof:name":"Accountancy At Altitude Ltd",
    "wof:placetype":"venue"
},
  "geometry": {"coordinates":[169.13885500000001,-44.695305],"type":"Point"}
}