{
  "type": "Feature",
  "properties": {
    "addr:full":"11 Margaret Rd Raumati Beach  Paraparaumu Wellington",
    "addr:housenumber":"11",
    "addr:street":"Margaret Rd",
    "iso:country":"NZ",
    "sg:address":"11 Margaret Rd Raumati Beach ",
    "sg:city":"Paraparaumu",
    "sg:orig_category":"Industrial: Equipment And Machinery: Specialist Equipment: Machinery: Sewing Machines",
    "sg:phone":"+64 4-902 9550",
    "sg:province":"Wellington",
    "wof:name":"Bernina Sewing Centre",
    "wof:placetype":"venue"
},
  "geometry": {"coordinates":[174.981506,-40.919636],"type":"Point"}
}