{
  "type": "Feature",
  "properties": {
    "iso:country":"NZ",
    "sg:address":"R D 2RD ",
    "sg:city":"Wyndham",
    "sg:orig_category":"Farming: Services: Livestock Related: Sheep Dipping",
    "sg:phone":"+64 3-206 4213",
    "wof:name":"AA Dipping & Spraying",
    "wof:placetype":"venue"
},
  "geometry": {"coordinates":[-77.613281,37.698261],"type":"Point"}
}