{
  "type": "Feature",
  "properties": {
    "addr:full":"47 George St Newmarket  Auckland Auckland",
    "addr:housenumber":"47",
    "addr:street":"George St",
    "iso:country":"NZ",
    "sg:address":"47 George St Newmarket ",
    "sg:city":"Auckland",
    "sg:orig_category":"Industrial: Engineering: Engineers",
    "sg:phone":"+64 9-379 1200",
    "sg:province":"Auckland",
    "sg:website":"http://www.meritec.org",
    "wof:name":"Meritec Ltd",
    "wof:placetype":"venue"
},
  "geometry": {"coordinates":[174.778976,-36.863823],"type":"Point"}
}