{
  "type": "Feature",
  "properties": {
    "iso:country":"NZ",
    "sg:address":"Bush Rd Mosgiel ",
    "sg:city":"Dunedin",
    "sg:classifiers":[
        {
            "category":"Retail",
            "subcategory":"Laundry & Dry Cleaning",
            "type":"Services"
        }
    ],
    "sg:phone":"+64 3-489 4408",
    "sg:province":"Otago",
    "sg:tags":[
        "product",
        "wool",
        "clothing",
        "fabric"
    ],
    "wof:name":"Taieri Wool & Skin Co Ltd",
    "wof:placetype":"venue"
},
  "geometry": {"coordinates":[170.347305,-45.874001],"type":"Point"}
}