{
  "type": "Feature",
  "properties": {
    "iso:country":"NZ",
    "sg:address":"10 B Catkin Cre Papatoetoe ",
    "sg:city":"Auckland",
    "sg:classifiers":[
        {
            "category":"Education",
            "subcategory":"Special Training",
            "type":"Public Place"
        }
    ],
    "sg:phone":"+64 9-278 2287",
    "sg:province":"Auckland",
    "sg:tags":[
        "driver"
    ],
    "wof:name":"Auckland Defensive Driving Academy",
    "wof:placetype":"venue"
},
  "geometry": {"coordinates":[174.835037,-36.985046],"type":"Point"}
}