{
  "type": "Feature",
  "properties": {
    "addr:full":"124 D Felton Mathew Ave St Johns  Auckland Auckland",
    "addr:housenumber":"124 d",
    "addr:street":"Felton Mathew Ave",
    "iso:country":"NZ",
    "sg:address":"124 D Felton Mathew Ave St Johns ",
    "sg:city":"Auckland",
    "sg:classifiers":[
        {
            "category":"Home & Garden",
            "subcategory":"Building Materials",
            "type":"Retail Goods"
        }
    ],
    "sg:phone":"+64 9-578 0391",
    "sg:province":"Auckland",
    "sg:tags":[
        "door",
        "fitting",
        "fittings"
    ],
    "wof:name":"J M Napier Joinery Ltd",
    "wof:placetype":"venue"
},
  "geometry": {"coordinates":[174.85179099999999,-36.878399],"type":"Point"}
}