{
  "type": "Feature",
  "properties": {
    "iso:country":"NZ",
    "sg:address":"PO Box 15648 New Lynn ",
    "sg:city":"Auckland",
    "sg:orig_category":"Industrial: Services: Marking And Coding",
    "sg:phone":"+64 9-826 3053",
    "sg:province":"Auckland",
    "wof:name":"Metromatics Ltd",
    "wof:placetype":"venue"
},
  "geometry": {"coordinates":[174.68309,-36.920143],"type":"Point"}
}