{
  "type": "Feature",
  "properties": {
    "addr:full":"85 North Rd  Invercargill Southland",
    "addr:housenumber":"85",
    "addr:street":"North Rd",
    "iso:country":"NZ",
    "sg:address":"85 North Rd ",
    "sg:city":"Invercargill",
    "sg:classifiers":[
        {
            "category":"Bars & Pubs",
            "subcategory":"Lounge",
            "type":"Food & Drink"
        }
    ],
    "sg:phone":"+64 3-215 7751",
    "sg:province":"Southland",
    "sg:tags":[
        "baker",
        "-"
    ],
    "wof:name":"Coupland's Bakery",
    "wof:placetype":"venue"
},
  "geometry": {"coordinates":[168.347061,-46.385918],"type":"Point"}
}