{
  "type": "Feature",
  "properties": {
    "iso:country":"NZ",
    "sg:address":"Sheffield St Riverlands ",
    "sg:city":"Blenheim",
    "sg:classifiers":[
        {
            "category":"Manufacturing",
            "subcategory":"Food",
            "type":"Manufacturing & Wholesale Goods"
        }
    ],
    "sg:phone":"+64 3-577 6919",
    "sg:province":"Marlborough",
    "sg:tags":[
        "processing",
        "drink"
    ],
    "wof:name":"Springbrook Processing",
    "wof:placetype":"venue"
},
  "geometry": {"coordinates":[174.00559999999999,-41.528778],"type":"Point"}
}