{
  "type": "Feature",
  "properties": {
    "iso:country":"NZ",
    "sg:address":"9 Fraser St ",
    "sg:city":"Whangarei",
    "sg:orig_category":"Industrial: Abrasives: Water Blasting",
    "sg:phone":"+64 9-438 5359",
    "sg:province":"Northland",
    "wof:name":"B S Industries",
    "wof:placetype":"venue"
},
  "geometry": {"coordinates":[174.345444,-35.741291],"type":"Point"}
}