{
  "type": "Feature",
  "properties": {
    "iso:country":"NZ",
    "sg:address":"411 High St Lower ",
    "sg:city":"Hutt",
    "sg:classifiers":[
        {
            "category":"Wholesale",
            "subcategory":"Hardware",
            "type":"Manufacturing & Wholesale Goods"
        }
    ],
    "sg:phone":"+64 4-569 4947",
    "sg:province":"Wellington",
    "sg:tags":[
        "gardening",
        "garden",
        "chainsaw",
        "products",
        "brush",
        "home",
        "cutter"
    ],
    "wof:name":"Aladdin Lawnmowers & Chainsaws",
    "wof:placetype":"venue"
},
  "geometry": {"coordinates":[174.909775,-41.205849],"type":"Point"}
}