{
  "type": "Feature",
  "properties": {
    "iso:country":"NZ",
    "sg:address":"Unit 1 61 Maleme St Greerton ",
    "sg:city":"Tauranga",
    "sg:orig_category":"Automotive: Parts And Supplies: Wheels",
    "sg:phone":"+64 7-541 0470",
    "sg:province":"Bay of Plenty",
    "wof:name":"Performance Wheels",
    "wof:placetype":"venue"
},
  "geometry": {"coordinates":[176.135178,-37.736111],"type":"Point"}
}