{
  "type": "Feature",
  "properties": {
    "iso:country":"NZ",
    "sg:address":"49 Sharp Rd Matakana ",
    "sg:city":"Warkworth",
    "sg:classifiers":[
        {
            "category":"Restaurant",
            "type":"Food & Drink"
        }
    ],
    "sg:phone":"+64 9-422 7915",
    "sg:province":"Auckland",
    "sg:tags":[
        "wining",
        "dining"
    ],
    "sg:website":"http://www.heronsflight.co.nz",
    "wof:name":"Heron's Flight",
    "wof:placetype":"venue"
},
  "geometry": {"coordinates":[174.703613,-36.377285],"type":"Point"}
}