{
  "type": "Feature",
  "properties": {
    "iso:country":"NZ",
    "sg:address":"62 A Hillside Rd Glenfield ",
    "sg:city":"Auckland",
    "sg:classifiers":[
        {
            "category":"Professional",
            "subcategory":"Business Services",
            "type":"Services"
        }
    ],
    "sg:phone":"+64 9-444 4420",
    "sg:province":"Auckland",
    "sg:tags":[
        "sport",
        "music",
        "leisure"
    ],
    "wof:name":"Computer Music Systems Ltd",
    "wof:placetype":"venue"
},
  "geometry": {"coordinates":[174.73571799999999,-36.77634],"type":"Point"}
}