{
  "type": "Feature",
  "properties": {
    "iso:country":"NZ",
    "sg:address":"2 Manadon St New Plymouth PO Box ",
    "sg:city":"5079",
    "sg:classifiers":[
        {
            "category":"Farming",
            "subcategory":"Fish & Marine Products",
            "type":"Manufacturing & Wholesale Goods"
        }
    ],
    "sg:phone":"+64 6-751 1101",
    "sg:province":"Wellington",
    "sg:tags":[
        "health",
        "beauty"
    ],
    "sg:website":"http://www.emergencycare.co.nz",
    "wof:name":"Emergency Care Consultants (NZ) Ltd",
    "wof:placetype":"venue"
},
  "geometry": {"coordinates":[-116.81971,43.972191],"type":"Point"}
}