{
  "type": "Feature",
  "properties": {
    "iso:country":"NZ",
    "sg:address":"Dent St ",
    "sg:city":"Whangarei",
    "sg:orig_category":"Automotive: Parts And Supplies: Windscreens",
    "sg:phone":"+64 9-438 0618",
    "sg:province":"Northland",
    "wof:name":"Glass North Ltd",
    "wof:placetype":"venue"
},
  "geometry": {"coordinates":[174.321609,-35.722321],"type":"Point"}
}