{
  "type": "Feature",
  "properties": {
    "addr:full":"606 A Rosebank Rd Avondale  Auckland Auckland",
    "addr:housenumber":"606 a",
    "addr:street":"Rosebank Rd",
    "iso:country":"NZ",
    "sg:address":"606 A Rosebank Rd Avondale ",
    "sg:city":"Auckland",
    "sg:orig_category":"Transport: Boats And Marine: Products: Marine Engines",
    "sg:phone":"+64 9-828 3524",
    "sg:province":"Auckland",
    "wof:name":"Moon Engines Ltd",
    "wof:placetype":"venue"
},
  "geometry": {"coordinates":[174.68568400000001,-36.888668],"type":"Point"}
}