{
  "type": "Feature",
  "properties": {
    "addr:full":"Milne Dve  Paraparaumu Wellington",
    "iso:country":"NZ",
    "sg:address":"Milne Dve ",
    "sg:city":"Paraparaumu",
    "sg:classifiers":[
        {
            "category":"Education",
            "subcategory":"Special Training",
            "type":"Public Place"
        }
    ],
    "sg:phone":"+64 4-298 9554",
    "sg:province":"Wellington",
    "sg:tags":[
        "charter",
        "shopping",
        "dive",
        "tuition",
        "water",
        "sports",
        "retailers",
        "sport"
    ],
    "wof:name":"Kapiti Dive Centre",
    "wof:placetype":"venue"
},
  "geometry": {"coordinates":[175.00799599999999,-40.910461],"type":"Point"}
}