{
  "type": "Feature",
  "properties": {
    "iso:country":"NZ",
    "sg:address":"PO Box 179 ",
    "sg:city":"Matamata",
    "sg:orig_category":"Farming: Machinery: Tractors",
    "sg:phone":"+64 7-888 7181",
    "sg:province":"Waikato",
    "wof:name":"Matamata Tractor Services",
    "wof:placetype":"venue"
},
  "geometry": {"coordinates":[175.77354399999999,-37.811764],"type":"Point"}
}