{
  "type": "Feature",
  "properties": {
    "iso:country":"NZ",
    "sg:address":"1 Inglis St ",
    "sg:city":"Havelock",
    "sg:orig_category":"Industrial: Engineering: Engineers: Engineers - General",
    "sg:phone":"+64 3-574 2849",
    "wof:name":"A1 Engineering",
    "wof:placetype":"venue"
},
  "geometry": {"coordinates":[-94.701714,42.834831],"type":"Point"}
}