{
  "type": "Feature",
  "properties": {
    "addr:full":"Beach Road Ext  Opotiki Auckland",
    "addr:street":"Beach Road Ext",
    "iso:country":"NZ",
    "sg:address":"Beach Road Ext ",
    "sg:city":"Opotiki",
    "sg:classifiers":[
        {
            "category":"Utilities",
            "subcategory":"Sewage",
            "type":"Services"
        }
    ],
    "sg:phone":"+64 274 843 409",
    "sg:province":"Auckland",
    "sg:tags":[
        "home",
        "tank",
        "garden",
        "septic"
    ],
    "wof:name":"Opotiki Septic Tank Cleaners Ltd",
    "wof:placetype":"venue"
},
  "geometry": {"coordinates":[177.31298799999999,-37.999161],"type":"Point"}
}