{
  "type": "Feature",
  "properties": {
    "addr:full":"Kokatahi Rd  Hokitika West Coast",
    "addr:street":"Kokatahi Rd",
    "iso:country":"NZ",
    "sg:address":"Kokatahi Rd ",
    "sg:city":"Hokitika",
    "sg:classifiers":[
        {
            "category":"Building & Trades",
            "subcategory":"Construction",
            "type":"Services"
        }
    ],
    "sg:phone":"+64 3-755 7840",
    "sg:province":"West Coast",
    "sg:tags":[
        "home",
        "garden",
        "related",
        "plasterer"
    ],
    "wof:name":"Pete Green",
    "wof:placetype":"venue"
},
  "geometry": {"coordinates":[170.97221400000001,-42.719032],"type":"Point"}
}