{
  "type": "Feature",
  "properties": {
    "addr:full":"15 Cashew St Grenada North  Wellington Wellington",
    "addr:housenumber":"15",
    "addr:street":"Cashew St",
    "iso:country":"NZ",
    "sg:address":"15 Cashew St Grenada North ",
    "sg:city":"Wellington",
    "sg:classifiers":[
        {
            "category":"Manufacturing",
            "subcategory":"Food",
            "type":"Manufacturing & Wholesale Goods"
        }
    ],
    "sg:phone":"+64 4-232 4798",
    "sg:province":"Wellington",
    "sg:tags":[
        "drink",
        "-",
        "manufacturer"
    ],
    "wof:name":"Bells Continental Smallgoods (1997)",
    "wof:placetype":"venue"
},
  "geometry": {"coordinates":[174.83952300000001,-41.181591],"type":"Point"}
}