{
  "type": "Feature",
  "properties": {
    "addr:full":"State Highway 5 PO Box 122  Reporoa",
    "addr:housenumber":"box 122",
    "addr:street":"State Highway 5 Po;Reporoa",
    "iso:country":"NZ",
    "sg:address":"State Highway 5 PO Box 122 ",
    "sg:city":"Reporoa",
    "sg:orig_category":"Automotive: General Services: Service Stations",
    "sg:phone":"+64 7-333 8060",
    "wof:name":"Shell Reporoa",
    "wof:placetype":"venue"
},
  "geometry": {"coordinates":[176.34466599999999,-38.433556],"type":"Point"}
}