{
  "type": "Feature",
  "properties": {
    "iso:country":"NZ",
    "sg:address":"58 Carters Rd Allenton ",
    "sg:city":"Ashburton",
    "sg:classifiers":[
        {
            "category":"Personal",
            "type":"Services"
        }
    ],
    "sg:phone":"+64 3-308 7225",
    "sg:province":"Canterbury",
    "sg:tags":[
        "celebrant",
        "arrangements",
        "marriage",
        "wedding"
    ],
    "wof:name":"Carol Gunn Celebrant Services",
    "wof:placetype":"venue"
},
  "geometry": {"coordinates":[171.746094,-43.887348],"type":"Point"}
}