{
  "type": "Feature",
  "properties": {
    "iso:country":"NZ",
    "sg:address":"76 Edgeware Rd St Albans ",
    "sg:city":"Christchurch",
    "sg:orig_category":"Transport: Transportation: Postal Services",
    "sg:phone":"+64 3-366 1846",
    "sg:province":"Canterbury",
    "wof:name":"Kiwi Bookshop",
    "wof:placetype":"venue"
},
  "geometry": {"coordinates":[172.63618500000001,-43.511974],"type":"Point"}
}