{
  "type": "Feature",
  "properties": {
    "addr:full":"Level 1 105 Ponsonby Rd Ponsonby  Auckland Auckland",
    "addr:housenumber":"level 1",
    "addr:postcode":"105",
    "addr:street":"Ponsonby Rd",
    "iso:country":"NZ",
    "sg:address":"Level 1 105 Ponsonby Rd Ponsonby ",
    "sg:city":"Auckland",
    "sg:classifiers":[
        {
            "category":"Communications",
            "subcategory":"Radio Station",
            "type":"Services"
        }
    ],
    "sg:phone":"+64 9-360 4495",
    "sg:province":"Auckland",
    "sg:tags":[
        "broadcasting"
    ],
    "wof:name":"George FM",
    "wof:placetype":"venue"
},
  "geometry": {"coordinates":[174.74681100000001,-36.85611],"type":"Point"}
}