{
  "type": "Feature",
  "properties": {
    "addr:full":"186 Gladstone Rd  Gisborne Gisborne",
    "addr:housenumber":"186",
    "addr:street":"Gladstone Rd",
    "iso:country":"NZ",
    "sg:address":"186 Gladstone Rd ",
    "sg:city":"Gisborne",
    "sg:classifiers":[
        {
            "category":"Sports & Exercise",
            "subcategory":"Ski Resort",
            "type":"Entertainment"
        }
    ],
    "sg:phone":"+64 6-867 6455",
    "sg:province":"Gisborne",
    "sg:tags":[
        "hobbies",
        "photographic",
        "leisure",
        "developing"
    ],
    "wof:name":"Camera Centre",
    "wof:placetype":"venue"
},
  "geometry": {"coordinates":[178.02397199999999,-38.665142],"type":"Point"}
}