{
  "type": "Feature",
  "properties": {
    "iso:country":"NZ",
    "sg:address":"345 Thames Hwy Orana Park ",
    "sg:city":"Oamaru",
    "sg:orig_category":"Industrial: Instruments",
    "sg:phone":"+64 3-437 2548",
    "sg:province":"Otago",
    "wof:name":"Iconix NZ Ltd",
    "wof:placetype":"venue"
},
  "geometry": {"coordinates":[170.97695899999999,-45.086777],"type":"Point"}
}