{
  "type": "Feature",
  "properties": {
    "addr:full":"134 Victoria St W Auckland Central  Auckland Auckland",
    "addr:housenumber":"134",
    "addr:street":"Victoria St W",
    "iso:country":"NZ",
    "sg:address":"134 Victoria St W Auckland Central ",
    "sg:city":"Auckland",
    "sg:classifiers":[
        {
            "category":"Shopping",
            "type":"Retail Goods"
        }
    ],
    "sg:phone":"+64 9-366 6044",
    "sg:province":"Auckland",
    "sg:tags":[
        "store"
    ],
    "sg:website":"http://www.passionflowers.co.nz",
    "wof:name":"Passion Flowers Ltd",
    "wof:placetype":"venue"
},
  "geometry": {"coordinates":[174.759872,-36.847797],"type":"Point"}
}