{
  "type": "Feature",
  "properties": {
    "iso:country":"NZ",
    "sg:address":"PO Box 44266 Point Chevalier ",
    "sg:city":"Auckland",
    "sg:orig_category":"Industrial: Energy And Utilities: Gas",
    "sg:phone":"+64 9-815 6483",
    "sg:province":"Auckland",
    "wof:name":"Simply Gas",
    "wof:placetype":"venue"
},
  "geometry": {"coordinates":[174.71022,-36.861404],"type":"Point"}
}