{
  "type": "Feature",
  "properties": {
    "iso:country":"NZ",
    "sg:address":"80 St John St ",
    "sg:city":"Tauranga",
    "sg:classifiers":[
        {
            "category":"Sports & Exercise",
            "subcategory":"Sports Center",
            "type":"Entertainment"
        }
    ],
    "sg:phone":"+64 7-579 4377",
    "sg:province":"Bay of Plenty",
    "sg:tags":[
        "health",
        "beauty",
        "fitness"
    ],
    "wof:name":"City Gym",
    "wof:placetype":"venue"
},
  "geometry": {"coordinates":[176.158615,-37.697472],"type":"Point"}
}