{
  "type": "Feature",
  "properties": {
    "addr:full":"61 Port Rd  Whangarei Northland",
    "addr:housenumber":"61",
    "addr:street":"Port Rd",
    "iso:country":"NZ",
    "sg:address":"61 Port Rd ",
    "sg:city":"Whangarei",
    "sg:classifiers":[
        {
            "category":"Fast Food",
            "type":"Food & Drink"
        }
    ],
    "sg:phone":"+64 9-438 3749",
    "sg:province":"Northland",
    "sg:tags":[
        "wining",
        "dining",
        "takeaway"
    ],
    "wof:name":"Okara Lunch Bar",
    "wof:placetype":"venue"
},
  "geometry": {"coordinates":[174.32936100000001,-35.729939],"type":"Point"}
}