{
  "type": "Feature",
  "properties": {
    "addr:full":"PO Box 5  Kaikoura",
    "addr:housenumber":"po;5",
    "addr:street":"Box",
    "iso:country":"NZ",
    "sg:address":"PO Box 5 ",
    "sg:city":"Kaikoura",
    "sg:classifiers":[
        {
            "category":"Organizations",
            "subcategory":"Labor Organization",
            "type":"Services"
        }
    ],
    "sg:phone":"+64 3-319 6609",
    "sg:tags":[
        "services",
        "helicopter",
        "travel",
        "tourism"
    ],
    "wof:name":"Kaikoura Helicopters Ltd",
    "wof:placetype":"venue"
},
  "geometry": {"coordinates":[173.68138099999999,-42.404366],"type":"Point"}
}