{
  "type": "Feature",
  "properties": {
    "addr:full":"39 Graham Ave Te Atatu Peninsula  Auckland Auckland",
    "addr:housenumber":"39",
    "addr:street":"Graham Ave",
    "iso:country":"NZ",
    "sg:address":"39 Graham Ave Te Atatu Peninsula ",
    "sg:city":"Auckland",
    "sg:orig_category":"Home And Garden: General: Handyman'S Services",
    "sg:phone":"+64 9-834 2017",
    "sg:province":"Auckland",
    "wof:name":"Repair Man",
    "wof:placetype":"venue"
},
  "geometry": {"coordinates":[174.65029899999999,-36.845467],"type":"Point"}
}