{
  "type": "Feature",
  "properties": {
    "addr:full":"143 Line Rd Glen Innes  Auckland Auckland",
    "addr:housenumber":"143",
    "addr:street":"Line Rd",
    "iso:country":"NZ",
    "sg:address":"143 Line Rd Glen Innes ",
    "sg:city":"Auckland",
    "sg:orig_category":"Clothing And Fabric: Fabric: Drapers",
    "sg:phone":"+64 9-528 4358",
    "sg:province":"Auckland",
    "wof:name":"Glen Innes Drapery",
    "wof:placetype":"venue"
},
  "geometry": {"coordinates":[174.856369,-36.878937],"type":"Point"}
}