{
  "type": "Feature",
  "properties": {
    "addr:full":"1st Floor 122 Maunganui Rd Mt  Maunganui Bay of Plenty",
    "addr:housenumber":"122",
    "addr:street":"Maunganui Rd;Maunganui",
    "iso:country":"NZ",
    "sg:address":"1st Floor 122 Maunganui Rd Mt ",
    "sg:city":"Maunganui",
    "sg:classifiers":[
        {
            "category":"Retail",
            "subcategory":"Repair Shop",
            "type":"Services"
        }
    ],
    "sg:phone":"+64 7-575 9931",
    "sg:province":"Bay of Plenty",
    "sg:tags":[
        "clothing",
        "fabric",
        "cleaning"
    ],
    "wof:name":"Cut & Tuck",
    "wof:placetype":"venue"
},
  "geometry": {"coordinates":[176.18284600000001,-37.637291],"type":"Point"}
}