{
  "type": "Feature",
  "properties": {
    "iso:country":"NZ",
    "sg:address":"State Highway 1 Riverlands ",
    "sg:city":"Blenheim",
    "sg:orig_category":"Sports And Leisure: Sports: Golf: Golf Courses",
    "sg:phone":"+64 3-577 7181",
    "sg:province":"Marlborough",
    "wof:name":"Golfer's World Driving Range",
    "wof:placetype":"venue"
},
  "geometry": {"coordinates":[174.014725,-41.529175],"type":"Point"}
}