{
  "type": "Feature",
  "properties": {
    "iso:country":"NZ",
    "sg:address":"5/1 Settlers Cre Woolston ",
    "sg:city":"Christchurch",
    "sg:orig_category":"Shopping: Dispensing: Dispensing Machines",
    "sg:phone":"+64 3-384 4487",
    "sg:province":"Canterbury",
    "wof:name":"Tasman Suppliers Ltd",
    "wof:placetype":"venue"
},
  "geometry": {"coordinates":[172.677719,-43.54937],"type":"Point"}
}