{
  "type": "Feature",
  "properties": {
    "iso:country":"NZ",
    "sg:address":"5 Cook St Howick ",
    "sg:city":"Auckland",
    "sg:classifiers":[
        {
            "category":"Arts & Performance",
            "subcategory":"Art Gallery",
            "type":"Entertainment"
        }
    ],
    "sg:phone":"+64 9-538 0102",
    "sg:province":"Auckland",
    "sg:tags":[
        "arts",
        "sport",
        "leisure"
    ],
    "sg:website":"http://www.montereyartgallery.co.nz",
    "wof:name":"Monterey Art Gallery",
    "wof:placetype":"venue"
},
  "geometry": {"coordinates":[174.933243,-36.895584],"type":"Point"}
}