{
  "type": "Feature",
  "properties": {
    "iso:country":"NZ",
    "sg:address":"Broadway ",
    "sg:city":"Stratford",
    "sg:orig_category":"Home And Garden: Accessories: Hardware",
    "sg:phone":"+64 6-765 6048",
    "sg:province":"Manawatu-Wanganui",
    "wof:name":"Mitre 10",
    "wof:placetype":"venue"
},
  "geometry": {"coordinates":[-73.129524,41.192841],"type":"Point"}
}