{
  "type": "Feature",
  "properties": {
    "addr:full":"94 Seddon St  Pukekohe Auckland",
    "addr:housenumber":"94",
    "addr:street":"Seddon St",
    "iso:country":"NZ",
    "sg:address":"94 Seddon St ",
    "sg:city":"Pukekohe",
    "sg:orig_category":"Education And Training: General: Schools",
    "sg:phone":"+64 9-238 7745",
    "sg:province":"Auckland",
    "wof:name":"St Joseph's School",
    "wof:placetype":"venue"
},
  "geometry": {"coordinates":[174.930252,-37.195728],"type":"Point"}
}