{
  "type": "Feature",
  "properties": {
    "addr:full":"11 Weymouth Rd Manurewa  Auckland Auckland",
    "addr:housenumber":"11",
    "addr:street":"Weymouth Rd",
    "iso:country":"NZ",
    "sg:address":"11 Weymouth Rd Manurewa ",
    "sg:city":"Auckland",
    "sg:classifiers":[
        {
            "category":"Communications",
            "subcategory":"Film & Video Production",
            "type":"Services"
        }
    ],
    "sg:phone":"+64 9-267 3660",
    "sg:province":"Auckland",
    "sg:tags":[
        "sport",
        "leisure",
        "library",
        "entertainment"
    ],
    "wof:name":"Video Ezy",
    "wof:placetype":"venue"
},
  "geometry": {"coordinates":[174.89726300000001,-37.023987],"type":"Point"}
}