{
  "type": "Feature",
  "properties": {
    "addr:full":"24 Tarewa Road  Whangarei Northland",
    "addr:housenumber":"24",
    "addr:street":"Tarewa Road",
    "iso:country":"NZ",
    "sg:address":"24 Tarewa Road ",
    "sg:city":"Whangarei",
    "sg:classifiers":[
        {
            "category":"Retail",
            "subcategory":"Auto Repair",
            "type":"Services"
        }
    ],
    "sg:phone":"+64 9-438 6698",
    "sg:province":"Northland",
    "sg:tags":[
        "automotive",
        "panel",
        "servicing",
        "beater"
    ],
    "wof:name":"Auto Craft Panelbeaters",
    "wof:placetype":"venue"
},
  "geometry": {"coordinates":[174.31596400000001,-35.731728],"type":"Point"}
}