{
  "type": "Feature",
  "properties": {
    "addr:full":"Martin Farm Rd  Kaiteriteri",
    "addr:street":"Martin Farm Rd",
    "iso:country":"NZ",
    "sg:address":"Martin Farm Rd ",
    "sg:city":"Kaiteriteri",
    "sg:classifiers":[
        {
            "category":"Insurance",
            "subcategory":"Health Insurance",
            "type":"Services"
        }
    ],
    "sg:phone":"+64 508 546 4672",
    "sg:tags":[
        "beauty"
    ],
    "sg:website":"http://www.kimiora.co.nz",
    "wof:name":"Kimi Ora Health Spa Resort",
    "wof:placetype":"venue"
},
  "geometry": {"coordinates":[173.01297,-41.041447],"type":"Point"}
}