{
  "type": "Feature",
  "properties": {
    "addr:full":"Ruakura AgResearch Centre East St  Hamilton Waikato",
    "addr:street":"East St",
    "iso:country":"NZ",
    "sg:address":"Ruakura AgResearch Centre East St ",
    "sg:city":"Hamilton",
    "sg:classifiers":[
        {
            "category":"Travel",
            "subcategory":"Travel Agent",
            "type":"Entertainment"
        }
    ],
    "sg:phone":"+64 7-838 5293",
    "sg:province":"Waikato",
    "sg:tags":[
        "tourism",
        "broker"
    ],
    "wof:name":"Signature Travel Ltd",
    "wof:placetype":"venue"
},
  "geometry": {"coordinates":[175.324478,-37.76757],"type":"Point"}
}