{
  "type": "Feature",
  "properties": {
    "addr:full":"111 B May Rd Mt Roskill  Auckland Auckland",
    "addr:housenumber":"111 b",
    "addr:street":"May Rd",
    "iso:country":"NZ",
    "sg:address":"111 B May Rd Mt Roskill ",
    "sg:city":"Auckland",
    "sg:orig_category":"Home And Garden: Accessories: Clocks",
    "sg:phone":"+64 9-620 9182",
    "sg:province":"Auckland",
    "wof:name":"Time World",
    "wof:placetype":"venue"
},
  "geometry": {"coordinates":[174.73317,-36.910976],"type":"Point"}
}