{
  "type": "Feature",
  "properties": {
    "addr:full":"Elizabeth Ave  Leeston",
    "addr:street":"Elizabeth Ave",
    "iso:country":"NZ",
    "sg:address":"Elizabeth Ave ",
    "sg:city":"Leeston",
    "sg:orig_category":"Health And Beauty: Specialists: Osteopaths",
    "sg:phone":"+64 3-303 5002",
    "wof:name":"Rakaia Medical Centre",
    "wof:placetype":"venue"
},
  "geometry": {"coordinates":[172.29849200000001,-43.760258],"type":"Point"}
}