{
  "type": "Feature",
  "properties": {
    "iso:country":"NZ",
    "sg:address":"53 Duke St Frankton ",
    "sg:city":"Hamilton",
    "sg:classifiers":[
        {
            "category":"Bars & Pubs",
            "subcategory":"Lounge",
            "type":"Food & Drink"
        }
    ],
    "sg:phone":"+64 7-847 3588",
    "sg:province":"Waikato",
    "sg:tags":[
        "baker",
        "-"
    ],
    "wof:name":"Mister Baker 1990 Ltd",
    "wof:placetype":"venue"
},
  "geometry": {"coordinates":[175.262711,-37.802979],"type":"Point"}
}