{
  "type": "Feature",
  "properties": {
    "addr:full":"Leslie St Upper Riccarton  Christchurch Canterbury",
    "addr:street":"Leslie St",
    "iso:country":"NZ",
    "sg:address":"Leslie St Upper Riccarton ",
    "sg:city":"Christchurch",
    "sg:orig_category":"Home And Garden: Accessories: Hardware",
    "sg:phone":"+64 3-348 7468",
    "sg:province":"Canterbury",
    "wof:name":"Church Corner Mitre 10",
    "wof:placetype":"venue"
},
  "geometry": {"coordinates":[172.57269299999999,-43.530807],"type":"Point"}
}