{
  "type": "Feature",
  "properties": {
    "addr:full":"Ngunguru Rd  Glenbervie",
    "addr:street":"Ngunguru Rd",
    "iso:country":"NZ",
    "sg:address":"Ngunguru Rd ",
    "sg:city":"Glenbervie",
    "sg:classifiers":[
        {
            "category":"Marine",
            "type":"Transportation"
        }
    ],
    "sg:phone":"+64 25456565",
    "sg:tags":[
        "boats",
        "builder",
        "yacht",
        "transport",
        "boat"
    ],
    "wof:name":"Alex Wakelin - Boat Builder",
    "wof:placetype":"venue"
},
  "geometry": {"coordinates":[174.33547999999999,-35.683395],"type":"Point"}
}