{
  "type": "Feature",
  "properties": {
    "addr:full":"44 Broad St Woolston  Christchurch Canterbury",
    "addr:housenumber":"44",
    "addr:street":"Broad St",
    "iso:country":"NZ",
    "sg:address":"44 Broad St Woolston ",
    "sg:city":"Christchurch",
    "sg:classifiers":[
        {
            "category":"Home & Garden",
            "subcategory":"Building Materials",
            "type":"Retail Goods"
        }
    ],
    "sg:phone":"+64 3-384 7117",
    "sg:province":"Canterbury",
    "sg:tags":[
        "furniture/furnishings",
        "recovering",
        "mattress"
    ],
    "wof:name":"Base & Mattress Sales & Recovering Services",
    "wof:placetype":"venue"
},
  "geometry": {"coordinates":[172.68667600000001,-43.559975],"type":"Point"}
}