{
  "type": "Feature",
  "properties": {
    "iso:country":"NZ",
    "sg:address":"222 Rutherford St ",
    "sg:city":"Nelson",
    "sg:classifiers":[
        {
            "category":"Personal",
            "subcategory":"Beauty Salon",
            "type":"Services"
        }
    ],
    "sg:phone":"+64 3-548 1146",
    "sg:province":"Nelson",
    "sg:tags":[
        "therapy",
        "health"
    ],
    "wof:name":"Carol Priest Natural Cosmetics NZ Ltd",
    "wof:placetype":"venue"
},
  "geometry": {"coordinates":[173.280441,-41.279259],"type":"Point"}
}