{
  "type": "Feature",
  "properties": {
    "iso:country":"NZ",
    "sg:address":"Shop 4 Casabella Lane 307 Barton St ",
    "sg:city":"Hamilton",
    "sg:classifiers":[
        {
            "category":"Retail",
            "subcategory":"Driving School",
            "type":"Services"
        }
    ],
    "sg:phone":"+64 7-834 0005",
    "sg:province":"Waikato",
    "sg:tags":[
        "health",
        "beauty"
    ],
    "wof:name":"So Natural's Academy of Nails",
    "wof:placetype":"venue"
},
  "geometry": {"coordinates":[-84.506676,39.377304],"type":"Point"}
}