{
  "type": "Feature",
  "properties": {
    "addr:full":"17th Floor, 1 Queen St Auckland City  Auckland Auckland",
    "addr:housenumber":"1",
    "addr:street":"Queen St",
    "iso:country":"NZ",
    "sg:address":"17th Floor, 1 Queen St Auckland City ",
    "sg:city":"Auckland",
    "sg:classifiers":[
        {
            "category":"Airline",
            "type":"Transportation"
        }
    ],
    "sg:phone":"+64 800 508 648",
    "sg:province":"Auckland",
    "sg:tags":[
        "services",
        "travel",
        "tourism"
    ],
    "wof:name":"United Airlines",
    "wof:placetype":"venue"
},
  "geometry": {"coordinates":[174.76712000000001,-36.843376],"type":"Point"}
}