{
  "type": "Feature",
  "properties": {
    "iso:country":"NZ",
    "sg:address":"402 Featherston St Palmerston ",
    "sg:city":"Palmerston North",
    "sg:orig_category":"Health And Beauty: Specialists: Osteopaths",
    "sg:phone":"+64 6-356 7951",
    "sg:province":"Manawatu-Wanganui",
    "wof:name":"Parrs Osteopathic Clinic",
    "wof:placetype":"venue"
},
  "geometry": {"coordinates":[175.618607,-40.344513],"type":"Point"}
}