{
  "type": "Feature",
  "properties": {
    "iso:country":"NZ",
    "sg:address":"5 Hinau St ",
    "sg:city":"Wanganui",
    "sg:classifiers":[
        {
            "category":"Shopping",
            "subcategory":"Crafts & Fabrics",
            "type":"Retail Goods"
        }
    ],
    "sg:phone":"+64 6-344 7834",
    "sg:province":"Manawatu-Wanganui",
    "sg:tags":[
        "clothing"
    ],
    "wof:name":"Stahl Australia Pty Ltd",
    "wof:placetype":"venue"
},
  "geometry": {"coordinates":[175.008148,-39.94569],"type":"Point"}
}