{
  "type": "Feature",
  "properties": {
    "addr:full":"62 Manchester St  Feilding Manawatu-Wanganui",
    "addr:housenumber":"62",
    "addr:street":"Manchester St",
    "iso:country":"NZ",
    "sg:address":"62 Manchester St ",
    "sg:city":"Feilding",
    "sg:classifiers":[
        {
            "category":"Bars & Pubs",
            "subcategory":"Wine Bar",
            "type":"Food & Drink"
        }
    ],
    "sg:phone":"+64 6-323 5672",
    "sg:province":"Manawatu-Wanganui",
    "sg:tags":[
        "wining",
        "dining",
        "cafe"
    ],
    "wof:name":"Mummies Cafe",
    "wof:placetype":"venue"
},
  "geometry": {"coordinates":[175.56501800000001,-40.227158],"type":"Point"}
}