{
  "type": "Feature",
  "properties": {
    "iso:country":"NZ",
    "sg:address":"Westgate Shopping Centre Hobsonville Rd Massey ",
    "sg:city":"Auckland",
    "sg:classifiers":[
        {
            "category":"Sports & Exercise",
            "subcategory":"Sports Center",
            "type":"Entertainment"
        }
    ],
    "sg:phone":"+64 9-831 0260",
    "sg:province":"Otago",
    "sg:tags":[
        "indoor",
        "-",
        "leisure",
        "sports"
    ],
    "wof:name":"Westgate Tenpin",
    "wof:placetype":"venue"
},
  "geometry": {"coordinates":[174.63568100000001,-36.828793],"type":"Point"}
}