{
  "type": "Feature",
  "properties": {
    "iso:country":"NZ",
    "sg:address":"1140 Hinemoa St ",
    "sg:city":"Rotorua",
    "sg:classifiers":[
        {
            "category":"Bars & Pubs",
            "subcategory":"Nightclub",
            "type":"Food & Drink"
        }
    ],
    "sg:phone":"+64 7-350 3291",
    "sg:province":"Bay of Plenty",
    "sg:tags":[
        "club",
        "night",
        "sport",
        "leisure",
        "entertainment"
    ],
    "wof:name":"Outlaws Saloon & Restaurant",
    "wof:placetype":"venue"
},
  "geometry": {"coordinates":[176.252487,-38.137997],"type":"Point"}
}