{
  "type": "Feature",
  "properties": {
    "iso:country":"NZ",
    "sg:address":"Plimmerton ",
    "sg:city":"Wellington",
    "sg:classifiers":[
        {
            "category":"Food & Beverages",
            "subcategory":"Bakery",
            "type":"Retail Goods"
        }
    ],
    "sg:phone":"+64 4-233 9210",
    "sg:province":"Wellington",
    "sg:tags":[
        "shop",
        "cake",
        "drink",
        "-"
    ],
    "wof:name":"Cake Artistry",
    "wof:placetype":"venue"
},
  "geometry": {"coordinates":[174.864288,-41.079514],"type":"Point"}
}