{
  "type": "Feature",
  "properties": {
    "addr:full":"60 Fairfield Rd  Hamilton Waikato",
    "addr:housenumber":"60",
    "addr:street":"Fairfield Rd",
    "iso:country":"NZ",
    "sg:address":"60 Fairfield Rd ",
    "sg:city":"Hamilton",
    "sg:classifiers":[
        {
            "category":"Education",
            "subcategory":"Dance Studio",
            "type":"Public Place"
        }
    ],
    "sg:phone":"+64 7-855 1524",
    "sg:province":"Waikato",
    "sg:tags":[
        "school",
        "dancing",
        "-",
        "leisure",
        "sports",
        "sport"
    ],
    "wof:name":"Valerie Lissette School of Dance",
    "wof:placetype":"venue"
},
  "geometry": {"coordinates":[175.276184,-37.769081],"type":"Point"}
}