{
  "type": "Feature",
  "properties": {
    "iso:country":"NZ",
    "sg:address":"10a Otanerua Rd Hatfields Beach Hibiscus ",
    "sg:city":"Hibiscus Coast",
    "sg:classifiers":[
        {
            "category":"Arena",
            "subcategory":"Sports Club",
            "type":"Entertainment"
        }
    ],
    "sg:phone":"+64 9-426 6144",
    "sg:province":"Auckland",
    "sg:tags":[
        "arts",
        "writer",
        "leisure",
        "author"
    ],
    "wof:name":"Isle Mike",
    "wof:placetype":"venue"
},
  "geometry": {"coordinates":[174.69194,-36.566326],"type":"Point"}
}