{
  "type": "Feature",
  "properties": {
    "addr:full":"21 Union St  Opotiki",
    "addr:housenumber":"21",
    "addr:street":"Union St",
    "iso:country":"NZ",
    "sg:address":"21 Union St ",
    "sg:city":"Opotiki",
    "sg:classifiers":[
        {
            "category":"Building & Trades",
            "subcategory":"Plumbing",
            "type":"Services"
        }
    ],
    "sg:phone":"+64 7-315 6739",
    "sg:tags":[
        "home",
        "plumber",
        "garden",
        "related"
    ],
    "wof:name":"Crosswell Plumbing Co Ltd",
    "wof:placetype":"venue"
},
  "geometry": {"coordinates":[177.27694700000001,-38.014717],"type":"Point"}
}