{
  "type": "Feature",
  "properties": {
    "iso:country":"NZ",
    "sg:address":"10 Grove Rd ",
    "sg:city":"Blenheim",
    "sg:classifiers":[
        {
            "category":"Home & Garden",
            "subcategory":"Home Furnishings",
            "type":"Retail Goods"
        }
    ],
    "sg:phone":"+64 3-578 5500",
    "sg:province":"Marlborough",
    "sg:tags":[
        "accessory"
    ],
    "wof:name":"Carl Gratton Glass Limited",
    "wof:placetype":"venue"
},
  "geometry": {"coordinates":[-74.459564,42.468643],"type":"Point"}
}