{
  "type": "Feature",
  "properties": {
    "iso:country":"NZ",
    "sg:address":"129 Perry St ",
    "sg:city":"Masterton",
    "sg:orig_category":"Farming: Services: Veterinarians",
    "sg:phone":"+64 6-377 4212",
    "sg:province":"Wellington",
    "wof:name":"Farman Roy S",
    "wof:placetype":"venue"
},
  "geometry": {"coordinates":[175.655426,-40.941772],"type":"Point"}
}