{
  "type": "Feature",
  "properties": {
    "addr:full":"129 Perry St  Masterton Wellington",
    "addr:housenumber":"129",
    "addr:street":"Perry St",
    "iso:country":"NZ",
    "sg:address":"129 Perry St ",
    "sg:city":"Masterton",
    "sg:orig_category":"Farming: Services: Veterinarians",
    "sg:phone":"+64 6-377 4212",
    "sg:province":"Wellington",
    "wof:name":"Farman Roy S",
    "wof:placetype":"venue"
},
  "geometry": {"coordinates":[175.65542600000001,-40.941772],"type":"Point"}
}