{
  "type": "Feature",
  "properties": {
    "addr:full":"2 Amber Cre  Tauranga Bay of Plenty",
    "addr:housenumber":"2;cre",
    "addr:street":"Amber",
    "iso:country":"NZ",
    "sg:address":"2 Amber Cre ",
    "sg:city":"Tauranga",
    "sg:classifiers":[
        {
            "category":"Farming",
            "subcategory":"Fish & Marine Products",
            "type":"Manufacturing & Wholesale Goods"
        }
    ],
    "sg:phone":"+64 7-571 0293",
    "sg:province":"Bay of Plenty",
    "sg:tags":[
        "-",
        "boat",
        "transport"
    ],
    "wof:name":"Checkpoint Engineering",
    "wof:placetype":"venue"
},
  "geometry": {"coordinates":[176.14915500000001,-37.698582],"type":"Point"}
}