{
  "type": "Feature",
  "properties": {
    "addr:full":"302 Main Rd Highway 16 Huapai  Auckland Auckland",
    "addr:housenumber":"302",
    "addr:street":"Main Rd Highway 16",
    "iso:country":"NZ",
    "sg:address":"302 Main Rd Highway 16 Huapai ",
    "sg:city":"Auckland",
    "sg:classifiers":[
        {
            "category":"Communications",
            "subcategory":"Film & Video Production",
            "type":"Services"
        }
    ],
    "sg:phone":"+64 9-412 9547",
    "sg:province":"Auckland",
    "sg:tags":[
        "sport",
        "leisure",
        "library",
        "entertainment"
    ],
    "wof:name":"Monster Video & Entertainment",
    "wof:placetype":"venue"
},
  "geometry": {"coordinates":[174.77041600000001,-36.884109],"type":"Point"}
}