{
  "type": "Feature",
  "properties": {
    "addr:full":"96 Church St  Opotiki",
    "addr:housenumber":"96",
    "addr:street":"Church St",
    "iso:country":"NZ",
    "sg:address":"96 Church St ",
    "sg:city":"Opotiki",
    "sg:classifiers":[
        {
            "category":"Bars & Pubs",
            "subcategory":"Lounge",
            "type":"Food & Drink"
        }
    ],
    "sg:phone":"+64 7-315 6330",
    "sg:tags":[
        "baker",
        "-"
    ],
    "wof:name":"The Bakehouse Opotiki",
    "wof:placetype":"venue"
},
  "geometry": {"coordinates":[177.28454600000001,-38.003643],"type":"Point"}
}