{
  "type": "Feature",
  "properties": {
    "addr:full":"PO Box 6065  Brookfield Bay of Plenty",
    "addr:housenumber":"po",
    "addr:street":"Box 6065",
    "iso:country":"NZ",
    "sg:address":"PO Box 6065 ",
    "sg:city":"Brookfield",
    "sg:orig_category":"Home And Garden: Gardening: Services: Tree Services",
    "sg:phone":"+64 25928560",
    "sg:province":"Bay of Plenty",
    "wof:name":"Westbay Mulching Services Ltd",
    "wof:placetype":"venue"
},
  "geometry": {"coordinates":[-73.396255,41.462093],"type":"Point"}
}