{
  "type": "Feature",
  "properties": {
    "addr:full":"Hunters Plaza Cnr Sutton Cres & Great Sth Rd Papatoetoe Auckland Auckland",
    "addr:street":"Cnr Sutton Cres & Great Sth Rd",
    "iso:country":"NZ",
    "sg:address":"Hunters Plaza Cnr Sutton Cres & Great Sth Rd Papatoetoe",
    "sg:city":"Auckland",
    "sg:orig_category":"Shopping: Retail Stores: Department Stores",
    "sg:phone":"+64 9-279 9300",
    "sg:province":"Auckland",
    "wof:name":"Kmart",
    "wof:placetype":"venue"
},
  "geometry": {"coordinates":[174.85188299999999,-36.974461],"type":"Point"}
}