{
  "type": "Feature",
  "properties": {
    "iso:country":"NZ",
    "sg:address":"1-7 Oxford St ",
    "sg:city":"Levin",
    "sg:classifiers":[
        {
            "category":"Autos & Motor Vehicles",
            "subcategory":"Automobile Sales",
            "type":"Retail Goods"
        }
    ],
    "sg:phone":"+64 6-368 5548",
    "sg:province":"Manawatu-Wanganui",
    "sg:tags":[
        "home",
        "caravan",
        "leasing",
        "automotive"
    ],
    "wof:name":"Gipsy Caravans 1996 Ltd",
    "wof:placetype":"venue"
},
  "geometry": {"coordinates":[-89.084503,37.193748],"type":"Point"}
}