{
  "type": "Feature",
  "properties": {
    "addr:full":"75 Fox St  Invercargill Southland",
    "addr:housenumber":"75",
    "addr:street":"Fox St",
    "iso:country":"NZ",
    "sg:address":"75 Fox St ",
    "sg:city":"Invercargill",
    "sg:classifiers":[
        {
            "category":"Retail",
            "subcategory":"Funeral Services",
            "type":"Services"
        }
    ],
    "sg:phone":"+64 3-218 9021",
    "sg:province":"Southland",
    "sg:tags":[
        "arrangements",
        "arrangement"
    ],
    "wof:name":"Avenal Park Funeral Home",
    "wof:placetype":"venue"
},
  "geometry": {"coordinates":[168.34818999999999,-46.401764],"type":"Point"}
}