{
  "type": "Feature",
  "properties": {
    "iso:country":"NZ",
    "sg:address":"119 Walmsley Rd Mangere ",
    "sg:city":"Auckland",
    "sg:orig_category":"Home And Garden: Gardening: Products: Palms",
    "sg:phone":"+64 9-275 5454",
    "sg:province":"Auckland",
    "wof:name":"The Palm Farm",
    "wof:placetype":"venue"
},
  "geometry": {"coordinates":[174.79541,-36.953739],"type":"Point"}
}