{
  "type": "Feature",
  "properties": {
    "iso:country":"NZ",
    "sg:address":"3 St Heliers Bay Rd St Heliers ",
    "sg:city":"Auckland",
    "sg:classifiers":[
        {
            "category":"Sports & Exercise",
            "subcategory":"Ski Resort",
            "type":"Entertainment"
        }
    ],
    "sg:phone":"+64 9-575 5077",
    "sg:province":"Auckland",
    "sg:tags":[
        "hobbies",
        "photographic",
        "leisure",
        "developing"
    ],
    "wof:name":"Eric Parr Pharmacy Ltd",
    "wof:placetype":"venue"
},
  "geometry": {"coordinates":[174.857285,-36.850517],"type":"Point"}
}