{
  "type": "Feature",
  "properties": {
    "iso:country":"NZ",
    "sg:address":"Tui Gro Te Haumi ",
    "sg:city":"Paihia",
    "sg:classifiers":[
        {
            "category":"Personal",
            "type":"Services"
        }
    ],
    "sg:phone":"+64 9-402 7864",
    "sg:province":"Northland",
    "sg:tags":[
        "celebrant",
        "arrangements",
        "marriage",
        "wedding"
    ],
    "wof:name":"Brown Vivienne",
    "wof:placetype":"venue"
},
  "geometry": {"coordinates":[174.099167,-35.299999],"type":"Point"}
}