{
  "type": "Feature",
  "properties": {
    "addr:full":"36 Vickerman St Port Nelson  Nelson Nelson",
    "addr:housenumber":"36",
    "addr:street":"Vickerman St",
    "iso:country":"NZ",
    "sg:address":"36 Vickerman St Port Nelson ",
    "sg:city":"Nelson",
    "sg:classifiers":[
        {
            "category":"Marine",
            "type":"Transportation"
        }
    ],
    "sg:phone":"+64 3-541 9136",
    "sg:province":"Nelson",
    "sg:tags":[
        "boats",
        "builder",
        "yacht",
        "transport",
        "boat"
    ],
    "wof:name":"Pomeroy Boat Building",
    "wof:placetype":"venue"
},
  "geometry": {"coordinates":[173.27742000000001,-41.265717],"type":"Point"}
}