{
  "type": "Feature",
  "properties": {
    "addr:full":"209 Hilton Hwy Washdyke  Timaru Canterbury",
    "addr:housenumber":"209",
    "addr:street":"Hilton Hwy",
    "iso:country":"NZ",
    "sg:address":"209 Hilton Hwy Washdyke ",
    "sg:city":"Timaru",
    "sg:orig_category":"Farming: Horticulture: Grain And Seed",
    "sg:phone":"+64 3-688 2035",
    "sg:province":"Canterbury",
    "wof:name":"Grainstore Ltd",
    "wof:placetype":"venue"
},
  "geometry": {"coordinates":[171.23788500000001,-44.352978],"type":"Point"}
}