{
  "type": "Feature",
  "properties": {
    "iso:country":"NZ",
    "sg:address":"16 Taylors Rd Morningside ",
    "sg:city":"Auckland",
    "sg:classifiers":[
        {
            "category":"Shopping",
            "subcategory":"Computers & Home Electronics",
            "type":"Retail Goods"
        }
    ],
    "sg:phone":"+64 9-846 5426",
    "sg:province":"Auckland",
    "sg:tags":[
        "recording",
        "equipment",
        "sport",
        "music",
        "leisure"
    ],
    "wof:name":"Oceania Audio Ltd",
    "wof:placetype":"venue"
},
  "geometry": {"coordinates":[174.733124,-36.876457],"type":"Point"}
}