{
  "type": "Feature",
  "properties": {
    "addr:full":"33 Morningside Dve Mt Albert  Auckland Auckland",
    "addr:housenumber":"33",
    "addr:street":"Morningside Dve",
    "iso:country":"NZ",
    "sg:address":"33 Morningside Dve Mt Albert ",
    "sg:city":"Auckland",
    "sg:classifiers":[
        {
            "category":"Shopping",
            "subcategory":"Pharmacy",
            "type":"Retail Goods"
        }
    ],
    "sg:phone":"+64 9-846 6044",
    "sg:province":"Auckland",
    "sg:tags":[
        "products",
        "medical",
        "health",
        "beauty",
        "supply"
    ],
    "sg:website":"http://www.yellowpages.co.nz/for/medipak/dp25484.html",
    "wof:name":"Medipak Surgical N.Z. Ltd",
    "wof:placetype":"venue"
},
  "geometry": {"coordinates":[174.714798,-36.88784],"type":"Point"}
}