{
  "type": "Feature",
  "properties": {
    "addr:full":"18-24 Westech Pl Kelston  Auckland Auckland",
    "addr:housenumber":"18-24",
    "addr:street":"Westech Pl",
    "iso:country":"NZ",
    "sg:address":"18-24 Westech Pl Kelston ",
    "sg:city":"Auckland",
    "sg:classifiers":[
        {
            "category":"Banks & Credit Unions",
            "subcategory":"Investment Brokerage",
            "type":"Services"
        }
    ],
    "sg:phone":"+64 9-813 9060",
    "sg:province":"Auckland",
    "sg:tags":[
        "industrial",
        "cleaning",
        "maintenance"
    ],
    "wof:name":"Hygiene & Catering Supplies",
    "wof:placetype":"venue"
},
  "geometry": {"coordinates":[174.66717499999999,-36.899097],"type":"Point"}
}