{
  "type": "Feature",
  "properties": {
    "iso:country":"NZ",
    "sg:address":"23 Low St Port Nelson ",
    "sg:city":"Nelson",
    "sg:orig_category":"Industrial: Metal: Services: Steel Processing",
    "sg:phone":"+64 3-545 8852",
    "sg:province":"Nelson",
    "wof:name":"Vulcan Steel Ltd",
    "wof:placetype":"venue"
},
  "geometry": {"coordinates":[173.27650499999999,-41.262829],"type":"Point"}
}