{
  "type": "Feature",
  "properties": {
    "addr:full":"216 Ohaupo Rd  Hamilton Waikato",
    "addr:housenumber":"216",
    "addr:street":"Ohaupo Rd",
    "iso:country":"NZ",
    "sg:address":"216 Ohaupo Rd ",
    "sg:city":"Hamilton",
    "sg:orig_category":"Automotive: General Services: Service Stations",
    "sg:phone":"+64 7-843 4405",
    "sg:province":"Waikato",
    "wof:name":"BP Glenview",
    "wof:placetype":"venue"
},
  "geometry": {"coordinates":[175.28656000000001,-37.821842],"type":"Point"}
}