{
  "type": "Feature",
  "properties": {
    "addr:full":"Morse St Wairau Valley R D 1 Blenheim Wairau  Valley",
    "addr:housenumber":"1",
    "addr:street":"Morse St;D;Wairau",
    "iso:country":"NZ",
    "sg:address":"Morse St Wairau Valley R D 1 Blenheim Wairau ",
    "sg:city":"Valley",
    "sg:orig_category":"Education And Training: General: Schools",
    "sg:phone":"+64 3-572 2715",
    "wof:name":"Wairau Valley School",
    "wof:placetype":"venue"
},
  "geometry": {"coordinates":[174.73814400000001,-36.774681],"type":"Point"}
}