{
  "type": "Feature",
  "properties": {
    "iso:country":"NZ",
    "sg:address":"42 c Quarantine Rd Tahunanui ",
    "sg:city":"Nelson",
    "sg:orig_category":"Industrial: Parts: Fasteners - Industrial",
    "sg:phone":"+64 3-547 4444",
    "sg:province":"Nelson",
    "sg:website":"http://www.yellowpages.co.nz/for/nzfasteners/dp28426.html",
    "wof:name":"NZF Stainless",
    "wof:placetype":"venue"
},
  "geometry": {"coordinates":[173.244644,-41.283855],"type":"Point"}
}