{
  "type": "Feature",
  "properties": {
    "iso:country":"NZ",
    "sg:address":"63 Murray St Mosgiel ",
    "sg:city":"Dunedin",
    "sg:classifiers":[
        {
            "category":"Social Services",
            "subcategory":"Child Care",
            "type":"Services"
        }
    ],
    "sg:phone":"+64 3-489 5515",
    "sg:province":"Otago",
    "sg:tags":[
        "home",
        "garden",
        "children"
    ],
    "wof:name":"Dunedin Kindergarten Association",
    "wof:placetype":"venue"
},
  "geometry": {"coordinates":[170.355392,-45.867416],"type":"Point"}
}