{
  "type": "Feature",
  "properties": {
    "addr:full":"PO Box 324  Alexandra Otago",
    "addr:housenumber":"po",
    "addr:street":"Box 324",
    "iso:country":"NZ",
    "sg:address":"PO Box 324 ",
    "sg:city":"Alexandra",
    "sg:classifiers":[
        {
            "category":"Utilities",
            "subcategory":"Refuse",
            "type":"Services"
        }
    ],
    "sg:phone":"+64 3-448 7134",
    "sg:province":"Otago",
    "sg:tags":[
        "bin",
        "hire",
        "garden",
        "cleaning",
        "rubbish",
        "home"
    ],
    "wof:name":"Pratty's Bins Limited",
    "wof:placetype":"venue"
},
  "geometry": {"coordinates":[169.389984,-45.251148],"type":"Point"}
}