{
  "type": "Feature",
  "properties": {
    "addr:full":"792 Brighton Rd Ocean  View",
    "addr:housenumber":"792",
    "addr:street":"Brighton Rd",
    "iso:country":"NZ",
    "sg:address":"792 Brighton Rd Ocean ",
    "sg:city":"View",
    "sg:classifiers":[
        {
            "category":"Home & Garden",
            "subcategory":"Building Materials",
            "type":"Retail Goods"
        }
    ],
    "sg:phone":"+64 252214748",
    "sg:tags":[
        "brick",
        "outdoor",
        "paving"
    ],
    "wof:name":"East Coast Landscapes",
    "wof:placetype":"venue"
},
  "geometry": {"coordinates":[170.34652700000001,-45.938938],"type":"Point"}
}