{
  "type": "Feature",
  "properties": {
    "iso:country":"NZ",
    "sg:address":"2/505 Southland Rd ",
    "sg:city":"Hastings",
    "sg:classifiers":[
        {
            "category":"Personal",
            "type":"Services"
        }
    ],
    "sg:phone":"+64 6-876 9294",
    "sg:province":"Hawke's Bay",
    "sg:tags":[
        "celebrant",
        "arrangements",
        "marriage",
        "wedding"
    ],
    "wof:name":"Waring Brenda",
    "wof:placetype":"venue"
},
  "geometry": {"coordinates":[-81.508163,29.711214],"type":"Point"}
}