{
  "type": "Feature",
  "properties": {
    "iso:country":"NZ",
    "sg:address":"PO Box 144 ",
    "sg:city":"Hilderthorpe",
    "sg:orig_category":"Sports And Leisure: Sports: Aerial",
    "sg:phone":"+64 3-431 3891",
    "wof:name":"North Otago Aero Club Inc",
    "wof:placetype":"venue"
},
  "geometry": {"coordinates":[171.05418399999999,-44.99852],"type":"Point"}
}