{
  "type": "Feature",
  "properties": {
    "addr:full":"57 Pururu St  Rotorua Bay of Plenty",
    "addr:housenumber":"57",
    "addr:street":"Pururu St",
    "iso:country":"NZ",
    "sg:address":"57 Pururu St ",
    "sg:city":"Rotorua",
    "sg:classifiers":[
        {
            "category":"Manufacturing",
            "subcategory":"Rubber & Plastics",
            "type":"Manufacturing & Wholesale Goods"
        }
    ],
    "sg:phone":"+64 25866226",
    "sg:province":"Bay of Plenty",
    "sg:tags":[
        "repair",
        "industrial",
        "-",
        "goods"
    ],
    "wof:name":"Mobile Bumper & Plastic Repairs",
    "wof:placetype":"venue"
},
  "geometry": {"coordinates":[176.23005699999999,-38.134224],"type":"Point"}
}