{
  "type": "Feature",
  "properties": {
    "addr:full":"2 C Brooklyn Rd Claudelands  Hamilton Waikato",
    "addr:housenumber":"2 c",
    "addr:street":"Brooklyn Rd",
    "iso:country":"NZ",
    "sg:address":"2 C Brooklyn Rd Claudelands ",
    "sg:city":"Hamilton",
    "sg:classifiers":[
        {
            "category":"Professional",
            "subcategory":"Detective & Security Services",
            "type":"Services"
        }
    ],
    "sg:phone":"+64 7-855 2400",
    "sg:province":"Waikato",
    "sg:tags":[
        "services",
        "automotive",
        "warrant",
        "fitness"
    ],
    "wof:name":"Vehicle Testing New Zealand Ltd",
    "wof:placetype":"venue"
},
  "geometry": {"coordinates":[175.29212999999999,-37.77964],"type":"Point"}
}