{
  "type": "Feature",
  "properties": {
    "addr:full":"97a Victoria Ave  Wanganui Manawatu-Wanganui",
    "addr:housenumber":"97a",
    "addr:street":"Victoria Ave",
    "iso:country":"NZ",
    "sg:address":"97a Victoria Ave ",
    "sg:city":"Wanganui",
    "sg:classifiers":[
        {
            "category":"Shopping",
            "subcategory":"Gifts & Souvenirs",
            "type":"Retail Goods"
        }
    ],
    "sg:phone":"+64 6-347 8916",
    "sg:province":"Manawatu-Wanganui",
    "sg:tags":[
        "shop",
        "gifts",
        "supplier"
    ],
    "wof:name":"Mi-Store",
    "wof:placetype":"venue"
},
  "geometry": {"coordinates":[175.05200199999999,-39.933056],"type":"Point"}
}