{
  "type": "Feature",
  "properties": {
    "iso:country":"NZ",
    "sg:address":"330 Tremaine Ave Palmerston ",
    "sg:city":"Palmerston North",
    "sg:classifiers":[
        {
            "category":"Marine",
            "type":"Transportation"
        }
    ],
    "sg:phone":"+64 6-354 2553",
    "sg:province":"Manawatu-Wanganui",
    "sg:tags":[
        "boats",
        "builder",
        "yacht",
        "transport",
        "boat"
    ],
    "wof:name":"McLachlan Ian R",
    "wof:placetype":"venue"
},
  "geometry": {"coordinates":[175.588135,-40.34959],"type":"Point"}
}