{
  "type": "Feature",
  "properties": {
    "addr:full":"330 Tremaine Ave Palmerston  Palmerston North Manawatu-Wanganui",
    "addr:housenumber":"330",
    "addr:street":"Tremaine Ave",
    "iso:country":"NZ",
    "sg:address":"330 Tremaine Ave Palmerston ",
    "sg:city":"Palmerston North",
    "sg:classifiers":[
        {
            "category":"Marine",
            "type":"Transportation"
        }
    ],
    "sg:phone":"+64 6-354 2553",
    "sg:province":"Manawatu-Wanganui",
    "sg:tags":[
        "boats",
        "builder",
        "yacht",
        "transport",
        "boat"
    ],
    "wof:name":"McLachlan Ian R",
    "wof:placetype":"venue"
},
  "geometry": {"coordinates":[175.58813499999999,-40.34959],"type":"Point"}
}