{
  "type": "Feature",
  "properties": {
    "addr:full":"PO Box 74382 Market  Road",
    "addr:housenumber":"po box 74382",
    "addr:street":"Market Road",
    "iso:country":"NZ",
    "sg:address":"PO Box 74382 Market ",
    "sg:city":"Road",
    "sg:classifiers":[
        {
            "category":"Restaurant",
            "type":"Food & Drink"
        }
    ],
    "sg:phone":"+64 9-525 3432",
    "sg:tags":[
        "fruit",
        "veges"
    ],
    "wof:name":"Certified Organics Ltd",
    "wof:placetype":"venue"
},
  "geometry": {"coordinates":[170.36663799999999,-43.587711],"type":"Point"}
}