{
  "type": "Feature",
  "properties": {
    "addr:full":"124 Dee St  Invercargill Southland",
    "addr:housenumber":"124",
    "addr:street":"Dee St",
    "iso:country":"NZ",
    "sg:address":"124 Dee St ",
    "sg:city":"Invercargill",
    "sg:classifiers":[
        {
            "category":"Internet Cafe",
            "subcategory":"None",
            "type":"Food & Drink"
        }
    ],
    "sg:phone":"+64 3-218 2772",
    "sg:province":"Southland",
    "sg:tags":[
        "wining",
        "dining"
    ],
    "wof:name":"Gordon Data Services 2001",
    "wof:placetype":"venue"
},
  "geometry": {"coordinates":[168.34732099999999,-46.392628],"type":"Point"}
}