{
  "type": "Feature",
  "properties": {
    "iso:country":"NZ",
    "sg:address":"175 Cuba St Palmerston ",
    "sg:city":"Palmerston North",
    "sg:classifiers":[
        {
            "category":"Travel",
            "subcategory":"Hotels & Motels",
            "type":"Entertainment"
        }
    ],
    "sg:phone":"+64 6-355 5895",
    "sg:province":"Manawatu-Wanganui",
    "sg:tags":[
        "tavern",
        "tourism",
        "accommodation"
    ],
    "wof:name":"Mercure Hotel Palmerston North",
    "wof:placetype":"venue"
},
  "geometry": {"coordinates":[175.60627700000001,-40.355991],"type":"Point"}
}