{
  "type": "Feature",
  "properties": {
    "iso:country":"NZ",
    "sg:address":"Whatawhata Rd PO Box 1 Whatawhata ",
    "sg:city":"Hamilton",
    "sg:classifiers":[
        {
            "category":"Home & Garden",
            "subcategory":"Building Materials",
            "type":"Retail Goods"
        }
    ],
    "sg:phone":"+64 7-829 8785",
    "sg:province":"Waikato",
    "sg:tags":[
        "gate",
        "fitting",
        "outdoor"
    ],
    "wof:name":"Whatawhata Products",
    "wof:placetype":"venue"
},
  "geometry": {"coordinates":[175.276993,-37.783215],"type":"Point"}
}