{
  "type": "Feature",
  "properties": {
    "iso:country":"NZ",
    "sg:address":"249 Queen St Richmond ",
    "sg:city":"Nelson",
    "sg:orig_category":"Clothing And Fabric: Clothing: Menswear",
    "sg:phone":"+64 3-543 9977",
    "sg:province":"Nelson",
    "wof:name":"Made For Men",
    "wof:placetype":"venue"
},
  "geometry": {"coordinates":[173.184082,-41.338947],"type":"Point"}
}