{
  "type": "Feature",
  "properties": {
    "addr:full":"288 Great South Rd Manurewa  Auckland Auckland",
    "addr:housenumber":"288",
    "addr:street":"Great South Rd",
    "iso:country":"NZ",
    "sg:address":"288 Great South Rd Manurewa ",
    "sg:city":"Auckland",
    "sg:orig_category":"Transport: Boats And Marine: Boats: Boat Dealers",
    "sg:phone":"+64 9-267 4465",
    "sg:province":"Auckland",
    "wof:name":"Waves & Wheels",
    "wof:placetype":"venue"
},
  "geometry": {"coordinates":[174.90441899999999,-37.030415],"type":"Point"}
}