{
  "type": "Feature",
  "properties": {
    "iso:country":"NZ",
    "sg:address":"Esk Street, Hire Enquiries - ICC ",
    "sg:city":"Invercargill",
    "sg:orig_category":"Sports And Leisure: General: Halls",
    "sg:phone":"+64 3-218 1959",
    "sg:province":"Southland",
    "wof:name":"Scottish Hall",
    "wof:placetype":"venue"
},
  "geometry": {"coordinates":[168.347488,-46.411854],"type":"Point"}
}