{
  "type": "Feature",
  "properties": {
    "addr:full":"101 Spey St  Invercargill Southland",
    "addr:housenumber":"101",
    "addr:street":"Spey St",
    "iso:country":"NZ",
    "sg:address":"101 Spey St ",
    "sg:city":"Invercargill",
    "sg:orig_category":"Industrial: Engineering: Engineers: Engineers - Consulting",
    "sg:phone":"+64 3-218 2429",
    "sg:province":"Southland",
    "wof:name":"Designbase Ltd",
    "wof:placetype":"venue"
},
  "geometry": {"coordinates":[168.348648,-46.409874],"type":"Point"}
}