{
  "type": "Feature",
  "properties": {
    "addr:full":"Joll Rd Havelock North  Hastings Hawke's Bay",
    "addr:street":"Joll Rd",
    "iso:country":"NZ",
    "sg:address":"Joll Rd Havelock North ",
    "sg:city":"Hastings",
    "sg:orig_category":"Clothing And Fabric: Clothing: Women'S Fashions",
    "sg:phone":"+64 6-877 6428",
    "sg:province":"Hawke's Bay",
    "wof:name":"Clothesline",
    "wof:placetype":"venue"
},
  "geometry": {"coordinates":[176.880112,-39.672813],"type":"Point"}
}