{
  "type": "Feature",
  "properties": {
    "addr:full":"Apt 10 386 Richmond Rd Ponsonby  Auckland Nelson",
    "addr:housenumber":"386",
    "addr:street":"10;Richmond Rd",
    "iso:country":"NZ",
    "sg:address":"Apt 10 386 Richmond Rd Ponsonby ",
    "sg:city":"Auckland",
    "sg:classifiers":[
        {
            "category":"Communications",
            "subcategory":"Film & Video Production",
            "type":"Services"
        }
    ],
    "sg:phone":"+64 9-378 0529",
    "sg:province":"Nelson",
    "sg:tags":[
        "broadcasting",
        "studio",
        "producer"
    ],
    "wof:name":"Messenger Films",
    "wof:placetype":"venue"
},
  "geometry": {"coordinates":[174.733093,-36.853977],"type":"Point"}
}