{
  "type": "Feature",
  "properties": {
    "addr:full":"55 A Dunlop Rd Onekawa  Napier Hawke's Bay",
    "addr:housenumber":"55",
    "addr:street":"A Dunlop Rd",
    "iso:country":"NZ",
    "sg:address":"55 A Dunlop Rd Onekawa ",
    "sg:city":"Napier",
    "sg:orig_category":"Industrial: Metal: Products: Aluminium Products",
    "sg:phone":"+64 6-843 5372",
    "sg:province":"Hawke's Bay",
    "wof:name":"Neville Windows Ltd",
    "wof:placetype":"venue"
},
  "geometry": {"coordinates":[176.887573,-39.500301],"type":"Point"}
}