{
  "type": "Feature",
  "properties": {
    "iso:country":"NZ",
    "sg:address":"671 Morrinsville Rd ",
    "sg:city":"Hamilton",
    "sg:classifiers":[
        {
            "category":"Home & Garden",
            "subcategory":"Building Materials",
            "type":"Retail Goods"
        }
    ],
    "sg:phone":"+64 252873223",
    "sg:province":"Waikato",
    "sg:tags":[
        "decorative",
        "glass",
        "window",
        "fittings"
    ],
    "wof:name":"MBD Leadlighting",
    "wof:placetype":"venue"
},
  "geometry": {"coordinates":[175.32762099999999,-37.7994],"type":"Point"}
}