{
  "type": "Feature",
  "properties": {
    "iso:country":"NZ",
    "sg:address":"173 Awapuni Rd ",
    "sg:city":"Gisborne",
    "sg:orig_category":"Transport: Distribution - General: Distributors",
    "sg:phone":"+64 6-867 0231",
    "sg:province":"Manawatu-Wanganui",
    "wof:name":"Griffins Foods Limited",
    "wof:placetype":"venue"
},
  "geometry": {"coordinates":[177.998932,-38.669556],"type":"Point"}
}