{
  "type": "Feature",
  "properties": {
    "iso:country":"NZ",
    "sg:address":"Hingaia Rd Papakura ",
    "sg:city":"Auckland",
    "sg:orig_category":"Industrial: Abrasives: Water Blasting",
    "sg:phone":"+64 9-296 5920",
    "sg:province":"Auckland",
    "wof:name":"Aquamax Northern Ltd",
    "wof:placetype":"venue"
},
  "geometry": {"coordinates":[174.95945739749999,-37.0595207214],"type":"Point"}
}