{
  "type": "Feature",
  "properties": {
    "iso:country":"NZ",
    "sg:address":"The Golden Centre 251 George St ",
    "sg:city":"Dunedin",
    "sg:orig_category":"Shopping: Retail Stores: Toys",
    "sg:phone":"+64 3-477 6614",
    "sg:province":"Otago",
    "wof:name":"Toyworld Dunedin",
    "wof:placetype":"venue"
},
  "geometry": {"coordinates":[-82.784721,28.013355],"type":"Point"}
}