{
  "type": "Feature",
  "properties": {
    "iso:country":"NZ",
    "sg:address":"124-126 Bond St ",
    "sg:city":"Dunedin",
    "sg:classifiers":[
        {
            "category":"Retail",
            "subcategory":"Auto Repair",
            "type":"Services"
        }
    ],
    "sg:phone":"+64 3-474 1137",
    "sg:province":"Otago",
    "sg:tags":[
        "automotive",
        "panel",
        "servicing",
        "beater"
    ],
    "wof:name":"Action Panelbeating",
    "wof:placetype":"venue"
},
  "geometry": {"coordinates":[-82.784721,28.013355],"type":"Point"}
}