{
  "type": "Feature",
  "properties": {
    "iso:country":"NZ",
    "sg:address":"SH58 Judgeford ",
    "sg:city":"Wellington",
    "sg:classifiers":[
        {
            "category":"Home & Garden",
            "subcategory":"Building Materials",
            "type":"Retail Goods"
        }
    ],
    "sg:phone":"+64 800 809 977",
    "sg:province":"Wellington",
    "sg:tags":[
        "door",
        "fitting",
        "fittings"
    ],
    "wof:name":"Rintoul Interiors NZ Ltd",
    "wof:placetype":"venue"
},
  "geometry": {"coordinates":[174.97319,-41.129154],"type":"Point"}
}