{
  "type": "Feature",
  "properties": {
    "iso:country":"NZ",
    "sg:address":"64 Sir William Ave East Tamaki ",
    "sg:city":"Auckland",
    "sg:orig_category":"Home And Garden: Furniture/Furnishings: Cabinetmakers",
    "sg:phone":"+64 9-274 0372",
    "sg:province":"Auckland",
    "wof:name":"The Design Workshop",
    "wof:placetype":"venue"
},
  "geometry": {"coordinates":[174.896729,-36.943691],"type":"Point"}
}