{
  "type": "Feature",
  "properties": {
    "iso:country":"NZ",
    "sg:address":"142 Everglade Dve ",
    "sg:city":"Manukau",
    "sg:classifiers":[
        {
            "category":"Manufacturing",
            "subcategory":"Motor Vehicles & Parts",
            "type":"Manufacturing & Wholesale Goods"
        }
    ],
    "sg:phone":"+64 272 837 631",
    "sg:tags":[
        "air conditioning",
        "automotive",
        "supplies"
    ],
    "wof:name":"Payle$$ Auto Air Ltd",
    "wof:placetype":"venue"
},
  "geometry": {"coordinates":[173.203003,-35.221741],"type":"Point"}
}