{
  "type": "Feature",
  "properties": {
    "addr:full":"193 Cashel St  Christchurch Canterbury",
    "addr:housenumber":"193",
    "addr:street":"Cashel St",
    "iso:country":"NZ",
    "sg:address":"193 Cashel St ",
    "sg:city":"Christchurch",
    "sg:classifiers":[
        {
            "category":"Organizations",
            "subcategory":"Labor Organization",
            "type":"Services"
        }
    ],
    "sg:phone":"+64 3-379 5575",
    "sg:province":"Canterbury",
    "sg:tags":[
        "travel",
        "tourism"
    ],
    "sg:website":"http://www.cdc.org.nz",
    "wof:name":"Canterbury Development Corporation",
    "wof:placetype":"venue"
},
  "geometry": {"coordinates":[172.64082300000001,-43.53299],"type":"Point"}
}