{
  "type": "Feature",
  "properties": {
    "iso:country":"NZ",
    "sg:address":"11 Ryan Pl Manukau City ",
    "sg:city":"Auckland",
    "sg:orig_category":"Industrial: Packaging: Cups And Containers",
    "sg:phone":"+64 9-262 3332",
    "sg:province":"Auckland",
    "wof:name":"Polycup Supplies",
    "wof:placetype":"venue"
},
  "geometry": {"coordinates":[174.87674000000001,-36.985973],"type":"Point"}
}