{
  "type": "Feature",
  "properties": {
    "iso:country":"NZ",
    "sg:address":"26 Duke St ",
    "sg:city":"Cambridge",
    "sg:classifiers":[
        {
            "category":"Banks & Credit Unions",
            "subcategory":"Investment Brokerage",
            "type":"Services"
        }
    ],
    "sg:phone":"+64 7-827 6006",
    "sg:province":"Waikato",
    "sg:tags":[
        "personal",
        "accountant",
        "chartered",
        "-",
        "finance"
    ],
    "wof:name":"Fisher Heaslip",
    "wof:placetype":"venue"
},
  "geometry": {"coordinates":[-116.676048,44.572186],"type":"Point"}
}