{
  "type": "Feature",
  "properties": {
    "iso:country":"NZ",
    "sg:address":"41 Methuen Rd Avondale ",
    "sg:city":"Auckland",
    "sg:orig_category":"Automotive: Servicing And Repair: Car Trimming/Upholstery",
    "sg:phone":"+64 9-820 8456",
    "sg:province":"Auckland",
    "wof:name":"Dave Thomas Car Upholstery",
    "wof:placetype":"venue"
},
  "geometry": {"coordinates":[174.704758,-36.899437],"type":"Point"}
}