{
  "type": "Feature",
  "properties": {
    "addr:full":"50 Newman Rd  Eketahuna",
    "addr:housenumber":"50",
    "addr:street":"Newman Rd",
    "iso:country":"NZ",
    "sg:address":"50 Newman Rd ",
    "sg:city":"Eketahuna",
    "sg:orig_category":"Industrial: Engineering: Engineers: Engineers - General",
    "sg:phone":"+64 6-375 8029",
    "wof:name":"Burling Engineering",
    "wof:placetype":"venue"
},
  "geometry": {"coordinates":[175.710419,-40.63723],"type":"Point"}
}