{
  "type": "Feature",
  "properties": {
    "iso:country":"NZ",
    "sg:address":"19 Water St ",
    "sg:city":"Whangarei",
    "sg:classifiers":[
        {
            "category":"Retail",
            "subcategory":"Auto Repair",
            "type":"Services"
        }
    ],
    "sg:phone":"+64 9-438 9168",
    "sg:province":"Northland",
    "sg:tags":[
        "engine",
        "automotive",
        "servicing"
    ],
    "wof:name":"Engine Room Reconditioning",
    "wof:placetype":"venue"
},
  "geometry": {"coordinates":[174.31838999999999,-35.726067],"type":"Point"}
}