{
  "type": "Feature",
  "properties": {
    "iso:country":"NZ",
    "sg:address":"16 Railway St Newmarket ",
    "sg:city":"Auckland",
    "sg:orig_category":"Clothing And Fabric: Fabric: Textiles",
    "sg:phone":"+64 9-523 0627",
    "sg:province":"Auckland",
    "wof:name":"Designers International",
    "wof:placetype":"venue"
},
  "geometry": {"coordinates":[174.78033400000001,-36.865311],"type":"Point"}
}