{
  "type": "Feature",
  "properties": {
    "addr:full":"435 Gt North Rd Henderson  Auckland Auckland",
    "addr:housenumber":"435",
    "addr:street":"Gt North Rd",
    "iso:country":"NZ",
    "sg:address":"435 Gt North Rd Henderson ",
    "sg:city":"Auckland",
    "sg:classifiers":[
        {
            "category":"Autos & Motor Vehicles",
            "subcategory":"Automobile Sales",
            "type":"Retail Goods"
        }
    ],
    "sg:phone":"+64 9-837 0907",
    "sg:province":"Auckland",
    "sg:tags":[
        "automotive"
    ],
    "sg:website":"http://www.yellowpages.co.nz/for/westcityholden/dp35687.html",
    "wof:name":"Holden West City",
    "wof:placetype":"venue"
},
  "geometry": {"coordinates":[174.62866199999999,-36.87598],"type":"Point"}
}