{
  "type": "Feature",
  "properties": {
    "iso:country":"NZ",
    "sg:address":"Unit E -10 Parkhead Place Nth Hbr Industrial Estate, Albany ",
    "sg:city":"Auckland",
    "sg:orig_category":"Industrial: Services: Toolmakers And Designers",
    "sg:phone":"+64 9-415 5485",
    "sg:province":"Auckland",
    "wof:name":"Broad Engineering Ltd",
    "wof:placetype":"venue"
},
  "geometry": {"coordinates":[174.744324,-36.714409],"type":"Point"}
}