{
  "type": "Feature",
  "properties": {
    "iso:country":"NZ",
    "sg:address":"119 Mays Rd Te Papapa ",
    "sg:city":"Auckland",
    "sg:orig_category":"Home And Garden: Furniture/Furnishings: Cabinetmakers",
    "sg:phone":"+64 9-636 8221",
    "sg:province":"Auckland",
    "wof:name":"Jackson & Cole Ltd",
    "wof:placetype":"venue"
},
  "geometry": {"coordinates":[174.802811,-36.920979],"type":"Point"}
}