{
  "type": "Feature",
  "properties": {
    "iso:country":"NZ",
    "sg:address":"371 McLeans Island Rd Yaldhurst ",
    "sg:city":"Christchurch",
    "sg:orig_category":"Sports And Leisure: Sports: Golf",
    "sg:phone":"+64 3-359 8853",
    "sg:province":"Canterbury",
    "wof:name":"Harewood Golf Club Inc",
    "wof:placetype":"venue"
},
  "geometry": {"coordinates":[172.512451,-43.469639],"type":"Point"}
}