{
  "type": "Feature",
  "properties": {
    "addr:full":"Tauranga, Rotorua, Taupo, Whakatane, 15 Koromiko St, Judea  Tauranga Bay of Plenty",
    "addr:housenumber":"15",
    "addr:street":"Whakatane;St",
    "iso:country":"NZ",
    "sg:address":"Tauranga, Rotorua, Taupo, Whakatane, 15 Koromiko St, Judea ",
    "sg:city":"Tauranga",
    "sg:classifiers":[
        {
            "category":"Home & Garden",
            "subcategory":"Building Materials",
            "type":"Retail Goods"
        }
    ],
    "sg:phone":"+64 7-577 0179",
    "sg:province":"Bay of Plenty",
    "sg:tags":[
        "design",
        "fitting",
        "fittings",
        "kitchen"
    ],
    "sg:website":"http://www.yellowpages.co.nz/for/modular/dp31597.html",
    "wof:name":"The Modular Kitchen Company",
    "wof:placetype":"venue"
},
  "geometry": {"coordinates":[176.14236500000001,-37.695297],"type":"Point"}
}