{
  "type": "Feature",
  "properties": {
    "iso:country":"NZ",
    "sg:address":"PO Box 38687 Petone Lower ",
    "sg:city":"Hutt",
    "sg:orig_category":"Home And Garden: Gardening: Services: Landscaping",
    "sg:phone":"+64 4-568 5322",
    "sg:province":"Wellington",
    "wof:name":"K C Property Services Ltd",
    "wof:placetype":"venue"
},
  "geometry": {"coordinates":[174.875076,-41.221291],"type":"Point"}
}