{
  "type": "Feature",
  "properties": {
    "iso:country":"NZ",
    "sg:address":"137 A Victoria Ave ",
    "sg:city":"Wanganui",
    "sg:classifiers":[
        {
            "category":"Shopping",
            "subcategory":"Crafts & Fabrics",
            "type":"Retail Goods"
        }
    ],
    "sg:phone":"+64 6-345 8816",
    "sg:province":"Manawatu-Wanganui",
    "sg:tags":[
        "foot",
        "clothing",
        "retailer",
        "footwear",
        "wear"
    ],
    "wof:name":"Ashley Jay Shoes",
    "wof:placetype":"venue"
},
  "geometry": {"coordinates":[175.050278,-39.932022],"type":"Point"}
}