{
  "type": "Feature",
  "properties": {
    "iso:country":"NZ",
    "sg:address":"PO Box 27-318 ",
    "sg:city":"Wellington",
    "sg:classifiers":[
        {
            "category":"Education",
            "subcategory":"Special Training",
            "type":"Public Place"
        }
    ],
    "sg:phone":"+64 4-473 3488",
    "sg:province":"Wellington",
    "sg:website":"http://www.smartforce.com",
    "wof:name":"SmartForce New Zealand Ltd",
    "wof:placetype":"venue"
},
  "geometry": {"coordinates":[-94.026131,39.10022],"type":"Point"}
}