{
  "type": "Feature",
  "properties": {
    "iso:country":"NZ",
    "sg:address":"24 Hokonui Dve ",
    "sg:city":"Gore",
    "sg:orig_category":"Shopping: Retail Stores: Secondhand Dealers",
    "sg:phone":"+64 3-208 7743",
    "sg:province":"Southland",
    "wof:name":"Gore Trading Co",
    "wof:placetype":"venue"
},
  "geometry": {"coordinates":[168.937439,-46.100636],"type":"Point"}
}