{
  "type": "Feature",
  "properties": {
    "addr:full":"Charman St  Timaru Canterbury",
    "addr:street":"Charman St",
    "iso:country":"NZ",
    "sg:address":"Charman St ",
    "sg:city":"Timaru",
    "sg:classifiers":[
        {
            "category":"Banks & Credit Unions",
            "subcategory":"Investment Brokerage",
            "type":"Services"
        }
    ],
    "sg:phone":"+64 3-684 8112",
    "sg:province":"Canterbury",
    "sg:tags":[
        "chemical",
        "industrial",
        "-",
        "compounds"
    ],
    "wof:name":"FIL Industries Ltd",
    "wof:placetype":"venue"
},
  "geometry": {"coordinates":[171.26033000000001,-44.392593],"type":"Point"}
}