{
  "type": "Feature",
  "properties": {
    "iso:country":"NZ",
    "sg:address":"Waihou Rd RD 3 Te ",
    "sg:city":"Aroha",
    "sg:orig_category":"Industrial: Metal: Stainless Steel",
    "sg:phone":"+64 7-884 8332",
    "sg:province":"Waikato",
    "wof:name":"R & P Stainless Ltd",
    "wof:placetype":"venue"
},
  "geometry": {"coordinates":[175.707718,-37.534805],"type":"Point"}
}