{
  "type": "Feature",
  "properties": {
    "iso:country":"NZ",
    "sg:address":"34 - 42 Manners Street - P.O. Box 11 - 343 - ",
    "sg:city":"Wellington",
    "sg:classifiers":[
        {
            "category":"Professional",
            "subcategory":"Art Services",
            "type":"Services"
        }
    ],
    "sg:phone":"+64 6443842555",
    "sg:province":"Wellington",
    "sg:tags":[
        "export-import"
    ],
    "sg:website":"http://www.ambafrance - nz.org",
    "wof:name":"French Embassy",
    "wof:placetype":"venue"
},
  "geometry": {"coordinates":[-85.910454,33.827946],"type":"Point"}
}