{
  "type": "Feature",
  "properties": {
    "addr:full":"71 Westlake Dve  Halswell Canterbury",
    "addr:housenumber":"71",
    "addr:street":"Westlake Dve",
    "iso:country":"NZ",
    "sg:address":"71 Westlake Dve ",
    "sg:city":"Halswell",
    "sg:classifiers":[
        {
            "category":"Parking",
            "subcategory":"Garage",
            "type":"Transportation"
        }
    ],
    "sg:phone":"+64 274 339 950",
    "sg:province":"Canterbury",
    "sg:tags":[
        "hire",
        "container",
        "transport",
        "lease"
    ],
    "wof:name":"Dermco Ltd",
    "wof:placetype":"venue"
},
  "geometry": {"coordinates":[172.56651299999999,-43.579105],"type":"Point"}
}