{
  "type": "Feature",
  "properties": {
    "iso:country":"NZ",
    "sg:address":"South Head Rd Sth Kaipara Head R D 1 ",
    "sg:city":"Helensville",
    "sg:orig_category":"Sports And Leisure: Sports: Golf: Golf Courses",
    "sg:phone":"+64 9-420 2838",
    "sg:province":"Auckland",
    "wof:name":"South Head Golf Club Inc",
    "wof:placetype":"venue"
},
  "geometry": {"coordinates":[174.451782,-36.683239],"type":"Point"}
}