{
  "type": "Feature",
  "properties": {
    "addr:full":"27 Reyburn St  Whangarei Northland",
    "addr:housenumber":"27",
    "addr:street":"Reyburn St",
    "iso:country":"NZ",
    "sg:address":"27 Reyburn St ",
    "sg:city":"Whangarei",
    "sg:orig_category":"Industrial: Parts",
    "sg:phone":"+64 9-438 1065",
    "sg:province":"Northland",
    "wof:name":"Northland Communications Ltd",
    "wof:placetype":"venue"
},
  "geometry": {"coordinates":[174.32598899999999,-35.726589],"type":"Point"}
}