{
  "type": "Feature",
  "properties": {
    "addr:full":"Kensington Pharmacy Building 4 Kensington Ave Kensington Whangarei Northland",
    "addr:street":"Kensington Ave",
    "iso:country":"NZ",
    "sg:address":"Kensington Pharmacy Building 4 Kensington Ave Kensington",
    "sg:city":"Whangarei",
    "sg:classifiers":[
        {
            "category":"Health Services",
            "subcategory":"Podiatrist",
            "type":"Services"
        }
    ],
    "sg:phone":"+64 9-437 0005",
    "sg:province":"Northland",
    "sg:tags":[
        "lens",
        "optical",
        "contact",
        "beauty"
    ],
    "wof:name":"Sandra Field",
    "wof:placetype":"venue"
},
  "geometry": {"coordinates":[174.32015999999999,-35.708782],"type":"Point"}
}