{
  "type": "Feature",
  "properties": {
    "addr:full":"199 Cameron Rd  Tauranga Bay of Plenty",
    "addr:housenumber":"199",
    "addr:street":"Cameron Rd",
    "iso:country":"NZ",
    "sg:address":"199 Cameron Rd ",
    "sg:city":"Tauranga",
    "sg:classifiers":[
        {
            "category":"Retail",
            "subcategory":"Auto Repair",
            "type":"Services"
        }
    ],
    "sg:phone":"+64 7-578 0074",
    "sg:province":"Bay of Plenty",
    "sg:tags":[
        "automotive",
        "servicing"
    ],
    "wof:name":"The Car Clinic",
    "wof:placetype":"venue"
},
  "geometry": {"coordinates":[176.165359,-37.685902],"type":"Point"}
}