{
  "type": "Feature",
  "properties": {
    "iso:country":"NZ",
    "sg:address":"33 Remuera Rd Newmarket ",
    "sg:city":"Auckland",
    "sg:classifiers":[
        {
            "category":"Shopping",
            "subcategory":"Bridal",
            "type":"Retail Goods"
        }
    ],
    "sg:phone":"+64 9-522 2225",
    "sg:province":"Auckland",
    "sg:tags":[
        "arrangements",
        "wear",
        "wedding"
    ],
    "wof:name":"Wedding Plaza",
    "wof:placetype":"venue"
},
  "geometry": {"coordinates":[174.77375799999999,-36.867878],"type":"Point"}
}