{
  "type": "Feature",
  "properties": {
    "iso:country":"NZ",
    "sg:address":"1-21 Fraser St ",
    "sg:city":"Timaru",
    "sg:classifiers":[
        {
            "category":"Shopping",
            "subcategory":"Pharmacy",
            "type":"Retail Goods"
        }
    ],
    "sg:phone":"+64 3-688 6208",
    "sg:province":"Canterbury",
    "sg:tags":[
        "products",
        "medical",
        "health",
        "beauty",
        "supply"
    ],
    "wof:name":"Starwood Ltd",
    "wof:placetype":"venue"
},
  "geometry": {"coordinates":[171.26062,-44.399696],"type":"Point"}
}