{
  "type": "Feature",
  "properties": {
    "addr:full":"455 Tremaine Ave Palmerston  Palmerston North Manawatu-Wanganui",
    "addr:housenumber":"455",
    "addr:street":"Tremaine Ave",
    "iso:country":"NZ",
    "sg:address":"455 Tremaine Ave Palmerston ",
    "sg:city":"Palmerston North",
    "sg:orig_category":"Shopping: Sports Retailers: Sports Goods: Canvas Goods",
    "sg:phone":"+64 6-358 0314",
    "sg:province":"Manawatu-Wanganui",
    "wof:name":"Lawrence Motor Trimmers Ltd",
    "wof:placetype":"venue"
},
  "geometry": {"coordinates":[175.59213299999999,-40.347469],"type":"Point"}
}