{
  "type": "Feature",
  "properties": {
    "addr:full":"7 Ecclesfield Gro Silverstream Upper  Hutt Wellington",
    "addr:housenumber":"7",
    "addr:street":"Silverstream",
    "iso:country":"NZ",
    "sg:address":"7 Ecclesfield Gro Silverstream Upper ",
    "sg:city":"Hutt",
    "sg:classifiers":[
        {
            "category":"Education",
            "subcategory":"Music School",
            "type":"Public Place"
        }
    ],
    "sg:phone":"+64 4-528 8559",
    "sg:province":"Wellington",
    "sg:tags":[
        "sport",
        "teacher",
        "leisure"
    ],
    "wof:name":"Modern School of Music",
    "wof:placetype":"venue"
},
  "geometry": {"coordinates":[175.01147499999999,-41.147579],"type":"Point"}
}