{
  "type": "Feature",
  "properties": {
    "addr:full":"Ellerslie 166 Marua Rd  Auckland Auckland",
    "addr:housenumber":"166",
    "addr:street":"Ellerslie;Marua Rd",
    "iso:country":"NZ",
    "sg:address":"Ellerslie 166 Marua Rd ",
    "sg:city":"Auckland",
    "sg:classifiers":[
        {
            "category":"Retail",
            "subcategory":"Laundry & Dry Cleaning",
            "type":"Services"
        }
    ],
    "sg:phone":"+64 9-526 0176",
    "sg:province":"Auckland",
    "sg:tags":[
        "repair",
        "clothing",
        "fabric",
        "cleaner"
    ],
    "wof:name":"Maxwells Drycleaning",
    "wof:placetype":"venue"
},
  "geometry": {"coordinates":[174.77041600000001,-36.884109],"type":"Point"}
}