{
  "type": "Feature",
  "properties": {
    "iso:country":"NZ",
    "sg:address":"211 Jackson St Petone Lower ",
    "sg:city":"Hutt",
    "sg:orig_category":"Shopping: Retail Stores: Books: Bookshops",
    "sg:phone":"+64 4-576 9652",
    "sg:province":"Wellington",
    "wof:name":"Story Time Books for kids",
    "wof:placetype":"venue"
},
  "geometry": {"coordinates":[174.879929,-41.225567],"type":"Point"}
}