{
  "type": "Feature",
  "properties": {
    "addr:full":"20 Hopkins St  Timaru Canterbury",
    "addr:housenumber":"20",
    "addr:street":"Hopkins St",
    "iso:country":"NZ",
    "sg:address":"20 Hopkins St ",
    "sg:city":"Timaru",
    "sg:classifiers":[
        {
            "category":"Shopping",
            "subcategory":"Crafts & Fabrics",
            "type":"Retail Goods"
        }
    ],
    "sg:phone":"+64 3-686 0808",
    "sg:province":"Canterbury",
    "sg:tags":[
        "sport",
        "art",
        "leisure",
        "hobbies"
    ],
    "wof:name":"Paint A Plate",
    "wof:placetype":"venue"
},
  "geometry": {"coordinates":[171.19897499999999,-44.386646],"type":"Point"}
}