{
  "type": "Feature",
  "properties": {
    "addr:full":"PO Box 11-646  Wellington Wellington",
    "addr:housenumber":"po box 11-646",
    "addr:street":"Wellington",
    "iso:country":"NZ",
    "sg:address":"PO Box 11-646 ",
    "sg:city":"Wellington",
    "sg:classifiers":[
        {
            "category":"Bus Charters",
            "type":"Transportation"
        }
    ],
    "sg:phone":"+64 4-801 7000",
    "sg:province":"Wellington",
    "sg:tags":[
        "services",
        "travel",
        "tourism"
    ],
    "wof:name":"Ridewell",
    "wof:placetype":"venue"
},
  "geometry": {"coordinates":[-105.037888,40.762012],"type":"Point"}
}