{
  "type": "Feature",
  "properties": {
    "addr:full":"PO Box 828  Timaru Canterbury",
    "addr:housenumber":"po",
    "addr:street":"Box 828 Timaru",
    "iso:country":"NZ",
    "sg:address":"PO Box 828 ",
    "sg:city":"Timaru",
    "sg:classifiers":[
        {
            "category":"Home & Garden",
            "subcategory":"Building Materials",
            "type":"Retail Goods"
        }
    ],
    "sg:phone":"+64 274 323 137",
    "sg:province":"Canterbury",
    "sg:tags":[
        "builder",
        "related"
    ],
    "wof:name":"Rickie Shore Building Ltd",
    "wof:placetype":"venue"
},
  "geometry": {"coordinates":[171.23741100000001,-44.395428],"type":"Point"}
}