{
  "type": "Feature",
  "properties": {
    "addr:full":"52 The Square Palmerston  Palmerston North Wellington",
    "addr:housenumber":"52",
    "addr:street":"The Square",
    "iso:country":"NZ",
    "sg:address":"52 The Square Palmerston ",
    "sg:city":"Palmerston North",
    "sg:classifiers":[
        {
            "category":"Landmark",
            "subcategory":"Tourist Information",
            "type":"Public Place"
        }
    ],
    "sg:phone":"+64 6-354 6593",
    "sg:province":"Wellington",
    "sg:tags":[
        "services",
        "travel",
        "tourism"
    ],
    "wof:name":"Palmerston North",
    "wof:placetype":"venue"
},
  "geometry": {"coordinates":[175.611481,-40.357418],"type":"Point"}
}