{
  "type": "Feature",
  "properties": {
    "iso:country":"NZ",
    "sg:address":"Chartwell Square ",
    "sg:city":"Hamilton",
    "sg:classifiers":[
        {
            "category":"Shopping",
            "subcategory":"Crafts & Fabrics",
            "type":"Retail Goods"
        }
    ],
    "sg:phone":"+64 7-855 4913",
    "sg:province":"Waikato",
    "sg:tags":[
        "foot",
        "clothing",
        "retailer",
        "footwear",
        "wear"
    ],
    "wof:name":"Hannahs Shoes",
    "wof:placetype":"venue"
},
  "geometry": {"coordinates":[175.27124,-37.763653],"type":"Point"}
}