{
  "type": "Feature",
  "properties": {
    "iso:country":"NZ",
    "sg:address":"Seaside Rd ",
    "sg:city":"Ashburton",
    "sg:classifiers":[
        {
            "category":"Wholesale",
            "subcategory":"Meat",
            "type":"Manufacturing & Wholesale Goods"
        }
    ],
    "sg:phone":"+64 3-308 1599",
    "sg:province":"Canterbury",
    "sg:tags":[
        "food",
        "distributor",
        "drink",
        "meats"
    ],
    "wof:name":"Five Star Beef Ltd",
    "wof:placetype":"venue"
},
  "geometry": {"coordinates":[-77.1278305054,39.0128517151],"type":"Point"}
}