{
  "type": "Feature",
  "properties": {
    "addr:full":"419 A Church St Onehunga  Auckland Auckland",
    "addr:housenumber":"419 a",
    "addr:street":"Church St",
    "iso:country":"NZ",
    "sg:address":"419 A Church St Onehunga ",
    "sg:city":"Auckland",
    "sg:classifiers":[
        {
            "category":"Retail",
            "subcategory":"Auto Repair",
            "type":"Services"
        }
    ],
    "sg:phone":"+64 9-579 0854",
    "sg:province":"Auckland",
    "sg:tags":[
        "wheel",
        "automotive",
        "servicing",
        "alignment"
    ],
    "wof:name":"Auckland Truck Wheel Alignment Specialists",
    "wof:placetype":"venue"
},
  "geometry": {"coordinates":[174.79212999999999,-36.922318],"type":"Point"}
}