{
  "type": "Feature",
  "properties": {
    "iso:country":"NZ",
    "sg:address":"51 Wakefield St Onekawa ",
    "sg:city":"Napier",
    "sg:classifiers":[
        {
            "category":"Home & Garden",
            "subcategory":"Kitchen Supply",
            "type":"Retail Goods"
        }
    ],
    "sg:phone":"+64 6-843 8230",
    "sg:province":"Hawke's Bay",
    "sg:tags":[
        "food",
        "equipment",
        "drink",
        "catering"
    ],
    "wof:name":"Bruce Moroney Electrical Ltd",
    "wof:placetype":"venue"
},
  "geometry": {"coordinates":[176.880997,-39.501904],"type":"Point"}
}