{
  "type": "Feature",
  "properties": {
    "addr:full":"19 Young Street  Wanganui Canterbury",
    "addr:housenumber":"19",
    "addr:street":"Young Street",
    "iso:country":"NZ",
    "sg:address":"19 Young Street ",
    "sg:city":"Wanganui",
    "sg:classifiers":[
        {
            "category":"Building & Trades",
            "subcategory":"Pest Control",
            "type":"Services"
        }
    ],
    "sg:phone":"+64 6-343 9933",
    "sg:province":"Canterbury",
    "sg:tags":[
        "home",
        "garden"
    ],
    "wof:name":"Bugs or Us",
    "wof:placetype":"venue"
},
  "geometry": {"coordinates":[175.05708300000001,-39.91283],"type":"Point"}
}