{
  "type": "Feature",
  "properties": {
    "addr:full":"166 Seaview Rd North New Brighton  Christchurch Canterbury",
    "addr:housenumber":"166",
    "addr:street":"Seaview Rd North",
    "iso:country":"NZ",
    "sg:address":"166 Seaview Rd North New Brighton ",
    "sg:city":"Christchurch",
    "sg:classifiers":[
        {
            "category":"Health Services",
            "subcategory":"Podiatrist",
            "type":"Services"
        }
    ],
    "sg:phone":"+64 3-388 8981",
    "sg:province":"Canterbury",
    "sg:tags":[
        "lens",
        "optical",
        "contact",
        "beauty"
    ],
    "wof:name":"Vision One",
    "wof:placetype":"venue"
},
  "geometry": {"coordinates":[172.72311400000001,-43.508621],"type":"Point"}
}