{
  "type": "Feature",
  "properties": {
    "iso:country":"NZ",
    "sg:address":"Cnr Church & Linton Sts Palmerston ",
    "sg:city":"Palmerston North",
    "sg:classifiers":[
        {
            "category":"Social Services",
            "subcategory":"Job Training",
            "type":"Services"
        }
    ],
    "sg:phone":"+64 6-350 5825",
    "sg:province":"Manawatu-Wanganui",
    "sg:tags":[
        "education"
    ],
    "sg:website":"http://www.nzoq.org.nz",
    "wof:name":"NZ Organisation for Quality",
    "wof:placetype":"venue"
},
  "geometry": {"coordinates":[175.553879,-40.432301],"type":"Point"}
}