{
  "type": "Feature",
  "properties": {
    "addr:full":"Cnr Church & Linton Sts Palmerston  Palmerston North Manawatu-Wanganui",
    "addr:housenumber":"cnr",
    "addr:street":"&;Sts",
    "iso:country":"NZ",
    "sg:address":"Cnr Church & Linton Sts Palmerston ",
    "sg:city":"Palmerston North",
    "sg:classifiers":[
        {
            "category":"Social Services",
            "subcategory":"Job Training",
            "type":"Services"
        }
    ],
    "sg:phone":"+64 6-350 5825",
    "sg:province":"Manawatu-Wanganui",
    "sg:tags":[
        "education"
    ],
    "sg:website":"http://www.nzoq.org.nz",
    "wof:name":"NZ Organisation for Quality",
    "wof:placetype":"venue"
},
  "geometry": {"coordinates":[175.55387899999999,-40.432301],"type":"Point"}
}