{
  "type": "Feature",
  "properties": {
    "iso:country":"NZ",
    "sg:address":"28 Lawson St Belleknowes ",
    "sg:city":"Dunedin",
    "sg:classifiers":[
        {
            "category":"Arena",
            "subcategory":"Sports Club",
            "type":"Entertainment"
        }
    ],
    "sg:phone":"+64 3-477 4805",
    "sg:province":"Otago",
    "sg:tags":[
        "-",
        "leisure",
        "sports"
    ],
    "wof:name":"Punga Croquet Club",
    "wof:placetype":"venue"
},
  "geometry": {"coordinates":[170.48048399999999,-45.876404],"type":"Point"}
}