{
  "type": "Feature",
  "properties": {
    "addr:full":"64 Ashurst Ave  Hamilton Waikato",
    "addr:housenumber":"64",
    "addr:street":"Ashurst Ave",
    "iso:country":"NZ",
    "sg:address":"64 Ashurst Ave ",
    "sg:city":"Hamilton",
    "sg:orig_category":"Transport: Transportation: Courier Services",
    "sg:phone":"+64 25864465",
    "sg:province":"Waikato",
    "wof:name":"Cowan Couriers",
    "wof:placetype":"venue"
},
  "geometry": {"coordinates":[-74.752594,40.218876],"type":"Point"}
}