{
  "type": "Feature",
  "properties": {
    "iso:country":"NZ",
    "sg:address":"40 Ingestre St ",
    "sg:city":"Wanganui",
    "sg:classifiers":[
        {
            "category":"Banks & Credit Unions",
            "subcategory":"Investment Brokerage",
            "type":"Services"
        }
    ],
    "sg:phone":"+64 6-348 8148",
    "sg:province":"Manawatu-Wanganui",
    "sg:tags":[
        "personal",
        "accountant",
        "chartered",
        "-",
        "finance"
    ],
    "wof:name":"Richard Millward & Associates LTD",
    "wof:placetype":"venue"
},
  "geometry": {"coordinates":[175.049438,-39.928364],"type":"Point"}
}