{
  "type": "Feature",
  "properties": {
    "iso:country":"NZ",
    "sg:address":"Unit G 7 Douglas Alexander Pde Albany ",
    "sg:city":"Auckland",
    "sg:classifiers":[
        {
            "category":"Wholesale",
            "subcategory":"Meat",
            "type":"Manufacturing & Wholesale Goods"
        }
    ],
    "sg:phone":"+64 9-415 3460",
    "sg:province":"Auckland",
    "sg:tags":[
        "food",
        "equipment",
        "drink",
        "abattoir",
        "meats"
    ],
    "wof:name":"Hennessy Grading Systems Ltd",
    "wof:placetype":"venue"
},
  "geometry": {"coordinates":[174.709686,-36.720142],"type":"Point"}
}