{
  "type": "Feature",
  "properties": {
    "addr:full":"PO Box 19 846  Christchurch Canterbury",
    "addr:housenumber":"po box 19 846",
    "addr:street":"Christchurch",
    "iso:country":"NZ",
    "sg:address":"PO Box 19 846 ",
    "sg:city":"Christchurch",
    "sg:classifiers":[
        {
            "category":"Shopping",
            "subcategory":"Pharmacy",
            "type":"Retail Goods"
        }
    ],
    "sg:phone":"+64 3-379 9200",
    "sg:province":"Canterbury",
    "sg:tags":[
        "products",
        "medical",
        "health",
        "beauty",
        "supply"
    ],
    "wof:name":"Cooper Medical",
    "wof:placetype":"venue"
},
  "geometry": {"coordinates":[-76.537834,37.605659],"type":"Point"}
}