{
  "type": "Feature",
  "properties": {
    "iso:country":"NZ",
    "sg:address":"801 Colombo St ",
    "sg:city":"Christchurch",
    "sg:classifiers":[
        {
            "category":"Banks & Credit Unions",
            "subcategory":"Investment Brokerage",
            "type":"Services"
        }
    ],
    "sg:phone":"+64 3-366 1952",
    "sg:province":"Canterbury",
    "sg:tags":[
        "services",
        "industrial",
        "refrigeration",
        "servicing"
    ],
    "wof:name":"Surefreeze Appliances Ltd",
    "wof:placetype":"venue"
},
  "geometry": {"coordinates":[172.636475,-43.526043],"type":"Point"}
}