{
  "type": "Feature",
  "properties": {
    "iso:country":"NZ",
    "sg:address":"233 Scenic Dve Titirangi ",
    "sg:city":"Auckland",
    "sg:orig_category":"Home And Garden: Children: Child Related: Children'S Entertainment",
    "sg:phone":"+64 9-817 1154",
    "sg:province":"Auckland",
    "wof:name":"The Underworld at Scenic Cafe",
    "wof:placetype":"venue"
},
  "geometry": {"coordinates":[174.66279599999999,-36.926861],"type":"Point"}
}