{
  "type": "Feature",
  "properties": {
    "iso:country":"NZ",
    "sg:address":"27 King Edward Tce ",
    "sg:city":"Woolston",
    "sg:classifiers":[
        {
            "category":"Home & Garden",
            "subcategory":"Garden Supply",
            "type":"Retail Goods"
        }
    ],
    "sg:phone":"+64 800 800 9473",
    "sg:province":"Canterbury",
    "sg:tags":[
        "fencing",
        "outdoor",
        "contractor"
    ],
    "wof:name":"Hurricane Wire Products Ltd",
    "wof:placetype":"venue"
},
  "geometry": {"coordinates":[-2.849113,52.479507],"type":"Point"}
}