{
  "type": "Feature",
  "properties": {
    "iso:country":"NZ",
    "sg:address":"51 Mackay St ",
    "sg:city":"Greymouth",
    "sg:orig_category":"Shopping: Retail Stores: Secondhand Dealers",
    "sg:phone":"+64 3-768 4533",
    "sg:province":"West Coast",
    "wof:name":"Recollections",
    "wof:placetype":"venue"
},
  "geometry": {"coordinates":[171.209473,-42.44854],"type":"Point"}
}