{
  "type": "Feature",
  "properties": {
    "addr:full":"Shop 7, Raumati Village, Raumati Beach  Paraparaumu Wellington",
    "addr:housenumber":"shop 7",
    "addr:street":"Raumati Village",
    "iso:country":"NZ",
    "sg:address":"Shop 7, Raumati Village, Raumati Beach ",
    "sg:city":"Paraparaumu",
    "sg:classifiers":[
        {
            "category":"Professional",
            "subcategory":"Art Services",
            "type":"Services"
        }
    ],
    "sg:phone":"+64 4-902 5626",
    "sg:province":"Wellington",
    "sg:tags":[
        "picture",
        "arts",
        "sport",
        "framing",
        "leisure"
    ],
    "wof:name":"Framework",
    "wof:placetype":"venue"
},
  "geometry": {"coordinates":[175.00799599999999,-40.910465],"type":"Point"}
}