{
  "type": "Feature",
  "properties": {
    "addr:full":"22 Dunlop Rd Onekawa  Napier Hawke's Bay",
    "addr:housenumber":"22",
    "addr:street":"Dunlop Rd",
    "iso:country":"NZ",
    "sg:address":"22 Dunlop Rd Onekawa ",
    "sg:city":"Napier",
    "sg:orig_category":"Industrial: Metal: Services: Steel Processing",
    "sg:phone":"+64 6-843 3533",
    "sg:province":"Hawke's Bay",
    "wof:name":"Meshmakers Ltd",
    "wof:placetype":"venue"
},
  "geometry": {"coordinates":[176.88528400000001,-39.503292],"type":"Point"}
}