{
  "type": "Feature",
  "properties": {
    "addr:full":"cnr Webb & Taranaki Sts  Wellington Wellington",
    "addr:street":"Cnr Webb",
    "iso:country":"NZ",
    "sg:address":"cnr Webb & Taranaki Sts ",
    "sg:city":"Wellington",
    "sg:orig_category":"Shopping: Tobacco: Tobacco Outlets",
    "sg:phone":"+64 4-385 8992",
    "sg:province":"Wellington",
    "wof:name":"British American Tobacco (New Zealand) Limited",
    "wof:placetype":"venue"
},
  "geometry": {"coordinates":[174.37120100000001,-39.127789],"type":"Point"}
}