{
  "type": "Feature",
  "properties": {
    "addr:full":"Kopeopeo Health Centre  Whakatane Bay of Plenty",
    "addr:street":"Whakatane",
    "iso:country":"NZ",
    "sg:address":"Kopeopeo Health Centre ",
    "sg:city":"Whakatane",
    "sg:orig_category":"Health And Beauty: Specialists: Physiotherapists",
    "sg:phone":"+64 7-308 0969",
    "sg:province":"Bay of Plenty",
    "wof:name":"Physiotherapy Associates",
    "wof:placetype":"venue"
},
  "geometry": {"coordinates":[176.98419200000001,-37.965305],"type":"Point"}
}