{
  "type": "Feature",
  "properties": {
    "iso:country":"NZ",
    "sg:address":"244 Victoria Ave ",
    "sg:city":"Wanganui",
    "sg:classifiers":[
        {
            "category":"Autos & Motor Vehicles",
            "subcategory":"Automobile Sales",
            "type":"Retail Goods"
        }
    ],
    "sg:phone":"+64 6-347 2012",
    "sg:province":"Manawatu-Wanganui",
    "sg:tags":[
        "car",
        "-used",
        "leasing",
        "truck",
        "automotive"
    ],
    "wof:name":"Maxwells Car Court LMVD",
    "wof:placetype":"venue"
},
  "geometry": {"coordinates":[175.046188,-39.92926],"type":"Point"}
}