{
  "type": "Feature",
  "properties": {
    "addr:full":"517 Manukau Rd Epsom  Auckland Auckland",
    "addr:housenumber":"517",
    "addr:street":"Manukau Rd",
    "iso:country":"NZ",
    "sg:address":"517 Manukau Rd Epsom ",
    "sg:city":"Auckland",
    "sg:classifiers":[
        {
            "category":"Home & Garden",
            "subcategory":"Home Furnishings",
            "type":"Retail Goods"
        }
    ],
    "sg:phone":"+64 9-623 8415",
    "sg:province":"Auckland",
    "sg:tags":[
        "furniture/furnishings",
        "bedding",
        "bed"
    ],
    "wof:name":"Growing Up Ltd",
    "wof:placetype":"venue"
},
  "geometry": {"coordinates":[174.77375799999999,-36.896404],"type":"Point"}
}