{
  "type": "Feature",
  "properties": {
    "iso:country":"NZ",
    "sg:address":"6 Greens La ",
    "sg:city":"Rahotu",
    "sg:classifiers":[
        {
            "category":"Retail",
            "subcategory":"Auto Repair",
            "type":"Services"
        }
    ],
    "sg:phone":"+64 6-763 8462",
    "sg:tags":[
        "automotive",
        "panel",
        "servicing",
        "beater"
    ],
    "wof:name":"Rahotu Panel & Paint",
    "wof:placetype":"venue"
},
  "geometry": {"coordinates":[173.80571,-39.33345],"type":"Point"}
}