{
  "type": "Feature",
  "properties": {
    "addr:full":"The Corner The Square  Methven Wellington",
    "addr:street":"The Square",
    "iso:country":"NZ",
    "sg:address":"The Corner The Square ",
    "sg:city":"Methven",
    "sg:classifiers":[
        {
            "category":"Fast Food",
            "type":"Food & Drink"
        }
    ],
    "sg:phone":"+64 3-302 8237",
    "sg:province":"Wellington",
    "sg:tags":[
        "wining",
        "dining",
        "takeaway"
    ],
    "wof:name":"Uncle Dominic's Pizza & Kebabs",
    "wof:placetype":"venue"
},
  "geometry": {"coordinates":[171.64428699999999,-43.631439],"type":"Point"}
}