{
  "type": "Feature",
  "properties": {
    "iso:country":"NZ",
    "sg:address":"595 Victoria St ",
    "sg:city":"Hamilton",
    "sg:classifiers":[
        {
            "category":"Fast Food",
            "type":"Food & Drink"
        }
    ],
    "sg:phone":"+64 7-839 5590",
    "sg:province":"Waikato",
    "sg:tags":[
        "wining",
        "dining",
        "takeaway"
    ],
    "wof:name":"Hoaghies Take-Aways",
    "wof:placetype":"venue"
},
  "geometry": {"coordinates":[142.025467,-37.734207],"type":"Point"}
}