{
  "type": "Feature",
  "properties": {
    "iso:country":"NZ",
    "sg:address":"81 Waimauku Station Rd Waimauku ",
    "sg:city":"Auckland",
    "sg:classifiers":[
        {
            "category":"Professional",
            "type":"Services"
        }
    ],
    "sg:phone":"+64 9-411 7809",
    "sg:province":"Auckland",
    "sg:tags":[
        "function",
        "entertainment",
        "leisure",
        "planning",
        "party",
        "sport"
    ],
    "wof:name":"Settlers Lodge Bar & Restaurant",
    "wof:placetype":"venue"
},
  "geometry": {"coordinates":[174.491837,-36.764091],"type":"Point"}
}