{
  "type": "Feature",
  "properties": {
    "iso:country":"NZ",
    "sg:address":"Shop 46a, Westfield Shoppingtown ",
    "sg:city":"Manukau",
    "sg:classifiers":[
        {
            "category":"Shopping",
            "subcategory":"Beauty & Cosmetics",
            "type":"Retail Goods"
        }
    ],
    "sg:phone":"+64 9-263 7055",
    "sg:tags":[
        "supply",
        "health",
        "hairdressing"
    ],
    "wof:name":"Shampoo n' Things",
    "wof:placetype":"venue"
},
  "geometry": {"coordinates":[173.203003,-35.221741],"type":"Point"}
}