{
  "type": "Feature",
  "properties": {
    "iso:country":"NZ",
    "sg:address":"131 Hilton Highway Washdyke ",
    "sg:city":"Timaru",
    "sg:classifiers":[
        {
            "category":"Retail",
            "subcategory":"Laundry & Dry Cleaning",
            "type":"Services"
        }
    ],
    "sg:phone":"+64 3-688 2185",
    "sg:province":"Canterbury",
    "sg:tags":[
        "product",
        "wool",
        "clothing",
        "fabric"
    ],
    "wof:name":"South Island Black Wool Pool",
    "wof:placetype":"venue"
},
  "geometry": {"coordinates":[171.23788500000001,-44.352978],"type":"Point"}
}