{
  "type": "Feature",
  "properties": {
    "iso:country":"NZ",
    "sg:address":"Windsor Rd Bellevue ",
    "sg:city":"Tauranga",
    "sg:orig_category":"Education And Training: General: Schools",
    "sg:phone":"+64 7-576 2316",
    "sg:province":"Bay of Plenty",
    "wof:name":"Otumoetai College",
    "wof:placetype":"venue"
},
  "geometry": {"coordinates":[176.12828099999999,-37.684273],"type":"Point"}
}