{
  "type": "Feature",
  "properties": {
    "iso:country":"NZ",
    "sg:address":"52 Preston Rd ",
    "sg:city":"Greymouth",
    "sg:classifiers":[
        {
            "category":"Mining & Drilling",
            "type":"Manufacturing & Wholesale Goods"
        }
    ],
    "sg:phone":"+64 3-768 0088",
    "sg:province":"West Coast",
    "sg:tags":[
        "raw",
        "industrial",
        "mineral",
        "materials"
    ],
    "wof:name":"Sandvik New Zealand Ltd",
    "wof:placetype":"venue"
},
  "geometry": {"coordinates":[171.19773900000001,-42.452484],"type":"Point"}
}