{
  "type": "Feature",
  "properties": {
    "iso:country":"NZ",
    "sg:address":"Unit 7 67 View Rd Glenfield ",
    "sg:city":"Auckland",
    "sg:orig_category":"Farming: Supplies",
    "sg:phone":"+64 9-443 0106",
    "sg:province":"Auckland",
    "wof:name":"Switched On Gardener",
    "wof:placetype":"venue"
},
  "geometry": {"coordinates":[174.73667900000001,-36.771469],"type":"Point"}
}