{
  "type": "Feature",
  "properties": {
    "addr:full":"PO Box 10 100  Wellington Wellington",
    "addr:housenumber":"po box 10 100",
    "iso:country":"NZ",
    "sg:address":"PO Box 10 100 ",
    "sg:city":"Wellington",
    "sg:orig_category":"Transport: Land: Taxis",
    "sg:phone":"+64 4-388 8888",
    "sg:province":"Wellington",
    "wof:name":"Gold & Black Taxis",
    "wof:placetype":"venue"
},
  "geometry": {"coordinates":[-87.692841,40.560177],"type":"Point"}
}