{
  "type": "Feature",
  "properties": {
    "iso:country":"NZ",
    "sg:address":"19 Sabulite Rd Glen Eden ",
    "sg:city":"Auckland",
    "sg:orig_category":"Industrial: Services: Specialist Services: Electroplating/Polishing",
    "sg:phone":"+64 9-818 8924",
    "sg:province":"Auckland",
    "wof:name":"Terei Brothers Holdings Ltd",
    "wof:placetype":"venue"
},
  "geometry": {"coordinates":[174.65625,-36.901039],"type":"Point"}
}