{
  "type": "Feature",
  "properties": {
    "iso:country":"NZ",
    "sg:address":"2 Catherine Pl Henderson ",
    "sg:city":"Auckland",
    "sg:classifiers":[
        {
            "category":"Organizations",
            "subcategory":"Labor Organization",
            "type":"Services"
        }
    ],
    "sg:phone":"+64 9-838 9881",
    "sg:province":"Auckland",
    "sg:tags":[
        "cake",
        "arrangements",
        "wedding"
    ],
    "wof:name":"Special Occasions Cake Design",
    "wof:placetype":"venue"
},
  "geometry": {"coordinates":[174.632797,-36.879848],"type":"Point"}
}