{
  "type": "Feature",
  "properties": {
    "iso:country":"NZ",
    "sg:address":"2 Rina St ",
    "sg:city":"Levin",
    "sg:classifiers":[
        {
            "category":"Retail",
            "subcategory":"Auto Repair",
            "type":"Services"
        }
    ],
    "sg:phone":"+64 6-368 4058",
    "sg:province":"Manawatu-Wanganui",
    "sg:tags":[
        "wheel",
        "automotive",
        "servicing",
        "alignment"
    ],
    "wof:name":"Emmerson Wheel Alignment",
    "wof:placetype":"venue"
},
  "geometry": {"coordinates":[175.277634,-40.630543],"type":"Point"}
}