{
  "type": "Feature",
  "properties": {
    "addr:full":"Woodlands Rd RD2  Waihi",
    "addr:postcode":"rd2",
    "addr:street":"Woodlands Rd",
    "iso:country":"NZ",
    "sg:address":"Woodlands Rd RD2 ",
    "sg:city":"Waihi",
    "sg:orig_category":"Food And Drink: Meats: Butchers",
    "sg:phone":"+64 7-863 7983",
    "sg:website":"http://www.cambrianmeats.co.nz",
    "wof:name":"Cambrian Meats",
    "wof:placetype":"venue"
},
  "geometry": {"coordinates":[175.83845500000001,-37.388897],"type":"Point"}
}