{
  "type": "Feature",
  "properties": {
    "addr:full":"92 Wilsons Rd St Martins  Christchurch Canterbury",
    "addr:housenumber":"92",
    "addr:street":"Wilsons Rd",
    "iso:country":"NZ",
    "sg:address":"92 Wilsons Rd St Martins ",
    "sg:city":"Christchurch",
    "sg:orig_category":"Health And Beauty: Products: Pharmacies",
    "sg:phone":"+64 3-332 6338",
    "sg:province":"Canterbury",
    "wof:name":"St Martins Pharmacy Ltd",
    "wof:placetype":"venue"
},
  "geometry": {"coordinates":[172.65237400000001,-43.555965],"type":"Point"}
}