{
  "type": "Feature",
  "properties": {
    "iso:country":"NZ",
    "sg:address":"Palmerston ",
    "sg:city":"Palmerston North",
    "sg:orig_category":"Industrial: Packaging: Packaging - General",
    "sg:phone":"+64 6-358 5193",
    "sg:province":"Manawatu-Wanganui",
    "wof:name":"Lanwood Plastics Ltd",
    "wof:placetype":"venue"
},
  "geometry": {"coordinates":[175.611481,-40.357418],"type":"Point"}
}