{
  "type": "Feature",
  "properties": {
    "iso:country":"NZ",
    "sg:address":"20 Morgan St Newmarket ",
    "sg:city":"Auckland",
    "sg:classifiers":[
        {
            "category":"Retail",
            "subcategory":"Auto Repair",
            "type":"Services"
        }
    ],
    "sg:phone":"+64 9-373 5095",
    "sg:province":"Auckland",
    "sg:tags":[
        "automotive",
        "panel",
        "servicing",
        "beater"
    ],
    "wof:name":"Parkside Of Newmarket Panel & Paint",
    "wof:placetype":"venue"
},
  "geometry": {"coordinates":[174.776779,-36.863949],"type":"Point"}
}