{
  "type": "Feature",
  "properties": {
    "addr:full":"1 Greenwood St  Hamilton Waikato",
    "addr:housenumber":"1",
    "addr:street":"Greenwood St",
    "iso:country":"NZ",
    "sg:address":"1 Greenwood St ",
    "sg:city":"Hamilton",
    "sg:classifiers":[
        {
            "category":"Communications",
            "subcategory":"Film & Video Production",
            "type":"Services"
        }
    ],
    "sg:phone":"+64 7-846 1959",
    "sg:province":"Waikato",
    "sg:tags":[
        "sport",
        "leisure",
        "library",
        "entertainment"
    ],
    "wof:name":"Video Ezy Greenwood",
    "wof:placetype":"venue"
},
  "geometry": {"coordinates":[-74.760239,40.214169],"type":"Point"}
}