{
  "type": "Feature",
  "properties": {
    "iso:country":"NZ",
    "sg:address":"PO Box 12-333 Chartwell Square ",
    "sg:city":"Hamilton",
    "sg:classifiers":[
        {
            "category":"Home & Garden",
            "subcategory":"Garden Supply",
            "type":"Retail Goods"
        }
    ],
    "sg:phone":"+64 7-855 5948",
    "sg:province":"Waikato",
    "sg:tags":[
        "products",
        "lawn",
        "gardening",
        "turf"
    ],
    "wof:name":"Turf Works",
    "wof:placetype":"venue"
},
  "geometry": {"coordinates":[175.276993,-37.783215],"type":"Point"}
}