{
  "type": "Feature",
  "properties": {
    "iso:country":"NZ",
    "sg:address":"Level 2, 160 Willis St ",
    "sg:city":"Wellington",
    "sg:orig_category":"Transport: Boats And Marine: Shipping",
    "sg:phone":"+64 4-499 3050",
    "sg:province":"Wellington",
    "wof:name":"EBI Corporation NZ Ltd",
    "wof:placetype":"venue"
},
  "geometry": {"coordinates":[-87.675285,40.541164],"type":"Point"}
}