{
  "type": "Feature",
  "properties": {
    "iso:country":"NZ",
    "sg:address":"133 Maces Rd Bromley ",
    "sg:city":"Christchurch",
    "sg:classifiers":[
        {
            "category":"Home & Garden",
            "subcategory":"Kitchen Supply",
            "type":"Retail Goods"
        }
    ],
    "sg:phone":"+64 3-384 4770",
    "sg:province":"Canterbury",
    "sg:tags":[
        "shop",
        "pet",
        "pets"
    ],
    "wof:name":"Eastern Trellis",
    "wof:placetype":"venue"
},
  "geometry": {"coordinates":[172.693115,-43.537277],"type":"Point"}
}