{
  "type": "Feature",
  "properties": {
    "addr:full":"Technology Services Building Springs Rd Lincoln  Christchurch Canterbury",
    "addr:street":"Springs Rd",
    "iso:country":"NZ",
    "sg:address":"Technology Services Building Springs Rd Lincoln ",
    "sg:city":"Christchurch",
    "sg:orig_category":"Industrial: Engineering: Engineers - Manufacturing",
    "sg:phone":"+64 3-325 3027",
    "sg:province":"Canterbury",
    "sg:website":"http://www.yellowpages.co.nz/for/linclab/dp7199.html",
    "wof:name":"LincLab",
    "wof:placetype":"venue"
},
  "geometry": {"coordinates":[172.48481799999999,-43.64016],"type":"Point"}
}