{
  "type": "Feature",
  "properties": {
    "addr:full":"130 Stornoway St Karitane  Waikouaiti",
    "addr:housenumber":"130",
    "addr:street":"Stornoway St",
    "iso:country":"NZ",
    "sg:address":"130 Stornoway St Karitane ",
    "sg:city":"Waikouaiti",
    "sg:orig_category":"Shopping: Retail Stores: Supermarkets",
    "sg:phone":"+64 3-465 7331",
    "wof:name":"Karitane Stores",
    "wof:placetype":"venue"
},
  "geometry": {"coordinates":[170.65660099999999,-45.63982],"type":"Point"}
}