{
  "type": "Feature",
  "properties": {
    "iso:country":"NZ",
    "sg:address":"130 Stornoway St Karitane ",
    "sg:city":"Waikouaiti",
    "sg:orig_category":"Shopping: Retail Stores: Supermarkets",
    "sg:phone":"+64 3-465 7331",
    "wof:name":"Karitane Stores",
    "wof:placetype":"venue"
},
  "geometry": {"coordinates":[170.656601,-45.63982],"type":"Point"}
}