{
  "type": "Feature",
  "properties": {
    "iso:country":"NZ",
    "sg:address":"28 Lorne St Auckland Central ",
    "sg:city":"Auckland",
    "sg:classifiers":[
        {
            "category":"Personal",
            "subcategory":"Skin Care",
            "type":"Services"
        }
    ],
    "sg:phone":"+64 9-377 0832",
    "sg:province":"Auckland",
    "sg:tags":[
        "introduction",
        "services",
        "garden",
        "home"
    ],
    "wof:name":"Ceroc Dance",
    "wof:placetype":"venue"
},
  "geometry": {"coordinates":[174.76577800000001,-36.850357],"type":"Point"}
}