{
  "type": "Feature",
  "properties": {
    "iso:country":"NZ",
    "sg:address":"8 Constable St Newtown ",
    "sg:city":"Wellington",
    "sg:classifiers":[
        {
            "category":"Food Court",
            "type":"Food & Drink"
        }
    ],
    "sg:phone":"+64 4-389 6868",
    "sg:province":"Wellington",
    "sg:tags":[
        "brew",
        "home",
        "supply"
    ],
    "wof:name":"Brewers World Wellington",
    "wof:placetype":"venue"
},
  "geometry": {"coordinates":[174.78019699999999,-41.313812],"type":"Point"}
}