{
  "type": "Feature",
  "properties": {
    "iso:country":"NZ",
    "sg:address":"Tararua Windfarm Treks, Gorge Rd R D 3 Ballance ",
    "sg:city":"Pahiatua",
    "sg:classifiers":[
        {
            "category":"Travel",
            "subcategory":"Travel Agent",
            "type":"Entertainment"
        }
    ],
    "sg:phone":"+64 6-376 6157",
    "sg:tags":[
        "tour",
        "tourism",
        "adventure",
        "sightseeing"
    ],
    "wof:name":"Clydesdale Wagon & Riding Adventures",
    "wof:placetype":"venue"
},
  "geometry": {"coordinates":[175.773636,-40.402111],"type":"Point"}
}