{
  "type": "Feature",
  "properties": {
    "iso:country":"NZ",
    "sg:address":"PO Box 1603 ",
    "sg:city":"Christchurch",
    "sg:classifiers":[
        {
            "category":"Arena",
            "subcategory":"Sports Club",
            "type":"Entertainment"
        }
    ],
    "sg:phone":"+64 25392203",
    "sg:province":"Canterbury",
    "sg:tags":[
        "arts",
        "writer",
        "leisure",
        "author"
    ],
    "wof:name":"Patricia Thornton & Associates Ltd",
    "wof:placetype":"venue"
},
  "geometry": {"coordinates":[-76.537834,37.605659],"type":"Point"}
}