{
  "type": "Feature",
  "properties": {
    "addr:full":"169 Great North Rd  Winton",
    "addr:housenumber":"169",
    "addr:street":"Great North Rd",
    "iso:country":"NZ",
    "sg:address":"169 Great North Rd ",
    "sg:city":"Winton",
    "sg:classifiers":[
        {
            "category":"Manufacturing",
            "subcategory":"Tools & Machinery",
            "type":"Manufacturing & Wholesale Goods"
        }
    ],
    "sg:phone":"+64 3-236 7275",
    "sg:tags":[
        "equipment",
        "industrial",
        "hydraulic"
    ],
    "wof:name":"McMaster Engineering",
    "wof:placetype":"venue"
},
  "geometry": {"coordinates":[-120.61348,37.386436],"type":"Point"}
}