{
  "type": "Feature",
  "properties": {
    "iso:country":"NZ",
    "sg:address":"23 Noel Rodgers Pl Palmerston ",
    "sg:city":"Palmerston North",
    "sg:orig_category":"Farming: Machinery",
    "sg:phone":"+64 6-356 8781",
    "sg:province":"Manawatu-Wanganui",
    "wof:name":"Mech Traders",
    "wof:placetype":"venue"
},
  "geometry": {"coordinates":[175.627487,-40.3242],"type":"Point"}
}