{
  "type": "Feature",
  "properties": {
    "iso:country":"NZ",
    "sg:address":"2001 Te Rapa Rd ",
    "sg:city":"Hamilton",
    "sg:orig_category":"Industrial: Products: Filters And Filtration",
    "sg:phone":"+64 7-849 2134",
    "sg:province":"Waikato",
    "wof:name":"Silicon Industries NZ Ltd",
    "wof:placetype":"venue"
},
  "geometry": {"coordinates":[175.26083399999999,-37.767639],"type":"Point"}
}