{
  "type": "Feature",
  "properties": {
    "addr:full":"154 Railside Ave Henderson  Auckland Auckland",
    "addr:housenumber":"154",
    "addr:street":"Railside Ave",
    "iso:country":"NZ",
    "sg:address":"154 Railside Ave Henderson ",
    "sg:city":"Auckland",
    "sg:classifiers":[
        {
            "category":"Sports & Exercise",
            "subcategory":"Swimming Pool",
            "type":"Entertainment"
        }
    ],
    "sg:phone":"+64 9-837 5195",
    "sg:province":"Auckland",
    "sg:tags":[
        "home",
        "outdoor",
        "garden",
        "spa"
    ],
    "sg:website":"http://www.aquatechnics.co.nz",
    "wof:name":"Aqua Technics NZ Ltd",
    "wof:placetype":"venue"
},
  "geometry": {"coordinates":[174.63197299999999,-36.891327],"type":"Point"}
}