{
  "type": "Feature",
  "properties": {
    "addr:full":"323 Gladstone Rd  Gisborne Gisborne",
    "addr:housenumber":"323",
    "addr:street":"Gladstone Rd",
    "iso:country":"NZ",
    "sg:address":"323 Gladstone Rd ",
    "sg:city":"Gisborne",
    "sg:classifiers":[
        {
            "category":"Autos & Motor Vehicles",
            "subcategory":"Automobile Sales",
            "type":"Retail Goods"
        }
    ],
    "sg:phone":"+64 6-867 8368",
    "sg:province":"Gisborne",
    "sg:tags":[
        "car",
        "-used",
        "leasing",
        "truck",
        "automotive"
    ],
    "wof:name":"Enterprise Motor Group",
    "wof:placetype":"venue"
},
  "geometry": {"coordinates":[178.020126,-38.661957],"type":"Point"}
}