{
  "type": "Feature",
  "properties": {
    "iso:country":"NZ",
    "sg:address":"9 Murray St Gate Pa ",
    "sg:city":"Tauranga",
    "sg:classifiers":[
        {
            "category":"Food & Beverages",
            "subcategory":"Groceries & Convenience Stores",
            "type":"Retail Goods"
        }
    ],
    "sg:phone":"+64 7-578 8494",
    "sg:province":"Bay of Plenty",
    "sg:tags":[
        "foodstuff",
        "drink",
        "-"
    ],
    "wof:name":"Food For Thought",
    "wof:placetype":"venue"
},
  "geometry": {"coordinates":[176.1353,-37.716984],"type":"Point"}
}