{
  "type": "Feature",
  "properties": {
    "iso:country":"NZ",
    "sg:address":"59 Western Springs Rd Western Springs ",
    "sg:city":"Auckland",
    "sg:orig_category":"Transport: Transportation: Carriers",
    "sg:phone":"+64 9-846 1018",
    "sg:province":"Auckland",
    "wof:name":"PJ Duffy Cartage",
    "wof:placetype":"venue"
},
  "geometry": {"coordinates":[174.721603,-36.854465],"type":"Point"}
}