{
  "type": "Feature",
  "properties": {
    "iso:country":"NZ",
    "sg:address":"17 Jervois Rd",
    "sg:city":"Auckland",
    "sg:classifiers":[
        {
            "category":"Banks & Credit Unions",
            "subcategory":"Bank",
            "type":"Services"
        }
    ],
    "sg:phone":"+64 9765370",
    "sg:province":"Auckland",
    "wof:name":"ASB Bank",
    "wof:placetype":"venue"
},
  "geometry": {"coordinates":[-119.10457599999999,36.597755],"type":"Point"}
}