{
  "type": "Feature",
  "properties": {
    "addr:full":"Miro St Mt  Maunganui Bay of Plenty",
    "addr:street":"Miro St;Maunganui",
    "iso:country":"NZ",
    "sg:address":"Miro St Mt ",
    "sg:city":"Maunganui",
    "sg:orig_category":"Sports And Leisure: General: Clubs",
    "sg:phone":"+64 7-575 4886",
    "sg:province":"Bay of Plenty",
    "wof:name":"Cosmopolitan Club Mt Maunganui (Inc)",
    "wof:placetype":"venue"
},
  "geometry": {"coordinates":[176.19009399999999,-37.65012],"type":"Point"}
}