{
  "type": "Feature",
  "properties": {
    "iso:country":"NZ",
    "sg:address":"43 Main St ",
    "sg:city":"Otaki",
    "sg:orig_category":"Transport: Transportation: Postal Services",
    "sg:phone":"+64 6-364 8190",
    "wof:name":"Otaki Post Shop",
    "wof:placetype":"venue"
},
  "geometry": {"coordinates":[175.138885,-40.752609],"type":"Point"}
}