{
  "type": "Feature",
  "properties": {
    "addr:full":"116 Ellis St Frankton  Hamilton Waikato",
    "addr:housenumber":"116",
    "addr:street":"Ellis St",
    "iso:country":"NZ",
    "sg:address":"116 Ellis St Frankton ",
    "sg:city":"Hamilton",
    "sg:classifiers":[
        {
            "category":"Manufacturing",
            "subcategory":"Tools & Machinery",
            "type":"Manufacturing & Wholesale Goods"
        }
    ],
    "sg:phone":"+64 7-847 1514",
    "sg:province":"Waikato",
    "sg:tags":[
        "equipment",
        "industrial",
        "hydraulic"
    ],
    "wof:name":"Complete Engineering+& Hydraulics Ltd",
    "wof:placetype":"venue"
},
  "geometry": {"coordinates":[175.264038,-37.795364],"type":"Point"}
}