{
  "type": "Feature",
  "properties": {
    "iso:country":"NZ",
    "sg:address":"11 Tuwharetoa St ",
    "sg:city":"Taupo",
    "sg:classifiers":[
        {
            "category":"Bars & Pubs",
            "type":"Food & Drink"
        }
    ],
    "sg:phone":"+64 7-378 3900",
    "sg:province":"Waikato",
    "sg:tags":[
        "wining",
        "dining",
        "brasserie"
    ],
    "wof:name":"The Tongue & Groove Bar & Brasserie",
    "wof:placetype":"venue"
},
  "geometry": {"coordinates":[176.06987,-38.688839],"type":"Point"}
}