{
  "type": "Feature",
  "properties": {
    "addr:full":"8/515 Wairakei Rd Burnside  Christchurch Canterbury",
    "addr:housenumber":"8 / 515",
    "addr:street":"Wairakei Rd",
    "iso:country":"NZ",
    "sg:address":"8/515 Wairakei Rd Burnside ",
    "sg:city":"Christchurch",
    "sg:orig_category":"Industrial: Metal: Services: Steel Processing",
    "sg:phone":"+64 3-359 9208",
    "sg:province":"Canterbury",
    "wof:name":"Innes Industries",
    "wof:placetype":"venue"
},
  "geometry": {"coordinates":[172.56745900000001,-43.489197],"type":"Point"}
}