{
  "type": "Feature",
  "properties": {
    "iso:country":"NZ",
    "sg:address":"41 Wainui Ave Point ",
    "sg:city":"Chevalier",
    "sg:classifiers":[
        {
            "category":"Retail",
            "subcategory":"Auto Repair",
            "type":"Services"
        }
    ],
    "sg:phone":"+64 25924671",
    "sg:tags":[
        "automotive",
        "electric",
        "servicing"
    ],
    "wof:name":"Shankland Auto Electrical",
    "wof:placetype":"venue"
},
  "geometry": {"coordinates":[174.707657,-36.861298],"type":"Point"}
}