{
  "type": "Feature",
  "properties": {
    "iso:country":"NZ",
    "sg:address":"Wainui Rd ",
    "sg:city":"Raglan",
    "sg:orig_category":"Travel And Tourism: Accommodation: Backpackers",
    "sg:phone":"+64 7-825 8268",
    "wof:name":"Raglan Wagon Cabins",
    "wof:placetype":"venue"
},
  "geometry": {"coordinates":[-117.892273,40.898647],"type":"Point"}
}