{
  "type": "Feature",
  "properties": {
    "addr:full":"330 Cashel St  Christchurch Canterbury",
    "addr:housenumber":"330",
    "addr:street":"Cashel St",
    "iso:country":"NZ",
    "sg:address":"330 Cashel St ",
    "sg:city":"Christchurch",
    "sg:classifiers":[
        {
            "category":"Home & Garden",
            "subcategory":"Hardware",
            "type":"Retail Goods"
        }
    ],
    "sg:phone":"+64 3-377 0770",
    "sg:province":"Canterbury",
    "sg:tags":[
        "window",
        "fitting"
    ],
    "wof:name":"The Blind Care Company",
    "wof:placetype":"venue"
},
  "geometry": {"coordinates":[172.64932300000001,-43.533237],"type":"Point"}
}