{
  "type": "Feature",
  "properties": {
    "iso:country":"NZ",
    "sg:address":"cnr Tom Pearce Dr & Geoffrey Roberts Rd Auckland, Airport ",
    "sg:city":"Auckland",
    "sg:classifiers":[
        {
            "category":"Transit Center",
            "subcategory":"Freight",
            "type":"Transportation"
        }
    ],
    "sg:phone":"+64 9-279 5210",
    "sg:province":"Auckland",
    "sg:tags":[
        "distribution",
        "-",
        "transport"
    ],
    "sg:website":"http://www.fliway.com",
    "wof:name":"Computer Transport Services (NZ) Ltd",
    "wof:placetype":"venue"
},
  "geometry": {"coordinates":[-119.104584,36.59774],"type":"Point"}
}