{
  "type": "Feature",
  "properties": {
    "addr:full":"42 Quarantine Rd Stoke  Nelson Nelson",
    "addr:housenumber":"42",
    "addr:street":"Quarantine Rd",
    "iso:country":"NZ",
    "sg:address":"42 Quarantine Rd Stoke ",
    "sg:city":"Nelson",
    "sg:classifiers":[
        {
            "category":"Professional",
            "subcategory":"Engineering",
            "type":"Services"
        }
    ],
    "sg:phone":"+64 3-547 3389",
    "sg:province":"Nelson",
    "sg:tags":[
        "industrial"
    ],
    "sg:website":"http://www.yellowpages.co.nz/for/bensoil/dp45163.html",
    "wof:name":"Bens Oil Ltd",
    "wof:placetype":"venue"
},
  "geometry": {"coordinates":[173.23419200000001,-41.312859],"type":"Point"}
}