{
  "type": "Feature",
  "properties": {
    "addr:full":"74 Ravenswood Rd Saint Clair  Dunedin Otago",
    "addr:housenumber":"74",
    "addr:street":"Ravenswood Rd",
    "iso:country":"NZ",
    "sg:address":"74 Ravenswood Rd Saint Clair ",
    "sg:city":"Dunedin",
    "sg:classifiers":[
        {
            "category":"Shopping",
            "subcategory":"Pharmacy",
            "type":"Retail Goods"
        }
    ],
    "sg:phone":"+64 3-455 6475",
    "sg:province":"Otago",
    "sg:tags":[
        "product",
        "health"
    ],
    "wof:name":"Glyco Nutrients",
    "wof:placetype":"venue"
},
  "geometry": {"coordinates":[170.48281900000001,-45.909851],"type":"Point"}
}