{
  "type": "Feature",
  "properties": {
    "iso:country":"NZ",
    "sg:address":"PO Box 33 ",
    "sg:city":"Westport",
    "sg:orig_category":"Transport: Transportation: Courier Services",
    "sg:phone":"+64 800 117 160",
    "sg:province":"West Coast",
    "wof:name":"North-West Freight",
    "wof:placetype":"venue"
},
  "geometry": {"coordinates":[-95.16027099999999,45.715504],"type":"Point"}
}