{
  "type": "Feature",
  "properties": {
    "addr:full":"96 King St  Whakatane Bay of Plenty",
    "addr:housenumber":"96",
    "addr:street":"King St",
    "iso:country":"NZ",
    "sg:address":"96 King St ",
    "sg:city":"Whakatane",
    "sg:orig_category":"Shopping: Retail Stores: Stationery",
    "sg:phone":"+64 7-308 6683",
    "sg:province":"Bay of Plenty",
    "wof:name":"Take Note Whakatane",
    "wof:placetype":"venue"
},
  "geometry": {"coordinates":[176.98202499999999,-37.962399],"type":"Point"}
}