{
  "type": "Feature",
  "properties": {
    "iso:country":"NZ",
    "sg:address":"96 King St ",
    "sg:city":"Whakatane",
    "sg:orig_category":"Shopping: Retail Stores: Stationery",
    "sg:phone":"+64 7-308 6683",
    "sg:province":"Bay of Plenty",
    "wof:name":"Take Note Whakatane",
    "wof:placetype":"venue"
},
  "geometry": {"coordinates":[176.982025,-37.962399],"type":"Point"}
}