{
  "type": "Feature",
  "properties": {
    "addr:full":"8 Locke St  Wairoa",
    "addr:housenumber":"8",
    "addr:street":"Locke St",
    "iso:country":"NZ",
    "sg:address":"8 Locke St ",
    "sg:city":"Wairoa",
    "sg:orig_category":"Health And Beauty: Dental: Dentists",
    "sg:phone":"+64 6-838 7144",
    "wof:name":"Forbes R G Dental Surgeon",
    "wof:placetype":"venue"
},
  "geometry": {"coordinates":[177.42214999999999,-39.033978],"type":"Point"}
}