{
  "type": "Feature",
  "properties": {
    "iso:country":"NZ",
    "sg:address":"96 Memorial Ave Burnside ",
    "sg:city":"Christchurch",
    "sg:classifiers":[
        {
            "category":"Education",
            "subcategory":"Special Training",
            "type":"Public Place"
        }
    ],
    "sg:phone":"+64 3-351 9407",
    "sg:province":"Canterbury",
    "sg:website":"http://www.yellowpages.co.nz/pages/101660035/dp47023.html",
    "wof:name":"Burnside Primary School",
    "wof:placetype":"venue"
},
  "geometry": {"coordinates":[172.5758972168,-43.5094528198],"type":"Point"}
}