{
  "type": "Feature",
  "properties": {
    "addr:full":"Main Rd Awanui  Kaitaia Northland",
    "addr:street":"Main Rd",
    "iso:country":"NZ",
    "sg:address":"Main Rd Awanui ",
    "sg:city":"Kaitaia",
    "sg:classifiers":[
        {
            "category":"Professional",
            "subcategory":"Detective & Security Services",
            "type":"Services"
        }
    ],
    "sg:phone":"+64 9-406 7317",
    "sg:province":"Northland",
    "sg:tags":[
        "services",
        "automotive",
        "warrant",
        "fitness"
    ],
    "wof:name":"Ninety Mile Motors",
    "wof:placetype":"venue"
},
  "geometry": {"coordinates":[173.25520299999999,-35.05006],"type":"Point"}
}