{
  "type": "Feature",
  "properties": {
    "addr:full":"39 Carlyle St Sydenham  Christchurch Canterbury",
    "addr:housenumber":"39",
    "addr:street":"Carlyle St",
    "iso:country":"NZ",
    "sg:address":"39 Carlyle St Sydenham ",
    "sg:city":"Christchurch",
    "sg:orig_category":"Industrial: Products: Laboratory Supplies",
    "sg:phone":"+64 3-366 6455",
    "sg:province":"Canterbury",
    "wof:name":"Roche Diagnostics New Zealand",
    "wof:placetype":"venue"
},
  "geometry": {"coordinates":[172.64166299999999,-43.541271],"type":"Point"}
}