{
  "type": "Feature",
  "properties": {
    "iso:country":"NZ",
    "sg:address":"16 Coutts St Kilbirnie ",
    "sg:city":"Wellington",
    "sg:orig_category":"Automotive: General Services: Service Stations",
    "sg:phone":"+64 4-387 8207",
    "sg:province":"Wellington",
    "wof:name":"Shell Service Station Kilbirnie",
    "wof:placetype":"venue"
},
  "geometry": {"coordinates":[174.794479,-41.320068],"type":"Point"}
}