{
  "type": "Feature",
  "properties": {
    "iso:country":"NZ",
    "sg:address":"39 Veronica St New Lynn ",
    "sg:city":"Auckland",
    "sg:classifiers":[
        {
            "category":"Home & Garden",
            "subcategory":"Furniture",
            "type":"Retail Goods"
        }
    ],
    "sg:phone":"+64 9-827 6744",
    "sg:province":"Auckland",
    "sg:tags":[
        "furniture/furnishings",
        "repair",
        "finishing"
    ],
    "wof:name":"Gees Furniture Furnishers Ltd",
    "wof:placetype":"venue"
},
  "geometry": {"coordinates":[174.68547100000001,-36.904831],"type":"Point"}
}