{
  "type": "Feature",
  "properties": {
    "iso:country":"NZ",
    "sg:address":"72 A Barrys Point Rd Takapuna ",
    "sg:city":"Auckland",
    "sg:orig_category":"Shopping: Retail Stores: Florists",
    "sg:phone":"+64 9-489 9653",
    "sg:province":"Auckland",
    "sg:website":"http://www.auck-flowers.co.nz",
    "wof:name":"Flower Wholesalers Ltd",
    "wof:placetype":"venue"
},
  "geometry": {"coordinates":[174.765869,-36.795712],"type":"Point"}
}