{
  "type": "Feature",
  "properties": {
    "iso:country":"NZ",
    "sg:address":"Toomey St ",
    "sg:city":"Waihi",
    "sg:classifiers":[
        {
            "category":"Social Services",
            "subcategory":"Retirement Home",
            "type":"Services"
        }
    ],
    "sg:phone":"+64 7-863 8089",
    "sg:tags":[
        "elderly",
        "convalescent",
        "garden",
        "rest",
        "care"
    ],
    "wof:name":"Waihi Hospital & LifeCare Village",
    "wof:placetype":"venue"
},
  "geometry": {"coordinates":[175.827332,-37.392548],"type":"Point"}
}