{
  "type": "Feature",
  "properties": {
    "addr:full":"10 Pacific Pl  Wanganui Manawatu-Wanganui",
    "addr:housenumber":"10",
    "addr:street":"Pacific Pl",
    "iso:country":"NZ",
    "sg:address":"10 Pacific Pl ",
    "sg:city":"Wanganui",
    "sg:classifiers":[
        {
            "category":"Home & Garden",
            "subcategory":"Building Materials",
            "type":"Retail Goods"
        }
    ],
    "sg:phone":"+64 6-345 2383",
    "sg:province":"Manawatu-Wanganui",
    "sg:tags":[
        "electrician",
        "related"
    ],
    "wof:name":"Dennis Fowler Electrical And Refrigeration",
    "wof:placetype":"venue"
},
  "geometry": {"coordinates":[175.04827900000001,-39.940521],"type":"Point"}
}