{
  "type": "Feature",
  "properties": {
    "addr:full":"12 Waikaukau Rd Glen Eden  Auckland Auckland",
    "addr:housenumber":"12",
    "addr:street":"Waikaukau Rd",
    "iso:country":"NZ",
    "sg:address":"12 Waikaukau Rd Glen Eden ",
    "sg:city":"Auckland",
    "sg:orig_category":"Industrial: Metal: Services: Steel Processing",
    "sg:phone":"+64 9-818 8180",
    "sg:province":"Auckland",
    "wof:name":"Wyatt Reinforcing",
    "wof:placetype":"venue"
},
  "geometry": {"coordinates":[174.637192,-36.907326],"type":"Point"}
}