{
  "type": "Feature",
  "properties": {
    "addr:full":"2/218 Lake Rd Northcote  Auckland Auckland",
    "addr:housenumber":"2 / 218",
    "addr:street":"Lake Rd",
    "iso:country":"NZ",
    "sg:address":"2/218 Lake Rd Northcote ",
    "sg:city":"Auckland",
    "sg:orig_category":"Industrial: Engineering: Engineers: Engineers - Consulting",
    "sg:phone":"+64 9-480 7823",
    "sg:province":"Auckland",
    "wof:name":"Day Consultants Ltd",
    "wof:placetype":"venue"
},
  "geometry": {"coordinates":[174.74432400000001,-36.802917],"type":"Point"}
}