{
  "type": "Feature",
  "properties": {
    "addr:full":"19-25 Lower Tarewa Rd  Whangarei Northland",
    "addr:housenumber":"19-25",
    "addr:street":"Lower Tarewa Rd",
    "iso:country":"NZ",
    "sg:address":"19-25 Lower Tarewa Rd ",
    "sg:city":"Whangarei",
    "sg:orig_category":"Home And Garden: Furniture/Furnishings: Curtains",
    "sg:phone":"+64 9-430 7220",
    "sg:province":"Northland",
    "wof:name":"Spotlight Stores Ltd",
    "wof:placetype":"venue"
},
  "geometry": {"coordinates":[174.31710799999999,-35.730259],"type":"Point"}
}