{
  "type": "Feature",
  "properties": {
    "addr:full":"10 Billabong Pl Howick  Auckland Auckland",
    "addr:housenumber":"10",
    "addr:street":"Billabong Pl",
    "iso:country":"NZ",
    "sg:address":"10 Billabong Pl Howick ",
    "sg:city":"Auckland",
    "sg:classifiers":[
        {
            "category":"Retail",
            "subcategory":"Auto Repair",
            "type":"Services"
        }
    ],
    "sg:phone":"+64 9-534 8200",
    "sg:province":"Auckland",
    "sg:tags":[
        "mobile",
        "automotive",
        "servicing",
        "mechanic"
    ],
    "wof:name":"Kennedy Vehicle Services",
    "wof:placetype":"venue"
},
  "geometry": {"coordinates":[174.916946,-36.894379],"type":"Point"}
}