{
  "type": "Feature",
  "properties": {
    "iso:country":"NZ",
    "sg:address":"75-89 Main South Rd Upper Riccarton PO Box 8044 Riccarton",
    "sg:city":"Christchurch",
    "sg:classifiers":[
        {
            "category":"Wholesale",
            "subcategory":"Electrical",
            "type":"Manufacturing & Wholesale Goods"
        }
    ],
    "sg:phone":"+64 3-348 5199",
    "sg:province":"Canterbury",
    "sg:tags":[
        "wire",
        "electrical/electronic",
        "industrial",
        "electric",
        "cable"
    ],
    "wof:name":"General Cable NZ Ltd",
    "wof:placetype":"venue"
},
  "geometry": {"coordinates":[172.597351,-43.532143],"type":"Point"}
}