{
  "type": "Feature",
  "properties": {
    "addr:full":"150 Kaikorai Valley Rd Kaikorai  Dunedin Otago",
    "addr:housenumber":"150",
    "addr:street":"Kaikorai Valley Rd",
    "iso:country":"NZ",
    "sg:address":"150 Kaikorai Valley Rd Kaikorai ",
    "sg:city":"Dunedin",
    "sg:orig_category":"Home And Garden: Gardening: Products: Lawnmowers",
    "sg:phone":"+64 3-476 3446",
    "sg:province":"Otago",
    "wof:name":"Roslyn Mower Centre",
    "wof:placetype":"venue"
},
  "geometry": {"coordinates":[170.46951300000001,-45.880348],"type":"Point"}
}