{
  "type": "Feature",
  "properties": {
    "iso:country":"NZ",
    "sg:address":"Shop 17 Mahurangi Shopping Centre Mahurangi East Rd, Snells Beach ",
    "sg:city":"Warkworth",
    "sg:orig_category":"Shopping: Sports Retailers: Water Sports: Diving Equipment",
    "sg:phone":"+64 9-425 5324",
    "sg:province":"Auckland",
    "wof:name":"Snells Beach Dive & Fishing",
    "wof:placetype":"venue"
},
  "geometry": {"coordinates":[174.72740200000001,-36.42046],"type":"Point"}
}