{
  "type": "Feature",
  "properties": {
    "iso:country":"NZ",
    "sg:address":"6B/7 Shortland St Auckland Central ",
    "sg:city":"Auckland",
    "sg:classifiers":[
        {
            "category":"Professional",
            "subcategory":"Management & Consulting",
            "type":"Services"
        }
    ],
    "sg:phone":"+64 9-357 0075",
    "sg:province":"Auckland",
    "sg:tags":[
        "consultant",
        "training",
        "education"
    ],
    "wof:name":"Millennium Overseas Education Centre",
    "wof:placetype":"venue"
},
  "geometry": {"coordinates":[174.76655600000001,-36.846619],"type":"Point"}
}