{
  "type": "Feature",
  "properties": {
    "iso:country":"NZ",
    "sg:address":"1071 Eruera St ",
    "sg:city":"Rotorua",
    "sg:classifiers":[
        {
            "category":"Shopping",
            "subcategory":"Beauty & Cosmetics",
            "type":"Retail Goods"
        }
    ],
    "sg:phone":"+64 7-347 8855",
    "sg:province":"Bay of Plenty",
    "sg:tags":[
        "health",
        "perfumery"
    ],
    "wof:name":"Beauty Spa",
    "wof:placetype":"venue"
},
  "geometry": {"coordinates":[176.254883,-38.138699],"type":"Point"}
}