{
  "type": "Feature",
  "properties": {
    "addr:full":"1071 Eruera St  Rotorua Bay of Plenty",
    "addr:housenumber":"1071",
    "addr:street":"Eruera St",
    "iso:country":"NZ",
    "sg:address":"1071 Eruera St ",
    "sg:city":"Rotorua",
    "sg:classifiers":[
        {
            "category":"Shopping",
            "subcategory":"Beauty & Cosmetics",
            "type":"Retail Goods"
        }
    ],
    "sg:phone":"+64 7-347 8855",
    "sg:province":"Bay of Plenty",
    "sg:tags":[
        "health",
        "perfumery"
    ],
    "wof:name":"Beauty Spa",
    "wof:placetype":"venue"
},
  "geometry": {"coordinates":[176.25488300000001,-38.138699],"type":"Point"}
}