{
  "type": "Feature",
  "properties": {
    "addr:full":"C/o Betty Lyon RD 3  Whakatane Bay of Plenty",
    "addr:housenumber":"/ o",
    "addr:street":"C;Betty Lyon Rd 3 Whakatane Bay",
    "iso:country":"NZ",
    "sg:address":"C/o Betty Lyon RD 3 ",
    "sg:city":"Whakatane",
    "sg:orig_category":"Sports And Leisure: General: Halls",
    "sg:phone":"+64 7-308 9584",
    "sg:province":"Bay of Plenty",
    "wof:name":"Awakeri War Memorial Hall",
    "wof:placetype":"venue"
},
  "geometry": {"coordinates":[176.98419200000001,-37.965305],"type":"Point"}
}