{
  "type": "Feature",
  "properties": {
    "iso:country":"NZ",
    "sg:address":"6 Fairfax Ave Penrose ",
    "sg:city":"Auckland",
    "sg:classifiers":[
        {
            "category":"Insurance",
            "subcategory":"Health Insurance",
            "type":"Services"
        }
    ],
    "sg:phone":"+64 9-580 2150",
    "sg:province":"Auckland",
    "sg:tags":[
        "beauty"
    ],
    "sg:website":"http://www.beadsandpieces.co.nz",
    "wof:name":"Beads & Pieces Ltd",
    "wof:placetype":"venue"
},
  "geometry": {"coordinates":[174.81015,-36.913128],"type":"Point"}
}