{
  "type": "Feature",
  "properties": {
    "addr:full":"Glenview Ladies Mile R D 1  Queenstown Auckland",
    "addr:housenumber":"1",
    "addr:street":"R D",
    "iso:country":"NZ",
    "sg:address":"Glenview Ladies Mile R D 1 ",
    "sg:city":"Queenstown",
    "sg:classifiers":[
        {
            "category":"Real Estate",
            "subcategory":"Real Estate Services",
            "type":"Services"
        }
    ],
    "sg:phone":"+64 3-442 3403",
    "sg:province":"Auckland",
    "sg:tags":[
        "home",
        "garden"
    ],
    "wof:name":"Stalker Sharyn",
    "wof:placetype":"venue"
},
  "geometry": {"coordinates":[-76.160561,38.991489],"type":"Point"}
}