{
  "type": "Feature",
  "properties": {
    "iso:country":"NZ",
    "sg:address":"65 Victoria St ",
    "sg:city":"Christchurch",
    "sg:orig_category":"Industrial: Services",
    "sg:phone":"+64 3-366 7731",
    "sg:province":"Canterbury",
    "sg:website":"http://www.yellowpages.co.nz/for/microfilm/dp9620.html",
    "wof:name":"Microfilm Ltd",
    "wof:placetype":"venue"
},
  "geometry": {"coordinates":[172.632263,-43.525806],"type":"Point"}
}