{
  "type": "Feature",
  "properties": {
    "iso:country":"NZ",
    "sg:address":"558 Kaikorai Valley Rd Kenmure ",
    "sg:city":"Dunedin",
    "sg:classifiers":[
        {
            "category":"Retail",
            "subcategory":"Laundry & Dry Cleaning",
            "type":"Services"
        }
    ],
    "sg:phone":"+64 3-488 4316",
    "sg:province":"Otago",
    "sg:tags":[
        "product",
        "wool",
        "clothing",
        "fabric"
    ],
    "wof:name":"Waters Ritchie & Taylor Ltd",
    "wof:placetype":"venue"
},
  "geometry": {"coordinates":[170.46203600000001,-45.889],"type":"Point"}
}