{
  "type": "Feature",
  "properties": {
    "addr:full":"10 McGowan St  Runanga",
    "addr:housenumber":"10",
    "addr:street":"Mcgowan St",
    "iso:country":"NZ",
    "sg:address":"10 McGowan St ",
    "sg:city":"Runanga",
    "sg:classifiers":[
        {
            "category":"Utilities",
            "subcategory":"Electric",
            "type":"Services"
        }
    ],
    "sg:phone":"+64 3-762 7778",
    "sg:tags":[
        "energy",
        "industrial"
    ],
    "wof:name":"Runanga Coal Depot",
    "wof:placetype":"venue"
},
  "geometry": {"coordinates":[171.25164799999999,-42.400848],"type":"Point"}
}