{
  "type": "Feature",
  "properties": {
    "iso:country":"NZ",
    "sg:address":"128 B Pah St ",
    "sg:city":"Motueka",
    "sg:classifiers":[
        {
            "category":"Retail",
            "subcategory":"Auto Repair",
            "type":"Services"
        }
    ],
    "sg:phone":"+64 3-528 0262",
    "sg:province":"Tasman",
    "sg:tags":[
        "automotive",
        "panel",
        "servicing",
        "beater"
    ],
    "wof:name":"Griffs Panelbeating",
    "wof:placetype":"venue"
},
  "geometry": {"coordinates":[173.005951,-41.110043],"type":"Point"}
}