{
  "type": "Feature",
  "properties": {
    "addr:full":"230-242 Queen St Auckland Central  Auckland Auckland",
    "addr:housenumber":"230-242",
    "addr:street":"Queen St",
    "iso:country":"NZ",
    "sg:address":"230-242 Queen St Auckland Central ",
    "sg:city":"Auckland",
    "sg:orig_category":"Clothing And Fabric: Clothing: Menswear",
    "sg:phone":"+64 9-379 9103",
    "sg:province":"Auckland",
    "wof:name":"Farmers Trading Co Ltd",
    "wof:placetype":"venue"
},
  "geometry": {"coordinates":[174.76513700000001,-36.849865],"type":"Point"}
}