{
  "type": "Feature",
  "properties": {
    "addr:full":"32 Lorne St Te Aro  Wellington Wellington",
    "addr:housenumber":"32",
    "addr:street":"Lorne St;Wellington",
    "iso:country":"NZ",
    "sg:address":"32 Lorne St Te Aro ",
    "sg:city":"Wellington",
    "sg:classifiers":[
        {
            "category":"Health Services",
            "subcategory":"Doctor",
            "type":"Services"
        }
    ],
    "sg:phone":"+64 4-801 6228",
    "sg:province":"Wellington",
    "sg:tags":[
        "specialists",
        "surgery",
        "cosmetic",
        "beauty"
    ],
    "sg:website":"http://www.yellowpages.co.nz/for/tennyson/dp19401.html",
    "wof:name":"Tennyson Dental Centre",
    "wof:placetype":"venue"
},
  "geometry": {"coordinates":[174.781204,-41.295414],"type":"Point"}
}