{
  "type": "Feature",
  "properties": {
    "addr:full":"Unit 2 19 Ihakara St  Paraparaumu Wellington",
    "addr:housenumber":"unit;19",
    "addr:street":"Ihakara St",
    "iso:country":"NZ",
    "sg:address":"Unit 2 19 Ihakara St ",
    "sg:city":"Paraparaumu",
    "sg:orig_category":"Automotive: Accessories: Car Audio Systems",
    "sg:phone":"+64 4-902 5143",
    "sg:province":"Wellington",
    "wof:name":"Kapiti Car Audio",
    "wof:placetype":"venue"
},
  "geometry": {"coordinates":[175.000687,-40.919701],"type":"Point"}
}