{
  "type": "Feature",
  "properties": {
    "iso:country":"NZ",
    "sg:address":"16 Riserra Dve Ranui ",
    "sg:city":"Auckland",
    "sg:orig_category":"Automotive: Servicing And Repair: Car Trimming/Upholstery",
    "sg:phone":"+64 9-832 2442",
    "sg:province":"Auckland",
    "wof:name":"Graham Carnie Auto & Marine Upholstery",
    "wof:placetype":"venue"
},
  "geometry": {"coordinates":[174.61137400000001,-36.864895],"type":"Point"}
}