{
  "type": "Feature",
  "properties": {
    "addr:full":"113 A Victoria Ave  Wanganui Manawatu-Wanganui",
    "addr:housenumber":"113 a",
    "addr:street":"Victoria Ave",
    "iso:country":"NZ",
    "sg:address":"113 A Victoria Ave ",
    "sg:city":"Wanganui",
    "sg:classifiers":[
        {
            "category":"Shopping",
            "subcategory":"Crafts & Fabrics",
            "type":"Retail Goods"
        }
    ],
    "sg:phone":"+64 6-345 5075",
    "sg:province":"Manawatu-Wanganui",
    "sg:tags":[
        "foot",
        "clothing",
        "retailer",
        "footwear",
        "wear"
    ],
    "wof:name":"Pfeffers Shoe Store",
    "wof:placetype":"venue"
},
  "geometry": {"coordinates":[175.05107100000001,-39.932495],"type":"Point"}
}