{
  "type": "Feature",
  "properties": {
    "addr:full":"124 Carter Rd Oratia  Auckland Auckland",
    "addr:housenumber":"124",
    "addr:street":"Carter Rd",
    "iso:country":"NZ",
    "sg:address":"124 Carter Rd Oratia ",
    "sg:city":"Auckland",
    "sg:orig_category":"Farming: Horticulture",
    "sg:phone":"+64 9-818 6650",
    "sg:province":"Auckland",
    "wof:name":"Pacific Services Limited",
    "wof:placetype":"venue"
},
  "geometry": {"coordinates":[174.61972,-36.932316],"type":"Point"}
}