{
  "type": "Feature",
  "properties": {
    "addr:full":"25 MacDonald St Mt  Maunganui Bay of Plenty",
    "addr:housenumber":"25",
    "addr:street":"Macdonald St;Maunganui Bay",
    "iso:country":"NZ",
    "sg:address":"25 MacDonald St Mt ",
    "sg:city":"Maunganui",
    "sg:classifiers":[
        {
            "category":"Home & Garden",
            "subcategory":"Home Furnishings",
            "type":"Retail Goods"
        }
    ],
    "sg:phone":"+64 7-575 4009",
    "sg:province":"Bay of Plenty",
    "sg:tags":[
        "accessory"
    ],
    "sg:website":"http://www.placemakers.co.nz",
    "wof:name":"PlaceMakers",
    "wof:placetype":"venue"
},
  "geometry": {"coordinates":[176.18627900000001,-37.641048],"type":"Point"}
}