{
  "type": "Feature",
  "properties": {
    "iso:country":"NZ",
    "sg:address":"1250 Owairaka Valley Rd R D 7 Te ",
    "sg:city":"Awamutu",
    "sg:orig_category":"Travel And Tourism: Accommodation: Backpackers",
    "sg:phone":"+64 800 225 462",
    "sg:province":"Auckland",
    "wof:name":"CastleRock Adventure Lodge",
    "wof:placetype":"venue"
},
  "geometry": {"coordinates":[175.319244,-38.009647],"type":"Point"}
}