{
  "type": "Feature",
  "properties": {
    "iso:country":"NZ",
    "sg:address":"9 Kitchener St ",
    "sg:city":"Dunedin",
    "sg:orig_category":"Shopping: Sports Retailers: Water Sports",
    "sg:phone":"+64 3-479 2206",
    "sg:province":"Otago",
    "wof:name":"Watercooled Sports Ltd",
    "wof:placetype":"venue"
},
  "geometry": {"coordinates":[170.506775,-45.884892],"type":"Point"}
}