{
  "type": "Feature",
  "properties": {
    "iso:country":"NZ",
    "sg:address":"2 Straven Rd Riccarton ",
    "sg:city":"Christchurch",
    "sg:orig_category":"Health And Beauty: Beauty: Hairdressers",
    "sg:phone":"+64 3-343 4690",
    "sg:province":"Canterbury",
    "wof:name":"Milan's Barbar Shop",
    "wof:placetype":"venue"
},
  "geometry": {"coordinates":[172.602158,-43.529499],"type":"Point"}
}