{
  "type": "Feature",
  "properties": {
    "iso:country":"NZ",
    "sg:address":"49 Rutherford St Melling ",
    "sg:city":"Wellington",
    "sg:classifiers":[
        {
            "category":"Manufacturing",
            "subcategory":"Food",
            "type":"Manufacturing & Wholesale Goods"
        }
    ],
    "sg:phone":"+64 4-566 3332",
    "sg:province":"Wellington",
    "sg:tags":[
        "drink",
        "-",
        "manufacturer"
    ],
    "wof:name":"Bluebird Foods Limited",
    "wof:placetype":"venue"
},
  "geometry": {"coordinates":[174.90614299999999,-41.203308],"type":"Point"}
}