{
  "type": "Feature",
  "properties": {
    "addr:full":"169 Maunganui Rd Mt  Maunganui Bay of Plenty",
    "addr:housenumber":"169",
    "addr:street":"Maunganui Rd;Maunganui",
    "iso:country":"NZ",
    "sg:address":"169 Maunganui Rd Mt ",
    "sg:city":"Maunganui",
    "sg:classifiers":[
        {
            "category":"Personal",
            "subcategory":"Tattoo Parlor",
            "type":"Services"
        }
    ],
    "sg:phone":"+64 7-572 1199",
    "sg:province":"Bay of Plenty",
    "sg:tags":[
        "services",
        "home",
        "tattooists",
        "garden"
    ],
    "wof:name":"A Point of View Tattoo",
    "wof:placetype":"venue"
},
  "geometry": {"coordinates":[176.183807,-37.638599],"type":"Point"}
}