{
  "type": "Feature",
  "properties": {
    "iso:country":"NZ",
    "sg:address":"62 Tidal Rd Mangere ",
    "sg:city":"Auckland",
    "sg:orig_category":"Shopping: Sports Retailers: Sports Goods: Canvas Goods",
    "sg:phone":"+64 9-276 5183",
    "sg:province":"Auckland",
    "wof:name":"Cairns & Woodward Auckland",
    "wof:placetype":"venue"
},
  "geometry": {"coordinates":[174.822723,-36.978668],"type":"Point"}
}