{
  "type": "Feature",
  "properties": {
    "addr:full":"170 Burwood Rd Burwood  Christchurch Canterbury",
    "addr:housenumber":"170",
    "addr:street":"Burwood Rd",
    "iso:country":"NZ",
    "sg:address":"170 Burwood Rd Burwood ",
    "sg:city":"Christchurch",
    "sg:orig_category":"Education And Training: General: Schools",
    "sg:phone":"+64 3-383 3301",
    "sg:province":"Canterbury",
    "wof:name":"Windsor Primary School",
    "wof:placetype":"venue"
},
  "geometry": {"coordinates":[172.68374600000001,-43.489346],"type":"Point"}
}