{
  "type": "Feature",
  "properties": {
    "iso:country":"NZ",
    "sg:address":"5/158 Cashel St ",
    "sg:city":"Christchurch",
    "sg:classifiers":[
        {
            "category":"Internet Cafe",
            "subcategory":"None",
            "type":"Food & Drink"
        }
    ],
    "sg:phone":"+64 3-366 9077",
    "sg:province":"Canterbury",
    "sg:tags":[
        "wining",
        "dining"
    ],
    "wof:name":"C2 Zone Limited",
    "wof:placetype":"venue"
},
  "geometry": {"coordinates":[-76.537834,37.605659],"type":"Point"}
}