{
  "type": "Feature",
  "properties": {
    "addr:full":"70 Pegasus Ave North New Brighton  Christchurch Canterbury",
    "addr:housenumber":"70",
    "addr:street":"Pegasus Ave North",
    "iso:country":"NZ",
    "sg:address":"70 Pegasus Ave North New Brighton ",
    "sg:city":"Christchurch",
    "sg:classifiers":[
        {
            "category":"Home & Garden",
            "subcategory":"Home Furnishings",
            "type":"Retail Goods"
        }
    ],
    "sg:phone":"+64 3-382 9211",
    "sg:province":"Canterbury",
    "sg:tags":[
        "furniture/furnishings",
        "upholstery",
        "supply"
    ],
    "wof:name":"Perfecto Upholstery",
    "wof:placetype":"venue"
},
  "geometry": {"coordinates":[172.71511799999999,-43.490089],"type":"Point"}
}