{
  "type": "Feature",
  "properties": {
    "addr:full":"117 O'Shannessy St Papakura  Auckland Auckland",
    "addr:housenumber":"117",
    "addr:street":"O'Shannessy St",
    "iso:country":"NZ",
    "sg:address":"117 O'Shannessy St Papakura ",
    "sg:city":"Auckland",
    "sg:orig_category":"Clothing And Fabric: Clothing: Dressmakers",
    "sg:phone":"+64 9-296 2617",
    "sg:province":"Auckland",
    "wof:name":"Sunan's Clothing Alterations",
    "wof:placetype":"venue"
},
  "geometry": {"coordinates":[174.94392400000001,-37.065418],"type":"Point"}
}