{
  "type": "Feature",
  "properties": {
    "addr:full":"279 Port Rd  Whangarei Northland",
    "addr:housenumber":"279",
    "addr:street":"Port Rd",
    "iso:country":"NZ",
    "sg:address":"279 Port Rd ",
    "sg:city":"Whangarei",
    "sg:orig_category":"Transport: Boats And Marine: Shipping: Ship Builders",
    "sg:phone":"+64 9-438 0963",
    "sg:province":"Northland",
    "wof:name":"McRaes Ship Repair Company Limited",
    "wof:placetype":"venue"
},
  "geometry": {"coordinates":[174.346619,-35.745689],"type":"Point"}
}