{
  "type": "Feature",
  "properties": {
    "addr:full":"cnr Clark & Three Mile Bush Rds Kamo  Whangarei Northland",
    "addr:housenumber":"kamo",
    "addr:street":"Cnr Clark & Three Mile Bush Rds",
    "iso:country":"NZ",
    "sg:address":"cnr Clark & Three Mile Bush Rds Kamo ",
    "sg:city":"Whangarei",
    "sg:orig_category":"Shopping: Retail Stores: Secondhand Dealers",
    "sg:phone":"+64 9-435 0279",
    "sg:province":"Northland",
    "wof:name":"Bellmacks Bargain Centre",
    "wof:placetype":"venue"
},
  "geometry": {"coordinates":[174.30029300000001,-35.68219],"type":"Point"}
}