{
  "type": "Feature",
  "properties": {
    "iso:country":"NZ",
    "sg:address":"1 Princess St ",
    "sg:city":"Dannevirke",
    "sg:orig_category":"Sports And Leisure: General: Clubs",
    "sg:phone":"+64 6-374 8885",
    "wof:name":"Dannevirke Services & Citizens Club Inc",
    "wof:placetype":"venue"
},
  "geometry": {"coordinates":[-98.605675,41.329346],"type":"Point"}
}