{
  "type": "Feature",
  "properties": {
    "addr:full":"62 Queen St  Waimate",
    "addr:housenumber":"62",
    "addr:street":"Queen St",
    "iso:country":"NZ",
    "sg:address":"62 Queen St ",
    "sg:city":"Waimate",
    "sg:orig_category":"Farming: Agriculture: Agricultural Contractors",
    "sg:phone":"+64 3-689 6006",
    "wof:name":"Balewrap Systems Ltd",
    "wof:placetype":"venue"
},
  "geometry": {"coordinates":[171.04478499999999,-44.735359],"type":"Point"}
}