{
  "type": "Feature",
  "properties": {
    "iso:country":"NZ",
    "sg:address":"48 Weraroa Rd ",
    "sg:city":"Levin",
    "sg:orig_category":"Education And Training: General: Schools",
    "sg:phone":"+64 6-368 8017",
    "sg:province":"Manawatu-Wanganui",
    "wof:name":"St Joseph's Catholic School",
    "wof:placetype":"venue"
},
  "geometry": {"coordinates":[175.278839,-40.62402],"type":"Point"}
}