{
  "type": "Feature",
  "properties": {
    "iso:country":"NZ",
    "sg:address":"125 Foundry Rd Silverdale Hibiscus ",
    "sg:city":"Hibiscus Coast",
    "sg:classifiers":[
        {
            "category":"Farming",
            "subcategory":"Fish & Marine Products",
            "type":"Manufacturing & Wholesale Goods"
        }
    ],
    "sg:phone":"+64 9-427 5040",
    "sg:province":"Auckland",
    "sg:tags":[
        "-",
        "boat",
        "transport"
    ],
    "wof:name":"Silverdale Marine Hatchery Ltd",
    "wof:placetype":"venue"
},
  "geometry": {"coordinates":[174.68542500000001,-36.622368],"type":"Point"}
}