{
  "type": "Feature",
  "properties": {
    "iso:country":"NZ",
    "sg:address":"PO Box 26 ",
    "sg:city":"Kaikoura",
    "sg:classifiers":[
        {
            "category":"Shopping",
            "subcategory":"Stationery & Office Supplies",
            "type":"Retail Goods"
        }
    ],
    "sg:phone":"+64 3-319 6658",
    "sg:tags":[
        "map",
        "chart"
    ],
    "wof:name":"Ocean Fun Publishing",
    "wof:placetype":"venue"
},
  "geometry": {"coordinates":[173.681381,-42.404366],"type":"Point"}
}