{
  "type": "Feature",
  "properties": {
    "iso:country":"NZ",
    "sg:address":"Scotland St ",
    "sg:city":"Roxburgh",
    "sg:classifiers":[
        {
            "category":"Sports & Exercise",
            "subcategory":"Sports Center",
            "type":"Entertainment"
        }
    ],
    "sg:phone":"+64 3-446 8449",
    "sg:tags":[
        "sporting",
        "sports",
        "-",
        "leisure",
        "facility"
    ],
    "wof:name":"Roxburgh Swimming Pool",
    "wof:placetype":"venue"
},
  "geometry": {"coordinates":[-2.479497,55.568378],"type":"Point"}
}