{
  "type": "Feature",
  "properties": {
    "iso:country":"NZ",
    "sg:address":"23 Adelaide Rd Newtown ",
    "sg:city":"Wellington",
    "sg:classifiers":[
        {
            "category":"Home & Garden",
            "subcategory":"Home Furnishings",
            "type":"Retail Goods"
        }
    ],
    "sg:phone":"+64 4-385 9289",
    "sg:province":"Wellington",
    "sg:tags":[
        "furniture/furnishings",
        "bedding",
        "bed"
    ],
    "wof:name":"Futon Company",
    "wof:placetype":"venue"
},
  "geometry": {"coordinates":[174.777908,-41.30727],"type":"Point"}
}