{
  "type": "Feature",
  "properties": {
    "iso:country":"NZ",
    "sg:address":"Suite 3 16 Bernard St Addington ",
    "sg:city":"Christchurch",
    "sg:classifiers":[
        {
            "category":"Professional",
            "subcategory":"Art Services",
            "type":"Services"
        }
    ],
    "sg:phone":"+64 3-338 8193",
    "sg:province":"Canterbury",
    "sg:tags":[
        "fashion",
        "clothing",
        "fabric",
        "designer"
    ],
    "wof:name":"Y-Knot Designs",
    "wof:placetype":"venue"
},
  "geometry": {"coordinates":[172.612915,-43.541367],"type":"Point"}
}