{
  "type": "Feature",
  "properties": {
    "addr:full":"48 Battersea St Sydenham  Christchurch Canterbury",
    "addr:housenumber":"48",
    "addr:street":"Battersea St",
    "iso:country":"NZ",
    "sg:address":"48 Battersea St Sydenham ",
    "sg:city":"Christchurch",
    "sg:classifiers":[
        {
            "category":"Shopping",
            "subcategory":"Crafts & Fabrics",
            "type":"Retail Goods"
        }
    ],
    "sg:phone":"+64 3-366 5975",
    "sg:province":"Canterbury",
    "sg:tags":[
        "leather",
        "clothing",
        "suede"
    ],
    "wof:name":"Frenzi Holdings Ltd",
    "wof:placetype":"venue"
},
  "geometry": {"coordinates":[172.63566599999999,-43.543774],"type":"Point"}
}