{
  "type": "Feature",
  "properties": {
    "addr:full":"215-217 Ruataniwha St  Waipukurau",
    "addr:housenumber":"215-217",
    "addr:street":"Ruataniwha St",
    "iso:country":"NZ",
    "sg:address":"215-217 Ruataniwha St ",
    "sg:city":"Waipukurau",
    "sg:classifiers":[
        {
            "category":"Communications",
            "subcategory":"Radio Station",
            "type":"Services"
        }
    ],
    "sg:phone":"+64 6-858 7710",
    "sg:tags":[
        "broadcasting"
    ],
    "wof:name":"Central FM",
    "wof:placetype":"venue"
},
  "geometry": {"coordinates":[176.55548099999999,-39.995388],"type":"Point"}
}