{
  "type": "Feature",
  "properties": {
    "iso:country":"NZ",
    "sg:address":"Pakuranga Plaza ",
    "sg:city":"Auckland",
    "sg:classifiers":[
        {
            "category":"Ice Cream",
            "type":"Food & Drink"
        }
    ],
    "sg:phone":"+64 9-576 3066",
    "sg:province":"Auckland",
    "sg:tags":[
        "-"
    ],
    "wof:name":"Scoffers Ice Cream Parlour",
    "wof:placetype":"venue"
},
  "geometry": {"coordinates":[174.89280700680001,-36.9012184143],"type":"Point"}
}