{
  "type": "Feature",
  "properties": {
    "addr:full":"76 Juliet St  Stratford",
    "addr:housenumber":"76",
    "addr:street":"Juliet St",
    "iso:country":"NZ",
    "sg:address":"76 Juliet St ",
    "sg:city":"Stratford",
    "sg:orig_category":"Farming: Machinery: Milking Machinery",
    "sg:phone":"+64 6-765 0241",
    "wof:name":"Dairymaster Milking Systems",
    "wof:placetype":"venue"
},
  "geometry": {"coordinates":[-119.824966,36.189419],"type":"Point"}
}