{
  "type": "Feature",
  "properties": {
    "iso:country":"NZ",
    "sg:address":"32 Seaview Rd Seaview Lower ",
    "sg:city":"Hutt",
    "sg:orig_category":"Automotive: Parts And Supplies: Automotive Dismantlers",
    "sg:phone":"+64 4-568 3998",
    "sg:province":"Wellington",
    "wof:name":"Ace Car Wreckers Ltd",
    "wof:placetype":"venue"
},
  "geometry": {"coordinates":[174.899567,-41.246059],"type":"Point"}
}