{
  "type": "Feature",
  "properties": {
    "addr:full":"Level 5, 39 Webb St  Wellington Wellington",
    "addr:housenumber":"level;39",
    "addr:street":"5;Webb St",
    "iso:country":"NZ",
    "sg:address":"Level 5, 39 Webb St ",
    "sg:city":"Wellington",
    "sg:classifiers":[
        {
            "category":"Shopping",
            "subcategory":"Computers & Home Electronics",
            "type":"Retail Goods"
        }
    ],
    "sg:phone":"+64 4-384 3393",
    "sg:province":"Wellington",
    "sg:tags":[
        "recording",
        "equipment",
        "sport",
        "music",
        "leisure"
    ],
    "wof:name":"Matrix Digital",
    "wof:placetype":"venue"
},
  "geometry": {"coordinates":[-105.002258,40.687988],"type":"Point"}
}