{
  "type": "Feature",
  "properties": {
    "addr:full":"Cnr Fairlie Cres & State Highway 12 Opononi  Kaikohe",
    "addr:housenumber":"cnr",
    "addr:street":"Fairlie Cres & State Highway 12 Opononi",
    "iso:country":"NZ",
    "sg:address":"Cnr Fairlie Cres & State Highway 12 Opononi ",
    "sg:city":"Kaikohe",
    "sg:classifiers":[
        {
            "category":"Travel",
            "subcategory":"Bed & Breakfast",
            "type":"Entertainment"
        }
    ],
    "sg:phone":"+64 9-405 8451",
    "sg:tags":[
        "tourism",
        "accommodation"
    ],
    "wof:name":"Opononi Dolphin Lodge",
    "wof:placetype":"venue"
},
  "geometry": {"coordinates":[173.79710399999999,-35.40649],"type":"Point"}
}