{
  "type": "Feature",
  "properties": {
    "addr:full":"43 A Linwood Ave Mt Albert  Auckland Canterbury",
    "addr:housenumber":"43",
    "addr:street":"A Linwood Ave",
    "iso:country":"NZ",
    "sg:address":"43 A Linwood Ave Mt Albert ",
    "sg:city":"Auckland",
    "sg:classifiers":[
        {
            "category":"Deli",
            "type":"Food & Drink"
        }
    ],
    "sg:phone":"+64 9-815 3890",
    "sg:province":"Canterbury",
    "sg:tags":[
        "delicatessen",
        "-"
    ],
    "wof:name":"Deli Direct Limited",
    "wof:placetype":"venue"
},
  "geometry": {"coordinates":[174.723297,-36.873463],"type":"Point"}
}