{
  "type": "Feature",
  "properties": {
    "iso:country":"NZ",
    "sg:address":"Victoria St ",
    "sg:city":"Waihi",
    "sg:classifiers":[
        {
            "category":"Manufacturing",
            "subcategory":"Glass & Minerals",
            "type":"Manufacturing & Wholesale Goods"
        }
    ],
    "sg:phone":"+64 7-863 6765",
    "sg:tags":[
        "industrial",
        "raw",
        "material"
    ],
    "wof:name":"Porter Engineering",
    "wof:placetype":"venue"
},
  "geometry": {"coordinates":[175.83744799999999,-37.398319],"type":"Point"}
}