{
  "type": "Feature",
  "properties": {
    "iso:country":"NZ",
    "sg:address":"148 Durham St ",
    "sg:city":"Tauranga",
    "sg:classifiers":[
        {
            "category":"Education",
            "subcategory":"Special Training",
            "type":"Public Place"
        }
    ],
    "sg:phone":"+64 7-578 9272",
    "sg:province":"Bay of Plenty",
    "sg:tags":[
        "aid",
        "medical",
        "health",
        "beauty",
        "first"
    ],
    "wof:name":"YMCA Community College",
    "wof:placetype":"venue"
},
  "geometry": {"coordinates":[176.167145,-37.686481],"type":"Point"}
}