{
  "type": "Feature",
  "properties": {
    "addr:full":"11 Dolamore Pl Wainoni  Christchurch Canterbury",
    "addr:housenumber":"11",
    "addr:street":"Dolamore Pl",
    "iso:country":"NZ",
    "sg:address":"11 Dolamore Pl Wainoni ",
    "sg:city":"Christchurch",
    "sg:classifiers":[
        {
            "category":"Shopping",
            "subcategory":"Gifts & Souvenirs",
            "type":"Retail Goods"
        }
    ],
    "sg:phone":"+64 3-389 3045",
    "sg:province":"Canterbury",
    "sg:tags":[
        "trophy",
        "award"
    ],
    "wof:name":"Amer Engravers",
    "wof:placetype":"venue"
},
  "geometry": {"coordinates":[172.69380200000001,-43.517765],"type":"Point"}
}