{
  "type": "Feature",
  "properties": {
    "iso:country":"NZ",
    "sg:address":"Salisbury St ",
    "sg:city":"Christchurch",
    "sg:classifiers":[
        {
            "category":"Personal",
            "subcategory":"Adult",
            "type":"Services"
        }
    ],
    "sg:phone":"+64 3-366 6462",
    "sg:province":"Canterbury",
    "sg:tags":[
        "sport",
        "parlour",
        "massage",
        "leisure"
    ],
    "wof:name":"Dial A Massage",
    "wof:placetype":"venue"
},
  "geometry": {"coordinates":[-76.537834,37.605659],"type":"Point"}
}