{
  "type": "Feature",
  "properties": {
    "iso:country":"NZ",
    "sg:address":"182 Main Rd ",
    "sg:city":"Waikouaiti",
    "sg:classifiers":[
        {
            "category":"Bars & Pubs",
            "type":"Food & Drink"
        }
    ],
    "sg:phone":"+64 3-465 8200",
    "sg:tags":[
        "-",
        "pie",
        "manufacturer"
    ],
    "wof:name":"Beano's Pies",
    "wof:placetype":"venue"
},
  "geometry": {"coordinates":[170.680161,-45.599018],"type":"Point"}
}