{
  "type": "Feature",
  "properties": {
    "addr:full":"PO Box 2061  Christchurch Canterbury",
    "addr:housenumber":"po",
    "addr:postcode":"2061",
    "addr:street":"Box",
    "iso:country":"NZ",
    "sg:address":"PO Box 2061 ",
    "sg:city":"Christchurch",
    "sg:classifiers":[
        {
            "category":"Professional",
            "subcategory":"Detective & Security Services",
            "type":"Services"
        }
    ],
    "sg:phone":"+64 3-366 0571",
    "sg:province":"Canterbury",
    "sg:tags":[
        "locker",
        "storage",
        "cabinet"
    ],
    "wof:name":"Cemac Southern Ltd",
    "wof:placetype":"venue"
},
  "geometry": {"coordinates":[-76.537834,37.605659],"type":"Point"}
}