{
  "type": "Feature",
  "properties": {
    "addr:full":"Johnsonville Mall Johnsonville  Wellington Wellington",
    "iso:country":"NZ",
    "sg:address":"Johnsonville Mall Johnsonville ",
    "sg:city":"Wellington",
    "sg:classifiers":[
        {
            "category":"Shopping",
            "subcategory":"Beauty & Cosmetics",
            "type":"Retail Goods"
        }
    ],
    "sg:phone":"+64 4-477 3667",
    "sg:province":"Wellington",
    "sg:tags":[
        "hair",
        "health",
        "product",
        "-"
    ],
    "wof:name":"Shampoo Plus",
    "wof:placetype":"venue"
},
  "geometry": {"coordinates":[174.80708300000001,-41.225975],"type":"Point"}
}