{
  "type": "Feature",
  "properties": {
    "iso:country":"NZ",
    "sg:address":"Main St ",
    "sg:city":"Methven",
    "sg:orig_category":"Sports And Leisure: Sports: Skiing",
    "sg:phone":"+64 3-302 8084",
    "wof:name":"Wombat's Ski Shop",
    "wof:placetype":"venue"
},
  "geometry": {"coordinates":[171.647888,-43.627678],"type":"Point"}
}