{
  "type": "Feature",
  "properties": {
    "addr:full":"9 Carney Ave  Whangarei Northland",
    "addr:housenumber":"9",
    "addr:street":"Carney Ave",
    "iso:country":"NZ",
    "sg:address":"9 Carney Ave ",
    "sg:city":"Whangarei",
    "sg:classifiers":[
        {
            "category":"Sports & Exercise",
            "subcategory":"Tennis Court",
            "type":"Entertainment"
        }
    ],
    "sg:phone":"+64 21 2574 587",
    "sg:province":"Northland",
    "sg:tags":[
        "hire",
        "-",
        "leisure"
    ],
    "wof:name":"Creative Design",
    "wof:placetype":"venue"
},
  "geometry": {"coordinates":[174.320526,-35.725399],"type":"Point"}
}