{
  "type": "Feature",
  "properties": {
    "addr:full":"28 Temple St Meadowbank  Auckland Auckland",
    "addr:housenumber":"28",
    "addr:street":"Temple St",
    "iso:country":"NZ",
    "sg:address":"28 Temple St Meadowbank ",
    "sg:city":"Auckland",
    "sg:orig_category":"Home And Garden: Accessories: Ceramics",
    "sg:phone":"+64 9-521 9125",
    "sg:province":"Auckland",
    "wof:name":"Brushstrokes On Ceramics",
    "wof:placetype":"venue"
},
  "geometry": {"coordinates":[174.82650799999999,-36.873817],"type":"Point"}
}