{
  "type": "Feature",
  "properties": {
    "addr:full":"P.O.Box 89083 Torbay Torbay  Auckland Auckland",
    "addr:postcode":"89083",
    "addr:street":"P.O.Box",
    "iso:country":"NZ",
    "sg:address":"P.O.Box 89083 Torbay Torbay ",
    "sg:city":"Auckland",
    "sg:orig_category":"Shopping: Retail Stores: Toys",
    "sg:phone":"+64 9-473 1270",
    "sg:province":"Auckland",
    "wof:name":"Liberty North Limited",
    "wof:placetype":"venue"
},
  "geometry": {"coordinates":[174.729614,-36.698483],"type":"Point"}
}