{
  "type": "Feature",
  "properties": {
    "addr:full":"1 Westney Rd Mangere  Auckland Auckland",
    "addr:housenumber":"1",
    "addr:street":"Westney Rd",
    "iso:country":"NZ",
    "sg:address":"1 Westney Rd Mangere ",
    "sg:city":"Auckland",
    "sg:classifiers":[
        {
            "category":"Travel",
            "subcategory":"Bed & Breakfast",
            "type":"Entertainment"
        }
    ],
    "sg:phone":"+64 9-275 0533",
    "sg:province":"Auckland",
    "sg:tags":[
        "tourism",
        "accommodation"
    ],
    "wof:name":"Airport Bed & Breakfast",
    "wof:placetype":"venue"
},
  "geometry": {"coordinates":[174.79260300000001,-36.975601],"type":"Point"}
}