{
  "type": "Feature",
  "properties": {
    "addr:full":"31 Landing Rd Whktn Ph/Fax  Whakatane Bay of Plenty",
    "addr:housenumber":"31",
    "addr:street":"Landing Rd Whktn Ph / Fax Whakatane Bay",
    "iso:country":"NZ",
    "sg:address":"31 Landing Rd Whktn Ph/Fax ",
    "sg:city":"Whakatane",
    "sg:orig_category":"Clothing And Fabric: Clothing: Uniforms",
    "sg:phone":"+64 7-307 0101",
    "sg:province":"Bay of Plenty",
    "wof:name":"Yellow House Embroidery",
    "wof:placetype":"venue"
},
  "geometry": {"coordinates":[176.98751799999999,-37.980568],"type":"Point"}
}