{
  "type": "Feature",
  "properties": {
    "addr:full":"Seadown Rd Timaru  Temuka",
    "addr:street":"Seadown Rd",
    "iso:country":"NZ",
    "sg:address":"Seadown Rd Timaru ",
    "sg:city":"Temuka",
    "sg:classifiers":[
        {
            "category":"Shopping",
            "subcategory":"Gifts & Souvenirs",
            "type":"Retail Goods"
        }
    ],
    "sg:phone":"+64 3-615 9043",
    "sg:tags":[
        "shop",
        "gifts",
        "supplier"
    ],
    "wof:name":"The Shearers Quarters",
    "wof:placetype":"venue"
},
  "geometry": {"coordinates":[171.24082899999999,-44.34972],"type":"Point"}
}