{
  "type": "Feature",
  "properties": {
    "iso:country":"NZ",
    "sg:address":"PO Box 6656 ",
    "sg:city":"Wellington",
    "sg:classifiers":[
        {
            "category":"Home & Garden",
            "subcategory":"Hardware",
            "type":"Retail Goods"
        }
    ],
    "sg:phone":"+64 4-232 3415",
    "sg:province":"Wellington",
    "sg:tags":[
        "window",
        "fitting"
    ],
    "sg:website":"http://www.windowfilm.co.nz",
    "wof:name":"Security & Solar Systems NZ",
    "wof:placetype":"venue"
},
  "geometry": {"coordinates":[174.76715100000001,-41.28054],"type":"Point"}
}