{
  "type": "Feature",
  "properties": {
    "addr:full":"Unit 4/ 310 Gt South Rd Manurewa  Auckland Auckland",
    "addr:housenumber":"unit 4 / 310",
    "addr:street":"Gt South Rd",
    "iso:country":"NZ",
    "sg:address":"Unit 4/ 310 Gt South Rd Manurewa ",
    "sg:city":"Auckland",
    "sg:classifiers":[
        {
            "category":"Manufacturing",
            "subcategory":"Glass & Minerals",
            "type":"Manufacturing & Wholesale Goods"
        }
    ],
    "sg:phone":"+64 9-266 2188",
    "sg:province":"Auckland",
    "sg:tags":[
        "raw",
        "industrial",
        "materials",
        "quarry",
        "equipment"
    ],
    "wof:name":"Quarry Machinery & Instalation Ltd",
    "wof:placetype":"venue"
},
  "geometry": {"coordinates":[174.90541099999999,-37.031914],"type":"Point"}
}