{
  "type": "Feature",
  "properties": {
    "addr:full":"175 Victoria Ave  Wanganui Manawatu-Wanganui",
    "addr:housenumber":"175",
    "addr:street":"Victoria Ave",
    "iso:country":"NZ",
    "sg:address":"175 Victoria Ave ",
    "sg:city":"Wanganui",
    "sg:classifiers":[
        {
            "category":"Bars & Pubs",
            "subcategory":"Lounge",
            "type":"Food & Drink"
        }
    ],
    "sg:phone":"+64 6-345 2009",
    "sg:province":"Manawatu-Wanganui",
    "sg:tags":[
        "baker",
        "-"
    ],
    "wof:name":"Gaslight Bakeries",
    "wof:placetype":"venue"
},
  "geometry": {"coordinates":[175.04861500000001,-39.931042],"type":"Point"}
}