{
  "type": "Feature",
  "properties": {
    "iso:country":"NZ",
    "sg:address":"Cnr Gorge Rd & Bowen St ",
    "sg:city":"Queenstown",
    "sg:classifiers":[
        {
            "category":"Home & Garden",
            "subcategory":"Home Furnishings",
            "type":"Retail Goods"
        }
    ],
    "sg:phone":"+64 3-442 7355",
    "sg:province":"Otago",
    "sg:tags":[
        "furniture/furnishings",
        "bedding",
        "bed"
    ],
    "wof:name":"McKenzie & Willis Ltd",
    "wof:placetype":"venue"
},
  "geometry": {"coordinates":[-76.157791,38.990379],"type":"Point"}
}