{
  "type": "Feature",
  "properties": {
    "addr:full":"Grasslands Pl  Hamilton Waikato",
    "addr:street":"Grasslands Pl",
    "iso:country":"NZ",
    "sg:address":"Grasslands Pl ",
    "sg:city":"Hamilton",
    "sg:classifiers":[
        {
            "category":"Manufacturing",
            "subcategory":"Tools & Machinery",
            "type":"Manufacturing & Wholesale Goods"
        }
    ],
    "sg:phone":"+64 7-847 7407",
    "sg:province":"Waikato",
    "sg:tags":[
        "equipment",
        "industrial"
    ],
    "sg:website":"http://www.diamondtools.co.nz",
    "wof:name":"Australasian Diamond Tools Ltd",
    "wof:placetype":"venue"
},
  "geometry": {"coordinates":[-87.988968,34.142426],"type":"Point"}
}