{
  "type": "Feature",
  "properties": {
    "addr:full":"95 High St  Waipawa",
    "addr:housenumber":"95",
    "addr:street":"High St",
    "iso:country":"NZ",
    "sg:address":"95 High St ",
    "sg:city":"Waipawa",
    "sg:orig_category":"Home And Garden: Furniture/Furnishings: Curtains",
    "sg:phone":"+64 6-857 8227",
    "wof:name":"Waipawa Furnishings Curtain Boutique",
    "wof:placetype":"venue"
},
  "geometry": {"coordinates":[176.58912699999999,-39.942047],"type":"Point"}
}