{
  "type": "Feature",
  "properties": {
    "addr:full":"168 Main St  Otautau",
    "addr:housenumber":"168",
    "addr:street":"Main St",
    "iso:country":"NZ",
    "sg:address":"168 Main St ",
    "sg:city":"Otautau",
    "sg:orig_category":"Health And Beauty: Products: Pharmacies",
    "sg:phone":"+64 3-225 8321",
    "wof:name":"Carletons Pharmacy",
    "wof:placetype":"venue"
},
  "geometry": {"coordinates":[168.00706500000001,-46.153759],"type":"Point"}
}