{
  "type": "Feature",
  "properties": {
    "addr:full":"46 Queen St  Masterton Wellington",
    "addr:housenumber":"46",
    "addr:street":"Queen St",
    "iso:country":"NZ",
    "sg:address":"46 Queen St ",
    "sg:city":"Masterton",
    "sg:classifiers":[
        {
            "category":"Shopping",
            "subcategory":"Crafts & Fabrics",
            "type":"Retail Goods"
        }
    ],
    "sg:phone":"+64 6-377 0618",
    "sg:province":"Wellington",
    "sg:tags":[
        "clothing"
    ],
    "wof:name":"Yvonne's Kids Wear",
    "wof:placetype":"venue"
},
  "geometry": {"coordinates":[175.663284,-40.948605],"type":"Point"}
}