{
  "type": "Feature",
  "properties": {
    "addr:full":"Treaty Ground Waitangi  Paihia Canterbury",
    "addr:housenumber":"treaty",
    "addr:street":"Waitangi",
    "iso:country":"NZ",
    "sg:address":"Treaty Ground Waitangi ",
    "sg:city":"Paihia",
    "sg:classifiers":[
        {
            "category":"Personal",
            "type":"Services"
        }
    ],
    "sg:phone":"+64 9-402 6275",
    "sg:province":"Canterbury",
    "sg:tags":[
        "arrangements",
        "wedding"
    ],
    "wof:name":"Waikokopu Cafe",
    "wof:placetype":"venue"
},
  "geometry": {"coordinates":[174.09106399999999,-35.283691],"type":"Point"}
}