{
  "type": "Feature",
  "properties": {
    "addr:full":"36 Willow St  Tauranga Bay of Plenty",
    "addr:housenumber":"36",
    "addr:street":"Willow St",
    "iso:country":"NZ",
    "sg:address":"36 Willow St ",
    "sg:city":"Tauranga",
    "sg:orig_category":"Non-Classified Establishments",
    "sg:phone":"+64 7-578 0811",
    "sg:province":"Bay of Plenty",
    "sg:website":"http://www.yellowpages.co.nz/for/dennispocockarchitects/dp50003.html",
    "wof:name":"Pocock Dennis",
    "wof:placetype":"venue"
},
  "geometry": {"coordinates":[176.16880800000001,-37.680485],"type":"Point"}
}