{
  "type": "Feature",
  "properties": {
    "addr:full":"12 Harrier St Greerton  Tauranga Bay of Plenty",
    "addr:housenumber":"12",
    "addr:street":"Harrier St",
    "iso:country":"NZ",
    "sg:address":"12 Harrier St Greerton ",
    "sg:city":"Tauranga",
    "sg:orig_category":"Health And Beauty: Beauty: Hairdressers",
    "sg:phone":"+64 7-571 1100",
    "sg:province":"Bay of Plenty",
    "wof:name":"Hair Studio 12",
    "wof:placetype":"venue"
},
  "geometry": {"coordinates":[176.12973,-37.729122],"type":"Point"}
}