{
  "type": "Feature",
  "properties": {
    "iso:country":"NZ",
    "sg:address":"373 Tiniroto Rd R D 2 ",
    "sg:city":"Gisborne",
    "sg:orig_category":"Home And Garden: General: Handyman'S Services",
    "sg:phone":"+64 6-862 7654",
    "sg:province":"Gisborne",
    "wof:name":"Twigley Mark",
    "wof:placetype":"venue"
},
  "geometry": {"coordinates":[178.024475,-38.66597],"type":"Point"}
}