{
  "type": "Feature",
  "properties": {
    "addr:full":"222 B Hibiscus Coast Hwy Orewa PO Box 79128 Royal Heights Auckland Auckland",
    "addr:housenumber":"222 b;po box 79128",
    "addr:street":"Hibiscus Coast Hwy;Heights",
    "iso:country":"NZ",
    "sg:address":"222 B Hibiscus Coast Hwy Orewa PO Box 79128 Royal Heights",
    "sg:city":"Auckland",
    "sg:classifiers":[
        {
            "category":"Retail",
            "subcategory":"Storage",
            "type":"Services"
        }
    ],
    "sg:phone":"+64 9-416 8098",
    "sg:province":"Auckland",
    "sg:tags":[
        "system"
    ],
    "wof:name":"Steel Storage (NZ) Limited",
    "wof:placetype":"venue"
},
  "geometry": {"coordinates":[174.77041600000001,-36.884109],"type":"Point"}
}