{
  "type": "Feature",
  "properties": {
    "addr:full":"Unit B/7 Sunlight Grove Porirua  Wellington Wellington",
    "addr:housenumber":"7",
    "addr:street":"Sunlight Grove",
    "iso:country":"NZ",
    "sg:address":"Unit B/7 Sunlight Grove Porirua ",
    "sg:city":"Wellington",
    "sg:orig_category":"Industrial: Metal: Services: Metal Detection",
    "sg:phone":"+64 508 722 537",
    "sg:province":"Wellington",
    "wof:name":"Metal Detection & X-Ray Food",
    "wof:placetype":"venue"
},
  "geometry": {"coordinates":[174.82162500000001,-41.325909],"type":"Point"}
}