{
  "type": "Feature",
  "properties": {
    "iso:country":"NZ",
    "sg:address":"2 White St ",
    "sg:city":"Rotorua",
    "sg:classifiers":[
        {
            "category":"Sports & Exercise",
            "subcategory":"Swimming Pool",
            "type":"Entertainment"
        }
    ],
    "sg:phone":"+64 7-349 4414",
    "sg:province":"Bay of Plenty",
    "sg:tags":[
        "home",
        "outdoor",
        "garden",
        "spa"
    ],
    "wof:name":"Poolcare Specialists Ltd",
    "wof:placetype":"venue"
},
  "geometry": {"coordinates":[176.262146,-38.149296],"type":"Point"}
}