{
  "type": "Feature",
  "properties": {
    "iso:country":"NZ",
    "sg:address":"Takapau Rd ",
    "sg:city":"Waipukurau",
    "sg:classifiers":[
        {
            "category":"Home & Garden",
            "subcategory":"Home Furnishings",
            "type":"Retail Goods"
        }
    ],
    "sg:phone":"+64 6-858 8411",
    "sg:tags":[
        "furniture/furnishings",
        "upholstery",
        "supply"
    ],
    "wof:name":"Sloans Saddlery & Canvas Ltd",
    "wof:placetype":"venue"
},
  "geometry": {"coordinates":[176.52529899999999,-39.990215],"type":"Point"}
}