{
  "type": "Feature",
  "properties": {
    "iso:country":"NZ",
    "sg:address":"128 A North St Parkside ",
    "sg:city":"Timaru",
    "sg:classifiers":[
        {
            "category":"Fast Food",
            "type":"Food & Drink"
        }
    ],
    "sg:phone":"+64 3-688 6553",
    "sg:province":"Canterbury",
    "sg:tags":[
        "wining",
        "dining",
        "takeaway"
    ],
    "wof:name":"Fast Food Factory",
    "wof:placetype":"venue"
},
  "geometry": {"coordinates":[171.24238600000001,-44.40052],"type":"Point"}
}