{
  "type": "Feature",
  "properties": {
    "addr:full":"57 Rue Lavaud  Akaroa Canterbury",
    "addr:housenumber":"57",
    "addr:street":"Rue Lavaud Akaroa",
    "iso:country":"NZ",
    "sg:address":"57 Rue Lavaud ",
    "sg:city":"Akaroa",
    "sg:classifiers":[
        {
            "category":"Shopping",
            "subcategory":"Gifts & Souvenirs",
            "type":"Retail Goods"
        }
    ],
    "sg:phone":"+64 3-304 7781",
    "sg:province":"Canterbury",
    "sg:tags":[
        "travel",
        "tourism"
    ],
    "wof:name":"Naturally Jade",
    "wof:placetype":"venue"
},
  "geometry": {"coordinates":[172.96785,-43.804455],"type":"Point"}
}