{
  "type": "Feature",
  "properties": {
    "addr:full":"85 Tahunanui Dve Tahunanui  Nelson Nelson",
    "addr:housenumber":"85",
    "addr:street":"Dve",
    "iso:country":"NZ",
    "sg:address":"85 Tahunanui Dve Tahunanui ",
    "sg:city":"Nelson",
    "sg:orig_category":"Health And Beauty: Dental: Dentists",
    "sg:phone":"+64 3-548 6564",
    "sg:province":"Nelson",
    "wof:name":"Tahunanui Dental Centre",
    "wof:placetype":"venue"
},
  "geometry": {"coordinates":[173.24464399999999,-41.283855],"type":"Point"}
}