{
  "type": "Feature",
  "properties": {
    "addr:full":"Sheffield St  Katikati",
    "addr:street":"Sheffield St",
    "iso:country":"NZ",
    "sg:address":"Sheffield St ",
    "sg:city":"Katikati",
    "sg:orig_category":"Farming: Machinery: Tractors",
    "sg:phone":"+64 7-549 0330",
    "wof:name":"Katikati Tractors & Auto",
    "wof:placetype":"venue"
},
  "geometry": {"coordinates":[175.91615300000001,-37.56065],"type":"Point"}
}