{
  "type": "Feature",
  "properties": {
    "iso:country":"NZ",
    "sg:address":"40 Leet St ",
    "sg:city":"Invercargill",
    "sg:classifiers":[
        {
            "category":"Retail",
            "subcategory":"Auto Repair",
            "type":"Services"
        }
    ],
    "sg:phone":"+64 3-214 2136",
    "sg:province":"Southland",
    "sg:tags":[
        "engine",
        "automotive",
        "servicing"
    ],
    "wof:name":"Autotec Tuning & Service",
    "wof:placetype":"venue"
},
  "geometry": {"coordinates":[168.34895299999999,-46.407372],"type":"Point"}
}