{
  "type": "Feature",
  "properties": {
    "iso:country":"NZ",
    "sg:address":"513 Barbadoes St St Albans ",
    "sg:city":"Christchurch",
    "sg:classifiers":[
        {
            "category":"Food & Beverages",
            "subcategory":"Candy",
            "type":"Retail Goods"
        }
    ],
    "sg:phone":"+64 3-366 6677",
    "sg:province":"Canterbury",
    "sg:tags":[
        "confectioner",
        "drink",
        "-"
    ],
    "wof:name":"Chocolataire",
    "wof:placetype":"venue"
},
  "geometry": {"coordinates":[172.63618500000001,-43.511974],"type":"Point"}
}