{
  "type": "Feature",
  "properties": {
    "addr:full":"R D 5 Oroua Rd  Kairanga",
    "addr:housenumber":"5",
    "addr:street":"R D;Oroua Rd",
    "iso:country":"NZ",
    "sg:address":"R D 5 Oroua Rd ",
    "sg:city":"Kairanga",
    "sg:orig_category":"Farming: Agriculture: Agricultural Contractors",
    "sg:phone":"+64 6-329 0793",
    "wof:name":"Andy Dahl Contracting Ltd",
    "wof:placetype":"venue"
},
  "geometry": {"coordinates":[175.42527799999999,-40.29071],"type":"Point"}
}