{
  "type": "Feature",
  "properties": {
    "iso:country":"NZ",
    "sg:address":"6 Birch St ",
    "sg:city":"Dunedin",
    "sg:orig_category":"Automotive: Parts And Supplies: Automotive Dismantlers",
    "sg:phone":"+64 3-474 1755",
    "sg:province":"Otago",
    "wof:name":"Japanese Auto Wreckers Ltd",
    "wof:placetype":"venue"
},
  "geometry": {"coordinates":[-82.745728,28.033939],"type":"Point"}
}