{
  "type": "Feature",
  "properties": {
    "addr:full":"52 Beatty Ave Te  Puke Bay of Plenty",
    "addr:housenumber":"52",
    "addr:street":"Beatty Ave",
    "iso:country":"NZ",
    "sg:address":"52 Beatty Ave Te ",
    "sg:city":"Puke",
    "sg:orig_category":"Shopping: Retail Stores: Cds, Cassettes And Records",
    "sg:phone":"+64 7-573 9609",
    "sg:province":"Bay of Plenty",
    "wof:name":"Sound City Country Music",
    "wof:placetype":"venue"
},
  "geometry": {"coordinates":[176.31942699999999,-37.786518],"type":"Point"}
}