{
  "type": "Feature",
  "properties": {
    "iso:country":"NZ",
    "sg:address":"29-31 Commerce St ",
    "sg:city":"Tokoroa",
    "sg:classifiers":[
        {
            "category":"Bus Charters",
            "type":"Transportation"
        }
    ],
    "sg:phone":"+64 7-886 5399",
    "sg:tags":[
        "services",
        "travel",
        "tourism"
    ],
    "wof:name":"Tokoroa Buses",
    "wof:placetype":"venue"
},
  "geometry": {"coordinates":[175.87114,-38.21627],"type":"Point"}
}