{
  "type": "Feature",
  "properties": {
    "iso:country":"NZ",
    "sg:address":"Bayfair Shopping Centre 103 Girven Rd Mt ",
    "sg:city":"Maunganui",
    "sg:orig_category":"Shopping: Sports Retailers: Sports Goods: Sportswear",
    "sg:phone":"+64 7-575 9320",
    "sg:province":"Bay of Plenty",
    "wof:name":"Canterbury of New Zealand - Tauranga",
    "wof:placetype":"venue"
},
  "geometry": {"coordinates":[176.21882600000001,-37.67791],"type":"Point"}
}