{
  "type": "Feature",
  "properties": {
    "iso:country":"NZ",
    "sg:address":"601 a Heretaunga St East ",
    "sg:city":"Hastings",
    "sg:classifiers":[
        {
            "category":"Arts & Performance",
            "subcategory":"Art Gallery",
            "type":"Entertainment"
        }
    ],
    "sg:phone":"+64 6-878 7986",
    "sg:province":"Hawke's Bay",
    "sg:tags":[
        "arts",
        "sport",
        "leisure"
    ],
    "wof:name":"Ingrids Art & Picture Framing",
    "wof:placetype":"venue"
},
  "geometry": {"coordinates":[-81.508163,29.711214],"type":"Point"}
}