{
  "type": "Feature",
  "properties": {
    "addr:full":"4070 Gt North Rd Glen Eden  Auckland Auckland",
    "addr:postcode":"4070 gt",
    "addr:street":"North Rd",
    "iso:country":"NZ",
    "sg:address":"4070 Gt North Rd Glen Eden ",
    "sg:city":"Auckland",
    "sg:orig_category":"Automotive: General Services: Service Stations",
    "sg:phone":"+64 9-818 5601",
    "sg:province":"Auckland",
    "wof:name":"Caltex Kelston",
    "wof:placetype":"venue"
},
  "geometry": {"coordinates":[174.65901199999999,-36.904671],"type":"Point"}
}