{
  "type": "Feature",
  "properties": {
    "iso:country":"NZ",
    "sg:address":"cnr Tutanekai & Amohau Sts ",
    "sg:city":"Rotorua",
    "sg:orig_category":"Health And Beauty: Products: Pharmacies",
    "sg:phone":"+64 7-348 3035",
    "sg:province":"Bay of Plenty",
    "wof:name":"Ludgates Amcal Pharmacy",
    "wof:placetype":"venue"
},
  "geometry": {"coordinates":[176.244995,-38.1418],"type":"Point"}
}