{
  "type": "Feature",
  "properties": {
    "addr:full":"396 Don Buck Rd Massey  Auckland Auckland",
    "addr:housenumber":"396",
    "addr:street":"Don Buck Rd",
    "iso:country":"NZ",
    "sg:address":"396 Don Buck Rd Massey ",
    "sg:city":"Auckland",
    "sg:classifiers":[
        {
            "category":"Food & Beverages",
            "subcategory":"Liquor & Beverages",
            "type":"Retail Goods"
        }
    ],
    "sg:phone":"+64 9-832 4220",
    "sg:province":"Auckland",
    "sg:tags":[
        "drink",
        "outlet"
    ],
    "wof:name":"Don Buck Liquor Store",
    "wof:placetype":"venue"
},
  "geometry": {"coordinates":[174.602631,-36.834946],"type":"Point"}
}