{
  "type": "Feature",
  "properties": {
    "iso:country":"NZ",
    "sg:address":"171 Willis St ",
    "sg:city":"Wellington",
    "sg:classifiers":[
        {
            "category":"Retail",
            "subcategory":"Laundry & Dry Cleaning",
            "type":"Services"
        }
    ],
    "sg:phone":"+64 4-384 7008",
    "sg:province":"Wellington",
    "sg:tags":[
        "repair",
        "clothing",
        "fabric",
        "cleaner"
    ],
    "wof:name":"New Zealand Drycleaners",
    "wof:placetype":"venue"
},
  "geometry": {"coordinates":[174.773804,-41.291069],"type":"Point"}
}