{
  "type": "Feature",
  "properties": {
    "addr:full":"113 Collingwood St  Hamilton Waikato",
    "addr:housenumber":"113",
    "addr:street":"Collingwood St",
    "iso:country":"NZ",
    "sg:address":"113 Collingwood St ",
    "sg:city":"Hamilton",
    "sg:classifiers":[
        {
            "category":"Professional",
            "type":"Services"
        }
    ],
    "sg:phone":"+64 7-839 9012",
    "sg:province":"Waikato",
    "sg:tags":[
        "home",
        "cleaning",
        "help",
        "garden"
    ],
    "wof:name":"HealthCare NZ",
    "wof:placetype":"venue"
},
  "geometry": {"coordinates":[-87.988968,34.142426],"type":"Point"}
}