{
  "type": "Feature",
  "properties": {
    "addr:full":"Paradise Valley Rd Ngongotaha  Rotorua Bay of Plenty",
    "addr:street":"Paradise Valley Rd",
    "iso:country":"NZ",
    "sg:address":"Paradise Valley Rd Ngongotaha ",
    "sg:city":"Rotorua",
    "sg:classifiers":[
        {
            "category":"Shopping",
            "subcategory":"Pets & Pet Supplies",
            "type":"Retail Goods"
        }
    ],
    "sg:phone":"+64 7-357 4873",
    "sg:province":"Bay of Plenty",
    "sg:tags":[
        "boarding",
        "garden",
        "pets",
        "catteries",
        "home",
        "kennel"
    ],
    "wof:name":"Ngongotaha Pet Motel",
    "wof:placetype":"venue"
},
  "geometry": {"coordinates":[176.162643,-38.102631],"type":"Point"}
}