{
  "type": "Feature",
  "properties": {
    "iso:country":"NZ",
    "sg:address":"PO Box 158 ",
    "sg:city":"Masterton",
    "sg:classifiers":[
        {
            "category":"Building & Trades",
            "subcategory":"Construction",
            "type":"Services"
        }
    ],
    "sg:phone":"+64 25587473",
    "sg:province":"Wellington",
    "sg:tags":[
        "home",
        "garden",
        "related",
        "plasterer"
    ],
    "wof:name":"Phil Carman Decorating Ltd",
    "wof:placetype":"venue"
},
  "geometry": {"coordinates":[175.657333,-40.94931],"type":"Point"}
}