{
  "type": "Feature",
  "properties": {
    "iso:country":"NZ",
    "sg:address":"420 C New North Rd ",
    "sg:city":"Kingsland",
    "sg:classifiers":[
        {
            "category":"Coffee & Tea",
            "type":"Food & Drink"
        }
    ],
    "sg:phone":"+64 9-846 5883",
    "sg:province":"Auckland",
    "sg:tags":[
        "merchant"
    ],
    "wof:name":"Atomic Coffee Roasters",
    "wof:placetype":"venue"
},
  "geometry": {"coordinates":[-92.296257,33.858845],"type":"Point"}
}