{
  "type": "Feature",
  "properties": {
    "addr:full":"200 Lower Emerson St  Napier Hawke's Bay",
    "addr:housenumber":"200",
    "addr:street":"Lower Emerson St",
    "iso:country":"NZ",
    "sg:address":"200 Lower Emerson St ",
    "sg:city":"Napier",
    "sg:classifiers":[
        {
            "category":"Shopping",
            "subcategory":"Hobbies, Toys, & Games",
            "type":"Retail Goods"
        }
    ],
    "sg:phone":"+64 6-833 7057",
    "sg:province":"Hawke's Bay",
    "sg:tags":[
        "hobby",
        "puzzle",
        "games"
    ],
    "wof:name":"The Gamesman",
    "wof:placetype":"venue"
},
  "geometry": {"coordinates":[-80.588562,38.790821],"type":"Point"}
}