{
  "type": "Feature",
  "properties": {
    "addr:full":"177 Flaxton Rd Rangiora R D 1 Kaiapoi  Rangiora Canterbury",
    "addr:housenumber":"177;1",
    "addr:street":"Flaxton Rd;R D",
    "iso:country":"NZ",
    "sg:address":"177 Flaxton Rd Rangiora R D 1 Kaiapoi ",
    "sg:city":"Rangiora",
    "sg:classifiers":[
        {
            "category":"Marine",
            "type":"Transportation"
        }
    ],
    "sg:phone":"+64 3-313 7260",
    "sg:province":"Canterbury",
    "sg:tags":[
        "boats",
        "builder",
        "yacht",
        "transport",
        "boat"
    ],
    "wof:name":"Rapidrunner Alloy Jetboats",
    "wof:placetype":"venue"
},
  "geometry": {"coordinates":[172.59030200000001,-43.302963],"type":"Point"}
}