{
  "type": "Feature",
  "properties": {
    "addr:full":"36 Mangakahia Rd  Kaikohe",
    "addr:housenumber":"36",
    "addr:street":"Mangakahia Rd",
    "iso:country":"NZ",
    "sg:address":"36 Mangakahia Rd ",
    "sg:city":"Kaikohe",
    "sg:orig_category":"Education And Training: General: Schools",
    "sg:phone":"+64 9-401 1532",
    "wof:name":"Kaikohe East School",
    "wof:placetype":"venue"
},
  "geometry": {"coordinates":[173.80602999999999,-35.410667],"type":"Point"}
}