{
  "type": "Feature",
  "properties": {
    "iso:country":"NZ",
    "sg:address":"Taradale ",
    "sg:city":"Napier",
    "sg:orig_category":"Home And Garden: Gardening: Services: Lawnmowing Services",
    "sg:phone":"+64 6-844 8098",
    "sg:province":"Hawke's Bay",
    "wof:name":"Lawnmowing Services",
    "wof:placetype":"venue"
},
  "geometry": {"coordinates":[176.847198,-39.534081],"type":"Point"}
}