{
  "type": "Feature",
  "properties": {
    "addr:full":"Whangamarino Rd Te  Kauwhata",
    "addr:street":"Whangamarino Rd",
    "iso:country":"NZ",
    "sg:address":"Whangamarino Rd Te ",
    "sg:city":"Kauwhata",
    "sg:classifiers":[
        {
            "category":"Shopping",
            "subcategory":"Computers & Home Electronics",
            "type":"Retail Goods"
        }
    ],
    "sg:phone":"+64 7-826 4262",
    "sg:tags":[
        "equipment",
        "sport",
        "leisure",
        "entertainment"
    ],
    "wof:name":"Electronic Leisure Games Ltd",
    "wof:placetype":"venue"
},
  "geometry": {"coordinates":[175.14735400000001,-37.403275],"type":"Point"}
}