{
  "type": "Feature",
  "properties": {
    "addr:full":"35 Westhaven Dve Tawa  Wellington Wellington",
    "addr:housenumber":"35",
    "addr:street":"Westhaven Dve",
    "iso:country":"NZ",
    "sg:address":"35 Westhaven Dve Tawa ",
    "sg:city":"Wellington",
    "sg:orig_category":"Industrial: Services: Gasfitters",
    "sg:phone":"+64 4-232 1383",
    "sg:province":"Wellington",
    "wof:name":"B+S Gas Services",
    "wof:placetype":"venue"
},
  "geometry": {"coordinates":[174.82420300000001,-41.171494],"type":"Point"}
}