{
  "type": "Feature",
  "properties": {
    "addr:full":"Glengarry Cre  Invercargill Southland",
    "iso:country":"NZ",
    "sg:address":"Glengarry Cre ",
    "sg:city":"Invercargill",
    "sg:orig_category":"Shopping: Retail Stores: Books: Bookshops",
    "sg:phone":"+64 3-217 5675",
    "sg:province":"Southland",
    "wof:name":"Glengarry News Agency",
    "wof:placetype":"venue"
},
  "geometry": {"coordinates":[168.381912,-46.398476],"type":"Point"}
}