{
  "type": "Feature",
  "properties": {
    "addr:full":"91 Treffers Rd Sockburn  Christchurch Canterbury",
    "addr:housenumber":"91",
    "addr:street":"Treffers Rd",
    "iso:country":"NZ",
    "sg:address":"91 Treffers Rd Sockburn ",
    "sg:city":"Christchurch",
    "sg:classifiers":[
        {
            "category":"Banks & Credit Unions",
            "subcategory":"Investment Brokerage",
            "type":"Services"
        }
    ],
    "sg:phone":"+64 3-348 5597",
    "sg:province":"Canterbury",
    "sg:tags":[
        "chemical",
        "industrial",
        "-",
        "compounds"
    ],
    "wof:name":"Bayer (NZ) Ltd",
    "wof:placetype":"venue"
},
  "geometry": {"coordinates":[172.55043000000001,-43.534966],"type":"Point"}
}