{
  "type": "Feature",
  "properties": {
    "addr:full":"Hinemoa Ave  Taupo Waikato",
    "addr:street":"Hinemoa Ave",
    "iso:country":"NZ",
    "sg:address":"Hinemoa Ave ",
    "sg:city":"Taupo",
    "sg:classifiers":[
        {
            "category":"Insurance",
            "subcategory":"Health Insurance",
            "type":"Services"
        }
    ],
    "sg:phone":"+64 7-378 0761",
    "sg:province":"Waikato",
    "sg:tags":[
        "beauty",
        "supply"
    ],
    "wof:name":"Hands'n'Feet",
    "wof:placetype":"venue"
},
  "geometry": {"coordinates":[176.09610000000001,-38.687874],"type":"Point"}
}