{
  "type": "Feature",
  "properties": {
    "addr:full":"169 Wordsworth St Sydenham  Christchurch Canterbury",
    "addr:housenumber":"169",
    "addr:street":"Wordsworth St",
    "iso:country":"NZ",
    "sg:address":"169 Wordsworth St Sydenham ",
    "sg:city":"Christchurch",
    "sg:orig_category":"Industrial: Abrasives: Abrasives - General",
    "sg:phone":"+64 3-366 5190",
    "sg:province":"Canterbury",
    "wof:name":"Avon Engineering Supplies Ltd",
    "wof:placetype":"venue"
},
  "geometry": {"coordinates":[172.64355499999999,-43.544533],"type":"Point"}
}