{
  "type": "Feature",
  "properties": {
    "addr:full":"Int'l Departure Terminal Christchurch Airport Christchurch, Airport  Christchurch Canterbury",
    "iso:country":"NZ",
    "sg:address":"Int'l Departure Terminal Christchurch Airport Christchurch, Airport ",
    "sg:city":"Christchurch",
    "sg:classifiers":[
        {
            "category":"Shopping",
            "subcategory":"Hobbies, Toys, & Games",
            "type":"Retail Goods"
        }
    ],
    "sg:phone":"+64 3-353 1985",
    "sg:province":"Canterbury",
    "sg:tags":[
        "hobby"
    ],
    "wof:name":"Seal 'N Secure Christchurch Ltd",
    "wof:placetype":"venue"
},
  "geometry": {"coordinates":[172.53401199999999,-43.485931],"type":"Point"}
}