{
  "type": "Feature",
  "properties": {
    "addr:full":"376 Kapiti Rd  Paraparaumu Wellington",
    "addr:housenumber":"376",
    "addr:street":"Kapiti Rd",
    "iso:country":"NZ",
    "sg:address":"376 Kapiti Rd ",
    "sg:city":"Paraparaumu",
    "sg:orig_category":"Sports And Leisure: Sports: Golf",
    "sg:phone":"+64 4-902 8200",
    "sg:province":"Wellington",
    "sg:website":"http://www.paraparaumubeachgolfclub.co.nz",
    "wof:name":"Paraparaumu Beach Golf Club Inc",
    "wof:placetype":"venue"
},
  "geometry": {"coordinates":[174.98275799999999,-40.892197],"type":"Point"}
}