{
  "type": "Feature",
  "properties": {
    "addr:full":"12 Stock St New Lynn  Auckland Auckland",
    "addr:housenumber":"12",
    "addr:street":"Stock St",
    "iso:country":"NZ",
    "sg:address":"12 Stock St New Lynn ",
    "sg:city":"Auckland",
    "sg:orig_category":"Shopping: Retail Stores: Toys",
    "sg:phone":"+64 9-827 8648",
    "sg:province":"Auckland",
    "wof:name":"Auckland Playcentre Shop",
    "wof:placetype":"venue"
},
  "geometry": {"coordinates":[174.68679800000001,-36.902889],"type":"Point"}
}