{
  "type": "Feature",
  "properties": {
    "iso:country":"NZ",
    "sg:address":"22 - 24 Cecil Rd ",
    "sg:city":"Mamaku",
    "sg:orig_category":"Food And Drink: Meats: Homekill Services",
    "sg:phone":"+64 7-332 5646",
    "wof:name":"Mamaku Custom Kill",
    "wof:placetype":"venue"
},
  "geometry": {"coordinates":[176.072281,-38.08778],"type":"Point"}
}