{
  "type": "Feature",
  "properties": {
    "iso:country":"NZ",
    "sg:address":"Pakuranga ",
    "sg:city":"Auckland",
    "sg:orig_category":"Shopping: Retail Stores: Cds, Cassettes And Records",
    "sg:phone":"+64 800 423 737",
    "sg:province":"Auckland",
    "sg:website":"http://www.discstation.co.nz",
    "wof:name":"DiscSTATION",
    "wof:placetype":"venue"
},
  "geometry": {"coordinates":[174.87904399999999,-36.91584],"type":"Point"}
}