{
  "type": "Feature",
  "properties": {
    "addr:full":"53 Greenmount Dve East Tamaki  Auckland Auckland",
    "addr:housenumber":"53",
    "addr:street":"Greenmount Dve",
    "iso:country":"NZ",
    "sg:address":"53 Greenmount Dve East Tamaki ",
    "sg:city":"Auckland",
    "sg:classifiers":[
        {
            "category":"Manufacturing",
            "subcategory":"Food",
            "type":"Manufacturing & Wholesale Goods"
        }
    ],
    "sg:phone":"+64 9-271 4792",
    "sg:province":"Auckland",
    "sg:tags":[
        "drink",
        "-",
        "manufacturer"
    ],
    "wof:name":"Kato Pacific Marketing Ltd",
    "wof:placetype":"venue"
},
  "geometry": {"coordinates":[174.90176399999999,-36.931881],"type":"Point"}
}