{
  "type": "Feature",
  "properties": {
    "iso:country":"NZ",
    "sg:address":"24 Liverpool St ",
    "sg:city":"Levin",
    "sg:orig_category":"Farming: Forestry: Forestry Contractors",
    "sg:phone":"+64 6-368 5285",
    "sg:province":"Manawatu-Wanganui",
    "sg:website":"http://www.yellowpages.co.nz/for/columnskapiticoast/dp48384.html",
    "wof:name":"Columns Kapiti Coast",
    "wof:placetype":"venue"
},
  "geometry": {"coordinates":[1.252869,52.00518],"type":"Point"}
}