{
  "type": "Feature",
  "properties": {
    "addr:full":"65 Riri St  Rotorua Bay of Plenty",
    "addr:housenumber":"65",
    "addr:street":"Riri St",
    "iso:country":"NZ",
    "sg:address":"65 Riri St ",
    "sg:city":"Rotorua",
    "sg:classifiers":[
        {
            "category":"Professional",
            "subcategory":"Art Services",
            "type":"Services"
        }
    ],
    "sg:phone":"+64 7-348 4650",
    "sg:province":"Bay of Plenty",
    "sg:tags":[
        "picture",
        "arts",
        "sport",
        "framing",
        "leisure"
    ],
    "wof:name":"Wholesale Picture Framers",
    "wof:placetype":"venue"
},
  "geometry": {"coordinates":[176.230164,-38.132324],"type":"Point"}
}