{
  "type": "Feature",
  "properties": {
    "iso:country":"NZ",
    "sg:address":"212 East St ",
    "sg:city":"Ashburton",
    "sg:orig_category":"Shopping: Retail Stores: Stationery",
    "sg:phone":"+64 3-308 8309",
    "sg:province":"Canterbury",
    "wof:name":"Ashburton Paper Plus",
    "wof:placetype":"venue"
},
  "geometry": {"coordinates":[-77.127831,39.012852],"type":"Point"}
}