{
  "type": "Feature",
  "properties": {
    "addr:full":"26 Botha Rd Penrose  Auckland Auckland",
    "addr:housenumber":"26",
    "addr:street":"Botha Rd",
    "iso:country":"NZ",
    "sg:address":"26 Botha Rd Penrose ",
    "sg:city":"Auckland",
    "sg:classifiers":[
        {
            "category":"Food & Beverages",
            "subcategory":"Candy",
            "type":"Retail Goods"
        }
    ],
    "sg:phone":"+64 9-579 4932",
    "sg:province":"Auckland",
    "sg:tags":[
        "confectioner",
        "drink",
        "-"
    ],
    "wof:name":"Waldrons Confectionery",
    "wof:placetype":"venue"
},
  "geometry": {"coordinates":[174.80874600000001,-36.911285],"type":"Point"}
}