{
  "type": "Feature",
  "properties": {
    "addr:full":"6 Borrell Ave New  Plymouth Taranaki",
    "addr:housenumber":"6",
    "addr:street":"Borrell Ave",
    "iso:country":"NZ",
    "sg:address":"6 Borrell Ave New ",
    "sg:city":"Plymouth",
    "sg:orig_category":"Automotive: Parts And Supplies: Automotive Dismantlers",
    "sg:phone":"+64 6-753 8106",
    "sg:province":"Taranaki",
    "wof:name":"Simply Subaru Auto Spares",
    "wof:placetype":"venue"
},
  "geometry": {"coordinates":[-116.81972500000001,43.97221],"type":"Point"}
}