{
  "type": "Feature",
  "properties": {
    "addr:full":"Rowland Rd Hoanga  Dargaville Northland",
    "addr:street":"Rowland Rd",
    "iso:country":"NZ",
    "sg:address":"Rowland Rd Hoanga ",
    "sg:city":"Dargaville",
    "sg:classifiers":[
        {
            "category":"Farming",
            "subcategory":"Poultry Farm",
            "type":"Manufacturing & Wholesale Goods"
        }
    ],
    "sg:phone":"+64 9-439 6263",
    "sg:province":"Northland",
    "sg:tags":[
        "emu",
        "-"
    ],
    "wof:name":"Warrakathi Yampa",
    "wof:placetype":"venue"
},
  "geometry": {"coordinates":[173.914841,-35.940647],"type":"Point"}
}