{
  "type": "Feature",
  "properties": {
    "addr:full":"11 Napier Rd Havelock North  Hastings Hawke's Bay",
    "addr:housenumber":"11",
    "addr:street":"Napier Rd",
    "iso:country":"NZ",
    "sg:address":"11 Napier Rd Havelock North ",
    "sg:city":"Hastings",
    "sg:orig_category":"Home And Garden: Furniture/Furnishings: Curtains",
    "sg:phone":"+64 6-877 7033",
    "sg:province":"Hawke's Bay",
    "wof:name":"Treachers Furniture and Furnishings",
    "wof:placetype":"venue"
},
  "geometry": {"coordinates":[176.87768600000001,-39.669476],"type":"Point"}
}