{
  "type": "Feature",
  "properties": {
    "addr:full":"331 Redoubt Rd Manurewa  Auckland Auckland",
    "addr:housenumber":"331",
    "addr:street":"Redoubt Rd",
    "iso:country":"NZ",
    "sg:address":"331 Redoubt Rd Manurewa ",
    "sg:city":"Auckland",
    "sg:classifiers":[
        {
            "category":"Retail",
            "subcategory":"Storage",
            "type":"Services"
        }
    ],
    "sg:phone":"+64 25954411",
    "sg:province":"Auckland",
    "sg:tags":[
        "system"
    ],
    "wof:name":"Adams Building Services Ltd",
    "wof:placetype":"venue"
},
  "geometry": {"coordinates":[174.91696200000001,-37.021488],"type":"Point"}
}