{
  "type": "Feature",
  "properties": {
    "iso:country":"NZ",
    "sg:address":"1362 State Highway 2 Omokoroa ",
    "sg:city":"Tauranga",
    "sg:classifiers":[
        {
            "category":"Retail",
            "subcategory":"Auto Repair",
            "type":"Services"
        }
    ],
    "sg:phone":"+64 7-548 1789",
    "sg:province":"Bay of Plenty",
    "sg:tags":[
        "automotive",
        "panel",
        "servicing",
        "beater"
    ],
    "wof:name":"Mike Deane Motors",
    "wof:placetype":"venue"
},
  "geometry": {"coordinates":[176.14476,-37.703152],"type":"Point"}
}