{
  "type": "Feature",
  "properties": {
    "iso:country":"NZ",
    "sg:address":"1034 Wainui Rd Ohope ",
    "sg:city":"Whakatane",
    "sg:classifiers":[
        {
            "category":"Shopping",
            "subcategory":"Crafts & Fabrics",
            "type":"Retail Goods"
        }
    ],
    "sg:phone":"+64 7-312 4583",
    "sg:province":"Bay of Plenty",
    "sg:tags":[
        "pottery",
        "home",
        "accessories",
        "garden",
        "supply"
    ],
    "wof:name":"Cheddar Valley Pottery",
    "wof:placetype":"venue"
},
  "geometry": {"coordinates":[177.068069,-37.979507],"type":"Point"}
}