{
  "type": "Feature",
  "properties": {
    "iso:country":"NZ",
    "sg:address":"202 State Highway 3 ",
    "sg:city":"Wanganui",
    "sg:orig_category":"Travel And Tourism: Accommodation: Farmstays And Homestays",
    "sg:phone":"+64 6-347 7751",
    "sg:province":"Manawatu-Wanganui",
    "wof:name":"Arlesford House",
    "wof:placetype":"venue"
},
  "geometry": {"coordinates":[175.03212,-39.929295],"type":"Point"}
}