{
  "type": "Feature",
  "properties": {
    "iso:country":"NZ",
    "sg:address":"54-57 Firth St ",
    "sg:city":"Matamata",
    "sg:classifiers":[
        {
            "category":"Retail",
            "subcategory":"Auto Repair",
            "type":"Services"
        }
    ],
    "sg:phone":"+64 7-888 6692",
    "sg:province":"Waikato",
    "sg:tags":[
        "muffler",
        "exhaust",
        "servicing",
        "automotive"
    ],
    "wof:name":"Matamata Under-Car Services",
    "wof:placetype":"venue"
},
  "geometry": {"coordinates":[175.769897,-37.825302],"type":"Point"}
}