{
  "type": "Feature",
  "properties": {
    "iso:country":"NZ",
    "sg:address":"Cnr Blenheim & Curletts Rds Sockburn ",
    "sg:city":"Christchurch",
    "sg:classifiers":[
        {
            "category":"Home & Garden",
            "subcategory":"Furniture",
            "type":"Retail Goods"
        }
    ],
    "sg:phone":"+64 3-343 3204",
    "sg:province":"Canterbury",
    "sg:tags":[
        "furniture/furnishings",
        "furnishing"
    ],
    "wof:name":"Target Furniture S.I Ltd",
    "wof:placetype":"venue"
},
  "geometry": {"coordinates":[172.55044599999999,-43.534962],"type":"Point"}
}