{
  "type": "Feature",
  "properties": {
    "iso:country":"NZ",
    "sg:address":"State Highway 8 Dumbarton ",
    "sg:city":"Roxburgh",
    "sg:orig_category":"Farming: Horticulture: Orchardists",
    "sg:phone":"+64 252234552",
    "wof:name":"Dunrock Orchard",
    "wof:placetype":"venue"
},
  "geometry": {"coordinates":[169.315643,-45.540482],"type":"Point"}
}