{
  "type": "Feature",
  "properties": {
    "addr:full":"1410 Karamu Rd North  Hastings Hawke's Bay",
    "addr:street":"Karamu Rd",
    "iso:country":"NZ",
    "sg:address":"1410 Karamu Rd North ",
    "sg:city":"Hastings",
    "sg:classifiers":[
        {
            "category":"Restaurant",
            "type":"Food & Drink"
        }
    ],
    "sg:phone":"+64 6-876 3764",
    "sg:province":"Hawke's Bay",
    "sg:tags":[
        "wining",
        "dining"
    ],
    "wof:name":"McGinty's Restaurant",
    "wof:placetype":"venue"
},
  "geometry": {"coordinates":[176.86256399999999,-39.632759],"type":"Point"}
}