{
  "type": "Feature",
  "properties": {
    "iso:country":"NZ",
    "sg:address":"72 Otewa Rd ",
    "sg:city":"Otorohanga",
    "sg:classifiers":[
        {
            "category":"Retail",
            "subcategory":"Auto Repair",
            "type":"Services"
        }
    ],
    "sg:phone":"+64 7-873 7319",
    "sg:tags":[
        "engine",
        "automotive",
        "servicing"
    ],
    "wof:name":"Motor Preparations Ltd",
    "wof:placetype":"venue"
},
  "geometry": {"coordinates":[175.215179,-38.194405],"type":"Point"}
}