{
  "type": "Feature",
  "properties": {
    "addr:full":"100 Great North Rd Grey Lynn  Auckland Auckland",
    "addr:housenumber":"100",
    "addr:street":"Great North Rd",
    "iso:country":"NZ",
    "sg:address":"100 Great North Rd Grey Lynn ",
    "sg:city":"Auckland",
    "sg:classifiers":[
        {
            "category":"Autos & Motor Vehicles",
            "subcategory":"Automobile Sales",
            "type":"Retail Goods"
        }
    ],
    "sg:phone":"+64 9-360 3200",
    "sg:province":"Auckland",
    "sg:tags":[
        "car",
        "management",
        "leasing",
        "fleet",
        "automotive"
    ],
    "sg:website":"http://www.giltrap.co.nz",
    "wof:name":"Giltrap Prestige",
    "wof:placetype":"venue"
},
  "geometry": {"coordinates":[174.75053399999999,-36.861588],"type":"Point"}
}