{
  "type": "Feature",
  "properties": {
    "addr:full":"P O Box 1293  Whangarei Northland",
    "addr:housenumber":"p o;1293",
    "iso:country":"NZ",
    "sg:address":"P O Box 1293 ",
    "sg:city":"Whangarei",
    "sg:classifiers":[
        {
            "category":"Manufacturing",
            "subcategory":"Tools & Machinery",
            "type":"Manufacturing & Wholesale Goods"
        }
    ],
    "sg:phone":"+64 9-435 5311",
    "sg:province":"Northland",
    "sg:tags":[
        "specialist",
        "energy",
        "industrial",
        "solar",
        "equipment"
    ],
    "wof:name":"Solar Services Ltd",
    "wof:placetype":"venue"
},
  "geometry": {"coordinates":[174.320526,-35.725399],"type":"Point"}
}