{
  "type": "Feature",
  "properties": {
    "addr:full":"15 Carnforth St PO Box 13087 Green Island  Dunedin Otago",
    "addr:housenumber":"15;box 13087",
    "addr:street":"Carnforth St Po",
    "iso:country":"NZ",
    "sg:address":"15 Carnforth St PO Box 13087 Green Island ",
    "sg:city":"Dunedin",
    "sg:classifiers":[
        {
            "category":"Wholesale",
            "subcategory":"Meat",
            "type":"Manufacturing & Wholesale Goods"
        }
    ],
    "sg:phone":"+64 3-488 4199",
    "sg:province":"Otago",
    "sg:tags":[
        "food",
        "distributor",
        "drink",
        "meats"
    ],
    "wof:name":"ANZCO Green Island Plant",
    "wof:placetype":"venue"
},
  "geometry": {"coordinates":[170.439133,-45.903397],"type":"Point"}
}