{
  "type": "Feature",
  "properties": {
    "iso:country":"NZ",
    "sg:address":"3 Preston Rd Blaketown ",
    "sg:city":"Greymouth",
    "sg:orig_category":"Industrial: Metal: Scrap Metal Dealers",
    "sg:phone":"+64 3-768 7336",
    "sg:province":"West Coast",
    "wof:name":"South Island Metal Exchange",
    "wof:placetype":"venue"
},
  "geometry": {"coordinates":[171.20137,-42.451694],"type":"Point"}
}