{
  "type": "Feature",
  "properties": {
    "iso:country":"NZ",
    "sg:address":"546 McNicol Rd Clevedon ",
    "sg:city":"Auckland",
    "sg:classifiers":[
        {
            "category":"Manufacturing",
            "subcategory":"Glass & Minerals",
            "type":"Manufacturing & Wholesale Goods"
        }
    ],
    "sg:phone":"+64 9-292 8314",
    "sg:province":"Auckland",
    "sg:tags":[
        "raw",
        "industrial",
        "quarry",
        "materials"
    ],
    "wof:name":"Warren Fowler Quarries Ltd",
    "wof:placetype":"venue"
},
  "geometry": {"coordinates":[175.07579,-37.026161],"type":"Point"}
}