{
  "type": "Feature",
  "properties": {
    "iso:country":"NZ",
    "sg:address":"36 Centennial Ave ",
    "sg:city":"Alexandra",
    "sg:orig_category":"Automotive: General Services: Service Stations",
    "sg:phone":"+64 3-448 6207",
    "sg:province":"Otago",
    "wof:name":"Alexandra Service Station",
    "wof:placetype":"venue"
},
  "geometry": {"coordinates":[-85.892349,33.766979],"type":"Point"}
}