{
  "type": "Feature",
  "properties": {
    "iso:country":"NZ",
    "sg:address":"2B/170 Railside Ave Henderson ",
    "sg:city":"Auckland",
    "sg:classifiers":[
        {
            "category":"Shopping",
            "subcategory":"Gifts & Souvenirs",
            "type":"Retail Goods"
        }
    ],
    "sg:phone":"+64 9-837 3218",
    "sg:province":"Auckland",
    "sg:tags":[
        "travel",
        "tourism"
    ],
    "wof:name":"Tiki Souvenirs Ltd",
    "wof:placetype":"venue"
},
  "geometry": {"coordinates":[174.632004,-36.892197],"type":"Point"}
}