{
  "type": "Feature",
  "properties": {
    "iso:country":"NZ",
    "sg:address":"17 Maurice Rd Penrose ",
    "sg:city":"Auckland",
    "sg:orig_category":"Farming: Services",
    "sg:phone":"+64 9-622 1271",
    "sg:province":"Auckland",
    "wof:name":"Optimech Services",
    "wof:placetype":"venue"
},
  "geometry": {"coordinates":[174.80955499999999,-36.916279],"type":"Point"}
}