{
  "type": "Feature",
  "properties": {
    "addr:full":"1 Layard St  Opunake",
    "addr:housenumber":"1",
    "addr:street":"Layard St",
    "iso:country":"NZ",
    "sg:address":"1 Layard St ",
    "sg:city":"Opunake",
    "sg:classifiers":[
        {
            "category":"Social Services",
            "subcategory":"Retirement Home",
            "type":"Services"
        }
    ],
    "sg:phone":"+64 6-761 8009",
    "sg:tags":[
        "elderly",
        "convalescent",
        "garden",
        "rest",
        "care"
    ],
    "wof:name":"The Cottage Rest Home",
    "wof:placetype":"venue"
},
  "geometry": {"coordinates":[173.85701,-39.461796],"type":"Point"}
}