{
  "type": "Feature",
  "properties": {
    "addr:full":"Paraparaumu Airport  Paraparaumu Wellington",
    "iso:country":"NZ",
    "sg:address":"Paraparaumu Airport ",
    "sg:city":"Paraparaumu",
    "sg:orig_category":"Sports And Leisure: Sports: Aerial",
    "sg:phone":"+64 4-298 6294",
    "sg:province":"Wellington",
    "wof:name":"Associated Aviation",
    "wof:placetype":"venue"
},
  "geometry": {"coordinates":[174.985229,-40.903809],"type":"Point"}
}