{
  "type": "Feature",
  "properties": {
    "iso:country":"NZ",
    "sg:address":"202 Stafford St ",
    "sg:city":"Timaru",
    "sg:orig_category":"Shopping: Accessories: Jewellers And Watchmakers",
    "sg:phone":"+64 3-684 9373",
    "sg:province":"Canterbury",
    "wof:name":"Michael Hill Jeweller",
    "wof:placetype":"venue"
},
  "geometry": {"coordinates":[171.25318899999999,-44.396084],"type":"Point"}
}