{
  "type": "Feature",
  "properties": {
    "addr:full":"20 Andrew Baxter Dve Mangere  Auckland Auckland",
    "addr:housenumber":"20;mangere",
    "addr:street":"Andrew Baxter Dve",
    "iso:country":"NZ",
    "sg:address":"20 Andrew Baxter Dve Mangere ",
    "sg:city":"Auckland",
    "sg:orig_category":"Non-Classified Establishments",
    "sg:phone":"+64 9-275 4850",
    "sg:province":"Auckland",
    "wof:name":"Advanced Four Wheel Equipment",
    "wof:placetype":"venue"
},
  "geometry": {"coordinates":[174.78028900000001,-36.974323],"type":"Point"}
}