{
  "type": "Feature",
  "properties": {
    "iso:country":"NZ",
    "sg:address":"29 Dacre St Newton ",
    "sg:city":"Auckland",
    "sg:classifiers":[
        {
            "category":"Shopping",
            "subcategory":"Beauty & Cosmetics",
            "type":"Retail Goods"
        }
    ],
    "sg:phone":"+64 9-358 3050",
    "sg:province":"Auckland",
    "sg:tags":[
        "podiatrist",
        "health",
        "products",
        "supply"
    ],
    "wof:name":"GEHWOL NZ",
    "wof:placetype":"venue"
},
  "geometry": {"coordinates":[174.75900300000001,-36.861629],"type":"Point"}
}