{
  "type": "Feature",
  "properties": {
    "iso:country":"NZ",
    "sg:address":"1 Waimahia Ave Weymouth ",
    "sg:city":"Auckland",
    "sg:orig_category":"Shopping: Retail Stores: Supermarkets",
    "sg:phone":"+64 9-267 4430",
    "sg:province":"Auckland",
    "wof:name":"Weymouth Superette",
    "wof:placetype":"venue"
},
  "geometry": {"coordinates":[174.86528,-37.04282],"type":"Point"}
}