{
  "type": "Feature",
  "properties": {
    "addr:full":"5/322 Remuera Rd Remuera  Auckland Auckland",
    "addr:housenumber":"5 / 322",
    "addr:street":"Remuera Rd",
    "iso:country":"NZ",
    "sg:address":"5/322 Remuera Rd Remuera ",
    "sg:city":"Auckland",
    "sg:classifiers":[
        {
            "category":"Retail",
            "subcategory":"Laundry & Dry Cleaning",
            "type":"Services"
        }
    ],
    "sg:phone":"+64 9-522 7195",
    "sg:province":"Auckland",
    "sg:tags":[
        "product",
        "wool",
        "clothing",
        "fabric"
    ],
    "wof:name":"Textile Wools Ltd",
    "wof:placetype":"venue"
},
  "geometry": {"coordinates":[174.79638700000001,-36.88044],"type":"Point"}
}