{
  "type": "Feature",
  "properties": {
    "iso:country":"NZ",
    "sg:address":"The Grand Willis St ",
    "sg:city":"Wellington",
    "sg:classifiers":[
        {
            "category":"Retail",
            "subcategory":"Repair Shop",
            "type":"Services"
        }
    ],
    "sg:phone":"+64 4-473 1266",
    "sg:province":"Wellington",
    "sg:tags":[
        "clothing",
        "fabric",
        "cleaning"
    ],
    "wof:name":"Harach Tailoring",
    "wof:placetype":"venue"
},
  "geometry": {"coordinates":[174.767151,-41.28054],"type":"Point"}
}