{
  "type": "Feature",
  "properties": {
    "addr:full":"Beaumont R D 1  Lawrence",
    "addr:housenumber":"1",
    "addr:street":"Lawrence",
    "iso:country":"NZ",
    "sg:address":"Beaumont R D 1 ",
    "sg:city":"Lawrence",
    "sg:orig_category":"Farming: Supplies",
    "sg:phone":"+64 3-485 9522",
    "wof:name":"South Farm Supplies Ltd",
    "wof:placetype":"venue"
},
  "geometry": {"coordinates":[-95.353767,38.87336],"type":"Point"}
}