{
  "type": "Feature",
  "properties": {
    "addr:full":"149 Rangiuru Rd  Otaki",
    "addr:housenumber":"149",
    "addr:street":"Rangiuru Rd",
    "iso:country":"NZ",
    "sg:address":"149 Rangiuru Rd ",
    "sg:city":"Otaki",
    "sg:orig_category":"Home And Garden: Gardening: Products: Greenhouses And Shadehouses",
    "sg:phone":"+64 6-364 7764",
    "wof:name":"Greenhouse Services",
    "wof:placetype":"venue"
},
  "geometry": {"coordinates":[175.122726,-40.754642],"type":"Point"}
}