{
  "type": "Feature",
  "properties": {
    "iso:country":"NZ",
    "sg:address":"7 Herbert St ",
    "sg:city":"Riverton",
    "sg:classifiers":[
        {
            "category":"Home & Garden",
            "subcategory":"Building Materials",
            "type":"Retail Goods"
        }
    ],
    "sg:phone":"+64 3-234 8703",
    "sg:tags":[
        "electrician",
        "related"
    ],
    "wof:name":"Riverton Electrical",
    "wof:placetype":"venue"
},
  "geometry": {"coordinates":[-73.025848,41.957958],"type":"Point"}
}