{
  "type": "Feature",
  "properties": {
    "addr:full":"31 Princess St  Putaruru",
    "addr:housenumber":"31",
    "addr:street":"Princess St",
    "iso:country":"NZ",
    "sg:address":"31 Princess St ",
    "sg:city":"Putaruru",
    "sg:classifiers":[
        {
            "category":"Shopping",
            "subcategory":"Crafts & Fabrics",
            "type":"Retail Goods"
        }
    ],
    "sg:phone":"+64 7-883 3228",
    "sg:tags":[
        "sport",
        "art",
        "leisure",
        "hobbies"
    ],
    "wof:name":"Scrapbookin Annie Ltd",
    "wof:placetype":"venue"
},
  "geometry": {"coordinates":[175.78021200000001,-38.052971],"type":"Point"}
}