{
  "type": "Feature",
  "properties": {
    "addr:full":"408 State Highway 6 Wakapuaka  Nelson Nelson",
    "addr:housenumber":"408",
    "addr:street":"State Highway 6 Wakapuaka",
    "iso:country":"NZ",
    "sg:address":"408 State Highway 6 Wakapuaka ",
    "sg:city":"Nelson",
    "sg:classifiers":[
        {
            "category":"Home & Garden",
            "subcategory":"Building Materials",
            "type":"Retail Goods"
        }
    ],
    "sg:phone":"+64 3-545 1738",
    "sg:province":"Nelson",
    "sg:tags":[
        "related"
    ],
    "sg:website":"http://www.kiwisparks.co.nz",
    "wof:name":"Greene Nigel Electrical Ltd",
    "wof:placetype":"venue"
},
  "geometry": {"coordinates":[173.35824600000001,-41.204315],"type":"Point"}
}