{
  "type": "Feature",
  "properties": {
    "iso:country":"NZ",
    "sg:address":"4 Latter St ",
    "sg:city":"Timaru",
    "sg:classifiers":[
        {
            "category":"Personal",
            "type":"Services"
        }
    ],
    "sg:phone":"+64 3-688 8125",
    "sg:province":"Canterbury",
    "sg:tags":[
        "arrangements",
        "wedding"
    ],
    "wof:name":"Robbies Timaru Bar & Bistro",
    "wof:placetype":"venue"
},
  "geometry": {"coordinates":[171.25292999999999,-44.400078],"type":"Point"}
}