{
  "type": "Feature",
  "properties": {
    "addr:full":"125 Crinan St  Invercargill Southland",
    "addr:housenumber":"125",
    "addr:street":"Crinan St",
    "iso:country":"NZ",
    "sg:address":"125 Crinan St ",
    "sg:city":"Invercargill",
    "sg:orig_category":"Sports And Leisure: Sports: Equestrian: Saddlers",
    "sg:phone":"+64 3-218 2438",
    "sg:province":"Southland",
    "wof:name":"Custom Canvas & Watsons Saddlery Ltd",
    "wof:placetype":"venue"
},
  "geometry": {"coordinates":[168.34909099999999,-46.422478],"type":"Point"}
}