{
  "type": "Feature",
  "properties": {
    "iso:country":"NZ",
    "sg:address":"97-99 Courtenay Pl ",
    "sg:city":"Wellington",
    "sg:classifiers":[
        {
            "category":"Internet Cafe",
            "subcategory":"None",
            "type":"Food & Drink"
        }
    ],
    "sg:phone":"+64 4-384 3717",
    "sg:province":"Wellington",
    "sg:tags":[
        "wining",
        "dining"
    ],
    "wof:name":"Cyber City",
    "wof:placetype":"venue"
},
  "geometry": {"coordinates":[-83.544167,37.88097],"type":"Point"}
}