{
  "type": "Feature",
  "properties": {
    "iso:country":"NZ",
    "sg:address":"PO Box 77097 ",
    "sg:city":"Auckland",
    "sg:classifiers":[
        {
            "category":"Retail",
            "subcategory":"Auto Repair",
            "type":"Services"
        }
    ],
    "sg:phone":"+64 9-378 0780",
    "sg:province":"Auckland",
    "sg:tags":[
        "breakdown",
        "automotive",
        "towing",
        "servicing"
    ],
    "wof:name":"Auckland Towing Co",
    "wof:placetype":"venue"
},
  "geometry": {"coordinates":[-119.10457599999999,36.597755],"type":"Point"}
}