{
  "type": "Feature",
  "properties": {
    "iso:country":"NZ",
    "sg:address":"4 Logan Ave ",
    "sg:city":"Taupo",
    "sg:classifiers":[
        {
            "category":"Shopping",
            "subcategory":"Computers & Home Electronics",
            "type":"Retail Goods"
        }
    ],
    "sg:phone":"+64 7-377 2558",
    "sg:province":"Waikato",
    "sg:tags":[
        "equipment",
        "sport",
        "leisure",
        "entertainment"
    ],
    "wof:name":"Juke Box Party Hire",
    "wof:placetype":"venue"
},
  "geometry": {"coordinates":[176.068024,-38.731491],"type":"Point"}
}