{
  "type": "Feature",
  "properties": {
    "iso:country":"NZ",
    "sg:address":"Branston Bdg Hornby ",
    "sg:city":"Christchurch",
    "sg:orig_category":"Clothing And Fabric: Clothing: Women'S Fashions",
    "sg:phone":"+64 3-349 7454",
    "sg:province":"Canterbury",
    "wof:name":"Elizabeth Fashions",
    "wof:placetype":"venue"
},
  "geometry": {"coordinates":[172.53633117679999,-43.5344314575],"type":"Point"}
}