{
  "type": "Feature",
  "properties": {
    "addr:full":"8 Doon St Mosgiel  Dunedin Otago",
    "addr:housenumber":"8",
    "addr:street":"Doon St",
    "iso:country":"NZ",
    "sg:address":"8 Doon St Mosgiel ",
    "sg:city":"Dunedin",
    "sg:classifiers":[
        {
            "category":"Home & Garden",
            "subcategory":"Furniture",
            "type":"Retail Goods"
        }
    ],
    "sg:phone":"+64 3-489 5002",
    "sg:province":"Otago",
    "sg:tags":[
        "furniture/furnishings",
        "repair",
        "finishing"
    ],
    "wof:name":"Taieri Turning & Joinery",
    "wof:placetype":"venue"
},
  "geometry": {"coordinates":[170.35642999999999,-45.877575],"type":"Point"}
}