{
  "type": "Feature",
  "properties": {
    "addr:full":"123 Main South Rd Tinwald  Ashburton Canterbury",
    "addr:housenumber":"123",
    "addr:street":"Main South Rd",
    "iso:country":"NZ",
    "sg:address":"123 Main South Rd Tinwald ",
    "sg:city":"Ashburton",
    "sg:classifiers":[
        {
            "category":"Bars & Pubs",
            "subcategory":"Lounge",
            "type":"Food & Drink"
        }
    ],
    "sg:phone":"+64 3-308 5774",
    "sg:province":"Canterbury",
    "sg:tags":[
        "baker",
        "-"
    ],
    "wof:name":"Sim's Bakery",
    "wof:placetype":"venue"
},
  "geometry": {"coordinates":[171.709991,-43.925568],"type":"Point"}
}