{
  "type": "Feature",
  "properties": {
    "iso:country":"NZ",
    "sg:address":"10 High St ",
    "sg:city":"Marton",
    "sg:classifiers":[
        {
            "category":"Bars & Pubs",
            "subcategory":"Lounge",
            "type":"Food & Drink"
        }
    ],
    "sg:phone":"+64 6-327 8482",
    "sg:tags":[
        "baker",
        "-"
    ],
    "wof:name":"BJs Home Bakery",
    "wof:placetype":"venue"
},
  "geometry": {"coordinates":[-0.741851,53.329758],"type":"Point"}
}