{
  "type": "Feature",
  "properties": {
    "addr:full":"168-172 Wairau Rd Glenfield  Auckland Auckland",
    "addr:postcode":"168-172",
    "addr:street":"Wairau Rd",
    "iso:country":"NZ",
    "sg:address":"168-172 Wairau Rd Glenfield ",
    "sg:city":"Auckland",
    "sg:orig_category":"Food And Drink: Catering: Caterers",
    "sg:phone":"+64 9-441 6088",
    "sg:province":"Auckland",
    "wof:name":"The Gourmet Associates",
    "wof:placetype":"venue"
},
  "geometry": {"coordinates":[174.736481,-36.770035],"type":"Point"}
}