{
  "type": "Feature",
  "properties": {
    "addr:full":"Glenfield  Auckland Auckland",
    "iso:country":"NZ",
    "sg:address":"Glenfield ",
    "sg:city":"Auckland",
    "sg:orig_category":"Home And Garden: Gardening: Services: Landscaping",
    "sg:phone":"+64 9-444 9879",
    "sg:province":"Auckland",
    "wof:name":"Millennium Landscape",
    "wof:placetype":"venue"
},
  "geometry": {"coordinates":[174.72280900000001,-36.77676],"type":"Point"}
}