{
  "type": "Feature",
  "properties": {
    "iso:country":"NZ",
    "sg:address":"149 Smart Rd New ",
    "sg:city":"Plymouth",
    "sg:orig_category":"Home And Garden",
    "sg:phone":"+64 6-758 8500",
    "sg:province":"Taranaki",
    "sg:website":"http://www.yellowpages.co.nz/pages/106214706/dp44244.html",
    "wof:name":"Pest Free Service (Taranaki) Ltd",
    "wof:placetype":"venue"
},
  "geometry": {"coordinates":[-116.819725,43.97221],"type":"Point"}
}