{
  "type": "Feature",
  "properties": {
    "iso:country":"NZ",
    "sg:address":"443 Gt North Rd ",
    "sg:city":"Auckland",
    "sg:classifiers":[
        {
            "category":"Manufacturing",
            "subcategory":"Motor Vehicles & Parts",
            "type":"Manufacturing & Wholesale Goods"
        }
    ],
    "sg:phone":"+64 9-837 3333",
    "sg:province":"Auckland",
    "sg:tags":[
        "automotive",
        "steering",
        "supplies",
        "suspension"
    ],
    "wof:name":"Midas Car Care",
    "wof:placetype":"venue"
},
  "geometry": {"coordinates":[-119.104576,36.597755],"type":"Point"}
}