{
  "type": "Feature",
  "properties": {
    "iso:country":"NZ",
    "sg:address":"PO Box 44 Doyleston ",
    "sg:city":"Leeston",
    "sg:classifiers":[
        {
            "category":"Utilities",
            "type":"Services"
        }
    ],
    "sg:phone":"+64 3-324 3945",
    "sg:tags":[
        "industrial",
        "energy",
        "utilities",
        "coal",
        "wood",
        "coke"
    ],
    "wof:name":"Bert Millin Contracting",
    "wof:placetype":"venue"
},
  "geometry": {"coordinates":[172.327393,-43.748341],"type":"Point"}
}