{
  "type": "Feature",
  "properties": {
    "iso:country":"NZ",
    "sg:address":"469 Fernside Rd ",
    "sg:city":"Rangiora",
    "sg:classifiers":[
        {
            "category":"Home & Garden",
            "subcategory":"Garden Supply",
            "type":"Retail Goods"
        }
    ],
    "sg:phone":"+64 3-313 6747",
    "sg:province":"Canterbury",
    "sg:tags":[
        "products",
        "nursery",
        "gardening"
    ],
    "wof:name":"Fernside Trees",
    "wof:placetype":"venue"
},
  "geometry": {"coordinates":[172.567444,-43.32193],"type":"Point"}
}