{
  "type": "Feature",
  "properties": {
    "iso:country":"NZ",
    "sg:address":"259 Matapihi ",
    "sg:city":"Rd",
    "sg:orig_category":"Industrial: Engineering: Engineers - Steam",
    "sg:phone":"+64 21 877 902",
    "wof:name":"Bendall Bros",
    "wof:placetype":"venue"
},
  "geometry": {"coordinates":[-101.235497,25.78413],"type":"Point"}
}