{
  "type": "Feature",
  "properties": {
    "addr:full":"114 Sawyers Arms Rd Papanui  Christchurch Canterbury",
    "addr:housenumber":"114",
    "addr:street":"Sawyers Arms Rd",
    "iso:country":"NZ",
    "sg:address":"114 Sawyers Arms Rd Papanui ",
    "sg:city":"Christchurch",
    "sg:orig_category":"Non-Classified Establishments",
    "sg:phone":"+64 3-352 0050",
    "sg:province":"Canterbury",
    "wof:name":"Sawyers Arms Timber Kilns",
    "wof:placetype":"venue"
},
  "geometry": {"coordinates":[172.59986900000001,-43.496452],"type":"Point"}
}