{
  "type": "Feature",
  "properties": {
    "addr:full":"80 Market St  Blenheim Marlborough",
    "addr:housenumber":"80",
    "addr:street":"Market St",
    "iso:country":"NZ",
    "sg:address":"80 Market St ",
    "sg:city":"Blenheim",
    "sg:orig_category":"Shopping: Retail Stores: Cds, Cassettes And Records",
    "sg:phone":"+64 3-578 6561",
    "sg:province":"Marlborough",
    "wof:name":"Tower Music",
    "wof:placetype":"venue"
},
  "geometry": {"coordinates":[-74.459564,42.468643],"type":"Point"}
}