{
  "type": "Feature",
  "properties": {
    "addr:full":"PO Box 74449 Market Rd Auckland  Auckland Auckland",
    "addr:housenumber":"po box 74449",
    "addr:street":"Market Rd",
    "iso:country":"NZ",
    "sg:address":"PO Box 74449 Market Rd Auckland ",
    "sg:city":"Auckland",
    "sg:classifiers":[
        {
            "category":"Autos & Motor Vehicles",
            "subcategory":"Automobile Sales",
            "type":"Retail Goods"
        }
    ],
    "sg:phone":"+64 800 822 213",
    "sg:province":"Auckland",
    "sg:tags":[
        "car",
        "management",
        "leasing",
        "fleet",
        "automotive"
    ],
    "wof:name":"LeasePlan New Zealand",
    "wof:placetype":"venue"
},
  "geometry": {"coordinates":[174.78450000000001,-37.006058],"type":"Point"}
}