{
  "type": "Feature",
  "properties": {
    "addr:full":"Marsden Village 159 Karori Rd Karori  Wellington Wellington",
    "addr:housenumber":"159",
    "addr:street":"Karori Rd",
    "iso:country":"NZ",
    "sg:address":"Marsden Village 159 Karori Rd Karori ",
    "sg:city":"Wellington",
    "sg:classifiers":[
        {
            "category":"Shopping",
            "subcategory":"Clothing, Apparel, & Fashions",
            "type":"Retail Goods"
        }
    ],
    "sg:phone":"+64 4-476 3076",
    "sg:province":"Wellington",
    "sg:tags":[
        "knitted",
        "clothing",
        "fabric"
    ],
    "wof:name":"Serendipity Boutique",
    "wof:placetype":"venue"
},
  "geometry": {"coordinates":[174.74087499999999,-41.283745],"type":"Point"}
}