{
  "type": "Feature",
  "properties": {
    "iso:country":"NZ",
    "sg:address":"Marsden Village 159 Karori Rd Karori ",
    "sg:city":"Wellington",
    "sg:classifiers":[
        {
            "category":"Shopping",
            "subcategory":"Clothing, Apparel, & Fashions",
            "type":"Retail Goods"
        }
    ],
    "sg:phone":"+64 4-476 3076",
    "sg:province":"Wellington",
    "sg:tags":[
        "knitted",
        "clothing",
        "fabric"
    ],
    "wof:name":"Serendipity Boutique",
    "wof:placetype":"venue"
},
  "geometry": {"coordinates":[174.740875,-41.283745],"type":"Point"}
}