{
  "type": "Feature",
  "properties": {
    "iso:country":"NZ",
    "sg:address":"9 Marina View Mana ",
    "sg:city":"Wellington",
    "sg:classifiers":[
        {
            "category":"Sports & Exercise",
            "subcategory":"Tennis Court",
            "type":"Entertainment"
        }
    ],
    "sg:phone":"+64 4-233 8238",
    "sg:province":"Wellington",
    "sg:tags":[
        "bait",
        "hunting",
        "fishing",
        "retailers",
        "tackle",
        "shopping"
    ],
    "wof:name":"Adventure Education Mana",
    "wof:placetype":"venue"
},
  "geometry": {"coordinates":[174.870544,-41.095112],"type":"Point"}
}