{
  "type": "Feature",
  "properties": {
    "addr:full":"34 Conical Hill Rd Hanmer  Springs",
    "addr:housenumber":"34",
    "addr:street":"Conical Hill Rd",
    "iso:country":"NZ",
    "sg:address":"34 Conical Hill Rd Hanmer ",
    "sg:city":"Springs",
    "sg:classifiers":[
        {
            "category":"Health Services",
            "subcategory":"Health Practitioner",
            "type":"Services"
        }
    ],
    "sg:phone":"+64 3-315 7026",
    "sg:tags":[
        "consultant",
        "medical",
        "beauty"
    ],
    "wof:name":"Wisteria Cottage Health & Beauty",
    "wof:placetype":"venue"
},
  "geometry": {"coordinates":[172.829498,-42.52071],"type":"Point"}
}