{
  "type": "Feature",
  "properties": {
    "addr:full":"430 Portobello Rd  Dunedin Otago",
    "addr:housenumber":"430",
    "addr:street":"Portobello Rd",
    "iso:country":"NZ",
    "sg:address":"430 Portobello Rd ",
    "sg:city":"Dunedin",
    "sg:classifiers":[
        {
            "category":"Professional",
            "type":"Services"
        }
    ],
    "sg:phone":"+64 3-476 1006",
    "sg:province":"Otago",
    "sg:tags":[
        "function",
        "entertainment",
        "leisure",
        "planning",
        "party",
        "sport"
    ],
    "wof:name":"Glenfalloch Restaurants",
    "wof:placetype":"venue"
},
  "geometry": {"coordinates":[170.58532700000001,-45.874229],"type":"Point"}
}