{
  "type": "Feature",
  "properties": {
    "addr:full":"54 Manchester St  Feilding Manawatu-Wanganui",
    "addr:housenumber":"54",
    "addr:street":"Manchester St",
    "iso:country":"NZ",
    "sg:address":"54 Manchester St ",
    "sg:city":"Feilding",
    "sg:orig_category":"Shopping: Accessories: Lingerie - Retail",
    "sg:phone":"+64 6-323 2377",
    "sg:province":"Manawatu-Wanganui",
    "wof:name":"Rachels Lingerie",
    "wof:placetype":"venue"
},
  "geometry": {"coordinates":[175.56514000000001,-40.22723],"type":"Point"}
}