{
  "type": "Feature",
  "properties": {
    "iso:country":"NZ",
    "sg:address":"Mako St ",
    "sg:city":"Dargaville",
    "sg:classifiers":[
        {
            "category":"Home & Garden",
            "subcategory":"Furniture",
            "type":"Retail Goods"
        }
    ],
    "sg:phone":"+64 9-439 6765",
    "sg:province":"Northland",
    "sg:tags":[
        "furniture/furnishings",
        "furnishing"
    ],
    "wof:name":"Compac Furniture",
    "wof:placetype":"venue"
},
  "geometry": {"coordinates":[173.887512,-35.930668],"type":"Point"}
}