{
  "type": "Feature",
  "properties": {
    "addr:full":"13 Tuahu Pl  Waitara",
    "addr:housenumber":"13",
    "addr:street":"Tuahu Pl",
    "iso:country":"NZ",
    "sg:address":"13 Tuahu Pl ",
    "sg:city":"Waitara",
    "sg:classifiers":[
        {
            "category":"Home & Garden",
            "subcategory":"Garden Supply",
            "type":"Retail Goods"
        }
    ],
    "sg:phone":"+64 25838510",
    "sg:tags":[
        "fencing",
        "outdoor",
        "contractor"
    ],
    "wof:name":"Taskmasters",
    "wof:placetype":"venue"
},
  "geometry": {"coordinates":[174.25460799999999,-39.002041],"type":"Point"}
}