{
  "type": "Feature",
  "properties": {
    "addr:full":"3rd Floor Farmers Mutual Bldg The Square Palmerston Palmerston North Wellington",
    "addr:housenumber":"3rd floor",
    "addr:street":"Farmers;The Square",
    "iso:country":"NZ",
    "sg:address":"3rd Floor Farmers Mutual Bldg The Square Palmerston",
    "sg:city":"Palmerston North",
    "sg:classifiers":[
        {
            "category":"Banks & Credit Unions",
            "subcategory":"Investment Brokerage",
            "type":"Services"
        }
    ],
    "sg:phone":"+64 6-350 6000",
    "sg:province":"Wellington",
    "sg:tags":[
        "personal",
        "-",
        "finance"
    ],
    "wof:name":"Speirs Group Ltd",
    "wof:placetype":"venue"
},
  "geometry": {"coordinates":[170.71632399999999,-45.48185],"type":"Point"}
}