{
  "type": "Feature",
  "properties": {
    "addr:full":"264 Great North Rd Grey Lynn  Auckland Auckland",
    "addr:housenumber":"264",
    "addr:street":"Great North Rd",
    "iso:country":"NZ",
    "sg:address":"264 Great North Rd Grey Lynn ",
    "sg:city":"Auckland",
    "sg:orig_category":"Industrial: Services: Platemakers Film/Print",
    "sg:phone":"+64 9-378 6947",
    "sg:province":"Auckland",
    "wof:name":"Hanwall Graphics",
    "wof:placetype":"venue"
},
  "geometry": {"coordinates":[174.689819,-36.902889],"type":"Point"}
}