{
  "type": "Feature",
  "properties": {
    "addr:full":"Main Rd  Rangiwahia",
    "addr:street":"Main Rd",
    "iso:country":"NZ",
    "sg:address":"Main Rd ",
    "sg:city":"Rangiwahia",
    "sg:orig_category":"Automotive: General Services: Service Stations",
    "sg:phone":"+64 6-328 2897",
    "wof:name":"Rangiwahia Garage",
    "wof:placetype":"venue"
},
  "geometry": {"coordinates":[175.96151699999999,-39.890301],"type":"Point"}
}