{
  "type": "Feature",
  "properties": {
    "addr:full":"51 Peterborough St  Christchurch Canterbury",
    "addr:housenumber":"51",
    "addr:street":"Peterborough St",
    "iso:country":"NZ",
    "sg:address":"51 Peterborough St ",
    "sg:city":"Christchurch",
    "sg:classifiers":[
        {
            "category":"Arts & Performance",
            "subcategory":"Art Gallery",
            "type":"Entertainment"
        }
    ],
    "sg:phone":"+64 3-379 7559",
    "sg:province":"Canterbury",
    "sg:tags":[
        "arts",
        "sport",
        "leisure"
    ],
    "wof:name":"Georgian Antiques & Gallery",
    "wof:placetype":"venue"
},
  "geometry": {"coordinates":[-76.537834,37.605659],"type":"Point"}
}