{
  "type": "Feature",
  "properties": {
    "iso:country":"NZ",
    "sg:address":"257 Ti Rakau Dve Pakuranga ",
    "sg:city":"Auckland",
    "sg:classifiers":[
        {
            "category":"Shopping",
            "subcategory":"Crafts & Fabrics",
            "type":"Retail Goods"
        }
    ],
    "sg:phone":"+64 9-273 7224",
    "sg:province":"Auckland",
    "sg:tags":[
        "pottery",
        "home",
        "accessories",
        "garden",
        "supply"
    ],
    "wof:name":"Priceless Pots",
    "wof:placetype":"venue"
},
  "geometry": {"coordinates":[174.892807,-36.901218],"type":"Point"}
}