{
  "type": "Feature",
  "properties": {
    "addr:full":"191 Ranolf St  Rotorua Bay of Plenty",
    "addr:housenumber":"191",
    "addr:street":"Ranolf St",
    "iso:country":"NZ",
    "sg:address":"191 Ranolf St ",
    "sg:city":"Rotorua",
    "sg:orig_category":"Clothing And Fabric: Clothing: Children'S Wear",
    "sg:phone":"+64 7-347 2714",
    "sg:province":"Bay of Plenty",
    "wof:name":"Kids Kloset",
    "wof:placetype":"venue"
},
  "geometry": {"coordinates":[176.24681100000001,-38.15276],"type":"Point"}
}