{
  "type": "Feature",
  "properties": {
    "iso:country":"NZ",
    "sg:address":"187 Ponsonby Rd Ponsonby ",
    "sg:city":"Auckland",
    "sg:classifiers":[
        {
            "category":"Food & Beverages",
            "subcategory":"Groceries & Convenience Stores",
            "type":"Retail Goods"
        }
    ],
    "sg:phone":"+64 9-376 8339",
    "sg:province":"Auckland",
    "sg:tags":[
        "foodstuff",
        "drink",
        "-"
    ],
    "wof:name":"La Cigale",
    "wof:placetype":"venue"
},
  "geometry": {"coordinates":[174.742416,-36.85326],"type":"Point"}
}