{
  "type": "Feature",
  "properties": {
    "addr:full":"187 Ponsonby Rd Ponsonby  Auckland Auckland",
    "addr:housenumber":"187",
    "addr:street":"Ponsonby Rd",
    "iso:country":"NZ",
    "sg:address":"187 Ponsonby Rd Ponsonby ",
    "sg:city":"Auckland",
    "sg:classifiers":[
        {
            "category":"Food & Beverages",
            "subcategory":"Groceries & Convenience Stores",
            "type":"Retail Goods"
        }
    ],
    "sg:phone":"+64 9-376 8339",
    "sg:province":"Auckland",
    "sg:tags":[
        "foodstuff",
        "drink",
        "-"
    ],
    "wof:name":"La Cigale",
    "wof:placetype":"venue"
},
  "geometry": {"coordinates":[174.74241599999999,-36.85326],"type":"Point"}
}