{
  "type": "Feature",
  "properties": {
    "addr:full":"157 Hurndal St  Maungaturoto",
    "addr:housenumber":"157",
    "addr:street":"Hurndal St",
    "iso:country":"NZ",
    "sg:address":"157 Hurndal St ",
    "sg:city":"Maungaturoto",
    "sg:orig_category":"Health And Beauty: Beauty: Hairdressers",
    "sg:phone":"+64 9-431 8329",
    "wof:name":"Urban Fringe Hair Design",
    "wof:placetype":"venue"
},
  "geometry": {"coordinates":[174.358597,-36.109028],"type":"Point"}
}