{
  "type": "Feature",
  "properties": {
    "addr:full":"671 Whangaparaoa Rd Whangaparaoa Hibiscus  Hibiscus Coast Auckland",
    "addr:housenumber":"671",
    "addr:street":"Whangaparaoa Rd",
    "iso:country":"NZ",
    "sg:address":"671 Whangaparaoa Rd Whangaparaoa Hibiscus ",
    "sg:city":"Hibiscus Coast",
    "sg:classifiers":[
        {
            "category":"Farming",
            "subcategory":"Fish & Marine Products",
            "type":"Manufacturing & Wholesale Goods"
        }
    ],
    "sg:phone":"+64 9-424 5556",
    "sg:province":"Auckland",
    "sg:tags":[
        "boats",
        "yacht",
        "transport",
        "boat",
        "supply"
    ],
    "wof:name":"Gulfland Marine",
    "wof:placetype":"venue"
},
  "geometry": {"coordinates":[174.74916099999999,-36.634239],"type":"Point"}
}