{
  "type": "Feature",
  "properties": {
    "iso:country":"NZ",
    "sg:address":"73 Grace Rd ",
    "sg:city":"Tauranga",
    "sg:classifiers":[
        {
            "category":"Health Services",
            "subcategory":"Dentist",
            "type":"Services"
        }
    ],
    "sg:phone":"+64 7-578 9659",
    "sg:province":"Bay of Plenty",
    "sg:tags":[
        "dental",
        "beauty"
    ],
    "wof:name":"Peter Scott Dental Laboratory (NZCDP)",
    "wof:placetype":"venue"
},
  "geometry": {"coordinates":[176.162476,-37.707218],"type":"Point"}
}