{
  "type": "Feature",
  "properties": {
    "iso:country":"NZ",
    "sg:address":"67 High St Renwick ",
    "sg:city":"Blenheim",
    "sg:orig_category":"Clothing And Fabric: Clothing: Women'S Fashions",
    "sg:phone":"+64 3-572 9912",
    "sg:province":"Marlborough",
    "wof:name":"Pollys & Hawkesbury Road Clothing Ltd",
    "wof:placetype":"venue"
},
  "geometry": {"coordinates":[173.955032,-41.512039],"type":"Point"}
}