{
  "type": "Feature",
  "properties": {
    "addr:full":"67 High St Renwick  Blenheim Marlborough",
    "addr:housenumber":"67",
    "addr:street":"High St",
    "iso:country":"NZ",
    "sg:address":"67 High St Renwick ",
    "sg:city":"Blenheim",
    "sg:orig_category":"Clothing And Fabric: Clothing: Women'S Fashions",
    "sg:phone":"+64 3-572 9912",
    "sg:province":"Marlborough",
    "wof:name":"Pollys & Hawkesbury Road Clothing Ltd",
    "wof:placetype":"venue"
},
  "geometry": {"coordinates":[173.95503199999999,-41.512039],"type":"Point"}
}