{
  "type": "Feature",
  "properties": {
    "addr:full":"3/42 Hawdon St Sydenham  Christchurch Canterbury",
    "addr:housenumber":"3 / 42",
    "addr:street":"Hawdon St",
    "iso:country":"NZ",
    "sg:address":"3/42 Hawdon St Sydenham ",
    "sg:city":"Christchurch",
    "sg:orig_category":"Industrial: Engineering: Engineers - Printing",
    "sg:phone":"+64 3-366 3211",
    "sg:province":"Canterbury",
    "wof:name":"Aspinall Graphics Ltd",
    "wof:placetype":"venue"
},
  "geometry": {"coordinates":[172.63911400000001,-43.545177],"type":"Point"}
}