{
  "type": "Feature",
  "properties": {
    "iso:country":"NZ",
    "sg:address":"186 Ferry Rd Linwood ",
    "sg:city":"Christchurch",
    "sg:classifiers":[
        {
            "category":"Shopping",
            "subcategory":"Shoes",
            "type":"Retail Goods"
        }
    ],
    "sg:phone":"+64 3-366 0024",
    "sg:province":"Canterbury",
    "sg:tags":[
        "foot",
        "clothing",
        "fabric",
        "wear"
    ],
    "wof:name":"Ferry Road Shoe Service",
    "wof:placetype":"venue"
},
  "geometry": {"coordinates":[172.66214,-43.53146],"type":"Point"}
}