{
  "type": "Feature",
  "properties": {
    "iso:country":"NZ",
    "sg:address":"27 City View Tce Birkenhead ",
    "sg:city":"Auckland",
    "sg:classifiers":[
        {
            "category":"Education",
            "subcategory":"Dance Studio",
            "type":"Public Place"
        }
    ],
    "sg:phone":"+64 9-418 3369",
    "sg:province":"Auckland",
    "sg:tags":[
        "school",
        "dancing",
        "-",
        "leisure",
        "sports",
        "sport"
    ],
    "wof:name":"Abbraccia School Of Dance",
    "wof:placetype":"venue"
},
  "geometry": {"coordinates":[174.72953799999999,-36.803699],"type":"Point"}
}