{
  "type": "Feature",
  "properties": {
    "addr:full":"1292 Fergusson Dve Brown Owl Upper  Hutt Wellington",
    "addr:housenumber":"1292",
    "addr:street":"Fergusson Dve Brown Owl",
    "iso:country":"NZ",
    "sg:address":"1292 Fergusson Dve Brown Owl Upper ",
    "sg:city":"Hutt",
    "sg:classifiers":[
        {
            "category":"Autos & Motor Vehicles",
            "subcategory":"Automobile Sales",
            "type":"Retail Goods"
        }
    ],
    "sg:phone":"+64 4-526 8466",
    "sg:province":"Wellington",
    "sg:tags":[
        "home",
        "caravan",
        "leasing",
        "automotive"
    ],
    "wof:name":"Caravan Hire",
    "wof:placetype":"venue"
},
  "geometry": {"coordinates":[175.09832800000001,-41.105091],"type":"Point"}
}