{
  "type": "Feature",
  "properties": {
    "addr:full":"56 Tarndale Gro Albany  Auckland Auckland",
    "addr:housenumber":"56",
    "addr:street":"Tarndale Gro",
    "iso:country":"NZ",
    "sg:address":"56 Tarndale Gro Albany ",
    "sg:city":"Auckland",
    "sg:orig_category":"Industrial: Instruments: Scales/Weighing Machines",
    "sg:phone":"+64 9-415 5110",
    "sg:province":"Auckland",
    "wof:name":"EMC Industrial Group Ltd",
    "wof:placetype":"venue"
},
  "geometry": {"coordinates":[174.703766,-36.745506],"type":"Point"}
}