{
  "type": "Feature",
  "properties": {
    "iso:country":"NZ",
    "sg:address":"320 Karapiro Rd ",
    "sg:city":"Cambridge",
    "sg:orig_category":"Home And Garden: Gardening: Products: Fertilisers",
    "sg:phone":"+64 7-834 3121",
    "sg:province":"Waikato",
    "wof:name":"Agronomic Consultancy Ltd",
    "wof:placetype":"venue"
},
  "geometry": {"coordinates":[175.471313,-37.893063],"type":"Point"}
}