{
  "type": "Feature",
  "properties": {
    "addr:full":"120 High St  Hawera Taranaki",
    "addr:housenumber":"120",
    "addr:street":"High St",
    "iso:country":"NZ",
    "sg:address":"120 High St ",
    "sg:city":"Hawera",
    "sg:orig_category":"Clothing And Fabric: Clothing: Menswear",
    "sg:phone":"+64 6-278 0017",
    "sg:province":"Taranaki",
    "wof:name":"Hallensteins",
    "wof:placetype":"venue"
},
  "geometry": {"coordinates":[174.28277600000001,-39.588985],"type":"Point"}
}