{
  "type": "Feature",
  "properties": {
    "addr:full":"235 Broadway  Marton Manawatu-Wanganui",
    "addr:housenumber":"235",
    "addr:street":"Broadway",
    "iso:country":"NZ",
    "sg:address":"235 Broadway ",
    "sg:city":"Marton",
    "sg:classifiers":[
        {
            "category":"Home & Garden",
            "subcategory":"Building Materials",
            "type":"Retail Goods"
        }
    ],
    "sg:phone":"+64 6-327 8394",
    "sg:province":"Manawatu-Wanganui",
    "sg:tags":[
        "electrician",
        "related"
    ],
    "wof:name":"Downs Alf & Sons Ltd",
    "wof:placetype":"venue"
},
  "geometry": {"coordinates":[-3.01544,53.799294],"type":"Point"}
}