{
  "type": "Feature",
  "properties": {
    "addr:full":"5 Cox St  Geraldine",
    "addr:housenumber":"5",
    "addr:street":"Cox St",
    "iso:country":"NZ",
    "sg:address":"5 Cox St ",
    "sg:city":"Geraldine",
    "sg:classifiers":[
        {
            "category":"Sports & Exercise",
            "subcategory":"Skate Park",
            "type":"Entertainment"
        }
    ],
    "sg:phone":"+64 3-693 7028",
    "sg:tags":[
        "arts",
        "museum",
        "leisure",
        "gallery"
    ],
    "wof:name":"Geraldine Museum",
    "wof:placetype":"venue"
},
  "geometry": {"coordinates":[-86.008263,34.360641],"type":"Point"}
}