{
  "type": "Feature",
  "properties": {
    "iso:country":"NZ",
    "sg:address":"13 Patiki Rd Avondale ",
    "sg:city":"Auckland",
    "sg:classifiers":[
        {
            "category":"Retail",
            "subcategory":"Laundry & Dry Cleaning",
            "type":"Services"
        }
    ],
    "sg:phone":"+64 9-828 6054",
    "sg:province":"Auckland",
    "sg:tags":[
        "control",
        "fume",
        "industrial",
        "dust",
        "maintenance"
    ],
    "wof:name":"Calibre Plastics Ltd",
    "wof:placetype":"venue"
},
  "geometry": {"coordinates":[174.690933,-36.8932],"type":"Point"}
}