{
  "type": "Feature",
  "properties": {
    "addr:full":"Porchester Rd Takanini  Auckland Auckland",
    "addr:street":"Porchester Rd",
    "iso:country":"NZ",
    "sg:address":"Porchester Rd Takanini ",
    "sg:city":"Auckland",
    "sg:orig_category":"Sports And Leisure: General: Clubs",
    "sg:phone":"+64 9-298 7507",
    "sg:province":"Auckland",
    "wof:name":"Auckland Racing Club",
    "wof:placetype":"venue"
},
  "geometry": {"coordinates":[174.92982499999999,-37.037186],"type":"Point"}
}