{
  "type": "Feature",
  "properties": {
    "iso:country":"NZ",
    "sg:address":"Unit 5 327 Gt South Rd Takanini ",
    "sg:city":"Auckland",
    "sg:orig_category":"Automotive: Servicing And Repair: Car Trimming/Upholstery",
    "sg:phone":"+64 9-296 0738",
    "sg:province":"Auckland",
    "wof:name":"Stirling Auto Trimmers (1996) Ltd",
    "wof:placetype":"venue"
},
  "geometry": {"coordinates":[174.93042,-37.051975],"type":"Point"}
}