{
  "type": "Feature",
  "properties": {
    "iso:country":"NZ",
    "sg:address":"Barringtons Shopping Centre Barrington St Spreydon",
    "sg:city":"Christchurch",
    "sg:classifiers":[
        {
            "category":"Health Services",
            "subcategory":"Podiatrist",
            "type":"Services"
        }
    ],
    "sg:phone":"+64 3-332 1730",
    "sg:province":"Canterbury",
    "sg:tags":[
        "lens",
        "optical",
        "contact",
        "beauty"
    ],
    "wof:name":"Suckling Richard J",
    "wof:placetype":"venue"
},
  "geometry": {"coordinates":[172.61621099999999,-43.553249],"type":"Point"}
}