{
  "type": "Feature",
  "properties": {
    "iso:country":"NZ",
    "sg:address":"Joll Rd Havelock North ",
    "sg:city":"Hastings",
    "sg:classifiers":[
        {
            "category":"Shopping",
            "subcategory":"Gifts & Souvenirs",
            "type":"Retail Goods"
        }
    ],
    "sg:phone":"+64 6-877 4797",
    "sg:province":"Hawke's Bay",
    "sg:tags":[
        "shop",
        "gifts",
        "supplier"
    ],
    "wof:name":"Cadeaux",
    "wof:placetype":"venue"
},
  "geometry": {"coordinates":[176.880112,-39.672813],"type":"Point"}
}