{
  "type": "Feature",
  "properties": {
    "addr:full":"Quarry Rd Awanui R D 2  Kaitaia Northland",
    "addr:housenumber":"2",
    "addr:street":"Quarry Rd;R D;Northland",
    "iso:country":"NZ",
    "sg:address":"Quarry Rd Awanui R D 2 ",
    "sg:city":"Kaitaia",
    "sg:classifiers":[
        {
            "category":"Social Services",
            "subcategory":"Job Training",
            "type":"Services"
        }
    ],
    "sg:phone":"+64 9-406 7433",
    "sg:province":"Northland",
    "sg:tags":[
        "education"
    ],
    "wof:name":"Te Wananga O Te Rangi Aniwaniwa",
    "wof:placetype":"venue"
},
  "geometry": {"coordinates":[173.259445,-35.114212],"type":"Point"}
}