{
  "type": "Feature",
  "properties": {
    "iso:country":"NZ",
    "sg:address":"106 Beachcroft Ave Onehunga ",
    "sg:city":"Auckland",
    "sg:classifiers":[
        {
            "category":"Manufacturing",
            "subcategory":"Tools & Machinery",
            "type":"Manufacturing & Wholesale Goods"
        }
    ],
    "sg:phone":"+64 9-634 3767",
    "sg:province":"Auckland",
    "sg:tags":[
        "equipment",
        "industrial",
        "hydraulic"
    ],
    "wof:name":"Oilflo Systems Ltd",
    "wof:placetype":"venue"
},
  "geometry": {"coordinates":[174.778717,-36.925518],"type":"Point"}
}