{
  "type": "Feature",
  "properties": {
    "iso:country":"NZ",
    "sg:address":"80 Vogel St ",
    "sg:city":"Woodville",
    "sg:classifiers":[
        {
            "category":"Bars & Pubs",
            "subcategory":"Lounge",
            "type":"Food & Drink"
        }
    ],
    "sg:phone":"+64 6-376 4343",
    "sg:tags":[
        "baker",
        "-"
    ],
    "wof:name":"Woodville Bakery",
    "wof:placetype":"venue"
},
  "geometry": {"coordinates":[-86.26593800000001,34.634071],"type":"Point"}
}