{
  "type": "Feature",
  "properties": {
    "iso:country":"NZ",
    "sg:address":"124 Musselburgh Rse Musselburgh ",
    "sg:city":"Dunedin",
    "sg:orig_category":"Health And Beauty: Mental: Psychology",
    "sg:phone":"+64 3-455 5622",
    "sg:province":"Otago",
    "wof:name":"Chris Skellett",
    "wof:placetype":"venue"
},
  "geometry": {"coordinates":[170.51994300000001,-45.897793],"type":"Point"}
}