{
  "type": "Feature",
  "properties": {
    "iso:country":"NZ",
    "sg:address":"5 Central Ave ",
    "sg:city":"Whangarei",
    "sg:classifiers":[
        {
            "category":"Health Services",
            "subcategory":"Hospital",
            "type":"Services"
        }
    ],
    "sg:phone":"+64 9-438 2239",
    "sg:province":"Northland",
    "sg:tags":[
        "medical",
        "beauty"
    ],
    "wof:name":"Ki a Ora Ngatiwai",
    "wof:placetype":"venue"
},
  "geometry": {"coordinates":[174.315918,-35.727261],"type":"Point"}
}