{
  "type": "Feature",
  "properties": {
    "iso:country":"NZ",
    "sg:address":"65 Grove Rd ",
    "sg:city":"Blenheim",
    "sg:classifiers":[
        {
            "category":"Retail",
            "subcategory":"Storage",
            "type":"Services"
        }
    ],
    "sg:phone":"+64 3-578 4874",
    "sg:province":"Marlborough",
    "wof:name":"Glenroy Insulated Products Ltd",
    "wof:placetype":"venue"
},
  "geometry": {"coordinates":[-74.459564,42.468643],"type":"Point"}
}