{
  "type": "Feature",
  "properties": {
    "iso:country":"NZ",
    "sg:address":"11 Midland St South Dunedin ",
    "sg:city":"Dunedin",
    "sg:classifiers":[
        {
            "category":"Food & Beverages",
            "subcategory":"Candy",
            "type":"Retail Goods"
        }
    ],
    "sg:phone":"+64 3-455 6588",
    "sg:province":"Otago",
    "sg:tags":[
        "confectioner",
        "drink",
        "-"
    ],
    "wof:name":"Alexanders Marketing Company",
    "wof:placetype":"venue"
},
  "geometry": {"coordinates":[170.50848400000001,-45.892941],"type":"Point"}
}