{
  "type": "Feature",
  "properties": {
    "iso:country":"NZ",
    "sg:address":"115 Manchester St ",
    "sg:city":"Christchurch",
    "sg:classifiers":[
        {
            "category":"Retail",
            "subcategory":"Laundry & Dry Cleaning",
            "type":"Services"
        }
    ],
    "sg:phone":"+64 3-366 0640",
    "sg:province":"Canterbury",
    "sg:tags":[
        "repair",
        "clothing",
        "fabric"
    ],
    "wof:name":"Mark v. Roosmalen Tailoring",
    "wof:placetype":"venue"
},
  "geometry": {"coordinates":[172.639526,-43.535675],"type":"Point"}
}