{
  "type": "Feature",
  "properties": {
    "iso:country":"NZ",
    "sg:address":"416 Gladstone Rd ",
    "sg:city":"Gisborne",
    "sg:orig_category":"Shopping: Retail Stores: Stationery",
    "sg:phone":"+64 6-868 6586",
    "sg:province":"Gisborne",
    "wof:name":"Corvos Supplies",
    "wof:placetype":"venue"
},
  "geometry": {"coordinates":[178.016541,-38.659706],"type":"Point"}
}