{
  "type": "Feature",
  "properties": {
    "iso:country":"NZ",
    "sg:address":"386 Fergusson Dve Heretaunga Upper ",
    "sg:city":"Hutt",
    "sg:classifiers":[
        {
            "category":"Bars & Pubs",
            "subcategory":"Wine Bar",
            "type":"Food & Drink"
        }
    ],
    "sg:phone":"+64 4-939 1068",
    "sg:province":"Wellington",
    "sg:tags":[
        "wining",
        "dining",
        "cafe"
    ],
    "wof:name":"Fig Tree Cafe & Larder",
    "wof:placetype":"venue"
},
  "geometry": {"coordinates":[175.023514,-41.141331],"type":"Point"}
}