{
  "type": "Feature",
  "properties": {
    "addr:full":"115 Rora St Te  Kuiti",
    "addr:housenumber":"115",
    "addr:street":"Rora St",
    "iso:country":"NZ",
    "sg:address":"115 Rora St Te ",
    "sg:city":"Kuiti",
    "sg:orig_category":"Health And Beauty: Products: Pharmacies",
    "sg:phone":"+64 7-878 8011",
    "wof:name":"Te Kuiti O'Fee & Bain Health Pharmacy",
    "wof:placetype":"venue"
},
  "geometry": {"coordinates":[175.15917999999999,-38.329369],"type":"Point"}
}