{
  "type": "Feature",
  "properties": {
    "addr:full":"1 Ngunguru Rd RD3 Ngunguru  Whangarei Northland",
    "addr:housenumber":"1",
    "addr:street":"Ngunguru Rd Rd3",
    "iso:country":"NZ",
    "sg:address":"1 Ngunguru Rd RD3 Ngunguru ",
    "sg:city":"Whangarei",
    "sg:orig_category":"Home And Garden: Gardening: Services: Lawnmowing Services",
    "sg:phone":"+64 9-437 0091",
    "sg:province":"Northland",
    "wof:name":"Lloyd's Neat 'n' Tidy",
    "wof:placetype":"venue"
},
  "geometry": {"coordinates":[174.320526,-35.725399],"type":"Point"}
}