{
  "type": "Feature",
  "properties": {
    "addr:full":"10 Johns Rd Taradale  Napier Hawke's Bay",
    "addr:housenumber":"10",
    "addr:street":"Johns Rd",
    "iso:country":"NZ",
    "sg:address":"10 Johns Rd Taradale ",
    "sg:city":"Napier",
    "sg:classifiers":[
        {
            "category":"Building & Trades",
            "subcategory":"Construction",
            "type":"Services"
        }
    ],
    "sg:phone":"+64 6-844 6168",
    "sg:province":"Hawke's Bay",
    "sg:tags":[
        "home",
        "garden",
        "related",
        "plasterer"
    ],
    "wof:name":"Bruce Neverman",
    "wof:placetype":"venue"
},
  "geometry": {"coordinates":[176.84719799999999,-39.534081],"type":"Point"}
}