{
  "type": "Feature",
  "properties": {
    "addr:full":"70 Constable St Newtown  Wellington Wellington",
    "addr:housenumber":"70",
    "addr:street":"Constable St",
    "iso:country":"NZ",
    "sg:address":"70 Constable St Newtown ",
    "sg:city":"Wellington",
    "sg:classifiers":[
        {
            "category":"Home & Garden",
            "subcategory":"Home Furnishings",
            "type":"Retail Goods"
        }
    ],
    "sg:phone":"+64 4-939 9402",
    "sg:province":"Wellington",
    "sg:tags":[
        "furniture/furnishings",
        "upholstery",
        "supply"
    ],
    "wof:name":"Waters Upholstery Ltd",
    "wof:placetype":"venue"
},
  "geometry": {"coordinates":[174.78385900000001,-41.313198],"type":"Point"}
}