{
  "type": "Feature",
  "properties": {
    "iso:country":"NZ",
    "sg:address":"Whangarei ",
    "sg:city":"Maungakaramea",
    "sg:orig_category":"Home And Garden: Gardening: Services: Lawnmowing Services",
    "sg:phone":"+64 9-432 3739",
    "wof:name":"Bill Brownlee-Total Lawn Care",
    "wof:placetype":"venue"
},
  "geometry": {"coordinates":[174.19593800000001,-35.846291],"type":"Point"}
}