{
  "type": "Feature",
  "properties": {
    "addr:full":"197 a Gt South Rd Takanini  Auckland Auckland",
    "addr:housenumber":"197 a",
    "addr:street":"Gt South Rd",
    "iso:country":"NZ",
    "sg:address":"197 a Gt South Rd Takanini ",
    "sg:city":"Auckland",
    "sg:classifiers":[
        {
            "category":"Retail",
            "subcategory":"Auto Repair",
            "type":"Services"
        }
    ],
    "sg:phone":"+64 9-298 5822",
    "sg:province":"Auckland",
    "sg:tags":[
        "clutch",
        "brake",
        "servicing",
        "automotive"
    ],
    "wof:name":"Precision Brake & Clutch Services",
    "wof:placetype":"venue"
},
  "geometry": {"coordinates":[174.922729,-37.046001],"type":"Point"}
}