{
  "type": "Feature",
  "properties": {
    "addr:full":"Blacks Rd  Kerikeri Northland",
    "addr:street":"Blacks Rd",
    "iso:country":"NZ",
    "sg:address":"Blacks Rd ",
    "sg:city":"Kerikeri",
    "sg:classifiers":[
        {
            "category":"Travel",
            "subcategory":"Bed & Breakfast",
            "type":"Entertainment"
        }
    ],
    "sg:phone":"+64 9-407 7500",
    "sg:province":"Northland",
    "sg:tags":[
        "tourism",
        "accommodation"
    ],
    "wof:name":"Holmes Homestay",
    "wof:placetype":"venue"
},
  "geometry": {"coordinates":[173.97457900000001,-35.221596],"type":"Point"}
}