{
  "type": "Feature",
  "properties": {
    "iso:country":"NZ",
    "sg:address":"91 Waterloo Rd Hornby ",
    "sg:city":"Christchurch",
    "sg:orig_category":"Industrial: Products: Filters And Filtration",
    "sg:phone":"+64 3-349 3966",
    "sg:province":"Canterbury",
    "wof:name":"C & M Auto Parts",
    "wof:placetype":"venue"
},
  "geometry": {"coordinates":[172.536621,-43.538113],"type":"Point"}
}