{
  "type": "Feature",
  "properties": {
    "iso:country":"NZ",
    "sg:address":"State Hwy 1 Mosgiel ",
    "sg:city":"Dunedin",
    "sg:classifiers":[
        {
            "category":"Banks & Credit Unions",
            "subcategory":"Investment Brokerage",
            "type":"Services"
        }
    ],
    "sg:phone":"+64 3-489 6268",
    "sg:province":"Otago",
    "sg:tags":[
        "chemical",
        "industrial",
        "-",
        "compounds"
    ],
    "wof:name":"Agrispray and Equipment Ltd",
    "wof:placetype":"venue"
},
  "geometry": {"coordinates":[170.50384500000001,-45.8745],"type":"Point"}
}