{
  "type": "Feature",
  "properties": {
    "iso:country":"NZ",
    "sg:address":"A1A/710 Great South Rd Manukau ",
    "sg:city":"Auckland",
    "sg:orig_category":"Industrial: Parts: Pipes, Tubes And Cabling: Cables",
    "sg:phone":"+64 9-262 1722",
    "sg:province":"Auckland",
    "wof:name":"CableCom",
    "wof:placetype":"venue"
},
  "geometry": {"coordinates":[-119.104576,36.597755],"type":"Point"}
}