{
  "type": "Feature",
  "properties": {
    "iso:country":"NZ",
    "sg:address":"cnr Percival & Alfred Sts ",
    "sg:city":"Rangiora",
    "sg:classifiers":[
        {
            "category":"Wholesale",
            "subcategory":"Auto Parts",
            "type":"Manufacturing & Wholesale Goods"
        }
    ],
    "sg:phone":"+64 3-313 8186",
    "sg:province":"Canterbury",
    "sg:tags":[
        "automotive",
        "supply"
    ],
    "sg:website":"http://www.rangioratoyota.co.nz",
    "wof:name":"Rangiora Toyota",
    "wof:placetype":"venue"
},
  "geometry": {"coordinates":[172.59030200000001,-43.302959],"type":"Point"}
}