{
  "type": "Feature",
  "properties": {
    "iso:country":"NZ",
    "sg:address":"11 Wharerangi Rd ",
    "sg:city":"Napier",
    "sg:orig_category":"Home And Garden: Gardening: Services: Landscaping",
    "sg:phone":"+64 25478398",
    "sg:province":"Hawke's Bay",
    "wof:name":"Twin City Landscapers Ltd",
    "wof:placetype":"venue"
},
  "geometry": {"coordinates":[-80.588562,38.790821],"type":"Point"}
}