{
  "type": "Feature",
  "properties": {
    "addr:full":"210 Clyde St  Invercargill Southland",
    "addr:housenumber":"210",
    "addr:street":"Clyde St",
    "iso:country":"NZ",
    "sg:address":"210 Clyde St ",
    "sg:city":"Invercargill",
    "sg:orig_category":"Home And Garden: Gardening: Products",
    "sg:phone":"+64 3-214 4262",
    "sg:province":"Southland",
    "sg:website":"http://www.morrifield.com",
    "wof:name":"Morrifield Developments Ltd",
    "wof:placetype":"venue"
},
  "geometry": {"coordinates":[168.34764100000001,-46.423717],"type":"Point"}
}