{
  "type": "Feature",
  "properties": {
    "addr:full":"2 a McClymont Pl  Tauranga Bay of Plenty",
    "addr:housenumber":"2",
    "addr:street":"A Mcclymont Pl",
    "iso:country":"NZ",
    "sg:address":"2 a McClymont Pl ",
    "sg:city":"Tauranga",
    "sg:classifiers":[
        {
            "category":"Retail",
            "subcategory":"Driving School",
            "type":"Services"
        }
    ],
    "sg:phone":"+64 7-578 9445",
    "sg:province":"Bay of Plenty",
    "sg:tags":[
        "training",
        "education",
        "driver"
    ],
    "wof:name":"ABC School of Driving",
    "wof:placetype":"venue"
},
  "geometry": {"coordinates":[176.14794900000001,-37.71093],"type":"Point"}
}