{
  "type": "Feature",
  "properties": {
    "iso:country":"NZ",
    "sg:address":"2 a McClymont Pl ",
    "sg:city":"Tauranga",
    "sg:classifiers":[
        {
            "category":"Retail",
            "subcategory":"Driving School",
            "type":"Services"
        }
    ],
    "sg:phone":"+64 7-578 9445",
    "sg:province":"Bay of Plenty",
    "sg:tags":[
        "training",
        "education",
        "driver"
    ],
    "wof:name":"ABC School of Driving",
    "wof:placetype":"venue"
},
  "geometry": {"coordinates":[176.147949,-37.71093],"type":"Point"}
}