{
  "type": "Feature",
  "properties": {
    "addr:full":"88 Taradale Rd  Napier Hawke's Bay",
    "addr:housenumber":"88",
    "addr:street":"Taradale Rd",
    "iso:country":"NZ",
    "sg:address":"88 Taradale Rd ",
    "sg:city":"Napier",
    "sg:classifiers":[
        {
            "category":"Shopping",
            "subcategory":"Stationery & Office Supplies",
            "type":"Retail Goods"
        }
    ],
    "sg:phone":"+64 6-843 1300",
    "sg:province":"Hawke's Bay",
    "sg:tags":[
        "supplies",
        "educational",
        "material",
        "education",
        "training"
    ],
    "wof:name":"EdSports Ltd",
    "wof:placetype":"venue"
},
  "geometry": {"coordinates":[176.87443500000001,-39.514668],"type":"Point"}
}