{
  "type": "Feature",
  "properties": {
    "addr:full":"115 East Belt  Rangiora Canterbury",
    "addr:housenumber":"115",
    "addr:street":"East Belt",
    "iso:country":"NZ",
    "sg:address":"115 East Belt ",
    "sg:city":"Rangiora",
    "sg:orig_category":"Farming: Forestry",
    "sg:phone":"+64 3-313 3756",
    "sg:province":"Canterbury",
    "wof:name":"Piers Maclaren & Assc Ltd",
    "wof:placetype":"venue"
},
  "geometry": {"coordinates":[172.59925799999999,-43.298592],"type":"Point"}
}