{
  "type": "Feature",
  "properties": {
    "addr:full":"State Highway 1  Kawakawa",
    "addr:street":"State Highway 1 Kawakawa",
    "iso:country":"NZ",
    "sg:address":"State Highway 1 ",
    "sg:city":"Kawakawa",
    "sg:classifiers":[
        {
            "category":"Farming",
            "subcategory":"Farm & Veterinary Services",
            "type":"Manufacturing & Wholesale Goods"
        }
    ],
    "sg:phone":"+64 9-404 0043",
    "sg:tags":[
        "supplies",
        "supply"
    ],
    "wof:name":"Kawakawa Farm Centre",
    "wof:placetype":"venue"
},
  "geometry": {"coordinates":[174.06539900000001,-35.379948],"type":"Point"}
}