{
  "type": "Feature",
  "properties": {
    "addr:full":"5 Manchester St  Paraparaumu Wellington",
    "addr:housenumber":"5",
    "addr:street":"Manchester St",
    "iso:country":"NZ",
    "sg:address":"5 Manchester St ",
    "sg:city":"Paraparaumu",
    "sg:classifiers":[
        {
            "category":"Marine",
            "type":"Transportation"
        }
    ],
    "sg:phone":"+64 4-902 6778",
    "sg:province":"Wellington",
    "sg:tags":[
        "boats",
        "builder",
        "yacht",
        "transport",
        "boat"
    ],
    "wof:name":"Aluminium Pontoon Boats",
    "wof:placetype":"venue"
},
  "geometry": {"coordinates":[175.001419,-40.904652],"type":"Point"}
}