{
  "type": "Feature",
  "properties": {
    "addr:full":"30 Bethlehem Rd  Tauranga Bay of Plenty",
    "addr:housenumber":"30",
    "addr:street":"Bethlehem Rd",
    "iso:country":"NZ",
    "sg:address":"30 Bethlehem Rd ",
    "sg:city":"Tauranga",
    "sg:classifiers":[
        {
            "category":"Restaurant",
            "type":"Food & Drink"
        }
    ],
    "sg:phone":"+64 7-576 6889",
    "sg:province":"Bay of Plenty",
    "sg:tags":[
        "wining",
        "dining"
    ],
    "wof:name":"Somerset Cottage Restaurant",
    "wof:placetype":"venue"
},
  "geometry": {"coordinates":[176.11038199999999,-37.69276],"type":"Point"}
}