{
  "type": "Feature",
  "properties": {
    "iso:country":"NZ",
    "sg:address":"37 Cotswold Ave ",
    "sg:city":"Bishopdale",
    "sg:classifiers":[
        {
            "category":"Utilities",
            "subcategory":"Refuse",
            "type":"Services"
        }
    ],
    "sg:phone":"+64 252874491",
    "sg:province":"Canterbury",
    "sg:tags":[
        "bin",
        "hire",
        "garden",
        "cleaning",
        "rubbish",
        "home"
    ],
    "wof:name":"Citywide Bins",
    "wof:placetype":"venue"
},
  "geometry": {"coordinates":[172.586243,-43.484016],"type":"Point"}
}