{
  "type": "Feature",
  "properties": {
    "addr:full":"9 Caspian St Southshore  Christchurch Canterbury",
    "addr:housenumber":"9",
    "addr:street":"Caspian St",
    "iso:country":"NZ",
    "sg:address":"9 Caspian St Southshore ",
    "sg:city":"Christchurch",
    "sg:classifiers":[
        {
            "category":"Manufacturing",
            "subcategory":"Food",
            "type":"Manufacturing & Wholesale Goods"
        }
    ],
    "sg:phone":"+64 3-388 2398",
    "sg:province":"Canterbury",
    "sg:tags":[
        "drink",
        "-",
        "manufacturer"
    ],
    "wof:name":"Southshore Foods",
    "wof:placetype":"venue"
},
  "geometry": {"coordinates":[172.74115,-43.538403],"type":"Point"}
}