{
  "type": "Feature",
  "properties": {
    "addr:full":"21 Clarence St Devonport  Auckland Auckland",
    "addr:housenumber":"21",
    "addr:street":"Clarence St",
    "iso:country":"NZ",
    "sg:address":"21 Clarence St Devonport ",
    "sg:city":"Auckland",
    "sg:classifiers":[
        {
            "category":"Retail",
            "subcategory":"Laundry & Dry Cleaning",
            "type":"Services"
        }
    ],
    "sg:phone":"+64 9-445 3096",
    "sg:province":"Auckland",
    "sg:tags":[
        "repair",
        "clothing",
        "fabric",
        "cleaner"
    ],
    "wof:name":"Devonport Drycleaners",
    "wof:placetype":"venue"
},
  "geometry": {"coordinates":[174.79594399999999,-36.830173],"type":"Point"}
}