{
  "type": "Feature",
  "properties": {
    "iso:country":"NZ",
    "sg:address":"35 Karaka St Newton ",
    "sg:city":"Auckland",
    "sg:classifiers":[
        {
            "category":"Manufacturing",
            "subcategory":"Tools & Machinery",
            "type":"Manufacturing & Wholesale Goods"
        }
    ],
    "sg:phone":"+64 800 538 722",
    "sg:province":"Auckland",
    "sg:tags":[
        "equipment",
        "industrial",
        "label"
    ],
    "wof:name":"Label Shop",
    "wof:placetype":"venue"
},
  "geometry": {"coordinates":[174.75878900000001,-36.862183],"type":"Point"}
}