{
  "type": "Feature",
  "properties": {
    "iso:country":"NZ",
    "sg:address":"28 Clarence St Devonport ",
    "sg:city":"Auckland",
    "sg:classifiers":[
        {
            "category":"Arts & Performance",
            "subcategory":"Art Gallery",
            "type":"Entertainment"
        }
    ],
    "sg:phone":"+64 9-445 9398",
    "sg:province":"Auckland",
    "sg:tags":[
        "arts",
        "sport",
        "leisure"
    ],
    "wof:name":"Depot Arts Space",
    "wof:placetype":"venue"
},
  "geometry": {"coordinates":[174.79582199999999,-36.829987],"type":"Point"}
}