{
  "type": "Feature",
  "properties": {
    "addr:full":"34 Klondyke Dve Islington  Christchurch Canterbury",
    "addr:housenumber":"34",
    "addr:street":"Dve",
    "iso:country":"NZ",
    "sg:address":"34 Klondyke Dve Islington ",
    "sg:city":"Christchurch",
    "sg:classifiers":[
        {
            "category":"Manufacturing",
            "subcategory":"Rubber & Plastics",
            "type":"Manufacturing & Wholesale Goods"
        }
    ],
    "sg:phone":"+64 3-349 9436",
    "sg:province":"Canterbury",
    "sg:tags":[
        "industrial",
        "goods"
    ],
    "wof:name":"Rubber Developments Limited",
    "wof:placetype":"venue"
},
  "geometry": {"coordinates":[172.51786799999999,-43.559753],"type":"Point"}
}