{
  "type": "Feature",
  "properties": {
    "addr:full":"124 Halsey St Freemans Bay  Auckland Auckland",
    "addr:housenumber":"124",
    "addr:street":"Halsey St",
    "iso:country":"NZ",
    "sg:address":"124 Halsey St Freemans Bay ",
    "sg:city":"Auckland",
    "sg:classifiers":[
        {
            "category":"Manufacturing",
            "subcategory":"Glass & Minerals",
            "type":"Manufacturing & Wholesale Goods"
        }
    ],
    "sg:phone":"+64 9-307 9033",
    "sg:province":"Auckland",
    "sg:tags":[
        "chemical",
        "paint",
        "industrial",
        "manufacturer",
        "compounds"
    ],
    "wof:name":"Altex Coatings Ltd",
    "wof:placetype":"venue"
},
  "geometry": {"coordinates":[174.75254799999999,-36.848648],"type":"Point"}
}