{
  "type": "Feature",
  "properties": {
    "iso:country":"NZ",
    "sg:address":"120 Kent Street ",
    "sg:city":"Hamilton",
    "sg:classifiers":[
        {
            "category":"Retail",
            "subcategory":"Auto Repair",
            "type":"Services"
        }
    ],
    "sg:phone":"+64 7-847 9833",
    "sg:province":"Wellington",
    "sg:tags":[
        "transmission",
        "automotive",
        "servicing"
    ],
    "wof:name":"Tranz Torque",
    "wof:placetype":"venue"
},
  "geometry": {"coordinates":[-74.74530799999999,40.214108],"type":"Point"}
}