{
  "type": "Feature",
  "properties": {
    "iso:country":"NZ",
    "sg:address":"3 Rennie Dve Airport Oaks ",
    "sg:city":"Auckland",
    "sg:orig_category":"Transport: Boats And Marine: Shipping",
    "sg:phone":"+64 9-275 7049",
    "sg:province":"Auckland",
    "sg:website":"http://www.yellowpages.co.nz/for/excessbaggageconzltd/dp15800.html",
    "wof:name":"Excess Baggage Company Ltd",
    "wof:placetype":"venue"
},
  "geometry": {"coordinates":[-119.10457599999999,36.597755],"type":"Point"}
}