{
  "type": "Feature",
  "properties": {
    "addr:full":"104 Forest Dve  Methven",
    "addr:housenumber":"104",
    "addr:street":"Forest Dve Methven",
    "iso:country":"NZ",
    "sg:address":"104 Forest Dve ",
    "sg:city":"Methven",
    "sg:classifiers":[
        {
            "category":"Banks & Credit Unions",
            "subcategory":"Financial Services",
            "type":"Services"
        }
    ],
    "sg:phone":"+64 3-302 8535",
    "sg:tags":[
        "livestock",
        "related",
        "agent",
        "services",
        "farming",
        "stock"
    ],
    "wof:name":"Provincial Livestock Co Ltd",
    "wof:placetype":"venue"
},
  "geometry": {"coordinates":[171.644272,-43.631443],"type":"Point"}
}