{
  "type": "Feature",
  "properties": {
    "addr:full":"602 B Tremaine Ave Palmerston  Palmerston North Manawatu-Wanganui",
    "addr:housenumber":"602 b",
    "addr:street":"Tremaine Ave",
    "iso:country":"NZ",
    "sg:address":"602 B Tremaine Ave Palmerston ",
    "sg:city":"Palmerston North",
    "sg:classifiers":[
        {
            "category":"Shopping",
            "subcategory":"Discount & Variety Stores",
            "type":"Retail Goods"
        }
    ],
    "sg:phone":"+64 6-357 8400",
    "sg:province":"Manawatu-Wanganui",
    "sg:tags":[
        "storage",
        "cool"
    ],
    "wof:name":"Flexi-Tech Ind Ltd",
    "wof:placetype":"venue"
},
  "geometry": {"coordinates":[175.603973,-40.342438],"type":"Point"}
}