{
  "type": "Feature",
  "properties": {
    "iso:country":"NZ",
    "sg:address":"129 Pasture St ",
    "sg:city":"Lumsden",
    "sg:classifiers":[
        {
            "category":"Farming",
            "subcategory":"Farm",
            "type":"Manufacturing & Wholesale Goods"
        }
    ],
    "sg:phone":"+64 3-248 7613",
    "sg:tags":[
        "-",
        "ostrich"
    ],
    "wof:name":"Lumsden Hatcheries Limited",
    "wof:placetype":"venue"
},
  "geometry": {"coordinates":[168.44928,-45.735283],"type":"Point"}
}