{
  "type": "Feature",
  "properties": {
    "iso:country":"NZ",
    "sg:address":"Fox Hall 41 Silverton St Andersons Bay ",
    "sg:city":"Dunedin",
    "sg:classifiers":[
        {
            "category":"Personal",
            "type":"Services"
        }
    ],
    "sg:phone":"+64 3-454 3902",
    "sg:province":"Otago",
    "sg:tags":[
        "celebrant",
        "arrangements",
        "marriage",
        "wedding"
    ],
    "wof:name":"Larkins Warwick N",
    "wof:placetype":"venue"
},
  "geometry": {"coordinates":[170.534546,-45.894531],"type":"Point"}
}