{
  "type": "Feature",
  "properties": {
    "iso:country":"NZ",
    "sg:address":"19 Wai-iti Valley Rd Belgrove ",
    "sg:city":"Wakefield",
    "sg:orig_category":"Home And Garden: Gardening: Products: Fertilisers",
    "sg:phone":"+64 3-541 9026",
    "wof:name":"Paul Breading",
    "wof:placetype":"venue"
},
  "geometry": {"coordinates":[173.046234,-41.406651],"type":"Point"}
}