{
  "type": "Feature",
  "properties": {
    "iso:country":"NZ",
    "sg:address":"Suite 19 Marinoto Clinic 72 Newington Ave ",
    "sg:city":"Dunedin",
    "sg:classifiers":[
        {
            "category":"Sports & Exercise",
            "subcategory":"Tennis Court",
            "type":"Entertainment"
        }
    ],
    "sg:phone":"+64 3-467 2046",
    "sg:province":"Otago",
    "sg:tags":[
        "medicine",
        "specialists",
        "health",
        "beauty"
    ],
    "wof:name":"Bentley Dr S C Musculoskeletal Physician",
    "wof:placetype":"venue"
},
  "geometry": {"coordinates":[-82.77282700000001,28.060875],"type":"Point"}
}