{
  "type": "Feature",
  "properties": {
    "addr:full":"Ground Floor Menzies Building The Crescent  Invercargill Waikato",
    "addr:housenumber":"ground floor menzies building",
    "addr:street":"The Crescent",
    "iso:country":"NZ",
    "sg:address":"Ground Floor Menzies Building The Crescent ",
    "sg:city":"Invercargill",
    "sg:classifiers":[
        {
            "category":"Sports & Exercise",
            "subcategory":"Sports Center",
            "type":"Entertainment"
        }
    ],
    "sg:phone":"+64 3-218 1094",
    "sg:province":"Waikato",
    "sg:tags":[
        "health",
        "beauty",
        "fitness"
    ],
    "wof:name":"Power Point Fitness Club",
    "wof:placetype":"venue"
},
  "geometry": {"coordinates":[168.35217299999999,-46.41185],"type":"Point"}
}