{
  "type": "Feature",
  "properties": {
    "addr:full":"Te Tahi St  Whakatane Bay of Plenty",
    "addr:street":"Te Tahi St",
    "iso:country":"NZ",
    "sg:address":"Te Tahi St ",
    "sg:city":"Whakatane",
    "sg:classifiers":[
        {
            "category":"Wholesale",
            "subcategory":"Machinery & Supplies",
            "type":"Manufacturing & Wholesale Goods"
        }
    ],
    "sg:phone":"+64 7-307 0858",
    "sg:province":"Bay of Plenty",
    "sg:tags":[
        "equipment",
        "crane",
        "industrial",
        "hoist",
        "lifting"
    ],
    "wof:name":"Mahy Crane Hire",
    "wof:placetype":"venue"
},
  "geometry": {"coordinates":[176.98426799999999,-37.977188],"type":"Point"}
}