{
  "type": "Feature",
  "properties": {
    "addr:full":"400 Main St West Palmerston  Palmerston North Manawatu-Wanganui",
    "addr:housenumber":"400",
    "addr:street":"Main St West",
    "iso:country":"NZ",
    "sg:address":"400 Main St West Palmerston ",
    "sg:city":"Palmerston North",
    "sg:orig_category":"Food And Drink: Catering: Caterers",
    "sg:phone":"+64 6-358 0000",
    "sg:province":"Manawatu-Wanganui",
    "wof:name":"Eurest New Zealand Ltd",
    "wof:placetype":"venue"
},
  "geometry": {"coordinates":[175.609802,-40.356876],"type":"Point"}
}