{
  "type": "Feature",
  "properties": {
    "addr:full":"Tahuna  Morrinsville Waikato",
    "addr:street":"Tahuna",
    "iso:country":"NZ",
    "sg:address":"Tahuna ",
    "sg:city":"Morrinsville",
    "sg:orig_category":"Farming: Services",
    "sg:phone":"+64 7-887 5549",
    "sg:province":"Waikato",
    "sg:website":"http://morrinsville.com/Paintball/index.shtml",
    "wof:name":"PAINTBALL - The Ultimate Challenge",
    "wof:placetype":"venue"
},
  "geometry": {"coordinates":[175.528717,-37.65411],"type":"Point"}
}