{
  "type": "Feature",
  "properties": {
    "addr:full":"35 a Kaka St  Whangarei Northland",
    "addr:housenumber":"35",
    "addr:street":"A Kaka St",
    "iso:country":"NZ",
    "sg:address":"35 a Kaka St ",
    "sg:city":"Whangarei",
    "sg:classifiers":[
        {
            "category":"Home & Garden",
            "subcategory":"Furniture",
            "type":"Retail Goods"
        }
    ],
    "sg:phone":"+64 9-430 3236",
    "sg:province":"Northland",
    "sg:tags":[
        "furniture/furnishings",
        "repair",
        "finishing"
    ],
    "wof:name":"Whangarei Furniture Spraypainters",
    "wof:placetype":"venue"
},
  "geometry": {"coordinates":[174.32107500000001,-35.733215],"type":"Point"}
}