{
  "type": "Feature",
  "properties": {
    "addr:full":"Hillcrest Rd  Kaitaia Waikato",
    "addr:street":"Hillcrest Rd",
    "iso:country":"NZ",
    "sg:address":"Hillcrest Rd ",
    "sg:city":"Kaitaia",
    "sg:classifiers":[
        {
            "category":"Sports & Exercise",
            "subcategory":"Sports Center",
            "type":"Entertainment"
        }
    ],
    "sg:phone":"+64 9-408 0097",
    "sg:province":"Waikato",
    "sg:tags":[
        "sporting",
        "sports",
        "-",
        "leisure",
        "facility"
    ],
    "wof:name":"Hillcrest Shooting Centre",
    "wof:placetype":"venue"
},
  "geometry": {"coordinates":[173.274551,-35.094238],"type":"Point"}
}