{
  "type": "Feature",
  "properties": {
    "addr:full":"9 Botha Rd Penrose  Auckland Auckland",
    "addr:housenumber":"9",
    "addr:street":"Botha Rd",
    "iso:country":"NZ",
    "sg:address":"9 Botha Rd Penrose ",
    "sg:city":"Auckland",
    "sg:classifiers":[
        {
            "category":"Retail",
            "subcategory":"Animal Services",
            "type":"Services"
        }
    ],
    "sg:phone":"+64 9-579 7496",
    "sg:province":"Auckland",
    "sg:tags":[
        "pet",
        "home",
        "garden",
        "pets"
    ],
    "wof:name":"Arthurs Dog Kennels & Runs",
    "wof:placetype":"venue"
},
  "geometry": {"coordinates":[174.808334,-36.910275],"type":"Point"}
}