{
  "type": "Feature",
  "properties": {
    "addr:full":"Lumley House 7 City Rd Auckland Central  Auckland Auckland",
    "addr:housenumber":"7",
    "addr:street":"City Rd",
    "iso:country":"NZ",
    "sg:address":"Lumley House 7 City Rd Auckland Central ",
    "sg:city":"Auckland",
    "sg:classifiers":[
        {
            "category":"Professional",
            "subcategory":"Detective & Security Services",
            "type":"Services"
        }
    ],
    "sg:phone":"+64 9-302 5332",
    "sg:province":"Auckland",
    "sg:tags":[
        "locker",
        "storage",
        "cabinet"
    ],
    "wof:name":"Kiwi Locker Co Ltd",
    "wof:placetype":"venue"
},
  "geometry": {"coordinates":[174.76454200000001,-36.848358],"type":"Point"}
}