{
  "type": "Feature",
  "properties": {
    "addr:full":"Napier Rd  Whakarongo",
    "addr:street":"Napier Rd",
    "iso:country":"NZ",
    "sg:address":"Napier Rd ",
    "sg:city":"Whakarongo",
    "sg:classifiers":[
        {
            "category":"Home & Garden",
            "subcategory":"Garden Supply",
            "type":"Retail Goods"
        }
    ],
    "sg:phone":"+64 800 529 628",
    "sg:tags":[
        "products",
        "lawn",
        "gardening",
        "turf"
    ],
    "wof:name":"Turflands",
    "wof:placetype":"venue"
},
  "geometry": {"coordinates":[175.646332,-40.341568],"type":"Point"}
}