{
  "type": "Feature",
  "properties": {
    "addr:full":"Taranaki Street Wharf  Wellington Marlborough",
    "addr:street":"Taranaki Street",
    "iso:country":"NZ",
    "sg:address":"Taranaki Street Wharf ",
    "sg:city":"Wellington",
    "sg:classifiers":[
        {
            "category":"Professional",
            "type":"Services"
        }
    ],
    "sg:phone":"+64 4-385 1003",
    "sg:province":"Marlborough",
    "sg:tags":[
        "function",
        "entertainment",
        "leisure",
        "planning",
        "party",
        "sport"
    ],
    "wof:name":"Wellington Rowers",
    "wof:placetype":"venue"
},
  "geometry": {"coordinates":[-85.910454,33.827946],"type":"Point"}
}