{
  "type": "Feature",
  "properties": {
    "iso:country":"NZ",
    "sg:address":"PO Box 26671 Epsom ",
    "sg:city":"Auckland",
    "sg:orig_category":"Home And Garden: Accessories: Candles",
    "sg:phone":"+64 9-845 3374",
    "sg:province":"Auckland",
    "wof:name":"Candleman Services",
    "wof:placetype":"venue"
},
  "geometry": {"coordinates":[174.77356,-36.876179],"type":"Point"}
}