{
  "type": "Feature",
  "properties": {
    "iso:country":"NZ",
    "sg:address":"44 Theodosia St ",
    "sg:city":"Timaru",
    "sg:orig_category":"Industrial: Engineering: Engineers: Engineers - Consulting",
    "sg:phone":"+64 3-688 9137",
    "sg:province":"Canterbury",
    "wof:name":"Littler G R",
    "wof:placetype":"venue"
},
  "geometry": {"coordinates":[171.245972,-44.390999],"type":"Point"}
}