{
  "type": "Feature",
  "properties": {
    "addr:full":"52 Symonds St Auckland Central  Auckland Auckland",
    "addr:housenumber":"52",
    "addr:street":"Symonds St",
    "iso:country":"NZ",
    "sg:address":"52 Symonds St Auckland Central ",
    "sg:city":"Auckland",
    "sg:orig_category":"Transport: Boats And Marine: Shipping",
    "sg:phone":"+64 9-377 3460",
    "sg:province":"Auckland",
    "sg:website":"http://www.columbusline.com",
    "wof:name":"Columbus Line New Zealand Ltd",
    "wof:placetype":"venue"
},
  "geometry": {"coordinates":[174.767166,-36.855331],"type":"Point"}
}