{
  "type": "Feature",
  "properties": {
    "addr:full":"PO Box 14627 Kilbirnie  Wellington Wellington",
    "addr:housenumber":"po box",
    "addr:postcode":"14627",
    "iso:country":"NZ",
    "sg:address":"PO Box 14627 Kilbirnie ",
    "sg:city":"Wellington",
    "sg:classifiers":[
        {
            "category":"Shopping",
            "subcategory":"Computers & Home Electronics",
            "type":"Retail Goods"
        }
    ],
    "sg:phone":"+64 4-973 0736",
    "sg:province":"Wellington",
    "sg:tags":[
        "equipment",
        "sport",
        "leisure",
        "entertainment"
    ],
    "wof:name":"Jaxons Karaoke",
    "wof:placetype":"venue"
},
  "geometry": {"coordinates":[174.794678,-41.318909],"type":"Point"}
}