{
  "type": "Feature",
  "properties": {
    "addr:full":"Opaki Rd R D 11  Masterton Wellington",
    "addr:housenumber":"11",
    "addr:street":"Opaki Rd R D",
    "iso:country":"NZ",
    "sg:address":"Opaki Rd R D 11 ",
    "sg:city":"Masterton",
    "sg:classifiers":[
        {
            "category":"Shopping",
            "subcategory":"Pets & Pet Supplies",
            "type":"Retail Goods"
        }
    ],
    "sg:phone":"+64 6-377 5595",
    "sg:province":"Wellington",
    "sg:tags":[
        "boarding",
        "garden",
        "pets",
        "catteries",
        "home",
        "kennel"
    ],
    "wof:name":"Ladymead Boarding Kennels & Cattery",
    "wof:placetype":"venue"
},
  "geometry": {"coordinates":[175.65733299999999,-40.94931],"type":"Point"}
}