{
  "type": "Feature",
  "properties": {
    "addr:full":"Anglesea St Renwick  Blenheim Marlborough",
    "addr:street":"Anglesea St",
    "iso:country":"NZ",
    "sg:address":"Anglesea St Renwick ",
    "sg:city":"Blenheim",
    "sg:classifiers":[
        {
            "category":"Building & Trades",
            "subcategory":"Pest Control",
            "type":"Services"
        }
    ],
    "sg:phone":"+64 3-572 8077",
    "sg:province":"Marlborough",
    "sg:tags":[
        "home",
        "garden"
    ],
    "wof:name":"Opossum 2000",
    "wof:placetype":"venue"
},
  "geometry": {"coordinates":[173.82148699999999,-41.510174],"type":"Point"}
}