{
  "type": "Feature",
  "properties": {
    "iso:country":"NZ",
    "sg:address":"Main Highway Bombay ",
    "sg:city":"Pukekohe",
    "sg:classifiers":[
        {
            "category":"Shopping",
            "subcategory":"Pets & Pet Supplies",
            "type":"Retail Goods"
        }
    ],
    "sg:phone":"+64 9-236 0877",
    "sg:province":"Auckland",
    "sg:tags":[
        "home",
        "garden"
    ],
    "wof:name":"The Petfood Shop",
    "wof:placetype":"venue"
},
  "geometry": {"coordinates":[174.90362500000001,-37.20063],"type":"Point"}
}