{
  "type": "Feature",
  "properties": {
    "iso:country":"NZ",
    "sg:address":"Ireland Rd ",
    "sg:city":"Waipawa",
    "sg:orig_category":"Farming: Services: Veterinarians",
    "sg:phone":"+64 6-857 8951",
    "wof:name":"Bill Henderson",
    "wof:placetype":"venue"
},
  "geometry": {"coordinates":[176.615524,-39.937706],"type":"Point"}
}