{
  "type": "Feature",
  "properties": {
    "addr:full":"Akoranga Dve Northcote  Auckland Auckland",
    "iso:country":"NZ",
    "sg:address":"Akoranga Dve Northcote ",
    "sg:city":"Auckland",
    "sg:classifiers":[
        {
            "category":"Retail",
            "subcategory":"Driving School",
            "type":"Services"
        }
    ],
    "sg:phone":"+64 9-917 9909",
    "sg:province":"Auckland",
    "sg:tags":[
        "health",
        "beauty"
    ],
    "wof:name":"Auckland University of Technology (AUT)",
    "wof:placetype":"venue"
},
  "geometry": {"coordinates":[174.747849,-36.801125],"type":"Point"}
}