{
  "type": "Feature",
  "properties": {
    "iso:country":"NZ",
    "sg:address":"Main Rd Franz ",
    "sg:city":"Josef",
    "sg:classifiers":[
        {
            "category":"Landmark",
            "subcategory":"Tourist Information",
            "type":"Public Place"
        }
    ],
    "sg:phone":"+64 800 800 793",
    "sg:tags":[
        "travel",
        "tourism",
        "tour",
        "sightseeing"
    ],
    "wof:name":"Alpine Adventure Centre",
    "wof:placetype":"venue"
},
  "geometry": {"coordinates":[170.181808,-43.387665],"type":"Point"}
}