{
  "type": "Feature",
  "properties": {
    "addr:full":"9th Floor State Insurance Building, 61-75 Rangitikei, St Palmerston  Palmerston North Manawatu-Wanganui",
    "addr:housenumber":"9th floor;61-75",
    "addr:street":"Rangitikei St Palmerston",
    "iso:country":"NZ",
    "sg:address":"9th Floor State Insurance Building, 61-75 Rangitikei, St Palmerston ",
    "sg:city":"Palmerston North",
    "sg:classifiers":[
        {
            "category":"Shopping",
            "subcategory":"Crafts & Fabrics",
            "type":"Retail Goods"
        }
    ],
    "sg:phone":"+64 6-353 0869",
    "sg:province":"Manawatu-Wanganui",
    "sg:tags":[
        "clothing"
    ],
    "wof:name":"Euro-China Company Limited",
    "wof:placetype":"venue"
},
  "geometry": {"coordinates":[175.611481,-40.357418],"type":"Point"}
}