{
  "type": "Feature",
  "properties": {
    "iso:country":"NZ",
    "sg:address":"132 The Mall Onehunga ",
    "sg:city":"Auckland",
    "sg:classifiers":[
        {
            "category":"Manufacturing",
            "subcategory":"Textiles",
            "type":"Manufacturing & Wholesale Goods"
        }
    ],
    "sg:phone":"+64 9-634 5732",
    "sg:province":"Otago",
    "sg:tags":[
        "lingerie",
        "clothing",
        "fabric",
        "manufacturer"
    ],
    "wof:name":"Waitemata Lingerie Ltd",
    "wof:placetype":"venue"
},
  "geometry": {"coordinates":[174.783661,-36.909973],"type":"Point"}
}