{
  "type": "Feature",
  "properties": {
    "iso:country":"NZ",
    "sg:address":"21 Glenmore Dve ",
    "sg:city":"Warkworth",
    "sg:classifiers":[
        {
            "category":"Home & Garden",
            "subcategory":"Hardware",
            "type":"Retail Goods"
        }
    ],
    "sg:phone":"+64 9-425 8022",
    "sg:province":"Auckland",
    "sg:tags":[
        "window",
        "fitting"
    ],
    "wof:name":"Warkworth Carpets & Interiors",
    "wof:placetype":"venue"
},
  "geometry": {"coordinates":[174.654846,-36.408409],"type":"Point"}
}