{
  "type": "Feature",
  "properties": {
    "iso:country":"NZ",
    "sg:address":"14 Flexman Pl Silverdale Hibiscus ",
    "sg:city":"Hibiscus Coast",
    "sg:orig_category":"Farming: Horticulture",
    "sg:phone":"+64 9-427 9008",
    "sg:province":"Auckland",
    "wof:name":"Terra Therma",
    "wof:placetype":"venue"
},
  "geometry": {"coordinates":[174.678177,-36.618492],"type":"Point"}
}