{
  "type": "Feature",
  "properties": {
    "iso:country":"NZ",
    "sg:address":"20 Halifax St ",
    "sg:city":"Nelson",
    "sg:orig_category":"Automotive: General Services: Service Stations",
    "sg:phone":"+64 3-548 8744",
    "sg:province":"Nelson",
    "wof:name":"Shell Halifax St",
    "wof:placetype":"venue"
},
  "geometry": {"coordinates":[173.282257,-41.270824],"type":"Point"}
}