{
  "type": "Feature",
  "properties": {
    "iso:country":"NZ",
    "sg:address":"46 Taonui St Palmerston ",
    "sg:city":"Palmerston North",
    "sg:classifiers":[
        {
            "category":"Retail",
            "subcategory":"Auto Repair",
            "type":"Services"
        }
    ],
    "sg:phone":"+64 6-356 4832",
    "sg:province":"Manawatu-Wanganui",
    "sg:tags":[
        "engine",
        "automotive",
        "servicing"
    ],
    "wof:name":"Motor Machinists Ltd",
    "wof:placetype":"venue"
},
  "geometry": {"coordinates":[175.606033,-40.352745],"type":"Point"}
}