{
  "type": "Feature",
  "properties": {
    "addr:full":"176 High St  Hawera Taranaki",
    "addr:housenumber":"176",
    "addr:street":"High St",
    "iso:country":"NZ",
    "sg:address":"176 High St ",
    "sg:city":"Hawera",
    "sg:classifiers":[
        {
            "category":"Sports & Exercise",
            "subcategory":"Ski Resort",
            "type":"Entertainment"
        }
    ],
    "sg:phone":"+64 6-278 7590",
    "sg:province":"Taranaki",
    "sg:tags":[
        "hobbies",
        "photographic",
        "leisure",
        "developing"
    ],
    "wof:name":"Maxilab 30 Minutes Photo",
    "wof:placetype":"venue"
},
  "geometry": {"coordinates":[174.281036,-39.588551],"type":"Point"}
}