{
  "type": "Feature",
  "properties": {
    "addr:full":"55 Victoria St  Hawera Taranaki",
    "addr:housenumber":"55",
    "addr:street":"Victoria St",
    "iso:country":"NZ",
    "sg:address":"55 Victoria St ",
    "sg:city":"Hawera",
    "sg:classifiers":[
        {
            "category":"Food & Beverages",
            "subcategory":"Liquor & Beverages",
            "type":"Retail Goods"
        }
    ],
    "sg:phone":"+64 6-278 4193",
    "sg:province":"Taranaki",
    "sg:tags":[
        "drink",
        "outlet"
    ],
    "wof:name":"The Mill Liquorsave",
    "wof:placetype":"venue"
},
  "geometry": {"coordinates":[174.280182,-39.588158],"type":"Point"}
}