{
  "type": "Feature",
  "properties": {
    "iso:country":"NZ",
    "sg:address":"PO Box 34030 Birkenhead ",
    "sg:city":"Auckland",
    "sg:classifiers":[
        {
            "category":"Retail",
            "subcategory":"Laundry & Dry Cleaning",
            "type":"Services"
        }
    ],
    "sg:phone":"+64 9-419 1651",
    "sg:province":"Auckland",
    "sg:tags":[
        "product",
        "wool",
        "clothing",
        "fabric"
    ],
    "wof:name":"Abraham's Wool Exchange",
    "wof:placetype":"venue"
},
  "geometry": {"coordinates":[174.734467,-36.818214],"type":"Point"}
}