{
  "type": "Feature",
  "properties": {
    "addr:full":"508 Williams St  Hastings Hawke's Bay",
    "addr:housenumber":"508",
    "addr:street":"Williams St",
    "iso:country":"NZ",
    "sg:address":"508 Williams St ",
    "sg:city":"Hastings",
    "sg:orig_category":"Home And Garden: Furniture/Furnishings",
    "sg:phone":"+64 6-870 9134",
    "sg:province":"Hawke's Bay",
    "sg:website":"http://www.chemdry.co.nz",
    "wof:name":"Chem-Dry Hawkes Bay Carpet Cleaning",
    "wof:placetype":"venue"
},
  "geometry": {"coordinates":[-85.281876,42.658848],"type":"Point"}
}