{
  "type": "Feature",
  "properties": {
    "iso:country":"NZ",
    "sg:address":"14 Kentigern Clo Pakuranga ",
    "sg:city":"Auckland",
    "sg:classifiers":[
        {
            "category":"Health Services",
            "subcategory":"Doctor",
            "type":"Services"
        }
    ],
    "sg:phone":"+64 9-577 3277",
    "sg:province":"Auckland",
    "sg:tags":[
        "services",
        "reflexology",
        "beauty"
    ],
    "wof:name":"Kentigern Beauty & Reflexology",
    "wof:placetype":"venue"
},
  "geometry": {"coordinates":[174.892807,-36.901218],"type":"Point"}
}