{
  "type": "Feature",
  "properties": {
    "iso:country":"NZ",
    "sg:address":"121 Tahunanui Dve Tahunanui ",
    "sg:city":"Nelson",
    "sg:classifiers":[
        {
            "category":"Travel",
            "subcategory":"Hotels & Motels",
            "type":"Entertainment"
        }
    ],
    "sg:phone":"+64 3-548 6898",
    "sg:province":"Nelson",
    "sg:tags":[
        "lodge",
        "tourism",
        "accommodation"
    ],
    "sg:website":"http://www.AbeliaMotorLodge.co.nz",
    "wof:name":"Abelia Motor Lodge",
    "wof:placetype":"venue"
},
  "geometry": {"coordinates":[173.244644,-41.283855],"type":"Point"}
}