{
  "type": "Feature",
  "properties": {
    "addr:full":"RD9 Te  Puke Bay of Plenty",
    "addr:street":"Rd9 Te;Bay",
    "iso:country":"NZ",
    "sg:address":"RD9 Te ",
    "sg:city":"Puke",
    "sg:classifiers":[
        {
            "category":"Recreation",
            "type":"Entertainment"
        }
    ],
    "sg:phone":"+64 274 732 682",
    "sg:province":"Bay of Plenty",
    "sg:tags":[
        "shopping",
        "hunting",
        "fishing",
        "retailers",
        "sport",
        "trip"
    ],
    "wof:name":"Maf Off-Brian (Goldy) Goldsbury",
    "wof:placetype":"venue"
},
  "geometry": {"coordinates":[169.60586499999999,-46.042324],"type":"Point"}
}