{
  "type": "Feature",
  "properties": {
    "addr:full":"4 A Elizabeth St  Timaru Canterbury",
    "addr:housenumber":"4 a",
    "addr:street":"Elizabeth St",
    "iso:country":"NZ",
    "sg:address":"4 A Elizabeth St ",
    "sg:city":"Timaru",
    "sg:classifiers":[
        {
            "category":"Fast Food",
            "type":"Food & Drink"
        }
    ],
    "sg:phone":"+64 3-688 8313",
    "sg:province":"Canterbury",
    "sg:tags":[
        "wining",
        "dining",
        "takeaway"
    ],
    "wof:name":"Red Rocket Pizza Restaurant & Cafe",
    "wof:placetype":"venue"
},
  "geometry": {"coordinates":[171.24939000000001,-44.394909],"type":"Point"}
}