{
  "type": "Feature",
  "properties": {
    "iso:country":"NZ",
    "sg:address":"63 George St Stokes Valley Lower ",
    "sg:city":"Hutt",
    "sg:orig_category":"Industrial: Engineering: Engineers: Civil Engineering Contractors",
    "sg:phone":"+64 4-563 8796",
    "sg:province":"Wellington",
    "wof:name":"Juno Civil Ltd",
    "wof:placetype":"venue"
},
  "geometry": {"coordinates":[174.98135400000001,-41.167706],"type":"Point"}
}