{
  "type": "Feature",
  "properties": {
    "iso:country":"NZ",
    "sg:address":"Level 2, Evan Parry House 43 Princes St, PO Box 800, Dunedin ",
    "sg:city":"Dunedin",
    "sg:orig_category":"Health And Beauty: Mental: Psychology",
    "sg:phone":"+64 3-471 7253",
    "sg:province":"Otago",
    "wof:name":"Mediation Matters",
    "wof:placetype":"venue"
},
  "geometry": {"coordinates":[-82.77870900000001,28.005699],"type":"Point"}
}