{
  "type": "Feature",
  "properties": {
    "addr:full":"18 Tamariki Ave Orewa Hibiscus  Hibiscus Coast Auckland",
    "addr:housenumber":"18",
    "addr:street":"Tamariki Ave",
    "iso:country":"NZ",
    "sg:address":"18 Tamariki Ave Orewa Hibiscus ",
    "sg:city":"Hibiscus Coast",
    "sg:orig_category":"Automotive: General Services: Rental Vehicles",
    "sg:phone":"+64 9-426 8335",
    "sg:province":"Auckland",
    "sg:website":"http://www.tokio.co.nz",
    "wof:name":"Tokio Car Rentals",
    "wof:placetype":"venue"
},
  "geometry": {"coordinates":[174.69012499999999,-36.582741],"type":"Point"}
}