{
  "type": "Feature",
  "properties": {
    "iso:country":"NZ",
    "sg:address":"55 Birchwood Rd ",
    "sg:city":"Ohai",
    "sg:classifiers":[
        {
            "category":"Travel",
            "subcategory":"Hotels & Motels",
            "type":"Entertainment"
        }
    ],
    "sg:phone":"+64 3-225 4749",
    "sg:tags":[
        "tavern",
        "tourism",
        "accommodation"
    ],
    "wof:name":"Ohai Country Inn Ltd",
    "wof:placetype":"venue"
},
  "geometry": {"coordinates":[167.954193,-45.933693],"type":"Point"}
}