{
  "type": "Feature",
  "properties": {
    "iso:country":"NZ",
    "sg:address":"Appleby Rd Drury ",
    "sg:city":"Auckland",
    "sg:orig_category":"Sports And Leisure: Sports: Aerial: Aero Clubs And Flying Schools",
    "sg:phone":"+64 9-294 8881",
    "sg:province":"Auckland",
    "wof:name":"Auckland Gliding Club",
    "wof:placetype":"venue"
},
  "geometry": {"coordinates":[174.971649,-37.100063],"type":"Point"}
}