{
  "type": "Feature",
  "properties": {
    "iso:country":"NZ",
    "sg:address":"55 Maurice Rd, Penrose",
    "sg:city":"Auckland",
    "sg:classifiers":[
        {
            "category":"Manufacturing",
            "subcategory":"Tools & Machinery",
            "type":"Manufacturing & Wholesale Goods"
        }
    ],
    "sg:phone":"+64 9-622 9109",
    "sg:province":"Auckland",
    "sg:tags":[
        "industrial",
        "equipment",
        "iron",
        "soldering",
        "solder",
        "tools"
    ],
    "wof:name":"Solder Products Consolidated Ltd",
    "wof:placetype":"venue"
},
  "geometry": {"coordinates":[174.809799,-36.919258],"type":"Point"}
}