{
  "type": "Feature",
  "properties": {
    "iso:country":"NZ",
    "sg:address":"Mission Bush Rd ",
    "sg:city":"Waiuku",
    "sg:classifiers":[
        {
            "category":"Manufacturing",
            "subcategory":"Glass & Minerals",
            "type":"Manufacturing & Wholesale Goods"
        }
    ],
    "sg:phone":"+64 9-235 7303",
    "sg:tags":[
        "raw",
        "industrial",
        "quarry",
        "materials"
    ],
    "wof:name":"SteelServ Ltd",
    "wof:placetype":"venue"
},
  "geometry": {"coordinates":[174.73268100000001,-37.248444],"type":"Point"}
}