{
  "type": "Feature",
  "properties": {
    "addr:full":"722 New North Rd Mt Albert  Auckland Auckland",
    "addr:housenumber":"722",
    "addr:street":"New North Rd",
    "iso:country":"NZ",
    "sg:address":"722 New North Rd Mt Albert ",
    "sg:city":"Auckland",
    "sg:orig_category":"Shopping: Engravers",
    "sg:phone":"+64 9-846 9507",
    "sg:province":"Auckland",
    "wof:name":"Aardvark Engraving",
    "wof:placetype":"venue"
},
  "geometry": {"coordinates":[174.72808800000001,-36.87851],"type":"Point"}
}