{
  "type": "Feature",
  "properties": {
    "iso:country":"NZ",
    "sg:address":"58 St Kilda Rd ",
    "sg:city":"Cambridge",
    "sg:classifiers":[
        {
            "category":"Retail",
            "subcategory":"Auto Repair",
            "type":"Services"
        }
    ],
    "sg:phone":"+64 7-827 5092",
    "sg:province":"Otago",
    "sg:tags":[
        "transmission",
        "automotive",
        "servicing"
    ],
    "wof:name":"Cambridge Transmissions",
    "wof:placetype":"venue"
},
  "geometry": {"coordinates":[-116.67604799999999,44.572186],"type":"Point"}
}