{
  "type": "Feature",
  "properties": {
    "addr:full":"119 Rimu Rd  Paraparaumu Wellington",
    "addr:housenumber":"119",
    "addr:street":"Rimu Rd",
    "iso:country":"NZ",
    "sg:address":"119 Rimu Rd ",
    "sg:city":"Paraparaumu",
    "sg:orig_category":"Industrial: Services: Gear Cutters",
    "sg:phone":"+64 4-298 5683",
    "sg:province":"Wellington",
    "wof:name":"Bettany Gears",
    "wof:placetype":"venue"
},
  "geometry": {"coordinates":[175.00006099999999,-40.918514],"type":"Point"}
}