{
  "type": "Feature",
  "properties": {
    "iso:country":"NZ",
    "sg:address":"343 Broadway Court Terrace End Palmerston ",
    "sg:city":"Palmerston North",
    "sg:orig_category":"Clothing And Fabric: Clothing: Women'S Fashions",
    "sg:phone":"+64 6-357 7886",
    "sg:province":"Manawatu-Wanganui",
    "wof:name":"Kears Fashions",
    "wof:placetype":"venue"
},
  "geometry": {"coordinates":[175.626724,-40.344013],"type":"Point"}
}