{
  "type": "Feature",
  "properties": {
    "addr:full":"40 Walls Rd Penrose  Auckland Auckland",
    "addr:housenumber":"40",
    "addr:street":"Walls Rd",
    "iso:country":"NZ",
    "sg:address":"40 Walls Rd Penrose ",
    "sg:city":"Auckland",
    "sg:orig_category":"Industrial: Engineering: Engineers: Engineers - Gas",
    "sg:phone":"+64 9-525 4150",
    "sg:province":"Auckland",
    "wof:name":"System Control Engineering NZ Ltd",
    "wof:placetype":"venue"
},
  "geometry": {"coordinates":[174.80873099999999,-36.909599],"type":"Point"}
}