{
  "type": "Feature",
  "properties": {
    "addr:full":"473 College St Palmerston  Palmerston North Manawatu-Wanganui",
    "addr:housenumber":"473",
    "addr:street":"College St Palmerston",
    "iso:country":"NZ",
    "sg:address":"473 College St Palmerston ",
    "sg:city":"Palmerston North",
    "sg:classifiers":[
        {
            "category":"Travel",
            "subcategory":"Bed & Breakfast",
            "type":"Entertainment"
        }
    ],
    "sg:phone":"+64 6-358 8684",
    "sg:province":"Manawatu-Wanganui",
    "sg:tags":[
        "tourism",
        "accommodation"
    ],
    "wof:name":"Karaka House",
    "wof:placetype":"venue"
},
  "geometry": {"coordinates":[175.62666300000001,-40.357182],"type":"Point"}
}