{
  "type": "Feature",
  "properties": {
    "iso:country":"NZ",
    "sg:address":"98, Kitchener Road, Milford - ",
    "sg:city":"Auckland",
    "sg:classifiers":[
        {
            "category":"Professional",
            "subcategory":"Art Services",
            "type":"Services"
        }
    ],
    "sg:phone":"+64 6194898249",
    "sg:province":"Auckland",
    "sg:tags":[
        "export-import"
    ],
    "wof:name":"Austria Honorary Consulate",
    "wof:placetype":"venue"
},
  "geometry": {"coordinates":[174.769699,-36.773987],"type":"Point"}
}