{
  "type": "Feature",
  "properties": {
    "addr:full":"28 Mortimer Pass Newmarket  Auckland Auckland",
    "addr:housenumber":"28",
    "addr:street":"Mortimer Pass",
    "iso:country":"NZ",
    "sg:address":"28 Mortimer Pass Newmarket ",
    "sg:city":"Auckland",
    "sg:classifiers":[
        {
            "category":"Retail",
            "subcategory":"Auto Repair",
            "type":"Services"
        }
    ],
    "sg:phone":"+64 9-520 0081",
    "sg:province":"Auckland",
    "sg:tags":[
        "automotive",
        "absorber",
        "shock",
        "servicing"
    ],
    "wof:name":"Midas Car Care",
    "wof:placetype":"venue"
},
  "geometry": {"coordinates":[174.774979,-36.871063],"type":"Point"}
}