{
  "type": "Feature",
  "properties": {
    "addr:full":"4 Wharf St South Dunedin  Dunedin Otago",
    "addr:housenumber":"4",
    "addr:street":"Wharf St",
    "iso:country":"NZ",
    "sg:address":"4 Wharf St South Dunedin ",
    "sg:city":"Dunedin",
    "sg:classifiers":[
        {
            "category":"Restaurant",
            "type":"Food & Drink"
        }
    ],
    "sg:phone":"+64 3-477 7044",
    "sg:province":"Otago",
    "sg:tags":[
        "sea"
    ],
    "wof:name":"Blue Water Products",
    "wof:placetype":"venue"
},
  "geometry": {"coordinates":[170.50633199999999,-45.886799],"type":"Point"}
}