{
  "type": "Feature",
  "properties": {
    "addr:full":"62 Stout St  Gisborne Gisborne",
    "addr:housenumber":"62",
    "addr:street":"Stout St",
    "iso:country":"NZ",
    "sg:address":"62 Stout St ",
    "sg:city":"Gisborne",
    "sg:classifiers":[
        {
            "category":"Travel",
            "subcategory":"Bed & Breakfast",
            "type":"Entertainment"
        }
    ],
    "sg:phone":"+64 6-868 4524",
    "sg:province":"Gisborne",
    "sg:tags":[
        "tourism",
        "accommodation"
    ],
    "wof:name":"Roseneath",
    "wof:placetype":"venue"
},
  "geometry": {"coordinates":[178.02726699999999,-38.65955],"type":"Point"}
}