{
  "type": "Feature",
  "properties": {
    "addr:full":"206 Great North Rd  Winton",
    "addr:housenumber":"206",
    "addr:street":"Great North Rd",
    "iso:country":"NZ",
    "sg:address":"206 Great North Rd ",
    "sg:city":"Winton",
    "sg:classifiers":[
        {
            "category":"Sports & Exercise",
            "subcategory":"Sports Center",
            "type":"Entertainment"
        }
    ],
    "sg:phone":"+64 3-236 7581",
    "sg:tags":[
        "health",
        "beauty",
        "fitness"
    ],
    "wof:name":"Winton Health & Fitness",
    "wof:placetype":"venue"
},
  "geometry": {"coordinates":[-120.61348,37.386436],"type":"Point"}
}