{
  "type": "Feature",
  "properties": {
    "iso:country":"NZ",
    "sg:address":"West Auckland ",
    "sg:city":"Auckland",
    "sg:classifiers":[
        {
            "category":"Education",
            "subcategory":"Special Training",
            "type":"Public Place"
        }
    ],
    "sg:phone":"+64 9-838 8593",
    "sg:province":"Auckland",
    "sg:tags":[
        "charter",
        "shopping",
        "dive",
        "tuition",
        "water",
        "sports",
        "retailers",
        "sport"
    ],
    "wof:name":"Norcross Dive School",
    "wof:placetype":"venue"
},
  "geometry": {"coordinates":[174.78450000000001,-37.006058],"type":"Point"}
}