{
  "type": "Feature",
  "properties": {
    "iso:country":"NZ",
    "sg:address":"172 Princes St ",
    "sg:city":"Hawera",
    "sg:classifiers":[
        {
            "category":"Wholesale",
            "subcategory":"Medical Equipment & Supplies",
            "type":"Manufacturing & Wholesale Goods"
        }
    ],
    "sg:phone":"+64 6-278 8950",
    "sg:province":"Taranaki",
    "sg:tags":[
        "health",
        "disability",
        "products",
        "beauty",
        "aid"
    ],
    "wof:name":"New Progress Enterprises",
    "wof:placetype":"venue"
},
  "geometry": {"coordinates":[174.28521699999999,-39.586655],"type":"Point"}
}