{
  "type": "Feature",
  "properties": {
    "iso:country":"NZ",
    "sg:address":"319 King Edward St South Dunedin ",
    "sg:city":"Dunedin",
    "sg:classifiers":[
        {
            "category":"Building & Trades",
            "subcategory":"Electrical",
            "type":"Services"
        }
    ],
    "sg:phone":"+64 3-455 2577",
    "sg:province":"Otago",
    "sg:tags":[
        "industrial",
        "refrigeration"
    ],
    "wof:name":"Washing Machine Repair Service (Dunedin) Ltd",
    "wof:placetype":"venue"
},
  "geometry": {"coordinates":[170.501282,-45.897007],"type":"Point"}
}