{
  "type": "Feature",
  "properties": {
    "addr:full":"cnr Memorial Ave & Greers Rd  Christchurch Canterbury",
    "addr:street":"Cnr Memorial Ave & Greers Rd",
    "iso:country":"NZ",
    "sg:address":"cnr Memorial Ave & Greers Rd ",
    "sg:city":"Christchurch",
    "sg:orig_category":"Sports And Leisure: Arts: Theatres",
    "sg:phone":"+64 3-357 1603",
    "sg:province":"Canterbury",
    "wof:name":"Aurora Centre for the Performing Arts",
    "wof:placetype":"venue"
},
  "geometry": {"coordinates":[-76.537834,37.605659],"type":"Point"}
}