{
  "type": "Feature",
  "properties": {
    "iso:country":"NZ",
    "sg:address":"2/43 Manuka St ",
    "sg:city":"Taupo",
    "sg:orig_category":"Farming: Forestry: Logging Services",
    "sg:phone":"+64 7-376 7420",
    "sg:province":"Waikato",
    "wof:name":"Lakeland Cable Logging Limited",
    "wof:placetype":"venue"
},
  "geometry": {"coordinates":[176.107681,-38.689114],"type":"Point"}
}