{
  "type": "Feature",
  "properties": {
    "addr:full":"132 Sunnybrae Rd Glenfield  Auckland Auckland",
    "addr:housenumber":"132",
    "addr:street":"Sunnybrae Rd",
    "iso:country":"NZ",
    "sg:address":"132 Sunnybrae Rd Glenfield ",
    "sg:city":"Auckland",
    "sg:orig_category":"Shopping: Sports Retailers: Water Sports: Personal Watercraft",
    "sg:phone":"+64 9-443 2924",
    "sg:province":"Auckland",
    "wof:name":"Dynobike",
    "wof:placetype":"venue"
},
  "geometry": {"coordinates":[174.728622,-36.784813],"type":"Point"}
}