{
  "type": "Feature",
  "properties": {
    "iso:country":"NZ",
    "sg:address":"State Highway 1 Levin Rd R D 13 ",
    "sg:city":"Foxton",
    "sg:orig_category":"Home And Garden: Children: Child Related",
    "sg:phone":"+64 6-363 6936",
    "wof:name":"Seldom Inn Minatures",
    "wof:placetype":"venue"
},
  "geometry": {"coordinates":[-105.235596,39.43111],"type":"Point"}
}