{
  "type": "Feature",
  "properties": {
    "iso:country":"NZ",
    "sg:address":"259 Wakefield St PO Box 6284 ",
    "sg:city":"Wellington",
    "sg:classifiers":[
        {
            "category":"Communications",
            "subcategory":"Television Station",
            "type":"Services"
        }
    ],
    "sg:phone":"+64 4-385 0185",
    "sg:province":"Wellington",
    "sg:tags":[
        "broadcasting"
    ],
    "sg:website":"http://www.oktobor.com",
    "wof:name":"Oktobor",
    "wof:placetype":"venue"
},
  "geometry": {"coordinates":[-85.910454,33.827946],"type":"Point"}
}