{
  "type": "Feature",
  "properties": {
    "addr:full":"748 Beach Rd Browns Bay  Auckland Auckland",
    "addr:housenumber":"748",
    "addr:street":"Beach Rd",
    "iso:country":"NZ",
    "sg:address":"748 Beach Rd Browns Bay ",
    "sg:city":"Auckland",
    "sg:classifiers":[
        {
            "category":"Shopping",
            "subcategory":"Gifts & Souvenirs",
            "type":"Retail Goods"
        }
    ],
    "sg:phone":"+64 9-479 7569",
    "sg:province":"Auckland",
    "sg:tags":[
        "travel",
        "tourism"
    ],
    "wof:name":"Regional Distributors Ltd",
    "wof:placetype":"venue"
},
  "geometry": {"coordinates":[174.74279799999999,-36.717812],"type":"Point"}
}