{
  "type": "Feature",
  "properties": {
    "addr:full":"241 Main South Rd  Greymouth West Coast",
    "addr:housenumber":"241",
    "addr:street":"Main South Rd",
    "iso:country":"NZ",
    "sg:address":"241 Main South Rd ",
    "sg:city":"Greymouth",
    "sg:orig_category":"Automotive: Parts And Supplies: Tyres",
    "sg:phone":"+64 3-768 5090",
    "sg:province":"West Coast",
    "wof:name":"Downes Tyre Service",
    "wof:placetype":"venue"
},
  "geometry": {"coordinates":[171.18924000000001,-42.470547],"type":"Point"}
}