{
  "type": "Feature",
  "properties": {
    "addr:full":"Weraroa Shopping Complex Oxford St  Levin Manawatu-Wanganui",
    "addr:street":"Oxford St",
    "iso:country":"NZ",
    "sg:address":"Weraroa Shopping Complex Oxford St ",
    "sg:city":"Levin",
    "sg:classifiers":[
        {
            "category":"Bars & Pubs",
            "subcategory":"Wine Bar",
            "type":"Food & Drink"
        }
    ],
    "sg:phone":"+64 6-368 6963",
    "sg:province":"Manawatu-Wanganui",
    "sg:tags":[
        "wining",
        "dining",
        "cafe"
    ],
    "wof:name":"Cafe Swee",
    "wof:placetype":"venue"
},
  "geometry": {"coordinates":[-89.084503,37.193748],"type":"Point"}
}