{
  "type": "Feature",
  "properties": {
    "iso:country":"NZ",
    "sg:address":"16 Birmingham Dve Middleton ",
    "sg:city":"Christchurch",
    "sg:orig_category":"Industrial: Parts: Pipes, Tubes And Cabling: Pipes - Plastic",
    "sg:phone":"+64 3-338 8009",
    "sg:province":"Canterbury",
    "wof:name":"PEL Industries Ltd",
    "wof:placetype":"venue"
},
  "geometry": {"coordinates":[172.591629,-43.544365],"type":"Point"}
}