{
  "type": "Feature",
  "properties": {
    "addr:full":"King Arthur Dve  Paraparaumu Wellington",
    "addr:street":"King;Dve",
    "iso:country":"NZ",
    "sg:address":"King Arthur Dve ",
    "sg:city":"Paraparaumu",
    "sg:classifiers":[
        {
            "category":"Manufacturing",
            "subcategory":"Glass & Minerals",
            "type":"Manufacturing & Wholesale Goods"
        }
    ],
    "sg:phone":"+64 4-297 3050",
    "sg:province":"Wellington",
    "sg:tags":[
        "raw",
        "industrial",
        "quarry",
        "materials"
    ],
    "wof:name":"Sand Quarry & Site Developments",
    "wof:placetype":"venue"
},
  "geometry": {"coordinates":[175.00799599999999,-40.910461],"type":"Point"}
}