{
  "type": "Feature",
  "properties": {
    "addr:full":"Rd 2 Waimauku  Auckland Auckland",
    "addr:street":"Rd 2",
    "iso:country":"NZ",
    "sg:address":"Rd 2 Waimauku ",
    "sg:city":"Auckland",
    "sg:classifiers":[
        {
            "category":"Food & Beverages",
            "subcategory":"Groceries & Convenience Stores",
            "type":"Retail Goods"
        }
    ],
    "sg:phone":"+64 9-411 7953",
    "sg:province":"Auckland",
    "sg:tags":[
        "honey",
        "drink",
        "-"
    ],
    "wof:name":"BeesOnline Ltd",
    "wof:placetype":"venue"
},
  "geometry": {"coordinates":[174.77041600000001,-36.884109],"type":"Point"}
}