{
  "type": "Feature",
  "properties": {
    "iso:country":"NZ",
    "sg:address":"280 High St Lower Hutt ",
    "sg:city":"Wellington",
    "sg:orig_category":"Health And Beauty: Beauty: Hairdressers",
    "sg:phone":"+64 4-569 7595",
    "sg:province":"Wellington",
    "wof:name":"Clipjoint Hair Salon",
    "wof:placetype":"venue"
},
  "geometry": {"coordinates":[174.90585300000001,-41.207966],"type":"Point"}
}