{
  "type": "Feature",
  "properties": {
    "addr:full":"cnr Tay St & Racecourse Rd  Invercargill Southland",
    "addr:street":"Cnr Tay St & Racecourse Rd",
    "iso:country":"NZ",
    "sg:address":"cnr Tay St & Racecourse Rd ",
    "sg:city":"Invercargill",
    "sg:classifiers":[
        {
            "category":"Travel",
            "subcategory":"Hotels & Motels",
            "type":"Entertainment"
        }
    ],
    "sg:phone":"+64 3-217 6195",
    "sg:province":"Southland",
    "sg:tags":[
        "tavern",
        "tourism",
        "accommodation"
    ],
    "wof:name":"Ascot Park Hotel",
    "wof:placetype":"venue"
},
  "geometry": {"coordinates":[168.35217299999999,-46.41185],"type":"Point"}
}