{
  "type": "Feature",
  "properties": {
    "addr:full":"9A Corunna Rd Milford  Auckland Auckland",
    "addr:housenumber":"9a",
    "addr:street":"Corunna Rd",
    "iso:country":"NZ",
    "sg:address":"9A Corunna Rd Milford ",
    "sg:city":"Auckland",
    "sg:classifiers":[
        {
            "category":"Recreation",
            "type":"Entertainment"
        }
    ],
    "sg:phone":"+64 9-410 2959",
    "sg:province":"Auckland",
    "sg:tags":[
        "shopping",
        "hunting",
        "fishing",
        "retailers",
        "sport",
        "trip"
    ],
    "wof:name":"Smokin' Reels",
    "wof:placetype":"venue"
},
  "geometry": {"coordinates":[174.764984,-36.771812],"type":"Point"}
}