{
  "type": "Feature",
  "properties": {
    "addr:full":"Wairau Vly R D 1 Wairau  Valley",
    "addr:housenumber":"1",
    "addr:street":"R D;Wairau Valley",
    "iso:country":"NZ",
    "sg:address":"Wairau Vly R D 1 Wairau ",
    "sg:city":"Valley",
    "sg:classifiers":[
        {
            "category":"Farming",
            "subcategory":"Fish & Marine Products",
            "type":"Manufacturing & Wholesale Goods"
        }
    ],
    "sg:phone":"+64 3-572 2770",
    "sg:tags":[
        "-",
        "boat",
        "transport"
    ],
    "wof:name":"Ormond Aquaculture Ltd",
    "wof:placetype":"venue"
},
  "geometry": {"coordinates":[173.76260400000001,-35.253605],"type":"Point"}
}