{
  "type": "Feature",
  "properties": {
    "addr:full":"4 Manchester St  Waimate",
    "addr:housenumber":"4",
    "addr:street":"Manchester St",
    "iso:country":"NZ",
    "sg:address":"4 Manchester St ",
    "sg:city":"Waimate",
    "sg:classifiers":[
        {
            "category":"Travel",
            "subcategory":"Travel Agent",
            "type":"Entertainment"
        }
    ],
    "sg:phone":"+64 3-689 8153",
    "sg:tags":[
        "tour",
        "tourism",
        "adventure",
        "sightseeing"
    ],
    "wof:name":"Whitehorse Safaris",
    "wof:placetype":"venue"
},
  "geometry": {"coordinates":[171.024078,-44.7234],"type":"Point"}
}