{
  "type": "Feature",
  "properties": {
    "addr:full":"80 Lansford Cre Avondale  Auckland Auckland",
    "addr:housenumber":"80",
    "addr:street":"Lansford Cre",
    "iso:country":"NZ",
    "sg:address":"80 Lansford Cre Avondale ",
    "sg:city":"Auckland",
    "sg:classifiers":[
        {
            "category":"Shopping",
            "subcategory":"Shoes",
            "type":"Retail Goods"
        }
    ],
    "sg:phone":"+64 9-828 0459",
    "sg:province":"Auckland",
    "sg:tags":[
        "foot",
        "clothing",
        "fabric",
        "wear"
    ],
    "wof:name":"Flett Footwear",
    "wof:placetype":"venue"
},
  "geometry": {"coordinates":[174.698151,-36.904575],"type":"Point"}
}