{
  "type": "Feature",
  "properties": {
    "iso:country":"NZ",
    "sg:address":"408 Warren St Nth ",
    "sg:city":"Hastings",
    "sg:classifiers":[
        {
            "category":"Home & Garden",
            "subcategory":"Building Materials",
            "type":"Retail Goods"
        }
    ],
    "sg:phone":"+64 6-878 9332",
    "sg:province":"Hawke's Bay",
    "sg:tags":[
        "electrician",
        "related"
    ],
    "wof:name":"Mike Randell Electrical",
    "wof:placetype":"venue"
},
  "geometry": {"coordinates":[-81.508163,29.711214],"type":"Point"}
}