{
  "type": "Feature",
  "properties": {
    "iso:country":"NZ",
    "sg:address":"176 Stanley Rd ",
    "sg:city":"Gisborne",
    "sg:orig_category":"Shopping: Retail Stores: Batteries",
    "sg:phone":"+64 6-868 9149",
    "sg:province":"Gisborne",
    "wof:name":"Besco Batteries",
    "wof:placetype":"venue"
},
  "geometry": {"coordinates":[178.006104,-38.664185],"type":"Point"}
}