{
  "type": "Feature",
  "properties": {
    "iso:country":"NZ",
    "sg:address":"Cnr Anglesea & Knox Sts ",
    "sg:city":"Hamilton",
    "sg:classifiers":[
        {
            "category":"Health Services",
            "subcategory":"Health Practitioner",
            "type":"Services"
        }
    ],
    "sg:phone":"+64 7-834 0737",
    "sg:province":"Waikato",
    "sg:tags":[
        "specialist",
        "medical",
        "beauty",
        "specialists"
    ],
    "wof:name":"Waikato Bone Density Services",
    "wof:placetype":"venue"
},
  "geometry": {"coordinates":[-87.988968,34.142426],"type":"Point"}
}