{
  "type": "Feature",
  "properties": {
    "iso:country":"NZ",
    "sg:address":"Cnr Bush Rd & William Pickering Dve Albany ",
    "sg:city":"Auckland",
    "sg:orig_category":"Industrial: Metal: Products: Merchants And Products",
    "sg:phone":"+64 9-415 8500",
    "sg:province":"Auckland",
    "wof:name":"Giltech Precision Castings Ltd",
    "wof:placetype":"venue"
},
  "geometry": {"coordinates":[174.698914,-36.727741],"type":"Point"}
}