{
  "type": "Feature",
  "properties": {
    "iso:country":"NZ",
    "sg:address":"PO Box 318 ",
    "sg:city":"Gore",
    "sg:classifiers":[
        {
            "category":"Personal",
            "type":"Services"
        }
    ],
    "sg:phone":"+64 3-208 4347",
    "sg:province":"Southland",
    "sg:tags":[
        "services",
        "home",
        "garden",
        "counselling"
    ],
    "wof:name":"Marian Cunningham Counselling Service",
    "wof:placetype":"venue"
},
  "geometry": {"coordinates":[-78.354027,39.282139],"type":"Point"}
}