{
  "type": "Feature",
  "properties": {
    "iso:country":"NZ",
    "sg:address":"Travis Rd North New Brighton ",
    "sg:city":"Christchurch",
    "sg:classifiers":[
        {
            "category":"Sports & Exercise",
            "subcategory":"Sports Center",
            "type":"Entertainment"
        }
    ],
    "sg:phone":"+64 3-941 6849",
    "sg:province":"Canterbury",
    "sg:tags":[
        "sporting",
        "sports",
        "-",
        "leisure",
        "facility"
    ],
    "wof:name":"QEII Park",
    "wof:placetype":"venue"
},
  "geometry": {"coordinates":[172.704742,-43.49366],"type":"Point"}
}