{
  "type": "Feature",
  "properties": {
    "iso:country":"NZ",
    "sg:address":"2 Main St ",
    "sg:city":"Gore",
    "sg:classifiers":[
        {
            "category":"Travel",
            "subcategory":"Hotels & Motels",
            "type":"Entertainment"
        }
    ],
    "sg:phone":"+64 3-208 3851",
    "sg:province":"Southland",
    "sg:tags":[
        "tavern",
        "tourism",
        "accommodation"
    ],
    "wof:name":"Howl At The Moon",
    "wof:placetype":"venue"
},
  "geometry": {"coordinates":[-95.117569,35.52932],"type":"Point"}
}