{
  "type": "Feature",
  "properties": {
    "addr:full":"Pauanui Village Shopping Centre 9 Jubillee Dve Pauanui Tairua",
    "addr:housenumber":"9",
    "addr:street":"Jubillee Dve",
    "iso:country":"NZ",
    "sg:address":"Pauanui Village Shopping Centre 9 Jubillee Dve Pauanui",
    "sg:city":"Tairua",
    "sg:classifiers":[
        {
            "category":"Health Services",
            "subcategory":"Clinic",
            "type":"Services"
        }
    ],
    "sg:phone":"+64 7-864 8404",
    "sg:tags":[
        "medical",
        "beauty"
    ],
    "wof:name":"Pauanui Medical Centre",
    "wof:placetype":"venue"
},
  "geometry": {"coordinates":[175.846405,-37.00642],"type":"Point"}
}