{
  "type": "Feature",
  "properties": {
    "addr:full":"Lower Hutt  Wellington Wellington",
    "addr:street":"Lower",
    "iso:country":"NZ",
    "sg:address":"Lower Hutt ",
    "sg:city":"Wellington",
    "sg:orig_category":"Industrial: Products",
    "sg:phone":"+64 800 258 387",
    "sg:province":"Wellington",
    "sg:website":"http://www.bluetruck.co.nz",
    "wof:name":"Blue Truck Scaffolds",
    "wof:placetype":"venue"
},
  "geometry": {"coordinates":[174.904526,-41.208431],"type":"Point"}
}