{
  "type": "Feature",
  "properties": {
    "addr:full":"7 Akatea Rd Glendene  Auckland Auckland",
    "addr:housenumber":"7",
    "addr:street":"Akatea Rd",
    "iso:country":"NZ",
    "sg:address":"7 Akatea Rd Glendene ",
    "sg:city":"Auckland",
    "sg:classifiers":[
        {
            "category":"Manufacturing",
            "subcategory":"Glass & Minerals",
            "type":"Manufacturing & Wholesale Goods"
        }
    ],
    "sg:phone":"+64 9-818 9215",
    "sg:province":"Auckland",
    "sg:tags":[
        "chemical",
        "paint",
        "industrial",
        "manufacturer",
        "compounds"
    ],
    "wof:name":"Protec",
    "wof:placetype":"venue"
},
  "geometry": {"coordinates":[174.66078200000001,-36.888428],"type":"Point"}
}