{
  "type": "Feature",
  "properties": {
    "iso:country":"NZ",
    "sg:address":"Moera Community House 107 Randwick Cre Moera ",
    "sg:city":"Wellington",
    "sg:classifiers":[
        {
            "category":"Education",
            "subcategory":"Special Training",
            "type":"Public Place"
        }
    ],
    "sg:phone":"+64 4-566 1034",
    "sg:province":"Wellington",
    "sg:tags":[
        "tutor",
        "coach",
        "teacher"
    ],
    "wof:name":"Hutt Adult Learning Support (ARLA inc.)",
    "wof:placetype":"venue"
},
  "geometry": {"coordinates":[174.868668,-41.13467],"type":"Point"}
}