{
  "type": "Feature",
  "properties": {
    "addr:full":"Moera Community House 107 Randwick Cre Moera  Wellington Wellington",
    "addr:housenumber":"107",
    "iso:country":"NZ",
    "sg:address":"Moera Community House 107 Randwick Cre Moera ",
    "sg:city":"Wellington",
    "sg:classifiers":[
        {
            "category":"Education",
            "subcategory":"Special Training",
            "type":"Public Place"
        }
    ],
    "sg:phone":"+64 4-566 1034",
    "sg:province":"Wellington",
    "sg:tags":[
        "tutor",
        "coach",
        "teacher"
    ],
    "wof:name":"Hutt Adult Learning Support (ARLA inc.)",
    "wof:placetype":"venue"
},
  "geometry": {"coordinates":[174.86866800000001,-41.13467],"type":"Point"}
}