{
  "type": "Feature",
  "properties": {
    "addr:full":"1/8 Blackburn Rd East Tamaki  Auckland Auckland",
    "addr:housenumber":"1 / 8",
    "addr:street":"Blackburn Rd",
    "iso:country":"NZ",
    "sg:address":"1/8 Blackburn Rd East Tamaki ",
    "sg:city":"Auckland",
    "sg:classifiers":[
        {
            "category":"Food Court",
            "type":"Food & Drink"
        }
    ],
    "sg:phone":"+64 9-274 8888",
    "sg:province":"Auckland",
    "sg:tags":[
        "packer",
        "processing",
        "processor"
    ],
    "wof:name":"Mandarin International (NZ) Ltd",
    "wof:placetype":"venue"
},
  "geometry": {"coordinates":[174.88896199999999,-36.941036],"type":"Point"}
}