{
  "type": "Feature",
  "properties": {
    "addr:full":"1 Cargill St Waikiwi  Invercargill Southland",
    "addr:housenumber":"1",
    "addr:street":"Cargill St",
    "iso:country":"NZ",
    "sg:address":"1 Cargill St Waikiwi ",
    "sg:city":"Invercargill",
    "sg:classifiers":[
        {
            "category":"Social Services",
            "subcategory":"Retirement Home",
            "type":"Services"
        }
    ],
    "sg:phone":"+64 3-215 8886",
    "sg:province":"Southland",
    "sg:tags":[
        "care",
        "garden",
        "elderly",
        "village"
    ],
    "wof:name":"Cargill Home Southland Ltd",
    "wof:placetype":"venue"
},
  "geometry": {"coordinates":[168.35264599999999,-46.377628],"type":"Point"}
}