{
  "type": "Feature",
  "properties": {
    "iso:country":"NZ",
    "sg:address":"(Behind Mobil) 350 St Heliers Bay Rd St Heliers ",
    "sg:city":"Auckland",
    "sg:classifiers":[
        {
            "category":"Retail",
            "subcategory":"Auto Repair",
            "type":"Services"
        }
    ],
    "sg:phone":"+64 9-521 0306",
    "sg:province":"Auckland",
    "sg:tags":[
        "automotive",
        "servicing"
    ],
    "wof:name":"Clearview Motors",
    "wof:placetype":"venue"
},
  "geometry": {"coordinates":[174.862976,-36.856163],"type":"Point"}
}