{
  "type": "Feature",
  "properties": {
    "addr:full":"Albany  Auckland Auckland",
    "iso:country":"NZ",
    "sg:address":"Albany ",
    "sg:city":"Auckland",
    "sg:classifiers":[
        {
            "category":"Home & Garden",
            "subcategory":"Home Furnishings",
            "type":"Retail Goods"
        }
    ],
    "sg:phone":"+64 9-415 2672",
    "sg:province":"Auckland",
    "sg:tags":[
        "furniture/furnishings",
        "bedding",
        "bed"
    ],
    "wof:name":"Albany Waterbeds",
    "wof:placetype":"venue"
},
  "geometry": {"coordinates":[174.698914,-36.727741],"type":"Point"}
}