{
  "type": "Feature",
  "properties": {
    "addr:full":"141 Cascades Rd Pakuranga  Auckland Auckland",
    "addr:housenumber":"141",
    "addr:street":"Cascades Rd",
    "iso:country":"NZ",
    "sg:address":"141 Cascades Rd Pakuranga ",
    "sg:city":"Auckland",
    "sg:classifiers":[
        {
            "category":"Sports & Exercise",
            "subcategory":"Tennis Court",
            "type":"Entertainment"
        }
    ],
    "sg:phone":"+64 9-576 2764",
    "sg:province":"Auckland",
    "sg:tags":[
        "bait",
        "hunting",
        "fishing",
        "retailers",
        "tackle",
        "shopping"
    ],
    "wof:name":"Big Fish Bait & Tackle Co Ltd",
    "wof:placetype":"venue"
},
  "geometry": {"coordinates":[174.90271000000001,-36.913734],"type":"Point"}
}