{
  "type": "Feature",
  "properties": {
    "iso:country":"NZ",
    "sg:address":"32 Barrow St PO Box 75 ",
    "sg:city":"Bluff",
    "sg:classifiers":[
        {
            "category":"Internet Cafe",
            "subcategory":"None",
            "type":"Food & Drink"
        }
    ],
    "sg:phone":"+64 3-212 7237",
    "sg:tags":[
        "fish",
        "processing",
        "processor"
    ],
    "wof:name":"Awarua Tio Development Ltd",
    "wof:placetype":"venue"
},
  "geometry": {"coordinates":[-109.546745,37.286579],"type":"Point"}
}