{
  "type": "Feature",
  "properties": {
    "addr:full":"Pirimai Plaza Shopping Centre cnr Bill Hercock St &, Allan Berry Ave  Napier Hawke's Bay",
    "addr:street":"Centre Cnr Bill Hercock St & Allan Berry Ave",
    "iso:country":"NZ",
    "sg:address":"Pirimai Plaza Shopping Centre cnr Bill Hercock St &, Allan Berry Ave ",
    "sg:city":"Napier",
    "sg:orig_category":"Health And Beauty: Beauty: Hairdressers",
    "sg:phone":"+64 6-843 9380",
    "sg:province":"Hawke's Bay",
    "wof:name":"A Shade Different",
    "wof:placetype":"venue"
},
  "geometry": {"coordinates":[-80.588562,38.790821],"type":"Point"}
}