{
  "type": "Feature",
  "properties": {
    "addr:full":"10 Hillcrest Ave  Rotorua Waikato",
    "addr:housenumber":"10",
    "addr:street":"Hillcrest Ave",
    "iso:country":"NZ",
    "sg:address":"10 Hillcrest Ave ",
    "sg:city":"Rotorua",
    "sg:classifiers":[
        {
            "category":"Banks & Credit Unions",
            "subcategory":"Investment Brokerage",
            "type":"Services"
        }
    ],
    "sg:phone":"+64 7-348 2631",
    "sg:province":"Waikato",
    "sg:tags":[
        "educational",
        "education",
        "training"
    ],
    "wof:name":"Helen O'Grady Children's Drama Academy",
    "wof:placetype":"venue"
},
  "geometry": {"coordinates":[176.23803699999999,-38.149776],"type":"Point"}
}