{
  "type": "Feature",
  "properties": {
    "iso:country":"NZ",
    "sg:address":"12 a Muller Rd ",
    "sg:city":"Blenheim",
    "sg:classifiers":[
        {
            "category":"Health Services",
            "subcategory":"Health Practitioner",
            "type":"Services"
        }
    ],
    "sg:phone":"+64 3-577 6172",
    "sg:province":"Marlborough",
    "sg:tags":[
        "consultant",
        "medical",
        "beauty"
    ],
    "wof:name":"Alzheimers Society Marlborough",
    "wof:placetype":"venue"
},
  "geometry": {"coordinates":[-74.459564,42.468643],"type":"Point"}
}