{
  "type": "Feature",
  "properties": {
    "addr:full":"52 Stewart St  Christchurch Canterbury",
    "addr:housenumber":"52",
    "addr:street":"Stewart St",
    "iso:country":"NZ",
    "sg:address":"52 Stewart St ",
    "sg:city":"Christchurch",
    "sg:classifiers":[
        {
            "category":"Manufacturing",
            "subcategory":"Motor Vehicles & Parts",
            "type":"Manufacturing & Wholesale Goods"
        }
    ],
    "sg:phone":"+64 3-366 9988",
    "sg:province":"Canterbury",
    "sg:tags":[
        "body",
        "repair",
        "builder",
        "servicing",
        "automotive"
    ],
    "wof:name":"Auto Restorations Ltd",
    "wof:placetype":"venue"
},
  "geometry": {"coordinates":[-76.537834,37.605659],"type":"Point"}
}