{
  "type": "Feature",
  "properties": {
    "addr:full":"67 Hogans Rd Glenfield  Auckland Auckland",
    "addr:housenumber":"67",
    "addr:street":"Hogans Rd",
    "iso:country":"NZ",
    "sg:address":"67 Hogans Rd Glenfield ",
    "sg:city":"Auckland",
    "sg:orig_category":"Industrial: Services: Specialist Services: Scanning",
    "sg:phone":"+64 9-443 0662",
    "sg:province":"Auckland",
    "wof:name":"ARTOVEC Scanning Services",
    "wof:placetype":"venue"
},
  "geometry": {"coordinates":[174.72688299999999,-36.77018],"type":"Point"}
}