{
  "type": "Feature",
  "properties": {
    "addr:full":"8 Prescott St Penrose  Auckland Auckland",
    "addr:housenumber":"8",
    "addr:street":"Prescott St",
    "iso:country":"NZ",
    "sg:address":"8 Prescott St Penrose ",
    "sg:city":"Auckland",
    "sg:classifiers":[
        {
            "category":"Wholesale",
            "subcategory":"Auto Parts",
            "type":"Manufacturing & Wholesale Goods"
        }
    ],
    "sg:phone":"+64 9-525 3856",
    "sg:province":"Auckland",
    "sg:tags":[
        "automotive",
        "supplies"
    ],
    "wof:name":"Transport Diesel & Marine",
    "wof:placetype":"venue"
},
  "geometry": {"coordinates":[174.818466,-36.910152],"type":"Point"}
}