{
  "type": "Feature",
  "properties": {
    "addr:full":"Nopera Bay Kenepuru Sounds R D 2  Picton Marlborough",
    "addr:housenumber":"2",
    "addr:street":"R D",
    "iso:country":"NZ",
    "sg:address":"Nopera Bay Kenepuru Sounds R D 2 ",
    "sg:city":"Picton",
    "sg:orig_category":"Sports And Leisure: Sports: Golf: Golf Courses",
    "sg:phone":"+64 3-573 4086",
    "sg:province":"Marlborough",
    "wof:name":"Nopera Bay Golf Club",
    "wof:placetype":"venue"
},
  "geometry": {"coordinates":[174.00427199999999,-41.294796],"type":"Point"}
}