{
  "type": "Feature",
  "properties": {
    "addr:full":"9 Kirk St Grey Lynn  Auckland Auckland",
    "addr:housenumber":"9",
    "addr:street":"Kirk St",
    "iso:country":"NZ",
    "sg:address":"9 Kirk St Grey Lynn ",
    "sg:city":"Auckland",
    "sg:classifiers":[
        {
            "category":"Education",
            "subcategory":"University",
            "type":"Public Place"
        }
    ],
    "sg:phone":"+64 9-376 0009",
    "sg:province":"Auckland",
    "sg:tags":[
        "training",
        "instruction",
        "language"
    ],
    "wof:name":"Alliance Francaise d'Auckland Inc",
    "wof:placetype":"venue"
},
  "geometry": {"coordinates":[174.73474100000001,-36.861408],"type":"Point"}
}