{
  "type": "Feature",
  "properties": {
    "iso:country":"NZ",
    "sg:address":"35 Day Pl ",
    "sg:city":"Rotorua",
    "sg:classifiers":[
        {
            "category":"Professional",
            "subcategory":"Art Services",
            "type":"Services"
        }
    ],
    "sg:phone":"+64 7-349 4794",
    "sg:province":"Bay of Plenty",
    "sg:tags":[
        "personal",
        "photographer",
        "services",
        "garden",
        "home"
    ],
    "wof:name":"Art City",
    "wof:placetype":"venue"
},
  "geometry": {"coordinates":[176.230209,-38.166229],"type":"Point"}
}