{
  "type": "Feature",
  "properties": {
    "iso:country":"NZ",
    "sg:address":"74 Don St ",
    "sg:city":"Invercargill",
    "sg:classifiers":[
        {
            "category":"Personal",
            "subcategory":"Piercing",
            "type":"Services"
        }
    ],
    "sg:phone":"+64 3-214 9092",
    "sg:province":"Southland",
    "sg:tags":[
        "body",
        "ear",
        "health",
        "nose",
        "beauty"
    ],
    "wof:name":"Platinum Piercing",
    "wof:placetype":"venue"
},
  "geometry": {"coordinates":[168.352234,-46.410629],"type":"Point"}
}