{
  "type": "Feature",
  "properties": {
    "iso:country":"NZ",
    "sg:address":"South Hwy ",
    "sg:city":"Whitianga",
    "sg:orig_category":"Sports And Leisure: Sports: Aerial",
    "sg:phone":"+64 7-866 5128",
    "wof:name":"Mercury Bay Aero Club",
    "wof:placetype":"venue"
},
  "geometry": {"coordinates":[175.691681,-36.839863],"type":"Point"}
}