{
  "type": "Feature",
  "properties": {
    "addr:full":"35 B Dornwell Rd Three Kings  Auckland Auckland",
    "addr:housenumber":"35 b",
    "addr:street":"Dornwell Rd",
    "iso:country":"NZ",
    "sg:address":"35 B Dornwell Rd Three Kings ",
    "sg:city":"Auckland",
    "sg:classifiers":[
        {
            "category":"Education",
            "subcategory":"Special Training",
            "type":"Public Place"
        }
    ],
    "sg:phone":"+64 9-624 2227",
    "sg:province":"Auckland",
    "sg:tags":[
        "tutor",
        "coach",
        "teacher"
    ],
    "wof:name":"Kip McGrath Education Centres (NZ) Ltd",
    "wof:placetype":"venue"
},
  "geometry": {"coordinates":[174.752365,-36.904594],"type":"Point"}
}