{
  "type": "Feature",
  "properties": {
    "iso:country":"NZ",
    "sg:address":"270 Broadway Ave Palmerston ",
    "sg:city":"Palmerston North",
    "sg:orig_category":"Health And Beauty: Dental: Dentists",
    "sg:phone":"+64 6-358 8277",
    "sg:province":"Manawatu-Wanganui",
    "wof:name":"Joe Robert BDS",
    "wof:placetype":"venue"
},
  "geometry": {"coordinates":[175.622482,-40.34988],"type":"Point"}
}