{
  "type": "Feature",
  "properties": {
    "iso:country":"NZ",
    "sg:address":"19 A Rylock Pl Pakuranga ",
    "sg:city":"Auckland",
    "sg:classifiers":[
        {
            "category":"Shopping",
            "subcategory":"Crafts & Fabrics",
            "type":"Retail Goods"
        }
    ],
    "sg:phone":"+64 9-576 2901",
    "sg:province":"Auckland",
    "sg:tags":[
        "leather",
        "clothing",
        "suede"
    ],
    "wof:name":"Desert Road Leathergoods",
    "wof:placetype":"venue"
},
  "geometry": {"coordinates":[174.899429,-36.918739],"type":"Point"}
}