{
  "type": "Feature",
  "properties": {
    "addr:full":"25 Brunswick St Lower  Hutt Wellington",
    "addr:housenumber":"25",
    "addr:street":"Brunswick St",
    "iso:country":"NZ",
    "sg:address":"25 Brunswick St Lower ",
    "sg:city":"Hutt",
    "sg:orig_category":"Automotive: General Services: Vehicle Inspection",
    "sg:phone":"+64 4-527 0520",
    "sg:province":"Wellington",
    "wof:name":"Vehicle Testing New Zealand Limited",
    "wof:placetype":"venue"
},
  "geometry": {"coordinates":[174.915131,-41.205021],"type":"Point"}
}