{
  "type": "Feature",
  "properties": {
    "iso:country":"NZ",
    "sg:address":"71 Arawa St ",
    "sg:city":"Matamata",
    "sg:classifiers":[
        {
            "category":"Communications",
            "subcategory":"Film & Video Production",
            "type":"Services"
        }
    ],
    "sg:phone":"+64 7-888 5227",
    "sg:province":"Waikato",
    "sg:tags":[
        "sport",
        "leisure",
        "library",
        "entertainment"
    ],
    "wof:name":"Video Ezy",
    "wof:placetype":"venue"
},
  "geometry": {"coordinates":[175.77357499999999,-37.809048],"type":"Point"}
}