{
  "type": "Feature",
  "properties": {
    "addr:full":"15 Main St  Levin Manawatu-Wanganui",
    "addr:housenumber":"15",
    "addr:street":"Main St",
    "iso:country":"NZ",
    "sg:address":"15 Main St ",
    "sg:city":"Levin",
    "sg:classifiers":[
        {
            "category":"Manufacturing",
            "subcategory":"Furniture",
            "type":"Manufacturing & Wholesale Goods"
        }
    ],
    "sg:phone":"+64 6-368 1165",
    "sg:province":"Manawatu-Wanganui",
    "sg:tags":[
        "furniture/furnishings",
        "home",
        "garden",
        "manufacturer"
    ],
    "wof:name":"J 'n' R Furniture",
    "wof:placetype":"venue"
},
  "geometry": {"coordinates":[175.285324,-40.625278],"type":"Point"}
}