{
  "type": "Feature",
  "properties": {
    "iso:country":"NZ",
    "sg:address":"39 Northway St Te Rapa ",
    "sg:city":"Hamilton",
    "sg:classifiers":[
        {
            "category":"Utilities",
            "subcategory":"Fuel Oil & Lpg",
            "type":"Services"
        }
    ],
    "sg:phone":"+64 7-849 0886",
    "sg:province":"Waikato",
    "sg:tags":[
        "energy",
        "industrial",
        "refiner",
        "utilities"
    ],
    "wof:name":"Paragon Oil Systems Ltd",
    "wof:placetype":"venue"
},
  "geometry": {"coordinates":[175.239853,-37.756996],"type":"Point"}
}