{
  "type": "Feature",
  "properties": {
    "addr:full":"5 Polson St  Wanganui Manawatu-Wanganui",
    "addr:housenumber":"5",
    "addr:street":"Polson St",
    "iso:country":"NZ",
    "sg:address":"5 Polson St ",
    "sg:city":"Wanganui",
    "sg:classifiers":[
        {
            "category":"Home & Garden",
            "subcategory":"Home Furnishings",
            "type":"Retail Goods"
        }
    ],
    "sg:phone":"+64 6-344 6194",
    "sg:province":"Manawatu-Wanganui",
    "sg:tags":[
        "furniture/furnishings",
        "bedding",
        "bed"
    ],
    "wof:name":"Castlecliff Second Choice Furniture - NEW & USED",
    "wof:placetype":"venue"
},
  "geometry": {"coordinates":[174.99380500000001,-39.942276],"type":"Point"}
}