{
  "type": "Feature",
  "properties": {
    "iso:country":"NZ",
    "sg:address":"259 Awapuni Rd ",
    "sg:city":"Gisborne",
    "sg:orig_category":"Transport: Transportation: Furniture Removal/Packers",
    "sg:phone":"+64 6-867 8410",
    "sg:province":"Manawatu-Wanganui",
    "wof:name":"Roadfreighters Ltd",
    "wof:placetype":"venue"
},
  "geometry": {"coordinates":[178.002045,-38.668922],"type":"Point"}
}