{
  "type": "Feature",
  "properties": {
    "addr:full":"259 Awapuni Rd  Gisborne Manawatu-Wanganui",
    "addr:housenumber":"259",
    "addr:street":"Awapuni Rd",
    "iso:country":"NZ",
    "sg:address":"259 Awapuni Rd ",
    "sg:city":"Gisborne",
    "sg:orig_category":"Transport: Transportation: Furniture Removal/Packers",
    "sg:phone":"+64 6-867 8410",
    "sg:province":"Manawatu-Wanganui",
    "wof:name":"Roadfreighters Ltd",
    "wof:placetype":"venue"
},
  "geometry": {"coordinates":[178.00204500000001,-38.668922],"type":"Point"}
}