{
  "type": "Feature",
  "properties": {
    "iso:country":"NZ",
    "sg:address":"39 Port Rd ",
    "sg:city":"Whangarei",
    "sg:orig_category":"Sports And Leisure: Sports: Equestrian: Equestrian Supplies",
    "sg:phone":"+64 9-459 7633",
    "sg:province":"Northland",
    "wof:name":"Port Road Saddlery",
    "wof:placetype":"venue"
},
  "geometry": {"coordinates":[174.32814,-35.729725],"type":"Point"}
}