{
  "type": "Feature",
  "properties": {
    "iso:country":"NZ",
    "sg:address":"24 A Gladstone Rd ",
    "sg:city":"Gisborne",
    "sg:classifiers":[
        {
            "category":"Shopping",
            "subcategory":"Computers & Home Electronics",
            "type":"Retail Goods"
        }
    ],
    "sg:phone":"+64 6-868 3562",
    "sg:province":"Gisborne",
    "sg:tags":[
        "recording",
        "equipment",
        "sport",
        "music",
        "leisure"
    ],
    "wof:name":"Junk Rock Records",
    "wof:placetype":"venue"
},
  "geometry": {"coordinates":[178.027481,-38.667713],"type":"Point"}
}