{
  "type": "Feature",
  "properties": {
    "addr:full":"cnr Willis & Tewsley Sts  Dunedin Otago",
    "addr:housenumber":"sts",
    "addr:street":"Cnr",
    "iso:country":"NZ",
    "sg:address":"cnr Willis & Tewsley Sts ",
    "sg:city":"Dunedin",
    "sg:orig_category":"Industrial: Metal: Services: Steel Processing",
    "sg:phone":"+64 3-477 9655",
    "sg:province":"Otago",
    "wof:name":"Steel & Tube Distribution",
    "wof:placetype":"venue"
},
  "geometry": {"coordinates":[-82.784721,28.013355],"type":"Point"}
}