{
  "type": "Feature",
  "properties": {
    "addr:full":"387 Grey St Hamilton East  Hamilton Waikato",
    "addr:housenumber":"387",
    "addr:street":"Grey St",
    "iso:country":"NZ",
    "sg:address":"387 Grey St Hamilton East ",
    "sg:city":"Hamilton",
    "sg:orig_category":"Shopping: Accessories: Jewellers And Watchmakers",
    "sg:phone":"+64 7-856 6750",
    "sg:province":"Waikato",
    "wof:name":"White Murray",
    "wof:placetype":"venue"
},
  "geometry": {"coordinates":[175.29307600000001,-37.793015],"type":"Point"}
}