{
  "type": "Feature",
  "properties": {
    "iso:country":"NZ",
    "sg:address":"Port Taranki New ",
    "sg:city":"Plymouth",
    "sg:classifiers":[
        {
            "category":"Shopping",
            "subcategory":"Stationery & Office Supplies",
            "type":"Retail Goods"
        }
    ],
    "sg:phone":"+64 6-751 4464",
    "sg:province":"Taranaki",
    "sg:tags":[
        "map",
        "chart"
    ],
    "wof:name":"Phoenix Shipping Agencies Ltd",
    "wof:placetype":"venue"
},
  "geometry": {"coordinates":[-116.819725,43.97221],"type":"Point"}
}