{
  "type": "Feature",
  "properties": {
    "addr:full":"311 Gt South Rd Manurewa  Auckland Auckland",
    "addr:housenumber":"311",
    "addr:street":"Gt South Rd",
    "iso:country":"NZ",
    "sg:address":"311 Gt South Rd Manurewa ",
    "sg:city":"Auckland",
    "sg:classifiers":[
        {
            "category":"Manufacturing",
            "subcategory":"Motor Vehicles & Parts",
            "type":"Manufacturing & Wholesale Goods"
        }
    ],
    "sg:phone":"+64 9-266 2558",
    "sg:province":"Auckland",
    "sg:tags":[
        "automotive",
        "steering",
        "supplies",
        "suspension"
    ],
    "wof:name":"Auckland Power Steering Specialists Ltd",
    "wof:placetype":"venue"
},
  "geometry": {"coordinates":[174.90501399999999,-37.031872],"type":"Point"}
}