{
  "type": "Feature",
  "properties": {
    "addr:full":"75 Chartwell Ave Glenfield  Auckland Auckland",
    "addr:housenumber":"75",
    "addr:street":"Chartwell Ave",
    "iso:country":"NZ",
    "sg:address":"75 Chartwell Ave Glenfield ",
    "sg:city":"Auckland",
    "sg:orig_category":"Home And Garden: Furniture/Furnishings: Cabinetmakers",
    "sg:phone":"+64 9-444 9517",
    "sg:province":"Auckland",
    "wof:name":"Wald Furniture",
    "wof:placetype":"venue"
},
  "geometry": {"coordinates":[174.72924800000001,-36.780495],"type":"Point"}
}