{
  "type": "Feature",
  "properties": {
    "addr:full":"201 A Linwood Ave Linwood  Christchurch Canterbury",
    "addr:housenumber":"201 a",
    "addr:street":"Linwood Ave",
    "iso:country":"NZ",
    "sg:address":"201 A Linwood Ave Linwood ",
    "sg:city":"Christchurch",
    "sg:orig_category":"Health And Beauty: Dental: Dentists",
    "sg:phone":"+64 3-389 6023",
    "sg:province":"Canterbury",
    "wof:name":"Foreman M P BDS",
    "wof:placetype":"venue"
},
  "geometry": {"coordinates":[172.67146299999999,-43.532227],"type":"Point"}
}