{
  "type": "Feature",
  "properties": {
    "iso:country":"NZ",
    "sg:address":"Shop 2, Churchill Drive Shopping Centre Crofton Downs",
    "sg:city":"Wellington",
    "sg:classifiers":[
        {
            "category":"Communications",
            "subcategory":"Film & Video Production",
            "type":"Services"
        }
    ],
    "sg:phone":"+64 4-939 1222",
    "sg:province":"Wellington",
    "sg:tags":[
        "sport",
        "leisure",
        "library",
        "entertainment"
    ],
    "wof:name":"Video Time",
    "wof:placetype":"venue"
},
  "geometry": {"coordinates":[174.763229,-41.262447],"type":"Point"}
}