{
  "type": "Feature",
  "properties": {
    "addr:full":"67 Mansfield Ave  Christchurch Canterbury",
    "addr:housenumber":"67",
    "addr:street":"Mansfield Ave",
    "iso:country":"NZ",
    "sg:address":"67 Mansfield Ave ",
    "sg:city":"Christchurch",
    "sg:classifiers":[
        {
            "category":"Social Services",
            "subcategory":"Retirement Home",
            "type":"Services"
        }
    ],
    "sg:phone":"+64 3-355 7745",
    "sg:province":"Canterbury",
    "sg:tags":[
        "elderly",
        "convalescent",
        "garden",
        "rest",
        "care"
    ],
    "wof:name":"Allenvale Rest Home",
    "wof:placetype":"venue"
},
  "geometry": {"coordinates":[-76.537834,37.605659],"type":"Point"}
}