{
  "type": "Feature",
  "properties": {
    "iso:country":"NZ",
    "sg:address":"6 Hill St ",
    "sg:city":"Hamilton",
    "sg:classifiers":[
        {
            "category":"Banks & Credit Unions",
            "subcategory":"Investment Brokerage",
            "type":"Services"
        }
    ],
    "sg:phone":"+64 7-839 2171",
    "sg:province":"Waikato",
    "sg:tags":[
        "personal",
        "accountant",
        "chartered",
        "-",
        "finance"
    ],
    "wof:name":"Hemi Edwards Bartels Ltd",
    "wof:placetype":"venue"
},
  "geometry": {"coordinates":[-74.760223,40.21104],"type":"Point"}
}