{
  "type": "Feature",
  "properties": {
    "addr:full":"20 A Rockfield Rd Penrose  Auckland Auckland",
    "addr:housenumber":"20 a",
    "addr:street":"Rockfield Rd",
    "iso:country":"NZ",
    "sg:address":"20 A Rockfield Rd Penrose ",
    "sg:city":"Auckland",
    "sg:classifiers":[
        {
            "category":"Education",
            "subcategory":"University",
            "type":"Public Place"
        }
    ],
    "sg:phone":"+64 9-579 3247",
    "sg:province":"Auckland",
    "sg:tags":[
        "training",
        "adult"
    ],
    "wof:name":"Community Education & Evening Classes",
    "wof:placetype":"venue"
},
  "geometry": {"coordinates":[174.804428,-36.903782],"type":"Point"}
}