{
  "type": "Feature",
  "properties": {
    "addr:full":"121 Rosedale Rd Albany  Auckland Auckland",
    "addr:housenumber":"121",
    "addr:street":"Rosedale Rd",
    "iso:country":"NZ",
    "sg:address":"121 Rosedale Rd Albany ",
    "sg:city":"Auckland",
    "sg:orig_category":"Shopping: Sports Retailers: Water Sports: Personal Watercraft",
    "sg:phone":"+64 9-478 9910",
    "sg:province":"Auckland",
    "wof:name":"Spec Watercraft & ATVs",
    "wof:placetype":"venue"
},
  "geometry": {"coordinates":[174.723679,-36.736992],"type":"Point"}
}