{
  "type": "Feature",
  "properties": {
    "addr:full":"Level 9 49 Boulcott St  Wellington Wellington",
    "addr:housenumber":"level;49",
    "addr:street":"9;St",
    "iso:country":"NZ",
    "sg:address":"Level 9 49 Boulcott St ",
    "sg:city":"Wellington",
    "sg:classifiers":[
        {
            "category":"Travel",
            "subcategory":"Travel Agent",
            "type":"Entertainment"
        }
    ],
    "sg:phone":"+64 4-472 4292",
    "sg:province":"Wellington",
    "sg:tags":[
        "tourism",
        "broker"
    ],
    "sg:website":"http://www.networktravel.co.nz",
    "wof:name":"Network Travel Limited",
    "wof:placetype":"venue"
},
  "geometry": {"coordinates":[174.92288199999999,-41.202381],"type":"Point"}
}