{
  "type": "Feature",
  "properties": {
    "addr:full":"913 Gordon Rd  Hastings Hawke's Bay",
    "addr:housenumber":"913",
    "addr:street":"Gordon Rd",
    "iso:country":"NZ",
    "sg:address":"913 Gordon Rd ",
    "sg:city":"Hastings",
    "sg:orig_category":"Shopping: Retail Stores: Lotto Outlets",
    "sg:phone":"+64 6-878 9789",
    "sg:province":"Hawke's Bay",
    "wof:name":"Raureka Lotto Superette",
    "wof:placetype":"venue"
},
  "geometry": {"coordinates":[-81.508163,29.711214],"type":"Point"}
}