{
  "type": "Feature",
  "properties": {
    "addr:full":"6 Maidstone St Grey Lynn  Auckland Auckland",
    "addr:housenumber":"6",
    "addr:street":"Maidstone St",
    "iso:country":"NZ",
    "sg:address":"6 Maidstone St Grey Lynn ",
    "sg:city":"Auckland",
    "sg:orig_category":"Shopping: Accessories: Sunglasses",
    "sg:phone":"+64 9-378 8593",
    "sg:province":"Auckland",
    "wof:name":"Safab No 12 Ltd",
    "wof:placetype":"venue"
},
  "geometry": {"coordinates":[174.75112899999999,-36.86026],"type":"Point"}
}