{
  "type": "Feature",
  "properties": {
    "iso:country":"NZ",
    "sg:address":"211 Totara St Mt ",
    "sg:city":"Maunganui",
    "sg:classifiers":[
        {
            "category":"Banks & Credit Unions",
            "subcategory":"Investment Brokerage",
            "type":"Services"
        }
    ],
    "sg:phone":"+64 7-575 7089",
    "sg:province":"Auckland",
    "sg:tags":[
        "chemical",
        "industrial",
        "-",
        "compounds"
    ],
    "wof:name":"Eka Chemicals (N.Z) Limited",
    "wof:placetype":"venue"
},
  "geometry": {"coordinates":[176.187073,-37.6502],"type":"Point"}
}