{
  "type": "Feature",
  "properties": {
    "iso:country":"NZ",
    "sg:address":"Wellington ",
    "sg:city":"Masterton",
    "sg:classifiers":[
        {
            "category":"Travel",
            "subcategory":"Bed & Breakfast",
            "type":"Entertainment"
        }
    ],
    "sg:phone":"+64 800 666 355",
    "sg:province":"Wellington",
    "sg:tags":[
        "tourism"
    ],
    "sg:website":"http://www.yellowpages.co.nz/for/waicoach/dp56983.html",
    "wof:name":"Wairarapa Coachlines & Limousines",
    "wof:placetype":"venue"
},
  "geometry": {"coordinates":[175.657333,-40.94931],"type":"Point"}
}