{
  "type": "Feature",
  "properties": {
    "iso:country":"NZ",
    "sg:address":"467 Johns Rd Harewood ",
    "sg:city":"Christchurch",
    "sg:orig_category":"Industrial: Packaging: Pallet Racking",
    "sg:phone":"+64 3-359 6395",
    "sg:province":"Canterbury",
    "wof:name":"Fred Edwards Engineering Ltd",
    "wof:placetype":"venue"
},
  "geometry": {"coordinates":[172.586243,-43.461521],"type":"Point"}
}