{
  "type": "Feature",
  "properties": {
    "addr:full":"627 Glenfield Rd Glenfield  Auckland Auckland",
    "addr:housenumber":"627",
    "addr:street":"Glenfield Rd",
    "iso:country":"NZ",
    "sg:address":"627 Glenfield Rd Glenfield ",
    "sg:city":"Auckland",
    "sg:orig_category":"Shopping: Engravers",
    "sg:phone":"+64 9-444 8704",
    "sg:province":"Auckland",
    "wof:name":"Alpha Engraving",
    "wof:placetype":"venue"
},
  "geometry": {"coordinates":[174.721924,-36.76973],"type":"Point"}
}