{
  "type": "Feature",
  "properties": {
    "addr:full":"36 Taylors Rd Morningside  Auckland Auckland",
    "addr:housenumber":"36",
    "addr:street":"Taylors Rd",
    "iso:country":"NZ",
    "sg:address":"36 Taylors Rd Morningside ",
    "sg:city":"Auckland",
    "sg:orig_category":"Shopping: Retail Stores: Department Stores",
    "sg:phone":"+64 9-815 3727",
    "sg:province":"Auckland",
    "wof:name":"Briscoes Homewares",
    "wof:placetype":"venue"
},
  "geometry": {"coordinates":[174.732834,-36.878319],"type":"Point"}
}