{
  "type": "Feature",
  "properties": {
    "addr:full":"27 Miramar Ave Miramar  Wellington Wellington",
    "addr:housenumber":"27",
    "addr:street":"Miramar Ave",
    "iso:country":"NZ",
    "sg:address":"27 Miramar Ave Miramar ",
    "sg:city":"Wellington",
    "sg:orig_category":"Automotive: General Services: Service Stations",
    "sg:phone":"+64 4-388 9753",
    "sg:province":"Wellington",
    "wof:name":"Shell Miramar Circle K",
    "wof:placetype":"venue"
},
  "geometry": {"coordinates":[174.81395000000001,-41.315178],"type":"Point"}
}