{
  "type": "Feature",
  "properties": {
    "addr:full":"383 Childers Rd  Gisborne Gisborne",
    "addr:housenumber":"383",
    "addr:street":"Childers Rd",
    "iso:country":"NZ",
    "sg:address":"383 Childers Rd ",
    "sg:city":"Gisborne",
    "sg:orig_category":"Automotive: Parts And Supplies: Windscreens",
    "sg:phone":"+64 6-867 9862",
    "sg:province":"Gisborne",
    "wof:name":"Gisborne Glass",
    "wof:placetype":"venue"
},
  "geometry": {"coordinates":[178.01637299999999,-38.661922],"type":"Point"}
}