{
  "type": "Feature",
  "properties": {
    "iso:country":"NZ",
    "sg:address":"26 Ireland Rd Panmure ",
    "sg:city":"Auckland",
    "sg:classifiers":[
        {
            "category":"Shopping",
            "subcategory":"Pets & Pet Supplies",
            "type":"Retail Goods"
        }
    ],
    "sg:phone":"+64 9-527 2884",
    "sg:province":"Auckland",
    "sg:tags":[
        "home",
        "grooming",
        "garden",
        "pets"
    ],
    "wof:name":"Dog Tub Ltd",
    "wof:placetype":"venue"
},
  "geometry": {"coordinates":[174.849335,-36.90023],"type":"Point"}
}