{
  "type": "Feature",
  "properties": {
    "iso:country":"NZ",
    "sg:address":"340 Church St Penrose ",
    "sg:city":"Auckland",
    "sg:classifiers":[
        {
            "category":"Retail",
            "subcategory":"Auto Repair",
            "type":"Services"
        }
    ],
    "sg:phone":"+64 9-579 4666",
    "sg:province":"Auckland",
    "sg:tags":[
        "clutch",
        "brake",
        "servicing",
        "automotive"
    ],
    "wof:name":"Just Brakes",
    "wof:placetype":"venue"
},
  "geometry": {"coordinates":[174.81102,-36.920246],"type":"Point"}
}