{
  "type": "Feature",
  "properties": {
    "iso:country":"NZ",
    "sg:address":"1 Lancaster St Waltham ",
    "sg:city":"Christchurch",
    "sg:orig_category":"Clothing And Fabric: Fabric: Textiles",
    "sg:phone":"+64 3-366 1669",
    "sg:province":"Canterbury",
    "wof:name":"Notions Fabrics",
    "wof:placetype":"venue"
},
  "geometry": {"coordinates":[172.6543121338,-43.540977478],"type":"Point"}
}