{
  "type": "Feature",
  "properties": {
    "iso:country":"NZ",
    "sg:address":"31 Aintree Ave Mangere ",
    "sg:city":"Auckland",
    "sg:orig_category":"Transport: Transportation: Freight",
    "sg:phone":"+64 9-275 3223",
    "sg:province":"Auckland",
    "wof:name":"SDV New Zealand",
    "wof:placetype":"venue"
},
  "geometry": {"coordinates":[174.77681,-36.975304],"type":"Point"}
}