{
  "type": "Feature",
  "properties": {
    "addr:full":"444 Papanui Rd Papanui  Christchurch Canterbury",
    "addr:housenumber":"444",
    "addr:street":"Papanui Rd",
    "iso:country":"NZ",
    "sg:address":"444 Papanui Rd Papanui ",
    "sg:city":"Christchurch",
    "sg:orig_category":"Health And Beauty: Specialists: Osteopaths",
    "sg:phone":"+64 3-352 6691",
    "sg:province":"Canterbury",
    "wof:name":"Marshall Anudharma",
    "wof:placetype":"venue"
},
  "geometry": {"coordinates":[172.61058,-43.499851],"type":"Point"}
}