{
  "type": "Feature",
  "properties": {
    "addr:full":"68 Pembroke St  Hamilton Waikato",
    "addr:housenumber":"68",
    "addr:street":"Pembroke St",
    "iso:country":"NZ",
    "sg:address":"68 Pembroke St ",
    "sg:city":"Hamilton",
    "sg:orig_category":"Automotive: General Services: Service Stations",
    "sg:phone":"+64 7-838 9108",
    "sg:province":"Waikato",
    "wof:name":"Shell Pembroke",
    "wof:placetype":"venue"
},
  "geometry": {"coordinates":[-79.79843099999999,43.195255],"type":"Point"}
}