{
  "type": "Feature",
  "properties": {
    "addr:full":"Westhaven Marina Westhaven Dve Westhaven  Auckland Auckland",
    "addr:street":"Westhaven Marina Westhaven Dve",
    "iso:country":"NZ",
    "sg:address":"Westhaven Marina Westhaven Dve Westhaven ",
    "sg:city":"Auckland",
    "sg:classifiers":[
        {
            "category":"Restaurant",
            "type":"Food & Drink"
        }
    ],
    "sg:phone":"+64 9-378 9890",
    "sg:province":"Auckland",
    "sg:tags":[
        "wining",
        "dining"
    ],
    "sg:website":"http://www.sailsrestaurant.co.nz",
    "wof:name":"Sails Restaurant",
    "wof:placetype":"venue"
},
  "geometry": {"coordinates":[174.754456,-36.841389],"type":"Point"}
}