{
  "type": "Feature",
  "properties": {
    "iso:country":"NZ",
    "sg:address":"84 Constable St Newtown ",
    "sg:city":"Wellington",
    "sg:classifiers":[
        {
            "category":"Shopping",
            "subcategory":"Crafts & Fabrics",
            "type":"Retail Goods"
        }
    ],
    "sg:phone":"+64 4-939 2225",
    "sg:province":"Wellington",
    "sg:tags":[
        "clothing",
        "maternity",
        "wear"
    ],
    "wof:name":"Babystar New & Preloved",
    "wof:placetype":"venue"
},
  "geometry": {"coordinates":[174.784836,-41.313023],"type":"Point"}
}