{
  "type": "Feature",
  "properties": {
    "iso:country":"NZ",
    "sg:address":"32 Hamilton Dve Lake ",
    "sg:city":"Tekapo",
    "sg:classifiers":[
        {
            "category":"Travel",
            "subcategory":"Bed & Breakfast",
            "type":"Entertainment"
        }
    ],
    "sg:phone":"+64 3-680 6910",
    "sg:tags":[
        "tourism",
        "accommodation"
    ],
    "wof:name":"Lake Tekapo Grand View",
    "wof:placetype":"venue"
},
  "geometry": {"coordinates":[170.48288,-44.00576],"type":"Point"}
}