{
  "type": "Feature",
  "properties": {
    "addr:full":"45 Ruahine St Palmerston  Palmerston North Manawatu-Wanganui",
    "addr:housenumber":"45",
    "addr:street":"Ruahine St Palmerston",
    "iso:country":"NZ",
    "sg:address":"45 Ruahine St Palmerston ",
    "sg:city":"Palmerston North",
    "sg:classifiers":[
        {
            "category":"Travel",
            "subcategory":"Hotels & Motels",
            "type":"Entertainment"
        }
    ],
    "sg:phone":"+64 6-355 8855",
    "sg:province":"Manawatu-Wanganui",
    "sg:tags":[
        "lodge",
        "tourism",
        "accommodation"
    ],
    "sg:website":"http://www.yellowpages.co.nz/for/carramar/dp21461.html",
    "wof:name":"Carramar Motor Inn",
    "wof:placetype":"venue"
},
  "geometry": {"coordinates":[175.62084999999999,-40.337803],"type":"Point"}
}