{
  "type": "Feature",
  "properties": {
    "addr:full":"11 Jellicoe Ave Stoke  Nelson Nelson",
    "addr:housenumber":"11",
    "addr:street":"Jellicoe Ave",
    "iso:country":"NZ",
    "sg:address":"11 Jellicoe Ave Stoke ",
    "sg:city":"Nelson",
    "sg:classifiers":[
        {
            "category":"Building & Trades",
            "subcategory":"Plumbing",
            "type":"Services"
        }
    ],
    "sg:phone":"+64 3-547 6353",
    "sg:province":"Nelson",
    "sg:tags":[
        "home",
        "plumber",
        "garden",
        "related"
    ],
    "wof:name":"Roger Taylor",
    "wof:placetype":"venue"
},
  "geometry": {"coordinates":[173.23419200000001,-41.312859],"type":"Point"}
}