{
  "type": "Feature",
  "properties": {
    "iso:country":"NZ",
    "sg:address":"191 Albert St Palmerston ",
    "sg:city":"Palmerston North",
    "sg:orig_category":"Automotive: Servicing And Repair: Car Trimming/Upholstery",
    "sg:phone":"+64 6-357 9098",
    "sg:province":"Manawatu-Wanganui",
    "wof:name":"Len Shailer Ltd",
    "wof:placetype":"venue"
},
  "geometry": {"coordinates":[175.628082,-40.355038],"type":"Point"}
}