{
  "type": "Feature",
  "properties": {
    "iso:country":"NZ",
    "sg:address":"10 b George Bourke Dve Mt Wellington ",
    "sg:city":"Auckland",
    "sg:orig_category":"Clothing And Fabric: Clothing: Uniforms",
    "sg:phone":"+64 9-270 3015",
    "sg:province":"Auckland",
    "wof:name":"Career Fashion Ltd",
    "wof:placetype":"venue"
},
  "geometry": {"coordinates":[174.844543,-36.925552],"type":"Point"}
}