{
  "type": "Feature",
  "properties": {
    "iso:country":"NZ",
    "sg:address":"PO Box 2010 ",
    "sg:city":"Masterton",
    "sg:classifiers":[
        {
            "category":"Bus Charters",
            "type":"Transportation"
        }
    ],
    "sg:phone":"+64 25916971",
    "sg:province":"Wellington",
    "sg:tags":[
        "services",
        "travel",
        "tourism"
    ],
    "wof:name":"Wairarapa Coachlines & Limousines",
    "wof:placetype":"venue"
},
  "geometry": {"coordinates":[175.657333,-40.94931],"type":"Point"}
}