{
  "type": "Feature",
  "properties": {
    "iso:country":"NZ",
    "sg:address":"14 Laery St Lower ",
    "sg:city":"Hutt",
    "sg:classifiers":[
        {
            "category":"Autos & Motor Vehicles",
            "subcategory":"Automobile Sales",
            "type":"Retail Goods"
        }
    ],
    "sg:phone":"+64 4-568 3153",
    "sg:province":"Wellington",
    "sg:tags":[
        "car",
        "importer",
        "leasing",
        "automotive"
    ],
    "wof:name":"Lada NZ Ltd",
    "wof:placetype":"venue"
},
  "geometry": {"coordinates":[174.904526,-41.208431],"type":"Point"}
}