{
  "type": "Feature",
  "properties": {
    "iso:country":"NZ",
    "sg:address":"22 Kalmia St Ellerslie ",
    "sg:city":"Auckland",
    "sg:orig_category":"Shopping: Accessories: Sunglasses",
    "sg:phone":"+64 9-525 6601",
    "sg:province":"Auckland",
    "sg:website":"http://www.dirtydog.co.nz",
    "wof:name":"Vision Marketing & Distribution Ltd (VMD)",
    "wof:placetype":"venue"
},
  "geometry": {"coordinates":[174.807098,-36.897945],"type":"Point"}
}