{
  "type": "Feature",
  "properties": {
    "iso:country":"NZ",
    "sg:address":"258 Peachgrove Rd ",
    "sg:city":"Hamilton",
    "sg:orig_category":"Shopping: Retail Stores: Stationery",
    "sg:phone":"+64 7-855 6768",
    "sg:province":"Waikato",
    "wof:name":"Five Cross Roads Lotto",
    "wof:placetype":"venue"
},
  "geometry": {"coordinates":[-87.988968,34.142426],"type":"Point"}
}