{
  "type": "Feature",
  "properties": {
    "addr:full":"95A Beresford St Bayswater  Auckland Auckland",
    "addr:housenumber":"95a",
    "addr:street":"Beresford St",
    "iso:country":"NZ",
    "sg:address":"95A Beresford St Bayswater ",
    "sg:city":"Auckland",
    "sg:orig_category":"Health And Beauty: Specialists: Osteopaths",
    "sg:phone":"+64 9-445 4460",
    "sg:province":"Auckland",
    "wof:name":"Heather Munro Dr",
    "wof:placetype":"venue"
},
  "geometry": {"coordinates":[174.77806100000001,-36.812557],"type":"Point"}
}