{
  "type": "Feature",
  "properties": {
    "addr:full":"580 B Gt North Rd Grey Lynn  Auckland Auckland",
    "addr:housenumber":"580 b",
    "addr:street":"Gt North Rd",
    "iso:country":"NZ",
    "sg:address":"580 B Gt North Rd Grey Lynn ",
    "sg:city":"Auckland",
    "sg:orig_category":"Health And Beauty: Products: Pharmacies",
    "sg:phone":"+64 9-360 1159",
    "sg:province":"Auckland",
    "wof:name":"West City Pharmacy (Grey Lynn) Ltd",
    "wof:placetype":"venue"
},
  "geometry": {"coordinates":[174.73739599999999,-36.865345],"type":"Point"}
}