{
  "type": "Feature",
  "properties": {
    "iso:country":"NZ",
    "sg:address":"334 Church St Te Papapa ",
    "sg:city":"Auckland",
    "sg:orig_category":"Home And Garden: Gardening: Products: Lawnmowers",
    "sg:phone":"+64 9-636 6542",
    "sg:province":"Auckland",
    "wof:name":"Mower & Machinery Ltd",
    "wof:placetype":"venue"
},
  "geometry": {"coordinates":[174.806198,-36.920898],"type":"Point"}
}