{
  "type": "Feature",
  "properties": {
    "addr:full":"11 A Tanya St Bromley  Christchurch Canterbury",
    "addr:housenumber":"11",
    "addr:street":"A Tanya St;Christchurch",
    "iso:country":"NZ",
    "sg:address":"11 A Tanya St Bromley ",
    "sg:city":"Christchurch",
    "sg:orig_category":"Industrial: Abrasives: Abrasive Blasting",
    "sg:phone":"+64 3-384 4180",
    "sg:province":"Canterbury",
    "wof:name":"Jennens Painting & Marine Coatings (Chch) Ltd",
    "wof:placetype":"venue"
},
  "geometry": {"coordinates":[172.696808,-43.538284],"type":"Point"}
}