{
  "type": "Feature",
  "properties": {
    "iso:country":"NZ",
    "sg:address":"135 Taonui St Palmerston ",
    "sg:city":"Palmerston North",
    "sg:classifiers":[
        {
            "category":"Sports & Exercise",
            "subcategory":"Tennis Court",
            "type":"Entertainment"
        }
    ],
    "sg:phone":"+64 6-356 0017",
    "sg:province":"Manawatu-Wanganui",
    "sg:tags":[
        "escort",
        "agency",
        "adult",
        "leisure"
    ],
    "wof:name":"The Lounge Bar",
    "wof:placetype":"venue"
},
  "geometry": {"coordinates":[175.60817,-40.355034],"type":"Point"}
}