{
  "type": "Feature",
  "properties": {
    "iso:country":"NZ",
    "sg:address":"5-6/435 Gt South Rd Otahuhu ",
    "sg:city":"Auckland",
    "sg:classifiers":[
        {
            "category":"Shopping",
            "subcategory":"Bridal",
            "type":"Retail Goods"
        }
    ],
    "sg:phone":"+64 9-276 8815",
    "sg:province":"Auckland",
    "sg:tags":[
        "arrangements",
        "wear",
        "wedding"
    ],
    "wof:name":"Silver Bird Bridal Wear",
    "wof:placetype":"venue"
},
  "geometry": {"coordinates":[174.836273,-36.936203],"type":"Point"}
}