{
  "type": "Feature",
  "properties": {
    "iso:country":"NZ",
    "sg:address":"Evans Bay ",
    "sg:city":"Wellington",
    "sg:classifiers":[
        {
            "category":"Farming",
            "subcategory":"Fish & Marine Products",
            "type":"Manufacturing & Wholesale Goods"
        }
    ],
    "sg:phone":"+64 4-386 3278",
    "sg:province":"Wellington",
    "sg:tags":[
        "-",
        "boat",
        "transport"
    ],
    "wof:name":"Totally Marine Ltd",
    "wof:placetype":"venue"
},
  "geometry": {"coordinates":[174.79690600000001,-41.312599],"type":"Point"}
}