{
  "type": "Feature",
  "properties": {
    "addr:full":"Percival St  Rangiora Canterbury",
    "addr:street":"Percival St",
    "iso:country":"NZ",
    "sg:address":"Percival St ",
    "sg:city":"Rangiora",
    "sg:classifiers":[
        {
            "category":"Shopping",
            "subcategory":"Clothing, Apparel, & Fashions",
            "type":"Retail Goods"
        }
    ],
    "sg:phone":"+64 3-313 5772",
    "sg:province":"Canterbury",
    "sg:tags":[
        "knitted",
        "clothing",
        "fabric"
    ],
    "wof:name":"Kotare Knitwear",
    "wof:placetype":"venue"
},
  "geometry": {"coordinates":[172.59626800000001,-43.312828],"type":"Point"}
}