{
  "type": "Feature",
  "properties": {
    "addr:full":"45 McKinnon Lop Te  Anau Southland",
    "addr:housenumber":"45;lop",
    "addr:street":"Mckinnon",
    "iso:country":"NZ",
    "sg:address":"45 McKinnon Lop Te ",
    "sg:city":"Anau",
    "sg:orig_category":"Transport",
    "sg:phone":"+64 3-249 7373",
    "sg:province":"Southland",
    "sg:website":"http://www.yellowpages.co.nz/for/fiordlandsail/dp51243.html",
    "wof:name":"Fiordland Sail Ltd",
    "wof:placetype":"venue"
},
  "geometry": {"coordinates":[167.71940599999999,-45.416828],"type":"Point"}
}