{
  "type": "Feature",
  "properties": {
    "iso:country":"NZ",
    "sg:address":"279 Parnell Rd Parnell ",
    "sg:city":"Auckland",
    "sg:orig_category":"Clothing And Fabric: Fabric: Drapers",
    "sg:phone":"+64 9-377 4068",
    "sg:province":"Auckland",
    "wof:name":"Courtyard Collections",
    "wof:placetype":"venue"
},
  "geometry": {"coordinates":[174.780991,-36.856529],"type":"Point"}
}