{
  "type": "Feature",
  "properties": {
    "addr:full":"Waikawa Marina  Picton Marlborough",
    "addr:street":"Waikawa Marina",
    "iso:country":"NZ",
    "sg:address":"Waikawa Marina ",
    "sg:city":"Picton",
    "sg:classifiers":[
        {
            "category":"Personal",
            "type":"Services"
        }
    ],
    "sg:phone":"+64 3-573 6798",
    "sg:province":"Marlborough",
    "sg:tags":[
        "arrangements",
        "wedding"
    ],
    "wof:name":"Waikawa Boating Club (Inc)",
    "wof:placetype":"venue"
},
  "geometry": {"coordinates":[174.00427199999999,-41.294788],"type":"Point"}
}