{
  "type": "Feature",
  "properties": {
    "addr:full":"55 Ridgway St  Wanganui Manawatu-Wanganui",
    "addr:housenumber":"55",
    "addr:street":"Ridgway St",
    "iso:country":"NZ",
    "sg:address":"55 Ridgway St ",
    "sg:city":"Wanganui",
    "sg:classifiers":[
        {
            "category":"Shopping",
            "subcategory":"Gifts & Souvenirs",
            "type":"Retail Goods"
        }
    ],
    "sg:phone":"+64 6-345 3067",
    "sg:province":"Manawatu-Wanganui",
    "sg:tags":[
        "trophy",
        "award"
    ],
    "wof:name":"Timms Hand Engraving",
    "wof:placetype":"venue"
},
  "geometry": {"coordinates":[175.05372600000001,-39.934326],"type":"Point"}
}