{
  "type": "Feature",
  "properties": {
    "addr:full":"Mercedes-Benz 74 Cambridge Tce  Wellington Wellington",
    "addr:housenumber":"74",
    "addr:street":"Cambridge Tce",
    "iso:country":"NZ",
    "sg:address":"Mercedes-Benz 74 Cambridge Tce ",
    "sg:city":"Wellington",
    "sg:classifiers":[
        {
            "category":"Autos & Motor Vehicles",
            "subcategory":"Automobile Sales",
            "type":"Retail Goods"
        }
    ],
    "sg:phone":"+64 4-384 8779",
    "sg:province":"Wellington",
    "sg:tags":[
        "car",
        "-used",
        "leasing",
        "truck",
        "automotive"
    ],
    "sg:website":"http://www.teameuropean.co.nz",
    "wof:name":"Team European Ltd L.M.V.D",
    "wof:placetype":"venue"
},
  "geometry": {"coordinates":[-64.680969,46.428822],"type":"Point"}
}