{
  "type": "Feature",
  "properties": {
    "iso:country":"NZ",
    "sg:address":"115 Jackson St Petone ",
    "sg:city":"Wellington",
    "sg:classifiers":[
        {
            "category":"Communications",
            "subcategory":"Film & Video Production",
            "type":"Services"
        }
    ],
    "sg:phone":"+64 4-939 2772",
    "sg:province":"Wellington",
    "sg:tags":[
        "sport",
        "leisure",
        "library",
        "entertainment"
    ],
    "wof:name":"Aspac Music & Video",
    "wof:placetype":"venue"
},
  "geometry": {"coordinates":[174.875626,-41.224335],"type":"Point"}
}