{
  "type": "Feature",
  "properties": {
    "addr:full":"10 Clarence St Hillmorton  Christchurch Canterbury",
    "addr:housenumber":"10",
    "addr:street":"Clarence St",
    "iso:country":"NZ",
    "sg:address":"10 Clarence St Hillmorton ",
    "sg:city":"Christchurch",
    "sg:orig_category":"Industrial: Coatings",
    "sg:phone":"+64 3-338 6211",
    "sg:province":"Canterbury",
    "wof:name":"Jeff Dermott Ltd",
    "wof:placetype":"venue"
},
  "geometry": {"coordinates":[172.58696,-43.55862],"type":"Point"}
}