{
  "type": "Feature",
  "properties": {
    "addr:full":"Stone Store Hill 190 Kerikeri Rd  Kerikeri Northland",
    "addr:housenumber":"190",
    "addr:street":"Kerikeri Rd",
    "iso:country":"NZ",
    "sg:address":"Stone Store Hill 190 Kerikeri Rd ",
    "sg:city":"Kerikeri",
    "sg:classifiers":[
        {
            "category":"Education",
            "subcategory":"Special Training",
            "type":"Public Place"
        }
    ],
    "sg:phone":"+64 9-407 8933",
    "sg:province":"Northland",
    "sg:website":"http://www.sub-tropicals.co.nz",
    "wof:name":"Wharepuke Subtropical Gardens & Nursery",
    "wof:placetype":"venue"
},
  "geometry": {"coordinates":[173.949905,-35.226269],"type":"Point"}
}