{
  "type": "Feature",
  "properties": {
    "iso:country":"NZ",
    "sg:address":"16 Cowley Dve ",
    "sg:city":"Cambridge",
    "sg:orig_category":"Health And Beauty: Specialists: Midwives",
    "sg:phone":"+64 7-823 3375",
    "sg:province":"Waikato",
    "wof:name":"Mother & Baby",
    "wof:placetype":"venue"
},
  "geometry": {"coordinates":[-116.676048,44.572186],"type":"Point"}
}