{
  "type": "Feature",
  "properties": {
    "iso:country":"NZ",
    "sg:address":"Camp Rd Linton RD ",
    "sg:city":"4",
    "sg:classifiers":[
        {
            "category":"Shopping",
            "subcategory":"Pets & Pet Supplies",
            "type":"Retail Goods"
        }
    ],
    "sg:phone":"+64 6-325 8563",
    "sg:tags":[
        "boarding",
        "garden",
        "pets",
        "catteries",
        "home",
        "kennel"
    ],
    "wof:name":"Cats No Dogs",
    "wof:placetype":"venue"
},
  "geometry": {"coordinates":[-2.574709,51.913834],"type":"Point"}
}