{
  "type": "Feature",
  "properties": {
    "iso:country":"NZ",
    "sg:address":"Evans Flat R D 1 ",
    "sg:city":"Lawrence",
    "sg:classifiers":[
        {
            "category":"Retail",
            "subcategory":"Laundry & Dry Cleaning",
            "type":"Services"
        }
    ],
    "sg:phone":"+64 3-485 9410",
    "sg:tags":[
        "product",
        "wool",
        "clothing",
        "fabric"
    ],
    "wof:name":"Evans Flat Wool Dag , Skin & Pet Food Abattoir",
    "wof:placetype":"venue"
},
  "geometry": {"coordinates":[169.6852722168,-45.9171447754],"type":"Point"}
}