{
  "type": "Feature",
  "properties": {
    "iso:country":"NZ",
    "sg:address":"P O Box ",
    "sg:city":"2439",
    "sg:classifiers":[
        {
            "category":"Health Services",
            "subcategory":"Medical Lab",
            "type":"Services"
        }
    ],
    "sg:phone":"+64 800 111 238",
    "sg:tags":[
        "alarm",
        "products",
        "beauty"
    ],
    "wof:name":"ADT RESIDENTIAL",
    "wof:placetype":"venue"
},
  "geometry": {"coordinates":[152.630264,-31.624559],"type":"Point"}
}