{
  "type": "Feature",
  "properties": {
    "addr:full":"1024 A Pakowhai Rd  Hastings Hawke's Bay",
    "addr:housenumber":"1024 a",
    "addr:street":"Pakowhai Rd",
    "iso:country":"NZ",
    "sg:address":"1024 A Pakowhai Rd ",
    "sg:city":"Hastings",
    "sg:classifiers":[
        {
            "category":"Winery",
            "type":"Food & Drink"
        }
    ],
    "sg:phone":"+64 6-873 2000",
    "sg:province":"Hawke's Bay",
    "sg:tags":[
        "wining",
        "vineyard",
        "dining"
    ],
    "wof:name":"Hettinga Estate Winery & Restaurant",
    "wof:placetype":"venue"
},
  "geometry": {"coordinates":[176.84582499999999,-39.620239],"type":"Point"}
}