{
  "type": "Feature",
  "properties": {
    "iso:country":"NZ",
    "sg:address":"Albany Street Centre 28 Albany St ",
    "sg:city":"Dunedin",
    "sg:classifiers":[
        {
            "category":"Insurance",
            "subcategory":"Health Insurance",
            "type":"Services"
        }
    ],
    "sg:phone":"+64 3-479 2169",
    "sg:province":"Southland",
    "sg:tags":[
        "mental",
        "beauty"
    ],
    "wof:name":"Carolyne Smith 'Positive Change'",
    "wof:placetype":"venue"
},
  "geometry": {"coordinates":[-82.784721,28.013355],"type":"Point"}
}