{
  "type": "Feature",
  "properties": {
    "addr:full":"Waikanae Main Rd Waikanae",
    "addr:street":"Main Rd",
    "iso:country":"NZ",
    "sg:address":"Waikanae Main Rd",
    "sg:city":"Waikanae",
    "sg:classifiers":[
        {
            "category":"Banks & Credit Unions",
            "subcategory":"Bank",
            "type":"Services"
        }
    ],
    "sg:phone":"+64 5835798",
    "wof:name":"Westpac Banking Corp.",
    "wof:placetype":"venue"
},
  "geometry": {"coordinates":[175.06102000000001,-40.873184],"type":"Point"}
}