{
  "type": "Feature",
  "properties": {
    "addr:full":"Cnr Maraekakaho Rd & Orchard Rd  Hastings Hawke's Bay",
    "addr:street":"Cnr Maraekakaho Rd & Orchard Rd",
    "iso:country":"NZ",
    "sg:address":"Cnr Maraekakaho Rd & Orchard Rd ",
    "sg:city":"Hastings",
    "sg:orig_category":"Farming: Services: Irrigation",
    "sg:phone":"+64 6-873 0950",
    "sg:province":"Hawke's Bay",
    "wof:name":"Fruitfed Supplies",
    "wof:placetype":"venue"
},
  "geometry": {"coordinates":[176.844818,-39.64167],"type":"Point"}
}