{
  "type": "Feature",
  "properties": {
    "iso:country":"NZ",
    "sg:address":"117 Newton St Mt ",
    "sg:city":"Maunganui",
    "sg:classifiers":[
        {
            "category":"Home & Garden",
            "subcategory":"Building Materials",
            "type":"Retail Goods"
        }
    ],
    "sg:phone":"+64 7-575 2850",
    "sg:province":"Auckland",
    "sg:tags":[
        "door",
        "fitting",
        "fittings"
    ],
    "wof:name":"Door Jamb Systems",
    "wof:placetype":"venue"
},
  "geometry": {"coordinates":[176.186279,-37.641048],"type":"Point"}
}