{
  "type": "Feature",
  "properties": {
    "addr:full":"515 Mt Wellington Hwy Penrose  Auckland Auckland",
    "addr:housenumber":"515",
    "addr:street":"Mt Wellington Hwy",
    "iso:country":"NZ",
    "sg:address":"515 Mt Wellington Hwy Penrose ",
    "sg:city":"Auckland",
    "sg:classifiers":[
        {
            "category":"Manufacturing",
            "subcategory":"Textiles",
            "type":"Manufacturing & Wholesale Goods"
        }
    ],
    "sg:phone":"+64 9-573 0688",
    "sg:province":"Auckland",
    "sg:tags":[
        "clothing",
        "fabric",
        "manufacturer"
    ],
    "wof:name":"C-Force Textiles",
    "wof:placetype":"venue"
},
  "geometry": {"coordinates":[174.84007299999999,-36.91938],"type":"Point"}
}