{
  "type": "Feature",
  "properties": {
    "addr:full":"421-429 Church St East Penrose  Auckland Auckland",
    "addr:housenumber":"421-429",
    "addr:street":"Church St",
    "iso:country":"NZ",
    "sg:address":"421-429 Church St East Penrose ",
    "sg:city":"Auckland",
    "sg:orig_category":"Food And Drink: Equipment: Bakers' Supplies",
    "sg:phone":"+64 9-579 6079",
    "sg:province":"Auckland",
    "wof:name":"Bakels",
    "wof:placetype":"venue"
},
  "geometry": {"coordinates":[174.82399000000001,-36.919178],"type":"Point"}
}