{
  "type": "Feature",
  "properties": {
    "addr:full":"21 Banks St  Gisborne Gisborne",
    "addr:housenumber":"21",
    "addr:street":"Banks St",
    "iso:country":"NZ",
    "sg:address":"21 Banks St ",
    "sg:city":"Gisborne",
    "sg:classifiers":[
        {
            "category":"Building & Trades",
            "subcategory":"Cleaning & Sanitation",
            "type":"Services"
        }
    ],
    "sg:phone":"+64 6-867 9550",
    "sg:province":"Gisborne",
    "sg:tags":[
        "equipment",
        "industrial",
        "maintenance"
    ],
    "wof:name":"Bay Trade Supplies",
    "wof:placetype":"venue"
},
  "geometry": {"coordinates":[178.00199900000001,-38.666885],"type":"Point"}
}