{
  "type": "Feature",
  "properties": {
    "addr:full":"78 Park Rd Miramar  Wellington Wellington",
    "addr:housenumber":"78",
    "addr:street":"Park Rd",
    "iso:country":"NZ",
    "sg:address":"78 Park Rd Miramar ",
    "sg:city":"Wellington",
    "sg:classifiers":[
        {
            "category":"Personal",
            "subcategory":"Tanning Parlor",
            "type":"Services"
        }
    ],
    "sg:phone":"+64 4-939 2025",
    "sg:province":"Wellington",
    "sg:tags":[
        "sun",
        "health",
        "beauty"
    ],
    "wof:name":"Babbe Skin Care & Sunbed Clinic",
    "wof:placetype":"venue"
},
  "geometry": {"coordinates":[174.819489,-41.312347],"type":"Point"}
}