{
  "type": "Feature",
  "properties": {
    "addr:full":"170 Hazeldean Rd Addington  Christchurch Canterbury",
    "addr:housenumber":"170",
    "addr:street":"Hazeldean Rd",
    "iso:country":"NZ",
    "sg:address":"170 Hazeldean Rd Addington ",
    "sg:city":"Christchurch",
    "sg:orig_category":"Automotive: Accessories: Towbars",
    "sg:phone":"+64 3-366 8823",
    "sg:province":"Canterbury",
    "wof:name":"East Coast Engineering",
    "wof:placetype":"venue"
},
  "geometry": {"coordinates":[172.626541,-43.541367],"type":"Point"}
}