{
  "type": "Feature",
  "properties": {
    "iso:country":"NZ",
    "sg:address":"300 Lincoln Rd Addington ",
    "sg:city":"Christchurch",
    "sg:classifiers":[
        {
            "category":"Personal",
            "subcategory":"Tanning Parlor",
            "type":"Services"
        }
    ],
    "sg:phone":"+64 3-338 2637",
    "sg:province":"Canterbury",
    "sg:tags":[
        "sun",
        "health",
        "beauty"
    ],
    "wof:name":"Jularky's Hair Studio",
    "wof:placetype":"venue"
},
  "geometry": {"coordinates":[172.611542,-43.543903],"type":"Point"}
}