{
  "type": "Feature",
  "properties": {
    "iso:country":"NZ",
    "sg:address":"1 Barr St ",
    "sg:city":"Balclutha",
    "sg:orig_category":"Automotive: Parts And Supplies: Windscreens",
    "sg:phone":"+64 3-418 0777",
    "wof:name":"Balclutha Windscreens n Glass",
    "wof:placetype":"venue"
},
  "geometry": {"coordinates":[169.735275,-46.240215],"type":"Point"}
}