{
  "type": "Feature",
  "properties": {
    "addr:full":"Main St  Foxton",
    "addr:street":"Main St",
    "iso:country":"NZ",
    "sg:address":"Main St ",
    "sg:city":"Foxton",
    "sg:orig_category":"Shopping: Retail Stores: Books: Bookshops",
    "sg:phone":"+64 6-363 8800",
    "wof:name":"Grays Book Centre, Lotto & Postshop",
    "wof:placetype":"venue"
},
  "geometry": {"coordinates":[-105.30012499999999,39.537884],"type":"Point"}
}