{
  "type": "Feature",
  "properties": {
    "addr:full":"PO Box 44 Beachlands  Auckland Auckland",
    "addr:housenumber":"po box 44",
    "iso:country":"NZ",
    "sg:address":"PO Box 44 Beachlands ",
    "sg:city":"Auckland",
    "sg:classifiers":[
        {
            "category":"Shopping",
            "subcategory":"Gifts & Souvenirs",
            "type":"Retail Goods"
        }
    ],
    "sg:phone":"+64 9-273 8255",
    "sg:province":"Auckland",
    "sg:tags":[
        "travel",
        "tourism"
    ],
    "wof:name":"Pearson & Craig Cosmetics",
    "wof:placetype":"venue"
},
  "geometry": {"coordinates":[175.000336,-36.88517],"type":"Point"}
}