{
  "type": "Feature",
  "properties": {
    "iso:country":"NZ",
    "sg:address":"5 Chicago St ",
    "sg:city":"Alexandra",
    "sg:orig_category":"Industrial: Metal: Products: Aluminium Products",
    "sg:phone":"+64 3-448 6468",
    "sg:province":"Otago",
    "wof:name":"First Aluminium Dunstan Ltd",
    "wof:placetype":"venue"
},
  "geometry": {"coordinates":[-92.438026,31.291],"type":"Point"}
}