{
  "type": "Feature",
  "properties": {
    "iso:country":"NZ",
    "sg:address":"Tekapo Bldg 259 Stafford St ",
    "sg:city":"Timaru",
    "sg:orig_category":"Health And Beauty: Dental: Dentists",
    "sg:phone":"+64 3-688 0033",
    "sg:province":"Canterbury",
    "wof:name":"Phillips Stephen J",
    "wof:placetype":"venue"
},
  "geometry": {"coordinates":[-108.941063,35.021729],"type":"Point"}
}