{
  "type": "Feature",
  "properties": {
    "addr:full":"Pine Dve  Murupara",
    "iso:country":"NZ",
    "sg:address":"Pine Dve ",
    "sg:city":"Murupara",
    "sg:orig_category":"Food And Drink: Meats: Butchers",
    "sg:phone":"+64 7-366 5526",
    "wof:name":"Unsworths Butchery",
    "wof:placetype":"venue"
},
  "geometry": {"coordinates":[176.703857,-38.456059],"type":"Point"}
}