{
  "type": "Feature",
  "properties": {
    "iso:country":"NZ",
    "sg:address":"Donnelly St ",
    "sg:city":"Hastings",
    "sg:classifiers":[
        {
            "category":"Food & Beverages",
            "subcategory":"Liquor & Beverages",
            "type":"Retail Goods"
        }
    ],
    "sg:phone":"+64 6-877 8208",
    "sg:province":"Hawke's Bay",
    "sg:tags":[
        "drink",
        "outlet"
    ],
    "wof:name":"Havelock Wine & Spirits",
    "wof:placetype":"venue"
},
  "geometry": {"coordinates":[-93.014915,44.682709],"type":"Point"}
}