{
  "type": "Feature",
  "properties": {
    "addr:full":"Beach Rd  Thames Waikato",
    "addr:street":"Beach Rd",
    "iso:country":"NZ",
    "sg:address":"Beach Rd ",
    "sg:city":"Thames",
    "sg:orig_category":"Industrial: Metal: Services: Foundries",
    "sg:phone":"+64 800 808 680",
    "sg:province":"Waikato",
    "wof:name":"A & G Price Limited",
    "wof:placetype":"venue"
},
  "geometry": {"coordinates":[-72.112679,41.394623],"type":"Point"}
}