{
  "type": "Feature",
  "properties": {
    "iso:country":"NZ",
    "sg:address":"73 Queen St ",
    "sg:city":"Blenheim",
    "sg:classifiers":[
        {
            "category":"Deli",
            "type":"Food & Drink"
        }
    ],
    "sg:phone":"+64 3-577 8886",
    "sg:province":"Marlborough",
    "sg:tags":[
        "delicatessen",
        "-"
    ],
    "wof:name":"Peppercorns Delicatessen & Cafe",
    "wof:placetype":"venue"
},
  "geometry": {"coordinates":[-74.459564,42.468643],"type":"Point"}
}