{
  "type": "Feature",
  "properties": {
    "addr:full":"209 Rora St Te  Kuiti",
    "addr:housenumber":"209",
    "addr:street":"Rora St",
    "iso:country":"NZ",
    "sg:address":"209 Rora St Te ",
    "sg:city":"Kuiti",
    "sg:classifiers":[
        {
            "category":"Bars & Pubs",
            "subcategory":"Lounge",
            "type":"Food & Drink"
        }
    ],
    "sg:phone":"+64 7-878 8731",
    "sg:tags":[
        "baker",
        "-"
    ],
    "wof:name":"Te Kuiti Bakery",
    "wof:placetype":"venue"
},
  "geometry": {"coordinates":[175.15917999999999,-38.329369],"type":"Point"}
}