{
  "type": "Feature",
  "properties": {
    "iso:country":"NZ",
    "sg:address":"158 Main St Upper ",
    "sg:city":"Hutt",
    "sg:orig_category":"Automotive: General Services: Automobile Associations",
    "sg:phone":"+64 4-528 5679",
    "sg:province":"Wellington",
    "wof:name":"A A Automobile Association",
    "wof:placetype":"venue"
},
  "geometry": {"coordinates":[175.072968,-41.124268],"type":"Point"}
}