{
  "type": "Feature",
  "properties": {
    "iso:country":"NZ",
    "sg:address":"27 Rust Ave ",
    "sg:city":"Whangarei",
    "sg:orig_category":"Industrial: Engineering: Engineers: Engineers - Consulting",
    "sg:phone":"+64 9-434 7808",
    "sg:province":"Northland",
    "wof:name":"Frank Muldowney Ltd",
    "wof:placetype":"venue"
},
  "geometry": {"coordinates":[174.316406,-35.722542],"type":"Point"}
}