{
  "type": "Feature",
  "properties": {
    "addr:full":"Waerenga Rd Te  Kauwhata",
    "addr:street":"Waerenga Rd",
    "iso:country":"NZ",
    "sg:address":"Waerenga Rd Te ",
    "sg:city":"Kauwhata",
    "sg:classifiers":[
        {
            "category":"Social Services",
            "subcategory":"Retirement Home",
            "type":"Services"
        }
    ],
    "sg:phone":"+64 7-826 3544",
    "sg:tags":[
        "elderly",
        "convalescent",
        "garden",
        "rest",
        "care"
    ],
    "wof:name":"Aparangi",
    "wof:placetype":"venue"
},
  "geometry": {"coordinates":[175.157318,-37.40033],"type":"Point"}
}