{
  "type": "Feature",
  "properties": {
    "iso:country":"NZ",
    "sg:address":"3/16 Picton St Ponsonby ",
    "sg:city":"Auckland",
    "sg:orig_category":"Non-Classified Establishments",
    "sg:phone":"+64 9-360 2413",
    "sg:province":"Auckland",
    "sg:website":"http://www.yellowpages.co.nz/for/alanclark/dp23103.html",
    "wof:name":"Alan Clark Lawyer",
    "wof:placetype":"venue"
},
  "geometry": {"coordinates":[174.742416,-36.85326],"type":"Point"}
}