{
  "type": "Feature",
  "properties": {
    "iso:country":"NZ",
    "sg:address":"Bay of ",
    "sg:city":"Plenty",
    "sg:classifiers":[
        {
            "category":"Banks & Credit Unions",
            "subcategory":"Financial Services",
            "type":"Services"
        }
    ],
    "sg:phone":"+64 800 229 2677",
    "sg:tags":[
        "finance"
    ],
    "sg:website":"http://www.yellowpages.co.nz/pages/228353860/dp59986.html",
    "wof:name":"Baycorp Advantage (NZ) Ltd",
    "wof:placetype":"venue"
},
  "geometry": {"coordinates":[176.956741,-38.188862],"type":"Point"}
}