{
  "type": "Feature",
  "properties": {
    "iso:country":"NZ",
    "sg:address":"Auckland Airport 154 McKenzie Rd Mangere ",
    "sg:city":"Auckland",
    "sg:orig_category":"Automotive: General Services: Rental Vehicles",
    "sg:phone":"+64 9-275 0066",
    "sg:province":"Auckland",
    "sg:website":"http://www.nationalcar.co.nz",
    "wof:name":"National Car Rental",
    "wof:placetype":"venue"
},
  "geometry": {"coordinates":[174.82380699999999,-36.96891],"type":"Point"}
}