{
  "type": "Feature",
  "properties": {
    "addr:full":"154 King Edward St South Dunedin  Dunedin Otago",
    "addr:housenumber":"154",
    "addr:street":"King Edward St",
    "iso:country":"NZ",
    "sg:address":"154 King Edward St South Dunedin ",
    "sg:city":"Dunedin",
    "sg:orig_category":"Shopping: Retail Stores: Books: Books - Secondhand",
    "sg:phone":"+64 3-455 7711",
    "sg:province":"Otago",
    "wof:name":"Books Rare & New Zealand",
    "wof:placetype":"venue"
},
  "geometry": {"coordinates":[170.49896200000001,-45.893749],"type":"Point"}
}