{
  "type": "Feature",
  "properties": {
    "addr:full":"Whitikahu Rd Gordonton  Hamilton Waikato",
    "addr:street":"Whitikahu Rd",
    "iso:country":"NZ",
    "sg:address":"Whitikahu Rd Gordonton ",
    "sg:city":"Hamilton",
    "sg:classifiers":[
        {
            "category":"Travel",
            "subcategory":"Travel Agent",
            "type":"Entertainment"
        }
    ],
    "sg:phone":"+64 7-824 3687",
    "sg:province":"Waikato",
    "sg:tags":[
        "tour",
        "tourism",
        "sightseeing"
    ],
    "sg:website":"http://www.promotionz.co.nz/woodlands",
    "wof:name":"Woodlands Historic Homestead Gardens & Function Centre",
    "wof:placetype":"venue"
},
  "geometry": {"coordinates":[175.34916699999999,-37.60627],"type":"Point"}
}