{
  "type": "Feature",
  "properties": {
    "iso:country":"NZ",
    "sg:address":"PO Box 399 Feilding Palmerston ",
    "sg:city":"Palmerston North",
    "sg:classifiers":[
        {
            "category":"Banks & Credit Unions",
            "subcategory":"Investment Brokerage",
            "type":"Services"
        }
    ],
    "sg:phone":"+64 6-354 9200",
    "sg:province":"Manawatu-Wanganui",
    "sg:tags":[
        "educational",
        "education",
        "training"
    ],
    "wof:name":"Parents As First Teachers",
    "wof:placetype":"venue"
},
  "geometry": {"coordinates":[175.547195,-40.224236],"type":"Point"}
}