{
  "type": "Feature",
  "properties": {
    "iso:country":"NZ",
    "sg:address":"11 Hartford Ave Papamoa Mt ",
    "sg:city":"Maunganui",
    "sg:classifiers":[
        {
            "category":"Recreation",
            "type":"Entertainment"
        }
    ],
    "sg:phone":"+64 7-574 7473",
    "sg:province":"Bay of Plenty",
    "sg:tags":[
        "sport",
        "leisure"
    ],
    "wof:name":"Timeout BJ's Ltd",
    "wof:placetype":"venue"
},
  "geometry": {"coordinates":[176.265396,-37.690628],"type":"Point"}
}