{
  "type": "Feature",
  "properties": {
    "addr:full":"196 Waltham Rd Waltham  Christchurch Canterbury",
    "addr:housenumber":"196",
    "addr:street":"Waltham Rd",
    "iso:country":"NZ",
    "sg:address":"196 Waltham Rd Waltham ",
    "sg:city":"Christchurch",
    "sg:classifiers":[
        {
            "category":"Retail",
            "subcategory":"Auto Repair",
            "type":"Services"
        }
    ],
    "sg:phone":"+64 3-366 7177",
    "sg:province":"Canterbury",
    "sg:tags":[
        "automotive",
        "servicing"
    ],
    "wof:name":"Gasson Motors Ltd",
    "wof:placetype":"venue"
},
  "geometry": {"coordinates":[172.64709500000001,-43.545502],"type":"Point"}
}