{
  "type": "Feature",
  "properties": {
    "iso:country":"NZ",
    "sg:address":"Rangi Rd Takanini ",
    "sg:city":"Auckland",
    "sg:orig_category":"Non-Classified Establishments",
    "sg:phone":"+64 9-267 3500",
    "sg:province":"Auckland",
    "wof:name":"Rallycross",
    "wof:placetype":"venue"
},
  "geometry": {"coordinates":[174.912781,-37.032688],"type":"Point"}
}