{
  "type": "Feature",
  "properties": {
    "iso:country":"NZ",
    "sg:address":"Mingaroa Rd R D 9 Feilding ",
    "sg:city":"Halcombe",
    "sg:orig_category":"Home And Garden: Gardening: Products: Fertilisers",
    "sg:phone":"+64 6-328 8828",
    "wof:name":"Rangitikei Groundspread",
    "wof:placetype":"venue"
},
  "geometry": {"coordinates":[175.56854200000001,-40.224361],"type":"Point"}
}