{
  "type": "Feature",
  "properties": {
    "iso:country":"NZ",
    "sg:address":"65 Kent Tce ",
    "sg:city":"Wellington",
    "sg:classifiers":[
        {
            "category":"Professional",
            "subcategory":"Detective & Security Services",
            "type":"Services"
        }
    ],
    "sg:phone":"+64 4-385 9966",
    "sg:province":"Wellington",
    "sg:tags":[
        "services",
        "automotive",
        "warrant",
        "fitness"
    ],
    "wof:name":"Honda Cars LMVD",
    "wof:placetype":"venue"
},
  "geometry": {"coordinates":[-64.680969,46.428822],"type":"Point"}
}