{
  "type": "Feature",
  "properties": {
    "iso:country":"NZ",
    "sg:address":"88 King St ",
    "sg:city":"Pukekohe",
    "sg:classifiers":[
        {
            "category":"Shopping",
            "subcategory":"Crafts & Fabrics",
            "type":"Retail Goods"
        }
    ],
    "sg:phone":"+64 9-238 7693",
    "sg:province":"Auckland",
    "sg:tags":[
        "knitting",
        "wool",
        "clothing"
    ],
    "wof:name":"Michele Ann Wool Shop",
    "wof:placetype":"venue"
},
  "geometry": {"coordinates":[174.930252,-37.195728],"type":"Point"}
}