{
  "type": "Feature",
  "properties": {
    "iso:country":"NZ",
    "sg:address":"3/231 Gt South Rd Papakura ",
    "sg:city":"Auckland",
    "sg:classifiers":[
        {
            "category":"Retail",
            "subcategory":"Laundry & Dry Cleaning",
            "type":"Services"
        }
    ],
    "sg:phone":"+64 9-296 0191",
    "sg:province":"Auckland",
    "sg:tags":[
        "repair",
        "clothing",
        "fabric",
        "cleaner"
    ],
    "wof:name":"Everest Dry Cleaning",
    "wof:placetype":"venue"
},
  "geometry": {"coordinates":[174.943405,-37.064442],"type":"Point"}
}