{
  "type": "Feature",
  "properties": {
    "iso:country":"NZ",
    "sg:address":"37 Willis St ",
    "sg:city":"Wellington",
    "sg:orig_category":"Shopping: Accessories",
    "sg:phone":"+64 4-499 9147",
    "sg:province":"Wellington",
    "wof:name":"Bustop",
    "wof:placetype":"venue"
},
  "geometry": {"coordinates":[-85.910454,33.827946],"type":"Point"}
}