{
  "type": "Feature",
  "properties": {
    "iso:country":"NZ",
    "sg:address":"Workshop Acklin St ",
    "sg:city":"Waipukurau",
    "sg:orig_category":"Farming: Services: Hedge Cutting Contractors",
    "sg:phone":"+64 6-858 6095",
    "wof:name":"Agpower Shelter Trimming Contractors",
    "wof:placetype":"venue"
},
  "geometry": {"coordinates":[176.5513,-39.994656],"type":"Point"}
}