{
  "type": "Feature",
  "properties": {
    "addr:full":"Junction Rd Egmont  Village",
    "addr:street":"Junction Rd",
    "iso:country":"NZ",
    "sg:address":"Junction Rd Egmont ",
    "sg:city":"Village",
    "sg:orig_category":"Farming: Machinery: Tractors",
    "sg:phone":"+64 6-752 2864",
    "wof:name":"Egmont Village Tractor Parts Ltd",
    "wof:placetype":"venue"
},
  "geometry": {"coordinates":[174.14683500000001,-39.14658],"type":"Point"}
}