{
  "type": "Feature",
  "properties": {
    "iso:country":"NZ",
    "sg:address":"218 Swanson Rd Henderson ",
    "sg:city":"Auckland",
    "sg:classifiers":[
        {
            "category":"Military Area",
            "subcategory":"Air Force Base",
            "type":"Public Place"
        }
    ],
    "sg:phone":"+64 9-813 1700",
    "sg:province":"Auckland",
    "sg:tags":[
        "fabric",
        "footwear",
        "wear",
        "foot",
        "clothing",
        "manufacturer"
    ],
    "wof:name":"Blundstone New Zealand Limited",
    "wof:placetype":"venue"
},
  "geometry": {"coordinates":[174.620514,-36.871212],"type":"Point"}
}