{
  "type": "Feature",
  "properties": {
    "addr:full":"P O Box 43-176 Wainuiomata Lower  Hutt Wellington",
    "addr:housenumber":"box",
    "addr:postcode":"43-176",
    "iso:country":"NZ",
    "sg:address":"P O Box 43-176 Wainuiomata Lower ",
    "sg:city":"Hutt",
    "sg:classifiers":[
        {
            "category":"Bus Charters",
            "type":"Transportation"
        }
    ],
    "sg:phone":"+64 4-564 5015",
    "sg:province":"Wellington",
    "sg:tags":[
        "services",
        "travel",
        "tourism"
    ],
    "wof:name":"Classic Coaches",
    "wof:placetype":"venue"
},
  "geometry": {"coordinates":[174.95083600000001,-41.261421],"type":"Point"}
}