{
  "type": "Feature",
  "properties": {
    "addr:full":"10 Newton Pl  Hamilton Auckland",
    "addr:housenumber":"10",
    "addr:street":"Newton Pl",
    "iso:country":"NZ",
    "sg:address":"10 Newton Pl ",
    "sg:city":"Hamilton",
    "sg:orig_category":"Industrial: Metal: Services: Metal Detection",
    "sg:phone":"+64 7-847 3396",
    "sg:province":"Auckland",
    "wof:name":"Jaymor Industries Ltd",
    "wof:placetype":"venue"
},
  "geometry": {"coordinates":[-74.627357,40.221657],"type":"Point"}
}