{
  "type": "Feature",
  "properties": {
    "iso:country":"NZ",
    "sg:address":"22 Patrick St Onehunga ",
    "sg:city":"Auckland",
    "sg:classifiers":[
        {
            "category":"Shopping",
            "subcategory":"Crafts & Fabrics",
            "type":"Retail Goods"
        }
    ],
    "sg:phone":"+64 9-636 4125",
    "sg:province":"Auckland",
    "sg:tags":[
        "clothing",
        "elastic",
        "manufacturer"
    ],
    "wof:name":"NZ Ribbon Manufacturers Ltd",
    "wof:placetype":"venue"
},
  "geometry": {"coordinates":[174.783661,-36.909973],"type":"Point"}
}