{
  "type": "Feature",
  "properties": {
    "iso:country":"NZ",
    "sg:address":"175 Mountainview Rd ",
    "sg:city":"Timaru",
    "sg:classifiers":[
        {
            "category":"Home & Garden",
            "subcategory":"Building Materials",
            "type":"Retail Goods"
        }
    ],
    "sg:phone":"+64 3-686 1403",
    "sg:province":"Canterbury",
    "sg:tags":[
        "builder",
        "related"
    ],
    "wof:name":"Curr R J Ltd",
    "wof:placetype":"venue"
},
  "geometry": {"coordinates":[171.206726,-44.376961],"type":"Point"}
}