{
  "type": "Feature",
  "properties": {
    "iso:country":"NZ",
    "sg:address":"40 Rosemont Rd ",
    "sg:city":"Waihi",
    "sg:orig_category":"Shopping: Retail Stores: Antiques",
    "sg:phone":"+64 7-863 9366",
    "wof:name":"In Vogue Costumes & Collectables",
    "wof:placetype":"venue"
},
  "geometry": {"coordinates":[175.84635900000001,-37.398495],"type":"Point"}
}