{
  "type": "Feature",
  "properties": {
    "iso:country":"NZ",
    "sg:address":"111 Barbara Ave ",
    "sg:city":"Whangamata",
    "sg:classifiers":[
        {
            "category":"Home & Garden",
            "subcategory":"Building Materials",
            "type":"Retail Goods"
        }
    ],
    "sg:phone":"+64 7-865 9305",
    "sg:tags":[
        "electrician",
        "related"
    ],
    "wof:name":"Laurenson Electrical",
    "wof:placetype":"venue"
},
  "geometry": {"coordinates":[175.872604,-37.207733],"type":"Point"}
}