{
  "type": "Feature",
  "properties": {
    "addr:full":"Corner of Revell & Hamilton Streets  Hokitika Wellington",
    "addr:street":"Corner",
    "iso:country":"NZ",
    "sg:address":"Corner of Revell & Hamilton Streets ",
    "sg:city":"Hokitika",
    "sg:classifiers":[
        {
            "category":"Retail",
            "subcategory":"Auto Repair",
            "type":"Services"
        }
    ],
    "sg:phone":"+64 3-755 8690",
    "sg:province":"Wellington",
    "sg:tags":[
        "automotive",
        "servicing"
    ],
    "wof:name":"Scenicland Motors",
    "wof:placetype":"venue"
},
  "geometry": {"coordinates":[170.97219799999999,-42.719028],"type":"Point"}
}