{
  "type": "Feature",
  "properties": {
    "iso:country":"NZ",
    "sg:address":"Meadowbank Med. Centre 2 Blackett Cre Meadowbank ",
    "sg:city":"Auckland",
    "sg:classifiers":[
        {
            "category":"Health Services",
            "subcategory":"Health Practitioner",
            "type":"Services"
        }
    ],
    "sg:phone":"+64 9-528 4242",
    "sg:province":"Auckland",
    "sg:tags":[
        "services",
        "beauty",
        "acupuncturists"
    ],
    "wof:name":"Tan Dr Wellington",
    "wof:placetype":"venue"
},
  "geometry": {"coordinates":[174.827087,-36.870098],"type":"Point"}
}