{
  "type": "Feature",
  "properties": {
    "iso:country":"NZ",
    "sg:address":"9 Bank St ",
    "sg:city":"Timaru",
    "sg:classifiers":[
        {
            "category":"Restaurant",
            "type":"Food & Drink"
        }
    ],
    "sg:phone":"+64 3-688 8856",
    "sg:province":"Canterbury",
    "sg:tags":[
        "fruit",
        "veges"
    ],
    "wof:name":"Timaru Produce Wholesalers",
    "wof:placetype":"venue"
},
  "geometry": {"coordinates":[171.250305,-44.399666],"type":"Point"}
}