{
  "type": "Feature",
  "properties": {
    "iso:country":"NZ",
    "sg:address":"44 Creyke Rd Fendalton ",
    "sg:city":"Christchurch",
    "sg:classifiers":[
        {
            "category":"Wholesale",
            "subcategory":"Meat",
            "type":"Manufacturing & Wholesale Goods"
        }
    ],
    "sg:phone":"+64 3-351 2000",
    "sg:province":"Canterbury",
    "sg:tags":[
        "food",
        "distributor",
        "drink",
        "meats"
    ],
    "wof:name":"Oriental By-Product Processors",
    "wof:placetype":"venue"
},
  "geometry": {"coordinates":[172.59677099999999,-43.516556],"type":"Point"}
}