{
  "type": "Feature",
  "properties": {
    "iso:country":"NZ",
    "sg:address":"Unit 4 95 Ellice Rd Glenfield ",
    "sg:city":"Auckland",
    "sg:orig_category":"Industrial: Products",
    "sg:phone":"+64 9-444 4510",
    "sg:province":"Auckland",
    "sg:website":"http://www.johngilbert.co.nz",
    "wof:name":"John Gilbert & Co Ltd",
    "wof:placetype":"venue"
},
  "geometry": {"coordinates":[174.728622,-36.784813],"type":"Point"}
}