{
  "type": "Feature",
  "properties": {
    "iso:country":"NZ",
    "sg:address":"18 Watts Rd Sockburn ",
    "sg:city":"Christchurch",
    "sg:orig_category":"Sports And Leisure: General: Halls",
    "sg:phone":"+64 3-348 0990",
    "sg:province":"Canterbury",
    "wof:name":"The Colosseum",
    "wof:placetype":"venue"
},
  "geometry": {"coordinates":[172.560959,-43.537647],"type":"Point"}
}