{
  "type": "Feature",
  "properties": {
    "addr:full":"4024 Great North Rd Kelston  Auckland Auckland",
    "addr:housenumber":"4024",
    "addr:street":"Great North Rd",
    "iso:country":"NZ",
    "sg:address":"4024 Great North Rd Kelston ",
    "sg:city":"Auckland",
    "sg:classifiers":[
        {
            "category":"Retail",
            "subcategory":"Repair Shop",
            "type":"Services"
        }
    ],
    "sg:phone":"+64 9-818 2434",
    "sg:province":"Auckland",
    "sg:tags":[
        "clothing",
        "fabric",
        "cleaning"
    ],
    "wof:name":"Paradise Alterations",
    "wof:placetype":"venue"
},
  "geometry": {"coordinates":[174.66392500000001,-36.908218],"type":"Point"}
}