{
  "type": "Feature",
  "properties": {
    "addr:full":"PO Box 18 Te  Kauwhata",
    "addr:housenumber":"po box 18",
    "addr:street":"Te Kauwhata",
    "iso:country":"NZ",
    "sg:address":"PO Box 18 Te ",
    "sg:city":"Kauwhata",
    "sg:classifiers":[
        {
            "category":"Farming",
            "subcategory":"Farm & Veterinary Services",
            "type":"Manufacturing & Wholesale Goods"
        }
    ],
    "sg:phone":"+64 7-826 3145",
    "sg:tags":[
        "supplies",
        "supply"
    ],
    "wof:name":"Stockyards Inc",
    "wof:placetype":"venue"
},
  "geometry": {"coordinates":[175.14735400000001,-37.403275],"type":"Point"}
}