{
  "type": "Feature",
  "properties": {
    "addr:full":"9 B Ward St New Lynn  Auckland Auckland",
    "addr:housenumber":"9 b",
    "addr:street":"Ward St",
    "iso:country":"NZ",
    "sg:address":"9 B Ward St New Lynn ",
    "sg:city":"Auckland",
    "sg:classifiers":[
        {
            "category":"Shopping",
            "subcategory":"Crafts & Fabrics",
            "type":"Retail Goods"
        }
    ],
    "sg:phone":"+64 9-826 1480",
    "sg:province":"Auckland",
    "sg:tags":[
        "arts",
        "sport",
        "art",
        "leisure",
        "supply"
    ],
    "wof:name":"Retsol Industries (1993) Limited",
    "wof:placetype":"venue"
},
  "geometry": {"coordinates":[174.68864400000001,-36.908691],"type":"Point"}
}