{
  "type": "Feature",
  "properties": {
    "iso:country":"NZ",
    "sg:address":"36 Carkeek St Port Nelson ",
    "sg:city":"Nelson",
    "sg:classifiers":[
        {
            "category":"Building & Trades",
            "subcategory":"Cleaning & Sanitation",
            "type":"Services"
        }
    ],
    "sg:phone":"+64 3-545 7212",
    "sg:province":"Nelson",
    "sg:tags":[
        "equipment",
        "industrial",
        "maintenance"
    ],
    "wof:name":"The Cleaning Oasis Nelson",
    "wof:placetype":"venue"
},
  "geometry": {"coordinates":[173.275803,-41.261845],"type":"Point"}
}