{
  "type": "Feature",
  "properties": {
    "iso:country":"NZ",
    "sg:address":"56 View Rd ",
    "sg:city":"Warkworth",
    "sg:orig_category":"Health And Beauty: Medical: Hospitals",
    "sg:phone":"+64 9-425 8201",
    "sg:province":"Auckland",
    "wof:name":"Rodney Coast Midwives Ltd",
    "wof:placetype":"venue"
},
  "geometry": {"coordinates":[174.65394599999999,-36.400196],"type":"Point"}
}