{
  "type": "Feature",
  "properties": {
    "iso:country":"NZ",
    "sg:address":"Palmerston ",
    "sg:city":"Palmerston North",
    "sg:classifiers":[
        {
            "category":"Banks & Credit Unions",
            "subcategory":"Investment Brokerage",
            "type":"Services"
        }
    ],
    "sg:phone":"+64 800 371 471",
    "sg:province":"Manawatu-Wanganui",
    "sg:tags":[
        "personal",
        "-",
        "finance"
    ],
    "sg:website":"http://www.publictrust.co.nz",
    "wof:name":"Public Trust",
    "wof:placetype":"venue"
},
  "geometry": {"coordinates":[175.611481,-40.357418],"type":"Point"}
}