{
  "type": "Feature",
  "properties": {
    "addr:full":"Cnr Hobson & Victoria Sts W Auckland Central  Auckland Auckland",
    "addr:street":"Cnr Hobson & Victoria Sts W",
    "iso:country":"NZ",
    "sg:address":"Cnr Hobson & Victoria Sts W Auckland Central ",
    "sg:city":"Auckland",
    "sg:classifiers":[
        {
            "category":"Bars & Pubs",
            "type":"Food & Drink"
        }
    ],
    "sg:phone":"+64 9-309 2118",
    "sg:province":"Auckland",
    "sg:tags":[
        "wining",
        "dining",
        "brasserie"
    ],
    "wof:name":"The Dispensary Bar",
    "wof:placetype":"venue"
},
  "geometry": {"coordinates":[174.76454200000001,-36.848358],"type":"Point"}
}