{
  "type": "Feature",
  "properties": {
    "addr:full":"31 Maurice Rd Penrose  Auckland Auckland",
    "addr:housenumber":"31",
    "addr:street":"Maurice Rd",
    "iso:country":"NZ",
    "sg:address":"31 Maurice Rd Penrose ",
    "sg:city":"Auckland",
    "sg:orig_category":"Industrial: Metal: Services: Steel Processing",
    "sg:phone":"+64 9-636 3908",
    "sg:province":"Auckland",
    "wof:name":"Steel & Tube Reinforcing",
    "wof:placetype":"venue"
},
  "geometry": {"coordinates":[174.809662,-36.91753],"type":"Point"}
}