{
  "type": "Feature",
  "properties": {
    "iso:country":"NZ",
    "sg:address":"295 Great North Rd Grey Lynn ",
    "sg:city":"Auckland",
    "sg:classifiers":[
        {
            "category":"Home & Garden",
            "subcategory":"Kitchen Supply",
            "type":"Retail Goods"
        }
    ],
    "sg:phone":"+64 9-361 5890",
    "sg:province":"Auckland",
    "sg:tags":[
        "food",
        "equipment",
        "drink",
        "catering"
    ],
    "wof:name":"Gul Consultants (NZ) Ltd",
    "wof:placetype":"venue"
},
  "geometry": {"coordinates":[174.744873,-36.865086],"type":"Point"}
}