{
  "type": "Feature",
  "properties": {
    "addr:full":"295 Great North Rd Grey Lynn  Auckland Auckland",
    "addr:housenumber":"295",
    "addr:street":"Great North Rd",
    "iso:country":"NZ",
    "sg:address":"295 Great North Rd Grey Lynn ",
    "sg:city":"Auckland",
    "sg:classifiers":[
        {
            "category":"Home & Garden",
            "subcategory":"Kitchen Supply",
            "type":"Retail Goods"
        }
    ],
    "sg:phone":"+64 9-361 5890",
    "sg:province":"Auckland",
    "sg:tags":[
        "food",
        "equipment",
        "drink",
        "catering"
    ],
    "wof:name":"Gul Consultants (NZ) Ltd",
    "wof:placetype":"venue"
},
  "geometry": {"coordinates":[174.74487300000001,-36.865086],"type":"Point"}
}