{
  "type": "Feature",
  "properties": {
    "addr:full":"36 Coutts St Rongotai  Wellington Wellington",
    "addr:housenumber":"36",
    "addr:street":"Coutts St",
    "iso:country":"NZ",
    "sg:address":"36 Coutts St Rongotai ",
    "sg:city":"Wellington",
    "sg:classifiers":[
        {
            "category":"Home & Garden",
            "subcategory":"Home Furnishings",
            "type":"Retail Goods"
        }
    ],
    "sg:phone":"+64 4-387 2093",
    "sg:province":"Wellington",
    "sg:tags":[
        "furniture/furnishings",
        "upholstery",
        "supply"
    ],
    "wof:name":"B Lawrie Upholstery",
    "wof:placetype":"venue"
},
  "geometry": {"coordinates":[174.80105599999999,-41.321198],"type":"Point"}
}