{
  "type": "Feature",
  "properties": {
    "iso:country":"NZ",
    "sg:address":"1108 Karamu Rd ",
    "sg:city":"Hastings",
    "sg:classifiers":[
        {
            "category":"Retail",
            "subcategory":"Funeral Services",
            "type":"Services"
        }
    ],
    "sg:phone":"+64 6-878 8751",
    "sg:province":"Hawke's Bay",
    "sg:tags":[
        "arrangements",
        "arrangement"
    ],
    "wof:name":"Heather Cairns",
    "wof:placetype":"venue"
},
  "geometry": {"coordinates":[176.85787999999999,-39.635162],"type":"Point"}
}