{
  "type": "Feature",
  "properties": {
    "addr:full":"57 River St Mataura  Mataura",
    "addr:housenumber":"57",
    "addr:street":"River St",
    "iso:country":"NZ",
    "sg:address":"57 River St Mataura ",
    "sg:city":"Mataura",
    "sg:orig_category":"Sports And Leisure: Hobbies: Taxidermists",
    "sg:phone":"+64 3-203 3011",
    "wof:name":"Steve Barclay Taxidermy",
    "wof:placetype":"venue"
},
  "geometry": {"coordinates":[168.86705000000001,-46.194851],"type":"Point"}
}