{
  "type": "Feature",
  "properties": {
    "iso:country":"NZ",
    "sg:address":"Te Hapua Rd Te Hapua ",
    "sg:city":"Kaitaia",
    "sg:classifiers":[
        {
            "category":"Banks & Credit Unions",
            "subcategory":"Investment Brokerage",
            "type":"Services"
        }
    ],
    "sg:phone":"+64 9-409 7591",
    "sg:province":"Northland",
    "sg:tags":[
        "educational",
        "education",
        "training"
    ],
    "wof:name":"Te Kohanga Reo Te Hapua",
    "wof:placetype":"venue"
},
  "geometry": {"coordinates":[173.259445,-35.114208],"type":"Point"}
}