{
  "type": "Feature",
  "properties": {
    "iso:country":"NZ",
    "sg:address":"11 C Airborne Rd Albany ",
    "sg:city":"Auckland",
    "sg:classifiers":[
        {
            "category":"Ice Cream",
            "type":"Food & Drink"
        }
    ],
    "sg:phone":"+64 9-414 1911",
    "sg:province":"Auckland",
    "sg:tags":[
        "-"
    ],
    "wof:name":"Gelato Italia",
    "wof:placetype":"venue"
},
  "geometry": {"coordinates":[174.70236199999999,-36.744171],"type":"Point"}
}