{
  "type": "Feature",
  "properties": {
    "iso:country":"NZ",
    "sg:address":"No 1 Rd Te ",
    "sg:city":"Puke",
    "sg:orig_category":"Health And Beauty: Medical: Hospitals",
    "sg:phone":"+64 7-573 9983",
    "sg:province":"Bay of Plenty",
    "wof:name":"Te Puke Country Lodge",
    "wof:placetype":"venue"
},
  "geometry": {"coordinates":[176.333771,-37.792152],"type":"Point"}
}