{
  "type": "Feature",
  "properties": {
    "iso:country":"NZ",
    "sg:address":"10 Te Mata Rd Havelock North ",
    "sg:city":"Hastings",
    "sg:orig_category":"Clothing And Fabric: Clothing: Menswear",
    "sg:phone":"+64 6-877 5355",
    "sg:province":"Hawke's Bay",
    "wof:name":"Poppelwell's HNth Ltd",
    "wof:placetype":"venue"
},
  "geometry": {"coordinates":[176.878204,-39.670048],"type":"Point"}
}