{
  "type": "Feature",
  "properties": {
    "addr:full":"32 Stackhouse Ave Bishopdale  Christchurch Canterbury",
    "addr:housenumber":"32",
    "addr:street":"Stackhouse Ave Bishopdale Christchurch",
    "iso:country":"NZ",
    "sg:address":"32 Stackhouse Ave Bishopdale ",
    "sg:city":"Christchurch",
    "sg:orig_category":"Sports And Leisure: Entertainment: Musicians",
    "sg:phone":"+64 3-359 7500",
    "sg:province":"Canterbury",
    "wof:name":"NZ Modern School of Music",
    "wof:placetype":"venue"
},
  "geometry": {"coordinates":[172.58923300000001,-43.490578],"type":"Point"}
}