{
  "type": "Feature",
  "properties": {
    "addr:full":"18 Lorikeet Pl Glenfield  Auckland Auckland",
    "addr:housenumber":"18",
    "addr:street":"Lorikeet Pl",
    "iso:country":"NZ",
    "sg:address":"18 Lorikeet Pl Glenfield ",
    "sg:city":"Auckland",
    "sg:classifiers":[
        {
            "category":"Food & Beverages",
            "subcategory":"Liquor & Beverages",
            "type":"Retail Goods"
        }
    ],
    "sg:phone":"+64 9-414 4177",
    "sg:province":"Auckland",
    "sg:tags":[
        "distributor",
        "drink"
    ],
    "wof:name":"Sam Malones Ltd",
    "wof:placetype":"venue"
},
  "geometry": {"coordinates":[174.728622,-36.784813],"type":"Point"}
}