{
  "type": "Feature",
  "properties": {
    "iso:country":"NZ",
    "sg:address":"600 Main St Palmerston ",
    "sg:city":"Palmerston North",
    "sg:classifiers":[
        {
            "category":"Sports & Exercise",
            "subcategory":"Tennis Court",
            "type":"Entertainment"
        }
    ],
    "sg:phone":"+64 6-356 4793",
    "sg:province":"Manawatu-Wanganui",
    "sg:tags":[
        "hobby",
        "leisure"
    ],
    "sg:website":"http://www.needlecraft.co.nz",
    "wof:name":"Needlecraft Distributors Ltd",
    "wof:placetype":"venue"
},
  "geometry": {"coordinates":[175.61552399999999,-40.354359],"type":"Point"}
}