{
  "type": "Feature",
  "properties": {
    "iso:country":"NZ",
    "sg:address":"182 Paekakariki Hill Rd Pauatahanui ",
    "sg:city":"Porirua",
    "sg:classifiers":[
        {
            "category":"Personal",
            "type":"Services"
        }
    ],
    "sg:phone":"+64 4-237 9007",
    "sg:province":"Wellington",
    "sg:tags":[
        "arrangements",
        "wedding"
    ],
    "sg:website":"http://www.lodgeattheinlet.co.nz",
    "wof:name":"The Lodge at the Inlet",
    "wof:placetype":"venue"
},
  "geometry": {"coordinates":[174.91717499999999,-41.091862],"type":"Point"}
}