{
  "type": "Feature",
  "properties": {
    "iso:country":"NZ",
    "sg:address":"18 High St Waipawa ",
    "sg:city":"Waipawa",
    "sg:orig_category":"Shopping: Retail Stores: Books: Bookshops",
    "sg:phone":"+64 6-857 8025",
    "wof:name":"Pearson's Books",
    "wof:placetype":"venue"
},
  "geometry": {"coordinates":[176.59179700000001,-39.94202],"type":"Point"}
}