{
  "type": "Feature",
  "properties": {
    "iso:country":"NZ",
    "sg:address":"151 Arthur St Onehunga ",
    "sg:city":"Auckland",
    "sg:classifiers":[
        {
            "category":"Sports & Exercise",
            "subcategory":"Tennis Court",
            "type":"Entertainment"
        }
    ],
    "sg:phone":"+64 9-636 7070",
    "sg:province":"Auckland",
    "sg:tags":[
        "jeweller",
        "hobbies",
        "leisure",
        "supply"
    ],
    "wof:name":"Watch Master",
    "wof:placetype":"venue"
},
  "geometry": {"coordinates":[174.786438,-36.920719],"type":"Point"}
}