{
  "type": "Feature",
  "properties": {
    "iso:country":"NZ",
    "sg:address":"121 Papanui Rd Merivale ",
    "sg:city":"Christchurch",
    "sg:classifiers":[
        {
            "category":"Travel",
            "subcategory":"Bed & Breakfast",
            "type":"Entertainment"
        }
    ],
    "sg:phone":"+64 3-355 5418",
    "sg:province":"Canterbury",
    "sg:tags":[
        "house",
        "tourism",
        "guest",
        "accommodation"
    ],
    "wof:name":"Highway Lodge Guest House",
    "wof:placetype":"venue"
},
  "geometry": {"coordinates":[172.62428299999999,-43.515648],"type":"Point"}
}