{
  "type": "Feature",
  "properties": {
    "iso:country":"NZ",
    "sg:address":"cnr Sawyers Arms & Broughs Rd Harewood ",
    "sg:city":"Christchurch",
    "sg:classifiers":[
        {
            "category":"Home & Garden",
            "subcategory":"Building Materials",
            "type":"Retail Goods"
        }
    ],
    "sg:phone":"+64 3-359 4160",
    "sg:province":"Canterbury",
    "sg:tags":[
        "brick",
        "outdoor",
        "paving"
    ],
    "wof:name":"Firth Industries",
    "wof:placetype":"venue"
},
  "geometry": {"coordinates":[172.563766,-43.476311],"type":"Point"}
}