{
  "type": "Feature",
  "properties": {
    "addr:full":"501 Evans Bay Pde Evans Bay  Wellington Wellington",
    "addr:housenumber":"501",
    "addr:street":"Evans Bay Pde Evans",
    "iso:country":"NZ",
    "sg:address":"501 Evans Bay Pde Evans Bay ",
    "sg:city":"Wellington",
    "sg:classifiers":[
        {
            "category":"Retail",
            "subcategory":"Driving School",
            "type":"Services"
        }
    ],
    "sg:province":"Wellington",
    "sg:tags":[
        "sailing",
        "boating",
        "transport",
        "boats",
        "marine",
        "boat"
    ],
    "wof:name":"Evans Bay Yacht & Motor Boat Club Inc",
    "wof:placetype":"venue"
},
  "geometry": {"coordinates":[174.908569,-41.278835],"type":"Point"}
}