{
  "type": "Feature",
  "properties": {
    "iso:country":"NZ",
    "sg:address":"271 Great North Rd Grey Lynn ",
    "sg:city":"Auckland",
    "sg:orig_category":"Automotive: General Services: Rental Vehicles",
    "sg:phone":"+64 9-376 3141",
    "sg:province":"Auckland",
    "sg:website":"http://www.trailerace.co.nz",
    "wof:name":"Trailer Ace",
    "wof:placetype":"venue"
},
  "geometry": {"coordinates":[174.74546799999999,-36.864941],"type":"Point"}
}