{
  "type": "Feature",
  "properties": {
    "iso:country":"NZ",
    "sg:address":"www.backload.ws ",
    "sg:city":"Gisborne",
    "sg:orig_category":"Transport: Transportation: Furniture Removal/Packers",
    "sg:phone":"+64 800 100 130",
    "sg:province":"Gisborne",
    "wof:name":"Backload Freight Brokers",
    "wof:placetype":"venue"
},
  "geometry": {"coordinates":[177.836197,-38.252838],"type":"Point"}
}