{
  "type": "Feature",
  "properties": {
    "addr:full":"PO Box 1677  Taupo Waikato",
    "addr:housenumber":"po;1677",
    "addr:street":"Box",
    "iso:country":"NZ",
    "sg:address":"PO Box 1677 ",
    "sg:city":"Taupo",
    "sg:orig_category":"Home And Garden: Accessories: Ceramics",
    "sg:phone":"+64 7-377 3922",
    "sg:province":"Waikato",
    "wof:name":"Bay Blue Design Limited",
    "wof:placetype":"venue"
},
  "geometry": {"coordinates":[176.084351,-38.689285],"type":"Point"}
}