{
  "type": "Feature",
  "properties": {
    "iso:country":"NZ",
    "sg:address":"2 Manadon St New ",
    "sg:city":"Plymouth",
    "sg:classifiers":[
        {
            "category":"Social Services",
            "subcategory":"Job Training",
            "type":"Services"
        }
    ],
    "sg:phone":"+64 800 707 383",
    "sg:province":"Wellington",
    "sg:tags":[
        "education"
    ],
    "wof:name":"Quantum Safety Ltd",
    "wof:placetype":"venue"
},
  "geometry": {"coordinates":[-116.819725,43.97221],"type":"Point"}
}