{
  "type": "Feature",
  "properties": {
    "iso:country":"NZ",
    "sg:address":"Bledisloe St ",
    "sg:city":"Kurow",
    "sg:orig_category":"Farming: Services: Veterinarians",
    "sg:phone":"+64 3-436 0567",
    "wof:name":"Kurow Veterinary Clinic",
    "wof:placetype":"venue"
},
  "geometry": {"coordinates":[170.47172499999999,-44.736259],"type":"Point"}
}