{
  "type": "Feature",
  "properties": {
    "addr:full":"6/229 State Highway 17 Albany  Auckland Auckland",
    "addr:housenumber":"6 / 229",
    "addr:street":"State Highway 17",
    "iso:country":"NZ",
    "sg:address":"6/229 State Highway 17 Albany ",
    "sg:city":"Auckland",
    "sg:classifiers":[
        {
            "category":"Deli",
            "type":"Food & Drink"
        }
    ],
    "sg:phone":"+64 9-415 3530",
    "sg:province":"Auckland",
    "sg:tags":[
        "delicatessen",
        "-"
    ],
    "wof:name":"Scotto's Italian/American Deli",
    "wof:placetype":"venue"
},
  "geometry": {"coordinates":[174.69546500000001,-36.725208],"type":"Point"}
}