{
  "type": "Feature",
  "properties": {
    "iso:country":"NZ",
    "sg:address":"Greymouth 208 Main South Rd ",
    "sg:city":"Greymouth",
    "sg:classifiers":[
        {
            "category":"Home & Garden",
            "subcategory":"Building Materials",
            "type":"Retail Goods"
        }
    ],
    "sg:phone":"+64 3-768 0560",
    "sg:province":"West Coast",
    "sg:tags":[
        "builder",
        "related"
    ],
    "wof:name":"Works Infrastructure Limited",
    "wof:placetype":"venue"
},
  "geometry": {"coordinates":[171.209885,-42.451618],"type":"Point"}
}