{
  "type": "Feature",
  "properties": {
    "addr:full":"Unit 1 11 View Rd Henderson  Auckland Auckland",
    "addr:housenumber":"unit;11",
    "addr:street":"View Rd",
    "iso:country":"NZ",
    "sg:address":"Unit 1 11 View Rd Henderson ",
    "sg:city":"Auckland",
    "sg:classifiers":[
        {
            "category":"Shopping",
            "subcategory":"Pharmacy",
            "type":"Retail Goods"
        }
    ],
    "sg:phone":"+64 9-835 1223",
    "sg:province":"Auckland",
    "sg:tags":[
        "product",
        "health"
    ],
    "wof:name":"Thomson's Foods Ltd",
    "wof:placetype":"venue"
},
  "geometry": {"coordinates":[174.632812,-36.886375],"type":"Point"}
}