{
  "type": "Feature",
  "properties": {
    "iso:country":"NZ",
    "sg:address":"19 High St ",
    "sg:city":"Picton",
    "sg:classifiers":[
        {
            "category":"Shopping",
            "subcategory":"Gifts & Souvenirs",
            "type":"Retail Goods"
        }
    ],
    "sg:phone":"+64 3-573 6648",
    "sg:province":"Marlborough",
    "sg:tags":[
        "travel",
        "tourism"
    ],
    "wof:name":"The Choice Gallery",
    "wof:placetype":"venue"
},
  "geometry": {"coordinates":[174.006775,-41.291874],"type":"Point"}
}