{
  "type": "Feature",
  "properties": {
    "addr:full":"21 Kenepuru Dve  Porirua Wellington",
    "addr:housenumber":"21",
    "addr:street":"Kenepuru Dve",
    "iso:country":"NZ",
    "sg:address":"21 Kenepuru Dve ",
    "sg:city":"Porirua",
    "sg:orig_category":"Shopping: Accessories",
    "sg:phone":"+64 4-237 5246",
    "sg:province":"Wellington",
    "wof:name":"Hills International Ltd",
    "wof:placetype":"venue"
},
  "geometry": {"coordinates":[174.85223400000001,-41.138294],"type":"Point"}
}