{
  "type": "Feature",
  "properties": {
    "iso:country":"NZ",
    "sg:address":"126 a Sixteenth Ave ",
    "sg:city":"Tauranga",
    "sg:classifiers":[
        {
            "category":"Education",
            "subcategory":"Music School",
            "type":"Public Place"
        }
    ],
    "sg:phone":"+64 7-578 6849",
    "sg:province":"Bay of Plenty",
    "sg:tags":[
        "sport",
        "teacher",
        "leisure"
    ],
    "wof:name":"Office World",
    "wof:placetype":"venue"
},
  "geometry": {"coordinates":[176.15387000000001,-37.706074],"type":"Point"}
}