{
  "type": "Feature",
  "properties": {
    "addr:full":"109 Blackbridge Rd Dairy Flat Hibiscus  Hibiscus Coast Auckland",
    "addr:housenumber":"109;hibiscus",
    "addr:street":"Blackbridge Rd;Hibiscus",
    "iso:country":"NZ",
    "sg:address":"109 Blackbridge Rd Dairy Flat Hibiscus ",
    "sg:city":"Hibiscus Coast",
    "sg:orig_category":"Industrial: Equipment And Machinery: Machinery",
    "sg:phone":"+64 9-427 5610",
    "sg:province":"Auckland",
    "wof:name":"Aspen Design Ltd",
    "wof:placetype":"venue"
},
  "geometry": {"coordinates":[174.62737999999999,-36.679661],"type":"Point"}
}