{
  "type": "Feature",
  "properties": {
    "addr:full":"Shop 5 180 E Yaldhurst Rd Avonhead  Christchurch Canterbury",
    "addr:housenumber":"shop 5 180 e",
    "addr:street":"Yaldhurst Rd",
    "iso:country":"NZ",
    "sg:address":"Shop 5 180 E Yaldhurst Rd Avonhead ",
    "sg:city":"Christchurch",
    "sg:orig_category":"Health And Beauty: Beauty: Hairdressers",
    "sg:phone":"+64 3-342 3489",
    "sg:province":"Canterbury",
    "wof:name":"Colleens Hair Design",
    "wof:placetype":"venue"
},
  "geometry": {"coordinates":[172.55342099999999,-43.52623],"type":"Point"}
}