{
  "type": "Feature",
  "properties": {
    "addr:full":"80 Waimumu Rd Massey  Auckland Auckland",
    "addr:housenumber":"80",
    "addr:street":"Waimumu Rd",
    "iso:country":"NZ",
    "sg:address":"80 Waimumu Rd Massey ",
    "sg:city":"Auckland",
    "sg:classifiers":[
        {
            "category":"Shopping",
            "subcategory":"Crafts & Fabrics",
            "type":"Retail Goods"
        }
    ],
    "sg:phone":"+64 9-832 5183",
    "sg:province":"Auckland",
    "sg:tags":[
        "knitting",
        "wool",
        "clothing"
    ],
    "wof:name":"Lister Yarns",
    "wof:placetype":"venue"
},
  "geometry": {"coordinates":[174.618942,-36.846889],"type":"Point"}
}