{
  "type": "Feature",
  "properties": {
    "iso:country":"NZ",
    "sg:address":"30 Golf Rd Tahunanui ",
    "sg:city":"Nelson",
    "sg:classifiers":[
        {
            "category":"Travel",
            "subcategory":"Hotels & Motels",
            "type":"Entertainment"
        }
    ],
    "sg:phone":"+64 3-548 5114",
    "sg:province":"Nelson",
    "sg:tags":[
        "holiday",
        "tourism",
        "accommodation"
    ],
    "sg:website":"http://www.courtesycourt.co.nz",
    "wof:name":"Courtesy Court Motel",
    "wof:placetype":"venue"
},
  "geometry": {"coordinates":[173.24040222170001,-41.2852935791],"type":"Point"}
}