{
  "type": "Feature",
  "properties": {
    "addr:full":"142 Hokio Sands Rd  Levin Manawatu-Wanganui",
    "addr:housenumber":"142",
    "addr:street":"Hokio Sands Rd",
    "iso:country":"NZ",
    "sg:address":"142 Hokio Sands Rd ",
    "sg:city":"Levin",
    "sg:classifiers":[
        {
            "category":"Food & Beverages",
            "subcategory":"Meat & Fish",
            "type":"Retail Goods"
        }
    ],
    "sg:phone":"+64 6-368 2614",
    "sg:province":"Manawatu-Wanganui",
    "sg:tags":[
        "drink"
    ],
    "wof:name":"NZ Meats",
    "wof:placetype":"venue"
},
  "geometry": {"coordinates":[175.285324,-40.625278],"type":"Point"}
}