{
  "type": "Feature",
  "properties": {
    "addr:full":"Main Highway R D 1  Oamaru Auckland",
    "addr:housenumber":"1",
    "addr:street":"Main Highway R D",
    "iso:country":"NZ",
    "sg:address":"Main Highway R D 1 ",
    "sg:city":"Oamaru",
    "sg:orig_category":"Sports And Leisure: General: Clubs",
    "sg:phone":"+64 3-437 0169",
    "sg:province":"Auckland",
    "wof:name":"Oamaru Harness Racing",
    "wof:placetype":"venue"
},
  "geometry": {"coordinates":[170.96902499999999,-45.097145],"type":"Point"}
}