{
  "type": "Feature",
  "properties": {
    "iso:country":"NZ",
    "sg:address":"21 Leven St ",
    "sg:city":"Invercargill",
    "sg:classifiers":[
        {
            "category":"Manufacturing",
            "subcategory":"Textiles",
            "type":"Manufacturing & Wholesale Goods"
        }
    ],
    "sg:phone":"+64 3-218 7277",
    "sg:province":"Southland",
    "sg:tags":[
        "clothing",
        "fabric",
        "manufacturer"
    ],
    "wof:name":"Knight Of New Zealand Ltd",
    "wof:placetype":"venue"
},
  "geometry": {"coordinates":[168.34582499999999,-46.410667],"type":"Point"}
}