{
  "type": "Feature",
  "properties": {
    "iso:country":"NZ",
    "sg:address":"92 Jellicoe St ",
    "sg:city":"Wanganui",
    "sg:classifiers":[
        {
            "category":"Home & Garden",
            "subcategory":"Building Materials",
            "type":"Retail Goods"
        }
    ],
    "sg:phone":"+64 6-343 3205",
    "sg:province":"Manawatu-Wanganui",
    "sg:tags":[
        "design",
        "fitting",
        "fittings",
        "kitchen"
    ],
    "wof:name":"Bench Factory The",
    "wof:placetype":"venue"
},
  "geometry": {"coordinates":[175.06308,-39.917114],"type":"Point"}
}