{
  "type": "Feature",
  "properties": {
    "addr:full":"5/217 Great South Rd Papatoetoe  Auckland Auckland",
    "addr:housenumber":"5 / 217",
    "addr:street":"Great South Rd",
    "iso:country":"NZ",
    "sg:address":"5/217 Great South Rd Papatoetoe ",
    "sg:city":"Auckland",
    "sg:classifiers":[
        {
            "category":"Internet Cafe",
            "subcategory":"None",
            "type":"Food & Drink"
        }
    ],
    "sg:phone":"+64 9-278 4247",
    "sg:province":"Auckland",
    "sg:tags":[
        "wining",
        "dining"
    ],
    "wof:name":"Ibuzsol",
    "wof:placetype":"venue"
},
  "geometry": {"coordinates":[174.861694,-36.97086],"type":"Point"}
}