{
  "type": "Feature",
  "properties": {
    "addr:full":"92 E Marua Rd Ellerslie  Auckland Auckland",
    "addr:housenumber":"92",
    "addr:street":"E Marua Rd",
    "iso:country":"NZ",
    "sg:address":"92 E Marua Rd Ellerslie ",
    "sg:city":"Auckland",
    "sg:classifiers":[
        {
            "category":"Education",
            "subcategory":"Music School",
            "type":"Public Place"
        }
    ],
    "sg:phone":"+64 9-525 2633",
    "sg:province":"Auckland",
    "sg:tags":[
        "sport",
        "teacher",
        "leisure"
    ],
    "wof:name":"Groundrush Music Studios Ltd",
    "wof:placetype":"venue"
},
  "geometry": {"coordinates":[174.822113,-36.89122],"type":"Point"}
}