{
  "type": "Feature",
  "properties": {
    "addr:full":"28 Alach St Greerton  Tauranga Bay of Plenty",
    "addr:housenumber":"28",
    "addr:street":"Alach St",
    "iso:country":"NZ",
    "sg:address":"28 Alach St Greerton ",
    "sg:city":"Tauranga",
    "sg:classifiers":[
        {
            "category":"Bars & Pubs",
            "type":"Food & Drink"
        }
    ],
    "sg:phone":"+64 7-571 5216",
    "sg:province":"Bay of Plenty",
    "sg:tags":[
        "-",
        "pie",
        "manufacturer"
    ],
    "wof:name":"Big Ben Pies",
    "wof:placetype":"venue"
},
  "geometry": {"coordinates":[176.125427,-37.724388],"type":"Point"}
}