{
  "type": "Feature",
  "properties": {
    "addr:full":"School Rd  Gisborne Gisborne",
    "addr:street":"School Rd",
    "iso:country":"NZ",
    "sg:address":"School Rd ",
    "sg:city":"Gisborne",
    "sg:classifiers":[
        {
            "category":"Retail",
            "subcategory":"Auto Repair",
            "type":"Services"
        }
    ],
    "sg:phone":"+64 6-868 4481",
    "sg:province":"Gisborne",
    "sg:tags":[
        "automotive",
        "servicing"
    ],
    "wof:name":"Gisborne Mechanical Ltd",
    "wof:placetype":"venue"
},
  "geometry": {"coordinates":[178.007462,-38.658245],"type":"Point"}
}