{
  "type": "Feature",
  "properties": {
    "addr:full":"Inside Greenlane Foodtown 326 Great South Rd Greenlane Auckland Auckland",
    "addr:housenumber":"326",
    "addr:street":"Greenlane;Great South Rd",
    "iso:country":"NZ",
    "sg:address":"Inside Greenlane Foodtown 326 Great South Rd Greenlane",
    "sg:city":"Auckland",
    "sg:classifiers":[
        {
            "category":"Retail",
            "subcategory":"Laundry & Dry Cleaning",
            "type":"Services"
        }
    ],
    "sg:phone":"+64 9-522 7083",
    "sg:province":"Auckland",
    "sg:tags":[
        "repair",
        "clothing",
        "fabric",
        "cleaner"
    ],
    "wof:name":"TLC Dry Cleaners Ltd",
    "wof:placetype":"venue"
},
  "geometry": {"coordinates":[174.79191599999999,-36.892967],"type":"Point"}
}