{
  "type": "Feature",
  "properties": {
    "addr:full":"185 Waitaha Rd Welcome Bay  Tauranga Bay of Plenty",
    "addr:housenumber":"185",
    "addr:street":"Waitaha Rd",
    "iso:country":"NZ",
    "sg:address":"185 Waitaha Rd Welcome Bay ",
    "sg:city":"Tauranga",
    "sg:orig_category":"Shopping: Accessories: Embroidery And Monograms",
    "sg:phone":"+64 7-544 5665",
    "sg:province":"Bay of Plenty",
    "wof:name":"Ace Embroidery",
    "wof:placetype":"venue"
},
  "geometry": {"coordinates":[176.190933,-37.733913],"type":"Point"}
}