{
  "type": "Feature",
  "properties": {
    "addr:full":"248 St Hill St  Wanganui Manawatu-Wanganui",
    "addr:housenumber":"248",
    "addr:street":"St Hill St",
    "iso:country":"NZ",
    "sg:address":"248 St Hill St ",
    "sg:city":"Wanganui",
    "sg:classifiers":[
        {
            "category":"Farming",
            "subcategory":"Farm & Veterinary Services",
            "type":"Manufacturing & Wholesale Goods"
        }
    ],
    "sg:phone":"+64 6-348 8215",
    "sg:province":"Manawatu-Wanganui",
    "sg:tags":[
        "supplies",
        "supply"
    ],
    "wof:name":"Ag Challenge Ltd",
    "wof:placetype":"venue"
},
  "geometry": {"coordinates":[175.04480000000001,-39.929855],"type":"Point"}
}