{
  "type": "Feature",
  "properties": {
    "addr:full":"6 Grassmere Rd Henderson  Auckland Auckland",
    "addr:housenumber":"6",
    "addr:street":"Grassmere Rd",
    "iso:country":"NZ",
    "sg:address":"6 Grassmere Rd Henderson ",
    "sg:city":"Auckland",
    "sg:classifiers":[
        {
            "category":"Personal",
            "subcategory":"Beauty Salon",
            "type":"Services"
        }
    ],
    "sg:phone":"+64 9-838 9573",
    "sg:province":"Auckland",
    "sg:tags":[
        "therapy",
        "health"
    ],
    "wof:name":"Sanctuary Beauty Therapy Studio",
    "wof:placetype":"venue"
},
  "geometry": {"coordinates":[174.63294999999999,-36.877289],"type":"Point"}
}