{
  "type": "Feature",
  "properties": {
    "addr:full":"16 Poutama St Richmond  Nelson Nelson",
    "addr:housenumber":"16",
    "addr:street":"Poutama St",
    "iso:country":"NZ",
    "sg:address":"16 Poutama St Richmond ",
    "sg:city":"Nelson",
    "sg:orig_category":"Home And Garden: Gardening: Products",
    "sg:phone":"+64 3-544 7965",
    "sg:province":"Nelson",
    "wof:name":"Mead Lew Farmquip Ltd",
    "wof:placetype":"venue"
},
  "geometry": {"coordinates":[173.17091400000001,-41.341583],"type":"Point"}
}