{
  "type": "Feature",
  "properties": {
    "iso:country":"NZ",
    "sg:address":"15/16 Weka St Otahuhu ",
    "sg:city":"Auckland",
    "sg:classifiers":[
        {
            "category":"Home & Garden",
            "subcategory":"Furniture",
            "type":"Retail Goods"
        }
    ],
    "sg:phone":"+64 9-276 2090",
    "sg:province":"Auckland",
    "sg:tags":[
        "furniture/furnishings",
        "repair",
        "finishing"
    ],
    "wof:name":"Roy Webber Ltd",
    "wof:placetype":"venue"
},
  "geometry": {"coordinates":[174.83609000000001,-36.951534],"type":"Point"}
}