{
  "type": "Feature",
  "properties": {
    "iso:country":"NZ",
    "sg:address":"Cambridge Rd ",
    "sg:city":"Hamilton",
    "sg:orig_category":"Shopping: Retail Stores: Books: Bookshops",
    "sg:phone":"+64 7-856 7937",
    "sg:province":"Waikato",
    "wof:name":"Major's Lotto & Post Shop",
    "wof:placetype":"venue"
},
  "geometry": {"coordinates":[175.309418,-37.797588],"type":"Point"}
}