{
  "type": "Feature",
  "properties": {
    "iso:country":"NZ",
    "sg:address":"159 Carnarvon St ",
    "sg:city":"Gisborne",
    "sg:classifiers":[
        {
            "category":"Retail",
            "subcategory":"Auto Repair",
            "type":"Services"
        }
    ],
    "sg:phone":"+64 6-867 8486",
    "sg:province":"Gisborne",
    "sg:tags":[
        "engine",
        "automotive",
        "diesel",
        "servicing"
    ],
    "wof:name":"Gisborne Diesel",
    "wof:placetype":"venue"
},
  "geometry": {"coordinates":[178.01589999999999,-38.663795],"type":"Point"}
}