{
  "type": "Feature",
  "properties": {
    "addr:full":"135 Carlton Gore Rd Newmarket  Auckland Auckland",
    "addr:housenumber":"135",
    "addr:street":"Carlton Gore Rd",
    "iso:country":"NZ",
    "sg:address":"135 Carlton Gore Rd Newmarket ",
    "sg:city":"Auckland",
    "sg:classifiers":[
        {
            "category":"Manufacturing",
            "subcategory":"Textiles",
            "type":"Manufacturing & Wholesale Goods"
        }
    ],
    "sg:phone":"+64 9-524 4306",
    "sg:province":"Auckland",
    "sg:tags":[
        "clothing",
        "fabric",
        "manufacturer"
    ],
    "wof:name":"Hart Manufacturing Ltd",
    "wof:placetype":"venue"
},
  "geometry": {"coordinates":[174.776993,-36.865402],"type":"Point"}
}