{
  "type": "Feature",
  "properties": {
    "iso:country":"NZ",
    "sg:address":"1/25 Tennyson St Petone Lower ",
    "sg:city":"Hutt",
    "sg:orig_category":"Sports And Leisure: Entertainment: Entertainers",
    "sg:phone":"+64 4-576 0300",
    "sg:province":"Wellington",
    "wof:name":"Murray Giblin",
    "wof:placetype":"venue"
},
  "geometry": {"coordinates":[174.890182,-41.225662],"type":"Point"}
}