{
  "type": "Feature",
  "properties": {
    "addr:full":"237 State Highway 2 Bethlehem  Tauranga Bay of Plenty",
    "addr:housenumber":"237",
    "addr:street":"State Highway 2",
    "iso:country":"NZ",
    "sg:address":"237 State Highway 2 Bethlehem ",
    "sg:city":"Tauranga",
    "sg:orig_category":"Automotive: Accessories: Towbars",
    "sg:phone":"+64 7-576 4799",
    "sg:province":"Bay of Plenty",
    "wof:name":"Bethlehem Motors",
    "wof:placetype":"venue"
},
  "geometry": {"coordinates":[176.109207,-37.695732],"type":"Point"}
}