{
  "type": "Feature",
  "properties": {
    "addr:full":"560 Cameron Rd  Tauranga Bay of Plenty",
    "addr:housenumber":"560",
    "addr:street":"Cameron Rd",
    "iso:country":"NZ",
    "sg:address":"560 Cameron Rd ",
    "sg:city":"Tauranga",
    "sg:orig_category":"Shopping: Retail Stores: Antiques",
    "sg:phone":"+64 7-577 0335",
    "sg:province":"Bay of Plenty",
    "wof:name":"Avenue Antiques & Collectables",
    "wof:placetype":"venue"
},
  "geometry": {"coordinates":[176.159042,-37.698898],"type":"Point"}
}