{
  "type": "Feature",
  "properties": {
    "addr:full":"1127 Pukuatua St  Rotorua Bay of Plenty",
    "addr:housenumber":"1127",
    "addr:street":"Pukuatua St",
    "iso:country":"NZ",
    "sg:address":"1127 Pukuatua St ",
    "sg:city":"Rotorua",
    "sg:orig_category":"Shopping: Accessories: Jewellers And Watchmakers",
    "sg:phone":"+64 7-347 3344",
    "sg:province":"Bay of Plenty",
    "wof:name":"Tahiti Pearl",
    "wof:placetype":"venue"
},
  "geometry": {"coordinates":[176.25285299999999,-38.136738],"type":"Point"}
}