{
  "type": "Feature",
  "properties": {
    "iso:country":"NZ",
    "sg:address":"339 Remuera Rd Remuera ",
    "sg:city":"Auckland",
    "sg:classifiers":[
        {
            "category":"Shopping",
            "subcategory":"Crafts & Fabrics",
            "type":"Retail Goods"
        }
    ],
    "sg:phone":"+64 9-520 1292",
    "sg:province":"Auckland",
    "sg:tags":[
        "foot",
        "clothing",
        "retailer",
        "footwear",
        "wear"
    ],
    "wof:name":"Carrano Shoes and Accessories",
    "wof:placetype":"venue"
},
  "geometry": {"coordinates":[174.79681400000001,-36.880756],"type":"Point"}
}