{
  "type": "Feature",
  "properties": {
    "iso:country":"NZ",
    "sg:address":"PO Box 111 ",
    "sg:city":"Matamata",
    "sg:orig_category":"Sports And Leisure: Sports: Equestrian: Stud Farms",
    "sg:phone":"+64 7-888 8887",
    "sg:province":"Waikato",
    "wof:name":"Paramount Lodge Ltd",
    "wof:placetype":"venue"
},
  "geometry": {"coordinates":[175.773544,-37.811764],"type":"Point"}
}