{
  "type": "Feature",
  "properties": {
    "iso:country":"NZ",
    "sg:address":"70 Eye St ",
    "sg:city":"Invercargill",
    "sg:classifiers":[
        {
            "category":"Banks & Credit Unions",
            "subcategory":"Investment Brokerage",
            "type":"Services"
        }
    ],
    "sg:phone":"+64 3-218 7905",
    "sg:province":"Southland",
    "sg:tags":[
        "educational",
        "education",
        "training"
    ],
    "wof:name":"Conductive Education - Focus",
    "wof:placetype":"venue"
},
  "geometry": {"coordinates":[168.352509,-46.416534],"type":"Point"}
}