{
  "type": "Feature",
  "properties": {
    "iso:country":"NZ",
    "sg:address":"7 Jarden Mle Ngauranga ",
    "sg:city":"Wellington",
    "sg:classifiers":[
        {
            "category":"Juice Bar",
            "subcategory":"None",
            "type":"Food & Drink"
        }
    ],
    "sg:phone":"+64 4-470 7731",
    "sg:province":"Wellington",
    "sg:tags":[
        "fruit",
        "processor",
        "veges"
    ],
    "wof:name":"Frucor Beverages Ltd",
    "wof:placetype":"venue"
},
  "geometry": {"coordinates":[174.811996,-41.247753],"type":"Point"}
}