{
  "type": "Feature",
  "properties": {
    "addr:full":"60 Bentley Ave Glenfield  Auckland Auckland",
    "addr:housenumber":"60",
    "addr:street":"Bentley Ave",
    "iso:country":"NZ",
    "sg:address":"60 Bentley Ave Glenfield ",
    "sg:city":"Auckland",
    "sg:orig_category":"Industrial: Equipment And Machinery: Specialist Equipment: Machinery: Sewing Machines",
    "sg:phone":"+64 9-444 5043",
    "sg:province":"Auckland",
    "wof:name":"Brian Deakin Sewing Machine Repairs",
    "wof:placetype":"venue"
},
  "geometry": {"coordinates":[174.724976,-36.781921],"type":"Point"}
}