{
  "type": "Feature",
  "properties": {
    "iso:country":"NZ",
    "sg:address":"39 Harrisfield Dve ",
    "sg:city":"Ohauiti",
    "sg:classifiers":[
        {
            "category":"Retail",
            "subcategory":"Auto Repair",
            "type":"Services"
        }
    ],
    "sg:phone":"+64 25530334",
    "sg:tags":[
        "mobile",
        "automotive",
        "servicing",
        "mechanic"
    ],
    "wof:name":"Autocraft Service Centre",
    "wof:placetype":"venue"
},
  "geometry": {"coordinates":[176.170181,-37.75882],"type":"Point"}
}