{
  "type": "Feature",
  "properties": {
    "addr:full":"79 Devonport Rd  Tauranga Auckland",
    "addr:housenumber":"79",
    "addr:street":"Devonport Rd",
    "iso:country":"NZ",
    "sg:address":"79 Devonport Rd ",
    "sg:city":"Tauranga",
    "sg:classifiers":[
        {
            "category":"Shopping",
            "subcategory":"Thrift Store",
            "type":"Retail Goods"
        }
    ],
    "sg:phone":"+64 7-578 7158",
    "sg:province":"Auckland",
    "sg:tags":[
        "-",
        "clothing",
        "secondhand",
        "fabric"
    ],
    "wof:name":"Sabotage",
    "wof:placetype":"venue"
},
  "geometry": {"coordinates":[176.16925000000001,-37.686062],"type":"Point"}
}