{
  "type": "Feature",
  "properties": {
    "addr:full":"201 Buckland Rd Mangere East  Auckland Auckland",
    "addr:housenumber":"201",
    "addr:street":"Buckland Rd",
    "iso:country":"NZ",
    "sg:address":"201 Buckland Rd Mangere East ",
    "sg:city":"Auckland",
    "sg:classifiers":[
        {
            "category":"Social Services",
            "subcategory":"Child Care",
            "type":"Services"
        }
    ],
    "sg:phone":"+64 9-275 1069",
    "sg:province":"Auckland",
    "sg:tags":[
        "home",
        "garden",
        "children"
    ],
    "wof:name":"Shiloh Children's Centre",
    "wof:placetype":"venue"
},
  "geometry": {"coordinates":[174.820099,-36.967339],"type":"Point"}
}