{
  "type": "Feature",
  "properties": {
    "iso:country":"NZ",
    "sg:address":"9 A Drury St New Lynn ",
    "sg:city":"Auckland",
    "sg:orig_category":"Industrial: Metal: Products: Tubular Steel Products",
    "sg:phone":"+64 9-827 2550",
    "sg:province":"Auckland",
    "wof:name":"James Hunter Engineering (1986) Ltd",
    "wof:placetype":"venue"
},
  "geometry": {"coordinates":[174.688293,-36.902691],"type":"Point"}
}