{
  "type": "Feature",
  "properties": {
    "addr:full":"30 Forest Dve  Methven",
    "addr:housenumber":"30",
    "addr:street":"Forest Dve Methven",
    "iso:country":"NZ",
    "sg:address":"30 Forest Dve ",
    "sg:city":"Methven",
    "sg:classifiers":[
        {
            "category":"Personal",
            "subcategory":"Massage",
            "type":"Services"
        }
    ],
    "sg:phone":"+64 3-302 8323",
    "sg:tags":[
        "services",
        "health",
        "-",
        "beauty",
        "fitness"
    ],
    "wof:name":"Methven Sports Massage Clinic",
    "wof:placetype":"venue"
},
  "geometry": {"coordinates":[171.644272,-43.631443],"type":"Point"}
}