{
  "type": "Feature",
  "properties": {
    "addr:full":"cnr Weka & Manuka Sts Miramar  Wellington Wellington",
    "addr:street":"Cnr",
    "iso:country":"NZ",
    "sg:address":"cnr Weka & Manuka Sts Miramar ",
    "sg:city":"Wellington",
    "sg:classifiers":[
        {
            "category":"Ice Cream",
            "type":"Food & Drink"
        }
    ],
    "sg:phone":"+64 4-388 2676",
    "sg:province":"Wellington",
    "sg:tags":[
        "-"
    ],
    "wof:name":"The New Zealand Ice Cream Co. Ltd",
    "wof:placetype":"venue"
},
  "geometry": {"coordinates":[174.818039,-41.311909],"type":"Point"}
}