{
  "type": "Feature",
  "properties": {
    "iso:country":"NZ",
    "sg:address":"Wainui Bay R D 1 ",
    "sg:city":"Takaka",
    "sg:classifiers":[
        {
            "category":"Farming",
            "subcategory":"Fish & Marine Products",
            "type":"Manufacturing & Wholesale Goods"
        }
    ],
    "sg:phone":"+64 3-525 9654",
    "sg:tags":[
        "health",
        "beauty"
    ],
    "wof:name":"Tui Balmes & Waxes",
    "wof:placetype":"venue"
},
  "geometry": {"coordinates":[172.80793800000001,-40.853374],"type":"Point"}
}