{
  "type": "Feature",
  "properties": {
    "addr:full":"3 Ferncroft St Grafton  Auckland Auckland",
    "addr:housenumber":"3",
    "addr:street":"Ferncroft St",
    "iso:country":"NZ",
    "sg:address":"3 Ferncroft St Grafton ",
    "sg:city":"Auckland",
    "sg:classifiers":[
        {
            "category":"Education",
            "subcategory":"University",
            "type":"Public Place"
        }
    ],
    "sg:phone":"+64 9-309 6559",
    "sg:province":"Auckland",
    "sg:tags":[
        "training",
        "college"
    ],
    "wof:name":"NZ Tertiary College",
    "wof:placetype":"venue"
},
  "geometry": {"coordinates":[174.76771500000001,-36.859135],"type":"Point"}
}