{
  "type": "Feature",
  "properties": {
    "iso:country":"NZ",
    "sg:address":"39 Olive Rd Penrose ",
    "sg:city":"Auckland",
    "sg:classifiers":[
        {
            "category":"Shopping",
            "subcategory":"Crafts & Fabrics",
            "type":"Retail Goods"
        }
    ],
    "sg:phone":"+64 9-579 9200",
    "sg:province":"Auckland",
    "sg:tags":[
        "clothing"
    ],
    "wof:name":"Icehouse NZ Ltd",
    "wof:placetype":"venue"
},
  "geometry": {"coordinates":[174.81135599999999,-36.909786],"type":"Point"}
}