{
  "type": "Feature",
  "properties": {
    "addr:full":"539 Mt Eden Rd Mt Eden  Auckland Auckland",
    "addr:housenumber":"539",
    "addr:street":"Mt Eden Rd",
    "iso:country":"NZ",
    "sg:address":"539 Mt Eden Rd Mt Eden ",
    "sg:city":"Auckland",
    "sg:orig_category":"Shopping: Retail Stores: Toys",
    "sg:phone":"+64 9-623 3132",
    "sg:province":"Auckland",
    "wof:name":"Educational Experience Stores",
    "wof:placetype":"venue"
},
  "geometry": {"coordinates":[174.76091,-36.886002],"type":"Point"}
}