{
  "type": "Feature",
  "properties": {
    "iso:country":"NZ",
    "sg:address":"41 Hunua Rd Papakura ",
    "sg:city":"Auckland",
    "sg:orig_category":"Industrial: Abrasives: Abrasive Blasting",
    "sg:phone":"+64 9-298 2038",
    "sg:province":"Auckland",
    "wof:name":"Papakura Abrasive Blasters",
    "wof:placetype":"venue"
},
  "geometry": {"coordinates":[174.970612,-37.076469],"type":"Point"}
}