{
  "type": "Feature",
  "properties": {
    "iso:country":"NZ",
    "sg:address":"11 A Bullen St Tahunanui ",
    "sg:city":"Nelson",
    "sg:classifiers":[
        {
            "category":"Food & Beverages",
            "subcategory":"Liquor & Beverages",
            "type":"Retail Goods"
        }
    ],
    "sg:phone":"+64 3-548 5140",
    "sg:province":"Nelson",
    "sg:tags":[
        "drink",
        "maker",
        "wine"
    ],
    "wof:name":"Montana Wines Limited",
    "wof:placetype":"venue"
},
  "geometry": {"coordinates":[173.244644,-41.283855],"type":"Point"}
}