{
  "type": "Feature",
  "properties": {
    "addr:full":"Aurere Rd Taipa R D 3 Kaitaia  Mangonui",
    "addr:housenumber":"3",
    "addr:street":"Aurere Rd;R D",
    "iso:country":"NZ",
    "sg:address":"Aurere Rd Taipa R D 3 Kaitaia ",
    "sg:city":"Mangonui",
    "sg:orig_category":"Transport: Transportation: Transport Operators",
    "sg:phone":"+64 9-406 0207",
    "wof:name":"Matthews Gordon",
    "wof:placetype":"venue"
},
  "geometry": {"coordinates":[173.52973900000001,-34.992897],"type":"Point"}
}