{
  "type": "Feature",
  "properties": {
    "iso:country":"NZ",
    "sg:address":"Clifford Rd Lake Grassmere ",
    "sg:city":"Blenheim",
    "sg:orig_category":"Travel And Tourism: Accommodation: Farmstays And Homestays",
    "sg:phone":"+64 3-575 7254",
    "sg:province":"Marlborough",
    "wof:name":"Clifford Bay Farmstay (Dorper Stud)",
    "wof:placetype":"venue"
},
  "geometry": {"coordinates":[174.132538,-41.724041],"type":"Point"}
}