{
  "type": "Feature",
  "properties": {
    "iso:country":"NZ",
    "sg:address":"21 Wilkinson St ",
    "sg:city":"Motueka",
    "sg:orig_category":"Health And Beauty: Beauty: Hairdressers",
    "sg:phone":"+64 3-528 7168",
    "sg:province":"Tasman",
    "wof:name":"Suzanne Hairdressing",
    "wof:placetype":"venue"
},
  "geometry": {"coordinates":[173.01422099999999,-41.111988],"type":"Point"}
}