{
  "type": "Feature",
  "properties": {
    "addr:full":"39 E Honan Pl Avondale  Auckland Auckland",
    "addr:housenumber":"39",
    "addr:street":"E Honan Pl",
    "iso:country":"NZ",
    "sg:address":"39 E Honan Pl Avondale ",
    "sg:city":"Auckland",
    "sg:orig_category":"Industrial: Services: Toolmakers And Designers",
    "sg:phone":"+64 9-828 4819",
    "sg:province":"Auckland",
    "wof:name":"Barnard Toolmaking & CNC Services Ltd",
    "wof:placetype":"venue"
},
  "geometry": {"coordinates":[174.690933,-36.8932],"type":"Point"}
}