{
  "type": "Feature",
  "properties": {
    "iso:country":"NZ",
    "sg:address":"Unit 2 23 Napier Rd Havelock North ",
    "sg:city":"Hastings",
    "sg:orig_category":"Food And Drink: Meats: Butchers' Supplies",
    "sg:phone":"+64 6-877 0236",
    "sg:province":"Hawke's Bay",
    "wof:name":"New Zealand By-Products Ltd",
    "wof:placetype":"venue"
},
  "geometry": {"coordinates":[176.878952,-39.66827],"type":"Point"}
}