{
  "type": "Feature",
  "properties": {
    "addr:full":"106 Hokonui Dve North Gore  Gore Southland",
    "addr:housenumber":"106",
    "addr:street":"Hokonui Dve North",
    "iso:country":"NZ",
    "sg:address":"106 Hokonui Dve North Gore ",
    "sg:city":"Gore",
    "sg:classifiers":[
        {
            "category":"Organizations",
            "subcategory":"Religious Organization",
            "type":"Services"
        }
    ],
    "sg:phone":"+64 3-208 6281",
    "sg:province":"Southland",
    "sg:tags":[
        "funeral",
        "arrangement"
    ],
    "wof:name":"McBride Bros Gore",
    "wof:placetype":"venue"
},
  "geometry": {"coordinates":[168.944534,-46.094173],"type":"Point"}
}