{
  "type": "Feature",
  "properties": {
    "iso:country":"NZ",
    "sg:address":"100 Mt Albert Rd Mt Albert ",
    "sg:city":"Auckland",
    "sg:classifiers":[
        {
            "category":"Sports & Exercise",
            "subcategory":"Skate Park",
            "type":"Entertainment"
        }
    ],
    "sg:phone":"+64 9-846 7367",
    "sg:province":"Auckland",
    "sg:tags":[
        "arts",
        "museum",
        "leisure",
        "gallery"
    ],
    "wof:name":"Alberton",
    "wof:placetype":"venue"
},
  "geometry": {"coordinates":[174.724487,-36.890373],"type":"Point"}
}