{
  "type": "Feature",
  "properties": {
    "addr:full":"17 Cartwright Rd Glen Eden  Auckland Auckland",
    "addr:housenumber":"17",
    "addr:street":"Cartwright Rd",
    "iso:country":"NZ",
    "sg:address":"17 Cartwright Rd Glen Eden ",
    "sg:city":"Auckland",
    "sg:orig_category":"Industrial: Coatings",
    "sg:phone":"+64 9-818 6883",
    "sg:province":"Auckland",
    "wof:name":"Component Powder Coating",
    "wof:placetype":"venue"
},
  "geometry": {"coordinates":[174.65806599999999,-36.90239],"type":"Point"}
}