{
  "type": "Feature",
  "properties": {
    "addr:full":"209 B Rifle Range Rd  Taupo Waikato",
    "addr:housenumber":"209 b",
    "addr:street":"Rifle Range Rd",
    "iso:country":"NZ",
    "sg:address":"209 B Rifle Range Rd ",
    "sg:city":"Taupo",
    "sg:classifiers":[
        {
            "category":"Manufacturing",
            "subcategory":"Tools & Machinery",
            "type":"Manufacturing & Wholesale Goods"
        }
    ],
    "sg:phone":"+64 7-378 0522",
    "sg:province":"Waikato",
    "sg:tags":[
        "equipment",
        "industrial",
        "hydraulic"
    ],
    "wof:name":"Pirtek Taupo Ltd",
    "wof:placetype":"venue"
},
  "geometry": {"coordinates":[176.095947,-38.684025],"type":"Point"}
}