{
  "type": "Feature",
  "properties": {
    "iso:country":"NZ",
    "sg:address":"Dinsdale Shopping Complex, Whatawhata Rd ",
    "sg:city":"Hamilton",
    "sg:orig_category":"Shopping: Hobbies And Games: Handcrafts",
    "sg:phone":"+64 7-847 7257",
    "sg:province":"Waikato",
    "wof:name":"Dinsdale Needlecraft",
    "wof:placetype":"venue"
},
  "geometry": {"coordinates":[175.24191300000001,-37.795715],"type":"Point"}
}