{
  "type": "Feature",
  "properties": {
    "addr:full":"10 Amokura St Henderson  Auckland Auckland",
    "addr:housenumber":"10",
    "addr:street":"Amokura St",
    "iso:country":"NZ",
    "sg:address":"10 Amokura St Henderson ",
    "sg:city":"Auckland",
    "sg:classifiers":[
        {
            "category":"Home & Garden",
            "subcategory":"Furniture",
            "type":"Retail Goods"
        }
    ],
    "sg:phone":"+64 9-838 8255",
    "sg:province":"Auckland",
    "sg:tags":[
        "furniture/furnishings",
        "furnishing"
    ],
    "sg:website":"http://www.coni.co.nz",
    "wof:name":"Coni Products",
    "wof:placetype":"venue"
},
  "geometry": {"coordinates":[174.625519,-36.886536],"type":"Point"}
}