{
  "type": "Feature",
  "properties": {
    "addr:full":"37 Herekino St  Whangarei Northland",
    "addr:housenumber":"37",
    "addr:street":"Herekino St",
    "iso:country":"NZ",
    "sg:address":"37 Herekino St ",
    "sg:city":"Whangarei",
    "sg:orig_category":"Transport: Transportation: Courier Services",
    "sg:phone":"+64 9-430 2396",
    "sg:province":"Northland",
    "wof:name":"Post Haste Couriers",
    "wof:placetype":"venue"
},
  "geometry": {"coordinates":[174.329758,-35.728367],"type":"Point"}
}