{
  "type": "Feature",
  "properties": {
    "iso:country":"NZ",
    "sg:address":"27 Maleme St ",
    "sg:city":"Tauranga",
    "sg:classifiers":[
        {
            "category":"Utilities",
            "subcategory":"Sewage",
            "type":"Services"
        }
    ],
    "sg:phone":"+64 7-541 3402",
    "sg:province":"Bay of Plenty",
    "sg:tags":[
        "home",
        "tank",
        "garden",
        "septic"
    ],
    "sg:website":"http://www.petestakeaways.co.nz",
    "wof:name":"Pete's Takeaways Ltd",
    "wof:placetype":"venue"
},
  "geometry": {"coordinates":[176.138138,-37.736385],"type":"Point"}
}