{
  "type": "Feature",
  "properties": {
    "iso:country":"NZ",
    "sg:address":"512 Main Rd Stoke ",
    "sg:city":"Nelson",
    "sg:orig_category":"Health And Beauty: Products: Pharmacies",
    "sg:phone":"+64 3-547 9689",
    "sg:province":"Nelson",
    "wof:name":"Hurst & Taylor Ltd",
    "wof:placetype":"venue"
},
  "geometry": {"coordinates":[173.23422199999999,-41.312756],"type":"Point"}
}