{
  "type": "Feature",
  "properties": {
    "iso:country":"NZ",
    "sg:address":"Napier PO Box 5067 Greenmeadows ",
    "sg:city":"Napier",
    "sg:classifiers":[
        {
            "category":"Home & Garden",
            "subcategory":"Carpets & Floor Coverings",
            "type":"Retail Goods"
        }
    ],
    "sg:phone":"+64 6-843 6440",
    "sg:province":"Hawke's Bay",
    "sg:tags":[
        "cleaning",
        "furniture"
    ],
    "wof:name":"Carpet Services Hawkes Bay",
    "wof:placetype":"venue"
},
  "geometry": {"coordinates":[176.916428,-39.49107],"type":"Point"}
}