{
  "type": "Feature",
  "properties": {
    "addr:full":"140 Hillsborough Rd Hillsborough  Auckland Auckland",
    "addr:housenumber":"140",
    "addr:street":"Hillsborough Rd",
    "iso:country":"NZ",
    "sg:address":"140 Hillsborough Rd Hillsborough ",
    "sg:city":"Auckland",
    "sg:classifiers":[
        {
            "category":"Health Services",
            "subcategory":"Health Practitioner",
            "type":"Services"
        }
    ],
    "sg:phone":"+64 9-625 5283",
    "sg:province":"Auckland",
    "sg:tags":[
        "services",
        "beauty",
        "acupuncturists"
    ],
    "wof:name":"Chinese Acupuncturist",
    "wof:placetype":"venue"
},
  "geometry": {"coordinates":[174.75808699999999,-36.91946],"type":"Point"}
}