{
  "type": "Feature",
  "properties": {
    "iso:country":"NZ",
    "sg:address":"110 Main St Upper ",
    "sg:city":"Hutt",
    "sg:classifiers":[
        {
            "category":"Shopping",
            "subcategory":"Shoes",
            "type":"Retail Goods"
        }
    ],
    "sg:phone":"+64 4-528 2254",
    "sg:province":"Wellington",
    "sg:tags":[
        "foot",
        "clothing",
        "fabric",
        "wear"
    ],
    "wof:name":"Wheeler Angus Ltd",
    "wof:placetype":"venue"
},
  "geometry": {"coordinates":[175.070358,-41.124577],"type":"Point"}
}