{
  "type": "Feature",
  "properties": {
    "iso:country":"NZ",
    "sg:address":"343 Thames Highway ",
    "sg:city":"Oamaru",
    "sg:classifiers":[
        {
            "category":"Banks & Credit Unions",
            "subcategory":"Financial Services",
            "type":"Services"
        }
    ],
    "sg:phone":"+64 800 100 097",
    "sg:province":"Otago",
    "sg:tags":[
        "personal",
        "loan",
        "-",
        "finance",
        "mortgage"
    ],
    "wof:name":"Mortgage Choice",
    "wof:placetype":"venue"
},
  "geometry": {"coordinates":[170.97662353519999,-45.0871276855],"type":"Point"}
}