{
  "type": "Feature",
  "properties": {
    "addr:full":"Ballantynes Building Canon St  Timaru Canterbury",
    "addr:street":"Canon St",
    "iso:country":"NZ",
    "sg:address":"Ballantynes Building Canon St ",
    "sg:city":"Timaru",
    "sg:classifiers":[
        {
            "category":"Banks & Credit Unions",
            "subcategory":"Financial Services",
            "type":"Services"
        }
    ],
    "sg:phone":"+64 3-688 5517",
    "sg:province":"Canterbury",
    "sg:tags":[
        "personal",
        "loan",
        "-",
        "finance",
        "mortgage"
    ],
    "wof:name":"LifeSpan Mortgages Ltd",
    "wof:placetype":"venue"
},
  "geometry": {"coordinates":[171.23741100000001,-44.395428],"type":"Point"}
}