{
  "type": "Feature",
  "properties": {
    "addr:full":"31 Malden St Palmerston  Palmerston North Manawatu-Wanganui",
    "addr:housenumber":"31",
    "addr:street":"Malden St Palmerston",
    "iso:country":"NZ",
    "sg:address":"31 Malden St Palmerston ",
    "sg:city":"Palmerston North",
    "sg:orig_category":"Industrial: Metal: Services: Steel Processing",
    "sg:phone":"+64 6-355 0899",
    "sg:province":"Manawatu-Wanganui",
    "wof:name":"Steel & Tube Reinforcing",
    "wof:placetype":"venue"
},
  "geometry": {"coordinates":[175.62167400000001,-40.332542],"type":"Point"}
}