{
  "type": "Feature",
  "properties": {
    "addr:full":"37 Opaheke Rd Papakura  Auckland Auckland",
    "addr:housenumber":"37",
    "addr:street":"Opaheke Rd",
    "iso:country":"NZ",
    "sg:address":"37 Opaheke Rd Papakura ",
    "sg:city":"Auckland",
    "sg:orig_category":"Shopping: Retail Stores: Supermarkets",
    "sg:phone":"+64 9-298 4537",
    "sg:province":"Auckland",
    "wof:name":"Opaheke Supermarket",
    "wof:placetype":"venue"
},
  "geometry": {"coordinates":[174.94738799999999,-37.073143],"type":"Point"}
}