{
  "type": "Feature",
  "properties": {
    "addr:full":"33 Huia Rd Otahuhu  Auckland Auckland",
    "addr:housenumber":"33",
    "addr:street":"Huia Rd",
    "iso:country":"NZ",
    "sg:address":"33 Huia Rd Otahuhu ",
    "sg:city":"Auckland",
    "sg:orig_category":"Home And Garden: Gardening: Products: Outdoor Furniture",
    "sg:phone":"+64 9-276 4342",
    "sg:province":"Auckland",
    "wof:name":"Casual Living",
    "wof:placetype":"venue"
},
  "geometry": {"coordinates":[174.83770799999999,-36.941097],"type":"Point"}
}