{
  "type": "Feature",
  "properties": {
    "iso:country":"NZ",
    "sg:address":"59 Higgins Rd ",
    "sg:city":"Hamilton",
    "sg:orig_category":"Industrial: Consultancy: Product Designers",
    "sg:phone":"+64 7-846 0617",
    "sg:province":"Waikato",
    "sg:website":"http://www.esplastics.co.nz",
    "wof:name":"ES Plastics Ltd",
    "wof:placetype":"venue"
},
  "geometry": {"coordinates":[-87.988968,34.142426],"type":"Point"}
}