{
  "type": "Feature",
  "properties": {
    "addr:full":"348 Hardy St  Nelson Nelson",
    "addr:housenumber":"348",
    "addr:street":"Hardy St",
    "iso:country":"NZ",
    "sg:address":"348 Hardy St ",
    "sg:city":"Nelson",
    "sg:classifiers":[
        {
            "category":"Health Services",
            "subcategory":"Dentist",
            "type":"Services"
        }
    ],
    "sg:phone":"+64 3-548 4601",
    "sg:province":"Nelson",
    "sg:tags":[
        "dental",
        "beauty"
    ],
    "wof:name":"Hay P C",
    "wof:placetype":"venue"
},
  "geometry": {"coordinates":[173.29063400000001,-41.27459],"type":"Point"}
}