{
  "type": "Feature",
  "properties": {
    "iso:country":"NZ",
    "sg:address":"Taupo Rd S H 1 ",
    "sg:city":"Putaruru",
    "sg:classifiers":[
        {
            "category":"Sports & Exercise",
            "subcategory":"Skate Park",
            "type":"Entertainment"
        }
    ],
    "sg:phone":"+64 7-883 7621",
    "sg:tags":[
        "arts",
        "museum",
        "leisure",
        "gallery"
    ],
    "wof:name":"Putaruru Timber Museum Society Inc",
    "wof:placetype":"venue"
},
  "geometry": {"coordinates":[175.78526299999999,-38.056492],"type":"Point"}
}