{
  "type": "Feature",
  "properties": {
    "addr:full":"31 Main St Upper  Hutt Wellington",
    "addr:housenumber":"31",
    "addr:street":"Main St",
    "iso:country":"NZ",
    "sg:address":"31 Main St Upper ",
    "sg:city":"Hutt",
    "sg:classifiers":[
        {
            "category":"Restaurant",
            "type":"Food & Drink"
        }
    ],
    "sg:phone":"+64 4-528 9674",
    "sg:province":"Wellington",
    "sg:tags":[
        "wining",
        "dining",
        "pizza"
    ],
    "wof:name":"Pizza Haven",
    "wof:placetype":"venue"
},
  "geometry": {"coordinates":[175.067612,-41.12458],"type":"Point"}
}