{
  "type": "Feature",
  "properties": {
    "iso:country":"NZ",
    "sg:address":"457 Linwood Ave Bromley ",
    "sg:city":"Christchurch",
    "sg:classifiers":[
        {
            "category":"Professional",
            "subcategory":"Detective & Security Services",
            "type":"Services"
        }
    ],
    "sg:phone":"+64 3-389 5919",
    "sg:province":"Canterbury",
    "sg:tags":[
        "services",
        "automotive",
        "warrant",
        "fitness"
    ],
    "wof:name":"BP Linwood Ave",
    "wof:placetype":"venue"
},
  "geometry": {"coordinates":[172.68751499999999,-43.54211],"type":"Point"}
}