{
  "type": "Feature",
  "properties": {
    "addr:full":"Wiroa Rd  Kerikeri Northland",
    "addr:street":"Wiroa Rd",
    "iso:country":"NZ",
    "sg:address":"Wiroa Rd ",
    "sg:city":"Kerikeri",
    "sg:orig_category":"Travel And Tourism: Accommodation: Hostels",
    "sg:phone":"+64 9-407 9773",
    "sg:province":"Northland",
    "wof:name":"Hideaway Lodge Motor Camp",
    "wof:placetype":"venue"
},
  "geometry": {"coordinates":[173.90862999999999,-35.265858],"type":"Point"}
}