{
  "type": "Feature",
  "properties": {
    "addr:full":"183 Morrin Rd Panmure  Auckland Auckland",
    "addr:housenumber":"183",
    "addr:street":"Morrin Rd",
    "iso:country":"NZ",
    "sg:address":"183 Morrin Rd Panmure ",
    "sg:city":"Auckland",
    "sg:classifiers":[
        {
            "category":"Retail",
            "subcategory":"Auto Repair",
            "type":"Services"
        }
    ],
    "sg:phone":"+64 9-527 6079",
    "sg:province":"Auckland",
    "sg:tags":[
        "clutch",
        "brake",
        "servicing",
        "automotive"
    ],
    "wof:name":"Morrin Rd Automotive",
    "wof:placetype":"venue"
},
  "geometry": {"coordinates":[174.85749799999999,-36.90181],"type":"Point"}
}