{
  "type": "Feature",
  "properties": {
    "iso:country":"NZ",
    "sg:address":"Cnr Madras & Cashel St ",
    "sg:city":"Christchurch",
    "sg:classifiers":[
        {
            "category":"Communications",
            "subcategory":"Radio Station",
            "type":"Services"
        }
    ],
    "sg:phone":"+64 3-379 4408",
    "sg:province":"Canterbury",
    "sg:tags":[
        "broadcasting"
    ],
    "wof:name":"Radio Canterbury on Air",
    "wof:placetype":"venue"
},
  "geometry": {"coordinates":[-76.537834,37.605659],"type":"Point"}
}