{
  "type": "Feature",
  "properties": {
    "addr:full":"191 Upper Symonds St Auckland Central  Auckland Auckland",
    "addr:housenumber":"191",
    "addr:street":"Upper Symonds St",
    "iso:country":"NZ",
    "sg:address":"191 Upper Symonds St Auckland Central ",
    "sg:city":"Auckland",
    "sg:classifiers":[
        {
            "category":"Personal",
            "subcategory":"Shoe Repair & Shine",
            "type":"Services"
        }
    ],
    "sg:phone":"+64 9-379 0322",
    "sg:province":"Auckland",
    "sg:tags":[
        "foot",
        "clothing",
        "fabric",
        "wear"
    ],
    "wof:name":"Gemmell's Footwear",
    "wof:placetype":"venue"
},
  "geometry": {"coordinates":[174.76454200000001,-36.848358],"type":"Point"}
}