{
  "type": "Feature",
  "properties": {
    "iso:country":"NZ",
    "sg:address":"Russ Cnr R D 1 Richmond ",
    "sg:city":"Nelson",
    "sg:classifiers":[
        {
            "category":"Home & Garden",
            "subcategory":"Garden Supply",
            "type":"Retail Goods"
        }
    ],
    "sg:phone":"+64 3-544 2713",
    "sg:province":"Nelson",
    "sg:tags":[
        "products",
        "nursery",
        "gardening"
    ],
    "wof:name":"Lambourne Marketing Ltd",
    "wof:placetype":"venue"
},
  "geometry": {"coordinates":[-92.942902,39.068924],"type":"Point"}
}