{
  "type": "Feature",
  "properties": {
    "addr:full":"39 C Rennie Dve Mangere  Auckland Auckland",
    "addr:housenumber":"39 c;mangere",
    "addr:street":"Rennie Dve",
    "iso:country":"NZ",
    "sg:address":"39 C Rennie Dve Mangere ",
    "sg:city":"Auckland",
    "sg:classifiers":[
        {
            "category":"Home & Garden",
            "subcategory":"Garden Supply",
            "type":"Retail Goods"
        }
    ],
    "sg:phone":"+64 9-256 0661",
    "sg:province":"Auckland",
    "sg:tags":[
        "pet",
        "food",
        "pets"
    ],
    "wof:name":"Royal Canin Premium Pet Foods Ltd",
    "wof:placetype":"venue"
},
  "geometry": {"coordinates":[174.77950999999999,-36.979286],"type":"Point"}
}