{
  "type": "Feature",
  "properties": {
    "addr:full":"308 Hibiscus Coast Hwy Orewa Hibiscus  Hibiscus Coast Auckland",
    "addr:housenumber":"308",
    "addr:street":"Hibiscus Coast Hwy",
    "iso:country":"NZ",
    "sg:address":"308 Hibiscus Coast Hwy Orewa Hibiscus ",
    "sg:city":"Hibiscus Coast",
    "sg:orig_category":"Shopping: Retail Stores: Cds, Cassettes And Records",
    "sg:phone":"+64 9-426 3272",
    "sg:province":"Auckland",
    "wof:name":"Fast Forward Music",
    "wof:placetype":"venue"
},
  "geometry": {"coordinates":[174.69012499999999,-36.582741],"type":"Point"}
}