{
  "type": "Feature",
  "properties": {
    "addr:full":"Gresson St  Greymouth West Coast",
    "addr:street":"St",
    "iso:country":"NZ",
    "sg:address":"Gresson St ",
    "sg:city":"Greymouth",
    "sg:classifiers":[
        {
            "category":"Restaurant",
            "type":"Food & Drink"
        }
    ],
    "sg:phone":"+64 3-768 7962",
    "sg:province":"West Coast",
    "sg:tags":[
        "sea"
    ],
    "wof:name":"Greymouth Wholesale Fish & Oyster Co",
    "wof:placetype":"venue"
},
  "geometry": {"coordinates":[171.20387299999999,-42.447323],"type":"Point"}
}