{
  "type": "Feature",
  "properties": {
    "iso:country":"NZ",
    "sg:address":"47 Lorne St ",
    "sg:city":"Morrinsville",
    "sg:orig_category":"Farming: Services: Veterinarians",
    "sg:phone":"+64 7-889 0414",
    "sg:province":"Waikato",
    "wof:name":"VisserVets",
    "wof:placetype":"venue"
},
  "geometry": {"coordinates":[175.52767900000001,-37.659504],"type":"Point"}
}