{
  "type": "Feature",
  "properties": {
    "iso:country":"NZ",
    "sg:address":"34 Auckland St ",
    "sg:city":"Picton",
    "sg:orig_category":"Travel And Tourism: Accommodation: Backpackers",
    "sg:phone":"+64 3-573 6598",
    "sg:province":"Marlborough",
    "wof:name":"The Villa Backpackers Lodge",
    "wof:placetype":"venue"
},
  "geometry": {"coordinates":[174.00593599999999,-41.291801],"type":"Point"}
}