{
  "type": "Feature",
  "properties": {
    "iso:country":"NZ",
    "sg:address":"243 Ohiwa Beach Rd ",
    "sg:city":"Opotiki",
    "sg:classifiers":[
        {
            "category":"Travel",
            "subcategory":"Bed & Breakfast",
            "type":"Entertainment"
        }
    ],
    "sg:phone":"+64 7-315 4782",
    "sg:tags":[
        "tourism",
        "accommodation"
    ],
    "wof:name":"Ani's Beach Hideaway",
    "wof:placetype":"venue"
},
  "geometry": {"coordinates":[177.28581237789999,-38.0102577209],"type":"Point"}
}