{
  "type": "Feature",
  "properties": {
    "iso:country":"NZ",
    "sg:address":"345 Fenton St ",
    "sg:city":"Rotorua",
    "sg:classifiers":[
        {
            "category":"Travel",
            "subcategory":"Hotels & Motels",
            "type":"Entertainment"
        }
    ],
    "sg:phone":"+64 7-347 7879",
    "sg:province":"Bay of Plenty",
    "sg:tags":[
        "tourism",
        "accommodation"
    ],
    "sg:website":"http://www.yellowpages.co.nz/for/wyliecourt/dp35087.html",
    "wof:name":"Wylie Court Motor Lodge",
    "wof:placetype":"venue"
},
  "geometry": {"coordinates":[176.253632,-38.155365],"type":"Point"}
}