{
  "type": "Feature",
  "properties": {
    "iso:country":"NZ",
    "sg:address":"396 Main St Palmerston ",
    "sg:city":"Palmerston North",
    "sg:classifiers":[
        {
            "category":"Sports & Exercise",
            "subcategory":"Skate Park",
            "type":"Entertainment"
        }
    ],
    "sg:phone":"+64 6-355 5000",
    "sg:province":"Manawatu-Wanganui",
    "sg:tags":[
        "arts",
        "museum",
        "leisure",
        "gallery"
    ],
    "wof:name":"Te Manawa Museum Gallery Science Centre",
    "wof:placetype":"venue"
},
  "geometry": {"coordinates":[175.609772,-40.356895],"type":"Point"}
}