{
  "type": "Feature",
  "properties": {
    "iso:country":"NZ",
    "sg:address":"47 Clyde St ",
    "sg:city":"Ohakune",
    "sg:classifiers":[
        {
            "category":"Restaurant",
            "type":"Food & Drink"
        }
    ],
    "sg:phone":"+64 6-385 9120",
    "sg:tags":[
        "wining",
        "dining"
    ],
    "wof:name":"Utopia Cafe",
    "wof:placetype":"venue"
},
  "geometry": {"coordinates":[175.39721700000001,-39.414413],"type":"Point"}
}