{
  "type": "Feature",
  "properties": {
    "addr:full":"246 Apirana Ave Glen Innes  Auckland Auckland",
    "addr:housenumber":"246",
    "addr:street":"Apirana Ave",
    "iso:country":"NZ",
    "sg:address":"246 Apirana Ave Glen Innes ",
    "sg:city":"Auckland",
    "sg:orig_category":"Food And Drink: Meats: Butchers",
    "sg:phone":"+64 9-521 1452",
    "sg:province":"Auckland",
    "wof:name":"Avons Butchery Ltd",
    "wof:placetype":"venue"
},
  "geometry": {"coordinates":[174.85269199999999,-36.87183],"type":"Point"}
}