{
  "type": "Feature",
  "properties": {
    "addr:full":"131 Lincoln Road - Henderson - P.O. Box 83 - 200 -  Auckland Auckland",
    "addr:housenumber":"131;p.o. box 83 200",
    "addr:street":"Lincoln Road",
    "iso:country":"NZ",
    "sg:address":"131 Lincoln Road - Henderson - P.O. Box 83 - 200 - ",
    "sg:city":"Auckland",
    "sg:classifiers":[
        {
            "category":"Professional",
            "subcategory":"Art Services",
            "type":"Services"
        }
    ],
    "sg:phone":"+64 6498365581",
    "sg:province":"Auckland",
    "sg:tags":[
        "export-import"
    ],
    "wof:name":"Croatia Consulate General Honorary",
    "wof:placetype":"venue"
},
  "geometry": {"coordinates":[174.77041600000001,-36.884109],"type":"Point"}
}