{
  "type": "Feature",
  "properties": {
    "addr:full":"38 Soldiers Rd Ohau  Manakau Wellington",
    "addr:housenumber":"38",
    "addr:street":"Soldiers Rd",
    "iso:country":"NZ",
    "sg:address":"38 Soldiers Rd Ohau ",
    "sg:city":"Manakau",
    "sg:orig_category":"Home And Garden: Gardening: Products: Fertilisers",
    "sg:phone":"+64 6-362 6062",
    "sg:province":"Wellington",
    "wof:name":"Page Spreaders",
    "wof:placetype":"venue"
},
  "geometry": {"coordinates":[175.21729999999999,-40.71666],"type":"Point"}
}