{
  "type": "Feature",
  "properties": {
    "addr:full":"16 Aetna Pl Henderson  Auckland Auckland",
    "addr:housenumber":"16",
    "addr:street":"Aetna Pl",
    "iso:country":"NZ",
    "sg:address":"16 Aetna Pl Henderson ",
    "sg:city":"Auckland",
    "sg:classifiers":[
        {
            "category":"Manufacturing",
            "subcategory":"Glass & Minerals",
            "type":"Manufacturing & Wholesale Goods"
        }
    ],
    "sg:phone":"+64 9-837 0897",
    "sg:province":"Auckland",
    "sg:tags":[
        "chemical",
        "paint",
        "industrial",
        "manufacturer",
        "compounds"
    ],
    "wof:name":"Coating Technologies Ltd",
    "wof:placetype":"venue"
},
  "geometry": {"coordinates":[174.63294999999999,-36.877289],"type":"Point"}
}