{
  "type": "Feature",
  "properties": {
    "addr:full":"70 Walls Rd Penrose  Auckland Auckland",
    "addr:housenumber":"70",
    "addr:street":"Walls Rd",
    "iso:country":"NZ",
    "sg:address":"70 Walls Rd Penrose ",
    "sg:city":"Auckland",
    "sg:orig_category":"Automotive: Accessories: Car Security Systems",
    "sg:phone":"+64 9-579 8554",
    "sg:province":"Auckland",
    "wof:name":"P K Auto Electrical Ltd",
    "wof:placetype":"venue"
},
  "geometry": {"coordinates":[174.806015,-36.909817],"type":"Point"}
}