{
  "type": "Feature",
  "properties": {
    "addr:full":"99 Kiripaka Rd  Whangarei Northland",
    "addr:housenumber":"99",
    "addr:street":"Kiripaka Rd",
    "iso:country":"NZ",
    "sg:address":"99 Kiripaka Rd ",
    "sg:city":"Whangarei",
    "sg:classifiers":[
        {
            "category":"Health Services",
            "subcategory":"Clinic",
            "type":"Services"
        }
    ],
    "sg:phone":"+64 9-437 0733",
    "sg:province":"Northland",
    "sg:tags":[
        "medical",
        "beauty"
    ],
    "wof:name":"Tikipunga Medical Centre",
    "wof:placetype":"venue"
},
  "geometry": {"coordinates":[174.326965,-35.691727],"type":"Point"}
}