{
  "type": "Feature",
  "properties": {
    "iso:country":"NZ",
    "sg:address":"606 Pioneer Hwy Palmerston ",
    "sg:city":"Palmerston North",
    "sg:classifiers":[
        {
            "category":"Travel",
            "subcategory":"Bed & Breakfast",
            "type":"Entertainment"
        }
    ],
    "sg:phone":"+64 6-353 8606",
    "sg:province":"Manawatu-Wanganui",
    "sg:tags":[
        "tourism",
        "accommodation"
    ],
    "wof:name":"Pumpernickel Bed & Breakfast",
    "wof:placetype":"venue"
},
  "geometry": {"coordinates":[175.587387,-40.367115],"type":"Point"}
}