{
  "type": "Feature",
  "properties": {
    "addr:full":"19 Lancaster St  Lawrence",
    "addr:housenumber":"19",
    "addr:street":"Lancaster St",
    "iso:country":"NZ",
    "sg:address":"19 Lancaster St ",
    "sg:city":"Lawrence",
    "sg:classifiers":[
        {
            "category":"Home & Garden",
            "subcategory":"Garden Supply",
            "type":"Retail Goods"
        }
    ],
    "sg:phone":"+64 3-485 9278",
    "sg:tags":[
        "fencing",
        "outdoor",
        "contractor"
    ],
    "wof:name":"MacDonald R W & B J",
    "wof:placetype":"venue"
},
  "geometry": {"coordinates":[169.68630999999999,-45.914314],"type":"Point"}
}