{
  "type": "Feature",
  "properties": {
    "iso:country":"NZ",
    "sg:address":"Level 4 CSI House 168 Featherston St ",
    "sg:city":"Wellington",
    "sg:orig_category":"Health And Beauty: Specialists: Osteopaths",
    "sg:phone":"+64 4-499 1439",
    "sg:province":"Wellington",
    "wof:name":"City Osteopaths",
    "wof:placetype":"venue"
},
  "geometry": {"coordinates":[174.76715100000001,-41.28054],"type":"Point"}
}