{
  "type": "Feature",
  "properties": {
    "addr:full":"28 A Moreau St St Kilda  Dunedin Otago",
    "addr:housenumber":"28",
    "addr:street":"A Moreau St",
    "iso:country":"NZ",
    "sg:address":"28 A Moreau St St Kilda ",
    "sg:city":"Dunedin",
    "sg:classifiers":[
        {
            "category":"Manufacturing",
            "subcategory":"Furniture",
            "type":"Manufacturing & Wholesale Goods"
        }
    ],
    "sg:phone":"+64 3-455 9487",
    "sg:province":"Otago",
    "sg:tags":[
        "furniture/furnishings",
        "home",
        "garden",
        "manufacturer"
    ],
    "wof:name":"R-Teez Furniture & Machining",
    "wof:placetype":"venue"
},
  "geometry": {"coordinates":[170.49821499999999,-45.903713],"type":"Point"}
}