{
  "type": "Feature",
  "properties": {
    "iso:country":"NZ",
    "sg:address":"5 Cambridge St Tawa ",
    "sg:city":"Wellington",
    "sg:classifiers":[
        {
            "category":"Landmark",
            "subcategory":"Tourist Information",
            "type":"Public Place"
        }
    ],
    "sg:phone":"+64 4-232 3333",
    "sg:province":"Wellington",
    "sg:tags":[
        "services",
        "travel",
        "tourism"
    ],
    "wof:name":"Tawa Community Resource Centre",
    "wof:placetype":"venue"
},
  "geometry": {"coordinates":[174.82550000000001,-41.170963],"type":"Point"}
}