{
  "type": "Feature",
  "properties": {
    "iso:country":"NZ",
    "sg:address":"27 Clive Sq ",
    "sg:city":"Napier",
    "sg:orig_category":"Health And Beauty: Dental: Dentists",
    "sg:phone":"+64 6-835 8169",
    "sg:province":"Hawke's Bay",
    "wof:name":"Longly S M",
    "wof:placetype":"venue"
},
  "geometry": {"coordinates":[-80.588562,38.790821],"type":"Point"}
}