{
  "type": "Feature",
  "properties": {
    "iso:country":"NZ",
    "sg:address":"81 Jeffries Rd Rapaura R D 3 ",
    "sg:city":"Blenheim",
    "sg:classifiers":[
        {
            "category":"Winery",
            "type":"Food & Drink"
        }
    ],
    "sg:phone":"+64 3-572 8770",
    "sg:province":"Marlborough",
    "sg:tags":[
        "wining",
        "vineyard",
        "dining"
    ],
    "sg:website":"http://www.herzog.co.nz",
    "wof:name":"Herzog Restaurant & Winery",
    "wof:placetype":"venue"
},
  "geometry": {"coordinates":[173.957291,-41.513084],"type":"Point"}
}