{
  "type": "Feature",
  "properties": {
    "iso:country":"NZ",
    "sg:address":"43 Matai St ",
    "sg:city":"Taupo",
    "sg:classifiers":[
        {
            "category":"Education",
            "subcategory":"Special Training",
            "type":"Public Place"
        }
    ],
    "sg:phone":"+64 7-377 6570",
    "sg:province":"Waikato",
    "sg:tags":[
        "school",
        "swimming"
    ],
    "wof:name":"Emile Palmers School of Swimming",
    "wof:placetype":"venue"
},
  "geometry": {"coordinates":[176.10282900000001,-38.688564],"type":"Point"}
}