{
  "type": "Feature",
  "properties": {
    "iso:country":"NZ",
    "sg:address":"86 Paragon Ave Beach Haven ",
    "sg:city":"Auckland",
    "sg:orig_category":"Industrial: Electrical/Electronic: Electrical Switchgear",
    "sg:phone":"+64 9-482 0684",
    "sg:province":"Auckland",
    "sg:website":"http://www.leestechnology.com",
    "wof:name":"Lees Technology Ltd",
    "wof:placetype":"venue"
},
  "geometry": {"coordinates":[174.690811,-36.785015],"type":"Point"}
}