{
  "type": "Feature",
  "properties": {
    "addr:full":"Kelburn Pde PO Box 600  Wellington Wellington",
    "addr:housenumber":"pde po box 600",
    "iso:country":"NZ",
    "sg:address":"Kelburn Pde PO Box 600 ",
    "sg:city":"Wellington",
    "sg:classifiers":[
        {
            "category":"Insurance",
            "subcategory":"Health Insurance",
            "type":"Services"
        }
    ],
    "sg:phone":"+64 4-472 1000",
    "sg:province":"Wellington",
    "sg:tags":[
        "specialist",
        "beauty"
    ],
    "sg:website":"http://www.vuw.ac.nz",
    "wof:name":"Victoria University Of Wellington",
    "wof:placetype":"venue"
},
  "geometry": {"coordinates":[174.76715100000001,-41.28054],"type":"Point"}
}