{
  "type": "Feature",
  "properties": {
    "iso:country":"NZ",
    "sg:address":"130 East Tamaki Road Rd Otara ",
    "sg:city":"Auckland",
    "sg:classifiers":[
        {
            "category":"Health Services",
            "subcategory":"Health Practitioner",
            "type":"Services"
        }
    ],
    "sg:phone":"+64 9-273 0048",
    "sg:province":"Waikato",
    "sg:tags":[
        "services",
        "beauty",
        "acupuncturists"
    ],
    "wof:name":"Chinese Health Centre",
    "wof:placetype":"venue"
},
  "geometry": {"coordinates":[174.87231399999999,-36.962402],"type":"Point"}
}