{
  "type": "Feature",
  "properties": {
    "iso:country":"NZ",
    "sg:address":"6/68 Grey St Palmerston ",
    "sg:city":"Palmerston North",
    "sg:classifiers":[
        {
            "category":"Home & Garden",
            "subcategory":"Home Furnishings",
            "type":"Retail Goods"
        }
    ],
    "sg:phone":"+64 6-355 3210",
    "sg:province":"Manawatu-Wanganui",
    "sg:tags":[
        "furniture/furnishings",
        "bedding",
        "bed"
    ],
    "wof:name":"The Bed Barn",
    "wof:placetype":"venue"
},
  "geometry": {"coordinates":[175.567825,-40.220108],"type":"Point"}
}