{
  "type": "Feature",
  "properties": {
    "addr:full":"38 Buchanan Pl  Rotorua Bay of Plenty",
    "addr:housenumber":"38",
    "addr:street":"Buchanan Pl",
    "iso:country":"NZ",
    "sg:address":"38 Buchanan Pl ",
    "sg:city":"Rotorua",
    "sg:classifiers":[
        {
            "category":"Arts & Performance",
            "subcategory":"Music",
            "type":"Entertainment"
        }
    ],
    "sg:phone":"+64 7-347 6613",
    "sg:province":"Bay of Plenty",
    "sg:tags":[
        "sport",
        "leisure"
    ],
    "wof:name":"Muscepts Rotorua",
    "wof:placetype":"venue"
},
  "geometry": {"coordinates":[176.209518,-38.147369],"type":"Point"}
}