{
  "type": "Feature",
  "properties": {
    "addr:full":"35 Saleyards Rd Otahuhu  Auckland Auckland",
    "addr:housenumber":"35",
    "addr:street":"Saleyards Rd",
    "iso:country":"NZ",
    "sg:address":"35 Saleyards Rd Otahuhu ",
    "sg:city":"Auckland",
    "sg:orig_category":"Industrial: Metal: Services: Metal Polishers",
    "sg:phone":"+64 9-276 4575",
    "sg:province":"Auckland",
    "wof:name":"Ace Metal Polishers",
    "wof:placetype":"venue"
},
  "geometry": {"coordinates":[174.83351099999999,-36.942242],"type":"Point"}
}