{
  "type": "Feature",
  "properties": {
    "iso:country":"NZ",
    "sg:address":"12 Iversen Tce Waltham ",
    "sg:city":"Christchurch",
    "sg:orig_category":"Industrial: Packaging: Paper And Cardboard",
    "sg:phone":"+64 3-366 1377",
    "sg:province":"Canterbury",
    "wof:name":"CPI Papers",
    "wof:placetype":"venue"
},
  "geometry": {"coordinates":[172.648178,-43.541027],"type":"Point"}
}