{
  "type": "Feature",
  "properties": {
    "addr:full":"Shop 2 / 28 Mangere Town Cntre Mangere  Auckland Auckland",
    "addr:housenumber":"shop 2 / 28 mangere town cntre",
    "iso:country":"NZ",
    "sg:address":"Shop 2 / 28 Mangere Town Cntre Mangere ",
    "sg:city":"Auckland",
    "sg:classifiers":[
        {
            "category":"Home & Garden",
            "subcategory":"Home Furnishings",
            "type":"Retail Goods"
        }
    ],
    "sg:phone":"+64 9-275 6040",
    "sg:province":"Auckland",
    "sg:tags":[
        "furniture/furnishings",
        "-",
        "secondhand",
        "furniture"
    ],
    "wof:name":"Mangere Furniture & Appliances Shop",
    "wof:placetype":"venue"
},
  "geometry": {"coordinates":[174.79969800000001,-36.969288],"type":"Point"}
}