{
  "type": "Feature",
  "properties": {
    "iso:country":"NZ",
    "sg:address":"York St ",
    "sg:city":"Russell",
    "sg:classifiers":[
        {
            "category":"Sports & Exercise",
            "subcategory":"Skate Park",
            "type":"Entertainment"
        }
    ],
    "sg:phone":"+64 9-403 7701",
    "sg:tags":[
        "arts",
        "museum",
        "leisure",
        "gallery"
    ],
    "wof:name":"Russell Museum",
    "wof:placetype":"venue"
},
  "geometry": {"coordinates":[-82.726128,38.538174],"type":"Point"}
}