{
  "type": "Feature",
  "properties": {
    "addr:full":"97 Orbell St Sydenham  Christchurch Canterbury",
    "addr:housenumber":"97",
    "addr:street":"Orbell St",
    "iso:country":"NZ",
    "sg:address":"97 Orbell St Sydenham ",
    "sg:city":"Christchurch",
    "sg:classifiers":[
        {
            "category":"Home & Garden",
            "subcategory":"Building Materials",
            "type":"Retail Goods"
        }
    ],
    "sg:phone":"+64 3-961 1144",
    "sg:province":"Canterbury",
    "sg:tags":[
        "design",
        "fitting",
        "fittings",
        "kitchen"
    ],
    "wof:name":"Precision Stone",
    "wof:placetype":"venue"
},
  "geometry": {"coordinates":[172.63192699999999,-43.542854],"type":"Point"}
}