{
  "type": "Feature",
  "properties": {
    "iso:country":"NZ",
    "sg:address":"161 Jellicoe St Te ",
    "sg:city":"Puke",
    "sg:classifiers":[
        {
            "category":"Home & Garden",
            "subcategory":"Kitchen Supply",
            "type":"Retail Goods"
        }
    ],
    "sg:phone":"+64 7-573 7340",
    "sg:province":"Bay of Plenty",
    "sg:tags":[
        "shop",
        "pet",
        "pets"
    ],
    "wof:name":"Te Puke Pets",
    "wof:placetype":"venue"
},
  "geometry": {"coordinates":[176.33049,-37.785503],"type":"Point"}
}