{
  "type": "Feature",
  "properties": {
    "iso:country":"NZ",
    "sg:address":"303 Kepa Rd Kohimarama ",
    "sg:city":"Auckland",
    "sg:orig_category":"Health And Beauty: Dental: Dentists",
    "sg:phone":"+64 9-528 7996",
    "sg:province":"Auckland",
    "wof:name":"Kohimarama Dental Centre",
    "wof:placetype":"venue"
},
  "geometry": {"coordinates":[174.84626800000001,-36.857433],"type":"Point"}
}