{
  "type": "Feature",
  "properties": {
    "addr:full":"Moir St  Mangawhai",
    "addr:street":"Moir St",
    "iso:country":"NZ",
    "sg:address":"Moir St ",
    "sg:city":"Mangawhai",
    "sg:orig_category":"Shopping: Sports Retailers: Sports Goods: Sportswear",
    "sg:phone":"+64 9-431 4660",
    "wof:name":"Bammas",
    "wof:placetype":"venue"
},
  "geometry": {"coordinates":[174.575714,-36.125828],"type":"Point"}
}