{
  "type": "Feature",
  "properties": {
    "addr:full":"69 Hutchinson Rd Howick  Auckland Auckland",
    "addr:housenumber":"69",
    "addr:street":"Hutchinson Rd",
    "iso:country":"NZ",
    "sg:address":"69 Hutchinson Rd Howick ",
    "sg:city":"Auckland",
    "sg:classifiers":[
        {
            "category":"Social Services",
            "subcategory":"Child Care",
            "type":"Services"
        }
    ],
    "sg:phone":"+64 9-535 3095",
    "sg:province":"Auckland",
    "sg:tags":[
        "home",
        "garden",
        "children"
    ],
    "wof:name":"Lighthouse Preschool",
    "wof:placetype":"venue"
},
  "geometry": {"coordinates":[174.916946,-36.894379],"type":"Point"}
}