{
  "type": "Feature",
  "properties": {
    "iso:country":"NZ",
    "sg:address":"221 Glenfield Rd Glenfield ",
    "sg:city":"Auckland",
    "sg:classifiers":[
        {
            "category":"Shopping",
            "subcategory":"Clothing, Apparel, & Fashions",
            "type":"Retail Goods"
        }
    ],
    "sg:phone":"+64 9-480 0372",
    "sg:province":"Auckland",
    "sg:tags":[
        "-",
        "hire",
        "clothing",
        "fabric"
    ],
    "wof:name":"Masquerade Fancy Costume Hire",
    "wof:placetype":"venue"
},
  "geometry": {"coordinates":[174.724167,-36.792469],"type":"Point"}
}