{
  "type": "Feature",
  "properties": {
    "addr:full":"163 Kapiti Rd  Paraparaumu Wellington",
    "addr:housenumber":"163",
    "addr:street":"Kapiti Rd",
    "iso:country":"NZ",
    "sg:address":"163 Kapiti Rd ",
    "sg:city":"Paraparaumu",
    "sg:classifiers":[
        {
            "category":"Home & Garden",
            "subcategory":"Building Materials",
            "type":"Retail Goods"
        }
    ],
    "sg:phone":"+64 4-902 9937",
    "sg:province":"Wellington",
    "sg:tags":[
        "shower",
        "fittings",
        "screen",
        "door"
    ],
    "wof:name":"Dolphin Shower Screens Ltd",
    "wof:placetype":"venue"
},
  "geometry": {"coordinates":[174.99468999999999,-40.90369],"type":"Point"}
}