{
  "type": "Feature",
  "properties": {
    "iso:country":"NZ",
    "sg:address":"9 Marsh St Tauranga Mt ",
    "sg:city":"Maunganui",
    "sg:orig_category":"Home And Garden: Accessories: Hardware",
    "sg:phone":"+64 7-575 4009",
    "sg:province":"Bay of Plenty",
    "wof:name":"PlaceMakers",
    "wof:placetype":"venue"
},
  "geometry": {"coordinates":[176.186279,-37.641052],"type":"Point"}
}