{
  "type": "Feature",
  "properties": {
    "iso:country":"NZ",
    "sg:address":"60 Khyber Pass Rd Grafton ",
    "sg:city":"Auckland",
    "sg:classifiers":[
        {
            "category":"Social Services",
            "subcategory":"Job Training",
            "type":"Services"
        }
    ],
    "sg:phone":"+64 9-916 6640",
    "sg:province":"Auckland",
    "sg:tags":[
        "education"
    ],
    "sg:website":"http://www.yellowpages.co.nz/pages/219734566/dp39663.html",
    "wof:name":"Spherion",
    "wof:placetype":"venue"
},
  "geometry": {"coordinates":[174.762451,-36.864216],"type":"Point"}
}