{
  "type": "Feature",
  "properties": {
    "addr:full":"222 Picquet Hill Rd Te  Awamutu Waikato",
    "addr:housenumber":"222",
    "addr:street":"Picquet Hill Rd",
    "iso:country":"NZ",
    "sg:address":"222 Picquet Hill Rd Te ",
    "sg:city":"Awamutu",
    "sg:classifiers":[
        {
            "category":"Home & Garden",
            "subcategory":"Carpets & Floor Coverings",
            "type":"Retail Goods"
        }
    ],
    "sg:phone":"+64 252800790",
    "sg:province":"Waikato",
    "sg:tags":[
        "cleaning",
        "furniture"
    ],
    "wof:name":"Clarke's Carpet Cleaning",
    "wof:placetype":"venue"
},
  "geometry": {"coordinates":[175.34710699999999,-38.004578],"type":"Point"}
}