{
  "type": "Feature",
  "properties": {
    "iso:country":"NZ",
    "sg:address":"28 Vivian St New ",
    "sg:city":"Plymouth",
    "sg:classifiers":[
        {
            "category":"Banks & Credit Unions",
            "subcategory":"Investment Brokerage",
            "type":"Services"
        }
    ],
    "sg:phone":"+64 6-757 3442",
    "sg:province":"Taranaki",
    "sg:tags":[
        "personal",
        "-",
        "finance"
    ],
    "wof:name":"Spicers Portfolio Management Ltd",
    "wof:placetype":"venue"
},
  "geometry": {"coordinates":[-116.819725,43.97221],"type":"Point"}
}