{
  "type": "Feature",
  "properties": {
    "iso:country":"NZ",
    "sg:address":"128 Ellis St ",
    "sg:city":"Brightwater",
    "sg:classifiers":[
        {
            "category":"Shopping",
            "subcategory":"Crafts & Fabrics",
            "type":"Retail Goods"
        }
    ],
    "sg:phone":"+64 3-542 3585",
    "sg:tags":[
        "pottery",
        "home",
        "accessories",
        "garden",
        "supply"
    ],
    "wof:name":"Macs Mud Company",
    "wof:placetype":"venue"
},
  "geometry": {"coordinates":[-82.520012,35.331444],"type":"Point"}
}