{
  "type": "Feature",
  "properties": {
    "addr:full":"25 Maunsell St Woolston  Christchurch Canterbury",
    "addr:housenumber":"25",
    "addr:street":"Maunsell St",
    "iso:country":"NZ",
    "sg:address":"25 Maunsell St Woolston ",
    "sg:city":"Christchurch",
    "sg:classifiers":[
        {
            "category":"Retail",
            "subcategory":"Auto Repair",
            "type":"Services"
        }
    ],
    "sg:phone":"+64 3-389 7070",
    "sg:province":"Canterbury",
    "sg:tags":[
        "mobile",
        "automotive",
        "servicing",
        "mechanic"
    ],
    "wof:name":"Sparks Auto Electric Ltd",
    "wof:placetype":"venue"
},
  "geometry": {"coordinates":[172.67681899999999,-43.557152],"type":"Point"}
}