{
  "type": "Feature",
  "properties": {
    "addr:full":"35 Elizabeth St  Blenheim Marlborough",
    "addr:housenumber":"35",
    "addr:street":"Elizabeth St",
    "iso:country":"NZ",
    "sg:address":"35 Elizabeth St ",
    "sg:city":"Blenheim",
    "sg:classifiers":[
        {
            "category":"Home & Garden",
            "subcategory":"Building Materials",
            "type":"Retail Goods"
        }
    ],
    "sg:phone":"+64 252033662",
    "sg:province":"Marlborough",
    "sg:tags":[
        "builder",
        "related"
    ],
    "wof:name":"Baker Colin Building Contractor",
    "wof:placetype":"venue"
},
  "geometry": {"coordinates":[-79.654922,34.504505],"type":"Point"}
}