{
  "type": "Feature",
  "properties": {
    "addr:full":"207 East Heretaunga St  Hastings Hawke's Bay",
    "addr:housenumber":"207",
    "addr:street":"East Heretaunga St",
    "iso:country":"NZ",
    "sg:address":"207 East Heretaunga St ",
    "sg:city":"Hastings",
    "sg:classifiers":[
        {
            "category":"Banks & Credit Unions",
            "subcategory":"Atm",
            "type":"Services"
        }
    ],
    "sg:phone":"+64 6-878 2406",
    "sg:province":"Hawke's Bay",
    "sg:tags":[
        "home",
        "rental",
        "garden"
    ],
    "wof:name":"Hastings Television Rentals Ltd",
    "wof:placetype":"venue"
},
  "geometry": {"coordinates":[-81.508163,29.711214],"type":"Point"}
}