{
  "type": "Feature",
  "properties": {
    "addr:full":"129 Blenheim Rd Riccarton  Christchurch Canterbury",
    "addr:housenumber":"129",
    "addr:street":"Blenheim Rd;Christchurch",
    "iso:country":"NZ",
    "sg:address":"129 Blenheim Rd Riccarton ",
    "sg:city":"Christchurch",
    "sg:classifiers":[
        {
            "category":"Home & Garden",
            "subcategory":"Building Materials",
            "type":"Retail Goods"
        }
    ],
    "sg:phone":"+64 3-348 4331",
    "sg:province":"Canterbury",
    "sg:tags":[
        "gate",
        "fitting",
        "outdoor"
    ],
    "wof:name":"Veronese Wrought Iron Ltd",
    "wof:placetype":"venue"
},
  "geometry": {"coordinates":[172.599197,-43.537479],"type":"Point"}
}