{
  "type": "Feature",
  "properties": {
    "iso:country":"NZ",
    "sg:address":"27 Home St Grey Lynn ",
    "sg:city":"Auckland",
    "sg:classifiers":[
        {
            "category":"Shopping",
            "subcategory":"Musical Instruments",
            "type":"Retail Goods"
        }
    ],
    "sg:phone":"+64 9-360 2423",
    "sg:province":"Auckland",
    "sg:tags":[
        "sport",
        "music",
        "leisure"
    ],
    "wof:name":"Piano Movers",
    "wof:placetype":"venue"
},
  "geometry": {"coordinates":[174.734741,-36.861408],"type":"Point"}
}