{
  "type": "Feature",
  "properties": {
    "iso:country":"NZ",
    "sg:address":"35 Gladstone Rd ",
    "sg:city":"Gisborne",
    "sg:classifiers":[
        {
            "category":"Restaurant",
            "type":"Food & Drink"
        }
    ],
    "sg:phone":"+64 6-867 8173",
    "sg:province":"Gisborne",
    "sg:tags":[
        "wining",
        "dining"
    ],
    "wof:name":"Scotty's Bar & Grill",
    "wof:placetype":"venue"
},
  "geometry": {"coordinates":[178.027435,-38.667316],"type":"Point"}
}