{
  "type": "Feature",
  "properties": {
    "addr:full":"33 Kings Cre Lower  Hutt Wellington",
    "addr:housenumber":"33",
    "addr:street":"Kings Cre",
    "iso:country":"NZ",
    "sg:address":"33 Kings Cre Lower ",
    "sg:city":"Hutt",
    "sg:classifiers":[
        {
            "category":"Travel",
            "subcategory":"Hotels & Motels",
            "type":"Entertainment"
        }
    ],
    "sg:phone":"+64 4-566 1385",
    "sg:province":"Wellington",
    "sg:tags":[
        "tourism",
        "-",
        "rental",
        "accommodation"
    ],
    "wof:name":"Hutt City Ltd - The Professionals",
    "wof:placetype":"venue"
},
  "geometry": {"coordinates":[174.904526,-41.208431],"type":"Point"}
}