{
  "type": "Feature",
  "properties": {
    "iso:country":"NZ",
    "sg:address":"Cnr Kamo & Western Hills Dve Kensington ",
    "sg:city":"Whangarei",
    "sg:orig_category":"Industrial: Services: Specialist Services: Laboratories",
    "sg:phone":"+64 9-459 5222",
    "sg:province":"Northland",
    "wof:name":"Earth-Lab",
    "wof:placetype":"venue"
},
  "geometry": {"coordinates":[174.32015999999999,-35.708778],"type":"Point"}
}