{
  "type": "Feature",
  "properties": {
    "addr:full":"6 Alamein Cre  Napier Hawke's Bay",
    "addr:housenumber":"6;cre",
    "addr:street":"Alamein",
    "iso:country":"NZ",
    "sg:address":"6 Alamein Cre ",
    "sg:city":"Napier",
    "sg:classifiers":[
        {
            "category":"Retail",
            "subcategory":"Driving School",
            "type":"Services"
        }
    ],
    "sg:phone":"+64 6-843 3425",
    "sg:province":"Hawke's Bay",
    "sg:tags":[
        "training",
        "education",
        "driver"
    ],
    "wof:name":"Bay Driving School",
    "wof:placetype":"venue"
},
  "geometry": {"coordinates":[-80.588562,38.790821],"type":"Point"}
}