{
  "type": "Feature",
  "properties": {
    "addr:full":"Te Papa Cable St  Wellington Wellington",
    "addr:street":"Cable St",
    "iso:country":"NZ",
    "sg:address":"Te Papa Cable St ",
    "sg:city":"Wellington",
    "sg:classifiers":[
        {
            "category":"Landmark",
            "subcategory":"Tourist Information",
            "type":"Public Place"
        }
    ],
    "sg:phone":"+64 4-381 7128",
    "sg:province":"Wellington",
    "sg:tags":[
        "travel",
        "tourism",
        "tour",
        "sightseeing"
    ],
    "sg:website":"http://www.tepapa.govt.nz/our_resources/TPImages/default.asp",
    "wof:name":"Images-Te Papa's Photographic Library",
    "wof:placetype":"venue"
},
  "geometry": {"coordinates":[174.76715100000001,-41.28054],"type":"Point"}
}