{
  "type": "Feature",
  "properties": {
    "addr:full":"5/9 Washington Way Sydenham  Christchurch Canterbury",
    "addr:housenumber":"5 / 9",
    "addr:street":"Washington Way",
    "iso:country":"NZ",
    "sg:address":"5/9 Washington Way Sydenham ",
    "sg:city":"Christchurch",
    "sg:orig_category":"Industrial: Electrical/Electronic: Electronic Components",
    "sg:phone":"+64 3-379 3889",
    "sg:province":"Canterbury",
    "wof:name":"Memec (NZ) Ltd",
    "wof:placetype":"venue"
},
  "geometry": {"coordinates":[172.64373800000001,-43.540676],"type":"Point"}
}