{
  "type": "Feature",
  "properties": {
    "iso:country":"NZ",
    "sg:address":"Tarapuhi St ",
    "sg:city":"Greymouth",
    "sg:orig_category":"Transport: Boats And Marine: Services",
    "sg:phone":"+64 3-768 7702",
    "sg:province":"West Coast",
    "wof:name":"Thorn J E & Sons",
    "wof:placetype":"venue"
},
  "geometry": {"coordinates":[171.208603,-42.450668],"type":"Point"}
}