{
  "type": "Feature",
  "properties": {
    "addr:full":"Christchurch  Christchurch Canterbury",
    "iso:country":"NZ",
    "sg:address":"Christchurch ",
    "sg:city":"Christchurch",
    "sg:classifiers":[
        {
            "category":"Building & Trades",
            "subcategory":"Plumbing",
            "type":"Services"
        }
    ],
    "sg:phone":"+64 3-379 6191",
    "sg:province":"Canterbury",
    "sg:tags":[
        "home",
        "plumber",
        "garden",
        "related"
    ],
    "wof:name":"Rheem",
    "wof:placetype":"venue"
},
  "geometry": {"coordinates":[-1.77656,50.73407],"type":"Point"}
}