{
  "type": "Feature",
  "properties": {
    "iso:country":"NZ",
    "sg:address":"14 Erson Ave Royal Oak ",
    "sg:city":"Auckland",
    "sg:classifiers":[
        {
            "category":"Wholesale",
            "subcategory":"Medical Equipment & Supplies",
            "type":"Manufacturing & Wholesale Goods"
        }
    ],
    "sg:phone":"+64 9-625 8069",
    "sg:province":"Auckland",
    "sg:tags":[
        "health",
        "disability",
        "products",
        "beauty",
        "aid"
    ],
    "wof:name":"Disability Resource Centre Auckland Inc",
    "wof:placetype":"venue"
},
  "geometry": {"coordinates":[174.773514,-36.910019],"type":"Point"}
}