{
  "type": "Feature",
  "properties": {
    "addr:full":"Angus Pl Onekawa  Napier Hawke's Bay",
    "addr:street":"Angus Pl",
    "iso:country":"NZ",
    "sg:address":"Angus Pl Onekawa ",
    "sg:city":"Napier",
    "sg:orig_category":"Industrial: Engineering: Engineers - Manufacturing",
    "sg:phone":"+64 6-843 8805",
    "sg:province":"Hawke's Bay",
    "wof:name":"Napier Engineering & Contracting Ltd",
    "wof:placetype":"venue"
},
  "geometry": {"coordinates":[176.880966,-39.49947],"type":"Point"}
}