{
  "type": "Feature",
  "properties": {
    "iso:country":"NZ",
    "sg:address":"40 C William Pickering Dve Albany ",
    "sg:city":"Auckland",
    "sg:classifiers":[
        {
            "category":"Shopping",
            "subcategory":"Gifts & Souvenirs",
            "type":"Retail Goods"
        }
    ],
    "sg:phone":"+64 9-415 3688",
    "sg:province":"Auckland",
    "sg:tags":[
        "postcard",
        "gifts",
        "greeting",
        "card"
    ],
    "wof:name":"Stewart & Wood Ltd",
    "wof:placetype":"venue"
},
  "geometry": {"coordinates":[174.69717399999999,-36.744556],"type":"Point"}
}