{
  "type": "Feature",
  "properties": {
    "addr:full":"9 Waikaraka Dve Te Puna R D 2  Tauranga Bay of Plenty",
    "addr:housenumber":"9;2",
    "addr:street":"Waikaraka Dve Te Puna R D",
    "iso:country":"NZ",
    "sg:address":"9 Waikaraka Dve Te Puna R D 2 ",
    "sg:city":"Tauranga",
    "sg:classifiers":[
        {
            "category":"Home & Garden",
            "subcategory":"Garden Supply",
            "type":"Retail Goods"
        }
    ],
    "sg:phone":"+64 7-552 5533",
    "sg:province":"Bay of Plenty",
    "sg:tags":[
        "products",
        "nursery",
        "gardening"
    ],
    "wof:name":"Opihi Wholesale Nurseries Ltd",
    "wof:placetype":"venue"
},
  "geometry": {"coordinates":[176.144745,-37.703156],"type":"Point"}
}