{
  "type": "Feature",
  "properties": {
    "addr:full":"147 Eruera St  Rotorua Bay of Plenty",
    "addr:housenumber":"147",
    "addr:street":"Eruera St",
    "iso:country":"NZ",
    "sg:address":"147 Eruera St ",
    "sg:city":"Rotorua",
    "sg:classifiers":[
        {
            "category":"Social Services",
            "subcategory":"Child Care",
            "type":"Services"
        }
    ],
    "sg:phone":"+64 7-346 8081",
    "sg:province":"Bay of Plenty",
    "sg:tags":[
        "home",
        "garden",
        "children"
    ],
    "wof:name":"Rotorua Family Daycare",
    "wof:placetype":"venue"
},
  "geometry": {"coordinates":[176.25773599999999,-38.139038],"type":"Point"}
}