{
  "type": "Feature",
  "properties": {
    "iso:country":"NZ",
    "sg:address":"90 Upland Rd Kelburn ",
    "sg:city":"Wellington",
    "sg:classifiers":[
        {
            "category":"Deli",
            "type":"Food & Drink"
        }
    ],
    "sg:phone":"+64 4-475 3784",
    "sg:province":"Wellington",
    "sg:tags":[
        "delicatessen",
        "-"
    ],
    "wof:name":"Horseradish Delicatessen",
    "wof:placetype":"venue"
},
  "geometry": {"coordinates":[174.762497,-41.289162],"type":"Point"}
}