{
  "type": "Feature",
  "properties": {
    "addr:full":"PO Box 50-426 Porirua  Wellington Wellington",
    "addr:housenumber":"po box",
    "addr:postcode":"50-426",
    "iso:country":"NZ",
    "sg:address":"PO Box 50-426 Porirua ",
    "sg:city":"Wellington",
    "sg:orig_category":"Automotive: General Services: Car Transporters",
    "sg:phone":"+64 4-237 0618",
    "sg:province":"Wellington",
    "wof:name":"NZVD Transport Ltd",
    "wof:placetype":"venue"
},
  "geometry": {"coordinates":[174.76715100000001,-41.28054],"type":"Point"}
}