{
  "type": "Feature",
  "properties": {
    "iso:country":"NZ",
    "sg:address":"Cnr Union & Nelson Sts ",
    "sg:city":"Hawera",
    "sg:classifiers":[
        {
            "category":"Personal",
            "type":"Services"
        }
    ],
    "sg:phone":"+64 6-278 8288",
    "sg:province":"Taranaki",
    "sg:tags":[
        "services",
        "home",
        "garden",
        "counselling"
    ],
    "wof:name":"South Taranaki Counselling Service",
    "wof:placetype":"venue"
},
  "geometry": {"coordinates":[174.271317,-39.57584],"type":"Point"}
}