{
  "type": "Feature",
  "properties": {
    "addr:full":"1113 Eruera St  Rotorua Bay of Plenty",
    "addr:housenumber":"1113",
    "addr:street":"Eruera St",
    "iso:country":"NZ",
    "sg:address":"1113 Eruera St ",
    "sg:city":"Rotorua",
    "sg:classifiers":[
        {
            "category":"Sports & Exercise",
            "subcategory":"Tennis Court",
            "type":"Entertainment"
        }
    ],
    "sg:phone":"+64 7-346 0178",
    "sg:province":"Bay of Plenty",
    "sg:tags":[
        "bait",
        "hunting",
        "fishing",
        "retailers",
        "tackle",
        "shopping"
    ],
    "wof:name":"O'Keefe's Fishing Specialists",
    "wof:placetype":"venue"
},
  "geometry": {"coordinates":[176.253265,-38.138699],"type":"Point"}
}