{
  "type": "Feature",
  "properties": {
    "iso:country":"NZ",
    "sg:address":"68 Main St ",
    "sg:city":"Gore",
    "sg:classifiers":[
        {
            "category":"Retail",
            "subcategory":"Repair Shop",
            "type":"Services"
        }
    ],
    "sg:phone":"+64 3-208 3747",
    "sg:province":"Southland",
    "sg:tags":[
        "clothing",
        "fabric",
        "cleaning"
    ],
    "wof:name":"Ruth's Place",
    "wof:placetype":"venue"
},
  "geometry": {"coordinates":[-95.117569,35.52932],"type":"Point"}
}