{
  "type": "Feature",
  "properties": {
    "iso:country":"NZ",
    "sg:address":"Green Rd R D ",
    "sg:city":"6",
    "sg:orig_category":"Home And Garden: General: Handyman'S Services",
    "sg:phone":"+64 800 345 444",
    "wof:name":"PropertyCare",
    "wof:placetype":"venue"
},
  "geometry": {"coordinates":[-6.188128,53.297649],"type":"Point"}
}