{
  "type": "Feature",
  "properties": {
    "iso:country":"NZ",
    "sg:address":"11/38 Eaglehurst Rd Ellerslie ",
    "sg:city":"Auckland",
    "sg:classifiers":[
        {
            "category":"Shopping",
            "subcategory":"Beauty & Cosmetics",
            "type":"Retail Goods"
        }
    ],
    "sg:phone":"+64 9-525 3315",
    "sg:province":"Auckland",
    "sg:tags":[
        "supply",
        "health",
        "hairdressing"
    ],
    "wof:name":"Combined Salon Supplies Ltd",
    "wof:placetype":"venue"
},
  "geometry": {"coordinates":[174.818008,-36.902248],"type":"Point"}
}