{
  "type": "Feature",
  "properties": {
    "iso:country":"NZ",
    "sg:address":"Shop 26, Barrington ",
    "sg:city":"Mall",
    "sg:classifiers":[
        {
            "category":"Health Services",
            "subcategory":"Medical Lab",
            "type":"Services"
        }
    ],
    "sg:phone":"+64 3-331 6319",
    "sg:province":"Canterbury",
    "sg:tags":[
        "laboratory",
        "beauty",
        "specialists"
    ],
    "wof:name":"Medlab South Ltd",
    "wof:placetype":"venue"
},
  "geometry": {"coordinates":[-82.883911,37.327473],"type":"Point"}
}