{
  "type": "Feature",
  "properties": {
    "addr:full":"70 Wilson St  Wanganui Manawatu-Wanganui",
    "addr:housenumber":"70",
    "addr:street":"Wilson St",
    "iso:country":"NZ",
    "sg:address":"70 Wilson St ",
    "sg:city":"Wanganui",
    "sg:classifiers":[
        {
            "category":"Retail",
            "subcategory":"Auto Repair",
            "type":"Services"
        }
    ],
    "sg:phone":"+64 6-345 3814",
    "sg:province":"Manawatu-Wanganui",
    "sg:tags":[
        "automotive",
        "electric",
        "servicing"
    ],
    "wof:name":"Smiths Auto Electric City",
    "wof:placetype":"venue"
},
  "geometry": {"coordinates":[175.04612700000001,-39.933403],"type":"Point"}
}