{
  "type": "Feature",
  "properties": {
    "iso:country":"NZ",
    "sg:address":"200 Elles Rd ",
    "sg:city":"Invercargill",
    "sg:classifiers":[
        {
            "category":"Restaurant",
            "type":"Food & Drink"
        }
    ],
    "sg:phone":"+64 3-216 0400",
    "sg:province":"Southland",
    "sg:tags":[
        "wining",
        "dining"
    ],
    "wof:name":"Strathern Inn Restaurant",
    "wof:placetype":"venue"
},
  "geometry": {"coordinates":[168.36163300000001,-46.425152],"type":"Point"}
}