{
  "type": "Feature",
  "properties": {
    "iso:country":"NZ",
    "sg:address":"40 B Huia Rd Otahuhu ",
    "sg:city":"Auckland",
    "sg:orig_category":"Industrial: Metal",
    "sg:phone":"+64 9-276 8399",
    "sg:province":"Auckland",
    "sg:website":"http://www.grinding.co.nz",
    "wof:name":"McGowan Abrasive Eng Ltd",
    "wof:placetype":"venue"
},
  "geometry": {"coordinates":[174.836227,-36.942196],"type":"Point"}
}