{
  "type": "Feature",
  "properties": {
    "iso:country":"NZ",
    "sg:address":"24 North St Parkside ",
    "sg:city":"Timaru",
    "sg:classifiers":[
        {
            "category":"Shopping",
            "subcategory":"Beauty & Cosmetics",
            "type":"Retail Goods"
        }
    ],
    "sg:phone":"+64 3-688 4400",
    "sg:province":"Canterbury",
    "sg:tags":[
        "medical",
        "health"
    ],
    "wof:name":"Collett Ross",
    "wof:placetype":"venue"
},
  "geometry": {"coordinates":[171.24588,-44.400558],"type":"Point"}
}