{
  "type": "Feature",
  "properties": {
    "addr:full":"98 Sophia St  Timaru Canterbury",
    "addr:housenumber":"98",
    "addr:street":"Sophia St",
    "iso:country":"NZ",
    "sg:address":"98 Sophia St ",
    "sg:city":"Timaru",
    "sg:orig_category":"Health And Beauty: Dental: Dentists",
    "sg:phone":"+64 3-688 9463",
    "sg:province":"Canterbury",
    "wof:name":"Easton Mark",
    "wof:placetype":"venue"
},
  "geometry": {"coordinates":[171.248749,-44.394173],"type":"Point"}
}