{
  "type": "Feature",
  "properties": {
    "iso:country":"NZ",
    "sg:address":"Nikau Cre Mt ",
    "sg:city":"Maunganui",
    "sg:classifiers":[
        {
            "category":"Sports & Exercise",
            "subcategory":"Sports Center",
            "type":"Entertainment"
        }
    ],
    "sg:phone":"+64 7-575 3838",
    "sg:province":"Bay of Plenty",
    "sg:tags":[
        "sporting",
        "sports",
        "-",
        "leisure",
        "facility"
    ],
    "wof:name":"Mount Maunganui Bowling Club",
    "wof:placetype":"venue"
},
  "geometry": {"coordinates":[176.18452453610001,-37.6411590576],"type":"Point"}
}