{
  "type": "Feature",
  "properties": {
    "iso:country":"NZ",
    "sg:address":"38 Ludlam Cre Lower ",
    "sg:city":"Hutt",
    "sg:classifiers":[
        {
            "category":"Building & Trades",
            "subcategory":"Construction",
            "type":"Services"
        }
    ],
    "sg:phone":"+64 4-566 9296",
    "sg:province":"Wellington",
    "sg:tags":[
        "home",
        "garden",
        "related",
        "plasterer"
    ],
    "wof:name":"Mark Hofsteede",
    "wof:placetype":"venue"
},
  "geometry": {"coordinates":[174.904526,-41.208431],"type":"Point"}
}