{
  "type": "Feature",
  "properties": {
    "addr:full":"73 Broadway  Kaikohe Manawatu-Wanganui",
    "addr:housenumber":"73",
    "addr:street":"Broadway",
    "iso:country":"NZ",
    "sg:address":"73 Broadway ",
    "sg:city":"Kaikohe",
    "sg:classifiers":[
        {
            "category":"Communications",
            "subcategory":"Film & Video Production",
            "type":"Services"
        }
    ],
    "sg:phone":"+64 9-401 0273",
    "sg:province":"Manawatu-Wanganui",
    "sg:tags":[
        "sport",
        "leisure",
        "library",
        "entertainment"
    ],
    "wof:name":"Video Ezy Kaikohe",
    "wof:placetype":"venue"
},
  "geometry": {"coordinates":[173.80107100000001,-35.407009],"type":"Point"}
}