{
  "type": "Feature",
  "properties": {
    "addr:full":"Koromiko Ave  Hawera Taranaki",
    "addr:street":"Koromiko Ave",
    "iso:country":"NZ",
    "sg:address":"Koromiko Ave ",
    "sg:city":"Hawera",
    "sg:classifiers":[
        {
            "category":"Social Services",
            "subcategory":"Child Care",
            "type":"Services"
        }
    ],
    "sg:phone":"+64 6-278 3028",
    "sg:province":"Taranaki",
    "sg:tags":[
        "home",
        "garden",
        "children"
    ],
    "wof:name":"Koromiko Free Kindergarten",
    "wof:placetype":"venue"
},
  "geometry": {"coordinates":[174.274338,-39.574848],"type":"Point"}
}