{
  "type": "Feature",
  "properties": {
    "addr:full":"Chester Rd RD1  Carterton",
    "addr:postcode":"rd1",
    "addr:street":"Chester Rd",
    "iso:country":"NZ",
    "sg:address":"Chester Rd RD1 ",
    "sg:city":"Carterton",
    "sg:classifiers":[
        {
            "category":"Building & Trades",
            "subcategory":"Construction",
            "type":"Services"
        }
    ],
    "sg:phone":"+64 6-379 5040",
    "sg:tags":[
        "home",
        "garden",
        "related",
        "plasterer"
    ],
    "wof:name":"Clive Whinn Plastering",
    "wof:placetype":"venue"
},
  "geometry": {"coordinates":[-82.190933,36.941956],"type":"Point"}
}