{
  "type": "Feature",
  "properties": {
    "iso:country":"NZ",
    "sg:address":"154 G Harris Rd East Tamaki ",
    "sg:city":"Auckland",
    "sg:orig_category":"Home And Garden: Gardening: Products: Fertilisers",
    "sg:phone":"+64 9-273 2299",
    "sg:province":"Auckland",
    "wof:name":"Interfert Corporation Ltd",
    "wof:placetype":"venue"
},
  "geometry": {"coordinates":[174.897278,-36.928825],"type":"Point"}
}