{
  "type": "Feature",
  "properties": {
    "addr:full":"Riverlands Industrial Estate Liverpool St Riverlands Blenheim Marlborough",
    "addr:street":"Industrial Estate;St",
    "iso:country":"NZ",
    "sg:address":"Riverlands Industrial Estate Liverpool St Riverlands",
    "sg:city":"Blenheim",
    "sg:classifiers":[
        {
            "category":"Utilities",
            "subcategory":"Electric",
            "type":"Services"
        }
    ],
    "sg:phone":"+64 3-578 1878",
    "sg:province":"Marlborough",
    "sg:tags":[
        "energy",
        "industrial"
    ],
    "wof:name":"Heagney Bros Ltd",
    "wof:placetype":"venue"
},
  "geometry": {"coordinates":[173.98223899999999,-41.521309],"type":"Point"}
}