{
  "type": "Feature",
  "properties": {
    "addr:full":"Suite 4a, 137 Hereford St  Christchurch Canterbury",
    "addr:housenumber":"suite 4a 137",
    "addr:street":"Hereford St",
    "iso:country":"NZ",
    "sg:address":"Suite 4a, 137 Hereford St ",
    "sg:city":"Christchurch",
    "sg:orig_category":"Shopping: Accessories: Jewellers And Watchmakers",
    "sg:phone":"+64 3-379 0550",
    "sg:province":"Canterbury",
    "sg:website":"http://www.julianharding.co.nz",
    "wof:name":"Julian Harding Lifestyle Jewellery Ltd",
    "wof:placetype":"venue"
},
  "geometry": {"coordinates":[-76.537834,37.605659],"type":"Point"}
}