{
  "type": "Feature",
  "properties": {
    "addr:full":"372 A Grey St Hamilton East  Hamilton Waikato",
    "addr:housenumber":"372 a",
    "addr:street":"Grey St",
    "iso:country":"NZ",
    "sg:address":"372 A Grey St Hamilton East ",
    "sg:city":"Hamilton",
    "sg:classifiers":[
        {
            "category":"Personal",
            "subcategory":"Tanning Parlor",
            "type":"Services"
        }
    ],
    "sg:phone":"+64 7-856 2996",
    "sg:province":"Waikato",
    "sg:tags":[
        "sun",
        "health",
        "beauty"
    ],
    "wof:name":"AZULE studio",
    "wof:placetype":"venue"
},
  "geometry": {"coordinates":[175.293274,-37.792622],"type":"Point"}
}