{
  "type": "Feature",
  "properties": {
    "addr:full":"399 Komokoriki Hill Rd Ahuroa  Warkworth Auckland",
    "addr:housenumber":"399",
    "addr:street":"Komokoriki Hill Rd",
    "iso:country":"NZ",
    "sg:address":"399 Komokoriki Hill Rd Ahuroa ",
    "sg:city":"Warkworth",
    "sg:orig_category":"Farming: Services: Farm Consultants",
    "sg:phone":"+64 9-422 4024",
    "sg:province":"Auckland",
    "wof:name":"Farmer For Hire",
    "wof:placetype":"venue"
},
  "geometry": {"coordinates":[174.66511499999999,-36.401459],"type":"Point"}
}