{
  "type": "Feature",
  "properties": {
    "iso:country":"NZ",
    "sg:address":"399 Komokoriki Hill Rd Ahuroa ",
    "sg:city":"Warkworth",
    "sg:orig_category":"Farming: Services: Farm Consultants",
    "sg:phone":"+64 9-422 4024",
    "sg:province":"Auckland",
    "wof:name":"Farmer For Hire",
    "wof:placetype":"venue"
},
  "geometry": {"coordinates":[174.665115,-36.401459],"type":"Point"}
}