{
  "type": "Feature",
  "properties": {
    "addr:full":"Kerikeri Rd  Kerikeri Northland",
    "addr:street":"Kerikeri Rd",
    "iso:country":"NZ",
    "sg:address":"Kerikeri Rd ",
    "sg:city":"Kerikeri",
    "sg:classifiers":[
        {
            "category":"Home & Garden",
            "subcategory":"Home Furnishings",
            "type":"Retail Goods"
        }
    ],
    "sg:phone":"+64 9-407 7158",
    "sg:province":"Northland",
    "sg:tags":[
        "accessory"
    ],
    "sg:website":"http://www.keriblue.co.nz",
    "wof:name":"Keriblue Ceramics",
    "wof:placetype":"venue"
},
  "geometry": {"coordinates":[173.943848,-35.233288],"type":"Point"}
}