{
  "type": "Feature",
  "properties": {
    "addr:full":"17 Wickham St Bromley  Christchurch Canterbury",
    "addr:housenumber":"17",
    "addr:street":"Wickham St;Christchurch",
    "iso:country":"NZ",
    "sg:address":"17 Wickham St Bromley ",
    "sg:city":"Christchurch",
    "sg:orig_category":"Industrial: Engineering: Engineers",
    "sg:phone":"+64 3-384 3154",
    "sg:province":"Canterbury",
    "sg:website":"http://www.crequipment.co.nz",
    "wof:name":"C & R Equipment Ltd",
    "wof:placetype":"venue"
},
  "geometry": {"coordinates":[172.70167499999999,-43.539078],"type":"Point"}
}