{
  "type": "Feature",
  "properties": {
    "iso:country":"NZ",
    "sg:address":"NZ Guardian Trust Bldg Station St ",
    "sg:city":"Napier",
    "sg:classifiers":[
        {
            "category":"Banks & Credit Unions",
            "subcategory":"Financial Services",
            "type":"Services"
        }
    ],
    "sg:phone":"+64 6-835 0024",
    "sg:province":"Hawke's Bay",
    "sg:tags":[
        "personal",
        "loan",
        "-",
        "finance",
        "mortgage"
    ],
    "wof:name":"MortgageLink Hawkes Bay",
    "wof:placetype":"venue"
},
  "geometry": {"coordinates":[170.366638,-43.587711],"type":"Point"}
}