{
  "type": "Feature",
  "properties": {
    "addr:full":"250 Cambridge Rd  Tauranga Bay of Plenty",
    "addr:housenumber":"250",
    "addr:street":"Cambridge Rd",
    "iso:country":"NZ",
    "sg:address":"250 Cambridge Rd ",
    "sg:city":"Tauranga",
    "sg:classifiers":[
        {
            "category":"Sports & Exercise",
            "subcategory":"Ice Rink",
            "type":"Entertainment"
        }
    ],
    "sg:phone":"+64 7-578 3081",
    "sg:province":"Bay of Plenty",
    "sg:tags":[
        "thermal",
        "pool",
        "leisure"
    ],
    "wof:name":"Fernland Spa Mineral Hot Pools",
    "wof:placetype":"venue"
},
  "geometry": {"coordinates":[176.123245,-37.705849],"type":"Point"}
}