{
  "type": "Feature",
  "properties": {
    "iso:country":"NZ",
    "sg:address":"27 Main North Rd Papanui ",
    "sg:city":"Christchurch",
    "sg:orig_category":"Home And Garden: Accessories: Hardware",
    "sg:phone":"+64 3-352 8283",
    "sg:province":"Canterbury",
    "wof:name":"Papanui Hammer Hardware",
    "wof:placetype":"venue"
},
  "geometry": {"coordinates":[172.59986900000001,-43.496452],"type":"Point"}
}