{
  "type": "Feature",
  "properties": {
    "addr:full":"6/92 Great South Rd Takanini  Auckland Auckland",
    "addr:housenumber":"6 / 92",
    "addr:street":"Great South Rd",
    "iso:country":"NZ",
    "sg:address":"6/92 Great South Rd Takanini ",
    "sg:city":"Auckland",
    "sg:classifiers":[
        {
            "category":"Retail",
            "subcategory":"Auto Repair",
            "type":"Services"
        }
    ],
    "sg:phone":"+64 9-298 0608",
    "sg:province":"Auckland",
    "sg:tags":[
        "breakdown",
        "automotive",
        "towing",
        "servicing"
    ],
    "wof:name":"Papakura Towing Ltd",
    "wof:placetype":"venue"
},
  "geometry": {"coordinates":[174.917664,-37.041962],"type":"Point"}
}