{
  "type": "Feature",
  "properties": {
    "iso:country":"NZ",
    "sg:address":"116 Buchan St Sydenham ",
    "sg:city":"Christchurch",
    "sg:orig_category":"Clothing And Fabric: Fabric: Textiles",
    "sg:phone":"+64 3-366 5113",
    "sg:province":"Canterbury",
    "wof:name":"Irvine Merchant Holdings Ltd",
    "wof:placetype":"venue"
},
  "geometry": {"coordinates":[172.638443,-43.541618],"type":"Point"}
}