{
  "type": "Feature",
  "properties": {
    "iso:country":"NZ",
    "sg:address":"42 Curries Rd Woolston ",
    "sg:city":"Christchurch",
    "sg:orig_category":"Automotive: Sales And Leasing: Trailers",
    "sg:phone":"+64 3-389 4752",
    "sg:province":"Canterbury",
    "wof:name":"Chris Sutton Engineering",
    "wof:placetype":"venue"
},
  "geometry": {"coordinates":[172.679047,-43.55896],"type":"Point"}
}