{
  "type": "Feature",
  "properties": {
    "addr:full":"166 Revell St  Hokitika West Coast",
    "addr:housenumber":"166",
    "addr:street":"Revell St",
    "iso:country":"NZ",
    "sg:address":"166 Revell St ",
    "sg:city":"Hokitika",
    "sg:classifiers":[
        {
            "category":"Building & Trades",
            "subcategory":"Pest Control",
            "type":"Services"
        }
    ],
    "sg:phone":"+64 21 397 393",
    "sg:province":"West Coast",
    "sg:tags":[
        "home",
        "garden"
    ],
    "wof:name":"Coast Carpet Clean & Property Maintenance",
    "wof:placetype":"venue"
},
  "geometry": {"coordinates":[170.96792600000001,-42.711647],"type":"Point"}
}