{
  "type": "Feature",
  "properties": {
    "iso:country":"NZ",
    "sg:address":"3/75 Ellice Rd Glenfield ",
    "sg:city":"Auckland",
    "sg:classifiers":[
        {
            "category":"Social Services",
            "subcategory":"Job Training",
            "type":"Services"
        }
    ],
    "sg:phone":"+64 9-444 3253",
    "sg:province":"Auckland",
    "sg:tags":[
        "education"
    ],
    "sg:website":"http://www.southseas.co.nz",
    "wof:name":"South Seas Film & Television School",
    "wof:placetype":"venue"
},
  "geometry": {"coordinates":[174.728622,-36.784813],"type":"Point"}
}