{
  "type": "Feature",
  "properties": {
    "iso:country":"NZ",
    "sg:address":"20 Dyer St Morningside ",
    "sg:city":"Whangarei",
    "sg:classifiers":[
        {
            "category":"Home & Garden",
            "subcategory":"Building Materials",
            "type":"Retail Goods"
        }
    ],
    "sg:phone":"+64 9-430 6580",
    "sg:province":"Northland",
    "sg:tags":[
        "brick",
        "outdoor",
        "paving"
    ],
    "wof:name":"Whangarei Brick & Tile Ltd",
    "wof:placetype":"venue"
},
  "geometry": {"coordinates":[174.319595,-35.7356],"type":"Point"}
}