{
  "type": "Feature",
  "properties": {
    "addr:full":"R D 10 Waimate  Glenavy",
    "addr:housenumber":"10",
    "addr:street":"R D",
    "iso:country":"NZ",
    "sg:address":"R D 10 Waimate ",
    "sg:city":"Glenavy",
    "sg:classifiers":[
        {
            "category":"Retail",
            "subcategory":"Auto Repair",
            "type":"Services"
        }
    ],
    "sg:phone":"+64 3-689 3860",
    "sg:tags":[
        "automotive",
        "servicing"
    ],
    "wof:name":"Glenavy Garage & Service Station",
    "wof:placetype":"venue"
},
  "geometry": {"coordinates":[171.04248000000001,-44.733082],"type":"Point"}
}