{
  "type": "Feature",
  "properties": {
    "iso:country":"NZ",
    "sg:address":"Pembroke Mall ",
    "sg:city":"Wanaka",
    "sg:classifiers":[
        {
            "category":"Arena",
            "subcategory":"Sports Club",
            "type":"Entertainment"
        }
    ],
    "sg:phone":"+64 3-443 4347",
    "sg:province":"Otago",
    "sg:tags":[
        "-",
        "leisure",
        "sports"
    ],
    "wof:name":"Wanaka Ski Club Incorporated",
    "wof:placetype":"venue"
},
  "geometry": {"coordinates":[169.13471999999999,-44.695663],"type":"Point"}
}