{
  "type": "Feature",
  "properties": {
    "addr:full":"28 Ferguson Pl  Rotorua Bay of Plenty",
    "addr:housenumber":"28",
    "addr:street":"Ferguson Pl",
    "iso:country":"NZ",
    "sg:address":"28 Ferguson Pl ",
    "sg:city":"Rotorua",
    "sg:orig_category":"Automotive: Accessories: Towbars",
    "sg:phone":"+64 7-349 6180",
    "sg:province":"Bay of Plenty",
    "wof:name":"Total Engineering (2001) Ltd",
    "wof:placetype":"venue"
},
  "geometry": {"coordinates":[176.22605899999999,-38.118904],"type":"Point"}
}