{
  "type": "Feature",
  "properties": {
    "addr:full":"12 Eyre St Henderson  Auckland Auckland",
    "addr:housenumber":"12",
    "addr:street":"Eyre St",
    "iso:country":"NZ",
    "sg:address":"12 Eyre St Henderson ",
    "sg:city":"Auckland",
    "sg:classifiers":[
        {
            "category":"Shopping",
            "subcategory":"Crafts & Fabrics",
            "type":"Retail Goods"
        }
    ],
    "sg:phone":"+64 9-837 0849",
    "sg:province":"Auckland",
    "sg:tags":[
        "leather",
        "clothing",
        "suede"
    ],
    "wof:name":"Leatherform",
    "wof:placetype":"venue"
},
  "geometry": {"coordinates":[174.618469,-36.881111],"type":"Point"}
}