{
  "type": "Feature",
  "properties": {
    "iso:country":"NZ",
    "sg:address":"3 Mortimer Pss Newmarket ",
    "sg:city":"Auckland",
    "sg:classifiers":[
        {
            "category":"Bars & Pubs",
            "subcategory":"Wine Bar",
            "type":"Food & Drink"
        }
    ],
    "sg:phone":"+64 9-524 3624",
    "sg:province":"Auckland",
    "sg:tags":[
        "wining",
        "dining",
        "cafe"
    ],
    "wof:name":"Cafe Extreme",
    "wof:placetype":"venue"
},
  "geometry": {"coordinates":[174.77626000000001,-36.871613],"type":"Point"}
}