{
  "type": "Feature",
  "properties": {
    "addr:full":"Harvard La Ardmore Airfield  Auckland Auckland",
    "iso:country":"NZ",
    "sg:address":"Harvard La Ardmore Airfield ",
    "sg:city":"Auckland",
    "sg:orig_category":"Transport: Air: Air Charter Services",
    "sg:phone":"+64 9-297 7299",
    "sg:province":"Auckland",
    "wof:name":"Flight 2000 Cloudriders TM",
    "wof:placetype":"venue"
},
  "geometry": {"coordinates":[174.97711200000001,-37.032997],"type":"Point"}
}