{
  "type": "Feature",
  "properties": {
    "addr:full":"1 Sutherland Tce  Blenheim Marlborough",
    "addr:housenumber":"1",
    "addr:street":"Sutherland Tce",
    "iso:country":"NZ",
    "sg:address":"1 Sutherland Tce ",
    "sg:city":"Blenheim",
    "sg:classifiers":[
        {
            "category":"Home & Garden",
            "subcategory":"Kitchen Supply",
            "type":"Retail Goods"
        }
    ],
    "sg:phone":"+64 3-577 9554",
    "sg:province":"Marlborough",
    "sg:tags":[
        "shop",
        "pet",
        "pets"
    ],
    "wof:name":"AgHire and Supplies",
    "wof:placetype":"venue"
},
  "geometry": {"coordinates":[173.96498099999999,-41.513939],"type":"Point"}
}