{
  "type": "Feature",
  "properties": {
    "iso:country":"NZ",
    "sg:address":"2/22 Harris Rd East Tamaki ",
    "sg:city":"Auckland",
    "sg:classifiers":[
        {
            "category":"Manufacturing",
            "subcategory":"Food",
            "type":"Manufacturing & Wholesale Goods"
        }
    ],
    "sg:phone":"+64 9-274 3637",
    "sg:province":"Auckland",
    "sg:tags":[
        "processing",
        "drink"
    ],
    "wof:name":"Selby Manufacturing Ltd",
    "wof:placetype":"venue"
},
  "geometry": {"coordinates":[174.893845,-36.941677],"type":"Point"}
}