{
  "type": "Feature",
  "properties": {
    "addr:full":"405 A Ilam Rd Fendalton  Christchurch Canterbury",
    "addr:housenumber":"405 a",
    "addr:street":"Ilam Rd",
    "iso:country":"NZ",
    "sg:address":"405 A Ilam Rd Fendalton ",
    "sg:city":"Christchurch",
    "sg:classifiers":[
        {
            "category":"Shopping",
            "subcategory":"Clothing, Apparel, & Fashions",
            "type":"Retail Goods"
        }
    ],
    "sg:phone":"+64 3-351 7666",
    "sg:province":"Canterbury",
    "sg:tags":[
        "school",
        "clothing",
        "fabric",
        "uniform"
    ],
    "wof:name":"The Grasshopper Childrens Wear",
    "wof:placetype":"venue"
},
  "geometry": {"coordinates":[172.58902,-43.509197],"type":"Point"}
}