{
  "type": "Feature",
  "properties": {
    "addr:full":"Headquarters Orakei Domain  Auckland Auckland",
    "iso:country":"NZ",
    "sg:address":"Headquarters Orakei Domain ",
    "sg:city":"Auckland",
    "sg:classifiers":[
        {
            "category":"Arena",
            "subcategory":"Sports Club",
            "type":"Entertainment"
        }
    ],
    "sg:phone":"+64 9-521 0538",
    "sg:province":"Auckland",
    "sg:tags":[
        "-",
        "leisure",
        "sports"
    ],
    "wof:name":"Teachers Eastern Rugby Football Club Inc",
    "wof:placetype":"venue"
},
  "geometry": {"coordinates":[174.81826799999999,-36.856617],"type":"Point"}
}