{
  "type": "Feature",
  "properties": {
    "addr:full":"65 Totara St Ravensbourne  Dunedin Auckland",
    "addr:housenumber":"65",
    "addr:street":"Totara St",
    "iso:country":"NZ",
    "sg:address":"65 Totara St Ravensbourne ",
    "sg:city":"Dunedin",
    "sg:classifiers":[
        {
            "category":"Insurance",
            "subcategory":"Health Insurance",
            "type":"Services"
        }
    ],
    "sg:phone":"+64 3-471 0400",
    "sg:province":"Auckland",
    "sg:tags":[
        "mental",
        "beauty"
    ],
    "wof:name":"Bannister Margaret",
    "wof:placetype":"venue"
},
  "geometry": {"coordinates":[170.56051600000001,-45.863281],"type":"Point"}
}