{
  "type": "Feature",
  "properties": {
    "addr:full":"PO Box 16-3084  Lynfield Auckland",
    "addr:housenumber":"po;16-3084",
    "addr:street":"Box",
    "iso:country":"NZ",
    "sg:address":"PO Box 16-3084 ",
    "sg:city":"Lynfield",
    "sg:orig_category":"Industrial: Parts: Bearings",
    "sg:phone":"+64 252973288",
    "sg:province":"Auckland",
    "wof:name":"General Bearing Supplies Ltd",
    "wof:placetype":"venue"
},
  "geometry": {"coordinates":[174.72358700000001,-36.917694],"type":"Point"}
}