{
  "type": "Feature",
  "properties": {
    "iso:country":"NZ",
    "sg:address":"PO Box 16-3084 ",
    "sg:city":"Lynfield",
    "sg:orig_category":"Industrial: Parts: Bearings",
    "sg:phone":"+64 252973288",
    "sg:province":"Auckland",
    "wof:name":"General Bearing Supplies Ltd",
    "wof:placetype":"venue"
},
  "geometry": {"coordinates":[174.723587,-36.917694],"type":"Point"}
}