{
  "type": "Feature",
  "properties": {
    "iso:country":"NZ",
    "sg:address":"Huntly Rd Outram ",
    "sg:city":"Dunedin",
    "sg:orig_category":"Farming: Agriculture: Agricultural Consultants",
    "sg:phone":"+64 3-486 2057",
    "sg:province":"Otago",
    "wof:name":"Pasture Plus",
    "wof:placetype":"venue"
},
  "geometry": {"coordinates":[170.201279,-45.873997],"type":"Point"}
}