{
  "type": "Feature",
  "properties": {
    "iso:country":"NZ",
    "sg:address":"112b Oakdale Rd Hillsborough ",
    "sg:city":"Auckland",
    "sg:classifiers":[
        {
            "category":"Bars & Pubs",
            "subcategory":"Wine Bar",
            "type":"Food & Drink"
        }
    ],
    "sg:phone":"+64 9-625 1307",
    "sg:province":"Auckland",
    "sg:tags":[
        "distributor"
    ],
    "wof:name":"Profile Wine Ltd",
    "wof:placetype":"venue"
},
  "geometry": {"coordinates":[174.74916099999999,-36.924828],"type":"Point"}
}