{
  "type": "Feature",
  "properties": {
    "addr:full":"16 Crestview Pl Browns Bay  Auckland Auckland",
    "addr:housenumber":"16",
    "addr:street":"Crestview Pl",
    "iso:country":"NZ",
    "sg:address":"16 Crestview Pl Browns Bay ",
    "sg:city":"Auckland",
    "sg:orig_category":"Clothing And Fabric: Clothing: Tailors",
    "sg:phone":"+64 9-478 2588",
    "sg:province":"Auckland",
    "wof:name":"Remake Tailors",
    "wof:placetype":"venue"
},
  "geometry": {"coordinates":[174.73732000000001,-36.72459],"type":"Point"}
}