{
  "type": "Feature",
  "properties": {
    "iso:country":"NZ",
    "sg:address":"16 Crestview Pl Browns Bay ",
    "sg:city":"Auckland",
    "sg:orig_category":"Clothing And Fabric: Clothing: Tailors",
    "sg:phone":"+64 9-478 2588",
    "sg:province":"Auckland",
    "wof:name":"Remake Tailors",
    "wof:placetype":"venue"
},
  "geometry": {"coordinates":[174.73732,-36.72459],"type":"Point"}
}