{
  "type": "Feature",
  "properties": {
    "iso:country":"NZ",
    "sg:address":"32 A Marine Pde Paraparaumu Beach ",
    "sg:city":"Paraparaumu",
    "sg:orig_category":"Sports And Leisure: General: Clubs",
    "sg:phone":"+64 4-298 4031",
    "sg:province":"Wellington",
    "wof:name":"Kapiti Club Inc",
    "wof:placetype":"venue"
},
  "geometry": {"coordinates":[174.97975199999999,-40.893608],"type":"Point"}
}