{
  "type": "Feature",
  "properties": {
    "iso:country":"NZ",
    "sg:address":"Bell Block Shopping Centre Devon Rd Bell Block New",
    "sg:city":"Plymouth",
    "sg:classifiers":[
        {
            "category":"Bars & Pubs",
            "subcategory":"Lounge",
            "type":"Food & Drink"
        }
    ],
    "sg:phone":"+64 6-755 1850",
    "sg:province":"Taranaki",
    "sg:tags":[
        "baker",
        "-"
    ],
    "wof:name":"Bell Block Bakery",
    "wof:placetype":"venue"
},
  "geometry": {"coordinates":[-4.13689,50.375801],"type":"Point"}
}