{
  "type": "Feature",
  "properties": {
    "iso:country":"NZ",
    "sg:address":"190 Driver Rd ",
    "sg:city":"Ngaruawahia",
    "sg:classifiers":[
        {
            "category":"Utilities",
            "subcategory":"Sewage",
            "type":"Services"
        }
    ],
    "sg:phone":"+64 7-824 6873",
    "sg:tags":[
        "home",
        "tank",
        "garden",
        "septic"
    ],
    "wof:name":"Jelaca Plumbing",
    "wof:placetype":"venue"
},
  "geometry": {"coordinates":[175.14703399999999,-37.669857],"type":"Point"}
}