{
  "type": "Feature",
  "properties": {
    "addr:full":"309 Rd  Whitianga",
    "addr:housenumber":"309",
    "addr:street":"Rd",
    "iso:country":"NZ",
    "sg:address":"309 Rd ",
    "sg:city":"Whitianga",
    "sg:classifiers":[
        {
            "category":"Manufacturing",
            "subcategory":"Glass & Minerals",
            "type":"Manufacturing & Wholesale Goods"
        }
    ],
    "sg:phone":"+64 7-866 4902",
    "sg:tags":[
        "raw",
        "industrial",
        "quarry",
        "materials"
    ],
    "wof:name":"Whitianga Metal Supplies",
    "wof:placetype":"venue"
},
  "geometry": {"coordinates":[175.55673200000001,-36.849995],"type":"Point"}
}