{
  "type": "Feature",
  "properties": {
    "addr:full":"Broadway  Kaikohe Manawatu-Wanganui",
    "addr:street":"Broadway",
    "iso:country":"NZ",
    "sg:address":"Broadway ",
    "sg:city":"Kaikohe",
    "sg:orig_category":"Shopping: Retail Stores: Books: Bookshops",
    "sg:phone":"+64 9-401 0196",
    "sg:province":"Manawatu-Wanganui",
    "wof:name":"Paper Plus",
    "wof:placetype":"venue"
},
  "geometry": {"coordinates":[173.80107100000001,-35.407009],"type":"Point"}
}