{
  "type": "Feature",
  "properties": {
    "addr:full":"210 Puriri St  Wanganui Manawatu-Wanganui",
    "addr:housenumber":"210",
    "addr:street":"Puriri St",
    "iso:country":"NZ",
    "sg:address":"210 Puriri St ",
    "sg:city":"Wanganui",
    "sg:orig_category":"Industrial: Services: Gasfitters",
    "sg:phone":"+64 6-344 5388",
    "sg:province":"Manawatu-Wanganui",
    "wof:name":"Moase Plumbing",
    "wof:placetype":"venue"
},
  "geometry": {"coordinates":[174.99884,-39.940891],"type":"Point"}
}