{
  "type": "Feature",
  "properties": {
    "addr:full":"1 Clark Rd Kamo  Whangarei Northland",
    "addr:housenumber":"1",
    "addr:street":"Clark Rd",
    "iso:country":"NZ",
    "sg:address":"1 Clark Rd Kamo ",
    "sg:city":"Whangarei",
    "sg:orig_category":"Industrial: Parts: Pipes, Tubes And Cabling: Cables",
    "sg:phone":"+64 25538266",
    "sg:province":"Northland",
    "wof:name":"Comms Northland",
    "wof:placetype":"venue"
},
  "geometry": {"coordinates":[174.29901100000001,-35.683105],"type":"Point"}
}