{
  "type": "Feature",
  "properties": {
    "addr:full":"34-38 Corbett Rd Bell  Block",
    "addr:housenumber":"34-38",
    "addr:street":"Corbett Rd",
    "iso:country":"NZ",
    "sg:address":"34-38 Corbett Rd Bell ",
    "sg:city":"Block",
    "sg:orig_category":"Industrial: Parts: Valves",
    "sg:phone":"+64 6-755 9083",
    "wof:name":"Tyco Flow Maintenance",
    "wof:placetype":"venue"
},
  "geometry": {"coordinates":[174.14274599999999,-39.032024],"type":"Point"}
}