{
  "type": "Feature",
  "properties": {
    "addr:full":"1st Floor 25 Station Rd Manurewa  Auckland Auckland",
    "addr:housenumber":"25",
    "addr:street":"Station Rd",
    "iso:country":"NZ",
    "sg:address":"1st Floor 25 Station Rd Manurewa ",
    "sg:city":"Auckland",
    "sg:classifiers":[
        {
            "category":"Education",
            "subcategory":"Special Training",
            "type":"Public Place"
        }
    ],
    "sg:phone":"+64 9-267 8392",
    "sg:province":"Auckland",
    "sg:tags":[
        "tutor",
        "coach",
        "teacher"
    ],
    "wof:name":"Kip McGrath Education Centres (NZ) Ltd",
    "wof:placetype":"venue"
},
  "geometry": {"coordinates":[174.89520300000001,-37.0215],"type":"Point"}
}