{
  "type": "Feature",
  "properties": {
    "addr:full":"Gate 5, Tristram St  Hamilton Waikato",
    "addr:housenumber":"5",
    "addr:street":"Gate;Tristram St",
    "iso:country":"NZ",
    "sg:address":"Gate 5, Tristram St ",
    "sg:city":"Hamilton",
    "sg:orig_category":"Shopping: Retail Stores: Books: Bookshops",
    "sg:phone":"+64 7-839 0003",
    "sg:province":"Waikato",
    "wof:name":"Bennetts Bookshops",
    "wof:placetype":"venue"
},
  "geometry": {"coordinates":[-91.35187500000001,40.393398],"type":"Point"}
}