{
  "type": "Feature",
  "properties": {
    "addr:full":"92 Owens Rd Mt Eden  Auckland Auckland",
    "addr:housenumber":"92",
    "addr:street":"Owens Rd",
    "iso:country":"NZ",
    "sg:address":"92 Owens Rd Mt Eden ",
    "sg:city":"Auckland",
    "sg:orig_category":"Health And Beauty: Mental: Psychology",
    "sg:phone":"+64 9-638 9804",
    "sg:province":"Auckland",
    "wof:name":"Batenburg Marijke",
    "wof:placetype":"venue"
},
  "geometry": {"coordinates":[174.76205400000001,-36.882732],"type":"Point"}
}