{
  "type": "Feature",
  "properties": {
    "iso:country":"NZ",
    "sg:address":"5 Chicago St ",
    "sg:city":"Alexandra",
    "sg:orig_category":"Industrial: Products: Window Control Gear",
    "sg:phone":"+64 3-448 6468",
    "sg:province":"Otago",
    "wof:name":"First Aluminium Dunstan Ltd",
    "wof:placetype":"venue"
},
  "geometry": {"coordinates":[169.39372299999999,-45.246628],"type":"Point"}
}