{
  "type": "Feature",
  "properties": {
    "addr:full":"Shop 5 236 Main Rd  Tairua",
    "addr:housenumber":"shop 5 236",
    "addr:street":"Main Rd",
    "iso:country":"NZ",
    "sg:address":"Shop 5 236 Main Rd ",
    "sg:city":"Tairua",
    "sg:orig_category":"Shopping: Gifts: China And Glassware",
    "sg:phone":"+64 7-864 7511",
    "wof:name":"Jenz Homeware & Gifts",
    "wof:placetype":"venue"
},
  "geometry": {"coordinates":[175.848465,-37.009243],"type":"Point"}
}