{
  "type": "Feature",
  "properties": {
    "iso:country":"NZ",
    "sg:address":"4 Cardinal Dve Hillmorton ",
    "sg:city":"Christchurch",
    "sg:classifiers":[
        {
            "category":"Sports & Exercise",
            "subcategory":"Ski Resort",
            "type":"Entertainment"
        }
    ],
    "sg:phone":"+64 3-338 3821",
    "sg:province":"Canterbury",
    "sg:tags":[
        "hobbies",
        "photographic",
        "leisure",
        "developing"
    ],
    "wof:name":"Alan's Cibachrome Prints",
    "wof:placetype":"venue"
},
  "geometry": {"coordinates":[172.57913199999999,-43.560204],"type":"Point"}
}