{
  "type": "Feature",
  "properties": {
    "addr:full":"PO Box 595  Warkworth Auckland",
    "addr:housenumber":"po",
    "addr:street":"Box 595",
    "iso:country":"NZ",
    "sg:address":"PO Box 595 ",
    "sg:city":"Warkworth",
    "sg:classifiers":[
        {
            "category":"Wholesale",
            "subcategory":"Medical Equipment & Supplies",
            "type":"Manufacturing & Wholesale Goods"
        }
    ],
    "sg:phone":"+64 9-425 7353",
    "sg:province":"Auckland",
    "sg:tags":[
        "health",
        "disability",
        "products",
        "beauty",
        "aid"
    ],
    "wof:name":"Liftwell Ltd",
    "wof:placetype":"venue"
},
  "geometry": {"coordinates":[174.66511499999999,-36.401466],"type":"Point"}
}