{
  "type": "Feature",
  "properties": {
    "addr:full":"Hibiscus Coast Whangaparaoa Hibiscus  Hibiscus Coast Auckland",
    "addr:street":"Hibiscus;Hibiscus",
    "iso:country":"NZ",
    "sg:address":"Hibiscus Coast Whangaparaoa Hibiscus ",
    "sg:city":"Hibiscus Coast",
    "sg:orig_category":"Transport: Land: Shuttle Services",
    "sg:phone":"+64 9-424 2622",
    "sg:province":"Auckland",
    "wof:name":"Liberty Shuttle - Ray Fussell",
    "wof:placetype":"venue"
},
  "geometry": {"coordinates":[174.74916099999999,-36.634239],"type":"Point"}
}