{
  "type": "Feature",
  "properties": {
    "addr:full":"Finlay St National Park  Taumarunui",
    "addr:street":"Finlay St",
    "iso:country":"NZ",
    "sg:address":"Finlay St National Park ",
    "sg:city":"Taumarunui",
    "sg:orig_category":"Travel And Tourism: Accommodation: Backpackers",
    "sg:phone":"+64 7-892 2870",
    "wof:name":"National Park Backpackers",
    "wof:placetype":"venue"
},
  "geometry": {"coordinates":[175.255234,-38.88081],"type":"Point"}
}