{
  "type": "Feature",
  "properties": {
    "addr:full":"11 Papawai Pl  Masterton Wellington",
    "addr:housenumber":"11",
    "addr:street":"Papawai Pl",
    "iso:country":"NZ",
    "sg:address":"11 Papawai Pl ",
    "sg:city":"Masterton",
    "sg:classifiers":[
        {
            "category":"Ice Cream",
            "type":"Food & Drink"
        }
    ],
    "sg:phone":"+64 25710720",
    "sg:province":"Wellington",
    "sg:tags":[
        "-"
    ],
    "wof:name":"Tip Top Icecream",
    "wof:placetype":"venue"
},
  "geometry": {"coordinates":[175.64666700000001,-40.942032],"type":"Point"}
}