{
  "type": "Feature",
  "properties": {
    "addr:full":"59 Marlborough Ave Glenfield  Auckland Auckland",
    "addr:housenumber":"59",
    "addr:street":"Marlborough Ave",
    "iso:country":"NZ",
    "sg:address":"59 Marlborough Ave Glenfield ",
    "sg:city":"Auckland",
    "sg:orig_category":"Home And Garden: Gardening: Services: Garden Maintenance",
    "sg:phone":"+64 9-441 2517",
    "sg:province":"Auckland",
    "wof:name":"Gardens 'R' Us",
    "wof:placetype":"venue"
},
  "geometry": {"coordinates":[174.72792100000001,-36.78371],"type":"Point"}
}