{
  "type": "Feature",
  "properties": {
    "iso:country":"NZ",
    "sg:address":"Cnr Nelson & Eastbourne St ",
    "sg:city":"Hastings",
    "sg:classifiers":[
        {
            "category":"Banks & Credit Unions",
            "subcategory":"Investment Brokerage",
            "type":"Services"
        }
    ],
    "sg:phone":"+64 6-876 4733",
    "sg:province":"Wellington",
    "sg:tags":[
        "personal",
        "accountant",
        "chartered",
        "-",
        "finance"
    ],
    "wof:name":"Hanna Lessels",
    "wof:placetype":"venue"
},
  "geometry": {"coordinates":[-98.39237199999999,40.585651],"type":"Point"}
}