{
  "type": "Feature",
  "properties": {
    "addr:full":"121 Bank St  Whangarei Northland",
    "addr:housenumber":"121",
    "addr:street":"Bank St",
    "iso:country":"NZ",
    "sg:address":"121 Bank St ",
    "sg:city":"Whangarei",
    "sg:classifiers":[
        {
            "category":"Health Services",
            "subcategory":"Clinic",
            "type":"Services"
        }
    ],
    "sg:phone":"+64 9-430 0046",
    "sg:province":"Northland",
    "sg:tags":[
        "medical",
        "beauty"
    ],
    "wof:name":"Accident & Medical Clinic - White Cross Whangarei",
    "wof:placetype":"venue"
},
  "geometry": {"coordinates":[174.32049599999999,-35.721127],"type":"Point"}
}