{
  "type": "Feature",
  "properties": {
    "iso:country":"NZ",
    "sg:address":"Astral Towers 86 Main St Upper ",
    "sg:city":"Hutt",
    "sg:classifiers":[
        {
            "category":"Shopping",
            "subcategory":"Crafts & Fabrics",
            "type":"Retail Goods"
        }
    ],
    "sg:phone":"+64 4-528 5623",
    "sg:province":"Wellington",
    "sg:tags":[
        "knitting",
        "wool",
        "clothing"
    ],
    "wof:name":"Fentons Woolcraft Ltd",
    "wof:placetype":"venue"
},
  "geometry": {"coordinates":[175.069031,-41.12458],"type":"Point"}
}