{
  "type": "Feature",
  "properties": {
    "addr:full":"113 Kidd Rd Karaka  Auckland Auckland",
    "addr:housenumber":"113",
    "addr:street":"Kidd Rd",
    "iso:country":"NZ",
    "sg:address":"113 Kidd Rd Karaka ",
    "sg:city":"Auckland",
    "sg:orig_category":"Sports And Leisure: Sports: Equestrian: Stud Farms",
    "sg:phone":"+64 9-292 7467",
    "sg:province":"Auckland",
    "wof:name":"Karaka Group Ltd",
    "wof:placetype":"venue"
},
  "geometry": {"coordinates":[174.82861299999999,-37.105274],"type":"Point"}
}