{
  "type": "Feature",
  "properties": {
    "iso:country":"NZ",
    "sg:address":"5/93 Ellice Rd Glenfield ",
    "sg:city":"Auckland",
    "sg:classifiers":[
        {
            "category":"Home & Garden",
            "subcategory":"Garden Supply",
            "type":"Retail Goods"
        }
    ],
    "sg:phone":"+64 9-915 7179",
    "sg:province":"Auckland",
    "sg:tags":[
        "plant",
        "accessories",
        "artificial"
    ],
    "wof:name":"Martec International",
    "wof:placetype":"venue"
},
  "geometry": {"coordinates":[174.728622,-36.784813],"type":"Point"}
}