{
  "type": "Feature",
  "properties": {
    "addr:full":"House of Shem Production 144 Victoria Ave  Wanganui Manawatu-Wanganui",
    "addr:housenumber":"144",
    "addr:street":"Victoria Ave",
    "iso:country":"NZ",
    "sg:address":"House of Shem Production 144 Victoria Ave ",
    "sg:city":"Wanganui",
    "sg:classifiers":[
        {
            "category":"Arts & Performance",
            "subcategory":"Music",
            "type":"Entertainment"
        }
    ],
    "sg:phone":"+64 6-348 4944",
    "sg:province":"Manawatu-Wanganui",
    "sg:tags":[
        "sport",
        "leisure"
    ],
    "wof:name":"Te Iwi Waiata Inc - Morehu Music Publishing",
    "wof:placetype":"venue"
},
  "geometry": {"coordinates":[175.052841,-39.933369],"type":"Point"}
}