{
  "type": "Feature",
  "properties": {
    "iso:country":"NZ",
    "sg:address":"Gloucester Arc 129 Gloucester St ",
    "sg:city":"Christchurch",
    "sg:classifiers":[
        {
            "category":"Shopping",
            "subcategory":"Hobbies, Toys, & Games",
            "type":"Retail Goods"
        }
    ],
    "sg:phone":"+64 3-365 7880",
    "sg:province":"Canterbury",
    "sg:tags":[
        "coin",
        "sport",
        "leisure",
        "hobbies"
    ],
    "wof:name":"Chalon Coins & Stamps Ltd",
    "wof:placetype":"venue"
},
  "geometry": {"coordinates":[172.637314,-43.531315],"type":"Point"}
}