{
  "type": "Feature",
  "properties": {
    "iso:country":"NZ",
    "sg:address":"1 Futter St ",
    "sg:city":"Foxton",
    "sg:classifiers":[
        {
            "category":"Home & Garden",
            "subcategory":"Home Furnishings",
            "type":"Retail Goods"
        }
    ],
    "sg:phone":"+64 6-363 5066",
    "sg:tags":[
        "accessory"
    ],
    "sg:website":"http://www.yellowpages.co.nz/for/aoteapottery/dp45463.html",
    "wof:name":"Aotea Studio Pottery",
    "wof:placetype":"venue"
},
  "geometry": {"coordinates":[-105.235596,39.43111],"type":"Point"}
}