{
  "type": "Feature",
  "properties": {
    "iso:country":"NZ",
    "sg:address":"State Hwy 26 Te ",
    "sg:city":"Aroha",
    "sg:orig_category":"Farming: Farms - General: Poultry",
    "sg:phone":"+64 7-884 8732",
    "wof:name":"Early Bird Poultry Processors",
    "wof:placetype":"venue"
},
  "geometry": {"coordinates":[175.707718,-37.534805],"type":"Point"}
}