{
  "type": "Feature",
  "properties": {
    "iso:country":"NZ",
    "sg:address":"48 Main St ",
    "sg:city":"Blenheim",
    "sg:orig_category":"Automotive: Parts And Supplies: Automotive Dismantlers",
    "sg:phone":"+64 3-578 6504",
    "sg:province":"Marlborough",
    "wof:name":"Trotts Auto Spares",
    "wof:placetype":"venue"
},
  "geometry": {"coordinates":[-79.65271,34.513569],"type":"Point"}
}