{
  "type": "Feature",
  "properties": {
    "addr:full":"30 Airedale St Auckland Central  Auckland Auckland",
    "addr:housenumber":"30",
    "addr:street":"Airedale St",
    "iso:country":"NZ",
    "sg:address":"30 Airedale St Auckland Central ",
    "sg:city":"Auckland",
    "sg:classifiers":[
        {
            "category":"Personal",
            "subcategory":"Massage",
            "type":"Services"
        }
    ],
    "sg:phone":"+64 9-366 6850",
    "sg:province":"Auckland",
    "sg:tags":[
        "services",
        "health",
        "-",
        "beauty",
        "fitness"
    ],
    "wof:name":"Long Life Health Centre Ltd",
    "wof:placetype":"venue"
},
  "geometry": {"coordinates":[174.764771,-36.854511],"type":"Point"}
}