{
  "type": "Feature",
  "properties": {
    "addr:full":"4 Ebor St  Wellington Wellington",
    "addr:housenumber":"4",
    "addr:street":"Ebor St",
    "iso:country":"NZ",
    "sg:address":"4 Ebor St ",
    "sg:city":"Wellington",
    "sg:classifiers":[
        {
            "category":"Manufacturing",
            "subcategory":"Rubber & Plastics",
            "type":"Manufacturing & Wholesale Goods"
        }
    ],
    "sg:phone":"+64 4-384 4816",
    "sg:province":"Wellington",
    "sg:tags":[
        "industrial"
    ],
    "sg:website":"http://www.displaytactix.co.nz",
    "wof:name":"Display Tactix",
    "wof:placetype":"venue"
},
  "geometry": {"coordinates":[-85.910454,33.827946],"type":"Point"}
}