{
  "type": "Feature",
  "properties": {
    "addr:full":"30 New North Rd Eden Terrace  Auckland Auckland",
    "addr:housenumber":"30",
    "addr:street":"New North Rd Eden Terrace",
    "iso:country":"NZ",
    "sg:address":"30 New North Rd Eden Terrace ",
    "sg:city":"Auckland",
    "sg:classifiers":[
        {
            "category":"Retail",
            "subcategory":"Auto Repair",
            "type":"Services"
        }
    ],
    "sg:phone":"+64 9-333 4443",
    "sg:province":"Auckland",
    "sg:tags":[
        "wheel",
        "automotive",
        "servicing",
        "alignment"
    ],
    "wof:name":"Pedders Suspension Ltd",
    "wof:placetype":"venue"
},
  "geometry": {"coordinates":[174.75945999999999,-36.865955],"type":"Point"}
}