{
  "type": "Feature",
  "properties": {
    "iso:country":"NZ",
    "sg:address":"112 Actaeon Rd Makarewa ",
    "sg:city":"Invercargill",
    "sg:classifiers":[
        {
            "category":"Autos & Motor Vehicles",
            "subcategory":"Motorcycle Sales",
            "type":"Retail Goods"
        }
    ],
    "sg:phone":"+64 3-235 8812",
    "sg:province":"Southland",
    "sg:tags":[
        "automotive",
        "scooter",
        "leasing"
    ],
    "wof:name":"Motorcycle Merchants-LMVD",
    "wof:placetype":"venue"
},
  "geometry": {"coordinates":[168.354279,-46.32663],"type":"Point"}
}