{
  "type": "Feature",
  "properties": {
    "iso:country":"NZ",
    "sg:address":"83 Byron St Sydenham ",
    "sg:city":"Christchurch",
    "sg:classifiers":[
        {
            "category":"Shopping",
            "subcategory":"Clothing, Apparel, & Fashions",
            "type":"Retail Goods"
        }
    ],
    "sg:phone":"+64 3-365 0480",
    "sg:province":"Canterbury",
    "sg:tags":[
        "-",
        "hire",
        "clothing",
        "fabric"
    ],
    "wof:name":"AA Recycled Clothing",
    "wof:placetype":"venue"
},
  "geometry": {"coordinates":[172.644302,-43.542362],"type":"Point"}
}