{
  "type": "Feature",
  "properties": {
    "iso:country":"NZ",
    "sg:address":"46 Pandora Rd Ahuriri ",
    "sg:city":"Napier",
    "sg:orig_category":"Transport: Boats And Marine: Boats: Boat Dealers",
    "sg:phone":"+64 6-835 8880",
    "sg:province":"Hawke's Bay",
    "wof:name":"Barton Marine Ltd",
    "wof:placetype":"venue"
},
  "geometry": {"coordinates":[176.890579,-39.486408],"type":"Point"}
}