{
  "type": "Feature",
  "properties": {
    "addr:full":"161 Main St  Pahiatua",
    "addr:housenumber":"161",
    "addr:street":"Main St",
    "iso:country":"NZ",
    "sg:address":"161 Main St ",
    "sg:city":"Pahiatua",
    "sg:classifiers":[
        {
            "category":"Manufacturing",
            "subcategory":"Textiles",
            "type":"Manufacturing & Wholesale Goods"
        }
    ],
    "sg:phone":"+64 6-376 7439",
    "sg:tags":[
        "clothing",
        "fabric",
        "manufacturer"
    ],
    "wof:name":"Bouzaid & Ballaben Ltd",
    "wof:placetype":"venue"
},
  "geometry": {"coordinates":[175.83583100000001,-40.458637],"type":"Point"}
}