{
  "type": "Feature",
  "properties": {
    "addr:full":"Titirangi  Auckland Auckland",
    "iso:country":"NZ",
    "sg:address":"Titirangi ",
    "sg:city":"Auckland",
    "sg:orig_category":"Home And Garden: Gardening: Services: Landscape Design",
    "sg:phone":"+64 252809735",
    "sg:province":"Auckland",
    "wof:name":"Buena Vista Landscapes Ltd",
    "wof:placetype":"venue"
},
  "geometry": {"coordinates":[174.655869,-36.93795],"type":"Point"}
}