{
  "type": "Feature",
  "properties": {
    "addr:full":"248 Fenton St  Rotorua Bay of Plenty",
    "addr:housenumber":"248",
    "addr:street":"Fenton St",
    "iso:country":"NZ",
    "sg:address":"248 Fenton St ",
    "sg:city":"Rotorua",
    "sg:orig_category":"Shopping: Retail Stores: Stationery",
    "sg:phone":"+64 7-347 8822",
    "sg:province":"Bay of Plenty",
    "wof:name":"Advocate Printing Co Ltd",
    "wof:placetype":"venue"
},
  "geometry": {"coordinates":[176.253998,-38.143616],"type":"Point"}
}