{
  "type": "Feature",
  "properties": {
    "iso:country":"NZ",
    "sg:address":"141 Te Atatu Rd Te Atatu South ",
    "sg:city":"Auckland",
    "sg:classifiers":[
        {
            "category":"Fast Food",
            "type":"Food & Drink"
        }
    ],
    "sg:phone":"+64 9-838 8350",
    "sg:province":"Auckland",
    "sg:tags":[
        "wining",
        "dining",
        "takeaway"
    ],
    "wof:name":"Roberts Rd Takeaway",
    "wof:placetype":"venue"
},
  "geometry": {"coordinates":[174.646027,-36.874165],"type":"Point"}
}