{
  "type": "Feature",
  "properties": {
    "addr:full":"4 Deveron St  Whangarei Northland",
    "addr:housenumber":"4",
    "addr:street":"Deveron St",
    "iso:country":"NZ",
    "sg:address":"4 Deveron St ",
    "sg:city":"Whangarei",
    "sg:classifiers":[
        {
            "category":"Home & Garden",
            "subcategory":"Garden Supply",
            "type":"Retail Goods"
        }
    ],
    "sg:phone":"+64 9-437 7009",
    "sg:province":"Northland",
    "sg:tags":[
        "cleaning"
    ],
    "sg:website":"http://www.yellowpages.co.nz/pages/400019277/dp51665.html",
    "wof:name":"I Do Windows",
    "wof:placetype":"venue"
},
  "geometry": {"coordinates":[174.32401999999999,-35.713745],"type":"Point"}
}