{
  "type": "Feature",
  "properties": {
    "iso:country":"NZ",
    "sg:address":"Shop 5/ 30 Kolmar Rd Papatoetoe ",
    "sg:city":"Auckland",
    "sg:classifiers":[
        {
            "category":"Shopping",
            "subcategory":"Gifts & Souvenirs",
            "type":"Retail Goods"
        }
    ],
    "sg:phone":"+64 9-279 0144",
    "sg:province":"Auckland",
    "sg:tags":[
        "trophy",
        "award"
    ],
    "wof:name":"Trophies Plus",
    "wof:placetype":"venue"
},
  "geometry": {"coordinates":[174.854416,-36.978905],"type":"Point"}
}