{
  "type": "Feature",
  "properties": {
    "addr:full":"Puckey Ave  Kaitaia Northland",
    "addr:street":"Puckey Ave",
    "iso:country":"NZ",
    "sg:address":"Puckey Ave ",
    "sg:city":"Kaitaia",
    "sg:classifiers":[
        {
            "category":"Professional",
            "type":"Services"
        }
    ],
    "sg:phone":"+64 9-408 6186",
    "sg:province":"Northland",
    "sg:tags":[
        "home",
        "cleaning",
        "help",
        "garden"
    ],
    "wof:name":"Home Support North Charitable Trust",
    "wof:placetype":"venue"
},
  "geometry": {"coordinates":[173.25984199999999,-35.111786],"type":"Point"}
}