{
  "type": "Feature",
  "properties": {
    "addr:full":"27 Trevethick Gro Lower  Hutt Wellington",
    "addr:housenumber":"27",
    "addr:street":"Trevethick Gro",
    "iso:country":"NZ",
    "sg:address":"27 Trevethick Gro Lower ",
    "sg:city":"Hutt",
    "sg:classifiers":[
        {
            "category":"Arena",
            "subcategory":"Sports Club",
            "type":"Entertainment"
        }
    ],
    "sg:phone":"+64 4-569 2633",
    "sg:province":"Wellington",
    "sg:tags":[
        "-",
        "leisure",
        "sports"
    ],
    "wof:name":"Touch Wellington",
    "wof:placetype":"venue"
},
  "geometry": {"coordinates":[174.904526,-41.208431],"type":"Point"}
}