{
  "type": "Feature",
  "properties": {
    "addr:full":"961 Colombo St St Albans  Christchurch Canterbury",
    "addr:housenumber":"961",
    "addr:street":"Colombo St",
    "iso:country":"NZ",
    "sg:address":"961 Colombo St St Albans ",
    "sg:city":"Christchurch",
    "sg:classifiers":[
        {
            "category":"Retail",
            "subcategory":"Auto Repair",
            "type":"Services"
        }
    ],
    "sg:phone":"+64 3-366 8954",
    "sg:province":"Canterbury",
    "sg:tags":[
        "wheel",
        "automotive",
        "servicing",
        "alignment"
    ],
    "wof:name":"Beatson Motors Ltd",
    "wof:placetype":"venue"
},
  "geometry": {"coordinates":[172.636414,-43.518845],"type":"Point"}
}