{
  "type": "Feature",
  "properties": {
    "iso:country":"NZ",
    "sg:address":"99 Wordsworth St Sydenham ",
    "sg:city":"Christchurch",
    "sg:classifiers":[
        {
            "category":"Manufacturing",
            "subcategory":"Tools & Machinery",
            "type":"Manufacturing & Wholesale Goods"
        }
    ],
    "sg:phone":"+64 3-366 5340",
    "sg:province":"Canterbury",
    "sg:tags":[
        "equipment",
        "industrial",
        "tools",
        "sharpener"
    ],
    "wof:name":"Spreydon Auto Centre Limited",
    "wof:placetype":"venue"
},
  "geometry": {"coordinates":[172.638443,-43.544598],"type":"Point"}
}