{
  "type": "Feature",
  "properties": {
    "iso:country":"NZ",
    "sg:address":"49 Essex St ",
    "sg:city":"Balclutha",
    "sg:classifiers":[
        {
            "category":"Autos & Motor Vehicles",
            "subcategory":"Automobile Sales",
            "type":"Retail Goods"
        }
    ],
    "sg:phone":"+64 3-418 2298",
    "sg:tags":[
        "car",
        "-used",
        "leasing",
        "truck",
        "automotive"
    ],
    "wof:name":"Campbells Toyota LMVD",
    "wof:placetype":"venue"
},
  "geometry": {"coordinates":[169.757355,-46.229843],"type":"Point"}
}