{
  "type": "Feature",
  "properties": {
    "addr:full":"4 Morrin Rd Panmure  Auckland Auckland",
    "addr:housenumber":"4",
    "addr:street":"Morrin Rd",
    "iso:country":"NZ",
    "sg:address":"4 Morrin Rd Panmure ",
    "sg:city":"Auckland",
    "sg:classifiers":[
        {
            "category":"Home & Garden",
            "subcategory":"Building Materials",
            "type":"Retail Goods"
        }
    ],
    "sg:phone":"+64 9-570 2070",
    "sg:province":"Auckland",
    "sg:tags":[
        "gate",
        "fitting",
        "outdoor"
    ],
    "wof:name":"Trellis Fence & Gate Makers",
    "wof:placetype":"venue"
},
  "geometry": {"coordinates":[174.85749799999999,-36.90181],"type":"Point"}
}