{
  "type": "Feature",
  "properties": {
    "addr:full":"193 Papanui Rd Merivale  Christchurch Canterbury",
    "addr:housenumber":"193",
    "addr:street":"Papanui Rd",
    "iso:country":"NZ",
    "sg:address":"193 Papanui Rd Merivale ",
    "sg:city":"Christchurch",
    "sg:orig_category":"Health And Beauty: Products: Pharmacies",
    "sg:phone":"+64 3-355 9049",
    "sg:province":"Canterbury",
    "wof:name":"Dodds Pharmacy",
    "wof:placetype":"venue"
},
  "geometry": {"coordinates":[172.62170399999999,-43.51236],"type":"Point"}
}