{
  "type": "Feature",
  "properties": {
    "iso:country":"NZ",
    "sg:address":"Nationwide. PO Box 2872 Wellington ",
    "sg:city":"Christchurch",
    "sg:classifiers":[
        {
            "category":"Shopping",
            "subcategory":"Stationery & Office Supplies",
            "type":"Retail Goods"
        }
    ],
    "sg:phone":"+64 508 483 772",
    "sg:province":"Canterbury",
    "sg:tags":[
        "map",
        "chart"
    ],
    "sg:website":"http://www.terralink.co.nz",
    "wof:name":"Terralink International Limited",
    "wof:placetype":"venue"
},
  "geometry": {"coordinates":[-76.537834,37.605659],"type":"Point"}
}