{
  "type": "Feature",
  "properties": {
    "addr:full":"11-13 West End  Kaikoura Canterbury",
    "addr:housenumber":"11-13",
    "addr:street":"West",
    "iso:country":"NZ",
    "sg:address":"11-13 West End ",
    "sg:city":"Kaikoura",
    "sg:classifiers":[
        {
            "category":"Restaurant",
            "type":"Food & Drink"
        }
    ],
    "sg:phone":"+64 3-319 6361",
    "sg:province":"Canterbury",
    "sg:tags":[
        "merchant",
        "fish",
        "sea"
    ],
    "wof:name":"Neptunes Fresh Fish Shop",
    "wof:placetype":"venue"
},
  "geometry": {"coordinates":[173.679596,-42.399712],"type":"Point"}
}