{
  "type": "Feature",
  "properties": {
    "addr:full":"3 Perry St  Masterton Wellington",
    "addr:housenumber":"3",
    "addr:street":"Perry St",
    "iso:country":"NZ",
    "sg:address":"3 Perry St ",
    "sg:city":"Masterton",
    "sg:classifiers":[
        {
            "category":"Restaurant",
            "type":"Food & Drink"
        }
    ],
    "sg:phone":"+64 6-370 5177",
    "sg:province":"Wellington",
    "sg:tags":[
        "wining",
        "dining"
    ],
    "wof:name":"Plaza India Bistro & Tandoor Ltd",
    "wof:placetype":"venue"
},
  "geometry": {"coordinates":[175.66029399999999,-40.950363],"type":"Point"}
}