{
  "type": "Feature",
  "properties": {
    "iso:country":"NZ",
    "sg:address":"37 Dudley St Lower ",
    "sg:city":"Hutt",
    "sg:classifiers":[
        {
            "category":"Banks & Credit Unions",
            "subcategory":"Financial Services",
            "type":"Services"
        }
    ],
    "sg:phone":"+64 4-566 6428",
    "sg:province":"Wellington",
    "sg:tags":[
        "lender",
        "money",
        "-",
        "finance",
        "personal"
    ],
    "wof:name":"Easyway Finance Ltd",
    "wof:placetype":"venue"
},
  "geometry": {"coordinates":[174.902008,-41.208801],"type":"Point"}
}