{
  "type": "Feature",
  "properties": {
    "iso:country":"NZ",
    "sg:address":"Shop 59 217 Gt South Rd Papatoetoe ",
    "sg:city":"Auckland",
    "sg:classifiers":[
        {
            "category":"Personal",
            "subcategory":"Shoe Repair & Shine",
            "type":"Services"
        }
    ],
    "sg:phone":"+64 9-277 8888",
    "sg:province":"Auckland",
    "sg:tags":[
        "foot",
        "clothing",
        "fabric",
        "wear"
    ],
    "wof:name":"Mister Minit NZ Ltd",
    "wof:placetype":"venue"
},
  "geometry": {"coordinates":[174.861694,-36.97086],"type":"Point"}
}