{
  "type": "Feature",
  "properties": {
    "iso:country":"NZ",
    "sg:address":"538 Marshland Rd Marshland ",
    "sg:city":"Christchurch",
    "sg:classifiers":[
        {
            "category":"Farming",
            "subcategory":"Farm",
            "type":"Manufacturing & Wholesale Goods"
        }
    ],
    "sg:phone":"+64 3-375 7003",
    "sg:province":"Canterbury",
    "sg:tags":[
        "-"
    ],
    "wof:name":"Farmer Brown Limited",
    "wof:placetype":"venue"
},
  "geometry": {"coordinates":[172.658646,-43.464996],"type":"Point"}
}