{
  "type": "Feature",
  "properties": {
    "addr:full":"3/91 Cook St Howick  Auckland Auckland",
    "addr:housenumber":"3 / 91",
    "addr:street":"Cook St",
    "iso:country":"NZ",
    "sg:address":"3/91 Cook St Howick ",
    "sg:city":"Auckland",
    "sg:classifiers":[
        {
            "category":"Shopping",
            "subcategory":"Comic Books",
            "type":"Retail Goods"
        }
    ],
    "sg:phone":"+64 9-535 8420",
    "sg:province":"Auckland",
    "sg:tags":[
        "supplies",
        "educational",
        "education",
        "training"
    ],
    "wof:name":"Creation Literature Society Inc",
    "wof:placetype":"venue"
},
  "geometry": {"coordinates":[174.93447900000001,-36.900219],"type":"Point"}
}