{
  "type": "Feature",
  "properties": {
    "iso:country":"NZ",
    "sg:address":"Queenstown Airport ",
    "sg:city":"Queenstown",
    "sg:orig_category":"Clothing And Fabric: Clothing: Clothing - Specialty",
    "sg:phone":"+64 3-441 4283",
    "sg:province":"Otago",
    "wof:name":"Legends Down Under",
    "wof:placetype":"venue"
},
  "geometry": {"coordinates":[26.8808,-31.9181],"type":"Point"}
}