{
  "type": "Feature",
  "properties": {
    "addr:full":"67 Church St Devonport  Auckland Auckland",
    "addr:housenumber":"67",
    "addr:street":"Church St",
    "iso:country":"NZ",
    "sg:address":"67 Church St Devonport ",
    "sg:city":"Auckland",
    "sg:orig_category":"Industrial: Consultancy: Scientific: Archaeology",
    "sg:phone":"+64 9-446 0586",
    "sg:province":"Auckland",
    "wof:name":"Northern Archaeological Research",
    "wof:placetype":"venue"
},
  "geometry": {"coordinates":[174.80055200000001,-36.824917],"type":"Point"}
}