{
  "type": "Feature",
  "properties": {
    "addr:full":"Simon Gaunt 9th Dan  Hamilton Waikato",
    "addr:street":"Simon Gaunt 9Th Dan",
    "iso:country":"NZ",
    "sg:address":"Simon Gaunt 9th Dan ",
    "sg:city":"Hamilton",
    "sg:classifiers":[
        {
            "category":"Arena",
            "subcategory":"Sports Club",
            "type":"Entertainment"
        }
    ],
    "sg:phone":"+64 252315006",
    "sg:province":"Waikato",
    "sg:tags":[
        "martial art",
        "-",
        "leisure",
        "sports"
    ],
    "wof:name":"Bujinkan Budo Taijutsu Dojo",
    "wof:placetype":"venue"
},
  "geometry": {"coordinates":[-77.64296,39.163082],"type":"Point"}
}