{
  "type": "Feature",
  "properties": {
    "addr:full":"7 b Stafson La Te Atatu Peninsula  Auckland Auckland",
    "addr:housenumber":"7 b",
    "addr:street":"Stafson La",
    "iso:country":"NZ",
    "sg:address":"7 b Stafson La Te Atatu Peninsula ",
    "sg:city":"Auckland",
    "sg:classifiers":[
        {
            "category":"Arena",
            "subcategory":"Sports Club",
            "type":"Entertainment"
        }
    ],
    "sg:phone":"+64 9-834 9476",
    "sg:province":"Auckland",
    "sg:tags":[
        "arts",
        "writer",
        "leisure",
        "author"
    ],
    "wof:name":"The Write Stuff",
    "wof:placetype":"venue"
},
  "geometry": {"coordinates":[174.64544699999999,-36.830097],"type":"Point"}
}