{
  "type": "Feature",
  "properties": {
    "addr:full":"209 High St  Masterton Wellington",
    "addr:housenumber":"209",
    "addr:street":"High St",
    "iso:country":"NZ",
    "sg:address":"209 High St ",
    "sg:city":"Masterton",
    "sg:orig_category":"Shopping: Retail Stores: Supermarkets",
    "sg:phone":"+64 6-378 7265",
    "sg:province":"Wellington",
    "wof:name":"Solway Super Store",
    "wof:placetype":"venue"
},
  "geometry": {"coordinates":[175.625595,-40.962231],"type":"Point"}
}