{
  "type": "Feature",
  "properties": {
    "iso:country":"NZ",
    "sg:address":"8 Smythe Rd Henderson ",
    "sg:city":"Auckland",
    "sg:classifiers":[
        {
            "category":"Retail",
            "subcategory":"Auto Repair",
            "type":"Services"
        }
    ],
    "sg:phone":"+64 9-836 2471",
    "sg:province":"Auckland",
    "sg:tags":[
        "breakdown",
        "automotive",
        "towing",
        "servicing"
    ],
    "wof:name":"Avon Towing & Salvage Ltd",
    "wof:placetype":"venue"
},
  "geometry": {"coordinates":[174.629715,-36.881599],"type":"Point"}
}