{
  "type": "Feature",
  "properties": {
    "addr:full":"Merivale Mall 189 Papanui Rd Merivale  Christchurch Canterbury",
    "addr:housenumber":"189",
    "addr:street":"Papanui Rd",
    "iso:country":"NZ",
    "sg:address":"Merivale Mall 189 Papanui Rd Merivale ",
    "sg:city":"Christchurch",
    "sg:orig_category":"Shopping: Accessories: Sunglasses",
    "sg:phone":"+64 3-355 3243",
    "sg:province":"Canterbury",
    "wof:name":"Sunglass Store The",
    "wof:placetype":"venue"
},
  "geometry": {"coordinates":[172.620758,-43.514442],"type":"Point"}
}