{
  "type": "Feature",
  "properties": {
    "addr:full":"C/- Ngaio Medical Centre  Ngaio Wellington",
    "addr:street":"C /",
    "iso:country":"NZ",
    "sg:address":"C/- Ngaio Medical Centre ",
    "sg:city":"Ngaio",
    "sg:classifiers":[
        {
            "category":"Insurance",
            "subcategory":"Health Insurance",
            "type":"Services"
        }
    ],
    "sg:phone":"+64 252415974",
    "sg:province":"Wellington",
    "sg:tags":[
        "mental",
        "beauty"
    ],
    "wof:name":"Diana Kane",
    "wof:placetype":"venue"
},
  "geometry": {"coordinates":[174.77516199999999,-41.251614],"type":"Point"}
}