{
  "type": "Feature",
  "properties": {
    "iso:country":"NZ",
    "sg:address":"Anglican House 32 Mulgrave St ",
    "sg:city":"Wellington",
    "sg:classifiers":[
        {
            "category":"Shopping",
            "subcategory":"Beauty & Cosmetics",
            "type":"Retail Goods"
        }
    ],
    "sg:phone":"+64 4-472 9996",
    "sg:province":"Wellington",
    "sg:tags":[
        "specialists",
        "colonic",
        "health",
        "treatment"
    ],
    "wof:name":"Hydro Health",
    "wof:placetype":"venue"
},
  "geometry": {"coordinates":[-87.634239,40.510559],"type":"Point"}
}