{
  "type": "Feature",
  "properties": {
    "addr:full":"425 Beach Rd Mairangi Bay  Auckland Auckland",
    "addr:housenumber":"425",
    "addr:street":"Beach Rd",
    "iso:country":"NZ",
    "sg:address":"425 Beach Rd Mairangi Bay ",
    "sg:city":"Auckland",
    "sg:classifiers":[
        {
            "category":"Retail",
            "subcategory":"Laundry & Dry Cleaning",
            "type":"Services"
        }
    ],
    "sg:phone":"+64 9-478 7647",
    "sg:province":"Auckland",
    "sg:tags":[
        "repair",
        "clothing",
        "fabric",
        "cleaner"
    ],
    "wof:name":"Maxwells Drycleaning",
    "wof:placetype":"venue"
},
  "geometry": {"coordinates":[174.753479,-36.738575],"type":"Point"}
}