{
  "type": "Feature",
  "properties": {
    "iso:country":"NZ",
    "sg:address":"West Qy ",
    "sg:city":"Waitara",
    "sg:orig_category":"Sports And Leisure: General: Clubs",
    "sg:phone":"+64 6-754 7139",
    "wof:name":"Waitara Town & Country Club Inc",
    "wof:placetype":"venue"
},
  "geometry": {"coordinates":[174.23808299999999,-38.999847],"type":"Point"}
}