{
  "type": "Feature",
  "properties": {
    "iso:country":"NZ",
    "sg:address":"3 Wainui Rd ",
    "sg:city":"Raglan",
    "sg:orig_category":"Shopping: Sports Retailers: Water Sports: Surfboards",
    "sg:phone":"+64 7-825 8988",
    "wof:name":"Raglan Surf Co Ltd",
    "wof:placetype":"venue"
},
  "geometry": {"coordinates":[-117.892273,40.898647],"type":"Point"}
}