{
  "type": "Feature",
  "properties": {
    "iso:country":"NZ",
    "sg:address":"6-8 Birmingham St ",
    "sg:city":"Paraparaumu",
    "sg:orig_category":"Automotive: Parts And Supplies: Automotive Dismantlers",
    "sg:phone":"+64 4-902 8639",
    "sg:province":"Wellington",
    "wof:name":"Wreck-King Ltd",
    "wof:placetype":"venue"
},
  "geometry": {"coordinates":[174.99916099999999,-40.904083],"type":"Point"}
}