{
  "type": "Feature",
  "properties": {
    "iso:country":"NZ",
    "sg:address":"500 Karamu Rd ",
    "sg:city":"Hastings",
    "sg:orig_category":"Food And Drink: Meats: Butchers",
    "sg:phone":"+64 6-878 8353",
    "sg:province":"Hawke's Bay",
    "wof:name":"Export Meat Warehouse",
    "wof:placetype":"venue"
},
  "geometry": {"coordinates":[176.83827199999999,-39.646893],"type":"Point"}
}