{
  "type": "Feature",
  "properties": {
    "addr:full":"13 Maunu Rd  Whangarei Northland",
    "addr:housenumber":"13",
    "addr:street":"Maunu Rd",
    "iso:country":"NZ",
    "sg:address":"13 Maunu Rd ",
    "sg:city":"Whangarei",
    "sg:classifiers":[
        {
            "category":"Building & Trades",
            "subcategory":"Cleaning & Sanitation",
            "type":"Services"
        }
    ],
    "sg:phone":"+64 9-438 4428",
    "sg:province":"Northland",
    "sg:tags":[
        "equipment",
        "industrial",
        "maintenance"
    ],
    "wof:name":"Smartclean",
    "wof:placetype":"venue"
},
  "geometry": {"coordinates":[174.31572,-35.728588],"type":"Point"}
}