{
  "type": "Feature",
  "properties": {
    "iso:country":"NZ",
    "sg:address":"78 Delta Ave New Lynn ",
    "sg:city":"Auckland",
    "sg:orig_category":"Industrial: Engineering: Engineers - Precision",
    "sg:phone":"+64 9-827 5526",
    "sg:province":"Auckland",
    "wof:name":"Langslow Dave Engineering",
    "wof:placetype":"venue"
},
  "geometry": {"coordinates":[174.68585200000001,-36.902302],"type":"Point"}
}