{
  "type": "Feature",
  "properties": {
    "iso:country":"NZ",
    "sg:address":"C/o N G & M J Ward Milford RD 26 ",
    "sg:city":"Temuka",
    "sg:classifiers":[
        {
            "category":"Coffee & Tea",
            "type":"Food & Drink"
        }
    ],
    "sg:phone":"+64 3-615 9595",
    "sg:province":"Auckland",
    "sg:tags":[
        "vegetable",
        "fruit",
        "veges"
    ],
    "wof:name":"Garlic Factory The",
    "wof:placetype":"venue"
},
  "geometry": {"coordinates":[171.283234,-44.24078],"type":"Point"}
}