{
  "type": "Feature",
  "properties": {
    "addr:full":"C/o N G & M J Ward Milford RD 26  Temuka Auckland",
    "addr:housenumber":"/ o;26",
    "addr:street":"C;N;Milford Rd",
    "iso:country":"NZ",
    "sg:address":"C/o N G & M J Ward Milford RD 26 ",
    "sg:city":"Temuka",
    "sg:classifiers":[
        {
            "category":"Coffee & Tea",
            "type":"Food & Drink"
        }
    ],
    "sg:phone":"+64 3-615 9595",
    "sg:province":"Auckland",
    "sg:tags":[
        "vegetable",
        "fruit",
        "veges"
    ],
    "wof:name":"Garlic Factory The",
    "wof:placetype":"venue"
},
  "geometry": {"coordinates":[171.28323399999999,-44.24078],"type":"Point"}
}