{
  "type": "Feature",
  "properties": {
    "addr:full":"49 Manners St  Wellington Wellington",
    "addr:housenumber":"49",
    "addr:street":"Manners St",
    "iso:country":"NZ",
    "sg:address":"49 Manners St ",
    "sg:city":"Wellington",
    "sg:classifiers":[
        {
            "category":"Internet Cafe",
            "subcategory":"None",
            "type":"Food & Drink"
        }
    ],
    "sg:phone":"+64 4-494 0088",
    "sg:province":"Wellington",
    "sg:tags":[
        "wining",
        "dining"
    ],
    "wof:name":"iPlay",
    "wof:placetype":"venue"
},
  "geometry": {"coordinates":[-85.910454,33.827946],"type":"Point"}
}