{
  "type": "Feature",
  "properties": {
    "iso:country":"NZ",
    "sg:address":"232 Wairau Rd ",
    "sg:city":"Glenfield",
    "sg:orig_category":"Health And Beauty: Medical: Hospitals",
    "sg:phone":"+64 9-443 3285",
    "sg:province":"Auckland",
    "wof:name":"Birthcare Auckland Limited",
    "wof:placetype":"venue"
},
  "geometry": {"coordinates":[-75.404037,43.709122],"type":"Point"}
}