{
  "type": "Feature",
  "properties": {
    "addr:full":"18 A Joval Pl Manukau  Auckland Auckland",
    "addr:housenumber":"18",
    "addr:street":"A Joval Pl",
    "iso:country":"NZ",
    "sg:address":"18 A Joval Pl Manukau ",
    "sg:city":"Auckland",
    "sg:classifiers":[
        {
            "category":"Personal",
            "subcategory":"Tanning Parlor",
            "type":"Services"
        }
    ],
    "sg:phone":"+64 9-263 4541",
    "sg:province":"Auckland",
    "sg:tags":[
        "sun",
        "health",
        "beauty"
    ],
    "wof:name":"Sunbed Hire",
    "wof:placetype":"venue"
},
  "geometry": {"coordinates":[174.88145399999999,-36.98967],"type":"Point"}
}