{
  "type": "Feature",
  "properties": {
    "addr:full":"Orakei  Auckland Auckland",
    "iso:country":"NZ",
    "sg:address":"Orakei ",
    "sg:city":"Auckland",
    "sg:classifiers":[
        {
            "category":"Organizations",
            "subcategory":"Religious Organization",
            "type":"Services"
        }
    ],
    "sg:phone":"+64 508 266 554",
    "sg:province":"Auckland",
    "sg:tags":[
        "arrangements",
        "tent",
        "marquee",
        "wedding"
    ],
    "wof:name":"Cool Kiwi Co Limited",
    "wof:placetype":"venue"
},
  "geometry": {"coordinates":[174.81826799999999,-36.856617],"type":"Point"}
}