{
  "type": "Feature",
  "properties": {
    "iso:country":"NZ",
    "sg:address":"149 Nelson St Auckland Central ",
    "sg:city":"Auckland",
    "sg:classifiers":[
        {
            "category":"Manufacturing",
            "subcategory":"Textiles",
            "type":"Manufacturing & Wholesale Goods"
        }
    ],
    "sg:phone":"+64 9-300 7207",
    "sg:province":"Auckland",
    "sg:tags":[
        "clothing",
        "fabric",
        "manufacturer"
    ],
    "wof:name":"Cutting Services Limited",
    "wof:placetype":"venue"
},
  "geometry": {"coordinates":[174.75744599999999,-36.853695],"type":"Point"}
}