{
  "type": "Feature",
  "properties": {
    "addr:full":"1 Vogel St Naenae Lower  Hutt Wellington",
    "addr:housenumber":"1",
    "addr:street":"Vogel St",
    "iso:country":"NZ",
    "sg:address":"1 Vogel St Naenae Lower ",
    "sg:city":"Hutt",
    "sg:orig_category":"Food And Drink: Meats: Butchers",
    "sg:phone":"+64 4-577 0131",
    "sg:province":"Wellington",
    "wof:name":"Farm Fresh Meats",
    "wof:placetype":"venue"
},
  "geometry": {"coordinates":[174.94628900000001,-41.199131],"type":"Point"}
}