{
  "type": "Feature",
  "properties": {
    "addr:full":"5 Washington Pl West Eyreton RD 1 Rangiora  Cust",
    "addr:housenumber":"5;1",
    "addr:street":"Washington Pl West Eyreton Rd",
    "iso:country":"NZ",
    "sg:address":"5 Washington Pl West Eyreton RD 1 Rangiora ",
    "sg:city":"Cust",
    "sg:orig_category":"Industrial: Abrasives: Water Blasting",
    "sg:phone":"+64 3-312 5388",
    "wof:name":"Metcalfe B W & M T",
    "wof:placetype":"venue"
},
  "geometry": {"coordinates":[172.381561,-43.319183],"type":"Point"}
}