{
  "type": "Feature",
  "properties": {
    "iso:country":"NZ",
    "sg:address":"Unit 7 100 Hugo Johnston Dve Penrose ",
    "sg:city":"Auckland",
    "sg:classifiers":[
        {
            "category":"Parking",
            "subcategory":"Garage",
            "type":"Transportation"
        }
    ],
    "sg:phone":"+64 9-525 6694",
    "sg:province":"Auckland",
    "sg:tags":[
        "hire",
        "container",
        "transport",
        "lease"
    ],
    "wof:name":"TNT Pallecon Logistics",
    "wof:placetype":"venue"
},
  "geometry": {"coordinates":[174.823044,-36.92371],"type":"Point"}
}