{
  "type": "Feature",
  "properties": {
    "iso:country":"NZ",
    "sg:address":"180 Havelock Rd ",
    "sg:city":"Hastings",
    "sg:classifiers":[
        {
            "category":"Food & Beverages",
            "subcategory":"Liquor & Beverages",
            "type":"Retail Goods"
        }
    ],
    "sg:phone":"+64 6-870 8524",
    "sg:province":"Hawke's Bay",
    "sg:tags":[
        "drink",
        "maker",
        "wine"
    ],
    "wof:name":"Prenzel On The Bay",
    "wof:placetype":"venue"
},
  "geometry": {"coordinates":[-77.95661200000001,44.30928],"type":"Point"}
}