{
  "type": "Feature",
  "properties": {
    "iso:country":"NZ",
    "sg:address":"309 Fitzgerald Rd Drury ",
    "sg:city":"Auckland",
    "sg:classifiers":[
        {
            "category":"Home & Garden",
            "subcategory":"Building Materials",
            "type":"Retail Goods"
        }
    ],
    "sg:phone":"+64 9-294 7325",
    "sg:province":"Auckland",
    "sg:tags":[
        "bricklaying",
        "related"
    ],
    "wof:name":"O'Connor S",
    "wof:placetype":"venue"
},
  "geometry": {"coordinates":[174.964722,-37.116131],"type":"Point"}
}