{
  "type": "Feature",
  "properties": {
    "iso:country":"NZ",
    "sg:address":"15 Clyde St ",
    "sg:city":"Whangarei",
    "sg:orig_category":"Shopping: Retail Stores: Batteries",
    "sg:phone":"+64 9-438 8813",
    "sg:province":"Northland",
    "wof:name":"Exide Technologies",
    "wof:placetype":"venue"
},
  "geometry": {"coordinates":[174.32183800000001,-35.727192],"type":"Point"}
}