{
  "type": "Feature",
  "properties": {
    "iso:country":"NZ",
    "sg:address":"8 Te Kea Pl Albany ",
    "sg:city":"Auckland",
    "sg:classifiers":[
        {
            "category":"Food & Beverages",
            "subcategory":"Bakery",
            "type":"Retail Goods"
        }
    ],
    "sg:phone":"+64 9-415 8777",
    "sg:province":"Auckland",
    "sg:tags":[
        "decoration",
        "cake",
        "drink",
        "-",
        "supply"
    ],
    "wof:name":"Golden Bridge Marketing Ltd (Wholesale)",
    "wof:placetype":"venue"
},
  "geometry": {"coordinates":[174.70399499999999,-36.750801],"type":"Point"}
}