{
  "type": "Feature",
  "properties": {
    "addr:full":"1st Floor Ferry Bldg Quay St Auckland City  Auckland Auckland",
    "addr:street":"Quay St",
    "iso:country":"NZ",
    "sg:address":"1st Floor Ferry Bldg Quay St Auckland City ",
    "sg:city":"Auckland",
    "sg:classifiers":[
        {
            "category":"Restaurant",
            "type":"Food & Drink"
        }
    ],
    "sg:phone":"+64 9-307 0556",
    "sg:province":"Auckland",
    "sg:tags":[
        "wining",
        "dining"
    ],
    "sg:website":"http://www.harboursiderestaurant.co.nz",
    "wof:name":"Harbourside Seafood Bar & Grill",
    "wof:placetype":"venue"
},
  "geometry": {"coordinates":[174.78450000000001,-37.006058],"type":"Point"}
}