{
  "type": "Feature",
  "properties": {
    "addr:full":"Level 14 PSIS Building Cnr Ballance & Featherston, Sts PO Box 2364  Wellington Wellington",
    "addr:housenumber":"14;po box 2364",
    "addr:street":"Cnr Ballance & Featherston Sts",
    "iso:country":"NZ",
    "sg:address":"Level 14 PSIS Building Cnr Ballance & Featherston, Sts PO Box 2364 ",
    "sg:city":"Wellington",
    "sg:classifiers":[
        {
            "category":"Communications",
            "subcategory":"Television Station",
            "type":"Services"
        }
    ],
    "sg:phone":"+64 4-473 0117",
    "sg:province":"Wellington",
    "sg:tags":[
        "broadcasting"
    ],
    "wof:name":"Te Whakaruruhau O Nga Reo Irirangi Maori",
    "wof:placetype":"venue"
},
  "geometry": {"coordinates":[175.32214400000001,-41.112888],"type":"Point"}
}