{
  "type": "Feature",
  "properties": {
    "iso:country":"NZ",
    "sg:address":"146 Lower Dent St ",
    "sg:city":"Whangarei",
    "sg:orig_category":"Home And Garden: Furniture/Furnishings: Blinds",
    "sg:phone":"+64 9-438 3986",
    "sg:province":"Northland",
    "wof:name":"Frazerhurst Curtains & Blinds",
    "wof:placetype":"venue"
},
  "geometry": {"coordinates":[174.32939099999999,-35.727539],"type":"Point"}
}