{
  "type": "Feature",
  "properties": {
    "addr:full":"18 Downing St Palmerston  Palmerston North Manawatu-Wanganui",
    "addr:housenumber":"18",
    "addr:street":"Downing St Palmerston",
    "iso:country":"NZ",
    "sg:address":"18 Downing St Palmerston ",
    "sg:city":"Palmerston North",
    "sg:classifiers":[
        {
            "category":"Manufacturing",
            "subcategory":"Metals",
            "type":"Manufacturing & Wholesale Goods"
        }
    ],
    "sg:phone":"+64 6-355 9107",
    "sg:province":"Manawatu-Wanganui",
    "sg:tags":[
        "-",
        "engineering",
        "industrial",
        "sheet",
        "engineer"
    ],
    "wof:name":"Advanced Sheetmetals Ltd",
    "wof:placetype":"venue"
},
  "geometry": {"coordinates":[175.588348,-40.348171],"type":"Point"}
}