{
  "type": "Feature",
  "properties": {
    "addr:full":"PO Box 20-191  Bishopdale Canterbury",
    "addr:housenumber":"po box",
    "addr:postcode":"20-191",
    "addr:street":"Bishopdale",
    "iso:country":"NZ",
    "sg:address":"PO Box 20-191 ",
    "sg:city":"Bishopdale",
    "sg:classifiers":[
        {
            "category":"Home & Garden",
            "subcategory":"Home Furnishings",
            "type":"Retail Goods"
        }
    ],
    "sg:phone":"+64 256237050",
    "sg:province":"Canterbury",
    "sg:tags":[
        "accessory"
    ],
    "wof:name":"Feature Wood Products",
    "wof:placetype":"venue"
},
  "geometry": {"coordinates":[172.58607499999999,-43.487144],"type":"Point"}
}