{
  "type": "Feature",
  "properties": {
    "addr:full":"4 90 Mahoe St  Hamilton Waikato",
    "addr:housenumber":"90",
    "addr:street":"4;Mahoe St",
    "iso:country":"NZ",
    "sg:address":"4 90 Mahoe St ",
    "sg:city":"Hamilton",
    "sg:classifiers":[
        {
            "category":"Retail",
            "subcategory":"Repair Shop",
            "type":"Services"
        }
    ],
    "sg:phone":"+64 7-843 5531",
    "sg:province":"Waikato",
    "sg:tags":[
        "clothing",
        "fabric",
        "cleaning"
    ],
    "wof:name":"Beverley Allen Clothing Alterations",
    "wof:placetype":"venue"
},
  "geometry": {"coordinates":[175.27642800000001,-37.813217],"type":"Point"}
}