{
  "type": "Feature",
  "properties": {
    "addr:full":"34 William Pickering Dve Albany  Auckland Auckland",
    "addr:housenumber":"34",
    "addr:street":"William Pickering Dve",
    "iso:country":"NZ",
    "sg:address":"34 William Pickering Dve Albany ",
    "sg:city":"Auckland",
    "sg:classifiers":[
        {
            "category":"Sports & Exercise",
            "subcategory":"Ski Resort",
            "type":"Entertainment"
        }
    ],
    "sg:phone":"+64 9-415 3101",
    "sg:province":"Auckland",
    "sg:tags":[
        "hobbies",
        "photographic",
        "leisure",
        "developing"
    ],
    "wof:name":"A One Colour Laboratory",
    "wof:placetype":"venue"
},
  "geometry": {"coordinates":[174.697754,-36.74596],"type":"Point"}
}