{
  "type": "Feature",
  "properties": {
    "iso:country":"NZ",
    "sg:address":"Waitohi Downs ",
    "sg:city":"Hawarden",
    "sg:classifiers":[
        {
            "category":"Travel",
            "subcategory":"Travel Agent",
            "type":"Entertainment"
        }
    ],
    "sg:phone":"+64 3-314 4293",
    "sg:tags":[
        "tour",
        "tourism",
        "sightseeing"
    ],
    "sg:website":"http://www.alpinehorse.co.nz",
    "wof:name":"Alpine Horse Safaris Ltd",
    "wof:placetype":"venue"
},
  "geometry": {"coordinates":[-96.488091,42.997459],"type":"Point"}
}