{
  "type": "Feature",
  "properties": {
    "iso:country":"NZ",
    "sg:address":"1 New Bond St Eden Terrace ",
    "sg:city":"Auckland",
    "sg:classifiers":[
        {
            "category":"Health Services",
            "subcategory":"Clinic",
            "type":"Services"
        }
    ],
    "sg:phone":"+64 9-849 2124",
    "sg:province":"Auckland",
    "sg:tags":[
        "optical",
        "beauty",
        "supply"
    ],
    "wof:name":"Read Prescription Services Ltd",
    "wof:placetype":"venue"
},
  "geometry": {"coordinates":[174.770416,-36.884109],"type":"Point"}
}