{
  "type": "Feature",
  "properties": {
    "iso:country":"NZ",
    "sg:address":"827 Tremaine Ave Palmerston ",
    "sg:city":"Palmerston North",
    "sg:classifiers":[
        {
            "category":"Manufacturing",
            "subcategory":"Tools & Machinery",
            "type":"Manufacturing & Wholesale Goods"
        }
    ],
    "sg:phone":"+64 6-357 1365",
    "sg:province":"Manawatu-Wanganui",
    "sg:tags":[
        "equipment",
        "industrial",
        "hydraulic"
    ],
    "wof:name":"Manawatu Hydraulics Ltd",
    "wof:placetype":"venue"
},
  "geometry": {"coordinates":[175.622543,-40.333813],"type":"Point"}
}