{
  "type": "Feature",
  "properties": {
    "iso:country":"NZ",
    "sg:address":"14 Scarlet La Redwood ",
    "sg:city":"Christchurch",
    "sg:orig_category":"Home And Garden: Gardening: Services: Lawnmowing Services",
    "sg:phone":"+64 3-354 6697",
    "sg:province":"Canterbury",
    "sg:website":"http://www.yellowpages.co.nz/for/grassbustersltd/dp61183.html",
    "wof:name":"Grassbusters (2002)",
    "wof:placetype":"venue"
},
  "geometry": {"coordinates":[172.625534,-43.467388],"type":"Point"}
}