{
  "type": "Feature",
  "properties": {
    "addr:full":"Buchanan Place  Masterton Auckland",
    "addr:street":"Buchanan Place",
    "iso:country":"NZ",
    "sg:address":"Buchanan Place ",
    "sg:city":"Masterton",
    "sg:classifiers":[
        {
            "category":"Manufacturing",
            "subcategory":"Glass & Minerals",
            "type":"Manufacturing & Wholesale Goods"
        }
    ],
    "sg:phone":"+64 6-370 8081",
    "sg:province":"Auckland",
    "sg:tags":[
        "raw",
        "industrial",
        "quarry",
        "materials"
    ],
    "wof:name":"Wairarapa Aggregates Ltd",
    "wof:placetype":"venue"
},
  "geometry": {"coordinates":[175.61273199999999,-40.9641],"type":"Point"}
}