{
  "type": "Feature",
  "properties": {
    "iso:country":"NZ",
    "sg:address":"44 a Victoria St Alicetown ",
    "sg:city":"Wellington",
    "sg:orig_category":"Industrial: Electrical/Electronic: Electronic Instruments",
    "sg:phone":"+64 4-939 0906",
    "sg:province":"Wellington",
    "wof:name":"Logic Systems Ltd",
    "wof:placetype":"venue"
},
  "geometry": {"coordinates":[174.892807,-41.215389],"type":"Point"}
}