{
  "type": "Feature",
  "properties": {
    "addr:full":"Main Rd Nth  Greytown",
    "addr:street":"Main Rd Nth Greytown",
    "iso:country":"NZ",
    "sg:address":"Main Rd Nth ",
    "sg:city":"Greytown",
    "sg:orig_category":"Home And Garden: Gardening: Products: Garden Ornaments",
    "sg:phone":"+64 6-304 8152",
    "wof:name":"Living Stone of Greytown",
    "wof:placetype":"venue"
},
  "geometry": {"coordinates":[175.45356799999999,-41.08231],"type":"Point"}
}