{
  "type": "Feature",
  "properties": {
    "addr:full":"PO Box 202  Feilding Manawatu-Wanganui",
    "addr:housenumber":"po;202",
    "addr:street":"Box",
    "iso:country":"NZ",
    "sg:address":"PO Box 202 ",
    "sg:city":"Feilding",
    "sg:classifiers":[
        {
            "category":"Shopping",
            "subcategory":"Crafts & Fabrics",
            "type":"Retail Goods"
        }
    ],
    "sg:phone":"+64 6-323 3577",
    "sg:province":"Manawatu-Wanganui",
    "sg:tags":[
        "knitting",
        "wool",
        "clothing"
    ],
    "wof:name":"Te Awa Wools 1999",
    "wof:placetype":"venue"
},
  "geometry": {"coordinates":[175.54719499999999,-40.224236],"type":"Point"}
}