{
  "type": "Feature",
  "properties": {
    "iso:country":"NZ",
    "sg:address":"49 Bond St ",
    "sg:city":"Invercargill",
    "sg:orig_category":"Shopping: Retail Stores: Batteries",
    "sg:phone":"+64 3-218 8300",
    "sg:province":"Southland",
    "wof:name":"Southland Batteries Ltd",
    "wof:placetype":"venue"
},
  "geometry": {"coordinates":[168.33995100000001,-46.407902],"type":"Point"}
}