{
  "type": "Feature",
  "properties": {
    "addr:full":"28 Kamo Rd Kensington  Whangarei Northland",
    "addr:housenumber":"28",
    "addr:street":"Kamo Rd",
    "iso:country":"NZ",
    "sg:address":"28 Kamo Rd Kensington ",
    "sg:city":"Whangarei",
    "sg:orig_category":"Health And Beauty: Specialists: Chiropractors",
    "sg:phone":"+64 9-437 6600",
    "sg:province":"Northland",
    "wof:name":"Smith Dr Melissa",
    "wof:placetype":"venue"
},
  "geometry": {"coordinates":[174.32015999999999,-35.708782],"type":"Point"}
}