{
  "type": "Feature",
  "properties": {
    "iso:country":"NZ",
    "sg:address":"31 Hakanoa St Grey ",
    "sg:city":"Lynn",
    "sg:orig_category":"Health And Beauty: Mental: Psychotherapy",
    "sg:phone":"+64 25578518",
    "wof:name":"Woods Margot",
    "wof:placetype":"venue"
},
  "geometry": {"coordinates":[174.733597,-36.857708],"type":"Point"}
}