{
  "type": "Feature",
  "properties": {
    "addr:full":"30 Kinloch Pl Papakowhai  Wellington Wellington",
    "addr:housenumber":"30",
    "addr:street":"Kinloch Pl",
    "iso:country":"NZ",
    "sg:address":"30 Kinloch Pl Papakowhai ",
    "sg:city":"Wellington",
    "sg:orig_category":"Health And Beauty: Specialists: Chiropractors",
    "sg:phone":"+64 21 675 809",
    "sg:province":"Wellington",
    "wof:name":"MacLean Dr Deanna Chiropractor",
    "wof:placetype":"venue"
},
  "geometry": {"coordinates":[174.86514299999999,-41.115562],"type":"Point"}
}