{
  "type": "Feature",
  "properties": {
    "iso:country":"NZ",
    "sg:address":"22 Bowen St ",
    "sg:city":"Feilding",
    "sg:classifiers":[
        {
            "category":"Home & Garden",
            "subcategory":"Building Materials",
            "type":"Retail Goods"
        }
    ],
    "sg:phone":"+64 6-323 6544",
    "sg:province":"Manawatu-Wanganui",
    "sg:tags":[
        "builder",
        "related"
    ],
    "wof:name":"Jennian Homes",
    "wof:placetype":"venue"
},
  "geometry": {"coordinates":[175.56341599999999,-40.225243],"type":"Point"}
}