{
  "type": "Feature",
  "properties": {
    "addr:full":"The Crossing 686 Colombo St  Christchurch Wellington",
    "addr:housenumber":"686",
    "addr:street":"Crossing;Colombo St",
    "iso:country":"NZ",
    "sg:address":"The Crossing 686 Colombo St ",
    "sg:city":"Christchurch",
    "sg:orig_category":"Shopping: Retail Stores: Convenience Stores",
    "sg:phone":"+64 3-366 9210",
    "sg:province":"Wellington",
    "wof:name":"Starmart",
    "wof:placetype":"venue"
},
  "geometry": {"coordinates":[-76.537834,37.605659],"type":"Point"}
}