{
  "type": "Feature",
  "properties": {
    "iso:country":"NZ",
    "sg:address":"310 Grey St ",
    "sg:city":"Hamilton",
    "sg:orig_category":"Clothing And Fabric: Clothing: Menswear",
    "sg:phone":"+64 7-856 6721",
    "sg:province":"Waikato",
    "wof:name":"Hamilton East Menswear Ltd",
    "wof:placetype":"venue"
},
  "geometry": {"coordinates":[175.293533,-37.793312],"type":"Point"}
}