{
  "type": "Feature",
  "properties": {
    "addr:full":"35 Ngata St Palmerston  Palmerston North Manawatu-Wanganui",
    "addr:housenumber":"35",
    "addr:street":"Ngata St Palmerston",
    "iso:country":"NZ",
    "sg:address":"35 Ngata St Palmerston ",
    "sg:city":"Palmerston North",
    "sg:classifiers":[
        {
            "category":"Education",
            "subcategory":"Dance Studio",
            "type":"Public Place"
        }
    ],
    "sg:phone":"+64 6-359 3905",
    "sg:province":"Manawatu-Wanganui",
    "sg:tags":[
        "school",
        "dancing",
        "-",
        "leisure",
        "sports",
        "sport"
    ],
    "wof:name":"Dean McKerras School of Dance",
    "wof:placetype":"venue"
},
  "geometry": {"coordinates":[175.61132799999999,-40.351376],"type":"Point"}
}