{
  "type": "Feature",
  "properties": {
    "addr:full":"3 Den Pl  Tauranga Bay of Plenty",
    "addr:housenumber":"3",
    "addr:street":"Den Pl",
    "iso:country":"NZ",
    "sg:address":"3 Den Pl ",
    "sg:city":"Tauranga",
    "sg:orig_category":"Industrial: Equipment And Machinery: Compressors",
    "sg:phone":"+64 7-571 5410",
    "sg:province":"Bay of Plenty",
    "wof:name":"Bayteck Systems Ltd",
    "wof:placetype":"venue"
},
  "geometry": {"coordinates":[176.170288,-37.673931],"type":"Point"}
}