{
  "type": "Feature",
  "properties": {
    "addr:full":"12 Taonui St Palmerston  Palmerston North Manawatu-Wanganui",
    "addr:housenumber":"12",
    "addr:street":"Taonui St Palmerston",
    "iso:country":"NZ",
    "sg:address":"12 Taonui St Palmerston ",
    "sg:city":"Palmerston North",
    "sg:classifiers":[
        {
            "category":"Shopping",
            "subcategory":"Hobbies, Toys, & Games",
            "type":"Retail Goods"
        }
    ],
    "sg:phone":"+64 6-358 9085",
    "sg:province":"Manawatu-Wanganui",
    "sg:tags":[
        "hobby"
    ],
    "sg:website":"http://www.phototronic.co.nz",
    "wof:name":"Phototronic Services (1995) Ltd",
    "wof:placetype":"venue"
},
  "geometry": {"coordinates":[175.60488899999999,-40.351246],"type":"Point"}
}