{
  "type": "Feature",
  "properties": {
    "iso:country":"NZ",
    "sg:address":"143 b Maunganui Rd Mt ",
    "sg:city":"Maunganui",
    "sg:classifiers":[
        {
            "category":"Bars & Pubs",
            "type":"Food & Drink"
        }
    ],
    "sg:phone":"+64 7-574 0477",
    "sg:province":"Bay of Plenty",
    "sg:tags":[
        "wining",
        "dining",
        "brasserie"
    ],
    "wof:name":"The Office",
    "wof:placetype":"venue"
},
  "geometry": {"coordinates":[176.18331900000001,-37.637703],"type":"Point"}
}