{
  "type": "Feature",
  "properties": {
    "iso:country":"NZ",
    "sg:address":"14 Beswick St ",
    "sg:city":"Kaiapoi",
    "sg:classifiers":[
        {
            "category":"Travel",
            "subcategory":"Bed & Breakfast",
            "type":"Entertainment"
        }
    ],
    "sg:phone":"+64 3-327 4891",
    "sg:tags":[
        "tourism",
        "accommodation"
    ],
    "sg:website":"http://www.nzhomestay.co.nz/pages/Canterbury/HO_262.html",
    "wof:name":"Beswick House Homestay",
    "wof:placetype":"venue"
},
  "geometry": {"coordinates":[172.664444,-43.384216],"type":"Point"}
}