{
  "type": "Feature",
  "properties": {
    "iso:country":"NZ",
    "sg:address":"153 Dee St ",
    "sg:city":"Invercargill",
    "sg:classifiers":[
        {
            "category":"Shopping",
            "subcategory":"Musical Instruments",
            "type":"Retail Goods"
        }
    ],
    "sg:phone":"+64 3-214 0673",
    "sg:province":"Southland",
    "sg:tags":[
        "sport",
        "music",
        "leisure"
    ],
    "wof:name":"Masterpiece Music Centre",
    "wof:placetype":"venue"
},
  "geometry": {"coordinates":[168.347321,-46.392628],"type":"Point"}
}