{
  "type": "Feature",
  "properties": {
    "addr:full":"PO Box 4259 New Plymouth  Oakura",
    "addr:housenumber":"po;4259",
    "addr:street":"Box",
    "iso:country":"NZ",
    "sg:address":"PO Box 4259 New Plymouth ",
    "sg:city":"Oakura",
    "sg:orig_category":"Industrial: Services: Specialist Services: Vibration Analysis",
    "sg:phone":"+64 6-752 7571",
    "wof:name":"Brown Yardley & Associates Ltd",
    "wof:placetype":"venue"
},
  "geometry": {"coordinates":[173.95230100000001,-39.115391],"type":"Point"}
}