{
  "type": "Feature",
  "properties": {
    "iso:country":"NZ",
    "sg:address":"60 Herbert St ",
    "sg:city":"Greymouth",
    "sg:classifiers":[
        {
            "category":"Food & Beverages",
            "subcategory":"Liquor & Beverages",
            "type":"Retail Goods"
        }
    ],
    "sg:phone":"+64 3-768 4149",
    "sg:province":"West Coast",
    "sg:tags":[
        "drink",
        "outlet"
    ],
    "wof:name":"Monteiths Brewing Company",
    "wof:placetype":"venue"
},
  "geometry": {"coordinates":[171.20723,-42.453209],"type":"Point"}
}