{
  "type": "Feature",
  "properties": {
    "addr:full":"106 Tainui St  Greymouth West Coast",
    "addr:housenumber":"106",
    "addr:street":"Tainui St",
    "iso:country":"NZ",
    "sg:address":"106 Tainui St ",
    "sg:city":"Greymouth",
    "sg:orig_category":"Health And Beauty: Specialists: Physiotherapists",
    "sg:phone":"+64 3-768 5836",
    "sg:province":"West Coast",
    "wof:name":"Sara Roberts Physiotherapy",
    "wof:placetype":"venue"
},
  "geometry": {"coordinates":[171.20938100000001,-42.452164],"type":"Point"}
}