{
  "type": "Feature",
  "properties": {
    "iso:country":"NZ",
    "sg:address":"PO Box 1066 Papakura ",
    "sg:city":"Auckland",
    "sg:classifiers":[
        {
            "category":"Arena",
            "subcategory":"Sports Club",
            "type":"Entertainment"
        }
    ],
    "sg:phone":"+64 9-267 7788",
    "sg:province":"Auckland",
    "sg:tags":[
        "martial art",
        "-",
        "leisure",
        "sports"
    ],
    "wof:name":"Southern Martial Arts Centre",
    "wof:placetype":"venue"
},
  "geometry": {"coordinates":[174.95945699999999,-37.059521],"type":"Point"}
}