{
  "type": "Feature",
  "properties": {
    "addr:full":"308 Lincoln Rd Addtn Christchurch Canterbury",
    "addr:housenumber":"308",
    "addr:street":"Lincoln Rd",
    "iso:country":"NZ",
    "sg:address":"308 Lincoln Rd Addtn",
    "sg:city":"Christchurch",
    "sg:classifiers":[
        {
            "category":"Banks & Credit Unions",
            "subcategory":"Bank",
            "type":"Services"
        }
    ],
    "sg:phone":"+64 3-338 4523",
    "sg:province":"Canterbury",
    "wof:name":"Trust Bank Canterbury Ltd",
    "wof:placetype":"venue"
},
  "geometry": {"coordinates":[172.611816,-43.543697],"type":"Point"}
}