{
  "type": "Feature",
  "properties": {
    "iso:country":"NZ",
    "sg:address":"900/9 Hopetoun St Auckland Central ",
    "sg:city":"Auckland",
    "sg:classifiers":[
        {
            "category":"Communications",
            "subcategory":"Film & Video Production",
            "type":"Services"
        }
    ],
    "sg:phone":"+64 9-377 7033",
    "sg:province":"Auckland",
    "sg:tags":[
        "broadcasting",
        "studio",
        "producer"
    ],
    "wof:name":"Film Investment Corporation",
    "wof:placetype":"venue"
},
  "geometry": {"coordinates":[174.755264,-36.857288],"type":"Point"}
}