{
  "type": "Feature",
  "properties": {
    "addr:full":"52 Lune St  Oamaru Otago",
    "addr:housenumber":"52",
    "addr:street":"Lune St",
    "iso:country":"NZ",
    "sg:address":"52 Lune St ",
    "sg:city":"Oamaru",
    "sg:classifiers":[
        {
            "category":"Organizations",
            "subcategory":"Community Association",
            "type":"Services"
        }
    ],
    "sg:phone":"+64 3-434 8422",
    "sg:province":"Otago",
    "sg:tags":[
        "funeral",
        "arrangements",
        "monumental",
        "mason"
    ],
    "wof:name":"Crombie Monumentalist",
    "wof:placetype":"venue"
},
  "geometry": {"coordinates":[170.957718,-45.106895],"type":"Point"}
}