{
  "type": "Feature",
  "properties": {
    "addr:full":"4 Kitson Pl Mt Wellington  Auckland Auckland",
    "addr:housenumber":"4",
    "addr:street":"Kitson Pl",
    "iso:country":"NZ",
    "sg:address":"4 Kitson Pl Mt Wellington ",
    "sg:city":"Auckland",
    "sg:classifiers":[
        {
            "category":"Shopping",
            "subcategory":"Clothing, Apparel, & Fashions",
            "type":"Retail Goods"
        }
    ],
    "sg:phone":"+64 9-570 9813",
    "sg:province":"Auckland",
    "sg:tags":[
        "repair",
        "fabric",
        "-",
        "cleaning",
        "pressers",
        "clothing"
    ],
    "wof:name":"C & F Tradepressers Ltd",
    "wof:placetype":"venue"
},
  "geometry": {"coordinates":[174.85012800000001,-36.888527],"type":"Point"}
}