{
  "type": "Feature",
  "properties": {
    "addr:full":"576 Gt South Rd Papatoetoe  Auckland Auckland",
    "addr:housenumber":"576",
    "addr:street":"Gt South Rd",
    "iso:country":"NZ",
    "sg:address":"576 Gt South Rd Papatoetoe ",
    "sg:city":"Auckland",
    "sg:classifiers":[
        {
            "category":"Bars & Pubs",
            "subcategory":"Lounge",
            "type":"Food & Drink"
        }
    ],
    "sg:phone":"+64 9-279 3122",
    "sg:province":"Auckland",
    "sg:tags":[
        "baker",
        "-"
    ],
    "wof:name":"B & T Bakeries & Takeaways",
    "wof:placetype":"venue"
},
  "geometry": {"coordinates":[174.876724,-36.980556],"type":"Point"}
}