{
  "type": "Feature",
  "properties": {
    "iso:country":"NZ",
    "sg:address":"cnr Queen & Market Sts ",
    "sg:city":"Hastings",
    "sg:classifiers":[
        {
            "category":"Banks & Credit Unions",
            "subcategory":"Financial Services",
            "type":"Services"
        }
    ],
    "sg:phone":"+64 6-878 9792",
    "sg:province":"Hawke's Bay",
    "sg:tags":[
        "personal",
        "loan",
        "-",
        "finance",
        "mortgage"
    ],
    "wof:name":"HBS",
    "wof:placetype":"venue"
},
  "geometry": {"coordinates":[-98.392372,40.585651],"type":"Point"}
}