{
  "type": "Feature",
  "properties": {
    "addr:full":"PO Box 13074  Hamilton Waikato",
    "addr:housenumber":"po box 13074",
    "iso:country":"NZ",
    "sg:address":"PO Box 13074 ",
    "sg:city":"Hamilton",
    "sg:orig_category":"Industrial: Services: Drillers",
    "sg:phone":"+64 7-856 8683",
    "sg:province":"Waikato",
    "wof:name":"King Drilling Co Ltd",
    "wof:placetype":"venue"
},
  "geometry": {"coordinates":[-87.988968,34.142426],"type":"Point"}
}