{
  "type": "Feature",
  "properties": {
    "addr:full":"13 Markham St  Amberley Canterbury",
    "addr:housenumber":"13",
    "addr:street":"Markham St",
    "iso:country":"NZ",
    "sg:address":"13 Markham St ",
    "sg:city":"Amberley",
    "sg:classifiers":[
        {
            "category":"Manufacturing",
            "subcategory":"Food",
            "type":"Manufacturing & Wholesale Goods"
        }
    ],
    "sg:phone":"+64 3-314 7033",
    "sg:province":"Canterbury",
    "sg:tags":[
        "processing",
        "drink"
    ],
    "wof:name":"Homekill Processing Ltd",
    "wof:placetype":"venue"
},
  "geometry": {"coordinates":[-84.430695,39.200546],"type":"Point"}
}