{
  "type": "Feature",
  "properties": {
    "iso:country":"NZ",
    "sg:address":"130 Udys Rd Pakuranga ",
    "sg:city":"Auckland",
    "sg:classifiers":[
        {
            "category":"Personal",
            "subcategory":"Beauty Salon",
            "type":"Services"
        }
    ],
    "sg:phone":"+64 9-576 9526",
    "sg:province":"Auckland",
    "sg:tags":[
        "therapy",
        "health"
    ],
    "wof:name":"Hannah Parker-Beauty Therapist",
    "wof:placetype":"venue"
},
  "geometry": {"coordinates":[174.88186645510001,-36.9194450378],"type":"Point"}
}