{
  "type": "Feature",
  "properties": {
    "addr:full":"283-301 Moray Pl  Dunedin Otago",
    "addr:housenumber":"283-301",
    "addr:street":"Moray Pl",
    "iso:country":"NZ",
    "sg:address":"283-301 Moray Pl ",
    "sg:city":"Dunedin",
    "sg:classifiers":[
        {
            "category":"Health Services",
            "subcategory":"Health Practitioner",
            "type":"Services"
        }
    ],
    "sg:phone":"+64 3-471 6160",
    "sg:province":"Otago",
    "sg:tags":[
        "consultant",
        "medical",
        "beauty"
    ],
    "wof:name":"Arthritis Foundation (NZ) Inc (Otago Div)",
    "wof:placetype":"venue"
},
  "geometry": {"coordinates":[170.505539,-45.87326],"type":"Point"}
}