{
  "type": "Feature",
  "properties": {
    "addr:full":"250 Stanmore Rd Richmond  Christchurch Nelson",
    "addr:housenumber":"250",
    "addr:street":"Stanmore Rd",
    "iso:country":"NZ",
    "sg:address":"250 Stanmore Rd Richmond ",
    "sg:city":"Christchurch",
    "sg:classifiers":[
        {
            "category":"Home & Garden",
            "subcategory":"Kitchen Supply",
            "type":"Retail Goods"
        }
    ],
    "sg:phone":"+64 3-389 2460",
    "sg:province":"Nelson",
    "sg:tags":[
        "shop",
        "pet",
        "pets"
    ],
    "wof:name":"The Fish Tank",
    "wof:placetype":"venue"
},
  "geometry": {"coordinates":[172.656677,-43.522602],"type":"Point"}
}