{
  "type": "Feature",
  "properties": {
    "addr:full":"94 Boundary Rd Tikipunga  Whangarei Northland",
    "addr:housenumber":"94",
    "addr:street":"Boundary Rd",
    "iso:country":"NZ",
    "sg:address":"94 Boundary Rd Tikipunga ",
    "sg:city":"Whangarei",
    "sg:classifiers":[
        {
            "category":"Social Services",
            "subcategory":"Retirement Home",
            "type":"Services"
        }
    ],
    "sg:phone":"+64 9-437 5844",
    "sg:province":"Northland",
    "sg:tags":[
        "care",
        "garden",
        "elderly",
        "village"
    ],
    "wof:name":"The Falls Estate",
    "wof:placetype":"venue"
},
  "geometry": {"coordinates":[174.33419799999999,-35.686844],"type":"Point"}
}