{
  "type": "Feature",
  "properties": {
    "iso:country":"NZ",
    "sg:address":"Brooklyn ",
    "sg:city":"Wellington",
    "sg:classifiers":[
        {
            "category":"Coffee & Tea",
            "type":"Food & Drink"
        }
    ],
    "sg:phone":"+64 4-934 9798",
    "sg:province":"Wellington",
    "sg:tags":[
        "vegetable",
        "fruit",
        "veges"
    ],
    "wof:name":"Nature's Backyard",
    "wof:placetype":"venue"
},
  "geometry": {"coordinates":[174.761185,-41.304153],"type":"Point"}
}