{
  "type": "Feature",
  "properties": {
    "iso:country":"NZ",
    "sg:address":"268 Devon St East New ",
    "sg:city":"Plymouth",
    "sg:classifiers":[
        {
            "category":"Organizations",
            "subcategory":"Community Association",
            "type":"Services"
        }
    ],
    "sg:phone":"+64 6-759 9975",
    "sg:province":"Taranaki",
    "sg:tags":[
        "funeral",
        "arrangements",
        "monumental",
        "mason"
    ],
    "wof:name":"Everlasting Memories Monumentalists",
    "wof:placetype":"venue"
},
  "geometry": {"coordinates":[-116.819725,43.97221],"type":"Point"}
}