{
  "type": "Feature",
  "properties": {
    "addr:full":"14 Bay Rd  Invercargill Southland",
    "addr:housenumber":"14",
    "addr:street":"Bay Rd",
    "iso:country":"NZ",
    "sg:address":"14 Bay Rd ",
    "sg:city":"Invercargill",
    "sg:classifiers":[
        {
            "category":"Retail",
            "subcategory":"Auto Repair",
            "type":"Services"
        }
    ],
    "sg:phone":"+64 3-215 9081",
    "sg:province":"Southland",
    "sg:tags":[
        "automotive",
        "panel",
        "servicing",
        "beater"
    ],
    "wof:name":"Gordon Officer (1991) Ltd",
    "wof:placetype":"venue"
},
  "geometry": {"coordinates":[168.346115,-46.388996],"type":"Point"}
}