{
  "type": "Feature",
  "properties": {
    "iso:country":"NZ",
    "sg:address":"The Quay Point Building Quay Point ",
    "sg:city":"Gisborne",
    "sg:orig_category":"Industrial: Engineering: Engineers: Engineers - Consulting",
    "sg:phone":"+64 6-867 6452",
    "sg:province":"Gisborne",
    "wof:name":"Loughnan Hall & Thompson Ltd",
    "wof:placetype":"venue"
},
  "geometry": {"coordinates":[177.836197,-38.252838],"type":"Point"}
}