{
  "type": "Feature",
  "properties": {
    "addr:full":"(Auckland  City)",
    "iso:country":"NZ",
    "sg:address":"(Auckland ",
    "sg:city":"City)",
    "sg:classifiers":[
        {
            "category":"Sports & Exercise",
            "subcategory":"Swimming Pool",
            "type":"Entertainment"
        }
    ],
    "sg:phone":"+64 25927949",
    "sg:tags":[
        "home",
        "outdoor",
        "garden",
        "spa"
    ],
    "wof:name":"Landscape Designs Pools & Spas",
    "wof:placetype":"venue"
},
  "geometry": {"coordinates":[170.36663799999999,-43.587711],"type":"Point"}
}