{
  "type": "Feature",
  "properties": {
    "iso:country":"NZ",
    "sg:address":"18 Wiltshire St ",
    "sg:city":"Arrowtown",
    "sg:orig_category":"Home And Garden: Gardening: Services: Landscape Architects",
    "sg:phone":"+64 3-442 0303",
    "sg:province":"Otago",
    "wof:name":"Blakely, Wallace Associates",
    "wof:placetype":"venue"
},
  "geometry": {"coordinates":[168.831772,-44.939358],"type":"Point"}
}