{
  "type": "Feature",
  "properties": {
    "iso:country":"NZ",
    "sg:address":"2 B Udy St Petone Lower ",
    "sg:city":"Hutt",
    "sg:orig_category":"Shopping: Sports Retailers: Sports Goods: Canvas Goods",
    "sg:phone":"+64 4-568 3327",
    "sg:province":"Wellington",
    "wof:name":"Gourock NZ Ltd",
    "wof:placetype":"venue"
},
  "geometry": {"coordinates":[174.87858600000001,-41.220078],"type":"Point"}
}