{
  "type": "Feature",
  "properties": {
    "addr:full":"46 Maleme St Greerton  Tauranga Bay of Plenty",
    "addr:housenumber":"46",
    "addr:street":"Maleme St",
    "iso:country":"NZ",
    "sg:address":"46 Maleme St Greerton ",
    "sg:city":"Tauranga",
    "sg:classifiers":[
        {
            "category":"Home & Garden",
            "subcategory":"Building Materials",
            "type":"Retail Goods"
        }
    ],
    "sg:phone":"+64 7-541 2121",
    "sg:province":"Bay of Plenty",
    "sg:tags":[
        "gate",
        "fitting",
        "outdoor"
    ],
    "wof:name":"Comet Services Ltd",
    "wof:placetype":"venue"
},
  "geometry": {"coordinates":[176.135986,-37.736366],"type":"Point"}
}