{
  "type": "Feature",
  "properties": {
    "addr:full":"Cnr Karepiro DR & Rishworth AV Arkles Bay  Auckland Auckland",
    "addr:street":"Cnr Karepiro Dr & Rishworth Av Arkles",
    "iso:country":"NZ",
    "sg:address":"Cnr Karepiro DR & Rishworth AV Arkles Bay ",
    "sg:city":"Auckland",
    "sg:classifiers":[
        {
            "category":"Retail",
            "subcategory":"Auto Repair",
            "type":"Services"
        }
    ],
    "sg:phone":"+64 800 782 9663",
    "sg:province":"Auckland",
    "sg:tags":[
        "automotive",
        "servicing"
    ],
    "sg:website":"http://www.cheapcarspeakers.com",
    "wof:name":"Car Audio Company Ltd",
    "wof:placetype":"venue"
},
  "geometry": {"coordinates":[174.745926,-36.640411],"type":"Point"}
}