{
  "type": "Feature",
  "properties": {
    "addr:full":"12 Maleme St  Tauranga Bay of Plenty",
    "addr:housenumber":"12",
    "addr:street":"Maleme St",
    "iso:country":"NZ",
    "sg:address":"12 Maleme St ",
    "sg:city":"Tauranga",
    "sg:classifiers":[
        {
            "category":"Manufacturing",
            "subcategory":"Furniture",
            "type":"Manufacturing & Wholesale Goods"
        }
    ],
    "sg:phone":"+64 7-541 0554",
    "sg:province":"Bay of Plenty",
    "sg:tags":[
        "furniture/furnishings",
        "home",
        "garden",
        "manufacturer"
    ],
    "wof:name":"Creative Furniture",
    "wof:placetype":"venue"
},
  "geometry": {"coordinates":[176.14082300000001,-37.736813],"type":"Point"}
}