{
  "type": "Feature",
  "properties": {
    "iso:country":"NZ",
    "sg:address":"3353 Ida Valley-Omakau Rd ",
    "sg:city":"Ranfurly",
    "sg:orig_category":"Shopping: Retail Stores: Supermarkets",
    "sg:phone":"+64 3-444 5808",
    "wof:name":"Gilchrist's Oturehua Store Ltd",
    "wof:placetype":"venue"
},
  "geometry": {"coordinates":[170.103378,-45.125645],"type":"Point"}
}