{
  "type": "Feature",
  "properties": {
    "addr:full":"3353 Ida Valley-Omakau Rd  Ranfurly",
    "addr:housenumber":"3353",
    "addr:street":"Ida Valley-Omakau Rd",
    "iso:country":"NZ",
    "sg:address":"3353 Ida Valley-Omakau Rd ",
    "sg:city":"Ranfurly",
    "sg:orig_category":"Shopping: Retail Stores: Supermarkets",
    "sg:phone":"+64 3-444 5808",
    "wof:name":"Gilchrist's Oturehua Store Ltd",
    "wof:placetype":"venue"
},
  "geometry": {"coordinates":[170.10337799999999,-45.125645],"type":"Point"}
}