{
  "type": "Feature",
  "properties": {
    "addr:full":"199 Thames St  Oamaru Otago",
    "addr:housenumber":"199",
    "addr:street":"Thames St",
    "iso:country":"NZ",
    "sg:address":"199 Thames St ",
    "sg:city":"Oamaru",
    "sg:orig_category":"Shopping: Accessories: Jewellers And Watchmakers",
    "sg:phone":"+64 3-434 6034",
    "sg:province":"Otago",
    "wof:name":"Time Technology Nationwide Jeweller",
    "wof:placetype":"venue"
},
  "geometry": {"coordinates":[170.97195400000001,-45.096275],"type":"Point"}
}