{
  "type": "Feature",
  "properties": {
    "iso:country":"NZ",
    "sg:address":"22 Torridge St ",
    "sg:city":"Oamaru",
    "sg:classifiers":[
        {
            "category":"Social Services",
            "subcategory":"Child Care",
            "type":"Services"
        }
    ],
    "sg:phone":"+64 3-434 5960",
    "sg:province":"Otago",
    "sg:tags":[
        "home",
        "garden",
        "children"
    ],
    "wof:name":"Teddy Bears Educare Centre",
    "wof:placetype":"venue"
},
  "geometry": {"coordinates":[170.974457,-45.092606],"type":"Point"}
}