{
  "type": "Feature",
  "properties": {
    "addr:full":"52 A Mandeville St  Christchurch Canterbury",
    "addr:housenumber":"52 a",
    "addr:street":"Mandeville St",
    "iso:country":"NZ",
    "sg:address":"52 A Mandeville St ",
    "sg:city":"Christchurch",
    "sg:classifiers":[
        {
            "category":"Health Services",
            "subcategory":"Doctor",
            "type":"Services"
        }
    ],
    "sg:phone":"+64 3-343 6365",
    "sg:province":"Canterbury",
    "sg:tags":[
        "specialists",
        "surgery",
        "cosmetic",
        "beauty"
    ],
    "wof:name":"Transform",
    "wof:placetype":"venue"
},
  "geometry": {"coordinates":[-76.537834,37.605659],"type":"Point"}
}