{
  "type": "Feature",
  "properties": {
    "iso:country":"NZ",
    "sg:address":"366 Dee St Avenal ",
    "sg:city":"Invercargill",
    "sg:classifiers":[
        {
            "category":"Shopping",
            "subcategory":"Pharmacy",
            "type":"Retail Goods"
        }
    ],
    "sg:phone":"+64 3-214 7783",
    "sg:province":"Southland",
    "sg:tags":[
        "product",
        "health"
    ],
    "wof:name":"Silberhorn",
    "wof:placetype":"venue"
},
  "geometry": {"coordinates":[168.34698499999999,-46.397198],"type":"Point"}
}