{
  "type": "Feature",
  "properties": {
    "addr:full":"620 Te Ngae Rd  Rotorua Bay of Plenty",
    "addr:housenumber":"620",
    "addr:street":"Te Ngae Rd",
    "iso:country":"NZ",
    "sg:address":"620 Te Ngae Rd ",
    "sg:city":"Rotorua",
    "sg:classifiers":[
        {
            "category":"Landmark",
            "subcategory":"Tourist Information",
            "type":"Public Place"
        }
    ],
    "sg:phone":"+64 7-345 6543",
    "sg:province":"Bay of Plenty",
    "sg:tags":[
        "travel",
        "tourism",
        "tour",
        "sightseeing"
    ],
    "sg:website":"http://www.riverrats.co.nz",
    "wof:name":"River Rats Whitewater Rafting & Adventures",
    "wof:placetype":"venue"
},
  "geometry": {"coordinates":[176.25822400000001,-38.145161],"type":"Point"}
}