{
  "type": "Feature",
  "properties": {
    "iso:country":"NZ",
    "sg:address":"101 Clyde Rd Browns Bay ",
    "sg:city":"Auckland",
    "sg:classifiers":[
        {
            "category":"Shopping",
            "subcategory":"Bridal",
            "type":"Retail Goods"
        }
    ],
    "sg:phone":"+64 9-478 2892",
    "sg:province":"Auckland",
    "sg:tags":[
        "arrangements",
        "wear",
        "wedding"
    ],
    "wof:name":"Play it Again Bridal Wear",
    "wof:placetype":"venue"
},
  "geometry": {"coordinates":[174.74854999999999,-36.71394],"type":"Point"}
}