{
  "type": "Feature",
  "properties": {
    "addr:full":"30 Downer St Lower Hutt  Wellington Wellington",
    "addr:housenumber":"30",
    "addr:street":"Downer St",
    "iso:country":"NZ",
    "sg:address":"30 Downer St Lower Hutt ",
    "sg:city":"Wellington",
    "sg:orig_category":"Industrial: Products: Filters And Filtration",
    "sg:phone":"+64 4-570 7500",
    "sg:province":"Wellington",
    "wof:name":"Medic Scientific",
    "wof:placetype":"venue"
},
  "geometry": {"coordinates":[174.91301000000001,-41.206146],"type":"Point"}
}