{
  "type": "Feature",
  "properties": {
    "iso:country":"NZ",
    "sg:address":"PO Box 751 ",
    "sg:city":"Blenheim",
    "sg:orig_category":"Farming: Forestry",
    "sg:phone":"+64 3-578 1733",
    "sg:province":"Marlborough",
    "sg:website":"http://www.palms.co.nz",
    "wof:name":"P.A.L.M.S.Ltd",
    "wof:placetype":"venue"
},
  "geometry": {"coordinates":[-74.459564,42.468643],"type":"Point"}
}