{
  "type": "Feature",
  "properties": {
    "addr:full":"26-38 Andrew Baxter Dve Mangere  Auckland Auckland",
    "addr:housenumber":"26-38;mangere",
    "addr:street":"Andrew Baxter Dve",
    "iso:country":"NZ",
    "sg:address":"26-38 Andrew Baxter Dve Mangere ",
    "sg:city":"Auckland",
    "sg:orig_category":"Industrial: Packaging: Bags",
    "sg:phone":"+64 9-275 0169",
    "sg:province":"Auckland",
    "wof:name":"Epic Flexible Packaging Ltd",
    "wof:placetype":"venue"
},
  "geometry": {"coordinates":[174.780045,-36.976269],"type":"Point"}
}