{
  "type": "Feature",
  "properties": {
    "addr:full":"Bolt Pl Christchurch Airport  Christchurch Canterbury",
    "addr:street":"Bolt Pl",
    "iso:country":"NZ",
    "sg:address":"Bolt Pl Christchurch Airport ",
    "sg:city":"Christchurch",
    "sg:classifiers":[
        {
            "category":"Restaurant",
            "type":"Food & Drink"
        }
    ],
    "sg:phone":"+64 3-358 2761",
    "sg:province":"Canterbury",
    "sg:tags":[
        "fishing",
        "sea"
    ],
    "wof:name":"Ngai Tahu Seafood Lobster Plant",
    "wof:placetype":"venue"
},
  "geometry": {"coordinates":[172.547134,-43.494045],"type":"Point"}
}