{
  "type": "Feature",
  "properties": {
    "addr:full":"Greers Rd Bryndwr  Christchurch Canterbury",
    "addr:street":"Greers Rd",
    "iso:country":"NZ",
    "sg:address":"Greers Rd Bryndwr ",
    "sg:city":"Christchurch",
    "sg:orig_category":"Shopping: Sports Retailers: Sports Goods: Dance Supplies",
    "sg:phone":"+64 3-359 4294",
    "sg:province":"Canterbury",
    "wof:name":"JJJoy Dancewear",
    "wof:placetype":"venue"
},
  "geometry": {"coordinates":[172.58485400000001,-43.50108],"type":"Point"}
}