{
  "type": "Feature",
  "properties": {
    "iso:country":"NZ",
    "sg:address":"cnr Dawson & Devon St West New ",
    "sg:city":"Plymouth",
    "sg:classifiers":[
        {
            "category":"Retail",
            "subcategory":"Auto Repair",
            "type":"Services"
        }
    ],
    "sg:phone":"+64 6-758 3777",
    "sg:province":"Taranaki",
    "sg:tags":[
        "clutch",
        "brake",
        "servicing",
        "automotive"
    ],
    "wof:name":"Huzziff Motors",
    "wof:placetype":"venue"
},
  "geometry": {"coordinates":[-116.81971,43.972191],"type":"Point"}
}