{
  "type": "Feature",
  "properties": {
    "addr:full":"189 Pigeon Mountain Rd Pakuranga  Auckland Auckland",
    "addr:housenumber":"189",
    "addr:street":"Pigeon Mountain Rd",
    "iso:country":"NZ",
    "sg:address":"189 Pigeon Mountain Rd Pakuranga ",
    "sg:city":"Auckland",
    "sg:classifiers":[
        {
            "category":"Bars & Pubs",
            "subcategory":"Wine Bar",
            "type":"Food & Drink"
        }
    ],
    "sg:phone":"+64 9-537 2174",
    "sg:province":"Auckland",
    "sg:tags":[
        "wining",
        "dining",
        "cafe"
    ],
    "wof:name":"Lily Cafe",
    "wof:placetype":"venue"
},
  "geometry": {"coordinates":[174.90147400000001,-36.898212],"type":"Point"}
}