{
  "type": "Feature",
  "properties": {
    "iso:country":"NZ",
    "sg:address":"189 Pigeon Mountain Rd Pakuranga ",
    "sg:city":"Auckland",
    "sg:classifiers":[
        {
            "category":"Bars & Pubs",
            "subcategory":"Wine Bar",
            "type":"Food & Drink"
        }
    ],
    "sg:phone":"+64 9-537 2174",
    "sg:province":"Auckland",
    "sg:tags":[
        "wining",
        "dining",
        "cafe"
    ],
    "wof:name":"Lily Cafe",
    "wof:placetype":"venue"
},
  "geometry": {"coordinates":[174.901474,-36.898212],"type":"Point"}
}