{
  "type": "Feature",
  "properties": {
    "iso:country":"NZ",
    "sg:address":"PO Box 46 038 Herne Bay ",
    "sg:city":"Auckland",
    "sg:classifiers":[
        {
            "category":"Retail",
            "subcategory":"Funeral Services",
            "type":"Services"
        }
    ],
    "sg:phone":"+64 9-827 2223",
    "sg:province":"Auckland",
    "sg:tags":[
        "arrangements",
        "arrangement"
    ],
    "wof:name":"Brown Fletcher Funeral Directors",
    "wof:placetype":"venue"
},
  "geometry": {"coordinates":[174.77041600000001,-36.884109],"type":"Point"}
}