{
  "type": "Feature",
  "properties": {
    "iso:country":"NZ",
    "sg:address":"3 Acorn St Royal Oak ",
    "sg:city":"Auckland",
    "sg:orig_category":"Automotive: Parts And Supplies: Windscreens",
    "sg:phone":"+64 9-307 8000",
    "sg:province":"Auckland",
    "wof:name":"Auckland Windscreen Services Ltd",
    "wof:placetype":"venue"
},
  "geometry": {"coordinates":[174.77267499999999,-36.910191],"type":"Point"}
}