{
  "type": "Feature",
  "properties": {
    "addr:full":"209 Moore St Howick  Auckland Auckland",
    "addr:housenumber":"209",
    "addr:street":"Moore St",
    "iso:country":"NZ",
    "sg:address":"209 Moore St Howick ",
    "sg:city":"Auckland",
    "sg:classifiers":[
        {
            "category":"Home & Garden",
            "subcategory":"Hardware",
            "type":"Retail Goods"
        }
    ],
    "sg:phone":"+64 9-535 4231",
    "sg:province":"Auckland",
    "sg:tags":[
        "equipment",
        "outdoor",
        "gardening",
        "products",
        "power"
    ],
    "wof:name":"Grasslands",
    "wof:placetype":"venue"
},
  "geometry": {"coordinates":[174.92659,-36.903683],"type":"Point"}
}