{
  "type": "Feature",
  "properties": {
    "addr:full":"249 Papanui Rd  Christchurch Canterbury",
    "addr:housenumber":"249",
    "addr:street":"Papanui Rd",
    "iso:country":"NZ",
    "sg:address":"249 Papanui Rd ",
    "sg:city":"Christchurch",
    "sg:orig_category":"Health And Beauty: Medical: Hospitals",
    "sg:phone":"+64 3-355 9179",
    "sg:province":"Canterbury",
    "wof:name":"St George's Hospital Inc",
    "wof:placetype":"venue"
},
  "geometry": {"coordinates":[172.61964399999999,-43.510021],"type":"Point"}
}