{
  "type": "Feature",
  "properties": {
    "addr:full":"31 Johnsonville Rd Johnsonville  Wellington Wellington",
    "addr:housenumber":"31",
    "addr:street":"Johnsonville Rd",
    "iso:country":"NZ",
    "sg:address":"31 Johnsonville Rd Johnsonville ",
    "sg:city":"Wellington",
    "sg:orig_category":"Sports And Leisure: Sports: Equestrian",
    "sg:phone":"+64 4-478 3709",
    "sg:province":"Wellington",
    "wof:name":"AnimalZ Ltd",
    "wof:placetype":"venue"
},
  "geometry": {"coordinates":[174.80746500000001,-41.223156],"type":"Point"}
}