{
  "type": "Feature",
  "properties": {
    "iso:country":"NZ",
    "sg:address":"1663 Main Rd South Wakefield ",
    "sg:city":"Nelson",
    "sg:orig_category":"Shopping: Retail Stores: Antiques",
    "sg:phone":"+64 3-541 8595",
    "sg:province":"Nelson",
    "wof:name":"Ivy Antiques",
    "wof:placetype":"venue"
},
  "geometry": {"coordinates":[-85.30452,37.968311],"type":"Point"}
}