{
  "type": "Feature",
  "properties": {
    "addr:full":"66 North St  Timaru Canterbury",
    "addr:housenumber":"66",
    "addr:street":"North St",
    "iso:country":"NZ",
    "sg:address":"66 North St ",
    "sg:city":"Timaru",
    "sg:orig_category":"Home And Garden",
    "sg:phone":"+64 3-684 8249",
    "sg:province":"Canterbury",
    "sg:website":"http://www.yellowpages.co.nz/pages/211481984/dp48427.html",
    "wof:name":"Warmup Heating Systems Ltd",
    "wof:placetype":"venue"
},
  "geometry": {"coordinates":[171.249222,-44.400677],"type":"Point"}
}