{
  "type": "Feature",
  "properties": {
    "addr:full":"138 Chadwick Rd Greerton  Tauranga Bay of Plenty",
    "addr:housenumber":"138",
    "addr:street":"Chadwick Rd",
    "iso:country":"NZ",
    "sg:address":"138 Chadwick Rd Greerton ",
    "sg:city":"Tauranga",
    "sg:classifiers":[
        {
            "category":"Bars & Pubs",
            "subcategory":"Wine Bar",
            "type":"Food & Drink"
        }
    ],
    "sg:phone":"+64 7-578 7682",
    "sg:province":"Bay of Plenty",
    "sg:tags":[
        "wining",
        "dining",
        "cafe"
    ],
    "wof:name":"Lemon Tree Cafe",
    "wof:placetype":"venue"
},
  "geometry": {"coordinates":[176.135345,-37.727764],"type":"Point"}
}