{
  "type": "Feature",
  "properties": {
    "addr:full":"40 Yorke Rd Haruru Falls R D 1  Paihia Northland",
    "addr:housenumber":"40;1",
    "addr:street":"Yorke Rd;R D;Northland",
    "iso:country":"NZ",
    "sg:address":"40 Yorke Rd Haruru Falls R D 1 ",
    "sg:city":"Paihia",
    "sg:classifiers":[
        {
            "category":"Social Services",
            "subcategory":"Child Care",
            "type":"Services"
        }
    ],
    "sg:phone":"+64 9-402 7324",
    "sg:province":"Northland",
    "sg:tags":[
        "home",
        "garden",
        "children"
    ],
    "wof:name":"Kiwicare Pre School",
    "wof:placetype":"venue"
},
  "geometry": {"coordinates":[174.09106399999999,-35.283699],"type":"Point"}
}