{
  "type": "Feature",
  "properties": {
    "iso:country":"NZ",
    "sg:address":"230 A Bush Rd Albany ",
    "sg:city":"Auckland",
    "sg:classifiers":[
        {
            "category":"Insurance",
            "subcategory":"Health Insurance",
            "type":"Services"
        }
    ],
    "sg:phone":"+64 9-415 6757",
    "sg:province":"Auckland",
    "sg:tags":[
        "beauty",
        "supply"
    ],
    "wof:name":"Dermal International NZ",
    "wof:placetype":"venue"
},
  "geometry": {"coordinates":[174.704697,-36.754417],"type":"Point"}
}