{
  "type": "Feature",
  "properties": {
    "addr:full":"230 A Bush Rd Albany  Auckland Auckland",
    "addr:housenumber":"230 a",
    "addr:street":"Bush Rd",
    "iso:country":"NZ",
    "sg:address":"230 A Bush Rd Albany ",
    "sg:city":"Auckland",
    "sg:classifiers":[
        {
            "category":"Insurance",
            "subcategory":"Health Insurance",
            "type":"Services"
        }
    ],
    "sg:phone":"+64 9-415 6757",
    "sg:province":"Auckland",
    "sg:tags":[
        "beauty",
        "supply"
    ],
    "wof:name":"Dermal International NZ",
    "wof:placetype":"venue"
},
  "geometry": {"coordinates":[174.70469700000001,-36.754417],"type":"Point"}
}