{
  "type": "Feature",
  "properties": {
    "iso:country":"NZ",
    "sg:address":"169 Mackenzies Rd ",
    "sg:city":"Waipara",
    "sg:classifiers":[
        {
            "category":"Food & Beverages",
            "subcategory":"Liquor & Beverages",
            "type":"Retail Goods"
        }
    ],
    "sg:phone":"+64 25310272",
    "sg:tags":[
        "drink",
        "maker",
        "wine"
    ],
    "wof:name":"Glenmark Wines",
    "wof:placetype":"venue"
},
  "geometry": {"coordinates":[172.75869800000001,-43.054855],"type":"Point"}
}