{
  "type": "Feature",
  "properties": {
    "iso:country":"NZ",
    "sg:address":"23 Cumnor Tce Woolston ",
    "sg:city":"Christchurch",
    "sg:orig_category":"Shopping: Gifts",
    "sg:phone":"+64 3-389 1038",
    "sg:province":"Canterbury",
    "sg:website":"http://www.nzsheepskin.com",
    "wof:name":"New Zealand Natural Classics Limited",
    "wof:placetype":"venue"
},
  "geometry": {"coordinates":[172.67804,-43.549911],"type":"Point"}
}