{
  "type": "Feature",
  "properties": {
    "iso:country":"NZ",
    "sg:address":"Hillary Sq Orewa Hibiscus ",
    "sg:city":"Hibiscus Coast",
    "sg:classifiers":[
        {
            "category":"Deli",
            "type":"Food & Drink"
        }
    ],
    "sg:phone":"+64 9-427 8477",
    "sg:province":"Auckland",
    "sg:tags":[
        "delicatessen",
        "-"
    ],
    "wof:name":"Windmill The No 1 Dutch Shop",
    "wof:placetype":"venue"
},
  "geometry": {"coordinates":[174.69012451169999,-36.5827407837],"type":"Point"}
}