{
  "type": "Feature",
  "properties": {
    "addr:full":"Main Rd Tokomaru  Bay",
    "addr:street":"Main Rd",
    "iso:country":"NZ",
    "sg:address":"Main Rd Tokomaru ",
    "sg:city":"Bay",
    "sg:classifiers":[
        {
            "category":"Fast Food",
            "type":"Food & Drink"
        }
    ],
    "sg:phone":"+64 6-864 5863",
    "sg:tags":[
        "wining",
        "dining",
        "takeaway"
    ],
    "wof:name":"Tokomaru Bay Fish N Chips",
    "wof:placetype":"venue"
},
  "geometry": {"coordinates":[178.31478899999999,-38.126328],"type":"Point"}
}