{
  "type": "Feature",
  "properties": {
    "addr:full":"197 Gt S Rd Takanini  Auckland Auckland",
    "addr:housenumber":"197",
    "addr:street":"Gt S Rd",
    "iso:country":"NZ",
    "sg:address":"197 Gt S Rd Takanini ",
    "sg:city":"Auckland",
    "sg:classifiers":[
        {
            "category":"Home & Garden",
            "subcategory":"Hardware",
            "type":"Retail Goods"
        }
    ],
    "sg:phone":"+64 9-296 3237",
    "sg:province":"Auckland",
    "sg:tags":[
        "window",
        "fitting"
    ],
    "wof:name":"Onsite Blind Cleaning",
    "wof:placetype":"venue"
},
  "geometry": {"coordinates":[174.923553,-37.042],"type":"Point"}
}