{
  "type": "Feature",
  "properties": {
    "iso:country":"NZ",
    "sg:address":"Amohau St ",
    "sg:city":"Rotorua",
    "sg:orig_category":"Shopping: Retail Stores: Department Stores",
    "sg:phone":"+64 7-346 3710",
    "sg:province":"Bay of Plenty",
    "wof:name":"The Warehouse Ltd",
    "wof:placetype":"venue"
},
  "geometry": {"coordinates":[176.258057,-38.139858],"type":"Point"}
}