{
  "type": "Feature",
  "properties": {
    "iso:country":"NZ",
    "sg:address":"2/7 Glover St Ngauranga ",
    "sg:city":"Wellington",
    "sg:orig_category":"Industrial: Products: Rope And Twine",
    "sg:phone":"+64 4-499 2058",
    "sg:province":"Wellington",
    "wof:name":"Legend Nautilus (NZ) Ltd",
    "wof:placetype":"venue"
},
  "geometry": {"coordinates":[174.813156,-41.240761],"type":"Point"}
}