{
  "type": "Feature",
  "properties": {
    "iso:country":"NZ",
    "sg:address":"3046 Gt North Rd New Lynn ",
    "sg:city":"Auckland",
    "sg:classifiers":[
        {
            "category":"Shopping",
            "subcategory":"Gifts & Souvenirs",
            "type":"Retail Goods"
        }
    ],
    "sg:phone":"+64 9-827 1644",
    "sg:province":"Auckland",
    "sg:tags":[
        "travel",
        "tourism"
    ],
    "wof:name":"Over The Top NZ Limited",
    "wof:placetype":"venue"
},
  "geometry": {"coordinates":[174.68641700000001,-36.90546],"type":"Point"}
}