{
  "type": "Feature",
  "properties": {
    "addr:full":"5B/64 Henderson Valley Rd Henderson  Auckland Auckland",
    "addr:housenumber":"5b / 64",
    "addr:street":"Henderson Valley Rd",
    "iso:country":"NZ",
    "sg:address":"5B/64 Henderson Valley Rd Henderson ",
    "sg:city":"Auckland",
    "sg:classifiers":[
        {
            "category":"Professional",
            "type":"Services"
        }
    ],
    "sg:phone":"+64 9-838 8280",
    "sg:province":"Auckland",
    "sg:tags":[
        "services",
        "car",
        "valet",
        "automotive"
    ],
    "wof:name":"West City Valet Limited",
    "wof:placetype":"venue"
},
  "geometry": {"coordinates":[174.627792,-36.888355],"type":"Point"}
}