{
  "type": "Feature",
  "properties": {
    "addr:full":"224 Neilson St Onehunga  Auckland Auckland",
    "addr:housenumber":"224",
    "addr:street":"Neilson St",
    "iso:country":"NZ",
    "sg:address":"224 Neilson St Onehunga ",
    "sg:city":"Auckland",
    "sg:orig_category":"Industrial: Parts: Pipes, Tubes And Cabling: Pipes",
    "sg:phone":"+64 9-622 4580",
    "sg:province":"Auckland",
    "wof:name":"Steelpipe New Zealand Ltd",
    "wof:placetype":"venue"
},
  "geometry": {"coordinates":[174.79257200000001,-36.9263],"type":"Point"}
}