{
  "type": "Feature",
  "properties": {
    "addr:full":"State Insurance Building 96 Bank St  Whangarei Northland",
    "addr:housenumber":"96",
    "addr:street":"Bank St",
    "iso:country":"NZ",
    "sg:address":"State Insurance Building 96 Bank St ",
    "sg:city":"Whangarei",
    "sg:classifiers":[
        {
            "category":"Banks & Credit Unions",
            "subcategory":"Financial Services",
            "type":"Services"
        }
    ],
    "sg:phone":"+64 9-430 4350",
    "sg:province":"Northland",
    "sg:tags":[
        "personal",
        "loan",
        "-",
        "finance",
        "mortgage"
    ],
    "sg:website":"http://www.hendersonreeveslawyers.co.nz",
    "wof:name":"Henderson Reeves Connell Rishworth",
    "wof:placetype":"venue"
},
  "geometry": {"coordinates":[174.320526,-35.725399],"type":"Point"}
}