{
  "type": "Feature",
  "properties": {
    "iso:country":"NZ",
    "sg:address":"41 Halswell Junction Rd Halswell ",
    "sg:city":"Christchurch",
    "sg:classifiers":[
        {
            "category":"Coffee & Tea",
            "type":"Food & Drink"
        }
    ],
    "sg:phone":"+64 3-322 7311",
    "sg:province":"Canterbury",
    "sg:tags":[
        "merchant"
    ],
    "wof:name":"Peter J Duncan Electrical",
    "wof:placetype":"venue"
},
  "geometry": {"coordinates":[172.567093,-43.583885],"type":"Point"}
}