{
  "type": "Feature",
  "properties": {
    "addr:full":"Main Highway North Paraparaumu  Paraparaumu Auckland",
    "addr:street":"Main Highway North",
    "iso:country":"NZ",
    "sg:address":"Main Highway North Paraparaumu ",
    "sg:city":"Paraparaumu",
    "sg:classifiers":[
        {
            "category":"Education",
            "subcategory":"University",
            "type":"Public Place"
        }
    ],
    "sg:phone":"+64 4-298 0205",
    "sg:province":"Auckland",
    "sg:tags":[
        "training",
        "college"
    ],
    "wof:name":"Whitireia Community Polytechnic",
    "wof:placetype":"venue"
},
  "geometry": {"coordinates":[175.00799599999999,-40.910461],"type":"Point"}
}