{
  "type": "Feature",
  "properties": {
    "addr:full":"41 Matipo St Upper  Riccarton Canterbury",
    "addr:housenumber":"41",
    "addr:street":"Matipo St",
    "iso:country":"NZ",
    "sg:address":"41 Matipo St Upper ",
    "sg:city":"Riccarton",
    "sg:classifiers":[
        {
            "category":"Professional",
            "subcategory":"Art Services",
            "type":"Services"
        }
    ],
    "sg:phone":"+64 21 361 702",
    "sg:province":"Canterbury",
    "sg:tags":[
        "picture",
        "arts",
        "sport",
        "framing",
        "leisure"
    ],
    "wof:name":"Matipo Picture Framing",
    "wof:placetype":"venue"
},
  "geometry": {"coordinates":[172.59617600000001,-43.53606],"type":"Point"}
}