{
  "type": "Feature",
  "properties": {
    "addr:full":"10/20 Marshlands Rd Shirley  Christchurch Canterbury",
    "addr:housenumber":"10 / 20",
    "addr:street":"Marshlands Rd",
    "iso:country":"NZ",
    "sg:address":"10/20 Marshlands Rd Shirley ",
    "sg:city":"Christchurch",
    "sg:orig_category":"Shopping: Retail Stores: Cds, Cassettes And Records",
    "sg:phone":"+64 3-385 0660",
    "sg:province":"Canterbury",
    "wof:name":"The C D Store Ltd",
    "wof:placetype":"venue"
},
  "geometry": {"coordinates":[172.66291799999999,-43.506496],"type":"Point"}
}