{
  "type": "Feature",
  "properties": {
    "iso:country":"NZ",
    "sg:address":"52 Newton St Mt Maunganui ",
    "sg:city":"Tauranga",
    "sg:classifiers":[
        {
            "category":"Recreation",
            "type":"Entertainment"
        }
    ],
    "sg:phone":"+64 7-579 0190",
    "sg:province":"Auckland",
    "sg:tags":[
        "sport",
        "leisure"
    ],
    "sg:website":"http://www.yellowpages.co.nz/for/baytexmanufacturing/dp47303.html",
    "wof:name":"Baytex Manufacturing Company Limited",
    "wof:placetype":"venue"
},
  "geometry": {"coordinates":[176.208359,-37.65926],"type":"Point"}
}