{
  "type": "Feature",
  "properties": {
    "iso:country":"NZ",
    "sg:address":"2/20 Hamilton Rd Herne Bay ",
    "sg:city":"Auckland",
    "sg:orig_category":"Health And Beauty: Specialists: Osteopaths",
    "sg:phone":"+64 9-489 6038",
    "sg:province":"Auckland",
    "wof:name":"Osteopathic Centre",
    "wof:placetype":"venue"
},
  "geometry": {"coordinates":[174.737579,-36.843842],"type":"Point"}
}