{
  "type": "Feature",
  "properties": {
    "addr:full":"Falvey Rd Timaru PO Box 89 Geraldine  Timaru Canterbury",
    "addr:housenumber":"po box 89",
    "addr:street":"Falvey Rd;Geraldine Timaru",
    "iso:country":"NZ",
    "sg:address":"Falvey Rd Timaru PO Box 89 Geraldine ",
    "sg:city":"Timaru",
    "sg:classifiers":[
        {
            "category":"Airport",
            "type":"Transportation"
        }
    ],
    "sg:phone":"+64 3-688 2189",
    "sg:province":"Canterbury",
    "sg:tags":[
        "aircraft",
        "transport",
        "sale",
        "maintenance",
        "air"
    ],
    "wof:name":"Aviation Teknology Ltd",
    "wof:placetype":"venue"
},
  "geometry": {"coordinates":[171.23741100000001,-44.395428],"type":"Point"}
}