{
  "type": "Feature",
  "properties": {
    "addr:full":"15 Papawai Pl  Masterton Wellington",
    "addr:housenumber":"15",
    "addr:street":"Papawai Pl",
    "iso:country":"NZ",
    "sg:address":"15 Papawai Pl ",
    "sg:city":"Masterton",
    "sg:orig_category":"Automotive: Parts And Supplies: Automotive Dismantlers",
    "sg:phone":"+64 6-377 7478",
    "sg:province":"Wellington",
    "wof:name":"Auto Parts Direct",
    "wof:placetype":"venue"
},
  "geometry": {"coordinates":[175.65733299999999,-40.94931],"type":"Point"}
}