{
  "type": "Feature",
  "properties": {
    "addr:full":"Mt  Albert",
    "iso:country":"NZ",
    "sg:address":"Mt ",
    "sg:city":"Albert",
    "sg:classifiers":[
        {
            "category":"Shopping",
            "subcategory":"Computers & Home Electronics",
            "type":"Retail Goods"
        }
    ],
    "sg:phone":"+64 25325715",
    "sg:tags":[
        "equipment",
        "sport",
        "leisure",
        "entertainment"
    ],
    "wof:name":"Show FX",
    "wof:placetype":"venue"
},
  "geometry": {"coordinates":[174.714798,-36.88784],"type":"Point"}
}