{
  "type": "Feature",
  "properties": {
    "addr:full":"2 Vermont St Ponsonby  Auckland Auckland",
    "addr:housenumber":"2",
    "addr:street":"Vermont St",
    "iso:country":"NZ",
    "sg:address":"2 Vermont St Ponsonby ",
    "sg:city":"Auckland",
    "sg:classifiers":[
        {
            "category":"Education",
            "subcategory":"University",
            "type":"Public Place"
        }
    ],
    "sg:phone":"+64 9-361 3800",
    "sg:province":"Auckland",
    "sg:tags":[
        "training",
        "adult"
    ],
    "wof:name":"Workbase The National Centre for Workplace Literacy & Language",
    "wof:placetype":"venue"
},
  "geometry": {"coordinates":[174.739822,-36.853363],"type":"Point"}
}