{
  "type": "Feature",
  "properties": {
    "addr:full":"87 Niven St Onekawa  Napier Hawke's Bay",
    "addr:housenumber":"87",
    "addr:street":"Niven St",
    "iso:country":"NZ",
    "sg:address":"87 Niven St Onekawa ",
    "sg:city":"Napier",
    "sg:classifiers":[
        {
            "category":"Food & Beverages",
            "subcategory":"Groceries & Convenience Stores",
            "type":"Retail Goods"
        }
    ],
    "sg:phone":"+64 6-843 2305",
    "sg:province":"Hawke's Bay",
    "sg:tags":[
        "foodstuff",
        "drink",
        "-"
    ],
    "wof:name":"Mr Chips Local Distributor",
    "wof:placetype":"venue"
},
  "geometry": {"coordinates":[176.875427,-39.501884],"type":"Point"}
}