{
  "type": "Feature",
  "properties": {
    "iso:country":"NZ",
    "sg:address":"Dressmart Shopping Centre, Cnr Main South & Shands, Rds Hornby ",
    "sg:city":"Christchurch",
    "sg:orig_category":"Shopping: Retail Stores: Cds, Cassettes And Records",
    "sg:phone":"+64 3-349 7020",
    "sg:province":"Canterbury",
    "wof:name":"planetjack.com",
    "wof:placetype":"venue"
},
  "geometry": {"coordinates":[172.525665,-43.543461],"type":"Point"}
}