{
  "type": "Feature",
  "properties": {
    "addr:full":"93 Tongariro St  Taupo Waikato",
    "addr:housenumber":"93",
    "addr:street":"Tongariro St",
    "iso:country":"NZ",
    "sg:address":"93 Tongariro St ",
    "sg:city":"Taupo",
    "sg:orig_category":"Automotive: General Services: Automobile Associations",
    "sg:phone":"+64 7-378 6000",
    "sg:province":"Waikato",
    "wof:name":"A A Automobile Association",
    "wof:placetype":"venue"
},
  "geometry": {"coordinates":[176.069748,-38.68071],"type":"Point"}
}