{
  "type": "Feature",
  "properties": {
    "addr:full":"14 Linmor Pl Palmerston  Palmerston North Manawatu-Wanganui",
    "addr:housenumber":"14",
    "addr:street":"Linmor Pl",
    "iso:country":"NZ",
    "sg:address":"14 Linmor Pl Palmerston ",
    "sg:city":"Palmerston North",
    "sg:orig_category":"Transport: Transportation: Refrigerated Transport",
    "sg:phone":"+64 6-353 3035",
    "sg:province":"Manawatu-Wanganui",
    "wof:name":"Gary's Cool Transport",
    "wof:placetype":"venue"
},
  "geometry": {"coordinates":[175.63644400000001,-40.356056],"type":"Point"}
}