{
  "type": "Feature",
  "properties": {
    "addr:full":"657 Great South Rd Penrose  Auckland Auckland",
    "addr:housenumber":"657",
    "addr:street":"Great South Rd",
    "iso:country":"NZ",
    "sg:address":"657 Great South Rd Penrose ",
    "sg:city":"Auckland",
    "sg:orig_category":"Industrial: Equipment And Machinery: Compressors",
    "sg:phone":"+64 9-579 3605",
    "sg:province":"Auckland",
    "wof:name":"Kaeser Compressors",
    "wof:placetype":"venue"
},
  "geometry": {"coordinates":[174.82225,-36.915718],"type":"Point"}
}