{
  "type": "Feature",
  "properties": {
    "addr:full":"32 Arthur St  Timaru Canterbury",
    "addr:housenumber":"32",
    "addr:street":"Arthur St",
    "iso:country":"NZ",
    "sg:address":"32 Arthur St ",
    "sg:city":"Timaru",
    "sg:classifiers":[
        {
            "category":"Banks & Credit Unions",
            "subcategory":"Investment Brokerage",
            "type":"Services"
        }
    ],
    "sg:phone":"+64 3-684 8240",
    "sg:province":"Canterbury",
    "sg:tags":[
        "educational",
        "education",
        "training"
    ],
    "sg:website":"http://www.aoraki.ac.nz",
    "wof:name":"Aoraki Polytechnic",
    "wof:placetype":"venue"
},
  "geometry": {"coordinates":[171.24691799999999,-44.398651],"type":"Point"}
}