{
  "type": "Feature",
  "properties": {
    "addr:full":"58 Hudson St  Hamilton Waikato",
    "addr:housenumber":"58",
    "addr:street":"Hudson St",
    "iso:country":"NZ",
    "sg:address":"58 Hudson St ",
    "sg:city":"Hamilton",
    "sg:orig_category":"Industrial: Engineering: Engineers - Automation",
    "sg:phone":"+64 7-843 8859",
    "sg:province":"Waikato",
    "wof:name":"Marshall Electrical & Automation Ltd",
    "wof:placetype":"venue"
},
  "geometry": {"coordinates":[-74.752274,40.21571],"type":"Point"}
}