{
  "type": "Feature",
  "properties": {
    "iso:country":"NZ",
    "sg:address":"46 Brentwood St Trentham Upper ",
    "sg:city":"Hutt",
    "sg:classifiers":[
        {
            "category":"Organizations",
            "subcategory":"Religious Organization",
            "type":"Services"
        }
    ],
    "sg:phone":"+64 4-528 6585",
    "sg:province":"Wellington",
    "sg:tags":[
        "arrangements",
        "tent",
        "marquee",
        "wedding"
    ],
    "wof:name":"Tarpaulin Hire",
    "wof:placetype":"venue"
},
  "geometry": {"coordinates":[175.03381300000001,-41.131985],"type":"Point"}
}