{
  "type": "Feature",
  "properties": {
    "addr:full":"516 Gt South Rd Greenlane  Auckland Auckland",
    "addr:housenumber":"516",
    "addr:street":"Gt South Rd",
    "iso:country":"NZ",
    "sg:address":"516 Gt South Rd Greenlane ",
    "sg:city":"Auckland",
    "sg:classifiers":[
        {
            "category":"Shopping",
            "subcategory":"Pharmacy",
            "type":"Retail Goods"
        }
    ],
    "sg:phone":"+64 9-524 4785",
    "sg:province":"Auckland",
    "sg:tags":[
        "product",
        "health"
    ],
    "wof:name":"Fitness World Ltd",
    "wof:placetype":"venue"
},
  "geometry": {"coordinates":[174.79808,-36.89333],"type":"Point"}
}