{
  "type": "Feature",
  "properties": {
    "addr:full":"34 Perry St  Masterton Wellington",
    "addr:housenumber":"34",
    "addr:street":"Perry St",
    "iso:country":"NZ",
    "sg:address":"34 Perry St ",
    "sg:city":"Masterton",
    "sg:classifiers":[
        {
            "category":"Banks & Credit Unions",
            "subcategory":"Financial Services",
            "type":"Services"
        }
    ],
    "sg:phone":"+64 6-370 1649",
    "sg:province":"Wellington",
    "sg:tags":[
        "personal",
        "loan",
        "-",
        "finance",
        "mortgage"
    ],
    "wof:name":"Mortgage Link (WAI) Ltd",
    "wof:placetype":"venue"
},
  "geometry": {"coordinates":[175.658997,-40.948711],"type":"Point"}
}