{
  "type": "Feature",
  "properties": {
    "iso:country":"NZ",
    "sg:address":"4 Dell Way ",
    "sg:city":"Judea",
    "sg:classifiers":[
        {
            "category":"Home & Garden",
            "subcategory":"Home Furnishings",
            "type":"Retail Goods"
        }
    ],
    "sg:phone":"+64 252272630",
    "sg:province":"Bay of Plenty",
    "sg:tags":[
        "furniture/furnishings",
        "upholstery",
        "supply"
    ],
    "wof:name":"Jim's Upholstery Services",
    "wof:placetype":"venue"
},
  "geometry": {"coordinates":[176.14608799999999,-37.694363],"type":"Point"}
}