{
  "type": "Feature",
  "properties": {
    "iso:country":"NZ",
    "sg:address":"PO Box 52 ",
    "sg:city":"Hamilton",
    "sg:orig_category":"Farming: Agriculture: Agricultural Consultants",
    "sg:phone":"+64 7-834 0732",
    "sg:province":"Waikato",
    "wof:name":"Agricultural Consulting Services",
    "wof:placetype":"venue"
},
  "geometry": {"coordinates":[-94.04692799999999,39.77124],"type":"Point"}
}