{
  "type": "Feature",
  "properties": {
    "iso:country":"NZ",
    "sg:address":"1 Botanical Rd Palmerston ",
    "sg:city":"Palmerston North",
    "sg:orig_category":"Industrial: Electrical/Electronic: Electronic Equipment",
    "sg:phone":"+64 6-353 6651",
    "sg:province":"Manawatu-Wanganui",
    "wof:name":"Industrial Software and Automation Ltd",
    "wof:placetype":"venue"
},
  "geometry": {"coordinates":[175.585068,-40.351006],"type":"Point"}
}