{
  "type": "Feature",
  "properties": {
    "iso:country":"NZ",
    "sg:address":"Level 5 345 Queen St Auckland Central ",
    "sg:city":"Auckland",
    "sg:classifiers":[
        {
            "category":"Banks & Credit Unions",
            "subcategory":"Investment Brokerage",
            "type":"Services"
        }
    ],
    "sg:province":"Auckland",
    "sg:tags":[
        "personal",
        "accountant",
        "chartered",
        "-",
        "finance"
    ],
    "wof:name":"Smith Nigel & Associates Ltd",
    "wof:placetype":"venue"
},
  "geometry": {"coordinates":[174.762711,-36.854588],"type":"Point"}
}