{
  "type": "Feature",
  "properties": {
    "addr:full":"42 E Valley Rd  Whakatane Bay of Plenty",
    "addr:housenumber":"42",
    "addr:street":"E Valley Rd",
    "iso:country":"NZ",
    "sg:address":"42 E Valley Rd ",
    "sg:city":"Whakatane",
    "sg:orig_category":"Industrial: Engineering: Engineers - Manufacturing",
    "sg:phone":"+64 7-307 8108",
    "sg:province":"Bay of Plenty",
    "wof:name":"C.A.T.S Engineering",
    "wof:placetype":"venue"
},
  "geometry": {"coordinates":[176.99174500000001,-37.966557],"type":"Point"}
}