{
  "type": "Feature",
  "properties": {
    "addr:full":"East Takaka Rd  Takaka",
    "addr:street":"East Takaka Rd",
    "iso:country":"NZ",
    "sg:address":"East Takaka Rd ",
    "sg:city":"Takaka",
    "sg:classifiers":[
        {
            "category":"Landmark",
            "subcategory":"Tourist Information",
            "type":"Public Place"
        }
    ],
    "sg:phone":"+64 800 173 371",
    "sg:tags":[
        "travel",
        "tourism",
        "tour",
        "sightseeing"
    ],
    "sg:website":"http://www.kahurangi.co.nz",
    "wof:name":"Kahurangi National Park Bus Services",
    "wof:placetype":"venue"
},
  "geometry": {"coordinates":[172.82560699999999,-40.967445],"type":"Point"}
}