{
  "type": "Feature",
  "properties": {
    "addr:full":"1/5 Cunard Rd New Lynn  Auckland Auckland",
    "addr:housenumber":"1 / 5",
    "addr:street":"Cunard Rd",
    "iso:country":"NZ",
    "sg:address":"1/5 Cunard Rd New Lynn ",
    "sg:city":"Auckland",
    "sg:classifiers":[
        {
            "category":"Shopping",
            "subcategory":"Gifts & Souvenirs",
            "type":"Retail Goods"
        }
    ],
    "sg:phone":"+64 9-827 6746",
    "sg:province":"Auckland",
    "sg:tags":[
        "postcard",
        "gifts",
        "greeting",
        "card"
    ],
    "wof:name":"Mouth & Foot Painting Artists",
    "wof:placetype":"venue"
},
  "geometry": {"coordinates":[174.683426,-36.901375],"type":"Point"}
}