{
  "type": "Feature",
  "properties": {
    "addr:full":"76 Waldegrave St Palmerston  Palmerston North Manawatu-Wanganui",
    "addr:housenumber":"76",
    "addr:street":"Waldegrave St Palmerston",
    "iso:country":"NZ",
    "sg:address":"76 Waldegrave St Palmerston ",
    "sg:city":"Palmerston North",
    "sg:classifiers":[
        {
            "category":"Sports & Exercise",
            "subcategory":"Tennis Court",
            "type":"Entertainment"
        }
    ],
    "sg:phone":"+64 6-358 8699",
    "sg:province":"Manawatu-Wanganui",
    "sg:tags":[
        "hire",
        "-",
        "leisure"
    ],
    "wof:name":"Manawatu Theatre Costume Hire",
    "wof:placetype":"venue"
},
  "geometry": {"coordinates":[175.60333299999999,-40.356335],"type":"Point"}
}