{
  "type": "Feature",
  "properties": {
    "iso:country":"NZ",
    "sg:address":"180 Monarch Downs Way ",
    "sg:city":"Warkworth",
    "sg:classifiers":[
        {
            "category":"Retail",
            "subcategory":"Driving School",
            "type":"Services"
        }
    ],
    "sg:phone":"+64 9-422 7211",
    "sg:province":"Auckland",
    "sg:tags":[
        "health",
        "beauty"
    ],
    "wof:name":"Alegria Beauty Farm",
    "wof:placetype":"venue"
},
  "geometry": {"coordinates":[174.685745,-36.382248],"type":"Point"}
}