{
  "type": "Feature",
  "properties": {
    "iso:country":"NZ",
    "sg:address":"PO Box 903 Auckland City ",
    "sg:city":"Auckland",
    "sg:classifiers":[
        {
            "category":"Landmark",
            "subcategory":"Tourist Information",
            "type":"Public Place"
        }
    ],
    "sg:phone":"+64 9-379 5535",
    "sg:province":"Auckland",
    "sg:tags":[
        "services",
        "travel",
        "tourism"
    ],
    "wof:name":"Tourism Tasmania",
    "wof:placetype":"venue"
},
  "geometry": {"coordinates":[174.7845,-37.006058],"type":"Point"}
}