{
  "type": "Feature",
  "properties": {
    "addr:full":"95 Grants Rd Papanui  Christchurch Canterbury",
    "addr:housenumber":"95",
    "addr:street":"Grants Rd",
    "iso:country":"NZ",
    "sg:address":"95 Grants Rd Papanui ",
    "sg:city":"Christchurch",
    "sg:orig_category":"Health And Beauty: Medical: Hospitals",
    "sg:phone":"+64 3-352 5140",
    "sg:province":"Canterbury",
    "wof:name":"Ngaio Marsh Retirement Village",
    "wof:placetype":"venue"
},
  "geometry": {"coordinates":[172.61497499999999,-43.497383],"type":"Point"}
}