{
  "type": "Feature",
  "properties": {
    "iso:country":"NZ",
    "sg:address":"121 Anderson Rd RD 2 Reece Block ",
    "sg:city":"Wanaka",
    "sg:orig_category":"Industrial: Manufacturing: Plaster Manufacturers",
    "sg:phone":"+64 252990379",
    "sg:province":"Otago",
    "wof:name":"Professional Stopping Ltd",
    "wof:placetype":"venue"
},
  "geometry": {"coordinates":[169.138443,-44.693981],"type":"Point"}
}