{
  "type": "Feature",
  "properties": {
    "iso:country":"NZ",
    "sg:address":"Henare Rd Motatau ",
    "sg:city":"Kawakawa",
    "sg:orig_category":"Education And Training: General: Schools",
    "sg:phone":"+64 9-404 0590",
    "wof:name":"Motatau Primary School",
    "wof:placetype":"venue"
},
  "geometry": {"coordinates":[174.035599,-35.49015],"type":"Point"}
}