{
  "type": "Feature",
  "properties": {
    "addr:full":"2 Hokianga Rd  Dargaville Northland",
    "addr:housenumber":"2",
    "addr:street":"Hokianga Rd",
    "iso:country":"NZ",
    "sg:address":"2 Hokianga Rd ",
    "sg:city":"Dargaville",
    "sg:classifiers":[
        {
            "category":"Retail",
            "subcategory":"Auto Repair",
            "type":"Services"
        }
    ],
    "sg:phone":"+64 9-439 3104",
    "sg:province":"Northland",
    "sg:tags":[
        "automotive",
        "electric",
        "servicing"
    ],
    "wof:name":"Dargaville Auto Electric",
    "wof:placetype":"venue"
},
  "geometry": {"coordinates":[173.86338799999999,-35.937065],"type":"Point"}
}