{
  "type": "Feature",
  "properties": {
    "iso:country":"NZ",
    "sg:address":"626 Lineside Rd ",
    "sg:city":"Rangiora",
    "sg:classifiers":[
        {
            "category":"Retail",
            "subcategory":"Auto Repair",
            "type":"Services"
        }
    ],
    "sg:phone":"+64 3-313 3344",
    "sg:province":"Canterbury",
    "sg:tags":[
        "muffler",
        "exhaust",
        "servicing",
        "automotive"
    ],
    "wof:name":"Kennetts Exhaust Specialists & Tyre Tech",
    "wof:placetype":"venue"
},
  "geometry": {"coordinates":[172.602417,-43.329014],"type":"Point"}
}