{
  "type": "Feature",
  "properties": {
    "iso:country":"NZ",
    "sg:address":"235 High St ",
    "sg:city":"Motueka",
    "sg:classifiers":[
        {
            "category":"Manufacturing",
            "subcategory":"Glass & Minerals",
            "type":"Manufacturing & Wholesale Goods"
        }
    ],
    "sg:phone":"+64 3-528 9220",
    "sg:province":"Tasman",
    "sg:tags":[
        "chemical",
        "fibre",
        "industrial",
        "compounds"
    ],
    "wof:name":"Wilkins & Field Ltd",
    "wof:placetype":"venue"
},
  "geometry": {"coordinates":[173.010269,-41.126648],"type":"Point"}
}