{
  "type": "Feature",
  "properties": {
    "addr:full":"274 West Coast Rd Glen Eden  Auckland Auckland",
    "addr:housenumber":"274",
    "addr:street":"West Coast Rd",
    "iso:country":"NZ",
    "sg:address":"274 West Coast Rd Glen Eden ",
    "sg:city":"Auckland",
    "sg:classifiers":[
        {
            "category":"Retail",
            "subcategory":"Laundry & Dry Cleaning",
            "type":"Services"
        }
    ],
    "sg:phone":"+64 9-818 8993",
    "sg:province":"Auckland",
    "sg:tags":[
        "repair",
        "clothing",
        "fabric",
        "cleaner"
    ],
    "wof:name":"Glen Eden Drycleaners",
    "wof:placetype":"venue"
},
  "geometry": {"coordinates":[174.65020799999999,-36.909901],"type":"Point"}
}