{
  "type": "Feature",
  "properties": {
    "addr:full":"285 Palmerston Rd  Gisborne Gisborne",
    "addr:housenumber":"285",
    "addr:street":"Palmerston Rd",
    "iso:country":"NZ",
    "sg:address":"285 Palmerston Rd ",
    "sg:city":"Gisborne",
    "sg:classifiers":[
        {
            "category":"Autos & Motor Vehicles",
            "subcategory":"Motorcycle Sales",
            "type":"Retail Goods"
        }
    ],
    "sg:phone":"+64 6-867 6638",
    "sg:province":"Gisborne",
    "sg:tags":[
        "automotive",
        "scooter",
        "leasing"
    ],
    "wof:name":"Yamaha",
    "wof:placetype":"venue"
},
  "geometry": {"coordinates":[178.02342200000001,-38.662193],"type":"Point"}
}