{
  "type": "Feature",
  "properties": {
    "iso:country":"NZ",
    "sg:address":"106 Commerce St ",
    "sg:city":"Kaitaia",
    "sg:classifiers":[
        {
            "category":"Bars & Pubs",
            "subcategory":"Lounge",
            "type":"Food & Drink"
        }
    ],
    "sg:phone":"+64 9-408 1350",
    "sg:province":"Northland",
    "sg:tags":[
        "baker",
        "-"
    ],
    "wof:name":"Coast to Coast Bakery Ltd",
    "wof:placetype":"venue"
},
  "geometry": {"coordinates":[173.262268,-35.112064],"type":"Point"}
}