{
  "type": "Feature",
  "properties": {
    "addr:full":"35 Newtown St Bromley  Christchurch Canterbury",
    "addr:housenumber":"35",
    "addr:street":"Newtown St;Christchurch",
    "iso:country":"NZ",
    "sg:address":"35 Newtown St Bromley ",
    "sg:city":"Christchurch",
    "sg:orig_category":"Industrial: Electrical/Electronic: Electric Motors",
    "sg:phone":"+64 3-384 8051",
    "sg:province":"Canterbury",
    "wof:name":"Russell Long Electrical Ltd",
    "wof:placetype":"venue"
},
  "geometry": {"coordinates":[172.69842499999999,-43.539974],"type":"Point"}
}