{
  "type": "Feature",
  "properties": {
    "addr:full":"120 Barrington St Somerfield  Christchurch Canterbury",
    "addr:housenumber":"120",
    "addr:street":"Barrington St",
    "iso:country":"NZ",
    "sg:address":"120 Barrington St Somerfield ",
    "sg:city":"Christchurch",
    "sg:classifiers":[
        {
            "category":"Sports & Exercise",
            "subcategory":"Swimming Pool",
            "type":"Entertainment"
        }
    ],
    "sg:phone":"+64 3-332 1934",
    "sg:province":"Canterbury",
    "sg:tags":[
        "home",
        "outdoor",
        "garden",
        "spa"
    ],
    "wof:name":"Discount Filtration",
    "wof:placetype":"venue"
},
  "geometry": {"coordinates":[172.628479,-43.55843],"type":"Point"}
}