{
  "type": "Feature",
  "properties": {
    "addr:full":"5 Parkwood Pl East Tamaki  Auckland Auckland",
    "addr:housenumber":"5",
    "addr:street":"Parkwood Pl",
    "iso:country":"NZ",
    "sg:address":"5 Parkwood Pl East Tamaki ",
    "sg:city":"Auckland",
    "sg:orig_category":"Transport: Transportation: Carriers",
    "sg:phone":"+64 9-274 8333",
    "sg:province":"Auckland",
    "wof:name":"Galaxy Transport",
    "wof:placetype":"venue"
},
  "geometry": {"coordinates":[174.90007,-36.933872],"type":"Point"}
}