{
  "type": "Feature",
  "properties": {
    "iso:country":"NZ",
    "sg:address":"10 Firth St Drury ",
    "sg:city":"Auckland",
    "sg:orig_category":"Farming: Horticulture: Horticultural Supplies",
    "sg:phone":"+64 9-294 8453",
    "sg:province":"Auckland",
    "wof:name":"Veg-Gro Supplies Ltd",
    "wof:placetype":"venue"
},
  "geometry": {"coordinates":[174.94813500000001,-37.105656],"type":"Point"}
}