{
  "type": "Feature",
  "properties": {
    "iso:country":"NZ",
    "sg:address":"28 Mersey St ",
    "sg:city":"Gore",
    "sg:classifiers":[
        {
            "category":"Banks & Credit Unions",
            "subcategory":"Investment Brokerage",
            "type":"Services"
        }
    ],
    "sg:phone":"+64 3-208 8221",
    "sg:province":"Southland",
    "sg:tags":[
        "educational",
        "education",
        "training"
    ],
    "wof:name":"REAP Southland Inc",
    "wof:placetype":"venue"
},
  "geometry": {"coordinates":[-95.116547,35.530331],"type":"Point"}
}