{
  "type": "Feature",
  "properties": {
    "addr:full":"36 Maleme St Greerton  Tauranga Bay of Plenty",
    "addr:housenumber":"36",
    "addr:street":"Maleme St",
    "iso:country":"NZ",
    "sg:address":"36 Maleme St Greerton ",
    "sg:city":"Tauranga",
    "sg:classifiers":[
        {
            "category":"Retail",
            "subcategory":"Driving School",
            "type":"Services"
        }
    ],
    "sg:phone":"+64 7-543 4567",
    "sg:province":"Bay of Plenty",
    "sg:tags":[
        "training",
        "education",
        "driver"
    ],
    "wof:name":"EMP Consultants Ltd",
    "wof:placetype":"venue"
},
  "geometry": {"coordinates":[176.1371,-37.736435],"type":"Point"}
}