{
  "type": "Feature",
  "properties": {
    "iso:country":"NZ",
    "sg:address":"Moroa Rd ",
    "sg:city":"Greytown",
    "sg:classifiers":[
        {
            "category":"Shopping",
            "subcategory":"Pets & Pet Supplies",
            "type":"Retail Goods"
        }
    ],
    "sg:phone":"+64 6-304 8017",
    "sg:tags":[
        "boarding",
        "garden",
        "pets",
        "catteries",
        "home",
        "kennel"
    ],
    "wof:name":"Greytown Dog Motels",
    "wof:placetype":"venue"
},
  "geometry": {"coordinates":[175.43779,-41.118851],"type":"Point"}
}