{
  "type": "Feature",
  "properties": {
    "addr:full":"143 Queen St Northcote  Auckland Auckland",
    "addr:housenumber":"143",
    "addr:street":"Queen St",
    "iso:country":"NZ",
    "sg:address":"143 Queen St Northcote ",
    "sg:city":"Auckland",
    "sg:classifiers":[
        {
            "category":"Deli",
            "type":"Food & Drink"
        }
    ],
    "sg:phone":"+64 9-480 2033",
    "sg:province":"Auckland",
    "sg:tags":[
        "delicatessen",
        "-"
    ],
    "wof:name":"Antipasti",
    "wof:placetype":"venue"
},
  "geometry": {"coordinates":[174.74556000000001,-36.815861],"type":"Point"}
}