{
  "type": "Feature",
  "properties": {
    "iso:country":"NZ",
    "sg:address":"252 Church St Onehunga ",
    "sg:city":"Auckland",
    "sg:classifiers":[
        {
            "category":"Manufacturing",
            "subcategory":"Metals",
            "type":"Manufacturing & Wholesale Goods"
        }
    ],
    "sg:phone":"+64 9-634 3116",
    "sg:province":"Auckland",
    "sg:tags":[
        "-",
        "engineering",
        "industrial",
        "sheet",
        "engineer"
    ],
    "sg:website":"http://www.yellowpages.co.nz/pages/200100981/dp33743.html",
    "wof:name":"Jensen Metal Products (NZ) Ltd",
    "wof:placetype":"venue"
},
  "geometry": {"coordinates":[174.79213,-36.922318],"type":"Point"}
}