{
  "type": "Feature",
  "properties": {
    "iso:country":"NZ",
    "sg:address":"704 Tomoana Rd ",
    "sg:city":"Hastings",
    "sg:classifiers":[
        {
            "category":"Social Services",
            "subcategory":"Retirement Home",
            "type":"Services"
        }
    ],
    "sg:phone":"+64 6-878 3870",
    "sg:province":"Hawke's Bay",
    "sg:tags":[
        "elderly",
        "convalescent",
        "garden",
        "rest",
        "care"
    ],
    "wof:name":"Cornwall Park Rest Home",
    "wof:placetype":"venue"
},
  "geometry": {"coordinates":[176.84613,-39.630825],"type":"Point"}
}