{
  "type": "Feature",
  "properties": {
    "iso:country":"NZ",
    "sg:address":"Cnr Union & Nelson Sts ",
    "sg:city":"Hawera",
    "sg:orig_category":"Shopping: Retail Stores: Supermarkets",
    "sg:phone":"+64 6-278 0026",
    "sg:province":"Taranaki",
    "wof:name":"Price Chopper",
    "wof:placetype":"venue"
},
  "geometry": {"coordinates":[174.271317,-39.57584],"type":"Point"}
}