{
  "type": "Feature",
  "properties": {
    "addr:full":"Main Rd  Waikouaiti",
    "addr:street":"Main Rd",
    "iso:country":"NZ",
    "sg:address":"Main Rd ",
    "sg:city":"Waikouaiti",
    "sg:classifiers":[
        {
            "category":"Health Services",
            "subcategory":"Clinic",
            "type":"Services"
        }
    ],
    "sg:phone":"+64 3-465 7599",
    "sg:tags":[
        "medical",
        "beauty"
    ],
    "wof:name":"Waikouaiti Medical Centre",
    "wof:placetype":"venue"
},
  "geometry": {"coordinates":[170.675522,-45.593781],"type":"Point"}
}