{
  "type": "Feature",
  "properties": {
    "addr:full":"259 The Mall & Arthur St Onehunga  Auckland Otago",
    "addr:housenumber":"259",
    "addr:street":"The Mall & Arthur St",
    "iso:country":"NZ",
    "sg:address":"259 The Mall & Arthur St Onehunga ",
    "sg:city":"Auckland",
    "sg:classifiers":[
        {
            "category":"Communications",
            "subcategory":"Film & Video Production",
            "type":"Services"
        }
    ],
    "sg:phone":"+64 9-634 5104",
    "sg:province":"Otago",
    "sg:tags":[
        "sport",
        "leisure",
        "library",
        "entertainment"
    ],
    "wof:name":"United Video",
    "wof:placetype":"venue"
},
  "geometry": {"coordinates":[174.78533899999999,-36.922909],"type":"Point"}
}