{
  "type": "Feature",
  "properties": {
    "iso:country":"NZ",
    "sg:address":"227 Waltham Rd Waltham ",
    "sg:city":"Christchurch",
    "sg:classifiers":[
        {
            "category":"Restaurant",
            "type":"Food & Drink"
        }
    ],
    "sg:phone":"+64 3-365 6868",
    "sg:province":"Canterbury",
    "sg:tags":[
        "equipment"
    ],
    "sg:website":"http://www.commercialrefrigeration.co.nz",
    "wof:name":"Commercial Refrigeration & Wholesale",
    "wof:placetype":"venue"
},
  "geometry": {"coordinates":[172.649872,-43.547878],"type":"Point"}
}