{
  "type": "Feature",
  "properties": {
    "addr:full":"33 Thames St Pandora  Napier Hawke's Bay",
    "addr:housenumber":"33",
    "addr:street":"Thames St",
    "iso:country":"NZ",
    "sg:address":"33 Thames St Pandora ",
    "sg:city":"Napier",
    "sg:orig_category":"Storage: Storage",
    "sg:phone":"+64 6-844 7860",
    "sg:province":"Hawke's Bay",
    "wof:name":"Accessible Safe Storage",
    "wof:placetype":"venue"
},
  "geometry": {"coordinates":[176.88644400000001,-39.489826],"type":"Point"}
}