{
  "type": "Feature",
  "properties": {
    "addr:full":"The Square & Main St, Palmerston  Palmerston North Wellington",
    "addr:street":"The;Main St",
    "iso:country":"NZ",
    "sg:address":"The Square & Main St, Palmerston ",
    "sg:city":"Palmerston North",
    "sg:classifiers":[
        {
            "category":"Banks & Credit Unions",
            "subcategory":"Bank",
            "type":"Services"
        }
    ],
    "sg:phone":"+64 6369199",
    "sg:province":"Wellington",
    "wof:name":"Post Office Savings Bank",
    "wof:placetype":"venue"
},
  "geometry": {"coordinates":[175.611481,-40.357422],"type":"Point"}
}