{
  "type": "Feature",
  "properties": {
    "addr:full":"3 Monier Pl Ellerslie  Auckland Auckland",
    "addr:housenumber":"3",
    "addr:street":"Monier Pl",
    "iso:country":"NZ",
    "sg:address":"3 Monier Pl Ellerslie ",
    "sg:city":"Auckland",
    "sg:classifiers":[
        {
            "category":"Manufacturing",
            "subcategory":"Rubber & Plastics",
            "type":"Manufacturing & Wholesale Goods"
        }
    ],
    "sg:phone":"+64 9-579 6347",
    "sg:province":"Auckland",
    "sg:tags":[
        "product",
        "industrial",
        "goods"
    ],
    "wof:name":"Rubber Services (1965) Ltd",
    "wof:placetype":"venue"
},
  "geometry": {"coordinates":[174.80912799999999,-36.884655],"type":"Point"}
}