{
  "type": "Feature",
  "properties": {
    "iso:country":"NZ",
    "sg:address":"540 High St Lower ",
    "sg:city":"Hutt",
    "sg:classifiers":[
        {
            "category":"Sports & Exercise",
            "subcategory":"Tennis Court",
            "type":"Entertainment"
        }
    ],
    "sg:phone":"+64 4-586 7440",
    "sg:province":"Wellington",
    "sg:tags":[
        "medicine",
        "specialists",
        "health",
        "beauty"
    ],
    "wof:name":"A K Osteopaths",
    "wof:placetype":"venue"
},
  "geometry": {"coordinates":[174.904526,-41.208431],"type":"Point"}
}