{
  "type": "Feature",
  "properties": {
    "addr:full":"Beach Rd Tahunanui  Nelson Nelson",
    "addr:street":"Beach Rd",
    "iso:country":"NZ",
    "sg:address":"Beach Rd Tahunanui ",
    "sg:city":"Nelson",
    "sg:classifiers":[
        {
            "category":"Recreation",
            "type":"Entertainment"
        }
    ],
    "sg:phone":"+64 3-548 6267",
    "sg:province":"Nelson",
    "sg:tags":[
        "sport",
        "leisure"
    ],
    "wof:name":"Nelson Fun Park Hydroslide",
    "wof:placetype":"venue"
},
  "geometry": {"coordinates":[173.24299600000001,-41.283409],"type":"Point"}
}