{
  "type": "Feature",
  "properties": {
    "addr:full":"9 Gow St  Mosgiel",
    "addr:housenumber":"9",
    "addr:street":"Gow St",
    "iso:country":"NZ",
    "sg:address":"9 Gow St ",
    "sg:city":"Mosgiel",
    "sg:orig_category":"Industrial: Products: Filters And Filtration",
    "sg:phone":"+64 800 243 553",
    "wof:name":"Filter Group Ltd",
    "wof:placetype":"venue"
},
  "geometry": {"coordinates":[170.35110499999999,-45.887875],"type":"Point"}
}