{
  "type": "Feature",
  "properties": {
    "iso:country":"NZ",
    "sg:address":"Joseph Hammond Pl Mangere ",
    "sg:city":"Auckland",
    "sg:orig_category":"Transport: Transportation: Postal Services",
    "sg:phone":"+64 9-255 0500",
    "sg:province":"Auckland",
    "sg:website":"http://www.tnt.com/nz",
    "wof:name":"TNT",
    "wof:placetype":"venue"
},
  "geometry": {"coordinates":[174.82380699999999,-36.96891],"type":"Point"}
}