{
  "type": "Feature",
  "properties": {
    "addr:full":"Auckland International Airport  Auckland Auckland",
    "iso:country":"NZ",
    "sg:address":"Auckland International Airport ",
    "sg:city":"Auckland",
    "sg:orig_category":"Transport: Transportation: Air Freight",
    "sg:phone":"+64 9-256 8464",
    "sg:province":"Auckland",
    "wof:name":"EVA Air Cargo",
    "wof:placetype":"venue"
},
  "geometry": {"coordinates":[174.782104,-37.008541],"type":"Point"}
}