{
  "type": "Feature",
  "properties": {
    "addr:full":"Mill Rd R D 1 Ohaupo  Hamilton Waikato",
    "addr:housenumber":"1",
    "addr:street":"Mill Rd R D",
    "iso:country":"NZ",
    "sg:address":"Mill Rd R D 1 Ohaupo ",
    "sg:city":"Hamilton",
    "sg:orig_category":"Industrial: Equipment And Machinery: Specialist Equipment: Machinery: Sewing Machines",
    "sg:phone":"+64 7-823 6836",
    "sg:province":"Waikato",
    "wof:name":"Sewtech",
    "wof:placetype":"venue"
},
  "geometry": {"coordinates":[175.30587800000001,-37.9193],"type":"Point"}
}