{
  "type": "Feature",
  "properties": {
    "addr:full":"Devon St  Kelburn Wellington",
    "addr:street":"Devon St",
    "iso:country":"NZ",
    "sg:address":"Devon St ",
    "sg:city":"Kelburn",
    "sg:orig_category":"Clothing And Fabric: Clothing: Dressmakers",
    "sg:phone":"+64 21 572 380",
    "sg:province":"Wellington",
    "wof:name":"Virginia Marie Crawford",
    "wof:placetype":"venue"
},
  "geometry": {"coordinates":[174.76329000000001,-41.287582],"type":"Point"}
}