{
  "type": "Feature",
  "properties": {
    "addr:full":"Auckland & North Shore  Auckland Auckland",
    "iso:country":"NZ",
    "sg:address":"Auckland & North Shore ",
    "sg:city":"Auckland",
    "sg:orig_category":"Automotive: Parts And Supplies: Tyres",
    "sg:phone":"+64 800 386 567",
    "sg:province":"Auckland",
    "sg:website":"http://www.dunlop.co.nz",
    "wof:name":"Dunlop Flag Dealers",
    "wof:placetype":"venue"
},
  "geometry": {"coordinates":[174.745667,-36.779221],"type":"Point"}
}