{
  "type": "Feature",
  "properties": {
    "addr:full":"PO Box 13641 Onehunga  Auckland Auckland",
    "addr:housenumber":"po box",
    "addr:postcode":"13641",
    "iso:country":"NZ",
    "sg:address":"PO Box 13641 Onehunga ",
    "sg:city":"Auckland",
    "sg:classifiers":[
        {
            "category":"Education",
            "subcategory":"Music School",
            "type":"Public Place"
        }
    ],
    "sg:phone":"+64 9-522 8252",
    "sg:province":"Auckland",
    "sg:tags":[
        "sport",
        "teacher",
        "leisure"
    ],
    "wof:name":"The Guitar Studio",
    "wof:placetype":"venue"
},
  "geometry": {"coordinates":[174.783661,-36.909973],"type":"Point"}
}