{
  "type": "Feature",
  "properties": {
    "addr:full":"320 Te Kowhai Road Te Rapa  Hamilton Waikato",
    "addr:housenumber":"320",
    "addr:street":"Te Kowhai Road",
    "iso:country":"NZ",
    "sg:address":"320 Te Kowhai Road Te Rapa ",
    "sg:city":"Hamilton",
    "sg:classifiers":[
        {
            "category":"Shopping",
            "subcategory":"Discount & Variety Stores",
            "type":"Retail Goods"
        }
    ],
    "sg:phone":"+64 7-849 1044",
    "sg:province":"Waikato",
    "sg:tags":[
        "storage",
        "cool"
    ],
    "wof:name":"Absolute Coolstore",
    "wof:placetype":"venue"
},
  "geometry": {"coordinates":[175.21069299999999,-37.7407],"type":"Point"}
}