{
  "type": "Feature",
  "properties": {
    "addr:full":"17 C Vega Pl Mairangi Bay  Auckland Auckland",
    "addr:housenumber":"17 c",
    "addr:street":"Vega Pl",
    "iso:country":"NZ",
    "sg:address":"17 C Vega Pl Mairangi Bay ",
    "sg:city":"Auckland",
    "sg:orig_category":"Home And Garden: Furniture/Furnishings: Curtains",
    "sg:phone":"+64 9-478 9945",
    "sg:province":"Auckland",
    "wof:name":"Creative Curtains By Lynn Ltd",
    "wof:placetype":"venue"
},
  "geometry": {"coordinates":[174.74816899999999,-36.738461],"type":"Point"}
}