{
  "type": "Feature",
  "properties": {
    "addr:full":"Howick  Auckland Auckland",
    "iso:country":"NZ",
    "sg:address":"Howick ",
    "sg:city":"Auckland",
    "sg:classifiers":[
        {
            "category":"Education",
            "subcategory":"Special Training",
            "type":"Public Place"
        }
    ],
    "sg:phone":"+64 9-534 7702",
    "sg:province":"Auckland",
    "sg:tags":[
        "therapist",
        "speech",
        "language"
    ],
    "wof:name":"Alison Owen",
    "wof:placetype":"venue"
},
  "geometry": {"coordinates":[174.928055,-36.89695],"type":"Point"}
}