{
  "type": "Feature",
  "properties": {
    "iso:country":"NZ",
    "sg:address":"60 Hattaway Ave Bucklands Beach ",
    "sg:city":"Auckland",
    "sg:classifiers":[
        {
            "category":"Retail",
            "subcategory":"Driving School",
            "type":"Services"
        }
    ],
    "sg:phone":"+64 9-534 4683",
    "sg:province":"Wellington",
    "sg:tags":[
        "training",
        "education",
        "driver"
    ],
    "wof:name":"Safeway Driving School",
    "wof:placetype":"venue"
},
  "geometry": {"coordinates":[174.903717,-36.865616],"type":"Point"}
}