{
  "type": "Feature",
  "properties": {
    "addr:full":"3 Pehi St  Wanganui Manawatu-Wanganui",
    "addr:housenumber":"3",
    "addr:street":"Pehi St",
    "iso:country":"NZ",
    "sg:address":"3 Pehi St ",
    "sg:city":"Wanganui",
    "sg:classifiers":[
        {
            "category":"Manufacturing",
            "subcategory":"Glass & Minerals",
            "type":"Manufacturing & Wholesale Goods"
        }
    ],
    "sg:phone":"+64 6-343 3131",
    "sg:province":"Manawatu-Wanganui",
    "sg:tags":[
        "chemical",
        "fibre",
        "industrial",
        "compounds"
    ],
    "wof:name":"Fibrecraft Ltd",
    "wof:placetype":"venue"
},
  "geometry": {"coordinates":[175.05834999999999,-39.910519],"type":"Point"}
}