{
  "type": "Feature",
  "properties": {
    "iso:country":"NZ",
    "sg:address":"40 Onehunga Mal Onehunga ",
    "sg:city":"Auckland",
    "sg:orig_category":"Home And Garden",
    "sg:phone":"+64 9-634 1881",
    "sg:province":"Auckland",
    "sg:website":"http://www.yellowpages.co.nz/for/superloo/dp58244.html",
    "wof:name":"Super Loo Sanitation Ltd",
    "wof:placetype":"venue"
},
  "geometry": {"coordinates":[174.78668200000001,-36.930019],"type":"Point"}
}