{
  "type": "Feature",
  "properties": {
    "addr:full":"St Lukes Foot Clinic 81 St Lukes Rd St Lukes  Auckland Auckland",
    "addr:housenumber":"81",
    "addr:street":"St Lukes Rd St",
    "iso:country":"NZ",
    "sg:address":"St Lukes Foot Clinic 81 St Lukes Rd St Lukes ",
    "sg:city":"Auckland",
    "sg:orig_category":"Health And Beauty: Specialists: Podiatrists",
    "sg:phone":"+64 9-379 1077",
    "sg:province":"Auckland",
    "wof:name":"Grech Roger Podiatry",
    "wof:placetype":"venue"
},
  "geometry": {"coordinates":[174.728973,-36.877918],"type":"Point"}
}