{
  "type": "Feature",
  "properties": {
    "iso:country":"NZ",
    "sg:address":"Waiaruhe Rd ",
    "sg:city":"Taihape",
    "sg:classifiers":[
        {
            "category":"Manufacturing",
            "subcategory":"Furniture",
            "type":"Manufacturing & Wholesale Goods"
        }
    ],
    "sg:phone":"+64 6-388 0345",
    "sg:tags":[
        "furniture/furnishings",
        "home",
        "garden",
        "manufacturer"
    ],
    "wof:name":"High Country Joinery",
    "wof:placetype":"venue"
},
  "geometry": {"coordinates":[175.669952,-39.544968],"type":"Point"}
}