{
  "type": "Feature",
  "properties": {
    "addr:full":"108 G Station Rd Otahuhu  Auckland Auckland",
    "addr:housenumber":"108 g",
    "addr:street":"Station Rd",
    "iso:country":"NZ",
    "sg:address":"108 G Station Rd Otahuhu ",
    "sg:city":"Auckland",
    "sg:orig_category":"Transport: Transportation: Container Services",
    "sg:phone":"+64 9-270 9219",
    "sg:province":"Auckland",
    "wof:name":"Container Wash Systems Ltd",
    "wof:placetype":"venue"
},
  "geometry": {"coordinates":[174.83471700000001,-36.945953],"type":"Point"}
}