{
  "type": "Feature",
  "properties": {
    "addr:full":"72 - 78 Tokomaru East Road R D 4 Palmerston  Palmerston North Canterbury",
    "addr:housenumber":"78;4;palmerston",
    "addr:street":"Tokomaru East Road R D;Palmerston",
    "iso:country":"NZ",
    "sg:address":"72 - 78 Tokomaru East Road R D 4 Palmerston ",
    "sg:city":"Palmerston North",
    "sg:classifiers":[
        {
            "category":"Shopping",
            "subcategory":"Pets & Pet Supplies",
            "type":"Retail Goods"
        }
    ],
    "sg:phone":"+64 6-329 8063",
    "sg:province":"Canterbury",
    "sg:tags":[
        "boarding",
        "garden",
        "pets",
        "catteries",
        "home",
        "kennel"
    ],
    "wof:name":"Able Boarding & Premimum Pet Food Sales",
    "wof:placetype":"venue"
},
  "geometry": {"coordinates":[175.611481,-40.357418],"type":"Point"}
}