{
  "type": "Feature",
  "properties": {
    "addr:full":"PO Box 237 Wellington Lower  Hutt Wellington",
    "addr:housenumber":"po;237",
    "addr:street":"Box;Wellington",
    "iso:country":"NZ",
    "sg:address":"PO Box 237 Wellington Lower ",
    "sg:city":"Hutt",
    "sg:orig_category":"Home And Garden: Gardening: Services: Landscape Consultants",
    "sg:phone":"+64 4-586 8406",
    "sg:province":"Wellington",
    "wof:name":"Keltic Landscapes",
    "wof:placetype":"venue"
},
  "geometry": {"coordinates":[174.90838600000001,-41.206631],"type":"Point"}
}