{
  "type": "Feature",
  "properties": {
    "iso:country":"NZ",
    "sg:address":"62b Diana Dve Glenfield ",
    "sg:city":"Auckland",
    "sg:orig_category":"Shopping: Retail Stores: Batteries",
    "sg:phone":"+64 9-917 4000",
    "sg:province":"Auckland",
    "wof:name":"Toshiba Batteries- CDB Media Ltd",
    "wof:placetype":"venue"
},
  "geometry": {"coordinates":[174.728622,-36.784813],"type":"Point"}
}