{
  "type": "Feature",
  "properties": {
    "iso:country":"NZ",
    "sg:address":"24 Silverdale St Silverdale Hibiscus ",
    "sg:city":"Hibiscus Coast",
    "sg:orig_category":"Home And Garden: Accessories: Linen",
    "sg:phone":"+64 9-426 0155",
    "sg:province":"Auckland",
    "wof:name":"Clive's Home Interiors",
    "wof:placetype":"venue"
},
  "geometry": {"coordinates":[174.676514,-36.617577],"type":"Point"}
}