{
  "type": "Feature",
  "properties": {
    "addr:full":"Hillary Ct 57 Treadwell St Naenae Lower  Hutt Wellington",
    "addr:housenumber":"57",
    "addr:street":"Hillary Ct;Treadwell St",
    "iso:country":"NZ",
    "sg:address":"Hillary Ct 57 Treadwell St Naenae Lower ",
    "sg:city":"Hutt",
    "sg:orig_category":"Health And Beauty: Dental: Dentists",
    "sg:phone":"+64 4-567 4752",
    "sg:province":"Wellington",
    "wof:name":"Naenae Dental Clinic Ltd",
    "wof:placetype":"venue"
},
  "geometry": {"coordinates":[174.949524,-41.201859],"type":"Point"}
}