{
  "type": "Feature",
  "properties": {
    "iso:country":"NZ",
    "sg:address":"Level 2 155-165 The Strand Parnell ",
    "sg:city":"Auckland",
    "sg:orig_category":"Clothing And Fabric: Fabric: Textiles",
    "sg:phone":"+64 9-302 1652",
    "sg:province":"Auckland",
    "wof:name":"Icon Textiles",
    "wof:placetype":"venue"
},
  "geometry": {"coordinates":[174.786087,-36.85479],"type":"Point"}
}