{
  "type": "Feature",
  "properties": {
    "iso:country":"NZ",
    "sg:address":"14 Putiki Rd Ostend Waiheke ",
    "sg:city":"Island",
    "sg:classifiers":[
        {
            "category":"Sports & Exercise",
            "subcategory":"Sports Center",
            "type":"Entertainment"
        }
    ],
    "sg:phone":"+64 9-372 6063",
    "sg:province":"Auckland",
    "sg:tags":[
        "health",
        "beauty",
        "fitness"
    ],
    "wof:name":"All About Women Health Club",
    "wof:placetype":"venue"
},
  "geometry": {"coordinates":[175.044128,-36.79723],"type":"Point"}
}