{
  "type": "Feature",
  "properties": {
    "addr:full":"13 Akiraho St Mt Eden  Auckland Auckland",
    "addr:housenumber":"13",
    "addr:street":"Akiraho St",
    "iso:country":"NZ",
    "sg:address":"13 Akiraho St Mt Eden ",
    "sg:city":"Auckland",
    "sg:orig_category":"Food And Drink: Catering: Caterers",
    "sg:phone":"+64 9-623 5930",
    "sg:province":"Auckland",
    "sg:website":"http://www.austins.co.nz",
    "wof:name":"Austin's Food Design Events",
    "wof:placetype":"venue"
},
  "geometry": {"coordinates":[174.75824,-36.868484],"type":"Point"}
}