{
  "type": "Feature",
  "properties": {
    "addr:full":"204 Great South Rd Papatoetoe  Auckland Auckland",
    "addr:housenumber":"204",
    "addr:street":"Great South Rd",
    "iso:country":"NZ",
    "sg:address":"204 Great South Rd Papatoetoe ",
    "sg:city":"Auckland",
    "sg:classifiers":[
        {
            "category":"Banks & Credit Unions",
            "subcategory":"Investment Brokerage",
            "type":"Services"
        }
    ],
    "sg:phone":"+64 9-278 5321",
    "sg:province":"Auckland",
    "sg:tags":[
        "director",
        "funeral",
        "arrangements"
    ],
    "wof:name":"Alan Shaw Funeral Director - Shaws Funeral Services Ltd",
    "wof:placetype":"venue"
},
  "geometry": {"coordinates":[174.86129800000001,-36.970036],"type":"Point"}
}