{
  "type": "Feature",
  "properties": {
    "iso:country":"NZ",
    "sg:address":"204 Great South Rd Papatoetoe ",
    "sg:city":"Auckland",
    "sg:classifiers":[
        {
            "category":"Banks & Credit Unions",
            "subcategory":"Investment Brokerage",
            "type":"Services"
        }
    ],
    "sg:phone":"+64 9-278 5321",
    "sg:province":"Auckland",
    "sg:tags":[
        "director",
        "funeral",
        "arrangements"
    ],
    "wof:name":"Alan Shaw Funeral Director - Shaws Funeral Services Ltd",
    "wof:placetype":"venue"
},
  "geometry": {"coordinates":[174.861298,-36.970036],"type":"Point"}
}