{
  "type": "Feature",
  "properties": {
    "addr:full":"227 Bush Rd, North Harbour Industrial Park Albany  Auckland Auckland",
    "addr:housenumber":"227",
    "addr:street":"Bush Rd",
    "iso:country":"NZ",
    "sg:address":"227 Bush Rd, North Harbour Industrial Park Albany ",
    "sg:city":"Auckland",
    "sg:orig_category":"Industrial: Refrigeration And Services: Refrigeration",
    "sg:phone":"+64 9-415 6910",
    "sg:province":"Auckland",
    "sg:website":"http://www.yellowpages.co.nz/for/finnemorerefrigeration/dp21901.html",
    "wof:name":"Finnemore Refrigeration Ltd",
    "wof:placetype":"venue"
},
  "geometry": {"coordinates":[174.70515399999999,-36.753681],"type":"Point"}
}