{
  "type": "Feature",
  "properties": {
    "addr:full":"49 Murdock Rd Grey Lynn  Auckland Auckland",
    "addr:housenumber":"49",
    "addr:street":"Murdock Rd",
    "iso:country":"NZ",
    "sg:address":"49 Murdock Rd Grey Lynn ",
    "sg:city":"Auckland",
    "sg:classifiers":[
        {
            "category":"Shopping",
            "subcategory":"Computers & Home Electronics",
            "type":"Retail Goods"
        }
    ],
    "sg:phone":"+64 9-376 2691",
    "sg:province":"Auckland",
    "sg:tags":[
        "recording",
        "equipment",
        "sport",
        "music",
        "leisure"
    ],
    "wof:name":"Montage Recording Studio",
    "wof:placetype":"venue"
},
  "geometry": {"coordinates":[174.74205000000001,-36.859932],"type":"Point"}
}