{
  "type": "Feature",
  "properties": {
    "addr:full":"1366 Tiki Rd  Coromandel",
    "addr:housenumber":"1366",
    "addr:street":"Tiki Rd",
    "iso:country":"NZ",
    "sg:address":"1366 Tiki Rd ",
    "sg:city":"Coromandel",
    "sg:classifiers":[
        {
            "category":"Home & Garden",
            "subcategory":"Home Furnishings",
            "type":"Retail Goods"
        }
    ],
    "sg:phone":"+64 7-866 7949",
    "sg:tags":[
        "furniture/furnishings",
        "upholstery",
        "supply"
    ],
    "wof:name":"Coromandel Upholstery & Trimming",
    "wof:placetype":"venue"
},
  "geometry": {"coordinates":[175.51211499999999,-36.787769],"type":"Point"}
}