{
  "type": "Feature",
  "properties": {
    "iso:country":"NZ",
    "sg:address":"15 Durham St ",
    "sg:city":"Levin",
    "sg:classifiers":[
        {
            "category":"Sports & Exercise",
            "subcategory":"Sports Center",
            "type":"Entertainment"
        }
    ],
    "sg:phone":"+64 6-368 8937",
    "sg:province":"Manawatu-Wanganui",
    "sg:tags":[
        "health",
        "beauty",
        "fitness"
    ],
    "wof:name":"Kiwi Fitness Clinic",
    "wof:placetype":"venue"
},
  "geometry": {"coordinates":[-89.084503,37.193748],"type":"Point"}
}