{
  "type": "Feature",
  "properties": {
    "iso:country":"NZ",
    "sg:address":"68 East Rd R D 1 ",
    "sg:city":"Invercargill",
    "sg:classifiers":[
        {
            "category":"Home & Garden",
            "subcategory":"Kitchen Supply",
            "type":"Retail Goods"
        }
    ],
    "sg:phone":"+64 3-217 3208",
    "sg:province":"Southland",
    "sg:tags":[
        "shop",
        "pet",
        "pets"
    ],
    "wof:name":"East Road Pets",
    "wof:placetype":"venue"
},
  "geometry": {"coordinates":[168.401535,-46.403423],"type":"Point"}
}