{
  "type": "Feature",
  "properties": {
    "addr:full":"23 Union St  Hawera Taranaki",
    "addr:housenumber":"23",
    "addr:street":"Union St",
    "iso:country":"NZ",
    "sg:address":"23 Union St ",
    "sg:city":"Hawera",
    "sg:orig_category":"Shopping: Retail Stores: Secondhand Dealers",
    "sg:phone":"+64 6-278 5613",
    "sg:province":"Taranaki",
    "wof:name":"All Sorts Traders & Pet Supplies",
    "wof:placetype":"venue"
},
  "geometry": {"coordinates":[174.28207399999999,-39.58783],"type":"Point"}
}