{
  "type": "Feature",
  "properties": {
    "iso:country":"NZ",
    "sg:address":"PO Box 467 Wellington Central ",
    "sg:city":"Wellington",
    "sg:classifiers":[
        {
            "category":"Travel",
            "subcategory":"Travel Agent",
            "type":"Entertainment"
        }
    ],
    "sg:phone":"+64 4-381 7000",
    "sg:province":"Wellington",
    "sg:tags":[
        "tour",
        "tourism",
        "sightseeing"
    ],
    "sg:website":"http://www.tepapa.govt.nz",
    "wof:name":"Te Papa",
    "wof:placetype":"venue"
},
  "geometry": {"coordinates":[174.77804599999999,-41.280739],"type":"Point"}
}