{
  "type": "Feature",
  "properties": {
    "iso:country":"NZ",
    "sg:address":"193 Main South Rd Green Island ",
    "sg:city":"Dunedin",
    "sg:orig_category":"Shopping: Retail Stores: Books: Bookshops",
    "sg:phone":"+64 3-488 2240",
    "sg:province":"Otago",
    "wof:name":"Green Island Post & Paper",
    "wof:placetype":"venue"
},
  "geometry": {"coordinates":[170.430145,-45.901642],"type":"Point"}
}