{
  "type": "Feature",
  "properties": {
    "addr:full":"118 B Railside Ave Henderson  Auckland Auckland",
    "addr:housenumber":"118 b",
    "addr:street":"Railside Ave",
    "iso:country":"NZ",
    "sg:address":"118 B Railside Ave Henderson ",
    "sg:city":"Auckland",
    "sg:classifiers":[
        {
            "category":"Health Services",
            "subcategory":"Hospital",
            "type":"Services"
        }
    ],
    "sg:phone":"+64 9-836 9974",
    "sg:province":"Auckland",
    "sg:tags":[
        "beauty",
        "fitness"
    ],
    "wof:name":"Auckbritt International Ltd",
    "wof:placetype":"venue"
},
  "geometry": {"coordinates":[174.631775,-36.887859],"type":"Point"}
}