{
  "type": "Feature",
  "properties": {
    "addr:full":"Ohauiti Rd Tauranga R D  3",
    "addr:housenumber":"3",
    "addr:street":"Ohauiti Rd;R D",
    "iso:country":"NZ",
    "sg:address":"Ohauiti Rd Tauranga R D ",
    "sg:city":"3",
    "sg:orig_category":"Industrial: Services: Drillers",
    "sg:phone":"+64 25730449",
    "wof:name":"Cameron Ewen",
    "wof:placetype":"venue"
},
  "geometry": {"coordinates":[176.14475999999999,-37.703152],"type":"Point"}
}