{
  "type": "Feature",
  "properties": {
    "iso:country":"NZ",
    "sg:address":"23/7 Cleveland Rd Parnell ",
    "sg:city":"Auckland",
    "sg:classifiers":[
        {
            "category":"Coffee & Tea",
            "type":"Food & Drink"
        }
    ],
    "sg:phone":"+64 9-368 5300",
    "sg:province":"Auckland",
    "sg:tags":[
        "merchant"
    ],
    "wof:name":"Time For Tea",
    "wof:placetype":"venue"
},
  "geometry": {"coordinates":[174.78398100000001,-36.851944],"type":"Point"}
}