{
  "type": "Feature",
  "properties": {
    "addr:full":"3 Te Apunga Pl Mt Wellington  Auckland Auckland",
    "addr:housenumber":"3",
    "addr:street":"Te Apunga Pl",
    "iso:country":"NZ",
    "sg:address":"3 Te Apunga Pl Mt Wellington ",
    "sg:city":"Auckland",
    "sg:orig_category":"Industrial: Parts: Bearings",
    "sg:phone":"+64 9-276 4992",
    "sg:province":"Auckland",
    "sg:website":"http://www.nsk.co.nz",
    "wof:name":"NSK New Zealand Ltd",
    "wof:placetype":"venue"
},
  "geometry": {"coordinates":[174.85022000000001,-36.92445],"type":"Point"}
}