{
  "type": "Feature",
  "properties": {
    "addr:full":"61 Stuart St  Oamaru Otago",
    "addr:housenumber":"61",
    "addr:street":"Stuart St",
    "iso:country":"NZ",
    "sg:address":"61 Stuart St ",
    "sg:city":"Oamaru",
    "sg:classifiers":[
        {
            "category":"Personal",
            "type":"Services"
        }
    ],
    "sg:phone":"+64 3-434 6688",
    "sg:province":"Otago",
    "sg:tags":[
        "celebrant",
        "arrangements",
        "marriage",
        "wedding"
    ],
    "wof:name":"Bond P J",
    "wof:placetype":"venue"
},
  "geometry": {"coordinates":[170.94490099999999,-45.107895],"type":"Point"}
}