{
  "type": "Feature",
  "properties": {
    "addr:full":"FOR YOUR NEAREST  DEALER",
    "iso:country":"NZ",
    "sg:address":"FOR YOUR NEAREST ",
    "sg:city":"DEALER",
    "sg:orig_category":"Automotive: Parts And Supplies: Tyres",
    "sg:phone":"+64 800 738 973",
    "wof:name":"Kumho Tyres",
    "wof:placetype":"venue"
},
  "geometry": {"coordinates":[-38.5322,-3.7758],"type":"Point"}
}