{
  "type": "Feature",
  "properties": {
    "iso:country":"NZ",
    "sg:address":"Kioreroa Rd ",
    "sg:city":"Whangarei",
    "sg:orig_category":"Home And Garden: Accessories: Hardware",
    "sg:phone":"+64 9-438 9359",
    "sg:province":"Northland",
    "wof:name":"Rosvall ITM",
    "wof:placetype":"venue"
},
  "geometry": {"coordinates":[174.325577,-35.74435],"type":"Point"}
}