{
  "type": "Feature",
  "properties": {
    "iso:country":"NZ",
    "sg:address":"Suite 1/ 9 St Marks Rd Remuera ",
    "sg:city":"Auckland",
    "sg:classifiers":[
        {
            "category":"Health Services",
            "subcategory":"Health Practitioner",
            "type":"Services"
        }
    ],
    "sg:phone":"+64 9-524 9055",
    "sg:province":"Auckland",
    "sg:tags":[
        "specialist",
        "medical",
        "beauty",
        "specialists"
    ],
    "wof:name":"Garrett Dr Jeff",
    "wof:placetype":"venue"
},
  "geometry": {"coordinates":[174.780045,-36.87405],"type":"Point"}
}