{
  "type": "Feature",
  "properties": {
    "addr:full":"Waikanae Community Centre Aputa Pl  Waikanae",
    "addr:street":"Pl",
    "iso:country":"NZ",
    "sg:address":"Waikanae Community Centre Aputa Pl ",
    "sg:city":"Waikanae",
    "sg:classifiers":[
        {
            "category":"Communications",
            "subcategory":"Radio Station",
            "type":"Services"
        }
    ],
    "sg:phone":"+64 4-293 4838",
    "sg:tags":[
        "broadcasting"
    ],
    "wof:name":"Coast Access F M",
    "wof:placetype":"venue"
},
  "geometry": {"coordinates":[175.06102000000001,-40.873184],"type":"Point"}
}