{
  "type": "Feature",
  "properties": {
    "addr:full":"62 Queens Dve Lower  Hutt Wellington",
    "addr:housenumber":"62",
    "addr:street":"Queens Dve",
    "iso:country":"NZ",
    "sg:address":"62 Queens Dve Lower ",
    "sg:city":"Hutt",
    "sg:orig_category":"Industrial: Equipment And Machinery: Specialist Equipment: Machinery: Knitting Machines",
    "sg:phone":"+64 4-566 4689",
    "sg:province":"Wellington",
    "wof:name":"Brother New Zealand Distributors",
    "wof:placetype":"venue"
},
  "geometry": {"coordinates":[174.904526,-41.208431],"type":"Point"}
}