{
  "type": "Feature",
  "properties": {
    "iso:country":"NZ",
    "sg:address":"Whitford Park Rd Whitford ",
    "sg:city":"Auckland",
    "sg:orig_category":"Sports And Leisure: Sports: Golf: Golf Courses",
    "sg:phone":"+64 9-530 8823",
    "sg:province":"Auckland",
    "wof:name":"Whitford Park Country Club Inc",
    "wof:placetype":"venue"
},
  "geometry": {"coordinates":[174.963684,-36.946308],"type":"Point"}
}