{
  "type": "Feature",
  "properties": {
    "iso:country":"NZ",
    "sg:address":"46 Hollywood Ave Titirangi ",
    "sg:city":"Auckland",
    "sg:classifiers":[
        {
            "category":"Personal",
            "type":"Services"
        }
    ],
    "sg:phone":"+64 9-817 7280",
    "sg:province":"Auckland",
    "sg:tags":[
        "services",
        "home",
        "garden",
        "counselling"
    ],
    "wof:name":"Miracle Computers",
    "wof:placetype":"venue"
},
  "geometry": {"coordinates":[174.662796,-36.926861],"type":"Point"}
}