{
  "type": "Feature",
  "properties": {
    "iso:country":"NZ",
    "sg:address":"9 Porowini Ave ",
    "sg:city":"Whangarei",
    "sg:classifiers":[
        {
            "category":"Home & Garden",
            "subcategory":"Home Furnishings",
            "type":"Retail Goods"
        }
    ],
    "sg:phone":"+64 9-438 7974",
    "sg:province":"Northland",
    "sg:tags":[
        "furniture/furnishings",
        "upholstery",
        "supply"
    ],
    "wof:name":"Brian J Green",
    "wof:placetype":"venue"
},
  "geometry": {"coordinates":[174.316376,-35.729183],"type":"Point"}
}