{
  "type": "Feature",
  "properties": {
    "addr:full":"Kemra Bank Leman St Tokti  Milton",
    "addr:street":"Leman St",
    "iso:country":"NZ",
    "sg:address":"Kemra Bank Leman St Tokti ",
    "sg:city":"Milton",
    "sg:classifiers":[
        {
            "category":"Manufacturing",
            "subcategory":"Furniture",
            "type":"Manufacturing & Wholesale Goods"
        }
    ],
    "sg:phone":"+64 3-417 7149",
    "sg:tags":[
        "furniture/furnishings",
        "home",
        "garden",
        "manufacturer"
    ],
    "wof:name":"Little Peoples Furniture Factory",
    "wof:placetype":"venue"
},
  "geometry": {"coordinates":[169.976562,-46.13147],"type":"Point"}
}