{
  "type": "Feature",
  "properties": {
    "iso:country":"NZ",
    "sg:address":"116 Princess St Palmerston ",
    "sg:city":"Palmerston North",
    "sg:classifiers":[
        {
            "category":"Professional",
            "type":"Services"
        }
    ],
    "sg:phone":"+64 6-356 1990",
    "sg:province":"Manawatu-Wanganui",
    "sg:tags":[
        "services",
        "car",
        "valet",
        "automotive"
    ],
    "wof:name":"The Grooming Men",
    "wof:placetype":"venue"
},
  "geometry": {"coordinates":[175.617004,-40.356537],"type":"Point"}
}