{
  "type": "Feature",
  "properties": {
    "addr:full":"14 Puketapu Rd Taradale  Napier Hawke's Bay",
    "addr:housenumber":"14",
    "addr:street":"Puketapu Rd",
    "iso:country":"NZ",
    "sg:address":"14 Puketapu Rd Taradale ",
    "sg:city":"Napier",
    "sg:classifiers":[
        {
            "category":"Home & Garden",
            "subcategory":"Home Furnishings",
            "type":"Retail Goods"
        }
    ],
    "sg:phone":"+64 6-844 5061",
    "sg:province":"Hawke's Bay",
    "sg:tags":[
        "furniture/furnishings",
        "upholstery",
        "supply"
    ],
    "wof:name":"Fine Furniture",
    "wof:placetype":"venue"
},
  "geometry": {"coordinates":[176.84660299999999,-39.537048],"type":"Point"}
}