{
  "type": "Feature",
  "properties": {
    "addr:full":"29 North Ave Devonport  Auckland Auckland",
    "addr:housenumber":"29",
    "addr:street":"North Ave",
    "iso:country":"NZ",
    "sg:address":"29 North Ave Devonport ",
    "sg:city":"Auckland",
    "sg:orig_category":"Shopping: Hobbies And Games: Aromatherapy",
    "sg:phone":"+64 9-445 0203",
    "sg:province":"Auckland",
    "wof:name":"The Oil Well Ltd",
    "wof:placetype":"venue"
},
  "geometry": {"coordinates":[174.79956100000001,-36.824425],"type":"Point"}
}