{
  "type": "Feature",
  "properties": {
    "addr:full":"72 Riccarton Rd  Christchurch Canterbury",
    "addr:housenumber":"72",
    "addr:street":"Riccarton Rd",
    "iso:country":"NZ",
    "sg:address":"72 Riccarton Rd ",
    "sg:city":"Christchurch",
    "sg:classifiers":[
        {
            "category":"Sports & Exercise",
            "subcategory":"Tennis Court",
            "type":"Entertainment"
        }
    ],
    "sg:phone":"+64 3-348 8836",
    "sg:province":"Canterbury",
    "sg:tags":[
        "bait",
        "hunting",
        "fishing",
        "retailers",
        "tackle",
        "shopping"
    ],
    "wof:name":"Fishermans Loft",
    "wof:placetype":"venue"
},
  "geometry": {"coordinates":[172.60380599999999,-43.52932],"type":"Point"}
}