{
  "type": "Feature",
  "properties": {
    "addr:full":"8 Augustus Tce Parnell  Auckland Auckland",
    "addr:housenumber":"8",
    "addr:street":"Augustus Tce",
    "iso:country":"NZ",
    "sg:address":"8 Augustus Tce Parnell ",
    "sg:city":"Auckland",
    "sg:orig_category":"Clothing And Fabric: Fabric: Textiles",
    "sg:phone":"+64 9-373 2775",
    "sg:province":"Auckland",
    "wof:name":"Woven Image Limited",
    "wof:placetype":"venue"
},
  "geometry": {"coordinates":[174.77799999999999,-36.849934],"type":"Point"}
}