{
  "type": "Feature",
  "properties": {
    "addr:full":"174 Centreway Rd Orewa Hibiscus  Hibiscus Coast Auckland",
    "addr:housenumber":"174",
    "addr:street":"Centreway Rd",
    "iso:country":"NZ",
    "sg:address":"174 Centreway Rd Orewa Hibiscus ",
    "sg:city":"Hibiscus Coast",
    "sg:orig_category":"Health And Beauty: Specialists: Chiropractors",
    "sg:phone":"+64 9-426 4545",
    "sg:province":"Auckland",
    "wof:name":"Orewa Chiropractic Centre",
    "wof:placetype":"venue"
},
  "geometry": {"coordinates":[174.69012499999999,-36.582741],"type":"Point"}
}