{
  "type": "Feature",
  "properties": {
    "addr:full":"16 Rangitoto Rd Papatoetoe  Auckland Auckland",
    "addr:housenumber":"16",
    "addr:street":"Rangitoto Rd",
    "iso:country":"NZ",
    "sg:address":"16 Rangitoto Rd Papatoetoe ",
    "sg:city":"Auckland",
    "sg:orig_category":"Shopping: Retail Stores: Batteries",
    "sg:phone":"+64 9-278 3217",
    "sg:province":"Auckland",
    "wof:name":"Battery Bill",
    "wof:placetype":"venue"
},
  "geometry": {"coordinates":[174.852158,-36.979259],"type":"Point"}
}