{
  "type": "Feature",
  "properties": {
    "iso:country":"NZ",
    "sg:address":"985 Mt Eden Rd Three Kings ",
    "sg:city":"Auckland",
    "sg:classifiers":[
        {
            "category":"Home & Garden",
            "subcategory":"Furniture",
            "type":"Retail Goods"
        }
    ],
    "sg:phone":"+64 9-625 8729",
    "sg:province":"Auckland",
    "sg:tags":[
        "fitting"
    ],
    "sg:website":"http://www.averills.co.nz",
    "wof:name":"Averill Construction Ltd",
    "wof:placetype":"venue"
},
  "geometry": {"coordinates":[174.75904800000001,-36.904671],"type":"Point"}
}