{
  "type": "Feature",
  "properties": {
    "iso:country":"NZ",
    "sg:address":"26 Spencer Rd Browns Bay ",
    "sg:city":"Auckland",
    "sg:classifiers":[
        {
            "category":"Education",
            "subcategory":"Junior College",
            "type":"Public Place"
        }
    ],
    "sg:phone":"+64 800 475 437",
    "sg:province":"Auckland",
    "sg:tags":[
        "school",
        "training",
        "care"
    ],
    "sg:website":"http://www.yellowpages.co.nz/pages/202061590/dp15420.html",
    "wof:name":"S.K.I.D.S",
    "wof:placetype":"venue"
},
  "geometry": {"coordinates":[174.744324,-36.714409],"type":"Point"}
}