{
  "type": "Feature",
  "properties": {
    "addr:full":"19-23 A Miami Pde Te Papapa  Auckland Auckland",
    "addr:housenumber":"19-23 a;pde",
    "iso:country":"NZ",
    "sg:address":"19-23 A Miami Pde Te Papapa ",
    "sg:city":"Auckland",
    "sg:orig_category":"Industrial: Products: Tallow Merchants",
    "sg:phone":"+64 9-636 8455",
    "sg:province":"Auckland",
    "wof:name":"Tallow Products Ltd",
    "wof:placetype":"venue"
},
  "geometry": {"coordinates":[174.80831900000001,-36.929474],"type":"Point"}
}