{
  "type": "Feature",
  "properties": {
    "addr:full":"Karori Acupuncture and Family Health Centre 92 A Karori, Rd Karori  Wellington Wellington",
    "addr:housenumber":"92 a",
    "addr:street":"Karori Rd",
    "iso:country":"NZ",
    "sg:address":"Karori Acupuncture and Family Health Centre 92 A Karori, Rd Karori ",
    "sg:city":"Wellington",
    "sg:classifiers":[
        {
            "category":"Health Services",
            "subcategory":"Health Practitioner",
            "type":"Services"
        }
    ],
    "sg:phone":"+64 4-476 2765",
    "sg:province":"Wellington",
    "sg:tags":[
        "services",
        "beauty",
        "acupuncturists"
    ],
    "wof:name":"Haiselden Tim",
    "wof:placetype":"venue"
},
  "geometry": {"coordinates":[174.74087499999999,-41.283745],"type":"Point"}
}