{
  "type": "Feature",
  "properties": {
    "addr:full":"Ferndale R D 2 Gore  Mataura",
    "addr:housenumber":"2",
    "addr:street":"R D",
    "iso:country":"NZ",
    "sg:address":"Ferndale R D 2 Gore ",
    "sg:city":"Mataura",
    "sg:orig_category":"Farming: Machinery: Farm Machinery",
    "sg:phone":"+64 3-203 8199",
    "wof:name":"McLeod Farm Equipment",
    "wof:placetype":"venue"
},
  "geometry": {"coordinates":[168.854309,-46.147888],"type":"Point"}
}