{
  "type": "Feature",
  "properties": {
    "iso:country":"NZ",
    "sg:address":"1 Shortland St Auckland City ",
    "sg:city":"Auckland",
    "sg:classifiers":[
        {
            "category":"Education",
            "subcategory":"Vocational School",
            "type":"Public Place"
        }
    ],
    "sg:phone":"+64 9-377 4855",
    "sg:province":"Auckland",
    "sg:tags":[
        "training",
        "hairdressing"
    ],
    "sg:website":"http://www.yellowpages.co.nz/for/winters/dp18183.html",
    "wof:name":"Winters The School Of Hairdressing Ltd",
    "wof:placetype":"venue"
},
  "geometry": {"coordinates":[174.766205,-36.846481],"type":"Point"}
}