{
  "type": "Feature",
  "properties": {
    "iso:country":"NZ",
    "sg:address":"Bathgates Rd R D 10 ",
    "sg:city":"Waimate",
    "sg:orig_category":"Sports And Leisure: Hobbies: Taxidermists",
    "sg:phone":"+64 3-689 1377",
    "wof:name":"Craig Dempster Taxidermy Artist",
    "wof:placetype":"venue"
},
  "geometry": {"coordinates":[171.042496,-44.733086],"type":"Point"}
}