{
  "type": "Feature",
  "properties": {
    "iso:country":"NZ",
    "sg:address":"PO Box 26286 Epsom ",
    "sg:city":"Auckland",
    "sg:classifiers":[
        {
            "category":"Shopping",
            "subcategory":"Beauty & Cosmetics",
            "type":"Retail Goods"
        }
    ],
    "sg:phone":"+64 9-634 7492",
    "sg:province":"Auckland",
    "sg:tags":[
        "health",
        "perfumery"
    ],
    "wof:name":"Ascal Laboratories NZ Ltd",
    "wof:placetype":"venue"
},
  "geometry": {"coordinates":[174.77356,-36.876179],"type":"Point"}
}