{
  "type": "Feature",
  "properties": {
    "iso:country":"NZ",
    "sg:address":"7 Rust Ave ",
    "sg:city":"Whangarei",
    "sg:orig_category":"Shopping: Retail Stores: Books",
    "sg:phone":"+64 9-430 4206",
    "sg:province":"Northland",
    "wof:name":"Library Public",
    "wof:placetype":"venue"
},
  "geometry": {"coordinates":[174.31869499999999,-35.724258],"type":"Point"}
}