{
  "type": "Feature",
  "properties": {
    "addr:full":"Private Bag 28900 Remuera  Auckland Auckland",
    "addr:postcode":"28900",
    "addr:street":"Bag",
    "iso:country":"NZ",
    "sg:address":"Private Bag 28900 Remuera ",
    "sg:city":"Auckland",
    "sg:classifiers":[
        {
            "category":"Shopping",
            "subcategory":"Beauty & Cosmetics",
            "type":"Retail Goods"
        }
    ],
    "sg:phone":"+64 9-630 1028",
    "sg:province":"Auckland",
    "sg:tags":[
        "equipment",
        "health",
        "therapy",
        "products"
    ],
    "wof:name":"Niagara Therapy NZ Ltd",
    "wof:placetype":"venue"
},
  "geometry": {"coordinates":[174.77041600000001,-36.884109],"type":"Point"}
}