{
  "type": "Feature",
  "properties": {
    "addr:full":"254 Church St Palmerston  Palmerston North Manawatu-Wanganui",
    "addr:housenumber":"254",
    "addr:street":"Church St",
    "iso:country":"NZ",
    "sg:address":"254 Church St Palmerston ",
    "sg:city":"Palmerston North",
    "sg:orig_category":"Health And Beauty: Dental: Dentists",
    "sg:phone":"+64 6-358 3988",
    "sg:province":"Manawatu-Wanganui",
    "wof:name":"Wilson Bruce R",
    "wof:placetype":"venue"
},
  "geometry": {"coordinates":[175.605469,-40.360355],"type":"Point"}
}