{
  "type": "Feature",
  "properties": {
    "iso:country":"NZ",
    "sg:address":"PO Box 3511 ",
    "sg:city":"Richmond",
    "sg:classifiers":[
        {
            "category":"Building & Trades",
            "subcategory":"Pest Control",
            "type":"Services"
        }
    ],
    "sg:phone":"+64 800 107 101",
    "sg:province":"Nelson",
    "sg:tags":[
        "home",
        "garden"
    ],
    "wof:name":"West Coast Pest Control Service & Hygiene Services",
    "wof:placetype":"venue"
},
  "geometry": {"coordinates":[-77.430267,37.560001],"type":"Point"}
}