{
  "type": "Feature",
  "properties": {
    "iso:country":"NZ",
    "sg:address":"Cnr Spey & Deveron Sts ",
    "sg:city":"Invercargill",
    "sg:classifiers":[
        {
            "category":"Banks & Credit Unions",
            "subcategory":"Investment Brokerage",
            "type":"Services"
        }
    ],
    "sg:phone":"+64 3-211 0103",
    "sg:province":"Southland",
    "sg:tags":[
        "personal",
        "accountant",
        "chartered",
        "-",
        "finance"
    ],
    "wof:name":"Ward Wilson Ltd",
    "wof:placetype":"venue"
},
  "geometry": {"coordinates":[168.352173,-46.41185],"type":"Point"}
}