{
  "type": "Feature",
  "properties": {
    "iso:country":"NZ",
    "sg:address":"Halbert Rd Makaraka ",
    "sg:city":"Gisborne",
    "sg:orig_category":"Farming: Services: Irrigation",
    "sg:phone":"+64 6-867 9379",
    "sg:province":"Gisborne",
    "wof:name":"Fruitfed Supplies",
    "wof:placetype":"venue"
},
  "geometry": {"coordinates":[177.96994000000001,-38.648338],"type":"Point"}
}