{
  "type": "Feature",
  "properties": {
    "iso:country":"NZ",
    "sg:address":"177 Haven Rd Port Nelson ",
    "sg:city":"Nelson",
    "sg:classifiers":[
        {
            "category":"Autos & Motor Vehicles",
            "subcategory":"Automobile Sales",
            "type":"Retail Goods"
        }
    ],
    "sg:phone":"+64 3-548 2734",
    "sg:province":"Nelson",
    "sg:tags":[
        "car",
        "-used",
        "leasing",
        "truck",
        "automotive"
    ],
    "wof:name":"Graham Jones Cars",
    "wof:placetype":"venue"
},
  "geometry": {"coordinates":[173.27462800000001,-41.266109],"type":"Point"}
}