{
  "type": "Feature",
  "properties": {
    "addr:full":"Churchill Shopping Centre Crofton Downs  Wellington Wellington",
    "iso:country":"NZ",
    "sg:address":"Churchill Shopping Centre Crofton Downs ",
    "sg:city":"Wellington",
    "sg:orig_category":"Shopping: Retail Stores: Toys",
    "sg:phone":"+64 4-939 8855",
    "sg:province":"Wellington",
    "wof:name":"Merry-Go-Round",
    "wof:placetype":"venue"
},
  "geometry": {"coordinates":[174.76242099999999,-41.255161],"type":"Point"}
}