{
  "type": "Feature",
  "properties": {
    "addr:full":"183 Lower Dent St  Whangarei Northland",
    "addr:housenumber":"183",
    "addr:street":"Lower Dent St",
    "iso:country":"NZ",
    "sg:address":"183 Lower Dent St ",
    "sg:city":"Whangarei",
    "sg:classifiers":[
        {
            "category":"Home & Garden",
            "subcategory":"Home Furnishings",
            "type":"Retail Goods"
        }
    ],
    "sg:phone":"+64 9-430 0130",
    "sg:province":"Northland",
    "sg:tags":[
        "furniture/furnishings",
        "bedding",
        "bed"
    ],
    "wof:name":"Bedz Direct",
    "wof:placetype":"venue"
},
  "geometry": {"coordinates":[174.33073400000001,-35.728024],"type":"Point"}
}