{
  "type": "Feature",
  "properties": {
    "addr:full":"65 Stout St  Gisborne Gisborne",
    "addr:housenumber":"65",
    "addr:street":"Stout St",
    "iso:country":"NZ",
    "sg:address":"65 Stout St ",
    "sg:city":"Gisborne",
    "sg:orig_category":"Health And Beauty: Beauty: Hairdressers",
    "sg:phone":"+64 6-863 2211",
    "sg:province":"Gisborne",
    "wof:name":"Melissa Gaukrodger",
    "wof:placetype":"venue"
},
  "geometry": {"coordinates":[178.02758800000001,-38.659435],"type":"Point"}
}