{
  "type": "Feature",
  "properties": {
    "addr:full":"36B Tree View Ave Glenfield  Auckland Auckland",
    "addr:housenumber":"36b",
    "addr:street":"Tree View Ave",
    "iso:country":"NZ",
    "sg:address":"36B Tree View Ave Glenfield ",
    "sg:city":"Auckland",
    "sg:classifiers":[
        {
            "category":"Recreation",
            "type":"Entertainment"
        }
    ],
    "sg:phone":"+64 9-303 0350",
    "sg:province":"Auckland",
    "sg:tags":[
        "shopping",
        "hunting",
        "fishing",
        "retailers",
        "sport",
        "trip"
    ],
    "wof:name":"Auckland & Gulf Booking Agency",
    "wof:placetype":"venue"
},
  "geometry": {"coordinates":[174.70799299999999,-36.789295],"type":"Point"}
}