{
  "type": "Feature",
  "properties": {
    "iso:country":"NZ",
    "sg:address":"32 William Pickering Dve Albany ",
    "sg:city":"Auckland",
    "sg:orig_category":"Automotive: Accessories: Motor Accessories",
    "sg:phone":"+64 9-415 1388",
    "sg:province":"Auckland",
    "wof:name":"Cardwell Racing Supplies",
    "wof:placetype":"venue"
},
  "geometry": {"coordinates":[174.69790599999999,-36.746246],"type":"Point"}
}