{
  "type": "Feature",
  "properties": {
    "iso:country":"NZ",
    "sg:address":"5 Dixon St ",
    "sg:city":"Masterton",
    "sg:classifiers":[
        {
            "category":"Landmark",
            "subcategory":"Tourist Information",
            "type":"Public Place"
        }
    ],
    "sg:phone":"+64 6-378 7373",
    "sg:province":"Wellington",
    "sg:tags":[
        "services",
        "travel",
        "tourism"
    ],
    "wof:name":"Tourism Wairarapa Visitor Information Centres",
    "wof:placetype":"venue"
},
  "geometry": {"coordinates":[175.66366600000001,-40.950127],"type":"Point"}
}