{
  "type": "Feature",
  "properties": {
    "addr:full":"cnr Lincoln & Dalefield Rds  Carterton",
    "addr:street":"Cnr Lincoln",
    "iso:country":"NZ",
    "sg:address":"cnr Lincoln & Dalefield Rds ",
    "sg:city":"Carterton",
    "sg:classifiers":[
        {
            "category":"Home & Garden",
            "subcategory":"Building Materials",
            "type":"Retail Goods"
        }
    ],
    "sg:phone":"+64 6-379 8286",
    "sg:tags":[
        "gate",
        "fitting",
        "outdoor"
    ],
    "wof:name":"Tower Gates",
    "wof:placetype":"venue"
},
  "geometry": {"coordinates":[175.49664300000001,-41.03722],"type":"Point"}
}