{
  "type": "Feature",
  "properties": {
    "addr:full":"20 Ross Pl  Lawrence",
    "addr:housenumber":"20",
    "addr:street":"Ross Pl",
    "iso:country":"NZ",
    "sg:address":"20 Ross Pl ",
    "sg:city":"Lawrence",
    "sg:orig_category":"Home And Garden: Accessories: Hardware",
    "sg:phone":"+64 3-485 9919",
    "wof:name":"Tuapeka Hardware Ltd",
    "wof:placetype":"venue"
},
  "geometry": {"coordinates":[169.687668,-45.912971],"type":"Point"}
}