{
  "type": "Feature",
  "properties": {
    "iso:country":"NZ",
    "sg:address":"cnr Gorge Rd & Commerce St ",
    "sg:city":"Whakatane",
    "sg:classifiers":[
        {
            "category":"Retail",
            "subcategory":"Auto Repair",
            "type":"Services"
        }
    ],
    "sg:phone":"+64 7-307 0705",
    "sg:province":"Bay of Plenty",
    "sg:tags":[
        "automotive",
        "electric",
        "servicing"
    ],
    "wof:name":"Gary's Auto Electrical",
    "wof:placetype":"venue"
},
  "geometry": {"coordinates":[176.984207,-37.965302],"type":"Point"}
}