{
  "type": "Feature",
  "properties": {
    "iso:country":"NZ",
    "sg:address":"9/11 Tamamutu St ",
    "sg:city":"Taupo",
    "sg:classifiers":[
        {
            "category":"Home & Garden",
            "subcategory":"Home Furnishings",
            "type":"Retail Goods"
        }
    ],
    "sg:phone":"+64 7-378 5794",
    "sg:province":"Waikato",
    "sg:tags":[
        "furniture/furnishings",
        "bedding",
        "bed"
    ],
    "wof:name":"Bedroom Warehouse The",
    "wof:placetype":"venue"
},
  "geometry": {"coordinates":[176.07081600000001,-38.685925],"type":"Point"}
}