{
  "type": "Feature",
  "properties": {
    "addr:full":"22 Porowini Ave  Whangarei Northland",
    "addr:housenumber":"22",
    "addr:street":"Porowini Ave",
    "iso:country":"NZ",
    "sg:address":"22 Porowini Ave ",
    "sg:city":"Whangarei",
    "sg:classifiers":[
        {
            "category":"Shopping",
            "subcategory":"Bicycles & Sporting Goods",
            "type":"Retail Goods"
        }
    ],
    "sg:phone":"+64 9-438 1623",
    "sg:province":"Northland",
    "sg:tags":[
        "equipment",
        "sport",
        "tramping",
        "leisure",
        "camping"
    ],
    "wof:name":"The Gas Man NZ Ltd",
    "wof:placetype":"venue"
},
  "geometry": {"coordinates":[174.31864899999999,-35.730797],"type":"Point"}
}