{
  "type": "Feature",
  "properties": {
    "iso:country":"NZ",
    "sg:address":"Don McKinnon Dve Albany ",
    "sg:city":"Auckland",
    "sg:orig_category":"Industrial: Electrical/Electronic: Electronic Components",
    "sg:phone":"+64 9-415 7410",
    "sg:province":"Auckland",
    "wof:name":"Dick Smith Electronics",
    "wof:placetype":"venue"
},
  "geometry": {"coordinates":[174.709686,-36.720142],"type":"Point"}
}