{
  "type": "Feature",
  "properties": {
    "addr:full":"66 Paora Hapi St  Taupo Waikato",
    "addr:housenumber":"66",
    "addr:street":"Paora Hapi St",
    "iso:country":"NZ",
    "sg:address":"66 Paora Hapi St ",
    "sg:city":"Taupo",
    "sg:orig_category":"Shopping: Retail Stores: Books",
    "sg:phone":"+64 7-376 0400",
    "sg:province":"Waikato",
    "sg:website":"http://www.laketauponz.com",
    "wof:name":"Destination Lake Taupo",
    "wof:placetype":"venue"
},
  "geometry": {"coordinates":[176.07547,-38.685192],"type":"Point"}
}