{
  "type": "Feature",
  "properties": {
    "iso:country":"NZ",
    "sg:address":"59 Handforth St Onerahi ",
    "sg:city":"Whangarei",
    "sg:orig_category":"Sports And Leisure: Sports: Aerial: Aero Clubs And Flying Schools",
    "sg:phone":"+64 9-436 0886",
    "sg:province":"Northland",
    "wof:name":"Tower Aviation Ltd",
    "wof:placetype":"venue"
},
  "geometry": {"coordinates":[174.36322,-35.767086],"type":"Point"}
}