{
  "type": "Feature",
  "properties": {
    "addr:full":"cnr Racecourse Rd & Martin St  Timaru Canterbury",
    "addr:street":"Cnr Racecourse Rd & Martin St",
    "iso:country":"NZ",
    "sg:address":"cnr Racecourse Rd & Martin St ",
    "sg:city":"Timaru",
    "sg:orig_category":"Farming: Machinery: Tractors",
    "sg:phone":"+64 3-688 2031",
    "sg:province":"Canterbury",
    "wof:name":"Paul Wilkins Tractors Ltd",
    "wof:placetype":"venue"
},
  "geometry": {"coordinates":[171.23739599999999,-44.395432],"type":"Point"}
}