{
  "type": "Feature",
  "properties": {
    "iso:country":"NZ",
    "sg:address":"154 Devon St W New ",
    "sg:city":"Plymouth",
    "sg:orig_category":"Shopping: Retail Stores: Secondhand Dealers",
    "sg:phone":"+64 6-757 3524",
    "sg:province":"Taranaki",
    "wof:name":"Trademark",
    "wof:placetype":"venue"
},
  "geometry": {"coordinates":[-116.819725,43.97221],"type":"Point"}
}