{
  "type": "Feature",
  "properties": {
    "addr:full":"Beach Rd  Papamoa",
    "addr:street":"Beach Rd",
    "iso:country":"NZ",
    "sg:address":"Beach Rd ",
    "sg:city":"Papamoa",
    "sg:classifiers":[
        {
            "category":"Bars & Pubs",
            "subcategory":"Wine Bar",
            "type":"Food & Drink"
        }
    ],
    "sg:phone":"+64 7-542 0737",
    "sg:tags":[
        "shop"
    ],
    "wof:name":"Papamoa Wine Cellars",
    "wof:placetype":"venue"
},
  "geometry": {"coordinates":[176.29817199999999,-37.73291],"type":"Point"}
}