{
  "type": "Feature",
  "properties": {
    "addr:full":"66 Cuba St Petone  Wellington Wellington",
    "addr:housenumber":"66",
    "addr:street":"Cuba St",
    "iso:country":"NZ",
    "sg:address":"66 Cuba St Petone ",
    "sg:city":"Wellington",
    "sg:classifiers":[
        {
            "category":"Shopping",
            "subcategory":"Pets & Pet Supplies",
            "type":"Retail Goods"
        }
    ],
    "sg:phone":"+64 4-939 8909",
    "sg:province":"Wellington",
    "sg:tags":[
        "home",
        "garden"
    ],
    "wof:name":"doG Zone Grooming Salon",
    "wof:placetype":"venue"
},
  "geometry": {"coordinates":[174.8862,-41.225098],"type":"Point"}
}