{
  "type": "Feature",
  "properties": {
    "addr:full":"4 Grants Rd Waimataitai  Timaru Canterbury",
    "addr:housenumber":"4",
    "addr:street":"Grants Rd",
    "iso:country":"NZ",
    "sg:address":"4 Grants Rd Waimataitai ",
    "sg:city":"Timaru",
    "sg:orig_category":"Industrial: Electrical/Electronic: Electronic Equipment",
    "sg:phone":"+64 3-684 7081",
    "sg:province":"Canterbury",
    "wof:name":"Samac Electronics Ltd",
    "wof:placetype":"venue"
},
  "geometry": {"coordinates":[171.24108899999999,-44.374023],"type":"Point"}
}