{
  "type": "Feature",
  "properties": {
    "iso:country":"NZ",
    "sg:address":"Katere Rd New ",
    "sg:city":"Plymouth",
    "sg:orig_category":"Farming: Supplies: Stock Foods",
    "sg:phone":"+64 6-758 6189",
    "sg:province":"Taranaki",
    "wof:name":"PCL Feeds",
    "wof:placetype":"venue"
},
  "geometry": {"coordinates":[-116.819725,43.97221],"type":"Point"}
}