{
  "type": "Feature",
  "properties": {
    "iso:country":"NZ",
    "sg:address":"214 Queen St Auckland Central ",
    "sg:city":"Auckland",
    "sg:orig_category":"Health And Beauty: Specialists: Chiropractors",
    "sg:phone":"+64 9-377 7795",
    "sg:province":"Auckland",
    "wof:name":"City Chiropractic",
    "wof:placetype":"venue"
},
  "geometry": {"coordinates":[174.900284,-37.212238],"type":"Point"}
}