{
  "type": "Feature",
  "properties": {
    "addr:full":"61 Wanganui Ave Herne Bay  Auckland Auckland",
    "addr:housenumber":"61",
    "addr:street":"Wanganui Ave",
    "iso:country":"NZ",
    "sg:address":"61 Wanganui Ave Herne Bay ",
    "sg:city":"Auckland",
    "sg:classifiers":[
        {
            "category":"Health Services",
            "subcategory":"Medical Lab",
            "type":"Services"
        }
    ],
    "sg:phone":"+64 9-360 1730",
    "sg:province":"Auckland",
    "sg:tags":[
        "services",
        "technique",
        "beauty",
        "alexander"
    ],
    "wof:name":"Peter Grunwald & Associates",
    "wof:placetype":"venue"
},
  "geometry": {"coordinates":[174.732178,-36.843193],"type":"Point"}
}