{
  "type": "Feature",
  "properties": {
    "addr:full":"Unit 3/ 90 Elizabeth Knox Pl Glen Innes  Auckland Auckland",
    "addr:housenumber":"unit 3 / 90",
    "addr:street":"Knox Pl",
    "iso:country":"NZ",
    "sg:address":"Unit 3/ 90 Elizabeth Knox Pl Glen Innes ",
    "sg:city":"Auckland",
    "sg:orig_category":"Home And Garden: Furniture/Furnishings: Cabinetmakers",
    "sg:phone":"+64 9-570 6433",
    "sg:province":"Auckland",
    "wof:name":"Ace Kitchens & Cabinets Ltd",
    "wof:placetype":"venue"
},
  "geometry": {"coordinates":[174.86842300000001,-36.873055],"type":"Point"}
}