{
  "type": "Feature",
  "properties": {
    "addr:full":"19 State Highway 1  Waiouru",
    "addr:housenumber":"19",
    "addr:street":"State Highway 1 Waiouru",
    "iso:country":"NZ",
    "sg:address":"19 State Highway 1 ",
    "sg:city":"Waiouru",
    "sg:orig_category":"Automotive: General Services: Service Stations",
    "sg:phone":"+64 6-387 6301",
    "wof:name":"BP Waiouru",
    "wof:placetype":"venue"
},
  "geometry": {"coordinates":[175.69534300000001,-39.554165],"type":"Point"}
}