{
  "type": "Feature",
  "properties": {
    "addr:full":"13 Cameron St  Methven",
    "addr:housenumber":"13",
    "addr:street":"Cameron St",
    "iso:country":"NZ",
    "sg:address":"13 Cameron St ",
    "sg:city":"Methven",
    "sg:classifiers":[
        {
            "category":"Recreation",
            "type":"Entertainment"
        }
    ],
    "sg:phone":"+64 3-302 8448",
    "sg:tags":[
        "shopping",
        "hunting",
        "fishing",
        "retailers",
        "sport",
        "trip"
    ],
    "wof:name":"Mainland Fishing",
    "wof:placetype":"venue"
},
  "geometry": {"coordinates":[171.64245600000001,-43.634644],"type":"Point"}
}