{
  "type": "Feature",
  "properties": {
    "addr:full":"289 B Highgate Roslyn  Dunedin Waikato",
    "addr:housenumber":"289 b",
    "addr:street":"Highgate",
    "iso:country":"NZ",
    "sg:address":"289 B Highgate Roslyn ",
    "sg:city":"Dunedin",
    "sg:orig_category":"Shopping: Retail Stores: Toys",
    "sg:phone":"+64 3-477 9794",
    "sg:province":"Waikato",
    "wof:name":"Roslyn Book & Toy Centre & Modellers' Attic",
    "wof:placetype":"venue"
},
  "geometry": {"coordinates":[170.48997499999999,-45.867161],"type":"Point"}
}