{
  "type": "Feature",
  "properties": {
    "iso:country":"NZ",
    "sg:address":"10 Udy Pl Te Rapa ",
    "sg:city":"Hamilton",
    "sg:classifiers":[
        {
            "category":"Parking",
            "subcategory":"Lot",
            "type":"Transportation"
        }
    ],
    "sg:phone":"+64 7-850 5512",
    "sg:province":"Waikato",
    "sg:tags":[
        "life",
        "jacket",
        "products",
        "transport",
        "raft",
        "marine",
        "boat"
    ],
    "sg:website":"http://www.yellowpages.co.nz/pages/102894335/dp48263.html",
    "wof:name":"Andrew Fink Marine",
    "wof:placetype":"venue"
},
  "geometry": {"coordinates":[175.224121,-37.740208],"type":"Point"}
}