{
  "type": "Feature",
  "properties": {
    "iso:country":"NZ",
    "sg:address":"PO Box 15-799 New Lynn ",
    "sg:city":"Auckland",
    "sg:orig_category":"Shopping: Dispensing: Vending Machines",
    "sg:phone":"+64 9-826 0160",
    "sg:province":"Auckland",
    "wof:name":"Self Service Systems NZ Ltd",
    "wof:placetype":"venue"
},
  "geometry": {"coordinates":[174.68309,-36.920143],"type":"Point"}
}