{
  "type": "Feature",
  "properties": {
    "addr:full":"16 Cathro Rd  Wanganui Manawatu-Wanganui",
    "addr:housenumber":"16",
    "addr:street":"Cathro Rd",
    "iso:country":"NZ",
    "sg:address":"16 Cathro Rd ",
    "sg:city":"Wanganui",
    "sg:classifiers":[
        {
            "category":"Home & Garden",
            "subcategory":"Building Materials",
            "type":"Retail Goods"
        }
    ],
    "sg:phone":"+64 25499749",
    "sg:province":"Manawatu-Wanganui",
    "sg:tags":[
        "builder",
        "related"
    ],
    "wof:name":"Walker Philip & Susan",
    "wof:placetype":"venue"
},
  "geometry": {"coordinates":[175.017349,-39.920628],"type":"Point"}
}