{
  "type": "Feature",
  "properties": {
    "addr:full":"402 Remuera Rd Remuera  Auckland Auckland",
    "addr:housenumber":"402",
    "addr:street":"Remuera Rd",
    "iso:country":"NZ",
    "sg:address":"402 Remuera Rd Remuera ",
    "sg:city":"Auckland",
    "sg:orig_category":"Shopping: Accessories: Lingerie - Retail",
    "sg:phone":"+64 9-524 4144",
    "sg:province":"Auckland",
    "wof:name":"Bennett & Bain Lingerie Shops",
    "wof:placetype":"venue"
},
  "geometry": {"coordinates":[174.799026,-36.880684],"type":"Point"}
}