{
  "type": "Feature",
  "properties": {
    "iso:country":"NZ",
    "sg:address":"320 Ti Rakau Dve East Tamaki ",
    "sg:city":"Auckland",
    "sg:orig_category":"Transport: Distribution - General: Warehousing/Distribution",
    "sg:phone":"+64 9-274 8034",
    "sg:province":"Auckland",
    "wof:name":"Tasman Logistics Ltd",
    "wof:placetype":"venue"
},
  "geometry": {"coordinates":[174.89883399999999,-36.927032],"type":"Point"}
}