{
  "type": "Feature",
  "properties": {
    "iso:country":"NZ",
    "sg:address":"50 Bracken Rd Newlands ",
    "sg:city":"Wellington",
    "sg:orig_category":"Sports And Leisure: General: Clubs",
    "sg:phone":"+64 4-477 4487",
    "sg:province":"Wellington",
    "wof:name":"Northern Squash Club",
    "wof:placetype":"venue"
},
  "geometry": {"coordinates":[174.823334,-41.221859],"type":"Point"}
}