{
  "type": "Feature",
  "properties": {
    "addr:full":"1 Chorley Ave Massey  Auckland Auckland",
    "addr:housenumber":"1",
    "addr:street":"Chorley Ave",
    "iso:country":"NZ",
    "sg:address":"1 Chorley Ave Massey ",
    "sg:city":"Auckland",
    "sg:orig_category":"Shopping: Accessories: Hats And Caps",
    "sg:phone":"+64 9-833 7526",
    "sg:province":"Auckland",
    "wof:name":"Carey Agencies Ltd",
    "wof:placetype":"venue"
},
  "geometry": {"coordinates":[174.62132299999999,-36.847496],"type":"Point"}
}