{
  "type": "Feature",
  "properties": {
    "addr:full":"1/4 Atlas Pl Mairangi Bay  Auckland Auckland",
    "addr:housenumber":"1 / 4",
    "addr:street":"Atlas Pl",
    "iso:country":"NZ",
    "sg:address":"1/4 Atlas Pl Mairangi Bay ",
    "sg:city":"Auckland",
    "sg:classifiers":[
        {
            "category":"Home & Garden",
            "subcategory":"Garden Supply",
            "type":"Retail Goods"
        }
    ],
    "sg:phone":"+64 9-479 8442",
    "sg:province":"Auckland",
    "sg:tags":[
        "products",
        "lawn",
        "gardening",
        "turf"
    ],
    "wof:name":"Sports Turf Renovators",
    "wof:placetype":"venue"
},
  "geometry": {"coordinates":[174.74816899999999,-36.738461],"type":"Point"}
}