{
  "type": "Feature",
  "properties": {
    "addr:full":"37 Broadway  Reefton Manawatu-Wanganui",
    "addr:housenumber":"37",
    "addr:street":"Broadway",
    "iso:country":"NZ",
    "sg:address":"37 Broadway ",
    "sg:city":"Reefton",
    "sg:orig_category":"Home And Garden: Accessories: Hardware",
    "sg:phone":"+64 3-732 8407",
    "sg:province":"Manawatu-Wanganui",
    "wof:name":"Reefton Hammer Hardware",
    "wof:placetype":"venue"
},
  "geometry": {"coordinates":[171.86291499999999,-42.119503],"type":"Point"}
}