{
  "type": "Feature",
  "properties": {
    "addr:full":"Drury Hills Rd Drury  Auckland Auckland",
    "addr:street":"Hills Rd",
    "iso:country":"NZ",
    "sg:address":"Drury Hills Rd Drury ",
    "sg:city":"Auckland",
    "sg:classifiers":[
        {
            "category":"Home & Garden",
            "subcategory":"Building Materials",
            "type":"Retail Goods"
        }
    ],
    "sg:phone":"+64 9-294 8366",
    "sg:province":"Auckland",
    "sg:tags":[
        "gate",
        "fitting",
        "outdoor"
    ],
    "wof:name":"JB & JF Hansen",
    "wof:placetype":"venue"
},
  "geometry": {"coordinates":[174.97747799999999,-37.102848],"type":"Point"}
}