{
  "type": "Feature",
  "properties": {
    "addr:full":"19 Mt Eden Rd Mt Eden  Auckland Auckland",
    "addr:housenumber":"19",
    "addr:street":"Mt Eden Rd",
    "iso:country":"NZ",
    "sg:address":"19 Mt Eden Rd Mt Eden ",
    "sg:city":"Auckland",
    "sg:classifiers":[
        {
            "category":"Food Court",
            "type":"Food & Drink"
        }
    ],
    "sg:phone":"+64 9-377 1544",
    "sg:province":"Auckland",
    "sg:tags":[
        "brew",
        "home",
        "supply"
    ],
    "wof:name":"Brewers World Mt Eden & Papakura",
    "wof:placetype":"venue"
},
  "geometry": {"coordinates":[174.76205400000001,-36.882732],"type":"Point"}
}