{
  "type": "Feature",
  "properties": {
    "iso:country":"NZ",
    "sg:address":"589 H Tremaine Ave Palmerston ",
    "sg:city":"Palmerston North",
    "sg:orig_category":"Industrial: Engineering: Engineers: Engineers Supplies",
    "sg:phone":"+64 6-358 9957",
    "sg:province":"Manawatu-Wanganui",
    "wof:name":"Trade Tools Ltd",
    "wof:placetype":"venue"
},
  "geometry": {"coordinates":[175.603836,-40.34219],"type":"Point"}
}