{
  "type": "Feature",
  "properties": {
    "iso:country":"NZ",
    "sg:address":"11 Rangitoto Rd Papatoetoe ",
    "sg:city":"Auckland",
    "sg:classifiers":[
        {
            "category":"Professional",
            "type":"Services"
        }
    ],
    "sg:phone":"+64 9-271 1544",
    "sg:province":"Auckland",
    "sg:tags":[
        "home",
        "cleaning",
        "help",
        "garden"
    ],
    "wof:name":"Whaiora Homecare Services",
    "wof:placetype":"venue"
},
  "geometry": {"coordinates":[174.852432,-36.978405],"type":"Point"}
}