{
  "type": "Feature",
  "properties": {
    "addr:full":"12-14 Pollen St Grey Lynn  Auckland Auckland",
    "addr:housenumber":"12-14",
    "addr:street":"Pollen St",
    "iso:country":"NZ",
    "sg:address":"12-14 Pollen St Grey Lynn ",
    "sg:city":"Auckland",
    "sg:classifiers":[
        {
            "category":"Banks & Credit Unions",
            "subcategory":"Investment Brokerage",
            "type":"Services"
        }
    ],
    "sg:phone":"+64 9-376 0088",
    "sg:province":"Auckland",
    "sg:tags":[
        "director",
        "funeral",
        "arrangements"
    ],
    "wof:name":"J Weir Funeral Services",
    "wof:placetype":"venue"
},
  "geometry": {"coordinates":[174.75006099999999,-36.860683],"type":"Point"}
}