{
  "type": "Feature",
  "properties": {
    "addr:full":"Unit 2 171 Ponsonby Rd Ponsonby  Auckland Auckland",
    "addr:housenumber":"unit 2",
    "addr:postcode":"171",
    "addr:street":"Ponsonby Rd",
    "iso:country":"NZ",
    "sg:address":"Unit 2 171 Ponsonby Rd Ponsonby ",
    "sg:city":"Auckland",
    "sg:orig_category":"Transport: Boats And Marine: Shipping: Ship Brokers",
    "sg:phone":"+64 9-378 1538",
    "sg:province":"Auckland",
    "wof:name":"Horizon Shipbrokers Limited",
    "wof:placetype":"venue"
},
  "geometry": {"coordinates":[174.74588,-36.854046],"type":"Point"}
}