{
  "type": "Feature",
  "properties": {
    "addr:full":"1234 Main Highway Otaki  Manakau Wellington",
    "addr:housenumber":"1234",
    "addr:street":"Main Highway",
    "iso:country":"NZ",
    "sg:address":"1234 Main Highway Otaki ",
    "sg:city":"Manakau",
    "sg:orig_category":"Farming: Horticulture",
    "sg:phone":"+64 6-362 6870",
    "sg:province":"Wellington",
    "wof:name":"Geerling Cut Flowers Ltd",
    "wof:placetype":"venue"
},
  "geometry": {"coordinates":[175.21729999999999,-40.71666],"type":"Point"}
}