{
  "type": "Feature",
  "properties": {
    "iso:country":"NZ",
    "sg:address":"PO Box 78 279 Grey Lynn ",
    "sg:city":"Auckland",
    "sg:classifiers":[
        {
            "category":"Personal",
            "type":"Services"
        }
    ],
    "sg:phone":"+64 9-377 5525",
    "sg:province":"Auckland",
    "sg:tags":[
        "diet",
        "reduction",
        "health",
        "beauty",
        "weight"
    ],
    "wof:name":"B-Med Weight Control",
    "wof:placetype":"venue"
},
  "geometry": {"coordinates":[174.73474100000001,-36.861408],"type":"Point"}
}