{
  "type": "Feature",
  "properties": {
    "addr:full":"5 St Marks Rd Remuera  Auckland Auckland",
    "addr:housenumber":"5",
    "addr:street":"St Marks Rd",
    "iso:country":"NZ",
    "sg:address":"5 St Marks Rd Remuera ",
    "sg:city":"Auckland",
    "sg:orig_category":"Health And Beauty: Dental: Dentists",
    "sg:phone":"+64 9-529 7949",
    "sg:province":"Auckland",
    "wof:name":"Periodontists Association Of",
    "wof:placetype":"venue"
},
  "geometry": {"coordinates":[174.78068500000001,-36.873478],"type":"Point"}
}