{
  "type": "Feature",
  "properties": {
    "addr:full":"192 Russell St  Gisborne Gisborne",
    "addr:housenumber":"192",
    "addr:street":"Russell St",
    "iso:country":"NZ",
    "sg:address":"192 Russell St ",
    "sg:city":"Gisborne",
    "sg:classifiers":[
        {
            "category":"Home & Garden",
            "subcategory":"Building Materials",
            "type":"Retail Goods"
        }
    ],
    "sg:phone":"+64 25455777",
    "sg:province":"Gisborne",
    "sg:tags":[
        "electrician",
        "related"
    ],
    "wof:name":"McFadyen Electrical (Peter)",
    "wof:placetype":"venue"
},
  "geometry": {"coordinates":[178.02766399999999,-38.650917],"type":"Point"}
}