{
  "type": "Feature",
  "properties": {
    "iso:country":"NZ",
    "sg:address":"132 North St ",
    "sg:city":"Feilding",
    "sg:classifiers":[
        {
            "category":"Social Services",
            "subcategory":"Child Care",
            "type":"Services"
        }
    ],
    "sg:phone":"+64 6-323 9024",
    "sg:province":"Manawatu-Wanganui",
    "sg:tags":[
        "home",
        "garden",
        "children"
    ],
    "wof:name":"Gail's Child Care Centre",
    "wof:placetype":"venue"
},
  "geometry": {"coordinates":[175.57600400000001,-40.215729],"type":"Point"}
}