{
  "type": "Feature",
  "properties": {
    "addr:full":"458 Ashworths Rd Leithfield  Amberley Canterbury",
    "addr:housenumber":"458",
    "addr:street":"Ashworths Rd;Amberley",
    "iso:country":"NZ",
    "sg:address":"458 Ashworths Rd Leithfield ",
    "sg:city":"Amberley",
    "sg:classifiers":[
        {
            "category":"Bars & Pubs",
            "subcategory":"Wine Bar",
            "type":"Food & Drink"
        }
    ],
    "sg:phone":"+64 3-314 8867",
    "sg:province":"Canterbury",
    "sg:tags":[
        "shop"
    ],
    "wof:name":"Pukeko Junction Regional Wine Centre & Gallery",
    "wof:placetype":"venue"
},
  "geometry": {"coordinates":[172.73951700000001,-43.192371],"type":"Point"}
}