{
  "type": "Feature",
  "properties": {
    "iso:country":"NZ",
    "sg:address":"Main Rd ",
    "sg:city":"Tapanui",
    "sg:orig_category":"Farming: Services: Veterinarians",
    "sg:phone":"+64 3-204 8233",
    "wof:name":"West Otago Vets",
    "wof:placetype":"venue"
},
  "geometry": {"coordinates":[169.261688,-45.946629],"type":"Point"}
}