{
  "type": "Feature",
  "properties": {
    "iso:country":"NZ",
    "sg:address":"13 Berg Pl ",
    "sg:city":"Whakatane",
    "sg:orig_category":"Storage: Storage",
    "sg:phone":"+64 7-308 0127",
    "sg:province":"Bay of Plenty",
    "wof:name":"Valley Rd Rent-A-Shed",
    "wof:placetype":"venue"
},
  "geometry": {"coordinates":[176.996979,-37.958069],"type":"Point"}
}