{
  "type": "Feature",
  "properties": {
    "addr:full":"28 Edward St  Rangiora Canterbury",
    "addr:housenumber":"28",
    "addr:street":"Edward St",
    "iso:country":"NZ",
    "sg:address":"28 Edward St ",
    "sg:city":"Rangiora",
    "sg:classifiers":[
        {
            "category":"Shopping",
            "subcategory":"Crafts & Fabrics",
            "type":"Retail Goods"
        }
    ],
    "sg:phone":"+64 3-313 4752",
    "sg:province":"Canterbury",
    "sg:tags":[
        "clothing"
    ],
    "wof:name":"Roberts Wools Ltd",
    "wof:placetype":"venue"
},
  "geometry": {"coordinates":[172.596451,-43.298489],"type":"Point"}
}