{
  "type": "Feature",
  "properties": {
    "iso:country":"NZ",
    "sg:address":"Leader Rd ",
    "sg:city":"Whakatane",
    "sg:orig_category":"Health And Beauty: Specialists: Midwives",
    "sg:phone":"+64 7-307 0017",
    "sg:province":"Bay of Plenty",
    "wof:name":"Norris Margaret",
    "wof:placetype":"venue"
},
  "geometry": {"coordinates":[176.984192,-37.965305],"type":"Point"}
}