{
  "type": "Feature",
  "properties": {
    "addr:full":"Main South Rd  Balclutha",
    "addr:street":"Main South Rd",
    "iso:country":"NZ",
    "sg:address":"Main South Rd ",
    "sg:city":"Balclutha",
    "sg:classifiers":[
        {
            "category":"Shopping",
            "subcategory":"Gifts & Souvenirs",
            "type":"Retail Goods"
        }
    ],
    "sg:phone":"+64 3-418 2345",
    "sg:tags":[
        "travel",
        "tourism"
    ],
    "wof:name":"Peggydale",
    "wof:placetype":"venue"
},
  "geometry": {"coordinates":[169.74681100000001,-46.234802],"type":"Point"}
}