{
  "type": "Feature",
  "properties": {
    "addr:full":"20 A Burwood Rd Burwood  Christchurch Canterbury",
    "addr:housenumber":"20 a",
    "addr:street":"Burwood Rd",
    "iso:country":"NZ",
    "sg:address":"20 A Burwood Rd Burwood ",
    "sg:city":"Christchurch",
    "sg:orig_category":"Industrial: Instruments",
    "sg:phone":"+64 3-383 3013",
    "sg:province":"Canterbury",
    "wof:name":"Dynamic Balancing",
    "wof:placetype":"venue"
},
  "geometry": {"coordinates":[172.683212,-43.49828],"type":"Point"}
}