{
  "type": "Feature",
  "properties": {
    "addr:full":"92 Queen St Auckland Central  Auckland Auckland",
    "addr:housenumber":"92",
    "addr:street":"Queen St",
    "iso:country":"NZ",
    "sg:address":"92 Queen St Auckland Central ",
    "sg:city":"Auckland",
    "sg:classifiers":[
        {
            "category":"Shopping",
            "subcategory":"Gifts & Souvenirs",
            "type":"Retail Goods"
        }
    ],
    "sg:phone":"+64 9-373 5588",
    "sg:province":"Auckland",
    "sg:tags":[
        "travel",
        "tourism"
    ],
    "wof:name":"Kiwi Town Souvenirs",
    "wof:placetype":"venue"
},
  "geometry": {"coordinates":[174.76617400000001,-36.846554],"type":"Point"}
}