{
  "type": "Feature",
  "properties": {
    "iso:country":"NZ",
    "sg:address":"All ",
    "sg:city":"Enquiries",
    "sg:orig_category":"Transport: Transportation: Air Freight",
    "sg:phone":"+64 800 800 020",
    "wof:name":"DHL Worldwide Express",
    "wof:placetype":"venue"
},
  "geometry": {"coordinates":[-93.035797,37.180599],"type":"Point"}
}