{
  "type": "Feature",
  "properties": {
    "iso:country":"NZ",
    "sg:address":"10 Ryan Pl Manukau ",
    "sg:city":"Auckland",
    "sg:classifiers":[
        {
            "category":"Shopping",
            "subcategory":"Crafts & Fabrics",
            "type":"Retail Goods"
        }
    ],
    "sg:phone":"+64 9-263 4566",
    "sg:province":"Auckland",
    "sg:tags":[
        "-",
        "protective",
        "clothing"
    ],
    "wof:name":"Jaedon Enterprises Ltd",
    "wof:placetype":"venue"
},
  "geometry": {"coordinates":[-119.104576,36.597755],"type":"Point"}
}