{
  "type": "Feature",
  "properties": {
    "iso:country":"NZ",
    "sg:address":"85 Main Rd Pleasant Point ",
    "sg:city":"Timaru",
    "sg:orig_category":"Sports And Leisure: Hobbies: Taxidermists",
    "sg:phone":"+64 3-614 7737",
    "sg:province":"Canterbury",
    "wof:name":"G D O'Rourke & Sons Ltd",
    "wof:placetype":"venue"
},
  "geometry": {"coordinates":[-80.307701,40.29929],"type":"Point"}
}