{
  "type": "Feature",
  "properties": {
    "addr:full":"42 Gloucester St Taradale  Napier Hawke's Bay",
    "addr:housenumber":"42",
    "addr:street":"Gloucester St",
    "iso:country":"NZ",
    "sg:address":"42 Gloucester St Taradale ",
    "sg:city":"Napier",
    "sg:orig_category":"Health And Beauty: Beauty: Hairdressers",
    "sg:phone":"+64 6-845 0580",
    "sg:province":"Hawke's Bay",
    "wof:name":"Tee Cee Top Cuts",
    "wof:placetype":"venue"
},
  "geometry": {"coordinates":[176.857956,-39.528389],"type":"Point"}
}