{
  "type": "Feature",
  "properties": {
    "iso:country":"NZ",
    "sg:address":"64 A Victoria St ",
    "sg:city":"Cambridge",
    "sg:classifiers":[
        {
            "category":"Sports & Exercise",
            "subcategory":"Ski Resort",
            "type":"Entertainment"
        }
    ],
    "sg:phone":"+64 7-827 5928",
    "sg:province":"Waikato",
    "sg:tags":[
        "hobbies",
        "photographic",
        "leisure",
        "developing"
    ],
    "wof:name":"Photoworld",
    "wof:placetype":"venue"
},
  "geometry": {"coordinates":[-116.676048,44.572186],"type":"Point"}
}