{
  "type": "Feature",
  "properties": {
    "iso:country":"NZ",
    "sg:address":"419 Great King St PO Box 6202 ",
    "sg:city":"Dunedin",
    "sg:classifiers":[
        {
            "category":"Sports & Exercise",
            "subcategory":"Skate Park",
            "type":"Entertainment"
        }
    ],
    "sg:phone":"+64 3-474 7474",
    "sg:province":"Otago",
    "sg:tags":[
        "arts",
        "museum",
        "leisure",
        "gallery"
    ],
    "wof:name":"Otago Museum",
    "wof:placetype":"venue"
},
  "geometry": {"coordinates":[-82.784721,28.013355],"type":"Point"}
}