{
  "type": "Feature",
  "properties": {
    "iso:country":"NZ",
    "sg:address":"19-21 Stevens St Waltham ",
    "sg:city":"Christchurch",
    "sg:classifiers":[
        {
            "category":"Manufacturing",
            "subcategory":"Rubber & Plastics",
            "type":"Manufacturing & Wholesale Goods"
        }
    ],
    "sg:phone":"+64 3-365 3529",
    "sg:province":"Canterbury",
    "sg:tags":[
        "industrial",
        "-",
        "foam",
        "goods"
    ],
    "wof:name":"Mainland Foams Ltd",
    "wof:placetype":"venue"
},
  "geometry": {"coordinates":[172.651901,-43.54084],"type":"Point"}
}