{
  "type": "Feature",
  "properties": {
    "addr:full":"NorthCity Mega Centre Semple St  Porirua Wellington",
    "addr:street":"Semple St",
    "iso:country":"NZ",
    "sg:address":"NorthCity Mega Centre Semple St ",
    "sg:city":"Porirua",
    "sg:orig_category":"Home And Garden: Accessories: Linen",
    "sg:phone":"+64 4-238 9103",
    "sg:province":"Wellington",
    "wof:name":"Arbuckles",
    "wof:placetype":"venue"
},
  "geometry": {"coordinates":[174.85223400000001,-41.138294],"type":"Point"}
}