{
  "type": "Feature",
  "properties": {
    "addr:full":"149 Hillside Rd South Dunedin  Dunedin Otago",
    "addr:housenumber":"149",
    "addr:street":"Hillside Rd",
    "iso:country":"NZ",
    "sg:address":"149 Hillside Rd South Dunedin ",
    "sg:city":"Dunedin",
    "sg:orig_category":"Transport: Land: Taxis",
    "sg:phone":"+64 3-455 5282",
    "sg:province":"Otago",
    "wof:name":"United Taxis",
    "wof:placetype":"venue"
},
  "geometry": {"coordinates":[170.498062,-45.893517],"type":"Point"}
}