{
  "type": "Feature",
  "properties": {
    "iso:country":"NZ",
    "sg:address":"Te Awanga ",
    "sg:city":"Napier",
    "sg:classifiers":[
        {
            "category":"Personal",
            "type":"Services"
        }
    ],
    "sg:phone":"+64 6-875 1447",
    "sg:province":"Hawke's Bay",
    "sg:tags":[
        "celebrant",
        "arrangements",
        "marriage",
        "wedding"
    ],
    "wof:name":"Charters Helen",
    "wof:placetype":"venue"
},
  "geometry": {"coordinates":[176.980515,-39.632919],"type":"Point"}
}