{
  "type": "Feature",
  "properties": {
    "iso:country":"NZ",
    "sg:address":"Kepa Rd Ruakaka ",
    "sg:city":"Whangarei",
    "sg:orig_category":"Shopping: Sports Retailers: Water Sports",
    "sg:phone":"+64 9-432 8110",
    "sg:province":"Northland",
    "wof:name":"Surfline Surfboards",
    "wof:placetype":"venue"
},
  "geometry": {"coordinates":[174.461365,-35.873512],"type":"Point"}
}