{
  "type": "Feature",
  "properties": {
    "iso:country":"NZ",
    "sg:address":"246 Coutts St Kilbirnie ",
    "sg:city":"Wellington",
    "sg:orig_category":"Sports And Leisure: Sports: Aerial",
    "sg:phone":"+64 4-388 8444",
    "sg:province":"Wellington",
    "wof:name":"Wellington Aero Club",
    "wof:placetype":"venue"
},
  "geometry": {"coordinates":[174.801056,-41.321198],"type":"Point"}
}