{
  "type": "Feature",
  "properties": {
    "addr:full":"Cnr Maleme St & Cameron Rd  Tauranga Bay of Plenty",
    "addr:street":"Cnr Maleme St & Cameron Rd",
    "iso:country":"NZ",
    "sg:address":"Cnr Maleme St & Cameron Rd ",
    "sg:city":"Tauranga",
    "sg:classifiers":[
        {
            "category":"Education",
            "subcategory":"Special Training",
            "type":"Public Place"
        }
    ],
    "sg:phone":"+64 7-541 1773",
    "sg:province":"Bay of Plenty",
    "sg:tags":[
        "forklift",
        "driver"
    ],
    "wof:name":"The Salvation Army Employment Plus",
    "wof:placetype":"venue"
},
  "geometry": {"coordinates":[176.14475999999999,-37.703152],"type":"Point"}
}