{
  "type": "Feature",
  "properties": {
    "addr:full":"3 Echelon Pl East Tamaki  Auckland Auckland",
    "addr:housenumber":"3",
    "addr:street":"Echelon Pl",
    "iso:country":"NZ",
    "sg:address":"3 Echelon Pl East Tamaki ",
    "sg:city":"Auckland",
    "sg:orig_category":"Automotive: Parts And Supplies: Wheels",
    "sg:phone":"+64 9-274 9181",
    "sg:province":"Auckland",
    "wof:name":"B G Marketing",
    "wof:placetype":"venue"
},
  "geometry": {"coordinates":[174.884186,-36.936405],"type":"Point"}
}