{
  "type": "Feature",
  "properties": {
    "iso:country":"NZ",
    "sg:address":"Waimate Cre ",
    "sg:city":"Tokoroa",
    "sg:classifiers":[
        {
            "category":"Home & Garden",
            "subcategory":"Carpets & Floor Coverings",
            "type":"Retail Goods"
        }
    ],
    "sg:phone":"+64 7-886 5298",
    "sg:tags":[
        "cleaning",
        "furniture"
    ],
    "wof:name":"Bob's Carpet Cleaning",
    "wof:placetype":"venue"
},
  "geometry": {"coordinates":[171.04248,-44.733082],"type":"Point"}
}