{
  "type": "Feature",
  "properties": {
    "addr:full":"State Highway 1  Omarama",
    "addr:street":"State Highway 1 Omarama",
    "iso:country":"NZ",
    "sg:address":"State Highway 1 ",
    "sg:city":"Omarama",
    "sg:orig_category":"Shopping: Retail Stores: Supermarkets",
    "sg:phone":"+64 3-438 9895",
    "wof:name":"Omarama Foodcentre",
    "wof:placetype":"venue"
},
  "geometry": {"coordinates":[169.96893299999999,-44.491158],"type":"Point"}
}