{
  "type": "Feature",
  "properties": {
    "addr:full":"Onerahi  Whangarei Northland",
    "iso:country":"NZ",
    "sg:address":"Onerahi ",
    "sg:city":"Whangarei",
    "sg:orig_category":"Sports And Leisure: Entertainment: Entertainers",
    "sg:phone":"+64 9-436 0926",
    "sg:province":"Northland",
    "wof:name":"Northland D J Services",
    "wof:placetype":"venue"
},
  "geometry": {"coordinates":[174.36286899999999,-35.765949],"type":"Point"}
}