{
  "type": "Feature",
  "properties": {
    "addr:full":"6 Panorama Pl  Whakatane Bay of Plenty",
    "addr:housenumber":"6",
    "addr:street":"Panorama Pl Whakatane Bay",
    "iso:country":"NZ",
    "sg:address":"6 Panorama Pl ",
    "sg:city":"Whakatane",
    "sg:orig_category":"Health And Beauty: Specialists: Midwives",
    "sg:phone":"+64 7-308 7228",
    "sg:province":"Bay of Plenty",
    "wof:name":"Groothoff D",
    "wof:placetype":"venue"
},
  "geometry": {"coordinates":[176.97131300000001,-37.935833],"type":"Point"}
}