{
  "type": "Feature",
  "properties": {
    "addr:full":"PO Box 275 Waiuku  Pukekohe Auckland",
    "addr:housenumber":"po",
    "addr:street":"Box 275",
    "iso:country":"NZ",
    "sg:address":"PO Box 275 Waiuku ",
    "sg:city":"Pukekohe",
    "sg:orig_category":"Farming: Forestry: Forestry Growers",
    "sg:phone":"+64 9-235 3877",
    "sg:province":"Auckland",
    "wof:name":"Forenza Ltd",
    "wof:placetype":"venue"
},
  "geometry": {"coordinates":[174.73268100000001,-37.24844],"type":"Point"}
}