{
  "type": "Feature",
  "properties": {
    "addr:full":"75 Henry Rd R D 1  Taupiri",
    "addr:housenumber":"75;1",
    "addr:street":"Henry Rd R D",
    "iso:country":"NZ",
    "sg:address":"75 Henry Rd R D 1 ",
    "sg:city":"Taupiri",
    "sg:classifiers":[
        {
            "category":"Food & Beverages",
            "subcategory":"Candy",
            "type":"Retail Goods"
        }
    ],
    "sg:phone":"+64 7-824 6818",
    "sg:tags":[
        "confectioner",
        "drink",
        "-"
    ],
    "wof:name":"Candyland",
    "wof:placetype":"venue"
},
  "geometry": {"coordinates":[175.18974299999999,-37.61385],"type":"Point"}
}