{
  "type": "Feature",
  "properties": {
    "iso:country":"NZ",
    "sg:address":"485 Papanui Rd Papanui ",
    "sg:city":"Christchurch",
    "sg:classifiers":[
        {
            "category":"Shopping",
            "subcategory":"Crafts & Fabrics",
            "type":"Retail Goods"
        }
    ],
    "sg:phone":"+64 3-352 4107",
    "sg:province":"Canterbury",
    "sg:tags":[
        "clothing",
        "maternity",
        "wear"
    ],
    "wof:name":"Pumpkin Patch Ltd",
    "wof:placetype":"venue"
},
  "geometry": {"coordinates":[172.608582,-43.497952],"type":"Point"}
}