{
  "type": "Feature",
  "properties": {
    "addr:full":"Conroys Rd Alexandra R D 1  Clyde",
    "addr:housenumber":"1",
    "addr:street":"Conroys Rd;R D",
    "iso:country":"NZ",
    "sg:address":"Conroys Rd Alexandra R D 1 ",
    "sg:city":"Clyde",
    "sg:classifiers":[
        {
            "category":"Winery",
            "type":"Food & Drink"
        }
    ],
    "sg:phone":"+64 3-449 2059",
    "sg:tags":[
        "wining",
        "vineyard",
        "dining"
    ],
    "wof:name":"Black Ridge Vineyard",
    "wof:placetype":"venue"
},
  "geometry": {"coordinates":[-110.60337800000001,45.882969],"type":"Point"}
}