{
  "type": "Feature",
  "properties": {
    "addr:full":"376 North Rd  Invercargill Southland",
    "addr:housenumber":"376",
    "addr:street":"North Rd",
    "iso:country":"NZ",
    "sg:address":"376 North Rd ",
    "sg:city":"Invercargill",
    "sg:orig_category":"Automotive: General Services: Service Stations",
    "sg:phone":"+64 3-215 7328",
    "sg:province":"Southland",
    "wof:name":"Waikiwi Motors (Invercargill) Ltd",
    "wof:placetype":"venue"
},
  "geometry": {"coordinates":[168.347092,-46.372772],"type":"Point"}
}