{
  "type": "Feature",
  "properties": {
    "addr:full":"2 Argyle St Morningside  Auckland Auckland",
    "addr:housenumber":"2",
    "addr:street":"Argyle St",
    "iso:country":"NZ",
    "sg:address":"2 Argyle St Morningside ",
    "sg:city":"Auckland",
    "sg:orig_category":"Industrial: Packaging: Packaging - General",
    "sg:phone":"+64 9-815 1028",
    "sg:province":"Auckland",
    "wof:name":"Renshaws Glass",
    "wof:placetype":"venue"
},
  "geometry": {"coordinates":[174.73477199999999,-36.877869],"type":"Point"}
}