{
  "type": "Feature",
  "properties": {
    "addr:full":"5 Barossa La  Hillmorton",
    "addr:housenumber":"5",
    "addr:street":"Barossa La Hillmorton",
    "iso:country":"NZ",
    "sg:address":"5 Barossa La ",
    "sg:city":"Hillmorton",
    "sg:classifiers":[
        {
            "category":"Home & Garden",
            "subcategory":"Building Materials",
            "type":"Retail Goods"
        }
    ],
    "sg:phone":"+64 800 442 739",
    "sg:tags":[
        "door",
        "fitting",
        "fittings"
    ],
    "wof:name":"Interior Effects",
    "wof:placetype":"venue"
},
  "geometry": {"coordinates":[172.58696,-43.55862],"type":"Point"}
}