{
  "type": "Feature",
  "properties": {
    "addr:full":"18 Lowe St  Gisborne Gisborne",
    "addr:housenumber":"18",
    "addr:street":"Lowe St",
    "iso:country":"NZ",
    "sg:address":"18 Lowe St ",
    "sg:city":"Gisborne",
    "sg:classifiers":[
        {
            "category":"Retail",
            "subcategory":"Laundry & Dry Cleaning",
            "type":"Services"
        }
    ],
    "sg:phone":"+64 6-867 6122",
    "sg:province":"Gisborne",
    "sg:tags":[
        "repair",
        "clothing",
        "fabric",
        "cleaner"
    ],
    "wof:name":"Select Drycleaners",
    "wof:placetype":"venue"
},
  "geometry": {"coordinates":[178.02761799999999,-38.666744],"type":"Point"}
}