{
  "type": "Feature",
  "properties": {
    "addr:full":"Level 1 139 Featherston St  Wellington Wellington",
    "addr:housenumber":"level 1 139",
    "addr:street":"Featherston St",
    "iso:country":"NZ",
    "sg:address":"Level 1 139 Featherston St ",
    "sg:city":"Wellington",
    "sg:orig_category":"Transport: Boats And Marine: Shipping: Shipping Companies",
    "sg:phone":"+64 4-499 5260",
    "sg:province":"Wellington",
    "wof:name":"McKay Shipping Ltd",
    "wof:placetype":"venue"
},
  "geometry": {"coordinates":[174.777252,-41.283192],"type":"Point"}
}