{
  "type": "Feature",
  "properties": {
    "addr:full":"5 B Riverbank Rd New Lynn  Auckland Auckland",
    "addr:housenumber":"5 b",
    "addr:street":"Riverbank Rd",
    "iso:country":"NZ",
    "sg:address":"5 B Riverbank Rd New Lynn ",
    "sg:city":"Auckland",
    "sg:orig_category":"Home And Garden: Accessories: Linen",
    "sg:phone":"+64 9-826 0544",
    "sg:province":"Auckland",
    "wof:name":"New Lynn Laundromat",
    "wof:placetype":"venue"
},
  "geometry": {"coordinates":[174.683853,-36.902775],"type":"Point"}
}