{
  "type": "Feature",
  "properties": {
    "iso:country":"NZ",
    "sg:address":"49 Schollum Rd Morrinsville ",
    "sg:city":"Hamilton",
    "sg:orig_category":"Farming: Agriculture: Agricultural Spraying",
    "sg:phone":"+64 7-824 0894",
    "sg:province":"Waikato",
    "wof:name":"Walling Contracting",
    "wof:placetype":"venue"
},
  "geometry": {"coordinates":[175.528717,-37.65411],"type":"Point"}
}