{
  "type": "Feature",
  "properties": {
    "iso:country":"NZ",
    "sg:address":"Unit 13/ 29 Aviemore Dve Howick ",
    "sg:city":"Auckland",
    "sg:classifiers":[
        {
            "category":"Internet Cafe",
            "subcategory":"None",
            "type":"Food & Drink"
        }
    ],
    "sg:phone":"+64 9-535 7889",
    "sg:province":"Auckland",
    "sg:tags":[
        "wining",
        "dining"
    ],
    "wof:name":"Netwarz Internet & Rio Cafe",
    "wof:placetype":"venue"
},
  "geometry": {"coordinates":[174.916946,-36.894379],"type":"Point"}
}