{
  "type": "Feature",
  "properties": {
    "addr:full":"38 Donald St  Featherston",
    "addr:housenumber":"38",
    "addr:street":"Donald St",
    "iso:country":"NZ",
    "sg:address":"38 Donald St ",
    "sg:city":"Featherston",
    "sg:classifiers":[
        {
            "category":"Personal",
            "type":"Services"
        }
    ],
    "sg:phone":"+64 6-308 8173",
    "sg:tags":[
        "arrangements",
        "wedding"
    ],
    "sg:website":"http://www.theloft.co.nz",
    "wof:name":"The Loft",
    "wof:placetype":"venue"
},
  "geometry": {"coordinates":[-95.472374,35.086483],"type":"Point"}
}