{
  "type": "Feature",
  "properties": {
    "iso:country":"NZ",
    "sg:address":"81 Ferry Rd ",
    "sg:city":"Christchurch",
    "sg:classifiers":[
        {
            "category":"Manufacturing",
            "subcategory":"Motor Vehicles & Parts",
            "type":"Manufacturing & Wholesale Goods"
        }
    ],
    "sg:phone":"+64 3-366 6966",
    "sg:province":"Canterbury",
    "sg:tags":[
        "automotive",
        "steering",
        "supplies",
        "suspension"
    ],
    "wof:name":"Budget Tyre & Alignment Centre",
    "wof:placetype":"venue"
},
  "geometry": {"coordinates":[-76.537834,37.605659],"type":"Point"}
}