{
  "type": "Feature",
  "properties": {
    "iso:country":"NZ",
    "sg:address":"Floor 2 16 Broadway Ave Palmerston ",
    "sg:city":"Palmerston North",
    "sg:classifiers":[
        {
            "category":"Social Services",
            "subcategory":"Job Training",
            "type":"Services"
        }
    ],
    "sg:phone":"+64 6-355 8251",
    "sg:province":"Manawatu-Wanganui",
    "sg:tags":[
        "education"
    ],
    "wof:name":"Aspirations Te Ara Tumanako Ltd",
    "wof:placetype":"venue"
},
  "geometry": {"coordinates":[175.612061,-40.354561],"type":"Point"}
}