{
  "type": "Feature",
  "properties": {
    "addr:full":"92 Orbell St  Christchurch Canterbury",
    "addr:housenumber":"92",
    "addr:street":"Orbell St",
    "iso:country":"NZ",
    "sg:address":"92 Orbell St ",
    "sg:city":"Christchurch",
    "sg:classifiers":[
        {
            "category":"Manufacturing",
            "subcategory":"Glass & Minerals",
            "type":"Manufacturing & Wholesale Goods"
        }
    ],
    "sg:phone":"+64 3-379 5423",
    "sg:province":"Canterbury",
    "sg:tags":[
        "chemical",
        "paint",
        "industrial",
        "manufacturer",
        "compounds"
    ],
    "wof:name":"Duromastic Membranes Limited",
    "wof:placetype":"venue"
},
  "geometry": {"coordinates":[-76.537834,37.605659],"type":"Point"}
}