{
  "type": "Feature",
  "properties": {
    "addr:full":"Waimauku Doctors' Building Waimauku Station Road Waimauku Auckland Auckland",
    "addr:street":"Waimauku Station Road",
    "iso:country":"NZ",
    "sg:address":"Waimauku Doctors' Building Waimauku Station Road Waimauku",
    "sg:city":"Auckland",
    "sg:classifiers":[
        {
            "category":"Personal",
            "subcategory":"Beauty Salon",
            "type":"Services"
        }
    ],
    "sg:phone":"+64 9-411 5226",
    "sg:province":"Auckland",
    "sg:tags":[
        "therapy",
        "health"
    ],
    "wof:name":"The Village Beauty Studio",
    "wof:placetype":"venue"
},
  "geometry": {"coordinates":[174.49212600000001,-36.76432],"type":"Point"}
}