{
  "type": "Feature",
  "properties": {
    "addr:full":"Flaxmere Ave  Hastings Hawke's Bay",
    "addr:street":"Flaxmere Ave",
    "iso:country":"NZ",
    "sg:address":"Flaxmere Ave ",
    "sg:city":"Hastings",
    "sg:orig_category":"Sports And Leisure: General: Clubs",
    "sg:phone":"+64 6-879 8140",
    "sg:province":"Hawke's Bay",
    "wof:name":"Flaxmere Club Inc",
    "wof:placetype":"venue"
},
  "geometry": {"coordinates":[176.78324900000001,-39.622997],"type":"Point"}
}