{
  "type": "Feature",
  "properties": {
    "iso:country":"NZ",
    "sg:address":"Cumberland St South Dunedin ",
    "sg:city":"Dunedin",
    "sg:orig_category":"Automotive: General Services: Service Stations",
    "sg:phone":"+64 3-474 8260",
    "sg:province":"Otago",
    "wof:name":"BP Southern",
    "wof:placetype":"venue"
},
  "geometry": {"coordinates":[170.508423,-45.871498],"type":"Point"}
}