{
  "type": "Feature",
  "properties": {
    "addr:full":"35 Hoskyns Rd  Rolleston",
    "addr:housenumber":"35",
    "addr:street":"Hoskyns Rd",
    "iso:country":"NZ",
    "sg:address":"35 Hoskyns Rd ",
    "sg:city":"Rolleston",
    "sg:classifiers":[
        {
            "category":"Autos & Motor Vehicles",
            "subcategory":"Automobile Sales",
            "type":"Retail Goods"
        }
    ],
    "sg:phone":"+64 3-347 9354",
    "sg:tags":[
        "bus",
        "leasing",
        "truck",
        "automotive"
    ],
    "wof:name":"Wilco Imports Ltd",
    "wof:placetype":"venue"
},
  "geometry": {"coordinates":[172.385345,-43.587574],"type":"Point"}
}