{
  "type": "Feature",
  "properties": {
    "addr:full":"PO Box 391  Tokoroa",
    "addr:housenumber":"po",
    "addr:street":"Box 391",
    "iso:country":"NZ",
    "sg:address":"PO Box 391 ",
    "sg:city":"Tokoroa",
    "sg:orig_category":"Industrial: Metal: Stainless Steel",
    "sg:phone":"+64 7-886 4118",
    "wof:name":"Appleton Design Engineering Ltd",
    "wof:placetype":"venue"
},
  "geometry": {"coordinates":[175.866333,-38.226044],"type":"Point"}
}