{
  "type": "Feature",
  "properties": {
    "addr:full":"Shop 306 Bayfair Shopping Centre Cnr Girven & Maunganui, Rds  Tauranga Bay of Plenty",
    "addr:housenumber":"306",
    "addr:street":"Bayfair Shopping;Cnr Girven",
    "iso:country":"NZ",
    "sg:address":"Shop 306 Bayfair Shopping Centre Cnr Girven & Maunganui, Rds ",
    "sg:city":"Tauranga",
    "sg:orig_category":"Clothing And Fabric: Clothing: Children'S Wear",
    "sg:phone":"+64 7-574 1034",
    "sg:province":"Bay of Plenty",
    "wof:name":"Pumpkin Patch Ltd",
    "wof:placetype":"venue"
},
  "geometry": {"coordinates":[176.14475999999999,-37.703152],"type":"Point"}
}