{
  "type": "Feature",
  "properties": {
    "iso:country":"NZ",
    "sg:address":"192 Maunganui Rd Mt ",
    "sg:city":"Maunganui",
    "sg:orig_category":"Shopping: Sports Retailers: Water Sports: Surfboards",
    "sg:phone":"+64 7-574 5624",
    "sg:province":"Bay of Plenty",
    "wof:name":"High Voltage Surf Boards",
    "wof:placetype":"venue"
},
  "geometry": {"coordinates":[176.18367000000001,-37.639091],"type":"Point"}
}