{
  "type": "Feature",
  "properties": {
    "iso:country":"NZ",
    "sg:address":"82 Greenmount Dve East Tamaki ",
    "sg:city":"Auckland",
    "sg:classifiers":[
        {
            "category":"Manufacturing",
            "subcategory":"Motor Vehicles & Parts",
            "type":"Manufacturing & Wholesale Goods"
        }
    ],
    "sg:phone":"+64 9-274 5627",
    "sg:province":"Auckland",
    "sg:tags":[
        "box",
        "industrial",
        "parts",
        "-",
        "gear"
    ],
    "wof:name":"SEW-Eurodrive (NZ) Ltd",
    "wof:placetype":"venue"
},
  "geometry": {"coordinates":[174.901566,-36.92923],"type":"Point"}
}