{
  "type": "Feature",
  "properties": {
    "iso:country":"NZ",
    "sg:address":"43 Lady Ruby Dve East Tamaki ",
    "sg:city":"Wellington",
    "sg:orig_category":"Industrial: Parts: Valves",
    "sg:phone":"+64 4-473 2923",
    "sg:province":"Wellington",
    "wof:name":"Swagelok Company The",
    "wof:placetype":"venue"
},
  "geometry": {"coordinates":[174.852234,-41.138294],"type":"Point"}
}