{
  "type": "Feature",
  "properties": {
    "addr:full":"120 Maleme St Greerton  Tauranga Bay of Plenty",
    "addr:housenumber":"120",
    "addr:street":"Maleme St",
    "iso:country":"NZ",
    "sg:address":"120 Maleme St Greerton ",
    "sg:city":"Tauranga",
    "sg:orig_category":"Transport: Transportation: Freight",
    "sg:phone":"+64 7-541 1988",
    "sg:province":"Bay of Plenty",
    "wof:name":"Phoenix Freight Ltd",
    "wof:placetype":"venue"
},
  "geometry": {"coordinates":[176.12840299999999,-37.735039],"type":"Point"}
}