{
  "type": "Feature",
  "properties": {
    "iso:country":"NZ",
    "sg:address":"38 Fort St Auckland Central ",
    "sg:city":"Auckland",
    "sg:orig_category":"Travel And Tourism: Accommodation: Backpackers",
    "sg:phone":"+64 9-307 0181",
    "sg:province":"Auckland",
    "wof:name":"Fat Camel Hostel & Bar",
    "wof:placetype":"venue"
},
  "geometry": {"coordinates":[174.76831100000001,-36.846203],"type":"Point"}
}