{
  "type": "Feature",
  "properties": {
    "addr:full":"PO Box 17 328 Greenlane  Auckland Auckland",
    "addr:housenumber":"po box 17 328",
    "iso:country":"NZ",
    "sg:address":"PO Box 17 328 Greenlane ",
    "sg:city":"Auckland",
    "sg:classifiers":[
        {
            "category":"Retail",
            "subcategory":"Animal Services",
            "type":"Services"
        }
    ],
    "sg:phone":"+64 9-522 4594",
    "sg:province":"Auckland",
    "sg:tags":[
        "pet",
        "home",
        "garden",
        "pets"
    ],
    "wof:name":"Nielsen Manufacturing Ltd",
    "wof:placetype":"venue"
},
  "geometry": {"coordinates":[174.79191599999999,-36.892967],"type":"Point"}
}