{
  "type": "Feature",
  "properties": {
    "iso:country":"NZ",
    "sg:address":"PO Box 45076 Epuni Lower ",
    "sg:city":"Hutt",
    "sg:classifiers":[
        {
            "category":"Home & Garden",
            "subcategory":"Building Materials",
            "type":"Retail Goods"
        }
    ],
    "sg:phone":"+64 4-568 8928",
    "sg:province":"Wellington",
    "sg:tags":[
        "decorative",
        "glass",
        "window",
        "fittings"
    ],
    "wof:name":"Creative Glassdek Ltd",
    "wof:placetype":"venue"
},
  "geometry": {"coordinates":[174.930115,-41.207329],"type":"Point"}
}