{
  "type": "Feature",
  "properties": {
    "addr:full":"29 Newton St Mt  Maunganui Auckland",
    "addr:housenumber":"29",
    "addr:street":"Newton St",
    "iso:country":"NZ",
    "sg:address":"29 Newton St Mt ",
    "sg:city":"Maunganui",
    "sg:classifiers":[
        {
            "category":"Retail",
            "subcategory":"Storage",
            "type":"Services"
        }
    ],
    "sg:phone":"+64 7-574 8686",
    "sg:province":"Auckland",
    "sg:tags":[
        "system"
    ],
    "wof:name":"Mr Shelf",
    "wof:placetype":"venue"
},
  "geometry": {"coordinates":[176.18627900000001,-37.641048],"type":"Point"}
}