{
  "type": "Feature",
  "properties": {
    "iso:country":"NZ",
    "sg:address":"29 Newton St Mt ",
    "sg:city":"Maunganui",
    "sg:classifiers":[
        {
            "category":"Retail",
            "subcategory":"Storage",
            "type":"Services"
        }
    ],
    "sg:phone":"+64 7-574 8686",
    "sg:province":"Auckland",
    "sg:tags":[
        "system"
    ],
    "wof:name":"Mr Shelf",
    "wof:placetype":"venue"
},
  "geometry": {"coordinates":[176.186279,-37.641048],"type":"Point"}
}