{
  "type": "Feature",
  "properties": {
    "iso:country":"NZ",
    "sg:address":"1 Cameron St St Marys Bay ",
    "sg:city":"Auckland",
    "sg:orig_category":"Shopping: Accessories: Sunglasses",
    "sg:phone":"+64 21 369 962",
    "sg:province":"Auckland",
    "wof:name":"Coral Mazlin Eyewear",
    "wof:placetype":"venue"
},
  "geometry": {"coordinates":[174.743301,-36.845104],"type":"Point"}
}