{
  "type": "Feature",
  "properties": {
    "iso:country":"NZ",
    "sg:address":"168 Victoria Ave Remuera ",
    "sg:city":"Auckland",
    "sg:orig_category":"Farming: Services: Veterinarians",
    "sg:phone":"+64 9-529 2091",
    "sg:province":"Auckland",
    "wof:name":"Remuera Veterinary Medical Centre",
    "wof:placetype":"venue"
},
  "geometry": {"coordinates":[174.799164,-36.87159],"type":"Point"}
}