{
  "type": "Feature",
  "properties": {
    "addr:full":"Shop/10 Customs St E Auckland Central  Auckland Auckland",
    "addr:housenumber":"/ 10",
    "addr:street":"Customs St E",
    "iso:country":"NZ",
    "sg:address":"Shop/10 Customs St E Auckland Central ",
    "sg:city":"Auckland",
    "sg:orig_category":"Shopping: Hobbies And Games: Collectables",
    "sg:phone":"+64 9-379 4547",
    "sg:province":"Auckland",
    "wof:name":"Military Memorabilia",
    "wof:placetype":"venue"
},
  "geometry": {"coordinates":[174.76951600000001,-36.845406],"type":"Point"}
}