{
  "type": "Feature",
  "properties": {
    "iso:country":"NZ",
    "sg:address":"5 Maunu Rd ",
    "sg:city":"Whangarei",
    "sg:classifiers":[
        {
            "category":"Restaurant",
            "type":"Food & Drink"
        }
    ],
    "sg:phone":"+64 9-438 0988",
    "sg:province":"Northland",
    "sg:tags":[
        "brewing",
        "supply"
    ],
    "wof:name":"Brewers World Hop Shop",
    "wof:placetype":"venue"
},
  "geometry": {"coordinates":[174.31617700000001,-35.728096],"type":"Point"}
}