{
  "type": "Feature",
  "properties": {
    "iso:country":"NZ",
    "sg:address":"79 Napier Tce ",
    "sg:city":"Napier",
    "sg:orig_category":"Travel And Tourism: Accommodation: Hostels",
    "sg:phone":"+64 6-835 2093",
    "sg:province":"Hawke's Bay",
    "wof:name":"Hinepare Accommodation Centre",
    "wof:placetype":"venue"
},
  "geometry": {"coordinates":[-80.588562,38.790821],"type":"Point"}
}