{
  "type": "Feature",
  "properties": {
    "iso:country":"NZ",
    "sg:address":"21-27 Mihini Rd Henderson ",
    "sg:city":"Auckland",
    "sg:classifiers":[
        {
            "category":"Food Court",
            "type":"Food & Drink"
        }
    ],
    "sg:phone":"+64 9-839 0292",
    "sg:province":"Auckland",
    "sg:tags":[
        "packer",
        "processing",
        "processor"
    ],
    "wof:name":"McCallum Industries Ltd",
    "wof:placetype":"venue"
},
  "geometry": {"coordinates":[174.63295,-36.877289],"type":"Point"}
}