{
  "type": "Feature",
  "properties": {
    "iso:country":"NZ",
    "sg:address":"Dean Cre ",
    "sg:city":"Waihi",
    "sg:classifiers":[
        {
            "category":"Sports & Exercise",
            "subcategory":"Tennis Court",
            "type":"Entertainment"
        }
    ],
    "sg:phone":"+64 7-863 8579",
    "sg:tags":[
        "hire",
        "-",
        "leisure"
    ],
    "wof:name":"Waihi Hire",
    "wof:placetype":"venue"
},
  "geometry": {"coordinates":[175.742645,-38.952],"type":"Point"}
}