{
  "type": "Feature",
  "properties": {
    "iso:country":"NZ",
    "sg:address":"79 Picton St Howick ",
    "sg:city":"Auckland",
    "sg:classifiers":[
        {
            "category":"Shopping",
            "subcategory":"Shoes",
            "type":"Retail Goods"
        }
    ],
    "sg:phone":"+64 9-534 3719",
    "sg:province":"Auckland",
    "sg:tags":[
        "foot",
        "clothing",
        "fabric",
        "wear"
    ],
    "wof:name":"Milan's Shoes",
    "wof:placetype":"venue"
},
  "geometry": {"coordinates":[174.932846,-36.894897],"type":"Point"}
}