{
  "type": "Feature",
  "properties": {
    "iso:country":"NZ",
    "sg:address":"SHP15 28 Rotherham Street Riccn Christchurch ",
    "sg:city":"Christchurch",
    "sg:orig_category":"Industrial: Electrical/Electronic: Electronic Components",
    "sg:phone":"+64 800 165 800",
    "sg:province":"Canterbury",
    "wof:name":"Altronics",
    "wof:placetype":"venue"
},
  "geometry": {"coordinates":[-1.77656,50.73407],"type":"Point"}
}