{
  "type": "Feature",
  "properties": {
    "iso:country":"NZ",
    "sg:address":"Bond Rd Ormond ",
    "sg:city":"Gisborne",
    "sg:classifiers":[
        {
            "category":"Building & Trades",
            "subcategory":"Construction",
            "type":"Services"
        }
    ],
    "sg:phone":"+64 6-862 5690",
    "sg:province":"Gisborne",
    "sg:tags":[
        "home",
        "garden",
        "related",
        "plasterer"
    ],
    "wof:name":"Wayne Norris Plasterer",
    "wof:placetype":"venue"
},
  "geometry": {"coordinates":[177.92344665530001,-38.5604286194],"type":"Point"}
}