{
  "type": "Feature",
  "properties": {
    "addr:full":"10 Borthwick St R D 42  Waitara",
    "addr:housenumber":"10;42",
    "addr:street":"Borthwick St R D",
    "iso:country":"NZ",
    "sg:address":"10 Borthwick St R D 42 ",
    "sg:city":"Waitara",
    "sg:classifiers":[
        {
            "category":"Home & Garden",
            "subcategory":"Garden Supply",
            "type":"Retail Goods"
        }
    ],
    "sg:phone":"+64 6-754 7083",
    "sg:tags":[
        "products",
        "nursery",
        "gardening"
    ],
    "wof:name":"Pratt G J Nursery",
    "wof:placetype":"venue"
},
  "geometry": {"coordinates":[174.24478099999999,-38.996071],"type":"Point"}
}