{
  "type": "Feature",
  "properties": {
    "iso:country":"NZ",
    "sg:address":"10 Woodson Pl Glenfield ",
    "sg:city":"Auckland",
    "sg:classifiers":[
        {
            "category":"Manufacturing",
            "subcategory":"Rubber & Plastics",
            "type":"Manufacturing & Wholesale Goods"
        }
    ],
    "sg:phone":"+64 9-444 7135",
    "sg:province":"Auckland",
    "sg:tags":[
        "industrial",
        "goods"
    ],
    "sg:website":"http://www.engineeringplastics.co.nz",
    "wof:name":"Engineering Plastics Ltd",
    "wof:placetype":"venue"
},
  "geometry": {"coordinates":[174.728622,-36.784813],"type":"Point"}
}