{
  "type": "Feature",
  "properties": {
    "addr:full":"175 Taranaki St  Wellington Wellington",
    "addr:housenumber":"175",
    "addr:street":"Taranaki St",
    "iso:country":"NZ",
    "sg:address":"175 Taranaki St ",
    "sg:city":"Wellington",
    "sg:classifiers":[
        {
            "category":"Retail",
            "subcategory":"Auto Repair",
            "type":"Services"
        }
    ],
    "sg:phone":"+64 4-385 9467",
    "sg:province":"Wellington",
    "sg:tags":[
        "engine",
        "automotive",
        "servicing"
    ],
    "wof:name":"Giles Engine Reconditioning Ltd",
    "wof:placetype":"venue"
},
  "geometry": {"coordinates":[-85.910454,33.827946],"type":"Point"}
}