{
  "type": "Feature",
  "properties": {
    "iso:country":"NZ",
    "sg:address":"7 Villa St ",
    "sg:city":"Masterton",
    "sg:classifiers":[
        {
            "category":"Marine",
            "type":"Transportation"
        }
    ],
    "sg:phone":"+64 6-377 2964",
    "sg:province":"Wellington",
    "sg:tags":[
        "boats",
        "builder",
        "yacht",
        "transport",
        "boat"
    ],
    "wof:name":"Stevens Marine Engineering",
    "wof:placetype":"venue"
},
  "geometry": {"coordinates":[175.66429099999999,-40.94455],"type":"Point"}
}