{
  "type": "Feature",
  "properties": {
    "addr:full":"8 Commerce St  Putaruru",
    "addr:housenumber":"8",
    "addr:street":"Commerce St",
    "iso:country":"NZ",
    "sg:address":"8 Commerce St ",
    "sg:city":"Putaruru",
    "sg:classifiers":[
        {
            "category":"Education",
            "subcategory":"Dance Studio",
            "type":"Public Place"
        }
    ],
    "sg:phone":"+64 7-883 8272",
    "sg:tags":[
        "school",
        "dancing",
        "-",
        "leisure",
        "sports",
        "sport"
    ],
    "wof:name":"Central Motors (1991)",
    "wof:placetype":"venue"
},
  "geometry": {"coordinates":[175.78126499999999,-38.049763],"type":"Point"}
}