{
  "type": "Feature",
  "properties": {
    "addr:full":"PO Box 34 Rolleston  Christchurch Canterbury",
    "addr:housenumber":"po box 34",
    "iso:country":"NZ",
    "sg:address":"PO Box 34 Rolleston ",
    "sg:city":"Christchurch",
    "sg:classifiers":[
        {
            "category":"Utilities",
            "type":"Services"
        }
    ],
    "sg:phone":"+64 3-347 8622",
    "sg:province":"Canterbury",
    "sg:tags":[
        "industrial",
        "energy",
        "utilities",
        "coal",
        "wood",
        "coke"
    ],
    "wof:name":"Wood n Tree Ltd",
    "wof:placetype":"venue"
},
  "geometry": {"coordinates":[172.375046,-43.593182],"type":"Point"}
}