{
  "type": "Feature",
  "properties": {
    "addr:full":"307 Wicksteed St  Wanganui Manawatu-Wanganui",
    "addr:housenumber":"307",
    "addr:street":"Wicksteed St",
    "iso:country":"NZ",
    "sg:address":"307 Wicksteed St ",
    "sg:city":"Wanganui",
    "sg:classifiers":[
        {
            "category":"Sports & Exercise",
            "subcategory":"Swimming Pool",
            "type":"Entertainment"
        }
    ],
    "sg:phone":"+64 6-348 8250",
    "sg:province":"Manawatu-Wanganui",
    "sg:tags":[
        "home",
        "outdoor",
        "garden",
        "spa"
    ],
    "wof:name":"Pool Clinic",
    "wof:placetype":"venue"
},
  "geometry": {"coordinates":[175.04293799999999,-39.926277],"type":"Point"}
}