{
  "type": "Feature",
  "properties": {
    "iso:country":"NZ",
    "sg:address":"19 Birmingham St ",
    "sg:city":"Tauranga",
    "sg:orig_category":"Industrial: Services: Gasfitters",
    "sg:phone":"+64 7-577 0308",
    "sg:province":"Bay of Plenty",
    "wof:name":"Gas Appliance Services & Installation",
    "wof:placetype":"venue"
},
  "geometry": {"coordinates":[176.13537600000001,-37.697521],"type":"Point"}
}