{
  "type": "Feature",
  "properties": {
    "iso:country":"NZ",
    "sg:address":"Katere Rd New ",
    "sg:city":"Plymouth",
    "sg:orig_category":"Industrial: Engineering: Engineers - Manufacturing",
    "sg:phone":"+64 6-758 4308",
    "sg:province":"Taranaki",
    "sg:website":"http://www.yellowpages.co.nz/for/toledoengineering/dp19860.html",
    "wof:name":"Toledo Engineering Co Ltd",
    "wof:placetype":"venue"
},
  "geometry": {"coordinates":[-116.819725,43.97221],"type":"Point"}
}