{
  "type": "Feature",
  "properties": {
    "addr:full":"Timaru & Oamaru  Timaru Canterbury",
    "iso:country":"NZ",
    "sg:address":"Timaru & Oamaru ",
    "sg:city":"Timaru",
    "sg:orig_category":"Automotive: Parts And Supplies: Tyres",
    "sg:phone":"+64 800 489 737",
    "sg:province":"Canterbury",
    "sg:website":"http://www.beaurepaires.co.nz",
    "wof:name":"Beaurepaires for Tyres",
    "wof:placetype":"venue"
},
  "geometry": {"coordinates":[171.23739599999999,-44.395432],"type":"Point"}
}