{
  "type": "Feature",
  "properties": {
    "iso:country":"NZ",
    "sg:address":"200 Gt South Rd Takanini ",
    "sg:city":"Auckland",
    "sg:classifiers":[
        {
            "category":"Retail",
            "subcategory":"Auto Repair",
            "type":"Services"
        }
    ],
    "sg:phone":"+64 9-298 7939",
    "sg:province":"Auckland",
    "sg:tags":[
        "automotive",
        "panel",
        "servicing",
        "beater"
    ],
    "wof:name":"Papakura Panelbeaters & Car Painters Ltd",
    "wof:placetype":"venue"
},
  "geometry": {"coordinates":[174.922943,-37.045818],"type":"Point"}
}