{
  "type": "Feature",
  "properties": {
    "addr:full":"The Big Top Recreation Centre Henderson  Auckland Auckland",
    "iso:country":"NZ",
    "sg:address":"The Big Top Recreation Centre Henderson ",
    "sg:city":"Auckland",
    "sg:classifiers":[
        {
            "category":"Sports & Exercise",
            "subcategory":"Ice Rink",
            "type":"Entertainment"
        }
    ],
    "sg:phone":"+64 9-836 5276",
    "sg:province":"Auckland",
    "sg:tags":[
        "skating",
        "-",
        "leisure",
        "sports"
    ],
    "wof:name":"City of Waitakere Roller Sports Club",
    "wof:placetype":"venue"
},
  "geometry": {"coordinates":[174.630402,-36.887714],"type":"Point"}
}