{
  "type": "Feature",
  "properties": {
    "iso:country":"NZ",
    "sg:address":"Shop/1 Hammond Pl Birkenhead ",
    "sg:city":"Auckland",
    "sg:classifiers":[
        {
            "category":"Health Services",
            "subcategory":"Health Practitioner",
            "type":"Services"
        }
    ],
    "sg:phone":"+64 9-419 9028",
    "sg:province":"Auckland",
    "sg:tags":[
        "services",
        "beauty",
        "acupuncturists"
    ],
    "wof:name":"Rona Wang's Healing Centre",
    "wof:placetype":"venue"
},
  "geometry": {"coordinates":[174.72477699999999,-36.811165],"type":"Point"}
}