{
  "type": "Feature",
  "properties": {
    "addr:full":"37 Mt Eden Rd Mt Eden  Auckland Auckland",
    "addr:housenumber":"37",
    "addr:street":"Mt Eden Rd",
    "iso:country":"NZ",
    "sg:address":"37 Mt Eden Rd Mt Eden ",
    "sg:city":"Auckland",
    "sg:classifiers":[
        {
            "category":"Communications",
            "subcategory":"Radio Station",
            "type":"Services"
        }
    ],
    "sg:phone":"+64 9-377 1592",
    "sg:province":"Auckland",
    "sg:tags":[
        "broadcasting"
    ],
    "wof:name":"Radio Samoa Network (NZ) Ltd",
    "wof:placetype":"venue"
},
  "geometry": {"coordinates":[174.76205400000001,-36.882732],"type":"Point"}
}