{
  "type": "Feature",
  "properties": {
    "iso:country":"NZ",
    "sg:address":"15 Dent St ",
    "sg:city":"Whangarei",
    "sg:orig_category":"Shopping: Hobbies And Games: Handcrafts",
    "sg:phone":"+64 9-438 8812",
    "sg:province":"Northland",
    "wof:name":"Handcraft House",
    "wof:placetype":"venue"
},
  "geometry": {"coordinates":[174.32312,-35.723015],"type":"Point"}
}