{
  "type": "Feature",
  "properties": {
    "addr:full":"15 Dent St  Whangarei Northland",
    "addr:housenumber":"15",
    "addr:street":"Dent St",
    "iso:country":"NZ",
    "sg:address":"15 Dent St ",
    "sg:city":"Whangarei",
    "sg:orig_category":"Shopping: Hobbies And Games: Handcrafts",
    "sg:phone":"+64 9-438 8812",
    "sg:province":"Northland",
    "wof:name":"Handcraft House",
    "wof:placetype":"venue"
},
  "geometry": {"coordinates":[174.32311999999999,-35.723015],"type":"Point"}
}