{
  "type": "Feature",
  "properties": {
    "iso:country":"NZ",
    "sg:address":"11 Witham St Hornby ",
    "sg:city":"Christchurch",
    "sg:classifiers":[
        {
            "category":"Food & Beverages",
            "subcategory":"Candy",
            "type":"Retail Goods"
        }
    ],
    "sg:phone":"+64 3-349 4737",
    "sg:province":"Canterbury",
    "sg:tags":[
        "confectioner",
        "drink",
        "-"
    ],
    "wof:name":"Sweet Treats Confectionery",
    "wof:placetype":"venue"
},
  "geometry": {"coordinates":[172.530731,-43.551594],"type":"Point"}
}