{
  "type": "Feature",
  "properties": {
    "addr:full":"53 Wilson Rd Flaxmere  Hastings Hawke's Bay",
    "addr:housenumber":"53",
    "addr:street":"Wilson Rd",
    "iso:country":"NZ",
    "sg:address":"53 Wilson Rd Flaxmere ",
    "sg:city":"Hastings",
    "sg:orig_category":"Farming: Agriculture: Agricultural Consultants",
    "sg:phone":"+64 6-879 8875",
    "sg:province":"Hawke's Bay",
    "wof:name":"Greg Tate, Crop Health Services",
    "wof:placetype":"venue"
},
  "geometry": {"coordinates":[176.794434,-39.629978],"type":"Point"}
}