{
  "type": "Feature",
  "properties": {
    "addr:full":"47 A Victoria St Onehunga  Auckland Auckland",
    "addr:housenumber":"47 a",
    "addr:street":"Victoria St",
    "iso:country":"NZ",
    "sg:address":"47 A Victoria St Onehunga ",
    "sg:city":"Auckland",
    "sg:classifiers":[
        {
            "category":"Farming",
            "subcategory":"Fish & Marine Products",
            "type":"Manufacturing & Wholesale Goods"
        }
    ],
    "sg:phone":"+64 9-636 5015",
    "sg:province":"Auckland",
    "sg:tags":[
        "boats",
        "yacht",
        "transport",
        "boat",
        "supply"
    ],
    "wof:name":"Kiwi Auto & Marine Upholsterers",
    "wof:placetype":"venue"
},
  "geometry": {"coordinates":[174.792664,-36.925568],"type":"Point"}
}