{
  "type": "Feature",
  "properties": {
    "addr:full":"95 Grey St Palmerston  Palmerston North Manawatu-Wanganui",
    "addr:housenumber":"95",
    "addr:street":"Grey St",
    "iso:country":"NZ",
    "sg:address":"95 Grey St Palmerston ",
    "sg:city":"Palmerston North",
    "sg:classifiers":[
        {
            "category":"Food & Beverages",
            "subcategory":"Liquor & Beverages",
            "type":"Retail Goods"
        }
    ],
    "sg:phone":"+64 6-354 6959",
    "sg:province":"Manawatu-Wanganui",
    "sg:tags":[
        "drink",
        "outlet"
    ],
    "wof:name":"The Mill Liquorsave",
    "wof:placetype":"venue"
},
  "geometry": {"coordinates":[175.566757,-40.220589],"type":"Point"}
}