{
  "type": "Feature",
  "properties": {
    "addr:full":"75 Beach Rd Auckland City  Auckland Auckland",
    "addr:housenumber":"75",
    "addr:street":"Beach Rd",
    "iso:country":"NZ",
    "sg:address":"75 Beach Rd Auckland City ",
    "sg:city":"Auckland",
    "sg:orig_category":"Automotive: General Services: Rental Vehicles",
    "sg:phone":"+64 9-377 5573",
    "sg:province":"Auckland",
    "sg:website":"http://www.akldnz.co.nz",
    "wof:name":"Omega Rental Cars Ltd",
    "wof:placetype":"venue"
},
  "geometry": {"coordinates":[174.77336099999999,-36.84726],"type":"Point"}
}