{
  "type": "Feature",
  "properties": {
    "iso:country":"NZ",
    "sg:address":"4 Holmglen St Washdyke ",
    "sg:city":"Timaru",
    "sg:classifiers":[
        {
            "category":"Manufacturing",
            "subcategory":"Tools & Machinery",
            "type":"Manufacturing & Wholesale Goods"
        }
    ],
    "sg:phone":"+64 3-688 2902",
    "sg:province":"Canterbury",
    "sg:tags":[
        "equipment",
        "industrial",
        "hydraulic"
    ],
    "wof:name":"Scarlett Hydraulics Ltd",
    "wof:placetype":"venue"
},
  "geometry": {"coordinates":[171.243988,-44.351059],"type":"Point"}
}