{
  "type": "Feature",
  "properties": {
    "iso:country":"NZ",
    "sg:address":"6/10 Newton St Bromley ",
    "sg:city":"Christchurch",
    "sg:orig_category":"Industrial: Services: Pressing And Stamping",
    "sg:phone":"+64 3-384 4519",
    "sg:province":"Auckland",
    "wof:name":"Barltrop & Son",
    "wof:placetype":"venue"
},
  "geometry": {"coordinates":[172.697525,-43.541317],"type":"Point"}
}