{
  "type": "Feature",
  "properties": {
    "addr:full":"244 Wiri Station Rd  Auckland Auckland",
    "addr:housenumber":"244",
    "addr:street":"Wiri Station Rd",
    "iso:country":"NZ",
    "sg:address":"244 Wiri Station Rd ",
    "sg:city":"Auckland",
    "sg:classifiers":[
        {
            "category":"Manufacturing",
            "subcategory":"Glass & Minerals",
            "type":"Manufacturing & Wholesale Goods"
        }
    ],
    "sg:phone":"+64 9-263 9076",
    "sg:province":"Auckland",
    "sg:tags":[
        "industrial",
        "raw",
        "material"
    ],
    "wof:name":"Holcim Aggregates",
    "wof:placetype":"venue"
},
  "geometry": {"coordinates":[174.87666300000001,-36.997929],"type":"Point"}
}