{
  "type": "Feature",
  "properties": {
    "iso:country":"NZ",
    "sg:address":"279 Waiwhetu Rd Fairfield Lower ",
    "sg:city":"Hutt",
    "sg:classifiers":[
        {
            "category":"Wholesale",
            "subcategory":"Hardware",
            "type":"Manufacturing & Wholesale Goods"
        }
    ],
    "sg:phone":"+64 4-567 8264",
    "sg:province":"Wellington",
    "sg:tags":[
        "gardening",
        "garden",
        "chainsaw",
        "products",
        "brush",
        "home",
        "cutter"
    ],
    "wof:name":"Motor Mowers & Cycles 1976 Ltd",
    "wof:placetype":"venue"
},
  "geometry": {"coordinates":[174.93347199999999,-41.210594],"type":"Point"}
}