{
  "type": "Feature",
  "properties": {
    "addr:full":"331 South Rd  Hawera Taranaki",
    "addr:housenumber":"331",
    "addr:street":"South Rd",
    "iso:country":"NZ",
    "sg:address":"331 South Rd ",
    "sg:city":"Hawera",
    "sg:orig_category":"Clothing And Fabric: Clothing: Dressmakers",
    "sg:phone":"+64 6-278 4191",
    "sg:province":"Taranaki",
    "wof:name":"Highway 45 Dressmaking",
    "wof:placetype":"venue"
},
  "geometry": {"coordinates":[174.26306199999999,-39.589977],"type":"Point"}
}