{
  "type": "Feature",
  "properties": {
    "iso:country":"NZ",
    "sg:address":"42 Halifax St ",
    "sg:city":"Nelson",
    "sg:classifiers":[
        {
            "category":"Farming",
            "subcategory":"Farm",
            "type":"Manufacturing & Wholesale Goods"
        }
    ],
    "sg:phone":"+64 3-548 9104",
    "sg:province":"Nelson",
    "sg:website":"http://www.valuersnelson.co.nz",
    "wof:name":"Duke & Cooke Ltd",
    "wof:placetype":"venue"
},
  "geometry": {"coordinates":[-121.765488,39.553471],"type":"Point"}
}