{
  "type": "Feature",
  "properties": {
    "iso:country":"NZ",
    "sg:address":"201 Gt South Rd Manurewa ",
    "sg:city":"Auckland",
    "sg:classifiers":[
        {
            "category":"Shopping",
            "subcategory":"Gifts & Souvenirs",
            "type":"Retail Goods"
        }
    ],
    "sg:phone":"+64 9-267 7570",
    "sg:province":"Auckland",
    "sg:tags":[
        "shop",
        "gifts",
        "supplier"
    ],
    "wof:name":"King Kong",
    "wof:placetype":"venue"
},
  "geometry": {"coordinates":[174.91696200000001,-37.021488],"type":"Point"}
}