{
  "type": "Feature",
  "properties": {
    "iso:country":"NZ",
    "sg:address":"558 Te Rapa Rd Te Rapa ",
    "sg:city":"Hamilton",
    "sg:orig_category":"Industrial: Chemicals And Compounds: Silicones",
    "sg:phone":"+64 7-850 7200",
    "sg:province":"Waikato",
    "wof:name":"Dec International NZ Ltd",
    "wof:placetype":"venue"
},
  "geometry": {"coordinates":[175.24766500000001,-37.759113],"type":"Point"}
}