{
  "type": "Feature",
  "properties": {
    "iso:country":"NZ",
    "sg:address":"Shoppe 4 150 Dickens St ",
    "sg:city":"Napier",
    "sg:classifiers":[
        {
            "category":"Health Services",
            "subcategory":"Dentist",
            "type":"Services"
        }
    ],
    "sg:phone":"+64 6-835 7535",
    "sg:province":"Hawke's Bay",
    "sg:tags":[
        "dental",
        "beauty"
    ],
    "wof:name":"Mark Clifford Dental Creations",
    "wof:placetype":"venue"
},
  "geometry": {"coordinates":[-80.596046,38.787933],"type":"Point"}
}