{
  "type": "Feature",
  "properties": {
    "iso:country":"NZ",
    "sg:address":"182 Morgans Rd ",
    "sg:city":"Timaru",
    "sg:classifiers":[
        {
            "category":"Home & Garden",
            "subcategory":"Garden Supply",
            "type":"Retail Goods"
        }
    ],
    "sg:phone":"+64 3-686 1109",
    "sg:province":"Canterbury",
    "sg:tags":[
        "products",
        "nursery",
        "gardening"
    ],
    "wof:name":"Nikau Gardenworld",
    "wof:placetype":"venue"
},
  "geometry": {"coordinates":[171.210648,-44.376984],"type":"Point"}
}