{
  "type": "Feature",
  "properties": {
    "iso:country":"NZ",
    "sg:address":"Hornby Mall 418 Main South Rd Hornby ",
    "sg:city":"Christchurch",
    "sg:orig_category":"Shopping: Accessories: Lingerie - Retail",
    "sg:phone":"+64 3-349 6897",
    "sg:province":"Canterbury",
    "wof:name":"Just Lingerie",
    "wof:placetype":"venue"
},
  "geometry": {"coordinates":[172.536331,-43.534431],"type":"Point"}
}