{
  "type": "Feature",
  "properties": {
    "iso:country":"NZ",
    "sg:address":"Joes Flat Lower Maruia ",
    "sg:city":"Murchison",
    "sg:classifiers":[
        {
            "category":"Personal",
            "type":"Services"
        }
    ],
    "sg:phone":"+64 3-523 9416",
    "sg:tags":[
        "celebrant",
        "arrangements",
        "marriage",
        "wedding"
    ],
    "wof:name":"Peacock M F",
    "wof:placetype":"venue"
},
  "geometry": {"coordinates":[-95.749489,32.278419],"type":"Point"}
}