{
  "type": "Feature",
  "properties": {
    "addr:full":"13 Mail Ave Weymouth  Auckland Auckland",
    "addr:housenumber":"13",
    "addr:street":"Mail Ave",
    "iso:country":"NZ",
    "sg:address":"13 Mail Ave Weymouth ",
    "sg:city":"Auckland",
    "sg:classifiers":[
        {
            "category":"Manufacturing",
            "subcategory":"Tools & Machinery",
            "type":"Manufacturing & Wholesale Goods"
        }
    ],
    "sg:phone":"+64 9-266 3364",
    "sg:province":"Auckland",
    "sg:tags":[
        "equipment",
        "industrial",
        "hydraulic"
    ],
    "wof:name":"Stanley Hydraulic Tools",
    "wof:placetype":"venue"
},
  "geometry": {"coordinates":[174.864868,-37.047466],"type":"Point"}
}