{
  "type": "Feature",
  "properties": {
    "addr:full":"101 Customs  St",
    "addr:housenumber":"101",
    "addr:street":"Customs St",
    "iso:country":"NZ",
    "sg:address":"101 Customs ",
    "sg:city":"St",
    "sg:classifiers":[
        {
            "category":"Travel",
            "subcategory":"Hotels & Motels",
            "type":"Entertainment"
        }
    ],
    "sg:phone":"+64 800 806 688",
    "sg:tags":[
        "tavern",
        "tourism",
        "accommodation"
    ],
    "wof:name":"Manor Inns Group Ltd",
    "wof:placetype":"venue"
},
  "geometry": {"coordinates":[170.36663799999999,-43.587711],"type":"Point"}
}