{
  "type": "Feature",
  "properties": {
    "addr:full":"8 Clemow Dve Mt Wellington  Auckland Auckland",
    "addr:housenumber":"8",
    "addr:street":"Clemow Dve",
    "iso:country":"NZ",
    "sg:address":"8 Clemow Dve Mt Wellington ",
    "sg:city":"Auckland",
    "sg:classifiers":[
        {
            "category":"Autos & Motor Vehicles",
            "subcategory":"Automobile Sales",
            "type":"Retail Goods"
        }
    ],
    "sg:phone":"+64 9-573 2050",
    "sg:province":"Auckland",
    "sg:tags":[
        "car",
        "importer",
        "leasing",
        "automotive"
    ],
    "wof:name":"Hyundai Automotive New Zealand Limited",
    "wof:placetype":"venue"
},
  "geometry": {"coordinates":[174.83029199999999,-36.909569],"type":"Point"}
}